Workbook
Name AccessList: Lists!$A$35:$A$53
Name AnnualRevenueTarget: Settings!$D$66
Name AreaUnit: Settings!$D$23
Name AreaUnitList: Lists!$E$282:$E$291
Name AttendanceList: Lists!$G$156:$G$173
Name BillingCycleList: Lists!$I$80:$I$95
Name BizAddress: Settings!$D$10
Name BizArea: Settings!$D$12
Name BizEmail: Settings!$D$8
Name BizInsurance: Settings!$D$15
Name BizName: Settings!$D$6
Name BizOwner: Settings!$D$7
Name BizPayDetails: Settings!$D$62
Name BizPhone: Settings!$D$9
Name BizRegNo: Settings!$D$14
Name BizTagline: Settings!$D$13
Name BizWebsite: Settings!$D$11
Name CalloutFee: Settings!$D$38
Name CalStart: Calendar!$B$5
Name CertWarningDays: Settings!$D$79
Name CleanersPerJob: Settings!$D$21
Name ClientIDs: OFFSET(Clients!$A$5,0,0,MAX(1,COUNTIF(Clients!$A$5:$A$204,"?*")),1)
Name ClientNames: OFFSET(Clients!$B$5,0,0,MAX(1,COUNTIF(Clients!$B$5:$B$204,"?*")),1)
Name ClientPrefix: Settings!$D$84
Name ClientStatusList: Lists!$G$9:$G$25
Name ClientTypeList: Lists!$E$9:$E$31
Name ComplaintPrefix: Settings!$D$96
Name ComplaintStatusList: Lists!$E$233:$E$248
Name ComplaintTypeList: Lists!$C$233:$C$254
Name ConditionFactors: Lists!$B$337:$B$345
Name ConditionList: Lists!$G$35:$G$47
Name ConditionNames: Lists!$A$337:$A$345
Name ContractStatusList: Lists!$E$80:$E$97
Name ContractTermList: Lists!$G$80:$G$94
Name CostPerHour: Settings!$D$49
Name DashKey: Dashboard!$H$5
Name DashMonth: Dashboard!$F$5
Name DeepCleanUplift: Settings!$D$39
Name DepositPercent: Settings!$D$42
Name DistanceUnit: Settings!$D$24
Name DistanceUnitList: Lists!$G$282:$G$291
Name DocStatusList: Lists!$E$257:$E$270
Name EmployeeIDs: OFFSET(Employees!$A$5,0,0,MAX(1,COUNTIF(Employees!$A$5:$A$44,"?*")),1)
Name EmployeeNames: OFFSET(Employees!$B$5,0,0,MAX(1,COUNTIF(Employees!$B$5:$B$44,"?*")),1)
Name EmployeePrefix: Settings!$D$92
Name EmployeeRoleList: Lists!$I$126:$I$145
Name EmployeeStatusList: Lists!$C$156:$C$171
Name EmployerOncost: Settings!$D$48
Name EmploymentTypeList: Lists!$A$156:$A$171
Name EquipmentNames: OFFSET(Equipment!$B$5,0,0,MAX(1,COUNTIF(Equipment!$B$5:$B$84,"?*")),1)
Name EquipmentPrefix: Settings!$D$94
Name EquipmentStatusList: Lists!$I$176:$I$191
Name EquipmentTypeList: Lists!$G$176:$G$196
Name ExpenseCategoryList: Lists!$E$199:$E$230
Name ExpenseMonths: OFFSET(Expenses!$C$5,0,0,MAX(1,COUNTIF(Expenses!$C$5:$C$404,"?*")),1)
Name ExpensePrefix: Settings!$D$95
Name ExpenseTypeList: Lists!$G$199:$G$211
Name FpAvgHours: 'Financial Plan'!$D$9
Name FpAvgJob: 'Financial Plan'!$D$8
Name FpBreakEvenHours: 'Financial Plan'!$D$14

Sheet Start Here
A1: Cleaning Business CRM & Pricing Calculator | H1: Novality Store | v1.0.0
A2: A complete back office for a cleaning business - clients, quotes, jobs, staff, invoices and profit.
A3: > Start Here | C3: > Dashboard | E3: > Clients | G3: > Jobs | I3: > Calendar
A5: Welcome. This workbook replaces the diary, the quote pad, the invoice book and the shoebox of receipts. Everything is a formula you can read and change - no macros, no add-ins, no subscription.
A7: What is in the file
B8: Tab | C8: What it does | D8: Your job
B9: Business Settings | C9: Your name, rates, tax, targets and every reminder window | H9: Fill in once, revisit twice a year
B10: Dashboard | C10: Twelve live numbers, the jobs for the week and everything that needs doing | H10: Read it every morning
B11: Pricing & Quote Calculator | C11: Prices a clean four different ways and shows the margin on each | H11: Use it before you quote
B12: Client CRM | C12: Every client, what they are worth and whether they are drifting away | H12: Add clients
B13: Property & Site Database | C13: Addresses, access, keys, pets, parking and the hours each property needs | H13: Add properties
B14: Leads & Sales Pipeline | C14: Enquiries from first call to won or lost | H14: Log every enquiry
B15: Service Catalog | C15: What you offer, what it costs you and what it earns an hour | H15: Set up once
B16: Quotes & Estimates | C16: Quotes, their lines, follow-ups and acceptance | H16: Raise quotes
B17: Job Scheduler | C17: Every visit: who, where, when, how long, how much | H17: The heart of the workbook
B18: Calendar | C18: The month at a glance and the next thirty visits in order | H18: Read only
B19: Cleaning Checklists | C19: Room-by-room task templates, and the tasks ticked off on the day | H19: Build your own
B20: Employee Database | C20: Your team, their pay, skills, checks and performance | H20: Add staff
... B32: Settings & Dropdown Lists | C32: Every drop-down list in the workbook | H32: Edit to suit you
A34: Twenty minutes to set it up
B35: Step | C35: Where | D35: What to do
B36: 1 | C36: Business Settings | E36: Your business name, address, phone and email. They print on every quote and invoice.
B37: 2 | C37: Business Settings | E37: Your hourly rate, minimum charge and what a cleaner costs you an hour. Nothing else works until these are right.
B38: 3 | C38: Business Settings | E38: Tax rate and payment terms. Set the tax rate to 0 if you are not registered.
B39: 4 | C39: Service Catalog | E39: Edit the services to match what you actually sell. Delete the ones you do not offer.
B40: 5 | C40: Cleaning Checklists | E40: Adjust the task templates. These become the job sheets your cleaners carry.
B41: 6 | C41: Employee Database | E41: Add your team - even if the team is just you. Put your own pay rate in; it is what makes the profit figures real.
B42: 7 | C42: Client CRM and Property & Site Database | E42: Add your clients, then their properties. The property is where the hours and the access details live.
B43: 8 | C43: Job Scheduler | E43: Put next week's visits in. The price, the finish time and the invoice link all work themselves out.
B44: 9 | C44: Dashboard | E44: Open it every morning. If a number looks wrong, the tab it came from is named right beside it.
A46: The rhythm that keeps it accurate
B47: When | C47: What | D47: How long
B48: Every morning | C48: Open the Dashboard. Confirm tomorrow's visits. Assign anything with no cleaner. | I48: 2 minutes
B49: After each job | C49: Mark it Completed and put the actual hours in. | I49: 30 seconds
B50: Every Friday | C50: Approve timesheets, raise the week's invoices, log receipts. | I50: 20 minutes
B51: Every Monday | C51: Chase unpaid invoices and unanswered quotes. This is the hour that pays for itself. | I51: 30 minutes
B52: Monthly | C52: Count supplies, check equipment servicing, read the Reports tab. | I52: 1 hour
B53: Quarterly | C53: Review prices against the Job Costing tab. Any client under your margin floor needs a conversation. | I53: 1 hour
A55: What the workbook does by itself
B56: Prices a clean from the floor area, the room count, the service or your target margin - and shows all four.
B57: Works out finish times, crew size and hours per cleaner.
B58: Applies the frequency discount, the pet surcharge, the minimum charge and your rounding rule.
B59: Flags double bookings, long days and jobs with nobody on them.
B60: Totals quotes from their lines, dates the expiry and tells you when to chase.
B61: Builds invoices from the lines, ages them, adds the late fee and tracks the balance after every payment.
B62: Costs every job with real wages from the timesheets, real supply usage and the travel, then shows the margin.
B63: Tracks stock down to days of cover and tells you what to reorder.
B64: Warns you before certificates expire and before machines are due a service.
B65: Spots clients going quiet long before they tell you they are leaving.
A67: What it honestly cannot do
B68: Every one of these needs something outside a spreadsheet. Anyone who tells you otherwise is selling you something.
B69: Send reminders by itself. It flags what needs chasing - you or your phone still send the message.
B70: Sync with Google Calendar, Outlook or a phone diary. Export the Jobs tab to CSV if you need that.
B71: Take card payments or connect to your bank. Record the payment here once it lands.
B72: Collect a legally binding electronic signature. Print the quote, or use a proper e-signature service.
B73: Track your cleaners' location, or clock them in by GPS.
B74: File your tax return. It gets the numbers ready for someone who can.
B75: Replace advice from an accountant or an employment lawyer, and it does not know your local rules.
A77: A word about privacy
B78: This file will end up holding client addresses, alarm codes, where the keys are kept, staff pay and background checks. That is genuinely sensitive. Keep it somewhere access-controlled, do not email the whole workbook to anyone, give cleaners the printed job sheet rather than the file, and delete entry details when a client leaves. The sheet password protects formulas from accidents - it is not encryption.
A80: Housekeeping
B81: Question | C81: Answer
B82: Is there example data in it? | C82: Both versions are in your download: one filled with a worked example, one empty and ready for your own.
B83: How do I clear the example? | C83: Select the data rows on a tab and press Delete. The formula columns refill themselves - they are not deleted.
B84: Why are some cells locked? | C84: Every calculated cell is protected so a stray paste cannot break it. The password is 'premium'. Review, Unprotect Sheet if you want to change a formula.
B85: Which cells do I type in? | C85: The white ones. Grey cells calculate themselves.
B86: Does it work in Google Sheets? | C86: Yes. File, Import, Upload. Drop-downs and conditional colours come across; sheet protection behaves a little differently.
B87: Which Excel versions? | C87: Excel 2010 and newer, Excel for Mac, Excel online, LibreOffice Calc and Google Sheets. No macros, so nothing to enable.
B88: Can I add more rows? | C88: Yes - insert rows inside the existing block and copy the formulas down. Never insert above the header row.
B89: Can I add my logo? | C89: Insert, Picture on the printable forms. Everything else is typed on the Settings tab.
B91: Cleaning Business CRM & Pricing Calculator - version 1.0.0, by Novality Store. Built with formulas only: no macros, no add-ins, nothing to install. The Help tab has the troubleshooting and a map of every feature.

Sheet Settings
A1: Business Settings | G1: Novality Store | v1.0.0
A2: Fill in the white cells once. Shaded cells are locked formulas. Every price, every invoice and every alert in the workbook reads these values.
A3: > Start Here | C3: > Dashboard | E3: > Clients | G3: > Jobs
A5: 1. Your business
B6: Business name | D6: Bright & Tidy Cleaning Co. | F6: Shown on every quote, invoice and printable page.
B7: Owner / manager | D7: Dana Whitfield
B8: Email | D8: hello@brightandtidy.co
B9: Phone | D9: (503) 555 0142
B10: Address | D10: 18 Juniper Way, Portland, OR 97214
B11: Website | D11: brightandtidy.co
B12: Area you cover | D12: Portland metro - 20 mile radius | F12: Used on quotes and to sanity check how far a job is.
B13: Tagline | D13: Reliable domestic and commercial cleaning since 2019
B14: Business / tax number | D14: BT-CLEAN-2019-0146
B15: Insurance policy | D15: Hartfield Commercial - policy HCX-884213 | F15: Clients ask for this more often than you think - keep it here so it is easy to quote.
A17: 2. Your working week
B18: Year | D18: 2026 | E18: The year the calendar, the planner and the reports open on.
B19: Week starts on | D19: Monday | E19: Used by the calendar grid, the staff rota and the week numbers.
B20: Billable hours in a working day | D20: 6 | E20: Hours one cleaner can actually charge for after travel, setup and breaks. The capacity and utilisation figures use this.
B21: Cleaners on a standard job | D21: 2 | E21: Two cleaners for three hours is six paid hours - the costing tab works that out for you.
B22: Travel allowance between jobs (minutes) | D22: 20 | E22: Added to each job when the scheduler checks whether two bookings clash.
B23: Area measured in | D23: sq ft | E23: Square feet or square metres - the price per unit below should match.
B24: Distance measured in | D24: miles
B25: Today | D25: =TODAY() -> 0 | E25: Every 'due', 'overdue' and 'coming up' flag in the workbook counts from this cell, so they all move on by themselves overnight.
B26: This month starts | D26: =DATE(YEAR(TodayDate),MONTH(TodayDate),1) -> 0
B27: This month ends | D27: =DATE(YEAR(TodayDate),MONTH(TodayDate)+1,1)-1 -> 0
B28: This week starts | D28: =TodayDate-WEEKDAY(TodayDate,IF(WeekStart="Sunday",1,2))+1 -> 0
A30: 3. What you charge
B31: These are the numbers the quote calculator multiplies. Set them once from your own costs and local market - the figures shipped with the workbook are a realistic starting point, not advice on what to charge.
B32: Standard hourly rate | D32: 45 | E32: What one cleaner's hour costs the client.
B33: Minimum charge for any job | D33: 90 | E33: No quote leaves below this, however small the job. It covers getting there and back.
B34: Price per sq ft | D34: 0.09 | E34: Used by the area based pricing method - common for offices and end of tenancy work.
B35: Price per bedroom | D35: 25
B36: Price per bathroom | D36: 30 | E36: Bathrooms and kitchens take the longest - price them higher than a bedroom.
B37: Price per other room | D37: 18
B38: Call out / travel fee | D38: 15
B39: Deep clean uplift | D39: 0.45 | E39: A deep clean takes far longer than a weekly visit. 45% means a $200 clean quotes at $290.
B40: Move in / move out uplift | D40: 0.35
B41: Pet surcharge | D41: 20 | E41: Hair and paw prints are real extra minutes. Set it to 0 if you would rather absorb it.
B42: Deposit to take up front | D42: 0.25 | E42: Shown on quotes and contracts for larger jobs.
B43: Price rounding | D43: Nearest 5 | E43: Quotes look more professional rounded. 'Nearest 5' turns 187.40 into 185.
A45: 4. What the work costs you
B46: Cleaner pay rate an hour | D46: 18 | E46: Gross pay before your on-costs.
B47: Overtime multiplier | D47: 1.5 | E47: 1.5 = time and a half on overtime hours.
B48: Employer on-costs | D48: 0.18 | E48: Payroll tax, insurance, holiday pay, sick pay - the part of an employee most owners forget to price in.
B49: True cost of one cleaner hour | D49: =PayRate*(1+EmployerOncost) -> 0 | E49: Pay plus on-costs. Every job costing and profit figure in the workbook uses this.
B50: Supplies used per hour | D50: 2.5 | E50: Chemicals, cloths, bags - the consumables a cleaning hour burns through.
B51: Mileage rate per mile | D51: 0.67 | E51: What you reimburse (or claim) for travel.
B52: Target gross margin | D52: 0.45 | E52: What a healthy job should make after wages and supplies. The quote calculator shows you the price that hits it.
B53: Flag a job below this margin | D53: 0.25 | E53: Anything thinner than this turns red on the costing tab and the dashboard.
A55: 5. Invoicing and payment
B56: Sales tax / VAT rate | D56: 0 | E56: Leave at 0 if you are not registered. Every invoice total adds this to the net amount.
B57: What you call the tax | D57: Sales tax | E57: VAT, GST, Sales tax - whatever the invoice should say.
B58: Payment terms (days) | D58: 14 | E58: Due date = invoice date plus this. The overdue flags count from the due date.
B59: Late fee | D59: 0.05 | E59: Only charge it if your contract says you can.
B60: Grace days before 'overdue' | D60: 0
B61: A quote stays valid for (days) | D61: 30
B62: Bank / payment details | D62: Bright & Tidy Ltd - 00-00-00 12345678 | F62: Printed at the bottom of every invoice.
A64: 6. Targets the dashboard measures you against
B65: Revenue target a month | D65: 6000
B66: Revenue target a year | D66: 72000
B67: Expense budget a month | D67: 4000
B68: Utilisation target | D68: 0.75 | E68: Share of the hours you pay for that you actually bill. 75% is good for a small team.
B69: Client retention target | D69: 0.85
B70: Quote win rate target | D70: 0.5 | E70: Winning every quote usually means you are too cheap. Half is a healthy place to be.
B71: Satisfaction target (out of 5) | D71: 4.5
A73: 7. When the workbook should nudge you
B74: Remind me about a job this many days early | D74: 2 | E74: Drives the 'coming up' list on the dashboard and the confirmation chase list.
B75: Chase an unanswered quote after (days) | D75: 3 | E75: The single highest value number on this tab. Most lost quotes were never followed up.
B76: A client is 'going quiet' after (days) | D76: 60 | E76: Used by the retention tab to spot clients drifting away before they are gone.
B77: Days of stock that counts as low | D77: 14
B78: Service equipment every (days) | D78: 90
B79: Warn before a certificate expires (days) | D79: 45 | E79: Insurance, background checks, training - the Safety tab turns amber this far ahead.
B80: Warn before a contract renews (days) | D80: 60
A82: 8. ID prefixes
B83: The letters in front of the automatic numbers. Change them before you start entering data, not after.
B84: Client IDs | D84: CL-
B85: Property IDs | D85: PR-
B86: Lead IDs | D86: LD-
B87: Service IDs | D87: SV-
B88: Quote IDs | D88: Q-
B89: Job IDs | D89: JOB-
B90: Invoice IDs | D90: INV-
B91: Payment IDs | D91: PAY-
B92: Employee IDs | D92: EMP-
B93: Supply IDs | D93: SUP-
B94: Equipment IDs | D94: EQ-
B95: Expense IDs | D95: EXP-
B96: Complaint IDs | D96: CMP-
A98: 9. About this workbook
B99: Product | D99: Cleaning Business CRM & Pricing Calculator
B100: Version | D100: 1.0.0
B101: Created by | D101: Novality Store
B102: Sheet protection password | D102: premium | E102: Review > Unprotect Sheet if you need to change a formula.
B103: Currency | D103: $ (USD)
B105: Changed a price here? Everything updates straight away - the quote calculator, every open quote, the job costing and the dashboard all read these cells rather than keeping their own copy. Invoices you have already sent keep the amount you typed on them.

Sheet Dashboard
A1: Business Dashboard | J1: Novality Store | v1.0.0
A2: Today, this week and the year so far - all worked out from the jobs, invoices and expenses you have already entered.
A3: > Start Here | C3: > Dashboard | E3: > Clients | G3: > Jobs | I3: > Calendar | K3: > Quotes
A5: Business | B5: =BizName -> 0 | E5: Month | F5: =TEXT(TodayDate,"mmmm yyyy") -> 0 | G5: Month key | H5: =TEXT(TodayDate,"yyyy-mm") -> 0 | I5: Today | K5: =TodayDate -> 0
A7: Revenue this month | D7: Invoiced this month | G7: Collected this month | J7: Owed to you right now
A8: =SUMIFS(Jobs!$AJ$5:$AJ$604,Jobs!$E$5:$E$604,DashKey,Jobs!$P$5:$P$604,"Completed")+SUMIFS(Jobs!$AJ$5:$AJ$604,Jobs!$E$5:$E$604,DashKey,Jobs!$P$5:$P$604,"Invoiced") -> 0 | D8: =SUMIFS(Invoices!$V$5:$V$404,Invoices!$C$5:$C$404,DashKey) -> 0 | G8: =SUMIFS(Payments!$G$5:$G$404,Payments!$C$5:$C$404,DashKey) -> 0 | J8: =SUM(Invoices!$X$5:$X$404) -> 0
A9: target $6,000 | D9: what you have billed | G9: money actually in | J9: every unpaid invoice
A11: Costs this month | D11: Profit this month | G11: Margin this month | J11: Average job value
A12: =SUMIFS(Expenses!$Q$5:$Q$404,Expenses!$C$5:$C$404,DashKey) -> 0 | D12: =SUMIFS(Jobs!$AJ$5:$AJ$604,Jobs!$E$5:$E$604,DashKey,Jobs!$P$5:$P$604,"Completed")+SUMIFS(Jobs!$AJ$5:$AJ$604,Jobs!$E$5:$E$604,DashKey,Jobs!$P$5:$P$604,"Invoiced")-SUMIFS(Expenses!$Q$5:$Q$404,Expenses!$C$5:$C$404,DashKey) -> 0 | G12: =IFERROR((SUMIFS(Jobs!$AJ$5:$AJ$604,Jobs!$E$5:$E$604,DashKey,Jobs!$P$5:$P$604,"Completed")+SUMIFS(Jobs!$AJ$5:$AJ$604,Jobs!$E$5:$E$604,DashKey,Jobs!$P$5:$P$604,"Invoiced")-SUMIFS(Expenses!$Q$5:$Q$404,Expenses!$C$5:$C$404,DashKey))/(SUMIFS(Jobs!$AJ$5:$AJ$604,Jobs!$E$5:$E$604,DashKey,Jobs!$P$5:$P$604,"Completed")+SUMIFS(Jobs!$AJ$5:$AJ$604,Jobs!$E$5:$E$604,DashKey,Jobs!$P$5:$P$604,"Invoiced")),"") -> 0 | J12: =IFERROR((SUMIFS(Jobs!$AJ$5:$AJ$604,Jobs!$E$5:$E$604,DashKey,Jobs!$P$5:$P$604,"Completed")+SUMIFS(Jobs!$AJ$5:$AJ$604,Jobs!$E$5:$E$604,DashKey,Jobs!$P$5:$P$604,"Invoiced"))/(COUNTIFS(Jobs!$E$5:$E$604,DashKey,Jobs!$P$5:$P$604,"Completed")+COUNTIFS(Jobs!$E$5:$E$604,DashKey,Jobs!$P$5:$P$604,"Invoiced")),"") -> 0
A13: budget $4,000 | D13: revenue less expenses | G13: after wages and overheads | J13: completed work this month
A15: Jobs this week | D15: Hours booked this week | G15: Quotes waiting | J15: Active clients
A16: =COUNTIFS(Jobs!$B$5:$B$604,">="&WeekStartDate,Jobs!$B$5:$B$604,"<="&WeekStartDate+6,Jobs!$P$5:$P$604,"<>Cancelled") -> 0 | D16: =SUMIFS(Jobs!$AF$5:$AF$604,Jobs!$B$5:$B$604,">="&WeekStartDate,Jobs!$B$5:$B$604,"<="&WeekStartDate+6,Jobs!$P$5:$P$604,"<>Cancelled") -> 0 | G16: =COUNTIFS(Quotes!$K$5:$K$204,"Sent")+COUNTIFS(Quotes!$K$5:$K$204,"Followed up") -> 0 | J16: =COUNTIFS(Clients!$H$5:$H$204,"Active")+COUNTIFS(Clients!$H$5:$H$204,"Regular") -> 0
A17: booked in the next seven days | D17: across the whole team | G17: worth chasing today | J17: on the books right now
A19: Needs your attention
A20: What | B20: How many | C20: What it means | D20: Where to fix it
A21: Jobs with no cleaner | B21: =COUNTIFS(Jobs!$R$5:$R$604,"",Jobs!$G$5:$G$604,"<>",Jobs!$B$5:$B$604,">="&TodayDate) -> 0 | C21: ="Booked work nobody is assigned to yet" -> 0 | K21: Jobs
A22: Visits to confirm | B22: =COUNTIF(Jobs!$AX$5:$AX$604,"Confirm*") -> 0 | C22: ="Coming up within "&ReminderDays&" days and not confirmed with the client" -> 0 | K22: Jobs
A23: Double bookings | B23: =COUNTIF(Jobs!$AR$5:$AR$604,"Clash") -> 0 | C23: ="The same cleaner booked twice at the same time" -> 0 | K23: Jobs
A24: Jobs done but not invoiced | B24: =COUNTIFS(Jobs!$P$5:$P$604,"Completed",Jobs!$AP$5:$AP$604,"") -> 0 | C24: ="Work you have done and not yet billed - worth "&TEXT(SUMIFS(Jobs!$AJ$5:$AJ$604,Jobs!$P$5:$P$604,"Completed",Jobs!$AP$5:$AP$604,""),"#,##0") -> 0 | K24: Invoices
A25: Overdue invoices | B25: =COUNTIF(Invoices!$AE$5:$AE$404,"Overdue*") -> 0 | C25: ="Past their due date, totalling "&TEXT(SUMIFS(Invoices!$X$5:$X$404,Invoices!$AB$5:$AB$404,"1-30 days")+SUMIFS(Invoices!$X$5:$X$404,Invoices!$AB$5:$AB$404,"31-60 days")+SUMIFS(Invoices!$X$5:$X$404,Invoices!$AB$5:$AB$404,"61-90 days")+SUMIFS(Invoices!$X$5:$X$404,Invoices!$AB$5:$AB$404,"90+ days"),"#,##0") -> 0 | K25: Invoices
A26: Quotes to chase | B26: =COUNTIF(Quotes!$AK$5:$AK$204,"Chase*") -> 0 | C26: ="Sent more than "&QuoteFollowupDays&" days ago with no answer - this is the fastest money in the workbook" -> 0 | K26: Quotes
A27: Leads with no quote | B27: =COUNTIF(Leads!$Z$5:$Z$154,"Action - no quote*") -> 0 | C27: ="Enquiries that have not been priced yet" -> 0 | K27: Leads
A28: Clients going quiet | B28: =COUNTIF(Clients!$AP$5:$AP$204,"At risk")+COUNTIF(Clients!$AP$5:$AP$204,"Slipping") -> 0 | C28: ="No visit booked, or nothing for "&InactiveClientDays&" days" -> 0 | K28: Client Retention
A29: Supplies to reorder | B29: =COUNTIF(Supplies!$Y$5:$Y$154,"Low stock")+COUNTIF(Supplies!$Y$5:$Y$154,"Out of stock") -> 0 | C29: ="Below the reorder level or less than "&LowStockDays&" days of cover" -> 0 | K29: Supplies
A30: Equipment due a service | B30: =COUNTIF(Equipment!$Z$5:$Z$84,"Overdue*")+COUNTIF(Equipment!$Z$5:$Z$84,"Due*") -> 0 | C30: ="A machine that dies mid-job costs you the day" -> 0 | K30: Equipment
A31: Certificates expiring | B31: =COUNTIF(Safety!$P$5:$P$84,"Due soon")+COUNTIF(Safety!$P$5:$P$84,"Expired") -> 0 | C31: ="Insurance, checks and training within "&CertWarningDays&" days of running out" -> 0 | K31: Safety
A32: Open complaints | B32: =COUNTIF(Complaints!$W$5:$W$84,"Yes") -> 0 | C32: ="Every day one of these stays open costs you a client" -> 0 | K32: Complaints
A33: Loss-making jobs | B33: =COUNTIF('Job Costing'!$AA$5:$AA$604,"Loss*") -> 0 | C33: ="Jobs that cost more than they earned" -> 0 | K33: Job Costing
A34: Timesheets to approve | B34: =COUNTIF(Timesheets!$Z$5:$Z$804,"Due - needs approving") -> 0 | C34: ="Hours entered but not signed off" -> 0 | K34: Timesheets
A36: The next seven days
A37: Day | B37: =TodayDate+0 -> 0 | C37: =TodayDate+1 -> 0 | D37: =TodayDate+2 -> 0 | E37: =TodayDate+3 -> 0 | F37: =TodayDate+4 -> 0 | G37: =TodayDate+5 -> 0 | H37: =TodayDate+6 -> 0 | I37: Week
A38: Jobs booked | B38: =COUNTIFS(Jobs!$B$5:$B$604,B$37,Jobs!$P$5:$P$604,"<>Cancelled") -> 0 | C38: =COUNTIFS(Jobs!$B$5:$B$604,C$37,Jobs!$P$5:$P$604,"<>Cancelled") -> 0 | D38: =COUNTIFS(Jobs!$B$5:$B$604,D$37,Jobs!$P$5:$P$604,"<>Cancelled") -> 0 | E38: =COUNTIFS(Jobs!$B$5:$B$604,E$37,Jobs!$P$5:$P$604,"<>Cancelled") -> 0 | F38: =COUNTIFS(Jobs!$B$5:$B$604,F$37,Jobs!$P$5:$P$604,"<>Cancelled") -> 0 | G38: =COUNTIFS(Jobs!$B$5:$B$604,G$37,Jobs!$P$5:$P$604,"<>Cancelled") -> 0 | H38: =COUNTIFS(Jobs!$B$5:$B$604,H$37,Jobs!$P$5:$P$604,"<>Cancelled") -> 0 | I38: =COUNTIFS(Jobs!$B$5:$B$604,">="&TodayDate,Jobs!$B$5:$B$604,"<="&TodayDate+6,Jobs!$P$5:$P$604,"<>Cancelled") -> 0
A39: Hours on site | B39: =SUMIFS(Jobs!$AF$5:$AF$604,Jobs!$B$5:$B$604,B$37,Jobs!$P$5:$P$604,"<>Cancelled") -> 0 | C39: =SUMIFS(Jobs!$AF$5:$AF$604,Jobs!$B$5:$B$604,C$37,Jobs!$P$5:$P$604,"<>Cancelled") -> 0 | D39: =SUMIFS(Jobs!$AF$5:$AF$604,Jobs!$B$5:$B$604,D$37,Jobs!$P$5:$P$604,"<>Cancelled") -> 0 | E39: =SUMIFS(Jobs!$AF$5:$AF$604,Jobs!$B$5:$B$604,E$37,Jobs!$P$5:$P$604,"<>Cancelled") -> 0 | F39: =SUMIFS(Jobs!$AF$5:$AF$604,Jobs!$B$5:$B$604,F$37,Jobs!$P$5:$P$604,"<>Cancelled") -> 0 | G39: =SUMIFS(Jobs!$AF$5:$AF$604,Jobs!$B$5:$B$604,G$37,Jobs!$P$5:$P$604,"<>Cancelled") -> 0 | H39: =SUMIFS(Jobs!$AF$5:$AF$604,Jobs!$B$5:$B$604,H$37,Jobs!$P$5:$P$604,"<>Cancelled") -> 0 | I39: =SUMIFS(Jobs!$AF$5:$AF$604,Jobs!$B$5:$B$604,">="&TodayDate,Jobs!$B$5:$B$604,"<="&TodayDate+6,Jobs!$P$5:$P$604,"<>Cancelled") -> 0
A40: Value | B40: =SUMIFS(Jobs!$AJ$5:$AJ$604,Jobs!$B$5:$B$604,B$37,Jobs!$P$5:$P$604,"<>Cancelled") -> 0 | C40: =SUMIFS(Jobs!$AJ$5:$AJ$604,Jobs!$B$5:$B$604,C$37,Jobs!$P$5:$P$604,"<>Cancelled") -> 0 | D40: =SUMIFS(Jobs!$AJ$5:$AJ$604,Jobs!$B$5:$B$604,D$37,Jobs!$P$5:$P$604,"<>Cancelled") -> 0 | E40: =SUMIFS(Jobs!$AJ$5:$AJ$604,Jobs!$B$5:$B$604,E$37,Jobs!$P$5:$P$604,"<>Cancelled") -> 0 | F40: =SUMIFS(Jobs!$AJ$5:$AJ$604,Jobs!$B$5:$B$604,F$37,Jobs!$P$5:$P$604,"<>Cancelled") -> 0 | G40: =SUMIFS(Jobs!$AJ$5:$AJ$604,Jobs!$B$5:$B$604,G$37,Jobs!$P$5:$P$604,"<>Cancelled") -> 0 | H40: =SUMIFS(Jobs!$AJ$5:$AJ$604,Jobs!$B$5:$B$604,H$37,Jobs!$P$5:$P$604,"<>Cancelled") -> 0 | I40: =SUMIFS(Jobs!$AJ$5:$AJ$604,Jobs!$B$5:$B$604,">="&TodayDate,Jobs!$B$5:$B$604,"<="&TodayDate+6,Jobs!$P$5:$P$604,"<>Cancelled") -> 0
A41: Cleaners needed | B41: =SUMIFS(Jobs!$AE$5:$AE$604,Jobs!$B$5:$B$604,B$37,Jobs!$P$5:$P$604,"<>Cancelled") -> 0 | C41: =SUMIFS(Jobs!$AE$5:$AE$604,Jobs!$B$5:$B$604,C$37,Jobs!$P$5:$P$604,"<>Cancelled") -> 0 | D41: =SUMIFS(Jobs!$AE$5:$AE$604,Jobs!$B$5:$B$604,D$37,Jobs!$P$5:$P$604,"<>Cancelled") -> 0 | E41: =SUMIFS(Jobs!$AE$5:$AE$604,Jobs!$B$5:$B$604,E$37,Jobs!$P$5:$P$604,"<>Cancelled") -> 0 | F41: =SUMIFS(Jobs!$AE$5:$AE$604,Jobs!$B$5:$B$604,F$37,Jobs!$P$5:$P$604,"<>Cancelled") -> 0 | G41: =SUMIFS(Jobs!$AE$5:$AE$604,Jobs!$B$5:$B$604,G$37,Jobs!$P$5:$P$604,"<>Cancelled") -> 0 | H41: =SUMIFS(Jobs!$AE$5:$AE$604,Jobs!$B$5:$B$604,H$37,Jobs!$P$5:$P$604,"<>Cancelled") -> 0 | I41: =SUMIFS(Jobs!$AE$5:$AE$604,Jobs!$B$5:$B$604,">="&TodayDate,Jobs!$B$5:$B$604,"<="&TodayDate+6,Jobs!$P$5:$P$604,"<>Cancelled") -> 0
A43: Nothing in a column means a free day - the best day to fit in a quote visit, a deep clean or some time off.
A45: Your five biggest clients
A46: Client | B46: Type | C46: Jobs done | D46: Invoiced | E46: Profit | F46: Margin | G46: Worth a year | H46: Last clean | I46: Standing
A47: =IFERROR(INDEX(Clients!$B$5:$B$204,MATCH(1,Clients!$AM$5:$AM$204,0)),"") -> 0 | B47: =IFERROR(INDEX(Clients!$C$5:$C$204,MATCH(1,Clients!$AM$5:$AM$204,0)),"") -> 0 | C47: =IFERROR(INDEX(Clients!$Y$5:$Y$204,MATCH(1,Clients!$AM$5:$AM$204,0)),"") -> 0 | D47: =IFERROR(INDEX(Clients!$AD$5:$AD$204,MATCH(1,Clients!$AM$5:$AM$204,0)),"") -> 0 | E47: =IFERROR(INDEX(Clients!$AH$5:$AH$204,MATCH(1,Clients!$AM$5:$AM$204,0)),"") -> 0 | F47: =IFERROR(INDEX(Clients!$AI$5:$AI$204,MATCH(1,Clients!$AM$5:$AM$204,0)),"") -> 0 | G47: =IFERROR(INDEX(Clients!$AJ$5:$AJ$204,MATCH(1,Clients!$AM$5:$AM$204,0)),"") -> 0 | H47: =IFERROR(INDEX(Clients!$AA$5:$AA$204,MATCH(1,Clients!$AM$5:$AM$204,0)),"") -> 0 | I47: =IFERROR(INDEX(Clients!$AP$5:$AP$204,MATCH(1,Clients!$AM$5:$AM$204,0)),"") -> 0
A48: =IFERROR(INDEX(Clients!$B$5:$B$204,MATCH(2,Clients!$AM$5:$AM$204,0)),"") -> 0 | B48: =IFERROR(INDEX(Clients!$C$5:$C$204,MATCH(2,Clients!$AM$5:$AM$204,0)),"") -> 0 | C48: =IFERROR(INDEX(Clients!$Y$5:$Y$204,MATCH(2,Clients!$AM$5:$AM$204,0)),"") -> 0 | D48: =IFERROR(INDEX(Clients!$AD$5:$AD$204,MATCH(2,Clients!$AM$5:$AM$204,0)),"") -> 0 | E48: =IFERROR(INDEX(Clients!$AH$5:$AH$204,MATCH(2,Clients!$AM$5:$AM$204,0)),"") -> 0 | F48: =IFERROR(INDEX(Clients!$AI$5:$AI$204,MATCH(2,Clients!$AM$5:$AM$204,0)),"") -> 0 | G48: =IFERROR(INDEX(Clients!$AJ$5:$AJ$204,MATCH(2,Clients!$AM$5:$AM$204,0)),"") -> 0 | H48: =IFERROR(INDEX(Clients!$AA$5:$AA$204,MATCH(2,Clients!$AM$5:$AM$204,0)),"") -> 0 | I48: =IFERROR(INDEX(Clients!$AP$5:$AP$204,MATCH(2,Clients!$AM$5:$AM$204,0)),"") -> 0
A49: =IFERROR(INDEX(Clients!$B$5:$B$204,MATCH(3,Clients!$AM$5:$AM$204,0)),"") -> 0 | B49: =IFERROR(INDEX(Clients!$C$5:$C$204,MATCH(3,Clients!$AM$5:$AM$204,0)),"") -> 0 | C49: =IFERROR(INDEX(Clients!$Y$5:$Y$204,MATCH(3,Clients!$AM$5:$AM$204,0)),"") -> 0 | D49: =IFERROR(INDEX(Clients!$AD$5:$AD$204,MATCH(3,Clients!$AM$5:$AM$204,0)),"") -> 0 | E49: =IFERROR(INDEX(Clients!$AH$5:$AH$204,MATCH(3,Clients!$AM$5:$AM$204,0)),"") -> 0 | F49: =IFERROR(INDEX(Clients!$AI$5:$AI$204,MATCH(3,Clients!$AM$5:$AM$204,0)),"") -> 0 | G49: =IFERROR(INDEX(Clients!$AJ$5:$AJ$204,MATCH(3,Clients!$AM$5:$AM$204,0)),"") -> 0 | H49: =IFERROR(INDEX(Clients!$AA$5:$AA$204,MATCH(3,Clients!$AM$5:$AM$204,0)),"") -> 0 | I49: =IFERROR(INDEX(Clients!$AP$5:$AP$204,MATCH(3,Clients!$AM$5:$AM$204,0)),"") -> 0
A50: =IFERROR(INDEX(Clients!$B$5:$B$204,MATCH(4,Clients!$AM$5:$AM$204,0)),"") -> 0 | B50: =IFERROR(INDEX(Clients!$C$5:$C$204,MATCH(4,Clients!$AM$5:$AM$204,0)),"") -> 0 | C50: =IFERROR(INDEX(Clients!$Y$5:$Y$204,MATCH(4,Clients!$AM$5:$AM$204,0)),"") -> 0 | D50: =IFERROR(INDEX(Clients!$AD$5:$AD$204,MATCH(4,Clients!$AM$5:$AM$204,0)),"") -> 0 | E50: =IFERROR(INDEX(Clients!$AH$5:$AH$204,MATCH(4,Clients!$AM$5:$AM$204,0)),"") -> 0 | F50: =IFERROR(INDEX(Clients!$AI$5:$AI$204,MATCH(4,Clients!$AM$5:$AM$204,0)),"") -> 0 | G50: =IFERROR(INDEX(Clients!$AJ$5:$AJ$204,MATCH(4,Clients!$AM$5:$AM$204,0)),"") -> 0 | H50: =IFERROR(INDEX(Clients!$AA$5:$AA$204,MATCH(4,Clients!$AM$5:$AM$204,0)),"") -> 0 | I50: =IFERROR(INDEX(Clients!$AP$5:$AP$204,MATCH(4,Clients!$AM$5:$AM$204,0)),"") -> 0
A51: =IFERROR(INDEX(Clients!$B$5:$B$204,MATCH(5,Clients!$AM$5:$AM$204,0)),"") -> 0 | B51: =IFERROR(INDEX(Clients!$C$5:$C$204,MATCH(5,Clients!$AM$5:$AM$204,0)),"") -> 0 | C51: =IFERROR(INDEX(Clients!$Y$5:$Y$204,MATCH(5,Clients!$AM$5:$AM$204,0)),"") -> 0 | D51: =IFERROR(INDEX(Clients!$AD$5:$AD$204,MATCH(5,Clients!$AM$5:$AM$204,0)),"") -> 0 | E51: =IFERROR(INDEX(Clients!$AH$5:$AH$204,MATCH(5,Clients!$AM$5:$AM$204,0)),"") -> 0 | F51: =IFERROR(INDEX(Clients!$AI$5:$AI$204,MATCH(5,Clients!$AM$5:$AM$204,0)),"") -> 0 | G51: =IFERROR(INDEX(Clients!$AJ$5:$AJ$204,MATCH(5,Clients!$AM$5:$AM$204,0)),"") -> 0 | H51: =IFERROR(INDEX(Clients!$AA$5:$AA$204,MATCH(5,Clients!$AM$5:$AM$204,0)),"") -> 0 | I51: =IFERROR(INDEX(Clients!$AP$5:$AP$204,MATCH(5,Clients!$AM$5:$AM$204,0)),"") -> 0
A53: The year so far
A54: Month | B54: Jobs | C54: Revenue | D54: Invoiced | E54: Collected | F54: Costs | G54: Profit | H54: Margin | I54: New clients | J54: Trend
A55: =TEXT(DATE(PlanYear,1,1),"mmm") -> 0 | B55: =COUNTIFS(Jobs!$E$5:$E$604,TEXT(DATE(PlanYear,1,1),"yyyy-mm"),Jobs!$P$5:$P$604,"<>Cancelled") -> 0 | C55: =SUMIFS(Jobs!$AJ$5:$AJ$604,Jobs!$E$5:$E$604,TEXT(DATE(PlanYear,1,1),"yyyy-mm"),Jobs!$P$5:$P$604,"Completed")+SUMIFS(Jobs!$AJ$5:$AJ$604,Jobs!$E$5:$E$604,TEXT(DATE(PlanYear,1,1),"yyyy-mm"),Jobs!$P$5:$P$604,"Invoiced") -> 0 | D55: =SUMIFS(Invoices!$V$5:$V$404,Invoices!$C$5:$C$404,TEXT(DATE(PlanYear,1,1),"yyyy-mm")) -> 0 | E55: =SUMIFS(Payments!$G$5:$G$404,Payments!$C$5:$C$404,TEXT(DATE(PlanYear,1,1),"yyyy-mm")) -> 0 | F55: =SUMIFS(Expenses!$Q$5:$Q$404,Expenses!$C$5:$C$404,TEXT(DATE(PlanYear,1,1),"yyyy-mm")) -> 0 | G55: =SUMIFS(Jobs!$AJ$5:$AJ$604,Jobs!$E$5:$E$604,TEXT(DATE(PlanYear,1,1),"yyyy-mm"),Jobs!$P$5:$P$604,"Completed")+SUMIFS(Jobs!$AJ$5:$AJ$604,Jobs!$E$5:$E$604,TEXT(DATE(PlanYear,1,1),"yyyy-mm"),Jobs!$P$5:$P$604,"Invoiced")-SUMIFS(Expenses!$Q$5:$Q$404,Expenses!$C$5:$C$404,TEXT(DATE(PlanYear,1,1),"yyyy-mm")) -> 0 | H55: =IFERROR((SUMIFS(Jobs!$AJ$5:$AJ$604,Jobs!$E$5:$E$604,TEXT(DATE(PlanYear,1,1),"yyyy-mm"),Jobs!$P$5:$P$604,"Completed")+SUMIFS(Jobs!$AJ$5:$AJ$604,Jobs!$E$5:$E$604,TEXT(DATE(PlanYear,1,1),"yyyy-mm"),Jobs!$P$5:$P$604,"Invoiced")-SUMIFS(Expenses!$Q$5:$Q$404,Expenses!$C$5:$C$404,TEXT(DATE(PlanYear,1,1),"yyyy-mm")))/(SUMIFS(Jobs!$AJ$5:$AJ$604,Jobs!$E$5:$E$604,TEXT(DATE(PlanYear,1,1),"yyyy-mm"),Jobs!$P$5:$P$604,"Completed")+SUMIFS(Jobs!$AJ$5:$AJ$604,Jobs!$E$5:$E$604,TEXT(DATE(PlanYear,1,1),"yyyy-mm"),Jobs!$P$5:$P$604,"Invoiced")),"") -> 0 | I55: =COUNTIFS(Clients!$J$5:$J$204,">="&DATE(PlanYear,1,1),Clients!$J$5:$J$204,"<"&DATE(PlanYear,2,1)) -> 0
A56: =TEXT(DATE(PlanYear,2,1),"mmm") -> 0 | B56: =COUNTIFS(Jobs!$E$5:$E$604,TEXT(DATE(PlanYear,2,1),"yyyy-mm"),Jobs!$P$5:$P$604,"<>Cancelled") -> 0 | C56: =SUMIFS(Jobs!$AJ$5:$AJ$604,Jobs!$E$5:$E$604,TEXT(DATE(PlanYear,2,1),"yyyy-mm"),Jobs!$P$5:$P$604,"Completed")+SUMIFS(Jobs!$AJ$5:$AJ$604,Jobs!$E$5:$E$604,TEXT(DATE(PlanYear,2,1),"yyyy-mm"),Jobs!$P$5:$P$604,"Invoiced") -> 0 | D56: =SUMIFS(Invoices!$V$5:$V$404,Invoices!$C$5:$C$404,TEXT(DATE(PlanYear,2,1),"yyyy-mm")) -> 0 | E56: =SUMIFS(Payments!$G$5:$G$404,Payments!$C$5:$C$404,TEXT(DATE(PlanYear,2,1),"yyyy-mm")) -> 0 | F56: =SUMIFS(Expenses!$Q$5:$Q$404,Expenses!$C$5:$C$404,TEXT(DATE(PlanYear,2,1),"yyyy-mm")) -> 0 | G56: =SUMIFS(Jobs!$AJ$5:$AJ$604,Jobs!$E$5:$E$604,TEXT(DATE(PlanYear,2,1),"yyyy-mm"),Jobs!$P$5:$P$604,"Completed")+SUMIFS(Jobs!$AJ$5:$AJ$604,Jobs!$E$5:$E$604,TEXT(DATE(PlanYear,2,1),"yyyy-mm"),Jobs!$P$5:$P$604,"Invoiced")-SUMIFS(Expenses!$Q$5:$Q$404,Expenses!$C$5:$C$404,TEXT(DATE(PlanYear,2,1),"yyyy-mm")) -> 0 | H56: =IFERROR((SUMIFS(Jobs!$AJ$5:$AJ$604,Jobs!$E$5:$E$604,TEXT(DATE(PlanYear,2,1),"yyyy-mm"),Jobs!$P$5:$P$604,"Completed")+SUMIFS(Jobs!$AJ$5:$AJ$604,Jobs!$E$5:$E$604,TEXT(DATE(PlanYear,2,1),"yyyy-mm"),Jobs!$P$5:$P$604,"Invoiced")-SUMIFS(Expenses!$Q$5:$Q$404,Expenses!$C$5:$C$404,TEXT(DATE(PlanYear,2,1),"yyyy-mm")))/(SUMIFS(Jobs!$AJ$5:$AJ$604,Jobs!$E$5:$E$604,TEXT(DATE(PlanYear,2,1),"yyyy-mm"),Jobs!$P$5:$P$604,"Completed")+SUMIFS(Jobs!$AJ$5:$AJ$604,Jobs!$E$5:$E$604,TEXT(DATE(PlanYear,2,1),"yyyy-mm"),Jobs!$P$5:$P$604,"Invoiced")),"") -> 0 | I56: =COUNTIFS(Clients!$J$5:$J$204,">="&DATE(PlanYear,2,1),Clients!$J$5:$J$204,"<"&DATE(PlanYear,3,1)) -> 0
A57: =TEXT(DATE(PlanYear,3,1),"mmm") -> 0 | B57: =COUNTIFS(Jobs!$E$5:$E$604,TEXT(DATE(PlanYear,3,1),"yyyy-mm"),Jobs!$P$5:$P$604,"<>Cancelled") -> 0 | C57: =SUMIFS(Jobs!$AJ$5:$AJ$604,Jobs!$E$5:$E$604,TEXT(DATE(PlanYear,3,1),"yyyy-mm"),Jobs!$P$5:$P$604,"Completed")+SUMIFS(Jobs!$AJ$5:$AJ$604,Jobs!$E$5:$E$604,TEXT(DATE(PlanYear,3,1),"yyyy-mm"),Jobs!$P$5:$P$604,"Invoiced") -> 0 | D57: =SUMIFS(Invoices!$V$5:$V$404,Invoices!$C$5:$C$404,TEXT(DATE(PlanYear,3,1),"yyyy-mm")) -> 0 | E57: =SUMIFS(Payments!$G$5:$G$404,Payments!$C$5:$C$404,TEXT(DATE(PlanYear,3,1),"yyyy-mm")) -> 0 | F57: =SUMIFS(Expenses!$Q$5:$Q$404,Expenses!$C$5:$C$404,TEXT(DATE(PlanYear,3,1),"yyyy-mm")) -> 0 | G57: =SUMIFS(Jobs!$AJ$5:$AJ$604,Jobs!$E$5:$E$604,TEXT(DATE(PlanYear,3,1),"yyyy-mm"),Jobs!$P$5:$P$604,"Completed")+SUMIFS(Jobs!$AJ$5:$AJ$604,Jobs!$E$5:$E$604,TEXT(DATE(PlanYear,3,1),"yyyy-mm"),Jobs!$P$5:$P$604,"Invoiced")-SUMIFS(Expenses!$Q$5:$Q$404,Expenses!$C$5:$C$404,TEXT(DATE(PlanYear,3,1),"yyyy-mm")) -> 0 | H57: =IFERROR((SUMIFS(Jobs!$AJ$5:$AJ$604,Jobs!$E$5:$E$604,TEXT(DATE(PlanYear,3,1),"yyyy-mm"),Jobs!$P$5:$P$604,"Completed")+SUMIFS(Jobs!$AJ$5:$AJ$604,Jobs!$E$5:$E$604,TEXT(DATE(PlanYear,3,1),"yyyy-mm"),Jobs!$P$5:$P$604,"Invoiced")-SUMIFS(Expenses!$Q$5:$Q$404,Expenses!$C$5:$C$404,TEXT(DATE(PlanYear,3,1),"yyyy-mm")))/(SUMIFS(Jobs!$AJ$5:$AJ$604,Jobs!$E$5:$E$604,TEXT(DATE(PlanYear,3,1),"yyyy-mm"),Jobs!$P$5:$P$604,"Completed")+SUMIFS(Jobs!$AJ$5:$AJ$604,Jobs!$E$5:$E$604,TEXT(DATE(PlanYear,3,1),"yyyy-mm"),Jobs!$P$5:$P$604,"Invoiced")),"") -> 0 | I57: =COUNTIFS(Clients!$J$5:$J$204,">="&DATE(PlanYear,3,1),Clients!$J$5:$J$204,"<"&DATE(PlanYear,4,1)) -> 0
A58: =TEXT(DATE(PlanYear,4,1),"mmm") -> 0 | B58: =COUNTIFS(Jobs!$E$5:$E$604,TEXT(DATE(PlanYear,4,1),"yyyy-mm"),Jobs!$P$5:$P$604,"<>Cancelled") -> 0 | C58: =SUMIFS(Jobs!$AJ$5:$AJ$604,Jobs!$E$5:$E$604,TEXT(DATE(PlanYear,4,1),"yyyy-mm"),Jobs!$P$5:$P$604,"Completed")+SUMIFS(Jobs!$AJ$5:$AJ$604,Jobs!$E$5:$E$604,TEXT(DATE(PlanYear,4,1),"yyyy-mm"),Jobs!$P$5:$P$604,"Invoiced") -> 0 | D58: =SUMIFS(Invoices!$V$5:$V$404,Invoices!$C$5:$C$404,TEXT(DATE(PlanYear,4,1),"yyyy-mm")) -> 0 | E58: =SUMIFS(Payments!$G$5:$G$404,Payments!$C$5:$C$404,TEXT(DATE(PlanYear,4,1),"yyyy-mm")) -> 0 | F58: =SUMIFS(Expenses!$Q$5:$Q$404,Expenses!$C$5:$C$404,TEXT(DATE(PlanYear,4,1),"yyyy-mm")) -> 0 | G58: =SUMIFS(Jobs!$AJ$5:$AJ$604,Jobs!$E$5:$E$604,TEXT(DATE(PlanYear,4,1),"yyyy-mm"),Jobs!$P$5:$P$604,"Completed")+SUMIFS(Jobs!$AJ$5:$AJ$604,Jobs!$E$5:$E$604,TEXT(DATE(PlanYear,4,1),"yyyy-mm"),Jobs!$P$5:$P$604,"Invoiced")-SUMIFS(Expenses!$Q$5:$Q$404,Expenses!$C$5:$C$404,TEXT(DATE(PlanYear,4,1),"yyyy-mm")) -> 0 | H58: =IFERROR((SUMIFS(Jobs!$AJ$5:$AJ$604,Jobs!$E$5:$E$604,TEXT(DATE(PlanYear,4,1),"yyyy-mm"),Jobs!$P$5:$P$604,"Completed")+SUMIFS(Jobs!$AJ$5:$AJ$604,Jobs!$E$5:$E$604,TEXT(DATE(PlanYear,4,1),"yyyy-mm"),Jobs!$P$5:$P$604,"Invoiced")-SUMIFS(Expenses!$Q$5:$Q$404,Expenses!$C$5:$C$404,TEXT(DATE(PlanYear,4,1),"yyyy-mm")))/(SUMIFS(Jobs!$AJ$5:$AJ$604,Jobs!$E$5:$E$604,TEXT(DATE(PlanYear,4,1),"yyyy-mm"),Jobs!$P$5:$P$604,"Completed")+SUMIFS(Jobs!$AJ$5:$AJ$604,Jobs!$E$5:$E$604,TEXT(DATE(PlanYear,4,1),"yyyy-mm"),Jobs!$P$5:$P$604,"Invoiced")),"") -> 0 | I58: =COUNTIFS(Clients!$J$5:$J$204,">="&DATE(PlanYear,4,1),Clients!$J$5:$J$204,"<"&DATE(PlanYear,5,1)) -> 0
A59: =TEXT(DATE(PlanYear,5,1),"mmm") -> 0 | B59: =COUNTIFS(Jobs!$E$5:$E$604,TEXT(DATE(PlanYear,5,1),"yyyy-mm"),Jobs!$P$5:$P$604,"<>Cancelled") -> 0 | C59: =SUMIFS(Jobs!$AJ$5:$AJ$604,Jobs!$E$5:$E$604,TEXT(DATE(PlanYear,5,1),"yyyy-mm"),Jobs!$P$5:$P$604,"Completed")+SUMIFS(Jobs!$AJ$5:$AJ$604,Jobs!$E$5:$E$604,TEXT(DATE(PlanYear,5,1),"yyyy-mm"),Jobs!$P$5:$P$604,"Invoiced") -> 0 | D59: =SUMIFS(Invoices!$V$5:$V$404,Invoices!$C$5:$C$404,TEXT(DATE(PlanYear,5,1),"yyyy-mm")) -> 0 | E59: =SUMIFS(Payments!$G$5:$G$404,Payments!$C$5:$C$404,TEXT(DATE(PlanYear,5,1),"yyyy-mm")) -> 0 | F59: =SUMIFS(Expenses!$Q$5:$Q$404,Expenses!$C$5:$C$404,TEXT(DATE(PlanYear,5,1),"yyyy-mm")) -> 0 | G59: =SUMIFS(Jobs!$AJ$5:$AJ$604,Jobs!$E$5:$E$604,TEXT(DATE(PlanYear,5,1),"yyyy-mm"),Jobs!$P$5:$P$604,"Completed")+SUMIFS(Jobs!$AJ$5:$AJ$604,Jobs!$E$5:$E$604,TEXT(DATE(PlanYear,5,1),"yyyy-mm"),Jobs!$P$5:$P$604,"Invoiced")-SUMIFS(Expenses!$Q$5:$Q$404,Expenses!$C$5:$C$404,TEXT(DATE(PlanYear,5,1),"yyyy-mm")) -> 0 | H59: =IFERROR((SUMIFS(Jobs!$AJ$5:$AJ$604,Jobs!$E$5:$E$604,TEXT(DATE(PlanYear,5,1),"yyyy-mm"),Jobs!$P$5:$P$604,"Completed")+SUMIFS(Jobs!$AJ$5:$AJ$604,Jobs!$E$5:$E$604,TEXT(DATE(PlanYear,5,1),"yyyy-mm"),Jobs!$P$5:$P$604,"Invoiced")-SUMIFS(Expenses!$Q$5:$Q$404,Expenses!$C$5:$C$404,TEXT(DATE(PlanYear,5,1),"yyyy-mm")))/(SUMIFS(Jobs!$AJ$5:$AJ$604,Jobs!$E$5:$E$604,TEXT(DATE(PlanYear,5,1),"yyyy-mm"),Jobs!$P$5:$P$604,"Completed")+SUMIFS(Jobs!$AJ$5:$AJ$604,Jobs!$E$5:$E$604,TEXT(DATE(PlanYear,5,1),"yyyy-mm"),Jobs!$P$5:$P$604,"Invoiced")),"") -> 0 | I59: =COUNTIFS(Clients!$J$5:$J$204,">="&DATE(PlanYear,5,1),Clients!$J$5:$J$204,"<"&DATE(PlanYear,6,1)) -> 0
A60: =TEXT(DATE(PlanYear,6,1),"mmm") -> 0 | B60: =COUNTIFS(Jobs!$E$5:$E$604,TEXT(DATE(PlanYear,6,1),"yyyy-mm"),Jobs!$P$5:$P$604,"<>Cancelled") -> 0 | C60: =SUMIFS(Jobs!$AJ$5:$AJ$604,Jobs!$E$5:$E$604,TEXT(DATE(PlanYear,6,1),"yyyy-mm"),Jobs!$P$5:$P$604,"Completed")+SUMIFS(Jobs!$AJ$5:$AJ$604,Jobs!$E$5:$E$604,TEXT(DATE(PlanYear,6,1),"yyyy-mm"),Jobs!$P$5:$P$604,"Invoiced") -> 0 | D60: =SUMIFS(Invoices!$V$5:$V$404,Invoices!$C$5:$C$404,TEXT(DATE(PlanYear,6,1),"yyyy-mm")) -> 0 | E60: =SUMIFS(Payments!$G$5:$G$404,Payments!$C$5:$C$404,TEXT(DATE(PlanYear,6,1),"yyyy-mm")) -> 0 | F60: =SUMIFS(Expenses!$Q$5:$Q$404,Expenses!$C$5:$C$404,TEXT(DATE(PlanYear,6,1),"yyyy-mm")) -> 0 | G60: =SUMIFS(Jobs!$AJ$5:$AJ$604,Jobs!$E$5:$E$604,TEXT(DATE(PlanYear,6,1),"yyyy-mm"),Jobs!$P$5:$P$604,"Completed")+SUMIFS(Jobs!$AJ$5:$AJ$604,Jobs!$E$5:$E$604,TEXT(DATE(PlanYear,6,1),"yyyy-mm"),Jobs!$P$5:$P$604,"Invoiced")-SUMIFS(Expenses!$Q$5:$Q$404,Expenses!$C$5:$C$404,TEXT(DATE(PlanYear,6,1),"yyyy-mm")) -> 0 | H60: =IFERROR((SUMIFS(Jobs!$AJ$5:$AJ$604,Jobs!$E$5:$E$604,TEXT(DATE(PlanYear,6,1),"yyyy-mm"),Jobs!$P$5:$P$604,"Completed")+SUMIFS(Jobs!$AJ$5:$AJ$604,Jobs!$E$5:$E$604,TEXT(DATE(PlanYear,6,1),"yyyy-mm"),Jobs!$P$5:$P$604,"Invoiced")-SUMIFS(Expenses!$Q$5:$Q$404,Expenses!$C$5:$C$404,TEXT(DATE(PlanYear,6,1),"yyyy-mm")))/(SUMIFS(Jobs!$AJ$5:$AJ$604,Jobs!$E$5:$E$604,TEXT(DATE(PlanYear,6,1),"yyyy-mm"),Jobs!$P$5:$P$604,"Completed")+SUMIFS(Jobs!$AJ$5:$AJ$604,Jobs!$E$5:$E$604,TEXT(DATE(PlanYear,6,1),"yyyy-mm"),Jobs!$P$5:$P$604,"Invoiced")),"") -> 0 | I60: =COUNTIFS(Clients!$J$5:$J$204,">="&DATE(PlanYear,6,1),Clients!$J$5:$J$204,"<"&DATE(PlanYear,7,1)) -> 0
A61: =TEXT(DATE(PlanYear,7,1),"mmm") -> 0 | B61: =COUNTIFS(Jobs!$E$5:$E$604,TEXT(DATE(PlanYear,7,1),"yyyy-mm"),Jobs!$P$5:$P$604,"<>Cancelled") -> 0 | C61: =SUMIFS(Jobs!$AJ$5:$AJ$604,Jobs!$E$5:$E$604,TEXT(DATE(PlanYear,7,1),"yyyy-mm"),Jobs!$P$5:$P$604,"Completed")+SUMIFS(Jobs!$AJ$5:$AJ$604,Jobs!$E$5:$E$604,TEXT(DATE(PlanYear,7,1),"yyyy-mm"),Jobs!$P$5:$P$604,"Invoiced") -> 0 | D61: =SUMIFS(Invoices!$V$5:$V$404,Invoices!$C$5:$C$404,TEXT(DATE(PlanYear,7,1),"yyyy-mm")) -> 0 | E61: =SUMIFS(Payments!$G$5:$G$404,Payments!$C$5:$C$404,TEXT(DATE(PlanYear,7,1),"yyyy-mm")) -> 0 | F61: =SUMIFS(Expenses!$Q$5:$Q$404,Expenses!$C$5:$C$404,TEXT(DATE(PlanYear,7,1),"yyyy-mm")) -> 0 | G61: =SUMIFS(Jobs!$AJ$5:$AJ$604,Jobs!$E$5:$E$604,TEXT(DATE(PlanYear,7,1),"yyyy-mm"),Jobs!$P$5:$P$604,"Completed")+SUMIFS(Jobs!$AJ$5:$AJ$604,Jobs!$E$5:$E$604,TEXT(DATE(PlanYear,7,1),"yyyy-mm"),Jobs!$P$5:$P$604,"Invoiced")-SUMIFS(Expenses!$Q$5:$Q$404,Expenses!$C$5:$C$404,TEXT(DATE(PlanYear,7,1),"yyyy-mm")) -> 0 | H61: =IFERROR((SUMIFS(Jobs!$AJ$5:$AJ$604,Jobs!$E$5:$E$604,TEXT(DATE(PlanYear,7,1),"yyyy-mm"),Jobs!$P$5:$P$604,"Completed")+SUMIFS(Jobs!$AJ$5:$AJ$604,Jobs!$E$5:$E$604,TEXT(DATE(PlanYear,7,1),"yyyy-mm"),Jobs!$P$5:$P$604,"Invoiced")-SUMIFS(Expenses!$Q$5:$Q$404,Expenses!$C$5:$C$404,TEXT(DATE(PlanYear,7,1),"yyyy-mm")))/(SUMIFS(Jobs!$AJ$5:$AJ$604,Jobs!$E$5:$E$604,TEXT(DATE(PlanYear,7,1),"yyyy-mm"),Jobs!$P$5:$P$604,"Completed")+SUMIFS(Jobs!$AJ$5:$AJ$604,Jobs!$E$5:$E$604,TEXT(DATE(PlanYear,7,1),"yyyy-mm"),Jobs!$P$5:$P$604,"Invoiced")),"") -> 0 | I61: =COUNTIFS(Clients!$J$5:$J$204,">="&DATE(PlanYear,7,1),Clients!$J$5:$J$204,"<"&DATE(PlanYear,8,1)) -> 0
A62: =TEXT(DATE(PlanYear,8,1),"mmm") -> 0 | B62: =COUNTIFS(Jobs!$E$5:$E$604,TEXT(DATE(PlanYear,8,1),"yyyy-mm"),Jobs!$P$5:$P$604,"<>Cancelled") -> 0 | C62: =SUMIFS(Jobs!$AJ$5:$AJ$604,Jobs!$E$5:$E$604,TEXT(DATE(PlanYear,8,1),"yyyy-mm"),Jobs!$P$5:$P$604,"Completed")+SUMIFS(Jobs!$AJ$5:$AJ$604,Jobs!$E$5:$E$604,TEXT(DATE(PlanYear,8,1),"yyyy-mm"),Jobs!$P$5:$P$604,"Invoiced") -> 0 | D62: =SUMIFS(Invoices!$V$5:$V$404,Invoices!$C$5:$C$404,TEXT(DATE(PlanYear,8,1),"yyyy-mm")) -> 0 | E62: =SUMIFS(Payments!$G$5:$G$404,Payments!$C$5:$C$404,TEXT(DATE(PlanYear,8,1),"yyyy-mm")) -> 0 | F62: =SUMIFS(Expenses!$Q$5:$Q$404,Expenses!$C$5:$C$404,TEXT(DATE(PlanYear,8,1),"yyyy-mm")) -> 0 | G62: =SUMIFS(Jobs!$AJ$5:$AJ$604,Jobs!$E$5:$E$604,TEXT(DATE(PlanYear,8,1),"yyyy-mm"),Jobs!$P$5:$P$604,"Completed")+SUMIFS(Jobs!$AJ$5:$AJ$604,Jobs!$E$5:$E$604,TEXT(DATE(PlanYear,8,1),"yyyy-mm"),Jobs!$P$5:$P$604,"Invoiced")-SUMIFS(Expenses!$Q$5:$Q$404,Expenses!$C$5:$C$404,TEXT(DATE(PlanYear,8,1),"yyyy-mm")) -> 0 | H62: =IFERROR((SUMIFS(Jobs!$AJ$5:$AJ$604,Jobs!$E$5:$E$604,TEXT(DATE(PlanYear,8,1),"yyyy-mm"),Jobs!$P$5:$P$604,"Completed")+SUMIFS(Jobs!$AJ$5:$AJ$604,Jobs!$E$5:$E$604,TEXT(DATE(PlanYear,8,1),"yyyy-mm"),Jobs!$P$5:$P$604,"Invoiced")-SUMIFS(Expenses!$Q$5:$Q$404,Expenses!$C$5:$C$404,TEXT(DATE(PlanYear,8,1),"yyyy-mm")))/(SUMIFS(Jobs!$AJ$5:$AJ$604,Jobs!$E$5:$E$604,TEXT(DATE(PlanYear,8,1),"yyyy-mm"),Jobs!$P$5:$P$604,"Completed")+SUMIFS(Jobs!$AJ$5:$AJ$604,Jobs!$E$5:$E$604,TEXT(DATE(PlanYear,8,1),"yyyy-mm"),Jobs!$P$5:$P$604,"Invoiced")),"") -> 0 | I62: =COUNTIFS(Clients!$J$5:$J$204,">="&DATE(PlanYear,8,1),Clients!$J$5:$J$204,"<"&DATE(PlanYear,9,1)) -> 0
A63: =TEXT(DATE(PlanYear,9,1),"mmm") -> 0 | B63: =COUNTIFS(Jobs!$E$5:$E$604,TEXT(DATE(PlanYear,9,1),"yyyy-mm"),Jobs!$P$5:$P$604,"<>Cancelled") -> 0 | C63: =SUMIFS(Jobs!$AJ$5:$AJ$604,Jobs!$E$5:$E$604,TEXT(DATE(PlanYear,9,1),"yyyy-mm"),Jobs!$P$5:$P$604,"Completed")+SUMIFS(Jobs!$AJ$5:$AJ$604,Jobs!$E$5:$E$604,TEXT(DATE(PlanYear,9,1),"yyyy-mm"),Jobs!$P$5:$P$604,"Invoiced") -> 0 | D63: =SUMIFS(Invoices!$V$5:$V$404,Invoices!$C$5:$C$404,TEXT(DATE(PlanYear,9,1),"yyyy-mm")) -> 0 | E63: =SUMIFS(Payments!$G$5:$G$404,Payments!$C$5:$C$404,TEXT(DATE(PlanYear,9,1),"yyyy-mm")) -> 0 | F63: =SUMIFS(Expenses!$Q$5:$Q$404,Expenses!$C$5:$C$404,TEXT(DATE(PlanYear,9,1),"yyyy-mm")) -> 0 | G63: =SUMIFS(Jobs!$AJ$5:$AJ$604,Jobs!$E$5:$E$604,TEXT(DATE(PlanYear,9,1),"yyyy-mm"),Jobs!$P$5:$P$604,"Completed")+SUMIFS(Jobs!$AJ$5:$AJ$604,Jobs!$E$5:$E$604,TEXT(DATE(PlanYear,9,1),"yyyy-mm"),Jobs!$P$5:$P$604,"Invoiced")-SUMIFS(Expenses!$Q$5:$Q$404,Expenses!$C$5:$C$404,TEXT(DATE(PlanYear,9,1),"yyyy-mm")) -> 0 | H63: =IFERROR((SUMIFS(Jobs!$AJ$5:$AJ$604,Jobs!$E$5:$E$604,TEXT(DATE(PlanYear,9,1),"yyyy-mm"),Jobs!$P$5:$P$604,"Completed")+SUMIFS(Jobs!$AJ$5:$AJ$604,Jobs!$E$5:$E$604,TEXT(DATE(PlanYear,9,1),"yyyy-mm"),Jobs!$P$5:$P$604,"Invoiced")-SUMIFS(Expenses!$Q$5:$Q$404,Expenses!$C$5:$C$404,TEXT(DATE(PlanYear,9,1),"yyyy-mm")))/(SUMIFS(Jobs!$AJ$5:$AJ$604,Jobs!$E$5:$E$604,TEXT(DATE(PlanYear,9,1),"yyyy-mm"),Jobs!$P$5:$P$604,"Completed")+SUMIFS(Jobs!$AJ$5:$AJ$604,Jobs!$E$5:$E$604,TEXT(DATE(PlanYear,9,1),"yyyy-mm"),Jobs!$P$5:$P$604,"Invoiced")),"") -> 0 | I63: =COUNTIFS(Clients!$J$5:$J$204,">="&DATE(PlanYear,9,1),Clients!$J$5:$J$204,"<"&DATE(PlanYear,10,1)) -> 0
A64: =TEXT(DATE(PlanYear,10,1),"mmm") -> 0 | B64: =COUNTIFS(Jobs!$E$5:$E$604,TEXT(DATE(PlanYear,10,1),"yyyy-mm"),Jobs!$P$5:$P$604,"<>Cancelled") -> 0 | C64: =SUMIFS(Jobs!$AJ$5:$AJ$604,Jobs!$E$5:$E$604,TEXT(DATE(PlanYear,10,1),"yyyy-mm"),Jobs!$P$5:$P$604,"Completed")+SUMIFS(Jobs!$AJ$5:$AJ$604,Jobs!$E$5:$E$604,TEXT(DATE(PlanYear,10,1),"yyyy-mm"),Jobs!$P$5:$P$604,"Invoiced") -> 0 | D64: =SUMIFS(Invoices!$V$5:$V$404,Invoices!$C$5:$C$404,TEXT(DATE(PlanYear,10,1),"yyyy-mm")) -> 0 | E64: =SUMIFS(Payments!$G$5:$G$404,Payments!$C$5:$C$404,TEXT(DATE(PlanYear,10,1),"yyyy-mm")) -> 0 | F64: =SUMIFS(Expenses!$Q$5:$Q$404,Expenses!$C$5:$C$404,TEXT(DATE(PlanYear,10,1),"yyyy-mm")) -> 0 | G64: =SUMIFS(Jobs!$AJ$5:$AJ$604,Jobs!$E$5:$E$604,TEXT(DATE(PlanYear,10,1),"yyyy-mm"),Jobs!$P$5:$P$604,"Completed")+SUMIFS(Jobs!$AJ$5:$AJ$604,Jobs!$E$5:$E$604,TEXT(DATE(PlanYear,10,1),"yyyy-mm"),Jobs!$P$5:$P$604,"Invoiced")-SUMIFS(Expenses!$Q$5:$Q$404,Expenses!$C$5:$C$404,TEXT(DATE(PlanYear,10,1),"yyyy-mm")) -> 0 | H64: =IFERROR((SUMIFS(Jobs!$AJ$5:$AJ$604,Jobs!$E$5:$E$604,TEXT(DATE(PlanYear,10,1),"yyyy-mm"),Jobs!$P$5:$P$604,"Completed")+SUMIFS(Jobs!$AJ$5:$AJ$604,Jobs!$E$5:$E$604,TEXT(DATE(PlanYear,10,1),"yyyy-mm"),Jobs!$P$5:$P$604,"Invoiced")-SUMIFS(Expenses!$Q$5:$Q$404,Expenses!$C$5:$C$404,TEXT(DATE(PlanYear,10,1),"yyyy-mm")))/(SUMIFS(Jobs!$AJ$5:$AJ$604,Jobs!$E$5:$E$604,TEXT(DATE(PlanYear,10,1),"yyyy-mm"),Jobs!$P$5:$P$604,"Completed")+SUMIFS(Jobs!$AJ$5:$AJ$604,Jobs!$E$5:$E$604,TEXT(DATE(PlanYear,10,1),"yyyy-mm"),Jobs!$P$5:$P$604,"Invoiced")),"") -> 0 | I64: =COUNTIFS(Clients!$J$5:$J$204,">="&DATE(PlanYear,10,1),Clients!$J$5:$J$204,"<"&DATE(PlanYear,11,1)) -> 0
A65: =TEXT(DATE(PlanYear,11,1),"mmm") -> 0 | B65: =COUNTIFS(Jobs!$E$5:$E$604,TEXT(DATE(PlanYear,11,1),"yyyy-mm"),Jobs!$P$5:$P$604,"<>Cancelled") -> 0 | C65: =SUMIFS(Jobs!$AJ$5:$AJ$604,Jobs!$E$5:$E$604,TEXT(DATE(PlanYear,11,1),"yyyy-mm"),Jobs!$P$5:$P$604,"Completed")+SUMIFS(Jobs!$AJ$5:$AJ$604,Jobs!$E$5:$E$604,TEXT(DATE(PlanYear,11,1),"yyyy-mm"),Jobs!$P$5:$P$604,"Invoiced") -> 0 | D65: =SUMIFS(Invoices!$V$5:$V$404,Invoices!$C$5:$C$404,TEXT(DATE(PlanYear,11,1),"yyyy-mm")) -> 0 | E65: =SUMIFS(Payments!$G$5:$G$404,Payments!$C$5:$C$404,TEXT(DATE(PlanYear,11,1),"yyyy-mm")) -> 0 | F65: =SUMIFS(Expenses!$Q$5:$Q$404,Expenses!$C$5:$C$404,TEXT(DATE(PlanYear,11,1),"yyyy-mm")) -> 0 | G65: =SUMIFS(Jobs!$AJ$5:$AJ$604,Jobs!$E$5:$E$604,TEXT(DATE(PlanYear,11,1),"yyyy-mm"),Jobs!$P$5:$P$604,"Completed")+SUMIFS(Jobs!$AJ$5:$AJ$604,Jobs!$E$5:$E$604,TEXT(DATE(PlanYear,11,1),"yyyy-mm"),Jobs!$P$5:$P$604,"Invoiced")-SUMIFS(Expenses!$Q$5:$Q$404,Expenses!$C$5:$C$404,TEXT(DATE(PlanYear,11,1),"yyyy-mm")) -> 0 | H65: =IFERROR((SUMIFS(Jobs!$AJ$5:$AJ$604,Jobs!$E$5:$E$604,TEXT(DATE(PlanYear,11,1),"yyyy-mm"),Jobs!$P$5:$P$604,"Completed")+SUMIFS(Jobs!$AJ$5:$AJ$604,Jobs!$E$5:$E$604,TEXT(DATE(PlanYear,11,1),"yyyy-mm"),Jobs!$P$5:$P$604,"Invoiced")-SUMIFS(Expenses!$Q$5:$Q$404,Expenses!$C$5:$C$404,TEXT(DATE(PlanYear,11,1),"yyyy-mm")))/(SUMIFS(Jobs!$AJ$5:$AJ$604,Jobs!$E$5:$E$604,TEXT(DATE(PlanYear,11,1),"yyyy-mm"),Jobs!$P$5:$P$604,"Completed")+SUMIFS(Jobs!$AJ$5:$AJ$604,Jobs!$E$5:$E$604,TEXT(DATE(PlanYear,11,1),"yyyy-mm"),Jobs!$P$5:$P$604,"Invoiced")),"") -> 0 | I65: =COUNTIFS(Clients!$J$5:$J$204,">="&DATE(PlanYear,11,1),Clients!$J$5:$J$204,"<"&DATE(PlanYear,12,1)) -> 0
A66: =TEXT(DATE(PlanYear,12,1),"mmm") -> 0 | B66: =COUNTIFS(Jobs!$E$5:$E$604,TEXT(DATE(PlanYear,12,1),"yyyy-mm"),Jobs!$P$5:$P$604,"<>Cancelled") -> 0 | C66: =SUMIFS(Jobs!$AJ$5:$AJ$604,Jobs!$E$5:$E$604,TEXT(DATE(PlanYear,12,1),"yyyy-mm"),Jobs!$P$5:$P$604,"Completed")+SUMIFS(Jobs!$AJ$5:$AJ$604,Jobs!$E$5:$E$604,TEXT(DATE(PlanYear,12,1),"yyyy-mm"),Jobs!$P$5:$P$604,"Invoiced") -> 0 | D66: =SUMIFS(Invoices!$V$5:$V$404,Invoices!$C$5:$C$404,TEXT(DATE(PlanYear,12,1),"yyyy-mm")) -> 0 | E66: =SUMIFS(Payments!$G$5:$G$404,Payments!$C$5:$C$404,TEXT(DATE(PlanYear,12,1),"yyyy-mm")) -> 0 | F66: =SUMIFS(Expenses!$Q$5:$Q$404,Expenses!$C$5:$C$404,TEXT(DATE(PlanYear,12,1),"yyyy-mm")) -> 0 | G66: =SUMIFS(Jobs!$AJ$5:$AJ$604,Jobs!$E$5:$E$604,TEXT(DATE(PlanYear,12,1),"yyyy-mm"),Jobs!$P$5:$P$604,"Completed")+SUMIFS(Jobs!$AJ$5:$AJ$604,Jobs!$E$5:$E$604,TEXT(DATE(PlanYear,12,1),"yyyy-mm"),Jobs!$P$5:$P$604,"Invoiced")-SUMIFS(Expenses!$Q$5:$Q$404,Expenses!$C$5:$C$404,TEXT(DATE(PlanYear,12,1),"yyyy-mm")) -> 0 | H66: =IFERROR((SUMIFS(Jobs!$AJ$5:$AJ$604,Jobs!$E$5:$E$604,TEXT(DATE(PlanYear,12,1),"yyyy-mm"),Jobs!$P$5:$P$604,"Completed")+SUMIFS(Jobs!$AJ$5:$AJ$604,Jobs!$E$5:$E$604,TEXT(DATE(PlanYear,12,1),"yyyy-mm"),Jobs!$P$5:$P$604,"Invoiced")-SUMIFS(Expenses!$Q$5:$Q$404,Expenses!$C$5:$C$404,TEXT(DATE(PlanYear,12,1),"yyyy-mm")))/(SUMIFS(Jobs!$AJ$5:$AJ$604,Jobs!$E$5:$E$604,TEXT(DATE(PlanYear,12,1),"yyyy-mm"),Jobs!$P$5:$P$604,"Completed")+SUMIFS(Jobs!$AJ$5:$AJ$604,Jobs!$E$5:$E$604,TEXT(DATE(PlanYear,12,1),"yyyy-mm"),Jobs!$P$5:$P$604,"Invoiced")),"") -> 0 | I66: =COUNTIFS(Clients!$J$5:$J$204,">="&DATE(PlanYear,12,1),Clients!$J$5:$J$204,"<"&DATE(PlanYear,13,1)) -> 0
A68: Revenue counts jobs marked Completed or Invoiced. Collected is money actually received. The little charts on the right are, top to bottom: revenue, costs, profit.
A70: Sales pipeline
A71: Stage | B71: How many | C71: Value | D71: Notes
A72: New enquiries | B72: =COUNTIF(Leads!$K$5:$K$154,"New enquiry") -> 0 | C72: =SUMIFS(Leads!$L$5:$L$154,Leads!$K$5:$K$154,"New enquiry") -> 0 | D72: Call them today - speed wins more cleaning work than price
A73: Quotes out | B73: =COUNTIF(Quotes!$K$5:$K$204,"Sent")+COUNTIF(Quotes!$K$5:$K$204,"Followed up") -> 0 | C73: =SUMIFS(Quotes!$AB$5:$AB$204,Quotes!$K$5:$K$204,"Sent")+SUMIFS(Quotes!$AB$5:$AB$204,Quotes!$K$5:$K$204,"Followed up") -> 0 | D73: Money sitting in somebody else's inbox
A74: Accepted, not booked | B74: =COUNTIFS(Quotes!$K$5:$K$204,"Accepted",Quotes!$R$5:$R$204,"") -> 0 | C74: =SUMIFS(Quotes!$AB$5:$AB$204,Quotes!$K$5:$K$204,"Accepted",Quotes!$R$5:$R$204,"") -> 0 | D74: They said yes. Put it in the diary before they forget
A75: Won this year | B75: =COUNTIF(Quotes!$AJ$5:$AJ$204,"Yes") -> 0 | C75: =SUMIFS(Quotes!$AB$5:$AB$204,Quotes!$AJ$5:$AJ$204,"Yes") -> 0 | D75: Quotes accepted
A76: Lost this year | B76: =COUNTIF(Quotes!$AJ$5:$AJ$204,"No") -> 0 | C76: =SUMIFS(Quotes!$AB$5:$AB$204,Quotes!$AJ$5:$AJ$204,"No") -> 0 | D76: Worth reading the reasons on the Leads tab
A78: Every figure on this page is calculated. If a number looks wrong, the fix is on the tab it came from - usually a job left at the wrong status, or an invoice with no lines.

Sheet Quote Calculator
A1: Pricing & Quote Calculator | J1: Novality Store | v1.0.0
A2: Fill in the white cells. The price, the cost, the margin and the yearly value all work themselves out.
A3: > Start Here | C3: > Dashboard | E3: > Clients | G3: > Jobs | I3: > Calendar | K3: > Quotes
A5: 1. What are we cleaning?
B6: You can start from a property you already have on file, or just type the numbers in. Nothing here changes any of your saved data.
B7: Service | D7: Regular home clean | F7: From the Services tab. Its hours, price and uplift are used below.
B8: Client type | D8: Residential
B9: Floor area (sq ft) | D9: 1450 | E9: Leave at 0 if you do not know it - the room count will carry the estimate.
B10: Bedrooms | D10: 3
B11: Bathrooms | D11: 2 | E11: Bathrooms and kitchens are where the time really goes.
B12: Other rooms | D12: 4
B13: Condition | D13: Normal | F13: Be honest. This multiplies the hours - the factors are on the Lists tab.
B14: How often | D14: Weekly | F14: Regular work takes less time per visit, so it is priced lower.
B15: Pets at the property? | D15: Yes
B16: Distance one way (miles) | D16: 6
B17: Add the call-out fee? | D17: No | E17: Adds the $15 call-out fee from Settings.
B18: Cleaners on the job | D18: 2
B19: Hours (override the estimate) | D19: 0 | E19: Leave at 0 to let the calculator estimate. Type a number if you have walked the job.
B20: Hourly rate (override) | D20: 0 | E20: 0 uses the standard rate from Settings.
B21: Discount | D21: 0 | E21: A first-clean discount is the cheapest way to win recurring work - but watch the margin below.
A23: 2. Extras
B24: Add-ons priced straight from the Services tab. Ovens, interior windows, inside the fridge - the jobs that turn an average clean into a good one.
B25: Extra | C25: Qty | D25: Each | E25: Total | F25: Hours it adds
B26: Oven clean | C26: 1 | D26: =IF(B26="","",IFERROR(INDEX(Services!$P$5:$P$64,MATCH(B26,Services!$B$5:$B$64,0)),0)) -> 0 | E26: =IF(B26="","",IF(C26="",0,C26)*D26) -> 0 | F26: =IF(B26="","",IFERROR(INDEX(Services!$G$5:$G$64,MATCH(B26,Services!$B$5:$B$64,0)),0)*IF(C26="",0,C26)) -> 0
D27: =IF(B27="","",IFERROR(INDEX(Services!$P$5:$P$64,MATCH(B27,Services!$B$5:$B$64,0)),0)) -> 0 | E27: =IF(B27="","",IF(C27="",0,C27)*D27) -> 0 | F27: =IF(B27="","",IFERROR(INDEX(Services!$G$5:$G$64,MATCH(B27,Services!$B$5:$B$64,0)),0)*IF(C27="",0,C27)) -> 0
D28: =IF(B28="","",IFERROR(INDEX(Services!$P$5:$P$64,MATCH(B28,Services!$B$5:$B$64,0)),0)) -> 0 | E28: =IF(B28="","",IF(C28="",0,C28)*D28) -> 0 | F28: =IF(B28="","",IFERROR(INDEX(Services!$G$5:$G$64,MATCH(B28,Services!$B$5:$B$64,0)),0)*IF(C28="",0,C28)) -> 0
D29: =IF(B29="","",IFERROR(INDEX(Services!$P$5:$P$64,MATCH(B29,Services!$B$5:$B$64,0)),0)) -> 0 | E29: =IF(B29="","",IF(C29="",0,C29)*D29) -> 0 | F29: =IF(B29="","",IFERROR(INDEX(Services!$G$5:$G$64,MATCH(B29,Services!$B$5:$B$64,0)),0)*IF(C29="",0,C29)) -> 0
B30: Extras total | E30: =SUM($E$26:$E$29) -> 0 | F30: =SUM($F$26:$F$29) -> 0
A32: 3. How long it should take
B33: Hours from the room count | D33: =QcBeds*0.45+QcBaths*0.6+QcRooms*0.3 -> 0 | E33: Bedrooms at 27 minutes, bathrooms at 36, everything else at 18. Change the weights here if your own figures differ.
B34: Hours from the floor area | D34: =IF(QcArea=0,0,QcArea/IF(AreaUnit="sq m",60,650)) -> 0 | E34: One cleaner covers about 650 sq ft (60 sq m) an hour on a standard clean.
B35: Hours the service allows | D35: =IFERROR(INDEX(Services!$G$5:$G$64,MATCH(QcService,Services!$B$5:$B$64,0)),0) -> 0
B36: Base hours used | D36: =IF(QcHoursOverride>0,QcHoursOverride,IF(AND(IFERROR(INDEX(Services!$D$5:$D$64,MATCH(QcService,Services!$B$5:$B$64,0)),"")<>"Per hour",QcServiceHours>0),QcServiceHours,MAX(QcRoomHours,QcAreaHours))) -> 0 | E36: Your override if you gave one, the service time for a fixed-price job, otherwise the larger of the room and area estimates.
B37: Condition factor | D37: =IFERROR(INDEX(ConditionFactors,MATCH(QcCondition,ConditionNames,0)),1) -> 0
B38: Hours for this job | D38: =ROUND(QcBaseHours*QcConditionFactor+QcExtraHours,2) -> 0 | E38: Total cleaner-hours, including the extras.
B39: Time on site | D39: =ROUND(QcHours/MAX(1,QcCleaners),2) -> 0 | E39: How long the visit lasts with your crew on it. This is what you tell the client.
A41: 4. Four ways to price it
B42: The same job, priced four different ways. They rarely agree - that is the point. Pick the method that suits the client and sanity-check it against the others.
B43: Rate used | D43: =IF(QcRateOverride>0,QcRateOverride,HourlyRate) -> 0
B44: Service uplift | D44: =IFERROR(INDEX(Services!$H$5:$H$64,MATCH(QcService,Services!$B$5:$B$64,0)),0) -> 0 | E44: Deep cleans and end of tenancy work carry an uplift - it is set on the Services tab.
B45: A. By the hour | D45: =ROUND(QcHours*QcRate*(1+QcUplift),2) -> 0
B46: B. By floor area | D46: =ROUND(QcArea*RatePerArea*(1+QcUplift),2) -> 0 | E46: The usual way to price offices and end of tenancy work.
B47: C. By the room | D47: =ROUND((QcBeds*RatePerBedroom+QcBaths*RatePerBathroom+QcRooms*RatePerRoom)*(1+QcUplift),2) -> 0
B48: D. The catalogue price | D48: =IFERROR(INDEX(Services!$P$5:$P$64,MATCH(QcService,Services!$B$5:$B$64,0)),0) -> 0
B49: Price for your target margin | D49: =IF(TargetMargin>=1,0,ROUND(QcCost/(1-TargetMargin),2)) -> 0 | E49: What you would have to charge to hit the margin on your Settings tab.
B50: Price using | D50: A - by the hour | F50: Choose the method this quote uses.
B51: My own price | D51: 0 | E51: Only used when the method above is F.
A53: 5. What the job costs you
B54: Wages | D54: =ROUND(QcHours*CostPerHour,2) -> 0 | E54: Hours times the true cost of a cleaner hour - pay plus your on-costs.
B55: Supplies | D55: =ROUND(QcHours*SuppliesPerHour,2) -> 0
B56: Travel | D56: =ROUND(QcDistance*2*MileageRate,2) -> 0 | E56: There and back, at the mileage rate on the Settings tab.
B57: Total cost to deliver | D57: =QcLabour+QcSupplies+QcTravel -> 0
A59: 6. The quote
B60: Chosen price | D60: =IF(LEFT(QcMethod,1)="A",QcPriceHour,IF(LEFT(QcMethod,1)="B",QcPriceArea,IF(LEFT(QcMethod,1)="C",QcPriceRoom,IF(LEFT(QcMethod,1)="D",QcPriceService,IF(LEFT(QcMethod,1)="E",QcPriceTarget,QcManual))))) -> 0
B61: Frequency factor | D61: =IFERROR(INDEX(FreqFactors,MATCH(QcFrequency,FreqNames,0)),1) -> 0 | E61: Weekly work is priced below a one-off because it takes less time. The factors are on the Lists tab.
B62: After the frequency discount | D62: =ROUND(QcChosen*QcFreqFactor,2) -> 0
B63: Pet surcharge | D63: =IF(QcPets="Yes",PetSurcharge,0) -> 0
B64: Call-out fee | D64: =IF(QcCallout="Yes",CalloutFee,0) -> 0
B65: Extras | D65: =QcExtras -> 0
B66: Discount | D66: =ROUND((QcAfterFreq+QcPetFee+QcCalloutFee+QcExtras)*QcDiscount,2) -> 0
B67: Price before rounding | D67: =MAX(MinimumCharge,QcAfterFreq+QcPetFee+QcCalloutFee+QcExtras-QcDiscountValue) -> 0 | E67: The minimum charge of $90 applies to every job.
B68: Quote this price | D68: =IF(PriceRounding="Nearest 10",ROUND((QcRaw)/10,0)*10,IF(PriceRounding="Nearest 5",ROUND((QcRaw)/5,0)*5,IF(PriceRounding="Nearest 1",ROUND(QcRaw,0),ROUND(QcRaw,2)))) -> 0 | E68: Rounded the way you asked on the Settings tab. This is the number you give the client.
B69: Sales tax | D69: =ROUND(QcPrice*TaxRate,2) -> 0
B70: Total including tax | D70: =QcPrice+QcTax -> 0
B71: Deposit to ask for | D71: =ROUND(QcTotal*DepositPercent,2) -> 0
A73: 7. Is it worth doing?
B74: Profit on the visit | D74: =QcPrice-QcCost -> 0
B75: Margin | D75: =IF(QcPrice=0,"",QcProfit/QcPrice) -> 0
B76: You earn an hour | D76: =IF(QcHours=0,"",QcProfit/QcHours) -> 0 | E76: Profit per cleaner-hour. Compare it with your other work before you say yes.
B77: Price per sq unit | D77: =IF(QcArea=0,"",QcPrice/QcArea) -> 0
B78: Verdict | D78: =IF(QcPrice=0,"Fill in the job above",IF(QcProfit<0,"No - this job loses money",IF(QcMargin<MarginFloor,"Careful - the margin is under your floor",IF(QcMargin<TargetMargin,"Acceptable - but under your target margin","Good - this one is worth having")))) -> 0
A80: 8. The same client at every frequency
B81: What this job is worth over twelve months if they book weekly, fortnightly or monthly. It is the argument for offering the regular discount - and the reason a one-off deep clean is worth less than it looks.
B82: Frequency | C82: Factor | D82: Price a visit | E82: Visits a year | F82: Value a year | G82: Profit a year | H82: Margin
B83: =IFERROR(INDEX(FreqNames,1),"") -> 0 | C83: =IFERROR(INDEX(FreqFactors,1),"") -> 0 | D83: =IF(IFERROR(INDEX(FreqNames,1),"")="","",IF(PriceRounding="Nearest 10",ROUND((MAX(MinimumCharge,(QcChosen*IFERROR(INDEX(FreqFactors,1),"")+QcPetFee+QcCalloutFee+QcExtras)*(1-QcDiscount)))/10,0)*10,IF(PriceRounding="Nearest 5",ROUND((MAX(MinimumCharge,(QcChosen*IFERROR(INDEX(FreqFactors,1),"")+QcPetFee+QcCalloutFee+QcExtras)*(1-QcDiscount)))/5,0)*5,IF(PriceRounding="Nearest 1",ROUND(MAX(MinimumCharge,(QcChosen*IFERROR(INDEX(FreqFactors,1),"")+QcPetFee+QcCalloutFee+QcExtras)*(1-QcDiscount)),0),ROUND(MAX(MinimumCharge,(QcChosen*IFERROR(INDEX(FreqFactors,1),"")+QcPetFee+QcCalloutFee+QcExtras)*(1-QcDiscount)),2))))) -> 0 | E83: =IFERROR(INDEX(FreqPerYear,1),"") -> 0 | F83: =IF(D83="","",D83*E83) -> 0 | G83: =IF(D83="","",(D83-QcCost)*E83) -> 0 | H83: =IF(OR(D83="",D83=0),"",(D83-QcCost)/D83) -> 0
B84: =IFERROR(INDEX(FreqNames,2),"") -> 0 | C84: =IFERROR(INDEX(FreqFactors,2),"") -> 0 | D84: =IF(IFERROR(INDEX(FreqNames,2),"")="","",IF(PriceRounding="Nearest 10",ROUND((MAX(MinimumCharge,(QcChosen*IFERROR(INDEX(FreqFactors,2),"")+QcPetFee+QcCalloutFee+QcExtras)*(1-QcDiscount)))/10,0)*10,IF(PriceRounding="Nearest 5",ROUND((MAX(MinimumCharge,(QcChosen*IFERROR(INDEX(FreqFactors,2),"")+QcPetFee+QcCalloutFee+QcExtras)*(1-QcDiscount)))/5,0)*5,IF(PriceRounding="Nearest 1",ROUND(MAX(MinimumCharge,(QcChosen*IFERROR(INDEX(FreqFactors,2),"")+QcPetFee+QcCalloutFee+QcExtras)*(1-QcDiscount)),0),ROUND(MAX(MinimumCharge,(QcChosen*IFERROR(INDEX(FreqFactors,2),"")+QcPetFee+QcCalloutFee+QcExtras)*(1-QcDiscount)),2))))) -> 0 | E84: =IFERROR(INDEX(FreqPerYear,2),"") -> 0 | F84: =IF(D84="","",D84*E84) -> 0 | G84: =IF(D84="","",(D84-QcCost)*E84) -> 0 | H84: =IF(OR(D84="",D84=0),"",(D84-QcCost)/D84) -> 0
B85: =IFERROR(INDEX(FreqNames,3),"") -> 0 | C85: =IFERROR(INDEX(FreqFactors,3),"") -> 0 | D85: =IF(IFERROR(INDEX(FreqNames,3),"")="","",IF(PriceRounding="Nearest 10",ROUND((MAX(MinimumCharge,(QcChosen*IFERROR(INDEX(FreqFactors,3),"")+QcPetFee+QcCalloutFee+QcExtras)*(1-QcDiscount)))/10,0)*10,IF(PriceRounding="Nearest 5",ROUND((MAX(MinimumCharge,(QcChosen*IFERROR(INDEX(FreqFactors,3),"")+QcPetFee+QcCalloutFee+QcExtras)*(1-QcDiscount)))/5,0)*5,IF(PriceRounding="Nearest 1",ROUND(MAX(MinimumCharge,(QcChosen*IFERROR(INDEX(FreqFactors,3),"")+QcPetFee+QcCalloutFee+QcExtras)*(1-QcDiscount)),0),ROUND(MAX(MinimumCharge,(QcChosen*IFERROR(INDEX(FreqFactors,3),"")+QcPetFee+QcCalloutFee+QcExtras)*(1-QcDiscount)),2))))) -> 0 | E85: =IFERROR(INDEX(FreqPerYear,3),"") -> 0 | F85: =IF(D85="","",D85*E85) -> 0 | G85: =IF(D85="","",(D85-QcCost)*E85) -> 0 | H85: =IF(OR(D85="",D85=0),"",(D85-QcCost)/D85) -> 0
B86: =IFERROR(INDEX(FreqNames,4),"") -> 0 | C86: =IFERROR(INDEX(FreqFactors,4),"") -> 0 | D86: =IF(IFERROR(INDEX(FreqNames,4),"")="","",IF(PriceRounding="Nearest 10",ROUND((MAX(MinimumCharge,(QcChosen*IFERROR(INDEX(FreqFactors,4),"")+QcPetFee+QcCalloutFee+QcExtras)*(1-QcDiscount)))/10,0)*10,IF(PriceRounding="Nearest 5",ROUND((MAX(MinimumCharge,(QcChosen*IFERROR(INDEX(FreqFactors,4),"")+QcPetFee+QcCalloutFee+QcExtras)*(1-QcDiscount)))/5,0)*5,IF(PriceRounding="Nearest 1",ROUND(MAX(MinimumCharge,(QcChosen*IFERROR(INDEX(FreqFactors,4),"")+QcPetFee+QcCalloutFee+QcExtras)*(1-QcDiscount)),0),ROUND(MAX(MinimumCharge,(QcChosen*IFERROR(INDEX(FreqFactors,4),"")+QcPetFee+QcCalloutFee+QcExtras)*(1-QcDiscount)),2))))) -> 0 | E86: =IFERROR(INDEX(FreqPerYear,4),"") -> 0 | F86: =IF(D86="","",D86*E86) -> 0 | G86: =IF(D86="","",(D86-QcCost)*E86) -> 0 | H86: =IF(OR(D86="",D86=0),"",(D86-QcCost)/D86) -> 0
B87: =IFERROR(INDEX(FreqNames,5),"") -> 0 | C87: =IFERROR(INDEX(FreqFactors,5),"") -> 0 | D87: =IF(IFERROR(INDEX(FreqNames,5),"")="","",IF(PriceRounding="Nearest 10",ROUND((MAX(MinimumCharge,(QcChosen*IFERROR(INDEX(FreqFactors,5),"")+QcPetFee+QcCalloutFee+QcExtras)*(1-QcDiscount)))/10,0)*10,IF(PriceRounding="Nearest 5",ROUND((MAX(MinimumCharge,(QcChosen*IFERROR(INDEX(FreqFactors,5),"")+QcPetFee+QcCalloutFee+QcExtras)*(1-QcDiscount)))/5,0)*5,IF(PriceRounding="Nearest 1",ROUND(MAX(MinimumCharge,(QcChosen*IFERROR(INDEX(FreqFactors,5),"")+QcPetFee+QcCalloutFee+QcExtras)*(1-QcDiscount)),0),ROUND(MAX(MinimumCharge,(QcChosen*IFERROR(INDEX(FreqFactors,5),"")+QcPetFee+QcCalloutFee+QcExtras)*(1-QcDiscount)),2))))) -> 0 | E87: =IFERROR(INDEX(FreqPerYear,5),"") -> 0 | F87: =IF(D87="","",D87*E87) -> 0 | G87: =IF(D87="","",(D87-QcCost)*E87) -> 0 | H87: =IF(OR(D87="",D87=0),"",(D87-QcCost)/D87) -> 0
B88: =IFERROR(INDEX(FreqNames,6),"") -> 0 | C88: =IFERROR(INDEX(FreqFactors,6),"") -> 0 | D88: =IF(IFERROR(INDEX(FreqNames,6),"")="","",IF(PriceRounding="Nearest 10",ROUND((MAX(MinimumCharge,(QcChosen*IFERROR(INDEX(FreqFactors,6),"")+QcPetFee+QcCalloutFee+QcExtras)*(1-QcDiscount)))/10,0)*10,IF(PriceRounding="Nearest 5",ROUND((MAX(MinimumCharge,(QcChosen*IFERROR(INDEX(FreqFactors,6),"")+QcPetFee+QcCalloutFee+QcExtras)*(1-QcDiscount)))/5,0)*5,IF(PriceRounding="Nearest 1",ROUND(MAX(MinimumCharge,(QcChosen*IFERROR(INDEX(FreqFactors,6),"")+QcPetFee+QcCalloutFee+QcExtras)*(1-QcDiscount)),0),ROUND(MAX(MinimumCharge,(QcChosen*IFERROR(INDEX(FreqFactors,6),"")+QcPetFee+QcCalloutFee+QcExtras)*(1-QcDiscount)),2))))) -> 0 | E88: =IFERROR(INDEX(FreqPerYear,6),"") -> 0 | F88: =IF(D88="","",D88*E88) -> 0 | G88: =IF(D88="","",(D88-QcCost)*E88) -> 0 | H88: =IF(OR(D88="",D88=0),"",(D88-QcCost)/D88) -> 0
B89: =IFERROR(INDEX(FreqNames,7),"") -> 0 | C89: =IFERROR(INDEX(FreqFactors,7),"") -> 0 | D89: =IF(IFERROR(INDEX(FreqNames,7),"")="","",IF(PriceRounding="Nearest 10",ROUND((MAX(MinimumCharge,(QcChosen*IFERROR(INDEX(FreqFactors,7),"")+QcPetFee+QcCalloutFee+QcExtras)*(1-QcDiscount)))/10,0)*10,IF(PriceRounding="Nearest 5",ROUND((MAX(MinimumCharge,(QcChosen*IFERROR(INDEX(FreqFactors,7),"")+QcPetFee+QcCalloutFee+QcExtras)*(1-QcDiscount)))/5,0)*5,IF(PriceRounding="Nearest 1",ROUND(MAX(MinimumCharge,(QcChosen*IFERROR(INDEX(FreqFactors,7),"")+QcPetFee+QcCalloutFee+QcExtras)*(1-QcDiscount)),0),ROUND(MAX(MinimumCharge,(QcChosen*IFERROR(INDEX(FreqFactors,7),"")+QcPetFee+QcCalloutFee+QcExtras)*(1-QcDiscount)),2))))) -> 0 | E89: =IFERROR(INDEX(FreqPerYear,7),"") -> 0 | F89: =IF(D89="","",D89*E89) -> 0 | G89: =IF(D89="","",(D89-QcCost)*E89) -> 0 | H89: =IF(OR(D89="",D89=0),"",(D89-QcCost)/D89) -> 0
B91: Happy with the number? Raise it on the Quotes tab, add the lines on Quote Lines, and the follow-up reminders start by themselves. Nothing you do on this page is saved - it is a calculator, not a record.

Sheet Clients
A1: Client Database | AQ1: Novality Store | v1.0.0
A2: Every customer, what they have spent, what they earn you and when you last saw them.
A3: > Start Here | C3: > Dashboard | E3: > Clients | G3: > Jobs | I3: > Calendar | K3: > Quotes | M3: > Invoices | O3: > Staff | Q3: > Help | S3: Add the client here first, then their address on the Properties tab, then book the work on the Jobs tab. Everything downstream keys off the client ID in column A.
A4: ID | B4: Client | C4: Type | D4: Main contact | E4: Phone | F4: Email | G4: Billing address | H4: Status | I4: Came from | J4: Client since | K4: Usual frequency | L4: Preferred day | M4: Preferred time | N4: Preferred cleaner | O4: Agreed hourly rate | P4: Payment terms (days) | Q4: Pays by | R4: Contract | S4: Contract ends | T4: VIP? | U4: Happy to be contacted? | V4: Notes | W4: Properties | X4: Jobs booked | Y4: Jobs done | Z4: Cancelled | AA4: Last clean | AB4: Days since | AC4: Next booking | AD4: Invoiced to date | AE4: Paid to date | AF4: Owing now | AG4: Average job | AH4: Profit to date | AI4: Margin | AJ4: Value a year | AK4: Average rating | AL4: Complaints | AM4: Rank | AN4: Rank | AO4: Rank | AP4: Standing | AQ4: Risk score | AR4: Risk order | AS4: Action
A5: =IF(B5="","",ClientPrefix&TEXT(ROW()-4,"0000")) -> 0 | B5: Harper Residence | C5: Residential | D5: Megan Harper | E5: (503) 555 0188 | F5: megan.harper@example.com | G5: 42 Larch Street, Portland OR 97215 | H5: Regular | I5: Google search | J5: 45553 | K5: Weekly | L5: Tuesday | M5: Morning (9-12) | N5: Marta Kovacs | O5: 45 | P5: 7 | R5: Rolling monthly | T5: No | U5: Yes | V5: Two cats. Hates the smell of bleach - use the eco spray. | W5: =IF(A5="","",COUNTIFS(Properties!$C$5:$C$254,A5)) -> 0 | X5: =IF(A5="","",COUNTIFS(Jobs!$G$5:$G$604,A5)) -> 0 | Y5: =IF(A5="","",COUNTIFS(Jobs!$G$5:$G$604,A5,Jobs!$P$5:$P$604,"Completed")+COUNTIFS(Jobs!$G$5:$G$604,A5,Jobs!$P$5:$P$604,"Invoiced")) -> 0 | Z5: =IF(A5="","",COUNTIFS(Jobs!$G$5:$G$604,A5,Jobs!$P$5:$P$604,"Cancelled")+COUNTIFS(Jobs!$G$5:$G$604,A5,Jobs!$P$5:$P$604,"No access")) -> 0 | AA5: =IF(A5="","",IF(SUMPRODUCT(MAX((Jobs!$G$5:$G$604=A5)*((Jobs!$P$5:$P$604="Completed")+(Jobs!$P$5:$P$604="Invoiced"))*Jobs!$B$5:$B$604))=0,"",SUMPRODUCT(MAX((Jobs!$G$5:$G$604=A5)*((Jobs!$P$5:$P$604="Completed")+(Jobs!$P$5:$P$604="Invoiced"))*Jobs!$B$5:$B$604)))) -> 0 | AB5: =IF(AA5="","",TodayDate-AA5) -> 0 | AC5: =IF(A5="","",IF(SUMPRODUCT(MIN((Jobs!$G$5:$G$604=A5)*(Jobs!$B$5:$B$604>=TodayDate)*(Jobs!$P$5:$P$604<>"Cancelled")*Jobs!$B$5:$B$604+(1-(Jobs!$G$5:$G$604=A5)*(Jobs!$B$5:$B$604>=TodayDate)*(Jobs!$P$5:$P$604<>"Cancelled"))*2958465))=2958465,"",SUMPRODUCT(MIN((Jobs!$G$5:$G$604=A5)*(Jobs!$B$5:$B$604>=TodayDate)*(Jobs!$P$5:$P$604<>"Cancelled")*Jobs!$B$5:$B$604+(1-(Jobs!$G$5:$G$604=A5)*(Jobs!$B$5:$B$604>=TodayDate)*(Jobs!$P$5:$P$604<>"Cancelled"))*2958465)))) -> 0 | AD5: =IF(A5="","",SUMIFS(Invoices!$V$5:$V$404,Invoices!$D$5:$D$404,A5)) -> 0 | AE5: =IF(A5="","",SUMIFS(Invoices!$W$5:$W$404,Invoices!$D$5:$D$404,A5)) -> 0 | AF5: =IF(A5="","",AD5-AE5) -> 0 | AG5: =IF(OR(A5="",Y5=0),"",AD5/Y5) -> 0 | AH5: =IF(A5="","",SUMIFS('Job Costing'!$U$5:$U$604,'Job Costing'!$D$5:$D$604,A5)) -> 0 | AI5: =IF(OR(A5="",AD5=0),"",AH5/AD5) -> 0 | AJ5: =IF(OR(A5="",K5="",AG5=""),"",AG5*IFERROR(INDEX(FreqPerYear,MATCH(K5,FreqNames,0)),1)) -> 0 | AK5: =IF(A5="","",IFERROR(AVERAGEIFS(Jobs!$AA$5:$AA$604,Jobs!$G$5:$G$604,A5,Jobs!$AA$5:$AA$604,">0"),"")) -> 0 | AL5: =IF(A5="","",COUNTIFS(Complaints!$D$5:$D$84,A5)) -> 0 | AM5: =IF(B5="","",COUNTIFS($AD$5:$AD$204,">"&AD5)+COUNTIFS($AD$5:AD5,AD5)) -> 0 | AN5: =IF(B5="","",COUNTIFS($AH$5:$AH$204,">"&AH5)+COUNTIFS($AH$5:AH5,AH5)) -> 0 | AO5: =IF(B5="","",COUNTIFS($AJ$5:$AJ$204,">"&AJ5)+COUNTIFS($AJ$5:AJ5,AJ5)) -> 0 | AP5: =IF(B5="","",IF(H5="Lost","Lost",IF(H5="Inactive","Dormant",IF(AA5="","Dormant",IF(AB5>InactiveClientDays*2,"Dormant",IF(AB5>InactiveClientDays,"At risk",IF(AC5="","Slipping",IF(Y5>=10,"Loyal","Steady")))))))) -> 0 | AQ5: =IF(OR(B5="",AP5="Lost",AP5="Dormant"),"",IF(OR(AP5="At risk",AP5="Slipping"),IF(AB5="",999,AB5),"")) -> 0 | AR5: =IF(AQ5="","",COUNTIFS($AQ$5:$AQ$204,">"&AQ5)+COUNTIFS($AQ$5:AQ5,AQ5)) -> 0 | AS5: =IF(B5="","",IF(AF5>0.5,"Chase - "&TEXT(AF5,"0")&" owing",IF(AND(H5<>"Lost",H5<>"Inactive",H5<>"Paused",AC5="",K5<>"One-off"),"Book - nothing in the diary",IF(AND(S5<>"",S5-TodayDate<=RenewalWarningDays,S5>=TodayDate),"Due - contract renews soon",IF(AP5="At risk","Call - going quiet",IF(AL5>=2,"Check - complaints logged",IF(AND(AI5<>"",AI5<MarginFloor,Y5>0),"Check - thin margin","OK"))))))) -> 0
A6: =IF(B6="","",ClientPrefix&TEXT(ROW()-4,"0000")) -> 0 | B6: Okafor Family | C6: Residential | D6: Tobi Okafor | E6: (503) 555 0231 | F6: tobi.okafor@example.com | G6: 9 Elmwood Court, Portland OR 97212 | H6: Regular | I6: Referral - client | J6: 45773 | K6: Fortnightly | L6: Thursday | M6: Afternoon (2-5) | N6: Jade Ellis | O6: 45 | P6: 7 | R6: Rolling monthly | T6: No | U6: Yes | V6: Twins under three - toys everywhere, allow extra tidy time. | W6: =IF(A6="","",COUNTIFS(Properties!$C$5:$C$254,A6)) -> 0 | X6: =IF(A6="","",COUNTIFS(Jobs!$G$5:$G$604,A6)) -> 0 | Y6: =IF(A6="","",COUNTIFS(Jobs!$G$5:$G$604,A6,Jobs!$P$5:$P$604,"Completed")+COUNTIFS(Jobs!$G$5:$G$604,A6,Jobs!$P$5:$P$604,"Invoiced")) -> 0 | Z6: =IF(A6="","",COUNTIFS(Jobs!$G$5:$G$604,A6,Jobs!$P$5:$P$604,"Cancelled")+COUNTIFS(Jobs!$G$5:$G$604,A6,Jobs!$P$5:$P$604,"No access")) -> 0 | AA6: =IF(A6="","",IF(SUMPRODUCT(MAX((Jobs!$G$5:$G$604=A6)*((Jobs!$P$5:$P$604="Completed")+(Jobs!$P$5:$P$604="Invoiced"))*Jobs!$B$5:$B$604))=0,"",SUMPRODUCT(MAX((Jobs!$G$5:$G$604=A6)*((Jobs!$P$5:$P$604="Completed")+(Jobs!$P$5:$P$604="Invoiced"))*Jobs!$B$5:$B$604)))) -> 0 | AB6: =IF(AA6="","",TodayDate-AA6) -> 0 | AC6: =IF(A6="","",IF(SUMPRODUCT(MIN((Jobs!$G$5:$G$604=A6)*(Jobs!$B$5:$B$604>=TodayDate)*(Jobs!$P$5:$P$604<>"Cancelled")*Jobs!$B$5:$B$604+(1-(Jobs!$G$5:$G$604=A6)*(Jobs!$B$5:$B$604>=TodayDate)*(Jobs!$P$5:$P$604<>"Cancelled"))*2958465))=2958465,"",SUMPRODUCT(MIN((Jobs!$G$5:$G$604=A6)*(Jobs!$B$5:$B$604>=TodayDate)*(Jobs!$P$5:$P$604<>"Cancelled")*Jobs!$B$5:$B$604+(1-(Jobs!$G$5:$G$604=A6)*(Jobs!$B$5:$B$604>=TodayDate)*(Jobs!$P$5:$P$604<>"Cancelled"))*2958465)))) -> 0 | AD6: =IF(A6="","",SUMIFS(Invoices!$V$5:$V$404,Invoices!$D$5:$D$404,A6)) -> 0 | AE6: =IF(A6="","",SUMIFS(Invoices!$W$5:$W$404,Invoices!$D$5:$D$404,A6)) -> 0 | AF6: =IF(A6="","",AD6-AE6) -> 0 | AG6: =IF(OR(A6="",Y6=0),"",AD6/Y6) -> 0 | AH6: =IF(A6="","",SUMIFS('Job Costing'!$U$5:$U$604,'Job Costing'!$D$5:$D$604,A6)) -> 0 | AI6: =IF(OR(A6="",AD6=0),"",AH6/AD6) -> 0 | AJ6: =IF(OR(A6="",K6="",AG6=""),"",AG6*IFERROR(INDEX(FreqPerYear,MATCH(K6,FreqNames,0)),1)) -> 0 | AK6: =IF(A6="","",IFERROR(AVERAGEIFS(Jobs!$AA$5:$AA$604,Jobs!$G$5:$G$604,A6,Jobs!$AA$5:$AA$604,">0"),"")) -> 0 | AL6: =IF(A6="","",COUNTIFS(Complaints!$D$5:$D$84,A6)) -> 0 | AM6: =IF(B6="","",COUNTIFS($AD$5:$AD$204,">"&AD6)+COUNTIFS($AD$5:AD6,AD6)) -> 0 | AN6: =IF(B6="","",COUNTIFS($AH$5:$AH$204,">"&AH6)+COUNTIFS($AH$5:AH6,AH6)) -> 0 | AO6: =IF(B6="","",COUNTIFS($AJ$5:$AJ$204,">"&AJ6)+COUNTIFS($AJ$5:AJ6,AJ6)) -> 0 | AP6: =IF(B6="","",IF(H6="Lost","Lost",IF(H6="Inactive","Dormant",IF(AA6="","Dormant",IF(AB6>InactiveClientDays*2,"Dormant",IF(AB6>InactiveClientDays,"At risk",IF(AC6="","Slipping",IF(Y6>=10,"Loyal","Steady")))))))) -> 0 | AQ6: =IF(OR(B6="",AP6="Lost",AP6="Dormant"),"",IF(OR(AP6="At risk",AP6="Slipping"),IF(AB6="",999,AB6),"")) -> 0 | AR6: =IF(AQ6="","",COUNTIFS($AQ$5:$AQ$204,">"&AQ6)+COUNTIFS($AQ$5:AQ6,AQ6)) -> 0 | AS6: =IF(B6="","",IF(AF6>0.5,"Chase - "&TEXT(AF6,"0")&" owing",IF(AND(H6<>"Lost",H6<>"Inactive",H6<>"Paused",AC6="",K6<>"One-off"),"Book - nothing in the diary",IF(AND(S6<>"",S6-TodayDate<=RenewalWarningDays,S6>=TodayDate),"Due - contract renews soon",IF(AP6="At risk","Call - going quiet",IF(AL6>=2,"Check - complaints logged",IF(AND(AI6<>"",AI6<MarginFloor,Y6>0),"Check - thin margin","OK"))))))) -> 0
A7: =IF(B7="","",ClientPrefix&TEXT(ROW()-4,"0000")) -> 0 | B7: Riverbend Dental | C7: Medical & dental | D7: Dr. Alan Reyes | E7: (503) 555 0410 | F7: practice@riverbenddental.example | G7: 118 Riverbend Plaza, Suite 3, Portland OR 97209 | H7: Active | I7: Directory listing | J7: 45883 | K7: Weekly | L7: Friday | M7: Late (5-8) | N7: Tomas Ruiz | O7: 52 | P7: 14 | R7: 12 months | T7: Yes | U7: Yes | V7: Clinical waste stays with the practice. Sign in at reception. | W7: =IF(A7="","",COUNTIFS(Properties!$C$5:$C$254,A7)) -> 0 | X7: =IF(A7="","",COUNTIFS(Jobs!$G$5:$G$604,A7)) -> 0 | Y7: =IF(A7="","",COUNTIFS(Jobs!$G$5:$G$604,A7,Jobs!$P$5:$P$604,"Completed")+COUNTIFS(Jobs!$G$5:$G$604,A7,Jobs!$P$5:$P$604,"Invoiced")) -> 0 | Z7: =IF(A7="","",COUNTIFS(Jobs!$G$5:$G$604,A7,Jobs!$P$5:$P$604,"Cancelled")+COUNTIFS(Jobs!$G$5:$G$604,A7,Jobs!$P$5:$P$604,"No access")) -> 0 | AA7: =IF(A7="","",IF(SUMPRODUCT(MAX((Jobs!$G$5:$G$604=A7)*((Jobs!$P$5:$P$604="Completed")+(Jobs!$P$5:$P$604="Invoiced"))*Jobs!$B$5:$B$604))=0,"",SUMPRODUCT(MAX((Jobs!$G$5:$G$604=A7)*((Jobs!$P$5:$P$604="Completed")+(Jobs!$P$5:$P$604="Invoiced"))*Jobs!$B$5:$B$604)))) -> 0 | AB7: =IF(AA7="","",TodayDate-AA7) -> 0 | AC7: =IF(A7="","",IF(SUMPRODUCT(MIN((Jobs!$G$5:$G$604=A7)*(Jobs!$B$5:$B$604>=TodayDate)*(Jobs!$P$5:$P$604<>"Cancelled")*Jobs!$B$5:$B$604+(1-(Jobs!$G$5:$G$604=A7)*(Jobs!$B$5:$B$604>=TodayDate)*(Jobs!$P$5:$P$604<>"Cancelled"))*2958465))=2958465,"",SUMPRODUCT(MIN((Jobs!$G$5:$G$604=A7)*(Jobs!$B$5:$B$604>=TodayDate)*(Jobs!$P$5:$P$604<>"Cancelled")*Jobs!$B$5:$B$604+(1-(Jobs!$G$5:$G$604=A7)*(Jobs!$B$5:$B$604>=TodayDate)*(Jobs!$P$5:$P$604<>"Cancelled"))*2958465)))) -> 0 | AD7: =IF(A7="","",SUMIFS(Invoices!$V$5:$V$404,Invoices!$D$5:$D$404,A7)) -> 0 | AE7: =IF(A7="","",SUMIFS(Invoices!$W$5:$W$404,Invoices!$D$5:$D$404,A7)) -> 0 | AF7: =IF(A7="","",AD7-AE7) -> 0 | AG7: =IF(OR(A7="",Y7=0),"",AD7/Y7) -> 0 | AH7: =IF(A7="","",SUMIFS('Job Costing'!$U$5:$U$604,'Job Costing'!$D$5:$D$604,A7)) -> 0 | AI7: =IF(OR(A7="",AD7=0),"",AH7/AD7) -> 0 | AJ7: =IF(OR(A7="",K7="",AG7=""),"",AG7*IFERROR(INDEX(FreqPerYear,MATCH(K7,FreqNames,0)),1)) -> 0 | AK7: =IF(A7="","",IFERROR(AVERAGEIFS(Jobs!$AA$5:$AA$604,Jobs!$G$5:$G$604,A7,Jobs!$AA$5:$AA$604,">0"),"")) -> 0 | AL7: =IF(A7="","",COUNTIFS(Complaints!$D$5:$D$84,A7)) -> 0 | AM7: =IF(B7="","",COUNTIFS($AD$5:$AD$204,">"&AD7)+COUNTIFS($AD$5:AD7,AD7)) -> 0 | AN7: =IF(B7="","",COUNTIFS($AH$5:$AH$204,">"&AH7)+COUNTIFS($AH$5:AH7,AH7)) -> 0 | AO7: =IF(B7="","",COUNTIFS($AJ$5:$AJ$204,">"&AJ7)+COUNTIFS($AJ$5:AJ7,AJ7)) -> 0 | AP7: =IF(B7="","",IF(H7="Lost","Lost",IF(H7="Inactive","Dormant",IF(AA7="","Dormant",IF(AB7>InactiveClientDays*2,"Dormant",IF(AB7>InactiveClientDays,"At risk",IF(AC7="","Slipping",IF(Y7>=10,"Loyal","Steady")))))))) -> 0 | AQ7: =IF(OR(B7="",AP7="Lost",AP7="Dormant"),"",IF(OR(AP7="At risk",AP7="Slipping"),IF(AB7="",999,AB7),"")) -> 0 | AR7: =IF(AQ7="","",COUNTIFS($AQ$5:$AQ$204,">"&AQ7)+COUNTIFS($AQ$5:AQ7,AQ7)) -> 0 | AS7: =IF(B7="","",IF(AF7>0.5,"Chase - "&TEXT(AF7,"0")&" owing",IF(AND(H7<>"Lost",H7<>"Inactive",H7<>"Paused",AC7="",K7<>"One-off"),"Book - nothing in the diary",IF(AND(S7<>"",S7-TodayDate<=RenewalWarningDays,S7>=TodayDate),"Due - contract renews soon",IF(AP7="At risk","Call - going quiet",IF(AL7>=2,"Check - complaints logged",IF(AND(AI7<>"",AI7<MarginFloor,Y7>0),"Check - thin margin","OK"))))))) -> 0
A8: =IF(B8="","",ClientPrefix&TEXT(ROW()-4,"0000")) -> 0 | B8: Cedar & Co Accountants | C8: Commercial office | D8: Priya Shah | E8: (503) 555 0366 | F8: priya@cedarandco.example | G8: 77 Cedar Avenue, Floor 2, Portland OR 97204 | H8: Regular | I8: Referral - client | J8: 45693 | K8: Twice a week | L8: Monday | M8: Late (5-8) | N8: Tomas Ruiz | O8: 50 | P8: 14 | R8: 12 months | T8: Yes | U8: Yes | V8: Out of hours only. Alarm code is on the Properties tab. | W8: =IF(A8="","",COUNTIFS(Properties!$C$5:$C$254,A8)) -> 0 | X8: =IF(A8="","",COUNTIFS(Jobs!$G$5:$G$604,A8)) -> 0 | Y8: =IF(A8="","",COUNTIFS(Jobs!$G$5:$G$604,A8,Jobs!$P$5:$P$604,"Completed")+COUNTIFS(Jobs!$G$5:$G$604,A8,Jobs!$P$5:$P$604,"Invoiced")) -> 0 | Z8: =IF(A8="","",COUNTIFS(Jobs!$G$5:$G$604,A8,Jobs!$P$5:$P$604,"Cancelled")+COUNTIFS(Jobs!$G$5:$G$604,A8,Jobs!$P$5:$P$604,"No access")) -> 0 | AA8: =IF(A8="","",IF(SUMPRODUCT(MAX((Jobs!$G$5:$G$604=A8)*((Jobs!$P$5:$P$604="Completed")+(Jobs!$P$5:$P$604="Invoiced"))*Jobs!$B$5:$B$604))=0,"",SUMPRODUCT(MAX((Jobs!$G$5:$G$604=A8)*((Jobs!$P$5:$P$604="Completed")+(Jobs!$P$5:$P$604="Invoiced"))*Jobs!$B$5:$B$604)))) -> 0 | AB8: =IF(AA8="","",TodayDate-AA8) -> 0 | AC8: =IF(A8="","",IF(SUMPRODUCT(MIN((Jobs!$G$5:$G$604=A8)*(Jobs!$B$5:$B$604>=TodayDate)*(Jobs!$P$5:$P$604<>"Cancelled")*Jobs!$B$5:$B$604+(1-(Jobs!$G$5:$G$604=A8)*(Jobs!$B$5:$B$604>=TodayDate)*(Jobs!$P$5:$P$604<>"Cancelled"))*2958465))=2958465,"",SUMPRODUCT(MIN((Jobs!$G$5:$G$604=A8)*(Jobs!$B$5:$B$604>=TodayDate)*(Jobs!$P$5:$P$604<>"Cancelled")*Jobs!$B$5:$B$604+(1-(Jobs!$G$5:$G$604=A8)*(Jobs!$B$5:$B$604>=TodayDate)*(Jobs!$P$5:$P$604<>"Cancelled"))*2958465)))) -> 0 | AD8: =IF(A8="","",SUMIFS(Invoices!$V$5:$V$404,Invoices!$D$5:$D$404,A8)) -> 0 | AE8: =IF(A8="","",SUMIFS(Invoices!$W$5:$W$404,Invoices!$D$5:$D$404,A8)) -> 0 | AF8: =IF(A8="","",AD8-AE8) -> 0 | AG8: =IF(OR(A8="",Y8=0),"",AD8/Y8) -> 0 | AH8: =IF(A8="","",SUMIFS('Job Costing'!$U$5:$U$604,'Job Costing'!$D$5:$D$604,A8)) -> 0 | AI8: =IF(OR(A8="",AD8=0),"",AH8/AD8) -> 0 | AJ8: =IF(OR(A8="",K8="",AG8=""),"",AG8*IFERROR(INDEX(FreqPerYear,MATCH(K8,FreqNames,0)),1)) -> 0 | AK8: =IF(A8="","",IFERROR(AVERAGEIFS(Jobs!$AA$5:$AA$604,Jobs!$G$5:$G$604,A8,Jobs!$AA$5:$AA$604,">0"),"")) -> 0 | AL8: =IF(A8="","",COUNTIFS(Complaints!$D$5:$D$84,A8)) -> 0 | AM8: =IF(B8="","",COUNTIFS($AD$5:$AD$204,">"&AD8)+COUNTIFS($AD$5:AD8,AD8)) -> 0 | AN8: =IF(B8="","",COUNTIFS($AH$5:$AH$204,">"&AH8)+COUNTIFS($AH$5:AH8,AH8)) -> 0 | AO8: =IF(B8="","",COUNTIFS($AJ$5:$AJ$204,">"&AJ8)+COUNTIFS($AJ$5:AJ8,AJ8)) -> 0 | AP8: =IF(B8="","",IF(H8="Lost","Lost",IF(H8="Inactive","Dormant",IF(AA8="","Dormant",IF(AB8>InactiveClientDays*2,"Dormant",IF(AB8>InactiveClientDays,"At risk",IF(AC8="","Slipping",IF(Y8>=10,"Loyal","Steady")))))))) -> 0 | AQ8: =IF(OR(B8="",AP8="Lost",AP8="Dormant"),"",IF(OR(AP8="At risk",AP8="Slipping"),IF(AB8="",999,AB8),"")) -> 0 | AR8: =IF(AQ8="","",COUNTIFS($AQ$5:$AQ$204,">"&AQ8)+COUNTIFS($AQ$5:AQ8,AQ8)) -> 0 | AS8: =IF(B8="","",IF(AF8>0.5,"Chase - "&TEXT(AF8,"0")&" owing",IF(AND(H8<>"Lost",H8<>"Inactive",H8<>"Paused",AC8="",K8<>"One-off"),"Book - nothing in the diary",IF(AND(S8<>"",S8-TodayDate<=RenewalWarningDays,S8>=TodayDate),"Due - contract renews soon",IF(AP8="At risk","Call - going quiet",IF(AL8>=2,"Check - complaints logged",IF(AND(AI8<>"",AI8<MarginFloor,Y8>0),"Check - thin margin","OK"))))))) -> 0
A9: =IF(B9="","",ClientPrefix&TEXT(ROW()-4,"0000")) -> 0 | B9: Lakeview Lettings | C9: Letting agent | D9: Sam Whitlock | E9: (503) 555 0177 | F9: sam@lakeviewlettings.example | G9: 3 Lakeview Road, Portland OR 97202 | H9: Active | I9: Letting agent | J9: 46283 | K9: One-off | L9: Flexible | M9: Flexible | N9: Priya Raman | O9: 48 | P9: 21 | R9: No contract | T9: No | U9: Yes | V9: End of tenancy work. Always wants photos and a receipt. | W9: =IF(A9="","",COUNTIFS(Properties!$C$5:$C$254,A9)) -> 0 | X9: =IF(A9="","",COUNTIFS(Jobs!$G$5:$G$604,A9)) -> 0 | Y9: =IF(A9="","",COUNTIFS(Jobs!$G$5:$G$604,A9,Jobs!$P$5:$P$604,"Completed")+COUNTIFS(Jobs!$G$5:$G$604,A9,Jobs!$P$5:$P$604,"Invoiced")) -> 0 | Z9: =IF(A9="","",COUNTIFS(Jobs!$G$5:$G$604,A9,Jobs!$P$5:$P$604,"Cancelled")+COUNTIFS(Jobs!$G$5:$G$604,A9,Jobs!$P$5:$P$604,"No access")) -> 0 | AA9: =IF(A9="","",IF(SUMPRODUCT(MAX((Jobs!$G$5:$G$604=A9)*((Jobs!$P$5:$P$604="Completed")+(Jobs!$P$5:$P$604="Invoiced"))*Jobs!$B$5:$B$604))=0,"",SUMPRODUCT(MAX((Jobs!$G$5:$G$604=A9)*((Jobs!$P$5:$P$604="Completed")+(Jobs!$P$5:$P$604="Invoiced"))*Jobs!$B$5:$B$604)))) -> 0 | AB9: =IF(AA9="","",TodayDate-AA9) -> 0 | AC9: =IF(A9="","",IF(SUMPRODUCT(MIN((Jobs!$G$5:$G$604=A9)*(Jobs!$B$5:$B$604>=TodayDate)*(Jobs!$P$5:$P$604<>"Cancelled")*Jobs!$B$5:$B$604+(1-(Jobs!$G$5:$G$604=A9)*(Jobs!$B$5:$B$604>=TodayDate)*(Jobs!$P$5:$P$604<>"Cancelled"))*2958465))=2958465,"",SUMPRODUCT(MIN((Jobs!$G$5:$G$604=A9)*(Jobs!$B$5:$B$604>=TodayDate)*(Jobs!$P$5:$P$604<>"Cancelled")*Jobs!$B$5:$B$604+(1-(Jobs!$G$5:$G$604=A9)*(Jobs!$B$5:$B$604>=TodayDate)*(Jobs!$P$5:$P$604<>"Cancelled"))*2958465)))) -> 0 | AD9: =IF(A9="","",SUMIFS(Invoices!$V$5:$V$404,Invoices!$D$5:$D$404,A9)) -> 0 | AE9: =IF(A9="","",SUMIFS(Invoices!$W$5:$W$404,Invoices!$D$5:$D$404,A9)) -> 0 | AF9: =IF(A9="","",AD9-AE9) -> 0 | AG9: =IF(OR(A9="",Y9=0),"",AD9/Y9) -> 0 | AH9: =IF(A9="","",SUMIFS('Job Costing'!$U$5:$U$604,'Job Costing'!$D$5:$D$604,A9)) -> 0 | AI9: =IF(OR(A9="",AD9=0),"",AH9/AD9) -> 0 | AJ9: =IF(OR(A9="",K9="",AG9=""),"",AG9*IFERROR(INDEX(FreqPerYear,MATCH(K9,FreqNames,0)),1)) -> 0 | AK9: =IF(A9="","",IFERROR(AVERAGEIFS(Jobs!$AA$5:$AA$604,Jobs!$G$5:$G$604,A9,Jobs!$AA$5:$AA$604,">0"),"")) -> 0 | AL9: =IF(A9="","",COUNTIFS(Complaints!$D$5:$D$84,A9)) -> 0 | AM9: =IF(B9="","",COUNTIFS($AD$5:$AD$204,">"&AD9)+COUNTIFS($AD$5:AD9,AD9)) -> 0 | AN9: =IF(B9="","",COUNTIFS($AH$5:$AH$204,">"&AH9)+COUNTIFS($AH$5:AH9,AH9)) -> 0 | AO9: =IF(B9="","",COUNTIFS($AJ$5:$AJ$204,">"&AJ9)+COUNTIFS($AJ$5:AJ9,AJ9)) -> 0 | AP9: =IF(B9="","",IF(H9="Lost","Lost",IF(H9="Inactive","Dormant",IF(AA9="","Dormant",IF(AB9>InactiveClientDays*2,"Dormant",IF(AB9>InactiveClientDays,"At risk",IF(AC9="","Slipping",IF(Y9>=10,"Loyal","Steady")))))))) -> 0 | AQ9: =IF(OR(B9="",AP9="Lost",AP9="Dormant"),"",IF(OR(AP9="At risk",AP9="Slipping"),IF(AB9="",999,AB9),"")) -> 0 | AR9: =IF(AQ9="","",COUNTIFS($AQ$5:$AQ$204,">"&AQ9)+COUNTIFS($AQ$5:AQ9,AQ9)) -> 0 | AS9: =IF(B9="","",IF(AF9>0.5,"Chase - "&TEXT(AF9,"0")&" owing",IF(AND(H9<>"Lost",H9<>"Inactive",H9<>"Paused",AC9="",K9<>"One-off"),"Book - nothing in the diary",IF(AND(S9<>"",S9-TodayDate<=RenewalWarningDays,S9>=TodayDate),"Due - contract renews soon",IF(AP9="At risk","Call - going quiet",IF(AL9>=2,"Check - complaints logged",IF(AND(AI9<>"",AI9<MarginFloor,Y9>0),"Check - thin margin","OK"))))))) -> 0
A10: =IF(B10="","",ClientPrefix&TEXT(ROW()-4,"0000")) -> 0 | B10: The Maple Cafe | C10: Restaurant & cafe | D10: Gio Bellini | E10: (503) 555 0145 | F10: gio@maplecafe.example | G10: 210 Maple Street, Portland OR 97214 | H10: Active | I10: Word of mouth | J10: 46013 | K10: Weekly | L10: Sunday | M10: Early (7-9) | N10: Amara Diallo | O10: 55 | P10: 7 | R10: 6 months | T10: No | U10: Yes | V10: Before opening. Kitchen deep clean quarterly, billed separately. | W10: =IF(A10="","",COUNTIFS(Properties!$C$5:$C$254,A10)) -> 0 | X10: =IF(A10="","",COUNTIFS(Jobs!$G$5:$G$604,A10)) -> 0 | Y10: =IF(A10="","",COUNTIFS(Jobs!$G$5:$G$604,A10,Jobs!$P$5:$P$604,"Completed")+COUNTIFS(Jobs!$G$5:$G$604,A10,Jobs!$P$5:$P$604,"Invoiced")) -> 0 | Z10: =IF(A10="","",COUNTIFS(Jobs!$G$5:$G$604,A10,Jobs!$P$5:$P$604,"Cancelled")+COUNTIFS(Jobs!$G$5:$G$604,A10,Jobs!$P$5:$P$604,"No access")) -> 0 | AA10: =IF(A10="","",IF(SUMPRODUCT(MAX((Jobs!$G$5:$G$604=A10)*((Jobs!$P$5:$P$604="Completed")+(Jobs!$P$5:$P$604="Invoiced"))*Jobs!$B$5:$B$604))=0,"",SUMPRODUCT(MAX((Jobs!$G$5:$G$604=A10)*((Jobs!$P$5:$P$604="Completed")+(Jobs!$P$5:$P$604="Invoiced"))*Jobs!$B$5:$B$604)))) -> 0 | AB10: =IF(AA10="","",TodayDate-AA10) -> 0 | AC10: =IF(A10="","",IF(SUMPRODUCT(MIN((Jobs!$G$5:$G$604=A10)*(Jobs!$B$5:$B$604>=TodayDate)*(Jobs!$P$5:$P$604<>"Cancelled")*Jobs!$B$5:$B$604+(1-(Jobs!$G$5:$G$604=A10)*(Jobs!$B$5:$B$604>=TodayDate)*(Jobs!$P$5:$P$604<>"Cancelled"))*2958465))=2958465,"",SUMPRODUCT(MIN((Jobs!$G$5:$G$604=A10)*(Jobs!$B$5:$B$604>=TodayDate)*(Jobs!$P$5:$P$604<>"Cancelled")*Jobs!$B$5:$B$604+(1-(Jobs!$G$5:$G$604=A10)*(Jobs!$B$5:$B$604>=TodayDate)*(Jobs!$P$5:$P$604<>"Cancelled"))*2958465)))) -> 0 | AD10: =IF(A10="","",SUMIFS(Invoices!$V$5:$V$404,Invoices!$D$5:$D$404,A10)) -> 0 | AE10: =IF(A10="","",SUMIFS(Invoices!$W$5:$W$404,Invoices!$D$5:$D$404,A10)) -> 0 | AF10: =IF(A10="","",AD10-AE10) -> 0 | AG10: =IF(OR(A10="",Y10=0),"",AD10/Y10) -> 0 | AH10: =IF(A10="","",SUMIFS('Job Costing'!$U$5:$U$604,'Job Costing'!$D$5:$D$604,A10)) -> 0 | AI10: =IF(OR(A10="",AD10=0),"",AH10/AD10) -> 0 | AJ10: =IF(OR(A10="",K10="",AG10=""),"",AG10*IFERROR(INDEX(FreqPerYear,MATCH(K10,FreqNames,0)),1)) -> 0 | AK10: =IF(A10="","",IFERROR(AVERAGEIFS(Jobs!$AA$5:$AA$604,Jobs!$G$5:$G$604,A10,Jobs!$AA$5:$AA$604,">0"),"")) -> 0 | AL10: =IF(A10="","",COUNTIFS(Complaints!$D$5:$D$84,A10)) -> 0 | AM10: =IF(B10="","",COUNTIFS($AD$5:$AD$204,">"&AD10)+COUNTIFS($AD$5:AD10,AD10)) -> 0 | AN10: =IF(B10="","",COUNTIFS($AH$5:$AH$204,">"&AH10)+COUNTIFS($AH$5:AH10,AH10)) -> 0 | AO10: =IF(B10="","",COUNTIFS($AJ$5:$AJ$204,">"&AJ10)+COUNTIFS($AJ$5:AJ10,AJ10)) -> 0 | AP10: =IF(B10="","",IF(H10="Lost","Lost",IF(H10="Inactive","Dormant",IF(AA10="","Dormant",IF(AB10>InactiveClientDays*2,"Dormant",IF(AB10>InactiveClientDays,"At risk",IF(AC10="","Slipping",IF(Y10>=10,"Loyal","Steady")))))))) -> 0 | AQ10: =IF(OR(B10="",AP10="Lost",AP10="Dormant"),"",IF(OR(AP10="At risk",AP10="Slipping"),IF(AB10="",999,AB10),"")) -> 0 | AR10: =IF(AQ10="","",COUNTIFS($AQ$5:$AQ$204,">"&AQ10)+COUNTIFS($AQ$5:AQ10,AQ10)) -> 0 | AS10: =IF(B10="","",IF(AF10>0.5,"Chase - "&TEXT(AF10,"0")&" owing",IF(AND(H10<>"Lost",H10<>"Inactive",H10<>"Paused",AC10="",K10<>"One-off"),"Book - nothing in the diary",IF(AND(S10<>"",S10-TodayDate<=RenewalWarningDays,S10>=TodayDate),"Due - contract renews soon",IF(AP10="At risk","Call - going quiet",IF(AL10>=2,"Check - complaints logged",IF(AND(AI10<>"",AI10<MarginFloor,Y10>0),"Check - thin margin","OK"))))))) -> 0
A11: =IF(B11="","",ClientPrefix&TEXT(ROW()-4,"0000")) -> 0 | B11: Bright Start Nursery | C11: School & nursery | D11: Carla Jensen | E11: (503) 555 0122 | F11: carla@brightstart.example | G11: 15 Juniper Lane, Portland OR 97213 | H11: Regular | I11: Google search | J11: 45903 | K11: Weekly | L11: Friday | M11: Late (5-8) | N11: Amara Diallo | O11: 50 | P11: 14 | R11: 12 months | T11: Yes | U11: Yes | V11: Background checks required for everyone on site. No harsh chemicals in the baby room. | W11: =IF(A11="","",COUNTIFS(Properties!$C$5:$C$254,A11)) -> 0 | X11: =IF(A11="","",COUNTIFS(Jobs!$G$5:$G$604,A11)) -> 0 | Y11: =IF(A11="","",COUNTIFS(Jobs!$G$5:$G$604,A11,Jobs!$P$5:$P$604,"Completed")+COUNTIFS(Jobs!$G$5:$G$604,A11,Jobs!$P$5:$P$604,"Invoiced")) -> 0 | Z11: =IF(A11="","",COUNTIFS(Jobs!$G$5:$G$604,A11,Jobs!$P$5:$P$604,"Cancelled")+COUNTIFS(Jobs!$G$5:$G$604,A11,Jobs!$P$5:$P$604,"No access")) -> 0 | AA11: =IF(A11="","",IF(SUMPRODUCT(MAX((Jobs!$G$5:$G$604=A11)*((Jobs!$P$5:$P$604="Completed")+(Jobs!$P$5:$P$604="Invoiced"))*Jobs!$B$5:$B$604))=0,"",SUMPRODUCT(MAX((Jobs!$G$5:$G$604=A11)*((Jobs!$P$5:$P$604="Completed")+(Jobs!$P$5:$P$604="Invoiced"))*Jobs!$B$5:$B$604)))) -> 0 | AB11: =IF(AA11="","",TodayDate-AA11) -> 0 | AC11: =IF(A11="","",IF(SUMPRODUCT(MIN((Jobs!$G$5:$G$604=A11)*(Jobs!$B$5:$B$604>=TodayDate)*(Jobs!$P$5:$P$604<>"Cancelled")*Jobs!$B$5:$B$604+(1-(Jobs!$G$5:$G$604=A11)*(Jobs!$B$5:$B$604>=TodayDate)*(Jobs!$P$5:$P$604<>"Cancelled"))*2958465))=2958465,"",SUMPRODUCT(MIN((Jobs!$G$5:$G$604=A11)*(Jobs!$B$5:$B$604>=TodayDate)*(Jobs!$P$5:$P$604<>"Cancelled")*Jobs!$B$5:$B$604+(1-(Jobs!$G$5:$G$604=A11)*(Jobs!$B$5:$B$604>=TodayDate)*(Jobs!$P$5:$P$604<>"Cancelled"))*2958465)))) -> 0 | AD11: =IF(A11="","",SUMIFS(Invoices!$V$5:$V$404,Invoices!$D$5:$D$404,A11)) -> 0 | AE11: =IF(A11="","",SUMIFS(Invoices!$W$5:$W$404,Invoices!$D$5:$D$404,A11)) -> 0 | AF11: =IF(A11="","",AD11-AE11) -> 0 | AG11: =IF(OR(A11="",Y11=0),"",AD11/Y11) -> 0 | AH11: =IF(A11="","",SUMIFS('Job Costing'!$U$5:$U$604,'Job Costing'!$D$5:$D$604,A11)) -> 0 | AI11: =IF(OR(A11="",AD11=0),"",AH11/AD11) -> 0 | AJ11: =IF(OR(A11="",K11="",AG11=""),"",AG11*IFERROR(INDEX(FreqPerYear,MATCH(K11,FreqNames,0)),1)) -> 0 | AK11: =IF(A11="","",IFERROR(AVERAGEIFS(Jobs!$AA$5:$AA$604,Jobs!$G$5:$G$604,A11,Jobs!$AA$5:$AA$604,">0"),"")) -> 0 | AL11: =IF(A11="","",COUNTIFS(Complaints!$D$5:$D$84,A11)) -> 0 | AM11: =IF(B11="","",COUNTIFS($AD$5:$AD$204,">"&AD11)+COUNTIFS($AD$5:AD11,AD11)) -> 0 | AN11: =IF(B11="","",COUNTIFS($AH$5:$AH$204,">"&AH11)+COUNTIFS($AH$5:AH11,AH11)) -> 0 | AO11: =IF(B11="","",COUNTIFS($AJ$5:$AJ$204,">"&AJ11)+COUNTIFS($AJ$5:AJ11,AJ11)) -> 0 | AP11: =IF(B11="","",IF(H11="Lost","Lost",IF(H11="Inactive","Dormant",IF(AA11="","Dormant",IF(AB11>InactiveClientDays*2,"Dormant",IF(AB11>InactiveClientDays,"At risk",IF(AC11="","Slipping",IF(Y11>=10,"Loyal","Steady")))))))) -> 0 | AQ11: =IF(OR(B11="",AP11="Lost",AP11="Dormant"),"",IF(OR(AP11="At risk",AP11="Slipping"),IF(AB11="",999,AB11),"")) -> 0 | AR11: =IF(AQ11="","",COUNTIFS($AQ$5:$AQ$204,">"&AQ11)+COUNTIFS($AQ$5:AQ11,AQ11)) -> 0 | AS11: =IF(B11="","",IF(AF11>0.5,"Chase - "&TEXT(AF11,"0")&" owing",IF(AND(H11<>"Lost",H11<>"Inactive",H11<>"Paused",AC11="",K11<>"One-off"),"Book - nothing in the diary",IF(AND(S11<>"",S11-TodayDate<=RenewalWarningDays,S11>=TodayDate),"Due - contract renews soon",IF(AP11="At risk","Call - going quiet",IF(AL11>=2,"Check - complaints logged",IF(AND(AI11<>"",AI11<MarginFloor,Y11>0),"Check - thin margin","OK"))))))) -> 0
A12: =IF(B12="","",ClientPrefix&TEXT(ROW()-4,"0000")) -> 0 | B12: Nguyen Household | C12: Residential | D12: Lien Nguyen | E12: (503) 555 0259 | F12: lien.nguyen@example.com | G12: 88 Alder Way, Portland OR 97211 | H12: Active | I12: Facebook | J12: 46103 | K12: Monthly | L12: Wednesday | M12: Morning (9-12) | N12: Jade Ellis | O12: 45 | P12: 7 | R12: Rolling monthly | T12: No | U12: Yes | V12: Shoes off at the door. Key is in the lockbox. | W12: =IF(A12="","",COUNTIFS(Properties!$C$5:$C$254,A12)) -> 0 | X12: =IF(A12="","",COUNTIFS(Jobs!$G$5:$G$604,A12)) -> 0 | Y12: =IF(A12="","",COUNTIFS(Jobs!$G$5:$G$604,A12,Jobs!$P$5:$P$604,"Completed")+COUNTIFS(Jobs!$G$5:$G$604,A12,Jobs!$P$5:$P$604,"Invoiced")) -> 0 | Z12: =IF(A12="","",COUNTIFS(Jobs!$G$5:$G$604,A12,Jobs!$P$5:$P$604,"Cancelled")+COUNTIFS(Jobs!$G$5:$G$604,A12,Jobs!$P$5:$P$604,"No access")) -> 0 | AA12: =IF(A12="","",IF(SUMPRODUCT(MAX((Jobs!$G$5:$G$604=A12)*((Jobs!$P$5:$P$604="Completed")+(Jobs!$P$5:$P$604="Invoiced"))*Jobs!$B$5:$B$604))=0,"",SUMPRODUCT(MAX((Jobs!$G$5:$G$604=A12)*((Jobs!$P$5:$P$604="Completed")+(Jobs!$P$5:$P$604="Invoiced"))*Jobs!$B$5:$B$604)))) -> 0 | AB12: =IF(AA12="","",TodayDate-AA12) -> 0 | AC12: =IF(A12="","",IF(SUMPRODUCT(MIN((Jobs!$G$5:$G$604=A12)*(Jobs!$B$5:$B$604>=TodayDate)*(Jobs!$P$5:$P$604<>"Cancelled")*Jobs!$B$5:$B$604+(1-(Jobs!$G$5:$G$604=A12)*(Jobs!$B$5:$B$604>=TodayDate)*(Jobs!$P$5:$P$604<>"Cancelled"))*2958465))=2958465,"",SUMPRODUCT(MIN((Jobs!$G$5:$G$604=A12)*(Jobs!$B$5:$B$604>=TodayDate)*(Jobs!$P$5:$P$604<>"Cancelled")*Jobs!$B$5:$B$604+(1-(Jobs!$G$5:$G$604=A12)*(Jobs!$B$5:$B$604>=TodayDate)*(Jobs!$P$5:$P$604<>"Cancelled"))*2958465)))) -> 0 | AD12: =IF(A12="","",SUMIFS(Invoices!$V$5:$V$404,Invoices!$D$5:$D$404,A12)) -> 0 | AE12: =IF(A12="","",SUMIFS(Invoices!$W$5:$W$404,Invoices!$D$5:$D$404,A12)) -> 0 | AF12: =IF(A12="","",AD12-AE12) -> 0 | AG12: =IF(OR(A12="",Y12=0),"",AD12/Y12) -> 0 | AH12: =IF(A12="","",SUMIFS('Job Costing'!$U$5:$U$604,'Job Costing'!$D$5:$D$604,A12)) -> 0 | AI12: =IF(OR(A12="",AD12=0),"",AH12/AD12) -> 0 | AJ12: =IF(OR(A12="",K12="",AG12=""),"",AG12*IFERROR(INDEX(FreqPerYear,MATCH(K12,FreqNames,0)),1)) -> 0 | AK12: =IF(A12="","",IFERROR(AVERAGEIFS(Jobs!$AA$5:$AA$604,Jobs!$G$5:$G$604,A12,Jobs!$AA$5:$AA$604,">0"),"")) -> 0 | AL12: =IF(A12="","",COUNTIFS(Complaints!$D$5:$D$84,A12)) -> 0 | AM12: =IF(B12="","",COUNTIFS($AD$5:$AD$204,">"&AD12)+COUNTIFS($AD$5:AD12,AD12)) -> 0 | AN12: =IF(B12="","",COUNTIFS($AH$5:$AH$204,">"&AH12)+COUNTIFS($AH$5:AH12,AH12)) -> 0 | AO12: =IF(B12="","",COUNTIFS($AJ$5:$AJ$204,">"&AJ12)+COUNTIFS($AJ$5:AJ12,AJ12)) -> 0 | AP12: =IF(B12="","",IF(H12="Lost","Lost",IF(H12="Inactive","Dormant",IF(AA12="","Dormant",IF(AB12>InactiveClientDays*2,"Dormant",IF(AB12>InactiveClientDays,"At risk",IF(AC12="","Slipping",IF(Y12>=10,"Loyal","Steady")))))))) -> 0 | AQ12: =IF(OR(B12="",AP12="Lost",AP12="Dormant"),"",IF(OR(AP12="At risk",AP12="Slipping"),IF(AB12="",999,AB12),"")) -> 0 | AR12: =IF(AQ12="","",COUNTIFS($AQ$5:$AQ$204,">"&AQ12)+COUNTIFS($AQ$5:AQ12,AQ12)) -> 0 | AS12: =IF(B12="","",IF(AF12>0.5,"Chase - "&TEXT(AF12,"0")&" owing",IF(AND(H12<>"Lost",H12<>"Inactive",H12<>"Paused",AC12="",K12<>"One-off"),"Book - nothing in the diary",IF(AND(S12<>"",S12-TodayDate<=RenewalWarningDays,S12>=TodayDate),"Due - contract renews soon",IF(AP12="At risk","Call - going quiet",IF(AL12>=2,"Check - complaints logged",IF(AND(AI12<>"",AI12<MarginFloor,Y12>0),"Check - thin margin","OK"))))))) -> 0
A13: =IF(B13="","",ClientPrefix&TEXT(ROW()-4,"0000")) -> 0 | B13: Summit Fitness Studio | C13: Gym & studio | D13: Dev Patel | E13: (503) 555 0333 | F13: dev@summitfitness.example | G13: 501 Summit Drive, Portland OR 97201 | H13: Active | I13: Instagram | J13: 46133 | K13: Twice a week | L13: Monday | M13: Early (7-9) | N13: Luke Bennett | O13: 52 | P13: 14 | R13: 6 months | T13: No | U13: Yes | V13: Mirrors and mats matter more than floors here. | W13: =IF(A13="","",COUNTIFS(Properties!$C$5:$C$254,A13)) -> 0 | X13: =IF(A13="","",COUNTIFS(Jobs!$G$5:$G$604,A13)) -> 0 | Y13: =IF(A13="","",COUNTIFS(Jobs!$G$5:$G$604,A13,Jobs!$P$5:$P$604,"Completed")+COUNTIFS(Jobs!$G$5:$G$604,A13,Jobs!$P$5:$P$604,"Invoiced")) -> 0 | Z13: =IF(A13="","",COUNTIFS(Jobs!$G$5:$G$604,A13,Jobs!$P$5:$P$604,"Cancelled")+COUNTIFS(Jobs!$G$5:$G$604,A13,Jobs!$P$5:$P$604,"No access")) -> 0 | AA13: =IF(A13="","",IF(SUMPRODUCT(MAX((Jobs!$G$5:$G$604=A13)*((Jobs!$P$5:$P$604="Completed")+(Jobs!$P$5:$P$604="Invoiced"))*Jobs!$B$5:$B$604))=0,"",SUMPRODUCT(MAX((Jobs!$G$5:$G$604=A13)*((Jobs!$P$5:$P$604="Completed")+(Jobs!$P$5:$P$604="Invoiced"))*Jobs!$B$5:$B$604)))) -> 0 | AB13: =IF(AA13="","",TodayDate-AA13) -> 0 | AC13: =IF(A13="","",IF(SUMPRODUCT(MIN((Jobs!$G$5:$G$604=A13)*(Jobs!$B$5:$B$604>=TodayDate)*(Jobs!$P$5:$P$604<>"Cancelled")*Jobs!$B$5:$B$604+(1-(Jobs!$G$5:$G$604=A13)*(Jobs!$B$5:$B$604>=TodayDate)*(Jobs!$P$5:$P$604<>"Cancelled"))*2958465))=2958465,"",SUMPRODUCT(MIN((Jobs!$G$5:$G$604=A13)*(Jobs!$B$5:$B$604>=TodayDate)*(Jobs!$P$5:$P$604<>"Cancelled")*Jobs!$B$5:$B$604+(1-(Jobs!$G$5:$G$604=A13)*(Jobs!$B$5:$B$604>=TodayDate)*(Jobs!$P$5:$P$604<>"Cancelled"))*2958465)))) -> 0 | AD13: =IF(A13="","",SUMIFS(Invoices!$V$5:$V$404,Invoices!$D$5:$D$404,A13)) -> 0 | AE13: =IF(A13="","",SUMIFS(Invoices!$W$5:$W$404,Invoices!$D$5:$D$404,A13)) -> 0 | AF13: =IF(A13="","",AD13-AE13) -> 0 | AG13: =IF(OR(A13="",Y13=0),"",AD13/Y13) -> 0 | AH13: =IF(A13="","",SUMIFS('Job Costing'!$U$5:$U$604,'Job Costing'!$D$5:$D$604,A13)) -> 0 | AI13: =IF(OR(A13="",AD13=0),"",AH13/AD13) -> 0 | AJ13: =IF(OR(A13="",K13="",AG13=""),"",AG13*IFERROR(INDEX(FreqPerYear,MATCH(K13,FreqNames,0)),1)) -> 0 | AK13: =IF(A13="","",IFERROR(AVERAGEIFS(Jobs!$AA$5:$AA$604,Jobs!$G$5:$G$604,A13,Jobs!$AA$5:$AA$604,">0"),"")) -> 0 | AL13: =IF(A13="","",COUNTIFS(Complaints!$D$5:$D$84,A13)) -> 0 | AM13: =IF(B13="","",COUNTIFS($AD$5:$AD$204,">"&AD13)+COUNTIFS($AD$5:AD13,AD13)) -> 0 | AN13: =IF(B13="","",COUNTIFS($AH$5:$AH$204,">"&AH13)+COUNTIFS($AH$5:AH13,AH13)) -> 0 | AO13: =IF(B13="","",COUNTIFS($AJ$5:$AJ$204,">"&AJ13)+COUNTIFS($AJ$5:AJ13,AJ13)) -> 0 | AP13: =IF(B13="","",IF(H13="Lost","Lost",IF(H13="Inactive","Dormant",IF(AA13="","Dormant",IF(AB13>InactiveClientDays*2,"Dormant",IF(AB13>InactiveClientDays,"At risk",IF(AC13="","Slipping",IF(Y13>=10,"Loyal","Steady")))))))) -> 0 | AQ13: =IF(OR(B13="",AP13="Lost",AP13="Dormant"),"",IF(OR(AP13="At risk",AP13="Slipping"),IF(AB13="",999,AB13),"")) -> 0 | AR13: =IF(AQ13="","",COUNTIFS($AQ$5:$AQ$204,">"&AQ13)+COUNTIFS($AQ$5:AQ13,AQ13)) -> 0 | AS13: =IF(B13="","",IF(AF13>0.5,"Chase - "&TEXT(AF13,"0")&" owing",IF(AND(H13<>"Lost",H13<>"Inactive",H13<>"Paused",AC13="",K13<>"One-off"),"Book - nothing in the diary",IF(AND(S13<>"",S13-TodayDate<=RenewalWarningDays,S13>=TodayDate),"Due - contract renews soon",IF(AP13="At risk","Call - going quiet",IF(AL13>=2,"Check - complaints logged",IF(AND(AI13<>"",AI13<MarginFloor,Y13>0),"Check - thin margin","OK"))))))) -> 0
A14: =IF(B14="","",ClientPrefix&TEXT(ROW()-4,"0000")) -> 0 | B14: Hartley Holiday Lets | C14: Holiday let / Airbnb | D14: Rosie Hartley | E14: (503) 555 0288 | F14: rosie@hartleylets.example | G14: 6 Quay Street, Portland OR 97209 | H14: Regular | I14: Nextdoor | J14: 45983 | K14: Weekly | L14: Saturday | M14: Midday (12-2) | N14: Jade Ellis | O14: 50 | P14: 7 | R14: Rolling monthly | T14: Yes | U14: Yes | V14: Changeover between 11 and 3. Linen is in the hall cupboard. | W14: =IF(A14="","",COUNTIFS(Properties!$C$5:$C$254,A14)) -> 0 | X14: =IF(A14="","",COUNTIFS(Jobs!$G$5:$G$604,A14)) -> 0 | Y14: =IF(A14="","",COUNTIFS(Jobs!$G$5:$G$604,A14,Jobs!$P$5:$P$604,"Completed")+COUNTIFS(Jobs!$G$5:$G$604,A14,Jobs!$P$5:$P$604,"Invoiced")) -> 0 | Z14: =IF(A14="","",COUNTIFS(Jobs!$G$5:$G$604,A14,Jobs!$P$5:$P$604,"Cancelled")+COUNTIFS(Jobs!$G$5:$G$604,A14,Jobs!$P$5:$P$604,"No access")) -> 0 | AA14: =IF(A14="","",IF(SUMPRODUCT(MAX((Jobs!$G$5:$G$604=A14)*((Jobs!$P$5:$P$604="Completed")+(Jobs!$P$5:$P$604="Invoiced"))*Jobs!$B$5:$B$604))=0,"",SUMPRODUCT(MAX((Jobs!$G$5:$G$604=A14)*((Jobs!$P$5:$P$604="Completed")+(Jobs!$P$5:$P$604="Invoiced"))*Jobs!$B$5:$B$604)))) -> 0 | AB14: =IF(AA14="","",TodayDate-AA14) -> 0 | AC14: =IF(A14="","",IF(SUMPRODUCT(MIN((Jobs!$G$5:$G$604=A14)*(Jobs!$B$5:$B$604>=TodayDate)*(Jobs!$P$5:$P$604<>"Cancelled")*Jobs!$B$5:$B$604+(1-(Jobs!$G$5:$G$604=A14)*(Jobs!$B$5:$B$604>=TodayDate)*(Jobs!$P$5:$P$604<>"Cancelled"))*2958465))=2958465,"",SUMPRODUCT(MIN((Jobs!$G$5:$G$604=A14)*(Jobs!$B$5:$B$604>=TodayDate)*(Jobs!$P$5:$P$604<>"Cancelled")*Jobs!$B$5:$B$604+(1-(Jobs!$G$5:$G$604=A14)*(Jobs!$B$5:$B$604>=TodayDate)*(Jobs!$P$5:$P$604<>"Cancelled"))*2958465)))) -> 0 | AD14: =IF(A14="","",SUMIFS(Invoices!$V$5:$V$404,Invoices!$D$5:$D$404,A14)) -> 0 | AE14: =IF(A14="","",SUMIFS(Invoices!$W$5:$W$404,Invoices!$D$5:$D$404,A14)) -> 0 | AF14: =IF(A14="","",AD14-AE14) -> 0 | AG14: =IF(OR(A14="",Y14=0),"",AD14/Y14) -> 0 | AH14: =IF(A14="","",SUMIFS('Job Costing'!$U$5:$U$604,'Job Costing'!$D$5:$D$604,A14)) -> 0 | AI14: =IF(OR(A14="",AD14=0),"",AH14/AD14) -> 0 | AJ14: =IF(OR(A14="",K14="",AG14=""),"",AG14*IFERROR(INDEX(FreqPerYear,MATCH(K14,FreqNames,0)),1)) -> 0 | AK14: =IF(A14="","",IFERROR(AVERAGEIFS(Jobs!$AA$5:$AA$604,Jobs!$G$5:$G$604,A14,Jobs!$AA$5:$AA$604,">0"),"")) -> 0 | AL14: =IF(A14="","",COUNTIFS(Complaints!$D$5:$D$84,A14)) -> 0 | AM14: =IF(B14="","",COUNTIFS($AD$5:$AD$204,">"&AD14)+COUNTIFS($AD$5:AD14,AD14)) -> 0 | AN14: =IF(B14="","",COUNTIFS($AH$5:$AH$204,">"&AH14)+COUNTIFS($AH$5:AH14,AH14)) -> 0 | AO14: =IF(B14="","",COUNTIFS($AJ$5:$AJ$204,">"&AJ14)+COUNTIFS($AJ$5:AJ14,AJ14)) -> 0 | AP14: =IF(B14="","",IF(H14="Lost","Lost",IF(H14="Inactive","Dormant",IF(AA14="","Dormant",IF(AB14>InactiveClientDays*2,"Dormant",IF(AB14>InactiveClientDays,"At risk",IF(AC14="","Slipping",IF(Y14>=10,"Loyal","Steady")))))))) -> 0 | AQ14: =IF(OR(B14="",AP14="Lost",AP14="Dormant"),"",IF(OR(AP14="At risk",AP14="Slipping"),IF(AB14="",999,AB14),"")) -> 0 | AR14: =IF(AQ14="","",COUNTIFS($AQ$5:$AQ$204,">"&AQ14)+COUNTIFS($AQ$5:AQ14,AQ14)) -> 0 | AS14: =IF(B14="","",IF(AF14>0.5,"Chase - "&TEXT(AF14,"0")&" owing",IF(AND(H14<>"Lost",H14<>"Inactive",H14<>"Paused",AC14="",K14<>"One-off"),"Book - nothing in the diary",IF(AND(S14<>"",S14-TodayDate<=RenewalWarningDays,S14>=TodayDate),"Due - contract renews soon",IF(AP14="At risk","Call - going quiet",IF(AL14>=2,"Check - complaints logged",IF(AND(AI14<>"",AI14<MarginFloor,Y14>0),"Check - thin margin","OK"))))))) -> 0
A15: =IF(B15="","",ClientPrefix&TEXT(ROW()-4,"0000")) -> 0 | B15: Donovan Residence | C15: Residential | D15: Paul Donovan | E15: (503) 555 0194 | F15: paul.donovan@example.com | G15: 27 Birch Close, Portland OR 97215 | H15: Paused | I15: Van signage | J15: 45833 | K15: Fortnightly | L15: Thursday | M15: Morning (9-12) | N15: Marta Kovacs | O15: 45 | P15: 7 | R15: Rolling monthly | T15: No | U15: Yes | V15: Paused for the summer, back in September - call in August. | W15: =IF(A15="","",COUNTIFS(Properties!$C$5:$C$254,A15)) -> 0 | X15: =IF(A15="","",COUNTIFS(Jobs!$G$5:$G$604,A15)) -> 0 | Y15: =IF(A15="","",COUNTIFS(Jobs!$G$5:$G$604,A15,Jobs!$P$5:$P$604,"Completed")+COUNTIFS(Jobs!$G$5:$G$604,A15,Jobs!$P$5:$P$604,"Invoiced")) -> 0 | Z15: =IF(A15="","",COUNTIFS(Jobs!$G$5:$G$604,A15,Jobs!$P$5:$P$604,"Cancelled")+COUNTIFS(Jobs!$G$5:$G$604,A15,Jobs!$P$5:$P$604,"No access")) -> 0 | AA15: =IF(A15="","",IF(SUMPRODUCT(MAX((Jobs!$G$5:$G$604=A15)*((Jobs!$P$5:$P$604="Completed")+(Jobs!$P$5:$P$604="Invoiced"))*Jobs!$B$5:$B$604))=0,"",SUMPRODUCT(MAX((Jobs!$G$5:$G$604=A15)*((Jobs!$P$5:$P$604="Completed")+(Jobs!$P$5:$P$604="Invoiced"))*Jobs!$B$5:$B$604)))) -> 0 | AB15: =IF(AA15="","",TodayDate-AA15) -> 0 | AC15: =IF(A15="","",IF(SUMPRODUCT(MIN((Jobs!$G$5:$G$604=A15)*(Jobs!$B$5:$B$604>=TodayDate)*(Jobs!$P$5:$P$604<>"Cancelled")*Jobs!$B$5:$B$604+(1-(Jobs!$G$5:$G$604=A15)*(Jobs!$B$5:$B$604>=TodayDate)*(Jobs!$P$5:$P$604<>"Cancelled"))*2958465))=2958465,"",SUMPRODUCT(MIN((Jobs!$G$5:$G$604=A15)*(Jobs!$B$5:$B$604>=TodayDate)*(Jobs!$P$5:$P$604<>"Cancelled")*Jobs!$B$5:$B$604+(1-(Jobs!$G$5:$G$604=A15)*(Jobs!$B$5:$B$604>=TodayDate)*(Jobs!$P$5:$P$604<>"Cancelled"))*2958465)))) -> 0 | AD15: =IF(A15="","",SUMIFS(Invoices!$V$5:$V$404,Invoices!$D$5:$D$404,A15)) -> 0 | AE15: =IF(A15="","",SUMIFS(Invoices!$W$5:$W$404,Invoices!$D$5:$D$404,A15)) -> 0 | AF15: =IF(A15="","",AD15-AE15) -> 0 | AG15: =IF(OR(A15="",Y15=0),"",AD15/Y15) -> 0 | AH15: =IF(A15="","",SUMIFS('Job Costing'!$U$5:$U$604,'Job Costing'!$D$5:$D$604,A15)) -> 0 | AI15: =IF(OR(A15="",AD15=0),"",AH15/AD15) -> 0 | AJ15: =IF(OR(A15="",K15="",AG15=""),"",AG15*IFERROR(INDEX(FreqPerYear,MATCH(K15,FreqNames,0)),1)) -> 0 | AK15: =IF(A15="","",IFERROR(AVERAGEIFS(Jobs!$AA$5:$AA$604,Jobs!$G$5:$G$604,A15,Jobs!$AA$5:$AA$604,">0"),"")) -> 0 | AL15: =IF(A15="","",COUNTIFS(Complaints!$D$5:$D$84,A15)) -> 0 | AM15: =IF(B15="","",COUNTIFS($AD$5:$AD$204,">"&AD15)+COUNTIFS($AD$5:AD15,AD15)) -> 0 | AN15: =IF(B15="","",COUNTIFS($AH$5:$AH$204,">"&AH15)+COUNTIFS($AH$5:AH15,AH15)) -> 0 | AO15: =IF(B15="","",COUNTIFS($AJ$5:$AJ$204,">"&AJ15)+COUNTIFS($AJ$5:AJ15,AJ15)) -> 0 | AP15: =IF(B15="","",IF(H15="Lost","Lost",IF(H15="Inactive","Dormant",IF(AA15="","Dormant",IF(AB15>InactiveClientDays*2,"Dormant",IF(AB15>InactiveClientDays,"At risk",IF(AC15="","Slipping",IF(Y15>=10,"Loyal","Steady")))))))) -> 0 | AQ15: =IF(OR(B15="",AP15="Lost",AP15="Dormant"),"",IF(OR(AP15="At risk",AP15="Slipping"),IF(AB15="",999,AB15),"")) -> 0 | AR15: =IF(AQ15="","",COUNTIFS($AQ$5:$AQ$204,">"&AQ15)+COUNTIFS($AQ$5:AQ15,AQ15)) -> 0 | AS15: =IF(B15="","",IF(AF15>0.5,"Chase - "&TEXT(AF15,"0")&" owing",IF(AND(H15<>"Lost",H15<>"Inactive",H15<>"Paused",AC15="",K15<>"One-off"),"Book - nothing in the diary",IF(AND(S15<>"",S15-TodayDate<=RenewalWarningDays,S15>=TodayDate),"Due - contract renews soon",IF(AP15="At risk","Call - going quiet",IF(AL15>=2,"Check - complaints logged",IF(AND(AI15<>"",AI15<MarginFloor,Y15>0),"Check - thin margin","OK"))))))) -> 0
A16: =IF(B16="","",ClientPrefix&TEXT(ROW()-4,"0000")) -> 0 | B16: Willow Park Estates | C16: Property manager | D16: Grace Lin | E16: (503) 555 0401 | F16: grace@willowpark.example | G16: Willow Park, Block A-D, Portland OR 97217 | H16: Active | I16: Referral - staff | J16: 46163 | K16: Monthly | L16: Wednesday | M16: Afternoon (2-5) | N16: Luke Bennett | O16: 48 | P16: 30 | R16: 12 months | T16: No | U16: Yes | V16: Four communal stairwells and the bin stores. Invoice monthly. | W16: =IF(A16="","",COUNTIFS(Properties!$C$5:$C$254,A16)) -> 0 | X16: =IF(A16="","",COUNTIFS(Jobs!$G$5:$G$604,A16)) -> 0 | Y16: =IF(A16="","",COUNTIFS(Jobs!$G$5:$G$604,A16,Jobs!$P$5:$P$604,"Completed")+COUNTIFS(Jobs!$G$5:$G$604,A16,Jobs!$P$5:$P$604,"Invoiced")) -> 0 | Z16: =IF(A16="","",COUNTIFS(Jobs!$G$5:$G$604,A16,Jobs!$P$5:$P$604,"Cancelled")+COUNTIFS(Jobs!$G$5:$G$604,A16,Jobs!$P$5:$P$604,"No access")) -> 0 | AA16: =IF(A16="","",IF(SUMPRODUCT(MAX((Jobs!$G$5:$G$604=A16)*((Jobs!$P$5:$P$604="Completed")+(Jobs!$P$5:$P$604="Invoiced"))*Jobs!$B$5:$B$604))=0,"",SUMPRODUCT(MAX((Jobs!$G$5:$G$604=A16)*((Jobs!$P$5:$P$604="Completed")+(Jobs!$P$5:$P$604="Invoiced"))*Jobs!$B$5:$B$604)))) -> 0 | AB16: =IF(AA16="","",TodayDate-AA16) -> 0 | AC16: =IF(A16="","",IF(SUMPRODUCT(MIN((Jobs!$G$5:$G$604=A16)*(Jobs!$B$5:$B$604>=TodayDate)*(Jobs!$P$5:$P$604<>"Cancelled")*Jobs!$B$5:$B$604+(1-(Jobs!$G$5:$G$604=A16)*(Jobs!$B$5:$B$604>=TodayDate)*(Jobs!$P$5:$P$604<>"Cancelled"))*2958465))=2958465,"",SUMPRODUCT(MIN((Jobs!$G$5:$G$604=A16)*(Jobs!$B$5:$B$604>=TodayDate)*(Jobs!$P$5:$P$604<>"Cancelled")*Jobs!$B$5:$B$604+(1-(Jobs!$G$5:$G$604=A16)*(Jobs!$B$5:$B$604>=TodayDate)*(Jobs!$P$5:$P$604<>"Cancelled"))*2958465)))) -> 0 | AD16: =IF(A16="","",SUMIFS(Invoices!$V$5:$V$404,Invoices!$D$5:$D$404,A16)) -> 0 | AE16: =IF(A16="","",SUMIFS(Invoices!$W$5:$W$404,Invoices!$D$5:$D$404,A16)) -> 0 | AF16: =IF(A16="","",AD16-AE16) -> 0 | AG16: =IF(OR(A16="",Y16=0),"",AD16/Y16) -> 0 | AH16: =IF(A16="","",SUMIFS('Job Costing'!$U$5:$U$604,'Job Costing'!$D$5:$D$604,A16)) -> 0 | AI16: =IF(OR(A16="",AD16=0),"",AH16/AD16) -> 0 | AJ16: =IF(OR(A16="",K16="",AG16=""),"",AG16*IFERROR(INDEX(FreqPerYear,MATCH(K16,FreqNames,0)),1)) -> 0 | AK16: =IF(A16="","",IFERROR(AVERAGEIFS(Jobs!$AA$5:$AA$604,Jobs!$G$5:$G$604,A16,Jobs!$AA$5:$AA$604,">0"),"")) -> 0 | AL16: =IF(A16="","",COUNTIFS(Complaints!$D$5:$D$84,A16)) -> 0 | AM16: =IF(B16="","",COUNTIFS($AD$5:$AD$204,">"&AD16)+COUNTIFS($AD$5:AD16,AD16)) -> 0 | AN16: =IF(B16="","",COUNTIFS($AH$5:$AH$204,">"&AH16)+COUNTIFS($AH$5:AH16,AH16)) -> 0 | AO16: =IF(B16="","",COUNTIFS($AJ$5:$AJ$204,">"&AJ16)+COUNTIFS($AJ$5:AJ16,AJ16)) -> 0 | AP16: =IF(B16="","",IF(H16="Lost","Lost",IF(H16="Inactive","Dormant",IF(AA16="","Dormant",IF(AB16>InactiveClientDays*2,"Dormant",IF(AB16>InactiveClientDays,"At risk",IF(AC16="","Slipping",IF(Y16>=10,"Loyal","Steady")))))))) -> 0 | AQ16: =IF(OR(B16="",AP16="Lost",AP16="Dormant"),"",IF(OR(AP16="At risk",AP16="Slipping"),IF(AB16="",999,AB16),"")) -> 0 | AR16: =IF(AQ16="","",COUNTIFS($AQ$5:$AQ$204,">"&AQ16)+COUNTIFS($AQ$5:AQ16,AQ16)) -> 0 | AS16: =IF(B16="","",IF(AF16>0.5,"Chase - "&TEXT(AF16,"0")&" owing",IF(AND(H16<>"Lost",H16<>"Inactive",H16<>"Paused",AC16="",K16<>"One-off"),"Book - nothing in the diary",IF(AND(S16<>"",S16-TodayDate<=RenewalWarningDays,S16>=TodayDate),"Due - contract renews soon",IF(AP16="At risk","Call - going quiet",IF(AL16>=2,"Check - complaints logged",IF(AND(AI16<>"",AI16<MarginFloor,Y16>0),"Check - thin margin","OK"))))))) -> 0
... A19: =IF(B19="","",ClientPrefix&TEXT(ROW()-4,"0000")) -> 0 | B19: Alvarez Family | C19: Residential | D19: Ines Alvarez | E19: (503) 555 0215 | F19: ines.alvarez@example.com | G19: 63 Hawthorn Road, Portland OR 97203 | H19: Inactive | I19: Flyer / leaflet | J19: 45613 | K19: One-off | L19: Flexible | M19: Flexible | N19: Jade Ellis | O19: 45 | P19: 7 | R19: No contract | T19: No | U19: Yes | V19: Moved out of the area in the spring. Left a five star review. | W19: =IF(A19="","",COUNTIFS(Properties!$C$5:$C$254,A19)) -> 0 | X19: =IF(A19="","",COUNTIFS(Jobs!$G$5:$G$604,A19)) -> 0 | Y19: =IF(A19="","",COUNTIFS(Jobs!$G$5:$G$604,A19,Jobs!$P$5:$P$604,"Completed")+COUNTIFS(Jobs!$G$5:$G$604,A19,Jobs!$P$5:$P$604,"Invoiced")) -> 0 | Z19: =IF(A19="","",COUNTIFS(Jobs!$G$5:$G$604,A19,Jobs!$P$5:$P$604,"Cancelled")+COUNTIFS(Jobs!$G$5:$G$604,A19,Jobs!$P$5:$P$604,"No access")) -> 0 | AA19: =IF(A19="","",IF(SUMPRODUCT(MAX((Jobs!$G$5:$G$604=A19)*((Jobs!$P$5:$P$604="Completed")+(Jobs!$P$5:$P$604="Invoiced"))*Jobs!$B$5:$B$604))=0,"",SUMPRODUCT(MAX((Jobs!$G$5:$G$604=A19)*((Jobs!$P$5:$P$604="Completed")+(Jobs!$P$5:$P$604="Invoiced"))*Jobs!$B$5:$B$604)))) -> 0 | AB19: =IF(AA19="","",TodayDate-AA19) -> 0 | AC19: =IF(A19="","",IF(SUMPRODUCT(MIN((Jobs!$G$5:$G$604=A19)*(Jobs!$B$5:$B$604>=TodayDate)*(Jobs!$P$5:$P$604<>"Cancelled")*Jobs!$B$5:$B$604+(1-(Jobs!$G$5:$G$604=A19)*(Jobs!$B$5:$B$604>=TodayDate)*(Jobs!$P$5:$P$604<>"Cancelled"))*2958465))=2958465,"",SUMPRODUCT(MIN((Jobs!$G$5:$G$604=A19)*(Jobs!$B$5:$B$604>=TodayDate)*(Jobs!$P$5:$P$604<>"Cancelled")*Jobs!$B$5:$B$604+(1-(Jobs!$G$5:$G$604=A19)*(Jobs!$B$5:$B$604>=TodayDate)*(Jobs!$P$5:$P$604<>"Cancelled"))*2958465)))) -> 0 | AD19: =IF(A19="","",SUMIFS(Invoices!$V$5:$V$404,Invoices!$D$5:$D$404,A19)) -> 0 | AE19: =IF(A19="","",SUMIFS(Invoices!$W$5:$W$404,Invoices!$D$5:$D$404,A19)) -> 0 | AF19: =IF(A19="","",AD19-AE19) -> 0 | AG19: =IF(OR(A19="",Y19=0),"",AD19/Y19) -> 0 | AH19: =IF(A19="","",SUMIFS('Job Costing'!$U$5:$U$604,'Job Costing'!$D$5:$D$604,A19)) -> 0 | AI19: =IF(OR(A19="",AD19=0),"",AH19/AD19) -> 0 | AJ19: =IF(OR(A19="",K19="",AG19=""),"",AG19*IFERROR(INDEX(FreqPerYear,MATCH(K19,FreqNames,0)),1)) -> 0 | AK19: =IF(A19="","",IFERROR(AVERAGEIFS(Jobs!$AA$5:$AA$604,Jobs!$G$5:$G$604,A19,Jobs!$AA$5:$AA$604,">0"),"")) -> 0 | AL19: =IF(A19="","",COUNTIFS(Complaints!$D$5:$D$84,A19)) -> 0 | AM19: =IF(B19="","",COUNTIFS($AD$5:$AD$204,">"&AD19)+COUNTIFS($AD$5:AD19,AD19)) -> 0 | AN19: =IF(B19="","",COUNTIFS($AH$5:$AH$204,">"&AH19)+COUNTIFS($AH$5:AH19,AH19)) -> 0 | AO19: =IF(B19="","",COUNTIFS($AJ$5:$AJ$204,">"&AJ19)+COUNTIFS($AJ$5:AJ19,AJ19)) -> 0 | AP19: =IF(B19="","",IF(H19="Lost","Lost",IF(H19="Inactive","Dormant",IF(AA19="","Dormant",IF(AB19>InactiveClientDays*2,"Dormant",IF(AB19>InactiveClientDays,"At risk",IF(AC19="","Slipping",IF(Y19>=10,"Loyal","Steady")))))))) -> 0 | AQ19: =IF(OR(B19="",AP19="Lost",AP19="Dormant"),"",IF(OR(AP19="At risk",AP19="Slipping"),IF(AB19="",999,AB19),"")) -> 0 | AR19: =IF(AQ19="","",COUNTIFS($AQ$5:$AQ$204,">"&AQ19)+COUNTIFS($AQ$5:AQ19,AQ19)) -> 0 | AS19: =IF(B19="","",IF(AF19>0.5,"Chase - "&TEXT(AF19,"0")&" owing",IF(AND(H19<>"Lost",H19<>"Inactive",H19<>"Paused",AC19="",K19<>"One-off"),"Book - nothing in the diary",IF(AND(S19<>"",S19-TodayDate<=RenewalWarningDays,S19>=TodayDate),"Due - contract renews soon",IF(AP19="At risk","Call - going quiet",IF(AL19>=2,"Check - complaints logged",IF(AND(AI19<>"",AI19<MarginFloor,Y19>0),"Check - thin margin","OK"))))))) -> 0
A20: =IF(B20="","",ClientPrefix&TEXT(ROW()-4,"0000")) -> 0 | W20: =IF(A20="","",COUNTIFS(Properties!$C$5:$C$254,A20)) -> 0 | X20: =IF(A20="","",COUNTIFS(Jobs!$G$5:$G$604,A20)) -> 0 | Y20: =IF(A20="","",COUNTIFS(Jobs!$G$5:$G$604,A20,Jobs!$P$5:$P$604,"Completed")+COUNTIFS(Jobs!$G$5:$G$604,A20,Jobs!$P$5:$P$604,"Invoiced")) -> 0 | Z20: =IF(A20="","",COUNTIFS(Jobs!$G$5:$G$604,A20,Jobs!$P$5:$P$604,"Cancelled")+COUNTIFS(Jobs!$G$5:$G$604,A20,Jobs!$P$5:$P$604,"No access")) -> 0 | AA20: =IF(A20="","",IF(SUMPRODUCT(MAX((Jobs!$G$5:$G$604=A20)*((Jobs!$P$5:$P$604="Completed")+(Jobs!$P$5:$P$604="Invoiced"))*Jobs!$B$5:$B$604))=0,"",SUMPRODUCT(MAX((Jobs!$G$5:$G$604=A20)*((Jobs!$P$5:$P$604="Completed")+(Jobs!$P$5:$P$604="Invoiced"))*Jobs!$B$5:$B$604)))) -> 0 | AB20: =IF(AA20="","",TodayDate-AA20) -> 0 | AC20: =IF(A20="","",IF(SUMPRODUCT(MIN((Jobs!$G$5:$G$604=A20)*(Jobs!$B$5:$B$604>=TodayDate)*(Jobs!$P$5:$P$604<>"Cancelled")*Jobs!$B$5:$B$604+(1-(Jobs!$G$5:$G$604=A20)*(Jobs!$B$5:$B$604>=TodayDate)*(Jobs!$P$5:$P$604<>"Cancelled"))*2958465))=2958465,"",SUMPRODUCT(MIN((Jobs!$G$5:$G$604=A20)*(Jobs!$B$5:$B$604>=TodayDate)*(Jobs!$P$5:$P$604<>"Cancelled")*Jobs!$B$5:$B$604+(1-(Jobs!$G$5:$G$604=A20)*(Jobs!$B$5:$B$604>=TodayDate)*(Jobs!$P$5:$P$604<>"Cancelled"))*2958465)))) -> 0 | AD20: =IF(A20="","",SUMIFS(Invoices!$V$5:$V$404,Invoices!$D$5:$D$404,A20)) -> 0 | AE20: =IF(A20="","",SUMIFS(Invoices!$W$5:$W$404,Invoices!$D$5:$D$404,A20)) -> 0 | AF20: =IF(A20="","",AD20-AE20) -> 0 | AG20: =IF(OR(A20="",Y20=0),"",AD20/Y20) -> 0 | AH20: =IF(A20="","",SUMIFS('Job Costing'!$U$5:$U$604,'Job Costing'!$D$5:$D$604,A20)) -> 0 | AI20: =IF(OR(A20="",AD20=0),"",AH20/AD20) -> 0 | AJ20: =IF(OR(A20="",K20="",AG20=""),"",AG20*IFERROR(INDEX(FreqPerYear,MATCH(K20,FreqNames,0)),1)) -> 0 | AK20: =IF(A20="","",IFERROR(AVERAGEIFS(Jobs!$AA$5:$AA$604,Jobs!$G$5:$G$604,A20,Jobs!$AA$5:$AA$604,">0"),"")) -> 0 | AL20: =IF(A20="","",COUNTIFS(Complaints!$D$5:$D$84,A20)) -> 0 | AM20: =IF(B20="","",COUNTIFS($AD$5:$AD$204,">"&AD20)+COUNTIFS($AD$5:AD20,AD20)) -> 0 | AN20: =IF(B20="","",COUNTIFS($AH$5:$AH$204,">"&AH20)+COUNTIFS($AH$5:AH20,AH20)) -> 0 | AO20: =IF(B20="","",COUNTIFS($AJ$5:$AJ$204,">"&AJ20)+COUNTIFS($AJ$5:AJ20,AJ20)) -> 0 | AP20: =IF(B20="","",IF(H20="Lost","Lost",IF(H20="Inactive","Dormant",IF(AA20="","Dormant",IF(AB20>InactiveClientDays*2,"Dormant",IF(AB20>InactiveClientDays,"At risk",IF(AC20="","Slipping",IF(Y20>=10,"Loyal","Steady")))))))) -> 0 | AQ20: =IF(OR(B20="",AP20="Lost",AP20="Dormant"),"",IF(OR(AP20="At risk",AP20="Slipping"),IF(AB20="",999,AB20),"")) -> 0 | AR20: =IF(AQ20="","",COUNTIFS($AQ$5:$AQ$204,">"&AQ20)+COUNTIFS($AQ$5:AQ20,AQ20)) -> 0 | AS20: =IF(B20="","",IF(AF20>0.5,"Chase - "&TEXT(AF20,"0")&" owing",IF(AND(H20<>"Lost",H20<>"Inactive",H20<>"Paused",AC20="",K20<>"One-off"),"Book - nothing in the diary",IF(AND(S20<>"",S20-TodayDate<=RenewalWarningDays,S20>=TodayDate),"Due - contract renews soon",IF(AP20="At risk","Call - going quiet",IF(AL20>=2,"Check - complaints logged",IF(AND(AI20<>"",AI20<MarginFloor,Y20>0),"Check - thin margin","OK"))))))) -> 0
A21: =IF(B21="","",ClientPrefix&TEXT(ROW()-4,"0000")) -> 0 | W21: =IF(A21="","",COUNTIFS(Properties!$C$5:$C$254,A21)) -> 0 | X21: =IF(A21="","",COUNTIFS(Jobs!$G$5:$G$604,A21)) -> 0 | Y21: =IF(A21="","",COUNTIFS(Jobs!$G$5:$G$604,A21,Jobs!$P$5:$P$604,"Completed")+COUNTIFS(Jobs!$G$5:$G$604,A21,Jobs!$P$5:$P$604,"Invoiced")) -> 0 | Z21: =IF(A21="","",COUNTIFS(Jobs!$G$5:$G$604,A21,Jobs!$P$5:$P$604,"Cancelled")+COUNTIFS(Jobs!$G$5:$G$604,A21,Jobs!$P$5:$P$604,"No access")) -> 0 | AA21: =IF(A21="","",IF(SUMPRODUCT(MAX((Jobs!$G$5:$G$604=A21)*((Jobs!$P$5:$P$604="Completed")+(Jobs!$P$5:$P$604="Invoiced"))*Jobs!$B$5:$B$604))=0,"",SUMPRODUCT(MAX((Jobs!$G$5:$G$604=A21)*((Jobs!$P$5:$P$604="Completed")+(Jobs!$P$5:$P$604="Invoiced"))*Jobs!$B$5:$B$604)))) -> 0 | AB21: =IF(AA21="","",TodayDate-AA21) -> 0 | AC21: =IF(A21="","",IF(SUMPRODUCT(MIN((Jobs!$G$5:$G$604=A21)*(Jobs!$B$5:$B$604>=TodayDate)*(Jobs!$P$5:$P$604<>"Cancelled")*Jobs!$B$5:$B$604+(1-(Jobs!$G$5:$G$604=A21)*(Jobs!$B$5:$B$604>=TodayDate)*(Jobs!$P$5:$P$604<>"Cancelled"))*2958465))=2958465,"",SUMPRODUCT(MIN((Jobs!$G$5:$G$604=A21)*(Jobs!$B$5:$B$604>=TodayDate)*(Jobs!$P$5:$P$604<>"Cancelled")*Jobs!$B$5:$B$604+(1-(Jobs!$G$5:$G$604=A21)*(Jobs!$B$5:$B$604>=TodayDate)*(Jobs!$P$5:$P$604<>"Cancelled"))*2958465)))) -> 0 | AD21: =IF(A21="","",SUMIFS(Invoices!$V$5:$V$404,Invoices!$D$5:$D$404,A21)) -> 0 | AE21: =IF(A21="","",SUMIFS(Invoices!$W$5:$W$404,Invoices!$D$5:$D$404,A21)) -> 0 | AF21: =IF(A21="","",AD21-AE21) -> 0 | AG21: =IF(OR(A21="",Y21=0),"",AD21/Y21) -> 0 | AH21: =IF(A21="","",SUMIFS('Job Costing'!$U$5:$U$604,'Job Costing'!$D$5:$D$604,A21)) -> 0 | AI21: =IF(OR(A21="",AD21=0),"",AH21/AD21) -> 0 | AJ21: =IF(OR(A21="",K21="",AG21=""),"",AG21*IFERROR(INDEX(FreqPerYear,MATCH(K21,FreqNames,0)),1)) -> 0 | AK21: =IF(A21="","",IFERROR(AVERAGEIFS(Jobs!$AA$5:$AA$604,Jobs!$G$5:$G$604,A21,Jobs!$AA$5:$AA$604,">0"),"")) -> 0 | AL21: =IF(A21="","",COUNTIFS(Complaints!$D$5:$D$84,A21)) -> 0 | AM21: =IF(B21="","",COUNTIFS($AD$5:$AD$204,">"&AD21)+COUNTIFS($AD$5:AD21,AD21)) -> 0 | AN21: =IF(B21="","",COUNTIFS($AH$5:$AH$204,">"&AH21)+COUNTIFS($AH$5:AH21,AH21)) -> 0 | AO21: =IF(B21="","",COUNTIFS($AJ$5:$AJ$204,">"&AJ21)+COUNTIFS($AJ$5:AJ21,AJ21)) -> 0 | AP21: =IF(B21="","",IF(H21="Lost","Lost",IF(H21="Inactive","Dormant",IF(AA21="","Dormant",IF(AB21>InactiveClientDays*2,"Dormant",IF(AB21>InactiveClientDays,"At risk",IF(AC21="","Slipping",IF(Y21>=10,"Loyal","Steady")))))))) -> 0 | AQ21: =IF(OR(B21="",AP21="Lost",AP21="Dormant"),"",IF(OR(AP21="At risk",AP21="Slipping"),IF(AB21="",999,AB21),"")) -> 0 | AR21: =IF(AQ21="","",COUNTIFS($AQ$5:$AQ$204,">"&AQ21)+COUNTIFS($AQ$5:AQ21,AQ21)) -> 0 | AS21: =IF(B21="","",IF(AF21>0.5,"Chase - "&TEXT(AF21,"0")&" owing",IF(AND(H21<>"Lost",H21<>"Inactive",H21<>"Paused",AC21="",K21<>"One-off"),"Book - nothing in the diary",IF(AND(S21<>"",S21-TodayDate<=RenewalWarningDays,S21>=TodayDate),"Due - contract renews soon",IF(AP21="At risk","Call - going quiet",IF(AL21>=2,"Check - complaints logged",IF(AND(AI21<>"",AI21<MarginFloor,Y21>0),"Check - thin margin","OK"))))))) -> 0
A22: =IF(B22="","",ClientPrefix&TEXT(ROW()-4,"0000")) -> 0 | W22: =IF(A22="","",COUNTIFS(Properties!$C$5:$C$254,A22)) -> 0 | X22: =IF(A22="","",COUNTIFS(Jobs!$G$5:$G$604,A22)) -> 0 | Y22: =IF(A22="","",COUNTIFS(Jobs!$G$5:$G$604,A22,Jobs!$P$5:$P$604,"Completed")+COUNTIFS(Jobs!$G$5:$G$604,A22,Jobs!$P$5:$P$604,"Invoiced")) -> 0 | Z22: =IF(A22="","",COUNTIFS(Jobs!$G$5:$G$604,A22,Jobs!$P$5:$P$604,"Cancelled")+COUNTIFS(Jobs!$G$5:$G$604,A22,Jobs!$P$5:$P$604,"No access")) -> 0 | AA22: =IF(A22="","",IF(SUMPRODUCT(MAX((Jobs!$G$5:$G$604=A22)*((Jobs!$P$5:$P$604="Completed")+(Jobs!$P$5:$P$604="Invoiced"))*Jobs!$B$5:$B$604))=0,"",SUMPRODUCT(MAX((Jobs!$G$5:$G$604=A22)*((Jobs!$P$5:$P$604="Completed")+(Jobs!$P$5:$P$604="Invoiced"))*Jobs!$B$5:$B$604)))) -> 0 | AB22: =IF(AA22="","",TodayDate-AA22) -> 0 | AC22: =IF(A22="","",IF(SUMPRODUCT(MIN((Jobs!$G$5:$G$604=A22)*(Jobs!$B$5:$B$604>=TodayDate)*(Jobs!$P$5:$P$604<>"Cancelled")*Jobs!$B$5:$B$604+(1-(Jobs!$G$5:$G$604=A22)*(Jobs!$B$5:$B$604>=TodayDate)*(Jobs!$P$5:$P$604<>"Cancelled"))*2958465))=2958465,"",SUMPRODUCT(MIN((Jobs!$G$5:$G$604=A22)*(Jobs!$B$5:$B$604>=TodayDate)*(Jobs!$P$5:$P$604<>"Cancelled")*Jobs!$B$5:$B$604+(1-(Jobs!$G$5:$G$604=A22)*(Jobs!$B$5:$B$604>=TodayDate)*(Jobs!$P$5:$P$604<>"Cancelled"))*2958465)))) -> 0 | AD22: =IF(A22="","",SUMIFS(Invoices!$V$5:$V$404,Invoices!$D$5:$D$404,A22)) -> 0 | AE22: =IF(A22="","",SUMIFS(Invoices!$W$5:$W$404,Invoices!$D$5:$D$404,A22)) -> 0 | AF22: =IF(A22="","",AD22-AE22) -> 0 | AG22: =IF(OR(A22="",Y22=0),"",AD22/Y22) -> 0 | AH22: =IF(A22="","",SUMIFS('Job Costing'!$U$5:$U$604,'Job Costing'!$D$5:$D$604,A22)) -> 0 | AI22: =IF(OR(A22="",AD22=0),"",AH22/AD22) -> 0 | AJ22: =IF(OR(A22="",K22="",AG22=""),"",AG22*IFERROR(INDEX(FreqPerYear,MATCH(K22,FreqNames,0)),1)) -> 0 | AK22: =IF(A22="","",IFERROR(AVERAGEIFS(Jobs!$AA$5:$AA$604,Jobs!$G$5:$G$604,A22,Jobs!$AA$5:$AA$604,">0"),"")) -> 0 | AL22: =IF(A22="","",COUNTIFS(Complaints!$D$5:$D$84,A22)) -> 0 | AM22: =IF(B22="","",COUNTIFS($AD$5:$AD$204,">"&AD22)+COUNTIFS($AD$5:AD22,AD22)) -> 0 | AN22: =IF(B22="","",COUNTIFS($AH$5:$AH$204,">"&AH22)+COUNTIFS($AH$5:AH22,AH22)) -> 0 | AO22: =IF(B22="","",COUNTIFS($AJ$5:$AJ$204,">"&AJ22)+COUNTIFS($AJ$5:AJ22,AJ22)) -> 0 | AP22: =IF(B22="","",IF(H22="Lost","Lost",IF(H22="Inactive","Dormant",IF(AA22="","Dormant",IF(AB22>InactiveClientDays*2,"Dormant",IF(AB22>InactiveClientDays,"At risk",IF(AC22="","Slipping",IF(Y22>=10,"Loyal","Steady")))))))) -> 0 | AQ22: =IF(OR(B22="",AP22="Lost",AP22="Dormant"),"",IF(OR(AP22="At risk",AP22="Slipping"),IF(AB22="",999,AB22),"")) -> 0 | AR22: =IF(AQ22="","",COUNTIFS($AQ$5:$AQ$204,">"&AQ22)+COUNTIFS($AQ$5:AQ22,AQ22)) -> 0 | AS22: =IF(B22="","",IF(AF22>0.5,"Chase - "&TEXT(AF22,"0")&" owing",IF(AND(H22<>"Lost",H22<>"Inactive",H22<>"Paused",AC22="",K22<>"One-off"),"Book - nothing in the diary",IF(AND(S22<>"",S22-TodayDate<=RenewalWarningDays,S22>=TodayDate),"Due - contract renews soon",IF(AP22="At risk","Call - going quiet",IF(AL22>=2,"Check - complaints logged",IF(AND(AI22<>"",AI22<MarginFloor,Y22>0),"Check - thin margin","OK"))))))) -> 0
A23: =IF(B23="","",ClientPrefix&TEXT(ROW()-4,"0000")) -> 0 | W23: =IF(A23="","",COUNTIFS(Properties!$C$5:$C$254,A23)) -> 0 | X23: =IF(A23="","",COUNTIFS(Jobs!$G$5:$G$604,A23)) -> 0 | Y23: =IF(A23="","",COUNTIFS(Jobs!$G$5:$G$604,A23,Jobs!$P$5:$P$604,"Completed")+COUNTIFS(Jobs!$G$5:$G$604,A23,Jobs!$P$5:$P$604,"Invoiced")) -> 0 | Z23: =IF(A23="","",COUNTIFS(Jobs!$G$5:$G$604,A23,Jobs!$P$5:$P$604,"Cancelled")+COUNTIFS(Jobs!$G$5:$G$604,A23,Jobs!$P$5:$P$604,"No access")) -> 0 | AA23: =IF(A23="","",IF(SUMPRODUCT(MAX((Jobs!$G$5:$G$604=A23)*((Jobs!$P$5:$P$604="Completed")+(Jobs!$P$5:$P$604="Invoiced"))*Jobs!$B$5:$B$604))=0,"",SUMPRODUCT(MAX((Jobs!$G$5:$G$604=A23)*((Jobs!$P$5:$P$604="Completed")+(Jobs!$P$5:$P$604="Invoiced"))*Jobs!$B$5:$B$604)))) -> 0 | AB23: =IF(AA23="","",TodayDate-AA23) -> 0 | AC23: =IF(A23="","",IF(SUMPRODUCT(MIN((Jobs!$G$5:$G$604=A23)*(Jobs!$B$5:$B$604>=TodayDate)*(Jobs!$P$5:$P$604<>"Cancelled")*Jobs!$B$5:$B$604+(1-(Jobs!$G$5:$G$604=A23)*(Jobs!$B$5:$B$604>=TodayDate)*(Jobs!$P$5:$P$604<>"Cancelled"))*2958465))=2958465,"",SUMPRODUCT(MIN((Jobs!$G$5:$G$604=A23)*(Jobs!$B$5:$B$604>=TodayDate)*(Jobs!$P$5:$P$604<>"Cancelled")*Jobs!$B$5:$B$604+(1-(Jobs!$G$5:$G$604=A23)*(Jobs!$B$5:$B$604>=TodayDate)*(Jobs!$P$5:$P$604<>"Cancelled"))*2958465)))) -> 0 | AD23: =IF(A23="","",SUMIFS(Invoices!$V$5:$V$404,Invoices!$D$5:$D$404,A23)) -> 0 | AE23: =IF(A23="","",SUMIFS(Invoices!$W$5:$W$404,Invoices!$D$5:$D$404,A23)) -> 0 | AF23: =IF(A23="","",AD23-AE23) -> 0 | AG23: =IF(OR(A23="",Y23=0),"",AD23/Y23) -> 0 | AH23: =IF(A23="","",SUMIFS('Job Costing'!$U$5:$U$604,'Job Costing'!$D$5:$D$604,A23)) -> 0 | AI23: =IF(OR(A23="",AD23=0),"",AH23/AD23) -> 0 | AJ23: =IF(OR(A23="",K23="",AG23=""),"",AG23*IFERROR(INDEX(FreqPerYear,MATCH(K23,FreqNames,0)),1)) -> 0 | AK23: =IF(A23="","",IFERROR(AVERAGEIFS(Jobs!$AA$5:$AA$604,Jobs!$G$5:$G$604,A23,Jobs!$AA$5:$AA$604,">0"),"")) -> 0 | AL23: =IF(A23="","",COUNTIFS(Complaints!$D$5:$D$84,A23)) -> 0 | AM23: =IF(B23="","",COUNTIFS($AD$5:$AD$204,">"&AD23)+COUNTIFS($AD$5:AD23,AD23)) -> 0 | AN23: =IF(B23="","",COUNTIFS($AH$5:$AH$204,">"&AH23)+COUNTIFS($AH$5:AH23,AH23)) -> 0 | AO23: =IF(B23="","",COUNTIFS($AJ$5:$AJ$204,">"&AJ23)+COUNTIFS($AJ$5:AJ23,AJ23)) -> 0 | AP23: =IF(B23="","",IF(H23="Lost","Lost",IF(H23="Inactive","Dormant",IF(AA23="","Dormant",IF(AB23>InactiveClientDays*2,"Dormant",IF(AB23>InactiveClientDays,"At risk",IF(AC23="","Slipping",IF(Y23>=10,"Loyal","Steady")))))))) -> 0 | AQ23: =IF(OR(B23="",AP23="Lost",AP23="Dormant"),"",IF(OR(AP23="At risk",AP23="Slipping"),IF(AB23="",999,AB23),"")) -> 0 | AR23: =IF(AQ23="","",COUNTIFS($AQ$5:$AQ$204,">"&AQ23)+COUNTIFS($AQ$5:AQ23,AQ23)) -> 0 | AS23: =IF(B23="","",IF(AF23>0.5,"Chase - "&TEXT(AF23,"0")&" owing",IF(AND(H23<>"Lost",H23<>"Inactive",H23<>"Paused",AC23="",K23<>"One-off"),"Book - nothing in the diary",IF(AND(S23<>"",S23-TodayDate<=RenewalWarningDays,S23>=TodayDate),"Due - contract renews soon",IF(AP23="At risk","Call - going quiet",IF(AL23>=2,"Check - complaints logged",IF(AND(AI23<>"",AI23<MarginFloor,Y23>0),"Check - thin margin","OK"))))))) -> 0
A24: =IF(B24="","",ClientPrefix&TEXT(ROW()-4,"0000")) -> 0 | W24: =IF(A24="","",COUNTIFS(Properties!$C$5:$C$254,A24)) -> 0 | X24: =IF(A24="","",COUNTIFS(Jobs!$G$5:$G$604,A24)) -> 0 | Y24: =IF(A24="","",COUNTIFS(Jobs!$G$5:$G$604,A24,Jobs!$P$5:$P$604,"Completed")+COUNTIFS(Jobs!$G$5:$G$604,A24,Jobs!$P$5:$P$604,"Invoiced")) -> 0 | Z24: =IF(A24="","",COUNTIFS(Jobs!$G$5:$G$604,A24,Jobs!$P$5:$P$604,"Cancelled")+COUNTIFS(Jobs!$G$5:$G$604,A24,Jobs!$P$5:$P$604,"No access")) -> 0 | AA24: =IF(A24="","",IF(SUMPRODUCT(MAX((Jobs!$G$5:$G$604=A24)*((Jobs!$P$5:$P$604="Completed")+(Jobs!$P$5:$P$604="Invoiced"))*Jobs!$B$5:$B$604))=0,"",SUMPRODUCT(MAX((Jobs!$G$5:$G$604=A24)*((Jobs!$P$5:$P$604="Completed")+(Jobs!$P$5:$P$604="Invoiced"))*Jobs!$B$5:$B$604)))) -> 0 | AB24: =IF(AA24="","",TodayDate-AA24) -> 0 | AC24: =IF(A24="","",IF(SUMPRODUCT(MIN((Jobs!$G$5:$G$604=A24)*(Jobs!$B$5:$B$604>=TodayDate)*(Jobs!$P$5:$P$604<>"Cancelled")*Jobs!$B$5:$B$604+(1-(Jobs!$G$5:$G$604=A24)*(Jobs!$B$5:$B$604>=TodayDate)*(Jobs!$P$5:$P$604<>"Cancelled"))*2958465))=2958465,"",SUMPRODUCT(MIN((Jobs!$G$5:$G$604=A24)*(Jobs!$B$5:$B$604>=TodayDate)*(Jobs!$P$5:$P$604<>"Cancelled")*Jobs!$B$5:$B$604+(1-(Jobs!$G$5:$G$604=A24)*(Jobs!$B$5:$B$604>=TodayDate)*(Jobs!$P$5:$P$604<>"Cancelled"))*2958465)))) -> 0 | AD24: =IF(A24="","",SUMIFS(Invoices!$V$5:$V$404,Invoices!$D$5:$D$404,A24)) -> 0 | AE24: =IF(A24="","",SUMIFS(Invoices!$W$5:$W$404,Invoices!$D$5:$D$404,A24)) -> 0 | AF24: =IF(A24="","",AD24-AE24) -> 0 | AG24: =IF(OR(A24="",Y24=0),"",AD24/Y24) -> 0 | AH24: =IF(A24="","",SUMIFS('Job Costing'!$U$5:$U$604,'Job Costing'!$D$5:$D$604,A24)) -> 0 | AI24: =IF(OR(A24="",AD24=0),"",AH24/AD24) -> 0 | AJ24: =IF(OR(A24="",K24="",AG24=""),"",AG24*IFERROR(INDEX(FreqPerYear,MATCH(K24,FreqNames,0)),1)) -> 0 | AK24: =IF(A24="","",IFERROR(AVERAGEIFS(Jobs!$AA$5:$AA$604,Jobs!$G$5:$G$604,A24,Jobs!$AA$5:$AA$604,">0"),"")) -> 0 | AL24: =IF(A24="","",COUNTIFS(Complaints!$D$5:$D$84,A24)) -> 0 | AM24: =IF(B24="","",COUNTIFS($AD$5:$AD$204,">"&AD24)+COUNTIFS($AD$5:AD24,AD24)) -> 0 | AN24: =IF(B24="","",COUNTIFS($AH$5:$AH$204,">"&AH24)+COUNTIFS($AH$5:AH24,AH24)) -> 0 | AO24: =IF(B24="","",COUNTIFS($AJ$5:$AJ$204,">"&AJ24)+COUNTIFS($AJ$5:AJ24,AJ24)) -> 0 | AP24: =IF(B24="","",IF(H24="Lost","Lost",IF(H24="Inactive","Dormant",IF(AA24="","Dormant",IF(AB24>InactiveClientDays*2,"Dormant",IF(AB24>InactiveClientDays,"At risk",IF(AC24="","Slipping",IF(Y24>=10,"Loyal","Steady")))))))) -> 0 | AQ24: =IF(OR(B24="",AP24="Lost",AP24="Dormant"),"",IF(OR(AP24="At risk",AP24="Slipping"),IF(AB24="",999,AB24),"")) -> 0 | AR24: =IF(AQ24="","",COUNTIFS($AQ$5:$AQ$204,">"&AQ24)+COUNTIFS($AQ$5:AQ24,AQ24)) -> 0 | AS24: =IF(B24="","",IF(AF24>0.5,"Chase - "&TEXT(AF24,"0")&" owing",IF(AND(H24<>"Lost",H24<>"Inactive",H24<>"Paused",AC24="",K24<>"One-off"),"Book - nothing in the diary",IF(AND(S24<>"",S24-TodayDate<=RenewalWarningDays,S24>=TodayDate),"Due - contract renews soon",IF(AP24="At risk","Call - going quiet",IF(AL24>=2,"Check - complaints logged",IF(AND(AI24<>"",AI24<MarginFloor,Y24>0),"Check - thin margin","OK"))))))) -> 0
A25: =IF(B25="","",ClientPrefix&TEXT(ROW()-4,"0000")) -> 0 | W25: =IF(A25="","",COUNTIFS(Properties!$C$5:$C$254,A25)) -> 0 | X25: =IF(A25="","",COUNTIFS(Jobs!$G$5:$G$604,A25)) -> 0 | Y25: =IF(A25="","",COUNTIFS(Jobs!$G$5:$G$604,A25,Jobs!$P$5:$P$604,"Completed")+COUNTIFS(Jobs!$G$5:$G$604,A25,Jobs!$P$5:$P$604,"Invoiced")) -> 0 | Z25: =IF(A25="","",COUNTIFS(Jobs!$G$5:$G$604,A25,Jobs!$P$5:$P$604,"Cancelled")+COUNTIFS(Jobs!$G$5:$G$604,A25,Jobs!$P$5:$P$604,"No access")) -> 0 | AA25: =IF(A25="","",IF(SUMPRODUCT(MAX((Jobs!$G$5:$G$604=A25)*((Jobs!$P$5:$P$604="Completed")+(Jobs!$P$5:$P$604="Invoiced"))*Jobs!$B$5:$B$604))=0,"",SUMPRODUCT(MAX((Jobs!$G$5:$G$604=A25)*((Jobs!$P$5:$P$604="Completed")+(Jobs!$P$5:$P$604="Invoiced"))*Jobs!$B$5:$B$604)))) -> 0 | AB25: =IF(AA25="","",TodayDate-AA25) -> 0 | AC25: =IF(A25="","",IF(SUMPRODUCT(MIN((Jobs!$G$5:$G$604=A25)*(Jobs!$B$5:$B$604>=TodayDate)*(Jobs!$P$5:$P$604<>"Cancelled")*Jobs!$B$5:$B$604+(1-(Jobs!$G$5:$G$604=A25)*(Jobs!$B$5:$B$604>=TodayDate)*(Jobs!$P$5:$P$604<>"Cancelled"))*2958465))=2958465,"",SUMPRODUCT(MIN((Jobs!$G$5:$G$604=A25)*(Jobs!$B$5:$B$604>=TodayDate)*(Jobs!$P$5:$P$604<>"Cancelled")*Jobs!$B$5:$B$604+(1-(Jobs!$G$5:$G$604=A25)*(Jobs!$B$5:$B$604>=TodayDate)*(Jobs!$P$5:$P$604<>"Cancelled"))*2958465)))) -> 0 | AD25: =IF(A25="","",SUMIFS(Invoices!$V$5:$V$404,Invoices!$D$5:$D$404,A25)) -> 0 | AE25: =IF(A25="","",SUMIFS(Invoices!$W$5:$W$404,Invoices!$D$5:$D$404,A25)) -> 0 | AF25: =IF(A25="","",AD25-AE25) -> 0 | AG25: =IF(OR(A25="",Y25=0),"",AD25/Y25) -> 0 | AH25: =IF(A25="","",SUMIFS('Job Costing'!$U$5:$U$604,'Job Costing'!$D$5:$D$604,A25)) -> 0 | AI25: =IF(OR(A25="",AD25=0),"",AH25/AD25) -> 0 | AJ25: =IF(OR(A25="",K25="",AG25=""),"",AG25*IFERROR(INDEX(FreqPerYear,MATCH(K25,FreqNames,0)),1)) -> 0 | AK25: =IF(A25="","",IFERROR(AVERAGEIFS(Jobs!$AA$5:$AA$604,Jobs!$G$5:$G$604,A25,Jobs!$AA$5:$AA$604,">0"),"")) -> 0 | AL25: =IF(A25="","",COUNTIFS(Complaints!$D$5:$D$84,A25)) -> 0 | AM25: =IF(B25="","",COUNTIFS($AD$5:$AD$204,">"&AD25)+COUNTIFS($AD$5:AD25,AD25)) -> 0 | AN25: =IF(B25="","",COUNTIFS($AH$5:$AH$204,">"&AH25)+COUNTIFS($AH$5:AH25,AH25)) -> 0 | AO25: =IF(B25="","",COUNTIFS($AJ$5:$AJ$204,">"&AJ25)+COUNTIFS($AJ$5:AJ25,AJ25)) -> 0 | AP25: =IF(B25="","",IF(H25="Lost","Lost",IF(H25="Inactive","Dormant",IF(AA25="","Dormant",IF(AB25>InactiveClientDays*2,"Dormant",IF(AB25>InactiveClientDays,"At risk",IF(AC25="","Slipping",IF(Y25>=10,"Loyal","Steady")))))))) -> 0 | AQ25: =IF(OR(B25="",AP25="Lost",AP25="Dormant"),"",IF(OR(AP25="At risk",AP25="Slipping"),IF(AB25="",999,AB25),"")) -> 0 | AR25: =IF(AQ25="","",COUNTIFS($AQ$5:$AQ$204,">"&AQ25)+COUNTIFS($AQ$5:AQ25,AQ25)) -> 0 | AS25: =IF(B25="","",IF(AF25>0.5,"Chase - "&TEXT(AF25,"0")&" owing",IF(AND(H25<>"Lost",H25<>"Inactive",H25<>"Paused",AC25="",K25<>"One-off"),"Book - nothing in the diary",IF(AND(S25<>"",S25-TodayDate<=RenewalWarningDays,S25>=TodayDate),"Due - contract renews soon",IF(AP25="At risk","Call - going quiet",IF(AL25>=2,"Check - complaints logged",IF(AND(AI25<>"",AI25<MarginFloor,Y25>0),"Check - thin margin","OK"))))))) -> 0
A26: =IF(B26="","",ClientPrefix&TEXT(ROW()-4,"0000")) -> 0 | W26: =IF(A26="","",COUNTIFS(Properties!$C$5:$C$254,A26)) -> 0 | X26: =IF(A26="","",COUNTIFS(Jobs!$G$5:$G$604,A26)) -> 0 | Y26: =IF(A26="","",COUNTIFS(Jobs!$G$5:$G$604,A26,Jobs!$P$5:$P$604,"Completed")+COUNTIFS(Jobs!$G$5:$G$604,A26,Jobs!$P$5:$P$604,"Invoiced")) -> 0 | Z26: =IF(A26="","",COUNTIFS(Jobs!$G$5:$G$604,A26,Jobs!$P$5:$P$604,"Cancelled")+COUNTIFS(Jobs!$G$5:$G$604,A26,Jobs!$P$5:$P$604,"No access")) -> 0 | AA26: =IF(A26="","",IF(SUMPRODUCT(MAX((Jobs!$G$5:$G$604=A26)*((Jobs!$P$5:$P$604="Completed")+(Jobs!$P$5:$P$604="Invoiced"))*Jobs!$B$5:$B$604))=0,"",SUMPRODUCT(MAX((Jobs!$G$5:$G$604=A26)*((Jobs!$P$5:$P$604="Completed")+(Jobs!$P$5:$P$604="Invoiced"))*Jobs!$B$5:$B$604)))) -> 0 | AB26: =IF(AA26="","",TodayDate-AA26) -> 0 | AC26: =IF(A26="","",IF(SUMPRODUCT(MIN((Jobs!$G$5:$G$604=A26)*(Jobs!$B$5:$B$604>=TodayDate)*(Jobs!$P$5:$P$604<>"Cancelled")*Jobs!$B$5:$B$604+(1-(Jobs!$G$5:$G$604=A26)*(Jobs!$B$5:$B$604>=TodayDate)*(Jobs!$P$5:$P$604<>"Cancelled"))*2958465))=2958465,"",SUMPRODUCT(MIN((Jobs!$G$5:$G$604=A26)*(Jobs!$B$5:$B$604>=TodayDate)*(Jobs!$P$5:$P$604<>"Cancelled")*Jobs!$B$5:$B$604+(1-(Jobs!$G$5:$G$604=A26)*(Jobs!$B$5:$B$604>=TodayDate)*(Jobs!$P$5:$P$604<>"Cancelled"))*2958465)))) -> 0 | AD26: =IF(A26="","",SUMIFS(Invoices!$V$5:$V$404,Invoices!$D$5:$D$404,A26)) -> 0 | AE26: =IF(A26="","",SUMIFS(Invoices!$W$5:$W$404,Invoices!$D$5:$D$404,A26)) -> 0 | AF26: =IF(A26="","",AD26-AE26) -> 0 | AG26: =IF(OR(A26="",Y26=0),"",AD26/Y26) -> 0 | AH26: =IF(A26="","",SUMIFS('Job Costing'!$U$5:$U$604,'Job Costing'!$D$5:$D$604,A26)) -> 0 | AI26: =IF(OR(A26="",AD26=0),"",AH26/AD26) -> 0 | AJ26: =IF(OR(A26="",K26="",AG26=""),"",AG26*IFERROR(INDEX(FreqPerYear,MATCH(K26,FreqNames,0)),1)) -> 0 | AK26: =IF(A26="","",IFERROR(AVERAGEIFS(Jobs!$AA$5:$AA$604,Jobs!$G$5:$G$604,A26,Jobs!$AA$5:$AA$604,">0"),"")) -> 0 | AL26: =IF(A26="","",COUNTIFS(Complaints!$D$5:$D$84,A26)) -> 0 | AM26: =IF(B26="","",COUNTIFS($AD$5:$AD$204,">"&AD26)+COUNTIFS($AD$5:AD26,AD26)) -> 0 | AN26: =IF(B26="","",COUNTIFS($AH$5:$AH$204,">"&AH26)+COUNTIFS($AH$5:AH26,AH26)) -> 0 | AO26: =IF(B26="","",COUNTIFS($AJ$5:$AJ$204,">"&AJ26)+COUNTIFS($AJ$5:AJ26,AJ26)) -> 0 | AP26: =IF(B26="","",IF(H26="Lost","Lost",IF(H26="Inactive","Dormant",IF(AA26="","Dormant",IF(AB26>InactiveClientDays*2,"Dormant",IF(AB26>InactiveClientDays,"At risk",IF(AC26="","Slipping",IF(Y26>=10,"Loyal","Steady")))))))) -> 0 | AQ26: =IF(OR(B26="",AP26="Lost",AP26="Dormant"),"",IF(OR(AP26="At risk",AP26="Slipping"),IF(AB26="",999,AB26),"")) -> 0 | AR26: =IF(AQ26="","",COUNTIFS($AQ$5:$AQ$204,">"&AQ26)+COUNTIFS($AQ$5:AQ26,AQ26)) -> 0 | AS26: =IF(B26="","",IF(AF26>0.5,"Chase - "&TEXT(AF26,"0")&" owing",IF(AND(H26<>"Lost",H26<>"Inactive",H26<>"Paused",AC26="",K26<>"One-off"),"Book - nothing in the diary",IF(AND(S26<>"",S26-TodayDate<=RenewalWarningDays,S26>=TodayDate),"Due - contract renews soon",IF(AP26="At risk","Call - going quiet",IF(AL26>=2,"Check - complaints logged",IF(AND(AI26<>"",AI26<MarginFloor,Y26>0),"Check - thin margin","OK"))))))) -> 0
A27: =IF(B27="","",ClientPrefix&TEXT(ROW()-4,"0000")) -> 0 | W27: =IF(A27="","",COUNTIFS(Properties!$C$5:$C$254,A27)) -> 0 | X27: =IF(A27="","",COUNTIFS(Jobs!$G$5:$G$604,A27)) -> 0 | Y27: =IF(A27="","",COUNTIFS(Jobs!$G$5:$G$604,A27,Jobs!$P$5:$P$604,"Completed")+COUNTIFS(Jobs!$G$5:$G$604,A27,Jobs!$P$5:$P$604,"Invoiced")) -> 0 | Z27: =IF(A27="","",COUNTIFS(Jobs!$G$5:$G$604,A27,Jobs!$P$5:$P$604,"Cancelled")+COUNTIFS(Jobs!$G$5:$G$604,A27,Jobs!$P$5:$P$604,"No access")) -> 0 | AA27: =IF(A27="","",IF(SUMPRODUCT(MAX((Jobs!$G$5:$G$604=A27)*((Jobs!$P$5:$P$604="Completed")+(Jobs!$P$5:$P$604="Invoiced"))*Jobs!$B$5:$B$604))=0,"",SUMPRODUCT(MAX((Jobs!$G$5:$G$604=A27)*((Jobs!$P$5:$P$604="Completed")+(Jobs!$P$5:$P$604="Invoiced"))*Jobs!$B$5:$B$604)))) -> 0 | AB27: =IF(AA27="","",TodayDate-AA27) -> 0 | AC27: =IF(A27="","",IF(SUMPRODUCT(MIN((Jobs!$G$5:$G$604=A27)*(Jobs!$B$5:$B$604>=TodayDate)*(Jobs!$P$5:$P$604<>"Cancelled")*Jobs!$B$5:$B$604+(1-(Jobs!$G$5:$G$604=A27)*(Jobs!$B$5:$B$604>=TodayDate)*(Jobs!$P$5:$P$604<>"Cancelled"))*2958465))=2958465,"",SUMPRODUCT(MIN((Jobs!$G$5:$G$604=A27)*(Jobs!$B$5:$B$604>=TodayDate)*(Jobs!$P$5:$P$604<>"Cancelled")*Jobs!$B$5:$B$604+(1-(Jobs!$G$5:$G$604=A27)*(Jobs!$B$5:$B$604>=TodayDate)*(Jobs!$P$5:$P$604<>"Cancelled"))*2958465)))) -> 0 | AD27: =IF(A27="","",SUMIFS(Invoices!$V$5:$V$404,Invoices!$D$5:$D$404,A27)) -> 0 | AE27: =IF(A27="","",SUMIFS(Invoices!$W$5:$W$404,Invoices!$D$5:$D$404,A27)) -> 0 | AF27: =IF(A27="","",AD27-AE27) -> 0 | AG27: =IF(OR(A27="",Y27=0),"",AD27/Y27) -> 0 | AH27: =IF(A27="","",SUMIFS('Job Costing'!$U$5:$U$604,'Job Costing'!$D$5:$D$604,A27)) -> 0 | AI27: =IF(OR(A27="",AD27=0),"",AH27/AD27) -> 0 | AJ27: =IF(OR(A27="",K27="",AG27=""),"",AG27*IFERROR(INDEX(FreqPerYear,MATCH(K27,FreqNames,0)),1)) -> 0 | AK27: =IF(A27="","",IFERROR(AVERAGEIFS(Jobs!$AA$5:$AA$604,Jobs!$G$5:$G$604,A27,Jobs!$AA$5:$AA$604,">0"),"")) -> 0 | AL27: =IF(A27="","",COUNTIFS(Complaints!$D$5:$D$84,A27)) -> 0 | AM27: =IF(B27="","",COUNTIFS($AD$5:$AD$204,">"&AD27)+COUNTIFS($AD$5:AD27,AD27)) -> 0 | AN27: =IF(B27="","",COUNTIFS($AH$5:$AH$204,">"&AH27)+COUNTIFS($AH$5:AH27,AH27)) -> 0 | AO27: =IF(B27="","",COUNTIFS($AJ$5:$AJ$204,">"&AJ27)+COUNTIFS($AJ$5:AJ27,AJ27)) -> 0 | AP27: =IF(B27="","",IF(H27="Lost","Lost",IF(H27="Inactive","Dormant",IF(AA27="","Dormant",IF(AB27>InactiveClientDays*2,"Dormant",IF(AB27>InactiveClientDays,"At risk",IF(AC27="","Slipping",IF(Y27>=10,"Loyal","Steady")))))))) -> 0 | AQ27: =IF(OR(B27="",AP27="Lost",AP27="Dormant"),"",IF(OR(AP27="At risk",AP27="Slipping"),IF(AB27="",999,AB27),"")) -> 0 | AR27: =IF(AQ27="","",COUNTIFS($AQ$5:$AQ$204,">"&AQ27)+COUNTIFS($AQ$5:AQ27,AQ27)) -> 0 | AS27: =IF(B27="","",IF(AF27>0.5,"Chase - "&TEXT(AF27,"0")&" owing",IF(AND(H27<>"Lost",H27<>"Inactive",H27<>"Paused",AC27="",K27<>"One-off"),"Book - nothing in the diary",IF(AND(S27<>"",S27-TodayDate<=RenewalWarningDays,S27>=TodayDate),"Due - contract renews soon",IF(AP27="At risk","Call - going quiet",IF(AL27>=2,"Check - complaints logged",IF(AND(AI27<>"",AI27<MarginFloor,Y27>0),"Check - thin margin","OK"))))))) -> 0
A28: =IF(B28="","",ClientPrefix&TEXT(ROW()-4,"0000")) -> 0 | W28: =IF(A28="","",COUNTIFS(Properties!$C$5:$C$254,A28)) -> 0 | X28: =IF(A28="","",COUNTIFS(Jobs!$G$5:$G$604,A28)) -> 0 | Y28: =IF(A28="","",COUNTIFS(Jobs!$G$5:$G$604,A28,Jobs!$P$5:$P$604,"Completed")+COUNTIFS(Jobs!$G$5:$G$604,A28,Jobs!$P$5:$P$604,"Invoiced")) -> 0 | Z28: =IF(A28="","",COUNTIFS(Jobs!$G$5:$G$604,A28,Jobs!$P$5:$P$604,"Cancelled")+COUNTIFS(Jobs!$G$5:$G$604,A28,Jobs!$P$5:$P$604,"No access")) -> 0 | AA28: =IF(A28="","",IF(SUMPRODUCT(MAX((Jobs!$G$5:$G$604=A28)*((Jobs!$P$5:$P$604="Completed")+(Jobs!$P$5:$P$604="Invoiced"))*Jobs!$B$5:$B$604))=0,"",SUMPRODUCT(MAX((Jobs!$G$5:$G$604=A28)*((Jobs!$P$5:$P$604="Completed")+(Jobs!$P$5:$P$604="Invoiced"))*Jobs!$B$5:$B$604)))) -> 0 | AB28: =IF(AA28="","",TodayDate-AA28) -> 0 | AC28: =IF(A28="","",IF(SUMPRODUCT(MIN((Jobs!$G$5:$G$604=A28)*(Jobs!$B$5:$B$604>=TodayDate)*(Jobs!$P$5:$P$604<>"Cancelled")*Jobs!$B$5:$B$604+(1-(Jobs!$G$5:$G$604=A28)*(Jobs!$B$5:$B$604>=TodayDate)*(Jobs!$P$5:$P$604<>"Cancelled"))*2958465))=2958465,"",SUMPRODUCT(MIN((Jobs!$G$5:$G$604=A28)*(Jobs!$B$5:$B$604>=TodayDate)*(Jobs!$P$5:$P$604<>"Cancelled")*Jobs!$B$5:$B$604+(1-(Jobs!$G$5:$G$604=A28)*(Jobs!$B$5:$B$604>=TodayDate)*(Jobs!$P$5:$P$604<>"Cancelled"))*2958465)))) -> 0 | AD28: =IF(A28="","",SUMIFS(Invoices!$V$5:$V$404,Invoices!$D$5:$D$404,A28)) -> 0 | AE28: =IF(A28="","",SUMIFS(Invoices!$W$5:$W$404,Invoices!$D$5:$D$404,A28)) -> 0 | AF28: =IF(A28="","",AD28-AE28) -> 0 | AG28: =IF(OR(A28="",Y28=0),"",AD28/Y28) -> 0 | AH28: =IF(A28="","",SUMIFS('Job Costing'!$U$5:$U$604,'Job Costing'!$D$5:$D$604,A28)) -> 0 | AI28: =IF(OR(A28="",AD28=0),"",AH28/AD28) -> 0 | AJ28: =IF(OR(A28="",K28="",AG28=""),"",AG28*IFERROR(INDEX(FreqPerYear,MATCH(K28,FreqNames,0)),1)) -> 0 | AK28: =IF(A28="","",IFERROR(AVERAGEIFS(Jobs!$AA$5:$AA$604,Jobs!$G$5:$G$604,A28,Jobs!$AA$5:$AA$604,">0"),"")) -> 0 | AL28: =IF(A28="","",COUNTIFS(Complaints!$D$5:$D$84,A28)) -> 0 | AM28: =IF(B28="","",COUNTIFS($AD$5:$AD$204,">"&AD28)+COUNTIFS($AD$5:AD28,AD28)) -> 0 | AN28: =IF(B28="","",COUNTIFS($AH$5:$AH$204,">"&AH28)+COUNTIFS($AH$5:AH28,AH28)) -> 0 | AO28: =IF(B28="","",COUNTIFS($AJ$5:$AJ$204,">"&AJ28)+COUNTIFS($AJ$5:AJ28,AJ28)) -> 0 | AP28: =IF(B28="","",IF(H28="Lost","Lost",IF(H28="Inactive","Dormant",IF(AA28="","Dormant",IF(AB28>InactiveClientDays*2,"Dormant",IF(AB28>InactiveClientDays,"At risk",IF(AC28="","Slipping",IF(Y28>=10,"Loyal","Steady")))))))) -> 0 | AQ28: =IF(OR(B28="",AP28="Lost",AP28="Dormant"),"",IF(OR(AP28="At risk",AP28="Slipping"),IF(AB28="",999,AB28),"")) -> 0 | AR28: =IF(AQ28="","",COUNTIFS($AQ$5:$AQ$204,">"&AQ28)+COUNTIFS($AQ$5:AQ28,AQ28)) -> 0 | AS28: =IF(B28="","",IF(AF28>0.5,"Chase - "&TEXT(AF28,"0")&" owing",IF(AND(H28<>"Lost",H28<>"Inactive",H28<>"Paused",AC28="",K28<>"One-off"),"Book - nothing in the diary",IF(AND(S28<>"",S28-TodayDate<=RenewalWarningDays,S28>=TodayDate),"Due - contract renews soon",IF(AP28="At risk","Call - going quiet",IF(AL28>=2,"Check - complaints logged",IF(AND(AI28<>"",AI28<MarginFloor,Y28>0),"Check - thin margin","OK"))))))) -> 0
A29: =IF(B29="","",ClientPrefix&TEXT(ROW()-4,"0000")) -> 0 | W29: =IF(A29="","",COUNTIFS(Properties!$C$5:$C$254,A29)) -> 0 | X29: =IF(A29="","",COUNTIFS(Jobs!$G$5:$G$604,A29)) -> 0 | Y29: =IF(A29="","",COUNTIFS(Jobs!$G$5:$G$604,A29,Jobs!$P$5:$P$604,"Completed")+COUNTIFS(Jobs!$G$5:$G$604,A29,Jobs!$P$5:$P$604,"Invoiced")) -> 0 | Z29: =IF(A29="","",COUNTIFS(Jobs!$G$5:$G$604,A29,Jobs!$P$5:$P$604,"Cancelled")+COUNTIFS(Jobs!$G$5:$G$604,A29,Jobs!$P$5:$P$604,"No access")) -> 0 | AA29: =IF(A29="","",IF(SUMPRODUCT(MAX((Jobs!$G$5:$G$604=A29)*((Jobs!$P$5:$P$604="Completed")+(Jobs!$P$5:$P$604="Invoiced"))*Jobs!$B$5:$B$604))=0,"",SUMPRODUCT(MAX((Jobs!$G$5:$G$604=A29)*((Jobs!$P$5:$P$604="Completed")+(Jobs!$P$5:$P$604="Invoiced"))*Jobs!$B$5:$B$604)))) -> 0 | AB29: =IF(AA29="","",TodayDate-AA29) -> 0 | AC29: =IF(A29="","",IF(SUMPRODUCT(MIN((Jobs!$G$5:$G$604=A29)*(Jobs!$B$5:$B$604>=TodayDate)*(Jobs!$P$5:$P$604<>"Cancelled")*Jobs!$B$5:$B$604+(1-(Jobs!$G$5:$G$604=A29)*(Jobs!$B$5:$B$604>=TodayDate)*(Jobs!$P$5:$P$604<>"Cancelled"))*2958465))=2958465,"",SUMPRODUCT(MIN((Jobs!$G$5:$G$604=A29)*(Jobs!$B$5:$B$604>=TodayDate)*(Jobs!$P$5:$P$604<>"Cancelled")*Jobs!$B$5:$B$604+(1-(Jobs!$G$5:$G$604=A29)*(Jobs!$B$5:$B$604>=TodayDate)*(Jobs!$P$5:$P$604<>"Cancelled"))*2958465)))) -> 0 | AD29: =IF(A29="","",SUMIFS(Invoices!$V$5:$V$404,Invoices!$D$5:$D$404,A29)) -> 0 | AE29: =IF(A29="","",SUMIFS(Invoices!$W$5:$W$404,Invoices!$D$5:$D$404,A29)) -> 0 | AF29: =IF(A29="","",AD29-AE29) -> 0 | AG29: =IF(OR(A29="",Y29=0),"",AD29/Y29) -> 0 | AH29: =IF(A29="","",SUMIFS('Job Costing'!$U$5:$U$604,'Job Costing'!$D$5:$D$604,A29)) -> 0 | AI29: =IF(OR(A29="",AD29=0),"",AH29/AD29) -> 0 | AJ29: =IF(OR(A29="",K29="",AG29=""),"",AG29*IFERROR(INDEX(FreqPerYear,MATCH(K29,FreqNames,0)),1)) -> 0 | AK29: =IF(A29="","",IFERROR(AVERAGEIFS(Jobs!$AA$5:$AA$604,Jobs!$G$5:$G$604,A29,Jobs!$AA$5:$AA$604,">0"),"")) -> 0 | AL29: =IF(A29="","",COUNTIFS(Complaints!$D$5:$D$84,A29)) -> 0 | AM29: =IF(B29="","",COUNTIFS($AD$5:$AD$204,">"&AD29)+COUNTIFS($AD$5:AD29,AD29)) -> 0 | AN29: =IF(B29="","",COUNTIFS($AH$5:$AH$204,">"&AH29)+COUNTIFS($AH$5:AH29,AH29)) -> 0 | AO29: =IF(B29="","",COUNTIFS($AJ$5:$AJ$204,">"&AJ29)+COUNTIFS($AJ$5:AJ29,AJ29)) -> 0 | AP29: =IF(B29="","",IF(H29="Lost","Lost",IF(H29="Inactive","Dormant",IF(AA29="","Dormant",IF(AB29>InactiveClientDays*2,"Dormant",IF(AB29>InactiveClientDays,"At risk",IF(AC29="","Slipping",IF(Y29>=10,"Loyal","Steady")))))))) -> 0 | AQ29: =IF(OR(B29="",AP29="Lost",AP29="Dormant"),"",IF(OR(AP29="At risk",AP29="Slipping"),IF(AB29="",999,AB29),"")) -> 0 | AR29: =IF(AQ29="","",COUNTIFS($AQ$5:$AQ$204,">"&AQ29)+COUNTIFS($AQ$5:AQ29,AQ29)) -> 0 | AS29: =IF(B29="","",IF(AF29>0.5,"Chase - "&TEXT(AF29,"0")&" owing",IF(AND(H29<>"Lost",H29<>"Inactive",H29<>"Paused",AC29="",K29<>"One-off"),"Book - nothing in the diary",IF(AND(S29<>"",S29-TodayDate<=RenewalWarningDays,S29>=TodayDate),"Due - contract renews soon",IF(AP29="At risk","Call - going quiet",IF(AL29>=2,"Check - complaints logged",IF(AND(AI29<>"",AI29<MarginFloor,Y29>0),"Check - thin margin","OK"))))))) -> 0
A30: =IF(B30="","",ClientPrefix&TEXT(ROW()-4,"0000")) -> 0 | W30: =IF(A30="","",COUNTIFS(Properties!$C$5:$C$254,A30)) -> 0 | X30: =IF(A30="","",COUNTIFS(Jobs!$G$5:$G$604,A30)) -> 0 | Y30: =IF(A30="","",COUNTIFS(Jobs!$G$5:$G$604,A30,Jobs!$P$5:$P$604,"Completed")+COUNTIFS(Jobs!$G$5:$G$604,A30,Jobs!$P$5:$P$604,"Invoiced")) -> 0 | Z30: =IF(A30="","",COUNTIFS(Jobs!$G$5:$G$604,A30,Jobs!$P$5:$P$604,"Cancelled")+COUNTIFS(Jobs!$G$5:$G$604,A30,Jobs!$P$5:$P$604,"No access")) -> 0 | AA30: =IF(A30="","",IF(SUMPRODUCT(MAX((Jobs!$G$5:$G$604=A30)*((Jobs!$P$5:$P$604="Completed")+(Jobs!$P$5:$P$604="Invoiced"))*Jobs!$B$5:$B$604))=0,"",SUMPRODUCT(MAX((Jobs!$G$5:$G$604=A30)*((Jobs!$P$5:$P$604="Completed")+(Jobs!$P$5:$P$604="Invoiced"))*Jobs!$B$5:$B$604)))) -> 0 | AB30: =IF(AA30="","",TodayDate-AA30) -> 0 | AC30: =IF(A30="","",IF(SUMPRODUCT(MIN((Jobs!$G$5:$G$604=A30)*(Jobs!$B$5:$B$604>=TodayDate)*(Jobs!$P$5:$P$604<>"Cancelled")*Jobs!$B$5:$B$604+(1-(Jobs!$G$5:$G$604=A30)*(Jobs!$B$5:$B$604>=TodayDate)*(Jobs!$P$5:$P$604<>"Cancelled"))*2958465))=2958465,"",SUMPRODUCT(MIN((Jobs!$G$5:$G$604=A30)*(Jobs!$B$5:$B$604>=TodayDate)*(Jobs!$P$5:$P$604<>"Cancelled")*Jobs!$B$5:$B$604+(1-(Jobs!$G$5:$G$604=A30)*(Jobs!$B$5:$B$604>=TodayDate)*(Jobs!$P$5:$P$604<>"Cancelled"))*2958465)))) -> 0 | AD30: =IF(A30="","",SUMIFS(Invoices!$V$5:$V$404,Invoices!$D$5:$D$404,A30)) -> 0 | AE30: =IF(A30="","",SUMIFS(Invoices!$W$5:$W$404,Invoices!$D$5:$D$404,A30)) -> 0 | AF30: =IF(A30="","",AD30-AE30) -> 0 | AG30: =IF(OR(A30="",Y30=0),"",AD30/Y30) -> 0 | AH30: =IF(A30="","",SUMIFS('Job Costing'!$U$5:$U$604,'Job Costing'!$D$5:$D$604,A30)) -> 0 | AI30: =IF(OR(A30="",AD30=0),"",AH30/AD30) -> 0 | AJ30: =IF(OR(A30="",K30="",AG30=""),"",AG30*IFERROR(INDEX(FreqPerYear,MATCH(K30,FreqNames,0)),1)) -> 0 | AK30: =IF(A30="","",IFERROR(AVERAGEIFS(Jobs!$AA$5:$AA$604,Jobs!$G$5:$G$604,A30,Jobs!$AA$5:$AA$604,">0"),"")) -> 0 | AL30: =IF(A30="","",COUNTIFS(Complaints!$D$5:$D$84,A30)) -> 0 | AM30: =IF(B30="","",COUNTIFS($AD$5:$AD$204,">"&AD30)+COUNTIFS($AD$5:AD30,AD30)) -> 0 | AN30: =IF(B30="","",COUNTIFS($AH$5:$AH$204,">"&AH30)+COUNTIFS($AH$5:AH30,AH30)) -> 0 | AO30: =IF(B30="","",COUNTIFS($AJ$5:$AJ$204,">"&AJ30)+COUNTIFS($AJ$5:AJ30,AJ30)) -> 0 | AP30: =IF(B30="","",IF(H30="Lost","Lost",IF(H30="Inactive","Dormant",IF(AA30="","Dormant",IF(AB30>InactiveClientDays*2,"Dormant",IF(AB30>InactiveClientDays,"At risk",IF(AC30="","Slipping",IF(Y30>=10,"Loyal","Steady")))))))) -> 0 | AQ30: =IF(OR(B30="",AP30="Lost",AP30="Dormant"),"",IF(OR(AP30="At risk",AP30="Slipping"),IF(AB30="",999,AB30),"")) -> 0 | AR30: =IF(AQ30="","",COUNTIFS($AQ$5:$AQ$204,">"&AQ30)+COUNTIFS($AQ$5:AQ30,AQ30)) -> 0 | AS30: =IF(B30="","",IF(AF30>0.5,"Chase - "&TEXT(AF30,"0")&" owing",IF(AND(H30<>"Lost",H30<>"Inactive",H30<>"Paused",AC30="",K30<>"One-off"),"Book - nothing in the diary",IF(AND(S30<>"",S30-TodayDate<=RenewalWarningDays,S30>=TodayDate),"Due - contract renews soon",IF(AP30="At risk","Call - going quiet",IF(AL30>=2,"Check - complaints logged",IF(AND(AI30<>"",AI30<MarginFloor,Y30>0),"Check - thin margin","OK"))))))) -> 0
A31: =IF(B31="","",ClientPrefix&TEXT(ROW()-4,"0000")) -> 0 | W31: =IF(A31="","",COUNTIFS(Properties!$C$5:$C$254,A31)) -> 0 | X31: =IF(A31="","",COUNTIFS(Jobs!$G$5:$G$604,A31)) -> 0 | Y31: =IF(A31="","",COUNTIFS(Jobs!$G$5:$G$604,A31,Jobs!$P$5:$P$604,"Completed")+COUNTIFS(Jobs!$G$5:$G$604,A31,Jobs!$P$5:$P$604,"Invoiced")) -> 0 | Z31: =IF(A31="","",COUNTIFS(Jobs!$G$5:$G$604,A31,Jobs!$P$5:$P$604,"Cancelled")+COUNTIFS(Jobs!$G$5:$G$604,A31,Jobs!$P$5:$P$604,"No access")) -> 0 | AA31: =IF(A31="","",IF(SUMPRODUCT(MAX((Jobs!$G$5:$G$604=A31)*((Jobs!$P$5:$P$604="Completed")+(Jobs!$P$5:$P$604="Invoiced"))*Jobs!$B$5:$B$604))=0,"",SUMPRODUCT(MAX((Jobs!$G$5:$G$604=A31)*((Jobs!$P$5:$P$604="Completed")+(Jobs!$P$5:$P$604="Invoiced"))*Jobs!$B$5:$B$604)))) -> 0 | AB31: =IF(AA31="","",TodayDate-AA31) -> 0 | AC31: =IF(A31="","",IF(SUMPRODUCT(MIN((Jobs!$G$5:$G$604=A31)*(Jobs!$B$5:$B$604>=TodayDate)*(Jobs!$P$5:$P$604<>"Cancelled")*Jobs!$B$5:$B$604+(1-(Jobs!$G$5:$G$604=A31)*(Jobs!$B$5:$B$604>=TodayDate)*(Jobs!$P$5:$P$604<>"Cancelled"))*2958465))=2958465,"",SUMPRODUCT(MIN((Jobs!$G$5:$G$604=A31)*(Jobs!$B$5:$B$604>=TodayDate)*(Jobs!$P$5:$P$604<>"Cancelled")*Jobs!$B$5:$B$604+(1-(Jobs!$G$5:$G$604=A31)*(Jobs!$B$5:$B$604>=TodayDate)*(Jobs!$P$5:$P$604<>"Cancelled"))*2958465)))) -> 0 | AD31: =IF(A31="","",SUMIFS(Invoices!$V$5:$V$404,Invoices!$D$5:$D$404,A31)) -> 0 | AE31: =IF(A31="","",SUMIFS(Invoices!$W$5:$W$404,Invoices!$D$5:$D$404,A31)) -> 0 | AF31: =IF(A31="","",AD31-AE31) -> 0 | AG31: =IF(OR(A31="",Y31=0),"",AD31/Y31) -> 0 | AH31: =IF(A31="","",SUMIFS('Job Costing'!$U$5:$U$604,'Job Costing'!$D$5:$D$604,A31)) -> 0 | AI31: =IF(OR(A31="",AD31=0),"",AH31/AD31) -> 0 | AJ31: =IF(OR(A31="",K31="",AG31=""),"",AG31*IFERROR(INDEX(FreqPerYear,MATCH(K31,FreqNames,0)),1)) -> 0 | AK31: =IF(A31="","",IFERROR(AVERAGEIFS(Jobs!$AA$5:$AA$604,Jobs!$G$5:$G$604,A31,Jobs!$AA$5:$AA$604,">0"),"")) -> 0 | AL31: =IF(A31="","",COUNTIFS(Complaints!$D$5:$D$84,A31)) -> 0 | AM31: =IF(B31="","",COUNTIFS($AD$5:$AD$204,">"&AD31)+COUNTIFS($AD$5:AD31,AD31)) -> 0 | AN31: =IF(B31="","",COUNTIFS($AH$5:$AH$204,">"&AH31)+COUNTIFS($AH$5:AH31,AH31)) -> 0 | AO31: =IF(B31="","",COUNTIFS($AJ$5:$AJ$204,">"&AJ31)+COUNTIFS($AJ$5:AJ31,AJ31)) -> 0 | AP31: =IF(B31="","",IF(H31="Lost","Lost",IF(H31="Inactive","Dormant",IF(AA31="","Dormant",IF(AB31>InactiveClientDays*2,"Dormant",IF(AB31>InactiveClientDays,"At risk",IF(AC31="","Slipping",IF(Y31>=10,"Loyal","Steady")))))))) -> 0 | AQ31: =IF(OR(B31="",AP31="Lost",AP31="Dormant"),"",IF(OR(AP31="At risk",AP31="Slipping"),IF(AB31="",999,AB31),"")) -> 0 | AR31: =IF(AQ31="","",COUNTIFS($AQ$5:$AQ$204,">"&AQ31)+COUNTIFS($AQ$5:AQ31,AQ31)) -> 0 | AS31: =IF(B31="","",IF(AF31>0.5,"Chase - "&TEXT(AF31,"0")&" owing",IF(AND(H31<>"Lost",H31<>"Inactive",H31<>"Paused",AC31="",K31<>"One-off"),"Book - nothing in the diary",IF(AND(S31<>"",S31-TodayDate<=RenewalWarningDays,S31>=TodayDate),"Due - contract renews soon",IF(AP31="At risk","Call - going quiet",IF(AL31>=2,"Check - complaints logged",IF(AND(AI31<>"",AI31<MarginFloor,Y31>0),"Check - thin margin","OK"))))))) -> 0
... A204: =IF(B204="","",ClientPrefix&TEXT(ROW()-4,"0000")) -> 0 | W204: =IF(A204="","",COUNTIFS(Properties!$C$5:$C$254,A204)) -> 0 | X204: =IF(A204="","",COUNTIFS(Jobs!$G$5:$G$604,A204)) -> 0 | Y204: =IF(A204="","",COUNTIFS(Jobs!$G$5:$G$604,A204,Jobs!$P$5:$P$604,"Completed")+COUNTIFS(Jobs!$G$5:$G$604,A204,Jobs!$P$5:$P$604,"Invoiced")) -> 0 | Z204: =IF(A204="","",COUNTIFS(Jobs!$G$5:$G$604,A204,Jobs!$P$5:$P$604,"Cancelled")+COUNTIFS(Jobs!$G$5:$G$604,A204,Jobs!$P$5:$P$604,"No access")) -> 0 | AA204: =IF(A204="","",IF(SUMPRODUCT(MAX((Jobs!$G$5:$G$604=A204)*((Jobs!$P$5:$P$604="Completed")+(Jobs!$P$5:$P$604="Invoiced"))*Jobs!$B$5:$B$604))=0,"",SUMPRODUCT(MAX((Jobs!$G$5:$G$604=A204)*((Jobs!$P$5:$P$604="Completed")+(Jobs!$P$5:$P$604="Invoiced"))*Jobs!$B$5:$B$604)))) -> 0 | AB204: =IF(AA204="","",TodayDate-AA204) -> 0 | AC204: =IF(A204="","",IF(SUMPRODUCT(MIN((Jobs!$G$5:$G$604=A204)*(Jobs!$B$5:$B$604>=TodayDate)*(Jobs!$P$5:$P$604<>"Cancelled")*Jobs!$B$5:$B$604+(1-(Jobs!$G$5:$G$604=A204)*(Jobs!$B$5:$B$604>=TodayDate)*(Jobs!$P$5:$P$604<>"Cancelled"))*2958465))=2958465,"",SUMPRODUCT(MIN((Jobs!$G$5:$G$604=A204)*(Jobs!$B$5:$B$604>=TodayDate)*(Jobs!$P$5:$P$604<>"Cancelled")*Jobs!$B$5:$B$604+(1-(Jobs!$G$5:$G$604=A204)*(Jobs!$B$5:$B$604>=TodayDate)*(Jobs!$P$5:$P$604<>"Cancelled"))*2958465)))) -> 0 | AD204: =IF(A204="","",SUMIFS(Invoices!$V$5:$V$404,Invoices!$D$5:$D$404,A204)) -> 0 | AE204: =IF(A204="","",SUMIFS(Invoices!$W$5:$W$404,Invoices!$D$5:$D$404,A204)) -> 0 | AF204: =IF(A204="","",AD204-AE204) -> 0 | AG204: =IF(OR(A204="",Y204=0),"",AD204/Y204) -> 0 | AH204: =IF(A204="","",SUMIFS('Job Costing'!$U$5:$U$604,'Job Costing'!$D$5:$D$604,A204)) -> 0 | AI204: =IF(OR(A204="",AD204=0),"",AH204/AD204) -> 0 | AJ204: =IF(OR(A204="",K204="",AG204=""),"",AG204*IFERROR(INDEX(FreqPerYear,MATCH(K204,FreqNames,0)),1)) -> 0 | AK204: =IF(A204="","",IFERROR(AVERAGEIFS(Jobs!$AA$5:$AA$604,Jobs!$G$5:$G$604,A204,Jobs!$AA$5:$AA$604,">0"),"")) -> 0 | AL204: =IF(A204="","",COUNTIFS(Complaints!$D$5:$D$84,A204)) -> 0 | AM204: =IF(B204="","",COUNTIFS($AD$5:$AD$204,">"&AD204)+COUNTIFS($AD$5:AD204,AD204)) -> 0 | AN204: =IF(B204="","",COUNTIFS($AH$5:$AH$204,">"&AH204)+COUNTIFS($AH$5:AH204,AH204)) -> 0 | AO204: =IF(B204="","",COUNTIFS($AJ$5:$AJ$204,">"&AJ204)+COUNTIFS($AJ$5:AJ204,AJ204)) -> 0 | AP204: =IF(B204="","",IF(H204="Lost","Lost",IF(H204="Inactive","Dormant",IF(AA204="","Dormant",IF(AB204>InactiveClientDays*2,"Dormant",IF(AB204>InactiveClientDays,"At risk",IF(AC204="","Slipping",IF(Y204>=10,"Loyal","Steady")))))))) -> 0 | AQ204: =IF(OR(B204="",AP204="Lost",AP204="Dormant"),"",IF(OR(AP204="At risk",AP204="Slipping"),IF(AB204="",999,AB204),"")) -> 0 | AR204: =IF(AQ204="","",COUNTIFS($AQ$5:$AQ$204,">"&AQ204)+COUNTIFS($AQ$5:AQ204,AQ204)) -> 0 | AS204: =IF(B204="","",IF(AF204>0.5,"Chase - "&TEXT(AF204,"0")&" owing",IF(AND(H204<>"Lost",H204<>"Inactive",H204<>"Paused",AC204="",K204<>"One-off"),"Book - nothing in the diary",IF(AND(S204<>"",S204-TodayDate<=RenewalWarningDays,S204>=TodayDate),"Due - contract renews soon",IF(AP204="At risk","Call - going quiet",IF(AL204>=2,"Check - complaints logged",IF(AND(AI204<>"",AI204<MarginFloor,Y204>0),"Check - thin margin","OK"))))))) -> 0

Sheet Properties
A1: Property & Site Database | AF1: Novality Store | v1.0.0
A2: The places you clean, how long they take and what they should be worth.
A3: > Start Here | C3: > Dashboard | E3: > Clients | G3: > Jobs | I3: > Calendar | K3: > Quotes | M3: > Invoices | O3: > Staff | Q3: > Help | S3: One row per address. Fill in the size, the condition and how you get in, and the workbook estimates the hours and suggests a price straight away.
A4: ID | B4: Property | C4: Client ID | D4: Client | E4: Property type | F4: Address | G4: Area (sq ft) | H4: Bedrooms | I4: Bathrooms | J4: Other rooms | K4: Floor types | L4: Condition | M4: Pets | N4: How we get in | O4: Key | P4: Entry instructions | Q4: Parking | R4: Distance (miles) | S4: Checklist | T4: Client supplies? | U4: Active? | V4: Notes | W4: Size hours | X4: Estimated hours | Y4: Hours on site | Z4: Suggested price | AA4: Labour cost | AB4: Estimated margin | AC4: Jobs here | AD4: Last visit | AE4: Average actual hours | AF4: Estimate vs actual | AG4: Revenue here | AH4: Action
A5: =IF(B5="","",PropertyPrefix&TEXT(ROW()-4,"0000")) -> 0 | B5: Harper - family home | C5: CL-0001 | D5: =IF(C5="","",IFERROR(INDEX(Clients!$B$5:$B$204,MATCH(C5,Clients!$A$5:$A$204,0)),"Not found")) -> 0 | E5: House | F5: 42 Larch Street, Portland OR 97215 | G5: 1450 | H5: 3 | I5: 2 | J5: 4 | K5: Mixed | L5: Normal | M5: Dog & cat | N5: We hold a key | O5: Held by us | P5: Key 12 on the board. Alarm panel inside the front door, code on the client card. | Q5: Driveway | R5: 4.2 | S5: Regular home clean | T5: No | U5: Yes | V5: Cat flap in the utility door. Dog is friendly. | W5: =IF(B5="","",MAX(IF(H5="",0,H5)*0.45+IF(I5="",0,I5)*0.6+IF(J5="",0,J5)*0.3,IF(G5="",0,G5)/650)) -> 0 | X5: =IF(B5="","",ROUND(MAX(1,W5)*IFERROR(INDEX(ConditionFactors,MATCH(L5,ConditionNames,0)),1),2)) -> 0 | Y5: =IF(B5="","",ROUND(X5/MAX(1,CleanersPerJob),2)) -> 0 | Z5: =IF(B5="","",MAX(MinimumCharge,ROUND(X5*IF(IFERROR(INDEX(Clients!$O$5:$O$204,MATCH(C5,Clients!$A$5:$A$204,0)),0)>0,INDEX(Clients!$O$5:$O$204,MATCH(C5,Clients!$A$5:$A$204,0)),HourlyRate)+IF(M5="",0,IF(M5="None",0,PetSurcharge)),2))) -> 0 | AA5: =IF(B5="","",ROUND(X5*CostPerHour,2)) -> 0 | AB5: =IF(B5="","",IF(Z5=0,"",(Z5-AA5-X5*SuppliesPerHour)/Z5)) -> 0 | AC5: =IF(A5="","",COUNTIFS(Jobs!$J$5:$J$604,A5)) -> 0 | AD5: =IF(A5="","",IF(SUMPRODUCT(MAX((Jobs!$J$5:$J$604=A5)*((Jobs!$P$5:$P$604="Completed")+(Jobs!$P$5:$P$604="Invoiced"))*Jobs!$B$5:$B$604))=0,"",SUMPRODUCT(MAX((Jobs!$J$5:$J$604=A5)*((Jobs!$P$5:$P$604="Completed")+(Jobs!$P$5:$P$604="Invoiced"))*Jobs!$B$5:$B$604)))) -> 0 | AE5: =IF(A5="","",IFERROR(AVERAGEIFS(Jobs!$AK$5:$AK$604,Jobs!$J$5:$J$604,A5,Jobs!$AK$5:$AK$604,">0"),"")) -> 0 | AF5: =IF(OR(AE5="",X5=""),"",AE5-X5) -> 0 | AG5: =IF(A5="","",SUMIFS(Jobs!$AJ$5:$AJ$604,Jobs!$J$5:$J$604,A5,Jobs!$P$5:$P$604,"Invoiced")+SUMIFS(Jobs!$AJ$5:$AJ$604,Jobs!$J$5:$J$604,A5,Jobs!$P$5:$P$604,"Completed")) -> 0 | AH5: =IF(B5="","",IF(C5="","Add - no client linked",IF(IFERROR(INDEX(Clients!$B$5:$B$204,MATCH(C5,Clients!$A$5:$A$204,0)),"")="","Check - client ID not found",IF(AND(G5="",H5=""),"Add - size needed to price it",IF(AND(AF5<>"",AF5>0.5),"Check - runs over the estimate",IF(N5="","Add - how do we get in?","OK")))))) -> 0
A6: =IF(B6="","",PropertyPrefix&TEXT(ROW()-4,"0000")) -> 0 | B6: Okafor - townhouse | C6: CL-0002 | D6: =IF(C6="","",IFERROR(INDEX(Clients!$B$5:$B$204,MATCH(C6,Clients!$A$5:$A$204,0)),"Not found")) -> 0 | E6: Townhouse | F6: 9 Elmwood Court, Portland OR 97212 | G6: 1700 | H6: 4 | I6: 2 | J6: 5 | K6: Carpet & tile | L6: Needs attention | M6: None | N6: Client at home | O6: Not applicable | P6: Someone is always in. Ring, do not knock - the bell wakes the baby. | Q6: Free street parking | R6: 6 | S6: Regular home clean | T6: No | U6: Yes | V6: Playroom gets the worst of it. | W6: =IF(B6="","",MAX(IF(H6="",0,H6)*0.45+IF(I6="",0,I6)*0.6+IF(J6="",0,J6)*0.3,IF(G6="",0,G6)/650)) -> 0 | X6: =IF(B6="","",ROUND(MAX(1,W6)*IFERROR(INDEX(ConditionFactors,MATCH(L6,ConditionNames,0)),1),2)) -> 0 | Y6: =IF(B6="","",ROUND(X6/MAX(1,CleanersPerJob),2)) -> 0 | Z6: =IF(B6="","",MAX(MinimumCharge,ROUND(X6*IF(IFERROR(INDEX(Clients!$O$5:$O$204,MATCH(C6,Clients!$A$5:$A$204,0)),0)>0,INDEX(Clients!$O$5:$O$204,MATCH(C6,Clients!$A$5:$A$204,0)),HourlyRate)+IF(M6="",0,IF(M6="None",0,PetSurcharge)),2))) -> 0 | AA6: =IF(B6="","",ROUND(X6*CostPerHour,2)) -> 0 | AB6: =IF(B6="","",IF(Z6=0,"",(Z6-AA6-X6*SuppliesPerHour)/Z6)) -> 0 | AC6: =IF(A6="","",COUNTIFS(Jobs!$J$5:$J$604,A6)) -> 0 | AD6: =IF(A6="","",IF(SUMPRODUCT(MAX((Jobs!$J$5:$J$604=A6)*((Jobs!$P$5:$P$604="Completed")+(Jobs!$P$5:$P$604="Invoiced"))*Jobs!$B$5:$B$604))=0,"",SUMPRODUCT(MAX((Jobs!$J$5:$J$604=A6)*((Jobs!$P$5:$P$604="Completed")+(Jobs!$P$5:$P$604="Invoiced"))*Jobs!$B$5:$B$604)))) -> 0 | AE6: =IF(A6="","",IFERROR(AVERAGEIFS(Jobs!$AK$5:$AK$604,Jobs!$J$5:$J$604,A6,Jobs!$AK$5:$AK$604,">0"),"")) -> 0 | AF6: =IF(OR(AE6="",X6=""),"",AE6-X6) -> 0 | AG6: =IF(A6="","",SUMIFS(Jobs!$AJ$5:$AJ$604,Jobs!$J$5:$J$604,A6,Jobs!$P$5:$P$604,"Invoiced")+SUMIFS(Jobs!$AJ$5:$AJ$604,Jobs!$J$5:$J$604,A6,Jobs!$P$5:$P$604,"Completed")) -> 0 | AH6: =IF(B6="","",IF(C6="","Add - no client linked",IF(IFERROR(INDEX(Clients!$B$5:$B$204,MATCH(C6,Clients!$A$5:$A$204,0)),"")="","Check - client ID not found",IF(AND(G6="",H6=""),"Add - size needed to price it",IF(AND(AF6<>"",AF6>0.5),"Check - runs over the estimate",IF(N6="","Add - how do we get in?","OK")))))) -> 0
A7: =IF(B7="","",PropertyPrefix&TEXT(ROW()-4,"0000")) -> 0 | B7: Riverbend Dental - practice | C7: CL-0003 | D7: =IF(C7="","",IFERROR(INDEX(Clients!$B$5:$B$204,MATCH(C7,Clients!$A$5:$A$204,0)),"Not found")) -> 0 | E7: Clinic | F7: 118 Riverbend Plaza, Suite 3, Portland OR 97209 | G7: 2200 | H7: 0 | I7: 3 | J7: 8 | K7: Vinyl | L7: Normal | M7: None | N7: Reception sign-in | O7: Not applicable | P7: Sign in at reception, collect the visitor badge, sign out on the way through. | Q7: Visitor bay | R7: 3.1 | S7: Office clean - small | T7: Yes | U7: Yes | V7: Four surgeries, waiting room, two staff rooms. Clinical bins are not ours. | W7: =IF(B7="","",MAX(IF(H7="",0,H7)*0.45+IF(I7="",0,I7)*0.6+IF(J7="",0,J7)*0.3,IF(G7="",0,G7)/650)) -> 0 | X7: =IF(B7="","",ROUND(MAX(1,W7)*IFERROR(INDEX(ConditionFactors,MATCH(L7,ConditionNames,0)),1),2)) -> 0 | Y7: =IF(B7="","",ROUND(X7/MAX(1,CleanersPerJob),2)) -> 0 | Z7: =IF(B7="","",MAX(MinimumCharge,ROUND(X7*IF(IFERROR(INDEX(Clients!$O$5:$O$204,MATCH(C7,Clients!$A$5:$A$204,0)),0)>0,INDEX(Clients!$O$5:$O$204,MATCH(C7,Clients!$A$5:$A$204,0)),HourlyRate)+IF(M7="",0,IF(M7="None",0,PetSurcharge)),2))) -> 0 | AA7: =IF(B7="","",ROUND(X7*CostPerHour,2)) -> 0 | AB7: =IF(B7="","",IF(Z7=0,"",(Z7-AA7-X7*SuppliesPerHour)/Z7)) -> 0 | AC7: =IF(A7="","",COUNTIFS(Jobs!$J$5:$J$604,A7)) -> 0 | AD7: =IF(A7="","",IF(SUMPRODUCT(MAX((Jobs!$J$5:$J$604=A7)*((Jobs!$P$5:$P$604="Completed")+(Jobs!$P$5:$P$604="Invoiced"))*Jobs!$B$5:$B$604))=0,"",SUMPRODUCT(MAX((Jobs!$J$5:$J$604=A7)*((Jobs!$P$5:$P$604="Completed")+(Jobs!$P$5:$P$604="Invoiced"))*Jobs!$B$5:$B$604)))) -> 0 | AE7: =IF(A7="","",IFERROR(AVERAGEIFS(Jobs!$AK$5:$AK$604,Jobs!$J$5:$J$604,A7,Jobs!$AK$5:$AK$604,">0"),"")) -> 0 | AF7: =IF(OR(AE7="",X7=""),"",AE7-X7) -> 0 | AG7: =IF(A7="","",SUMIFS(Jobs!$AJ$5:$AJ$604,Jobs!$J$5:$J$604,A7,Jobs!$P$5:$P$604,"Invoiced")+SUMIFS(Jobs!$AJ$5:$AJ$604,Jobs!$J$5:$J$604,A7,Jobs!$P$5:$P$604,"Completed")) -> 0 | AH7: =IF(B7="","",IF(C7="","Add - no client linked",IF(IFERROR(INDEX(Clients!$B$5:$B$204,MATCH(C7,Clients!$A$5:$A$204,0)),"")="","Check - client ID not found",IF(AND(G7="",H7=""),"Add - size needed to price it",IF(AND(AF7<>"",AF7>0.5),"Check - runs over the estimate",IF(N7="","Add - how do we get in?","OK")))))) -> 0
A8: =IF(B8="","",PropertyPrefix&TEXT(ROW()-4,"0000")) -> 0 | B8: Cedar & Co - second floor | C8: CL-0004 | D8: =IF(C8="","",IFERROR(INDEX(Clients!$B$5:$B$204,MATCH(C8,Clients!$A$5:$A$204,0)),"Not found")) -> 0 | E8: Office suite | F8: 77 Cedar Avenue, Floor 2, Portland OR 97204 | G8: 3100 | H8: 0 | I8: 2 | J8: 9 | K8: Carpet | L8: Very clean - upkeep only | M8: None | N8: Keypad code | O8: Not applicable | P8: Keypad code then the green button. Re-arm on the way out or the alarm company calls the owner. | Q8: Car park | R8: 2.4 | S8: Office clean - small | T8: Yes | U8: Yes | V8: Alarm: enter code within 30 seconds, panel by the lift. | W8: =IF(B8="","",MAX(IF(H8="",0,H8)*0.45+IF(I8="",0,I8)*0.6+IF(J8="",0,J8)*0.3,IF(G8="",0,G8)/650)) -> 0 | X8: =IF(B8="","",ROUND(MAX(1,W8)*IFERROR(INDEX(ConditionFactors,MATCH(L8,ConditionNames,0)),1),2)) -> 0 | Y8: =IF(B8="","",ROUND(X8/MAX(1,CleanersPerJob),2)) -> 0 | Z8: =IF(B8="","",MAX(MinimumCharge,ROUND(X8*IF(IFERROR(INDEX(Clients!$O$5:$O$204,MATCH(C8,Clients!$A$5:$A$204,0)),0)>0,INDEX(Clients!$O$5:$O$204,MATCH(C8,Clients!$A$5:$A$204,0)),HourlyRate)+IF(M8="",0,IF(M8="None",0,PetSurcharge)),2))) -> 0 | AA8: =IF(B8="","",ROUND(X8*CostPerHour,2)) -> 0 | AB8: =IF(B8="","",IF(Z8=0,"",(Z8-AA8-X8*SuppliesPerHour)/Z8)) -> 0 | AC8: =IF(A8="","",COUNTIFS(Jobs!$J$5:$J$604,A8)) -> 0 | AD8: =IF(A8="","",IF(SUMPRODUCT(MAX((Jobs!$J$5:$J$604=A8)*((Jobs!$P$5:$P$604="Completed")+(Jobs!$P$5:$P$604="Invoiced"))*Jobs!$B$5:$B$604))=0,"",SUMPRODUCT(MAX((Jobs!$J$5:$J$604=A8)*((Jobs!$P$5:$P$604="Completed")+(Jobs!$P$5:$P$604="Invoiced"))*Jobs!$B$5:$B$604)))) -> 0 | AE8: =IF(A8="","",IFERROR(AVERAGEIFS(Jobs!$AK$5:$AK$604,Jobs!$J$5:$J$604,A8,Jobs!$AK$5:$AK$604,">0"),"")) -> 0 | AF8: =IF(OR(AE8="",X8=""),"",AE8-X8) -> 0 | AG8: =IF(A8="","",SUMIFS(Jobs!$AJ$5:$AJ$604,Jobs!$J$5:$J$604,A8,Jobs!$P$5:$P$604,"Invoiced")+SUMIFS(Jobs!$AJ$5:$AJ$604,Jobs!$J$5:$J$604,A8,Jobs!$P$5:$P$604,"Completed")) -> 0 | AH8: =IF(B8="","",IF(C8="","Add - no client linked",IF(IFERROR(INDEX(Clients!$B$5:$B$204,MATCH(C8,Clients!$A$5:$A$204,0)),"")="","Check - client ID not found",IF(AND(G8="",H8=""),"Add - size needed to price it",IF(AND(AF8<>"",AF8>0.5),"Check - runs over the estimate",IF(N8="","Add - how do we get in?","OK")))))) -> 0
A9: =IF(B9="","",PropertyPrefix&TEXT(ROW()-4,"0000")) -> 0 | B9: Lakeview - 12B Lakeview Road | C9: CL-0005 | D9: =IF(C9="","",IFERROR(INDEX(Clients!$B$5:$B$204,MATCH(C9,Clients!$A$5:$A$204,0)),"Not found")) -> 0 | E9: Apartment | F9: 12B Lakeview Road, Portland OR 97202 | G9: 780 | H9: 2 | I9: 1 | J9: 3 | K9: Laminate | L9: Heavily soiled | M9: None | N9: Agent meets us | O9: Not applicable | P9: The agent unlocks and leaves. Call them when you are finished so they can lock up. | Q9: Metered street | R9: 7.5 | S9: End of tenancy clean | T9: No | U9: Yes | V9: End of tenancy. Oven and extractor are the big jobs. | W9: =IF(B9="","",MAX(IF(H9="",0,H9)*0.45+IF(I9="",0,I9)*0.6+IF(J9="",0,J9)*0.3,IF(G9="",0,G9)/650)) -> 0 | X9: =IF(B9="","",ROUND(MAX(1,W9)*IFERROR(INDEX(ConditionFactors,MATCH(L9,ConditionNames,0)),1),2)) -> 0 | Y9: =IF(B9="","",ROUND(X9/MAX(1,CleanersPerJob),2)) -> 0 | Z9: =IF(B9="","",MAX(MinimumCharge,ROUND(X9*IF(IFERROR(INDEX(Clients!$O$5:$O$204,MATCH(C9,Clients!$A$5:$A$204,0)),0)>0,INDEX(Clients!$O$5:$O$204,MATCH(C9,Clients!$A$5:$A$204,0)),HourlyRate)+IF(M9="",0,IF(M9="None",0,PetSurcharge)),2))) -> 0 | AA9: =IF(B9="","",ROUND(X9*CostPerHour,2)) -> 0 | AB9: =IF(B9="","",IF(Z9=0,"",(Z9-AA9-X9*SuppliesPerHour)/Z9)) -> 0 | AC9: =IF(A9="","",COUNTIFS(Jobs!$J$5:$J$604,A9)) -> 0 | AD9: =IF(A9="","",IF(SUMPRODUCT(MAX((Jobs!$J$5:$J$604=A9)*((Jobs!$P$5:$P$604="Completed")+(Jobs!$P$5:$P$604="Invoiced"))*Jobs!$B$5:$B$604))=0,"",SUMPRODUCT(MAX((Jobs!$J$5:$J$604=A9)*((Jobs!$P$5:$P$604="Completed")+(Jobs!$P$5:$P$604="Invoiced"))*Jobs!$B$5:$B$604)))) -> 0 | AE9: =IF(A9="","",IFERROR(AVERAGEIFS(Jobs!$AK$5:$AK$604,Jobs!$J$5:$J$604,A9,Jobs!$AK$5:$AK$604,">0"),"")) -> 0 | AF9: =IF(OR(AE9="",X9=""),"",AE9-X9) -> 0 | AG9: =IF(A9="","",SUMIFS(Jobs!$AJ$5:$AJ$604,Jobs!$J$5:$J$604,A9,Jobs!$P$5:$P$604,"Invoiced")+SUMIFS(Jobs!$AJ$5:$AJ$604,Jobs!$J$5:$J$604,A9,Jobs!$P$5:$P$604,"Completed")) -> 0 | AH9: =IF(B9="","",IF(C9="","Add - no client linked",IF(IFERROR(INDEX(Clients!$B$5:$B$204,MATCH(C9,Clients!$A$5:$A$204,0)),"")="","Check - client ID not found",IF(AND(G9="",H9=""),"Add - size needed to price it",IF(AND(AF9<>"",AF9>0.5),"Check - runs over the estimate",IF(N9="","Add - how do we get in?","OK")))))) -> 0
A10: =IF(B10="","",PropertyPrefix&TEXT(ROW()-4,"0000")) -> 0 | B10: The Maple Cafe - front of house | C10: CL-0006 | D10: =IF(C10="","",IFERROR(INDEX(Clients!$B$5:$B$204,MATCH(C10,Clients!$A$5:$A$204,0)),"Not found")) -> 0 | E10: Restaurant | F10: 210 Maple Street, Portland OR 97214 | G10: 1200 | H10: 0 | I10: 2 | J10: 4 | K10: Tile | L10: Normal | M10: None | N10: We hold a key | O10: Held by us | P10: Key 12 on the board. Alarm panel inside the front door, code on the client card. | Q10: Loading bay | R10: 5 | S10: Restaurant & kitchen clean | T10: Yes | U10: Yes | V10: Before 8am. Chairs down, floors mopped, glass polished. | W10: =IF(B10="","",MAX(IF(H10="",0,H10)*0.45+IF(I10="",0,I10)*0.6+IF(J10="",0,J10)*0.3,IF(G10="",0,G10)/650)) -> 0 | X10: =IF(B10="","",ROUND(MAX(1,W10)*IFERROR(INDEX(ConditionFactors,MATCH(L10,ConditionNames,0)),1),2)) -> 0 | Y10: =IF(B10="","",ROUND(X10/MAX(1,CleanersPerJob),2)) -> 0 | Z10: =IF(B10="","",MAX(MinimumCharge,ROUND(X10*IF(IFERROR(INDEX(Clients!$O$5:$O$204,MATCH(C10,Clients!$A$5:$A$204,0)),0)>0,INDEX(Clients!$O$5:$O$204,MATCH(C10,Clients!$A$5:$A$204,0)),HourlyRate)+IF(M10="",0,IF(M10="None",0,PetSurcharge)),2))) -> 0 | AA10: =IF(B10="","",ROUND(X10*CostPerHour,2)) -> 0 | AB10: =IF(B10="","",IF(Z10=0,"",(Z10-AA10-X10*SuppliesPerHour)/Z10)) -> 0 | AC10: =IF(A10="","",COUNTIFS(Jobs!$J$5:$J$604,A10)) -> 0 | AD10: =IF(A10="","",IF(SUMPRODUCT(MAX((Jobs!$J$5:$J$604=A10)*((Jobs!$P$5:$P$604="Completed")+(Jobs!$P$5:$P$604="Invoiced"))*Jobs!$B$5:$B$604))=0,"",SUMPRODUCT(MAX((Jobs!$J$5:$J$604=A10)*((Jobs!$P$5:$P$604="Completed")+(Jobs!$P$5:$P$604="Invoiced"))*Jobs!$B$5:$B$604)))) -> 0 | AE10: =IF(A10="","",IFERROR(AVERAGEIFS(Jobs!$AK$5:$AK$604,Jobs!$J$5:$J$604,A10,Jobs!$AK$5:$AK$604,">0"),"")) -> 0 | AF10: =IF(OR(AE10="",X10=""),"",AE10-X10) -> 0 | AG10: =IF(A10="","",SUMIFS(Jobs!$AJ$5:$AJ$604,Jobs!$J$5:$J$604,A10,Jobs!$P$5:$P$604,"Invoiced")+SUMIFS(Jobs!$AJ$5:$AJ$604,Jobs!$J$5:$J$604,A10,Jobs!$P$5:$P$604,"Completed")) -> 0 | AH10: =IF(B10="","",IF(C10="","Add - no client linked",IF(IFERROR(INDEX(Clients!$B$5:$B$204,MATCH(C10,Clients!$A$5:$A$204,0)),"")="","Check - client ID not found",IF(AND(G10="",H10=""),"Add - size needed to price it",IF(AND(AF10<>"",AF10>0.5),"Check - runs over the estimate",IF(N10="","Add - how do we get in?","OK")))))) -> 0
A11: =IF(B11="","",PropertyPrefix&TEXT(ROW()-4,"0000")) -> 0 | B11: Bright Start Nursery - main building | C11: CL-0007 | D11: =IF(C11="","",IFERROR(INDEX(Clients!$B$5:$B$204,MATCH(C11,Clients!$A$5:$A$204,0)),"Not found")) -> 0 | E11: School | F11: 15 Juniper Lane, Portland OR 97213 | G11: 2600 | H11: 0 | I11: 4 | J11: 10 | K11: Vinyl | L11: Normal | M11: None | N11: We hold a key | O11: In the key safe | P11: Key 12 on the board. Alarm panel inside the front door, code on the client card. | Q11: Driveway | R11: 4.6 | S11: Nursery & school clean | T11: Yes | U11: Yes | V11: Toy sanitising on Fridays. Log it on the checklist. | W11: =IF(B11="","",MAX(IF(H11="",0,H11)*0.45+IF(I11="",0,I11)*0.6+IF(J11="",0,J11)*0.3,IF(G11="",0,G11)/650)) -> 0 | X11: =IF(B11="","",ROUND(MAX(1,W11)*IFERROR(INDEX(ConditionFactors,MATCH(L11,ConditionNames,0)),1),2)) -> 0 | Y11: =IF(B11="","",ROUND(X11/MAX(1,CleanersPerJob),2)) -> 0 | Z11: =IF(B11="","",MAX(MinimumCharge,ROUND(X11*IF(IFERROR(INDEX(Clients!$O$5:$O$204,MATCH(C11,Clients!$A$5:$A$204,0)),0)>0,INDEX(Clients!$O$5:$O$204,MATCH(C11,Clients!$A$5:$A$204,0)),HourlyRate)+IF(M11="",0,IF(M11="None",0,PetSurcharge)),2))) -> 0 | AA11: =IF(B11="","",ROUND(X11*CostPerHour,2)) -> 0 | AB11: =IF(B11="","",IF(Z11=0,"",(Z11-AA11-X11*SuppliesPerHour)/Z11)) -> 0 | AC11: =IF(A11="","",COUNTIFS(Jobs!$J$5:$J$604,A11)) -> 0 | AD11: =IF(A11="","",IF(SUMPRODUCT(MAX((Jobs!$J$5:$J$604=A11)*((Jobs!$P$5:$P$604="Completed")+(Jobs!$P$5:$P$604="Invoiced"))*Jobs!$B$5:$B$604))=0,"",SUMPRODUCT(MAX((Jobs!$J$5:$J$604=A11)*((Jobs!$P$5:$P$604="Completed")+(Jobs!$P$5:$P$604="Invoiced"))*Jobs!$B$5:$B$604)))) -> 0 | AE11: =IF(A11="","",IFERROR(AVERAGEIFS(Jobs!$AK$5:$AK$604,Jobs!$J$5:$J$604,A11,Jobs!$AK$5:$AK$604,">0"),"")) -> 0 | AF11: =IF(OR(AE11="",X11=""),"",AE11-X11) -> 0 | AG11: =IF(A11="","",SUMIFS(Jobs!$AJ$5:$AJ$604,Jobs!$J$5:$J$604,A11,Jobs!$P$5:$P$604,"Invoiced")+SUMIFS(Jobs!$AJ$5:$AJ$604,Jobs!$J$5:$J$604,A11,Jobs!$P$5:$P$604,"Completed")) -> 0 | AH11: =IF(B11="","",IF(C11="","Add - no client linked",IF(IFERROR(INDEX(Clients!$B$5:$B$204,MATCH(C11,Clients!$A$5:$A$204,0)),"")="","Check - client ID not found",IF(AND(G11="",H11=""),"Add - size needed to price it",IF(AND(AF11<>"",AF11>0.5),"Check - runs over the estimate",IF(N11="","Add - how do we get in?","OK")))))) -> 0
A12: =IF(B12="","",PropertyPrefix&TEXT(ROW()-4,"0000")) -> 0 | B12: Nguyen - family home | C12: CL-0008 | D12: =IF(C12="","",IFERROR(INDEX(Clients!$B$5:$B$204,MATCH(C12,Clients!$A$5:$A$204,0)),"Not found")) -> 0 | E12: House | F12: 88 Alder Way, Portland OR 97211 | G12: 1900 | H12: 4 | I12: 2 | J12: 5 | K12: Hardwood | L12: Normal | M12: Cat | N12: Lockbox | O12: In the key safe | P12: Lockbox on the gatepost. Put the key back before you leave, never in your pocket. | Q12: Driveway | R12: 8.2 | S12: Regular home clean | T12: No | U12: Yes | V12: Lockbox code changes every quarter - check before you go. | W12: =IF(B12="","",MAX(IF(H12="",0,H12)*0.45+IF(I12="",0,I12)*0.6+IF(J12="",0,J12)*0.3,IF(G12="",0,G12)/650)) -> 0 | X12: =IF(B12="","",ROUND(MAX(1,W12)*IFERROR(INDEX(ConditionFactors,MATCH(L12,ConditionNames,0)),1),2)) -> 0 | Y12: =IF(B12="","",ROUND(X12/MAX(1,CleanersPerJob),2)) -> 0 | Z12: =IF(B12="","",MAX(MinimumCharge,ROUND(X12*IF(IFERROR(INDEX(Clients!$O$5:$O$204,MATCH(C12,Clients!$A$5:$A$204,0)),0)>0,INDEX(Clients!$O$5:$O$204,MATCH(C12,Clients!$A$5:$A$204,0)),HourlyRate)+IF(M12="",0,IF(M12="None",0,PetSurcharge)),2))) -> 0 | AA12: =IF(B12="","",ROUND(X12*CostPerHour,2)) -> 0 | AB12: =IF(B12="","",IF(Z12=0,"",(Z12-AA12-X12*SuppliesPerHour)/Z12)) -> 0 | AC12: =IF(A12="","",COUNTIFS(Jobs!$J$5:$J$604,A12)) -> 0 | AD12: =IF(A12="","",IF(SUMPRODUCT(MAX((Jobs!$J$5:$J$604=A12)*((Jobs!$P$5:$P$604="Completed")+(Jobs!$P$5:$P$604="Invoiced"))*Jobs!$B$5:$B$604))=0,"",SUMPRODUCT(MAX((Jobs!$J$5:$J$604=A12)*((Jobs!$P$5:$P$604="Completed")+(Jobs!$P$5:$P$604="Invoiced"))*Jobs!$B$5:$B$604)))) -> 0 | AE12: =IF(A12="","",IFERROR(AVERAGEIFS(Jobs!$AK$5:$AK$604,Jobs!$J$5:$J$604,A12,Jobs!$AK$5:$AK$604,">0"),"")) -> 0 | AF12: =IF(OR(AE12="",X12=""),"",AE12-X12) -> 0 | AG12: =IF(A12="","",SUMIFS(Jobs!$AJ$5:$AJ$604,Jobs!$J$5:$J$604,A12,Jobs!$P$5:$P$604,"Invoiced")+SUMIFS(Jobs!$AJ$5:$AJ$604,Jobs!$J$5:$J$604,A12,Jobs!$P$5:$P$604,"Completed")) -> 0 | AH12: =IF(B12="","",IF(C12="","Add - no client linked",IF(IFERROR(INDEX(Clients!$B$5:$B$204,MATCH(C12,Clients!$A$5:$A$204,0)),"")="","Check - client ID not found",IF(AND(G12="",H12=""),"Add - size needed to price it",IF(AND(AF12<>"",AF12>0.5),"Check - runs over the estimate",IF(N12="","Add - how do we get in?","OK")))))) -> 0
A13: =IF(B13="","",PropertyPrefix&TEXT(ROW()-4,"0000")) -> 0 | B13: Summit Fitness - studio | C13: CL-0009 | D13: =IF(C13="","",IFERROR(INDEX(Clients!$B$5:$B$204,MATCH(C13,Clients!$A$5:$A$204,0)),"Not found")) -> 0 | E13: Gym | F13: 501 Summit Drive, Portland OR 97201 | G13: 2400 | H13: 0 | I13: 2 | J13: 5 | K13: Rubber | L13: Normal | M13: None | N13: Keypad code | O13: Not applicable | P13: Keypad code then the green button. Re-arm on the way out or the alarm company calls the owner. | Q13: Car park | R13: 3.8 | S13: Office clean - small | T13: Yes | U13: Yes | V13: Mats, mirrors, changing rooms. Before 7am. | W13: =IF(B13="","",MAX(IF(H13="",0,H13)*0.45+IF(I13="",0,I13)*0.6+IF(J13="",0,J13)*0.3,IF(G13="",0,G13)/650)) -> 0 | X13: =IF(B13="","",ROUND(MAX(1,W13)*IFERROR(INDEX(ConditionFactors,MATCH(L13,ConditionNames,0)),1),2)) -> 0 | Y13: =IF(B13="","",ROUND(X13/MAX(1,CleanersPerJob),2)) -> 0 | Z13: =IF(B13="","",MAX(MinimumCharge,ROUND(X13*IF(IFERROR(INDEX(Clients!$O$5:$O$204,MATCH(C13,Clients!$A$5:$A$204,0)),0)>0,INDEX(Clients!$O$5:$O$204,MATCH(C13,Clients!$A$5:$A$204,0)),HourlyRate)+IF(M13="",0,IF(M13="None",0,PetSurcharge)),2))) -> 0 | AA13: =IF(B13="","",ROUND(X13*CostPerHour,2)) -> 0 | AB13: =IF(B13="","",IF(Z13=0,"",(Z13-AA13-X13*SuppliesPerHour)/Z13)) -> 0 | AC13: =IF(A13="","",COUNTIFS(Jobs!$J$5:$J$604,A13)) -> 0 | AD13: =IF(A13="","",IF(SUMPRODUCT(MAX((Jobs!$J$5:$J$604=A13)*((Jobs!$P$5:$P$604="Completed")+(Jobs!$P$5:$P$604="Invoiced"))*Jobs!$B$5:$B$604))=0,"",SUMPRODUCT(MAX((Jobs!$J$5:$J$604=A13)*((Jobs!$P$5:$P$604="Completed")+(Jobs!$P$5:$P$604="Invoiced"))*Jobs!$B$5:$B$604)))) -> 0 | AE13: =IF(A13="","",IFERROR(AVERAGEIFS(Jobs!$AK$5:$AK$604,Jobs!$J$5:$J$604,A13,Jobs!$AK$5:$AK$604,">0"),"")) -> 0 | AF13: =IF(OR(AE13="",X13=""),"",AE13-X13) -> 0 | AG13: =IF(A13="","",SUMIFS(Jobs!$AJ$5:$AJ$604,Jobs!$J$5:$J$604,A13,Jobs!$P$5:$P$604,"Invoiced")+SUMIFS(Jobs!$AJ$5:$AJ$604,Jobs!$J$5:$J$604,A13,Jobs!$P$5:$P$604,"Completed")) -> 0 | AH13: =IF(B13="","",IF(C13="","Add - no client linked",IF(IFERROR(INDEX(Clients!$B$5:$B$204,MATCH(C13,Clients!$A$5:$A$204,0)),"")="","Check - client ID not found",IF(AND(G13="",H13=""),"Add - size needed to price it",IF(AND(AF13<>"",AF13>0.5),"Check - runs over the estimate",IF(N13="","Add - how do we get in?","OK")))))) -> 0
A14: =IF(B14="","",PropertyPrefix&TEXT(ROW()-4,"0000")) -> 0 | B14: Hartley - Quay Street loft | C14: CL-0010 | D14: =IF(C14="","",IFERROR(INDEX(Clients!$B$5:$B$204,MATCH(C14,Clients!$A$5:$A$204,0)),"Not found")) -> 0 | E14: Holiday let | F14: 6 Quay Street, Portland OR 97209 | G14: 950 | H14: 2 | I14: 1 | J14: 3 | K14: Hardwood | L14: Normal | M14: None | N14: Lockbox | O14: In the key safe | P14: Lockbox on the gatepost. Put the key back before you leave, never in your pocket. | Q14: Permit needed | R14: 2.9 | S14: Airbnb changeover | T14: Yes | U14: Yes | V14: Full changeover: linen, towels, welcome pack, photos. | W14: =IF(B14="","",MAX(IF(H14="",0,H14)*0.45+IF(I14="",0,I14)*0.6+IF(J14="",0,J14)*0.3,IF(G14="",0,G14)/650)) -> 0 | X14: =IF(B14="","",ROUND(MAX(1,W14)*IFERROR(INDEX(ConditionFactors,MATCH(L14,ConditionNames,0)),1),2)) -> 0 | Y14: =IF(B14="","",ROUND(X14/MAX(1,CleanersPerJob),2)) -> 0 | Z14: =IF(B14="","",MAX(MinimumCharge,ROUND(X14*IF(IFERROR(INDEX(Clients!$O$5:$O$204,MATCH(C14,Clients!$A$5:$A$204,0)),0)>0,INDEX(Clients!$O$5:$O$204,MATCH(C14,Clients!$A$5:$A$204,0)),HourlyRate)+IF(M14="",0,IF(M14="None",0,PetSurcharge)),2))) -> 0 | AA14: =IF(B14="","",ROUND(X14*CostPerHour,2)) -> 0 | AB14: =IF(B14="","",IF(Z14=0,"",(Z14-AA14-X14*SuppliesPerHour)/Z14)) -> 0 | AC14: =IF(A14="","",COUNTIFS(Jobs!$J$5:$J$604,A14)) -> 0 | AD14: =IF(A14="","",IF(SUMPRODUCT(MAX((Jobs!$J$5:$J$604=A14)*((Jobs!$P$5:$P$604="Completed")+(Jobs!$P$5:$P$604="Invoiced"))*Jobs!$B$5:$B$604))=0,"",SUMPRODUCT(MAX((Jobs!$J$5:$J$604=A14)*((Jobs!$P$5:$P$604="Completed")+(Jobs!$P$5:$P$604="Invoiced"))*Jobs!$B$5:$B$604)))) -> 0 | AE14: =IF(A14="","",IFERROR(AVERAGEIFS(Jobs!$AK$5:$AK$604,Jobs!$J$5:$J$604,A14,Jobs!$AK$5:$AK$604,">0"),"")) -> 0 | AF14: =IF(OR(AE14="",X14=""),"",AE14-X14) -> 0 | AG14: =IF(A14="","",SUMIFS(Jobs!$AJ$5:$AJ$604,Jobs!$J$5:$J$604,A14,Jobs!$P$5:$P$604,"Invoiced")+SUMIFS(Jobs!$AJ$5:$AJ$604,Jobs!$J$5:$J$604,A14,Jobs!$P$5:$P$604,"Completed")) -> 0 | AH14: =IF(B14="","",IF(C14="","Add - no client linked",IF(IFERROR(INDEX(Clients!$B$5:$B$204,MATCH(C14,Clients!$A$5:$A$204,0)),"")="","Check - client ID not found",IF(AND(G14="",H14=""),"Add - size needed to price it",IF(AND(AF14<>"",AF14>0.5),"Check - runs over the estimate",IF(N14="","Add - how do we get in?","OK")))))) -> 0
A15: =IF(B15="","",PropertyPrefix&TEXT(ROW()-4,"0000")) -> 0 | B15: Hartley - Riverside studio | C15: CL-0010 | D15: =IF(C15="","",IFERROR(INDEX(Clients!$B$5:$B$204,MATCH(C15,Clients!$A$5:$A$204,0)),"Not found")) -> 0 | E15: Holiday let | F15: 19 Riverside Walk, Portland OR 97209 | G15: 540 | H15: 1 | I15: 1 | J15: 2 | K15: Laminate | L15: Normal | M15: None | N15: Lockbox | O15: In the key safe | P15: Lockbox on the gatepost. Put the key back before you leave, never in your pocket. | Q15: Pay and display | R15: 3.4 | S15: Airbnb changeover | T15: Yes | U15: Yes | V15: Small but fiddly. Same checklist as the loft. | W15: =IF(B15="","",MAX(IF(H15="",0,H15)*0.45+IF(I15="",0,I15)*0.6+IF(J15="",0,J15)*0.3,IF(G15="",0,G15)/650)) -> 0 | X15: =IF(B15="","",ROUND(MAX(1,W15)*IFERROR(INDEX(ConditionFactors,MATCH(L15,ConditionNames,0)),1),2)) -> 0 | Y15: =IF(B15="","",ROUND(X15/MAX(1,CleanersPerJob),2)) -> 0 | Z15: =IF(B15="","",MAX(MinimumCharge,ROUND(X15*IF(IFERROR(INDEX(Clients!$O$5:$O$204,MATCH(C15,Clients!$A$5:$A$204,0)),0)>0,INDEX(Clients!$O$5:$O$204,MATCH(C15,Clients!$A$5:$A$204,0)),HourlyRate)+IF(M15="",0,IF(M15="None",0,PetSurcharge)),2))) -> 0 | AA15: =IF(B15="","",ROUND(X15*CostPerHour,2)) -> 0 | AB15: =IF(B15="","",IF(Z15=0,"",(Z15-AA15-X15*SuppliesPerHour)/Z15)) -> 0 | AC15: =IF(A15="","",COUNTIFS(Jobs!$J$5:$J$604,A15)) -> 0 | AD15: =IF(A15="","",IF(SUMPRODUCT(MAX((Jobs!$J$5:$J$604=A15)*((Jobs!$P$5:$P$604="Completed")+(Jobs!$P$5:$P$604="Invoiced"))*Jobs!$B$5:$B$604))=0,"",SUMPRODUCT(MAX((Jobs!$J$5:$J$604=A15)*((Jobs!$P$5:$P$604="Completed")+(Jobs!$P$5:$P$604="Invoiced"))*Jobs!$B$5:$B$604)))) -> 0 | AE15: =IF(A15="","",IFERROR(AVERAGEIFS(Jobs!$AK$5:$AK$604,Jobs!$J$5:$J$604,A15,Jobs!$AK$5:$AK$604,">0"),"")) -> 0 | AF15: =IF(OR(AE15="",X15=""),"",AE15-X15) -> 0 | AG15: =IF(A15="","",SUMIFS(Jobs!$AJ$5:$AJ$604,Jobs!$J$5:$J$604,A15,Jobs!$P$5:$P$604,"Invoiced")+SUMIFS(Jobs!$AJ$5:$AJ$604,Jobs!$J$5:$J$604,A15,Jobs!$P$5:$P$604,"Completed")) -> 0 | AH15: =IF(B15="","",IF(C15="","Add - no client linked",IF(IFERROR(INDEX(Clients!$B$5:$B$204,MATCH(C15,Clients!$A$5:$A$204,0)),"")="","Check - client ID not found",IF(AND(G15="",H15=""),"Add - size needed to price it",IF(AND(AF15<>"",AF15>0.5),"Check - runs over the estimate",IF(N15="","Add - how do we get in?","OK")))))) -> 0
A16: =IF(B16="","",PropertyPrefix&TEXT(ROW()-4,"0000")) -> 0 | B16: Donovan - bungalow | C16: CL-0011 | D16: =IF(C16="","",IFERROR(INDEX(Clients!$B$5:$B$204,MATCH(C16,Clients!$A$5:$A$204,0)),"Not found")) -> 0 | E16: Bungalow | F16: 27 Birch Close, Portland OR 97215 | G16: 1100 | H16: 2 | I16: 1 | J16: 4 | K16: Carpet | L16: Normal | M16: Dog | N16: We hold a key | O16: Held by us | P16: Key 12 on the board. Alarm panel inside the front door, code on the client card. | Q16: Driveway | R16: 6.8 | S16: Regular home clean | T16: No | U16: Yes | V16: Paused until September. | W16: =IF(B16="","",MAX(IF(H16="",0,H16)*0.45+IF(I16="",0,I16)*0.6+IF(J16="",0,J16)*0.3,IF(G16="",0,G16)/650)) -> 0 | X16: =IF(B16="","",ROUND(MAX(1,W16)*IFERROR(INDEX(ConditionFactors,MATCH(L16,ConditionNames,0)),1),2)) -> 0 | Y16: =IF(B16="","",ROUND(X16/MAX(1,CleanersPerJob),2)) -> 0 | Z16: =IF(B16="","",MAX(MinimumCharge,ROUND(X16*IF(IFERROR(INDEX(Clients!$O$5:$O$204,MATCH(C16,Clients!$A$5:$A$204,0)),0)>0,INDEX(Clients!$O$5:$O$204,MATCH(C16,Clients!$A$5:$A$204,0)),HourlyRate)+IF(M16="",0,IF(M16="None",0,PetSurcharge)),2))) -> 0 | AA16: =IF(B16="","",ROUND(X16*CostPerHour,2)) -> 0 | AB16: =IF(B16="","",IF(Z16=0,"",(Z16-AA16-X16*SuppliesPerHour)/Z16)) -> 0 | AC16: =IF(A16="","",COUNTIFS(Jobs!$J$5:$J$604,A16)) -> 0 | AD16: =IF(A16="","",IF(SUMPRODUCT(MAX((Jobs!$J$5:$J$604=A16)*((Jobs!$P$5:$P$604="Completed")+(Jobs!$P$5:$P$604="Invoiced"))*Jobs!$B$5:$B$604))=0,"",SUMPRODUCT(MAX((Jobs!$J$5:$J$604=A16)*((Jobs!$P$5:$P$604="Completed")+(Jobs!$P$5:$P$604="Invoiced"))*Jobs!$B$5:$B$604)))) -> 0 | AE16: =IF(A16="","",IFERROR(AVERAGEIFS(Jobs!$AK$5:$AK$604,Jobs!$J$5:$J$604,A16,Jobs!$AK$5:$AK$604,">0"),"")) -> 0 | AF16: =IF(OR(AE16="",X16=""),"",AE16-X16) -> 0 | AG16: =IF(A16="","",SUMIFS(Jobs!$AJ$5:$AJ$604,Jobs!$J$5:$J$604,A16,Jobs!$P$5:$P$604,"Invoiced")+SUMIFS(Jobs!$AJ$5:$AJ$604,Jobs!$J$5:$J$604,A16,Jobs!$P$5:$P$604,"Completed")) -> 0 | AH16: =IF(B16="","",IF(C16="","Add - no client linked",IF(IFERROR(INDEX(Clients!$B$5:$B$204,MATCH(C16,Clients!$A$5:$A$204,0)),"")="","Check - client ID not found",IF(AND(G16="",H16=""),"Add - size needed to price it",IF(AND(AF16<>"",AF16>0.5),"Check - runs over the estimate",IF(N16="","Add - how do we get in?","OK")))))) -> 0
... A20: =IF(B20="","",PropertyPrefix&TEXT(ROW()-4,"0000")) -> 0 | B20: Stonebridge Law - ground floor | C20: CL-0014 | D20: =IF(C20="","",IFERROR(INDEX(Clients!$B$5:$B$204,MATCH(C20,Clients!$A$5:$A$204,0)),"Not found")) -> 0 | E20: Office suite | F20: 4 Stonebridge Court, Portland OR 97204 | G20: 2100 | H20: 0 | I20: 2 | J20: 7 | K20: Carpet | L20: Very clean - upkeep only | M20: None | N20: Smart lock | O20: Not applicable | P20: One-time code sent the morning of the visit. It expires at midnight. | Q20: Underground garage | R20: 2.2 | S20: Office clean - small | T20: Yes | U20: Yes | V20: Desks are never to be cleared. Bins and floors only. | W20: =IF(B20="","",MAX(IF(H20="",0,H20)*0.45+IF(I20="",0,I20)*0.6+IF(J20="",0,J20)*0.3,IF(G20="",0,G20)/650)) -> 0 | X20: =IF(B20="","",ROUND(MAX(1,W20)*IFERROR(INDEX(ConditionFactors,MATCH(L20,ConditionNames,0)),1),2)) -> 0 | Y20: =IF(B20="","",ROUND(X20/MAX(1,CleanersPerJob),2)) -> 0 | Z20: =IF(B20="","",MAX(MinimumCharge,ROUND(X20*IF(IFERROR(INDEX(Clients!$O$5:$O$204,MATCH(C20,Clients!$A$5:$A$204,0)),0)>0,INDEX(Clients!$O$5:$O$204,MATCH(C20,Clients!$A$5:$A$204,0)),HourlyRate)+IF(M20="",0,IF(M20="None",0,PetSurcharge)),2))) -> 0 | AA20: =IF(B20="","",ROUND(X20*CostPerHour,2)) -> 0 | AB20: =IF(B20="","",IF(Z20=0,"",(Z20-AA20-X20*SuppliesPerHour)/Z20)) -> 0 | AC20: =IF(A20="","",COUNTIFS(Jobs!$J$5:$J$604,A20)) -> 0 | AD20: =IF(A20="","",IF(SUMPRODUCT(MAX((Jobs!$J$5:$J$604=A20)*((Jobs!$P$5:$P$604="Completed")+(Jobs!$P$5:$P$604="Invoiced"))*Jobs!$B$5:$B$604))=0,"",SUMPRODUCT(MAX((Jobs!$J$5:$J$604=A20)*((Jobs!$P$5:$P$604="Completed")+(Jobs!$P$5:$P$604="Invoiced"))*Jobs!$B$5:$B$604)))) -> 0 | AE20: =IF(A20="","",IFERROR(AVERAGEIFS(Jobs!$AK$5:$AK$604,Jobs!$J$5:$J$604,A20,Jobs!$AK$5:$AK$604,">0"),"")) -> 0 | AF20: =IF(OR(AE20="",X20=""),"",AE20-X20) -> 0 | AG20: =IF(A20="","",SUMIFS(Jobs!$AJ$5:$AJ$604,Jobs!$J$5:$J$604,A20,Jobs!$P$5:$P$604,"Invoiced")+SUMIFS(Jobs!$AJ$5:$AJ$604,Jobs!$J$5:$J$604,A20,Jobs!$P$5:$P$604,"Completed")) -> 0 | AH20: =IF(B20="","",IF(C20="","Add - no client linked",IF(IFERROR(INDEX(Clients!$B$5:$B$204,MATCH(C20,Clients!$A$5:$A$204,0)),"")="","Check - client ID not found",IF(AND(G20="",H20=""),"Add - size needed to price it",IF(AND(AF20<>"",AF20>0.5),"Check - runs over the estimate",IF(N20="","Add - how do we get in?","OK")))))) -> 0
A21: =IF(B21="","",PropertyPrefix&TEXT(ROW()-4,"0000")) -> 0 | D21: =IF(C21="","",IFERROR(INDEX(Clients!$B$5:$B$204,MATCH(C21,Clients!$A$5:$A$204,0)),"Not found")) -> 0 | W21: =IF(B21="","",MAX(IF(H21="",0,H21)*0.45+IF(I21="",0,I21)*0.6+IF(J21="",0,J21)*0.3,IF(G21="",0,G21)/650)) -> 0 | X21: =IF(B21="","",ROUND(MAX(1,W21)*IFERROR(INDEX(ConditionFactors,MATCH(L21,ConditionNames,0)),1),2)) -> 0 | Y21: =IF(B21="","",ROUND(X21/MAX(1,CleanersPerJob),2)) -> 0 | Z21: =IF(B21="","",MAX(MinimumCharge,ROUND(X21*IF(IFERROR(INDEX(Clients!$O$5:$O$204,MATCH(C21,Clients!$A$5:$A$204,0)),0)>0,INDEX(Clients!$O$5:$O$204,MATCH(C21,Clients!$A$5:$A$204,0)),HourlyRate)+IF(M21="",0,IF(M21="None",0,PetSurcharge)),2))) -> 0 | AA21: =IF(B21="","",ROUND(X21*CostPerHour,2)) -> 0 | AB21: =IF(B21="","",IF(Z21=0,"",(Z21-AA21-X21*SuppliesPerHour)/Z21)) -> 0 | AC21: =IF(A21="","",COUNTIFS(Jobs!$J$5:$J$604,A21)) -> 0 | AD21: =IF(A21="","",IF(SUMPRODUCT(MAX((Jobs!$J$5:$J$604=A21)*((Jobs!$P$5:$P$604="Completed")+(Jobs!$P$5:$P$604="Invoiced"))*Jobs!$B$5:$B$604))=0,"",SUMPRODUCT(MAX((Jobs!$J$5:$J$604=A21)*((Jobs!$P$5:$P$604="Completed")+(Jobs!$P$5:$P$604="Invoiced"))*Jobs!$B$5:$B$604)))) -> 0 | AE21: =IF(A21="","",IFERROR(AVERAGEIFS(Jobs!$AK$5:$AK$604,Jobs!$J$5:$J$604,A21,Jobs!$AK$5:$AK$604,">0"),"")) -> 0 | AF21: =IF(OR(AE21="",X21=""),"",AE21-X21) -> 0 | AG21: =IF(A21="","",SUMIFS(Jobs!$AJ$5:$AJ$604,Jobs!$J$5:$J$604,A21,Jobs!$P$5:$P$604,"Invoiced")+SUMIFS(Jobs!$AJ$5:$AJ$604,Jobs!$J$5:$J$604,A21,Jobs!$P$5:$P$604,"Completed")) -> 0 | AH21: =IF(B21="","",IF(C21="","Add - no client linked",IF(IFERROR(INDEX(Clients!$B$5:$B$204,MATCH(C21,Clients!$A$5:$A$204,0)),"")="","Check - client ID not found",IF(AND(G21="",H21=""),"Add - size needed to price it",IF(AND(AF21<>"",AF21>0.5),"Check - runs over the estimate",IF(N21="","Add - how do we get in?","OK")))))) -> 0
A22: =IF(B22="","",PropertyPrefix&TEXT(ROW()-4,"0000")) -> 0 | D22: =IF(C22="","",IFERROR(INDEX(Clients!$B$5:$B$204,MATCH(C22,Clients!$A$5:$A$204,0)),"Not found")) -> 0 | W22: =IF(B22="","",MAX(IF(H22="",0,H22)*0.45+IF(I22="",0,I22)*0.6+IF(J22="",0,J22)*0.3,IF(G22="",0,G22)/650)) -> 0 | X22: =IF(B22="","",ROUND(MAX(1,W22)*IFERROR(INDEX(ConditionFactors,MATCH(L22,ConditionNames,0)),1),2)) -> 0 | Y22: =IF(B22="","",ROUND(X22/MAX(1,CleanersPerJob),2)) -> 0 | Z22: =IF(B22="","",MAX(MinimumCharge,ROUND(X22*IF(IFERROR(INDEX(Clients!$O$5:$O$204,MATCH(C22,Clients!$A$5:$A$204,0)),0)>0,INDEX(Clients!$O$5:$O$204,MATCH(C22,Clients!$A$5:$A$204,0)),HourlyRate)+IF(M22="",0,IF(M22="None",0,PetSurcharge)),2))) -> 0 | AA22: =IF(B22="","",ROUND(X22*CostPerHour,2)) -> 0 | AB22: =IF(B22="","",IF(Z22=0,"",(Z22-AA22-X22*SuppliesPerHour)/Z22)) -> 0 | AC22: =IF(A22="","",COUNTIFS(Jobs!$J$5:$J$604,A22)) -> 0 | AD22: =IF(A22="","",IF(SUMPRODUCT(MAX((Jobs!$J$5:$J$604=A22)*((Jobs!$P$5:$P$604="Completed")+(Jobs!$P$5:$P$604="Invoiced"))*Jobs!$B$5:$B$604))=0,"",SUMPRODUCT(MAX((Jobs!$J$5:$J$604=A22)*((Jobs!$P$5:$P$604="Completed")+(Jobs!$P$5:$P$604="Invoiced"))*Jobs!$B$5:$B$604)))) -> 0 | AE22: =IF(A22="","",IFERROR(AVERAGEIFS(Jobs!$AK$5:$AK$604,Jobs!$J$5:$J$604,A22,Jobs!$AK$5:$AK$604,">0"),"")) -> 0 | AF22: =IF(OR(AE22="",X22=""),"",AE22-X22) -> 0 | AG22: =IF(A22="","",SUMIFS(Jobs!$AJ$5:$AJ$604,Jobs!$J$5:$J$604,A22,Jobs!$P$5:$P$604,"Invoiced")+SUMIFS(Jobs!$AJ$5:$AJ$604,Jobs!$J$5:$J$604,A22,Jobs!$P$5:$P$604,"Completed")) -> 0 | AH22: =IF(B22="","",IF(C22="","Add - no client linked",IF(IFERROR(INDEX(Clients!$B$5:$B$204,MATCH(C22,Clients!$A$5:$A$204,0)),"")="","Check - client ID not found",IF(AND(G22="",H22=""),"Add - size needed to price it",IF(AND(AF22<>"",AF22>0.5),"Check - runs over the estimate",IF(N22="","Add - how do we get in?","OK")))))) -> 0
A23: =IF(B23="","",PropertyPrefix&TEXT(ROW()-4,"0000")) -> 0 | D23: =IF(C23="","",IFERROR(INDEX(Clients!$B$5:$B$204,MATCH(C23,Clients!$A$5:$A$204,0)),"Not found")) -> 0 | W23: =IF(B23="","",MAX(IF(H23="",0,H23)*0.45+IF(I23="",0,I23)*0.6+IF(J23="",0,J23)*0.3,IF(G23="",0,G23)/650)) -> 0 | X23: =IF(B23="","",ROUND(MAX(1,W23)*IFERROR(INDEX(ConditionFactors,MATCH(L23,ConditionNames,0)),1),2)) -> 0 | Y23: =IF(B23="","",ROUND(X23/MAX(1,CleanersPerJob),2)) -> 0 | Z23: =IF(B23="","",MAX(MinimumCharge,ROUND(X23*IF(IFERROR(INDEX(Clients!$O$5:$O$204,MATCH(C23,Clients!$A$5:$A$204,0)),0)>0,INDEX(Clients!$O$5:$O$204,MATCH(C23,Clients!$A$5:$A$204,0)),HourlyRate)+IF(M23="",0,IF(M23="None",0,PetSurcharge)),2))) -> 0 | AA23: =IF(B23="","",ROUND(X23*CostPerHour,2)) -> 0 | AB23: =IF(B23="","",IF(Z23=0,"",(Z23-AA23-X23*SuppliesPerHour)/Z23)) -> 0 | AC23: =IF(A23="","",COUNTIFS(Jobs!$J$5:$J$604,A23)) -> 0 | AD23: =IF(A23="","",IF(SUMPRODUCT(MAX((Jobs!$J$5:$J$604=A23)*((Jobs!$P$5:$P$604="Completed")+(Jobs!$P$5:$P$604="Invoiced"))*Jobs!$B$5:$B$604))=0,"",SUMPRODUCT(MAX((Jobs!$J$5:$J$604=A23)*((Jobs!$P$5:$P$604="Completed")+(Jobs!$P$5:$P$604="Invoiced"))*Jobs!$B$5:$B$604)))) -> 0 | AE23: =IF(A23="","",IFERROR(AVERAGEIFS(Jobs!$AK$5:$AK$604,Jobs!$J$5:$J$604,A23,Jobs!$AK$5:$AK$604,">0"),"")) -> 0 | AF23: =IF(OR(AE23="",X23=""),"",AE23-X23) -> 0 | AG23: =IF(A23="","",SUMIFS(Jobs!$AJ$5:$AJ$604,Jobs!$J$5:$J$604,A23,Jobs!$P$5:$P$604,"Invoiced")+SUMIFS(Jobs!$AJ$5:$AJ$604,Jobs!$J$5:$J$604,A23,Jobs!$P$5:$P$604,"Completed")) -> 0 | AH23: =IF(B23="","",IF(C23="","Add - no client linked",IF(IFERROR(INDEX(Clients!$B$5:$B$204,MATCH(C23,Clients!$A$5:$A$204,0)),"")="","Check - client ID not found",IF(AND(G23="",H23=""),"Add - size needed to price it",IF(AND(AF23<>"",AF23>0.5),"Check - runs over the estimate",IF(N23="","Add - how do we get in?","OK")))))) -> 0
A24: =IF(B24="","",PropertyPrefix&TEXT(ROW()-4,"0000")) -> 0 | D24: =IF(C24="","",IFERROR(INDEX(Clients!$B$5:$B$204,MATCH(C24,Clients!$A$5:$A$204,0)),"Not found")) -> 0 | W24: =IF(B24="","",MAX(IF(H24="",0,H24)*0.45+IF(I24="",0,I24)*0.6+IF(J24="",0,J24)*0.3,IF(G24="",0,G24)/650)) -> 0 | X24: =IF(B24="","",ROUND(MAX(1,W24)*IFERROR(INDEX(ConditionFactors,MATCH(L24,ConditionNames,0)),1),2)) -> 0 | Y24: =IF(B24="","",ROUND(X24/MAX(1,CleanersPerJob),2)) -> 0 | Z24: =IF(B24="","",MAX(MinimumCharge,ROUND(X24*IF(IFERROR(INDEX(Clients!$O$5:$O$204,MATCH(C24,Clients!$A$5:$A$204,0)),0)>0,INDEX(Clients!$O$5:$O$204,MATCH(C24,Clients!$A$5:$A$204,0)),HourlyRate)+IF(M24="",0,IF(M24="None",0,PetSurcharge)),2))) -> 0 | AA24: =IF(B24="","",ROUND(X24*CostPerHour,2)) -> 0 | AB24: =IF(B24="","",IF(Z24=0,"",(Z24-AA24-X24*SuppliesPerHour)/Z24)) -> 0 | AC24: =IF(A24="","",COUNTIFS(Jobs!$J$5:$J$604,A24)) -> 0 | AD24: =IF(A24="","",IF(SUMPRODUCT(MAX((Jobs!$J$5:$J$604=A24)*((Jobs!$P$5:$P$604="Completed")+(Jobs!$P$5:$P$604="Invoiced"))*Jobs!$B$5:$B$604))=0,"",SUMPRODUCT(MAX((Jobs!$J$5:$J$604=A24)*((Jobs!$P$5:$P$604="Completed")+(Jobs!$P$5:$P$604="Invoiced"))*Jobs!$B$5:$B$604)))) -> 0 | AE24: =IF(A24="","",IFERROR(AVERAGEIFS(Jobs!$AK$5:$AK$604,Jobs!$J$5:$J$604,A24,Jobs!$AK$5:$AK$604,">0"),"")) -> 0 | AF24: =IF(OR(AE24="",X24=""),"",AE24-X24) -> 0 | AG24: =IF(A24="","",SUMIFS(Jobs!$AJ$5:$AJ$604,Jobs!$J$5:$J$604,A24,Jobs!$P$5:$P$604,"Invoiced")+SUMIFS(Jobs!$AJ$5:$AJ$604,Jobs!$J$5:$J$604,A24,Jobs!$P$5:$P$604,"Completed")) -> 0 | AH24: =IF(B24="","",IF(C24="","Add - no client linked",IF(IFERROR(INDEX(Clients!$B$5:$B$204,MATCH(C24,Clients!$A$5:$A$204,0)),"")="","Check - client ID not found",IF(AND(G24="",H24=""),"Add - size needed to price it",IF(AND(AF24<>"",AF24>0.5),"Check - runs over the estimate",IF(N24="","Add - how do we get in?","OK")))))) -> 0
A25: =IF(B25="","",PropertyPrefix&TEXT(ROW()-4,"0000")) -> 0 | D25: =IF(C25="","",IFERROR(INDEX(Clients!$B$5:$B$204,MATCH(C25,Clients!$A$5:$A$204,0)),"Not found")) -> 0 | W25: =IF(B25="","",MAX(IF(H25="",0,H25)*0.45+IF(I25="",0,I25)*0.6+IF(J25="",0,J25)*0.3,IF(G25="",0,G25)/650)) -> 0 | X25: =IF(B25="","",ROUND(MAX(1,W25)*IFERROR(INDEX(ConditionFactors,MATCH(L25,ConditionNames,0)),1),2)) -> 0 | Y25: =IF(B25="","",ROUND(X25/MAX(1,CleanersPerJob),2)) -> 0 | Z25: =IF(B25="","",MAX(MinimumCharge,ROUND(X25*IF(IFERROR(INDEX(Clients!$O$5:$O$204,MATCH(C25,Clients!$A$5:$A$204,0)),0)>0,INDEX(Clients!$O$5:$O$204,MATCH(C25,Clients!$A$5:$A$204,0)),HourlyRate)+IF(M25="",0,IF(M25="None",0,PetSurcharge)),2))) -> 0 | AA25: =IF(B25="","",ROUND(X25*CostPerHour,2)) -> 0 | AB25: =IF(B25="","",IF(Z25=0,"",(Z25-AA25-X25*SuppliesPerHour)/Z25)) -> 0 | AC25: =IF(A25="","",COUNTIFS(Jobs!$J$5:$J$604,A25)) -> 0 | AD25: =IF(A25="","",IF(SUMPRODUCT(MAX((Jobs!$J$5:$J$604=A25)*((Jobs!$P$5:$P$604="Completed")+(Jobs!$P$5:$P$604="Invoiced"))*Jobs!$B$5:$B$604))=0,"",SUMPRODUCT(MAX((Jobs!$J$5:$J$604=A25)*((Jobs!$P$5:$P$604="Completed")+(Jobs!$P$5:$P$604="Invoiced"))*Jobs!$B$5:$B$604)))) -> 0 | AE25: =IF(A25="","",IFERROR(AVERAGEIFS(Jobs!$AK$5:$AK$604,Jobs!$J$5:$J$604,A25,Jobs!$AK$5:$AK$604,">0"),"")) -> 0 | AF25: =IF(OR(AE25="",X25=""),"",AE25-X25) -> 0 | AG25: =IF(A25="","",SUMIFS(Jobs!$AJ$5:$AJ$604,Jobs!$J$5:$J$604,A25,Jobs!$P$5:$P$604,"Invoiced")+SUMIFS(Jobs!$AJ$5:$AJ$604,Jobs!$J$5:$J$604,A25,Jobs!$P$5:$P$604,"Completed")) -> 0 | AH25: =IF(B25="","",IF(C25="","Add - no client linked",IF(IFERROR(INDEX(Clients!$B$5:$B$204,MATCH(C25,Clients!$A$5:$A$204,0)),"")="","Check - client ID not found",IF(AND(G25="",H25=""),"Add - size needed to price it",IF(AND(AF25<>"",AF25>0.5),"Check - runs over the estimate",IF(N25="","Add - how do we get in?","OK")))))) -> 0
A26: =IF(B26="","",PropertyPrefix&TEXT(ROW()-4,"0000")) -> 0 | D26: =IF(C26="","",IFERROR(INDEX(Clients!$B$5:$B$204,MATCH(C26,Clients!$A$5:$A$204,0)),"Not found")) -> 0 | W26: =IF(B26="","",MAX(IF(H26="",0,H26)*0.45+IF(I26="",0,I26)*0.6+IF(J26="",0,J26)*0.3,IF(G26="",0,G26)/650)) -> 0 | X26: =IF(B26="","",ROUND(MAX(1,W26)*IFERROR(INDEX(ConditionFactors,MATCH(L26,ConditionNames,0)),1),2)) -> 0 | Y26: =IF(B26="","",ROUND(X26/MAX(1,CleanersPerJob),2)) -> 0 | Z26: =IF(B26="","",MAX(MinimumCharge,ROUND(X26*IF(IFERROR(INDEX(Clients!$O$5:$O$204,MATCH(C26,Clients!$A$5:$A$204,0)),0)>0,INDEX(Clients!$O$5:$O$204,MATCH(C26,Clients!$A$5:$A$204,0)),HourlyRate)+IF(M26="",0,IF(M26="None",0,PetSurcharge)),2))) -> 0 | AA26: =IF(B26="","",ROUND(X26*CostPerHour,2)) -> 0 | AB26: =IF(B26="","",IF(Z26=0,"",(Z26-AA26-X26*SuppliesPerHour)/Z26)) -> 0 | AC26: =IF(A26="","",COUNTIFS(Jobs!$J$5:$J$604,A26)) -> 0 | AD26: =IF(A26="","",IF(SUMPRODUCT(MAX((Jobs!$J$5:$J$604=A26)*((Jobs!$P$5:$P$604="Completed")+(Jobs!$P$5:$P$604="Invoiced"))*Jobs!$B$5:$B$604))=0,"",SUMPRODUCT(MAX((Jobs!$J$5:$J$604=A26)*((Jobs!$P$5:$P$604="Completed")+(Jobs!$P$5:$P$604="Invoiced"))*Jobs!$B$5:$B$604)))) -> 0 | AE26: =IF(A26="","",IFERROR(AVERAGEIFS(Jobs!$AK$5:$AK$604,Jobs!$J$5:$J$604,A26,Jobs!$AK$5:$AK$604,">0"),"")) -> 0 | AF26: =IF(OR(AE26="",X26=""),"",AE26-X26) -> 0 | AG26: =IF(A26="","",SUMIFS(Jobs!$AJ$5:$AJ$604,Jobs!$J$5:$J$604,A26,Jobs!$P$5:$P$604,"Invoiced")+SUMIFS(Jobs!$AJ$5:$AJ$604,Jobs!$J$5:$J$604,A26,Jobs!$P$5:$P$604,"Completed")) -> 0 | AH26: =IF(B26="","",IF(C26="","Add - no client linked",IF(IFERROR(INDEX(Clients!$B$5:$B$204,MATCH(C26,Clients!$A$5:$A$204,0)),"")="","Check - client ID not found",IF(AND(G26="",H26=""),"Add - size needed to price it",IF(AND(AF26<>"",AF26>0.5),"Check - runs over the estimate",IF(N26="","Add - how do we get in?","OK")))))) -> 0
A27: =IF(B27="","",PropertyPrefix&TEXT(ROW()-4,"0000")) -> 0 | D27: =IF(C27="","",IFERROR(INDEX(Clients!$B$5:$B$204,MATCH(C27,Clients!$A$5:$A$204,0)),"Not found")) -> 0 | W27: =IF(B27="","",MAX(IF(H27="",0,H27)*0.45+IF(I27="",0,I27)*0.6+IF(J27="",0,J27)*0.3,IF(G27="",0,G27)/650)) -> 0 | X27: =IF(B27="","",ROUND(MAX(1,W27)*IFERROR(INDEX(ConditionFactors,MATCH(L27,ConditionNames,0)),1),2)) -> 0 | Y27: =IF(B27="","",ROUND(X27/MAX(1,CleanersPerJob),2)) -> 0 | Z27: =IF(B27="","",MAX(MinimumCharge,ROUND(X27*IF(IFERROR(INDEX(Clients!$O$5:$O$204,MATCH(C27,Clients!$A$5:$A$204,0)),0)>0,INDEX(Clients!$O$5:$O$204,MATCH(C27,Clients!$A$5:$A$204,0)),HourlyRate)+IF(M27="",0,IF(M27="None",0,PetSurcharge)),2))) -> 0 | AA27: =IF(B27="","",ROUND(X27*CostPerHour,2)) -> 0 | AB27: =IF(B27="","",IF(Z27=0,"",(Z27-AA27-X27*SuppliesPerHour)/Z27)) -> 0 | AC27: =IF(A27="","",COUNTIFS(Jobs!$J$5:$J$604,A27)) -> 0 | AD27: =IF(A27="","",IF(SUMPRODUCT(MAX((Jobs!$J$5:$J$604=A27)*((Jobs!$P$5:$P$604="Completed")+(Jobs!$P$5:$P$604="Invoiced"))*Jobs!$B$5:$B$604))=0,"",SUMPRODUCT(MAX((Jobs!$J$5:$J$604=A27)*((Jobs!$P$5:$P$604="Completed")+(Jobs!$P$5:$P$604="Invoiced"))*Jobs!$B$5:$B$604)))) -> 0 | AE27: =IF(A27="","",IFERROR(AVERAGEIFS(Jobs!$AK$5:$AK$604,Jobs!$J$5:$J$604,A27,Jobs!$AK$5:$AK$604,">0"),"")) -> 0 | AF27: =IF(OR(AE27="",X27=""),"",AE27-X27) -> 0 | AG27: =IF(A27="","",SUMIFS(Jobs!$AJ$5:$AJ$604,Jobs!$J$5:$J$604,A27,Jobs!$P$5:$P$604,"Invoiced")+SUMIFS(Jobs!$AJ$5:$AJ$604,Jobs!$J$5:$J$604,A27,Jobs!$P$5:$P$604,"Completed")) -> 0 | AH27: =IF(B27="","",IF(C27="","Add - no client linked",IF(IFERROR(INDEX(Clients!$B$5:$B$204,MATCH(C27,Clients!$A$5:$A$204,0)),"")="","Check - client ID not found",IF(AND(G27="",H27=""),"Add - size needed to price it",IF(AND(AF27<>"",AF27>0.5),"Check - runs over the estimate",IF(N27="","Add - how do we get in?","OK")))))) -> 0
A28: =IF(B28="","",PropertyPrefix&TEXT(ROW()-4,"0000")) -> 0 | D28: =IF(C28="","",IFERROR(INDEX(Clients!$B$5:$B$204,MATCH(C28,Clients!$A$5:$A$204,0)),"Not found")) -> 0 | W28: =IF(B28="","",MAX(IF(H28="",0,H28)*0.45+IF(I28="",0,I28)*0.6+IF(J28="",0,J28)*0.3,IF(G28="",0,G28)/650)) -> 0 | X28: =IF(B28="","",ROUND(MAX(1,W28)*IFERROR(INDEX(ConditionFactors,MATCH(L28,ConditionNames,0)),1),2)) -> 0 | Y28: =IF(B28="","",ROUND(X28/MAX(1,CleanersPerJob),2)) -> 0 | Z28: =IF(B28="","",MAX(MinimumCharge,ROUND(X28*IF(IFERROR(INDEX(Clients!$O$5:$O$204,MATCH(C28,Clients!$A$5:$A$204,0)),0)>0,INDEX(Clients!$O$5:$O$204,MATCH(C28,Clients!$A$5:$A$204,0)),HourlyRate)+IF(M28="",0,IF(M28="None",0,PetSurcharge)),2))) -> 0 | AA28: =IF(B28="","",ROUND(X28*CostPerHour,2)) -> 0 | AB28: =IF(B28="","",IF(Z28=0,"",(Z28-AA28-X28*SuppliesPerHour)/Z28)) -> 0 | AC28: =IF(A28="","",COUNTIFS(Jobs!$J$5:$J$604,A28)) -> 0 | AD28: =IF(A28="","",IF(SUMPRODUCT(MAX((Jobs!$J$5:$J$604=A28)*((Jobs!$P$5:$P$604="Completed")+(Jobs!$P$5:$P$604="Invoiced"))*Jobs!$B$5:$B$604))=0,"",SUMPRODUCT(MAX((Jobs!$J$5:$J$604=A28)*((Jobs!$P$5:$P$604="Completed")+(Jobs!$P$5:$P$604="Invoiced"))*Jobs!$B$5:$B$604)))) -> 0 | AE28: =IF(A28="","",IFERROR(AVERAGEIFS(Jobs!$AK$5:$AK$604,Jobs!$J$5:$J$604,A28,Jobs!$AK$5:$AK$604,">0"),"")) -> 0 | AF28: =IF(OR(AE28="",X28=""),"",AE28-X28) -> 0 | AG28: =IF(A28="","",SUMIFS(Jobs!$AJ$5:$AJ$604,Jobs!$J$5:$J$604,A28,Jobs!$P$5:$P$604,"Invoiced")+SUMIFS(Jobs!$AJ$5:$AJ$604,Jobs!$J$5:$J$604,A28,Jobs!$P$5:$P$604,"Completed")) -> 0 | AH28: =IF(B28="","",IF(C28="","Add - no client linked",IF(IFERROR(INDEX(Clients!$B$5:$B$204,MATCH(C28,Clients!$A$5:$A$204,0)),"")="","Check - client ID not found",IF(AND(G28="",H28=""),"Add - size needed to price it",IF(AND(AF28<>"",AF28>0.5),"Check - runs over the estimate",IF(N28="","Add - how do we get in?","OK")))))) -> 0
