Workbook
Name AllocationList: Lists!$C$122:$C$134
Name BatchIDs: OFFSET(Batches!$A$5,0,0,MAX(1,COUNTIF(Batches!$A$5:$A$204,"?*")),1)
Name BatchPrefix: Settings!$D$98
Name BatchStatusList: Lists!$A$146:$A$162
Name BeCm: 'Profit & Break-Even'!$C$21
Name BeContribution: 'Profit & Break-Even'!$C$20
Name BeFeeFixed: 'Profit & Break-Even'!$D$12
Name BeFeePct: 'Profit & Break-Even'!$D$11
Name BeFees: 'Profit & Break-Even'!$C$18
Name BeFixed: 'Profit & Break-Even'!$D$7
Name BeFixedTotal: 'Profit & Break-Even'!$C$16
Name BeP: 'Profit & Break-Even'!$C$17
Name BePrice: 'Profit & Break-Even'!$D$9
Name BeProduct: 'Profit & Break-Even'!$D$6
Name BeVar: 'Profit & Break-Even'!$C$19
Name BeVariable: 'Profit & Break-Even'!$D$10
Name BeWage: 'Profit & Break-Even'!$D$8
Name BundleIDs: OFFSET(Bundles!$A$5,0,0,MAX(1,COUNTIF(Bundles!$A$5:$A$64,"?*")),1)
Name BundlePrefix: Settings!$D$96
Name BundleTypeList: Lists!$C$265:$C$280
Name CandlePrefix: Settings!$D$107
Name CategoryList: Lists!$E$9:$E$31
Name ChannelList: Lists!$I$9:$I$23
Name ChannelNames: OFFSET(Channels!$A$5,0,0,MAX(1,COUNTIF(Channels!$A$5:$A$18,"?*")),1)
Name ClothingPrefix: Settings!$D$108
Name ContractorRate: Settings!$D$30
Name CrochetPrefix: Settings!$D$105
Name CurrencyFee: Settings!$D$65
Name CustomerIDs: OFFSET('Wholesale Customers'!$A$5,0,0,MAX(1,COUNTIF('Wholesale Customers'!$A$5:$A$64,"?*")),1)
Name CustomerNames: OFFSET('Wholesale Customers'!$B$5,0,0,MAX(1,COUNTIF('Wholesale Customers'!$B$5:$B$64,"?*")),1)
Name CustomerPrefix: Settings!$D$100
Name CustomerTypeList: Lists!$I$146:$I$164
Name DashKey: Dashboard!$H$5
Name DefaultBatchSize: Settings!$D$35
Name DefaultChannel: Settings!$D$71
Name DefaultDefect: Settings!$D$41
Name DefaultDiscount: Settings!$D$80
Name DefaultMarkup: Settings!$D$76
Name DefaultPackaging: Settings!$D$45
Name DefaultShipping: Settings!$D$46
Name DefaultWaste: Settings!$D$40
Name DevPrefix: Settings!$D$102
Name DevStageList: Lists!$A$192:$A$207
Name DifficultyList: Lists!$A$65:$A$77
Name DiffNames: Lists!$A$320:$A$328
Name DiffPriceFactors: Lists!$C$320:$C$328
Name DiffTimeFactors: Lists!$B$320:$B$328
Name DigitalPrefix: Settings!$D$110
Name DigitalTypeList: Lists!$G$241:$G$260
Name EmployeeRate: Settings!$D$29
Name EventNames: OFFSET(Events!$A$5,0,0,MAX(1,COUNTIF(Events!$A$5:$A$44,"?*")),1)
Name EventPrefix: Settings!$D$103
Name EventTypeList: Lists!$G$146:$G$163
Name FabricList: Lists!$I$215:$I$238
Name FeeReviewDays: Settings!$D$69
Name FeesOnShipping: Settings!$D$66
Name FeesOnTax: Settings!$D$67
Name FeesReviewed: Settings!$D$68
Name FeesStale: Settings!$D$70
Name FeeTypeList: Lists!$E$122:$E$136

Sheet Start Here
A1: Handmade Product Pricing & Profit Calculator | H1: Novality Store | v1.0.0
A2: Materials, labour, packaging, fees and overhead - turned into a price that pays you.
A3: > Start Here | C3: > Dashboard | E3: > Products | G3: > Materials | I3: > Labour
A5: Most handmade pricing advice stops at 'materials times two'. That is why so many makers work for nothing. This workbook counts the yarn, the hours, the box, the postage, the Etsy fees and the studio rent, then solves for the price that leaves the margin you actually want.
A7: Five minutes to your first honest price
B8: Step | C8: Where | D8: What to do
B9: 1 | C9: Settings | D9: Put your hourly rate in. That one number changes more than anything else here.
B10: 2 | C10: Materials | D10: Add the three or four materials the product uses, with what you paid and how much came in the pack.
B11: 3 | C11: Material Usage | D11: List how much of each goes into one piece.
B12: 4 | C12: Labor | D12: Put the minutes in - all of them, including finishing and packing.
B13: 5 | C13: Products | D13: Add the product. Cost, suggested price, margin and your hourly wage appear.
B14: 6 | C14: Retail Calculator | D14: Check the price, try the ladder, and decide.
A16: The formula everything is built on
B17: Marketplace fees are charged on the price - the price you have not worked out yet. That is why you cannot just add 20% to your costs: the fee is charged on the fee. Solving it properly looks like this.
B18: Cost | C18: C = materials + labour + packaging + postage + overhead | G18: What one piece costs you.
B19: Labour | C19: L = minutes / 60 x your hourly rate | G19: Every minute, not just the fun ones.
B20: Price | C20: Price = (C + fixed fees) / (1 - target margin - fee rate) | G20: The price that leaves the margin you asked for, after the percentage fees.
B21: Margin | C21: Margin = profit / price x 100 | G21: The share of the price you keep.
B22: Markup | C22: Markup = profit / cost x 100 | G22: The share of the cost you added. Not the same thing.
B23: Break-even | C23: Units = fixed costs / contribution a unit | G23: Rounded up, because you cannot sell two thirds of a candle.
B25: Worked example. A beanie costs $8.40 in yarn and labour, $1.85 to package and post, and carries $1.20 of overhead - $11.45. Etsy takes about 9.5% plus $0.45. You want a 55% margin. The price is (11.45 + 0.45) / (1 - 0.55 - 0.095) = $33.52, rounded to $33.99. Adding 55% to the cost would have given $17.75 and a real margin of 25%.
A27: What is in the file
B28: Tab | C28: What it does | D28: Your job
B29: Settings | C29: Your rates, targets, fee rates, rounding rule and every default | H29: Fill in once, review twice a year
B30: Dashboard | C30: Your margins, your month and everything that needs fixing | H30: Read it weekly
B31: Products | C31: The catalog: cost, price, margin, hourly wage and what sold | H31: The heart of the workbook
B32: Materials | C32: Every yarn, bead, wax and board, with the cost per gram worked out | H32: Add as you buy
B33: Material Usage | C33: How much of each material goes into each product | H33: The bill of materials
B34: Labor | C34: Minutes per stage, per item or per batch | H34: Be honest about the time
B35: Packaging / Shipping | C35: Boxes, tissue, labels, postage services and what you absorb | H35: Set up once
B36: Overhead | C36: Studio, insurance, subscriptions - shared across what you make | H36: Add your bills
B37: Channels | C37: Etsy, Shopify, markets, wholesale - every fee, fully editable | H37: Check twice a year
B38: Retail Calculator | C38: The price, the ladder and the sanity check | H38: Use before you list
B39: Wholesale Calculator | C39: What a stockist leaves you and what retail price supports it | H39: Use before you say yes
B40: Profit & Break-Even | C40: Contribution, break-even units, margin against markup | H40: Use when you are planning
... B51: Lists / Help | C51: Every drop-down, every factor table, and the troubleshooting | H51: Edit the lists
A53: A rhythm that keeps it accurate
B54: As you buy | C54: Add new materials with the pack price and pack size. Nothing else is needed. | I54: 1 minute
B55: As you make | C55: Log batches with the real hours. Two runs and your estimates become facts. | I55: 2 minutes
B56: Every week | C56: Enter the week's sales with the real fees and postage. | I56: 15 minutes
B57: Every month | C57: Read the Dashboard. Fix anything below minimum wage before you make more of it. | I57: 20 minutes
B58: Every quarter | C58: Check your material prices and the fee rates on the Channels tab. Both move. | I58: 30 minutes
B59: Twice a year | C59: Re-price. Log every change on Price History so you can see what worked. | I59: 1 hour
A61: What the workbook does by itself
B62: Turns a pack price into a cost per gram, millilitre or centimetre, and applies your waste allowance.
B63: Adds every material and every labour stage into a cost per piece, with a difficulty factor for the fiddly ones.
B64: Solves for the price that leaves your target margin after percentage fees and fixed fees - separately, because they behave differently.
B65: Applies your rounding rule so prices come out at $33.99 rather than $33.52.
B66: Warns you when a product pays under minimum wage, loses money, or has not been re-priced while its materials moved.
B67: Prices six crafts the way those crafts actually work - skeins and hooks, grams of silver and scrap recovery, wax and fragrance load, fabric and size factors, timber and offcuts, design time spread over expected sales.
B68: Works out wholesale both ways: what a discount leaves you, and what retail price would make it work.
B69: Shows break-even in units, in money and in hours.
B70: Compares what you estimated with what the batch really cost and what the marketplace really charged.
B71: Tells you what a discount costs in profit and how much more you would have to sell to stand still.
A73: What it honestly cannot do
B74: Every one of these needs something outside a spreadsheet. Anyone who tells you otherwise is selling you something.
B75: Know the current Etsy, Shopify or Amazon Handmade fees. They change, they vary by country, and they are different for offsite ads. Put your real rates on the Channels tab and check them against the official fee schedule twice a year.
B76: Pull your orders in automatically. Export a CSV from your shop and paste it into the Sales tab.
B77: Tell you what your market will pay. It tells you what you need - the Competitors tab is where you record the other half.
B78: Make a product sell. A correct price on a bad photograph sells nothing.
B79: Handle sales tax, VAT or import duty properly. It has a simple tax rate and nothing more.
B80: Replace an accountant, and it does not know your local rules on labelling, safety testing or candle regulations.
A82: About marketplace fees
B83: ="Every fee in this workbook is a number you can edit on the Channels tab, because published fees change and vary by country. The rates in this file were last reviewed on "&TEXT(FeesReviewed,"d mmmm yyyy")&". Before you rely on a price, verify the current official fee schedule for your marketplace and your country, and update the Channels tab." -> 0
A85: Housekeeping
B86: Question | C86: Answer
B87: Is there example data in it? | C87: Both versions are in your download: one filled with a worked example shop, one empty and ready for yours.
B88: How do I clear the example? | C88: Select the data rows on a tab and press Delete. The formula columns refill themselves - they are not deleted.
B89: Why are some cells locked? | C89: Every calculated cell is protected so a stray paste cannot break it. The password is 'premium'. Review, Unprotect Sheet if you want to change a formula.
B90: Which cells do I type in? | C90: The white ones. Shaded cells work themselves out.
B91: Can I change the currency? | C91: Yes - the Settings tab holds the symbol, and every money cell follows it.
B92: Does it work in Google Sheets? | C92: Yes. File, Import, Upload. Drop-downs and colours come across; sheet protection behaves a little differently.
B93: Which Excel versions? | C93: Excel 2010 and newer, Excel for Mac, Excel online, LibreOffice Calc and Google Sheets. No macros, so there is nothing to enable.
B94: Can I add more rows? | C94: Yes - insert rows inside the existing block and copy the formulas down. Never insert above the header row.
B95: My craft is not one of the six tabs | C95: Use the Products, Materials and Labor tabs - they work for anything. The six specialist tabs are shortcuts, not requirements.
B97: Handmade Product Pricing & Profit Calculator - version 1.0.0, by Novality Store. Built with formulas only: no macros, no add-ins, nothing to install. The Help tab has the troubleshooting and a map of every feature.

Sheet Settings
A1: Business Settings | G1: Novality Store | v1.0.0
A2: Fill in the white cells once. Shaded cells are locked formulas. Every price, every margin and every warning in the workbook reads these values.
A3: > Start Here | C3: > Dashboard | E3: > Products | G3: > Materials
A5: 1. Your shop
B6: Business name | D6: Willow & Thread Handmade | F6: Shown on every quote, order form and printable page.
B7: Maker / owner | D7: Maya Albright
B8: Brand name | D8: Willow & Thread | F8: If you trade under a shorter name than the business one.
B9: Email | D9: hello@willowandthread.co
B10: Phone | D10: (828) 555 0176
B11: Address | D11: 42 Larkspur Lane, Asheville, NC 28801
B12: Website | D12: willowandthread.co
B13: Marketplace shop name | D13: WillowAndThreadCo | F13: Your Etsy / Amazon Handmade / Folksy shop name, for the order forms.
B14: Social handle | D14: @willowandthread
B15: Tagline | D15: Small batch crochet, candles and keepsakes since 2021
B16: Business / tax number | D16: NC-HM-2021-4471
A18: 2. Dates
B19: Year | D19: 2026 | E19: The year the reports and the sales summaries open on.
B20: Today | D20: =TODAY() -> 0 | E20: Every 'due', 'stale price' and 'review the fees' flag counts from this cell, so they all move on by themselves overnight.
B21: This month starts | D21: =DATE(YEAR(TodayDate),MONTH(TodayDate),1) -> 0
B22: This month ends | D22: =DATE(YEAR(TodayDate),MONTH(TodayDate)+1,1)-1 -> 0
B23: This year starts | D23: =DATE(PlanYear,1,1) -> 0
A25: 3. What your time is worth
B26: The single number most handmade sellers get wrong. If your products do not pay you for the hours you spend making them, you do not have a business, you have an expensive hobby. Pay yourself a real wage here and let the prices follow.
B27: What you pay yourself an hour | D27: 25 | E27: What one hour of your making time costs. Not what is left over - what you are worth.
B28: Local minimum wage (for the warning) | D28: 15 | E28: The workbook flags any product whose price pays you less than this an hour.
B29: Employee hourly rate | D29: 18
B30: Contractor / outsourced hourly rate | D30: 32 | E30: Used when a labour line says somebody else made it.
B31: On-costs on paid labour | D31: 0.12 | E31: Employer tax, insurance and holiday pay. Added to employee and contractor hours.
B32: Your hour, with on-costs | D32: =ROUND(HourlyRate*(1+PayrollBurden),2) -> 0 | E32: This is the rate the labour calculator multiplies your minutes by.
B33: Hours a month you actually make things | D33: 70 | E33: Bench hours only - not admin, not photos, not scrolling. Overhead per hour is divided by this.
B34: Items a month you usually finish | D34: 24 | E34: Used when overhead is spread per item instead of per hour.
B35: Default batch size | D35: 10
B36: Consumables an hour | D36: 0.6 | E36: Glue, needles, sandpaper, thread - the small things nobody itemises. Added per labour hour.
A38: 4. Materials and waste
B39: Measurement system | D39: Metric | E39: Metric weighs in grams, imperial in ounces. The unit table on Lists converts either way.
B40: Default waste allowance | D40: 0.05 | E40: Offcuts, frogged rows, the last inch of a board. Added to every material line that does not set its own.
B41: Default defect / seconds rate | D41: 0.03 | E41: The share of a batch that never makes it to the shop. The batch tab spreads its cost over the pieces that do.
B42: Days of stock that counts as low | D42: 21
A44: 5. Packaging and shipping
B45: Fallback packaging cost | D45: 1.85 | E45: Used for a product that has not picked a packaging profile on the Packaging tab.
B46: Shipping you absorb | D46: 0 | E46: Only what you pay and do not charge on. Postage the buyer pays is not your cost - the workbook keeps the two apart.
B47: Free shipping over | D47: 50 | E47: Orders above this are shipped free, so the postage becomes your cost.
A49: 6. Overhead
B50: Rent, insurance, the shop subscription, the website, the accountant. Type the bills on the Overhead tab - this is only how they get spread across your products.
B51: Spread overhead | D51: Per hour worked | E51: Per hour is the fairest for slow, careful work. Per item suits a maker who turns out many small, similar pieces.
B52: Overhead a month (from the Overhead tab) | D52: =ROUND(SUMPRODUCT(IFERROR(Overhead!$L$5:$L$44*1,0)),2) -> 0
B53: Overhead per hour worked | D53: =IF(ProductiveHours<=0,0,ROUND(OverheadMonthly/ProductiveHours,2)) -> 0
B54: Overhead per item made | D54: =IF(UnitsPerMonth<=0,0,ROUND(OverheadMonthly/UnitsPerMonth,2)) -> 0
A56: 7. Marketplace fees
B57: IMPORTANT: marketplace fees change, and they differ by country. The figures below are the defaults this workbook shipped with - verify them against the current official fee schedule for your shop and your region before you trust a price. Every one of them is editable here, and every channel can override them on the Channels tab.
B58: Listing fee (per listing) | D58: 0.2 | E58: Charged when you list and again when the listing renews.
B59: Transaction fee | D59: 0.065 | E59: A percentage of what the buyer pays.
B60: Payment processing % | D60: 0.03
B61: Payment processing fixed | D61: 0.25 | E61: The flat part - this is what quietly eats small orders alive.
B62: Offsite ads fee | D62: 0.15 | E62: Only charged on orders that came from the marketplace's own advertising.
B63: Share of orders from offsite ads | D63: 0.2 | E63: Used to work out the average ads cost per order. Check your own statements.
B64: Regulatory operating fee | D64: 0.004 | E64: Charged in some countries only. Set it to 0 if your shop is not in one.
B65: Currency conversion fee | D65: 0.025 | E65: Applies when you are paid in a currency other than your bank's.
B66: Fees charged on shipping too? | D66: Yes | E66: On most marketplaces the transaction fee applies to the postage the buyer paid as well.
B67: Fees charged on sales tax? | D67: No
B68: Fee schedule last reviewed | D68: 46317 | E68: Put today's date here each time you check the official fee page. The dashboard nags you when it goes stale.
B69: Review the fee schedule every (days) | D69: 180
B70: Fees are stale | D70: =IF(FeesReviewed="","Never reviewed",IF(TodayDate-FeesReviewed>FeeReviewDays,"Check the fee schedule","OK")) -> 0
B71: Default sales channel | D71: Etsy | E71: The channel a new product is priced for until you pick another.
A73: 8. Pricing rules
B74: Target retail margin | D74: 0.3 | E74: Margin, not markup. 55% margin means 55 cents of every dollar you take is left after costs and fees.
B75: Target wholesale margin | D75: 0.2 | E75: Lower than retail, because the shop does the selling. It must still be positive.
B76: Default markup on cost | D76: 1.2 | E76: Markup is a percentage OF YOUR COST. 100% markup is a 50% margin - the workbook shows both so you never confuse them again.
B77: Wholesale is this much off retail | D77: 0.4 | E77: The traditional handmade rule is half the retail price. Only sustainable if the retail price was built properly in the first place.
B78: Warn below this margin | D78: 0.15 | E78: Any product under this turns amber on the catalog and appears on the dashboard.
B79: Round prices to | D79: Nearest 0.99 | E79: Charm pricing always rounds UP, so a rounded price can never fall below the price the maths asked for.
B80: Usual discount | D80: 0.1 | E80: What a sale usually knocks off. The promotion tab shows what each one costs you.
B81: Sales tax / VAT on your prices | D81: 0 | E81: Leave at 0 if you are not registered or the marketplace handles it for you.
B82: Minimum wholesale order (items) | D82: 6
B83: Minimum wholesale order (value) | D83: 150
B84: Review a price after (days) | D84: 180 | E84: Material costs drift upwards quietly. This is how long a price can go unchecked.
A86: 9. Targets
B87: Revenue target a month | D87: 2400
B88: Revenue target a year | D88: 28800
B89: Profit target a month | D89: 900
B90: Hourly pay you are aiming for | D90: 25 | E90: The dashboard works out what you are actually earning an hour and compares it with this.
A92: 10. ID prefixes
B93: The letters in front of the automatic numbers. Change them before you start entering data, not after.
B94: Product IDs | D94: P-
B95: Material IDs | D95: M-
B96: Bundle IDs | D96: BN-
B97: Variation IDs | D97: VR-
B98: Batch IDs | D98: BT-
B99: Sale IDs | D99: SL-
B100: Wholesale customer IDs | D100: WC-
B101: Wholesale order IDs | D101: WO-
B102: Development IDs | D102: DV-
B103: Event IDs | D103: EV-
B104: Waste log IDs | D104: WL-
B105: Crochet sheet IDs | D105: CRO-
... B110: Digital sheet IDs | D110: DIG-
A112: 11. About this workbook
B113: Product | D113: Handmade Product Pricing & Profit Calculator
B114: Version | D114: 1.0.0
B115: Created by | D115: Novality Store
...

Sheet Dashboard
A1: Pricing Dashboard | L1: Novality Store | v1.0.0
A2: Your range, your margins and your month - worked out from the products, costs and sales you have already entered.
A3: > Start Here | C3: > Dashboard | E3: > Products | G3: > Materials | I3: > Labour | K3: > Retail Price | M3: > Wholesale
A5: Shop | B5: =ShopName -> 0 | E5: Month | F5: =TEXT(TodayDate,"mmmm yyyy") -> 0 | G5: Month key | H5: =TEXT(TodayDate,"yyyy-mm") -> 0 | I5: Today | K5: =TodayDate -> 0
A7: Products priced | D7: Average margin | G7: Average you earn an hour | J7: Products below target
A8: =COUNTIF(Products!$B$5:$B$304,"<>") -> 0 | D8: =IFERROR(AVERAGE(Products!$AW$5:$AW$304),"") -> 0 | G8: =IFERROR(AVERAGE(Products!$AZ$5:$AZ$304),"") -> 0 | J8: =COUNTIFS(Products!$AW$5:$AW$304,"<"&MarginWarning,Products!$B$5:$B$304,"<>") -> 0
A9: in the catalog | D9: target 30% | G9: your rate is $25.00 | J9: margin under your warning level
A11: Revenue this month | D11: Profit this month | G11: Margin this month | J11: Items sold this month
A12: =ROUND(SUMIFS(Sales!$V$5:$V$804,Sales!$R$5:$R$804,DashKey),2) -> 0 | D12: =ROUND(SUMIFS(Sales!$AG$5:$AG$804,Sales!$R$5:$R$804,DashKey),2) -> 0 | G12: =IFERROR(SUMIFS(Sales!$AG$5:$AG$804,Sales!$R$5:$R$804,DashKey)/SUMIFS(Sales!$V$5:$V$804,Sales!$R$5:$R$804,DashKey),"") -> 0 | J12: =SUMIFS(Sales!$D$5:$D$804,Sales!$R$5:$R$804,DashKey) -> 0
A13: target $2,400 | D13: after fees and postage | G13: what you actually kept | J13: across every channel
A15: Overhead a month | D15: Covered by this month | G15: Value of your materials | J15: Hours of work sold
A16: =ROUND(OverheadMonthly,2) -> 0 | D16: =IFERROR(SUMIFS(Sales!$AG$5:$AG$804,Sales!$R$5:$R$804,DashKey)/MAX(0.01,OverheadMonthly),"") -> 0 | G16: =ROUND(SUM(Materials!$Y$5:$Y$254),2) -> 0 | J16: =ROUND(SUMIFS(Sales!$AK$5:$AK$804,Sales!$R$5:$R$804,DashKey),1) -> 0
A17: studio, insurance, software | D17: 100% means the studio has paid for itself | G17: money sitting on the shelf | J17: this month
A19: Needs your attention
A20: What | B20: How many | C20: What it means | D20: Where to fix it
A21: Products with no price | B21: =COUNTIFS(Products!$B$5:$B$304,"<>",Products!$AR$5:$AR$304,"") -> 0 | C21: ="Listed in the catalog with nothing to sell them at" -> 0 | M21: Products
A22: Products that lose money | B22: =COUNTIF(Products!$BS$5:$BS$304,"Loss*") -> 0 | C22: ="The price does not cover the cost and the fees" -> 0 | M22: Products
A23: Products below minimum wage | B23: =COUNTIF(Products!$BS$5:$BS$304,"Below*") -> 0 | C23: ="You would earn less than "&TEXT(MinimumWage,"0.00")&" an hour making these" -> 0 | M23: Products
A24: Products under your margin warning | B24: =COUNTIFS(Products!$AW$5:$AW$304,"<"&MarginWarning,Products!$B$5:$B$304,"<>") -> 0 | C24: ="Thinner than "&TEXT(MarginWarning,"0%")&" - one bad month away from nothing" -> 0 | M24: Retail Calculator
A25: Products with no costs entered | B25: =COUNTIF(Products!$BS$5:$BS$304,"Add - no costs*") -> 0 | C25: ="Nothing on the Material Usage or Labor tabs for these" -> 0 | M25: Material Usage
A26: Materials with no price | B26: =COUNTIF(Materials!$AG$5:$AG$254,"Add*") -> 0 | C26: ="Every product using them is under-costed" -> 0 | M26: Materials
A27: Materials running low | B27: =COUNTIF(Materials!$AE$5:$AE$254,"Low stock")+COUNTIF(Materials!$AE$5:$AE$254,"Out of stock") -> 0 | C27: ="Below the reorder level or less than "&LowStockDays&" days of cover" -> 0 | M27: Materials
A28: Prices going stale | B28: =COUNTIF(Products!$BS$5:$BS$304,"Review*") -> 0 | C28: ="Not changed in "&PriceReviewDays&" days, while your costs moved" -> 0 | M28: Price History
A29: Fee settings to check | B29: =IF(FeesStale="Yes",1,0) -> 0 | C29: ="Marketplace fees change. Yours were last reviewed "&TEXT(FeesReviewed,"d mmm yyyy") -> 0 | M29: Channels
A30: Orders that lost money | B30: =COUNTIFS(Sales!$AG$5:$AG$804,"<0") -> 0 | C30: ="Real orders where the money went the wrong way" -> 0 | M30: Sales
A31: Batches costing more than the estimate | B31: =COUNTIF(Batches!$AE$5:$AE$204,"Check - costing*") -> 0 | C31: ="The catalog is optimistic about these" -> 0 | M31: Batches
A32: Wholesale orders below target margin | B32: =COUNTIF('Wholesale Orders'!$AD$5:$AD$204,"Low margin*") -> 0 | C32: ="The discount is deeper than the product can carry" -> 0 | M32: Wholesale Orders
A33: Unpaid wholesale invoices | B33: =ROUND(SUMIFS('Wholesale Orders'!$V$5:$V$204,'Wholesale Orders'!$M$5:$M$204,"No"),0) -> 0 | C33: ="Money shops owe you right now" -> 0 | M33: Wholesale Customers
A34: Avoidable waste this year | B34: =ROUND(SUMIFS('Waste Log'!$L$5:$L$204,'Waste Log'!$G$5:$G$204,"Yes"),0) -> 0 | C34: ="Material you paid for and did not sell" -> 0 | M34: Waste Log
A36: What is working
A37: Most profit a sale | B37: Profit | C37: Best margin | D37: Margin | E37: Best paid an hour | F37: An hour | G37: Most sold | H37: Sold
A38: =IFERROR(INDEX(Products!$B$5:$B$304,MATCH(1,Products!$BO$5:$BO$304,0)),"") -> 0 | B38: =IFERROR(INDEX(Products!$AV$5:$AV$304,MATCH(1,Products!$BO$5:$BO$304,0)),"") -> 0 | C38: =IFERROR(INDEX(Products!$B$5:$B$304,MATCH(1,Products!$BP$5:$BP$304,0)),"") -> 0 | D38: =IFERROR(INDEX(Products!$AW$5:$AW$304,MATCH(1,Products!$BP$5:$BP$304,0)),"") -> 0 | E38: =IFERROR(INDEX(Products!$B$5:$B$304,MATCH(1,Products!$BR$5:$BR$304,0)),"") -> 0 | F38: =IFERROR(INDEX(Products!$AY$5:$AY$304,MATCH(1,Products!$BR$5:$BR$304,0)),"") -> 0 | G38: =IFERROR(INDEX(Products!$B$5:$B$304,MATCH(1,Products!$BQ$5:$BQ$304,0)),"") -> 0 | H38: =IFERROR(INDEX(Products!$BH$5:$BH$304,MATCH(1,Products!$BQ$5:$BQ$304,0)),"") -> 0
A39: =IFERROR(INDEX(Products!$B$5:$B$304,MATCH(2,Products!$BO$5:$BO$304,0)),"") -> 0 | B39: =IFERROR(INDEX(Products!$AV$5:$AV$304,MATCH(2,Products!$BO$5:$BO$304,0)),"") -> 0 | C39: =IFERROR(INDEX(Products!$B$5:$B$304,MATCH(2,Products!$BP$5:$BP$304,0)),"") -> 0 | D39: =IFERROR(INDEX(Products!$AW$5:$AW$304,MATCH(2,Products!$BP$5:$BP$304,0)),"") -> 0 | E39: =IFERROR(INDEX(Products!$B$5:$B$304,MATCH(2,Products!$BR$5:$BR$304,0)),"") -> 0 | F39: =IFERROR(INDEX(Products!$AY$5:$AY$304,MATCH(2,Products!$BR$5:$BR$304,0)),"") -> 0 | G39: =IFERROR(INDEX(Products!$B$5:$B$304,MATCH(2,Products!$BQ$5:$BQ$304,0)),"") -> 0 | H39: =IFERROR(INDEX(Products!$BH$5:$BH$304,MATCH(2,Products!$BQ$5:$BQ$304,0)),"") -> 0
A40: =IFERROR(INDEX(Products!$B$5:$B$304,MATCH(3,Products!$BO$5:$BO$304,0)),"") -> 0 | B40: =IFERROR(INDEX(Products!$AV$5:$AV$304,MATCH(3,Products!$BO$5:$BO$304,0)),"") -> 0 | C40: =IFERROR(INDEX(Products!$B$5:$B$304,MATCH(3,Products!$BP$5:$BP$304,0)),"") -> 0 | D40: =IFERROR(INDEX(Products!$AW$5:$AW$304,MATCH(3,Products!$BP$5:$BP$304,0)),"") -> 0 | E40: =IFERROR(INDEX(Products!$B$5:$B$304,MATCH(3,Products!$BR$5:$BR$304,0)),"") -> 0 | F40: =IFERROR(INDEX(Products!$AY$5:$AY$304,MATCH(3,Products!$BR$5:$BR$304,0)),"") -> 0 | G40: =IFERROR(INDEX(Products!$B$5:$B$304,MATCH(3,Products!$BQ$5:$BQ$304,0)),"") -> 0 | H40: =IFERROR(INDEX(Products!$BH$5:$BH$304,MATCH(3,Products!$BQ$5:$BQ$304,0)),"") -> 0
A41: =IFERROR(INDEX(Products!$B$5:$B$304,MATCH(4,Products!$BO$5:$BO$304,0)),"") -> 0 | B41: =IFERROR(INDEX(Products!$AV$5:$AV$304,MATCH(4,Products!$BO$5:$BO$304,0)),"") -> 0 | C41: =IFERROR(INDEX(Products!$B$5:$B$304,MATCH(4,Products!$BP$5:$BP$304,0)),"") -> 0 | D41: =IFERROR(INDEX(Products!$AW$5:$AW$304,MATCH(4,Products!$BP$5:$BP$304,0)),"") -> 0 | E41: =IFERROR(INDEX(Products!$B$5:$B$304,MATCH(4,Products!$BR$5:$BR$304,0)),"") -> 0 | F41: =IFERROR(INDEX(Products!$AY$5:$AY$304,MATCH(4,Products!$BR$5:$BR$304,0)),"") -> 0 | G41: =IFERROR(INDEX(Products!$B$5:$B$304,MATCH(4,Products!$BQ$5:$BQ$304,0)),"") -> 0 | H41: =IFERROR(INDEX(Products!$BH$5:$BH$304,MATCH(4,Products!$BQ$5:$BQ$304,0)),"") -> 0
A42: =IFERROR(INDEX(Products!$B$5:$B$304,MATCH(5,Products!$BO$5:$BO$304,0)),"") -> 0 | B42: =IFERROR(INDEX(Products!$AV$5:$AV$304,MATCH(5,Products!$BO$5:$BO$304,0)),"") -> 0 | C42: =IFERROR(INDEX(Products!$B$5:$B$304,MATCH(5,Products!$BP$5:$BP$304,0)),"") -> 0 | D42: =IFERROR(INDEX(Products!$AW$5:$AW$304,MATCH(5,Products!$BP$5:$BP$304,0)),"") -> 0 | E42: =IFERROR(INDEX(Products!$B$5:$B$304,MATCH(5,Products!$BR$5:$BR$304,0)),"") -> 0 | F42: =IFERROR(INDEX(Products!$AY$5:$AY$304,MATCH(5,Products!$BR$5:$BR$304,0)),"") -> 0 | G42: =IFERROR(INDEX(Products!$B$5:$B$304,MATCH(5,Products!$BQ$5:$BQ$304,0)),"") -> 0 | H42: =IFERROR(INDEX(Products!$BH$5:$BH$304,MATCH(5,Products!$BQ$5:$BQ$304,0)),"") -> 0
A43: =IFERROR(INDEX(Products!$B$5:$B$304,MATCH(6,Products!$BO$5:$BO$304,0)),"") -> 0 | B43: =IFERROR(INDEX(Products!$AV$5:$AV$304,MATCH(6,Products!$BO$5:$BO$304,0)),"") -> 0 | C43: =IFERROR(INDEX(Products!$B$5:$B$304,MATCH(6,Products!$BP$5:$BP$304,0)),"") -> 0 | D43: =IFERROR(INDEX(Products!$AW$5:$AW$304,MATCH(6,Products!$BP$5:$BP$304,0)),"") -> 0 | E43: =IFERROR(INDEX(Products!$B$5:$B$304,MATCH(6,Products!$BR$5:$BR$304,0)),"") -> 0 | F43: =IFERROR(INDEX(Products!$AY$5:$AY$304,MATCH(6,Products!$BR$5:$BR$304,0)),"") -> 0 | G43: =IFERROR(INDEX(Products!$B$5:$B$304,MATCH(6,Products!$BQ$5:$BQ$304,0)),"") -> 0 | H43: =IFERROR(INDEX(Products!$BH$5:$BH$304,MATCH(6,Products!$BQ$5:$BQ$304,0)),"") -> 0
A44: =IFERROR(INDEX(Products!$B$5:$B$304,MATCH(7,Products!$BO$5:$BO$304,0)),"") -> 0 | B44: =IFERROR(INDEX(Products!$AV$5:$AV$304,MATCH(7,Products!$BO$5:$BO$304,0)),"") -> 0 | C44: =IFERROR(INDEX(Products!$B$5:$B$304,MATCH(7,Products!$BP$5:$BP$304,0)),"") -> 0 | D44: =IFERROR(INDEX(Products!$AW$5:$AW$304,MATCH(7,Products!$BP$5:$BP$304,0)),"") -> 0 | E44: =IFERROR(INDEX(Products!$B$5:$B$304,MATCH(7,Products!$BR$5:$BR$304,0)),"") -> 0 | F44: =IFERROR(INDEX(Products!$AY$5:$AY$304,MATCH(7,Products!$BR$5:$BR$304,0)),"") -> 0 | G44: =IFERROR(INDEX(Products!$B$5:$B$304,MATCH(7,Products!$BQ$5:$BQ$304,0)),"") -> 0 | H44: =IFERROR(INDEX(Products!$BH$5:$BH$304,MATCH(7,Products!$BQ$5:$BQ$304,0)),"") -> 0
A45: =IFERROR(INDEX(Products!$B$5:$B$304,MATCH(8,Products!$BO$5:$BO$304,0)),"") -> 0 | B45: =IFERROR(INDEX(Products!$AV$5:$AV$304,MATCH(8,Products!$BO$5:$BO$304,0)),"") -> 0 | C45: =IFERROR(INDEX(Products!$B$5:$B$304,MATCH(8,Products!$BP$5:$BP$304,0)),"") -> 0 | D45: =IFERROR(INDEX(Products!$AW$5:$AW$304,MATCH(8,Products!$BP$5:$BP$304,0)),"") -> 0 | E45: =IFERROR(INDEX(Products!$B$5:$B$304,MATCH(8,Products!$BR$5:$BR$304,0)),"") -> 0 | F45: =IFERROR(INDEX(Products!$AY$5:$AY$304,MATCH(8,Products!$BR$5:$BR$304,0)),"") -> 0 | G45: =IFERROR(INDEX(Products!$B$5:$B$304,MATCH(8,Products!$BQ$5:$BQ$304,0)),"") -> 0 | H45: =IFERROR(INDEX(Products!$BH$5:$BH$304,MATCH(8,Products!$BQ$5:$BQ$304,0)),"") -> 0
A47: The four columns rarely agree. The piece that makes the most profit is often not the one that pays best per hour - and the hourly column is the one that decides what you should be making more of.
A49: By category
A50: Category | B50: Products | C50: Average cost | D50: Average price | E50: Average margin | F50: Sold | G50: Revenue | H50: Profit
A51: =IFERROR(INDEX(CategoryList,1),"") -> 0 | B51: =IF(IFERROR(INDEX(CategoryList,1),"")="","",COUNTIFS(Products!$D$5:$D$304,IFERROR(INDEX(CategoryList,1),""))) -> 0 | C51: =IF(IFERROR(INDEX(CategoryList,1),"")="","",IFERROR(AVERAGEIFS(Products!$AT$5:$AT$304,Products!$D$5:$D$304,IFERROR(INDEX(CategoryList,1),"")),"")) -> 0 | D51: =IF(IFERROR(INDEX(CategoryList,1),"")="","",IFERROR(AVERAGEIFS(Products!$AR$5:$AR$304,Products!$D$5:$D$304,IFERROR(INDEX(CategoryList,1),"")),"")) -> 0 | E51: =IF(IFERROR(INDEX(CategoryList,1),"")="","",IFERROR(AVERAGEIFS(Products!$AW$5:$AW$304,Products!$D$5:$D$304,IFERROR(INDEX(CategoryList,1),"")),"")) -> 0 | F51: =IF(IFERROR(INDEX(CategoryList,1),"")="","",SUMIFS(Products!$BH$5:$BH$304,Products!$D$5:$D$304,IFERROR(INDEX(CategoryList,1),""))) -> 0 | G51: =IF(IFERROR(INDEX(CategoryList,1),"")="","",ROUND(SUMIFS(Products!$BI$5:$BI$304,Products!$D$5:$D$304,IFERROR(INDEX(CategoryList,1),"")),2)) -> 0 | H51: =IF(IFERROR(INDEX(CategoryList,1),"")="","",ROUND(SUMIFS(Products!$BJ$5:$BJ$304,Products!$D$5:$D$304,IFERROR(INDEX(CategoryList,1),"")),2)) -> 0
A52: =IFERROR(INDEX(CategoryList,2),"") -> 0 | B52: =IF(IFERROR(INDEX(CategoryList,2),"")="","",COUNTIFS(Products!$D$5:$D$304,IFERROR(INDEX(CategoryList,2),""))) -> 0 | C52: =IF(IFERROR(INDEX(CategoryList,2),"")="","",IFERROR(AVERAGEIFS(Products!$AT$5:$AT$304,Products!$D$5:$D$304,IFERROR(INDEX(CategoryList,2),"")),"")) -> 0 | D52: =IF(IFERROR(INDEX(CategoryList,2),"")="","",IFERROR(AVERAGEIFS(Products!$AR$5:$AR$304,Products!$D$5:$D$304,IFERROR(INDEX(CategoryList,2),"")),"")) -> 0 | E52: =IF(IFERROR(INDEX(CategoryList,2),"")="","",IFERROR(AVERAGEIFS(Products!$AW$5:$AW$304,Products!$D$5:$D$304,IFERROR(INDEX(CategoryList,2),"")),"")) -> 0 | F52: =IF(IFERROR(INDEX(CategoryList,2),"")="","",SUMIFS(Products!$BH$5:$BH$304,Products!$D$5:$D$304,IFERROR(INDEX(CategoryList,2),""))) -> 0 | G52: =IF(IFERROR(INDEX(CategoryList,2),"")="","",ROUND(SUMIFS(Products!$BI$5:$BI$304,Products!$D$5:$D$304,IFERROR(INDEX(CategoryList,2),"")),2)) -> 0 | H52: =IF(IFERROR(INDEX(CategoryList,2),"")="","",ROUND(SUMIFS(Products!$BJ$5:$BJ$304,Products!$D$5:$D$304,IFERROR(INDEX(CategoryList,2),"")),2)) -> 0
A53: =IFERROR(INDEX(CategoryList,3),"") -> 0 | B53: =IF(IFERROR(INDEX(CategoryList,3),"")="","",COUNTIFS(Products!$D$5:$D$304,IFERROR(INDEX(CategoryList,3),""))) -> 0 | C53: =IF(IFERROR(INDEX(CategoryList,3),"")="","",IFERROR(AVERAGEIFS(Products!$AT$5:$AT$304,Products!$D$5:$D$304,IFERROR(INDEX(CategoryList,3),"")),"")) -> 0 | D53: =IF(IFERROR(INDEX(CategoryList,3),"")="","",IFERROR(AVERAGEIFS(Products!$AR$5:$AR$304,Products!$D$5:$D$304,IFERROR(INDEX(CategoryList,3),"")),"")) -> 0 | E53: =IF(IFERROR(INDEX(CategoryList,3),"")="","",IFERROR(AVERAGEIFS(Products!$AW$5:$AW$304,Products!$D$5:$D$304,IFERROR(INDEX(CategoryList,3),"")),"")) -> 0 | F53: =IF(IFERROR(INDEX(CategoryList,3),"")="","",SUMIFS(Products!$BH$5:$BH$304,Products!$D$5:$D$304,IFERROR(INDEX(CategoryList,3),""))) -> 0 | G53: =IF(IFERROR(INDEX(CategoryList,3),"")="","",ROUND(SUMIFS(Products!$BI$5:$BI$304,Products!$D$5:$D$304,IFERROR(INDEX(CategoryList,3),"")),2)) -> 0 | H53: =IF(IFERROR(INDEX(CategoryList,3),"")="","",ROUND(SUMIFS(Products!$BJ$5:$BJ$304,Products!$D$5:$D$304,IFERROR(INDEX(CategoryList,3),"")),2)) -> 0
A54: =IFERROR(INDEX(CategoryList,4),"") -> 0 | B54: =IF(IFERROR(INDEX(CategoryList,4),"")="","",COUNTIFS(Products!$D$5:$D$304,IFERROR(INDEX(CategoryList,4),""))) -> 0 | C54: =IF(IFERROR(INDEX(CategoryList,4),"")="","",IFERROR(AVERAGEIFS(Products!$AT$5:$AT$304,Products!$D$5:$D$304,IFERROR(INDEX(CategoryList,4),"")),"")) -> 0 | D54: =IF(IFERROR(INDEX(CategoryList,4),"")="","",IFERROR(AVERAGEIFS(Products!$AR$5:$AR$304,Products!$D$5:$D$304,IFERROR(INDEX(CategoryList,4),"")),"")) -> 0 | E54: =IF(IFERROR(INDEX(CategoryList,4),"")="","",IFERROR(AVERAGEIFS(Products!$AW$5:$AW$304,Products!$D$5:$D$304,IFERROR(INDEX(CategoryList,4),"")),"")) -> 0 | F54: =IF(IFERROR(INDEX(CategoryList,4),"")="","",SUMIFS(Products!$BH$5:$BH$304,Products!$D$5:$D$304,IFERROR(INDEX(CategoryList,4),""))) -> 0 | G54: =IF(IFERROR(INDEX(CategoryList,4),"")="","",ROUND(SUMIFS(Products!$BI$5:$BI$304,Products!$D$5:$D$304,IFERROR(INDEX(CategoryList,4),"")),2)) -> 0 | H54: =IF(IFERROR(INDEX(CategoryList,4),"")="","",ROUND(SUMIFS(Products!$BJ$5:$BJ$304,Products!$D$5:$D$304,IFERROR(INDEX(CategoryList,4),"")),2)) -> 0
A55: =IFERROR(INDEX(CategoryList,5),"") -> 0 | B55: =IF(IFERROR(INDEX(CategoryList,5),"")="","",COUNTIFS(Products!$D$5:$D$304,IFERROR(INDEX(CategoryList,5),""))) -> 0 | C55: =IF(IFERROR(INDEX(CategoryList,5),"")="","",IFERROR(AVERAGEIFS(Products!$AT$5:$AT$304,Products!$D$5:$D$304,IFERROR(INDEX(CategoryList,5),"")),"")) -> 0 | D55: =IF(IFERROR(INDEX(CategoryList,5),"")="","",IFERROR(AVERAGEIFS(Products!$AR$5:$AR$304,Products!$D$5:$D$304,IFERROR(INDEX(CategoryList,5),"")),"")) -> 0 | E55: =IF(IFERROR(INDEX(CategoryList,5),"")="","",IFERROR(AVERAGEIFS(Products!$AW$5:$AW$304,Products!$D$5:$D$304,IFERROR(INDEX(CategoryList,5),"")),"")) -> 0 | F55: =IF(IFERROR(INDEX(CategoryList,5),"")="","",SUMIFS(Products!$BH$5:$BH$304,Products!$D$5:$D$304,IFERROR(INDEX(CategoryList,5),""))) -> 0 | G55: =IF(IFERROR(INDEX(CategoryList,5),"")="","",ROUND(SUMIFS(Products!$BI$5:$BI$304,Products!$D$5:$D$304,IFERROR(INDEX(CategoryList,5),"")),2)) -> 0 | H55: =IF(IFERROR(INDEX(CategoryList,5),"")="","",ROUND(SUMIFS(Products!$BJ$5:$BJ$304,Products!$D$5:$D$304,IFERROR(INDEX(CategoryList,5),"")),2)) -> 0
A56: =IFERROR(INDEX(CategoryList,6),"") -> 0 | B56: =IF(IFERROR(INDEX(CategoryList,6),"")="","",COUNTIFS(Products!$D$5:$D$304,IFERROR(INDEX(CategoryList,6),""))) -> 0 | C56: =IF(IFERROR(INDEX(CategoryList,6),"")="","",IFERROR(AVERAGEIFS(Products!$AT$5:$AT$304,Products!$D$5:$D$304,IFERROR(INDEX(CategoryList,6),"")),"")) -> 0 | D56: =IF(IFERROR(INDEX(CategoryList,6),"")="","",IFERROR(AVERAGEIFS(Products!$AR$5:$AR$304,Products!$D$5:$D$304,IFERROR(INDEX(CategoryList,6),"")),"")) -> 0 | E56: =IF(IFERROR(INDEX(CategoryList,6),"")="","",IFERROR(AVERAGEIFS(Products!$AW$5:$AW$304,Products!$D$5:$D$304,IFERROR(INDEX(CategoryList,6),"")),"")) -> 0 | F56: =IF(IFERROR(INDEX(CategoryList,6),"")="","",SUMIFS(Products!$BH$5:$BH$304,Products!$D$5:$D$304,IFERROR(INDEX(CategoryList,6),""))) -> 0 | G56: =IF(IFERROR(INDEX(CategoryList,6),"")="","",ROUND(SUMIFS(Products!$BI$5:$BI$304,Products!$D$5:$D$304,IFERROR(INDEX(CategoryList,6),"")),2)) -> 0 | H56: =IF(IFERROR(INDEX(CategoryList,6),"")="","",ROUND(SUMIFS(Products!$BJ$5:$BJ$304,Products!$D$5:$D$304,IFERROR(INDEX(CategoryList,6),"")),2)) -> 0
A57: =IFERROR(INDEX(CategoryList,7),"") -> 0 | B57: =IF(IFERROR(INDEX(CategoryList,7),"")="","",COUNTIFS(Products!$D$5:$D$304,IFERROR(INDEX(CategoryList,7),""))) -> 0 | C57: =IF(IFERROR(INDEX(CategoryList,7),"")="","",IFERROR(AVERAGEIFS(Products!$AT$5:$AT$304,Products!$D$5:$D$304,IFERROR(INDEX(CategoryList,7),"")),"")) -> 0 | D57: =IF(IFERROR(INDEX(CategoryList,7),"")="","",IFERROR(AVERAGEIFS(Products!$AR$5:$AR$304,Products!$D$5:$D$304,IFERROR(INDEX(CategoryList,7),"")),"")) -> 0 | E57: =IF(IFERROR(INDEX(CategoryList,7),"")="","",IFERROR(AVERAGEIFS(Products!$AW$5:$AW$304,Products!$D$5:$D$304,IFERROR(INDEX(CategoryList,7),"")),"")) -> 0 | F57: =IF(IFERROR(INDEX(CategoryList,7),"")="","",SUMIFS(Products!$BH$5:$BH$304,Products!$D$5:$D$304,IFERROR(INDEX(CategoryList,7),""))) -> 0 | G57: =IF(IFERROR(INDEX(CategoryList,7),"")="","",ROUND(SUMIFS(Products!$BI$5:$BI$304,Products!$D$5:$D$304,IFERROR(INDEX(CategoryList,7),"")),2)) -> 0 | H57: =IF(IFERROR(INDEX(CategoryList,7),"")="","",ROUND(SUMIFS(Products!$BJ$5:$BJ$304,Products!$D$5:$D$304,IFERROR(INDEX(CategoryList,7),"")),2)) -> 0
A58: =IFERROR(INDEX(CategoryList,8),"") -> 0 | B58: =IF(IFERROR(INDEX(CategoryList,8),"")="","",COUNTIFS(Products!$D$5:$D$304,IFERROR(INDEX(CategoryList,8),""))) -> 0 | C58: =IF(IFERROR(INDEX(CategoryList,8),"")="","",IFERROR(AVERAGEIFS(Products!$AT$5:$AT$304,Products!$D$5:$D$304,IFERROR(INDEX(CategoryList,8),"")),"")) -> 0 | D58: =IF(IFERROR(INDEX(CategoryList,8),"")="","",IFERROR(AVERAGEIFS(Products!$AR$5:$AR$304,Products!$D$5:$D$304,IFERROR(INDEX(CategoryList,8),"")),"")) -> 0 | E58: =IF(IFERROR(INDEX(CategoryList,8),"")="","",IFERROR(AVERAGEIFS(Products!$AW$5:$AW$304,Products!$D$5:$D$304,IFERROR(INDEX(CategoryList,8),"")),"")) -> 0 | F58: =IF(IFERROR(INDEX(CategoryList,8),"")="","",SUMIFS(Products!$BH$5:$BH$304,Products!$D$5:$D$304,IFERROR(INDEX(CategoryList,8),""))) -> 0 | G58: =IF(IFERROR(INDEX(CategoryList,8),"")="","",ROUND(SUMIFS(Products!$BI$5:$BI$304,Products!$D$5:$D$304,IFERROR(INDEX(CategoryList,8),"")),2)) -> 0 | H58: =IF(IFERROR(INDEX(CategoryList,8),"")="","",ROUND(SUMIFS(Products!$BJ$5:$BJ$304,Products!$D$5:$D$304,IFERROR(INDEX(CategoryList,8),"")),2)) -> 0
A59: =IFERROR(INDEX(CategoryList,9),"") -> 0 | B59: =IF(IFERROR(INDEX(CategoryList,9),"")="","",COUNTIFS(Products!$D$5:$D$304,IFERROR(INDEX(CategoryList,9),""))) -> 0 | C59: =IF(IFERROR(INDEX(CategoryList,9),"")="","",IFERROR(AVERAGEIFS(Products!$AT$5:$AT$304,Products!$D$5:$D$304,IFERROR(INDEX(CategoryList,9),"")),"")) -> 0 | D59: =IF(IFERROR(INDEX(CategoryList,9),"")="","",IFERROR(AVERAGEIFS(Products!$AR$5:$AR$304,Products!$D$5:$D$304,IFERROR(INDEX(CategoryList,9),"")),"")) -> 0 | E59: =IF(IFERROR(INDEX(CategoryList,9),"")="","",IFERROR(AVERAGEIFS(Products!$AW$5:$AW$304,Products!$D$5:$D$304,IFERROR(INDEX(CategoryList,9),"")),"")) -> 0 | F59: =IF(IFERROR(INDEX(CategoryList,9),"")="","",SUMIFS(Products!$BH$5:$BH$304,Products!$D$5:$D$304,IFERROR(INDEX(CategoryList,9),""))) -> 0 | G59: =IF(IFERROR(INDEX(CategoryList,9),"")="","",ROUND(SUMIFS(Products!$BI$5:$BI$304,Products!$D$5:$D$304,IFERROR(INDEX(CategoryList,9),"")),2)) -> 0 | H59: =IF(IFERROR(INDEX(CategoryList,9),"")="","",ROUND(SUMIFS(Products!$BJ$5:$BJ$304,Products!$D$5:$D$304,IFERROR(INDEX(CategoryList,9),"")),2)) -> 0
A60: =IFERROR(INDEX(CategoryList,10),"") -> 0 | B60: =IF(IFERROR(INDEX(CategoryList,10),"")="","",COUNTIFS(Products!$D$5:$D$304,IFERROR(INDEX(CategoryList,10),""))) -> 0 | C60: =IF(IFERROR(INDEX(CategoryList,10),"")="","",IFERROR(AVERAGEIFS(Products!$AT$5:$AT$304,Products!$D$5:$D$304,IFERROR(INDEX(CategoryList,10),"")),"")) -> 0 | D60: =IF(IFERROR(INDEX(CategoryList,10),"")="","",IFERROR(AVERAGEIFS(Products!$AR$5:$AR$304,Products!$D$5:$D$304,IFERROR(INDEX(CategoryList,10),"")),"")) -> 0 | E60: =IF(IFERROR(INDEX(CategoryList,10),"")="","",IFERROR(AVERAGEIFS(Products!$AW$5:$AW$304,Products!$D$5:$D$304,IFERROR(INDEX(CategoryList,10),"")),"")) -> 0 | F60: =IF(IFERROR(INDEX(CategoryList,10),"")="","",SUMIFS(Products!$BH$5:$BH$304,Products!$D$5:$D$304,IFERROR(INDEX(CategoryList,10),""))) -> 0 | G60: =IF(IFERROR(INDEX(CategoryList,10),"")="","",ROUND(SUMIFS(Products!$BI$5:$BI$304,Products!$D$5:$D$304,IFERROR(INDEX(CategoryList,10),"")),2)) -> 0 | H60: =IF(IFERROR(INDEX(CategoryList,10),"")="","",ROUND(SUMIFS(Products!$BJ$5:$BJ$304,Products!$D$5:$D$304,IFERROR(INDEX(CategoryList,10),"")),2)) -> 0
A63: The last twelve months
A64: Month | B64: =TEXT(DATE(YEAR(TodayDate),MONTH(TodayDate)-11,1),"mmm yy") -> 0 | C64: =TEXT(DATE(YEAR(TodayDate),MONTH(TodayDate)-10,1),"mmm yy") -> 0 | D64: =TEXT(DATE(YEAR(TodayDate),MONTH(TodayDate)-9,1),"mmm yy") -> 0 | E64: =TEXT(DATE(YEAR(TodayDate),MONTH(TodayDate)-8,1),"mmm yy") -> 0 | F64: =TEXT(DATE(YEAR(TodayDate),MONTH(TodayDate)-7,1),"mmm yy") -> 0 | G64: =TEXT(DATE(YEAR(TodayDate),MONTH(TodayDate)-6,1),"mmm yy") -> 0 | H64: =TEXT(DATE(YEAR(TodayDate),MONTH(TodayDate)-5,1),"mmm yy") -> 0 | I64: =TEXT(DATE(YEAR(TodayDate),MONTH(TodayDate)-4,1),"mmm yy") -> 0 | J64: =TEXT(DATE(YEAR(TodayDate),MONTH(TodayDate)-3,1),"mmm yy") -> 0 | K64: =TEXT(DATE(YEAR(TodayDate),MONTH(TodayDate)-2,1),"mmm yy") -> 0 | L64: =TEXT(DATE(YEAR(TodayDate),MONTH(TodayDate)-1,1),"mmm yy") -> 0 | M64: =TEXT(DATE(YEAR(TodayDate),MONTH(TodayDate)-0,1),"mmm yy") -> 0
A65: Key | B65: =TEXT(DATE(YEAR(TodayDate),MONTH(TodayDate)-11,1),"yyyy-mm") -> 0 | C65: =TEXT(DATE(YEAR(TodayDate),MONTH(TodayDate)-10,1),"yyyy-mm") -> 0 | D65: =TEXT(DATE(YEAR(TodayDate),MONTH(TodayDate)-9,1),"yyyy-mm") -> 0 | E65: =TEXT(DATE(YEAR(TodayDate),MONTH(TodayDate)-8,1),"yyyy-mm") -> 0 | F65: =TEXT(DATE(YEAR(TodayDate),MONTH(TodayDate)-7,1),"yyyy-mm") -> 0 | G65: =TEXT(DATE(YEAR(TodayDate),MONTH(TodayDate)-6,1),"yyyy-mm") -> 0 | H65: =TEXT(DATE(YEAR(TodayDate),MONTH(TodayDate)-5,1),"yyyy-mm") -> 0 | I65: =TEXT(DATE(YEAR(TodayDate),MONTH(TodayDate)-4,1),"yyyy-mm") -> 0 | J65: =TEXT(DATE(YEAR(TodayDate),MONTH(TodayDate)-3,1),"yyyy-mm") -> 0 | K65: =TEXT(DATE(YEAR(TodayDate),MONTH(TodayDate)-2,1),"yyyy-mm") -> 0 | L65: =TEXT(DATE(YEAR(TodayDate),MONTH(TodayDate)-1,1),"yyyy-mm") -> 0 | M65: =TEXT(DATE(YEAR(TodayDate),MONTH(TodayDate)-0,1),"yyyy-mm") -> 0
A66: Revenue | B66: =ROUND(SUMIFS(Sales!$V$5:$V$804,Sales!$R$5:$R$804,B$65),2) -> 0 | C66: =ROUND(SUMIFS(Sales!$V$5:$V$804,Sales!$R$5:$R$804,C$65),2) -> 0 | D66: =ROUND(SUMIFS(Sales!$V$5:$V$804,Sales!$R$5:$R$804,D$65),2) -> 0 | E66: =ROUND(SUMIFS(Sales!$V$5:$V$804,Sales!$R$5:$R$804,E$65),2) -> 0 | F66: =ROUND(SUMIFS(Sales!$V$5:$V$804,Sales!$R$5:$R$804,F$65),2) -> 0 | G66: =ROUND(SUMIFS(Sales!$V$5:$V$804,Sales!$R$5:$R$804,G$65),2) -> 0 | H66: =ROUND(SUMIFS(Sales!$V$5:$V$804,Sales!$R$5:$R$804,H$65),2) -> 0 | I66: =ROUND(SUMIFS(Sales!$V$5:$V$804,Sales!$R$5:$R$804,I$65),2) -> 0 | ... M66: =ROUND(SUMIFS(Sales!$V$5:$V$804,Sales!$R$5:$R$804,M$65),2) -> 0
A67: Cost of goods | B67: =ROUND(SUMIFS(Sales!$Y$5:$Y$804,Sales!$R$5:$R$804,B$65),2) -> 0 | C67: =ROUND(SUMIFS(Sales!$Y$5:$Y$804,Sales!$R$5:$R$804,C$65),2) -> 0 | D67: =ROUND(SUMIFS(Sales!$Y$5:$Y$804,Sales!$R$5:$R$804,D$65),2) -> 0 | E67: =ROUND(SUMIFS(Sales!$Y$5:$Y$804,Sales!$R$5:$R$804,E$65),2) -> 0 | F67: =ROUND(SUMIFS(Sales!$Y$5:$Y$804,Sales!$R$5:$R$804,F$65),2) -> 0 | G67: =ROUND(SUMIFS(Sales!$Y$5:$Y$804,Sales!$R$5:$R$804,G$65),2) -> 0 | H67: =ROUND(SUMIFS(Sales!$Y$5:$Y$804,Sales!$R$5:$R$804,H$65),2) -> 0 | I67: =ROUND(SUMIFS(Sales!$Y$5:$Y$804,Sales!$R$5:$R$804,I$65),2) -> 0 | ... M67: =ROUND(SUMIFS(Sales!$Y$5:$Y$804,Sales!$R$5:$R$804,M$65),2) -> 0
A68: Fees | B68: =ROUND(SUMIFS(Sales!$AE$5:$AE$804,Sales!$R$5:$R$804,B$65),2) -> 0 | C68: =ROUND(SUMIFS(Sales!$AE$5:$AE$804,Sales!$R$5:$R$804,C$65),2) -> 0 | D68: =ROUND(SUMIFS(Sales!$AE$5:$AE$804,Sales!$R$5:$R$804,D$65),2) -> 0 | E68: =ROUND(SUMIFS(Sales!$AE$5:$AE$804,Sales!$R$5:$R$804,E$65),2) -> 0 | F68: =ROUND(SUMIFS(Sales!$AE$5:$AE$804,Sales!$R$5:$R$804,F$65),2) -> 0 | G68: =ROUND(SUMIFS(Sales!$AE$5:$AE$804,Sales!$R$5:$R$804,G$65),2) -> 0 | H68: =ROUND(SUMIFS(Sales!$AE$5:$AE$804,Sales!$R$5:$R$804,H$65),2) -> 0 | I68: =ROUND(SUMIFS(Sales!$AE$5:$AE$804,Sales!$R$5:$R$804,I$65),2) -> 0 | ... M68: =ROUND(SUMIFS(Sales!$AE$5:$AE$804,Sales!$R$5:$R$804,M$65),2) -> 0
A69: Profit | B69: =ROUND(SUMIFS(Sales!$AG$5:$AG$804,Sales!$R$5:$R$804,B$65),2) -> 0 | C69: =ROUND(SUMIFS(Sales!$AG$5:$AG$804,Sales!$R$5:$R$804,C$65),2) -> 0 | D69: =ROUND(SUMIFS(Sales!$AG$5:$AG$804,Sales!$R$5:$R$804,D$65),2) -> 0 | E69: =ROUND(SUMIFS(Sales!$AG$5:$AG$804,Sales!$R$5:$R$804,E$65),2) -> 0 | F69: =ROUND(SUMIFS(Sales!$AG$5:$AG$804,Sales!$R$5:$R$804,F$65),2) -> 0 | G69: =ROUND(SUMIFS(Sales!$AG$5:$AG$804,Sales!$R$5:$R$804,G$65),2) -> 0 | H69: =ROUND(SUMIFS(Sales!$AG$5:$AG$804,Sales!$R$5:$R$804,H$65),2) -> 0 | I69: =ROUND(SUMIFS(Sales!$AG$5:$AG$804,Sales!$R$5:$R$804,I$65),2) -> 0 | ... M69: =ROUND(SUMIFS(Sales!$AG$5:$AG$804,Sales!$R$5:$R$804,M$65),2) -> 0
A70: Items | B70: =ROUND(SUMIFS(Sales!$D$5:$D$804,Sales!$R$5:$R$804,B$65),2) -> 0 | C70: =ROUND(SUMIFS(Sales!$D$5:$D$804,Sales!$R$5:$R$804,C$65),2) -> 0 | D70: =ROUND(SUMIFS(Sales!$D$5:$D$804,Sales!$R$5:$R$804,D$65),2) -> 0 | E70: =ROUND(SUMIFS(Sales!$D$5:$D$804,Sales!$R$5:$R$804,E$65),2) -> 0 | F70: =ROUND(SUMIFS(Sales!$D$5:$D$804,Sales!$R$5:$R$804,F$65),2) -> 0 | G70: =ROUND(SUMIFS(Sales!$D$5:$D$804,Sales!$R$5:$R$804,G$65),2) -> 0 | H70: =ROUND(SUMIFS(Sales!$D$5:$D$804,Sales!$R$5:$R$804,H$65),2) -> 0 | I70: =ROUND(SUMIFS(Sales!$D$5:$D$804,Sales!$R$5:$R$804,I$65),2) -> 0 | ... M70: =ROUND(SUMIFS(Sales!$D$5:$D$804,Sales!$R$5:$R$804,M$65),2) -> 0
A71: Hours sold | B71: =ROUND(SUMIFS(Sales!$AK$5:$AK$804,Sales!$R$5:$R$804,B$65),2) -> 0 | C71: =ROUND(SUMIFS(Sales!$AK$5:$AK$804,Sales!$R$5:$R$804,C$65),2) -> 0 | D71: =ROUND(SUMIFS(Sales!$AK$5:$AK$804,Sales!$R$5:$R$804,D$65),2) -> 0 | E71: =ROUND(SUMIFS(Sales!$AK$5:$AK$804,Sales!$R$5:$R$804,E$65),2) -> 0 | F71: =ROUND(SUMIFS(Sales!$AK$5:$AK$804,Sales!$R$5:$R$804,F$65),2) -> 0 | G71: =ROUND(SUMIFS(Sales!$AK$5:$AK$804,Sales!$R$5:$R$804,G$65),2) -> 0 | H71: =ROUND(SUMIFS(Sales!$AK$5:$AK$804,Sales!$R$5:$R$804,H$65),2) -> 0 | I71: =ROUND(SUMIFS(Sales!$AK$5:$AK$804,Sales!$R$5:$R$804,I$65),2) -> 0 | ... M71: =ROUND(SUMIFS(Sales!$AK$5:$AK$804,Sales!$R$5:$R$804,M$65),2) -> 0
A72: Margin | B72: =IFERROR(B69/B66,"") -> 0 | C72: =IFERROR(C69/C66,"") -> 0 | D72: =IFERROR(D69/D66,"") -> 0 | E72: =IFERROR(E69/E66,"") -> 0 | F72: =IFERROR(F69/F66,"") -> 0 | G72: =IFERROR(G69/G66,"") -> 0 | H72: =IFERROR(H69/H66,"") -> 0 | I72: =IFERROR(I69/I66,"") -> 0 | ... M72: =IFERROR(M69/M66,"") -> 0
A74: Blank months are months with nothing logged on the Sales tab, not months with no sales.
A76: Where the money comes from
A77: Channel | B77: Orders | C77: Revenue | D77: Fees | E77: Fee rate | F77: Profit | G77: Margin | H77: Share of revenue
A78: =IFERROR(INDEX(Channels!$A$5:$A$18,1)&"","") -> 0 | B78: =IF(IFERROR(INDEX(Channels!$A$5:$A$18,1)&"","")="","",COUNTIFS(Sales!$E$5:$E$804,IFERROR(INDEX(Channels!$A$5:$A$18,1)&"",""))) -> 0 | C78: =IF(IFERROR(INDEX(Channels!$A$5:$A$18,1)&"","")="","",ROUND(SUMIFS(Sales!$V$5:$V$804,Sales!$E$5:$E$804,IFERROR(INDEX(Channels!$A$5:$A$18,1)&"","")),2)) -> 0 | D78: =IF(IFERROR(INDEX(Channels!$A$5:$A$18,1)&"","")="","",ROUND(SUMIFS(Sales!$AE$5:$AE$804,Sales!$E$5:$E$804,IFERROR(INDEX(Channels!$A$5:$A$18,1)&"","")),2)) -> 0 | E78: =IFERROR(D78/C78,"") -> 0 | F78: =IF(IFERROR(INDEX(Channels!$A$5:$A$18,1)&"","")="","",ROUND(SUMIFS(Sales!$AG$5:$AG$804,Sales!$E$5:$E$804,IFERROR(INDEX(Channels!$A$5:$A$18,1)&"","")),2)) -> 0 | G78: =IFERROR(F78/C78,"") -> 0 | H78: =IFERROR(C78/SUM(Sales!$V$5:$V$804),"") -> 0
A79: =IFERROR(INDEX(Channels!$A$5:$A$18,2)&"","") -> 0 | B79: =IF(IFERROR(INDEX(Channels!$A$5:$A$18,2)&"","")="","",COUNTIFS(Sales!$E$5:$E$804,IFERROR(INDEX(Channels!$A$5:$A$18,2)&"",""))) -> 0 | C79: =IF(IFERROR(INDEX(Channels!$A$5:$A$18,2)&"","")="","",ROUND(SUMIFS(Sales!$V$5:$V$804,Sales!$E$5:$E$804,IFERROR(INDEX(Channels!$A$5:$A$18,2)&"","")),2)) -> 0 | D79: =IF(IFERROR(INDEX(Channels!$A$5:$A$18,2)&"","")="","",ROUND(SUMIFS(Sales!$AE$5:$AE$804,Sales!$E$5:$E$804,IFERROR(INDEX(Channels!$A$5:$A$18,2)&"","")),2)) -> 0 | E79: =IFERROR(D79/C79,"") -> 0 | F79: =IF(IFERROR(INDEX(Channels!$A$5:$A$18,2)&"","")="","",ROUND(SUMIFS(Sales!$AG$5:$AG$804,Sales!$E$5:$E$804,IFERROR(INDEX(Channels!$A$5:$A$18,2)&"","")),2)) -> 0 | G79: =IFERROR(F79/C79,"") -> 0 | H79: =IFERROR(C79/SUM(Sales!$V$5:$V$804),"") -> 0
A80: =IFERROR(INDEX(Channels!$A$5:$A$18,3)&"","") -> 0 | B80: =IF(IFERROR(INDEX(Channels!$A$5:$A$18,3)&"","")="","",COUNTIFS(Sales!$E$5:$E$804,IFERROR(INDEX(Channels!$A$5:$A$18,3)&"",""))) -> 0 | C80: =IF(IFERROR(INDEX(Channels!$A$5:$A$18,3)&"","")="","",ROUND(SUMIFS(Sales!$V$5:$V$804,Sales!$E$5:$E$804,IFERROR(INDEX(Channels!$A$5:$A$18,3)&"","")),2)) -> 0 | D80: =IF(IFERROR(INDEX(Channels!$A$5:$A$18,3)&"","")="","",ROUND(SUMIFS(Sales!$AE$5:$AE$804,Sales!$E$5:$E$804,IFERROR(INDEX(Channels!$A$5:$A$18,3)&"","")),2)) -> 0 | E80: =IFERROR(D80/C80,"") -> 0 | F80: =IF(IFERROR(INDEX(Channels!$A$5:$A$18,3)&"","")="","",ROUND(SUMIFS(Sales!$AG$5:$AG$804,Sales!$E$5:$E$804,IFERROR(INDEX(Channels!$A$5:$A$18,3)&"","")),2)) -> 0 | G80: =IFERROR(F80/C80,"") -> 0 | H80: =IFERROR(C80/SUM(Sales!$V$5:$V$804),"") -> 0
A81: =IFERROR(INDEX(Channels!$A$5:$A$18,4)&"","") -> 0 | B81: =IF(IFERROR(INDEX(Channels!$A$5:$A$18,4)&"","")="","",COUNTIFS(Sales!$E$5:$E$804,IFERROR(INDEX(Channels!$A$5:$A$18,4)&"",""))) -> 0 | C81: =IF(IFERROR(INDEX(Channels!$A$5:$A$18,4)&"","")="","",ROUND(SUMIFS(Sales!$V$5:$V$804,Sales!$E$5:$E$804,IFERROR(INDEX(Channels!$A$5:$A$18,4)&"","")),2)) -> 0 | D81: =IF(IFERROR(INDEX(Channels!$A$5:$A$18,4)&"","")="","",ROUND(SUMIFS(Sales!$AE$5:$AE$804,Sales!$E$5:$E$804,IFERROR(INDEX(Channels!$A$5:$A$18,4)&"","")),2)) -> 0 | E81: =IFERROR(D81/C81,"") -> 0 | F81: =IF(IFERROR(INDEX(Channels!$A$5:$A$18,4)&"","")="","",ROUND(SUMIFS(Sales!$AG$5:$AG$804,Sales!$E$5:$E$804,IFERROR(INDEX(Channels!$A$5:$A$18,4)&"","")),2)) -> 0 | G81: =IFERROR(F81/C81,"") -> 0 | H81: =IFERROR(C81/SUM(Sales!$V$5:$V$804),"") -> 0
A82: =IFERROR(INDEX(Channels!$A$5:$A$18,5)&"","") -> 0 | B82: =IF(IFERROR(INDEX(Channels!$A$5:$A$18,5)&"","")="","",COUNTIFS(Sales!$E$5:$E$804,IFERROR(INDEX(Channels!$A$5:$A$18,5)&"",""))) -> 0 | C82: =IF(IFERROR(INDEX(Channels!$A$5:$A$18,5)&"","")="","",ROUND(SUMIFS(Sales!$V$5:$V$804,Sales!$E$5:$E$804,IFERROR(INDEX(Channels!$A$5:$A$18,5)&"","")),2)) -> 0 | D82: =IF(IFERROR(INDEX(Channels!$A$5:$A$18,5)&"","")="","",ROUND(SUMIFS(Sales!$AE$5:$AE$804,Sales!$E$5:$E$804,IFERROR(INDEX(Channels!$A$5:$A$18,5)&"","")),2)) -> 0 | E82: =IFERROR(D82/C82,"") -> 0 | F82: =IF(IFERROR(INDEX(Channels!$A$5:$A$18,5)&"","")="","",ROUND(SUMIFS(Sales!$AG$5:$AG$804,Sales!$E$5:$E$804,IFERROR(INDEX(Channels!$A$5:$A$18,5)&"","")),2)) -> 0 | G82: =IFERROR(F82/C82,"") -> 0 | H82: =IFERROR(C82/SUM(Sales!$V$5:$V$804),"") -> 0
A83: =IFERROR(INDEX(Channels!$A$5:$A$18,6)&"","") -> 0 | B83: =IF(IFERROR(INDEX(Channels!$A$5:$A$18,6)&"","")="","",COUNTIFS(Sales!$E$5:$E$804,IFERROR(INDEX(Channels!$A$5:$A$18,6)&"",""))) -> 0 | C83: =IF(IFERROR(INDEX(Channels!$A$5:$A$18,6)&"","")="","",ROUND(SUMIFS(Sales!$V$5:$V$804,Sales!$E$5:$E$804,IFERROR(INDEX(Channels!$A$5:$A$18,6)&"","")),2)) -> 0 | D83: =IF(IFERROR(INDEX(Channels!$A$5:$A$18,6)&"","")="","",ROUND(SUMIFS(Sales!$AE$5:$AE$804,Sales!$E$5:$E$804,IFERROR(INDEX(Channels!$A$5:$A$18,6)&"","")),2)) -> 0 | E83: =IFERROR(D83/C83,"") -> 0 | F83: =IF(IFERROR(INDEX(Channels!$A$5:$A$18,6)&"","")="","",ROUND(SUMIFS(Sales!$AG$5:$AG$804,Sales!$E$5:$E$804,IFERROR(INDEX(Channels!$A$5:$A$18,6)&"","")),2)) -> 0 | G83: =IFERROR(F83/C83,"") -> 0 | H83: =IFERROR(C83/SUM(Sales!$V$5:$V$804),"") -> 0
A84: =IFERROR(INDEX(Channels!$A$5:$A$18,7)&"","") -> 0 | B84: =IF(IFERROR(INDEX(Channels!$A$5:$A$18,7)&"","")="","",COUNTIFS(Sales!$E$5:$E$804,IFERROR(INDEX(Channels!$A$5:$A$18,7)&"",""))) -> 0 | C84: =IF(IFERROR(INDEX(Channels!$A$5:$A$18,7)&"","")="","",ROUND(SUMIFS(Sales!$V$5:$V$804,Sales!$E$5:$E$804,IFERROR(INDEX(Channels!$A$5:$A$18,7)&"","")),2)) -> 0 | D84: =IF(IFERROR(INDEX(Channels!$A$5:$A$18,7)&"","")="","",ROUND(SUMIFS(Sales!$AE$5:$AE$804,Sales!$E$5:$E$804,IFERROR(INDEX(Channels!$A$5:$A$18,7)&"","")),2)) -> 0 | E84: =IFERROR(D84/C84,"") -> 0 | F84: =IF(IFERROR(INDEX(Channels!$A$5:$A$18,7)&"","")="","",ROUND(SUMIFS(Sales!$AG$5:$AG$804,Sales!$E$5:$E$804,IFERROR(INDEX(Channels!$A$5:$A$18,7)&"","")),2)) -> 0 | G84: =IFERROR(F84/C84,"") -> 0 | H84: =IFERROR(C84/SUM(Sales!$V$5:$V$804),"") -> 0
A85: =IFERROR(INDEX(Channels!$A$5:$A$18,8)&"","") -> 0 | B85: =IF(IFERROR(INDEX(Channels!$A$5:$A$18,8)&"","")="","",COUNTIFS(Sales!$E$5:$E$804,IFERROR(INDEX(Channels!$A$5:$A$18,8)&"",""))) -> 0 | C85: =IF(IFERROR(INDEX(Channels!$A$5:$A$18,8)&"","")="","",ROUND(SUMIFS(Sales!$V$5:$V$804,Sales!$E$5:$E$804,IFERROR(INDEX(Channels!$A$5:$A$18,8)&"","")),2)) -> 0 | D85: =IF(IFERROR(INDEX(Channels!$A$5:$A$18,8)&"","")="","",ROUND(SUMIFS(Sales!$AE$5:$AE$804,Sales!$E$5:$E$804,IFERROR(INDEX(Channels!$A$5:$A$18,8)&"","")),2)) -> 0 | E85: =IFERROR(D85/C85,"") -> 0 | F85: =IF(IFERROR(INDEX(Channels!$A$5:$A$18,8)&"","")="","",ROUND(SUMIFS(Sales!$AG$5:$AG$804,Sales!$E$5:$E$804,IFERROR(INDEX(Channels!$A$5:$A$18,8)&"","")),2)) -> 0 | G85: =IFERROR(F85/C85,"") -> 0 | H85: =IFERROR(C85/SUM(Sales!$V$5:$V$804),"") -> 0
A86: =IFERROR(INDEX(Channels!$A$5:$A$18,9)&"","") -> 0 | B86: =IF(IFERROR(INDEX(Channels!$A$5:$A$18,9)&"","")="","",COUNTIFS(Sales!$E$5:$E$804,IFERROR(INDEX(Channels!$A$5:$A$18,9)&"",""))) -> 0 | C86: =IF(IFERROR(INDEX(Channels!$A$5:$A$18,9)&"","")="","",ROUND(SUMIFS(Sales!$V$5:$V$804,Sales!$E$5:$E$804,IFERROR(INDEX(Channels!$A$5:$A$18,9)&"","")),2)) -> 0 | D86: =IF(IFERROR(INDEX(Channels!$A$5:$A$18,9)&"","")="","",ROUND(SUMIFS(Sales!$AE$5:$AE$804,Sales!$E$5:$E$804,IFERROR(INDEX(Channels!$A$5:$A$18,9)&"","")),2)) -> 0 | E86: =IFERROR(D86/C86,"") -> 0 | F86: =IF(IFERROR(INDEX(Channels!$A$5:$A$18,9)&"","")="","",ROUND(SUMIFS(Sales!$AG$5:$AG$804,Sales!$E$5:$E$804,IFERROR(INDEX(Channels!$A$5:$A$18,9)&"","")),2)) -> 0 | G86: =IFERROR(F86/C86,"") -> 0 | H86: =IFERROR(C86/SUM(Sales!$V$5:$V$804),"") -> 0
A87: =IFERROR(INDEX(Channels!$A$5:$A$18,10)&"","") -> 0 | B87: =IF(IFERROR(INDEX(Channels!$A$5:$A$18,10)&"","")="","",COUNTIFS(Sales!$E$5:$E$804,IFERROR(INDEX(Channels!$A$5:$A$18,10)&"",""))) -> 0 | C87: =IF(IFERROR(INDEX(Channels!$A$5:$A$18,10)&"","")="","",ROUND(SUMIFS(Sales!$V$5:$V$804,Sales!$E$5:$E$804,IFERROR(INDEX(Channels!$A$5:$A$18,10)&"","")),2)) -> 0 | D87: =IF(IFERROR(INDEX(Channels!$A$5:$A$18,10)&"","")="","",ROUND(SUMIFS(Sales!$AE$5:$AE$804,Sales!$E$5:$E$804,IFERROR(INDEX(Channels!$A$5:$A$18,10)&"","")),2)) -> 0 | E87: =IFERROR(D87/C87,"") -> 0 | F87: =IF(IFERROR(INDEX(Channels!$A$5:$A$18,10)&"","")="","",ROUND(SUMIFS(Sales!$AG$5:$AG$804,Sales!$E$5:$E$804,IFERROR(INDEX(Channels!$A$5:$A$18,10)&"","")),2)) -> 0 | G87: =IFERROR(F87/C87,"") -> 0 | H87: =IFERROR(C87/SUM(Sales!$V$5:$V$804),"") -> 0
A90: If you only do one thing this week
A91: =IF(COUNTIF(Products!$BS$5:$BS$304,"Loss*")>0,"Fix the products that lose money. There are "&COUNTIF(Products!$BS$5:$BS$304,"Loss*")&" of them on the Product Catalog - every sale of those makes things worse.",IF(COUNTIF(Products!$BS$5:$BS$304,"Below*")>0,"Re-price the "&COUNTIF(Products!$BS$5:$BS$304,"Below*")&" products that pay you under minimum wage. Start with the Retail Price Calculator.",IF(COUNTIFS(Products!$B$5:$B$304,"<>",Products!$AR$5:$AR$304,"")>0,"Price the products that have no price yet.",IF(FeesStale="Yes","Check your marketplace fee rates on the Channels tab - they were last reviewed "&TEXT(FeesReviewed,"d mmm yyyy")&".",IF(COUNTIF(Products!$BS$5:$BS$304,"Review*")>0,"Review the prices that have not moved in "&PriceReviewDays&" days. Your costs have.","Everything is priced, nothing is losing money and your fees are current. Log this month's sales and look at what pays you best an hour."))))) -> 0

Sheet Products
A1: Product Catalog | BQ1: Novality Store | v1.0.0
A2: Every product, every cost, the price the maths asks for and the margin you actually make.
A3: > Start Here | C3: > Dashboard | E3: > Products | G3: > Materials | I3: > Labour | K3: > Retail Price | M3: > Wholesale | O3: > Sales | Q3: > Help | S3: Give a product a name, a category, a packaging profile and a channel. Cost it on the Materials and Labor tabs (or a specialist tab) and the price appears here.
A4: ID | B4: Product | C4: SKU override | D4: Category | E4: Status | F4: Season | G4: Difficulty | H4: Main channel | I4: Packaging | J4: Shipping option | K4: Item weight (g) | L4: In stock | M4: Your price | N4: Target margin | O4: Made so far | P4: Listed on | Q4: Listing link | R4: Notes | S4: SKU | T4: Materials | U4: Labour | V4: Minutes logged | W4: Difficulty factor | X4: Minutes | Y4: Hours | Z4: Labour at difficulty | AA4: Consumables | AB4: Packaging | AC4: Packaging weight | AD4: Postage costs | AE4: Postage charged | AF4: Weight band | AG4: Postage you absorb | AH4: Cost before overhead | AI4: Fee rate | AJ4: Fees on postage? | AK4: Fixed fees | AL4: Overhead rate | AM4: Overhead in cost | AN4: Target margin used | AO4: Pricing denominator | AP4: Suggested, unrounded | AQ4: Suggested price | AR4: Price used | AS4: Overhead | AT4: Total cost | AU4: Channel fees | AV4: Profit | AW4: Margin | AX4: Markup | AY4: Profit an hour | AZ4: You earn an hour | BA4: Never sell below | BB4: Keystone (x2) | BC4: Wholesale price | BD4: Wholesale profit | BE4: Wholesale margin | BF4: Competitors average | BG4: Versus the market | BH4: Units sold | BI4: Revenue | BJ4: Actual profit | BK4: Actual margin | BL4: Last sold | BM4: Price changed | BN4: Days since review | BO4: Profit rank | BP4: Margin rank | BQ4: Revenue rank | BR4: Hourly rank | BS4: Action
A5: =IF(B5="","",ProductPrefix&TEXT(ROW()-4,"0000")) -> 0 | B5: Willow cable beanie | D5: Crochet & knitting | E5: Active | F5: Autumn | G5: Moderate | H5: Etsy | I5: Standard | J5: First class - Domestic to 250g | K5: 140 | L5: 9 | M5: 78 | O5: 46305 | P5: 45917 | Q5: willowandthread.co/beanie | R5: Costed on the Crochet tab, not the bill of materials. | S5: =IF(B5="","",IF(C5<>"",C5,UPPER(LEFT(IF(D5="","GEN",D5),3))&"-"&TEXT(ROW()-4,"000"))) -> 0 | T5: =IF(B5="","",ROUND(SUMIFS('Material Usage'!$M$5:$M$904,'Material Usage'!$A$5:$A$904,A5)+SUMIFS(Crochet!$AD$5:$AD$84,Crochet!$A$5:$A$84,A5)+SUMIFS(Jewelry!$AF$5:$AF$84,Jewelry!$A$5:$A$84,A5)+SUMIFS(Candles!$AF$5:$AF$84,Candles!$A$5:$A$84,A5)+SUMIFS(Clothing!$AB$5:$AB$84,Clothing!$A$5:$A$84,A5)+SUMIFS(Woodworking!$AC$5:$AC$84,Woodworking!$A$5:$A$84,A5)+SUMIFS(Digital!$X$5:$X$84,Digital!$A$5:$A$84,A5),2)) -> 0 | U5: =IF(B5="","",ROUND(SUMIFS(Labor!$O$5:$O$304,Labor!$A$5:$A$304,A5)+SUMIFS(Crochet!$AG$5:$AG$84,Crochet!$A$5:$A$84,A5)+SUMIFS(Jewelry!$AI$5:$AI$84,Jewelry!$A$5:$A$84,A5)+SUMIFS(Candles!$AI$5:$AI$84,Candles!$A$5:$A$84,A5)+SUMIFS(Clothing!$AE$5:$AE$84,Clothing!$A$5:$A$84,A5)+SUMIFS(Woodworking!$AF$5:$AF$84,Woodworking!$A$5:$A$84,A5)+SUMIFS(Digital!$Z$5:$Z$84,Digital!$A$5:$A$84,A5),2)) -> 0 | V5: =IF(B5="","",ROUND(SUMIFS(Labor!$P$5:$P$304,Labor!$A$5:$A$304,A5)+SUMIFS(Crochet!$AE$5:$AE$84,Crochet!$A$5:$A$84,A5)+SUMIFS(Jewelry!$AG$5:$AG$84,Jewelry!$A$5:$A$84,A5)+SUMIFS(Candles!$AG$5:$AG$84,Candles!$A$5:$A$84,A5)+SUMIFS(Clothing!$AC$5:$AC$84,Clothing!$A$5:$A$84,A5)+SUMIFS(Woodworking!$AD$5:$AD$84,Woodworking!$A$5:$A$84,A5)+SUMIFS(Digital!$Y$5:$Y$84,Digital!$A$5:$A$84,A5),1)) -> 0 | W5: =IF(B5="","",IFERROR(INDEX(DiffTimeFactors,MATCH(G5,DiffNames,0)),1)) -> 0 | X5: =IF(B5="","",ROUND(V5*W5,1)) -> 0 | Y5: =IF(B5="","",ROUND(X5/60,3)) -> 0 | Z5: =IF(B5="","",ROUND(U5*W5,2)) -> 0 | AA5: =IF(B5="","",ROUND(SUMIFS(Labor!$Q$5:$Q$304,Labor!$A$5:$A$304,A5)+SUMIFS(Crochet!$AH$5:$AH$84,Crochet!$A$5:$A$84,A5)+SUMIFS(Jewelry!$AJ$5:$AJ$84,Jewelry!$A$5:$A$84,A5)+SUMIFS(Candles!$AJ$5:$AJ$84,Candles!$A$5:$A$84,A5)+SUMIFS(Clothing!$AF$5:$AF$84,Clothing!$A$5:$A$84,A5)+SUMIFS(Woodworking!$AH$5:$AH$84,Woodworking!$A$5:$A$84,A5)+SUMIFS(Digital!$AA$5:$AA$84,Digital!$A$5:$A$84,A5),2)) -> 0 | AB5: =IF(B5="","",ROUND(IF(I5="Budget",PackBudget,IF(I5="Standard",PackStandard,IF(I5="Gift",PackGift,IF(I5="Premium",PackPremium,DefaultPackaging)))),2)) -> 0 | AC5: =IF(B5="","",IF(I5="Budget",PackWeightBudget,IF(I5="Standard",PackWeightStandard,IF(I5="Gift",PackWeightGift,IF(I5="Premium",PackWeightPremium,0))))) -> 0 | AD5: =IF(B5="","",IFERROR(INDEX(Shipping!$M$5:$M$64,MATCH(J5,Shipping!$L$5:$L$64,0)),DefaultShipping)) -> 0 | AE5: =IF(B5="","",IFERROR(INDEX(Shipping!$F$5:$F$64,MATCH(J5,Shipping!$L$5:$L$64,0)),0)) -> 0 | AF5: =IF(B5="","",IFERROR(INDEX(Shipping!$C$5:$C$64,MATCH(J5,Shipping!$L$5:$L$64,0)),"")) -> 0 | AG5: =IF(B5="","",ROUND(MAX(0,AD5-AE5),2)) -> 0 | AH5: =IF(B5="","",ROUND(T5+Z5+AA5+AB5+AG5,2)) -> 0 | AI5: =IF(B5="","",IFERROR(INDEX(Channels!$S$5:$S$18,MATCH(IF(H5="",DefaultChannel,H5),Channels!$A$5:$A$18,0)),0)) -> 0 | AJ5: =IF(B5="","",IFERROR(INDEX(Channels!$O$5:$O$18,MATCH(IF(H5="",DefaultChannel,H5),Channels!$A$5:$A$18,0)),"No")) -> 0 | AK5: =IF(B5="","",ROUND(IFERROR(INDEX(Channels!$T$5:$T$18,MATCH(IF(H5="",DefaultChannel,H5),Channels!$A$5:$A$18,0)),0)+IF(AJ5="Yes",AE5*AI5,0),4)) -> 0 | AL5: =IF(B5="","",IF(OverheadMethod="Share of revenue",IF(RevenueTargetMonth<=0,0,OverheadMonthly/RevenueTargetMonth),0)) -> 0 | AM5: =IF(B5="","",IF(OverheadMethod="Per hour worked",ROUND(OverheadPerHour*Y5,2),IF(OR(OverheadMethod="Per unit made",OverheadMethod="Per order"),OverheadPerUnit,0))) -> 0 | AN5: =IF(B5="","",IF(N5<>"",N5,TargetRetailMargin)) -> 0 | AO5: =IF(B5="","",1-AN5-AI5-AL5) -> 0 | AP5: =IF(B5="","",IF(AO5<=0,"",(AH5+AM5+AK5)/AO5)) -> 0 | AQ5: =IF(B5="","",IF(AP5="","Check the settings",ROUND(IF(RoundingRule="None",AP5,IF(RoundingRule="Nearest 0.99",MAX(0.99,CEILING(AP5,1)-0.01),IF(RoundingRule="Nearest 0.95",MAX(0.95,CEILING(AP5,1)-0.05),IF(RoundingRule="Nearest 0.50",CEILING(AP5,0.5),IF(RoundingRule="Nearest 1",CEILING(AP5,1),IF(RoundingRule="Nearest 5",CEILING(AP5,5),IF(RoundingRule="Up to whole 1",CEILING(AP5,1),IF(RoundingRule="Up to whole 5",CEILING(AP5,5),ROUND(AP5,2))))))))),2))) -> 0 | AR5: =IF(B5="","",IF(M5<>"",M5,IF(ISNUMBER(AQ5),AQ5,""))) -> 0 | AS5: =IF(B5="","",IF(AR5="","",ROUND(AM5+AR5*AL5,2))) -> 0 | AT5: =IF(B5="","",IF(AR5="","",ROUND(AH5+AS5,2))) -> 0 | AU5: =IF(B5="","",IF(AR5="","",ROUND(AR5*AI5+AK5,2))) -> 0 | AV5: =IF(B5="","",IF(AR5="","",ROUND(AR5-AT5-AU5,2))) -> 0 | AW5: =IF(B5="","",IF(OR(AR5="",AR5=0),"",AV5/AR5)) -> 0 | AX5: =IF(B5="","",IF(OR(AT5="",AT5=0),"",AV5/AT5)) -> 0 | AY5: =IF(B5="","",IF(OR(Y5="",Y5=0,AV5=""),"",ROUND(AV5/Y5,2))) -> 0 | AZ5: =IF(B5="","",IF(OR(Y5="",Y5=0,AV5=""),"",ROUND((AV5+Z5)/Y5,2))) -> 0 | BA5: =IF(B5="","",IF(1-AI5-AL5<=0,"",ROUND((AH5+AM5+AK5)/(1-AI5-AL5),2))) -> 0 | BB5: =IF(B5="","",IF(AT5="","",ROUND(AT5*2,2))) -> 0 | BC5: =IF(B5="","",IF(AR5="","",ROUND(AR5*(1-WholesaleDiscount),2))) -> 0 | BD5: =IF(B5="","",IF(BC5="","",ROUND(BC5-AH5-AM5,2))) -> 0 | BE5: =IF(B5="","",IF(OR(BC5="",BC5=0),"",BD5/BC5)) -> 0 | BF5: =IF(B5="","",IFERROR(ROUND(AVERAGEIFS(Competitors!$F$5:$F$154,Competitors!$A$5:$A$154,A5),2),"")) -> 0 | BG5: =IF(B5="","",IF(OR(BF5="",BF5=0,AR5=""),"",AR5/BF5-1)) -> 0 | BH5: =IF(B5="","",SUMIFS(Sales!$D$5:$D$804,Sales!$C$5:$C$804,A5)) -> 0 | BI5: =IF(B5="","",ROUND(SUMIFS(Sales!$V$5:$V$804,Sales!$C$5:$C$804,A5),2)) -> 0 | BJ5: =IF(B5="","",ROUND(SUMIFS(Sales!$AG$5:$AG$804,Sales!$C$5:$C$804,A5),2)) -> 0 | BK5: =IF(B5="","",IF(OR(BI5="",BI5=0),"",BJ5/BI5)) -> 0 | BL5: =IF(B5="","",IF(SUMPRODUCT(MAX((Sales!$C$5:$C$804=A5)*Sales!$B$5:$B$804))=0,"",SUMPRODUCT(MAX((Sales!$C$5:$C$804=A5)*Sales!$B$5:$B$804)))) -> 0 | BM5: =IF(B5="","",IF(SUMPRODUCT(MAX(('Price History'!$B$5:$B$304=A5)*'Price History'!$A$5:$A$304))=0,IF(P5="","",P5),SUMPRODUCT(MAX(('Price History'!$B$5:$B$304=A5)*'Price History'!$A$5:$A$304)))) -> 0 | BN5: =IF(B5="","",IF(BM5="","",TodayDate-BM5)) -> 0 | BO5: =IF(B5="","",COUNTIFS($AV$5:$AV$304,">"&AV5)+COUNTIFS($AV$5:AV5,AV5)) -> 0 | BP5: =IF(B5="","",COUNTIFS($AW$5:$AW$304,">"&AW5)+COUNTIFS($AW$5:AW5,AW5)) -> 0 | BQ5: =IF(B5="","",COUNTIFS($BI$5:$BI$304,">"&BI5)+COUNTIFS($BI$5:BI5,BI5)) -> 0 | BR5: =IF(B5="","",COUNTIFS($AY$5:$AY$304,">"&AY5)+COUNTIFS($AY$5:AY5,AY5)) -> 0 | BS5: =IF(B5="","",IF(AH5=0,"Add - no costs entered yet",IF(AR5="","Check - no price yet",IF(AV5<0,"Loss - every sale costs you money",IF(AND(AZ5<>"",AZ5<MinimumWage),"Below - pays under minimum wage",IF(AW5<MarginWarning,"Low margin - re-price it",IF(AND(AF5<>"",K5<>"",K5+AC5>AF5),"Check - too heavy for that postage band",IF(AND(BN5<>"",BN5>PriceReviewDays),"Due - price has not been reviewed",IF(AND(BG5<>"",BG5>0.5),"Check - well above the market","OK")))))))) ) -> 0
A6: =IF(B6="","",ProductPrefix&TEXT(ROW()-4,"0000")) -> 0 | B6: Chunky market bag | D6: Bags & leather | E6: Active | F6: All year | G6: Simple | H6: Etsy | I6: Budget | J6: First class - Domestic to 500g | K6: 320 | L6: 6 | M6: 75 | O6: 46297 | P6: 45797 | S6: =IF(B6="","",IF(C6<>"",C6,UPPER(LEFT(IF(D6="","GEN",D6),3))&"-"&TEXT(ROW()-4,"000"))) -> 0 | T6: =IF(B6="","",ROUND(SUMIFS('Material Usage'!$M$5:$M$904,'Material Usage'!$A$5:$A$904,A6)+SUMIFS(Crochet!$AD$5:$AD$84,Crochet!$A$5:$A$84,A6)+SUMIFS(Jewelry!$AF$5:$AF$84,Jewelry!$A$5:$A$84,A6)+SUMIFS(Candles!$AF$5:$AF$84,Candles!$A$5:$A$84,A6)+SUMIFS(Clothing!$AB$5:$AB$84,Clothing!$A$5:$A$84,A6)+SUMIFS(Woodworking!$AC$5:$AC$84,Woodworking!$A$5:$A$84,A6)+SUMIFS(Digital!$X$5:$X$84,Digital!$A$5:$A$84,A6),2)) -> 0 | U6: =IF(B6="","",ROUND(SUMIFS(Labor!$O$5:$O$304,Labor!$A$5:$A$304,A6)+SUMIFS(Crochet!$AG$5:$AG$84,Crochet!$A$5:$A$84,A6)+SUMIFS(Jewelry!$AI$5:$AI$84,Jewelry!$A$5:$A$84,A6)+SUMIFS(Candles!$AI$5:$AI$84,Candles!$A$5:$A$84,A6)+SUMIFS(Clothing!$AE$5:$AE$84,Clothing!$A$5:$A$84,A6)+SUMIFS(Woodworking!$AF$5:$AF$84,Woodworking!$A$5:$A$84,A6)+SUMIFS(Digital!$Z$5:$Z$84,Digital!$A$5:$A$84,A6),2)) -> 0 | V6: =IF(B6="","",ROUND(SUMIFS(Labor!$P$5:$P$304,Labor!$A$5:$A$304,A6)+SUMIFS(Crochet!$AE$5:$AE$84,Crochet!$A$5:$A$84,A6)+SUMIFS(Jewelry!$AG$5:$AG$84,Jewelry!$A$5:$A$84,A6)+SUMIFS(Candles!$AG$5:$AG$84,Candles!$A$5:$A$84,A6)+SUMIFS(Clothing!$AC$5:$AC$84,Clothing!$A$5:$A$84,A6)+SUMIFS(Woodworking!$AD$5:$AD$84,Woodworking!$A$5:$A$84,A6)+SUMIFS(Digital!$Y$5:$Y$84,Digital!$A$5:$A$84,A6),1)) -> 0 | W6: =IF(B6="","",IFERROR(INDEX(DiffTimeFactors,MATCH(G6,DiffNames,0)),1)) -> 0 | X6: =IF(B6="","",ROUND(V6*W6,1)) -> 0 | Y6: =IF(B6="","",ROUND(X6/60,3)) -> 0 | Z6: =IF(B6="","",ROUND(U6*W6,2)) -> 0 | AA6: =IF(B6="","",ROUND(SUMIFS(Labor!$Q$5:$Q$304,Labor!$A$5:$A$304,A6)+SUMIFS(Crochet!$AH$5:$AH$84,Crochet!$A$5:$A$84,A6)+SUMIFS(Jewelry!$AJ$5:$AJ$84,Jewelry!$A$5:$A$84,A6)+SUMIFS(Candles!$AJ$5:$AJ$84,Candles!$A$5:$A$84,A6)+SUMIFS(Clothing!$AF$5:$AF$84,Clothing!$A$5:$A$84,A6)+SUMIFS(Woodworking!$AH$5:$AH$84,Woodworking!$A$5:$A$84,A6)+SUMIFS(Digital!$AA$5:$AA$84,Digital!$A$5:$A$84,A6),2)) -> 0 | AB6: =IF(B6="","",ROUND(IF(I6="Budget",PackBudget,IF(I6="Standard",PackStandard,IF(I6="Gift",PackGift,IF(I6="Premium",PackPremium,DefaultPackaging)))),2)) -> 0 | AC6: =IF(B6="","",IF(I6="Budget",PackWeightBudget,IF(I6="Standard",PackWeightStandard,IF(I6="Gift",PackWeightGift,IF(I6="Premium",PackWeightPremium,0))))) -> 0 | AD6: =IF(B6="","",IFERROR(INDEX(Shipping!$M$5:$M$64,MATCH(J6,Shipping!$L$5:$L$64,0)),DefaultShipping)) -> 0 | AE6: =IF(B6="","",IFERROR(INDEX(Shipping!$F$5:$F$64,MATCH(J6,Shipping!$L$5:$L$64,0)),0)) -> 0 | AF6: =IF(B6="","",IFERROR(INDEX(Shipping!$C$5:$C$64,MATCH(J6,Shipping!$L$5:$L$64,0)),"")) -> 0 | AG6: =IF(B6="","",ROUND(MAX(0,AD6-AE6),2)) -> 0 | AH6: =IF(B6="","",ROUND(T6+Z6+AA6+AB6+AG6,2)) -> 0 | AI6: =IF(B6="","",IFERROR(INDEX(Channels!$S$5:$S$18,MATCH(IF(H6="",DefaultChannel,H6),Channels!$A$5:$A$18,0)),0)) -> 0 | AJ6: =IF(B6="","",IFERROR(INDEX(Channels!$O$5:$O$18,MATCH(IF(H6="",DefaultChannel,H6),Channels!$A$5:$A$18,0)),"No")) -> 0 | AK6: =IF(B6="","",ROUND(IFERROR(INDEX(Channels!$T$5:$T$18,MATCH(IF(H6="",DefaultChannel,H6),Channels!$A$5:$A$18,0)),0)+IF(AJ6="Yes",AE6*AI6,0),4)) -> 0 | AL6: =IF(B6="","",IF(OverheadMethod="Share of revenue",IF(RevenueTargetMonth<=0,0,OverheadMonthly/RevenueTargetMonth),0)) -> 0 | AM6: =IF(B6="","",IF(OverheadMethod="Per hour worked",ROUND(OverheadPerHour*Y6,2),IF(OR(OverheadMethod="Per unit made",OverheadMethod="Per order"),OverheadPerUnit,0))) -> 0 | AN6: =IF(B6="","",IF(N6<>"",N6,TargetRetailMargin)) -> 0 | AO6: =IF(B6="","",1-AN6-AI6-AL6) -> 0 | AP6: =IF(B6="","",IF(AO6<=0,"",(AH6+AM6+AK6)/AO6)) -> 0 | AQ6: =IF(B6="","",IF(AP6="","Check the settings",ROUND(IF(RoundingRule="None",AP6,IF(RoundingRule="Nearest 0.99",MAX(0.99,CEILING(AP6,1)-0.01),IF(RoundingRule="Nearest 0.95",MAX(0.95,CEILING(AP6,1)-0.05),IF(RoundingRule="Nearest 0.50",CEILING(AP6,0.5),IF(RoundingRule="Nearest 1",CEILING(AP6,1),IF(RoundingRule="Nearest 5",CEILING(AP6,5),IF(RoundingRule="Up to whole 1",CEILING(AP6,1),IF(RoundingRule="Up to whole 5",CEILING(AP6,5),ROUND(AP6,2))))))))),2))) -> 0 | AR6: =IF(B6="","",IF(M6<>"",M6,IF(ISNUMBER(AQ6),AQ6,""))) -> 0 | AS6: =IF(B6="","",IF(AR6="","",ROUND(AM6+AR6*AL6,2))) -> 0 | AT6: =IF(B6="","",IF(AR6="","",ROUND(AH6+AS6,2))) -> 0 | AU6: =IF(B6="","",IF(AR6="","",ROUND(AR6*AI6+AK6,2))) -> 0 | AV6: =IF(B6="","",IF(AR6="","",ROUND(AR6-AT6-AU6,2))) -> 0 | AW6: =IF(B6="","",IF(OR(AR6="",AR6=0),"",AV6/AR6)) -> 0 | AX6: =IF(B6="","",IF(OR(AT6="",AT6=0),"",AV6/AT6)) -> 0 | AY6: =IF(B6="","",IF(OR(Y6="",Y6=0,AV6=""),"",ROUND(AV6/Y6,2))) -> 0 | AZ6: =IF(B6="","",IF(OR(Y6="",Y6=0,AV6=""),"",ROUND((AV6+Z6)/Y6,2))) -> 0 | BA6: =IF(B6="","",IF(1-AI6-AL6<=0,"",ROUND((AH6+AM6+AK6)/(1-AI6-AL6),2))) -> 0 | BB6: =IF(B6="","",IF(AT6="","",ROUND(AT6*2,2))) -> 0 | BC6: =IF(B6="","",IF(AR6="","",ROUND(AR6*(1-WholesaleDiscount),2))) -> 0 | BD6: =IF(B6="","",IF(BC6="","",ROUND(BC6-AH6-AM6,2))) -> 0 | BE6: =IF(B6="","",IF(OR(BC6="",BC6=0),"",BD6/BC6)) -> 0 | BF6: =IF(B6="","",IFERROR(ROUND(AVERAGEIFS(Competitors!$F$5:$F$154,Competitors!$A$5:$A$154,A6),2),"")) -> 0 | BG6: =IF(B6="","",IF(OR(BF6="",BF6=0,AR6=""),"",AR6/BF6-1)) -> 0 | BH6: =IF(B6="","",SUMIFS(Sales!$D$5:$D$804,Sales!$C$5:$C$804,A6)) -> 0 | BI6: =IF(B6="","",ROUND(SUMIFS(Sales!$V$5:$V$804,Sales!$C$5:$C$804,A6),2)) -> 0 | BJ6: =IF(B6="","",ROUND(SUMIFS(Sales!$AG$5:$AG$804,Sales!$C$5:$C$804,A6),2)) -> 0 | BK6: =IF(B6="","",IF(OR(BI6="",BI6=0),"",BJ6/BI6)) -> 0 | BL6: =IF(B6="","",IF(SUMPRODUCT(MAX((Sales!$C$5:$C$804=A6)*Sales!$B$5:$B$804))=0,"",SUMPRODUCT(MAX((Sales!$C$5:$C$804=A6)*Sales!$B$5:$B$804)))) -> 0 | BM6: =IF(B6="","",IF(SUMPRODUCT(MAX(('Price History'!$B$5:$B$304=A6)*'Price History'!$A$5:$A$304))=0,IF(P6="","",P6),SUMPRODUCT(MAX(('Price History'!$B$5:$B$304=A6)*'Price History'!$A$5:$A$304)))) -> 0 | BN6: =IF(B6="","",IF(BM6="","",TodayDate-BM6)) -> 0 | BO6: =IF(B6="","",COUNTIFS($AV$5:$AV$304,">"&AV6)+COUNTIFS($AV$5:AV6,AV6)) -> 0 | BP6: =IF(B6="","",COUNTIFS($AW$5:$AW$304,">"&AW6)+COUNTIFS($AW$5:AW6,AW6)) -> 0 | BQ6: =IF(B6="","",COUNTIFS($BI$5:$BI$304,">"&BI6)+COUNTIFS($BI$5:BI6,BI6)) -> 0 | BR6: =IF(B6="","",COUNTIFS($AY$5:$AY$304,">"&AY6)+COUNTIFS($AY$5:AY6,AY6)) -> 0 | BS6: =IF(B6="","",IF(AH6=0,"Add - no costs entered yet",IF(AR6="","Check - no price yet",IF(AV6<0,"Loss - every sale costs you money",IF(AND(AZ6<>"",AZ6<MinimumWage),"Below - pays under minimum wage",IF(AW6<MarginWarning,"Low margin - re-price it",IF(AND(AF6<>"",K6<>"",K6+AC6>AF6),"Check - too heavy for that postage band",IF(AND(BN6<>"",BN6>PriceReviewDays),"Due - price has not been reviewed",IF(AND(BG6<>"",BG6>0.5),"Check - well above the market","OK")))))))) ) -> 0
A7: =IF(B7="","",ProductPrefix&TEXT(ROW()-4,"0000")) -> 0 | B7: Woodland fox amigurumi | D7: Toys & amigurumi | E7: Active | F7: Christmas | G7: Moderate | H7: Etsy | I7: Gift | J7: First class - Domestic to 500g | K7: 180 | L7: 4 | M7: 78 | O7: 46310 | P7: 46017 | S7: =IF(B7="","",IF(C7<>"",C7,UPPER(LEFT(IF(D7="","GEN",D7),3))&"-"&TEXT(ROW()-4,"000"))) -> 0 | T7: =IF(B7="","",ROUND(SUMIFS('Material Usage'!$M$5:$M$904,'Material Usage'!$A$5:$A$904,A7)+SUMIFS(Crochet!$AD$5:$AD$84,Crochet!$A$5:$A$84,A7)+SUMIFS(Jewelry!$AF$5:$AF$84,Jewelry!$A$5:$A$84,A7)+SUMIFS(Candles!$AF$5:$AF$84,Candles!$A$5:$A$84,A7)+SUMIFS(Clothing!$AB$5:$AB$84,Clothing!$A$5:$A$84,A7)+SUMIFS(Woodworking!$AC$5:$AC$84,Woodworking!$A$5:$A$84,A7)+SUMIFS(Digital!$X$5:$X$84,Digital!$A$5:$A$84,A7),2)) -> 0 | U7: =IF(B7="","",ROUND(SUMIFS(Labor!$O$5:$O$304,Labor!$A$5:$A$304,A7)+SUMIFS(Crochet!$AG$5:$AG$84,Crochet!$A$5:$A$84,A7)+SUMIFS(Jewelry!$AI$5:$AI$84,Jewelry!$A$5:$A$84,A7)+SUMIFS(Candles!$AI$5:$AI$84,Candles!$A$5:$A$84,A7)+SUMIFS(Clothing!$AE$5:$AE$84,Clothing!$A$5:$A$84,A7)+SUMIFS(Woodworking!$AF$5:$AF$84,Woodworking!$A$5:$A$84,A7)+SUMIFS(Digital!$Z$5:$Z$84,Digital!$A$5:$A$84,A7),2)) -> 0 | V7: =IF(B7="","",ROUND(SUMIFS(Labor!$P$5:$P$304,Labor!$A$5:$A$304,A7)+SUMIFS(Crochet!$AE$5:$AE$84,Crochet!$A$5:$A$84,A7)+SUMIFS(Jewelry!$AG$5:$AG$84,Jewelry!$A$5:$A$84,A7)+SUMIFS(Candles!$AG$5:$AG$84,Candles!$A$5:$A$84,A7)+SUMIFS(Clothing!$AC$5:$AC$84,Clothing!$A$5:$A$84,A7)+SUMIFS(Woodworking!$AD$5:$AD$84,Woodworking!$A$5:$A$84,A7)+SUMIFS(Digital!$Y$5:$Y$84,Digital!$A$5:$A$84,A7),1)) -> 0 | W7: =IF(B7="","",IFERROR(INDEX(DiffTimeFactors,MATCH(G7,DiffNames,0)),1)) -> 0 | X7: =IF(B7="","",ROUND(V7*W7,1)) -> 0 | Y7: =IF(B7="","",ROUND(X7/60,3)) -> 0 | Z7: =IF(B7="","",ROUND(U7*W7,2)) -> 0 | AA7: =IF(B7="","",ROUND(SUMIFS(Labor!$Q$5:$Q$304,Labor!$A$5:$A$304,A7)+SUMIFS(Crochet!$AH$5:$AH$84,Crochet!$A$5:$A$84,A7)+SUMIFS(Jewelry!$AJ$5:$AJ$84,Jewelry!$A$5:$A$84,A7)+SUMIFS(Candles!$AJ$5:$AJ$84,Candles!$A$5:$A$84,A7)+SUMIFS(Clothing!$AF$5:$AF$84,Clothing!$A$5:$A$84,A7)+SUMIFS(Woodworking!$AH$5:$AH$84,Woodworking!$A$5:$A$84,A7)+SUMIFS(Digital!$AA$5:$AA$84,Digital!$A$5:$A$84,A7),2)) -> 0 | AB7: =IF(B7="","",ROUND(IF(I7="Budget",PackBudget,IF(I7="Standard",PackStandard,IF(I7="Gift",PackGift,IF(I7="Premium",PackPremium,DefaultPackaging)))),2)) -> 0 | AC7: =IF(B7="","",IF(I7="Budget",PackWeightBudget,IF(I7="Standard",PackWeightStandard,IF(I7="Gift",PackWeightGift,IF(I7="Premium",PackWeightPremium,0))))) -> 0 | AD7: =IF(B7="","",IFERROR(INDEX(Shipping!$M$5:$M$64,MATCH(J7,Shipping!$L$5:$L$64,0)),DefaultShipping)) -> 0 | AE7: =IF(B7="","",IFERROR(INDEX(Shipping!$F$5:$F$64,MATCH(J7,Shipping!$L$5:$L$64,0)),0)) -> 0 | AF7: =IF(B7="","",IFERROR(INDEX(Shipping!$C$5:$C$64,MATCH(J7,Shipping!$L$5:$L$64,0)),"")) -> 0 | AG7: =IF(B7="","",ROUND(MAX(0,AD7-AE7),2)) -> 0 | AH7: =IF(B7="","",ROUND(T7+Z7+AA7+AB7+AG7,2)) -> 0 | AI7: =IF(B7="","",IFERROR(INDEX(Channels!$S$5:$S$18,MATCH(IF(H7="",DefaultChannel,H7),Channels!$A$5:$A$18,0)),0)) -> 0 | AJ7: =IF(B7="","",IFERROR(INDEX(Channels!$O$5:$O$18,MATCH(IF(H7="",DefaultChannel,H7),Channels!$A$5:$A$18,0)),"No")) -> 0 | AK7: =IF(B7="","",ROUND(IFERROR(INDEX(Channels!$T$5:$T$18,MATCH(IF(H7="",DefaultChannel,H7),Channels!$A$5:$A$18,0)),0)+IF(AJ7="Yes",AE7*AI7,0),4)) -> 0 | AL7: =IF(B7="","",IF(OverheadMethod="Share of revenue",IF(RevenueTargetMonth<=0,0,OverheadMonthly/RevenueTargetMonth),0)) -> 0 | AM7: =IF(B7="","",IF(OverheadMethod="Per hour worked",ROUND(OverheadPerHour*Y7,2),IF(OR(OverheadMethod="Per unit made",OverheadMethod="Per order"),OverheadPerUnit,0))) -> 0 | AN7: =IF(B7="","",IF(N7<>"",N7,TargetRetailMargin)) -> 0 | AO7: =IF(B7="","",1-AN7-AI7-AL7) -> 0 | AP7: =IF(B7="","",IF(AO7<=0,"",(AH7+AM7+AK7)/AO7)) -> 0 | AQ7: =IF(B7="","",IF(AP7="","Check the settings",ROUND(IF(RoundingRule="None",AP7,IF(RoundingRule="Nearest 0.99",MAX(0.99,CEILING(AP7,1)-0.01),IF(RoundingRule="Nearest 0.95",MAX(0.95,CEILING(AP7,1)-0.05),IF(RoundingRule="Nearest 0.50",CEILING(AP7,0.5),IF(RoundingRule="Nearest 1",CEILING(AP7,1),IF(RoundingRule="Nearest 5",CEILING(AP7,5),IF(RoundingRule="Up to whole 1",CEILING(AP7,1),IF(RoundingRule="Up to whole 5",CEILING(AP7,5),ROUND(AP7,2))))))))),2))) -> 0 | AR7: =IF(B7="","",IF(M7<>"",M7,IF(ISNUMBER(AQ7),AQ7,""))) -> 0 | AS7: =IF(B7="","",IF(AR7="","",ROUND(AM7+AR7*AL7,2))) -> 0 | AT7: =IF(B7="","",IF(AR7="","",ROUND(AH7+AS7,2))) -> 0 | AU7: =IF(B7="","",IF(AR7="","",ROUND(AR7*AI7+AK7,2))) -> 0 | AV7: =IF(B7="","",IF(AR7="","",ROUND(AR7-AT7-AU7,2))) -> 0 | AW7: =IF(B7="","",IF(OR(AR7="",AR7=0),"",AV7/AR7)) -> 0 | AX7: =IF(B7="","",IF(OR(AT7="",AT7=0),"",AV7/AT7)) -> 0 | AY7: =IF(B7="","",IF(OR(Y7="",Y7=0,AV7=""),"",ROUND(AV7/Y7,2))) -> 0 | AZ7: =IF(B7="","",IF(OR(Y7="",Y7=0,AV7=""),"",ROUND((AV7+Z7)/Y7,2))) -> 0 | BA7: =IF(B7="","",IF(1-AI7-AL7<=0,"",ROUND((AH7+AM7+AK7)/(1-AI7-AL7),2))) -> 0 | BB7: =IF(B7="","",IF(AT7="","",ROUND(AT7*2,2))) -> 0 | BC7: =IF(B7="","",IF(AR7="","",ROUND(AR7*(1-WholesaleDiscount),2))) -> 0 | BD7: =IF(B7="","",IF(BC7="","",ROUND(BC7-AH7-AM7,2))) -> 0 | BE7: =IF(B7="","",IF(OR(BC7="",BC7=0),"",BD7/BC7)) -> 0 | BF7: =IF(B7="","",IFERROR(ROUND(AVERAGEIFS(Competitors!$F$5:$F$154,Competitors!$A$5:$A$154,A7),2),"")) -> 0 | BG7: =IF(B7="","",IF(OR(BF7="",BF7=0,AR7=""),"",AR7/BF7-1)) -> 0 | BH7: =IF(B7="","",SUMIFS(Sales!$D$5:$D$804,Sales!$C$5:$C$804,A7)) -> 0 | BI7: =IF(B7="","",ROUND(SUMIFS(Sales!$V$5:$V$804,Sales!$C$5:$C$804,A7),2)) -> 0 | BJ7: =IF(B7="","",ROUND(SUMIFS(Sales!$AG$5:$AG$804,Sales!$C$5:$C$804,A7),2)) -> 0 | BK7: =IF(B7="","",IF(OR(BI7="",BI7=0),"",BJ7/BI7)) -> 0 | BL7: =IF(B7="","",IF(SUMPRODUCT(MAX((Sales!$C$5:$C$804=A7)*Sales!$B$5:$B$804))=0,"",SUMPRODUCT(MAX((Sales!$C$5:$C$804=A7)*Sales!$B$5:$B$804)))) -> 0 | BM7: =IF(B7="","",IF(SUMPRODUCT(MAX(('Price History'!$B$5:$B$304=A7)*'Price History'!$A$5:$A$304))=0,IF(P7="","",P7),SUMPRODUCT(MAX(('Price History'!$B$5:$B$304=A7)*'Price History'!$A$5:$A$304)))) -> 0 | BN7: =IF(B7="","",IF(BM7="","",TodayDate-BM7)) -> 0 | BO7: =IF(B7="","",COUNTIFS($AV$5:$AV$304,">"&AV7)+COUNTIFS($AV$5:AV7,AV7)) -> 0 | BP7: =IF(B7="","",COUNTIFS($AW$5:$AW$304,">"&AW7)+COUNTIFS($AW$5:AW7,AW7)) -> 0 | BQ7: =IF(B7="","",COUNTIFS($BI$5:$BI$304,">"&BI7)+COUNTIFS($BI$5:BI7,BI7)) -> 0 | BR7: =IF(B7="","",COUNTIFS($AY$5:$AY$304,">"&AY7)+COUNTIFS($AY$5:AY7,AY7)) -> 0 | BS7: =IF(B7="","",IF(AH7=0,"Add - no costs entered yet",IF(AR7="","Check - no price yet",IF(AV7<0,"Loss - every sale costs you money",IF(AND(AZ7<>"",AZ7<MinimumWage),"Below - pays under minimum wage",IF(AW7<MarginWarning,"Low margin - re-price it",IF(AND(AF7<>"",K7<>"",K7+AC7>AF7),"Check - too heavy for that postage band",IF(AND(BN7<>"",BN7>PriceReviewDays),"Due - price has not been reviewed",IF(AND(BG7<>"",BG7>0.5),"Check - well above the market","OK")))))))) ) -> 0
A8: =IF(B8="","",ProductPrefix&TEXT(ROW()-4,"0000")) -> 0 | B8: Hammered silver stacking ring | D8: Jewelry | E8: Active | F8: All year | G8: Moderate | H8: Etsy | I8: Gift | J8: First class - Domestic to 100g | K8: 25 | L8: 14 | M8: 58 | O8: 46308 | P8: 45697 | S8: =IF(B8="","",IF(C8<>"",C8,UPPER(LEFT(IF(D8="","GEN",D8),3))&"-"&TEXT(ROW()-4,"000"))) -> 0 | T8: =IF(B8="","",ROUND(SUMIFS('Material Usage'!$M$5:$M$904,'Material Usage'!$A$5:$A$904,A8)+SUMIFS(Crochet!$AD$5:$AD$84,Crochet!$A$5:$A$84,A8)+SUMIFS(Jewelry!$AF$5:$AF$84,Jewelry!$A$5:$A$84,A8)+SUMIFS(Candles!$AF$5:$AF$84,Candles!$A$5:$A$84,A8)+SUMIFS(Clothing!$AB$5:$AB$84,Clothing!$A$5:$A$84,A8)+SUMIFS(Woodworking!$AC$5:$AC$84,Woodworking!$A$5:$A$84,A8)+SUMIFS(Digital!$X$5:$X$84,Digital!$A$5:$A$84,A8),2)) -> 0 | U8: =IF(B8="","",ROUND(SUMIFS(Labor!$O$5:$O$304,Labor!$A$5:$A$304,A8)+SUMIFS(Crochet!$AG$5:$AG$84,Crochet!$A$5:$A$84,A8)+SUMIFS(Jewelry!$AI$5:$AI$84,Jewelry!$A$5:$A$84,A8)+SUMIFS(Candles!$AI$5:$AI$84,Candles!$A$5:$A$84,A8)+SUMIFS(Clothing!$AE$5:$AE$84,Clothing!$A$5:$A$84,A8)+SUMIFS(Woodworking!$AF$5:$AF$84,Woodworking!$A$5:$A$84,A8)+SUMIFS(Digital!$Z$5:$Z$84,Digital!$A$5:$A$84,A8),2)) -> 0 | V8: =IF(B8="","",ROUND(SUMIFS(Labor!$P$5:$P$304,Labor!$A$5:$A$304,A8)+SUMIFS(Crochet!$AE$5:$AE$84,Crochet!$A$5:$A$84,A8)+SUMIFS(Jewelry!$AG$5:$AG$84,Jewelry!$A$5:$A$84,A8)+SUMIFS(Candles!$AG$5:$AG$84,Candles!$A$5:$A$84,A8)+SUMIFS(Clothing!$AC$5:$AC$84,Clothing!$A$5:$A$84,A8)+SUMIFS(Woodworking!$AD$5:$AD$84,Woodworking!$A$5:$A$84,A8)+SUMIFS(Digital!$Y$5:$Y$84,Digital!$A$5:$A$84,A8),1)) -> 0 | W8: =IF(B8="","",IFERROR(INDEX(DiffTimeFactors,MATCH(G8,DiffNames,0)),1)) -> 0 | X8: =IF(B8="","",ROUND(V8*W8,1)) -> 0 | Y8: =IF(B8="","",ROUND(X8/60,3)) -> 0 | Z8: =IF(B8="","",ROUND(U8*W8,2)) -> 0 | AA8: =IF(B8="","",ROUND(SUMIFS(Labor!$Q$5:$Q$304,Labor!$A$5:$A$304,A8)+SUMIFS(Crochet!$AH$5:$AH$84,Crochet!$A$5:$A$84,A8)+SUMIFS(Jewelry!$AJ$5:$AJ$84,Jewelry!$A$5:$A$84,A8)+SUMIFS(Candles!$AJ$5:$AJ$84,Candles!$A$5:$A$84,A8)+SUMIFS(Clothing!$AF$5:$AF$84,Clothing!$A$5:$A$84,A8)+SUMIFS(Woodworking!$AH$5:$AH$84,Woodworking!$A$5:$A$84,A8)+SUMIFS(Digital!$AA$5:$AA$84,Digital!$A$5:$A$84,A8),2)) -> 0 | AB8: =IF(B8="","",ROUND(IF(I8="Budget",PackBudget,IF(I8="Standard",PackStandard,IF(I8="Gift",PackGift,IF(I8="Premium",PackPremium,DefaultPackaging)))),2)) -> 0 | AC8: =IF(B8="","",IF(I8="Budget",PackWeightBudget,IF(I8="Standard",PackWeightStandard,IF(I8="Gift",PackWeightGift,IF(I8="Premium",PackWeightPremium,0))))) -> 0 | AD8: =IF(B8="","",IFERROR(INDEX(Shipping!$M$5:$M$64,MATCH(J8,Shipping!$L$5:$L$64,0)),DefaultShipping)) -> 0 | AE8: =IF(B8="","",IFERROR(INDEX(Shipping!$F$5:$F$64,MATCH(J8,Shipping!$L$5:$L$64,0)),0)) -> 0 | AF8: =IF(B8="","",IFERROR(INDEX(Shipping!$C$5:$C$64,MATCH(J8,Shipping!$L$5:$L$64,0)),"")) -> 0 | AG8: =IF(B8="","",ROUND(MAX(0,AD8-AE8),2)) -> 0 | AH8: =IF(B8="","",ROUND(T8+Z8+AA8+AB8+AG8,2)) -> 0 | AI8: =IF(B8="","",IFERROR(INDEX(Channels!$S$5:$S$18,MATCH(IF(H8="",DefaultChannel,H8),Channels!$A$5:$A$18,0)),0)) -> 0 | AJ8: =IF(B8="","",IFERROR(INDEX(Channels!$O$5:$O$18,MATCH(IF(H8="",DefaultChannel,H8),Channels!$A$5:$A$18,0)),"No")) -> 0 | AK8: =IF(B8="","",ROUND(IFERROR(INDEX(Channels!$T$5:$T$18,MATCH(IF(H8="",DefaultChannel,H8),Channels!$A$5:$A$18,0)),0)+IF(AJ8="Yes",AE8*AI8,0),4)) -> 0 | AL8: =IF(B8="","",IF(OverheadMethod="Share of revenue",IF(RevenueTargetMonth<=0,0,OverheadMonthly/RevenueTargetMonth),0)) -> 0 | AM8: =IF(B8="","",IF(OverheadMethod="Per hour worked",ROUND(OverheadPerHour*Y8,2),IF(OR(OverheadMethod="Per unit made",OverheadMethod="Per order"),OverheadPerUnit,0))) -> 0 | AN8: =IF(B8="","",IF(N8<>"",N8,TargetRetailMargin)) -> 0 | AO8: =IF(B8="","",1-AN8-AI8-AL8) -> 0 | AP8: =IF(B8="","",IF(AO8<=0,"",(AH8+AM8+AK8)/AO8)) -> 0 | AQ8: =IF(B8="","",IF(AP8="","Check the settings",ROUND(IF(RoundingRule="None",AP8,IF(RoundingRule="Nearest 0.99",MAX(0.99,CEILING(AP8,1)-0.01),IF(RoundingRule="Nearest 0.95",MAX(0.95,CEILING(AP8,1)-0.05),IF(RoundingRule="Nearest 0.50",CEILING(AP8,0.5),IF(RoundingRule="Nearest 1",CEILING(AP8,1),IF(RoundingRule="Nearest 5",CEILING(AP8,5),IF(RoundingRule="Up to whole 1",CEILING(AP8,1),IF(RoundingRule="Up to whole 5",CEILING(AP8,5),ROUND(AP8,2))))))))),2))) -> 0 | AR8: =IF(B8="","",IF(M8<>"",M8,IF(ISNUMBER(AQ8),AQ8,""))) -> 0 | AS8: =IF(B8="","",IF(AR8="","",ROUND(AM8+AR8*AL8,2))) -> 0 | AT8: =IF(B8="","",IF(AR8="","",ROUND(AH8+AS8,2))) -> 0 | AU8: =IF(B8="","",IF(AR8="","",ROUND(AR8*AI8+AK8,2))) -> 0 | AV8: =IF(B8="","",IF(AR8="","",ROUND(AR8-AT8-AU8,2))) -> 0 | AW8: =IF(B8="","",IF(OR(AR8="",AR8=0),"",AV8/AR8)) -> 0 | AX8: =IF(B8="","",IF(OR(AT8="",AT8=0),"",AV8/AT8)) -> 0 | AY8: =IF(B8="","",IF(OR(Y8="",Y8=0,AV8=""),"",ROUND(AV8/Y8,2))) -> 0 | AZ8: =IF(B8="","",IF(OR(Y8="",Y8=0,AV8=""),"",ROUND((AV8+Z8)/Y8,2))) -> 0 | BA8: =IF(B8="","",IF(1-AI8-AL8<=0,"",ROUND((AH8+AM8+AK8)/(1-AI8-AL8),2))) -> 0 | BB8: =IF(B8="","",IF(AT8="","",ROUND(AT8*2,2))) -> 0 | BC8: =IF(B8="","",IF(AR8="","",ROUND(AR8*(1-WholesaleDiscount),2))) -> 0 | BD8: =IF(B8="","",IF(BC8="","",ROUND(BC8-AH8-AM8,2))) -> 0 | BE8: =IF(B8="","",IF(OR(BC8="",BC8=0),"",BD8/BC8)) -> 0 | BF8: =IF(B8="","",IFERROR(ROUND(AVERAGEIFS(Competitors!$F$5:$F$154,Competitors!$A$5:$A$154,A8),2),"")) -> 0 | BG8: =IF(B8="","",IF(OR(BF8="",BF8=0,AR8=""),"",AR8/BF8-1)) -> 0 | BH8: =IF(B8="","",SUMIFS(Sales!$D$5:$D$804,Sales!$C$5:$C$804,A8)) -> 0 | BI8: =IF(B8="","",ROUND(SUMIFS(Sales!$V$5:$V$804,Sales!$C$5:$C$804,A8),2)) -> 0 | BJ8: =IF(B8="","",ROUND(SUMIFS(Sales!$AG$5:$AG$804,Sales!$C$5:$C$804,A8),2)) -> 0 | BK8: =IF(B8="","",IF(OR(BI8="",BI8=0),"",BJ8/BI8)) -> 0 | BL8: =IF(B8="","",IF(SUMPRODUCT(MAX((Sales!$C$5:$C$804=A8)*Sales!$B$5:$B$804))=0,"",SUMPRODUCT(MAX((Sales!$C$5:$C$804=A8)*Sales!$B$5:$B$804)))) -> 0 | BM8: =IF(B8="","",IF(SUMPRODUCT(MAX(('Price History'!$B$5:$B$304=A8)*'Price History'!$A$5:$A$304))=0,IF(P8="","",P8),SUMPRODUCT(MAX(('Price History'!$B$5:$B$304=A8)*'Price History'!$A$5:$A$304)))) -> 0 | BN8: =IF(B8="","",IF(BM8="","",TodayDate-BM8)) -> 0 | BO8: =IF(B8="","",COUNTIFS($AV$5:$AV$304,">"&AV8)+COUNTIFS($AV$5:AV8,AV8)) -> 0 | BP8: =IF(B8="","",COUNTIFS($AW$5:$AW$304,">"&AW8)+COUNTIFS($AW$5:AW8,AW8)) -> 0 | BQ8: =IF(B8="","",COUNTIFS($BI$5:$BI$304,">"&BI8)+COUNTIFS($BI$5:BI8,BI8)) -> 0 | BR8: =IF(B8="","",COUNTIFS($AY$5:$AY$304,">"&AY8)+COUNTIFS($AY$5:AY8,AY8)) -> 0 | BS8: =IF(B8="","",IF(AH8=0,"Add - no costs entered yet",IF(AR8="","Check - no price yet",IF(AV8<0,"Loss - every sale costs you money",IF(AND(AZ8<>"",AZ8<MinimumWage),"Below - pays under minimum wage",IF(AW8<MarginWarning,"Low margin - re-price it",IF(AND(AF8<>"",K8<>"",K8+AC8>AF8),"Check - too heavy for that postage band",IF(AND(BN8<>"",BN8>PriceReviewDays),"Due - price has not been reviewed",IF(AND(BG8<>"",BG8>0.5),"Check - well above the market","OK")))))))) ) -> 0
A9: =IF(B9="","",ProductPrefix&TEXT(ROW()-4,"0000")) -> 0 | B9: Sea glass pendant | D9: Jewelry | E9: Active | F9: Summer | G9: Simple | H9: Etsy | I9: Gift | J9: First class - Domestic to 100g | K9: 30 | L9: 11 | M9: 52 | O9: 46302 | P9: 45897 | S9: =IF(B9="","",IF(C9<>"",C9,UPPER(LEFT(IF(D9="","GEN",D9),3))&"-"&TEXT(ROW()-4,"000"))) -> 0 | T9: =IF(B9="","",ROUND(SUMIFS('Material Usage'!$M$5:$M$904,'Material Usage'!$A$5:$A$904,A9)+SUMIFS(Crochet!$AD$5:$AD$84,Crochet!$A$5:$A$84,A9)+SUMIFS(Jewelry!$AF$5:$AF$84,Jewelry!$A$5:$A$84,A9)+SUMIFS(Candles!$AF$5:$AF$84,Candles!$A$5:$A$84,A9)+SUMIFS(Clothing!$AB$5:$AB$84,Clothing!$A$5:$A$84,A9)+SUMIFS(Woodworking!$AC$5:$AC$84,Woodworking!$A$5:$A$84,A9)+SUMIFS(Digital!$X$5:$X$84,Digital!$A$5:$A$84,A9),2)) -> 0 | U9: =IF(B9="","",ROUND(SUMIFS(Labor!$O$5:$O$304,Labor!$A$5:$A$304,A9)+SUMIFS(Crochet!$AG$5:$AG$84,Crochet!$A$5:$A$84,A9)+SUMIFS(Jewelry!$AI$5:$AI$84,Jewelry!$A$5:$A$84,A9)+SUMIFS(Candles!$AI$5:$AI$84,Candles!$A$5:$A$84,A9)+SUMIFS(Clothing!$AE$5:$AE$84,Clothing!$A$5:$A$84,A9)+SUMIFS(Woodworking!$AF$5:$AF$84,Woodworking!$A$5:$A$84,A9)+SUMIFS(Digital!$Z$5:$Z$84,Digital!$A$5:$A$84,A9),2)) -> 0 | V9: =IF(B9="","",ROUND(SUMIFS(Labor!$P$5:$P$304,Labor!$A$5:$A$304,A9)+SUMIFS(Crochet!$AE$5:$AE$84,Crochet!$A$5:$A$84,A9)+SUMIFS(Jewelry!$AG$5:$AG$84,Jewelry!$A$5:$A$84,A9)+SUMIFS(Candles!$AG$5:$AG$84,Candles!$A$5:$A$84,A9)+SUMIFS(Clothing!$AC$5:$AC$84,Clothing!$A$5:$A$84,A9)+SUMIFS(Woodworking!$AD$5:$AD$84,Woodworking!$A$5:$A$84,A9)+SUMIFS(Digital!$Y$5:$Y$84,Digital!$A$5:$A$84,A9),1)) -> 0 | W9: =IF(B9="","",IFERROR(INDEX(DiffTimeFactors,MATCH(G9,DiffNames,0)),1)) -> 0 | X9: =IF(B9="","",ROUND(V9*W9,1)) -> 0 | Y9: =IF(B9="","",ROUND(X9/60,3)) -> 0 | Z9: =IF(B9="","",ROUND(U9*W9,2)) -> 0 | AA9: =IF(B9="","",ROUND(SUMIFS(Labor!$Q$5:$Q$304,Labor!$A$5:$A$304,A9)+SUMIFS(Crochet!$AH$5:$AH$84,Crochet!$A$5:$A$84,A9)+SUMIFS(Jewelry!$AJ$5:$AJ$84,Jewelry!$A$5:$A$84,A9)+SUMIFS(Candles!$AJ$5:$AJ$84,Candles!$A$5:$A$84,A9)+SUMIFS(Clothing!$AF$5:$AF$84,Clothing!$A$5:$A$84,A9)+SUMIFS(Woodworking!$AH$5:$AH$84,Woodworking!$A$5:$A$84,A9)+SUMIFS(Digital!$AA$5:$AA$84,Digital!$A$5:$A$84,A9),2)) -> 0 | AB9: =IF(B9="","",ROUND(IF(I9="Budget",PackBudget,IF(I9="Standard",PackStandard,IF(I9="Gift",PackGift,IF(I9="Premium",PackPremium,DefaultPackaging)))),2)) -> 0 | AC9: =IF(B9="","",IF(I9="Budget",PackWeightBudget,IF(I9="Standard",PackWeightStandard,IF(I9="Gift",PackWeightGift,IF(I9="Premium",PackWeightPremium,0))))) -> 0 | AD9: =IF(B9="","",IFERROR(INDEX(Shipping!$M$5:$M$64,MATCH(J9,Shipping!$L$5:$L$64,0)),DefaultShipping)) -> 0 | AE9: =IF(B9="","",IFERROR(INDEX(Shipping!$F$5:$F$64,MATCH(J9,Shipping!$L$5:$L$64,0)),0)) -> 0 | AF9: =IF(B9="","",IFERROR(INDEX(Shipping!$C$5:$C$64,MATCH(J9,Shipping!$L$5:$L$64,0)),"")) -> 0 | AG9: =IF(B9="","",ROUND(MAX(0,AD9-AE9),2)) -> 0 | AH9: =IF(B9="","",ROUND(T9+Z9+AA9+AB9+AG9,2)) -> 0 | AI9: =IF(B9="","",IFERROR(INDEX(Channels!$S$5:$S$18,MATCH(IF(H9="",DefaultChannel,H9),Channels!$A$5:$A$18,0)),0)) -> 0 | AJ9: =IF(B9="","",IFERROR(INDEX(Channels!$O$5:$O$18,MATCH(IF(H9="",DefaultChannel,H9),Channels!$A$5:$A$18,0)),"No")) -> 0 | AK9: =IF(B9="","",ROUND(IFERROR(INDEX(Channels!$T$5:$T$18,MATCH(IF(H9="",DefaultChannel,H9),Channels!$A$5:$A$18,0)),0)+IF(AJ9="Yes",AE9*AI9,0),4)) -> 0 | AL9: =IF(B9="","",IF(OverheadMethod="Share of revenue",IF(RevenueTargetMonth<=0,0,OverheadMonthly/RevenueTargetMonth),0)) -> 0 | AM9: =IF(B9="","",IF(OverheadMethod="Per hour worked",ROUND(OverheadPerHour*Y9,2),IF(OR(OverheadMethod="Per unit made",OverheadMethod="Per order"),OverheadPerUnit,0))) -> 0 | AN9: =IF(B9="","",IF(N9<>"",N9,TargetRetailMargin)) -> 0 | AO9: =IF(B9="","",1-AN9-AI9-AL9) -> 0 | AP9: =IF(B9="","",IF(AO9<=0,"",(AH9+AM9+AK9)/AO9)) -> 0 | AQ9: =IF(B9="","",IF(AP9="","Check the settings",ROUND(IF(RoundingRule="None",AP9,IF(RoundingRule="Nearest 0.99",MAX(0.99,CEILING(AP9,1)-0.01),IF(RoundingRule="Nearest 0.95",MAX(0.95,CEILING(AP9,1)-0.05),IF(RoundingRule="Nearest 0.50",CEILING(AP9,0.5),IF(RoundingRule="Nearest 1",CEILING(AP9,1),IF(RoundingRule="Nearest 5",CEILING(AP9,5),IF(RoundingRule="Up to whole 1",CEILING(AP9,1),IF(RoundingRule="Up to whole 5",CEILING(AP9,5),ROUND(AP9,2))))))))),2))) -> 0 | AR9: =IF(B9="","",IF(M9<>"",M9,IF(ISNUMBER(AQ9),AQ9,""))) -> 0 | AS9: =IF(B9="","",IF(AR9="","",ROUND(AM9+AR9*AL9,2))) -> 0 | AT9: =IF(B9="","",IF(AR9="","",ROUND(AH9+AS9,2))) -> 0 | AU9: =IF(B9="","",IF(AR9="","",ROUND(AR9*AI9+AK9,2))) -> 0 | AV9: =IF(B9="","",IF(AR9="","",ROUND(AR9-AT9-AU9,2))) -> 0 | AW9: =IF(B9="","",IF(OR(AR9="",AR9=0),"",AV9/AR9)) -> 0 | AX9: =IF(B9="","",IF(OR(AT9="",AT9=0),"",AV9/AT9)) -> 0 | AY9: =IF(B9="","",IF(OR(Y9="",Y9=0,AV9=""),"",ROUND(AV9/Y9,2))) -> 0 | AZ9: =IF(B9="","",IF(OR(Y9="",Y9=0,AV9=""),"",ROUND((AV9+Z9)/Y9,2))) -> 0 | BA9: =IF(B9="","",IF(1-AI9-AL9<=0,"",ROUND((AH9+AM9+AK9)/(1-AI9-AL9),2))) -> 0 | BB9: =IF(B9="","",IF(AT9="","",ROUND(AT9*2,2))) -> 0 | BC9: =IF(B9="","",IF(AR9="","",ROUND(AR9*(1-WholesaleDiscount),2))) -> 0 | BD9: =IF(B9="","",IF(BC9="","",ROUND(BC9-AH9-AM9,2))) -> 0 | BE9: =IF(B9="","",IF(OR(BC9="",BC9=0),"",BD9/BC9)) -> 0 | BF9: =IF(B9="","",IFERROR(ROUND(AVERAGEIFS(Competitors!$F$5:$F$154,Competitors!$A$5:$A$154,A9),2),"")) -> 0 | BG9: =IF(B9="","",IF(OR(BF9="",BF9=0,AR9=""),"",AR9/BF9-1)) -> 0 | BH9: =IF(B9="","",SUMIFS(Sales!$D$5:$D$804,Sales!$C$5:$C$804,A9)) -> 0 | BI9: =IF(B9="","",ROUND(SUMIFS(Sales!$V$5:$V$804,Sales!$C$5:$C$804,A9),2)) -> 0 | BJ9: =IF(B9="","",ROUND(SUMIFS(Sales!$AG$5:$AG$804,Sales!$C$5:$C$804,A9),2)) -> 0 | BK9: =IF(B9="","",IF(OR(BI9="",BI9=0),"",BJ9/BI9)) -> 0 | BL9: =IF(B9="","",IF(SUMPRODUCT(MAX((Sales!$C$5:$C$804=A9)*Sales!$B$5:$B$804))=0,"",SUMPRODUCT(MAX((Sales!$C$5:$C$804=A9)*Sales!$B$5:$B$804)))) -> 0 | BM9: =IF(B9="","",IF(SUMPRODUCT(MAX(('Price History'!$B$5:$B$304=A9)*'Price History'!$A$5:$A$304))=0,IF(P9="","",P9),SUMPRODUCT(MAX(('Price History'!$B$5:$B$304=A9)*'Price History'!$A$5:$A$304)))) -> 0 | BN9: =IF(B9="","",IF(BM9="","",TodayDate-BM9)) -> 0 | BO9: =IF(B9="","",COUNTIFS($AV$5:$AV$304,">"&AV9)+COUNTIFS($AV$5:AV9,AV9)) -> 0 | BP9: =IF(B9="","",COUNTIFS($AW$5:$AW$304,">"&AW9)+COUNTIFS($AW$5:AW9,AW9)) -> 0 | BQ9: =IF(B9="","",COUNTIFS($BI$5:$BI$304,">"&BI9)+COUNTIFS($BI$5:BI9,BI9)) -> 0 | BR9: =IF(B9="","",COUNTIFS($AY$5:$AY$304,">"&AY9)+COUNTIFS($AY$5:AY9,AY9)) -> 0 | BS9: =IF(B9="","",IF(AH9=0,"Add - no costs entered yet",IF(AR9="","Check - no price yet",IF(AV9<0,"Loss - every sale costs you money",IF(AND(AZ9<>"",AZ9<MinimumWage),"Below - pays under minimum wage",IF(AW9<MarginWarning,"Low margin - re-price it",IF(AND(AF9<>"",K9<>"",K9+AC9>AF9),"Check - too heavy for that postage band",IF(AND(BN9<>"",BN9>PriceReviewDays),"Due - price has not been reviewed",IF(AND(BG9<>"",BG9>0.5),"Check - well above the market","OK")))))))) ) -> 0
A10: =IF(B10="","",ProductPrefix&TEXT(ROW()-4,"0000")) -> 0 | B10: Amber & fir candle 220 ml | D10: Candles & home fragrance | E10: Active | F10: Winter | G10: Simple | H10: Etsy | I10: Standard | J10: Priority - Domestic to 1,000g | K10: 520 | L10: 22 | M10: 32 | O10: 46312 | P10: 46057 | S10: =IF(B10="","",IF(C10<>"",C10,UPPER(LEFT(IF(D10="","GEN",D10),3))&"-"&TEXT(ROW()-4,"000"))) -> 0 | T10: =IF(B10="","",ROUND(SUMIFS('Material Usage'!$M$5:$M$904,'Material Usage'!$A$5:$A$904,A10)+SUMIFS(Crochet!$AD$5:$AD$84,Crochet!$A$5:$A$84,A10)+SUMIFS(Jewelry!$AF$5:$AF$84,Jewelry!$A$5:$A$84,A10)+SUMIFS(Candles!$AF$5:$AF$84,Candles!$A$5:$A$84,A10)+SUMIFS(Clothing!$AB$5:$AB$84,Clothing!$A$5:$A$84,A10)+SUMIFS(Woodworking!$AC$5:$AC$84,Woodworking!$A$5:$A$84,A10)+SUMIFS(Digital!$X$5:$X$84,Digital!$A$5:$A$84,A10),2)) -> 0 | U10: =IF(B10="","",ROUND(SUMIFS(Labor!$O$5:$O$304,Labor!$A$5:$A$304,A10)+SUMIFS(Crochet!$AG$5:$AG$84,Crochet!$A$5:$A$84,A10)+SUMIFS(Jewelry!$AI$5:$AI$84,Jewelry!$A$5:$A$84,A10)+SUMIFS(Candles!$AI$5:$AI$84,Candles!$A$5:$A$84,A10)+SUMIFS(Clothing!$AE$5:$AE$84,Clothing!$A$5:$A$84,A10)+SUMIFS(Woodworking!$AF$5:$AF$84,Woodworking!$A$5:$A$84,A10)+SUMIFS(Digital!$Z$5:$Z$84,Digital!$A$5:$A$84,A10),2)) -> 0 | V10: =IF(B10="","",ROUND(SUMIFS(Labor!$P$5:$P$304,Labor!$A$5:$A$304,A10)+SUMIFS(Crochet!$AE$5:$AE$84,Crochet!$A$5:$A$84,A10)+SUMIFS(Jewelry!$AG$5:$AG$84,Jewelry!$A$5:$A$84,A10)+SUMIFS(Candles!$AG$5:$AG$84,Candles!$A$5:$A$84,A10)+SUMIFS(Clothing!$AC$5:$AC$84,Clothing!$A$5:$A$84,A10)+SUMIFS(Woodworking!$AD$5:$AD$84,Woodworking!$A$5:$A$84,A10)+SUMIFS(Digital!$Y$5:$Y$84,Digital!$A$5:$A$84,A10),1)) -> 0 | W10: =IF(B10="","",IFERROR(INDEX(DiffTimeFactors,MATCH(G10,DiffNames,0)),1)) -> 0 | X10: =IF(B10="","",ROUND(V10*W10,1)) -> 0 | Y10: =IF(B10="","",ROUND(X10/60,3)) -> 0 | Z10: =IF(B10="","",ROUND(U10*W10,2)) -> 0 | AA10: =IF(B10="","",ROUND(SUMIFS(Labor!$Q$5:$Q$304,Labor!$A$5:$A$304,A10)+SUMIFS(Crochet!$AH$5:$AH$84,Crochet!$A$5:$A$84,A10)+SUMIFS(Jewelry!$AJ$5:$AJ$84,Jewelry!$A$5:$A$84,A10)+SUMIFS(Candles!$AJ$5:$AJ$84,Candles!$A$5:$A$84,A10)+SUMIFS(Clothing!$AF$5:$AF$84,Clothing!$A$5:$A$84,A10)+SUMIFS(Woodworking!$AH$5:$AH$84,Woodworking!$A$5:$A$84,A10)+SUMIFS(Digital!$AA$5:$AA$84,Digital!$A$5:$A$84,A10),2)) -> 0 | AB10: =IF(B10="","",ROUND(IF(I10="Budget",PackBudget,IF(I10="Standard",PackStandard,IF(I10="Gift",PackGift,IF(I10="Premium",PackPremium,DefaultPackaging)))),2)) -> 0 | AC10: =IF(B10="","",IF(I10="Budget",PackWeightBudget,IF(I10="Standard",PackWeightStandard,IF(I10="Gift",PackWeightGift,IF(I10="Premium",PackWeightPremium,0))))) -> 0 | AD10: =IF(B10="","",IFERROR(INDEX(Shipping!$M$5:$M$64,MATCH(J10,Shipping!$L$5:$L$64,0)),DefaultShipping)) -> 0 | AE10: =IF(B10="","",IFERROR(INDEX(Shipping!$F$5:$F$64,MATCH(J10,Shipping!$L$5:$L$64,0)),0)) -> 0 | AF10: =IF(B10="","",IFERROR(INDEX(Shipping!$C$5:$C$64,MATCH(J10,Shipping!$L$5:$L$64,0)),"")) -> 0 | AG10: =IF(B10="","",ROUND(MAX(0,AD10-AE10),2)) -> 0 | AH10: =IF(B10="","",ROUND(T10+Z10+AA10+AB10+AG10,2)) -> 0 | AI10: =IF(B10="","",IFERROR(INDEX(Channels!$S$5:$S$18,MATCH(IF(H10="",DefaultChannel,H10),Channels!$A$5:$A$18,0)),0)) -> 0 | AJ10: =IF(B10="","",IFERROR(INDEX(Channels!$O$5:$O$18,MATCH(IF(H10="",DefaultChannel,H10),Channels!$A$5:$A$18,0)),"No")) -> 0 | AK10: =IF(B10="","",ROUND(IFERROR(INDEX(Channels!$T$5:$T$18,MATCH(IF(H10="",DefaultChannel,H10),Channels!$A$5:$A$18,0)),0)+IF(AJ10="Yes",AE10*AI10,0),4)) -> 0 | AL10: =IF(B10="","",IF(OverheadMethod="Share of revenue",IF(RevenueTargetMonth<=0,0,OverheadMonthly/RevenueTargetMonth),0)) -> 0 | AM10: =IF(B10="","",IF(OverheadMethod="Per hour worked",ROUND(OverheadPerHour*Y10,2),IF(OR(OverheadMethod="Per unit made",OverheadMethod="Per order"),OverheadPerUnit,0))) -> 0 | AN10: =IF(B10="","",IF(N10<>"",N10,TargetRetailMargin)) -> 0 | AO10: =IF(B10="","",1-AN10-AI10-AL10) -> 0 | AP10: =IF(B10="","",IF(AO10<=0,"",(AH10+AM10+AK10)/AO10)) -> 0 | AQ10: =IF(B10="","",IF(AP10="","Check the settings",ROUND(IF(RoundingRule="None",AP10,IF(RoundingRule="Nearest 0.99",MAX(0.99,CEILING(AP10,1)-0.01),IF(RoundingRule="Nearest 0.95",MAX(0.95,CEILING(AP10,1)-0.05),IF(RoundingRule="Nearest 0.50",CEILING(AP10,0.5),IF(RoundingRule="Nearest 1",CEILING(AP10,1),IF(RoundingRule="Nearest 5",CEILING(AP10,5),IF(RoundingRule="Up to whole 1",CEILING(AP10,1),IF(RoundingRule="Up to whole 5",CEILING(AP10,5),ROUND(AP10,2))))))))),2))) -> 0 | AR10: =IF(B10="","",IF(M10<>"",M10,IF(ISNUMBER(AQ10),AQ10,""))) -> 0 | AS10: =IF(B10="","",IF(AR10="","",ROUND(AM10+AR10*AL10,2))) -> 0 | AT10: =IF(B10="","",IF(AR10="","",ROUND(AH10+AS10,2))) -> 0 | AU10: =IF(B10="","",IF(AR10="","",ROUND(AR10*AI10+AK10,2))) -> 0 | AV10: =IF(B10="","",IF(AR10="","",ROUND(AR10-AT10-AU10,2))) -> 0 | AW10: =IF(B10="","",IF(OR(AR10="",AR10=0),"",AV10/AR10)) -> 0 | AX10: =IF(B10="","",IF(OR(AT10="",AT10=0),"",AV10/AT10)) -> 0 | AY10: =IF(B10="","",IF(OR(Y10="",Y10=0,AV10=""),"",ROUND(AV10/Y10,2))) -> 0 | AZ10: =IF(B10="","",IF(OR(Y10="",Y10=0,AV10=""),"",ROUND((AV10+Z10)/Y10,2))) -> 0 | BA10: =IF(B10="","",IF(1-AI10-AL10<=0,"",ROUND((AH10+AM10+AK10)/(1-AI10-AL10),2))) -> 0 | BB10: =IF(B10="","",IF(AT10="","",ROUND(AT10*2,2))) -> 0 | BC10: =IF(B10="","",IF(AR10="","",ROUND(AR10*(1-WholesaleDiscount),2))) -> 0 | BD10: =IF(B10="","",IF(BC10="","",ROUND(BC10-AH10-AM10,2))) -> 0 | BE10: =IF(B10="","",IF(OR(BC10="",BC10=0),"",BD10/BC10)) -> 0 | BF10: =IF(B10="","",IFERROR(ROUND(AVERAGEIFS(Competitors!$F$5:$F$154,Competitors!$A$5:$A$154,A10),2),"")) -> 0 | BG10: =IF(B10="","",IF(OR(BF10="",BF10=0,AR10=""),"",AR10/BF10-1)) -> 0 | BH10: =IF(B10="","",SUMIFS(Sales!$D$5:$D$804,Sales!$C$5:$C$804,A10)) -> 0 | BI10: =IF(B10="","",ROUND(SUMIFS(Sales!$V$5:$V$804,Sales!$C$5:$C$804,A10),2)) -> 0 | BJ10: =IF(B10="","",ROUND(SUMIFS(Sales!$AG$5:$AG$804,Sales!$C$5:$C$804,A10),2)) -> 0 | BK10: =IF(B10="","",IF(OR(BI10="",BI10=0),"",BJ10/BI10)) -> 0 | BL10: =IF(B10="","",IF(SUMPRODUCT(MAX((Sales!$C$5:$C$804=A10)*Sales!$B$5:$B$804))=0,"",SUMPRODUCT(MAX((Sales!$C$5:$C$804=A10)*Sales!$B$5:$B$804)))) -> 0 | BM10: =IF(B10="","",IF(SUMPRODUCT(MAX(('Price History'!$B$5:$B$304=A10)*'Price History'!$A$5:$A$304))=0,IF(P10="","",P10),SUMPRODUCT(MAX(('Price History'!$B$5:$B$304=A10)*'Price History'!$A$5:$A$304)))) -> 0 | BN10: =IF(B10="","",IF(BM10="","",TodayDate-BM10)) -> 0 | BO10: =IF(B10="","",COUNTIFS($AV$5:$AV$304,">"&AV10)+COUNTIFS($AV$5:AV10,AV10)) -> 0 | BP10: =IF(B10="","",COUNTIFS($AW$5:$AW$304,">"&AW10)+COUNTIFS($AW$5:AW10,AW10)) -> 0 | BQ10: =IF(B10="","",COUNTIFS($BI$5:$BI$304,">"&BI10)+COUNTIFS($BI$5:BI10,BI10)) -> 0 | BR10: =IF(B10="","",COUNTIFS($AY$5:$AY$304,">"&AY10)+COUNTIFS($AY$5:AY10,AY10)) -> 0 | BS10: =IF(B10="","",IF(AH10=0,"Add - no costs entered yet",IF(AR10="","Check - no price yet",IF(AV10<0,"Loss - every sale costs you money",IF(AND(AZ10<>"",AZ10<MinimumWage),"Below - pays under minimum wage",IF(AW10<MarginWarning,"Low margin - re-price it",IF(AND(AF10<>"",K10<>"",K10+AC10>AF10),"Check - too heavy for that postage band",IF(AND(BN10<>"",BN10>PriceReviewDays),"Due - price has not been reviewed",IF(AND(BG10<>"",BG10>0.5),"Check - well above the market","OK")))))))) ) -> 0
A11: =IF(B11="","",ProductPrefix&TEXT(ROW()-4,"0000")) -> 0 | B11: Lavender tin candle 120 ml | D11: Candles & home fragrance | E11: Active | F11: All year | G11: Very simple | H11: Etsy | I11: Budget | J11: First class - Domestic to 500g | K11: 260 | L11: 31 | M11: 19 | O11: 46312 | P11: 46057 | S11: =IF(B11="","",IF(C11<>"",C11,UPPER(LEFT(IF(D11="","GEN",D11),3))&"-"&TEXT(ROW()-4,"000"))) -> 0 | T11: =IF(B11="","",ROUND(SUMIFS('Material Usage'!$M$5:$M$904,'Material Usage'!$A$5:$A$904,A11)+SUMIFS(Crochet!$AD$5:$AD$84,Crochet!$A$5:$A$84,A11)+SUMIFS(Jewelry!$AF$5:$AF$84,Jewelry!$A$5:$A$84,A11)+SUMIFS(Candles!$AF$5:$AF$84,Candles!$A$5:$A$84,A11)+SUMIFS(Clothing!$AB$5:$AB$84,Clothing!$A$5:$A$84,A11)+SUMIFS(Woodworking!$AC$5:$AC$84,Woodworking!$A$5:$A$84,A11)+SUMIFS(Digital!$X$5:$X$84,Digital!$A$5:$A$84,A11),2)) -> 0 | U11: =IF(B11="","",ROUND(SUMIFS(Labor!$O$5:$O$304,Labor!$A$5:$A$304,A11)+SUMIFS(Crochet!$AG$5:$AG$84,Crochet!$A$5:$A$84,A11)+SUMIFS(Jewelry!$AI$5:$AI$84,Jewelry!$A$5:$A$84,A11)+SUMIFS(Candles!$AI$5:$AI$84,Candles!$A$5:$A$84,A11)+SUMIFS(Clothing!$AE$5:$AE$84,Clothing!$A$5:$A$84,A11)+SUMIFS(Woodworking!$AF$5:$AF$84,Woodworking!$A$5:$A$84,A11)+SUMIFS(Digital!$Z$5:$Z$84,Digital!$A$5:$A$84,A11),2)) -> 0 | V11: =IF(B11="","",ROUND(SUMIFS(Labor!$P$5:$P$304,Labor!$A$5:$A$304,A11)+SUMIFS(Crochet!$AE$5:$AE$84,Crochet!$A$5:$A$84,A11)+SUMIFS(Jewelry!$AG$5:$AG$84,Jewelry!$A$5:$A$84,A11)+SUMIFS(Candles!$AG$5:$AG$84,Candles!$A$5:$A$84,A11)+SUMIFS(Clothing!$AC$5:$AC$84,Clothing!$A$5:$A$84,A11)+SUMIFS(Woodworking!$AD$5:$AD$84,Woodworking!$A$5:$A$84,A11)+SUMIFS(Digital!$Y$5:$Y$84,Digital!$A$5:$A$84,A11),1)) -> 0 | W11: =IF(B11="","",IFERROR(INDEX(DiffTimeFactors,MATCH(G11,DiffNames,0)),1)) -> 0 | X11: =IF(B11="","",ROUND(V11*W11,1)) -> 0 | Y11: =IF(B11="","",ROUND(X11/60,3)) -> 0 | Z11: =IF(B11="","",ROUND(U11*W11,2)) -> 0 | AA11: =IF(B11="","",ROUND(SUMIFS(Labor!$Q$5:$Q$304,Labor!$A$5:$A$304,A11)+SUMIFS(Crochet!$AH$5:$AH$84,Crochet!$A$5:$A$84,A11)+SUMIFS(Jewelry!$AJ$5:$AJ$84,Jewelry!$A$5:$A$84,A11)+SUMIFS(Candles!$AJ$5:$AJ$84,Candles!$A$5:$A$84,A11)+SUMIFS(Clothing!$AF$5:$AF$84,Clothing!$A$5:$A$84,A11)+SUMIFS(Woodworking!$AH$5:$AH$84,Woodworking!$A$5:$A$84,A11)+SUMIFS(Digital!$AA$5:$AA$84,Digital!$A$5:$A$84,A11),2)) -> 0 | AB11: =IF(B11="","",ROUND(IF(I11="Budget",PackBudget,IF(I11="Standard",PackStandard,IF(I11="Gift",PackGift,IF(I11="Premium",PackPremium,DefaultPackaging)))),2)) -> 0 | AC11: =IF(B11="","",IF(I11="Budget",PackWeightBudget,IF(I11="Standard",PackWeightStandard,IF(I11="Gift",PackWeightGift,IF(I11="Premium",PackWeightPremium,0))))) -> 0 | AD11: =IF(B11="","",IFERROR(INDEX(Shipping!$M$5:$M$64,MATCH(J11,Shipping!$L$5:$L$64,0)),DefaultShipping)) -> 0 | AE11: =IF(B11="","",IFERROR(INDEX(Shipping!$F$5:$F$64,MATCH(J11,Shipping!$L$5:$L$64,0)),0)) -> 0 | AF11: =IF(B11="","",IFERROR(INDEX(Shipping!$C$5:$C$64,MATCH(J11,Shipping!$L$5:$L$64,0)),"")) -> 0 | AG11: =IF(B11="","",ROUND(MAX(0,AD11-AE11),2)) -> 0 | AH11: =IF(B11="","",ROUND(T11+Z11+AA11+AB11+AG11,2)) -> 0 | AI11: =IF(B11="","",IFERROR(INDEX(Channels!$S$5:$S$18,MATCH(IF(H11="",DefaultChannel,H11),Channels!$A$5:$A$18,0)),0)) -> 0 | AJ11: =IF(B11="","",IFERROR(INDEX(Channels!$O$5:$O$18,MATCH(IF(H11="",DefaultChannel,H11),Channels!$A$5:$A$18,0)),"No")) -> 0 | AK11: =IF(B11="","",ROUND(IFERROR(INDEX(Channels!$T$5:$T$18,MATCH(IF(H11="",DefaultChannel,H11),Channels!$A$5:$A$18,0)),0)+IF(AJ11="Yes",AE11*AI11,0),4)) -> 0 | AL11: =IF(B11="","",IF(OverheadMethod="Share of revenue",IF(RevenueTargetMonth<=0,0,OverheadMonthly/RevenueTargetMonth),0)) -> 0 | AM11: =IF(B11="","",IF(OverheadMethod="Per hour worked",ROUND(OverheadPerHour*Y11,2),IF(OR(OverheadMethod="Per unit made",OverheadMethod="Per order"),OverheadPerUnit,0))) -> 0 | AN11: =IF(B11="","",IF(N11<>"",N11,TargetRetailMargin)) -> 0 | AO11: =IF(B11="","",1-AN11-AI11-AL11) -> 0 | AP11: =IF(B11="","",IF(AO11<=0,"",(AH11+AM11+AK11)/AO11)) -> 0 | AQ11: =IF(B11="","",IF(AP11="","Check the settings",ROUND(IF(RoundingRule="None",AP11,IF(RoundingRule="Nearest 0.99",MAX(0.99,CEILING(AP11,1)-0.01),IF(RoundingRule="Nearest 0.95",MAX(0.95,CEILING(AP11,1)-0.05),IF(RoundingRule="Nearest 0.50",CEILING(AP11,0.5),IF(RoundingRule="Nearest 1",CEILING(AP11,1),IF(RoundingRule="Nearest 5",CEILING(AP11,5),IF(RoundingRule="Up to whole 1",CEILING(AP11,1),IF(RoundingRule="Up to whole 5",CEILING(AP11,5),ROUND(AP11,2))))))))),2))) -> 0 | AR11: =IF(B11="","",IF(M11<>"",M11,IF(ISNUMBER(AQ11),AQ11,""))) -> 0 | AS11: =IF(B11="","",IF(AR11="","",ROUND(AM11+AR11*AL11,2))) -> 0 | AT11: =IF(B11="","",IF(AR11="","",ROUND(AH11+AS11,2))) -> 0 | AU11: =IF(B11="","",IF(AR11="","",ROUND(AR11*AI11+AK11,2))) -> 0 | AV11: =IF(B11="","",IF(AR11="","",ROUND(AR11-AT11-AU11,2))) -> 0 | AW11: =IF(B11="","",IF(OR(AR11="",AR11=0),"",AV11/AR11)) -> 0 | AX11: =IF(B11="","",IF(OR(AT11="",AT11=0),"",AV11/AT11)) -> 0 | AY11: =IF(B11="","",IF(OR(Y11="",Y11=0,AV11=""),"",ROUND(AV11/Y11,2))) -> 0 | AZ11: =IF(B11="","",IF(OR(Y11="",Y11=0,AV11=""),"",ROUND((AV11+Z11)/Y11,2))) -> 0 | BA11: =IF(B11="","",IF(1-AI11-AL11<=0,"",ROUND((AH11+AM11+AK11)/(1-AI11-AL11),2))) -> 0 | BB11: =IF(B11="","",IF(AT11="","",ROUND(AT11*2,2))) -> 0 | BC11: =IF(B11="","",IF(AR11="","",ROUND(AR11*(1-WholesaleDiscount),2))) -> 0 | BD11: =IF(B11="","",IF(BC11="","",ROUND(BC11-AH11-AM11,2))) -> 0 | BE11: =IF(B11="","",IF(OR(BC11="",BC11=0),"",BD11/BC11)) -> 0 | BF11: =IF(B11="","",IFERROR(ROUND(AVERAGEIFS(Competitors!$F$5:$F$154,Competitors!$A$5:$A$154,A11),2),"")) -> 0 | BG11: =IF(B11="","",IF(OR(BF11="",BF11=0,AR11=""),"",AR11/BF11-1)) -> 0 | BH11: =IF(B11="","",SUMIFS(Sales!$D$5:$D$804,Sales!$C$5:$C$804,A11)) -> 0 | BI11: =IF(B11="","",ROUND(SUMIFS(Sales!$V$5:$V$804,Sales!$C$5:$C$804,A11),2)) -> 0 | BJ11: =IF(B11="","",ROUND(SUMIFS(Sales!$AG$5:$AG$804,Sales!$C$5:$C$804,A11),2)) -> 0 | BK11: =IF(B11="","",IF(OR(BI11="",BI11=0),"",BJ11/BI11)) -> 0 | BL11: =IF(B11="","",IF(SUMPRODUCT(MAX((Sales!$C$5:$C$804=A11)*Sales!$B$5:$B$804))=0,"",SUMPRODUCT(MAX((Sales!$C$5:$C$804=A11)*Sales!$B$5:$B$804)))) -> 0 | BM11: =IF(B11="","",IF(SUMPRODUCT(MAX(('Price History'!$B$5:$B$304=A11)*'Price History'!$A$5:$A$304))=0,IF(P11="","",P11),SUMPRODUCT(MAX(('Price History'!$B$5:$B$304=A11)*'Price History'!$A$5:$A$304)))) -> 0 | BN11: =IF(B11="","",IF(BM11="","",TodayDate-BM11)) -> 0 | BO11: =IF(B11="","",COUNTIFS($AV$5:$AV$304,">"&AV11)+COUNTIFS($AV$5:AV11,AV11)) -> 0 | BP11: =IF(B11="","",COUNTIFS($AW$5:$AW$304,">"&AW11)+COUNTIFS($AW$5:AW11,AW11)) -> 0 | BQ11: =IF(B11="","",COUNTIFS($BI$5:$BI$304,">"&BI11)+COUNTIFS($BI$5:BI11,BI11)) -> 0 | BR11: =IF(B11="","",COUNTIFS($AY$5:$AY$304,">"&AY11)+COUNTIFS($AY$5:AY11,AY11)) -> 0 | BS11: =IF(B11="","",IF(AH11=0,"Add - no costs entered yet",IF(AR11="","Check - no price yet",IF(AV11<0,"Loss - every sale costs you money",IF(AND(AZ11<>"",AZ11<MinimumWage),"Below - pays under minimum wage",IF(AW11<MarginWarning,"Low margin - re-price it",IF(AND(AF11<>"",K11<>"",K11+AC11>AF11),"Check - too heavy for that postage band",IF(AND(BN11<>"",BN11>PriceReviewDays),"Due - price has not been reviewed",IF(AND(BG11<>"",BG11>0.5),"Check - well above the market","OK")))))))) ) -> 0
A12: =IF(B12="","",ProductPrefix&TEXT(ROW()-4,"0000")) -> 0 | B12: Linen crossbody bag | D12: Bags & leather | E12: Active | F12: All year | G12: Complex | H12: Etsy | I12: Standard | J12: Priority - Domestic to 1,000g | K12: 380 | L12: 3 | M12: 195 | O12: 46287 | P12: 46137 | S12: =IF(B12="","",IF(C12<>"",C12,UPPER(LEFT(IF(D12="","GEN",D12),3))&"-"&TEXT(ROW()-4,"000"))) -> 0 | T12: =IF(B12="","",ROUND(SUMIFS('Material Usage'!$M$5:$M$904,'Material Usage'!$A$5:$A$904,A12)+SUMIFS(Crochet!$AD$5:$AD$84,Crochet!$A$5:$A$84,A12)+SUMIFS(Jewelry!$AF$5:$AF$84,Jewelry!$A$5:$A$84,A12)+SUMIFS(Candles!$AF$5:$AF$84,Candles!$A$5:$A$84,A12)+SUMIFS(Clothing!$AB$5:$AB$84,Clothing!$A$5:$A$84,A12)+SUMIFS(Woodworking!$AC$5:$AC$84,Woodworking!$A$5:$A$84,A12)+SUMIFS(Digital!$X$5:$X$84,Digital!$A$5:$A$84,A12),2)) -> 0 | U12: =IF(B12="","",ROUND(SUMIFS(Labor!$O$5:$O$304,Labor!$A$5:$A$304,A12)+SUMIFS(Crochet!$AG$5:$AG$84,Crochet!$A$5:$A$84,A12)+SUMIFS(Jewelry!$AI$5:$AI$84,Jewelry!$A$5:$A$84,A12)+SUMIFS(Candles!$AI$5:$AI$84,Candles!$A$5:$A$84,A12)+SUMIFS(Clothing!$AE$5:$AE$84,Clothing!$A$5:$A$84,A12)+SUMIFS(Woodworking!$AF$5:$AF$84,Woodworking!$A$5:$A$84,A12)+SUMIFS(Digital!$Z$5:$Z$84,Digital!$A$5:$A$84,A12),2)) -> 0 | V12: =IF(B12="","",ROUND(SUMIFS(Labor!$P$5:$P$304,Labor!$A$5:$A$304,A12)+SUMIFS(Crochet!$AE$5:$AE$84,Crochet!$A$5:$A$84,A12)+SUMIFS(Jewelry!$AG$5:$AG$84,Jewelry!$A$5:$A$84,A12)+SUMIFS(Candles!$AG$5:$AG$84,Candles!$A$5:$A$84,A12)+SUMIFS(Clothing!$AC$5:$AC$84,Clothing!$A$5:$A$84,A12)+SUMIFS(Woodworking!$AD$5:$AD$84,Woodworking!$A$5:$A$84,A12)+SUMIFS(Digital!$Y$5:$Y$84,Digital!$A$5:$A$84,A12),1)) -> 0 | W12: =IF(B12="","",IFERROR(INDEX(DiffTimeFactors,MATCH(G12,DiffNames,0)),1)) -> 0 | X12: =IF(B12="","",ROUND(V12*W12,1)) -> 0 | Y12: =IF(B12="","",ROUND(X12/60,3)) -> 0 | Z12: =IF(B12="","",ROUND(U12*W12,2)) -> 0 | AA12: =IF(B12="","",ROUND(SUMIFS(Labor!$Q$5:$Q$304,Labor!$A$5:$A$304,A12)+SUMIFS(Crochet!$AH$5:$AH$84,Crochet!$A$5:$A$84,A12)+SUMIFS(Jewelry!$AJ$5:$AJ$84,Jewelry!$A$5:$A$84,A12)+SUMIFS(Candles!$AJ$5:$AJ$84,Candles!$A$5:$A$84,A12)+SUMIFS(Clothing!$AF$5:$AF$84,Clothing!$A$5:$A$84,A12)+SUMIFS(Woodworking!$AH$5:$AH$84,Woodworking!$A$5:$A$84,A12)+SUMIFS(Digital!$AA$5:$AA$84,Digital!$A$5:$A$84,A12),2)) -> 0 | AB12: =IF(B12="","",ROUND(IF(I12="Budget",PackBudget,IF(I12="Standard",PackStandard,IF(I12="Gift",PackGift,IF(I12="Premium",PackPremium,DefaultPackaging)))),2)) -> 0 | AC12: =IF(B12="","",IF(I12="Budget",PackWeightBudget,IF(I12="Standard",PackWeightStandard,IF(I12="Gift",PackWeightGift,IF(I12="Premium",PackWeightPremium,0))))) -> 0 | AD12: =IF(B12="","",IFERROR(INDEX(Shipping!$M$5:$M$64,MATCH(J12,Shipping!$L$5:$L$64,0)),DefaultShipping)) -> 0 | AE12: =IF(B12="","",IFERROR(INDEX(Shipping!$F$5:$F$64,MATCH(J12,Shipping!$L$5:$L$64,0)),0)) -> 0 | AF12: =IF(B12="","",IFERROR(INDEX(Shipping!$C$5:$C$64,MATCH(J12,Shipping!$L$5:$L$64,0)),"")) -> 0 | AG12: =IF(B12="","",ROUND(MAX(0,AD12-AE12),2)) -> 0 | AH12: =IF(B12="","",ROUND(T12+Z12+AA12+AB12+AG12,2)) -> 0 | AI12: =IF(B12="","",IFERROR(INDEX(Channels!$S$5:$S$18,MATCH(IF(H12="",DefaultChannel,H12),Channels!$A$5:$A$18,0)),0)) -> 0 | AJ12: =IF(B12="","",IFERROR(INDEX(Channels!$O$5:$O$18,MATCH(IF(H12="",DefaultChannel,H12),Channels!$A$5:$A$18,0)),"No")) -> 0 | AK12: =IF(B12="","",ROUND(IFERROR(INDEX(Channels!$T$5:$T$18,MATCH(IF(H12="",DefaultChannel,H12),Channels!$A$5:$A$18,0)),0)+IF(AJ12="Yes",AE12*AI12,0),4)) -> 0 | AL12: =IF(B12="","",IF(OverheadMethod="Share of revenue",IF(RevenueTargetMonth<=0,0,OverheadMonthly/RevenueTargetMonth),0)) -> 0 | AM12: =IF(B12="","",IF(OverheadMethod="Per hour worked",ROUND(OverheadPerHour*Y12,2),IF(OR(OverheadMethod="Per unit made",OverheadMethod="Per order"),OverheadPerUnit,0))) -> 0 | AN12: =IF(B12="","",IF(N12<>"",N12,TargetRetailMargin)) -> 0 | AO12: =IF(B12="","",1-AN12-AI12-AL12) -> 0 | AP12: =IF(B12="","",IF(AO12<=0,"",(AH12+AM12+AK12)/AO12)) -> 0 | AQ12: =IF(B12="","",IF(AP12="","Check the settings",ROUND(IF(RoundingRule="None",AP12,IF(RoundingRule="Nearest 0.99",MAX(0.99,CEILING(AP12,1)-0.01),IF(RoundingRule="Nearest 0.95",MAX(0.95,CEILING(AP12,1)-0.05),IF(RoundingRule="Nearest 0.50",CEILING(AP12,0.5),IF(RoundingRule="Nearest 1",CEILING(AP12,1),IF(RoundingRule="Nearest 5",CEILING(AP12,5),IF(RoundingRule="Up to whole 1",CEILING(AP12,1),IF(RoundingRule="Up to whole 5",CEILING(AP12,5),ROUND(AP12,2))))))))),2))) -> 0 | AR12: =IF(B12="","",IF(M12<>"",M12,IF(ISNUMBER(AQ12),AQ12,""))) -> 0 | AS12: =IF(B12="","",IF(AR12="","",ROUND(AM12+AR12*AL12,2))) -> 0 | AT12: =IF(B12="","",IF(AR12="","",ROUND(AH12+AS12,2))) -> 0 | AU12: =IF(B12="","",IF(AR12="","",ROUND(AR12*AI12+AK12,2))) -> 0 | AV12: =IF(B12="","",IF(AR12="","",ROUND(AR12-AT12-AU12,2))) -> 0 | AW12: =IF(B12="","",IF(OR(AR12="",AR12=0),"",AV12/AR12)) -> 0 | AX12: =IF(B12="","",IF(OR(AT12="",AT12=0),"",AV12/AT12)) -> 0 | AY12: =IF(B12="","",IF(OR(Y12="",Y12=0,AV12=""),"",ROUND(AV12/Y12,2))) -> 0 | AZ12: =IF(B12="","",IF(OR(Y12="",Y12=0,AV12=""),"",ROUND((AV12+Z12)/Y12,2))) -> 0 | BA12: =IF(B12="","",IF(1-AI12-AL12<=0,"",ROUND((AH12+AM12+AK12)/(1-AI12-AL12),2))) -> 0 | BB12: =IF(B12="","",IF(AT12="","",ROUND(AT12*2,2))) -> 0 | BC12: =IF(B12="","",IF(AR12="","",ROUND(AR12*(1-WholesaleDiscount),2))) -> 0 | BD12: =IF(B12="","",IF(BC12="","",ROUND(BC12-AH12-AM12,2))) -> 0 | BE12: =IF(B12="","",IF(OR(BC12="",BC12=0),"",BD12/BC12)) -> 0 | BF12: =IF(B12="","",IFERROR(ROUND(AVERAGEIFS(Competitors!$F$5:$F$154,Competitors!$A$5:$A$154,A12),2),"")) -> 0 | BG12: =IF(B12="","",IF(OR(BF12="",BF12=0,AR12=""),"",AR12/BF12-1)) -> 0 | BH12: =IF(B12="","",SUMIFS(Sales!$D$5:$D$804,Sales!$C$5:$C$804,A12)) -> 0 | BI12: =IF(B12="","",ROUND(SUMIFS(Sales!$V$5:$V$804,Sales!$C$5:$C$804,A12),2)) -> 0 | BJ12: =IF(B12="","",ROUND(SUMIFS(Sales!$AG$5:$AG$804,Sales!$C$5:$C$804,A12),2)) -> 0 | BK12: =IF(B12="","",IF(OR(BI12="",BI12=0),"",BJ12/BI12)) -> 0 | BL12: =IF(B12="","",IF(SUMPRODUCT(MAX((Sales!$C$5:$C$804=A12)*Sales!$B$5:$B$804))=0,"",SUMPRODUCT(MAX((Sales!$C$5:$C$804=A12)*Sales!$B$5:$B$804)))) -> 0 | BM12: =IF(B12="","",IF(SUMPRODUCT(MAX(('Price History'!$B$5:$B$304=A12)*'Price History'!$A$5:$A$304))=0,IF(P12="","",P12),SUMPRODUCT(MAX(('Price History'!$B$5:$B$304=A12)*'Price History'!$A$5:$A$304)))) -> 0 | BN12: =IF(B12="","",IF(BM12="","",TodayDate-BM12)) -> 0 | BO12: =IF(B12="","",COUNTIFS($AV$5:$AV$304,">"&AV12)+COUNTIFS($AV$5:AV12,AV12)) -> 0 | BP12: =IF(B12="","",COUNTIFS($AW$5:$AW$304,">"&AW12)+COUNTIFS($AW$5:AW12,AW12)) -> 0 | BQ12: =IF(B12="","",COUNTIFS($BI$5:$BI$304,">"&BI12)+COUNTIFS($BI$5:BI12,BI12)) -> 0 | BR12: =IF(B12="","",COUNTIFS($AY$5:$AY$304,">"&AY12)+COUNTIFS($AY$5:AY12,AY12)) -> 0 | BS12: =IF(B12="","",IF(AH12=0,"Add - no costs entered yet",IF(AR12="","Check - no price yet",IF(AV12<0,"Loss - every sale costs you money",IF(AND(AZ12<>"",AZ12<MinimumWage),"Below - pays under minimum wage",IF(AW12<MarginWarning,"Low margin - re-price it",IF(AND(AF12<>"",K12<>"",K12+AC12>AF12),"Check - too heavy for that postage band",IF(AND(BN12<>"",BN12>PriceReviewDays),"Due - price has not been reviewed",IF(AND(BG12<>"",BG12>0.5),"Check - well above the market","OK")))))))) ) -> 0
A13: =IF(B13="","",ProductPrefix&TEXT(ROW()-4,"0000")) -> 0 | B13: Linen pinafore apron | D13: Clothing & accessories | E13: Active | F13: All year | G13: Moderate | H13: Own website | I13: Standard | J13: Priority - Domestic to 1,000g | K13: 420 | L13: 5 | M13: 148 | O13: 46277 | P13: 46107 | S13: =IF(B13="","",IF(C13<>"",C13,UPPER(LEFT(IF(D13="","GEN",D13),3))&"-"&TEXT(ROW()-4,"000"))) -> 0 | T13: =IF(B13="","",ROUND(SUMIFS('Material Usage'!$M$5:$M$904,'Material Usage'!$A$5:$A$904,A13)+SUMIFS(Crochet!$AD$5:$AD$84,Crochet!$A$5:$A$84,A13)+SUMIFS(Jewelry!$AF$5:$AF$84,Jewelry!$A$5:$A$84,A13)+SUMIFS(Candles!$AF$5:$AF$84,Candles!$A$5:$A$84,A13)+SUMIFS(Clothing!$AB$5:$AB$84,Clothing!$A$5:$A$84,A13)+SUMIFS(Woodworking!$AC$5:$AC$84,Woodworking!$A$5:$A$84,A13)+SUMIFS(Digital!$X$5:$X$84,Digital!$A$5:$A$84,A13),2)) -> 0 | U13: =IF(B13="","",ROUND(SUMIFS(Labor!$O$5:$O$304,Labor!$A$5:$A$304,A13)+SUMIFS(Crochet!$AG$5:$AG$84,Crochet!$A$5:$A$84,A13)+SUMIFS(Jewelry!$AI$5:$AI$84,Jewelry!$A$5:$A$84,A13)+SUMIFS(Candles!$AI$5:$AI$84,Candles!$A$5:$A$84,A13)+SUMIFS(Clothing!$AE$5:$AE$84,Clothing!$A$5:$A$84,A13)+SUMIFS(Woodworking!$AF$5:$AF$84,Woodworking!$A$5:$A$84,A13)+SUMIFS(Digital!$Z$5:$Z$84,Digital!$A$5:$A$84,A13),2)) -> 0 | V13: =IF(B13="","",ROUND(SUMIFS(Labor!$P$5:$P$304,Labor!$A$5:$A$304,A13)+SUMIFS(Crochet!$AE$5:$AE$84,Crochet!$A$5:$A$84,A13)+SUMIFS(Jewelry!$AG$5:$AG$84,Jewelry!$A$5:$A$84,A13)+SUMIFS(Candles!$AG$5:$AG$84,Candles!$A$5:$A$84,A13)+SUMIFS(Clothing!$AC$5:$AC$84,Clothing!$A$5:$A$84,A13)+SUMIFS(Woodworking!$AD$5:$AD$84,Woodworking!$A$5:$A$84,A13)+SUMIFS(Digital!$Y$5:$Y$84,Digital!$A$5:$A$84,A13),1)) -> 0 | W13: =IF(B13="","",IFERROR(INDEX(DiffTimeFactors,MATCH(G13,DiffNames,0)),1)) -> 0 | X13: =IF(B13="","",ROUND(V13*W13,1)) -> 0 | Y13: =IF(B13="","",ROUND(X13/60,3)) -> 0 | Z13: =IF(B13="","",ROUND(U13*W13,2)) -> 0 | AA13: =IF(B13="","",ROUND(SUMIFS(Labor!$Q$5:$Q$304,Labor!$A$5:$A$304,A13)+SUMIFS(Crochet!$AH$5:$AH$84,Crochet!$A$5:$A$84,A13)+SUMIFS(Jewelry!$AJ$5:$AJ$84,Jewelry!$A$5:$A$84,A13)+SUMIFS(Candles!$AJ$5:$AJ$84,Candles!$A$5:$A$84,A13)+SUMIFS(Clothing!$AF$5:$AF$84,Clothing!$A$5:$A$84,A13)+SUMIFS(Woodworking!$AH$5:$AH$84,Woodworking!$A$5:$A$84,A13)+SUMIFS(Digital!$AA$5:$AA$84,Digital!$A$5:$A$84,A13),2)) -> 0 | AB13: =IF(B13="","",ROUND(IF(I13="Budget",PackBudget,IF(I13="Standard",PackStandard,IF(I13="Gift",PackGift,IF(I13="Premium",PackPremium,DefaultPackaging)))),2)) -> 0 | AC13: =IF(B13="","",IF(I13="Budget",PackWeightBudget,IF(I13="Standard",PackWeightStandard,IF(I13="Gift",PackWeightGift,IF(I13="Premium",PackWeightPremium,0))))) -> 0 | AD13: =IF(B13="","",IFERROR(INDEX(Shipping!$M$5:$M$64,MATCH(J13,Shipping!$L$5:$L$64,0)),DefaultShipping)) -> 0 | AE13: =IF(B13="","",IFERROR(INDEX(Shipping!$F$5:$F$64,MATCH(J13,Shipping!$L$5:$L$64,0)),0)) -> 0 | AF13: =IF(B13="","",IFERROR(INDEX(Shipping!$C$5:$C$64,MATCH(J13,Shipping!$L$5:$L$64,0)),"")) -> 0 | AG13: =IF(B13="","",ROUND(MAX(0,AD13-AE13),2)) -> 0 | AH13: =IF(B13="","",ROUND(T13+Z13+AA13+AB13+AG13,2)) -> 0 | AI13: =IF(B13="","",IFERROR(INDEX(Channels!$S$5:$S$18,MATCH(IF(H13="",DefaultChannel,H13),Channels!$A$5:$A$18,0)),0)) -> 0 | AJ13: =IF(B13="","",IFERROR(INDEX(Channels!$O$5:$O$18,MATCH(IF(H13="",DefaultChannel,H13),Channels!$A$5:$A$18,0)),"No")) -> 0 | AK13: =IF(B13="","",ROUND(IFERROR(INDEX(Channels!$T$5:$T$18,MATCH(IF(H13="",DefaultChannel,H13),Channels!$A$5:$A$18,0)),0)+IF(AJ13="Yes",AE13*AI13,0),4)) -> 0 | AL13: =IF(B13="","",IF(OverheadMethod="Share of revenue",IF(RevenueTargetMonth<=0,0,OverheadMonthly/RevenueTargetMonth),0)) -> 0 | AM13: =IF(B13="","",IF(OverheadMethod="Per hour worked",ROUND(OverheadPerHour*Y13,2),IF(OR(OverheadMethod="Per unit made",OverheadMethod="Per order"),OverheadPerUnit,0))) -> 0 | AN13: =IF(B13="","",IF(N13<>"",N13,TargetRetailMargin)) -> 0 | AO13: =IF(B13="","",1-AN13-AI13-AL13) -> 0 | AP13: =IF(B13="","",IF(AO13<=0,"",(AH13+AM13+AK13)/AO13)) -> 0 | AQ13: =IF(B13="","",IF(AP13="","Check the settings",ROUND(IF(RoundingRule="None",AP13,IF(RoundingRule="Nearest 0.99",MAX(0.99,CEILING(AP13,1)-0.01),IF(RoundingRule="Nearest 0.95",MAX(0.95,CEILING(AP13,1)-0.05),IF(RoundingRule="Nearest 0.50",CEILING(AP13,0.5),IF(RoundingRule="Nearest 1",CEILING(AP13,1),IF(RoundingRule="Nearest 5",CEILING(AP13,5),IF(RoundingRule="Up to whole 1",CEILING(AP13,1),IF(RoundingRule="Up to whole 5",CEILING(AP13,5),ROUND(AP13,2))))))))),2))) -> 0 | AR13: =IF(B13="","",IF(M13<>"",M13,IF(ISNUMBER(AQ13),AQ13,""))) -> 0 | AS13: =IF(B13="","",IF(AR13="","",ROUND(AM13+AR13*AL13,2))) -> 0 | AT13: =IF(B13="","",IF(AR13="","",ROUND(AH13+AS13,2))) -> 0 | AU13: =IF(B13="","",IF(AR13="","",ROUND(AR13*AI13+AK13,2))) -> 0 | AV13: =IF(B13="","",IF(AR13="","",ROUND(AR13-AT13-AU13,2))) -> 0 | AW13: =IF(B13="","",IF(OR(AR13="",AR13=0),"",AV13/AR13)) -> 0 | AX13: =IF(B13="","",IF(OR(AT13="",AT13=0),"",AV13/AT13)) -> 0 | AY13: =IF(B13="","",IF(OR(Y13="",Y13=0,AV13=""),"",ROUND(AV13/Y13,2))) -> 0 | AZ13: =IF(B13="","",IF(OR(Y13="",Y13=0,AV13=""),"",ROUND((AV13+Z13)/Y13,2))) -> 0 | BA13: =IF(B13="","",IF(1-AI13-AL13<=0,"",ROUND((AH13+AM13+AK13)/(1-AI13-AL13),2))) -> 0 | BB13: =IF(B13="","",IF(AT13="","",ROUND(AT13*2,2))) -> 0 | BC13: =IF(B13="","",IF(AR13="","",ROUND(AR13*(1-WholesaleDiscount),2))) -> 0 | BD13: =IF(B13="","",IF(BC13="","",ROUND(BC13-AH13-AM13,2))) -> 0 | BE13: =IF(B13="","",IF(OR(BC13="",BC13=0),"",BD13/BC13)) -> 0 | BF13: =IF(B13="","",IFERROR(ROUND(AVERAGEIFS(Competitors!$F$5:$F$154,Competitors!$A$5:$A$154,A13),2),"")) -> 0 | BG13: =IF(B13="","",IF(OR(BF13="",BF13=0,AR13=""),"",AR13/BF13-1)) -> 0 | BH13: =IF(B13="","",SUMIFS(Sales!$D$5:$D$804,Sales!$C$5:$C$804,A13)) -> 0 | BI13: =IF(B13="","",ROUND(SUMIFS(Sales!$V$5:$V$804,Sales!$C$5:$C$804,A13),2)) -> 0 | BJ13: =IF(B13="","",ROUND(SUMIFS(Sales!$AG$5:$AG$804,Sales!$C$5:$C$804,A13),2)) -> 0 | BK13: =IF(B13="","",IF(OR(BI13="",BI13=0),"",BJ13/BI13)) -> 0 | BL13: =IF(B13="","",IF(SUMPRODUCT(MAX((Sales!$C$5:$C$804=A13)*Sales!$B$5:$B$804))=0,"",SUMPRODUCT(MAX((Sales!$C$5:$C$804=A13)*Sales!$B$5:$B$804)))) -> 0 | BM13: =IF(B13="","",IF(SUMPRODUCT(MAX(('Price History'!$B$5:$B$304=A13)*'Price History'!$A$5:$A$304))=0,IF(P13="","",P13),SUMPRODUCT(MAX(('Price History'!$B$5:$B$304=A13)*'Price History'!$A$5:$A$304)))) -> 0 | BN13: =IF(B13="","",IF(BM13="","",TodayDate-BM13)) -> 0 | BO13: =IF(B13="","",COUNTIFS($AV$5:$AV$304,">"&AV13)+COUNTIFS($AV$5:AV13,AV13)) -> 0 | BP13: =IF(B13="","",COUNTIFS($AW$5:$AW$304,">"&AW13)+COUNTIFS($AW$5:AW13,AW13)) -> 0 | BQ13: =IF(B13="","",COUNTIFS($BI$5:$BI$304,">"&BI13)+COUNTIFS($BI$5:BI13,BI13)) -> 0 | BR13: =IF(B13="","",COUNTIFS($AY$5:$AY$304,">"&AY13)+COUNTIFS($AY$5:AY13,AY13)) -> 0 | BS13: =IF(B13="","",IF(AH13=0,"Add - no costs entered yet",IF(AR13="","Check - no price yet",IF(AV13<0,"Loss - every sale costs you money",IF(AND(AZ13<>"",AZ13<MinimumWage),"Below - pays under minimum wage",IF(AW13<MarginWarning,"Low margin - re-price it",IF(AND(AF13<>"",K13<>"",K13+AC13>AF13),"Check - too heavy for that postage band",IF(AND(BN13<>"",BN13>PriceReviewDays),"Due - price has not been reviewed",IF(AND(BG13<>"",BG13>0.5),"Check - well above the market","OK")))))))) ) -> 0
A14: =IF(B14="","",ProductPrefix&TEXT(ROW()-4,"0000")) -> 0 | B14: Walnut serving board | D14: Woodworking | E14: Active | F14: All year | G14: Moderate | H14: Own website | I14: Standard | J14: Courier - Domestic to 5,000g | K14: 1400 | L14: 4 | M14: 135 | O14: 46299 | P14: 45977 | S14: =IF(B14="","",IF(C14<>"",C14,UPPER(LEFT(IF(D14="","GEN",D14),3))&"-"&TEXT(ROW()-4,"000"))) -> 0 | T14: =IF(B14="","",ROUND(SUMIFS('Material Usage'!$M$5:$M$904,'Material Usage'!$A$5:$A$904,A14)+SUMIFS(Crochet!$AD$5:$AD$84,Crochet!$A$5:$A$84,A14)+SUMIFS(Jewelry!$AF$5:$AF$84,Jewelry!$A$5:$A$84,A14)+SUMIFS(Candles!$AF$5:$AF$84,Candles!$A$5:$A$84,A14)+SUMIFS(Clothing!$AB$5:$AB$84,Clothing!$A$5:$A$84,A14)+SUMIFS(Woodworking!$AC$5:$AC$84,Woodworking!$A$5:$A$84,A14)+SUMIFS(Digital!$X$5:$X$84,Digital!$A$5:$A$84,A14),2)) -> 0 | U14: =IF(B14="","",ROUND(SUMIFS(Labor!$O$5:$O$304,Labor!$A$5:$A$304,A14)+SUMIFS(Crochet!$AG$5:$AG$84,Crochet!$A$5:$A$84,A14)+SUMIFS(Jewelry!$AI$5:$AI$84,Jewelry!$A$5:$A$84,A14)+SUMIFS(Candles!$AI$5:$AI$84,Candles!$A$5:$A$84,A14)+SUMIFS(Clothing!$AE$5:$AE$84,Clothing!$A$5:$A$84,A14)+SUMIFS(Woodworking!$AF$5:$AF$84,Woodworking!$A$5:$A$84,A14)+SUMIFS(Digital!$Z$5:$Z$84,Digital!$A$5:$A$84,A14),2)) -> 0 | V14: =IF(B14="","",ROUND(SUMIFS(Labor!$P$5:$P$304,Labor!$A$5:$A$304,A14)+SUMIFS(Crochet!$AE$5:$AE$84,Crochet!$A$5:$A$84,A14)+SUMIFS(Jewelry!$AG$5:$AG$84,Jewelry!$A$5:$A$84,A14)+SUMIFS(Candles!$AG$5:$AG$84,Candles!$A$5:$A$84,A14)+SUMIFS(Clothing!$AC$5:$AC$84,Clothing!$A$5:$A$84,A14)+SUMIFS(Woodworking!$AD$5:$AD$84,Woodworking!$A$5:$A$84,A14)+SUMIFS(Digital!$Y$5:$Y$84,Digital!$A$5:$A$84,A14),1)) -> 0 | W14: =IF(B14="","",IFERROR(INDEX(DiffTimeFactors,MATCH(G14,DiffNames,0)),1)) -> 0 | X14: =IF(B14="","",ROUND(V14*W14,1)) -> 0 | Y14: =IF(B14="","",ROUND(X14/60,3)) -> 0 | Z14: =IF(B14="","",ROUND(U14*W14,2)) -> 0 | AA14: =IF(B14="","",ROUND(SUMIFS(Labor!$Q$5:$Q$304,Labor!$A$5:$A$304,A14)+SUMIFS(Crochet!$AH$5:$AH$84,Crochet!$A$5:$A$84,A14)+SUMIFS(Jewelry!$AJ$5:$AJ$84,Jewelry!$A$5:$A$84,A14)+SUMIFS(Candles!$AJ$5:$AJ$84,Candles!$A$5:$A$84,A14)+SUMIFS(Clothing!$AF$5:$AF$84,Clothing!$A$5:$A$84,A14)+SUMIFS(Woodworking!$AH$5:$AH$84,Woodworking!$A$5:$A$84,A14)+SUMIFS(Digital!$AA$5:$AA$84,Digital!$A$5:$A$84,A14),2)) -> 0 | AB14: =IF(B14="","",ROUND(IF(I14="Budget",PackBudget,IF(I14="Standard",PackStandard,IF(I14="Gift",PackGift,IF(I14="Premium",PackPremium,DefaultPackaging)))),2)) -> 0 | AC14: =IF(B14="","",IF(I14="Budget",PackWeightBudget,IF(I14="Standard",PackWeightStandard,IF(I14="Gift",PackWeightGift,IF(I14="Premium",PackWeightPremium,0))))) -> 0 | AD14: =IF(B14="","",IFERROR(INDEX(Shipping!$M$5:$M$64,MATCH(J14,Shipping!$L$5:$L$64,0)),DefaultShipping)) -> 0 | AE14: =IF(B14="","",IFERROR(INDEX(Shipping!$F$5:$F$64,MATCH(J14,Shipping!$L$5:$L$64,0)),0)) -> 0 | AF14: =IF(B14="","",IFERROR(INDEX(Shipping!$C$5:$C$64,MATCH(J14,Shipping!$L$5:$L$64,0)),"")) -> 0 | AG14: =IF(B14="","",ROUND(MAX(0,AD14-AE14),2)) -> 0 | AH14: =IF(B14="","",ROUND(T14+Z14+AA14+AB14+AG14,2)) -> 0 | AI14: =IF(B14="","",IFERROR(INDEX(Channels!$S$5:$S$18,MATCH(IF(H14="",DefaultChannel,H14),Channels!$A$5:$A$18,0)),0)) -> 0 | AJ14: =IF(B14="","",IFERROR(INDEX(Channels!$O$5:$O$18,MATCH(IF(H14="",DefaultChannel,H14),Channels!$A$5:$A$18,0)),"No")) -> 0 | AK14: =IF(B14="","",ROUND(IFERROR(INDEX(Channels!$T$5:$T$18,MATCH(IF(H14="",DefaultChannel,H14),Channels!$A$5:$A$18,0)),0)+IF(AJ14="Yes",AE14*AI14,0),4)) -> 0 | AL14: =IF(B14="","",IF(OverheadMethod="Share of revenue",IF(RevenueTargetMonth<=0,0,OverheadMonthly/RevenueTargetMonth),0)) -> 0 | AM14: =IF(B14="","",IF(OverheadMethod="Per hour worked",ROUND(OverheadPerHour*Y14,2),IF(OR(OverheadMethod="Per unit made",OverheadMethod="Per order"),OverheadPerUnit,0))) -> 0 | AN14: =IF(B14="","",IF(N14<>"",N14,TargetRetailMargin)) -> 0 | AO14: =IF(B14="","",1-AN14-AI14-AL14) -> 0 | AP14: =IF(B14="","",IF(AO14<=0,"",(AH14+AM14+AK14)/AO14)) -> 0 | AQ14: =IF(B14="","",IF(AP14="","Check the settings",ROUND(IF(RoundingRule="None",AP14,IF(RoundingRule="Nearest 0.99",MAX(0.99,CEILING(AP14,1)-0.01),IF(RoundingRule="Nearest 0.95",MAX(0.95,CEILING(AP14,1)-0.05),IF(RoundingRule="Nearest 0.50",CEILING(AP14,0.5),IF(RoundingRule="Nearest 1",CEILING(AP14,1),IF(RoundingRule="Nearest 5",CEILING(AP14,5),IF(RoundingRule="Up to whole 1",CEILING(AP14,1),IF(RoundingRule="Up to whole 5",CEILING(AP14,5),ROUND(AP14,2))))))))),2))) -> 0 | AR14: =IF(B14="","",IF(M14<>"",M14,IF(ISNUMBER(AQ14),AQ14,""))) -> 0 | AS14: =IF(B14="","",IF(AR14="","",ROUND(AM14+AR14*AL14,2))) -> 0 | AT14: =IF(B14="","",IF(AR14="","",ROUND(AH14+AS14,2))) -> 0 | AU14: =IF(B14="","",IF(AR14="","",ROUND(AR14*AI14+AK14,2))) -> 0 | AV14: =IF(B14="","",IF(AR14="","",ROUND(AR14-AT14-AU14,2))) -> 0 | AW14: =IF(B14="","",IF(OR(AR14="",AR14=0),"",AV14/AR14)) -> 0 | AX14: =IF(B14="","",IF(OR(AT14="",AT14=0),"",AV14/AT14)) -> 0 | AY14: =IF(B14="","",IF(OR(Y14="",Y14=0,AV14=""),"",ROUND(AV14/Y14,2))) -> 0 | AZ14: =IF(B14="","",IF(OR(Y14="",Y14=0,AV14=""),"",ROUND((AV14+Z14)/Y14,2))) -> 0 | BA14: =IF(B14="","",IF(1-AI14-AL14<=0,"",ROUND((AH14+AM14+AK14)/(1-AI14-AL14),2))) -> 0 | BB14: =IF(B14="","",IF(AT14="","",ROUND(AT14*2,2))) -> 0 | BC14: =IF(B14="","",IF(AR14="","",ROUND(AR14*(1-WholesaleDiscount),2))) -> 0 | BD14: =IF(B14="","",IF(BC14="","",ROUND(BC14-AH14-AM14,2))) -> 0 | BE14: =IF(B14="","",IF(OR(BC14="",BC14=0),"",BD14/BC14)) -> 0 | BF14: =IF(B14="","",IFERROR(ROUND(AVERAGEIFS(Competitors!$F$5:$F$154,Competitors!$A$5:$A$154,A14),2),"")) -> 0 | BG14: =IF(B14="","",IF(OR(BF14="",BF14=0,AR14=""),"",AR14/BF14-1)) -> 0 | BH14: =IF(B14="","",SUMIFS(Sales!$D$5:$D$804,Sales!$C$5:$C$804,A14)) -> 0 | BI14: =IF(B14="","",ROUND(SUMIFS(Sales!$V$5:$V$804,Sales!$C$5:$C$804,A14),2)) -> 0 | BJ14: =IF(B14="","",ROUND(SUMIFS(Sales!$AG$5:$AG$804,Sales!$C$5:$C$804,A14),2)) -> 0 | BK14: =IF(B14="","",IF(OR(BI14="",BI14=0),"",BJ14/BI14)) -> 0 | BL14: =IF(B14="","",IF(SUMPRODUCT(MAX((Sales!$C$5:$C$804=A14)*Sales!$B$5:$B$804))=0,"",SUMPRODUCT(MAX((Sales!$C$5:$C$804=A14)*Sales!$B$5:$B$804)))) -> 0 | BM14: =IF(B14="","",IF(SUMPRODUCT(MAX(('Price History'!$B$5:$B$304=A14)*'Price History'!$A$5:$A$304))=0,IF(P14="","",P14),SUMPRODUCT(MAX(('Price History'!$B$5:$B$304=A14)*'Price History'!$A$5:$A$304)))) -> 0 | BN14: =IF(B14="","",IF(BM14="","",TodayDate-BM14)) -> 0 | BO14: =IF(B14="","",COUNTIFS($AV$5:$AV$304,">"&AV14)+COUNTIFS($AV$5:AV14,AV14)) -> 0 | BP14: =IF(B14="","",COUNTIFS($AW$5:$AW$304,">"&AW14)+COUNTIFS($AW$5:AW14,AW14)) -> 0 | BQ14: =IF(B14="","",COUNTIFS($BI$5:$BI$304,">"&BI14)+COUNTIFS($BI$5:BI14,BI14)) -> 0 | BR14: =IF(B14="","",COUNTIFS($AY$5:$AY$304,">"&AY14)+COUNTIFS($AY$5:AY14,AY14)) -> 0 | BS14: =IF(B14="","",IF(AH14=0,"Add - no costs entered yet",IF(AR14="","Check - no price yet",IF(AV14<0,"Loss - every sale costs you money",IF(AND(AZ14<>"",AZ14<MinimumWage),"Below - pays under minimum wage",IF(AW14<MarginWarning,"Low margin - re-price it",IF(AND(AF14<>"",K14<>"",K14+AC14>AF14),"Check - too heavy for that postage band",IF(AND(BN14<>"",BN14>PriceReviewDays),"Due - price has not been reviewed",IF(AND(BG14<>"",BG14>0.5),"Check - well above the market","OK")))))))) ) -> 0
A15: =IF(B15="","",ProductPrefix&TEXT(ROW()-4,"0000")) -> 0 | B15: Oak floating shelf 60 cm | D15: Woodworking | E15: Made to order | F15: All year | G15: Simple | H15: Own website | I15: Budget | J15: Courier - Domestic to 5,000g | K15: 2100 | L15: 0 | O15: 46257 | P15: 46167 | R15: No price yet - the dashboard is right to complain about it. | S15: =IF(B15="","",IF(C15<>"",C15,UPPER(LEFT(IF(D15="","GEN",D15),3))&"-"&TEXT(ROW()-4,"000"))) -> 0 | T15: =IF(B15="","",ROUND(SUMIFS('Material Usage'!$M$5:$M$904,'Material Usage'!$A$5:$A$904,A15)+SUMIFS(Crochet!$AD$5:$AD$84,Crochet!$A$5:$A$84,A15)+SUMIFS(Jewelry!$AF$5:$AF$84,Jewelry!$A$5:$A$84,A15)+SUMIFS(Candles!$AF$5:$AF$84,Candles!$A$5:$A$84,A15)+SUMIFS(Clothing!$AB$5:$AB$84,Clothing!$A$5:$A$84,A15)+SUMIFS(Woodworking!$AC$5:$AC$84,Woodworking!$A$5:$A$84,A15)+SUMIFS(Digital!$X$5:$X$84,Digital!$A$5:$A$84,A15),2)) -> 0 | U15: =IF(B15="","",ROUND(SUMIFS(Labor!$O$5:$O$304,Labor!$A$5:$A$304,A15)+SUMIFS(Crochet!$AG$5:$AG$84,Crochet!$A$5:$A$84,A15)+SUMIFS(Jewelry!$AI$5:$AI$84,Jewelry!$A$5:$A$84,A15)+SUMIFS(Candles!$AI$5:$AI$84,Candles!$A$5:$A$84,A15)+SUMIFS(Clothing!$AE$5:$AE$84,Clothing!$A$5:$A$84,A15)+SUMIFS(Woodworking!$AF$5:$AF$84,Woodworking!$A$5:$A$84,A15)+SUMIFS(Digital!$Z$5:$Z$84,Digital!$A$5:$A$84,A15),2)) -> 0 | V15: =IF(B15="","",ROUND(SUMIFS(Labor!$P$5:$P$304,Labor!$A$5:$A$304,A15)+SUMIFS(Crochet!$AE$5:$AE$84,Crochet!$A$5:$A$84,A15)+SUMIFS(Jewelry!$AG$5:$AG$84,Jewelry!$A$5:$A$84,A15)+SUMIFS(Candles!$AG$5:$AG$84,Candles!$A$5:$A$84,A15)+SUMIFS(Clothing!$AC$5:$AC$84,Clothing!$A$5:$A$84,A15)+SUMIFS(Woodworking!$AD$5:$AD$84,Woodworking!$A$5:$A$84,A15)+SUMIFS(Digital!$Y$5:$Y$84,Digital!$A$5:$A$84,A15),1)) -> 0 | W15: =IF(B15="","",IFERROR(INDEX(DiffTimeFactors,MATCH(G15,DiffNames,0)),1)) -> 0 | X15: =IF(B15="","",ROUND(V15*W15,1)) -> 0 | Y15: =IF(B15="","",ROUND(X15/60,3)) -> 0 | Z15: =IF(B15="","",ROUND(U15*W15,2)) -> 0 | AA15: =IF(B15="","",ROUND(SUMIFS(Labor!$Q$5:$Q$304,Labor!$A$5:$A$304,A15)+SUMIFS(Crochet!$AH$5:$AH$84,Crochet!$A$5:$A$84,A15)+SUMIFS(Jewelry!$AJ$5:$AJ$84,Jewelry!$A$5:$A$84,A15)+SUMIFS(Candles!$AJ$5:$AJ$84,Candles!$A$5:$A$84,A15)+SUMIFS(Clothing!$AF$5:$AF$84,Clothing!$A$5:$A$84,A15)+SUMIFS(Woodworking!$AH$5:$AH$84,Woodworking!$A$5:$A$84,A15)+SUMIFS(Digital!$AA$5:$AA$84,Digital!$A$5:$A$84,A15),2)) -> 0 | AB15: =IF(B15="","",ROUND(IF(I15="Budget",PackBudget,IF(I15="Standard",PackStandard,IF(I15="Gift",PackGift,IF(I15="Premium",PackPremium,DefaultPackaging)))),2)) -> 0 | AC15: =IF(B15="","",IF(I15="Budget",PackWeightBudget,IF(I15="Standard",PackWeightStandard,IF(I15="Gift",PackWeightGift,IF(I15="Premium",PackWeightPremium,0))))) -> 0 | AD15: =IF(B15="","",IFERROR(INDEX(Shipping!$M$5:$M$64,MATCH(J15,Shipping!$L$5:$L$64,0)),DefaultShipping)) -> 0 | AE15: =IF(B15="","",IFERROR(INDEX(Shipping!$F$5:$F$64,MATCH(J15,Shipping!$L$5:$L$64,0)),0)) -> 0 | AF15: =IF(B15="","",IFERROR(INDEX(Shipping!$C$5:$C$64,MATCH(J15,Shipping!$L$5:$L$64,0)),"")) -> 0 | AG15: =IF(B15="","",ROUND(MAX(0,AD15-AE15),2)) -> 0 | AH15: =IF(B15="","",ROUND(T15+Z15+AA15+AB15+AG15,2)) -> 0 | AI15: =IF(B15="","",IFERROR(INDEX(Channels!$S$5:$S$18,MATCH(IF(H15="",DefaultChannel,H15),Channels!$A$5:$A$18,0)),0)) -> 0 | AJ15: =IF(B15="","",IFERROR(INDEX(Channels!$O$5:$O$18,MATCH(IF(H15="",DefaultChannel,H15),Channels!$A$5:$A$18,0)),"No")) -> 0 | AK15: =IF(B15="","",ROUND(IFERROR(INDEX(Channels!$T$5:$T$18,MATCH(IF(H15="",DefaultChannel,H15),Channels!$A$5:$A$18,0)),0)+IF(AJ15="Yes",AE15*AI15,0),4)) -> 0 | AL15: =IF(B15="","",IF(OverheadMethod="Share of revenue",IF(RevenueTargetMonth<=0,0,OverheadMonthly/RevenueTargetMonth),0)) -> 0 | AM15: =IF(B15="","",IF(OverheadMethod="Per hour worked",ROUND(OverheadPerHour*Y15,2),IF(OR(OverheadMethod="Per unit made",OverheadMethod="Per order"),OverheadPerUnit,0))) -> 0 | AN15: =IF(B15="","",IF(N15<>"",N15,TargetRetailMargin)) -> 0 | AO15: =IF(B15="","",1-AN15-AI15-AL15) -> 0 | AP15: =IF(B15="","",IF(AO15<=0,"",(AH15+AM15+AK15)/AO15)) -> 0 | AQ15: =IF(B15="","",IF(AP15="","Check the settings",ROUND(IF(RoundingRule="None",AP15,IF(RoundingRule="Nearest 0.99",MAX(0.99,CEILING(AP15,1)-0.01),IF(RoundingRule="Nearest 0.95",MAX(0.95,CEILING(AP15,1)-0.05),IF(RoundingRule="Nearest 0.50",CEILING(AP15,0.5),IF(RoundingRule="Nearest 1",CEILING(AP15,1),IF(RoundingRule="Nearest 5",CEILING(AP15,5),IF(RoundingRule="Up to whole 1",CEILING(AP15,1),IF(RoundingRule="Up to whole 5",CEILING(AP15,5),ROUND(AP15,2))))))))),2))) -> 0 | AR15: =IF(B15="","",IF(M15<>"",M15,IF(ISNUMBER(AQ15),AQ15,""))) -> 0 | AS15: =IF(B15="","",IF(AR15="","",ROUND(AM15+AR15*AL15,2))) -> 0 | AT15: =IF(B15="","",IF(AR15="","",ROUND(AH15+AS15,2))) -> 0 | AU15: =IF(B15="","",IF(AR15="","",ROUND(AR15*AI15+AK15,2))) -> 0 | AV15: =IF(B15="","",IF(AR15="","",ROUND(AR15-AT15-AU15,2))) -> 0 | AW15: =IF(B15="","",IF(OR(AR15="",AR15=0),"",AV15/AR15)) -> 0 | AX15: =IF(B15="","",IF(OR(AT15="",AT15=0),"",AV15/AT15)) -> 0 | AY15: =IF(B15="","",IF(OR(Y15="",Y15=0,AV15=""),"",ROUND(AV15/Y15,2))) -> 0 | AZ15: =IF(B15="","",IF(OR(Y15="",Y15=0,AV15=""),"",ROUND((AV15+Z15)/Y15,2))) -> 0 | BA15: =IF(B15="","",IF(1-AI15-AL15<=0,"",ROUND((AH15+AM15+AK15)/(1-AI15-AL15),2))) -> 0 | BB15: =IF(B15="","",IF(AT15="","",ROUND(AT15*2,2))) -> 0 | BC15: =IF(B15="","",IF(AR15="","",ROUND(AR15*(1-WholesaleDiscount),2))) -> 0 | BD15: =IF(B15="","",IF(BC15="","",ROUND(BC15-AH15-AM15,2))) -> 0 | BE15: =IF(B15="","",IF(OR(BC15="",BC15=0),"",BD15/BC15)) -> 0 | BF15: =IF(B15="","",IFERROR(ROUND(AVERAGEIFS(Competitors!$F$5:$F$154,Competitors!$A$5:$A$154,A15),2),"")) -> 0 | BG15: =IF(B15="","",IF(OR(BF15="",BF15=0,AR15=""),"",AR15/BF15-1)) -> 0 | BH15: =IF(B15="","",SUMIFS(Sales!$D$5:$D$804,Sales!$C$5:$C$804,A15)) -> 0 | BI15: =IF(B15="","",ROUND(SUMIFS(Sales!$V$5:$V$804,Sales!$C$5:$C$804,A15),2)) -> 0 | BJ15: =IF(B15="","",ROUND(SUMIFS(Sales!$AG$5:$AG$804,Sales!$C$5:$C$804,A15),2)) -> 0 | BK15: =IF(B15="","",IF(OR(BI15="",BI15=0),"",BJ15/BI15)) -> 0 | BL15: =IF(B15="","",IF(SUMPRODUCT(MAX((Sales!$C$5:$C$804=A15)*Sales!$B$5:$B$804))=0,"",SUMPRODUCT(MAX((Sales!$C$5:$C$804=A15)*Sales!$B$5:$B$804)))) -> 0 | BM15: =IF(B15="","",IF(SUMPRODUCT(MAX(('Price History'!$B$5:$B$304=A15)*'Price History'!$A$5:$A$304))=0,IF(P15="","",P15),SUMPRODUCT(MAX(('Price History'!$B$5:$B$304=A15)*'Price History'!$A$5:$A$304)))) -> 0 | BN15: =IF(B15="","",IF(BM15="","",TodayDate-BM15)) -> 0 | BO15: =IF(B15="","",COUNTIFS($AV$5:$AV$304,">"&AV15)+COUNTIFS($AV$5:AV15,AV15)) -> 0 | BP15: =IF(B15="","",COUNTIFS($AW$5:$AW$304,">"&AW15)+COUNTIFS($AW$5:AW15,AW15)) -> 0 | BQ15: =IF(B15="","",COUNTIFS($BI$5:$BI$304,">"&BI15)+COUNTIFS($BI$5:BI15,BI15)) -> 0 | BR15: =IF(B15="","",COUNTIFS($AY$5:$AY$304,">"&AY15)+COUNTIFS($AY$5:AY15,AY15)) -> 0 | BS15: =IF(B15="","",IF(AH15=0,"Add - no costs entered yet",IF(AR15="","Check - no price yet",IF(AV15<0,"Loss - every sale costs you money",IF(AND(AZ15<>"",AZ15<MinimumWage),"Below - pays under minimum wage",IF(AW15<MarginWarning,"Low margin - re-price it",IF(AND(AF15<>"",K15<>"",K15+AC15>AF15),"Check - too heavy for that postage band",IF(AND(BN15<>"",BN15>PriceReviewDays),"Due - price has not been reviewed",IF(AND(BG15<>"",BG15>0.5),"Check - well above the market","OK")))))))) ) -> 0
A16: =IF(B16="","",ProductPrefix&TEXT(ROW()-4,"0000")) -> 0 | B16: Cable beanie crochet pattern | D16: Digital download | E16: Active | F16: Autumn | G16: Very simple | H16: Etsy | K16: 0 | L16: 0 | M16: 8.5 | P16: 45937 | R16: Instant download - no packaging profile, so nothing is charged for a box that is never posted. | S16: =IF(B16="","",IF(C16<>"",C16,UPPER(LEFT(IF(D16="","GEN",D16),3))&"-"&TEXT(ROW()-4,"000"))) -> 0 | T16: =IF(B16="","",ROUND(SUMIFS('Material Usage'!$M$5:$M$904,'Material Usage'!$A$5:$A$904,A16)+SUMIFS(Crochet!$AD$5:$AD$84,Crochet!$A$5:$A$84,A16)+SUMIFS(Jewelry!$AF$5:$AF$84,Jewelry!$A$5:$A$84,A16)+SUMIFS(Candles!$AF$5:$AF$84,Candles!$A$5:$A$84,A16)+SUMIFS(Clothing!$AB$5:$AB$84,Clothing!$A$5:$A$84,A16)+SUMIFS(Woodworking!$AC$5:$AC$84,Woodworking!$A$5:$A$84,A16)+SUMIFS(Digital!$X$5:$X$84,Digital!$A$5:$A$84,A16),2)) -> 0 | U16: =IF(B16="","",ROUND(SUMIFS(Labor!$O$5:$O$304,Labor!$A$5:$A$304,A16)+SUMIFS(Crochet!$AG$5:$AG$84,Crochet!$A$5:$A$84,A16)+SUMIFS(Jewelry!$AI$5:$AI$84,Jewelry!$A$5:$A$84,A16)+SUMIFS(Candles!$AI$5:$AI$84,Candles!$A$5:$A$84,A16)+SUMIFS(Clothing!$AE$5:$AE$84,Clothing!$A$5:$A$84,A16)+SUMIFS(Woodworking!$AF$5:$AF$84,Woodworking!$A$5:$A$84,A16)+SUMIFS(Digital!$Z$5:$Z$84,Digital!$A$5:$A$84,A16),2)) -> 0 | V16: =IF(B16="","",ROUND(SUMIFS(Labor!$P$5:$P$304,Labor!$A$5:$A$304,A16)+SUMIFS(Crochet!$AE$5:$AE$84,Crochet!$A$5:$A$84,A16)+SUMIFS(Jewelry!$AG$5:$AG$84,Jewelry!$A$5:$A$84,A16)+SUMIFS(Candles!$AG$5:$AG$84,Candles!$A$5:$A$84,A16)+SUMIFS(Clothing!$AC$5:$AC$84,Clothing!$A$5:$A$84,A16)+SUMIFS(Woodworking!$AD$5:$AD$84,Woodworking!$A$5:$A$84,A16)+SUMIFS(Digital!$Y$5:$Y$84,Digital!$A$5:$A$84,A16),1)) -> 0 | W16: =IF(B16="","",IFERROR(INDEX(DiffTimeFactors,MATCH(G16,DiffNames,0)),1)) -> 0 | X16: =IF(B16="","",ROUND(V16*W16,1)) -> 0 | Y16: =IF(B16="","",ROUND(X16/60,3)) -> 0 | Z16: =IF(B16="","",ROUND(U16*W16,2)) -> 0 | AA16: =IF(B16="","",ROUND(SUMIFS(Labor!$Q$5:$Q$304,Labor!$A$5:$A$304,A16)+SUMIFS(Crochet!$AH$5:$AH$84,Crochet!$A$5:$A$84,A16)+SUMIFS(Jewelry!$AJ$5:$AJ$84,Jewelry!$A$5:$A$84,A16)+SUMIFS(Candles!$AJ$5:$AJ$84,Candles!$A$5:$A$84,A16)+SUMIFS(Clothing!$AF$5:$AF$84,Clothing!$A$5:$A$84,A16)+SUMIFS(Woodworking!$AH$5:$AH$84,Woodworking!$A$5:$A$84,A16)+SUMIFS(Digital!$AA$5:$AA$84,Digital!$A$5:$A$84,A16),2)) -> 0 | AB16: =IF(B16="","",ROUND(IF(I16="Budget",PackBudget,IF(I16="Standard",PackStandard,IF(I16="Gift",PackGift,IF(I16="Premium",PackPremium,DefaultPackaging)))),2)) -> 0 | AC16: =IF(B16="","",IF(I16="Budget",PackWeightBudget,IF(I16="Standard",PackWeightStandard,IF(I16="Gift",PackWeightGift,IF(I16="Premium",PackWeightPremium,0))))) -> 0 | AD16: =IF(B16="","",IFERROR(INDEX(Shipping!$M$5:$M$64,MATCH(J16,Shipping!$L$5:$L$64,0)),DefaultShipping)) -> 0 | AE16: =IF(B16="","",IFERROR(INDEX(Shipping!$F$5:$F$64,MATCH(J16,Shipping!$L$5:$L$64,0)),0)) -> 0 | AF16: =IF(B16="","",IFERROR(INDEX(Shipping!$C$5:$C$64,MATCH(J16,Shipping!$L$5:$L$64,0)),"")) -> 0 | AG16: =IF(B16="","",ROUND(MAX(0,AD16-AE16),2)) -> 0 | AH16: =IF(B16="","",ROUND(T16+Z16+AA16+AB16+AG16,2)) -> 0 | AI16: =IF(B16="","",IFERROR(INDEX(Channels!$S$5:$S$18,MATCH(IF(H16="",DefaultChannel,H16),Channels!$A$5:$A$18,0)),0)) -> 0 | AJ16: =IF(B16="","",IFERROR(INDEX(Channels!$O$5:$O$18,MATCH(IF(H16="",DefaultChannel,H16),Channels!$A$5:$A$18,0)),"No")) -> 0 | AK16: =IF(B16="","",ROUND(IFERROR(INDEX(Channels!$T$5:$T$18,MATCH(IF(H16="",DefaultChannel,H16),Channels!$A$5:$A$18,0)),0)+IF(AJ16="Yes",AE16*AI16,0),4)) -> 0 | AL16: =IF(B16="","",IF(OverheadMethod="Share of revenue",IF(RevenueTargetMonth<=0,0,OverheadMonthly/RevenueTargetMonth),0)) -> 0 | AM16: =IF(B16="","",IF(OverheadMethod="Per hour worked",ROUND(OverheadPerHour*Y16,2),IF(OR(OverheadMethod="Per unit made",OverheadMethod="Per order"),OverheadPerUnit,0))) -> 0 | AN16: =IF(B16="","",IF(N16<>"",N16,TargetRetailMargin)) -> 0 | AO16: =IF(B16="","",1-AN16-AI16-AL16) -> 0 | AP16: =IF(B16="","",IF(AO16<=0,"",(AH16+AM16+AK16)/AO16)) -> 0 | AQ16: =IF(B16="","",IF(AP16="","Check the settings",ROUND(IF(RoundingRule="None",AP16,IF(RoundingRule="Nearest 0.99",MAX(0.99,CEILING(AP16,1)-0.01),IF(RoundingRule="Nearest 0.95",MAX(0.95,CEILING(AP16,1)-0.05),IF(RoundingRule="Nearest 0.50",CEILING(AP16,0.5),IF(RoundingRule="Nearest 1",CEILING(AP16,1),IF(RoundingRule="Nearest 5",CEILING(AP16,5),IF(RoundingRule="Up to whole 1",CEILING(AP16,1),IF(RoundingRule="Up to whole 5",CEILING(AP16,5),ROUND(AP16,2))))))))),2))) -> 0 | AR16: =IF(B16="","",IF(M16<>"",M16,IF(ISNUMBER(AQ16),AQ16,""))) -> 0 | AS16: =IF(B16="","",IF(AR16="","",ROUND(AM16+AR16*AL16,2))) -> 0 | AT16: =IF(B16="","",IF(AR16="","",ROUND(AH16+AS16,2))) -> 0 | AU16: =IF(B16="","",IF(AR16="","",ROUND(AR16*AI16+AK16,2))) -> 0 | AV16: =IF(B16="","",IF(AR16="","",ROUND(AR16-AT16-AU16,2))) -> 0 | AW16: =IF(B16="","",IF(OR(AR16="",AR16=0),"",AV16/AR16)) -> 0 | AX16: =IF(B16="","",IF(OR(AT16="",AT16=0),"",AV16/AT16)) -> 0 | AY16: =IF(B16="","",IF(OR(Y16="",Y16=0,AV16=""),"",ROUND(AV16/Y16,2))) -> 0 | AZ16: =IF(B16="","",IF(OR(Y16="",Y16=0,AV16=""),"",ROUND((AV16+Z16)/Y16,2))) -> 0 | BA16: =IF(B16="","",IF(1-AI16-AL16<=0,"",ROUND((AH16+AM16+AK16)/(1-AI16-AL16),2))) -> 0 | BB16: =IF(B16="","",IF(AT16="","",ROUND(AT16*2,2))) -> 0 | BC16: =IF(B16="","",IF(AR16="","",ROUND(AR16*(1-WholesaleDiscount),2))) -> 0 | BD16: =IF(B16="","",IF(BC16="","",ROUND(BC16-AH16-AM16,2))) -> 0 | BE16: =IF(B16="","",IF(OR(BC16="",BC16=0),"",BD16/BC16)) -> 0 | BF16: =IF(B16="","",IFERROR(ROUND(AVERAGEIFS(Competitors!$F$5:$F$154,Competitors!$A$5:$A$154,A16),2),"")) -> 0 | BG16: =IF(B16="","",IF(OR(BF16="",BF16=0,AR16=""),"",AR16/BF16-1)) -> 0 | BH16: =IF(B16="","",SUMIFS(Sales!$D$5:$D$804,Sales!$C$5:$C$804,A16)) -> 0 | BI16: =IF(B16="","",ROUND(SUMIFS(Sales!$V$5:$V$804,Sales!$C$5:$C$804,A16),2)) -> 0 | BJ16: =IF(B16="","",ROUND(SUMIFS(Sales!$AG$5:$AG$804,Sales!$C$5:$C$804,A16),2)) -> 0 | BK16: =IF(B16="","",IF(OR(BI16="",BI16=0),"",BJ16/BI16)) -> 0 | BL16: =IF(B16="","",IF(SUMPRODUCT(MAX((Sales!$C$5:$C$804=A16)*Sales!$B$5:$B$804))=0,"",SUMPRODUCT(MAX((Sales!$C$5:$C$804=A16)*Sales!$B$5:$B$804)))) -> 0 | BM16: =IF(B16="","",IF(SUMPRODUCT(MAX(('Price History'!$B$5:$B$304=A16)*'Price History'!$A$5:$A$304))=0,IF(P16="","",P16),SUMPRODUCT(MAX(('Price History'!$B$5:$B$304=A16)*'Price History'!$A$5:$A$304)))) -> 0 | BN16: =IF(B16="","",IF(BM16="","",TodayDate-BM16)) -> 0 | BO16: =IF(B16="","",COUNTIFS($AV$5:$AV$304,">"&AV16)+COUNTIFS($AV$5:AV16,AV16)) -> 0 | BP16: =IF(B16="","",COUNTIFS($AW$5:$AW$304,">"&AW16)+COUNTIFS($AW$5:AW16,AW16)) -> 0 | BQ16: =IF(B16="","",COUNTIFS($BI$5:$BI$304,">"&BI16)+COUNTIFS($BI$5:BI16,BI16)) -> 0 | BR16: =IF(B16="","",COUNTIFS($AY$5:$AY$304,">"&AY16)+COUNTIFS($AY$5:AY16,AY16)) -> 0 | BS16: =IF(B16="","",IF(AH16=0,"Add - no costs entered yet",IF(AR16="","Check - no price yet",IF(AV16<0,"Loss - every sale costs you money",IF(AND(AZ16<>"",AZ16<MinimumWage),"Below - pays under minimum wage",IF(AW16<MarginWarning,"Low margin - re-price it",IF(AND(AF16<>"",K16<>"",K16+AC16>AF16),"Check - too heavy for that postage band",IF(AND(BN16<>"",BN16>PriceReviewDays),"Due - price has not been reviewed",IF(AND(BG16<>"",BG16>0.5),"Check - well above the market","OK")))))))) ) -> 0
A17: =IF(B17="","",ProductPrefix&TEXT(ROW()-4,"0000")) -> 0 | B17: Woodland fox pattern | D17: Digital download | E17: Active | F17: Christmas | G17: Very simple | H17: Etsy | K17: 0 | L17: 0 | M17: 9.5 | P17: 46197 | S17: =IF(B17="","",IF(C17<>"",C17,UPPER(LEFT(IF(D17="","GEN",D17),3))&"-"&TEXT(ROW()-4,"000"))) -> 0 | T17: =IF(B17="","",ROUND(SUMIFS('Material Usage'!$M$5:$M$904,'Material Usage'!$A$5:$A$904,A17)+SUMIFS(Crochet!$AD$5:$AD$84,Crochet!$A$5:$A$84,A17)+SUMIFS(Jewelry!$AF$5:$AF$84,Jewelry!$A$5:$A$84,A17)+SUMIFS(Candles!$AF$5:$AF$84,Candles!$A$5:$A$84,A17)+SUMIFS(Clothing!$AB$5:$AB$84,Clothing!$A$5:$A$84,A17)+SUMIFS(Woodworking!$AC$5:$AC$84,Woodworking!$A$5:$A$84,A17)+SUMIFS(Digital!$X$5:$X$84,Digital!$A$5:$A$84,A17),2)) -> 0 | U17: =IF(B17="","",ROUND(SUMIFS(Labor!$O$5:$O$304,Labor!$A$5:$A$304,A17)+SUMIFS(Crochet!$AG$5:$AG$84,Crochet!$A$5:$A$84,A17)+SUMIFS(Jewelry!$AI$5:$AI$84,Jewelry!$A$5:$A$84,A17)+SUMIFS(Candles!$AI$5:$AI$84,Candles!$A$5:$A$84,A17)+SUMIFS(Clothing!$AE$5:$AE$84,Clothing!$A$5:$A$84,A17)+SUMIFS(Woodworking!$AF$5:$AF$84,Woodworking!$A$5:$A$84,A17)+SUMIFS(Digital!$Z$5:$Z$84,Digital!$A$5:$A$84,A17),2)) -> 0 | V17: =IF(B17="","",ROUND(SUMIFS(Labor!$P$5:$P$304,Labor!$A$5:$A$304,A17)+SUMIFS(Crochet!$AE$5:$AE$84,Crochet!$A$5:$A$84,A17)+SUMIFS(Jewelry!$AG$5:$AG$84,Jewelry!$A$5:$A$84,A17)+SUMIFS(Candles!$AG$5:$AG$84,Candles!$A$5:$A$84,A17)+SUMIFS(Clothing!$AC$5:$AC$84,Clothing!$A$5:$A$84,A17)+SUMIFS(Woodworking!$AD$5:$AD$84,Woodworking!$A$5:$A$84,A17)+SUMIFS(Digital!$Y$5:$Y$84,Digital!$A$5:$A$84,A17),1)) -> 0 | W17: =IF(B17="","",IFERROR(INDEX(DiffTimeFactors,MATCH(G17,DiffNames,0)),1)) -> 0 | X17: =IF(B17="","",ROUND(V17*W17,1)) -> 0 | Y17: =IF(B17="","",ROUND(X17/60,3)) -> 0 | Z17: =IF(B17="","",ROUND(U17*W17,2)) -> 0 | AA17: =IF(B17="","",ROUND(SUMIFS(Labor!$Q$5:$Q$304,Labor!$A$5:$A$304,A17)+SUMIFS(Crochet!$AH$5:$AH$84,Crochet!$A$5:$A$84,A17)+SUMIFS(Jewelry!$AJ$5:$AJ$84,Jewelry!$A$5:$A$84,A17)+SUMIFS(Candles!$AJ$5:$AJ$84,Candles!$A$5:$A$84,A17)+SUMIFS(Clothing!$AF$5:$AF$84,Clothing!$A$5:$A$84,A17)+SUMIFS(Woodworking!$AH$5:$AH$84,Woodworking!$A$5:$A$84,A17)+SUMIFS(Digital!$AA$5:$AA$84,Digital!$A$5:$A$84,A17),2)) -> 0 | AB17: =IF(B17="","",ROUND(IF(I17="Budget",PackBudget,IF(I17="Standard",PackStandard,IF(I17="Gift",PackGift,IF(I17="Premium",PackPremium,DefaultPackaging)))),2)) -> 0 | AC17: =IF(B17="","",IF(I17="Budget",PackWeightBudget,IF(I17="Standard",PackWeightStandard,IF(I17="Gift",PackWeightGift,IF(I17="Premium",PackWeightPremium,0))))) -> 0 | AD17: =IF(B17="","",IFERROR(INDEX(Shipping!$M$5:$M$64,MATCH(J17,Shipping!$L$5:$L$64,0)),DefaultShipping)) -> 0 | AE17: =IF(B17="","",IFERROR(INDEX(Shipping!$F$5:$F$64,MATCH(J17,Shipping!$L$5:$L$64,0)),0)) -> 0 | AF17: =IF(B17="","",IFERROR(INDEX(Shipping!$C$5:$C$64,MATCH(J17,Shipping!$L$5:$L$64,0)),"")) -> 0 | AG17: =IF(B17="","",ROUND(MAX(0,AD17-AE17),2)) -> 0 | AH17: =IF(B17="","",ROUND(T17+Z17+AA17+AB17+AG17,2)) -> 0 | AI17: =IF(B17="","",IFERROR(INDEX(Channels!$S$5:$S$18,MATCH(IF(H17="",DefaultChannel,H17),Channels!$A$5:$A$18,0)),0)) -> 0 | AJ17: =IF(B17="","",IFERROR(INDEX(Channels!$O$5:$O$18,MATCH(IF(H17="",DefaultChannel,H17),Channels!$A$5:$A$18,0)),"No")) -> 0 | AK17: =IF(B17="","",ROUND(IFERROR(INDEX(Channels!$T$5:$T$18,MATCH(IF(H17="",DefaultChannel,H17),Channels!$A$5:$A$18,0)),0)+IF(AJ17="Yes",AE17*AI17,0),4)) -> 0 | AL17: =IF(B17="","",IF(OverheadMethod="Share of revenue",IF(RevenueTargetMonth<=0,0,OverheadMonthly/RevenueTargetMonth),0)) -> 0 | AM17: =IF(B17="","",IF(OverheadMethod="Per hour worked",ROUND(OverheadPerHour*Y17,2),IF(OR(OverheadMethod="Per unit made",OverheadMethod="Per order"),OverheadPerUnit,0))) -> 0 | AN17: =IF(B17="","",IF(N17<>"",N17,TargetRetailMargin)) -> 0 | AO17: =IF(B17="","",1-AN17-AI17-AL17) -> 0 | AP17: =IF(B17="","",IF(AO17<=0,"",(AH17+AM17+AK17)/AO17)) -> 0 | AQ17: =IF(B17="","",IF(AP17="","Check the settings",ROUND(IF(RoundingRule="None",AP17,IF(RoundingRule="Nearest 0.99",MAX(0.99,CEILING(AP17,1)-0.01),IF(RoundingRule="Nearest 0.95",MAX(0.95,CEILING(AP17,1)-0.05),IF(RoundingRule="Nearest 0.50",CEILING(AP17,0.5),IF(RoundingRule="Nearest 1",CEILING(AP17,1),IF(RoundingRule="Nearest 5",CEILING(AP17,5),IF(RoundingRule="Up to whole 1",CEILING(AP17,1),IF(RoundingRule="Up to whole 5",CEILING(AP17,5),ROUND(AP17,2))))))))),2))) -> 0 | AR17: =IF(B17="","",IF(M17<>"",M17,IF(ISNUMBER(AQ17),AQ17,""))) -> 0 | AS17: =IF(B17="","",IF(AR17="","",ROUND(AM17+AR17*AL17,2))) -> 0 | AT17: =IF(B17="","",IF(AR17="","",ROUND(AH17+AS17,2))) -> 0 | AU17: =IF(B17="","",IF(AR17="","",ROUND(AR17*AI17+AK17,2))) -> 0 | AV17: =IF(B17="","",IF(AR17="","",ROUND(AR17-AT17-AU17,2))) -> 0 | AW17: =IF(B17="","",IF(OR(AR17="",AR17=0),"",AV17/AR17)) -> 0 | AX17: =IF(B17="","",IF(OR(AT17="",AT17=0),"",AV17/AT17)) -> 0 | AY17: =IF(B17="","",IF(OR(Y17="",Y17=0,AV17=""),"",ROUND(AV17/Y17,2))) -> 0 | AZ17: =IF(B17="","",IF(OR(Y17="",Y17=0,AV17=""),"",ROUND((AV17+Z17)/Y17,2))) -> 0 | BA17: =IF(B17="","",IF(1-AI17-AL17<=0,"",ROUND((AH17+AM17+AK17)/(1-AI17-AL17),2))) -> 0 | BB17: =IF(B17="","",IF(AT17="","",ROUND(AT17*2,2))) -> 0 | BC17: =IF(B17="","",IF(AR17="","",ROUND(AR17*(1-WholesaleDiscount),2))) -> 0 | BD17: =IF(B17="","",IF(BC17="","",ROUND(BC17-AH17-AM17,2))) -> 0 | BE17: =IF(B17="","",IF(OR(BC17="",BC17=0),"",BD17/BC17)) -> 0 | BF17: =IF(B17="","",IFERROR(ROUND(AVERAGEIFS(Competitors!$F$5:$F$154,Competitors!$A$5:$A$154,A17),2),"")) -> 0 | BG17: =IF(B17="","",IF(OR(BF17="",BF17=0,AR17=""),"",AR17/BF17-1)) -> 0 | BH17: =IF(B17="","",SUMIFS(Sales!$D$5:$D$804,Sales!$C$5:$C$804,A17)) -> 0 | BI17: =IF(B17="","",ROUND(SUMIFS(Sales!$V$5:$V$804,Sales!$C$5:$C$804,A17),2)) -> 0 | BJ17: =IF(B17="","",ROUND(SUMIFS(Sales!$AG$5:$AG$804,Sales!$C$5:$C$804,A17),2)) -> 0 | BK17: =IF(B17="","",IF(OR(BI17="",BI17=0),"",BJ17/BI17)) -> 0 | BL17: =IF(B17="","",IF(SUMPRODUCT(MAX((Sales!$C$5:$C$804=A17)*Sales!$B$5:$B$804))=0,"",SUMPRODUCT(MAX((Sales!$C$5:$C$804=A17)*Sales!$B$5:$B$804)))) -> 0 | BM17: =IF(B17="","",IF(SUMPRODUCT(MAX(('Price History'!$B$5:$B$304=A17)*'Price History'!$A$5:$A$304))=0,IF(P17="","",P17),SUMPRODUCT(MAX(('Price History'!$B$5:$B$304=A17)*'Price History'!$A$5:$A$304)))) -> 0 | BN17: =IF(B17="","",IF(BM17="","",TodayDate-BM17)) -> 0 | BO17: =IF(B17="","",COUNTIFS($AV$5:$AV$304,">"&AV17)+COUNTIFS($AV$5:AV17,AV17)) -> 0 | BP17: =IF(B17="","",COUNTIFS($AW$5:$AW$304,">"&AW17)+COUNTIFS($AW$5:AW17,AW17)) -> 0 | BQ17: =IF(B17="","",COUNTIFS($BI$5:$BI$304,">"&BI17)+COUNTIFS($BI$5:BI17,BI17)) -> 0 | BR17: =IF(B17="","",COUNTIFS($AY$5:$AY$304,">"&AY17)+COUNTIFS($AY$5:AY17,AY17)) -> 0 | BS17: =IF(B17="","",IF(AH17=0,"Add - no costs entered yet",IF(AR17="","Check - no price yet",IF(AV17<0,"Loss - every sale costs you money",IF(AND(AZ17<>"",AZ17<MinimumWage),"Below - pays under minimum wage",IF(AW17<MarginWarning,"Low margin - re-price it",IF(AND(AF17<>"",K17<>"",K17+AC17>AF17),"Check - too heavy for that postage band",IF(AND(BN17<>"",BN17>PriceReviewDays),"Due - price has not been reviewed",IF(AND(BG17<>"",BG17>0.5),"Check - well above the market","OK")))))))) ) -> 0
A18: =IF(B18="","",ProductPrefix&TEXT(ROW()-4,"0000")) -> 0 | B18: Beeswax wrap set of three | D18: Other handmade | E18: Prototype | F18: All year | G18: Simple | H18: Etsy | I18: Budget | J18: First class - Domestic to 250g | K18: 120 | L18: 0 | R18: Still costing it. No materials entered yet. | S18: =IF(B18="","",IF(C18<>"",C18,UPPER(LEFT(IF(D18="","GEN",D18),3))&"-"&TEXT(ROW()-4,"000"))) -> 0 | T18: =IF(B18="","",ROUND(SUMIFS('Material Usage'!$M$5:$M$904,'Material Usage'!$A$5:$A$904,A18)+SUMIFS(Crochet!$AD$5:$AD$84,Crochet!$A$5:$A$84,A18)+SUMIFS(Jewelry!$AF$5:$AF$84,Jewelry!$A$5:$A$84,A18)+SUMIFS(Candles!$AF$5:$AF$84,Candles!$A$5:$A$84,A18)+SUMIFS(Clothing!$AB$5:$AB$84,Clothing!$A$5:$A$84,A18)+SUMIFS(Woodworking!$AC$5:$AC$84,Woodworking!$A$5:$A$84,A18)+SUMIFS(Digital!$X$5:$X$84,Digital!$A$5:$A$84,A18),2)) -> 0 | U18: =IF(B18="","",ROUND(SUMIFS(Labor!$O$5:$O$304,Labor!$A$5:$A$304,A18)+SUMIFS(Crochet!$AG$5:$AG$84,Crochet!$A$5:$A$84,A18)+SUMIFS(Jewelry!$AI$5:$AI$84,Jewelry!$A$5:$A$84,A18)+SUMIFS(Candles!$AI$5:$AI$84,Candles!$A$5:$A$84,A18)+SUMIFS(Clothing!$AE$5:$AE$84,Clothing!$A$5:$A$84,A18)+SUMIFS(Woodworking!$AF$5:$AF$84,Woodworking!$A$5:$A$84,A18)+SUMIFS(Digital!$Z$5:$Z$84,Digital!$A$5:$A$84,A18),2)) -> 0 | V18: =IF(B18="","",ROUND(SUMIFS(Labor!$P$5:$P$304,Labor!$A$5:$A$304,A18)+SUMIFS(Crochet!$AE$5:$AE$84,Crochet!$A$5:$A$84,A18)+SUMIFS(Jewelry!$AG$5:$AG$84,Jewelry!$A$5:$A$84,A18)+SUMIFS(Candles!$AG$5:$AG$84,Candles!$A$5:$A$84,A18)+SUMIFS(Clothing!$AC$5:$AC$84,Clothing!$A$5:$A$84,A18)+SUMIFS(Woodworking!$AD$5:$AD$84,Woodworking!$A$5:$A$84,A18)+SUMIFS(Digital!$Y$5:$Y$84,Digital!$A$5:$A$84,A18),1)) -> 0 | W18: =IF(B18="","",IFERROR(INDEX(DiffTimeFactors,MATCH(G18,DiffNames,0)),1)) -> 0 | X18: =IF(B18="","",ROUND(V18*W18,1)) -> 0 | Y18: =IF(B18="","",ROUND(X18/60,3)) -> 0 | Z18: =IF(B18="","",ROUND(U18*W18,2)) -> 0 | AA18: =IF(B18="","",ROUND(SUMIFS(Labor!$Q$5:$Q$304,Labor!$A$5:$A$304,A18)+SUMIFS(Crochet!$AH$5:$AH$84,Crochet!$A$5:$A$84,A18)+SUMIFS(Jewelry!$AJ$5:$AJ$84,Jewelry!$A$5:$A$84,A18)+SUMIFS(Candles!$AJ$5:$AJ$84,Candles!$A$5:$A$84,A18)+SUMIFS(Clothing!$AF$5:$AF$84,Clothing!$A$5:$A$84,A18)+SUMIFS(Woodworking!$AH$5:$AH$84,Woodworking!$A$5:$A$84,A18)+SUMIFS(Digital!$AA$5:$AA$84,Digital!$A$5:$A$84,A18),2)) -> 0 | AB18: =IF(B18="","",ROUND(IF(I18="Budget",PackBudget,IF(I18="Standard",PackStandard,IF(I18="Gift",PackGift,IF(I18="Premium",PackPremium,DefaultPackaging)))),2)) -> 0 | AC18: =IF(B18="","",IF(I18="Budget",PackWeightBudget,IF(I18="Standard",PackWeightStandard,IF(I18="Gift",PackWeightGift,IF(I18="Premium",PackWeightPremium,0))))) -> 0 | AD18: =IF(B18="","",IFERROR(INDEX(Shipping!$M$5:$M$64,MATCH(J18,Shipping!$L$5:$L$64,0)),DefaultShipping)) -> 0 | AE18: =IF(B18="","",IFERROR(INDEX(Shipping!$F$5:$F$64,MATCH(J18,Shipping!$L$5:$L$64,0)),0)) -> 0 | AF18: =IF(B18="","",IFERROR(INDEX(Shipping!$C$5:$C$64,MATCH(J18,Shipping!$L$5:$L$64,0)),"")) -> 0 | AG18: =IF(B18="","",ROUND(MAX(0,AD18-AE18),2)) -> 0 | AH18: =IF(B18="","",ROUND(T18+Z18+AA18+AB18+AG18,2)) -> 0 | AI18: =IF(B18="","",IFERROR(INDEX(Channels!$S$5:$S$18,MATCH(IF(H18="",DefaultChannel,H18),Channels!$A$5:$A$18,0)),0)) -> 0 | AJ18: =IF(B18="","",IFERROR(INDEX(Channels!$O$5:$O$18,MATCH(IF(H18="",DefaultChannel,H18),Channels!$A$5:$A$18,0)),"No")) -> 0 | AK18: =IF(B18="","",ROUND(IFERROR(INDEX(Channels!$T$5:$T$18,MATCH(IF(H18="",DefaultChannel,H18),Channels!$A$5:$A$18,0)),0)+IF(AJ18="Yes",AE18*AI18,0),4)) -> 0 | AL18: =IF(B18="","",IF(OverheadMethod="Share of revenue",IF(RevenueTargetMonth<=0,0,OverheadMonthly/RevenueTargetMonth),0)) -> 0 | AM18: =IF(B18="","",IF(OverheadMethod="Per hour worked",ROUND(OverheadPerHour*Y18,2),IF(OR(OverheadMethod="Per unit made",OverheadMethod="Per order"),OverheadPerUnit,0))) -> 0 | AN18: =IF(B18="","",IF(N18<>"",N18,TargetRetailMargin)) -> 0 | AO18: =IF(B18="","",1-AN18-AI18-AL18) -> 0 | AP18: =IF(B18="","",IF(AO18<=0,"",(AH18+AM18+AK18)/AO18)) -> 0 | AQ18: =IF(B18="","",IF(AP18="","Check the settings",ROUND(IF(RoundingRule="None",AP18,IF(RoundingRule="Nearest 0.99",MAX(0.99,CEILING(AP18,1)-0.01),IF(RoundingRule="Nearest 0.95",MAX(0.95,CEILING(AP18,1)-0.05),IF(RoundingRule="Nearest 0.50",CEILING(AP18,0.5),IF(RoundingRule="Nearest 1",CEILING(AP18,1),IF(RoundingRule="Nearest 5",CEILING(AP18,5),IF(RoundingRule="Up to whole 1",CEILING(AP18,1),IF(RoundingRule="Up to whole 5",CEILING(AP18,5),ROUND(AP18,2))))))))),2))) -> 0 | AR18: =IF(B18="","",IF(M18<>"",M18,IF(ISNUMBER(AQ18),AQ18,""))) -> 0 | AS18: =IF(B18="","",IF(AR18="","",ROUND(AM18+AR18*AL18,2))) -> 0 | AT18: =IF(B18="","",IF(AR18="","",ROUND(AH18+AS18,2))) -> 0 | AU18: =IF(B18="","",IF(AR18="","",ROUND(AR18*AI18+AK18,2))) -> 0 | AV18: =IF(B18="","",IF(AR18="","",ROUND(AR18-AT18-AU18,2))) -> 0 | AW18: =IF(B18="","",IF(OR(AR18="",AR18=0),"",AV18/AR18)) -> 0 | AX18: =IF(B18="","",IF(OR(AT18="",AT18=0),"",AV18/AT18)) -> 0 | AY18: =IF(B18="","",IF(OR(Y18="",Y18=0,AV18=""),"",ROUND(AV18/Y18,2))) -> 0 | AZ18: =IF(B18="","",IF(OR(Y18="",Y18=0,AV18=""),"",ROUND((AV18+Z18)/Y18,2))) -> 0 | BA18: =IF(B18="","",IF(1-AI18-AL18<=0,"",ROUND((AH18+AM18+AK18)/(1-AI18-AL18),2))) -> 0 | BB18: =IF(B18="","",IF(AT18="","",ROUND(AT18*2,2))) -> 0 | BC18: =IF(B18="","",IF(AR18="","",ROUND(AR18*(1-WholesaleDiscount),2))) -> 0 | BD18: =IF(B18="","",IF(BC18="","",ROUND(BC18-AH18-AM18,2))) -> 0 | BE18: =IF(B18="","",IF(OR(BC18="",BC18=0),"",BD18/BC18)) -> 0 | BF18: =IF(B18="","",IFERROR(ROUND(AVERAGEIFS(Competitors!$F$5:$F$154,Competitors!$A$5:$A$154,A18),2),"")) -> 0 | BG18: =IF(B18="","",IF(OR(BF18="",BF18=0,AR18=""),"",AR18/BF18-1)) -> 0 | BH18: =IF(B18="","",SUMIFS(Sales!$D$5:$D$804,Sales!$C$5:$C$804,A18)) -> 0 | BI18: =IF(B18="","",ROUND(SUMIFS(Sales!$V$5:$V$804,Sales!$C$5:$C$804,A18),2)) -> 0 | BJ18: =IF(B18="","",ROUND(SUMIFS(Sales!$AG$5:$AG$804,Sales!$C$5:$C$804,A18),2)) -> 0 | BK18: =IF(B18="","",IF(OR(BI18="",BI18=0),"",BJ18/BI18)) -> 0 | BL18: =IF(B18="","",IF(SUMPRODUCT(MAX((Sales!$C$5:$C$804=A18)*Sales!$B$5:$B$804))=0,"",SUMPRODUCT(MAX((Sales!$C$5:$C$804=A18)*Sales!$B$5:$B$804)))) -> 0 | BM18: =IF(B18="","",IF(SUMPRODUCT(MAX(('Price History'!$B$5:$B$304=A18)*'Price History'!$A$5:$A$304))=0,IF(P18="","",P18),SUMPRODUCT(MAX(('Price History'!$B$5:$B$304=A18)*'Price History'!$A$5:$A$304)))) -> 0 | BN18: =IF(B18="","",IF(BM18="","",TodayDate-BM18)) -> 0 | BO18: =IF(B18="","",COUNTIFS($AV$5:$AV$304,">"&AV18)+COUNTIFS($AV$5:AV18,AV18)) -> 0 | BP18: =IF(B18="","",COUNTIFS($AW$5:$AW$304,">"&AW18)+COUNTIFS($AW$5:AW18,AW18)) -> 0 | BQ18: =IF(B18="","",COUNTIFS($BI$5:$BI$304,">"&BI18)+COUNTIFS($BI$5:BI18,BI18)) -> 0 | BR18: =IF(B18="","",COUNTIFS($AY$5:$AY$304,">"&AY18)+COUNTIFS($AY$5:AY18,AY18)) -> 0 | BS18: =IF(B18="","",IF(AH18=0,"Add - no costs entered yet",IF(AR18="","Check - no price yet",IF(AV18<0,"Loss - every sale costs you money",IF(AND(AZ18<>"",AZ18<MinimumWage),"Below - pays under minimum wage",IF(AW18<MarginWarning,"Low margin - re-price it",IF(AND(AF18<>"",K18<>"",K18+AC18>AF18),"Check - too heavy for that postage band",IF(AND(BN18<>"",BN18>PriceReviewDays),"Due - price has not been reviewed",IF(AND(BG18<>"",BG18>0.5),"Check - well above the market","OK")))))))) ) -> 0
A19: =IF(B19="","",ProductPrefix&TEXT(ROW()-4,"0000")) -> 0 | S19: =IF(B19="","",IF(C19<>"",C19,UPPER(LEFT(IF(D19="","GEN",D19),3))&"-"&TEXT(ROW()-4,"000"))) -> 0 | T19: =IF(B19="","",ROUND(SUMIFS('Material Usage'!$M$5:$M$904,'Material Usage'!$A$5:$A$904,A19)+SUMIFS(Crochet!$AD$5:$AD$84,Crochet!$A$5:$A$84,A19)+SUMIFS(Jewelry!$AF$5:$AF$84,Jewelry!$A$5:$A$84,A19)+SUMIFS(Candles!$AF$5:$AF$84,Candles!$A$5:$A$84,A19)+SUMIFS(Clothing!$AB$5:$AB$84,Clothing!$A$5:$A$84,A19)+SUMIFS(Woodworking!$AC$5:$AC$84,Woodworking!$A$5:$A$84,A19)+SUMIFS(Digital!$X$5:$X$84,Digital!$A$5:$A$84,A19),2)) -> 0 | U19: =IF(B19="","",ROUND(SUMIFS(Labor!$O$5:$O$304,Labor!$A$5:$A$304,A19)+SUMIFS(Crochet!$AG$5:$AG$84,Crochet!$A$5:$A$84,A19)+SUMIFS(Jewelry!$AI$5:$AI$84,Jewelry!$A$5:$A$84,A19)+SUMIFS(Candles!$AI$5:$AI$84,Candles!$A$5:$A$84,A19)+SUMIFS(Clothing!$AE$5:$AE$84,Clothing!$A$5:$A$84,A19)+SUMIFS(Woodworking!$AF$5:$AF$84,Woodworking!$A$5:$A$84,A19)+SUMIFS(Digital!$Z$5:$Z$84,Digital!$A$5:$A$84,A19),2)) -> 0 | V19: =IF(B19="","",ROUND(SUMIFS(Labor!$P$5:$P$304,Labor!$A$5:$A$304,A19)+SUMIFS(Crochet!$AE$5:$AE$84,Crochet!$A$5:$A$84,A19)+SUMIFS(Jewelry!$AG$5:$AG$84,Jewelry!$A$5:$A$84,A19)+SUMIFS(Candles!$AG$5:$AG$84,Candles!$A$5:$A$84,A19)+SUMIFS(Clothing!$AC$5:$AC$84,Clothing!$A$5:$A$84,A19)+SUMIFS(Woodworking!$AD$5:$AD$84,Woodworking!$A$5:$A$84,A19)+SUMIFS(Digital!$Y$5:$Y$84,Digital!$A$5:$A$84,A19),1)) -> 0 | W19: =IF(B19="","",IFERROR(INDEX(DiffTimeFactors,MATCH(G19,DiffNames,0)),1)) -> 0 | X19: =IF(B19="","",ROUND(V19*W19,1)) -> 0 | Y19: =IF(B19="","",ROUND(X19/60,3)) -> 0 | Z19: =IF(B19="","",ROUND(U19*W19,2)) -> 0 | AA19: =IF(B19="","",ROUND(SUMIFS(Labor!$Q$5:$Q$304,Labor!$A$5:$A$304,A19)+SUMIFS(Crochet!$AH$5:$AH$84,Crochet!$A$5:$A$84,A19)+SUMIFS(Jewelry!$AJ$5:$AJ$84,Jewelry!$A$5:$A$84,A19)+SUMIFS(Candles!$AJ$5:$AJ$84,Candles!$A$5:$A$84,A19)+SUMIFS(Clothing!$AF$5:$AF$84,Clothing!$A$5:$A$84,A19)+SUMIFS(Woodworking!$AH$5:$AH$84,Woodworking!$A$5:$A$84,A19)+SUMIFS(Digital!$AA$5:$AA$84,Digital!$A$5:$A$84,A19),2)) -> 0 | AB19: =IF(B19="","",ROUND(IF(I19="Budget",PackBudget,IF(I19="Standard",PackStandard,IF(I19="Gift",PackGift,IF(I19="Premium",PackPremium,DefaultPackaging)))),2)) -> 0 | AC19: =IF(B19="","",IF(I19="Budget",PackWeightBudget,IF(I19="Standard",PackWeightStandard,IF(I19="Gift",PackWeightGift,IF(I19="Premium",PackWeightPremium,0))))) -> 0 | AD19: =IF(B19="","",IFERROR(INDEX(Shipping!$M$5:$M$64,MATCH(J19,Shipping!$L$5:$L$64,0)),DefaultShipping)) -> 0 | AE19: =IF(B19="","",IFERROR(INDEX(Shipping!$F$5:$F$64,MATCH(J19,Shipping!$L$5:$L$64,0)),0)) -> 0 | AF19: =IF(B19="","",IFERROR(INDEX(Shipping!$C$5:$C$64,MATCH(J19,Shipping!$L$5:$L$64,0)),"")) -> 0 | AG19: =IF(B19="","",ROUND(MAX(0,AD19-AE19),2)) -> 0 | AH19: =IF(B19="","",ROUND(T19+Z19+AA19+AB19+AG19,2)) -> 0 | AI19: =IF(B19="","",IFERROR(INDEX(Channels!$S$5:$S$18,MATCH(IF(H19="",DefaultChannel,H19),Channels!$A$5:$A$18,0)),0)) -> 0 | AJ19: =IF(B19="","",IFERROR(INDEX(Channels!$O$5:$O$18,MATCH(IF(H19="",DefaultChannel,H19),Channels!$A$5:$A$18,0)),"No")) -> 0 | AK19: =IF(B19="","",ROUND(IFERROR(INDEX(Channels!$T$5:$T$18,MATCH(IF(H19="",DefaultChannel,H19),Channels!$A$5:$A$18,0)),0)+IF(AJ19="Yes",AE19*AI19,0),4)) -> 0 | AL19: =IF(B19="","",IF(OverheadMethod="Share of revenue",IF(RevenueTargetMonth<=0,0,OverheadMonthly/RevenueTargetMonth),0)) -> 0 | AM19: =IF(B19="","",IF(OverheadMethod="Per hour worked",ROUND(OverheadPerHour*Y19,2),IF(OR(OverheadMethod="Per unit made",OverheadMethod="Per order"),OverheadPerUnit,0))) -> 0 | AN19: =IF(B19="","",IF(N19<>"",N19,TargetRetailMargin)) -> 0 | AO19: =IF(B19="","",1-AN19-AI19-AL19) -> 0 | AP19: =IF(B19="","",IF(AO19<=0,"",(AH19+AM19+AK19)/AO19)) -> 0 | AQ19: =IF(B19="","",IF(AP19="","Check the settings",ROUND(IF(RoundingRule="None",AP19,IF(RoundingRule="Nearest 0.99",MAX(0.99,CEILING(AP19,1)-0.01),IF(RoundingRule="Nearest 0.95",MAX(0.95,CEILING(AP19,1)-0.05),IF(RoundingRule="Nearest 0.50",CEILING(AP19,0.5),IF(RoundingRule="Nearest 1",CEILING(AP19,1),IF(RoundingRule="Nearest 5",CEILING(AP19,5),IF(RoundingRule="Up to whole 1",CEILING(AP19,1),IF(RoundingRule="Up to whole 5",CEILING(AP19,5),ROUND(AP19,2))))))))),2))) -> 0 | AR19: =IF(B19="","",IF(M19<>"",M19,IF(ISNUMBER(AQ19),AQ19,""))) -> 0 | AS19: =IF(B19="","",IF(AR19="","",ROUND(AM19+AR19*AL19,2))) -> 0 | AT19: =IF(B19="","",IF(AR19="","",ROUND(AH19+AS19,2))) -> 0 | AU19: =IF(B19="","",IF(AR19="","",ROUND(AR19*AI19+AK19,2))) -> 0 | AV19: =IF(B19="","",IF(AR19="","",ROUND(AR19-AT19-AU19,2))) -> 0 | AW19: =IF(B19="","",IF(OR(AR19="",AR19=0),"",AV19/AR19)) -> 0 | AX19: =IF(B19="","",IF(OR(AT19="",AT19=0),"",AV19/AT19)) -> 0 | AY19: =IF(B19="","",IF(OR(Y19="",Y19=0,AV19=""),"",ROUND(AV19/Y19,2))) -> 0 | AZ19: =IF(B19="","",IF(OR(Y19="",Y19=0,AV19=""),"",ROUND((AV19+Z19)/Y19,2))) -> 0 | BA19: =IF(B19="","",IF(1-AI19-AL19<=0,"",ROUND((AH19+AM19+AK19)/(1-AI19-AL19),2))) -> 0 | BB19: =IF(B19="","",IF(AT19="","",ROUND(AT19*2,2))) -> 0 | BC19: =IF(B19="","",IF(AR19="","",ROUND(AR19*(1-WholesaleDiscount),2))) -> 0 | BD19: =IF(B19="","",IF(BC19="","",ROUND(BC19-AH19-AM19,2))) -> 0 | BE19: =IF(B19="","",IF(OR(BC19="",BC19=0),"",BD19/BC19)) -> 0 | BF19: =IF(B19="","",IFERROR(ROUND(AVERAGEIFS(Competitors!$F$5:$F$154,Competitors!$A$5:$A$154,A19),2),"")) -> 0 | BG19: =IF(B19="","",IF(OR(BF19="",BF19=0,AR19=""),"",AR19/BF19-1)) -> 0 | BH19: =IF(B19="","",SUMIFS(Sales!$D$5:$D$804,Sales!$C$5:$C$804,A19)) -> 0 | BI19: =IF(B19="","",ROUND(SUMIFS(Sales!$V$5:$V$804,Sales!$C$5:$C$804,A19),2)) -> 0 | BJ19: =IF(B19="","",ROUND(SUMIFS(Sales!$AG$5:$AG$804,Sales!$C$5:$C$804,A19),2)) -> 0 | BK19: =IF(B19="","",IF(OR(BI19="",BI19=0),"",BJ19/BI19)) -> 0 | BL19: =IF(B19="","",IF(SUMPRODUCT(MAX((Sales!$C$5:$C$804=A19)*Sales!$B$5:$B$804))=0,"",SUMPRODUCT(MAX((Sales!$C$5:$C$804=A19)*Sales!$B$5:$B$804)))) -> 0 | BM19: =IF(B19="","",IF(SUMPRODUCT(MAX(('Price History'!$B$5:$B$304=A19)*'Price History'!$A$5:$A$304))=0,IF(P19="","",P19),SUMPRODUCT(MAX(('Price History'!$B$5:$B$304=A19)*'Price History'!$A$5:$A$304)))) -> 0 | BN19: =IF(B19="","",IF(BM19="","",TodayDate-BM19)) -> 0 | BO19: =IF(B19="","",COUNTIFS($AV$5:$AV$304,">"&AV19)+COUNTIFS($AV$5:AV19,AV19)) -> 0 | BP19: =IF(B19="","",COUNTIFS($AW$5:$AW$304,">"&AW19)+COUNTIFS($AW$5:AW19,AW19)) -> 0 | BQ19: =IF(B19="","",COUNTIFS($BI$5:$BI$304,">"&BI19)+COUNTIFS($BI$5:BI19,BI19)) -> 0 | BR19: =IF(B19="","",COUNTIFS($AY$5:$AY$304,">"&AY19)+COUNTIFS($AY$5:AY19,AY19)) -> 0 | BS19: =IF(B19="","",IF(AH19=0,"Add - no costs entered yet",IF(AR19="","Check - no price yet",IF(AV19<0,"Loss - every sale costs you money",IF(AND(AZ19<>"",AZ19<MinimumWage),"Below - pays under minimum wage",IF(AW19<MarginWarning,"Low margin - re-price it",IF(AND(AF19<>"",K19<>"",K19+AC19>AF19),"Check - too heavy for that postage band",IF(AND(BN19<>"",BN19>PriceReviewDays),"Due - price has not been reviewed",IF(AND(BG19<>"",BG19>0.5),"Check - well above the market","OK")))))))) ) -> 0
A20: =IF(B20="","",ProductPrefix&TEXT(ROW()-4,"0000")) -> 0 | S20: =IF(B20="","",IF(C20<>"",C20,UPPER(LEFT(IF(D20="","GEN",D20),3))&"-"&TEXT(ROW()-4,"000"))) -> 0 | T20: =IF(B20="","",ROUND(SUMIFS('Material Usage'!$M$5:$M$904,'Material Usage'!$A$5:$A$904,A20)+SUMIFS(Crochet!$AD$5:$AD$84,Crochet!$A$5:$A$84,A20)+SUMIFS(Jewelry!$AF$5:$AF$84,Jewelry!$A$5:$A$84,A20)+SUMIFS(Candles!$AF$5:$AF$84,Candles!$A$5:$A$84,A20)+SUMIFS(Clothing!$AB$5:$AB$84,Clothing!$A$5:$A$84,A20)+SUMIFS(Woodworking!$AC$5:$AC$84,Woodworking!$A$5:$A$84,A20)+SUMIFS(Digital!$X$5:$X$84,Digital!$A$5:$A$84,A20),2)) -> 0 | U20: =IF(B20="","",ROUND(SUMIFS(Labor!$O$5:$O$304,Labor!$A$5:$A$304,A20)+SUMIFS(Crochet!$AG$5:$AG$84,Crochet!$A$5:$A$84,A20)+SUMIFS(Jewelry!$AI$5:$AI$84,Jewelry!$A$5:$A$84,A20)+SUMIFS(Candles!$AI$5:$AI$84,Candles!$A$5:$A$84,A20)+SUMIFS(Clothing!$AE$5:$AE$84,Clothing!$A$5:$A$84,A20)+SUMIFS(Woodworking!$AF$5:$AF$84,Woodworking!$A$5:$A$84,A20)+SUMIFS(Digital!$Z$5:$Z$84,Digital!$A$5:$A$84,A20),2)) -> 0 | V20: =IF(B20="","",ROUND(SUMIFS(Labor!$P$5:$P$304,Labor!$A$5:$A$304,A20)+SUMIFS(Crochet!$AE$5:$AE$84,Crochet!$A$5:$A$84,A20)+SUMIFS(Jewelry!$AG$5:$AG$84,Jewelry!$A$5:$A$84,A20)+SUMIFS(Candles!$AG$5:$AG$84,Candles!$A$5:$A$84,A20)+SUMIFS(Clothing!$AC$5:$AC$84,Clothing!$A$5:$A$84,A20)+SUMIFS(Woodworking!$AD$5:$AD$84,Woodworking!$A$5:$A$84,A20)+SUMIFS(Digital!$Y$5:$Y$84,Digital!$A$5:$A$84,A20),1)) -> 0 | W20: =IF(B20="","",IFERROR(INDEX(DiffTimeFactors,MATCH(G20,DiffNames,0)),1)) -> 0 | X20: =IF(B20="","",ROUND(V20*W20,1)) -> 0 | Y20: =IF(B20="","",ROUND(X20/60,3)) -> 0 | Z20: =IF(B20="","",ROUND(U20*W20,2)) -> 0 | AA20: =IF(B20="","",ROUND(SUMIFS(Labor!$Q$5:$Q$304,Labor!$A$5:$A$304,A20)+SUMIFS(Crochet!$AH$5:$AH$84,Crochet!$A$5:$A$84,A20)+SUMIFS(Jewelry!$AJ$5:$AJ$84,Jewelry!$A$5:$A$84,A20)+SUMIFS(Candles!$AJ$5:$AJ$84,Candles!$A$5:$A$84,A20)+SUMIFS(Clothing!$AF$5:$AF$84,Clothing!$A$5:$A$84,A20)+SUMIFS(Woodworking!$AH$5:$AH$84,Woodworking!$A$5:$A$84,A20)+SUMIFS(Digital!$AA$5:$AA$84,Digital!$A$5:$A$84,A20),2)) -> 0 | AB20: =IF(B20="","",ROUND(IF(I20="Budget",PackBudget,IF(I20="Standard",PackStandard,IF(I20="Gift",PackGift,IF(I20="Premium",PackPremium,DefaultPackaging)))),2)) -> 0 | AC20: =IF(B20="","",IF(I20="Budget",PackWeightBudget,IF(I20="Standard",PackWeightStandard,IF(I20="Gift",PackWeightGift,IF(I20="Premium",PackWeightPremium,0))))) -> 0 | AD20: =IF(B20="","",IFERROR(INDEX(Shipping!$M$5:$M$64,MATCH(J20,Shipping!$L$5:$L$64,0)),DefaultShipping)) -> 0 | AE20: =IF(B20="","",IFERROR(INDEX(Shipping!$F$5:$F$64,MATCH(J20,Shipping!$L$5:$L$64,0)),0)) -> 0 | AF20: =IF(B20="","",IFERROR(INDEX(Shipping!$C$5:$C$64,MATCH(J20,Shipping!$L$5:$L$64,0)),"")) -> 0 | AG20: =IF(B20="","",ROUND(MAX(0,AD20-AE20),2)) -> 0 | AH20: =IF(B20="","",ROUND(T20+Z20+AA20+AB20+AG20,2)) -> 0 | AI20: =IF(B20="","",IFERROR(INDEX(Channels!$S$5:$S$18,MATCH(IF(H20="",DefaultChannel,H20),Channels!$A$5:$A$18,0)),0)) -> 0 | AJ20: =IF(B20="","",IFERROR(INDEX(Channels!$O$5:$O$18,MATCH(IF(H20="",DefaultChannel,H20),Channels!$A$5:$A$18,0)),"No")) -> 0 | AK20: =IF(B20="","",ROUND(IFERROR(INDEX(Channels!$T$5:$T$18,MATCH(IF(H20="",DefaultChannel,H20),Channels!$A$5:$A$18,0)),0)+IF(AJ20="Yes",AE20*AI20,0),4)) -> 0 | AL20: =IF(B20="","",IF(OverheadMethod="Share of revenue",IF(RevenueTargetMonth<=0,0,OverheadMonthly/RevenueTargetMonth),0)) -> 0 | AM20: =IF(B20="","",IF(OverheadMethod="Per hour worked",ROUND(OverheadPerHour*Y20,2),IF(OR(OverheadMethod="Per unit made",OverheadMethod="Per order"),OverheadPerUnit,0))) -> 0 | AN20: =IF(B20="","",IF(N20<>"",N20,TargetRetailMargin)) -> 0 | AO20: =IF(B20="","",1-AN20-AI20-AL20) -> 0 | AP20: =IF(B20="","",IF(AO20<=0,"",(AH20+AM20+AK20)/AO20)) -> 0 | AQ20: =IF(B20="","",IF(AP20="","Check the settings",ROUND(IF(RoundingRule="None",AP20,IF(RoundingRule="Nearest 0.99",MAX(0.99,CEILING(AP20,1)-0.01),IF(RoundingRule="Nearest 0.95",MAX(0.95,CEILING(AP20,1)-0.05),IF(RoundingRule="Nearest 0.50",CEILING(AP20,0.5),IF(RoundingRule="Nearest 1",CEILING(AP20,1),IF(RoundingRule="Nearest 5",CEILING(AP20,5),IF(RoundingRule="Up to whole 1",CEILING(AP20,1),IF(RoundingRule="Up to whole 5",CEILING(AP20,5),ROUND(AP20,2))))))))),2))) -> 0 | AR20: =IF(B20="","",IF(M20<>"",M20,IF(ISNUMBER(AQ20),AQ20,""))) -> 0 | AS20: =IF(B20="","",IF(AR20="","",ROUND(AM20+AR20*AL20,2))) -> 0 | AT20: =IF(B20="","",IF(AR20="","",ROUND(AH20+AS20,2))) -> 0 | AU20: =IF(B20="","",IF(AR20="","",ROUND(AR20*AI20+AK20,2))) -> 0 | AV20: =IF(B20="","",IF(AR20="","",ROUND(AR20-AT20-AU20,2))) -> 0 | AW20: =IF(B20="","",IF(OR(AR20="",AR20=0),"",AV20/AR20)) -> 0 | AX20: =IF(B20="","",IF(OR(AT20="",AT20=0),"",AV20/AT20)) -> 0 | AY20: =IF(B20="","",IF(OR(Y20="",Y20=0,AV20=""),"",ROUND(AV20/Y20,2))) -> 0 | AZ20: =IF(B20="","",IF(OR(Y20="",Y20=0,AV20=""),"",ROUND((AV20+Z20)/Y20,2))) -> 0 | BA20: =IF(B20="","",IF(1-AI20-AL20<=0,"",ROUND((AH20+AM20+AK20)/(1-AI20-AL20),2))) -> 0 | BB20: =IF(B20="","",IF(AT20="","",ROUND(AT20*2,2))) -> 0 | BC20: =IF(B20="","",IF(AR20="","",ROUND(AR20*(1-WholesaleDiscount),2))) -> 0 | BD20: =IF(B20="","",IF(BC20="","",ROUND(BC20-AH20-AM20,2))) -> 0 | BE20: =IF(B20="","",IF(OR(BC20="",BC20=0),"",BD20/BC20)) -> 0 | BF20: =IF(B20="","",IFERROR(ROUND(AVERAGEIFS(Competitors!$F$5:$F$154,Competitors!$A$5:$A$154,A20),2),"")) -> 0 | BG20: =IF(B20="","",IF(OR(BF20="",BF20=0,AR20=""),"",AR20/BF20-1)) -> 0 | BH20: =IF(B20="","",SUMIFS(Sales!$D$5:$D$804,Sales!$C$5:$C$804,A20)) -> 0 | BI20: =IF(B20="","",ROUND(SUMIFS(Sales!$V$5:$V$804,Sales!$C$5:$C$804,A20),2)) -> 0 | BJ20: =IF(B20="","",ROUND(SUMIFS(Sales!$AG$5:$AG$804,Sales!$C$5:$C$804,A20),2)) -> 0 | BK20: =IF(B20="","",IF(OR(BI20="",BI20=0),"",BJ20/BI20)) -> 0 | BL20: =IF(B20="","",IF(SUMPRODUCT(MAX((Sales!$C$5:$C$804=A20)*Sales!$B$5:$B$804))=0,"",SUMPRODUCT(MAX((Sales!$C$5:$C$804=A20)*Sales!$B$5:$B$804)))) -> 0 | BM20: =IF(B20="","",IF(SUMPRODUCT(MAX(('Price History'!$B$5:$B$304=A20)*'Price History'!$A$5:$A$304))=0,IF(P20="","",P20),SUMPRODUCT(MAX(('Price History'!$B$5:$B$304=A20)*'Price History'!$A$5:$A$304)))) -> 0 | BN20: =IF(B20="","",IF(BM20="","",TodayDate-BM20)) -> 0 | BO20: =IF(B20="","",COUNTIFS($AV$5:$AV$304,">"&AV20)+COUNTIFS($AV$5:AV20,AV20)) -> 0 | BP20: =IF(B20="","",COUNTIFS($AW$5:$AW$304,">"&AW20)+COUNTIFS($AW$5:AW20,AW20)) -> 0 | BQ20: =IF(B20="","",COUNTIFS($BI$5:$BI$304,">"&BI20)+COUNTIFS($BI$5:BI20,BI20)) -> 0 | BR20: =IF(B20="","",COUNTIFS($AY$5:$AY$304,">"&AY20)+COUNTIFS($AY$5:AY20,AY20)) -> 0 | BS20: =IF(B20="","",IF(AH20=0,"Add - no costs entered yet",IF(AR20="","Check - no price yet",IF(AV20<0,"Loss - every sale costs you money",IF(AND(AZ20<>"",AZ20<MinimumWage),"Below - pays under minimum wage",IF(AW20<MarginWarning,"Low margin - re-price it",IF(AND(AF20<>"",K20<>"",K20+AC20>AF20),"Check - too heavy for that postage band",IF(AND(BN20<>"",BN20>PriceReviewDays),"Due - price has not been reviewed",IF(AND(BG20<>"",BG20>0.5),"Check - well above the market","OK")))))))) ) -> 0
A21: =IF(B21="","",ProductPrefix&TEXT(ROW()-4,"0000")) -> 0 | S21: =IF(B21="","",IF(C21<>"",C21,UPPER(LEFT(IF(D21="","GEN",D21),3))&"-"&TEXT(ROW()-4,"000"))) -> 0 | T21: =IF(B21="","",ROUND(SUMIFS('Material Usage'!$M$5:$M$904,'Material Usage'!$A$5:$A$904,A21)+SUMIFS(Crochet!$AD$5:$AD$84,Crochet!$A$5:$A$84,A21)+SUMIFS(Jewelry!$AF$5:$AF$84,Jewelry!$A$5:$A$84,A21)+SUMIFS(Candles!$AF$5:$AF$84,Candles!$A$5:$A$84,A21)+SUMIFS(Clothing!$AB$5:$AB$84,Clothing!$A$5:$A$84,A21)+SUMIFS(Woodworking!$AC$5:$AC$84,Woodworking!$A$5:$A$84,A21)+SUMIFS(Digital!$X$5:$X$84,Digital!$A$5:$A$84,A21),2)) -> 0 | U21: =IF(B21="","",ROUND(SUMIFS(Labor!$O$5:$O$304,Labor!$A$5:$A$304,A21)+SUMIFS(Crochet!$AG$5:$AG$84,Crochet!$A$5:$A$84,A21)+SUMIFS(Jewelry!$AI$5:$AI$84,Jewelry!$A$5:$A$84,A21)+SUMIFS(Candles!$AI$5:$AI$84,Candles!$A$5:$A$84,A21)+SUMIFS(Clothing!$AE$5:$AE$84,Clothing!$A$5:$A$84,A21)+SUMIFS(Woodworking!$AF$5:$AF$84,Woodworking!$A$5:$A$84,A21)+SUMIFS(Digital!$Z$5:$Z$84,Digital!$A$5:$A$84,A21),2)) -> 0 | V21: =IF(B21="","",ROUND(SUMIFS(Labor!$P$5:$P$304,Labor!$A$5:$A$304,A21)+SUMIFS(Crochet!$AE$5:$AE$84,Crochet!$A$5:$A$84,A21)+SUMIFS(Jewelry!$AG$5:$AG$84,Jewelry!$A$5:$A$84,A21)+SUMIFS(Candles!$AG$5:$AG$84,Candles!$A$5:$A$84,A21)+SUMIFS(Clothing!$AC$5:$AC$84,Clothing!$A$5:$A$84,A21)+SUMIFS(Woodworking!$AD$5:$AD$84,Woodworking!$A$5:$A$84,A21)+SUMIFS(Digital!$Y$5:$Y$84,Digital!$A$5:$A$84,A21),1)) -> 0 | W21: =IF(B21="","",IFERROR(INDEX(DiffTimeFactors,MATCH(G21,DiffNames,0)),1)) -> 0 | X21: =IF(B21="","",ROUND(V21*W21,1)) -> 0 | Y21: =IF(B21="","",ROUND(X21/60,3)) -> 0 | Z21: =IF(B21="","",ROUND(U21*W21,2)) -> 0 | AA21: =IF(B21="","",ROUND(SUMIFS(Labor!$Q$5:$Q$304,Labor!$A$5:$A$304,A21)+SUMIFS(Crochet!$AH$5:$AH$84,Crochet!$A$5:$A$84,A21)+SUMIFS(Jewelry!$AJ$5:$AJ$84,Jewelry!$A$5:$A$84,A21)+SUMIFS(Candles!$AJ$5:$AJ$84,Candles!$A$5:$A$84,A21)+SUMIFS(Clothing!$AF$5:$AF$84,Clothing!$A$5:$A$84,A21)+SUMIFS(Woodworking!$AH$5:$AH$84,Woodworking!$A$5:$A$84,A21)+SUMIFS(Digital!$AA$5:$AA$84,Digital!$A$5:$A$84,A21),2)) -> 0 | AB21: =IF(B21="","",ROUND(IF(I21="Budget",PackBudget,IF(I21="Standard",PackStandard,IF(I21="Gift",PackGift,IF(I21="Premium",PackPremium,DefaultPackaging)))),2)) -> 0 | AC21: =IF(B21="","",IF(I21="Budget",PackWeightBudget,IF(I21="Standard",PackWeightStandard,IF(I21="Gift",PackWeightGift,IF(I21="Premium",PackWeightPremium,0))))) -> 0 | AD21: =IF(B21="","",IFERROR(INDEX(Shipping!$M$5:$M$64,MATCH(J21,Shipping!$L$5:$L$64,0)),DefaultShipping)) -> 0 | AE21: =IF(B21="","",IFERROR(INDEX(Shipping!$F$5:$F$64,MATCH(J21,Shipping!$L$5:$L$64,0)),0)) -> 0 | AF21: =IF(B21="","",IFERROR(INDEX(Shipping!$C$5:$C$64,MATCH(J21,Shipping!$L$5:$L$64,0)),"")) -> 0 | AG21: =IF(B21="","",ROUND(MAX(0,AD21-AE21),2)) -> 0 | AH21: =IF(B21="","",ROUND(T21+Z21+AA21+AB21+AG21,2)) -> 0 | AI21: =IF(B21="","",IFERROR(INDEX(Channels!$S$5:$S$18,MATCH(IF(H21="",DefaultChannel,H21),Channels!$A$5:$A$18,0)),0)) -> 0 | AJ21: =IF(B21="","",IFERROR(INDEX(Channels!$O$5:$O$18,MATCH(IF(H21="",DefaultChannel,H21),Channels!$A$5:$A$18,0)),"No")) -> 0 | AK21: =IF(B21="","",ROUND(IFERROR(INDEX(Channels!$T$5:$T$18,MATCH(IF(H21="",DefaultChannel,H21),Channels!$A$5:$A$18,0)),0)+IF(AJ21="Yes",AE21*AI21,0),4)) -> 0 | AL21: =IF(B21="","",IF(OverheadMethod="Share of revenue",IF(RevenueTargetMonth<=0,0,OverheadMonthly/RevenueTargetMonth),0)) -> 0 | AM21: =IF(B21="","",IF(OverheadMethod="Per hour worked",ROUND(OverheadPerHour*Y21,2),IF(OR(OverheadMethod="Per unit made",OverheadMethod="Per order"),OverheadPerUnit,0))) -> 0 | AN21: =IF(B21="","",IF(N21<>"",N21,TargetRetailMargin)) -> 0 | AO21: =IF(B21="","",1-AN21-AI21-AL21) -> 0 | AP21: =IF(B21="","",IF(AO21<=0,"",(AH21+AM21+AK21)/AO21)) -> 0 | AQ21: =IF(B21="","",IF(AP21="","Check the settings",ROUND(IF(RoundingRule="None",AP21,IF(RoundingRule="Nearest 0.99",MAX(0.99,CEILING(AP21,1)-0.01),IF(RoundingRule="Nearest 0.95",MAX(0.95,CEILING(AP21,1)-0.05),IF(RoundingRule="Nearest 0.50",CEILING(AP21,0.5),IF(RoundingRule="Nearest 1",CEILING(AP21,1),IF(RoundingRule="Nearest 5",CEILING(AP21,5),IF(RoundingRule="Up to whole 1",CEILING(AP21,1),IF(RoundingRule="Up to whole 5",CEILING(AP21,5),ROUND(AP21,2))))))))),2))) -> 0 | AR21: =IF(B21="","",IF(M21<>"",M21,IF(ISNUMBER(AQ21),AQ21,""))) -> 0 | AS21: =IF(B21="","",IF(AR21="","",ROUND(AM21+AR21*AL21,2))) -> 0 | AT21: =IF(B21="","",IF(AR21="","",ROUND(AH21+AS21,2))) -> 0 | AU21: =IF(B21="","",IF(AR21="","",ROUND(AR21*AI21+AK21,2))) -> 0 | AV21: =IF(B21="","",IF(AR21="","",ROUND(AR21-AT21-AU21,2))) -> 0 | AW21: =IF(B21="","",IF(OR(AR21="",AR21=0),"",AV21/AR21)) -> 0 | AX21: =IF(B21="","",IF(OR(AT21="",AT21=0),"",AV21/AT21)) -> 0 | AY21: =IF(B21="","",IF(OR(Y21="",Y21=0,AV21=""),"",ROUND(AV21/Y21,2))) -> 0 | AZ21: =IF(B21="","",IF(OR(Y21="",Y21=0,AV21=""),"",ROUND((AV21+Z21)/Y21,2))) -> 0 | BA21: =IF(B21="","",IF(1-AI21-AL21<=0,"",ROUND((AH21+AM21+AK21)/(1-AI21-AL21),2))) -> 0 | BB21: =IF(B21="","",IF(AT21="","",ROUND(AT21*2,2))) -> 0 | BC21: =IF(B21="","",IF(AR21="","",ROUND(AR21*(1-WholesaleDiscount),2))) -> 0 | BD21: =IF(B21="","",IF(BC21="","",ROUND(BC21-AH21-AM21,2))) -> 0 | BE21: =IF(B21="","",IF(OR(BC21="",BC21=0),"",BD21/BC21)) -> 0 | BF21: =IF(B21="","",IFERROR(ROUND(AVERAGEIFS(Competitors!$F$5:$F$154,Competitors!$A$5:$A$154,A21),2),"")) -> 0 | BG21: =IF(B21="","",IF(OR(BF21="",BF21=0,AR21=""),"",AR21/BF21-1)) -> 0 | BH21: =IF(B21="","",SUMIFS(Sales!$D$5:$D$804,Sales!$C$5:$C$804,A21)) -> 0 | BI21: =IF(B21="","",ROUND(SUMIFS(Sales!$V$5:$V$804,Sales!$C$5:$C$804,A21),2)) -> 0 | BJ21: =IF(B21="","",ROUND(SUMIFS(Sales!$AG$5:$AG$804,Sales!$C$5:$C$804,A21),2)) -> 0 | BK21: =IF(B21="","",IF(OR(BI21="",BI21=0),"",BJ21/BI21)) -> 0 | BL21: =IF(B21="","",IF(SUMPRODUCT(MAX((Sales!$C$5:$C$804=A21)*Sales!$B$5:$B$804))=0,"",SUMPRODUCT(MAX((Sales!$C$5:$C$804=A21)*Sales!$B$5:$B$804)))) -> 0 | BM21: =IF(B21="","",IF(SUMPRODUCT(MAX(('Price History'!$B$5:$B$304=A21)*'Price History'!$A$5:$A$304))=0,IF(P21="","",P21),SUMPRODUCT(MAX(('Price History'!$B$5:$B$304=A21)*'Price History'!$A$5:$A$304)))) -> 0 | BN21: =IF(B21="","",IF(BM21="","",TodayDate-BM21)) -> 0 | BO21: =IF(B21="","",COUNTIFS($AV$5:$AV$304,">"&AV21)+COUNTIFS($AV$5:AV21,AV21)) -> 0 | BP21: =IF(B21="","",COUNTIFS($AW$5:$AW$304,">"&AW21)+COUNTIFS($AW$5:AW21,AW21)) -> 0 | BQ21: =IF(B21="","",COUNTIFS($BI$5:$BI$304,">"&BI21)+COUNTIFS($BI$5:BI21,BI21)) -> 0 | BR21: =IF(B21="","",COUNTIFS($AY$5:$AY$304,">"&AY21)+COUNTIFS($AY$5:AY21,AY21)) -> 0 | BS21: =IF(B21="","",IF(AH21=0,"Add - no costs entered yet",IF(AR21="","Check - no price yet",IF(AV21<0,"Loss - every sale costs you money",IF(AND(AZ21<>"",AZ21<MinimumWage),"Below - pays under minimum wage",IF(AW21<MarginWarning,"Low margin - re-price it",IF(AND(AF21<>"",K21<>"",K21+AC21>AF21),"Check - too heavy for that postage band",IF(AND(BN21<>"",BN21>PriceReviewDays),"Due - price has not been reviewed",IF(AND(BG21<>"",BG21>0.5),"Check - well above the market","OK")))))))) ) -> 0
A22: =IF(B22="","",ProductPrefix&TEXT(ROW()-4,"0000")) -> 0 | S22: =IF(B22="","",IF(C22<>"",C22,UPPER(LEFT(IF(D22="","GEN",D22),3))&"-"&TEXT(ROW()-4,"000"))) -> 0 | T22: =IF(B22="","",ROUND(SUMIFS('Material Usage'!$M$5:$M$904,'Material Usage'!$A$5:$A$904,A22)+SUMIFS(Crochet!$AD$5:$AD$84,Crochet!$A$5:$A$84,A22)+SUMIFS(Jewelry!$AF$5:$AF$84,Jewelry!$A$5:$A$84,A22)+SUMIFS(Candles!$AF$5:$AF$84,Candles!$A$5:$A$84,A22)+SUMIFS(Clothing!$AB$5:$AB$84,Clothing!$A$5:$A$84,A22)+SUMIFS(Woodworking!$AC$5:$AC$84,Woodworking!$A$5:$A$84,A22)+SUMIFS(Digital!$X$5:$X$84,Digital!$A$5:$A$84,A22),2)) -> 0 | U22: =IF(B22="","",ROUND(SUMIFS(Labor!$O$5:$O$304,Labor!$A$5:$A$304,A22)+SUMIFS(Crochet!$AG$5:$AG$84,Crochet!$A$5:$A$84,A22)+SUMIFS(Jewelry!$AI$5:$AI$84,Jewelry!$A$5:$A$84,A22)+SUMIFS(Candles!$AI$5:$AI$84,Candles!$A$5:$A$84,A22)+SUMIFS(Clothing!$AE$5:$AE$84,Clothing!$A$5:$A$84,A22)+SUMIFS(Woodworking!$AF$5:$AF$84,Woodworking!$A$5:$A$84,A22)+SUMIFS(Digital!$Z$5:$Z$84,Digital!$A$5:$A$84,A22),2)) -> 0 | V22: =IF(B22="","",ROUND(SUMIFS(Labor!$P$5:$P$304,Labor!$A$5:$A$304,A22)+SUMIFS(Crochet!$AE$5:$AE$84,Crochet!$A$5:$A$84,A22)+SUMIFS(Jewelry!$AG$5:$AG$84,Jewelry!$A$5:$A$84,A22)+SUMIFS(Candles!$AG$5:$AG$84,Candles!$A$5:$A$84,A22)+SUMIFS(Clothing!$AC$5:$AC$84,Clothing!$A$5:$A$84,A22)+SUMIFS(Woodworking!$AD$5:$AD$84,Woodworking!$A$5:$A$84,A22)+SUMIFS(Digital!$Y$5:$Y$84,Digital!$A$5:$A$84,A22),1)) -> 0 | W22: =IF(B22="","",IFERROR(INDEX(DiffTimeFactors,MATCH(G22,DiffNames,0)),1)) -> 0 | X22: =IF(B22="","",ROUND(V22*W22,1)) -> 0 | Y22: =IF(B22="","",ROUND(X22/60,3)) -> 0 | Z22: =IF(B22="","",ROUND(U22*W22,2)) -> 0 | AA22: =IF(B22="","",ROUND(SUMIFS(Labor!$Q$5:$Q$304,Labor!$A$5:$A$304,A22)+SUMIFS(Crochet!$AH$5:$AH$84,Crochet!$A$5:$A$84,A22)+SUMIFS(Jewelry!$AJ$5:$AJ$84,Jewelry!$A$5:$A$84,A22)+SUMIFS(Candles!$AJ$5:$AJ$84,Candles!$A$5:$A$84,A22)+SUMIFS(Clothing!$AF$5:$AF$84,Clothing!$A$5:$A$84,A22)+SUMIFS(Woodworking!$AH$5:$AH$84,Woodworking!$A$5:$A$84,A22)+SUMIFS(Digital!$AA$5:$AA$84,Digital!$A$5:$A$84,A22),2)) -> 0 | AB22: =IF(B22="","",ROUND(IF(I22="Budget",PackBudget,IF(I22="Standard",PackStandard,IF(I22="Gift",PackGift,IF(I22="Premium",PackPremium,DefaultPackaging)))),2)) -> 0 | AC22: =IF(B22="","",IF(I22="Budget",PackWeightBudget,IF(I22="Standard",PackWeightStandard,IF(I22="Gift",PackWeightGift,IF(I22="Premium",PackWeightPremium,0))))) -> 0 | AD22: =IF(B22="","",IFERROR(INDEX(Shipping!$M$5:$M$64,MATCH(J22,Shipping!$L$5:$L$64,0)),DefaultShipping)) -> 0 | AE22: =IF(B22="","",IFERROR(INDEX(Shipping!$F$5:$F$64,MATCH(J22,Shipping!$L$5:$L$64,0)),0)) -> 0 | AF22: =IF(B22="","",IFERROR(INDEX(Shipping!$C$5:$C$64,MATCH(J22,Shipping!$L$5:$L$64,0)),"")) -> 0 | AG22: =IF(B22="","",ROUND(MAX(0,AD22-AE22),2)) -> 0 | AH22: =IF(B22="","",ROUND(T22+Z22+AA22+AB22+AG22,2)) -> 0 | AI22: =IF(B22="","",IFERROR(INDEX(Channels!$S$5:$S$18,MATCH(IF(H22="",DefaultChannel,H22),Channels!$A$5:$A$18,0)),0)) -> 0 | AJ22: =IF(B22="","",IFERROR(INDEX(Channels!$O$5:$O$18,MATCH(IF(H22="",DefaultChannel,H22),Channels!$A$5:$A$18,0)),"No")) -> 0 | AK22: =IF(B22="","",ROUND(IFERROR(INDEX(Channels!$T$5:$T$18,MATCH(IF(H22="",DefaultChannel,H22),Channels!$A$5:$A$18,0)),0)+IF(AJ22="Yes",AE22*AI22,0),4)) -> 0 | AL22: =IF(B22="","",IF(OverheadMethod="Share of revenue",IF(RevenueTargetMonth<=0,0,OverheadMonthly/RevenueTargetMonth),0)) -> 0 | AM22: =IF(B22="","",IF(OverheadMethod="Per hour worked",ROUND(OverheadPerHour*Y22,2),IF(OR(OverheadMethod="Per unit made",OverheadMethod="Per order"),OverheadPerUnit,0))) -> 0 | AN22: =IF(B22="","",IF(N22<>"",N22,TargetRetailMargin)) -> 0 | AO22: =IF(B22="","",1-AN22-AI22-AL22) -> 0 | AP22: =IF(B22="","",IF(AO22<=0,"",(AH22+AM22+AK22)/AO22)) -> 0 | AQ22: =IF(B22="","",IF(AP22="","Check the settings",ROUND(IF(RoundingRule="None",AP22,IF(RoundingRule="Nearest 0.99",MAX(0.99,CEILING(AP22,1)-0.01),IF(RoundingRule="Nearest 0.95",MAX(0.95,CEILING(AP22,1)-0.05),IF(RoundingRule="Nearest 0.50",CEILING(AP22,0.5),IF(RoundingRule="Nearest 1",CEILING(AP22,1),IF(RoundingRule="Nearest 5",CEILING(AP22,5),IF(RoundingRule="Up to whole 1",CEILING(AP22,1),IF(RoundingRule="Up to whole 5",CEILING(AP22,5),ROUND(AP22,2))))))))),2))) -> 0 | AR22: =IF(B22="","",IF(M22<>"",M22,IF(ISNUMBER(AQ22),AQ22,""))) -> 0 | AS22: =IF(B22="","",IF(AR22="","",ROUND(AM22+AR22*AL22,2))) -> 0 | AT22: =IF(B22="","",IF(AR22="","",ROUND(AH22+AS22,2))) -> 0 | AU22: =IF(B22="","",IF(AR22="","",ROUND(AR22*AI22+AK22,2))) -> 0 | AV22: =IF(B22="","",IF(AR22="","",ROUND(AR22-AT22-AU22,2))) -> 0 | AW22: =IF(B22="","",IF(OR(AR22="",AR22=0),"",AV22/AR22)) -> 0 | AX22: =IF(B22="","",IF(OR(AT22="",AT22=0),"",AV22/AT22)) -> 0 | AY22: =IF(B22="","",IF(OR(Y22="",Y22=0,AV22=""),"",ROUND(AV22/Y22,2))) -> 0 | AZ22: =IF(B22="","",IF(OR(Y22="",Y22=0,AV22=""),"",ROUND((AV22+Z22)/Y22,2))) -> 0 | BA22: =IF(B22="","",IF(1-AI22-AL22<=0,"",ROUND((AH22+AM22+AK22)/(1-AI22-AL22),2))) -> 0 | BB22: =IF(B22="","",IF(AT22="","",ROUND(AT22*2,2))) -> 0 | BC22: =IF(B22="","",IF(AR22="","",ROUND(AR22*(1-WholesaleDiscount),2))) -> 0 | BD22: =IF(B22="","",IF(BC22="","",ROUND(BC22-AH22-AM22,2))) -> 0 | BE22: =IF(B22="","",IF(OR(BC22="",BC22=0),"",BD22/BC22)) -> 0 | BF22: =IF(B22="","",IFERROR(ROUND(AVERAGEIFS(Competitors!$F$5:$F$154,Competitors!$A$5:$A$154,A22),2),"")) -> 0 | BG22: =IF(B22="","",IF(OR(BF22="",BF22=0,AR22=""),"",AR22/BF22-1)) -> 0 | BH22: =IF(B22="","",SUMIFS(Sales!$D$5:$D$804,Sales!$C$5:$C$804,A22)) -> 0 | BI22: =IF(B22="","",ROUND(SUMIFS(Sales!$V$5:$V$804,Sales!$C$5:$C$804,A22),2)) -> 0 | BJ22: =IF(B22="","",ROUND(SUMIFS(Sales!$AG$5:$AG$804,Sales!$C$5:$C$804,A22),2)) -> 0 | BK22: =IF(B22="","",IF(OR(BI22="",BI22=0),"",BJ22/BI22)) -> 0 | BL22: =IF(B22="","",IF(SUMPRODUCT(MAX((Sales!$C$5:$C$804=A22)*Sales!$B$5:$B$804))=0,"",SUMPRODUCT(MAX((Sales!$C$5:$C$804=A22)*Sales!$B$5:$B$804)))) -> 0 | BM22: =IF(B22="","",IF(SUMPRODUCT(MAX(('Price History'!$B$5:$B$304=A22)*'Price History'!$A$5:$A$304))=0,IF(P22="","",P22),SUMPRODUCT(MAX(('Price History'!$B$5:$B$304=A22)*'Price History'!$A$5:$A$304)))) -> 0 | BN22: =IF(B22="","",IF(BM22="","",TodayDate-BM22)) -> 0 | BO22: =IF(B22="","",COUNTIFS($AV$5:$AV$304,">"&AV22)+COUNTIFS($AV$5:AV22,AV22)) -> 0 | BP22: =IF(B22="","",COUNTIFS($AW$5:$AW$304,">"&AW22)+COUNTIFS($AW$5:AW22,AW22)) -> 0 | BQ22: =IF(B22="","",COUNTIFS($BI$5:$BI$304,">"&BI22)+COUNTIFS($BI$5:BI22,BI22)) -> 0 | BR22: =IF(B22="","",COUNTIFS($AY$5:$AY$304,">"&AY22)+COUNTIFS($AY$5:AY22,AY22)) -> 0 | BS22: =IF(B22="","",IF(AH22=0,"Add - no costs entered yet",IF(AR22="","Check - no price yet",IF(AV22<0,"Loss - every sale costs you money",IF(AND(AZ22<>"",AZ22<MinimumWage),"Below - pays under minimum wage",IF(AW22<MarginWarning,"Low margin - re-price it",IF(AND(AF22<>"",K22<>"",K22+AC22>AF22),"Check - too heavy for that postage band",IF(AND(BN22<>"",BN22>PriceReviewDays),"Due - price has not been reviewed",IF(AND(BG22<>"",BG22>0.5),"Check - well above the market","OK")))))))) ) -> 0
A23: =IF(B23="","",ProductPrefix&TEXT(ROW()-4,"0000")) -> 0 | S23: =IF(B23="","",IF(C23<>"",C23,UPPER(LEFT(IF(D23="","GEN",D23),3))&"-"&TEXT(ROW()-4,"000"))) -> 0 | T23: =IF(B23="","",ROUND(SUMIFS('Material Usage'!$M$5:$M$904,'Material Usage'!$A$5:$A$904,A23)+SUMIFS(Crochet!$AD$5:$AD$84,Crochet!$A$5:$A$84,A23)+SUMIFS(Jewelry!$AF$5:$AF$84,Jewelry!$A$5:$A$84,A23)+SUMIFS(Candles!$AF$5:$AF$84,Candles!$A$5:$A$84,A23)+SUMIFS(Clothing!$AB$5:$AB$84,Clothing!$A$5:$A$84,A23)+SUMIFS(Woodworking!$AC$5:$AC$84,Woodworking!$A$5:$A$84,A23)+SUMIFS(Digital!$X$5:$X$84,Digital!$A$5:$A$84,A23),2)) -> 0 | U23: =IF(B23="","",ROUND(SUMIFS(Labor!$O$5:$O$304,Labor!$A$5:$A$304,A23)+SUMIFS(Crochet!$AG$5:$AG$84,Crochet!$A$5:$A$84,A23)+SUMIFS(Jewelry!$AI$5:$AI$84,Jewelry!$A$5:$A$84,A23)+SUMIFS(Candles!$AI$5:$AI$84,Candles!$A$5:$A$84,A23)+SUMIFS(Clothing!$AE$5:$AE$84,Clothing!$A$5:$A$84,A23)+SUMIFS(Woodworking!$AF$5:$AF$84,Woodworking!$A$5:$A$84,A23)+SUMIFS(Digital!$Z$5:$Z$84,Digital!$A$5:$A$84,A23),2)) -> 0 | V23: =IF(B23="","",ROUND(SUMIFS(Labor!$P$5:$P$304,Labor!$A$5:$A$304,A23)+SUMIFS(Crochet!$AE$5:$AE$84,Crochet!$A$5:$A$84,A23)+SUMIFS(Jewelry!$AG$5:$AG$84,Jewelry!$A$5:$A$84,A23)+SUMIFS(Candles!$AG$5:$AG$84,Candles!$A$5:$A$84,A23)+SUMIFS(Clothing!$AC$5:$AC$84,Clothing!$A$5:$A$84,A23)+SUMIFS(Woodworking!$AD$5:$AD$84,Woodworking!$A$5:$A$84,A23)+SUMIFS(Digital!$Y$5:$Y$84,Digital!$A$5:$A$84,A23),1)) -> 0 | W23: =IF(B23="","",IFERROR(INDEX(DiffTimeFactors,MATCH(G23,DiffNames,0)),1)) -> 0 | X23: =IF(B23="","",ROUND(V23*W23,1)) -> 0 | Y23: =IF(B23="","",ROUND(X23/60,3)) -> 0 | Z23: =IF(B23="","",ROUND(U23*W23,2)) -> 0 | AA23: =IF(B23="","",ROUND(SUMIFS(Labor!$Q$5:$Q$304,Labor!$A$5:$A$304,A23)+SUMIFS(Crochet!$AH$5:$AH$84,Crochet!$A$5:$A$84,A23)+SUMIFS(Jewelry!$AJ$5:$AJ$84,Jewelry!$A$5:$A$84,A23)+SUMIFS(Candles!$AJ$5:$AJ$84,Candles!$A$5:$A$84,A23)+SUMIFS(Clothing!$AF$5:$AF$84,Clothing!$A$5:$A$84,A23)+SUMIFS(Woodworking!$AH$5:$AH$84,Woodworking!$A$5:$A$84,A23)+SUMIFS(Digital!$AA$5:$AA$84,Digital!$A$5:$A$84,A23),2)) -> 0 | AB23: =IF(B23="","",ROUND(IF(I23="Budget",PackBudget,IF(I23="Standard",PackStandard,IF(I23="Gift",PackGift,IF(I23="Premium",PackPremium,DefaultPackaging)))),2)) -> 0 | AC23: =IF(B23="","",IF(I23="Budget",PackWeightBudget,IF(I23="Standard",PackWeightStandard,IF(I23="Gift",PackWeightGift,IF(I23="Premium",PackWeightPremium,0))))) -> 0 | AD23: =IF(B23="","",IFERROR(INDEX(Shipping!$M$5:$M$64,MATCH(J23,Shipping!$L$5:$L$64,0)),DefaultShipping)) -> 0 | AE23: =IF(B23="","",IFERROR(INDEX(Shipping!$F$5:$F$64,MATCH(J23,Shipping!$L$5:$L$64,0)),0)) -> 0 | AF23: =IF(B23="","",IFERROR(INDEX(Shipping!$C$5:$C$64,MATCH(J23,Shipping!$L$5:$L$64,0)),"")) -> 0 | AG23: =IF(B23="","",ROUND(MAX(0,AD23-AE23),2)) -> 0 | AH23: =IF(B23="","",ROUND(T23+Z23+AA23+AB23+AG23,2)) -> 0 | AI23: =IF(B23="","",IFERROR(INDEX(Channels!$S$5:$S$18,MATCH(IF(H23="",DefaultChannel,H23),Channels!$A$5:$A$18,0)),0)) -> 0 | AJ23: =IF(B23="","",IFERROR(INDEX(Channels!$O$5:$O$18,MATCH(IF(H23="",DefaultChannel,H23),Channels!$A$5:$A$18,0)),"No")) -> 0 | AK23: =IF(B23="","",ROUND(IFERROR(INDEX(Channels!$T$5:$T$18,MATCH(IF(H23="",DefaultChannel,H23),Channels!$A$5:$A$18,0)),0)+IF(AJ23="Yes",AE23*AI23,0),4)) -> 0 | AL23: =IF(B23="","",IF(OverheadMethod="Share of revenue",IF(RevenueTargetMonth<=0,0,OverheadMonthly/RevenueTargetMonth),0)) -> 0 | AM23: =IF(B23="","",IF(OverheadMethod="Per hour worked",ROUND(OverheadPerHour*Y23,2),IF(OR(OverheadMethod="Per unit made",OverheadMethod="Per order"),OverheadPerUnit,0))) -> 0 | AN23: =IF(B23="","",IF(N23<>"",N23,TargetRetailMargin)) -> 0 | AO23: =IF(B23="","",1-AN23-AI23-AL23) -> 0 | AP23: =IF(B23="","",IF(AO23<=0,"",(AH23+AM23+AK23)/AO23)) -> 0 | AQ23: =IF(B23="","",IF(AP23="","Check the settings",ROUND(IF(RoundingRule="None",AP23,IF(RoundingRule="Nearest 0.99",MAX(0.99,CEILING(AP23,1)-0.01),IF(RoundingRule="Nearest 0.95",MAX(0.95,CEILING(AP23,1)-0.05),IF(RoundingRule="Nearest 0.50",CEILING(AP23,0.5),IF(RoundingRule="Nearest 1",CEILING(AP23,1),IF(RoundingRule="Nearest 5",CEILING(AP23,5),IF(RoundingRule="Up to whole 1",CEILING(AP23,1),IF(RoundingRule="Up to whole 5",CEILING(AP23,5),ROUND(AP23,2))))))))),2))) -> 0 | AR23: =IF(B23="","",IF(M23<>"",M23,IF(ISNUMBER(AQ23),AQ23,""))) -> 0 | AS23: =IF(B23="","",IF(AR23="","",ROUND(AM23+AR23*AL23,2))) -> 0 | AT23: =IF(B23="","",IF(AR23="","",ROUND(AH23+AS23,2))) -> 0 | AU23: =IF(B23="","",IF(AR23="","",ROUND(AR23*AI23+AK23,2))) -> 0 | AV23: =IF(B23="","",IF(AR23="","",ROUND(AR23-AT23-AU23,2))) -> 0 | AW23: =IF(B23="","",IF(OR(AR23="",AR23=0),"",AV23/AR23)) -> 0 | AX23: =IF(B23="","",IF(OR(AT23="",AT23=0),"",AV23/AT23)) -> 0 | AY23: =IF(B23="","",IF(OR(Y23="",Y23=0,AV23=""),"",ROUND(AV23/Y23,2))) -> 0 | AZ23: =IF(B23="","",IF(OR(Y23="",Y23=0,AV23=""),"",ROUND((AV23+Z23)/Y23,2))) -> 0 | BA23: =IF(B23="","",IF(1-AI23-AL23<=0,"",ROUND((AH23+AM23+AK23)/(1-AI23-AL23),2))) -> 0 | BB23: =IF(B23="","",IF(AT23="","",ROUND(AT23*2,2))) -> 0 | BC23: =IF(B23="","",IF(AR23="","",ROUND(AR23*(1-WholesaleDiscount),2))) -> 0 | BD23: =IF(B23="","",IF(BC23="","",ROUND(BC23-AH23-AM23,2))) -> 0 | BE23: =IF(B23="","",IF(OR(BC23="",BC23=0),"",BD23/BC23)) -> 0 | BF23: =IF(B23="","",IFERROR(ROUND(AVERAGEIFS(Competitors!$F$5:$F$154,Competitors!$A$5:$A$154,A23),2),"")) -> 0 | BG23: =IF(B23="","",IF(OR(BF23="",BF23=0,AR23=""),"",AR23/BF23-1)) -> 0 | BH23: =IF(B23="","",SUMIFS(Sales!$D$5:$D$804,Sales!$C$5:$C$804,A23)) -> 0 | BI23: =IF(B23="","",ROUND(SUMIFS(Sales!$V$5:$V$804,Sales!$C$5:$C$804,A23),2)) -> 0 | BJ23: =IF(B23="","",ROUND(SUMIFS(Sales!$AG$5:$AG$804,Sales!$C$5:$C$804,A23),2)) -> 0 | BK23: =IF(B23="","",IF(OR(BI23="",BI23=0),"",BJ23/BI23)) -> 0 | BL23: =IF(B23="","",IF(SUMPRODUCT(MAX((Sales!$C$5:$C$804=A23)*Sales!$B$5:$B$804))=0,"",SUMPRODUCT(MAX((Sales!$C$5:$C$804=A23)*Sales!$B$5:$B$804)))) -> 0 | BM23: =IF(B23="","",IF(SUMPRODUCT(MAX(('Price History'!$B$5:$B$304=A23)*'Price History'!$A$5:$A$304))=0,IF(P23="","",P23),SUMPRODUCT(MAX(('Price History'!$B$5:$B$304=A23)*'Price History'!$A$5:$A$304)))) -> 0 | BN23: =IF(B23="","",IF(BM23="","",TodayDate-BM23)) -> 0 | BO23: =IF(B23="","",COUNTIFS($AV$5:$AV$304,">"&AV23)+COUNTIFS($AV$5:AV23,AV23)) -> 0 | BP23: =IF(B23="","",COUNTIFS($AW$5:$AW$304,">"&AW23)+COUNTIFS($AW$5:AW23,AW23)) -> 0 | BQ23: =IF(B23="","",COUNTIFS($BI$5:$BI$304,">"&BI23)+COUNTIFS($BI$5:BI23,BI23)) -> 0 | BR23: =IF(B23="","",COUNTIFS($AY$5:$AY$304,">"&AY23)+COUNTIFS($AY$5:AY23,AY23)) -> 0 | BS23: =IF(B23="","",IF(AH23=0,"Add - no costs entered yet",IF(AR23="","Check - no price yet",IF(AV23<0,"Loss - every sale costs you money",IF(AND(AZ23<>"",AZ23<MinimumWage),"Below - pays under minimum wage",IF(AW23<MarginWarning,"Low margin - re-price it",IF(AND(AF23<>"",K23<>"",K23+AC23>AF23),"Check - too heavy for that postage band",IF(AND(BN23<>"",BN23>PriceReviewDays),"Due - price has not been reviewed",IF(AND(BG23<>"",BG23>0.5),"Check - well above the market","OK")))))))) ) -> 0
A24: =IF(B24="","",ProductPrefix&TEXT(ROW()-4,"0000")) -> 0 | S24: =IF(B24="","",IF(C24<>"",C24,UPPER(LEFT(IF(D24="","GEN",D24),3))&"-"&TEXT(ROW()-4,"000"))) -> 0 | T24: =IF(B24="","",ROUND(SUMIFS('Material Usage'!$M$5:$M$904,'Material Usage'!$A$5:$A$904,A24)+SUMIFS(Crochet!$AD$5:$AD$84,Crochet!$A$5:$A$84,A24)+SUMIFS(Jewelry!$AF$5:$AF$84,Jewelry!$A$5:$A$84,A24)+SUMIFS(Candles!$AF$5:$AF$84,Candles!$A$5:$A$84,A24)+SUMIFS(Clothing!$AB$5:$AB$84,Clothing!$A$5:$A$84,A24)+SUMIFS(Woodworking!$AC$5:$AC$84,Woodworking!$A$5:$A$84,A24)+SUMIFS(Digital!$X$5:$X$84,Digital!$A$5:$A$84,A24),2)) -> 0 | U24: =IF(B24="","",ROUND(SUMIFS(Labor!$O$5:$O$304,Labor!$A$5:$A$304,A24)+SUMIFS(Crochet!$AG$5:$AG$84,Crochet!$A$5:$A$84,A24)+SUMIFS(Jewelry!$AI$5:$AI$84,Jewelry!$A$5:$A$84,A24)+SUMIFS(Candles!$AI$5:$AI$84,Candles!$A$5:$A$84,A24)+SUMIFS(Clothing!$AE$5:$AE$84,Clothing!$A$5:$A$84,A24)+SUMIFS(Woodworking!$AF$5:$AF$84,Woodworking!$A$5:$A$84,A24)+SUMIFS(Digital!$Z$5:$Z$84,Digital!$A$5:$A$84,A24),2)) -> 0 | V24: =IF(B24="","",ROUND(SUMIFS(Labor!$P$5:$P$304,Labor!$A$5:$A$304,A24)+SUMIFS(Crochet!$AE$5:$AE$84,Crochet!$A$5:$A$84,A24)+SUMIFS(Jewelry!$AG$5:$AG$84,Jewelry!$A$5:$A$84,A24)+SUMIFS(Candles!$AG$5:$AG$84,Candles!$A$5:$A$84,A24)+SUMIFS(Clothing!$AC$5:$AC$84,Clothing!$A$5:$A$84,A24)+SUMIFS(Woodworking!$AD$5:$AD$84,Woodworking!$A$5:$A$84,A24)+SUMIFS(Digital!$Y$5:$Y$84,Digital!$A$5:$A$84,A24),1)) -> 0 | W24: =IF(B24="","",IFERROR(INDEX(DiffTimeFactors,MATCH(G24,DiffNames,0)),1)) -> 0 | X24: =IF(B24="","",ROUND(V24*W24,1)) -> 0 | Y24: =IF(B24="","",ROUND(X24/60,3)) -> 0 | Z24: =IF(B24="","",ROUND(U24*W24,2)) -> 0 | AA24: =IF(B24="","",ROUND(SUMIFS(Labor!$Q$5:$Q$304,Labor!$A$5:$A$304,A24)+SUMIFS(Crochet!$AH$5:$AH$84,Crochet!$A$5:$A$84,A24)+SUMIFS(Jewelry!$AJ$5:$AJ$84,Jewelry!$A$5:$A$84,A24)+SUMIFS(Candles!$AJ$5:$AJ$84,Candles!$A$5:$A$84,A24)+SUMIFS(Clothing!$AF$5:$AF$84,Clothing!$A$5:$A$84,A24)+SUMIFS(Woodworking!$AH$5:$AH$84,Woodworking!$A$5:$A$84,A24)+SUMIFS(Digital!$AA$5:$AA$84,Digital!$A$5:$A$84,A24),2)) -> 0 | AB24: =IF(B24="","",ROUND(IF(I24="Budget",PackBudget,IF(I24="Standard",PackStandard,IF(I24="Gift",PackGift,IF(I24="Premium",PackPremium,DefaultPackaging)))),2)) -> 0 | AC24: =IF(B24="","",IF(I24="Budget",PackWeightBudget,IF(I24="Standard",PackWeightStandard,IF(I24="Gift",PackWeightGift,IF(I24="Premium",PackWeightPremium,0))))) -> 0 | AD24: =IF(B24="","",IFERROR(INDEX(Shipping!$M$5:$M$64,MATCH(J24,Shipping!$L$5:$L$64,0)),DefaultShipping)) -> 0 | AE24: =IF(B24="","",IFERROR(INDEX(Shipping!$F$5:$F$64,MATCH(J24,Shipping!$L$5:$L$64,0)),0)) -> 0 | AF24: =IF(B24="","",IFERROR(INDEX(Shipping!$C$5:$C$64,MATCH(J24,Shipping!$L$5:$L$64,0)),"")) -> 0 | AG24: =IF(B24="","",ROUND(MAX(0,AD24-AE24),2)) -> 0 | AH24: =IF(B24="","",ROUND(T24+Z24+AA24+AB24+AG24,2)) -> 0 | AI24: =IF(B24="","",IFERROR(INDEX(Channels!$S$5:$S$18,MATCH(IF(H24="",DefaultChannel,H24),Channels!$A$5:$A$18,0)),0)) -> 0 | AJ24: =IF(B24="","",IFERROR(INDEX(Channels!$O$5:$O$18,MATCH(IF(H24="",DefaultChannel,H24),Channels!$A$5:$A$18,0)),"No")) -> 0 | AK24: =IF(B24="","",ROUND(IFERROR(INDEX(Channels!$T$5:$T$18,MATCH(IF(H24="",DefaultChannel,H24),Channels!$A$5:$A$18,0)),0)+IF(AJ24="Yes",AE24*AI24,0),4)) -> 0 | AL24: =IF(B24="","",IF(OverheadMethod="Share of revenue",IF(RevenueTargetMonth<=0,0,OverheadMonthly/RevenueTargetMonth),0)) -> 0 | AM24: =IF(B24="","",IF(OverheadMethod="Per hour worked",ROUND(OverheadPerHour*Y24,2),IF(OR(OverheadMethod="Per unit made",OverheadMethod="Per order"),OverheadPerUnit,0))) -> 0 | AN24: =IF(B24="","",IF(N24<>"",N24,TargetRetailMargin)) -> 0 | AO24: =IF(B24="","",1-AN24-AI24-AL24) -> 0 | AP24: =IF(B24="","",IF(AO24<=0,"",(AH24+AM24+AK24)/AO24)) -> 0 | AQ24: =IF(B24="","",IF(AP24="","Check the settings",ROUND(IF(RoundingRule="None",AP24,IF(RoundingRule="Nearest 0.99",MAX(0.99,CEILING(AP24,1)-0.01),IF(RoundingRule="Nearest 0.95",MAX(0.95,CEILING(AP24,1)-0.05),IF(RoundingRule="Nearest 0.50",CEILING(AP24,0.5),IF(RoundingRule="Nearest 1",CEILING(AP24,1),IF(RoundingRule="Nearest 5",CEILING(AP24,5),IF(RoundingRule="Up to whole 1",CEILING(AP24,1),IF(RoundingRule="Up to whole 5",CEILING(AP24,5),ROUND(AP24,2))))))))),2))) -> 0 | AR24: =IF(B24="","",IF(M24<>"",M24,IF(ISNUMBER(AQ24),AQ24,""))) -> 0 | AS24: =IF(B24="","",IF(AR24="","",ROUND(AM24+AR24*AL24,2))) -> 0 | AT24: =IF(B24="","",IF(AR24="","",ROUND(AH24+AS24,2))) -> 0 | AU24: =IF(B24="","",IF(AR24="","",ROUND(AR24*AI24+AK24,2))) -> 0 | AV24: =IF(B24="","",IF(AR24="","",ROUND(AR24-AT24-AU24,2))) -> 0 | AW24: =IF(B24="","",IF(OR(AR24="",AR24=0),"",AV24/AR24)) -> 0 | AX24: =IF(B24="","",IF(OR(AT24="",AT24=0),"",AV24/AT24)) -> 0 | AY24: =IF(B24="","",IF(OR(Y24="",Y24=0,AV24=""),"",ROUND(AV24/Y24,2))) -> 0 | AZ24: =IF(B24="","",IF(OR(Y24="",Y24=0,AV24=""),"",ROUND((AV24+Z24)/Y24,2))) -> 0 | BA24: =IF(B24="","",IF(1-AI24-AL24<=0,"",ROUND((AH24+AM24+AK24)/(1-AI24-AL24),2))) -> 0 | BB24: =IF(B24="","",IF(AT24="","",ROUND(AT24*2,2))) -> 0 | BC24: =IF(B24="","",IF(AR24="","",ROUND(AR24*(1-WholesaleDiscount),2))) -> 0 | BD24: =IF(B24="","",IF(BC24="","",ROUND(BC24-AH24-AM24,2))) -> 0 | BE24: =IF(B24="","",IF(OR(BC24="",BC24=0),"",BD24/BC24)) -> 0 | BF24: =IF(B24="","",IFERROR(ROUND(AVERAGEIFS(Competitors!$F$5:$F$154,Competitors!$A$5:$A$154,A24),2),"")) -> 0 | BG24: =IF(B24="","",IF(OR(BF24="",BF24=0,AR24=""),"",AR24/BF24-1)) -> 0 | BH24: =IF(B24="","",SUMIFS(Sales!$D$5:$D$804,Sales!$C$5:$C$804,A24)) -> 0 | BI24: =IF(B24="","",ROUND(SUMIFS(Sales!$V$5:$V$804,Sales!$C$5:$C$804,A24),2)) -> 0 | BJ24: =IF(B24="","",ROUND(SUMIFS(Sales!$AG$5:$AG$804,Sales!$C$5:$C$804,A24),2)) -> 0 | BK24: =IF(B24="","",IF(OR(BI24="",BI24=0),"",BJ24/BI24)) -> 0 | BL24: =IF(B24="","",IF(SUMPRODUCT(MAX((Sales!$C$5:$C$804=A24)*Sales!$B$5:$B$804))=0,"",SUMPRODUCT(MAX((Sales!$C$5:$C$804=A24)*Sales!$B$5:$B$804)))) -> 0 | BM24: =IF(B24="","",IF(SUMPRODUCT(MAX(('Price History'!$B$5:$B$304=A24)*'Price History'!$A$5:$A$304))=0,IF(P24="","",P24),SUMPRODUCT(MAX(('Price History'!$B$5:$B$304=A24)*'Price History'!$A$5:$A$304)))) -> 0 | BN24: =IF(B24="","",IF(BM24="","",TodayDate-BM24)) -> 0 | BO24: =IF(B24="","",COUNTIFS($AV$5:$AV$304,">"&AV24)+COUNTIFS($AV$5:AV24,AV24)) -> 0 | BP24: =IF(B24="","",COUNTIFS($AW$5:$AW$304,">"&AW24)+COUNTIFS($AW$5:AW24,AW24)) -> 0 | BQ24: =IF(B24="","",COUNTIFS($BI$5:$BI$304,">"&BI24)+COUNTIFS($BI$5:BI24,BI24)) -> 0 | BR24: =IF(B24="","",COUNTIFS($AY$5:$AY$304,">"&AY24)+COUNTIFS($AY$5:AY24,AY24)) -> 0 | BS24: =IF(B24="","",IF(AH24=0,"Add - no costs entered yet",IF(AR24="","Check - no price yet",IF(AV24<0,"Loss - every sale costs you money",IF(AND(AZ24<>"",AZ24<MinimumWage),"Below - pays under minimum wage",IF(AW24<MarginWarning,"Low margin - re-price it",IF(AND(AF24<>"",K24<>"",K24+AC24>AF24),"Check - too heavy for that postage band",IF(AND(BN24<>"",BN24>PriceReviewDays),"Due - price has not been reviewed",IF(AND(BG24<>"",BG24>0.5),"Check - well above the market","OK")))))))) ) -> 0
