Workbook
Name ActiveList: Lists!$G$174:$G$185
Name AgeGroupList: Lists!$I$174:$I$187
Name AisleList: Lists!$G$59:$G$82
Name AllergenList: Lists!$C$59:$C$81
Name AnnualBudget: Settings!$D$29
Name BoughtLunch: 'Recipe Costs'!$D$11
Name BudgetLineList: Lists!$A$190:$A$206
Name CalorieTarget: Settings!$D$35
Name CarbTarget: Settings!$D$37
Name CardFactor: 'Print Recipe'!$H$6
Name CardPeople: 'Print Recipe'!$D$5
Name CardRecipe: 'Print Recipe'!$B$5
Name ContainerList: Lists!$A$85:$A$101
Name CookingMethodList: Lists!$C$31:$C$50
Name CuisineList: Lists!$A$31:$A$56
Name DashKey: Dashboard!$F$5
Name DashMonth: Dashboard!$D$5
Name DashWeek: Dashboard!$B$5
Name DefaultServings: Settings!$D$21
Name DietList: Lists!$A$59:$A$81
Name DifficultyList: Lists!$E$31:$E$41
Name DirectionList: Lists!$C$210:$C$219
Name DisposalList: Lists!$E$210:$E$222
Name EatingOutBudget: Settings!$D$30
Name EventNames: OFFSET(Events!$B$5,0,0,MAX(1,COUNTIF(Events!$B$5:$B$44,"?*")),1)
Name EventPrefix: Settings!$D$67
Name EventStatusList: Lists!$A$210:$A$223
Name EventTypeList: Lists!$C$107:$C$126
Name ExpiryWarningDays: Settings!$D$45
Name FatTarget: Settings!$D$38
Name FibreTarget: Settings!$D$39
Name FilterAllergen: 'Dietary Filters'!$D$11
Name FilterCategory: 'Dietary Filters'!$D$7
Name FilterCost: 'Dietary Filters'!$D$10
Name FilterDiet: 'Dietary Filters'!$D$6
Name FilterMethod: 'Dietary Filters'!$D$8
Name FilterTime: 'Dietary Filters'!$D$9
Name FreezerDays: Settings!$D$47
Name FrequencyList: Lists!$I$129:$I$142
Name GoalCategoryList: Lists!$E$129:$E$143
Name GoalNames: OFFSET(Goals!$B$5,0,0,MAX(1,COUNTIF(Goals!$B$5:$B$44,"?*")),1)
Name GoalStatusList: Lists!$G$129:$G$142
Name GroceryCategoryList: Lists!$E$59:$E$80
Name GroceryPrefix: Settings!$D$65
Name HomeCookedTarget: Settings!$D$53
Name HouseCook: Settings!$D$7
Name HouseEmail: Settings!$D$8
Name HouseMembers: Settings!$D$10
Name HouseName: Settings!$D$6
Name HouseNotes: Settings!$D$12
Name HouseTown: Settings!$D$9
Name IngredientIDs: OFFSET(Ingredients!$A$5,0,0,MAX(1,COUNTIF(Ingredients!$A$5:$A$304,"?*")),1)
Name IngredientNames: OFFSET(Ingredients!$B$5,0,0,MAX(1,COUNTIF(Ingredients!$B$5:$B$304,"?*")),1)
Name IngredientPrefix: Settings!$D$62
Name LeftoverDays: Settings!$D$46
Name LeftoverItems: OFFSET(Leftovers!$B$5,0,0,MAX(1,COUNTIF(Leftovers!$B$5:$B$124,"?*")),1)
Name LeftoverPrefix: Settings!$D$66
Name LeftoverStatusList: Lists!$E$107:$E$121
Name LowStockDays: Settings!$D$48
Name MainStore: Settings!$D$11

Sheet Start Here
A1: Automated Meal Planner & Grocery List Spreadsheet | J1: Novality Store | v1.0.0
A2: Plan the week, price it before you shop, and stop buying things you already own.
A3: > Start Here | C3: > Dashboard | E3: > Recipes | G3: > Week | I3: > Month | K3: > Grocery
B5: Everything in this workbook is linked. Type something once - a recipe, a price, a meal - and it turns up everywhere it is needed: the planner, the shopping list, the budget, the nutrition tracker and the alerts. Cream cells are yours to fill in; grey cells are formulas and are locked so they cannot be broken by accident.
A7: Six steps to set it up
B8: Step | C8: Where | D8: What to do
B9: 1 | C9: Settings | D9: Your household, how many you feed, the weekly budget, your shopping day and your nutrition targets. Ten minutes, and it feeds every other tab.
B10: 2 | C10: Household | D10: One row per person: portion size, diet, allergies, what they will not touch and which meals they are in for.
B11: 3 | C11: Ingredients | D11: The price book. Pack size and pack price for the thirty things you buy most. This is what prices every recipe and every shopping list, so it is the tab worth the effort.
B12: 4 | C12: Recipes + Recipe Ingredients | D12: Add a recipe, then list its ingredients one line each with a quantity and a unit. The cost, the calories and the allergens are worked out for you.
B13: 5 | C13: Pantry | D13: What is already in the cupboard, the fridge and the freezer. This is what stops the grocery list buying things you own.
B14: 6 | C14: Meal Plan | D14: Plan the week: date, meal, recipe, how many you are feeding. The Weekly Planner shows it as a week and the Grocery List builds itself.
A16: How the automatic grocery list works
B17: 1. The Meal Plan says you are cooking recipe R-0002 on Tuesday for 4 people.
B18: 2. The recipe serves 6, so everything in it is multiplied by 0.67 - that is the scaling, done for you.
B19: 3. Each ingredient line is converted to a base unit: 2 tbsp of oil becomes 30 ml, 1 kg of mince becomes 1000 g.
B20: 4. Every meal in the shopping window is added up by ingredient, so three recipes using onions make one line.
B21: 5. Whatever the Pantry says you already own is taken off.
B22: 6. What is left is rounded up to whole packs and priced from the Ingredients tab - that is your list, with a total, before you leave the house.
A24: The weekly rhythm
B25: FRIDAY (10 minutes) - look at the Pantry 'Use soon' list and the Leftovers tab, then plan next week on the Meal Plan tab.
B26: SATURDAY MORNING - open the Grocery List, tick off anything you already have, print it or take the laptop, and shop.
B27: AFTER THE SHOP (2 minutes) - log the total on the Grocery Spending tab and update the Pantry for the big items.
B28: PREP DAY - work through the Meal Prep tab: two or three jobs, not ten.
B29: DURING THE WEEK - mark meals 'Eaten' as you go and log leftovers while you are putting them in the fridge.
B30: END OF THE MONTH - read the Dashboard and the Food Waste tab, and change one thing.
A32: What is in the workbook
B33: Tab | C33: What it is for
B34: Dashboard | C34: This week at a glance - cost, meals, alerts
B35: Weekly Planner | C35: Seven days on one page, ready to print
B36: Monthly Planner | C36: The month as a calendar grid
B37: Settings | C37: Household, budget, targets, shopping window
B38: Lists | C38: Every drop-down, plus the unit conversion table
B39: Household | C39: Who eats here, portions, diets and allergies
B40: Recipes | C40: THE RECIPE BOOK - cost and nutrition worked out
B41: Recipe Ingredients | C41: What goes in each recipe. The engine room
B42: Ingredients | C42: The price book: pack sizes, prices, nutrition
B43: Meal Plan | C43: THE MAIN TAB - one row per planned meal
B44: Grocery List | C44: Builds itself from the plan, minus the pantry
... B55: Help | C55: Every question answered, including the honest limits
A57: Good to know
B58: PROTECTION - every sheet is protected so the formulas cannot be edited by accident. The password is 'premium'. Review > Unprotect Sheet if you want to change something.
B59: ADDING ROWS - every register has spare rows ready to use. Right click a row inside the list and choose Insert to add more; the formulas copy down.
B60: SORTING - use the filter arrows in the header row rather than re-sorting the sheet, so the recipe IDs keep matching the other tabs.
B61: DROP DOWNS - every list lives on the Lists tab, including the unit table. Add a unit there and it works everywhere.
B62: UNITS - weights convert to grams, volumes to millilitres, and counted things stay as 'each'. Weight and volume are deliberately kept apart because 100 ml of oil is not 100 g.
B63: GOOGLE SHEETS - File > Import works, and everything except the sheet protection carries over.
B64: YOUR CURRENCY - set the symbol on the Settings tab, or rebuild the workbook with a different currency.
A66: What a spreadsheet can and cannot do
B67: Being straight with you. This workbook does the arithmetic on the information you give it: it cannot read the barcodes in your cupboard, it cannot check tonight's shelf prices, and it will not order the shopping for you. The automatic grocery list is only as good as your ingredient lines and units - a recipe that says 'a splash of oil' cannot be added up. Nutrition comes from the numbers you copy off the packet and is a guide, not medical advice. Allergen flags and use-by dates are a second pair of eyes, not a guarantee: always read the label and trust your nose. Reminders appear on the tabs - a spreadsheet cannot push a notification to your phone. What it does do is turn a vague plan into a priced shopping list in ten minutes a week, and show you exactly where the food money goes.
B69: Automated Meal Planner & Grocery List Spreadsheet | Novality Store | version 1.0.0

Sheet Dashboard
A1: Dashboard | J1: Novality Store | v1.0.0
A2: This week, this month and the year so far - all from the numbers you have already entered.
A3: > Start Here | C3: > Dashboard | E3: > Recipes | G3: > Week | I3: > Month | K3: > Grocery
A5: Week of | B5: =WeekPick -> 0 | C5: Month | D5: =TEXT(TODAY(),"mmmm yyyy") -> 0 | E5: Month key | F5: =TEXT(TODAY(),"yyyy-mm") -> 0 | G5: Household | H5: =HouseMembers -> 0 | I5: Updated | K5: =TODAY() -> 0
A7: Meals planned this week | D7: Planned cost this week | G7: This week's shopping list | J7: Left in the weekly budget
A8: =COUNTIFS('Meal Plan'!$B$5:$B$504,">="&DashWeek,'Meal Plan'!$B$5:$B$504,"<="&DashWeek+6) -> 0 | D8: =SUMIFS('Meal Plan'!$T$5:$T$504,'Meal Plan'!$B$5:$B$504,">="&DashWeek,'Meal Plan'!$B$5:$B$504,"<="&DashWeek+6) -> 0 | G8: =SUM('Grocery List'!$O$5:$O$304) -> 0 | J8: =WeeklyBudget-SUM('Grocery List'!$O$5:$O$304) -> 0
A9: every slot with something in it | D9: at price book prices | G9: what the list adds up to | J9: green is money left
A11: Spent this month | D11: Pantry value | G11: Food wasted this month | J11: Cooked at home this week
A12: =SUMIFS('Grocery Spending'!$K$5:$K$404,'Grocery Spending'!$E$5:$E$404,DashKey) -> 0 | D12: =SUM(Pantry!$P$5:$P$304) -> 0 | G12: =SUMIFS('Food Waste'!$L$5:$L$154,'Food Waste'!$D$5:$D$154,DashKey) -> 0 | J12: =COUNTIFS('Meal Plan'!$B$5:$B$504,">="&DashWeek,'Meal Plan'!$B$5:$B$504,"<="&DashWeek+6,'Meal Plan'!$AD$5:$AD$504,"Yes") -> 0
A13: every shop, takeaway and meal out | D13: what is sitting in the cupboards | G13: target under $15 | J13: target 18 a week
A15: Needs your attention
A16: What | B16: How many | C16: What it means | D16: Where to fix it
A17: Food about to go off | B17: =COUNTIF(Pantry!$W$5:$W$304,"Use soon") -> 0 | C17: ="Use these within 5 days or they are money in the bin" -> 0 | K17: Pantry
A18: Already expired | B18: =COUNTIF(Pantry!$W$5:$W$304,"Expired") -> 0 | C18: ="Past their date - check, then bin and log them" -> 0 | K18: Pantry
A19: Leftovers waiting | B19: =SUMIFS(Leftovers!$F$5:$F$124,Leftovers!$Q$5:$Q$124,"<>Eaten",Leftovers!$Q$5:$Q$124,"<>Binned") -> 0 | C19: ="Portions in the fridge or freezer worth "&TEXT(SUMIFS(Leftovers!$M$5:$M$124,Leftovers!$Q$5:$Q$124,"<>Eaten",Leftovers!$Q$5:$Q$124,"<>Binned"),"0.00") -> 0 | K19: Leftovers
A20: Staples below par | B20: =COUNTIF(Staples!$Q$5:$Q$104,"Low stock")+COUNTIF(Staples!$Q$5:$Q$104,"Out of stock") -> 0 | C20: ="Things you said you never want to run out of" -> 0 | K20: Staples
A21: Ingredients with no price | B21: =COUNTIFS(Ingredients!$B$5:$B$304,"<>",Ingredients!$I$5:$I$304,"") -> 0 | C21: ="Until these have a price, recipes using them are under-costed" -> 0 | K21: Ingredients
A22: Recipe lines to fix | B22: =COUNTIF('Recipe Ingredients'!$AB$5:$AB$1204,"Missing*")+COUNTIF('Recipe Ingredients'!$AB$5:$AB$1204,"Check - *") -> 0 | C22: ="Unit mismatches or ingredients not in the price book - they are left out of the shopping list" -> 0 | K22: Recipe Ingredients
A23: Days with nothing planned | B23: =(COUNTIFS('Meal Plan'!$B$5:$B$504,DashWeek+0,'Meal Plan'!$F$5:$F$504,"Dinner")=0)*1+(COUNTIFS('Meal Plan'!$B$5:$B$504,DashWeek+1,'Meal Plan'!$F$5:$F$504,"Dinner")=0)*1+(COUNTIFS('Meal Plan'!$B$5:$B$504,DashWeek+2,'Meal Plan'!$F$5:$F$504,"Dinner")=0)*1+(COUNTIFS('Meal Plan'!$B$5:$B$504,DashWeek+3,'Meal Plan'!$F$5:$F$504,"Dinner")=0)*1+(COUNTIFS('Meal Plan'!$B$5:$B$504,DashWeek+4,'Meal Plan'!$F$5:$F$504,"Dinner")=0)*1+(COUNTIFS('Meal Plan'!$B$5:$B$504,DashWeek+5,'Meal Plan'!$F$5:$F$504,"Dinner")=0)*1+(COUNTIFS('Meal Plan'!$B$5:$B$504,DashWeek+6,'Meal Plan'!$F$5:$F$504,"Dinner")=0)*1 -> 0 | C23: ="Dinner slots still empty in the week you are looking at" -> 0 | K23: Meal Plan
A24: Prep jobs outstanding | B24: =COUNTIFS('Meal Prep'!$W$5:$W$124,"<>Done",'Meal Prep'!$B$5:$B$124,"<>") -> 0 | C24: ="Batch cooking you planned but have not made yet" -> 0 | K24: Meal Prep
A25: Goals behind target | B25: =COUNTIF(Goals!$K$5:$K$44,"No") -> 0 | C25: ="Worth five minutes with a cup of tea" -> 0 | K25: Goals
A27: This week's dinners
A28: Day | B28: =DashWeek+0 -> 0 | C28: =DashWeek+1 -> 0 | D28: =DashWeek+2 -> 0 | E28: =DashWeek+3 -> 0 | F28: =DashWeek+4 -> 0 | G28: =DashWeek+5 -> 0 | H28: =DashWeek+6 -> 0 | I28: Week
A29: Dinner | B29: =IFERROR(INDEX('Meal Plan'!$H$5:$H$504,MATCH(TEXT(B$28,"yyyy-mm-dd")&"|Dinner",'Meal Plan'!$AE$5:$AE$504,0)),"-") -> 0 | C29: =IFERROR(INDEX('Meal Plan'!$H$5:$H$504,MATCH(TEXT(C$28,"yyyy-mm-dd")&"|Dinner",'Meal Plan'!$AE$5:$AE$504,0)),"-") -> 0 | D29: =IFERROR(INDEX('Meal Plan'!$H$5:$H$504,MATCH(TEXT(D$28,"yyyy-mm-dd")&"|Dinner",'Meal Plan'!$AE$5:$AE$504,0)),"-") -> 0 | E29: =IFERROR(INDEX('Meal Plan'!$H$5:$H$504,MATCH(TEXT(E$28,"yyyy-mm-dd")&"|Dinner",'Meal Plan'!$AE$5:$AE$504,0)),"-") -> 0 | F29: =IFERROR(INDEX('Meal Plan'!$H$5:$H$504,MATCH(TEXT(F$28,"yyyy-mm-dd")&"|Dinner",'Meal Plan'!$AE$5:$AE$504,0)),"-") -> 0 | G29: =IFERROR(INDEX('Meal Plan'!$H$5:$H$504,MATCH(TEXT(G$28,"yyyy-mm-dd")&"|Dinner",'Meal Plan'!$AE$5:$AE$504,0)),"-") -> 0 | H29: =IFERROR(INDEX('Meal Plan'!$H$5:$H$504,MATCH(TEXT(H$28,"yyyy-mm-dd")&"|Dinner",'Meal Plan'!$AE$5:$AE$504,0)),"-") -> 0 | I29: =COUNTIFS('Meal Plan'!$B$5:$B$504,">="&DashWeek,'Meal Plan'!$B$5:$B$504,"<="&DashWeek+6,'Meal Plan'!$F$5:$F$504,"Dinner") -> 0
A30: Cost | B30: =IF(B$28="","",SUMIFS('Meal Plan'!$T$5:$T$504,'Meal Plan'!$B$5:$B$504,B$28)) -> 0 | C30: =IF(C$28="","",SUMIFS('Meal Plan'!$T$5:$T$504,'Meal Plan'!$B$5:$B$504,C$28)) -> 0 | D30: =IF(D$28="","",SUMIFS('Meal Plan'!$T$5:$T$504,'Meal Plan'!$B$5:$B$504,D$28)) -> 0 | E30: =IF(E$28="","",SUMIFS('Meal Plan'!$T$5:$T$504,'Meal Plan'!$B$5:$B$504,E$28)) -> 0 | F30: =IF(F$28="","",SUMIFS('Meal Plan'!$T$5:$T$504,'Meal Plan'!$B$5:$B$504,F$28)) -> 0 | G30: =IF(G$28="","",SUMIFS('Meal Plan'!$T$5:$T$504,'Meal Plan'!$B$5:$B$504,G$28)) -> 0 | H30: =IF(H$28="","",SUMIFS('Meal Plan'!$T$5:$T$504,'Meal Plan'!$B$5:$B$504,H$28)) -> 0 | I30: =SUMIFS('Meal Plan'!$T$5:$T$504,'Meal Plan'!$B$5:$B$504,">="&DashWeek,'Meal Plan'!$B$5:$B$504,"<="&DashWeek+6) -> 0
A32: The year so far
A33: Month | B33: Grocery spend | C33: Budget | D33: Difference | E33: Eating out | F33: Food waste | G33: Meals cooked at home | H33: Trend
A34: =TEXT(DATE(PlanYear,1,1),"mmm") -> 0 | B34: =SUMIFS('Grocery Spending'!$K$5:$K$404,'Grocery Spending'!$E$5:$E$404,TEXT(DATE(PlanYear,1,1),"yyyy-mm")) -> 0 | C34: =MonthlyBudget -> 0 | D34: =MonthlyBudget-SUMIFS('Grocery Spending'!$K$5:$K$404,'Grocery Spending'!$E$5:$E$404,TEXT(DATE(PlanYear,1,1),"yyyy-mm")) -> 0 | E34: =SUMIFS('Grocery Spending'!$K$5:$K$404,'Grocery Spending'!$E$5:$E$404,TEXT(DATE(PlanYear,1,1),"yyyy-mm"),'Grocery Spending'!$G$5:$G$404,"Eating out")+SUMIFS('Grocery Spending'!$K$5:$K$404,'Grocery Spending'!$E$5:$E$404,TEXT(DATE(PlanYear,1,1),"yyyy-mm"),'Grocery Spending'!$G$5:$G$404,"Takeaway") -> 0 | F34: =SUMIFS('Food Waste'!$L$5:$L$154,'Food Waste'!$D$5:$D$154,TEXT(DATE(PlanYear,1,1),"yyyy-mm")) -> 0 | G34: =COUNTIFS('Meal Plan'!$E$5:$E$504,TEXT(DATE(PlanYear,1,1),"yyyy-mm"),'Meal Plan'!$AD$5:$AD$504,"Yes") -> 0
A35: =TEXT(DATE(PlanYear,2,1),"mmm") -> 0 | B35: =SUMIFS('Grocery Spending'!$K$5:$K$404,'Grocery Spending'!$E$5:$E$404,TEXT(DATE(PlanYear,2,1),"yyyy-mm")) -> 0 | C35: =MonthlyBudget -> 0 | D35: =MonthlyBudget-SUMIFS('Grocery Spending'!$K$5:$K$404,'Grocery Spending'!$E$5:$E$404,TEXT(DATE(PlanYear,2,1),"yyyy-mm")) -> 0 | E35: =SUMIFS('Grocery Spending'!$K$5:$K$404,'Grocery Spending'!$E$5:$E$404,TEXT(DATE(PlanYear,2,1),"yyyy-mm"),'Grocery Spending'!$G$5:$G$404,"Eating out")+SUMIFS('Grocery Spending'!$K$5:$K$404,'Grocery Spending'!$E$5:$E$404,TEXT(DATE(PlanYear,2,1),"yyyy-mm"),'Grocery Spending'!$G$5:$G$404,"Takeaway") -> 0 | F35: =SUMIFS('Food Waste'!$L$5:$L$154,'Food Waste'!$D$5:$D$154,TEXT(DATE(PlanYear,2,1),"yyyy-mm")) -> 0 | G35: =COUNTIFS('Meal Plan'!$E$5:$E$504,TEXT(DATE(PlanYear,2,1),"yyyy-mm"),'Meal Plan'!$AD$5:$AD$504,"Yes") -> 0
A36: =TEXT(DATE(PlanYear,3,1),"mmm") -> 0 | B36: =SUMIFS('Grocery Spending'!$K$5:$K$404,'Grocery Spending'!$E$5:$E$404,TEXT(DATE(PlanYear,3,1),"yyyy-mm")) -> 0 | C36: =MonthlyBudget -> 0 | D36: =MonthlyBudget-SUMIFS('Grocery Spending'!$K$5:$K$404,'Grocery Spending'!$E$5:$E$404,TEXT(DATE(PlanYear,3,1),"yyyy-mm")) -> 0 | E36: =SUMIFS('Grocery Spending'!$K$5:$K$404,'Grocery Spending'!$E$5:$E$404,TEXT(DATE(PlanYear,3,1),"yyyy-mm"),'Grocery Spending'!$G$5:$G$404,"Eating out")+SUMIFS('Grocery Spending'!$K$5:$K$404,'Grocery Spending'!$E$5:$E$404,TEXT(DATE(PlanYear,3,1),"yyyy-mm"),'Grocery Spending'!$G$5:$G$404,"Takeaway") -> 0 | F36: =SUMIFS('Food Waste'!$L$5:$L$154,'Food Waste'!$D$5:$D$154,TEXT(DATE(PlanYear,3,1),"yyyy-mm")) -> 0 | G36: =COUNTIFS('Meal Plan'!$E$5:$E$504,TEXT(DATE(PlanYear,3,1),"yyyy-mm"),'Meal Plan'!$AD$5:$AD$504,"Yes") -> 0
A37: =TEXT(DATE(PlanYear,4,1),"mmm") -> 0 | B37: =SUMIFS('Grocery Spending'!$K$5:$K$404,'Grocery Spending'!$E$5:$E$404,TEXT(DATE(PlanYear,4,1),"yyyy-mm")) -> 0 | C37: =MonthlyBudget -> 0 | D37: =MonthlyBudget-SUMIFS('Grocery Spending'!$K$5:$K$404,'Grocery Spending'!$E$5:$E$404,TEXT(DATE(PlanYear,4,1),"yyyy-mm")) -> 0 | E37: =SUMIFS('Grocery Spending'!$K$5:$K$404,'Grocery Spending'!$E$5:$E$404,TEXT(DATE(PlanYear,4,1),"yyyy-mm"),'Grocery Spending'!$G$5:$G$404,"Eating out")+SUMIFS('Grocery Spending'!$K$5:$K$404,'Grocery Spending'!$E$5:$E$404,TEXT(DATE(PlanYear,4,1),"yyyy-mm"),'Grocery Spending'!$G$5:$G$404,"Takeaway") -> 0 | F37: =SUMIFS('Food Waste'!$L$5:$L$154,'Food Waste'!$D$5:$D$154,TEXT(DATE(PlanYear,4,1),"yyyy-mm")) -> 0 | G37: =COUNTIFS('Meal Plan'!$E$5:$E$504,TEXT(DATE(PlanYear,4,1),"yyyy-mm"),'Meal Plan'!$AD$5:$AD$504,"Yes") -> 0
A38: =TEXT(DATE(PlanYear,5,1),"mmm") -> 0 | B38: =SUMIFS('Grocery Spending'!$K$5:$K$404,'Grocery Spending'!$E$5:$E$404,TEXT(DATE(PlanYear,5,1),"yyyy-mm")) -> 0 | C38: =MonthlyBudget -> 0 | D38: =MonthlyBudget-SUMIFS('Grocery Spending'!$K$5:$K$404,'Grocery Spending'!$E$5:$E$404,TEXT(DATE(PlanYear,5,1),"yyyy-mm")) -> 0 | E38: =SUMIFS('Grocery Spending'!$K$5:$K$404,'Grocery Spending'!$E$5:$E$404,TEXT(DATE(PlanYear,5,1),"yyyy-mm"),'Grocery Spending'!$G$5:$G$404,"Eating out")+SUMIFS('Grocery Spending'!$K$5:$K$404,'Grocery Spending'!$E$5:$E$404,TEXT(DATE(PlanYear,5,1),"yyyy-mm"),'Grocery Spending'!$G$5:$G$404,"Takeaway") -> 0 | F38: =SUMIFS('Food Waste'!$L$5:$L$154,'Food Waste'!$D$5:$D$154,TEXT(DATE(PlanYear,5,1),"yyyy-mm")) -> 0 | G38: =COUNTIFS('Meal Plan'!$E$5:$E$504,TEXT(DATE(PlanYear,5,1),"yyyy-mm"),'Meal Plan'!$AD$5:$AD$504,"Yes") -> 0
A39: =TEXT(DATE(PlanYear,6,1),"mmm") -> 0 | B39: =SUMIFS('Grocery Spending'!$K$5:$K$404,'Grocery Spending'!$E$5:$E$404,TEXT(DATE(PlanYear,6,1),"yyyy-mm")) -> 0 | C39: =MonthlyBudget -> 0 | D39: =MonthlyBudget-SUMIFS('Grocery Spending'!$K$5:$K$404,'Grocery Spending'!$E$5:$E$404,TEXT(DATE(PlanYear,6,1),"yyyy-mm")) -> 0 | E39: =SUMIFS('Grocery Spending'!$K$5:$K$404,'Grocery Spending'!$E$5:$E$404,TEXT(DATE(PlanYear,6,1),"yyyy-mm"),'Grocery Spending'!$G$5:$G$404,"Eating out")+SUMIFS('Grocery Spending'!$K$5:$K$404,'Grocery Spending'!$E$5:$E$404,TEXT(DATE(PlanYear,6,1),"yyyy-mm"),'Grocery Spending'!$G$5:$G$404,"Takeaway") -> 0 | F39: =SUMIFS('Food Waste'!$L$5:$L$154,'Food Waste'!$D$5:$D$154,TEXT(DATE(PlanYear,6,1),"yyyy-mm")) -> 0 | G39: =COUNTIFS('Meal Plan'!$E$5:$E$504,TEXT(DATE(PlanYear,6,1),"yyyy-mm"),'Meal Plan'!$AD$5:$AD$504,"Yes") -> 0
A40: =TEXT(DATE(PlanYear,7,1),"mmm") -> 0 | B40: =SUMIFS('Grocery Spending'!$K$5:$K$404,'Grocery Spending'!$E$5:$E$404,TEXT(DATE(PlanYear,7,1),"yyyy-mm")) -> 0 | C40: =MonthlyBudget -> 0 | D40: =MonthlyBudget-SUMIFS('Grocery Spending'!$K$5:$K$404,'Grocery Spending'!$E$5:$E$404,TEXT(DATE(PlanYear,7,1),"yyyy-mm")) -> 0 | E40: =SUMIFS('Grocery Spending'!$K$5:$K$404,'Grocery Spending'!$E$5:$E$404,TEXT(DATE(PlanYear,7,1),"yyyy-mm"),'Grocery Spending'!$G$5:$G$404,"Eating out")+SUMIFS('Grocery Spending'!$K$5:$K$404,'Grocery Spending'!$E$5:$E$404,TEXT(DATE(PlanYear,7,1),"yyyy-mm"),'Grocery Spending'!$G$5:$G$404,"Takeaway") -> 0 | F40: =SUMIFS('Food Waste'!$L$5:$L$154,'Food Waste'!$D$5:$D$154,TEXT(DATE(PlanYear,7,1),"yyyy-mm")) -> 0 | G40: =COUNTIFS('Meal Plan'!$E$5:$E$504,TEXT(DATE(PlanYear,7,1),"yyyy-mm"),'Meal Plan'!$AD$5:$AD$504,"Yes") -> 0
A41: =TEXT(DATE(PlanYear,8,1),"mmm") -> 0 | B41: =SUMIFS('Grocery Spending'!$K$5:$K$404,'Grocery Spending'!$E$5:$E$404,TEXT(DATE(PlanYear,8,1),"yyyy-mm")) -> 0 | C41: =MonthlyBudget -> 0 | D41: =MonthlyBudget-SUMIFS('Grocery Spending'!$K$5:$K$404,'Grocery Spending'!$E$5:$E$404,TEXT(DATE(PlanYear,8,1),"yyyy-mm")) -> 0 | E41: =SUMIFS('Grocery Spending'!$K$5:$K$404,'Grocery Spending'!$E$5:$E$404,TEXT(DATE(PlanYear,8,1),"yyyy-mm"),'Grocery Spending'!$G$5:$G$404,"Eating out")+SUMIFS('Grocery Spending'!$K$5:$K$404,'Grocery Spending'!$E$5:$E$404,TEXT(DATE(PlanYear,8,1),"yyyy-mm"),'Grocery Spending'!$G$5:$G$404,"Takeaway") -> 0 | F41: =SUMIFS('Food Waste'!$L$5:$L$154,'Food Waste'!$D$5:$D$154,TEXT(DATE(PlanYear,8,1),"yyyy-mm")) -> 0 | G41: =COUNTIFS('Meal Plan'!$E$5:$E$504,TEXT(DATE(PlanYear,8,1),"yyyy-mm"),'Meal Plan'!$AD$5:$AD$504,"Yes") -> 0
A42: =TEXT(DATE(PlanYear,9,1),"mmm") -> 0 | B42: =SUMIFS('Grocery Spending'!$K$5:$K$404,'Grocery Spending'!$E$5:$E$404,TEXT(DATE(PlanYear,9,1),"yyyy-mm")) -> 0 | C42: =MonthlyBudget -> 0 | D42: =MonthlyBudget-SUMIFS('Grocery Spending'!$K$5:$K$404,'Grocery Spending'!$E$5:$E$404,TEXT(DATE(PlanYear,9,1),"yyyy-mm")) -> 0 | E42: =SUMIFS('Grocery Spending'!$K$5:$K$404,'Grocery Spending'!$E$5:$E$404,TEXT(DATE(PlanYear,9,1),"yyyy-mm"),'Grocery Spending'!$G$5:$G$404,"Eating out")+SUMIFS('Grocery Spending'!$K$5:$K$404,'Grocery Spending'!$E$5:$E$404,TEXT(DATE(PlanYear,9,1),"yyyy-mm"),'Grocery Spending'!$G$5:$G$404,"Takeaway") -> 0 | F42: =SUMIFS('Food Waste'!$L$5:$L$154,'Food Waste'!$D$5:$D$154,TEXT(DATE(PlanYear,9,1),"yyyy-mm")) -> 0 | G42: =COUNTIFS('Meal Plan'!$E$5:$E$504,TEXT(DATE(PlanYear,9,1),"yyyy-mm"),'Meal Plan'!$AD$5:$AD$504,"Yes") -> 0
A43: =TEXT(DATE(PlanYear,10,1),"mmm") -> 0 | B43: =SUMIFS('Grocery Spending'!$K$5:$K$404,'Grocery Spending'!$E$5:$E$404,TEXT(DATE(PlanYear,10,1),"yyyy-mm")) -> 0 | C43: =MonthlyBudget -> 0 | D43: =MonthlyBudget-SUMIFS('Grocery Spending'!$K$5:$K$404,'Grocery Spending'!$E$5:$E$404,TEXT(DATE(PlanYear,10,1),"yyyy-mm")) -> 0 | E43: =SUMIFS('Grocery Spending'!$K$5:$K$404,'Grocery Spending'!$E$5:$E$404,TEXT(DATE(PlanYear,10,1),"yyyy-mm"),'Grocery Spending'!$G$5:$G$404,"Eating out")+SUMIFS('Grocery Spending'!$K$5:$K$404,'Grocery Spending'!$E$5:$E$404,TEXT(DATE(PlanYear,10,1),"yyyy-mm"),'Grocery Spending'!$G$5:$G$404,"Takeaway") -> 0 | F43: =SUMIFS('Food Waste'!$L$5:$L$154,'Food Waste'!$D$5:$D$154,TEXT(DATE(PlanYear,10,1),"yyyy-mm")) -> 0 | G43: =COUNTIFS('Meal Plan'!$E$5:$E$504,TEXT(DATE(PlanYear,10,1),"yyyy-mm"),'Meal Plan'!$AD$5:$AD$504,"Yes") -> 0
A44: =TEXT(DATE(PlanYear,11,1),"mmm") -> 0 | B44: =SUMIFS('Grocery Spending'!$K$5:$K$404,'Grocery Spending'!$E$5:$E$404,TEXT(DATE(PlanYear,11,1),"yyyy-mm")) -> 0 | C44: =MonthlyBudget -> 0 | D44: =MonthlyBudget-SUMIFS('Grocery Spending'!$K$5:$K$404,'Grocery Spending'!$E$5:$E$404,TEXT(DATE(PlanYear,11,1),"yyyy-mm")) -> 0 | E44: =SUMIFS('Grocery Spending'!$K$5:$K$404,'Grocery Spending'!$E$5:$E$404,TEXT(DATE(PlanYear,11,1),"yyyy-mm"),'Grocery Spending'!$G$5:$G$404,"Eating out")+SUMIFS('Grocery Spending'!$K$5:$K$404,'Grocery Spending'!$E$5:$E$404,TEXT(DATE(PlanYear,11,1),"yyyy-mm"),'Grocery Spending'!$G$5:$G$404,"Takeaway") -> 0 | F44: =SUMIFS('Food Waste'!$L$5:$L$154,'Food Waste'!$D$5:$D$154,TEXT(DATE(PlanYear,11,1),"yyyy-mm")) -> 0 | G44: =COUNTIFS('Meal Plan'!$E$5:$E$504,TEXT(DATE(PlanYear,11,1),"yyyy-mm"),'Meal Plan'!$AD$5:$AD$504,"Yes") -> 0
A45: =TEXT(DATE(PlanYear,12,1),"mmm") -> 0 | B45: =SUMIFS('Grocery Spending'!$K$5:$K$404,'Grocery Spending'!$E$5:$E$404,TEXT(DATE(PlanYear,12,1),"yyyy-mm")) -> 0 | C45: =MonthlyBudget -> 0 | D45: =MonthlyBudget-SUMIFS('Grocery Spending'!$K$5:$K$404,'Grocery Spending'!$E$5:$E$404,TEXT(DATE(PlanYear,12,1),"yyyy-mm")) -> 0 | E45: =SUMIFS('Grocery Spending'!$K$5:$K$404,'Grocery Spending'!$E$5:$E$404,TEXT(DATE(PlanYear,12,1),"yyyy-mm"),'Grocery Spending'!$G$5:$G$404,"Eating out")+SUMIFS('Grocery Spending'!$K$5:$K$404,'Grocery Spending'!$E$5:$E$404,TEXT(DATE(PlanYear,12,1),"yyyy-mm"),'Grocery Spending'!$G$5:$G$404,"Takeaway") -> 0 | F45: =SUMIFS('Food Waste'!$L$5:$L$154,'Food Waste'!$D$5:$D$154,TEXT(DATE(PlanYear,12,1),"yyyy-mm")) -> 0 | G45: =COUNTIFS('Meal Plan'!$E$5:$E$504,TEXT(DATE(PlanYear,12,1),"yyyy-mm"),'Meal Plan'!$AD$5:$AD$504,"Yes") -> 0
A47: Spend, waste and home cooking by month. The little charts on the right are, top to bottom: grocery spend, food waste, meals cooked at home.
A49: The year in one line
A50: Spent on food | B50: Food budget | C50: Difference | D50: Wasted | E50: Waste as a share | F50: Meals cooked at home | G50: Recipes in the book | H50: Pantry value
A51: =SUM('Grocery Spending'!$K$5:$K$404) -> 0 | B51: =AnnualBudget -> 0 | C51: =AnnualBudget-SUM('Grocery Spending'!$K$5:$K$404) -> 0 | D51: =SUM('Food Waste'!$L$5:$L$154) -> 0 | E51: =IFERROR(SUM('Food Waste'!$L$5:$L$154)/SUM('Grocery Spending'!$K$5:$K$404),"") -> 0 | F51: =COUNTIF('Meal Plan'!$AD$5:$AD$504,"Yes") -> 0 | G51: =COUNTIF(Recipes!$B$5:$B$204,"<>") -> 0 | H51: =SUM(Pantry!$P$5:$P$304) -> 0
A53: Everything on this page is live. If a number looks wrong, the fix is always on the tab named in the 'Where to fix it' column - never here.

Sheet Weekly Planner
A1: Weekly Meal Planner | G1: Novality Store | v1.0.0
A2: One week at a glance - what you are eating, what it costs and what still needs cooking.
A3: > Start Here | C3: > Dashboard | E3: > Recipes | G3: > Week
A5: Week starting | B5: 46300 | C5: Week number | D5: =WEEKNUM(WeekPick,IF(WeekStart="Sunday",1,2)) -> 0 | E5: People | F5: =DefaultServings -> 0 | G5: Weekly budget | H5: =WeeklyBudget -> 0
A6: Change the date above to any Monday - every box on the page follows it. Meals themselves are added on the Meal Plan tab; this page is the view, not the entry form.
A7: Meal | B7: =WeekPick+0 -> 0 | C7: =WeekPick+1 -> 0 | D7: =WeekPick+2 -> 0 | E7: =WeekPick+3 -> 0 | F7: =WeekPick+4 -> 0 | G7: =WeekPick+5 -> 0 | H7: =WeekPick+6 -> 0 | I7: Week total
A8: Breakfast | B8: =IF(B$7="","",IFERROR(INDEX('Meal Plan'!$H$5:$H$504,MATCH(TEXT(B$7,"yyyy-mm-dd")&"|"&"Breakfast",'Meal Plan'!$AE$5:$AE$504,0)),"")) -> 0 | C8: =IF(C$7="","",IFERROR(INDEX('Meal Plan'!$H$5:$H$504,MATCH(TEXT(C$7,"yyyy-mm-dd")&"|"&"Breakfast",'Meal Plan'!$AE$5:$AE$504,0)),"")) -> 0 | D8: =IF(D$7="","",IFERROR(INDEX('Meal Plan'!$H$5:$H$504,MATCH(TEXT(D$7,"yyyy-mm-dd")&"|"&"Breakfast",'Meal Plan'!$AE$5:$AE$504,0)),"")) -> 0 | E8: =IF(E$7="","",IFERROR(INDEX('Meal Plan'!$H$5:$H$504,MATCH(TEXT(E$7,"yyyy-mm-dd")&"|"&"Breakfast",'Meal Plan'!$AE$5:$AE$504,0)),"")) -> 0 | F8: =IF(F$7="","",IFERROR(INDEX('Meal Plan'!$H$5:$H$504,MATCH(TEXT(F$7,"yyyy-mm-dd")&"|"&"Breakfast",'Meal Plan'!$AE$5:$AE$504,0)),"")) -> 0 | G8: =IF(G$7="","",IFERROR(INDEX('Meal Plan'!$H$5:$H$504,MATCH(TEXT(G$7,"yyyy-mm-dd")&"|"&"Breakfast",'Meal Plan'!$AE$5:$AE$504,0)),"")) -> 0 | H8: =IF(H$7="","",IFERROR(INDEX('Meal Plan'!$H$5:$H$504,MATCH(TEXT(H$7,"yyyy-mm-dd")&"|"&"Breakfast",'Meal Plan'!$AE$5:$AE$504,0)),"")) -> 0 | I8: =COUNTIFS('Meal Plan'!$B$5:$B$504,">="&WeekPick,'Meal Plan'!$B$5:$B$504,"<="&WeekPick+6,'Meal Plan'!$F$5:$F$504,"Breakfast") -> 0
A9: Morning snack | B9: =IF(B$7="","",IFERROR(INDEX('Meal Plan'!$H$5:$H$504,MATCH(TEXT(B$7,"yyyy-mm-dd")&"|"&"Morning snack",'Meal Plan'!$AE$5:$AE$504,0)),"")) -> 0 | C9: =IF(C$7="","",IFERROR(INDEX('Meal Plan'!$H$5:$H$504,MATCH(TEXT(C$7,"yyyy-mm-dd")&"|"&"Morning snack",'Meal Plan'!$AE$5:$AE$504,0)),"")) -> 0 | D9: =IF(D$7="","",IFERROR(INDEX('Meal Plan'!$H$5:$H$504,MATCH(TEXT(D$7,"yyyy-mm-dd")&"|"&"Morning snack",'Meal Plan'!$AE$5:$AE$504,0)),"")) -> 0 | E9: =IF(E$7="","",IFERROR(INDEX('Meal Plan'!$H$5:$H$504,MATCH(TEXT(E$7,"yyyy-mm-dd")&"|"&"Morning snack",'Meal Plan'!$AE$5:$AE$504,0)),"")) -> 0 | F9: =IF(F$7="","",IFERROR(INDEX('Meal Plan'!$H$5:$H$504,MATCH(TEXT(F$7,"yyyy-mm-dd")&"|"&"Morning snack",'Meal Plan'!$AE$5:$AE$504,0)),"")) -> 0 | G9: =IF(G$7="","",IFERROR(INDEX('Meal Plan'!$H$5:$H$504,MATCH(TEXT(G$7,"yyyy-mm-dd")&"|"&"Morning snack",'Meal Plan'!$AE$5:$AE$504,0)),"")) -> 0 | H9: =IF(H$7="","",IFERROR(INDEX('Meal Plan'!$H$5:$H$504,MATCH(TEXT(H$7,"yyyy-mm-dd")&"|"&"Morning snack",'Meal Plan'!$AE$5:$AE$504,0)),"")) -> 0 | I9: =COUNTIFS('Meal Plan'!$B$5:$B$504,">="&WeekPick,'Meal Plan'!$B$5:$B$504,"<="&WeekPick+6,'Meal Plan'!$F$5:$F$504,"Morning snack") -> 0
A10: Lunch | B10: =IF(B$7="","",IFERROR(INDEX('Meal Plan'!$H$5:$H$504,MATCH(TEXT(B$7,"yyyy-mm-dd")&"|"&"Lunch",'Meal Plan'!$AE$5:$AE$504,0)),"")) -> 0 | C10: =IF(C$7="","",IFERROR(INDEX('Meal Plan'!$H$5:$H$504,MATCH(TEXT(C$7,"yyyy-mm-dd")&"|"&"Lunch",'Meal Plan'!$AE$5:$AE$504,0)),"")) -> 0 | D10: =IF(D$7="","",IFERROR(INDEX('Meal Plan'!$H$5:$H$504,MATCH(TEXT(D$7,"yyyy-mm-dd")&"|"&"Lunch",'Meal Plan'!$AE$5:$AE$504,0)),"")) -> 0 | E10: =IF(E$7="","",IFERROR(INDEX('Meal Plan'!$H$5:$H$504,MATCH(TEXT(E$7,"yyyy-mm-dd")&"|"&"Lunch",'Meal Plan'!$AE$5:$AE$504,0)),"")) -> 0 | F10: =IF(F$7="","",IFERROR(INDEX('Meal Plan'!$H$5:$H$504,MATCH(TEXT(F$7,"yyyy-mm-dd")&"|"&"Lunch",'Meal Plan'!$AE$5:$AE$504,0)),"")) -> 0 | G10: =IF(G$7="","",IFERROR(INDEX('Meal Plan'!$H$5:$H$504,MATCH(TEXT(G$7,"yyyy-mm-dd")&"|"&"Lunch",'Meal Plan'!$AE$5:$AE$504,0)),"")) -> 0 | H10: =IF(H$7="","",IFERROR(INDEX('Meal Plan'!$H$5:$H$504,MATCH(TEXT(H$7,"yyyy-mm-dd")&"|"&"Lunch",'Meal Plan'!$AE$5:$AE$504,0)),"")) -> 0 | I10: =COUNTIFS('Meal Plan'!$B$5:$B$504,">="&WeekPick,'Meal Plan'!$B$5:$B$504,"<="&WeekPick+6,'Meal Plan'!$F$5:$F$504,"Lunch") -> 0
A11: Afternoon snack | B11: =IF(B$7="","",IFERROR(INDEX('Meal Plan'!$H$5:$H$504,MATCH(TEXT(B$7,"yyyy-mm-dd")&"|"&"Afternoon snack",'Meal Plan'!$AE$5:$AE$504,0)),"")) -> 0 | C11: =IF(C$7="","",IFERROR(INDEX('Meal Plan'!$H$5:$H$504,MATCH(TEXT(C$7,"yyyy-mm-dd")&"|"&"Afternoon snack",'Meal Plan'!$AE$5:$AE$504,0)),"")) -> 0 | D11: =IF(D$7="","",IFERROR(INDEX('Meal Plan'!$H$5:$H$504,MATCH(TEXT(D$7,"yyyy-mm-dd")&"|"&"Afternoon snack",'Meal Plan'!$AE$5:$AE$504,0)),"")) -> 0 | E11: =IF(E$7="","",IFERROR(INDEX('Meal Plan'!$H$5:$H$504,MATCH(TEXT(E$7,"yyyy-mm-dd")&"|"&"Afternoon snack",'Meal Plan'!$AE$5:$AE$504,0)),"")) -> 0 | F11: =IF(F$7="","",IFERROR(INDEX('Meal Plan'!$H$5:$H$504,MATCH(TEXT(F$7,"yyyy-mm-dd")&"|"&"Afternoon snack",'Meal Plan'!$AE$5:$AE$504,0)),"")) -> 0 | G11: =IF(G$7="","",IFERROR(INDEX('Meal Plan'!$H$5:$H$504,MATCH(TEXT(G$7,"yyyy-mm-dd")&"|"&"Afternoon snack",'Meal Plan'!$AE$5:$AE$504,0)),"")) -> 0 | H11: =IF(H$7="","",IFERROR(INDEX('Meal Plan'!$H$5:$H$504,MATCH(TEXT(H$7,"yyyy-mm-dd")&"|"&"Afternoon snack",'Meal Plan'!$AE$5:$AE$504,0)),"")) -> 0 | I11: =COUNTIFS('Meal Plan'!$B$5:$B$504,">="&WeekPick,'Meal Plan'!$B$5:$B$504,"<="&WeekPick+6,'Meal Plan'!$F$5:$F$504,"Afternoon snack") -> 0
A12: Dinner | B12: =IF(B$7="","",IFERROR(INDEX('Meal Plan'!$H$5:$H$504,MATCH(TEXT(B$7,"yyyy-mm-dd")&"|"&"Dinner",'Meal Plan'!$AE$5:$AE$504,0)),"")) -> 0 | C12: =IF(C$7="","",IFERROR(INDEX('Meal Plan'!$H$5:$H$504,MATCH(TEXT(C$7,"yyyy-mm-dd")&"|"&"Dinner",'Meal Plan'!$AE$5:$AE$504,0)),"")) -> 0 | D12: =IF(D$7="","",IFERROR(INDEX('Meal Plan'!$H$5:$H$504,MATCH(TEXT(D$7,"yyyy-mm-dd")&"|"&"Dinner",'Meal Plan'!$AE$5:$AE$504,0)),"")) -> 0 | E12: =IF(E$7="","",IFERROR(INDEX('Meal Plan'!$H$5:$H$504,MATCH(TEXT(E$7,"yyyy-mm-dd")&"|"&"Dinner",'Meal Plan'!$AE$5:$AE$504,0)),"")) -> 0 | F12: =IF(F$7="","",IFERROR(INDEX('Meal Plan'!$H$5:$H$504,MATCH(TEXT(F$7,"yyyy-mm-dd")&"|"&"Dinner",'Meal Plan'!$AE$5:$AE$504,0)),"")) -> 0 | G12: =IF(G$7="","",IFERROR(INDEX('Meal Plan'!$H$5:$H$504,MATCH(TEXT(G$7,"yyyy-mm-dd")&"|"&"Dinner",'Meal Plan'!$AE$5:$AE$504,0)),"")) -> 0 | H12: =IF(H$7="","",IFERROR(INDEX('Meal Plan'!$H$5:$H$504,MATCH(TEXT(H$7,"yyyy-mm-dd")&"|"&"Dinner",'Meal Plan'!$AE$5:$AE$504,0)),"")) -> 0 | I12: =COUNTIFS('Meal Plan'!$B$5:$B$504,">="&WeekPick,'Meal Plan'!$B$5:$B$504,"<="&WeekPick+6,'Meal Plan'!$F$5:$F$504,"Dinner") -> 0
A13: Evening snack | B13: =IF(B$7="","",IFERROR(INDEX('Meal Plan'!$H$5:$H$504,MATCH(TEXT(B$7,"yyyy-mm-dd")&"|"&"Evening snack",'Meal Plan'!$AE$5:$AE$504,0)),"")) -> 0 | C13: =IF(C$7="","",IFERROR(INDEX('Meal Plan'!$H$5:$H$504,MATCH(TEXT(C$7,"yyyy-mm-dd")&"|"&"Evening snack",'Meal Plan'!$AE$5:$AE$504,0)),"")) -> 0 | D13: =IF(D$7="","",IFERROR(INDEX('Meal Plan'!$H$5:$H$504,MATCH(TEXT(D$7,"yyyy-mm-dd")&"|"&"Evening snack",'Meal Plan'!$AE$5:$AE$504,0)),"")) -> 0 | E13: =IF(E$7="","",IFERROR(INDEX('Meal Plan'!$H$5:$H$504,MATCH(TEXT(E$7,"yyyy-mm-dd")&"|"&"Evening snack",'Meal Plan'!$AE$5:$AE$504,0)),"")) -> 0 | F13: =IF(F$7="","",IFERROR(INDEX('Meal Plan'!$H$5:$H$504,MATCH(TEXT(F$7,"yyyy-mm-dd")&"|"&"Evening snack",'Meal Plan'!$AE$5:$AE$504,0)),"")) -> 0 | G13: =IF(G$7="","",IFERROR(INDEX('Meal Plan'!$H$5:$H$504,MATCH(TEXT(G$7,"yyyy-mm-dd")&"|"&"Evening snack",'Meal Plan'!$AE$5:$AE$504,0)),"")) -> 0 | H13: =IF(H$7="","",IFERROR(INDEX('Meal Plan'!$H$5:$H$504,MATCH(TEXT(H$7,"yyyy-mm-dd")&"|"&"Evening snack",'Meal Plan'!$AE$5:$AE$504,0)),"")) -> 0 | I13: =COUNTIFS('Meal Plan'!$B$5:$B$504,">="&WeekPick,'Meal Plan'!$B$5:$B$504,"<="&WeekPick+6,'Meal Plan'!$F$5:$F$504,"Evening snack") -> 0
A14: Dessert | B14: =IF(B$7="","",IFERROR(INDEX('Meal Plan'!$H$5:$H$504,MATCH(TEXT(B$7,"yyyy-mm-dd")&"|"&"Dessert",'Meal Plan'!$AE$5:$AE$504,0)),"")) -> 0 | C14: =IF(C$7="","",IFERROR(INDEX('Meal Plan'!$H$5:$H$504,MATCH(TEXT(C$7,"yyyy-mm-dd")&"|"&"Dessert",'Meal Plan'!$AE$5:$AE$504,0)),"")) -> 0 | D14: =IF(D$7="","",IFERROR(INDEX('Meal Plan'!$H$5:$H$504,MATCH(TEXT(D$7,"yyyy-mm-dd")&"|"&"Dessert",'Meal Plan'!$AE$5:$AE$504,0)),"")) -> 0 | E14: =IF(E$7="","",IFERROR(INDEX('Meal Plan'!$H$5:$H$504,MATCH(TEXT(E$7,"yyyy-mm-dd")&"|"&"Dessert",'Meal Plan'!$AE$5:$AE$504,0)),"")) -> 0 | F14: =IF(F$7="","",IFERROR(INDEX('Meal Plan'!$H$5:$H$504,MATCH(TEXT(F$7,"yyyy-mm-dd")&"|"&"Dessert",'Meal Plan'!$AE$5:$AE$504,0)),"")) -> 0 | G14: =IF(G$7="","",IFERROR(INDEX('Meal Plan'!$H$5:$H$504,MATCH(TEXT(G$7,"yyyy-mm-dd")&"|"&"Dessert",'Meal Plan'!$AE$5:$AE$504,0)),"")) -> 0 | H14: =IF(H$7="","",IFERROR(INDEX('Meal Plan'!$H$5:$H$504,MATCH(TEXT(H$7,"yyyy-mm-dd")&"|"&"Dessert",'Meal Plan'!$AE$5:$AE$504,0)),"")) -> 0 | I14: =COUNTIFS('Meal Plan'!$B$5:$B$504,">="&WeekPick,'Meal Plan'!$B$5:$B$504,"<="&WeekPick+6,'Meal Plan'!$F$5:$F$504,"Dessert") -> 0
A15: Cost of the day | B15: =IF(B$7="","",SUMIFS('Meal Plan'!$T$5:$T$504,'Meal Plan'!$B$5:$B$504,B$7)) -> 0 | C15: =IF(C$7="","",SUMIFS('Meal Plan'!$T$5:$T$504,'Meal Plan'!$B$5:$B$504,C$7)) -> 0 | D15: =IF(D$7="","",SUMIFS('Meal Plan'!$T$5:$T$504,'Meal Plan'!$B$5:$B$504,D$7)) -> 0 | E15: =IF(E$7="","",SUMIFS('Meal Plan'!$T$5:$T$504,'Meal Plan'!$B$5:$B$504,E$7)) -> 0 | F15: =IF(F$7="","",SUMIFS('Meal Plan'!$T$5:$T$504,'Meal Plan'!$B$5:$B$504,F$7)) -> 0 | G15: =IF(G$7="","",SUMIFS('Meal Plan'!$T$5:$T$504,'Meal Plan'!$B$5:$B$504,G$7)) -> 0 | H15: =IF(H$7="","",SUMIFS('Meal Plan'!$T$5:$T$504,'Meal Plan'!$B$5:$B$504,H$7)) -> 0 | I15: =SUMIFS('Meal Plan'!$T$5:$T$504,'Meal Plan'!$B$5:$B$504,">="&WeekPick,'Meal Plan'!$B$5:$B$504,"<="&WeekPick+6) -> 0
A16: Calories a head | B16: =IF(B$7="","",IFERROR(SUMIFS('Meal Plan'!$AA$5:$AA$504,'Meal Plan'!$B$5:$B$504,B$7)/DefaultServings,"")) -> 0 | C16: =IF(C$7="","",IFERROR(SUMIFS('Meal Plan'!$AA$5:$AA$504,'Meal Plan'!$B$5:$B$504,C$7)/DefaultServings,"")) -> 0 | D16: =IF(D$7="","",IFERROR(SUMIFS('Meal Plan'!$AA$5:$AA$504,'Meal Plan'!$B$5:$B$504,D$7)/DefaultServings,"")) -> 0 | E16: =IF(E$7="","",IFERROR(SUMIFS('Meal Plan'!$AA$5:$AA$504,'Meal Plan'!$B$5:$B$504,E$7)/DefaultServings,"")) -> 0 | F16: =IF(F$7="","",IFERROR(SUMIFS('Meal Plan'!$AA$5:$AA$504,'Meal Plan'!$B$5:$B$504,F$7)/DefaultServings,"")) -> 0 | G16: =IF(G$7="","",IFERROR(SUMIFS('Meal Plan'!$AA$5:$AA$504,'Meal Plan'!$B$5:$B$504,G$7)/DefaultServings,"")) -> 0 | H16: =IF(H$7="","",IFERROR(SUMIFS('Meal Plan'!$AA$5:$AA$504,'Meal Plan'!$B$5:$B$504,H$7)/DefaultServings,"")) -> 0 | I16: =IFERROR(SUMIFS('Meal Plan'!$AA$5:$AA$504,'Meal Plan'!$B$5:$B$504,">="&WeekPick,'Meal Plan'!$B$5:$B$504,"<="&WeekPick+6)/(DefaultServings*7),"") -> 0
A17: Who is cooking | B17: =IF(B$7="","",IFERROR(INDEX('Meal Plan'!$O$5:$O$504,MATCH(TEXT(B$7,"yyyy-mm-dd")&"|"&"Dinner",'Meal Plan'!$AE$5:$AE$504,0)),"")) -> 0 | C17: =IF(C$7="","",IFERROR(INDEX('Meal Plan'!$O$5:$O$504,MATCH(TEXT(C$7,"yyyy-mm-dd")&"|"&"Dinner",'Meal Plan'!$AE$5:$AE$504,0)),"")) -> 0 | D17: =IF(D$7="","",IFERROR(INDEX('Meal Plan'!$O$5:$O$504,MATCH(TEXT(D$7,"yyyy-mm-dd")&"|"&"Dinner",'Meal Plan'!$AE$5:$AE$504,0)),"")) -> 0 | E17: =IF(E$7="","",IFERROR(INDEX('Meal Plan'!$O$5:$O$504,MATCH(TEXT(E$7,"yyyy-mm-dd")&"|"&"Dinner",'Meal Plan'!$AE$5:$AE$504,0)),"")) -> 0 | F17: =IF(F$7="","",IFERROR(INDEX('Meal Plan'!$O$5:$O$504,MATCH(TEXT(F$7,"yyyy-mm-dd")&"|"&"Dinner",'Meal Plan'!$AE$5:$AE$504,0)),"")) -> 0 | G17: =IF(G$7="","",IFERROR(INDEX('Meal Plan'!$O$5:$O$504,MATCH(TEXT(G$7,"yyyy-mm-dd")&"|"&"Dinner",'Meal Plan'!$AE$5:$AE$504,0)),"")) -> 0 | H17: =IF(H$7="","",IFERROR(INDEX('Meal Plan'!$O$5:$O$504,MATCH(TEXT(H$7,"yyyy-mm-dd")&"|"&"Dinner",'Meal Plan'!$AE$5:$AE$504,0)),"")) -> 0 | I17: =COUNTIFS('Meal Plan'!$B$5:$B$504,">="&WeekPick,'Meal Plan'!$B$5:$B$504,"<="&WeekPick+6,'Meal Plan'!$O$5:$O$504,"<>") -> 0
A19: This week in numbers
A20: Meals planned | C20: Planned food cost | E20: Against the budget | G20: Cooked at home
A21: =COUNTIFS('Meal Plan'!$B$5:$B$504,">="&WeekPick,'Meal Plan'!$B$5:$B$504,"<="&WeekPick+6) -> 0 | C21: =SUMIFS('Meal Plan'!$T$5:$T$504,'Meal Plan'!$B$5:$B$504,">="&WeekPick,'Meal Plan'!$B$5:$B$504,"<="&WeekPick+6) -> 0 | E21: =WeeklyBudget-SUMIFS('Meal Plan'!$T$5:$T$504,'Meal Plan'!$B$5:$B$504,">="&WeekPick,'Meal Plan'!$B$5:$B$504,"<="&WeekPick+6) -> 0 | G21: =COUNTIFS('Meal Plan'!$B$5:$B$504,">="&WeekPick,'Meal Plan'!$B$5:$B$504,"<="&WeekPick+6,'Meal Plan'!$AD$5:$AD$504,"Yes") -> 0
A22: every slot with something in it | C22: recipes only - the shop may differ | E22: green is money left | G22: target 18 a week
A24: Before the week starts
A25: Job | B25: Where it stands | C25: Detail
A26: Shopping list built | B26: =IF(COUNTIF('Grocery List'!$B$5:$B$304,"<>")=0,"Nothing on it","Ready") -> 0 | C26: ="The list covers "&TEXT(ShopFrom,"d mmm")&" to "&TEXT(ShopTo,"d mmm")&" - "&COUNTIF('Grocery List'!$B$5:$B$304,"<>")&" items, about "&TEXT(SUM('Grocery List'!$O$5:$O$304),"0.00") -> 0
A27: Shopping done | B27: =IF(COUNTIF('Grocery List'!$V$5:$V$304,"Yes")=0,"Not started",IF(COUNTIFS('Grocery List'!$I$5:$I$304,">0",'Grocery List'!$V$5:$V$304,"<>Yes")=0,"Done","In progress")) -> 0 | C27: =COUNTIF('Grocery List'!$V$5:$V$304,"Yes")&" of "&COUNTIFS('Grocery List'!$I$5:$I$304,">0")&" items ticked off" -> 0
A28: Prep jobs for this week | B28: =IF(COUNTIFS('Meal Prep'!$C$5:$C$124,">="&WeekPick,'Meal Prep'!$C$5:$C$124,"<="&WeekPick+6)=0,"None planned",IF(COUNTIFS('Meal Prep'!$C$5:$C$124,">="&WeekPick,'Meal Prep'!$C$5:$C$124,"<="&WeekPick+6,'Meal Prep'!$W$5:$W$124,"<>Done")=0,"Done","To do")) -> 0 | C28: =COUNTIFS('Meal Prep'!$C$5:$C$124,">="&WeekPick,'Meal Prep'!$C$5:$C$124,"<="&WeekPick+6)&" job(s) on the prep day" -> 0
A29: Leftovers to eat first | B29: =IF(COUNTIFS(Leftovers!$Q$5:$Q$124,"<>Eaten",Leftovers!$Q$5:$Q$124,"<>Binned")=0,"None","Use soon") -> 0 | C29: =SUMIFS(Leftovers!$F$5:$F$124,Leftovers!$Q$5:$Q$124,"<>Eaten",Leftovers!$Q$5:$Q$124,"<>Binned")&" portion(s) in the fridge or freezer" -> 0
A30: Food about to go off | B30: =IF(COUNTIF(Pantry!$W$5:$W$304,"Use soon")=0,"All good","Use soon") -> 0 | C30: =COUNTIF(Pantry!$W$5:$W$304,"Use soon")&" pantry item(s) within "&ExpiryWarningDays&" days of their date" -> 0
A32: Printing: this page is set to one page wide. Print it on a Sunday, stick it on the fridge and the week looks after itself.

Sheet Monthly Planner
A1: Monthly Meal Planner | E1: Novality Store | v1.0.0
A2: The whole month on one page - dinners, lunches and what each day costs. Print it and pin it up.
A3: > Start Here | C3: > Dashboard | E3: > Recipes
A5: Month | B5: October | C5: First day | D5: =DATE(PlanYear,MAX(1,IFERROR(MATCH(PlanMonthName,MonthList,0),MONTH(TODAY()))),1) -> 0 | E5: Meals planned | F5: =COUNTIFS('Meal Plan'!$B$5:$B$504,">="&PlanMonthStart,'Meal Plan'!$B$5:$B$504,"<="&EOMONTH(PlanMonthStart,0)) -> 0 | G5: =SUMIFS('Meal Plan'!$T$5:$T$504,'Meal Plan'!$B$5:$B$504,">="&PlanMonthStart,'Meal Plan'!$B$5:$B$504,"<="&EOMONTH(PlanMonthStart,0)) -> 0
A6: Each box shows the dinner in bold type, then the lunch, then what the day costs. Empty boxes are days with nothing planned - the gaps are the point.
A7: =TEXT(PlanMonthStart-MOD(WEEKDAY(PlanMonthStart,IF(WeekStart="Sunday",1,2))-1,7)+0,"dddd") -> 0 | B7: =TEXT(PlanMonthStart-MOD(WEEKDAY(PlanMonthStart,IF(WeekStart="Sunday",1,2))-1,7)+1,"dddd") -> 0 | C7: =TEXT(PlanMonthStart-MOD(WEEKDAY(PlanMonthStart,IF(WeekStart="Sunday",1,2))-1,7)+2,"dddd") -> 0 | D7: =TEXT(PlanMonthStart-MOD(WEEKDAY(PlanMonthStart,IF(WeekStart="Sunday",1,2))-1,7)+3,"dddd") -> 0 | E7: =TEXT(PlanMonthStart-MOD(WEEKDAY(PlanMonthStart,IF(WeekStart="Sunday",1,2))-1,7)+4,"dddd") -> 0 | F7: =TEXT(PlanMonthStart-MOD(WEEKDAY(PlanMonthStart,IF(WeekStart="Sunday",1,2))-1,7)+5,"dddd") -> 0 | G7: =TEXT(PlanMonthStart-MOD(WEEKDAY(PlanMonthStart,IF(WeekStart="Sunday",1,2))-1,7)+6,"dddd") -> 0
A8: =PlanMonthStart-MOD(WEEKDAY(PlanMonthStart,IF(WeekStart="Sunday",1,2))-1,7)+0 -> 0 | B8: =PlanMonthStart-MOD(WEEKDAY(PlanMonthStart,IF(WeekStart="Sunday",1,2))-1,7)+1 -> 0 | C8: =PlanMonthStart-MOD(WEEKDAY(PlanMonthStart,IF(WeekStart="Sunday",1,2))-1,7)+2 -> 0 | D8: =PlanMonthStart-MOD(WEEKDAY(PlanMonthStart,IF(WeekStart="Sunday",1,2))-1,7)+3 -> 0 | E8: =PlanMonthStart-MOD(WEEKDAY(PlanMonthStart,IF(WeekStart="Sunday",1,2))-1,7)+4 -> 0 | F8: =PlanMonthStart-MOD(WEEKDAY(PlanMonthStart,IF(WeekStart="Sunday",1,2))-1,7)+5 -> 0 | G8: =PlanMonthStart-MOD(WEEKDAY(PlanMonthStart,IF(WeekStart="Sunday",1,2))-1,7)+6 -> 0
A9: =IF(A$8="","",IFERROR(INDEX('Meal Plan'!$H$5:$H$504,MATCH(TEXT(A$8,"yyyy-mm-dd")&"|"&"Dinner",'Meal Plan'!$AE$5:$AE$504,0)),"")) -> 0 | B9: =IF(B$8="","",IFERROR(INDEX('Meal Plan'!$H$5:$H$504,MATCH(TEXT(B$8,"yyyy-mm-dd")&"|"&"Dinner",'Meal Plan'!$AE$5:$AE$504,0)),"")) -> 0 | C9: =IF(C$8="","",IFERROR(INDEX('Meal Plan'!$H$5:$H$504,MATCH(TEXT(C$8,"yyyy-mm-dd")&"|"&"Dinner",'Meal Plan'!$AE$5:$AE$504,0)),"")) -> 0 | D9: =IF(D$8="","",IFERROR(INDEX('Meal Plan'!$H$5:$H$504,MATCH(TEXT(D$8,"yyyy-mm-dd")&"|"&"Dinner",'Meal Plan'!$AE$5:$AE$504,0)),"")) -> 0 | E9: =IF(E$8="","",IFERROR(INDEX('Meal Plan'!$H$5:$H$504,MATCH(TEXT(E$8,"yyyy-mm-dd")&"|"&"Dinner",'Meal Plan'!$AE$5:$AE$504,0)),"")) -> 0 | F9: =IF(F$8="","",IFERROR(INDEX('Meal Plan'!$H$5:$H$504,MATCH(TEXT(F$8,"yyyy-mm-dd")&"|"&"Dinner",'Meal Plan'!$AE$5:$AE$504,0)),"")) -> 0 | G9: =IF(G$8="","",IFERROR(INDEX('Meal Plan'!$H$5:$H$504,MATCH(TEXT(G$8,"yyyy-mm-dd")&"|"&"Dinner",'Meal Plan'!$AE$5:$AE$504,0)),"")) -> 0
A10: =IF(A$8="","",IFERROR(INDEX('Meal Plan'!$H$5:$H$504,MATCH(TEXT(A$8,"yyyy-mm-dd")&"|"&"Lunch",'Meal Plan'!$AE$5:$AE$504,0)),"")) -> 0 | B10: =IF(B$8="","",IFERROR(INDEX('Meal Plan'!$H$5:$H$504,MATCH(TEXT(B$8,"yyyy-mm-dd")&"|"&"Lunch",'Meal Plan'!$AE$5:$AE$504,0)),"")) -> 0 | C10: =IF(C$8="","",IFERROR(INDEX('Meal Plan'!$H$5:$H$504,MATCH(TEXT(C$8,"yyyy-mm-dd")&"|"&"Lunch",'Meal Plan'!$AE$5:$AE$504,0)),"")) -> 0 | D10: =IF(D$8="","",IFERROR(INDEX('Meal Plan'!$H$5:$H$504,MATCH(TEXT(D$8,"yyyy-mm-dd")&"|"&"Lunch",'Meal Plan'!$AE$5:$AE$504,0)),"")) -> 0 | E10: =IF(E$8="","",IFERROR(INDEX('Meal Plan'!$H$5:$H$504,MATCH(TEXT(E$8,"yyyy-mm-dd")&"|"&"Lunch",'Meal Plan'!$AE$5:$AE$504,0)),"")) -> 0 | F10: =IF(F$8="","",IFERROR(INDEX('Meal Plan'!$H$5:$H$504,MATCH(TEXT(F$8,"yyyy-mm-dd")&"|"&"Lunch",'Meal Plan'!$AE$5:$AE$504,0)),"")) -> 0 | G10: =IF(G$8="","",IFERROR(INDEX('Meal Plan'!$H$5:$H$504,MATCH(TEXT(G$8,"yyyy-mm-dd")&"|"&"Lunch",'Meal Plan'!$AE$5:$AE$504,0)),"")) -> 0
A11: =IF(A$8="","",IF(SUMIFS('Meal Plan'!$T$5:$T$504,'Meal Plan'!$B$5:$B$504,A$8)=0,"",SUMIFS('Meal Plan'!$T$5:$T$504,'Meal Plan'!$B$5:$B$504,A$8))) -> 0 | B11: =IF(B$8="","",IF(SUMIFS('Meal Plan'!$T$5:$T$504,'Meal Plan'!$B$5:$B$504,B$8)=0,"",SUMIFS('Meal Plan'!$T$5:$T$504,'Meal Plan'!$B$5:$B$504,B$8))) -> 0 | C11: =IF(C$8="","",IF(SUMIFS('Meal Plan'!$T$5:$T$504,'Meal Plan'!$B$5:$B$504,C$8)=0,"",SUMIFS('Meal Plan'!$T$5:$T$504,'Meal Plan'!$B$5:$B$504,C$8))) -> 0 | D11: =IF(D$8="","",IF(SUMIFS('Meal Plan'!$T$5:$T$504,'Meal Plan'!$B$5:$B$504,D$8)=0,"",SUMIFS('Meal Plan'!$T$5:$T$504,'Meal Plan'!$B$5:$B$504,D$8))) -> 0 | E11: =IF(E$8="","",IF(SUMIFS('Meal Plan'!$T$5:$T$504,'Meal Plan'!$B$5:$B$504,E$8)=0,"",SUMIFS('Meal Plan'!$T$5:$T$504,'Meal Plan'!$B$5:$B$504,E$8))) -> 0 | F11: =IF(F$8="","",IF(SUMIFS('Meal Plan'!$T$5:$T$504,'Meal Plan'!$B$5:$B$504,F$8)=0,"",SUMIFS('Meal Plan'!$T$5:$T$504,'Meal Plan'!$B$5:$B$504,F$8))) -> 0 | G11: =IF(G$8="","",IF(SUMIFS('Meal Plan'!$T$5:$T$504,'Meal Plan'!$B$5:$B$504,G$8)=0,"",SUMIFS('Meal Plan'!$T$5:$T$504,'Meal Plan'!$B$5:$B$504,G$8))) -> 0
A12: =PlanMonthStart-MOD(WEEKDAY(PlanMonthStart,IF(WeekStart="Sunday",1,2))-1,7)+7 -> 0 | B12: =PlanMonthStart-MOD(WEEKDAY(PlanMonthStart,IF(WeekStart="Sunday",1,2))-1,7)+8 -> 0 | C12: =PlanMonthStart-MOD(WEEKDAY(PlanMonthStart,IF(WeekStart="Sunday",1,2))-1,7)+9 -> 0 | D12: =PlanMonthStart-MOD(WEEKDAY(PlanMonthStart,IF(WeekStart="Sunday",1,2))-1,7)+10 -> 0 | E12: =PlanMonthStart-MOD(WEEKDAY(PlanMonthStart,IF(WeekStart="Sunday",1,2))-1,7)+11 -> 0 | F12: =PlanMonthStart-MOD(WEEKDAY(PlanMonthStart,IF(WeekStart="Sunday",1,2))-1,7)+12 -> 0 | G12: =PlanMonthStart-MOD(WEEKDAY(PlanMonthStart,IF(WeekStart="Sunday",1,2))-1,7)+13 -> 0
A13: =IF(A$12="","",IFERROR(INDEX('Meal Plan'!$H$5:$H$504,MATCH(TEXT(A$12,"yyyy-mm-dd")&"|"&"Dinner",'Meal Plan'!$AE$5:$AE$504,0)),"")) -> 0 | B13: =IF(B$12="","",IFERROR(INDEX('Meal Plan'!$H$5:$H$504,MATCH(TEXT(B$12,"yyyy-mm-dd")&"|"&"Dinner",'Meal Plan'!$AE$5:$AE$504,0)),"")) -> 0 | C13: =IF(C$12="","",IFERROR(INDEX('Meal Plan'!$H$5:$H$504,MATCH(TEXT(C$12,"yyyy-mm-dd")&"|"&"Dinner",'Meal Plan'!$AE$5:$AE$504,0)),"")) -> 0 | D13: =IF(D$12="","",IFERROR(INDEX('Meal Plan'!$H$5:$H$504,MATCH(TEXT(D$12,"yyyy-mm-dd")&"|"&"Dinner",'Meal Plan'!$AE$5:$AE$504,0)),"")) -> 0 | E13: =IF(E$12="","",IFERROR(INDEX('Meal Plan'!$H$5:$H$504,MATCH(TEXT(E$12,"yyyy-mm-dd")&"|"&"Dinner",'Meal Plan'!$AE$5:$AE$504,0)),"")) -> 0 | F13: =IF(F$12="","",IFERROR(INDEX('Meal Plan'!$H$5:$H$504,MATCH(TEXT(F$12,"yyyy-mm-dd")&"|"&"Dinner",'Meal Plan'!$AE$5:$AE$504,0)),"")) -> 0 | G13: =IF(G$12="","",IFERROR(INDEX('Meal Plan'!$H$5:$H$504,MATCH(TEXT(G$12,"yyyy-mm-dd")&"|"&"Dinner",'Meal Plan'!$AE$5:$AE$504,0)),"")) -> 0
A14: =IF(A$12="","",IFERROR(INDEX('Meal Plan'!$H$5:$H$504,MATCH(TEXT(A$12,"yyyy-mm-dd")&"|"&"Lunch",'Meal Plan'!$AE$5:$AE$504,0)),"")) -> 0 | B14: =IF(B$12="","",IFERROR(INDEX('Meal Plan'!$H$5:$H$504,MATCH(TEXT(B$12,"yyyy-mm-dd")&"|"&"Lunch",'Meal Plan'!$AE$5:$AE$504,0)),"")) -> 0 | C14: =IF(C$12="","",IFERROR(INDEX('Meal Plan'!$H$5:$H$504,MATCH(TEXT(C$12,"yyyy-mm-dd")&"|"&"Lunch",'Meal Plan'!$AE$5:$AE$504,0)),"")) -> 0 | D14: =IF(D$12="","",IFERROR(INDEX('Meal Plan'!$H$5:$H$504,MATCH(TEXT(D$12,"yyyy-mm-dd")&"|"&"Lunch",'Meal Plan'!$AE$5:$AE$504,0)),"")) -> 0 | E14: =IF(E$12="","",IFERROR(INDEX('Meal Plan'!$H$5:$H$504,MATCH(TEXT(E$12,"yyyy-mm-dd")&"|"&"Lunch",'Meal Plan'!$AE$5:$AE$504,0)),"")) -> 0 | F14: =IF(F$12="","",IFERROR(INDEX('Meal Plan'!$H$5:$H$504,MATCH(TEXT(F$12,"yyyy-mm-dd")&"|"&"Lunch",'Meal Plan'!$AE$5:$AE$504,0)),"")) -> 0 | G14: =IF(G$12="","",IFERROR(INDEX('Meal Plan'!$H$5:$H$504,MATCH(TEXT(G$12,"yyyy-mm-dd")&"|"&"Lunch",'Meal Plan'!$AE$5:$AE$504,0)),"")) -> 0
A15: =IF(A$12="","",IF(SUMIFS('Meal Plan'!$T$5:$T$504,'Meal Plan'!$B$5:$B$504,A$12)=0,"",SUMIFS('Meal Plan'!$T$5:$T$504,'Meal Plan'!$B$5:$B$504,A$12))) -> 0 | B15: =IF(B$12="","",IF(SUMIFS('Meal Plan'!$T$5:$T$504,'Meal Plan'!$B$5:$B$504,B$12)=0,"",SUMIFS('Meal Plan'!$T$5:$T$504,'Meal Plan'!$B$5:$B$504,B$12))) -> 0 | C15: =IF(C$12="","",IF(SUMIFS('Meal Plan'!$T$5:$T$504,'Meal Plan'!$B$5:$B$504,C$12)=0,"",SUMIFS('Meal Plan'!$T$5:$T$504,'Meal Plan'!$B$5:$B$504,C$12))) -> 0 | D15: =IF(D$12="","",IF(SUMIFS('Meal Plan'!$T$5:$T$504,'Meal Plan'!$B$5:$B$504,D$12)=0,"",SUMIFS('Meal Plan'!$T$5:$T$504,'Meal Plan'!$B$5:$B$504,D$12))) -> 0 | E15: =IF(E$12="","",IF(SUMIFS('Meal Plan'!$T$5:$T$504,'Meal Plan'!$B$5:$B$504,E$12)=0,"",SUMIFS('Meal Plan'!$T$5:$T$504,'Meal Plan'!$B$5:$B$504,E$12))) -> 0 | F15: =IF(F$12="","",IF(SUMIFS('Meal Plan'!$T$5:$T$504,'Meal Plan'!$B$5:$B$504,F$12)=0,"",SUMIFS('Meal Plan'!$T$5:$T$504,'Meal Plan'!$B$5:$B$504,F$12))) -> 0 | G15: =IF(G$12="","",IF(SUMIFS('Meal Plan'!$T$5:$T$504,'Meal Plan'!$B$5:$B$504,G$12)=0,"",SUMIFS('Meal Plan'!$T$5:$T$504,'Meal Plan'!$B$5:$B$504,G$12))) -> 0
A16: =PlanMonthStart-MOD(WEEKDAY(PlanMonthStart,IF(WeekStart="Sunday",1,2))-1,7)+14 -> 0 | B16: =PlanMonthStart-MOD(WEEKDAY(PlanMonthStart,IF(WeekStart="Sunday",1,2))-1,7)+15 -> 0 | C16: =PlanMonthStart-MOD(WEEKDAY(PlanMonthStart,IF(WeekStart="Sunday",1,2))-1,7)+16 -> 0 | D16: =PlanMonthStart-MOD(WEEKDAY(PlanMonthStart,IF(WeekStart="Sunday",1,2))-1,7)+17 -> 0 | E16: =PlanMonthStart-MOD(WEEKDAY(PlanMonthStart,IF(WeekStart="Sunday",1,2))-1,7)+18 -> 0 | F16: =PlanMonthStart-MOD(WEEKDAY(PlanMonthStart,IF(WeekStart="Sunday",1,2))-1,7)+19 -> 0 | G16: =PlanMonthStart-MOD(WEEKDAY(PlanMonthStart,IF(WeekStart="Sunday",1,2))-1,7)+20 -> 0
A17: =IF(A$16="","",IFERROR(INDEX('Meal Plan'!$H$5:$H$504,MATCH(TEXT(A$16,"yyyy-mm-dd")&"|"&"Dinner",'Meal Plan'!$AE$5:$AE$504,0)),"")) -> 0 | B17: =IF(B$16="","",IFERROR(INDEX('Meal Plan'!$H$5:$H$504,MATCH(TEXT(B$16,"yyyy-mm-dd")&"|"&"Dinner",'Meal Plan'!$AE$5:$AE$504,0)),"")) -> 0 | C17: =IF(C$16="","",IFERROR(INDEX('Meal Plan'!$H$5:$H$504,MATCH(TEXT(C$16,"yyyy-mm-dd")&"|"&"Dinner",'Meal Plan'!$AE$5:$AE$504,0)),"")) -> 0 | D17: =IF(D$16="","",IFERROR(INDEX('Meal Plan'!$H$5:$H$504,MATCH(TEXT(D$16,"yyyy-mm-dd")&"|"&"Dinner",'Meal Plan'!$AE$5:$AE$504,0)),"")) -> 0 | E17: =IF(E$16="","",IFERROR(INDEX('Meal Plan'!$H$5:$H$504,MATCH(TEXT(E$16,"yyyy-mm-dd")&"|"&"Dinner",'Meal Plan'!$AE$5:$AE$504,0)),"")) -> 0 | F17: =IF(F$16="","",IFERROR(INDEX('Meal Plan'!$H$5:$H$504,MATCH(TEXT(F$16,"yyyy-mm-dd")&"|"&"Dinner",'Meal Plan'!$AE$5:$AE$504,0)),"")) -> 0 | G17: =IF(G$16="","",IFERROR(INDEX('Meal Plan'!$H$5:$H$504,MATCH(TEXT(G$16,"yyyy-mm-dd")&"|"&"Dinner",'Meal Plan'!$AE$5:$AE$504,0)),"")) -> 0
A18: =IF(A$16="","",IFERROR(INDEX('Meal Plan'!$H$5:$H$504,MATCH(TEXT(A$16,"yyyy-mm-dd")&"|"&"Lunch",'Meal Plan'!$AE$5:$AE$504,0)),"")) -> 0 | B18: =IF(B$16="","",IFERROR(INDEX('Meal Plan'!$H$5:$H$504,MATCH(TEXT(B$16,"yyyy-mm-dd")&"|"&"Lunch",'Meal Plan'!$AE$5:$AE$504,0)),"")) -> 0 | C18: =IF(C$16="","",IFERROR(INDEX('Meal Plan'!$H$5:$H$504,MATCH(TEXT(C$16,"yyyy-mm-dd")&"|"&"Lunch",'Meal Plan'!$AE$5:$AE$504,0)),"")) -> 0 | D18: =IF(D$16="","",IFERROR(INDEX('Meal Plan'!$H$5:$H$504,MATCH(TEXT(D$16,"yyyy-mm-dd")&"|"&"Lunch",'Meal Plan'!$AE$5:$AE$504,0)),"")) -> 0 | E18: =IF(E$16="","",IFERROR(INDEX('Meal Plan'!$H$5:$H$504,MATCH(TEXT(E$16,"yyyy-mm-dd")&"|"&"Lunch",'Meal Plan'!$AE$5:$AE$504,0)),"")) -> 0 | F18: =IF(F$16="","",IFERROR(INDEX('Meal Plan'!$H$5:$H$504,MATCH(TEXT(F$16,"yyyy-mm-dd")&"|"&"Lunch",'Meal Plan'!$AE$5:$AE$504,0)),"")) -> 0 | G18: =IF(G$16="","",IFERROR(INDEX('Meal Plan'!$H$5:$H$504,MATCH(TEXT(G$16,"yyyy-mm-dd")&"|"&"Lunch",'Meal Plan'!$AE$5:$AE$504,0)),"")) -> 0
A19: =IF(A$16="","",IF(SUMIFS('Meal Plan'!$T$5:$T$504,'Meal Plan'!$B$5:$B$504,A$16)=0,"",SUMIFS('Meal Plan'!$T$5:$T$504,'Meal Plan'!$B$5:$B$504,A$16))) -> 0 | B19: =IF(B$16="","",IF(SUMIFS('Meal Plan'!$T$5:$T$504,'Meal Plan'!$B$5:$B$504,B$16)=0,"",SUMIFS('Meal Plan'!$T$5:$T$504,'Meal Plan'!$B$5:$B$504,B$16))) -> 0 | C19: =IF(C$16="","",IF(SUMIFS('Meal Plan'!$T$5:$T$504,'Meal Plan'!$B$5:$B$504,C$16)=0,"",SUMIFS('Meal Plan'!$T$5:$T$504,'Meal Plan'!$B$5:$B$504,C$16))) -> 0 | D19: =IF(D$16="","",IF(SUMIFS('Meal Plan'!$T$5:$T$504,'Meal Plan'!$B$5:$B$504,D$16)=0,"",SUMIFS('Meal Plan'!$T$5:$T$504,'Meal Plan'!$B$5:$B$504,D$16))) -> 0 | E19: =IF(E$16="","",IF(SUMIFS('Meal Plan'!$T$5:$T$504,'Meal Plan'!$B$5:$B$504,E$16)=0,"",SUMIFS('Meal Plan'!$T$5:$T$504,'Meal Plan'!$B$5:$B$504,E$16))) -> 0 | F19: =IF(F$16="","",IF(SUMIFS('Meal Plan'!$T$5:$T$504,'Meal Plan'!$B$5:$B$504,F$16)=0,"",SUMIFS('Meal Plan'!$T$5:$T$504,'Meal Plan'!$B$5:$B$504,F$16))) -> 0 | G19: =IF(G$16="","",IF(SUMIFS('Meal Plan'!$T$5:$T$504,'Meal Plan'!$B$5:$B$504,G$16)=0,"",SUMIFS('Meal Plan'!$T$5:$T$504,'Meal Plan'!$B$5:$B$504,G$16))) -> 0
A20: =PlanMonthStart-MOD(WEEKDAY(PlanMonthStart,IF(WeekStart="Sunday",1,2))-1,7)+21 -> 0 | B20: =PlanMonthStart-MOD(WEEKDAY(PlanMonthStart,IF(WeekStart="Sunday",1,2))-1,7)+22 -> 0 | C20: =PlanMonthStart-MOD(WEEKDAY(PlanMonthStart,IF(WeekStart="Sunday",1,2))-1,7)+23 -> 0 | D20: =PlanMonthStart-MOD(WEEKDAY(PlanMonthStart,IF(WeekStart="Sunday",1,2))-1,7)+24 -> 0 | E20: =PlanMonthStart-MOD(WEEKDAY(PlanMonthStart,IF(WeekStart="Sunday",1,2))-1,7)+25 -> 0 | F20: =PlanMonthStart-MOD(WEEKDAY(PlanMonthStart,IF(WeekStart="Sunday",1,2))-1,7)+26 -> 0 | G20: =PlanMonthStart-MOD(WEEKDAY(PlanMonthStart,IF(WeekStart="Sunday",1,2))-1,7)+27 -> 0
A21: =IF(A$20="","",IFERROR(INDEX('Meal Plan'!$H$5:$H$504,MATCH(TEXT(A$20,"yyyy-mm-dd")&"|"&"Dinner",'Meal Plan'!$AE$5:$AE$504,0)),"")) -> 0 | B21: =IF(B$20="","",IFERROR(INDEX('Meal Plan'!$H$5:$H$504,MATCH(TEXT(B$20,"yyyy-mm-dd")&"|"&"Dinner",'Meal Plan'!$AE$5:$AE$504,0)),"")) -> 0 | C21: =IF(C$20="","",IFERROR(INDEX('Meal Plan'!$H$5:$H$504,MATCH(TEXT(C$20,"yyyy-mm-dd")&"|"&"Dinner",'Meal Plan'!$AE$5:$AE$504,0)),"")) -> 0 | D21: =IF(D$20="","",IFERROR(INDEX('Meal Plan'!$H$5:$H$504,MATCH(TEXT(D$20,"yyyy-mm-dd")&"|"&"Dinner",'Meal Plan'!$AE$5:$AE$504,0)),"")) -> 0 | E21: =IF(E$20="","",IFERROR(INDEX('Meal Plan'!$H$5:$H$504,MATCH(TEXT(E$20,"yyyy-mm-dd")&"|"&"Dinner",'Meal Plan'!$AE$5:$AE$504,0)),"")) -> 0 | F21: =IF(F$20="","",IFERROR(INDEX('Meal Plan'!$H$5:$H$504,MATCH(TEXT(F$20,"yyyy-mm-dd")&"|"&"Dinner",'Meal Plan'!$AE$5:$AE$504,0)),"")) -> 0 | G21: =IF(G$20="","",IFERROR(INDEX('Meal Plan'!$H$5:$H$504,MATCH(TEXT(G$20,"yyyy-mm-dd")&"|"&"Dinner",'Meal Plan'!$AE$5:$AE$504,0)),"")) -> 0
A22: =IF(A$20="","",IFERROR(INDEX('Meal Plan'!$H$5:$H$504,MATCH(TEXT(A$20,"yyyy-mm-dd")&"|"&"Lunch",'Meal Plan'!$AE$5:$AE$504,0)),"")) -> 0 | B22: =IF(B$20="","",IFERROR(INDEX('Meal Plan'!$H$5:$H$504,MATCH(TEXT(B$20,"yyyy-mm-dd")&"|"&"Lunch",'Meal Plan'!$AE$5:$AE$504,0)),"")) -> 0 | C22: =IF(C$20="","",IFERROR(INDEX('Meal Plan'!$H$5:$H$504,MATCH(TEXT(C$20,"yyyy-mm-dd")&"|"&"Lunch",'Meal Plan'!$AE$5:$AE$504,0)),"")) -> 0 | D22: =IF(D$20="","",IFERROR(INDEX('Meal Plan'!$H$5:$H$504,MATCH(TEXT(D$20,"yyyy-mm-dd")&"|"&"Lunch",'Meal Plan'!$AE$5:$AE$504,0)),"")) -> 0 | E22: =IF(E$20="","",IFERROR(INDEX('Meal Plan'!$H$5:$H$504,MATCH(TEXT(E$20,"yyyy-mm-dd")&"|"&"Lunch",'Meal Plan'!$AE$5:$AE$504,0)),"")) -> 0 | F22: =IF(F$20="","",IFERROR(INDEX('Meal Plan'!$H$5:$H$504,MATCH(TEXT(F$20,"yyyy-mm-dd")&"|"&"Lunch",'Meal Plan'!$AE$5:$AE$504,0)),"")) -> 0 | G22: =IF(G$20="","",IFERROR(INDEX('Meal Plan'!$H$5:$H$504,MATCH(TEXT(G$20,"yyyy-mm-dd")&"|"&"Lunch",'Meal Plan'!$AE$5:$AE$504,0)),"")) -> 0
A23: =IF(A$20="","",IF(SUMIFS('Meal Plan'!$T$5:$T$504,'Meal Plan'!$B$5:$B$504,A$20)=0,"",SUMIFS('Meal Plan'!$T$5:$T$504,'Meal Plan'!$B$5:$B$504,A$20))) -> 0 | B23: =IF(B$20="","",IF(SUMIFS('Meal Plan'!$T$5:$T$504,'Meal Plan'!$B$5:$B$504,B$20)=0,"",SUMIFS('Meal Plan'!$T$5:$T$504,'Meal Plan'!$B$5:$B$504,B$20))) -> 0 | C23: =IF(C$20="","",IF(SUMIFS('Meal Plan'!$T$5:$T$504,'Meal Plan'!$B$5:$B$504,C$20)=0,"",SUMIFS('Meal Plan'!$T$5:$T$504,'Meal Plan'!$B$5:$B$504,C$20))) -> 0 | D23: =IF(D$20="","",IF(SUMIFS('Meal Plan'!$T$5:$T$504,'Meal Plan'!$B$5:$B$504,D$20)=0,"",SUMIFS('Meal Plan'!$T$5:$T$504,'Meal Plan'!$B$5:$B$504,D$20))) -> 0 | E23: =IF(E$20="","",IF(SUMIFS('Meal Plan'!$T$5:$T$504,'Meal Plan'!$B$5:$B$504,E$20)=0,"",SUMIFS('Meal Plan'!$T$5:$T$504,'Meal Plan'!$B$5:$B$504,E$20))) -> 0 | F23: =IF(F$20="","",IF(SUMIFS('Meal Plan'!$T$5:$T$504,'Meal Plan'!$B$5:$B$504,F$20)=0,"",SUMIFS('Meal Plan'!$T$5:$T$504,'Meal Plan'!$B$5:$B$504,F$20))) -> 0 | G23: =IF(G$20="","",IF(SUMIFS('Meal Plan'!$T$5:$T$504,'Meal Plan'!$B$5:$B$504,G$20)=0,"",SUMIFS('Meal Plan'!$T$5:$T$504,'Meal Plan'!$B$5:$B$504,G$20))) -> 0
A24: =PlanMonthStart-MOD(WEEKDAY(PlanMonthStart,IF(WeekStart="Sunday",1,2))-1,7)+28 -> 0 | B24: =PlanMonthStart-MOD(WEEKDAY(PlanMonthStart,IF(WeekStart="Sunday",1,2))-1,7)+29 -> 0 | C24: =PlanMonthStart-MOD(WEEKDAY(PlanMonthStart,IF(WeekStart="Sunday",1,2))-1,7)+30 -> 0 | D24: =PlanMonthStart-MOD(WEEKDAY(PlanMonthStart,IF(WeekStart="Sunday",1,2))-1,7)+31 -> 0 | E24: =PlanMonthStart-MOD(WEEKDAY(PlanMonthStart,IF(WeekStart="Sunday",1,2))-1,7)+32 -> 0 | F24: =PlanMonthStart-MOD(WEEKDAY(PlanMonthStart,IF(WeekStart="Sunday",1,2))-1,7)+33 -> 0 | G24: =PlanMonthStart-MOD(WEEKDAY(PlanMonthStart,IF(WeekStart="Sunday",1,2))-1,7)+34 -> 0
A25: =IF(A$24="","",IFERROR(INDEX('Meal Plan'!$H$5:$H$504,MATCH(TEXT(A$24,"yyyy-mm-dd")&"|"&"Dinner",'Meal Plan'!$AE$5:$AE$504,0)),"")) -> 0 | B25: =IF(B$24="","",IFERROR(INDEX('Meal Plan'!$H$5:$H$504,MATCH(TEXT(B$24,"yyyy-mm-dd")&"|"&"Dinner",'Meal Plan'!$AE$5:$AE$504,0)),"")) -> 0 | C25: =IF(C$24="","",IFERROR(INDEX('Meal Plan'!$H$5:$H$504,MATCH(TEXT(C$24,"yyyy-mm-dd")&"|"&"Dinner",'Meal Plan'!$AE$5:$AE$504,0)),"")) -> 0 | D25: =IF(D$24="","",IFERROR(INDEX('Meal Plan'!$H$5:$H$504,MATCH(TEXT(D$24,"yyyy-mm-dd")&"|"&"Dinner",'Meal Plan'!$AE$5:$AE$504,0)),"")) -> 0 | E25: =IF(E$24="","",IFERROR(INDEX('Meal Plan'!$H$5:$H$504,MATCH(TEXT(E$24,"yyyy-mm-dd")&"|"&"Dinner",'Meal Plan'!$AE$5:$AE$504,0)),"")) -> 0 | F25: =IF(F$24="","",IFERROR(INDEX('Meal Plan'!$H$5:$H$504,MATCH(TEXT(F$24,"yyyy-mm-dd")&"|"&"Dinner",'Meal Plan'!$AE$5:$AE$504,0)),"")) -> 0 | G25: =IF(G$24="","",IFERROR(INDEX('Meal Plan'!$H$5:$H$504,MATCH(TEXT(G$24,"yyyy-mm-dd")&"|"&"Dinner",'Meal Plan'!$AE$5:$AE$504,0)),"")) -> 0
A26: =IF(A$24="","",IFERROR(INDEX('Meal Plan'!$H$5:$H$504,MATCH(TEXT(A$24,"yyyy-mm-dd")&"|"&"Lunch",'Meal Plan'!$AE$5:$AE$504,0)),"")) -> 0 | B26: =IF(B$24="","",IFERROR(INDEX('Meal Plan'!$H$5:$H$504,MATCH(TEXT(B$24,"yyyy-mm-dd")&"|"&"Lunch",'Meal Plan'!$AE$5:$AE$504,0)),"")) -> 0 | C26: =IF(C$24="","",IFERROR(INDEX('Meal Plan'!$H$5:$H$504,MATCH(TEXT(C$24,"yyyy-mm-dd")&"|"&"Lunch",'Meal Plan'!$AE$5:$AE$504,0)),"")) -> 0 | D26: =IF(D$24="","",IFERROR(INDEX('Meal Plan'!$H$5:$H$504,MATCH(TEXT(D$24,"yyyy-mm-dd")&"|"&"Lunch",'Meal Plan'!$AE$5:$AE$504,0)),"")) -> 0 | E26: =IF(E$24="","",IFERROR(INDEX('Meal Plan'!$H$5:$H$504,MATCH(TEXT(E$24,"yyyy-mm-dd")&"|"&"Lunch",'Meal Plan'!$AE$5:$AE$504,0)),"")) -> 0 | F26: =IF(F$24="","",IFERROR(INDEX('Meal Plan'!$H$5:$H$504,MATCH(TEXT(F$24,"yyyy-mm-dd")&"|"&"Lunch",'Meal Plan'!$AE$5:$AE$504,0)),"")) -> 0 | G26: =IF(G$24="","",IFERROR(INDEX('Meal Plan'!$H$5:$H$504,MATCH(TEXT(G$24,"yyyy-mm-dd")&"|"&"Lunch",'Meal Plan'!$AE$5:$AE$504,0)),"")) -> 0
A27: =IF(A$24="","",IF(SUMIFS('Meal Plan'!$T$5:$T$504,'Meal Plan'!$B$5:$B$504,A$24)=0,"",SUMIFS('Meal Plan'!$T$5:$T$504,'Meal Plan'!$B$5:$B$504,A$24))) -> 0 | B27: =IF(B$24="","",IF(SUMIFS('Meal Plan'!$T$5:$T$504,'Meal Plan'!$B$5:$B$504,B$24)=0,"",SUMIFS('Meal Plan'!$T$5:$T$504,'Meal Plan'!$B$5:$B$504,B$24))) -> 0 | C27: =IF(C$24="","",IF(SUMIFS('Meal Plan'!$T$5:$T$504,'Meal Plan'!$B$5:$B$504,C$24)=0,"",SUMIFS('Meal Plan'!$T$5:$T$504,'Meal Plan'!$B$5:$B$504,C$24))) -> 0 | D27: =IF(D$24="","",IF(SUMIFS('Meal Plan'!$T$5:$T$504,'Meal Plan'!$B$5:$B$504,D$24)=0,"",SUMIFS('Meal Plan'!$T$5:$T$504,'Meal Plan'!$B$5:$B$504,D$24))) -> 0 | E27: =IF(E$24="","",IF(SUMIFS('Meal Plan'!$T$5:$T$504,'Meal Plan'!$B$5:$B$504,E$24)=0,"",SUMIFS('Meal Plan'!$T$5:$T$504,'Meal Plan'!$B$5:$B$504,E$24))) -> 0 | F27: =IF(F$24="","",IF(SUMIFS('Meal Plan'!$T$5:$T$504,'Meal Plan'!$B$5:$B$504,F$24)=0,"",SUMIFS('Meal Plan'!$T$5:$T$504,'Meal Plan'!$B$5:$B$504,F$24))) -> 0 | G27: =IF(G$24="","",IF(SUMIFS('Meal Plan'!$T$5:$T$504,'Meal Plan'!$B$5:$B$504,G$24)=0,"",SUMIFS('Meal Plan'!$T$5:$T$504,'Meal Plan'!$B$5:$B$504,G$24))) -> 0
A28: =PlanMonthStart-MOD(WEEKDAY(PlanMonthStart,IF(WeekStart="Sunday",1,2))-1,7)+35 -> 0 | B28: =PlanMonthStart-MOD(WEEKDAY(PlanMonthStart,IF(WeekStart="Sunday",1,2))-1,7)+36 -> 0 | C28: =PlanMonthStart-MOD(WEEKDAY(PlanMonthStart,IF(WeekStart="Sunday",1,2))-1,7)+37 -> 0 | D28: =PlanMonthStart-MOD(WEEKDAY(PlanMonthStart,IF(WeekStart="Sunday",1,2))-1,7)+38 -> 0 | E28: =PlanMonthStart-MOD(WEEKDAY(PlanMonthStart,IF(WeekStart="Sunday",1,2))-1,7)+39 -> 0 | F28: =PlanMonthStart-MOD(WEEKDAY(PlanMonthStart,IF(WeekStart="Sunday",1,2))-1,7)+40 -> 0 | G28: =PlanMonthStart-MOD(WEEKDAY(PlanMonthStart,IF(WeekStart="Sunday",1,2))-1,7)+41 -> 0
A29: =IF(A$28="","",IFERROR(INDEX('Meal Plan'!$H$5:$H$504,MATCH(TEXT(A$28,"yyyy-mm-dd")&"|"&"Dinner",'Meal Plan'!$AE$5:$AE$504,0)),"")) -> 0 | B29: =IF(B$28="","",IFERROR(INDEX('Meal Plan'!$H$5:$H$504,MATCH(TEXT(B$28,"yyyy-mm-dd")&"|"&"Dinner",'Meal Plan'!$AE$5:$AE$504,0)),"")) -> 0 | C29: =IF(C$28="","",IFERROR(INDEX('Meal Plan'!$H$5:$H$504,MATCH(TEXT(C$28,"yyyy-mm-dd")&"|"&"Dinner",'Meal Plan'!$AE$5:$AE$504,0)),"")) -> 0 | D29: =IF(D$28="","",IFERROR(INDEX('Meal Plan'!$H$5:$H$504,MATCH(TEXT(D$28,"yyyy-mm-dd")&"|"&"Dinner",'Meal Plan'!$AE$5:$AE$504,0)),"")) -> 0 | E29: =IF(E$28="","",IFERROR(INDEX('Meal Plan'!$H$5:$H$504,MATCH(TEXT(E$28,"yyyy-mm-dd")&"|"&"Dinner",'Meal Plan'!$AE$5:$AE$504,0)),"")) -> 0 | F29: =IF(F$28="","",IFERROR(INDEX('Meal Plan'!$H$5:$H$504,MATCH(TEXT(F$28,"yyyy-mm-dd")&"|"&"Dinner",'Meal Plan'!$AE$5:$AE$504,0)),"")) -> 0 | G29: =IF(G$28="","",IFERROR(INDEX('Meal Plan'!$H$5:$H$504,MATCH(TEXT(G$28,"yyyy-mm-dd")&"|"&"Dinner",'Meal Plan'!$AE$5:$AE$504,0)),"")) -> 0
A30: =IF(A$28="","",IFERROR(INDEX('Meal Plan'!$H$5:$H$504,MATCH(TEXT(A$28,"yyyy-mm-dd")&"|"&"Lunch",'Meal Plan'!$AE$5:$AE$504,0)),"")) -> 0 | B30: =IF(B$28="","",IFERROR(INDEX('Meal Plan'!$H$5:$H$504,MATCH(TEXT(B$28,"yyyy-mm-dd")&"|"&"Lunch",'Meal Plan'!$AE$5:$AE$504,0)),"")) -> 0 | C30: =IF(C$28="","",IFERROR(INDEX('Meal Plan'!$H$5:$H$504,MATCH(TEXT(C$28,"yyyy-mm-dd")&"|"&"Lunch",'Meal Plan'!$AE$5:$AE$504,0)),"")) -> 0 | D30: =IF(D$28="","",IFERROR(INDEX('Meal Plan'!$H$5:$H$504,MATCH(TEXT(D$28,"yyyy-mm-dd")&"|"&"Lunch",'Meal Plan'!$AE$5:$AE$504,0)),"")) -> 0 | E30: =IF(E$28="","",IFERROR(INDEX('Meal Plan'!$H$5:$H$504,MATCH(TEXT(E$28,"yyyy-mm-dd")&"|"&"Lunch",'Meal Plan'!$AE$5:$AE$504,0)),"")) -> 0 | F30: =IF(F$28="","",IFERROR(INDEX('Meal Plan'!$H$5:$H$504,MATCH(TEXT(F$28,"yyyy-mm-dd")&"|"&"Lunch",'Meal Plan'!$AE$5:$AE$504,0)),"")) -> 0 | G30: =IF(G$28="","",IFERROR(INDEX('Meal Plan'!$H$5:$H$504,MATCH(TEXT(G$28,"yyyy-mm-dd")&"|"&"Lunch",'Meal Plan'!$AE$5:$AE$504,0)),"")) -> 0
A31: =IF(A$28="","",IF(SUMIFS('Meal Plan'!$T$5:$T$504,'Meal Plan'!$B$5:$B$504,A$28)=0,"",SUMIFS('Meal Plan'!$T$5:$T$504,'Meal Plan'!$B$5:$B$504,A$28))) -> 0 | B31: =IF(B$28="","",IF(SUMIFS('Meal Plan'!$T$5:$T$504,'Meal Plan'!$B$5:$B$504,B$28)=0,"",SUMIFS('Meal Plan'!$T$5:$T$504,'Meal Plan'!$B$5:$B$504,B$28))) -> 0 | C31: =IF(C$28="","",IF(SUMIFS('Meal Plan'!$T$5:$T$504,'Meal Plan'!$B$5:$B$504,C$28)=0,"",SUMIFS('Meal Plan'!$T$5:$T$504,'Meal Plan'!$B$5:$B$504,C$28))) -> 0 | D31: =IF(D$28="","",IF(SUMIFS('Meal Plan'!$T$5:$T$504,'Meal Plan'!$B$5:$B$504,D$28)=0,"",SUMIFS('Meal Plan'!$T$5:$T$504,'Meal Plan'!$B$5:$B$504,D$28))) -> 0 | E31: =IF(E$28="","",IF(SUMIFS('Meal Plan'!$T$5:$T$504,'Meal Plan'!$B$5:$B$504,E$28)=0,"",SUMIFS('Meal Plan'!$T$5:$T$504,'Meal Plan'!$B$5:$B$504,E$28))) -> 0 | F31: =IF(F$28="","",IF(SUMIFS('Meal Plan'!$T$5:$T$504,'Meal Plan'!$B$5:$B$504,F$28)=0,"",SUMIFS('Meal Plan'!$T$5:$T$504,'Meal Plan'!$B$5:$B$504,F$28))) -> 0 | G31: =IF(G$28="","",IF(SUMIFS('Meal Plan'!$T$5:$T$504,'Meal Plan'!$B$5:$B$504,G$28)=0,"",SUMIFS('Meal Plan'!$T$5:$T$504,'Meal Plan'!$B$5:$B$504,G$28))) -> 0
A33: The month in numbers
A34: Meals planned | B34: Days covered | C34: Planned food cost | D34: Monthly budget | E34: Difference | F34: Cooked at home | G34: Eaten out
A35: =COUNTIFS('Meal Plan'!$B$5:$B$504,">="&PlanMonthStart,'Meal Plan'!$B$5:$B$504,"<="&EOMONTH(PlanMonthStart,0)) -> 0 | B35: =SUMPRODUCT((COUNTIFS('Meal Plan'!$B$5:$B$504,">="&PlanMonthStart,'Meal Plan'!$B$5:$B$504,"<="&EOMONTH(PlanMonthStart,0),'Meal Plan'!$B$5:$B$504,'Meal Plan'!$B$5:$B$504)>0)*1)/MAX(1,1) -> 0 | C35: =SUMIFS('Meal Plan'!$T$5:$T$504,'Meal Plan'!$B$5:$B$504,">="&PlanMonthStart,'Meal Plan'!$B$5:$B$504,"<="&EOMONTH(PlanMonthStart,0)) -> 0 | D35: =MonthlyBudget -> 0 | E35: =MonthlyBudget-SUMIFS('Meal Plan'!$T$5:$T$504,'Meal Plan'!$B$5:$B$504,">="&PlanMonthStart,'Meal Plan'!$B$5:$B$504,"<="&EOMONTH(PlanMonthStart,0)) -> 0 | F35: =COUNTIFS('Meal Plan'!$B$5:$B$504,">="&PlanMonthStart,'Meal Plan'!$B$5:$B$504,"<="&EOMONTH(PlanMonthStart,0),'Meal Plan'!$AD$5:$AD$504,"Yes") -> 0 | G35: =COUNTIFS('Meal Plan'!$B$5:$B$504,">="&PlanMonthStart,'Meal Plan'!$B$5:$B$504,"<="&EOMONTH(PlanMonthStart,0),'Meal Plan'!$AD$5:$AD$504,"No") -> 0
A37: Tip: plan the month roughly - the same six or seven dinners on a rotation is fine - then fine tune one week at a time on the Weekly Planner.

Sheet Settings
A1: Household Setup & Settings | G1: Novality Store | v1.0.0
A2: Fill in the cream cells once. Grey cells are locked formulas. Everything else in the workbook reads these values.
A3: > Start Here | C3: > Dashboard | E3: > Recipes | G3: > Week
A5: 1. Your household
B6: Household name | D6: The Harper Household | F6: Shown on every printable page and report.
B7: Main cook / planner | D7: Maya Harper
B8: Email | D8: maya@harperhome.com
B9: Town / city | D9: Portland, OR
B10: People to cook for | D10: 4 | E10: Used as the default serving count and to work out the cost per person.
B11: Usual supermarket | D11: Greenfield Market | F11: The store the grocery list defaults to.
B12: Notes about the household | D12: Two adults, two children, one nut allergy in the house
A14: 2. Planning window
B15: Planning year | D15: 2026 | E15: The year the monthly planner and the reports open on.
B16: Meal planning starts on | D16: 46300 | E16: The first day of week 1 on the weekly planner. Usually a Monday.
B17: Week starts on | D17: Monday | E17: Used by the planner grids and the week numbers.
B18: Shopping day | D18: Saturday | E18: The grocery list counts down to this day.
B19: Meal prep day | D19: Sunday
B20: Measurement system | D20: Metric | E20: Metric shows grams and millilitres, Imperial shows ounces and cups. Both always work - this only changes what the converter leads with.
B21: Default servings per meal | D21: 4
B22: Shopping list covers from | D22: =PlanStart -> 0 | E22: The grocery list adds up every meal planned between these two dates. Type over the dates whenever you want a different window - the whole list rebuilds itself.
B23: Shopping list covers to | D23: =ShopFrom+6 -> 0 | E23: Six days after the start gives you one week. Make it +13 for a fortnight's shop.
B24: Rounding on the grocery list | D24: Whole packs | F24: 'Whole packs' turns 1.3 tins into 2 tins - what the shop actually sells you. 'Exact quantity' leaves the raw number.
A26: 3. Food budget
B27: Weekly food budget | D27: 180 | E27: Groceries only - eating out has its own line.
B28: Monthly food budget | D28: 780
B29: Yearly food budget | D29: 9360
B30: Eating out / takeaway budget (month) | D30: 120
B31: Food waste cost you will accept (month) | D31: 15 | E31: The waste dashboard turns red above this.
A33: 4. Daily nutrition targets (per person)
B34: Optional. Leave them as they are if you only want the planning and the shopping - nothing else depends on them. These are general placeholders, not medical advice; set your own from your own guidance.
B35: Calories a day | D35: 2000
B36: Protein (g) | D36: 90
B37: Carbohydrates (g) | D37: 230
B38: Fat (g) | D38: 70
B39: Fibre (g) | D39: 30
B40: Sugar limit (g) | D40: 50
B41: Sodium limit (mg) | D41: 2300
B42: Water target (glasses a day) | D42: 8
A44: 5. Reminder windows
B45: Warn me this many days before food expires | D45: 5 | E45: Drives the 'use it soon' flags on the fridge, freezer and pantry tabs.
B46: Days a cooked leftover keeps in the fridge | D46: 3 | E46: A guide for the leftovers tab, not a food safety ruling - go by how it looks and smells, and by local guidance.
B47: Days before a freezer item is 'old' | D47: 90
B48: Days of stock that counts as low | D48: 7
B49: Flag prep tasks this many days early | D49: 2
B50: Days before a meal can repeat | D50: 14 | E50: The rotation planner flags anything cooked again sooner than this.
A52: 6. Habit targets
B53: Home cooked meals a week | D53: 18
B54: New recipes a month | D54: 2
B55: Takeaways a month (limit) | D55: 4
B56: Packed lunches a week | D56: 5
B57: Food waste target (share of spend) | D57: 0.05
A59: 7. ID prefixes
B60: The letters in front of the automatic numbers. Change them before you start entering data, not after.
B61: Recipe IDs | D61: R-
B62: Ingredient IDs | D62: ING-
B63: Planned meal IDs | D63: M-
B64: Pantry item IDs | D64: P-
B65: Shopping line IDs | D65: G-
B66: Leftover IDs | D66: L-
B67: Event IDs | D67: E-
B68: Purchase IDs | D68: S-
A70: 8. About this workbook
B71: Product | D71: Automated Meal Planner & Grocery List Spreadsheet
B72: Version | D72: 1.0.0
B73: Created by | D73: Novality Store
B74: Sheet protection password | D74: premium | E74: Review > Unprotect Sheet if you need to change a formula.
B75: Currency | D75: $ (USD)
B77: Changed your mind about something here? Everything updates straight away - the planner, the grocery list, the budget and the dashboard all read these cells rather than keeping their own copy.

Sheet Lists
A1: Drop Down Lists | H1: Novality Store | v1.0.0
A2: Every list the workbook offers you. Edit, add or delete an entry and the drop down that uses it changes everywhere.
A3: > Start Here | C3: > Dashboard | E3: > Recipes | G3: > Week | I3: > Month
A5: Add new entries directly under the last one in a column - the lists are sized with room to grow, and blanks are ignored. Do not delete a whole column: a drop down pointing at a missing list stops working.
A7: The drop downs
A8: YesNo | C8: YesNoNA | E8: MealSlot | G8: MealStatus | I8: RecipeCategory
A9: Yes | C9: Yes | E9: Breakfast | G9: Planned | I9: Main
A10: No | C10: No | E10: Morning snack | G10: Prepared | I10: Side
C11: N/A | E11: Lunch | G11: Eaten | I11: Soup
E12: Afternoon snack | G12: Skipped | I12: Salad
E13: Dinner | G13: Ate out | I13: Breakfast
E14: Evening snack | G14: Takeaway | I14: Snack
E15: Dessert | G15: Leftovers | I15: Dessert
G16: Cancelled | I16: Baking
I17: Sauce & dip
I18: Drink
I19: Batch base
I20: Lunchbox
A30: Cuisine | C30: CookingMethod | E30: Difficulty | G30: SpiceLevel | I30: PortionSize
A31: American | C31: Oven | E31: Easy | G31: None | I31: Small
A32: British | C32: Hob | E32: Medium | G32: Mild | I32: Regular
A33: Chinese | C33: One pot | E33: Hard | G33: Medium | I33: Large
A34: French | C34: Slow cooker | G34: Hot | I34: Extra large
A35: Greek | C35: Pressure cooker | G35: Very hot
A36: Indian | C36: Air fryer
A37: Italian | C37: Grill
A38: Japanese | C38: Barbecue
A39: Korean | C39: Microwave
A40: Mexican | C40: No cook
A41: Middle Eastern | C41: Blender
A42: Spanish | C42: Bread machine
A43: Thai
A44: Vietnamese
A45: Caribbean
A46: African
A47: Fusion
A48: Other
A58: Diet | C58: Allergen | E58: GroceryCategory | G58: Aisle | I58: Storage
A59: Vegetarian | C59: Celery | E59: Produce | G59: 1 - Produce | I59: Pantry
A60: Vegan | C60: Cereals with gluten | E60: Meat & seafood | G60: 2 - Bakery | I60: Cupboard
A61: Pescatarian | C61: Crustaceans | E61: Dairy & eggs | G61: 3 - Deli & cheese | I61: Fridge
A62: Gluten-free | C62: Eggs | E62: Bakery | G62: 4 - Meat & fish | I62: Freezer
A63: Dairy-free | C63: Fish | E63: Pantry staples | G63: 5 - Dairy & eggs | I63: Fruit bowl
A64: Egg-free | C64: Lupin | E64: Frozen | G64: 6 - Frozen | I64: Spice rack
A65: Nut-free | C65: Milk | E65: Beverages | G65: 7 - Tins & jars | I65: Garage shelf
A66: Soy-free | C66: Molluscs | E66: Spices & seasonings | G66: 8 - Pasta, rice & grains | I66: Cellar
A67: Low sodium | C67: Mustard | E67: Snacks | G67: 9 - Baking | I67: Other
A68: Low carb | C68: Nuts | E68: Baby & kids | G68: 10 - Spices & sauces
A69: High protein | C69: Peanuts | E69: Household | G69: 11 - Snacks
A70: High fibre | C70: Sesame | E70: Health & personal care | G70: 12 - Drinks
A71: Halal | C71: Soya | E71: Pet | G71: 13 - Household
A72: Kosher | C72: Sulphites | E72: Other | G72: 14 - Health
A73: No restriction | C73: None | G73: Online only
G74: Market stall
A84: Container | C84: ShoppingStatus | E84: Priority | G84: TaskStatus | I84: PrepTask
A85: Glass box | C85: To buy | E85: Must have | G85: To do | I85: Wash & chop
A86: Plastic box | C86: On the list | E86: Nice to have | G86: In progress | I86: Marinate
A87: Freezer bag | C87: Bought | E87: Only if cheap | G87: Done | I87: Batch cook
A88: Jar | C88: Substituted | E88: Stock up | G88: Blocked | I88: Bake
A89: Foil tray | C89: Out of stock | G89: Not needed | I89: Portion & label
A90: Vacuum bag | C90: Not needed | I90: Freeze
A91: Original pack | C91: Ordered | I91: Defrost
A92: Wrapped plate | I92: Soak
A93: Bowl with lid | I93: Make sauce
I94: Pack lunchboxes
I95: Shop
I96: Tidy
A106: MemberRole | C106: EventType | E106: LeftoverStatus | G106: WasteReason | I106: WasteAction
A107: Cook | C107: Birthday | E107: In the fridge | G107: Expired | I107: Binned
A108: Shopper | C108: Christmas | E108: In the freezer | G108: Went mouldy | I108: Composted
A109: Helper | C109: Thanksgiving | E109: Planned | G109: Cooked too much | I109: Fed to pets
A110: Dishes | C110: Easter | E110: Eaten | G110: Did not like it | I110: Given away
A111: Lunchbox duty | C111: Dinner party | E111: Frozen for later | G111: Forgot about it | I111: Donated
A112: Guest | C112: Barbecue | E112: Binned | G112: Freezer burn
A113: Child | C113: Picnic | E113: Given away | G113: Left out too long
C114: Potluck | G114: Bought too much
C115: Sunday lunch | G115: Plate scrapings
C116: Anniversary | G116: Other
C117: School event
C118: Other
A128: StoreType | C128: SpendCategory | E128: GoalCategory | G128: GoalStatus | I128: Frequency
A129: Supermarket | C129: Groceries | E129: Budget | G129: Not started | I129: Daily
A130: Discounter | C130: Fresh top-up | E130: Health | G130: In progress | I130: Weekly
A131: Local grocer | C131: Bulk shop | E131: Waste | G131: On track | I131: Fortnightly
A132: Butcher | C132: Takeaway | E132: Habit | G132: Behind | I132: Monthly
A133: Fishmonger | C133: Restaurant | E133: Variety | G133: Complete | I133: Occasionally
A134: Bakery | C134: Coffee & drinks | E134: Skill | G134: Paused | I134: One-off
A135: Farm shop | C135: Work lunch | E135: Time
A136: Market | C136: School meals
A137: Online delivery | C137: Snacks
A138: Wholesale | C138: Subscription box
A139: Convenience | C139: Delivery fee
A140: Takeaway | C140: Household
A141: Restaurant
A151: Season | C151: Rating | E151: Texture | G151: Month | I151: Weekday
A152: All year | C152: 5 - Make it again | E152: Any | G152: January | I152: Monday
A153: Spring | C153: 4 - Good | E153: Soft | G153: February | I153: Tuesday
A154: Summer | C154: 3 - Fine | E154: Crunchy | G154: March | I154: Wednesday
A155: Autumn | C155: 2 - Needs work | E155: Creamy | G155: April | I155: Thursday
A156: Winter | C156: 1 - Never again | E156: Crispy | G156: May | I156: Friday
...

Sheet Household
A1: Household & Preferences | W1: Novality Store | v1.0.0
A2: Who eats here, what they can and cannot eat, and how much of it - the numbers behind every portion in the workbook.
A3: > Start Here | C3: > Dashboard | E3: > Recipes | G3: > Week | I3: > Month | K3: > Grocery | M3: > Pantry | O3: > Budget | Q3: > Help | S3: Fill this in once. The portion factors add up to the household size the planner uses when you do not type a number of servings.
A4: ID | B4: Name | C4: Role | D4: Age group | E4: Portion factor | F4: Diet | G4: Allergies | H4: Avoids | I4: Will not touch | J4: Favourites | K4: In for breakfast? | L4: In for lunch? | M4: In for dinner? | N4: Takes a packed lunch? | O4: Daily calories | P4: Calories used | Q4: Cooks? | R4: Cooking nights | S4: Does the shopping? | T4: Kitchen jobs | U4: Meals planned for them | V4: Birthday | W4: Status | X4: Check | Y4: Notes
A5: =IF(B5="","","HH-"&TEXT(ROW()-4,"00")) -> 0 | B5: Maya Harper | C5: Cook | D5: Adult | E5: 1 | F5: No restriction | G5: None | I5: Olives | J5: Anything with chilli | K5: Yes | L5: No | M5: Yes | N5: No | O5: 2000 | P5: =IF(B5="","",IF(O5="",CalorieTarget*IF(E5="",1,E5),O5)) -> 0 | Q5: Yes | R5: Most nights | S5: Yes | T5: Meal plan, big shop | U5: =IF(B5="","",COUNTIFS('Meal Plan'!$O$5:$O$504,B5)) -> 0 | V5: 46406 | W5: Active | X5: =IF(B5="","",IF(E5="","Add - no portion factor",IF(AND(G5<>"",G5<>"None"),"Check - allergy on file","OK"))) -> 0 | Y5: Does the planning on a Friday with a coffee.
A6: =IF(B6="","","HH-"&TEXT(ROW()-4,"00")) -> 0 | B6: Tom Harper | C6: Shopper | D6: Adult | E6: 1.2 | F6: No restriction | G6: None | I6: Mushrooms | J6: Curry night | K6: No | L6: No | M6: Yes | N6: Yes | O6: 2400 | P6: =IF(B6="","",IF(O6="",CalorieTarget*IF(E6="",1,E6),O6)) -> 0 | Q6: Yes | R6: Tuesday and Thursday | S6: Yes | T6: Top-up shop, washing up | U6: =IF(B6="","",COUNTIFS('Meal Plan'!$O$5:$O$504,B6)) -> 0 | V6: 46321 | W6: Active | X6: =IF(B6="","",IF(E6="","Add - no portion factor",IF(AND(G6<>"",G6<>"None"),"Check - allergy on file","OK"))) -> 0 | Y6: Takes a packed lunch four days out of five.
A7: =IF(B7="","","HH-"&TEXT(ROW()-4,"00")) -> 0 | B7: Rory Harper | C7: Helper | D7: Teenager | E7: 1.4 | F7: Vegetarian | G7: None | I7: Anything 'mixed up' | J7: Pasta, pancakes | K7: Yes | L7: Yes | M7: Yes | N7: Yes | O7: 2600 | P7: =IF(B7="","",IF(O7="",CalorieTarget*IF(E7="",1,E7),O7)) -> 0 | Q7: Yes | R7: Sunday pudding | S7: No | T7: Lunchboxes | U7: =IF(B7="","",COUNTIFS('Meal Plan'!$O$5:$O$504,B7)) -> 0 | V7: 46486 | W7: Active | X7: =IF(B7="","",IF(E7="","Add - no portion factor",IF(AND(G7<>"",G7<>"None"),"Check - allergy on file","OK"))) -> 0 | Y7: Went vegetarian in March - needs a protein swap on meat nights.
A8: =IF(B8="","","HH-"&TEXT(ROW()-4,"00")) -> 0 | B8: Esme Harper | C8: Child | D8: Child | E8: 0.6 | F8: No restriction | G8: Peanuts | I8: Mushrooms, anything spicy | J8: Pancakes | K8: Yes | L8: Yes | M8: Yes | N8: Yes | O8: 1400 | P8: =IF(B8="","",IF(O8="",CalorieTarget*IF(E8="",1,E8),O8)) -> 0 | Q8: No | S8: No | T8: Laying the table | U8: =IF(B8="","",COUNTIFS('Meal Plan'!$O$5:$O$504,B8)) -> 0 | V8: 46356 | W8: Active | X8: =IF(B8="","",IF(E8="","Add - no portion factor",IF(AND(G8<>"",G8<>"None"),"Check - allergy on file","OK"))) -> 0 | Y8: Peanut allergy - no peanut butter in the house, check every label.
A9: =IF(B9="","","HH-"&TEXT(ROW()-4,"00")) -> 0 | P9: =IF(B9="","",IF(O9="",CalorieTarget*IF(E9="",1,E9),O9)) -> 0 | U9: =IF(B9="","",COUNTIFS('Meal Plan'!$O$5:$O$504,B9)) -> 0 | X9: =IF(B9="","",IF(E9="","Add - no portion factor",IF(AND(G9<>"",G9<>"None"),"Check - allergy on file","OK"))) -> 0
A10: =IF(B10="","","HH-"&TEXT(ROW()-4,"00")) -> 0 | P10: =IF(B10="","",IF(O10="",CalorieTarget*IF(E10="",1,E10),O10)) -> 0 | U10: =IF(B10="","",COUNTIFS('Meal Plan'!$O$5:$O$504,B10)) -> 0 | X10: =IF(B10="","",IF(E10="","Add - no portion factor",IF(AND(G10<>"",G10<>"None"),"Check - allergy on file","OK"))) -> 0
A11: =IF(B11="","","HH-"&TEXT(ROW()-4,"00")) -> 0 | P11: =IF(B11="","",IF(O11="",CalorieTarget*IF(E11="",1,E11),O11)) -> 0 | U11: =IF(B11="","",COUNTIFS('Meal Plan'!$O$5:$O$504,B11)) -> 0 | X11: =IF(B11="","",IF(E11="","Add - no portion factor",IF(AND(G11<>"",G11<>"None"),"Check - allergy on file","OK"))) -> 0
A12: =IF(B12="","","HH-"&TEXT(ROW()-4,"00")) -> 0 | P12: =IF(B12="","",IF(O12="",CalorieTarget*IF(E12="",1,E12),O12)) -> 0 | U12: =IF(B12="","",COUNTIFS('Meal Plan'!$O$5:$O$504,B12)) -> 0 | X12: =IF(B12="","",IF(E12="","Add - no portion factor",IF(AND(G12<>"",G12<>"None"),"Check - allergy on file","OK"))) -> 0
A13: =IF(B13="","","HH-"&TEXT(ROW()-4,"00")) -> 0 | P13: =IF(B13="","",IF(O13="",CalorieTarget*IF(E13="",1,E13),O13)) -> 0 | U13: =IF(B13="","",COUNTIFS('Meal Plan'!$O$5:$O$504,B13)) -> 0 | X13: =IF(B13="","",IF(E13="","Add - no portion factor",IF(AND(G13<>"",G13<>"None"),"Check - allergy on file","OK"))) -> 0
A14: =IF(B14="","","HH-"&TEXT(ROW()-4,"00")) -> 0 | P14: =IF(B14="","",IF(O14="",CalorieTarget*IF(E14="",1,E14),O14)) -> 0 | U14: =IF(B14="","",COUNTIFS('Meal Plan'!$O$5:$O$504,B14)) -> 0 | X14: =IF(B14="","",IF(E14="","Add - no portion factor",IF(AND(G14<>"",G14<>"None"),"Check - allergy on file","OK"))) -> 0
A15: =IF(B15="","","HH-"&TEXT(ROW()-4,"00")) -> 0 | P15: =IF(B15="","",IF(O15="",CalorieTarget*IF(E15="",1,E15),O15)) -> 0 | U15: =IF(B15="","",COUNTIFS('Meal Plan'!$O$5:$O$504,B15)) -> 0 | X15: =IF(B15="","",IF(E15="","Add - no portion factor",IF(AND(G15<>"",G15<>"None"),"Check - allergy on file","OK"))) -> 0
A16: =IF(B16="","","HH-"&TEXT(ROW()-4,"00")) -> 0 | P16: =IF(B16="","",IF(O16="",CalorieTarget*IF(E16="",1,E16),O16)) -> 0 | U16: =IF(B16="","",COUNTIFS('Meal Plan'!$O$5:$O$504,B16)) -> 0 | X16: =IF(B16="","",IF(E16="","Add - no portion factor",IF(AND(G16<>"",G16<>"None"),"Check - allergy on file","OK"))) -> 0
A18: The household in numbers
A19: People | B19: Total portions | C19: Daily calories for the house | D19: Allergies on file | E19: Packed lunches | F19: Cooks in the house
A20: =COUNTIFS(Household!$B$5:$B$16,"<>",Household!$W$5:$W$16,"Active") -> 0 | B20: =SUMIFS(Household!$E$5:$E$16,Household!$W$5:$W$16,"Active") -> 0 | C20: =SUMIFS(Household!$P$5:$P$16,Household!$W$5:$W$16,"Active") -> 0 | D20: =COUNTIFS(Household!$G$5:$G$16,"<>",Household!$G$5:$G$16,"<>None") -> 0 | E20: =COUNTIF(Household!$N$5:$N$16,"Yes") -> 0 | F20: =COUNTIF(Household!$Q$5:$Q$16,"Yes") -> 0

Sheet Recipes
A1: Recipe Database | BD1: Novality Store | v1.0.0
A2: Every recipe you cook, with its cost and nutrition worked out from the ingredients rather than typed in.
A3: > Start Here | C3: > Dashboard | E3: > Recipes | G3: > Week | I3: > Month | K3: > Grocery | M3: > Pantry | O3: > Budget | Q3: > Help | S3: Add the recipe here first, then list its ingredients on the Recipe Ingredients tab using the ID in column A. That is what makes the grocery list automatic.
A4: ID | B4: Recipe | C4: Category | D4: Usual meal | E4: Cuisine | F4: What it is | G4: Serves | H4: Prep (min) | I4: Cook (min) | J4: Total (min) | K4: Quick meal? | L4: Method | M4: Difficulty | N4: Equipment | O4: One pot? | P4: No cook? | Q4: Batch / prep friendly? | R4: Freezes well? | S4: Kid friendly? | T4: Suits | U4: Spice level | V4: Best season | W4: Tags | X4: Where it came from | Y4: Link | Z4: Photo link | AA4: How to make it | AB4: Ingredients | AC4: Cost to make | AD4: Cost per serving | AE4: Calories a serving | AF4: Protein (g) | AG4: Carbs (g) | AH4: Fat (g) | AI4: Fibre (g) | AJ4: Allergens in it | AK4: Cost rank | AL4: Matches the filter | AM4: Filter rank | AN4: Popularity rank | AO4: Calorie rank | AP4: Protein rank | AQ4: Fibre rank | AR4: Rotation rank | AS4: Sort key | AT4: Batches in the shopping window | AU4: Cost in the window | AV4: Missing a price | AW4: Your rating | AX4: Family score | AY4: Favourite? | AZ4: Times planned | BA4: Times cooked | BB4: Last cooked | BC4: Days since | BD4: Tweaks & notes | BE4: Added on | BF4: Check
A5: =IF(B5="","",RecipePrefix&TEXT(ROW()-4,"0000")) -> 0 | B5: Weeknight chicken traybake | C5: Main | D5: Dinner | E5: British | F5: Weeknight chicken traybake - 6 ingredients, serves 4. | G5: 4 | H5: 15 | I5: 45 | J5: =IF(B5="","",IF(AND(H5="",I5=""),"",IF(H5="",0,H5)+IF(I5="",0,I5))) -> 0 | K5: =IF(J5="","",IF(J5<=30,"Yes","No")) -> 0 | L5: Oven | M5: Easy | N5: Roasting tin | O5: No | P5: No | Q5: Yes | R5: No | S5: Yes | T5: No restriction | U5: None | V5: All year | W5: one tray, no washing up | X5: Family favourite | AA5: 1. Prep everything first. 2. Cook as usual. 3. Taste before you serve it. | AB5: =IF(A5="","",COUNTIFS('Recipe Ingredients'!$B$5:$B$1204,A5)) -> 0 | AC5: =IF(A5="","",SUMIFS('Recipe Ingredients'!$N$5:$N$1204,'Recipe Ingredients'!$B$5:$B$1204,A5)) -> 0 | AD5: =IF(OR(AC5="",G5=""),"",IF(G5=0,"",AC5/G5)) -> 0 | AE5: =IF(OR(A5="",G5=""),"",IF(G5=0,"",SUMIFS('Recipe Ingredients'!$Q$5:$Q$1204,'Recipe Ingredients'!$B$5:$B$1204,A5)/G5)) -> 0 | AF5: =IF(OR(A5="",G5=""),"",IF(G5=0,"",SUMIFS('Recipe Ingredients'!$R$5:$R$1204,'Recipe Ingredients'!$B$5:$B$1204,A5)/G5)) -> 0 | AG5: =IF(OR(A5="",G5=""),"",IF(G5=0,"",SUMIFS('Recipe Ingredients'!$S$5:$S$1204,'Recipe Ingredients'!$B$5:$B$1204,A5)/G5)) -> 0 | AH5: =IF(OR(A5="",G5=""),"",IF(G5=0,"",SUMIFS('Recipe Ingredients'!$T$5:$T$1204,'Recipe Ingredients'!$B$5:$B$1204,A5)/G5)) -> 0 | AI5: =IF(OR(A5="",G5=""),"",IF(G5=0,"",SUMIFS('Recipe Ingredients'!$U$5:$U$1204,'Recipe Ingredients'!$B$5:$B$1204,A5)/G5)) -> 0 | AJ5: =IF(A5="","",IF(COUNTIFS('Recipe Ingredients'!$B$5:$B$1204,A5,'Recipe Ingredients'!$V$5:$V$1204,"<>",'Recipe Ingredients'!$V$5:$V$1204,"<>None")=0,"None listed",COUNTIFS('Recipe Ingredients'!$B$5:$B$1204,A5,'Recipe Ingredients'!$V$5:$V$1204,"<>",'Recipe Ingredients'!$V$5:$V$1204,"<>None")&" ingredient(s) flagged")) -> 0 | AK5: =IF(OR(AD5="",NOT(ISNUMBER(AD5))),"",COUNTIFS($AD$5:$AD$204,"<"&AD5)+COUNTIFS($AD$5:AD5,AD5)) -> 0 | AL5: =IF(B5="",0,IF(AND(OR(FilterDiet="Any",T5=FilterDiet),OR(FilterCategory="Any",C5=FilterCategory),OR(FilterMethod="Any",L5=FilterMethod),OR(FilterTime=0,AND(J5<>"",J5<=FilterTime)),OR(FilterCost=0,AND(AD5<>"",ISNUMBER(AD5),AD5<=FilterCost)),OR(FilterAllergen="Any",COUNTIFS('Recipe Ingredients'!$B$5:$B$1204,A5,'Recipe Ingredients'!$V$5:$V$1204,FilterAllergen)=0)),1,0)) -> 0 | AM5: =IF(AL5=0,"",SUM($AL$5:AL5)) -> 0 | AN5: =IF(B5="","",COUNTIFS($AZ$5:$AZ$204,">"&AZ5)+COUNTIFS($AZ$5:AZ5,AZ5)) -> 0 | AO5: =IF(B5="","",COUNTIFS($AE$5:$AE$204,">"&AE5)+COUNTIFS($AE$5:AE5,AE5)) -> 0 | AP5: =IF(B5="","",COUNTIFS($AF$5:$AF$204,">"&AF5)+COUNTIFS($AF$5:AF5,AF5)) -> 0 | AQ5: =IF(B5="","",COUNTIFS($AI$5:$AI$204,">"&AI5)+COUNTIFS($AI$5:AI5,AI5)) -> 0 | AR5: =IF(B5="","",COUNTIFS($AS$5:$AS$204,">"&AS5)+COUNTIFS($AS$5:AS5,AS5)) -> 0 | AS5: =IF(B5="","",IF(BB5="",99999,BC5)) -> 0 | AT5: =IF(A5="",0,SUMIFS('Meal Plan'!$L$5:$L$504,'Meal Plan'!$G$5:$G$504,A5,'Meal Plan'!$B$5:$B$504,">="&ShopFrom,'Meal Plan'!$B$5:$B$504,"<="&ShopTo,'Meal Plan'!$M$5:$M$504,"Yes")) -> 0 | AU5: =IF(OR(A5="",AC5=""),"",AC5*AT5) -> 0 | AV5: =IF(A5="","",COUNTIFS('Recipe Ingredients'!$B$5:$B$1204,A5,'Recipe Ingredients'!$N$5:$N$1204,"")) -> 0 | AW5: 5 | AX5: 5 | AY5: Yes | AZ5: =IF(A5="","",COUNTIFS('Meal Plan'!$G$5:$G$504,A5)) -> 0 | BA5: =IF(A5="","",COUNTIFS('Meal Plan'!$G$5:$G$504,A5,'Meal Plan'!$N$5:$N$504,"Prepared")+COUNTIFS('Meal Plan'!$G$5:$G$504,A5,'Meal Plan'!$N$5:$N$504,"Eaten")) -> 0 | BB5: =IF(A5="","",IF(COUNTIFS('Meal Plan'!$G$5:$G$504,A5,'Meal Plan'!$B$5:$B$504,"<="&TODAY())=0,"",SUMPRODUCT(MAX(('Meal Plan'!$G$5:$G$504=A5)*('Meal Plan'!$B$5:$B$504<=TODAY())*'Meal Plan'!$B$5:$B$504)))) -> 0 | BC5: =IF(BB5="","",TODAY()-BB5) -> 0 | BE5: 46249 | BF5: =IF(B5="","",IF(G5="","Add - how many does it serve?",IF(AB5=0,"Add - no ingredients listed yet",IF(AV5>0,"Check - "&AV5&" ingredient(s) have no price",IF(AND(BC5<>"",BC5<RotationGapDays),"Cooked recently","OK"))))) -> 0
A6: =IF(B6="","",RecipePrefix&TEXT(ROW()-4,"0000")) -> 0 | B6: Beef bolognese | C6: Main | D6: Dinner | E6: Italian | F6: Beef bolognese - 7 ingredients, serves 6. | G6: 6 | H6: 20 | I6: 60 | J6: =IF(B6="","",IF(AND(H6="",I6=""),"",IF(H6="",0,H6)+IF(I6="",0,I6))) -> 0 | K6: =IF(J6="","",IF(J6<=30,"Yes","No")) -> 0 | L6: Hob | M6: Easy | N6: Big pan | O6: No | P6: No | Q6: Yes | R6: Yes | S6: Yes | T6: No restriction | U6: None | V6: All year | W6: batch base, freezer friendly | X6: Family favourite | AA6: 1. Prep everything first. 2. Cook as usual. 3. Taste before you serve it. | AB6: =IF(A6="","",COUNTIFS('Recipe Ingredients'!$B$5:$B$1204,A6)) -> 0 | AC6: =IF(A6="","",SUMIFS('Recipe Ingredients'!$N$5:$N$1204,'Recipe Ingredients'!$B$5:$B$1204,A6)) -> 0 | AD6: =IF(OR(AC6="",G6=""),"",IF(G6=0,"",AC6/G6)) -> 0 | AE6: =IF(OR(A6="",G6=""),"",IF(G6=0,"",SUMIFS('Recipe Ingredients'!$Q$5:$Q$1204,'Recipe Ingredients'!$B$5:$B$1204,A6)/G6)) -> 0 | AF6: =IF(OR(A6="",G6=""),"",IF(G6=0,"",SUMIFS('Recipe Ingredients'!$R$5:$R$1204,'Recipe Ingredients'!$B$5:$B$1204,A6)/G6)) -> 0 | AG6: =IF(OR(A6="",G6=""),"",IF(G6=0,"",SUMIFS('Recipe Ingredients'!$S$5:$S$1204,'Recipe Ingredients'!$B$5:$B$1204,A6)/G6)) -> 0 | AH6: =IF(OR(A6="",G6=""),"",IF(G6=0,"",SUMIFS('Recipe Ingredients'!$T$5:$T$1204,'Recipe Ingredients'!$B$5:$B$1204,A6)/G6)) -> 0 | AI6: =IF(OR(A6="",G6=""),"",IF(G6=0,"",SUMIFS('Recipe Ingredients'!$U$5:$U$1204,'Recipe Ingredients'!$B$5:$B$1204,A6)/G6)) -> 0 | AJ6: =IF(A6="","",IF(COUNTIFS('Recipe Ingredients'!$B$5:$B$1204,A6,'Recipe Ingredients'!$V$5:$V$1204,"<>",'Recipe Ingredients'!$V$5:$V$1204,"<>None")=0,"None listed",COUNTIFS('Recipe Ingredients'!$B$5:$B$1204,A6,'Recipe Ingredients'!$V$5:$V$1204,"<>",'Recipe Ingredients'!$V$5:$V$1204,"<>None")&" ingredient(s) flagged")) -> 0 | AK6: =IF(OR(AD6="",NOT(ISNUMBER(AD6))),"",COUNTIFS($AD$5:$AD$204,"<"&AD6)+COUNTIFS($AD$5:AD6,AD6)) -> 0 | AL6: =IF(B6="",0,IF(AND(OR(FilterDiet="Any",T6=FilterDiet),OR(FilterCategory="Any",C6=FilterCategory),OR(FilterMethod="Any",L6=FilterMethod),OR(FilterTime=0,AND(J6<>"",J6<=FilterTime)),OR(FilterCost=0,AND(AD6<>"",ISNUMBER(AD6),AD6<=FilterCost)),OR(FilterAllergen="Any",COUNTIFS('Recipe Ingredients'!$B$5:$B$1204,A6,'Recipe Ingredients'!$V$5:$V$1204,FilterAllergen)=0)),1,0)) -> 0 | AM6: =IF(AL6=0,"",SUM($AL$5:AL6)) -> 0 | AN6: =IF(B6="","",COUNTIFS($AZ$5:$AZ$204,">"&AZ6)+COUNTIFS($AZ$5:AZ6,AZ6)) -> 0 | AO6: =IF(B6="","",COUNTIFS($AE$5:$AE$204,">"&AE6)+COUNTIFS($AE$5:AE6,AE6)) -> 0 | AP6: =IF(B6="","",COUNTIFS($AF$5:$AF$204,">"&AF6)+COUNTIFS($AF$5:AF6,AF6)) -> 0 | AQ6: =IF(B6="","",COUNTIFS($AI$5:$AI$204,">"&AI6)+COUNTIFS($AI$5:AI6,AI6)) -> 0 | AR6: =IF(B6="","",COUNTIFS($AS$5:$AS$204,">"&AS6)+COUNTIFS($AS$5:AS6,AS6)) -> 0 | AS6: =IF(B6="","",IF(BB6="",99999,BC6)) -> 0 | AT6: =IF(A6="",0,SUMIFS('Meal Plan'!$L$5:$L$504,'Meal Plan'!$G$5:$G$504,A6,'Meal Plan'!$B$5:$B$504,">="&ShopFrom,'Meal Plan'!$B$5:$B$504,"<="&ShopTo,'Meal Plan'!$M$5:$M$504,"Yes")) -> 0 | AU6: =IF(OR(A6="",AC6=""),"",AC6*AT6) -> 0 | AV6: =IF(A6="","",COUNTIFS('Recipe Ingredients'!$B$5:$B$1204,A6,'Recipe Ingredients'!$N$5:$N$1204,"")) -> 0 | AW6: 5 | AX6: 4 | AY6: Yes | AZ6: =IF(A6="","",COUNTIFS('Meal Plan'!$G$5:$G$504,A6)) -> 0 | BA6: =IF(A6="","",COUNTIFS('Meal Plan'!$G$5:$G$504,A6,'Meal Plan'!$N$5:$N$504,"Prepared")+COUNTIFS('Meal Plan'!$G$5:$G$504,A6,'Meal Plan'!$N$5:$N$504,"Eaten")) -> 0 | BB6: =IF(A6="","",IF(COUNTIFS('Meal Plan'!$G$5:$G$504,A6,'Meal Plan'!$B$5:$B$504,"<="&TODAY())=0,"",SUMPRODUCT(MAX(('Meal Plan'!$G$5:$G$504=A6)*('Meal Plan'!$B$5:$B$504<=TODAY())*'Meal Plan'!$B$5:$B$504)))) -> 0 | BC6: =IF(BB6="","",TODAY()-BB6) -> 0 | BE6: 45979 | BF6: =IF(B6="","",IF(G6="","Add - how many does it serve?",IF(AB6=0,"Add - no ingredients listed yet",IF(AV6>0,"Check - "&AV6&" ingredient(s) have no price",IF(AND(BC6<>"",BC6<RotationGapDays),"Cooked recently","OK"))))) -> 0
A7: =IF(B7="","",RecipePrefix&TEXT(ROW()-4,"0000")) -> 0 | B7: Red lentil dhal | C7: Main | D7: Dinner | E7: Indian | F7: Red lentil dhal - 6 ingredients, serves 4. | G7: 4 | H7: 10 | I7: 30 | J7: =IF(B7="","",IF(AND(H7="",I7=""),"",IF(H7="",0,H7)+IF(I7="",0,I7))) -> 0 | K7: =IF(J7="","",IF(J7<=30,"Yes","No")) -> 0 | L7: One pot | M7: Easy | O7: Yes | P7: No | Q7: Yes | R7: Yes | S7: No | T7: Vegan | U7: Mild | V7: All year | W7: cheap, store cupboard | AA7: 1. Prep everything first. 2. Cook as usual. 3. Taste before you serve it. | AB7: =IF(A7="","",COUNTIFS('Recipe Ingredients'!$B$5:$B$1204,A7)) -> 0 | AC7: =IF(A7="","",SUMIFS('Recipe Ingredients'!$N$5:$N$1204,'Recipe Ingredients'!$B$5:$B$1204,A7)) -> 0 | AD7: =IF(OR(AC7="",G7=""),"",IF(G7=0,"",AC7/G7)) -> 0 | AE7: =IF(OR(A7="",G7=""),"",IF(G7=0,"",SUMIFS('Recipe Ingredients'!$Q$5:$Q$1204,'Recipe Ingredients'!$B$5:$B$1204,A7)/G7)) -> 0 | AF7: =IF(OR(A7="",G7=""),"",IF(G7=0,"",SUMIFS('Recipe Ingredients'!$R$5:$R$1204,'Recipe Ingredients'!$B$5:$B$1204,A7)/G7)) -> 0 | AG7: =IF(OR(A7="",G7=""),"",IF(G7=0,"",SUMIFS('Recipe Ingredients'!$S$5:$S$1204,'Recipe Ingredients'!$B$5:$B$1204,A7)/G7)) -> 0 | AH7: =IF(OR(A7="",G7=""),"",IF(G7=0,"",SUMIFS('Recipe Ingredients'!$T$5:$T$1204,'Recipe Ingredients'!$B$5:$B$1204,A7)/G7)) -> 0 | AI7: =IF(OR(A7="",G7=""),"",IF(G7=0,"",SUMIFS('Recipe Ingredients'!$U$5:$U$1204,'Recipe Ingredients'!$B$5:$B$1204,A7)/G7)) -> 0 | AJ7: =IF(A7="","",IF(COUNTIFS('Recipe Ingredients'!$B$5:$B$1204,A7,'Recipe Ingredients'!$V$5:$V$1204,"<>",'Recipe Ingredients'!$V$5:$V$1204,"<>None")=0,"None listed",COUNTIFS('Recipe Ingredients'!$B$5:$B$1204,A7,'Recipe Ingredients'!$V$5:$V$1204,"<>",'Recipe Ingredients'!$V$5:$V$1204,"<>None")&" ingredient(s) flagged")) -> 0 | AK7: =IF(OR(AD7="",NOT(ISNUMBER(AD7))),"",COUNTIFS($AD$5:$AD$204,"<"&AD7)+COUNTIFS($AD$5:AD7,AD7)) -> 0 | AL7: =IF(B7="",0,IF(AND(OR(FilterDiet="Any",T7=FilterDiet),OR(FilterCategory="Any",C7=FilterCategory),OR(FilterMethod="Any",L7=FilterMethod),OR(FilterTime=0,AND(J7<>"",J7<=FilterTime)),OR(FilterCost=0,AND(AD7<>"",ISNUMBER(AD7),AD7<=FilterCost)),OR(FilterAllergen="Any",COUNTIFS('Recipe Ingredients'!$B$5:$B$1204,A7,'Recipe Ingredients'!$V$5:$V$1204,FilterAllergen)=0)),1,0)) -> 0 | AM7: =IF(AL7=0,"",SUM($AL$5:AL7)) -> 0 | AN7: =IF(B7="","",COUNTIFS($AZ$5:$AZ$204,">"&AZ7)+COUNTIFS($AZ$5:AZ7,AZ7)) -> 0 | AO7: =IF(B7="","",COUNTIFS($AE$5:$AE$204,">"&AE7)+COUNTIFS($AE$5:AE7,AE7)) -> 0 | AP7: =IF(B7="","",COUNTIFS($AF$5:$AF$204,">"&AF7)+COUNTIFS($AF$5:AF7,AF7)) -> 0 | AQ7: =IF(B7="","",COUNTIFS($AI$5:$AI$204,">"&AI7)+COUNTIFS($AI$5:AI7,AI7)) -> 0 | AR7: =IF(B7="","",COUNTIFS($AS$5:$AS$204,">"&AS7)+COUNTIFS($AS$5:AS7,AS7)) -> 0 | AS7: =IF(B7="","",IF(BB7="",99999,BC7)) -> 0 | AT7: =IF(A7="",0,SUMIFS('Meal Plan'!$L$5:$L$504,'Meal Plan'!$G$5:$G$504,A7,'Meal Plan'!$B$5:$B$504,">="&ShopFrom,'Meal Plan'!$B$5:$B$504,"<="&ShopTo,'Meal Plan'!$M$5:$M$504,"Yes")) -> 0 | AU7: =IF(OR(A7="",AC7=""),"",AC7*AT7) -> 0 | AV7: =IF(A7="","",COUNTIFS('Recipe Ingredients'!$B$5:$B$1204,A7,'Recipe Ingredients'!$N$5:$N$1204,"")) -> 0 | AW7: 4 | AX7: 4 | AY7: No | AZ7: =IF(A7="","",COUNTIFS('Meal Plan'!$G$5:$G$504,A7)) -> 0 | BA7: =IF(A7="","",COUNTIFS('Meal Plan'!$G$5:$G$504,A7,'Meal Plan'!$N$5:$N$504,"Prepared")+COUNTIFS('Meal Plan'!$G$5:$G$504,A7,'Meal Plan'!$N$5:$N$504,"Eaten")) -> 0 | BB7: =IF(A7="","",IF(COUNTIFS('Meal Plan'!$G$5:$G$504,A7,'Meal Plan'!$B$5:$B$504,"<="&TODAY())=0,"",SUMPRODUCT(MAX(('Meal Plan'!$G$5:$G$504=A7)*('Meal Plan'!$B$5:$B$504<=TODAY())*'Meal Plan'!$B$5:$B$504)))) -> 0 | BC7: =IF(BB7="","",TODAY()-BB7) -> 0 | BE7: 45952 | BF7: =IF(B7="","",IF(G7="","Add - how many does it serve?",IF(AB7=0,"Add - no ingredients listed yet",IF(AV7>0,"Check - "&AV7&" ingredient(s) have no price",IF(AND(BC7<>"",BC7<RotationGapDays),"Cooked recently","OK"))))) -> 0
A8: =IF(B8="","",RecipePrefix&TEXT(ROW()-4,"0000")) -> 0 | B8: Salmon, new potatoes & greens | C8: Main | D8: Dinner | E8: British | F8: Salmon, new potatoes & greens - 5 ingredients, serves 2. | G8: 2 | H8: 10 | I8: 25 | J8: =IF(B8="","",IF(AND(H8="",I8=""),"",IF(H8="",0,H8)+IF(I8="",0,I8))) -> 0 | K8: =IF(J8="","",IF(J8<=30,"Yes","No")) -> 0 | L8: Oven | M8: Easy | N8: Roasting tin | O8: No | P8: No | Q8: No | R8: No | S8: No | T8: Pescatarian | U8: None | V8: All year | W8: payday treat | AA8: 1. Prep everything first. 2. Cook as usual. 3. Taste before you serve it. | AB8: =IF(A8="","",COUNTIFS('Recipe Ingredients'!$B$5:$B$1204,A8)) -> 0 | AC8: =IF(A8="","",SUMIFS('Recipe Ingredients'!$N$5:$N$1204,'Recipe Ingredients'!$B$5:$B$1204,A8)) -> 0 | AD8: =IF(OR(AC8="",G8=""),"",IF(G8=0,"",AC8/G8)) -> 0 | AE8: =IF(OR(A8="",G8=""),"",IF(G8=0,"",SUMIFS('Recipe Ingredients'!$Q$5:$Q$1204,'Recipe Ingredients'!$B$5:$B$1204,A8)/G8)) -> 0 | AF8: =IF(OR(A8="",G8=""),"",IF(G8=0,"",SUMIFS('Recipe Ingredients'!$R$5:$R$1204,'Recipe Ingredients'!$B$5:$B$1204,A8)/G8)) -> 0 | AG8: =IF(OR(A8="",G8=""),"",IF(G8=0,"",SUMIFS('Recipe Ingredients'!$S$5:$S$1204,'Recipe Ingredients'!$B$5:$B$1204,A8)/G8)) -> 0 | AH8: =IF(OR(A8="",G8=""),"",IF(G8=0,"",SUMIFS('Recipe Ingredients'!$T$5:$T$1204,'Recipe Ingredients'!$B$5:$B$1204,A8)/G8)) -> 0 | AI8: =IF(OR(A8="",G8=""),"",IF(G8=0,"",SUMIFS('Recipe Ingredients'!$U$5:$U$1204,'Recipe Ingredients'!$B$5:$B$1204,A8)/G8)) -> 0 | AJ8: =IF(A8="","",IF(COUNTIFS('Recipe Ingredients'!$B$5:$B$1204,A8,'Recipe Ingredients'!$V$5:$V$1204,"<>",'Recipe Ingredients'!$V$5:$V$1204,"<>None")=0,"None listed",COUNTIFS('Recipe Ingredients'!$B$5:$B$1204,A8,'Recipe Ingredients'!$V$5:$V$1204,"<>",'Recipe Ingredients'!$V$5:$V$1204,"<>None")&" ingredient(s) flagged")) -> 0 | AK8: =IF(OR(AD8="",NOT(ISNUMBER(AD8))),"",COUNTIFS($AD$5:$AD$204,"<"&AD8)+COUNTIFS($AD$5:AD8,AD8)) -> 0 | AL8: =IF(B8="",0,IF(AND(OR(FilterDiet="Any",T8=FilterDiet),OR(FilterCategory="Any",C8=FilterCategory),OR(FilterMethod="Any",L8=FilterMethod),OR(FilterTime=0,AND(J8<>"",J8<=FilterTime)),OR(FilterCost=0,AND(AD8<>"",ISNUMBER(AD8),AD8<=FilterCost)),OR(FilterAllergen="Any",COUNTIFS('Recipe Ingredients'!$B$5:$B$1204,A8,'Recipe Ingredients'!$V$5:$V$1204,FilterAllergen)=0)),1,0)) -> 0 | AM8: =IF(AL8=0,"",SUM($AL$5:AL8)) -> 0 | AN8: =IF(B8="","",COUNTIFS($AZ$5:$AZ$204,">"&AZ8)+COUNTIFS($AZ$5:AZ8,AZ8)) -> 0 | AO8: =IF(B8="","",COUNTIFS($AE$5:$AE$204,">"&AE8)+COUNTIFS($AE$5:AE8,AE8)) -> 0 | AP8: =IF(B8="","",COUNTIFS($AF$5:$AF$204,">"&AF8)+COUNTIFS($AF$5:AF8,AF8)) -> 0 | AQ8: =IF(B8="","",COUNTIFS($AI$5:$AI$204,">"&AI8)+COUNTIFS($AI$5:AI8,AI8)) -> 0 | AR8: =IF(B8="","",COUNTIFS($AS$5:$AS$204,">"&AS8)+COUNTIFS($AS$5:AS8,AS8)) -> 0 | AS8: =IF(B8="","",IF(BB8="",99999,BC8)) -> 0 | AT8: =IF(A8="",0,SUMIFS('Meal Plan'!$L$5:$L$504,'Meal Plan'!$G$5:$G$504,A8,'Meal Plan'!$B$5:$B$504,">="&ShopFrom,'Meal Plan'!$B$5:$B$504,"<="&ShopTo,'Meal Plan'!$M$5:$M$504,"Yes")) -> 0 | AU8: =IF(OR(A8="",AC8=""),"",AC8*AT8) -> 0 | AV8: =IF(A8="","",COUNTIFS('Recipe Ingredients'!$B$5:$B$1204,A8,'Recipe Ingredients'!$N$5:$N$1204,"")) -> 0 | AW8: 4 | AX8: 3 | AY8: No | AZ8: =IF(A8="","",COUNTIFS('Meal Plan'!$G$5:$G$504,A8)) -> 0 | BA8: =IF(A8="","",COUNTIFS('Meal Plan'!$G$5:$G$504,A8,'Meal Plan'!$N$5:$N$504,"Prepared")+COUNTIFS('Meal Plan'!$G$5:$G$504,A8,'Meal Plan'!$N$5:$N$504,"Eaten")) -> 0 | BB8: =IF(A8="","",IF(COUNTIFS('Meal Plan'!$G$5:$G$504,A8,'Meal Plan'!$B$5:$B$504,"<="&TODAY())=0,"",SUMPRODUCT(MAX(('Meal Plan'!$G$5:$G$504=A8)*('Meal Plan'!$B$5:$B$504<=TODAY())*'Meal Plan'!$B$5:$B$504)))) -> 0 | BC8: =IF(BB8="","",TODAY()-BB8) -> 0 | BE8: 46240 | BF8: =IF(B8="","",IF(G8="","Add - how many does it serve?",IF(AB8=0,"Add - no ingredients listed yet",IF(AV8>0,"Check - "&AV8&" ingredient(s) have no price",IF(AND(BC8<>"",BC8<RotationGapDays),"Cooked recently","OK"))))) -> 0
A9: =IF(B9="","",RecipePrefix&TEXT(ROW()-4,"0000")) -> 0 | B9: Chickpea & spinach curry | C9: Main | D9: Dinner | E9: Indian | F9: Chickpea & spinach curry - 6 ingredients, serves 4. | G9: 4 | H9: 10 | I9: 25 | J9: =IF(B9="","",IF(AND(H9="",I9=""),"",IF(H9="",0,H9)+IF(I9="",0,I9))) -> 0 | K9: =IF(J9="","",IF(J9<=30,"Yes","No")) -> 0 | L9: One pot | M9: Easy | O9: Yes | P9: No | Q9: Yes | R9: Yes | S9: No | T9: Vegan | U9: Mild | V9: All year | W9: store cupboard | AA9: 1. Prep everything first. 2. Cook as usual. 3. Taste before you serve it. | AB9: =IF(A9="","",COUNTIFS('Recipe Ingredients'!$B$5:$B$1204,A9)) -> 0 | AC9: =IF(A9="","",SUMIFS('Recipe Ingredients'!$N$5:$N$1204,'Recipe Ingredients'!$B$5:$B$1204,A9)) -> 0 | AD9: =IF(OR(AC9="",G9=""),"",IF(G9=0,"",AC9/G9)) -> 0 | AE9: =IF(OR(A9="",G9=""),"",IF(G9=0,"",SUMIFS('Recipe Ingredients'!$Q$5:$Q$1204,'Recipe Ingredients'!$B$5:$B$1204,A9)/G9)) -> 0 | AF9: =IF(OR(A9="",G9=""),"",IF(G9=0,"",SUMIFS('Recipe Ingredients'!$R$5:$R$1204,'Recipe Ingredients'!$B$5:$B$1204,A9)/G9)) -> 0 | AG9: =IF(OR(A9="",G9=""),"",IF(G9=0,"",SUMIFS('Recipe Ingredients'!$S$5:$S$1204,'Recipe Ingredients'!$B$5:$B$1204,A9)/G9)) -> 0 | AH9: =IF(OR(A9="",G9=""),"",IF(G9=0,"",SUMIFS('Recipe Ingredients'!$T$5:$T$1204,'Recipe Ingredients'!$B$5:$B$1204,A9)/G9)) -> 0 | AI9: =IF(OR(A9="",G9=""),"",IF(G9=0,"",SUMIFS('Recipe Ingredients'!$U$5:$U$1204,'Recipe Ingredients'!$B$5:$B$1204,A9)/G9)) -> 0 | AJ9: =IF(A9="","",IF(COUNTIFS('Recipe Ingredients'!$B$5:$B$1204,A9,'Recipe Ingredients'!$V$5:$V$1204,"<>",'Recipe Ingredients'!$V$5:$V$1204,"<>None")=0,"None listed",COUNTIFS('Recipe Ingredients'!$B$5:$B$1204,A9,'Recipe Ingredients'!$V$5:$V$1204,"<>",'Recipe Ingredients'!$V$5:$V$1204,"<>None")&" ingredient(s) flagged")) -> 0 | AK9: =IF(OR(AD9="",NOT(ISNUMBER(AD9))),"",COUNTIFS($AD$5:$AD$204,"<"&AD9)+COUNTIFS($AD$5:AD9,AD9)) -> 0 | AL9: =IF(B9="",0,IF(AND(OR(FilterDiet="Any",T9=FilterDiet),OR(FilterCategory="Any",C9=FilterCategory),OR(FilterMethod="Any",L9=FilterMethod),OR(FilterTime=0,AND(J9<>"",J9<=FilterTime)),OR(FilterCost=0,AND(AD9<>"",ISNUMBER(AD9),AD9<=FilterCost)),OR(FilterAllergen="Any",COUNTIFS('Recipe Ingredients'!$B$5:$B$1204,A9,'Recipe Ingredients'!$V$5:$V$1204,FilterAllergen)=0)),1,0)) -> 0 | AM9: =IF(AL9=0,"",SUM($AL$5:AL9)) -> 0 | AN9: =IF(B9="","",COUNTIFS($AZ$5:$AZ$204,">"&AZ9)+COUNTIFS($AZ$5:AZ9,AZ9)) -> 0 | AO9: =IF(B9="","",COUNTIFS($AE$5:$AE$204,">"&AE9)+COUNTIFS($AE$5:AE9,AE9)) -> 0 | AP9: =IF(B9="","",COUNTIFS($AF$5:$AF$204,">"&AF9)+COUNTIFS($AF$5:AF9,AF9)) -> 0 | AQ9: =IF(B9="","",COUNTIFS($AI$5:$AI$204,">"&AI9)+COUNTIFS($AI$5:AI9,AI9)) -> 0 | AR9: =IF(B9="","",COUNTIFS($AS$5:$AS$204,">"&AS9)+COUNTIFS($AS$5:AS9,AS9)) -> 0 | AS9: =IF(B9="","",IF(BB9="",99999,BC9)) -> 0 | AT9: =IF(A9="",0,SUMIFS('Meal Plan'!$L$5:$L$504,'Meal Plan'!$G$5:$G$504,A9,'Meal Plan'!$B$5:$B$504,">="&ShopFrom,'Meal Plan'!$B$5:$B$504,"<="&ShopTo,'Meal Plan'!$M$5:$M$504,"Yes")) -> 0 | AU9: =IF(OR(A9="",AC9=""),"",AC9*AT9) -> 0 | AV9: =IF(A9="","",COUNTIFS('Recipe Ingredients'!$B$5:$B$1204,A9,'Recipe Ingredients'!$N$5:$N$1204,"")) -> 0 | AW9: 4 | AX9: 4 | AY9: No | AZ9: =IF(A9="","",COUNTIFS('Meal Plan'!$G$5:$G$504,A9)) -> 0 | BA9: =IF(A9="","",COUNTIFS('Meal Plan'!$G$5:$G$504,A9,'Meal Plan'!$N$5:$N$504,"Prepared")+COUNTIFS('Meal Plan'!$G$5:$G$504,A9,'Meal Plan'!$N$5:$N$504,"Eaten")) -> 0 | BB9: =IF(A9="","",IF(COUNTIFS('Meal Plan'!$G$5:$G$504,A9,'Meal Plan'!$B$5:$B$504,"<="&TODAY())=0,"",SUMPRODUCT(MAX(('Meal Plan'!$G$5:$G$504=A9)*('Meal Plan'!$B$5:$B$504<=TODAY())*'Meal Plan'!$B$5:$B$504)))) -> 0 | BC9: =IF(BB9="","",TODAY()-BB9) -> 0 | BE9: 46024 | BF9: =IF(B9="","",IF(G9="","Add - how many does it serve?",IF(AB9=0,"Add - no ingredients listed yet",IF(AV9>0,"Check - "&AV9&" ingredient(s) have no price",IF(AND(BC9<>"",BC9<RotationGapDays),"Cooked recently","OK"))))) -> 0
A10: =IF(B10="","",RecipePrefix&TEXT(ROW()-4,"0000")) -> 0 | B10: Tomato & mascarpone pasta | C10: Main | D10: Dinner | E10: Italian | F10: Tomato & mascarpone pasta - 5 ingredients, serves 4. | G10: 4 | H10: 5 | I10: 20 | J10: =IF(B10="","",IF(AND(H10="",I10=""),"",IF(H10="",0,H10)+IF(I10="",0,I10))) -> 0 | K10: =IF(J10="","",IF(J10<=30,"Yes","No")) -> 0 | L10: Hob | M10: Easy | N10: Big pan | O10: No | P10: No | Q10: No | R10: No | S10: Yes | T10: Vegetarian | U10: None | V10: All year | W10: twenty minutes flat | AA10: 1. Prep everything first. 2. Cook as usual. 3. Taste before you serve it. | AB10: =IF(A10="","",COUNTIFS('Recipe Ingredients'!$B$5:$B$1204,A10)) -> 0 | AC10: =IF(A10="","",SUMIFS('Recipe Ingredients'!$N$5:$N$1204,'Recipe Ingredients'!$B$5:$B$1204,A10)) -> 0 | AD10: =IF(OR(AC10="",G10=""),"",IF(G10=0,"",AC10/G10)) -> 0 | AE10: =IF(OR(A10="",G10=""),"",IF(G10=0,"",SUMIFS('Recipe Ingredients'!$Q$5:$Q$1204,'Recipe Ingredients'!$B$5:$B$1204,A10)/G10)) -> 0 | AF10: =IF(OR(A10="",G10=""),"",IF(G10=0,"",SUMIFS('Recipe Ingredients'!$R$5:$R$1204,'Recipe Ingredients'!$B$5:$B$1204,A10)/G10)) -> 0 | AG10: =IF(OR(A10="",G10=""),"",IF(G10=0,"",SUMIFS('Recipe Ingredients'!$S$5:$S$1204,'Recipe Ingredients'!$B$5:$B$1204,A10)/G10)) -> 0 | AH10: =IF(OR(A10="",G10=""),"",IF(G10=0,"",SUMIFS('Recipe Ingredients'!$T$5:$T$1204,'Recipe Ingredients'!$B$5:$B$1204,A10)/G10)) -> 0 | AI10: =IF(OR(A10="",G10=""),"",IF(G10=0,"",SUMIFS('Recipe Ingredients'!$U$5:$U$1204,'Recipe Ingredients'!$B$5:$B$1204,A10)/G10)) -> 0 | AJ10: =IF(A10="","",IF(COUNTIFS('Recipe Ingredients'!$B$5:$B$1204,A10,'Recipe Ingredients'!$V$5:$V$1204,"<>",'Recipe Ingredients'!$V$5:$V$1204,"<>None")=0,"None listed",COUNTIFS('Recipe Ingredients'!$B$5:$B$1204,A10,'Recipe Ingredients'!$V$5:$V$1204,"<>",'Recipe Ingredients'!$V$5:$V$1204,"<>None")&" ingredient(s) flagged")) -> 0 | AK10: =IF(OR(AD10="",NOT(ISNUMBER(AD10))),"",COUNTIFS($AD$5:$AD$204,"<"&AD10)+COUNTIFS($AD$5:AD10,AD10)) -> 0 | AL10: =IF(B10="",0,IF(AND(OR(FilterDiet="Any",T10=FilterDiet),OR(FilterCategory="Any",C10=FilterCategory),OR(FilterMethod="Any",L10=FilterMethod),OR(FilterTime=0,AND(J10<>"",J10<=FilterTime)),OR(FilterCost=0,AND(AD10<>"",ISNUMBER(AD10),AD10<=FilterCost)),OR(FilterAllergen="Any",COUNTIFS('Recipe Ingredients'!$B$5:$B$1204,A10,'Recipe Ingredients'!$V$5:$V$1204,FilterAllergen)=0)),1,0)) -> 0 | AM10: =IF(AL10=0,"",SUM($AL$5:AL10)) -> 0 | AN10: =IF(B10="","",COUNTIFS($AZ$5:$AZ$204,">"&AZ10)+COUNTIFS($AZ$5:AZ10,AZ10)) -> 0 | AO10: =IF(B10="","",COUNTIFS($AE$5:$AE$204,">"&AE10)+COUNTIFS($AE$5:AE10,AE10)) -> 0 | AP10: =IF(B10="","",COUNTIFS($AF$5:$AF$204,">"&AF10)+COUNTIFS($AF$5:AF10,AF10)) -> 0 | AQ10: =IF(B10="","",COUNTIFS($AI$5:$AI$204,">"&AI10)+COUNTIFS($AI$5:AI10,AI10)) -> 0 | AR10: =IF(B10="","",COUNTIFS($AS$5:$AS$204,">"&AS10)+COUNTIFS($AS$5:AS10,AS10)) -> 0 | AS10: =IF(B10="","",IF(BB10="",99999,BC10)) -> 0 | AT10: =IF(A10="",0,SUMIFS('Meal Plan'!$L$5:$L$504,'Meal Plan'!$G$5:$G$504,A10,'Meal Plan'!$B$5:$B$504,">="&ShopFrom,'Meal Plan'!$B$5:$B$504,"<="&ShopTo,'Meal Plan'!$M$5:$M$504,"Yes")) -> 0 | AU10: =IF(OR(A10="",AC10=""),"",AC10*AT10) -> 0 | AV10: =IF(A10="","",COUNTIFS('Recipe Ingredients'!$B$5:$B$1204,A10,'Recipe Ingredients'!$N$5:$N$1204,"")) -> 0 | AW10: 4 | AX10: 3 | AY10: No | AZ10: =IF(A10="","",COUNTIFS('Meal Plan'!$G$5:$G$504,A10)) -> 0 | BA10: =IF(A10="","",COUNTIFS('Meal Plan'!$G$5:$G$504,A10,'Meal Plan'!$N$5:$N$504,"Prepared")+COUNTIFS('Meal Plan'!$G$5:$G$504,A10,'Meal Plan'!$N$5:$N$504,"Eaten")) -> 0 | BB10: =IF(A10="","",IF(COUNTIFS('Meal Plan'!$G$5:$G$504,A10,'Meal Plan'!$B$5:$B$504,"<="&TODAY())=0,"",SUMPRODUCT(MAX(('Meal Plan'!$G$5:$G$504=A10)*('Meal Plan'!$B$5:$B$504<=TODAY())*'Meal Plan'!$B$5:$B$504)))) -> 0 | BC10: =IF(BB10="","",TODAY()-BB10) -> 0 | BE10: 46014 | BF10: =IF(B10="","",IF(G10="","Add - how many does it serve?",IF(AB10=0,"Add - no ingredients listed yet",IF(AV10>0,"Check - "&AV10&" ingredient(s) have no price",IF(AND(BC10<>"",BC10<RotationGapDays),"Cooked recently","OK"))))) -> 0
A11: =IF(B11="","",RecipePrefix&TEXT(ROW()-4,"0000")) -> 0 | B11: Chicken fajitas | C11: Main | D11: Dinner | E11: Mexican | F11: Chicken fajitas - 6 ingredients, serves 4. | G11: 4 | H11: 15 | I11: 20 | J11: =IF(B11="","",IF(AND(H11="",I11=""),"",IF(H11="",0,H11)+IF(I11="",0,I11))) -> 0 | K11: =IF(J11="","",IF(J11<=30,"Yes","No")) -> 0 | L11: Hob | M11: Easy | N11: Big pan | O11: No | P11: No | Q11: No | R11: No | S11: Yes | T11: No restriction | U11: Mild | V11: All year | W11: friday night | X11: Family favourite | AA11: 1. Prep everything first. 2. Cook as usual. 3. Taste before you serve it. | AB11: =IF(A11="","",COUNTIFS('Recipe Ingredients'!$B$5:$B$1204,A11)) -> 0 | AC11: =IF(A11="","",SUMIFS('Recipe Ingredients'!$N$5:$N$1204,'Recipe Ingredients'!$B$5:$B$1204,A11)) -> 0 | AD11: =IF(OR(AC11="",G11=""),"",IF(G11=0,"",AC11/G11)) -> 0 | AE11: =IF(OR(A11="",G11=""),"",IF(G11=0,"",SUMIFS('Recipe Ingredients'!$Q$5:$Q$1204,'Recipe Ingredients'!$B$5:$B$1204,A11)/G11)) -> 0 | AF11: =IF(OR(A11="",G11=""),"",IF(G11=0,"",SUMIFS('Recipe Ingredients'!$R$5:$R$1204,'Recipe Ingredients'!$B$5:$B$1204,A11)/G11)) -> 0 | AG11: =IF(OR(A11="",G11=""),"",IF(G11=0,"",SUMIFS('Recipe Ingredients'!$S$5:$S$1204,'Recipe Ingredients'!$B$5:$B$1204,A11)/G11)) -> 0 | AH11: =IF(OR(A11="",G11=""),"",IF(G11=0,"",SUMIFS('Recipe Ingredients'!$T$5:$T$1204,'Recipe Ingredients'!$B$5:$B$1204,A11)/G11)) -> 0 | AI11: =IF(OR(A11="",G11=""),"",IF(G11=0,"",SUMIFS('Recipe Ingredients'!$U$5:$U$1204,'Recipe Ingredients'!$B$5:$B$1204,A11)/G11)) -> 0 | AJ11: =IF(A11="","",IF(COUNTIFS('Recipe Ingredients'!$B$5:$B$1204,A11,'Recipe Ingredients'!$V$5:$V$1204,"<>",'Recipe Ingredients'!$V$5:$V$1204,"<>None")=0,"None listed",COUNTIFS('Recipe Ingredients'!$B$5:$B$1204,A11,'Recipe Ingredients'!$V$5:$V$1204,"<>",'Recipe Ingredients'!$V$5:$V$1204,"<>None")&" ingredient(s) flagged")) -> 0 | AK11: =IF(OR(AD11="",NOT(ISNUMBER(AD11))),"",COUNTIFS($AD$5:$AD$204,"<"&AD11)+COUNTIFS($AD$5:AD11,AD11)) -> 0 | AL11: =IF(B11="",0,IF(AND(OR(FilterDiet="Any",T11=FilterDiet),OR(FilterCategory="Any",C11=FilterCategory),OR(FilterMethod="Any",L11=FilterMethod),OR(FilterTime=0,AND(J11<>"",J11<=FilterTime)),OR(FilterCost=0,AND(AD11<>"",ISNUMBER(AD11),AD11<=FilterCost)),OR(FilterAllergen="Any",COUNTIFS('Recipe Ingredients'!$B$5:$B$1204,A11,'Recipe Ingredients'!$V$5:$V$1204,FilterAllergen)=0)),1,0)) -> 0 | AM11: =IF(AL11=0,"",SUM($AL$5:AL11)) -> 0 | AN11: =IF(B11="","",COUNTIFS($AZ$5:$AZ$204,">"&AZ11)+COUNTIFS($AZ$5:AZ11,AZ11)) -> 0 | AO11: =IF(B11="","",COUNTIFS($AE$5:$AE$204,">"&AE11)+COUNTIFS($AE$5:AE11,AE11)) -> 0 | AP11: =IF(B11="","",COUNTIFS($AF$5:$AF$204,">"&AF11)+COUNTIFS($AF$5:AF11,AF11)) -> 0 | AQ11: =IF(B11="","",COUNTIFS($AI$5:$AI$204,">"&AI11)+COUNTIFS($AI$5:AI11,AI11)) -> 0 | AR11: =IF(B11="","",COUNTIFS($AS$5:$AS$204,">"&AS11)+COUNTIFS($AS$5:AS11,AS11)) -> 0 | AS11: =IF(B11="","",IF(BB11="",99999,BC11)) -> 0 | AT11: =IF(A11="",0,SUMIFS('Meal Plan'!$L$5:$L$504,'Meal Plan'!$G$5:$G$504,A11,'Meal Plan'!$B$5:$B$504,">="&ShopFrom,'Meal Plan'!$B$5:$B$504,"<="&ShopTo,'Meal Plan'!$M$5:$M$504,"Yes")) -> 0 | AU11: =IF(OR(A11="",AC11=""),"",AC11*AT11) -> 0 | AV11: =IF(A11="","",COUNTIFS('Recipe Ingredients'!$B$5:$B$1204,A11,'Recipe Ingredients'!$N$5:$N$1204,"")) -> 0 | AW11: 5 | AX11: 5 | AY11: Yes | AZ11: =IF(A11="","",COUNTIFS('Meal Plan'!$G$5:$G$504,A11)) -> 0 | BA11: =IF(A11="","",COUNTIFS('Meal Plan'!$G$5:$G$504,A11,'Meal Plan'!$N$5:$N$504,"Prepared")+COUNTIFS('Meal Plan'!$G$5:$G$504,A11,'Meal Plan'!$N$5:$N$504,"Eaten")) -> 0 | BB11: =IF(A11="","",IF(COUNTIFS('Meal Plan'!$G$5:$G$504,A11,'Meal Plan'!$B$5:$B$504,"<="&TODAY())=0,"",SUMPRODUCT(MAX(('Meal Plan'!$G$5:$G$504=A11)*('Meal Plan'!$B$5:$B$504<=TODAY())*'Meal Plan'!$B$5:$B$504)))) -> 0 | BC11: =IF(BB11="","",TODAY()-BB11) -> 0 | BE11: 46027 | BF11: =IF(B11="","",IF(G11="","Add - how many does it serve?",IF(AB11=0,"Add - no ingredients listed yet",IF(AV11>0,"Check - "&AV11&" ingredient(s) have no price",IF(AND(BC11<>"",BC11<RotationGapDays),"Cooked recently","OK"))))) -> 0
A12: =IF(B12="","",RecipePrefix&TEXT(ROW()-4,"0000")) -> 0 | B12: Black bean chilli | C12: Main | D12: Dinner | E12: Mexican | F12: Black bean chilli - 6 ingredients, serves 6. | G12: 6 | H12: 15 | I12: 40 | J12: =IF(B12="","",IF(AND(H12="",I12=""),"",IF(H12="",0,H12)+IF(I12="",0,I12))) -> 0 | K12: =IF(J12="","",IF(J12<=30,"Yes","No")) -> 0 | L12: Slow cooker | M12: Easy | N12: Slow cooker | O12: Yes | P12: No | Q12: Yes | R12: Yes | S12: Yes | T12: Vegan | U12: Mild | V12: All year | W12: batch base | AA12: 1. Prep everything first. 2. Cook as usual. 3. Taste before you serve it. | AB12: =IF(A12="","",COUNTIFS('Recipe Ingredients'!$B$5:$B$1204,A12)) -> 0 | AC12: =IF(A12="","",SUMIFS('Recipe Ingredients'!$N$5:$N$1204,'Recipe Ingredients'!$B$5:$B$1204,A12)) -> 0 | AD12: =IF(OR(AC12="",G12=""),"",IF(G12=0,"",AC12/G12)) -> 0 | AE12: =IF(OR(A12="",G12=""),"",IF(G12=0,"",SUMIFS('Recipe Ingredients'!$Q$5:$Q$1204,'Recipe Ingredients'!$B$5:$B$1204,A12)/G12)) -> 0 | AF12: =IF(OR(A12="",G12=""),"",IF(G12=0,"",SUMIFS('Recipe Ingredients'!$R$5:$R$1204,'Recipe Ingredients'!$B$5:$B$1204,A12)/G12)) -> 0 | AG12: =IF(OR(A12="",G12=""),"",IF(G12=0,"",SUMIFS('Recipe Ingredients'!$S$5:$S$1204,'Recipe Ingredients'!$B$5:$B$1204,A12)/G12)) -> 0 | AH12: =IF(OR(A12="",G12=""),"",IF(G12=0,"",SUMIFS('Recipe Ingredients'!$T$5:$T$1204,'Recipe Ingredients'!$B$5:$B$1204,A12)/G12)) -> 0 | AI12: =IF(OR(A12="",G12=""),"",IF(G12=0,"",SUMIFS('Recipe Ingredients'!$U$5:$U$1204,'Recipe Ingredients'!$B$5:$B$1204,A12)/G12)) -> 0 | AJ12: =IF(A12="","",IF(COUNTIFS('Recipe Ingredients'!$B$5:$B$1204,A12,'Recipe Ingredients'!$V$5:$V$1204,"<>",'Recipe Ingredients'!$V$5:$V$1204,"<>None")=0,"None listed",COUNTIFS('Recipe Ingredients'!$B$5:$B$1204,A12,'Recipe Ingredients'!$V$5:$V$1204,"<>",'Recipe Ingredients'!$V$5:$V$1204,"<>None")&" ingredient(s) flagged")) -> 0 | AK12: =IF(OR(AD12="",NOT(ISNUMBER(AD12))),"",COUNTIFS($AD$5:$AD$204,"<"&AD12)+COUNTIFS($AD$5:AD12,AD12)) -> 0 | AL12: =IF(B12="",0,IF(AND(OR(FilterDiet="Any",T12=FilterDiet),OR(FilterCategory="Any",C12=FilterCategory),OR(FilterMethod="Any",L12=FilterMethod),OR(FilterTime=0,AND(J12<>"",J12<=FilterTime)),OR(FilterCost=0,AND(AD12<>"",ISNUMBER(AD12),AD12<=FilterCost)),OR(FilterAllergen="Any",COUNTIFS('Recipe Ingredients'!$B$5:$B$1204,A12,'Recipe Ingredients'!$V$5:$V$1204,FilterAllergen)=0)),1,0)) -> 0 | AM12: =IF(AL12=0,"",SUM($AL$5:AL12)) -> 0 | AN12: =IF(B12="","",COUNTIFS($AZ$5:$AZ$204,">"&AZ12)+COUNTIFS($AZ$5:AZ12,AZ12)) -> 0 | AO12: =IF(B12="","",COUNTIFS($AE$5:$AE$204,">"&AE12)+COUNTIFS($AE$5:AE12,AE12)) -> 0 | AP12: =IF(B12="","",COUNTIFS($AF$5:$AF$204,">"&AF12)+COUNTIFS($AF$5:AF12,AF12)) -> 0 | AQ12: =IF(B12="","",COUNTIFS($AI$5:$AI$204,">"&AI12)+COUNTIFS($AI$5:AI12,AI12)) -> 0 | AR12: =IF(B12="","",COUNTIFS($AS$5:$AS$204,">"&AS12)+COUNTIFS($AS$5:AS12,AS12)) -> 0 | AS12: =IF(B12="","",IF(BB12="",99999,BC12)) -> 0 | AT12: =IF(A12="",0,SUMIFS('Meal Plan'!$L$5:$L$504,'Meal Plan'!$G$5:$G$504,A12,'Meal Plan'!$B$5:$B$504,">="&ShopFrom,'Meal Plan'!$B$5:$B$504,"<="&ShopTo,'Meal Plan'!$M$5:$M$504,"Yes")) -> 0 | AU12: =IF(OR(A12="",AC12=""),"",AC12*AT12) -> 0 | AV12: =IF(A12="","",COUNTIFS('Recipe Ingredients'!$B$5:$B$1204,A12,'Recipe Ingredients'!$N$5:$N$1204,"")) -> 0 | AW12: 4 | AX12: 3 | AY12: No | AZ12: =IF(A12="","",COUNTIFS('Meal Plan'!$G$5:$G$504,A12)) -> 0 | BA12: =IF(A12="","",COUNTIFS('Meal Plan'!$G$5:$G$504,A12,'Meal Plan'!$N$5:$N$504,"Prepared")+COUNTIFS('Meal Plan'!$G$5:$G$504,A12,'Meal Plan'!$N$5:$N$504,"Eaten")) -> 0 | BB12: =IF(A12="","",IF(COUNTIFS('Meal Plan'!$G$5:$G$504,A12,'Meal Plan'!$B$5:$B$504,"<="&TODAY())=0,"",SUMPRODUCT(MAX(('Meal Plan'!$G$5:$G$504=A12)*('Meal Plan'!$B$5:$B$504<=TODAY())*'Meal Plan'!$B$5:$B$504)))) -> 0 | BC12: =IF(BB12="","",TODAY()-BB12) -> 0 | BE12: 45958 | BF12: =IF(B12="","",IF(G12="","Add - how many does it serve?",IF(AB12=0,"Add - no ingredients listed yet",IF(AV12>0,"Check - "&AV12&" ingredient(s) have no price",IF(AND(BC12<>"",BC12<RotationGapDays),"Cooked recently","OK"))))) -> 0
A13: =IF(B13="","",RecipePrefix&TEXT(ROW()-4,"0000")) -> 0 | B13: Veg-packed shepherd's pie | C13: Main | D13: Dinner | E13: British | F13: Veg-packed shepherd's pie - 7 ingredients, serves 6. | G13: 6 | H13: 25 | I13: 50 | J13: =IF(B13="","",IF(AND(H13="",I13=""),"",IF(H13="",0,H13)+IF(I13="",0,I13))) -> 0 | K13: =IF(J13="","",IF(J13<=30,"Yes","No")) -> 0 | L13: Oven | M13: Medium | N13: Roasting tin | O13: No | P13: No | Q13: Yes | R13: Yes | S13: Yes | T13: No restriction | U13: None | V13: All year | W13: hides the carrots | X13: Family favourite | AA13: 1. Prep everything first. 2. Cook as usual. 3. Taste before you serve it. | AB13: =IF(A13="","",COUNTIFS('Recipe Ingredients'!$B$5:$B$1204,A13)) -> 0 | AC13: =IF(A13="","",SUMIFS('Recipe Ingredients'!$N$5:$N$1204,'Recipe Ingredients'!$B$5:$B$1204,A13)) -> 0 | AD13: =IF(OR(AC13="",G13=""),"",IF(G13=0,"",AC13/G13)) -> 0 | AE13: =IF(OR(A13="",G13=""),"",IF(G13=0,"",SUMIFS('Recipe Ingredients'!$Q$5:$Q$1204,'Recipe Ingredients'!$B$5:$B$1204,A13)/G13)) -> 0 | AF13: =IF(OR(A13="",G13=""),"",IF(G13=0,"",SUMIFS('Recipe Ingredients'!$R$5:$R$1204,'Recipe Ingredients'!$B$5:$B$1204,A13)/G13)) -> 0 | AG13: =IF(OR(A13="",G13=""),"",IF(G13=0,"",SUMIFS('Recipe Ingredients'!$S$5:$S$1204,'Recipe Ingredients'!$B$5:$B$1204,A13)/G13)) -> 0 | AH13: =IF(OR(A13="",G13=""),"",IF(G13=0,"",SUMIFS('Recipe Ingredients'!$T$5:$T$1204,'Recipe Ingredients'!$B$5:$B$1204,A13)/G13)) -> 0 | AI13: =IF(OR(A13="",G13=""),"",IF(G13=0,"",SUMIFS('Recipe Ingredients'!$U$5:$U$1204,'Recipe Ingredients'!$B$5:$B$1204,A13)/G13)) -> 0 | AJ13: =IF(A13="","",IF(COUNTIFS('Recipe Ingredients'!$B$5:$B$1204,A13,'Recipe Ingredients'!$V$5:$V$1204,"<>",'Recipe Ingredients'!$V$5:$V$1204,"<>None")=0,"None listed",COUNTIFS('Recipe Ingredients'!$B$5:$B$1204,A13,'Recipe Ingredients'!$V$5:$V$1204,"<>",'Recipe Ingredients'!$V$5:$V$1204,"<>None")&" ingredient(s) flagged")) -> 0 | AK13: =IF(OR(AD13="",NOT(ISNUMBER(AD13))),"",COUNTIFS($AD$5:$AD$204,"<"&AD13)+COUNTIFS($AD$5:AD13,AD13)) -> 0 | AL13: =IF(B13="",0,IF(AND(OR(FilterDiet="Any",T13=FilterDiet),OR(FilterCategory="Any",C13=FilterCategory),OR(FilterMethod="Any",L13=FilterMethod),OR(FilterTime=0,AND(J13<>"",J13<=FilterTime)),OR(FilterCost=0,AND(AD13<>"",ISNUMBER(AD13),AD13<=FilterCost)),OR(FilterAllergen="Any",COUNTIFS('Recipe Ingredients'!$B$5:$B$1204,A13,'Recipe Ingredients'!$V$5:$V$1204,FilterAllergen)=0)),1,0)) -> 0 | AM13: =IF(AL13=0,"",SUM($AL$5:AL13)) -> 0 | AN13: =IF(B13="","",COUNTIFS($AZ$5:$AZ$204,">"&AZ13)+COUNTIFS($AZ$5:AZ13,AZ13)) -> 0 | AO13: =IF(B13="","",COUNTIFS($AE$5:$AE$204,">"&AE13)+COUNTIFS($AE$5:AE13,AE13)) -> 0 | AP13: =IF(B13="","",COUNTIFS($AF$5:$AF$204,">"&AF13)+COUNTIFS($AF$5:AF13,AF13)) -> 0 | AQ13: =IF(B13="","",COUNTIFS($AI$5:$AI$204,">"&AI13)+COUNTIFS($AI$5:AI13,AI13)) -> 0 | AR13: =IF(B13="","",COUNTIFS($AS$5:$AS$204,">"&AS13)+COUNTIFS($AS$5:AS13,AS13)) -> 0 | AS13: =IF(B13="","",IF(BB13="",99999,BC13)) -> 0 | AT13: =IF(A13="",0,SUMIFS('Meal Plan'!$L$5:$L$504,'Meal Plan'!$G$5:$G$504,A13,'Meal Plan'!$B$5:$B$504,">="&ShopFrom,'Meal Plan'!$B$5:$B$504,"<="&ShopTo,'Meal Plan'!$M$5:$M$504,"Yes")) -> 0 | AU13: =IF(OR(A13="",AC13=""),"",AC13*AT13) -> 0 | AV13: =IF(A13="","",COUNTIFS('Recipe Ingredients'!$B$5:$B$1204,A13,'Recipe Ingredients'!$N$5:$N$1204,"")) -> 0 | AW13: 5 | AX13: 5 | AY13: Yes | AZ13: =IF(A13="","",COUNTIFS('Meal Plan'!$G$5:$G$504,A13)) -> 0 | BA13: =IF(A13="","",COUNTIFS('Meal Plan'!$G$5:$G$504,A13,'Meal Plan'!$N$5:$N$504,"Prepared")+COUNTIFS('Meal Plan'!$G$5:$G$504,A13,'Meal Plan'!$N$5:$N$504,"Eaten")) -> 0 | BB13: =IF(A13="","",IF(COUNTIFS('Meal Plan'!$G$5:$G$504,A13,'Meal Plan'!$B$5:$B$504,"<="&TODAY())=0,"",SUMPRODUCT(MAX(('Meal Plan'!$G$5:$G$504=A13)*('Meal Plan'!$B$5:$B$504<=TODAY())*'Meal Plan'!$B$5:$B$504)))) -> 0 | BC13: =IF(BB13="","",TODAY()-BB13) -> 0 | BE13: 46001 | BF13: =IF(B13="","",IF(G13="","Add - how many does it serve?",IF(AB13=0,"Add - no ingredients listed yet",IF(AV13>0,"Check - "&AV13&" ingredient(s) have no price",IF(AND(BC13<>"",BC13<RotationGapDays),"Cooked recently","OK"))))) -> 0
A14: =IF(B14="","",RecipePrefix&TEXT(ROW()-4,"0000")) -> 0 | B14: Teriyaki salmon & rice | C14: Main | D14: Dinner | E14: Japanese | F14: Teriyaki salmon & rice - 5 ingredients, serves 2. | G14: 2 | H14: 10 | I14: 20 | J14: =IF(B14="","",IF(AND(H14="",I14=""),"",IF(H14="",0,H14)+IF(I14="",0,I14))) -> 0 | K14: =IF(J14="","",IF(J14<=30,"Yes","No")) -> 0 | L14: Hob | M14: Easy | N14: Big pan | O14: No | P14: No | Q14: No | R14: No | S14: No | T14: Pescatarian | U14: None | V14: All year | AA14: 1. Prep everything first. 2. Cook as usual. 3. Taste before you serve it. | AB14: =IF(A14="","",COUNTIFS('Recipe Ingredients'!$B$5:$B$1204,A14)) -> 0 | AC14: =IF(A14="","",SUMIFS('Recipe Ingredients'!$N$5:$N$1204,'Recipe Ingredients'!$B$5:$B$1204,A14)) -> 0 | AD14: =IF(OR(AC14="",G14=""),"",IF(G14=0,"",AC14/G14)) -> 0 | AE14: =IF(OR(A14="",G14=""),"",IF(G14=0,"",SUMIFS('Recipe Ingredients'!$Q$5:$Q$1204,'Recipe Ingredients'!$B$5:$B$1204,A14)/G14)) -> 0 | AF14: =IF(OR(A14="",G14=""),"",IF(G14=0,"",SUMIFS('Recipe Ingredients'!$R$5:$R$1204,'Recipe Ingredients'!$B$5:$B$1204,A14)/G14)) -> 0 | AG14: =IF(OR(A14="",G14=""),"",IF(G14=0,"",SUMIFS('Recipe Ingredients'!$S$5:$S$1204,'Recipe Ingredients'!$B$5:$B$1204,A14)/G14)) -> 0 | AH14: =IF(OR(A14="",G14=""),"",IF(G14=0,"",SUMIFS('Recipe Ingredients'!$T$5:$T$1204,'Recipe Ingredients'!$B$5:$B$1204,A14)/G14)) -> 0 | AI14: =IF(OR(A14="",G14=""),"",IF(G14=0,"",SUMIFS('Recipe Ingredients'!$U$5:$U$1204,'Recipe Ingredients'!$B$5:$B$1204,A14)/G14)) -> 0 | AJ14: =IF(A14="","",IF(COUNTIFS('Recipe Ingredients'!$B$5:$B$1204,A14,'Recipe Ingredients'!$V$5:$V$1204,"<>",'Recipe Ingredients'!$V$5:$V$1204,"<>None")=0,"None listed",COUNTIFS('Recipe Ingredients'!$B$5:$B$1204,A14,'Recipe Ingredients'!$V$5:$V$1204,"<>",'Recipe Ingredients'!$V$5:$V$1204,"<>None")&" ingredient(s) flagged")) -> 0 | AK14: =IF(OR(AD14="",NOT(ISNUMBER(AD14))),"",COUNTIFS($AD$5:$AD$204,"<"&AD14)+COUNTIFS($AD$5:AD14,AD14)) -> 0 | AL14: =IF(B14="",0,IF(AND(OR(FilterDiet="Any",T14=FilterDiet),OR(FilterCategory="Any",C14=FilterCategory),OR(FilterMethod="Any",L14=FilterMethod),OR(FilterTime=0,AND(J14<>"",J14<=FilterTime)),OR(FilterCost=0,AND(AD14<>"",ISNUMBER(AD14),AD14<=FilterCost)),OR(FilterAllergen="Any",COUNTIFS('Recipe Ingredients'!$B$5:$B$1204,A14,'Recipe Ingredients'!$V$5:$V$1204,FilterAllergen)=0)),1,0)) -> 0 | AM14: =IF(AL14=0,"",SUM($AL$5:AL14)) -> 0 | AN14: =IF(B14="","",COUNTIFS($AZ$5:$AZ$204,">"&AZ14)+COUNTIFS($AZ$5:AZ14,AZ14)) -> 0 | AO14: =IF(B14="","",COUNTIFS($AE$5:$AE$204,">"&AE14)+COUNTIFS($AE$5:AE14,AE14)) -> 0 | AP14: =IF(B14="","",COUNTIFS($AF$5:$AF$204,">"&AF14)+COUNTIFS($AF$5:AF14,AF14)) -> 0 | AQ14: =IF(B14="","",COUNTIFS($AI$5:$AI$204,">"&AI14)+COUNTIFS($AI$5:AI14,AI14)) -> 0 | AR14: =IF(B14="","",COUNTIFS($AS$5:$AS$204,">"&AS14)+COUNTIFS($AS$5:AS14,AS14)) -> 0 | AS14: =IF(B14="","",IF(BB14="",99999,BC14)) -> 0 | AT14: =IF(A14="",0,SUMIFS('Meal Plan'!$L$5:$L$504,'Meal Plan'!$G$5:$G$504,A14,'Meal Plan'!$B$5:$B$504,">="&ShopFrom,'Meal Plan'!$B$5:$B$504,"<="&ShopTo,'Meal Plan'!$M$5:$M$504,"Yes")) -> 0 | AU14: =IF(OR(A14="",AC14=""),"",AC14*AT14) -> 0 | AV14: =IF(A14="","",COUNTIFS('Recipe Ingredients'!$B$5:$B$1204,A14,'Recipe Ingredients'!$N$5:$N$1204,"")) -> 0 | AW14: 4 | AX14: 3 | AY14: No | AZ14: =IF(A14="","",COUNTIFS('Meal Plan'!$G$5:$G$504,A14)) -> 0 | BA14: =IF(A14="","",COUNTIFS('Meal Plan'!$G$5:$G$504,A14,'Meal Plan'!$N$5:$N$504,"Prepared")+COUNTIFS('Meal Plan'!$G$5:$G$504,A14,'Meal Plan'!$N$5:$N$504,"Eaten")) -> 0 | BB14: =IF(A14="","",IF(COUNTIFS('Meal Plan'!$G$5:$G$504,A14,'Meal Plan'!$B$5:$B$504,"<="&TODAY())=0,"",SUMPRODUCT(MAX(('Meal Plan'!$G$5:$G$504=A14)*('Meal Plan'!$B$5:$B$504<=TODAY())*'Meal Plan'!$B$5:$B$504)))) -> 0 | BC14: =IF(BB14="","",TODAY()-BB14) -> 0 | BE14: 45997 | BF14: =IF(B14="","",IF(G14="","Add - how many does it serve?",IF(AB14=0,"Add - no ingredients listed yet",IF(AV14>0,"Check - "&AV14&" ingredient(s) have no price",IF(AND(BC14<>"",BC14<RotationGapDays),"Cooked recently","OK"))))) -> 0
A15: =IF(B15="","",RecipePrefix&TEXT(ROW()-4,"0000")) -> 0 | B15: Overnight oats | C15: Breakfast | D15: Breakfast | E15: British | F15: Overnight oats - 5 ingredients, serves 2. | G15: 2 | H15: 5 | I15: 0 | J15: =IF(B15="","",IF(AND(H15="",I15=""),"",IF(H15="",0,H15)+IF(I15="",0,I15))) -> 0 | K15: =IF(J15="","",IF(J15<=30,"Yes","No")) -> 0 | L15: No cook | M15: Easy | O15: No | P15: Yes | Q15: Yes | R15: No | S15: Yes | T15: Vegetarian | U15: None | V15: All year | W15: make it the night before | AA15: 1. Prep everything first. 2. Cook as usual. 3. Taste before you serve it. | AB15: =IF(A15="","",COUNTIFS('Recipe Ingredients'!$B$5:$B$1204,A15)) -> 0 | AC15: =IF(A15="","",SUMIFS('Recipe Ingredients'!$N$5:$N$1204,'Recipe Ingredients'!$B$5:$B$1204,A15)) -> 0 | AD15: =IF(OR(AC15="",G15=""),"",IF(G15=0,"",AC15/G15)) -> 0 | AE15: =IF(OR(A15="",G15=""),"",IF(G15=0,"",SUMIFS('Recipe Ingredients'!$Q$5:$Q$1204,'Recipe Ingredients'!$B$5:$B$1204,A15)/G15)) -> 0 | AF15: =IF(OR(A15="",G15=""),"",IF(G15=0,"",SUMIFS('Recipe Ingredients'!$R$5:$R$1204,'Recipe Ingredients'!$B$5:$B$1204,A15)/G15)) -> 0 | AG15: =IF(OR(A15="",G15=""),"",IF(G15=0,"",SUMIFS('Recipe Ingredients'!$S$5:$S$1204,'Recipe Ingredients'!$B$5:$B$1204,A15)/G15)) -> 0 | AH15: =IF(OR(A15="",G15=""),"",IF(G15=0,"",SUMIFS('Recipe Ingredients'!$T$5:$T$1204,'Recipe Ingredients'!$B$5:$B$1204,A15)/G15)) -> 0 | AI15: =IF(OR(A15="",G15=""),"",IF(G15=0,"",SUMIFS('Recipe Ingredients'!$U$5:$U$1204,'Recipe Ingredients'!$B$5:$B$1204,A15)/G15)) -> 0 | AJ15: =IF(A15="","",IF(COUNTIFS('Recipe Ingredients'!$B$5:$B$1204,A15,'Recipe Ingredients'!$V$5:$V$1204,"<>",'Recipe Ingredients'!$V$5:$V$1204,"<>None")=0,"None listed",COUNTIFS('Recipe Ingredients'!$B$5:$B$1204,A15,'Recipe Ingredients'!$V$5:$V$1204,"<>",'Recipe Ingredients'!$V$5:$V$1204,"<>None")&" ingredient(s) flagged")) -> 0 | AK15: =IF(OR(AD15="",NOT(ISNUMBER(AD15))),"",COUNTIFS($AD$5:$AD$204,"<"&AD15)+COUNTIFS($AD$5:AD15,AD15)) -> 0 | AL15: =IF(B15="",0,IF(AND(OR(FilterDiet="Any",T15=FilterDiet),OR(FilterCategory="Any",C15=FilterCategory),OR(FilterMethod="Any",L15=FilterMethod),OR(FilterTime=0,AND(J15<>"",J15<=FilterTime)),OR(FilterCost=0,AND(AD15<>"",ISNUMBER(AD15),AD15<=FilterCost)),OR(FilterAllergen="Any",COUNTIFS('Recipe Ingredients'!$B$5:$B$1204,A15,'Recipe Ingredients'!$V$5:$V$1204,FilterAllergen)=0)),1,0)) -> 0 | AM15: =IF(AL15=0,"",SUM($AL$5:AL15)) -> 0 | AN15: =IF(B15="","",COUNTIFS($AZ$5:$AZ$204,">"&AZ15)+COUNTIFS($AZ$5:AZ15,AZ15)) -> 0 | AO15: =IF(B15="","",COUNTIFS($AE$5:$AE$204,">"&AE15)+COUNTIFS($AE$5:AE15,AE15)) -> 0 | AP15: =IF(B15="","",COUNTIFS($AF$5:$AF$204,">"&AF15)+COUNTIFS($AF$5:AF15,AF15)) -> 0 | AQ15: =IF(B15="","",COUNTIFS($AI$5:$AI$204,">"&AI15)+COUNTIFS($AI$5:AI15,AI15)) -> 0 | AR15: =IF(B15="","",COUNTIFS($AS$5:$AS$204,">"&AS15)+COUNTIFS($AS$5:AS15,AS15)) -> 0 | AS15: =IF(B15="","",IF(BB15="",99999,BC15)) -> 0 | AT15: =IF(A15="",0,SUMIFS('Meal Plan'!$L$5:$L$504,'Meal Plan'!$G$5:$G$504,A15,'Meal Plan'!$B$5:$B$504,">="&ShopFrom,'Meal Plan'!$B$5:$B$504,"<="&ShopTo,'Meal Plan'!$M$5:$M$504,"Yes")) -> 0 | AU15: =IF(OR(A15="",AC15=""),"",AC15*AT15) -> 0 | AV15: =IF(A15="","",COUNTIFS('Recipe Ingredients'!$B$5:$B$1204,A15,'Recipe Ingredients'!$N$5:$N$1204,"")) -> 0 | AW15: 4 | AX15: 4 | AY15: No | AZ15: =IF(A15="","",COUNTIFS('Meal Plan'!$G$5:$G$504,A15)) -> 0 | BA15: =IF(A15="","",COUNTIFS('Meal Plan'!$G$5:$G$504,A15,'Meal Plan'!$N$5:$N$504,"Prepared")+COUNTIFS('Meal Plan'!$G$5:$G$504,A15,'Meal Plan'!$N$5:$N$504,"Eaten")) -> 0 | BB15: =IF(A15="","",IF(COUNTIFS('Meal Plan'!$G$5:$G$504,A15,'Meal Plan'!$B$5:$B$504,"<="&TODAY())=0,"",SUMPRODUCT(MAX(('Meal Plan'!$G$5:$G$504=A15)*('Meal Plan'!$B$5:$B$504<=TODAY())*'Meal Plan'!$B$5:$B$504)))) -> 0 | BC15: =IF(BB15="","",TODAY()-BB15) -> 0 | BE15: 46073 | BF15: =IF(B15="","",IF(G15="","Add - how many does it serve?",IF(AB15=0,"Add - no ingredients listed yet",IF(AV15>0,"Check - "&AV15&" ingredient(s) have no price",IF(AND(BC15<>"",BC15<RotationGapDays),"Cooked recently","OK"))))) -> 0
A16: =IF(B16="","",RecipePrefix&TEXT(ROW()-4,"0000")) -> 0 | B16: Scrambled eggs on toast | C16: Breakfast | D16: Breakfast | E16: British | F16: Scrambled eggs on toast - 4 ingredients, serves 2. | G16: 2 | H16: 5 | I16: 8 | J16: =IF(B16="","",IF(AND(H16="",I16=""),"",IF(H16="",0,H16)+IF(I16="",0,I16))) -> 0 | K16: =IF(J16="","",IF(J16<=30,"Yes","No")) -> 0 | L16: Hob | M16: Easy | N16: Big pan | O16: No | P16: No | Q16: No | R16: No | S16: Yes | T16: Vegetarian | U16: None | V16: All year | AA16: 1. Prep everything first. 2. Cook as usual. 3. Taste before you serve it. | AB16: =IF(A16="","",COUNTIFS('Recipe Ingredients'!$B$5:$B$1204,A16)) -> 0 | AC16: =IF(A16="","",SUMIFS('Recipe Ingredients'!$N$5:$N$1204,'Recipe Ingredients'!$B$5:$B$1204,A16)) -> 0 | AD16: =IF(OR(AC16="",G16=""),"",IF(G16=0,"",AC16/G16)) -> 0 | AE16: =IF(OR(A16="",G16=""),"",IF(G16=0,"",SUMIFS('Recipe Ingredients'!$Q$5:$Q$1204,'Recipe Ingredients'!$B$5:$B$1204,A16)/G16)) -> 0 | AF16: =IF(OR(A16="",G16=""),"",IF(G16=0,"",SUMIFS('Recipe Ingredients'!$R$5:$R$1204,'Recipe Ingredients'!$B$5:$B$1204,A16)/G16)) -> 0 | AG16: =IF(OR(A16="",G16=""),"",IF(G16=0,"",SUMIFS('Recipe Ingredients'!$S$5:$S$1204,'Recipe Ingredients'!$B$5:$B$1204,A16)/G16)) -> 0 | AH16: =IF(OR(A16="",G16=""),"",IF(G16=0,"",SUMIFS('Recipe Ingredients'!$T$5:$T$1204,'Recipe Ingredients'!$B$5:$B$1204,A16)/G16)) -> 0 | AI16: =IF(OR(A16="",G16=""),"",IF(G16=0,"",SUMIFS('Recipe Ingredients'!$U$5:$U$1204,'Recipe Ingredients'!$B$5:$B$1204,A16)/G16)) -> 0 | AJ16: =IF(A16="","",IF(COUNTIFS('Recipe Ingredients'!$B$5:$B$1204,A16,'Recipe Ingredients'!$V$5:$V$1204,"<>",'Recipe Ingredients'!$V$5:$V$1204,"<>None")=0,"None listed",COUNTIFS('Recipe Ingredients'!$B$5:$B$1204,A16,'Recipe Ingredients'!$V$5:$V$1204,"<>",'Recipe Ingredients'!$V$5:$V$1204,"<>None")&" ingredient(s) flagged")) -> 0 | AK16: =IF(OR(AD16="",NOT(ISNUMBER(AD16))),"",COUNTIFS($AD$5:$AD$204,"<"&AD16)+COUNTIFS($AD$5:AD16,AD16)) -> 0 | AL16: =IF(B16="",0,IF(AND(OR(FilterDiet="Any",T16=FilterDiet),OR(FilterCategory="Any",C16=FilterCategory),OR(FilterMethod="Any",L16=FilterMethod),OR(FilterTime=0,AND(J16<>"",J16<=FilterTime)),OR(FilterCost=0,AND(AD16<>"",ISNUMBER(AD16),AD16<=FilterCost)),OR(FilterAllergen="Any",COUNTIFS('Recipe Ingredients'!$B$5:$B$1204,A16,'Recipe Ingredients'!$V$5:$V$1204,FilterAllergen)=0)),1,0)) -> 0 | AM16: =IF(AL16=0,"",SUM($AL$5:AL16)) -> 0 | AN16: =IF(B16="","",COUNTIFS($AZ$5:$AZ$204,">"&AZ16)+COUNTIFS($AZ$5:AZ16,AZ16)) -> 0 | AO16: =IF(B16="","",COUNTIFS($AE$5:$AE$204,">"&AE16)+COUNTIFS($AE$5:AE16,AE16)) -> 0 | AP16: =IF(B16="","",COUNTIFS($AF$5:$AF$204,">"&AF16)+COUNTIFS($AF$5:AF16,AF16)) -> 0 | AQ16: =IF(B16="","",COUNTIFS($AI$5:$AI$204,">"&AI16)+COUNTIFS($AI$5:AI16,AI16)) -> 0 | AR16: =IF(B16="","",COUNTIFS($AS$5:$AS$204,">"&AS16)+COUNTIFS($AS$5:AS16,AS16)) -> 0 | AS16: =IF(B16="","",IF(BB16="",99999,BC16)) -> 0 | AT16: =IF(A16="",0,SUMIFS('Meal Plan'!$L$5:$L$504,'Meal Plan'!$G$5:$G$504,A16,'Meal Plan'!$B$5:$B$504,">="&ShopFrom,'Meal Plan'!$B$5:$B$504,"<="&ShopTo,'Meal Plan'!$M$5:$M$504,"Yes")) -> 0 | AU16: =IF(OR(A16="",AC16=""),"",AC16*AT16) -> 0 | AV16: =IF(A16="","",COUNTIFS('Recipe Ingredients'!$B$5:$B$1204,A16,'Recipe Ingredients'!$N$5:$N$1204,"")) -> 0 | AW16: 4 | AX16: 3 | AY16: No | AZ16: =IF(A16="","",COUNTIFS('Meal Plan'!$G$5:$G$504,A16)) -> 0 | BA16: =IF(A16="","",COUNTIFS('Meal Plan'!$G$5:$G$504,A16,'Meal Plan'!$N$5:$N$504,"Prepared")+COUNTIFS('Meal Plan'!$G$5:$G$504,A16,'Meal Plan'!$N$5:$N$504,"Eaten")) -> 0 | BB16: =IF(A16="","",IF(COUNTIFS('Meal Plan'!$G$5:$G$504,A16,'Meal Plan'!$B$5:$B$504,"<="&TODAY())=0,"",SUMPRODUCT(MAX(('Meal Plan'!$G$5:$G$504=A16)*('Meal Plan'!$B$5:$B$504<=TODAY())*'Meal Plan'!$B$5:$B$504)))) -> 0 | BC16: =IF(BB16="","",TODAY()-BB16) -> 0 | BE16: 46147 | BF16: =IF(B16="","",IF(G16="","Add - how many does it serve?",IF(AB16=0,"Add - no ingredients listed yet",IF(AV16>0,"Check - "&AV16&" ingredient(s) have no price",IF(AND(BC16<>"",BC16<RotationGapDays),"Cooked recently","OK"))))) -> 0
A17: =IF(B17="","",RecipePrefix&TEXT(ROW()-4,"0000")) -> 0 | B17: Banana pancakes | C17: Breakfast | D17: Breakfast | E17: American | F17: Banana pancakes - 5 ingredients, serves 4. | G17: 4 | H17: 10 | I17: 15 | J17: =IF(B17="","",IF(AND(H17="",I17=""),"",IF(H17="",0,H17)+IF(I17="",0,I17))) -> 0 | K17: =IF(J17="","",IF(J17<=30,"Yes","No")) -> 0 | L17: Hob | M17: Easy | N17: Big pan | O17: No | P17: No | Q17: No | R17: Yes | S17: Yes | T17: Vegetarian | U17: None | V17: All year | W17: saturday morning | X17: Family favourite | AA17: 1. Prep everything first. 2. Cook as usual. 3. Taste before you serve it. | AB17: =IF(A17="","",COUNTIFS('Recipe Ingredients'!$B$5:$B$1204,A17)) -> 0 | AC17: =IF(A17="","",SUMIFS('Recipe Ingredients'!$N$5:$N$1204,'Recipe Ingredients'!$B$5:$B$1204,A17)) -> 0 | AD17: =IF(OR(AC17="",G17=""),"",IF(G17=0,"",AC17/G17)) -> 0 | AE17: =IF(OR(A17="",G17=""),"",IF(G17=0,"",SUMIFS('Recipe Ingredients'!$Q$5:$Q$1204,'Recipe Ingredients'!$B$5:$B$1204,A17)/G17)) -> 0 | AF17: =IF(OR(A17="",G17=""),"",IF(G17=0,"",SUMIFS('Recipe Ingredients'!$R$5:$R$1204,'Recipe Ingredients'!$B$5:$B$1204,A17)/G17)) -> 0 | AG17: =IF(OR(A17="",G17=""),"",IF(G17=0,"",SUMIFS('Recipe Ingredients'!$S$5:$S$1204,'Recipe Ingredients'!$B$5:$B$1204,A17)/G17)) -> 0 | AH17: =IF(OR(A17="",G17=""),"",IF(G17=0,"",SUMIFS('Recipe Ingredients'!$T$5:$T$1204,'Recipe Ingredients'!$B$5:$B$1204,A17)/G17)) -> 0 | AI17: =IF(OR(A17="",G17=""),"",IF(G17=0,"",SUMIFS('Recipe Ingredients'!$U$5:$U$1204,'Recipe Ingredients'!$B$5:$B$1204,A17)/G17)) -> 0 | AJ17: =IF(A17="","",IF(COUNTIFS('Recipe Ingredients'!$B$5:$B$1204,A17,'Recipe Ingredients'!$V$5:$V$1204,"<>",'Recipe Ingredients'!$V$5:$V$1204,"<>None")=0,"None listed",COUNTIFS('Recipe Ingredients'!$B$5:$B$1204,A17,'Recipe Ingredients'!$V$5:$V$1204,"<>",'Recipe Ingredients'!$V$5:$V$1204,"<>None")&" ingredient(s) flagged")) -> 0 | AK17: =IF(OR(AD17="",NOT(ISNUMBER(AD17))),"",COUNTIFS($AD$5:$AD$204,"<"&AD17)+COUNTIFS($AD$5:AD17,AD17)) -> 0 | AL17: =IF(B17="",0,IF(AND(OR(FilterDiet="Any",T17=FilterDiet),OR(FilterCategory="Any",C17=FilterCategory),OR(FilterMethod="Any",L17=FilterMethod),OR(FilterTime=0,AND(J17<>"",J17<=FilterTime)),OR(FilterCost=0,AND(AD17<>"",ISNUMBER(AD17),AD17<=FilterCost)),OR(FilterAllergen="Any",COUNTIFS('Recipe Ingredients'!$B$5:$B$1204,A17,'Recipe Ingredients'!$V$5:$V$1204,FilterAllergen)=0)),1,0)) -> 0 | AM17: =IF(AL17=0,"",SUM($AL$5:AL17)) -> 0 | AN17: =IF(B17="","",COUNTIFS($AZ$5:$AZ$204,">"&AZ17)+COUNTIFS($AZ$5:AZ17,AZ17)) -> 0 | AO17: =IF(B17="","",COUNTIFS($AE$5:$AE$204,">"&AE17)+COUNTIFS($AE$5:AE17,AE17)) -> 0 | AP17: =IF(B17="","",COUNTIFS($AF$5:$AF$204,">"&AF17)+COUNTIFS($AF$5:AF17,AF17)) -> 0 | AQ17: =IF(B17="","",COUNTIFS($AI$5:$AI$204,">"&AI17)+COUNTIFS($AI$5:AI17,AI17)) -> 0 | AR17: =IF(B17="","",COUNTIFS($AS$5:$AS$204,">"&AS17)+COUNTIFS($AS$5:AS17,AS17)) -> 0 | AS17: =IF(B17="","",IF(BB17="",99999,BC17)) -> 0 | AT17: =IF(A17="",0,SUMIFS('Meal Plan'!$L$5:$L$504,'Meal Plan'!$G$5:$G$504,A17,'Meal Plan'!$B$5:$B$504,">="&ShopFrom,'Meal Plan'!$B$5:$B$504,"<="&ShopTo,'Meal Plan'!$M$5:$M$504,"Yes")) -> 0 | AU17: =IF(OR(A17="",AC17=""),"",AC17*AT17) -> 0 | AV17: =IF(A17="","",COUNTIFS('Recipe Ingredients'!$B$5:$B$1204,A17,'Recipe Ingredients'!$N$5:$N$1204,"")) -> 0 | AW17: 5 | AX17: 5 | AY17: Yes | AZ17: =IF(A17="","",COUNTIFS('Meal Plan'!$G$5:$G$504,A17)) -> 0 | BA17: =IF(A17="","",COUNTIFS('Meal Plan'!$G$5:$G$504,A17,'Meal Plan'!$N$5:$N$504,"Prepared")+COUNTIFS('Meal Plan'!$G$5:$G$504,A17,'Meal Plan'!$N$5:$N$504,"Eaten")) -> 0 | BB17: =IF(A17="","",IF(COUNTIFS('Meal Plan'!$G$5:$G$504,A17,'Meal Plan'!$B$5:$B$504,"<="&TODAY())=0,"",SUMPRODUCT(MAX(('Meal Plan'!$G$5:$G$504=A17)*('Meal Plan'!$B$5:$B$504<=TODAY())*'Meal Plan'!$B$5:$B$504)))) -> 0 | BC17: =IF(BB17="","",TODAY()-BB17) -> 0 | BE17: 46204 | BF17: =IF(B17="","",IF(G17="","Add - how many does it serve?",IF(AB17=0,"Add - no ingredients listed yet",IF(AV17>0,"Check - "&AV17&" ingredient(s) have no price",IF(AND(BC17<>"",BC17<RotationGapDays),"Cooked recently","OK"))))) -> 0
A18: =IF(B18="","",RecipePrefix&TEXT(ROW()-4,"0000")) -> 0 | B18: Couscous lunch jars | C18: Lunchbox | D18: Lunch | E18: Middle Eastern | F18: Couscous lunch jars - 6 ingredients, serves 4. | G18: 4 | H18: 15 | I18: 10 | J18: =IF(B18="","",IF(AND(H18="",I18=""),"",IF(H18="",0,H18)+IF(I18="",0,I18))) -> 0 | K18: =IF(J18="","",IF(J18<=30,"Yes","No")) -> 0 | L18: No cook | M18: Easy | O18: No | P18: Yes | Q18: Yes | R18: No | S18: No | T18: Vegan | U18: None | V18: All year | W18: lunchbox, prep ahead | AA18: 1. Prep everything first. 2. Cook as usual. 3. Taste before you serve it. | AB18: =IF(A18="","",COUNTIFS('Recipe Ingredients'!$B$5:$B$1204,A18)) -> 0 | AC18: =IF(A18="","",SUMIFS('Recipe Ingredients'!$N$5:$N$1204,'Recipe Ingredients'!$B$5:$B$1204,A18)) -> 0 | AD18: =IF(OR(AC18="",G18=""),"",IF(G18=0,"",AC18/G18)) -> 0 | AE18: =IF(OR(A18="",G18=""),"",IF(G18=0,"",SUMIFS('Recipe Ingredients'!$Q$5:$Q$1204,'Recipe Ingredients'!$B$5:$B$1204,A18)/G18)) -> 0 | AF18: =IF(OR(A18="",G18=""),"",IF(G18=0,"",SUMIFS('Recipe Ingredients'!$R$5:$R$1204,'Recipe Ingredients'!$B$5:$B$1204,A18)/G18)) -> 0 | AG18: =IF(OR(A18="",G18=""),"",IF(G18=0,"",SUMIFS('Recipe Ingredients'!$S$5:$S$1204,'Recipe Ingredients'!$B$5:$B$1204,A18)/G18)) -> 0 | AH18: =IF(OR(A18="",G18=""),"",IF(G18=0,"",SUMIFS('Recipe Ingredients'!$T$5:$T$1204,'Recipe Ingredients'!$B$5:$B$1204,A18)/G18)) -> 0 | AI18: =IF(OR(A18="",G18=""),"",IF(G18=0,"",SUMIFS('Recipe Ingredients'!$U$5:$U$1204,'Recipe Ingredients'!$B$5:$B$1204,A18)/G18)) -> 0 | AJ18: =IF(A18="","",IF(COUNTIFS('Recipe Ingredients'!$B$5:$B$1204,A18,'Recipe Ingredients'!$V$5:$V$1204,"<>",'Recipe Ingredients'!$V$5:$V$1204,"<>None")=0,"None listed",COUNTIFS('Recipe Ingredients'!$B$5:$B$1204,A18,'Recipe Ingredients'!$V$5:$V$1204,"<>",'Recipe Ingredients'!$V$5:$V$1204,"<>None")&" ingredient(s) flagged")) -> 0 | AK18: =IF(OR(AD18="",NOT(ISNUMBER(AD18))),"",COUNTIFS($AD$5:$AD$204,"<"&AD18)+COUNTIFS($AD$5:AD18,AD18)) -> 0 | AL18: =IF(B18="",0,IF(AND(OR(FilterDiet="Any",T18=FilterDiet),OR(FilterCategory="Any",C18=FilterCategory),OR(FilterMethod="Any",L18=FilterMethod),OR(FilterTime=0,AND(J18<>"",J18<=FilterTime)),OR(FilterCost=0,AND(AD18<>"",ISNUMBER(AD18),AD18<=FilterCost)),OR(FilterAllergen="Any",COUNTIFS('Recipe Ingredients'!$B$5:$B$1204,A18,'Recipe Ingredients'!$V$5:$V$1204,FilterAllergen)=0)),1,0)) -> 0 | AM18: =IF(AL18=0,"",SUM($AL$5:AL18)) -> 0 | AN18: =IF(B18="","",COUNTIFS($AZ$5:$AZ$204,">"&AZ18)+COUNTIFS($AZ$5:AZ18,AZ18)) -> 0 | AO18: =IF(B18="","",COUNTIFS($AE$5:$AE$204,">"&AE18)+COUNTIFS($AE$5:AE18,AE18)) -> 0 | AP18: =IF(B18="","",COUNTIFS($AF$5:$AF$204,">"&AF18)+COUNTIFS($AF$5:AF18,AF18)) -> 0 | AQ18: =IF(B18="","",COUNTIFS($AI$5:$AI$204,">"&AI18)+COUNTIFS($AI$5:AI18,AI18)) -> 0 | AR18: =IF(B18="","",COUNTIFS($AS$5:$AS$204,">"&AS18)+COUNTIFS($AS$5:AS18,AS18)) -> 0 | AS18: =IF(B18="","",IF(BB18="",99999,BC18)) -> 0 | AT18: =IF(A18="",0,SUMIFS('Meal Plan'!$L$5:$L$504,'Meal Plan'!$G$5:$G$504,A18,'Meal Plan'!$B$5:$B$504,">="&ShopFrom,'Meal Plan'!$B$5:$B$504,"<="&ShopTo,'Meal Plan'!$M$5:$M$504,"Yes")) -> 0 | AU18: =IF(OR(A18="",AC18=""),"",AC18*AT18) -> 0 | AV18: =IF(A18="","",COUNTIFS('Recipe Ingredients'!$B$5:$B$1204,A18,'Recipe Ingredients'!$N$5:$N$1204,"")) -> 0 | AW18: 4 | AX18: 3 | AY18: No | AZ18: =IF(A18="","",COUNTIFS('Meal Plan'!$G$5:$G$504,A18)) -> 0 | BA18: =IF(A18="","",COUNTIFS('Meal Plan'!$G$5:$G$504,A18,'Meal Plan'!$N$5:$N$504,"Prepared")+COUNTIFS('Meal Plan'!$G$5:$G$504,A18,'Meal Plan'!$N$5:$N$504,"Eaten")) -> 0 | BB18: =IF(A18="","",IF(COUNTIFS('Meal Plan'!$G$5:$G$504,A18,'Meal Plan'!$B$5:$B$504,"<="&TODAY())=0,"",SUMPRODUCT(MAX(('Meal Plan'!$G$5:$G$504=A18)*('Meal Plan'!$B$5:$B$504<=TODAY())*'Meal Plan'!$B$5:$B$504)))) -> 0 | BC18: =IF(BB18="","",TODAY()-BB18) -> 0 | BE18: 45987 | BF18: =IF(B18="","",IF(G18="","Add - how many does it serve?",IF(AB18=0,"Add - no ingredients listed yet",IF(AV18>0,"Check - "&AV18&" ingredient(s) have no price",IF(AND(BC18<>"",BC18<RotationGapDays),"Cooked recently","OK"))))) -> 0
A19: =IF(B19="","",RecipePrefix&TEXT(ROW()-4,"0000")) -> 0 | B19: Hummus & veg wraps | C19: Lunchbox | D19: Lunch | E19: Middle Eastern | F19: Hummus & veg wraps - 4 ingredients, serves 2. | G19: 2 | H19: 10 | I19: 0 | J19: =IF(B19="","",IF(AND(H19="",I19=""),"",IF(H19="",0,H19)+IF(I19="",0,I19))) -> 0 | K19: =IF(J19="","",IF(J19<=30,"Yes","No")) -> 0 | L19: No cook | M19: Easy | O19: No | P19: Yes | Q19: No | R19: No | S19: Yes | T19: Vegan | U19: None | V19: All year | W19: lunchbox | AA19: 1. Prep everything first. 2. Cook as usual. 3. Taste before you serve it. | AB19: =IF(A19="","",COUNTIFS('Recipe Ingredients'!$B$5:$B$1204,A19)) -> 0 | AC19: =IF(A19="","",SUMIFS('Recipe Ingredients'!$N$5:$N$1204,'Recipe Ingredients'!$B$5:$B$1204,A19)) -> 0 | AD19: =IF(OR(AC19="",G19=""),"",IF(G19=0,"",AC19/G19)) -> 0 | AE19: =IF(OR(A19="",G19=""),"",IF(G19=0,"",SUMIFS('Recipe Ingredients'!$Q$5:$Q$1204,'Recipe Ingredients'!$B$5:$B$1204,A19)/G19)) -> 0 | AF19: =IF(OR(A19="",G19=""),"",IF(G19=0,"",SUMIFS('Recipe Ingredients'!$R$5:$R$1204,'Recipe Ingredients'!$B$5:$B$1204,A19)/G19)) -> 0 | AG19: =IF(OR(A19="",G19=""),"",IF(G19=0,"",SUMIFS('Recipe Ingredients'!$S$5:$S$1204,'Recipe Ingredients'!$B$5:$B$1204,A19)/G19)) -> 0 | AH19: =IF(OR(A19="",G19=""),"",IF(G19=0,"",SUMIFS('Recipe Ingredients'!$T$5:$T$1204,'Recipe Ingredients'!$B$5:$B$1204,A19)/G19)) -> 0 | AI19: =IF(OR(A19="",G19=""),"",IF(G19=0,"",SUMIFS('Recipe Ingredients'!$U$5:$U$1204,'Recipe Ingredients'!$B$5:$B$1204,A19)/G19)) -> 0 | AJ19: =IF(A19="","",IF(COUNTIFS('Recipe Ingredients'!$B$5:$B$1204,A19,'Recipe Ingredients'!$V$5:$V$1204,"<>",'Recipe Ingredients'!$V$5:$V$1204,"<>None")=0,"None listed",COUNTIFS('Recipe Ingredients'!$B$5:$B$1204,A19,'Recipe Ingredients'!$V$5:$V$1204,"<>",'Recipe Ingredients'!$V$5:$V$1204,"<>None")&" ingredient(s) flagged")) -> 0 | AK19: =IF(OR(AD19="",NOT(ISNUMBER(AD19))),"",COUNTIFS($AD$5:$AD$204,"<"&AD19)+COUNTIFS($AD$5:AD19,AD19)) -> 0 | AL19: =IF(B19="",0,IF(AND(OR(FilterDiet="Any",T19=FilterDiet),OR(FilterCategory="Any",C19=FilterCategory),OR(FilterMethod="Any",L19=FilterMethod),OR(FilterTime=0,AND(J19<>"",J19<=FilterTime)),OR(FilterCost=0,AND(AD19<>"",ISNUMBER(AD19),AD19<=FilterCost)),OR(FilterAllergen="Any",COUNTIFS('Recipe Ingredients'!$B$5:$B$1204,A19,'Recipe Ingredients'!$V$5:$V$1204,FilterAllergen)=0)),1,0)) -> 0 | AM19: =IF(AL19=0,"",SUM($AL$5:AL19)) -> 0 | AN19: =IF(B19="","",COUNTIFS($AZ$5:$AZ$204,">"&AZ19)+COUNTIFS($AZ$5:AZ19,AZ19)) -> 0 | AO19: =IF(B19="","",COUNTIFS($AE$5:$AE$204,">"&AE19)+COUNTIFS($AE$5:AE19,AE19)) -> 0 | AP19: =IF(B19="","",COUNTIFS($AF$5:$AF$204,">"&AF19)+COUNTIFS($AF$5:AF19,AF19)) -> 0 | AQ19: =IF(B19="","",COUNTIFS($AI$5:$AI$204,">"&AI19)+COUNTIFS($AI$5:AI19,AI19)) -> 0 | AR19: =IF(B19="","",COUNTIFS($AS$5:$AS$204,">"&AS19)+COUNTIFS($AS$5:AS19,AS19)) -> 0 | AS19: =IF(B19="","",IF(BB19="",99999,BC19)) -> 0 | AT19: =IF(A19="",0,SUMIFS('Meal Plan'!$L$5:$L$504,'Meal Plan'!$G$5:$G$504,A19,'Meal Plan'!$B$5:$B$504,">="&ShopFrom,'Meal Plan'!$B$5:$B$504,"<="&ShopTo,'Meal Plan'!$M$5:$M$504,"Yes")) -> 0 | AU19: =IF(OR(A19="",AC19=""),"",AC19*AT19) -> 0 | AV19: =IF(A19="","",COUNTIFS('Recipe Ingredients'!$B$5:$B$1204,A19,'Recipe Ingredients'!$N$5:$N$1204,"")) -> 0 | AW19: 3 | AX19: 3 | AY19: No | AZ19: =IF(A19="","",COUNTIFS('Meal Plan'!$G$5:$G$504,A19)) -> 0 | BA19: =IF(A19="","",COUNTIFS('Meal Plan'!$G$5:$G$504,A19,'Meal Plan'!$N$5:$N$504,"Prepared")+COUNTIFS('Meal Plan'!$G$5:$G$504,A19,'Meal Plan'!$N$5:$N$504,"Eaten")) -> 0 | BB19: =IF(A19="","",IF(COUNTIFS('Meal Plan'!$G$5:$G$504,A19,'Meal Plan'!$B$5:$B$504,"<="&TODAY())=0,"",SUMPRODUCT(MAX(('Meal Plan'!$G$5:$G$504=A19)*('Meal Plan'!$B$5:$B$504<=TODAY())*'Meal Plan'!$B$5:$B$504)))) -> 0 | BC19: =IF(BB19="","",TODAY()-BB19) -> 0 | BE19: 45995 | BF19: =IF(B19="","",IF(G19="","Add - how many does it serve?",IF(AB19=0,"Add - no ingredients listed yet",IF(AV19>0,"Check - "&AV19&" ingredient(s) have no price",IF(AND(BC19<>"",BC19<RotationGapDays),"Cooked recently","OK"))))) -> 0
A20: =IF(B20="","",RecipePrefix&TEXT(ROW()-4,"0000")) -> 0 | B20: Leftover soup | C20: Soup | D20: Lunch | E20: British | F20: Leftover soup - 5 ingredients, serves 4. | G20: 4 | H20: 10 | I20: 25 | J20: =IF(B20="","",IF(AND(H20="",I20=""),"",IF(H20="",0,H20)+IF(I20="",0,I20))) -> 0 | K20: =IF(J20="","",IF(J20<=30,"Yes","No")) -> 0 | L20: One pot | M20: Easy | O20: Yes | P20: No | Q20: Yes | R20: Yes | S20: No | T20: Vegan | U20: None | V20: All year | W20: uses up leftovers | AA20: 1. Prep everything first. 2. Cook as usual. 3. Taste before you serve it. | AB20: =IF(A20="","",COUNTIFS('Recipe Ingredients'!$B$5:$B$1204,A20)) -> 0 | AC20: =IF(A20="","",SUMIFS('Recipe Ingredients'!$N$5:$N$1204,'Recipe Ingredients'!$B$5:$B$1204,A20)) -> 0 | AD20: =IF(OR(AC20="",G20=""),"",IF(G20=0,"",AC20/G20)) -> 0 | AE20: =IF(OR(A20="",G20=""),"",IF(G20=0,"",SUMIFS('Recipe Ingredients'!$Q$5:$Q$1204,'Recipe Ingredients'!$B$5:$B$1204,A20)/G20)) -> 0 | AF20: =IF(OR(A20="",G20=""),"",IF(G20=0,"",SUMIFS('Recipe Ingredients'!$R$5:$R$1204,'Recipe Ingredients'!$B$5:$B$1204,A20)/G20)) -> 0 | AG20: =IF(OR(A20="",G20=""),"",IF(G20=0,"",SUMIFS('Recipe Ingredients'!$S$5:$S$1204,'Recipe Ingredients'!$B$5:$B$1204,A20)/G20)) -> 0 | AH20: =IF(OR(A20="",G20=""),"",IF(G20=0,"",SUMIFS('Recipe Ingredients'!$T$5:$T$1204,'Recipe Ingredients'!$B$5:$B$1204,A20)/G20)) -> 0 | AI20: =IF(OR(A20="",G20=""),"",IF(G20=0,"",SUMIFS('Recipe Ingredients'!$U$5:$U$1204,'Recipe Ingredients'!$B$5:$B$1204,A20)/G20)) -> 0 | AJ20: =IF(A20="","",IF(COUNTIFS('Recipe Ingredients'!$B$5:$B$1204,A20,'Recipe Ingredients'!$V$5:$V$1204,"<>",'Recipe Ingredients'!$V$5:$V$1204,"<>None")=0,"None listed",COUNTIFS('Recipe Ingredients'!$B$5:$B$1204,A20,'Recipe Ingredients'!$V$5:$V$1204,"<>",'Recipe Ingredients'!$V$5:$V$1204,"<>None")&" ingredient(s) flagged")) -> 0 | AK20: =IF(OR(AD20="",NOT(ISNUMBER(AD20))),"",COUNTIFS($AD$5:$AD$204,"<"&AD20)+COUNTIFS($AD$5:AD20,AD20)) -> 0 | AL20: =IF(B20="",0,IF(AND(OR(FilterDiet="Any",T20=FilterDiet),OR(FilterCategory="Any",C20=FilterCategory),OR(FilterMethod="Any",L20=FilterMethod),OR(FilterTime=0,AND(J20<>"",J20<=FilterTime)),OR(FilterCost=0,AND(AD20<>"",ISNUMBER(AD20),AD20<=FilterCost)),OR(FilterAllergen="Any",COUNTIFS('Recipe Ingredients'!$B$5:$B$1204,A20,'Recipe Ingredients'!$V$5:$V$1204,FilterAllergen)=0)),1,0)) -> 0 | AM20: =IF(AL20=0,"",SUM($AL$5:AL20)) -> 0 | AN20: =IF(B20="","",COUNTIFS($AZ$5:$AZ$204,">"&AZ20)+COUNTIFS($AZ$5:AZ20,AZ20)) -> 0 | AO20: =IF(B20="","",COUNTIFS($AE$5:$AE$204,">"&AE20)+COUNTIFS($AE$5:AE20,AE20)) -> 0 | AP20: =IF(B20="","",COUNTIFS($AF$5:$AF$204,">"&AF20)+COUNTIFS($AF$5:AF20,AF20)) -> 0 | AQ20: =IF(B20="","",COUNTIFS($AI$5:$AI$204,">"&AI20)+COUNTIFS($AI$5:AI20,AI20)) -> 0 | AR20: =IF(B20="","",COUNTIFS($AS$5:$AS$204,">"&AS20)+COUNTIFS($AS$5:AS20,AS20)) -> 0 | AS20: =IF(B20="","",IF(BB20="",99999,BC20)) -> 0 | AT20: =IF(A20="",0,SUMIFS('Meal Plan'!$L$5:$L$504,'Meal Plan'!$G$5:$G$504,A20,'Meal Plan'!$B$5:$B$504,">="&ShopFrom,'Meal Plan'!$B$5:$B$504,"<="&ShopTo,'Meal Plan'!$M$5:$M$504,"Yes")) -> 0 | AU20: =IF(OR(A20="",AC20=""),"",AC20*AT20) -> 0 | AV20: =IF(A20="","",COUNTIFS('Recipe Ingredients'!$B$5:$B$1204,A20,'Recipe Ingredients'!$N$5:$N$1204,"")) -> 0 | AW20: 4 | AX20: 3 | AY20: No | AZ20: =IF(A20="","",COUNTIFS('Meal Plan'!$G$5:$G$504,A20)) -> 0 | BA20: =IF(A20="","",COUNTIFS('Meal Plan'!$G$5:$G$504,A20,'Meal Plan'!$N$5:$N$504,"Prepared")+COUNTIFS('Meal Plan'!$G$5:$G$504,A20,'Meal Plan'!$N$5:$N$504,"Eaten")) -> 0 | BB20: =IF(A20="","",IF(COUNTIFS('Meal Plan'!$G$5:$G$504,A20,'Meal Plan'!$B$5:$B$504,"<="&TODAY())=0,"",SUMPRODUCT(MAX(('Meal Plan'!$G$5:$G$504=A20)*('Meal Plan'!$B$5:$B$504<=TODAY())*'Meal Plan'!$B$5:$B$504)))) -> 0 | BC20: =IF(BB20="","",TODAY()-BB20) -> 0 | BE20: 46031 | BF20: =IF(B20="","",IF(G20="","Add - how many does it serve?",IF(AB20=0,"Add - no ingredients listed yet",IF(AV20>0,"Check - "&AV20&" ingredient(s) have no price",IF(AND(BC20<>"",BC20<RotationGapDays),"Cooked recently","OK"))))) -> 0
A21: =IF(B21="","",RecipePrefix&TEXT(ROW()-4,"0000")) -> 0 | B21: Tofu stir fry | C21: Main | D21: Dinner | E21: Chinese | F21: Tofu stir fry - 6 ingredients, serves 4. | G21: 4 | H21: 15 | I21: 15 | J21: =IF(B21="","",IF(AND(H21="",I21=""),"",IF(H21="",0,H21)+IF(I21="",0,I21))) -> 0 | K21: =IF(J21="","",IF(J21<=30,"Yes","No")) -> 0 | L21: Hob | M21: Easy | N21: Big pan | O21: No | P21: No | Q21: No | R21: No | S21: No | T21: Vegan | U21: None | V21: All year | AA21: 1. Prep everything first. 2. Cook as usual. 3. Taste before you serve it. | AB21: =IF(A21="","",COUNTIFS('Recipe Ingredients'!$B$5:$B$1204,A21)) -> 0 | AC21: =IF(A21="","",SUMIFS('Recipe Ingredients'!$N$5:$N$1204,'Recipe Ingredients'!$B$5:$B$1204,A21)) -> 0 | AD21: =IF(OR(AC21="",G21=""),"",IF(G21=0,"",AC21/G21)) -> 0 | AE21: =IF(OR(A21="",G21=""),"",IF(G21=0,"",SUMIFS('Recipe Ingredients'!$Q$5:$Q$1204,'Recipe Ingredients'!$B$5:$B$1204,A21)/G21)) -> 0 | AF21: =IF(OR(A21="",G21=""),"",IF(G21=0,"",SUMIFS('Recipe Ingredients'!$R$5:$R$1204,'Recipe Ingredients'!$B$5:$B$1204,A21)/G21)) -> 0 | AG21: =IF(OR(A21="",G21=""),"",IF(G21=0,"",SUMIFS('Recipe Ingredients'!$S$5:$S$1204,'Recipe Ingredients'!$B$5:$B$1204,A21)/G21)) -> 0 | AH21: =IF(OR(A21="",G21=""),"",IF(G21=0,"",SUMIFS('Recipe Ingredients'!$T$5:$T$1204,'Recipe Ingredients'!$B$5:$B$1204,A21)/G21)) -> 0 | AI21: =IF(OR(A21="",G21=""),"",IF(G21=0,"",SUMIFS('Recipe Ingredients'!$U$5:$U$1204,'Recipe Ingredients'!$B$5:$B$1204,A21)/G21)) -> 0 | AJ21: =IF(A21="","",IF(COUNTIFS('Recipe Ingredients'!$B$5:$B$1204,A21,'Recipe Ingredients'!$V$5:$V$1204,"<>",'Recipe Ingredients'!$V$5:$V$1204,"<>None")=0,"None listed",COUNTIFS('Recipe Ingredients'!$B$5:$B$1204,A21,'Recipe Ingredients'!$V$5:$V$1204,"<>",'Recipe Ingredients'!$V$5:$V$1204,"<>None")&" ingredient(s) flagged")) -> 0 | AK21: =IF(OR(AD21="",NOT(ISNUMBER(AD21))),"",COUNTIFS($AD$5:$AD$204,"<"&AD21)+COUNTIFS($AD$5:AD21,AD21)) -> 0 | AL21: =IF(B21="",0,IF(AND(OR(FilterDiet="Any",T21=FilterDiet),OR(FilterCategory="Any",C21=FilterCategory),OR(FilterMethod="Any",L21=FilterMethod),OR(FilterTime=0,AND(J21<>"",J21<=FilterTime)),OR(FilterCost=0,AND(AD21<>"",ISNUMBER(AD21),AD21<=FilterCost)),OR(FilterAllergen="Any",COUNTIFS('Recipe Ingredients'!$B$5:$B$1204,A21,'Recipe Ingredients'!$V$5:$V$1204,FilterAllergen)=0)),1,0)) -> 0 | AM21: =IF(AL21=0,"",SUM($AL$5:AL21)) -> 0 | AN21: =IF(B21="","",COUNTIFS($AZ$5:$AZ$204,">"&AZ21)+COUNTIFS($AZ$5:AZ21,AZ21)) -> 0 | AO21: =IF(B21="","",COUNTIFS($AE$5:$AE$204,">"&AE21)+COUNTIFS($AE$5:AE21,AE21)) -> 0 | AP21: =IF(B21="","",COUNTIFS($AF$5:$AF$204,">"&AF21)+COUNTIFS($AF$5:AF21,AF21)) -> 0 | AQ21: =IF(B21="","",COUNTIFS($AI$5:$AI$204,">"&AI21)+COUNTIFS($AI$5:AI21,AI21)) -> 0 | AR21: =IF(B21="","",COUNTIFS($AS$5:$AS$204,">"&AS21)+COUNTIFS($AS$5:AS21,AS21)) -> 0 | AS21: =IF(B21="","",IF(BB21="",99999,BC21)) -> 0 | AT21: =IF(A21="",0,SUMIFS('Meal Plan'!$L$5:$L$504,'Meal Plan'!$G$5:$G$504,A21,'Meal Plan'!$B$5:$B$504,">="&ShopFrom,'Meal Plan'!$B$5:$B$504,"<="&ShopTo,'Meal Plan'!$M$5:$M$504,"Yes")) -> 0 | AU21: =IF(OR(A21="",AC21=""),"",AC21*AT21) -> 0 | AV21: =IF(A21="","",COUNTIFS('Recipe Ingredients'!$B$5:$B$1204,A21,'Recipe Ingredients'!$N$5:$N$1204,"")) -> 0 | AW21: 3 | AX21: 3 | AY21: No | AZ21: =IF(A21="","",COUNTIFS('Meal Plan'!$G$5:$G$504,A21)) -> 0 | BA21: =IF(A21="","",COUNTIFS('Meal Plan'!$G$5:$G$504,A21,'Meal Plan'!$N$5:$N$504,"Prepared")+COUNTIFS('Meal Plan'!$G$5:$G$504,A21,'Meal Plan'!$N$5:$N$504,"Eaten")) -> 0 | BB21: =IF(A21="","",IF(COUNTIFS('Meal Plan'!$G$5:$G$504,A21,'Meal Plan'!$B$5:$B$504,"<="&TODAY())=0,"",SUMPRODUCT(MAX(('Meal Plan'!$G$5:$G$504=A21)*('Meal Plan'!$B$5:$B$504<=TODAY())*'Meal Plan'!$B$5:$B$504)))) -> 0 | BC21: =IF(BB21="","",TODAY()-BB21) -> 0 | BE21: 46093 | BF21: =IF(B21="","",IF(G21="","Add - how many does it serve?",IF(AB21=0,"Add - no ingredients listed yet",IF(AV21>0,"Check - "&AV21&" ingredient(s) have no price",IF(AND(BC21<>"",BC21<RotationGapDays),"Cooked recently","OK"))))) -> 0
A22: =IF(B22="","",RecipePrefix&TEXT(ROW()-4,"0000")) -> 0 | B22: Apple crumble | C22: Dessert | D22: Dessert | E22: British | F22: Apple crumble - 4 ingredients, serves 6. | G22: 6 | H22: 20 | I22: 35 | J22: =IF(B22="","",IF(AND(H22="",I22=""),"",IF(H22="",0,H22)+IF(I22="",0,I22))) -> 0 | K22: =IF(J22="","",IF(J22<=30,"Yes","No")) -> 0 | L22: Oven | M22: Easy | N22: Roasting tin | O22: No | P22: No | Q22: No | R22: Yes | S22: Yes | T22: Vegetarian | U22: None | V22: All year | W22: sunday pudding | X22: Family favourite | AA22: 1. Prep everything first. 2. Cook as usual. 3. Taste before you serve it. | AB22: =IF(A22="","",COUNTIFS('Recipe Ingredients'!$B$5:$B$1204,A22)) -> 0 | AC22: =IF(A22="","",SUMIFS('Recipe Ingredients'!$N$5:$N$1204,'Recipe Ingredients'!$B$5:$B$1204,A22)) -> 0 | AD22: =IF(OR(AC22="",G22=""),"",IF(G22=0,"",AC22/G22)) -> 0 | AE22: =IF(OR(A22="",G22=""),"",IF(G22=0,"",SUMIFS('Recipe Ingredients'!$Q$5:$Q$1204,'Recipe Ingredients'!$B$5:$B$1204,A22)/G22)) -> 0 | AF22: =IF(OR(A22="",G22=""),"",IF(G22=0,"",SUMIFS('Recipe Ingredients'!$R$5:$R$1204,'Recipe Ingredients'!$B$5:$B$1204,A22)/G22)) -> 0 | AG22: =IF(OR(A22="",G22=""),"",IF(G22=0,"",SUMIFS('Recipe Ingredients'!$S$5:$S$1204,'Recipe Ingredients'!$B$5:$B$1204,A22)/G22)) -> 0 | AH22: =IF(OR(A22="",G22=""),"",IF(G22=0,"",SUMIFS('Recipe Ingredients'!$T$5:$T$1204,'Recipe Ingredients'!$B$5:$B$1204,A22)/G22)) -> 0 | AI22: =IF(OR(A22="",G22=""),"",IF(G22=0,"",SUMIFS('Recipe Ingredients'!$U$5:$U$1204,'Recipe Ingredients'!$B$5:$B$1204,A22)/G22)) -> 0 | AJ22: =IF(A22="","",IF(COUNTIFS('Recipe Ingredients'!$B$5:$B$1204,A22,'Recipe Ingredients'!$V$5:$V$1204,"<>",'Recipe Ingredients'!$V$5:$V$1204,"<>None")=0,"None listed",COUNTIFS('Recipe Ingredients'!$B$5:$B$1204,A22,'Recipe Ingredients'!$V$5:$V$1204,"<>",'Recipe Ingredients'!$V$5:$V$1204,"<>None")&" ingredient(s) flagged")) -> 0 | AK22: =IF(OR(AD22="",NOT(ISNUMBER(AD22))),"",COUNTIFS($AD$5:$AD$204,"<"&AD22)+COUNTIFS($AD$5:AD22,AD22)) -> 0 | AL22: =IF(B22="",0,IF(AND(OR(FilterDiet="Any",T22=FilterDiet),OR(FilterCategory="Any",C22=FilterCategory),OR(FilterMethod="Any",L22=FilterMethod),OR(FilterTime=0,AND(J22<>"",J22<=FilterTime)),OR(FilterCost=0,AND(AD22<>"",ISNUMBER(AD22),AD22<=FilterCost)),OR(FilterAllergen="Any",COUNTIFS('Recipe Ingredients'!$B$5:$B$1204,A22,'Recipe Ingredients'!$V$5:$V$1204,FilterAllergen)=0)),1,0)) -> 0 | AM22: =IF(AL22=0,"",SUM($AL$5:AL22)) -> 0 | AN22: =IF(B22="","",COUNTIFS($AZ$5:$AZ$204,">"&AZ22)+COUNTIFS($AZ$5:AZ22,AZ22)) -> 0 | AO22: =IF(B22="","",COUNTIFS($AE$5:$AE$204,">"&AE22)+COUNTIFS($AE$5:AE22,AE22)) -> 0 | AP22: =IF(B22="","",COUNTIFS($AF$5:$AF$204,">"&AF22)+COUNTIFS($AF$5:AF22,AF22)) -> 0 | AQ22: =IF(B22="","",COUNTIFS($AI$5:$AI$204,">"&AI22)+COUNTIFS($AI$5:AI22,AI22)) -> 0 | AR22: =IF(B22="","",COUNTIFS($AS$5:$AS$204,">"&AS22)+COUNTIFS($AS$5:AS22,AS22)) -> 0 | AS22: =IF(B22="","",IF(BB22="",99999,BC22)) -> 0 | AT22: =IF(A22="",0,SUMIFS('Meal Plan'!$L$5:$L$504,'Meal Plan'!$G$5:$G$504,A22,'Meal Plan'!$B$5:$B$504,">="&ShopFrom,'Meal Plan'!$B$5:$B$504,"<="&ShopTo,'Meal Plan'!$M$5:$M$504,"Yes")) -> 0 | AU22: =IF(OR(A22="",AC22=""),"",AC22*AT22) -> 0 | AV22: =IF(A22="","",COUNTIFS('Recipe Ingredients'!$B$5:$B$1204,A22,'Recipe Ingredients'!$N$5:$N$1204,"")) -> 0 | AW22: 5 | AX22: 4 | AY22: Yes | AZ22: =IF(A22="","",COUNTIFS('Meal Plan'!$G$5:$G$504,A22)) -> 0 | BA22: =IF(A22="","",COUNTIFS('Meal Plan'!$G$5:$G$504,A22,'Meal Plan'!$N$5:$N$504,"Prepared")+COUNTIFS('Meal Plan'!$G$5:$G$504,A22,'Meal Plan'!$N$5:$N$504,"Eaten")) -> 0 | BB22: =IF(A22="","",IF(COUNTIFS('Meal Plan'!$G$5:$G$504,A22,'Meal Plan'!$B$5:$B$504,"<="&TODAY())=0,"",SUMPRODUCT(MAX(('Meal Plan'!$G$5:$G$504=A22)*('Meal Plan'!$B$5:$B$504<=TODAY())*'Meal Plan'!$B$5:$B$504)))) -> 0 | BC22: =IF(BB22="","",TODAY()-BB22) -> 0 | BE22: 45953 | BF22: =IF(B22="","",IF(G22="","Add - how many does it serve?",IF(AB22=0,"Add - no ingredients listed yet",IF(AV22>0,"Check - "&AV22&" ingredient(s) have no price",IF(AND(BC22<>"",BC22<RotationGapDays),"Cooked recently","OK"))))) -> 0
A23: =IF(B23="","",RecipePrefix&TEXT(ROW()-4,"0000")) -> 0 | J23: =IF(B23="","",IF(AND(H23="",I23=""),"",IF(H23="",0,H23)+IF(I23="",0,I23))) -> 0 | K23: =IF(J23="","",IF(J23<=30,"Yes","No")) -> 0 | AB23: =IF(A23="","",COUNTIFS('Recipe Ingredients'!$B$5:$B$1204,A23)) -> 0 | AC23: =IF(A23="","",SUMIFS('Recipe Ingredients'!$N$5:$N$1204,'Recipe Ingredients'!$B$5:$B$1204,A23)) -> 0 | AD23: =IF(OR(AC23="",G23=""),"",IF(G23=0,"",AC23/G23)) -> 0 | AE23: =IF(OR(A23="",G23=""),"",IF(G23=0,"",SUMIFS('Recipe Ingredients'!$Q$5:$Q$1204,'Recipe Ingredients'!$B$5:$B$1204,A23)/G23)) -> 0 | AF23: =IF(OR(A23="",G23=""),"",IF(G23=0,"",SUMIFS('Recipe Ingredients'!$R$5:$R$1204,'Recipe Ingredients'!$B$5:$B$1204,A23)/G23)) -> 0 | AG23: =IF(OR(A23="",G23=""),"",IF(G23=0,"",SUMIFS('Recipe Ingredients'!$S$5:$S$1204,'Recipe Ingredients'!$B$5:$B$1204,A23)/G23)) -> 0 | AH23: =IF(OR(A23="",G23=""),"",IF(G23=0,"",SUMIFS('Recipe Ingredients'!$T$5:$T$1204,'Recipe Ingredients'!$B$5:$B$1204,A23)/G23)) -> 0 | AI23: =IF(OR(A23="",G23=""),"",IF(G23=0,"",SUMIFS('Recipe Ingredients'!$U$5:$U$1204,'Recipe Ingredients'!$B$5:$B$1204,A23)/G23)) -> 0 | AJ23: =IF(A23="","",IF(COUNTIFS('Recipe Ingredients'!$B$5:$B$1204,A23,'Recipe Ingredients'!$V$5:$V$1204,"<>",'Recipe Ingredients'!$V$5:$V$1204,"<>None")=0,"None listed",COUNTIFS('Recipe Ingredients'!$B$5:$B$1204,A23,'Recipe Ingredients'!$V$5:$V$1204,"<>",'Recipe Ingredients'!$V$5:$V$1204,"<>None")&" ingredient(s) flagged")) -> 0 | AK23: =IF(OR(AD23="",NOT(ISNUMBER(AD23))),"",COUNTIFS($AD$5:$AD$204,"<"&AD23)+COUNTIFS($AD$5:AD23,AD23)) -> 0 | AL23: =IF(B23="",0,IF(AND(OR(FilterDiet="Any",T23=FilterDiet),OR(FilterCategory="Any",C23=FilterCategory),OR(FilterMethod="Any",L23=FilterMethod),OR(FilterTime=0,AND(J23<>"",J23<=FilterTime)),OR(FilterCost=0,AND(AD23<>"",ISNUMBER(AD23),AD23<=FilterCost)),OR(FilterAllergen="Any",COUNTIFS('Recipe Ingredients'!$B$5:$B$1204,A23,'Recipe Ingredients'!$V$5:$V$1204,FilterAllergen)=0)),1,0)) -> 0 | AM23: =IF(AL23=0,"",SUM($AL$5:AL23)) -> 0 | AN23: =IF(B23="","",COUNTIFS($AZ$5:$AZ$204,">"&AZ23)+COUNTIFS($AZ$5:AZ23,AZ23)) -> 0 | AO23: =IF(B23="","",COUNTIFS($AE$5:$AE$204,">"&AE23)+COUNTIFS($AE$5:AE23,AE23)) -> 0 | AP23: =IF(B23="","",COUNTIFS($AF$5:$AF$204,">"&AF23)+COUNTIFS($AF$5:AF23,AF23)) -> 0 | AQ23: =IF(B23="","",COUNTIFS($AI$5:$AI$204,">"&AI23)+COUNTIFS($AI$5:AI23,AI23)) -> 0 | AR23: =IF(B23="","",COUNTIFS($AS$5:$AS$204,">"&AS23)+COUNTIFS($AS$5:AS23,AS23)) -> 0 | AS23: =IF(B23="","",IF(BB23="",99999,BC23)) -> 0 | AT23: =IF(A23="",0,SUMIFS('Meal Plan'!$L$5:$L$504,'Meal Plan'!$G$5:$G$504,A23,'Meal Plan'!$B$5:$B$504,">="&ShopFrom,'Meal Plan'!$B$5:$B$504,"<="&ShopTo,'Meal Plan'!$M$5:$M$504,"Yes")) -> 0 | AU23: =IF(OR(A23="",AC23=""),"",AC23*AT23) -> 0 | AV23: =IF(A23="","",COUNTIFS('Recipe Ingredients'!$B$5:$B$1204,A23,'Recipe Ingredients'!$N$5:$N$1204,"")) -> 0 | AZ23: =IF(A23="","",COUNTIFS('Meal Plan'!$G$5:$G$504,A23)) -> 0 | BA23: =IF(A23="","",COUNTIFS('Meal Plan'!$G$5:$G$504,A23,'Meal Plan'!$N$5:$N$504,"Prepared")+COUNTIFS('Meal Plan'!$G$5:$G$504,A23,'Meal Plan'!$N$5:$N$504,"Eaten")) -> 0 | BB23: =IF(A23="","",IF(COUNTIFS('Meal Plan'!$G$5:$G$504,A23,'Meal Plan'!$B$5:$B$504,"<="&TODAY())=0,"",SUMPRODUCT(MAX(('Meal Plan'!$G$5:$G$504=A23)*('Meal Plan'!$B$5:$B$504<=TODAY())*'Meal Plan'!$B$5:$B$504)))) -> 0 | BC23: =IF(BB23="","",TODAY()-BB23) -> 0 | BF23: =IF(B23="","",IF(G23="","Add - how many does it serve?",IF(AB23=0,"Add - no ingredients listed yet",IF(AV23>0,"Check - "&AV23&" ingredient(s) have no price",IF(AND(BC23<>"",BC23<RotationGapDays),"Cooked recently","OK"))))) -> 0
A24: =IF(B24="","",RecipePrefix&TEXT(ROW()-4,"0000")) -> 0 | J24: =IF(B24="","",IF(AND(H24="",I24=""),"",IF(H24="",0,H24)+IF(I24="",0,I24))) -> 0 | K24: =IF(J24="","",IF(J24<=30,"Yes","No")) -> 0 | AB24: =IF(A24="","",COUNTIFS('Recipe Ingredients'!$B$5:$B$1204,A24)) -> 0 | AC24: =IF(A24="","",SUMIFS('Recipe Ingredients'!$N$5:$N$1204,'Recipe Ingredients'!$B$5:$B$1204,A24)) -> 0 | AD24: =IF(OR(AC24="",G24=""),"",IF(G24=0,"",AC24/G24)) -> 0 | AE24: =IF(OR(A24="",G24=""),"",IF(G24=0,"",SUMIFS('Recipe Ingredients'!$Q$5:$Q$1204,'Recipe Ingredients'!$B$5:$B$1204,A24)/G24)) -> 0 | AF24: =IF(OR(A24="",G24=""),"",IF(G24=0,"",SUMIFS('Recipe Ingredients'!$R$5:$R$1204,'Recipe Ingredients'!$B$5:$B$1204,A24)/G24)) -> 0 | AG24: =IF(OR(A24="",G24=""),"",IF(G24=0,"",SUMIFS('Recipe Ingredients'!$S$5:$S$1204,'Recipe Ingredients'!$B$5:$B$1204,A24)/G24)) -> 0 | AH24: =IF(OR(A24="",G24=""),"",IF(G24=0,"",SUMIFS('Recipe Ingredients'!$T$5:$T$1204,'Recipe Ingredients'!$B$5:$B$1204,A24)/G24)) -> 0 | AI24: =IF(OR(A24="",G24=""),"",IF(G24=0,"",SUMIFS('Recipe Ingredients'!$U$5:$U$1204,'Recipe Ingredients'!$B$5:$B$1204,A24)/G24)) -> 0 | AJ24: =IF(A24="","",IF(COUNTIFS('Recipe Ingredients'!$B$5:$B$1204,A24,'Recipe Ingredients'!$V$5:$V$1204,"<>",'Recipe Ingredients'!$V$5:$V$1204,"<>None")=0,"None listed",COUNTIFS('Recipe Ingredients'!$B$5:$B$1204,A24,'Recipe Ingredients'!$V$5:$V$1204,"<>",'Recipe Ingredients'!$V$5:$V$1204,"<>None")&" ingredient(s) flagged")) -> 0 | AK24: =IF(OR(AD24="",NOT(ISNUMBER(AD24))),"",COUNTIFS($AD$5:$AD$204,"<"&AD24)+COUNTIFS($AD$5:AD24,AD24)) -> 0 | AL24: =IF(B24="",0,IF(AND(OR(FilterDiet="Any",T24=FilterDiet),OR(FilterCategory="Any",C24=FilterCategory),OR(FilterMethod="Any",L24=FilterMethod),OR(FilterTime=0,AND(J24<>"",J24<=FilterTime)),OR(FilterCost=0,AND(AD24<>"",ISNUMBER(AD24),AD24<=FilterCost)),OR(FilterAllergen="Any",COUNTIFS('Recipe Ingredients'!$B$5:$B$1204,A24,'Recipe Ingredients'!$V$5:$V$1204,FilterAllergen)=0)),1,0)) -> 0 | AM24: =IF(AL24=0,"",SUM($AL$5:AL24)) -> 0 | AN24: =IF(B24="","",COUNTIFS($AZ$5:$AZ$204,">"&AZ24)+COUNTIFS($AZ$5:AZ24,AZ24)) -> 0 | AO24: =IF(B24="","",COUNTIFS($AE$5:$AE$204,">"&AE24)+COUNTIFS($AE$5:AE24,AE24)) -> 0 | AP24: =IF(B24="","",COUNTIFS($AF$5:$AF$204,">"&AF24)+COUNTIFS($AF$5:AF24,AF24)) -> 0 | AQ24: =IF(B24="","",COUNTIFS($AI$5:$AI$204,">"&AI24)+COUNTIFS($AI$5:AI24,AI24)) -> 0 | AR24: =IF(B24="","",COUNTIFS($AS$5:$AS$204,">"&AS24)+COUNTIFS($AS$5:AS24,AS24)) -> 0 | AS24: =IF(B24="","",IF(BB24="",99999,BC24)) -> 0 | AT24: =IF(A24="",0,SUMIFS('Meal Plan'!$L$5:$L$504,'Meal Plan'!$G$5:$G$504,A24,'Meal Plan'!$B$5:$B$504,">="&ShopFrom,'Meal Plan'!$B$5:$B$504,"<="&ShopTo,'Meal Plan'!$M$5:$M$504,"Yes")) -> 0 | AU24: =IF(OR(A24="",AC24=""),"",AC24*AT24) -> 0 | AV24: =IF(A24="","",COUNTIFS('Recipe Ingredients'!$B$5:$B$1204,A24,'Recipe Ingredients'!$N$5:$N$1204,"")) -> 0 | AZ24: =IF(A24="","",COUNTIFS('Meal Plan'!$G$5:$G$504,A24)) -> 0 | BA24: =IF(A24="","",COUNTIFS('Meal Plan'!$G$5:$G$504,A24,'Meal Plan'!$N$5:$N$504,"Prepared")+COUNTIFS('Meal Plan'!$G$5:$G$504,A24,'Meal Plan'!$N$5:$N$504,"Eaten")) -> 0 | BB24: =IF(A24="","",IF(COUNTIFS('Meal Plan'!$G$5:$G$504,A24,'Meal Plan'!$B$5:$B$504,"<="&TODAY())=0,"",SUMPRODUCT(MAX(('Meal Plan'!$G$5:$G$504=A24)*('Meal Plan'!$B$5:$B$504<=TODAY())*'Meal Plan'!$B$5:$B$504)))) -> 0 | BC24: =IF(BB24="","",TODAY()-BB24) -> 0 | BF24: =IF(B24="","",IF(G24="","Add - how many does it serve?",IF(AB24=0,"Add - no ingredients listed yet",IF(AV24>0,"Check - "&AV24&" ingredient(s) have no price",IF(AND(BC24<>"",BC24<RotationGapDays),"Cooked recently","OK"))))) -> 0
A25: =IF(B25="","",RecipePrefix&TEXT(ROW()-4,"0000")) -> 0 | J25: =IF(B25="","",IF(AND(H25="",I25=""),"",IF(H25="",0,H25)+IF(I25="",0,I25))) -> 0 | K25: =IF(J25="","",IF(J25<=30,"Yes","No")) -> 0 | AB25: =IF(A25="","",COUNTIFS('Recipe Ingredients'!$B$5:$B$1204,A25)) -> 0 | AC25: =IF(A25="","",SUMIFS('Recipe Ingredients'!$N$5:$N$1204,'Recipe Ingredients'!$B$5:$B$1204,A25)) -> 0 | AD25: =IF(OR(AC25="",G25=""),"",IF(G25=0,"",AC25/G25)) -> 0 | AE25: =IF(OR(A25="",G25=""),"",IF(G25=0,"",SUMIFS('Recipe Ingredients'!$Q$5:$Q$1204,'Recipe Ingredients'!$B$5:$B$1204,A25)/G25)) -> 0 | AF25: =IF(OR(A25="",G25=""),"",IF(G25=0,"",SUMIFS('Recipe Ingredients'!$R$5:$R$1204,'Recipe Ingredients'!$B$5:$B$1204,A25)/G25)) -> 0 | AG25: =IF(OR(A25="",G25=""),"",IF(G25=0,"",SUMIFS('Recipe Ingredients'!$S$5:$S$1204,'Recipe Ingredients'!$B$5:$B$1204,A25)/G25)) -> 0 | AH25: =IF(OR(A25="",G25=""),"",IF(G25=0,"",SUMIFS('Recipe Ingredients'!$T$5:$T$1204,'Recipe Ingredients'!$B$5:$B$1204,A25)/G25)) -> 0 | AI25: =IF(OR(A25="",G25=""),"",IF(G25=0,"",SUMIFS('Recipe Ingredients'!$U$5:$U$1204,'Recipe Ingredients'!$B$5:$B$1204,A25)/G25)) -> 0 | AJ25: =IF(A25="","",IF(COUNTIFS('Recipe Ingredients'!$B$5:$B$1204,A25,'Recipe Ingredients'!$V$5:$V$1204,"<>",'Recipe Ingredients'!$V$5:$V$1204,"<>None")=0,"None listed",COUNTIFS('Recipe Ingredients'!$B$5:$B$1204,A25,'Recipe Ingredients'!$V$5:$V$1204,"<>",'Recipe Ingredients'!$V$5:$V$1204,"<>None")&" ingredient(s) flagged")) -> 0 | AK25: =IF(OR(AD25="",NOT(ISNUMBER(AD25))),"",COUNTIFS($AD$5:$AD$204,"<"&AD25)+COUNTIFS($AD$5:AD25,AD25)) -> 0 | AL25: =IF(B25="",0,IF(AND(OR(FilterDiet="Any",T25=FilterDiet),OR(FilterCategory="Any",C25=FilterCategory),OR(FilterMethod="Any",L25=FilterMethod),OR(FilterTime=0,AND(J25<>"",J25<=FilterTime)),OR(FilterCost=0,AND(AD25<>"",ISNUMBER(AD25),AD25<=FilterCost)),OR(FilterAllergen="Any",COUNTIFS('Recipe Ingredients'!$B$5:$B$1204,A25,'Recipe Ingredients'!$V$5:$V$1204,FilterAllergen)=0)),1,0)) -> 0 | AM25: =IF(AL25=0,"",SUM($AL$5:AL25)) -> 0 | AN25: =IF(B25="","",COUNTIFS($AZ$5:$AZ$204,">"&AZ25)+COUNTIFS($AZ$5:AZ25,AZ25)) -> 0 | AO25: =IF(B25="","",COUNTIFS($AE$5:$AE$204,">"&AE25)+COUNTIFS($AE$5:AE25,AE25)) -> 0 | AP25: =IF(B25="","",COUNTIFS($AF$5:$AF$204,">"&AF25)+COUNTIFS($AF$5:AF25,AF25)) -> 0 | AQ25: =IF(B25="","",COUNTIFS($AI$5:$AI$204,">"&AI25)+COUNTIFS($AI$5:AI25,AI25)) -> 0 | AR25: =IF(B25="","",COUNTIFS($AS$5:$AS$204,">"&AS25)+COUNTIFS($AS$5:AS25,AS25)) -> 0 | AS25: =IF(B25="","",IF(BB25="",99999,BC25)) -> 0 | AT25: =IF(A25="",0,SUMIFS('Meal Plan'!$L$5:$L$504,'Meal Plan'!$G$5:$G$504,A25,'Meal Plan'!$B$5:$B$504,">="&ShopFrom,'Meal Plan'!$B$5:$B$504,"<="&ShopTo,'Meal Plan'!$M$5:$M$504,"Yes")) -> 0 | AU25: =IF(OR(A25="",AC25=""),"",AC25*AT25) -> 0 | AV25: =IF(A25="","",COUNTIFS('Recipe Ingredients'!$B$5:$B$1204,A25,'Recipe Ingredients'!$N$5:$N$1204,"")) -> 0 | AZ25: =IF(A25="","",COUNTIFS('Meal Plan'!$G$5:$G$504,A25)) -> 0 | BA25: =IF(A25="","",COUNTIFS('Meal Plan'!$G$5:$G$504,A25,'Meal Plan'!$N$5:$N$504,"Prepared")+COUNTIFS('Meal Plan'!$G$5:$G$504,A25,'Meal Plan'!$N$5:$N$504,"Eaten")) -> 0 | BB25: =IF(A25="","",IF(COUNTIFS('Meal Plan'!$G$5:$G$504,A25,'Meal Plan'!$B$5:$B$504,"<="&TODAY())=0,"",SUMPRODUCT(MAX(('Meal Plan'!$G$5:$G$504=A25)*('Meal Plan'!$B$5:$B$504<=TODAY())*'Meal Plan'!$B$5:$B$504)))) -> 0 | BC25: =IF(BB25="","",TODAY()-BB25) -> 0 | BF25: =IF(B25="","",IF(G25="","Add - how many does it serve?",IF(AB25=0,"Add - no ingredients listed yet",IF(AV25>0,"Check - "&AV25&" ingredient(s) have no price",IF(AND(BC25<>"",BC25<RotationGapDays),"Cooked recently","OK"))))) -> 0
A26: =IF(B26="","",RecipePrefix&TEXT(ROW()-4,"0000")) -> 0 | J26: =IF(B26="","",IF(AND(H26="",I26=""),"",IF(H26="",0,H26)+IF(I26="",0,I26))) -> 0 | K26: =IF(J26="","",IF(J26<=30,"Yes","No")) -> 0 | AB26: =IF(A26="","",COUNTIFS('Recipe Ingredients'!$B$5:$B$1204,A26)) -> 0 | AC26: =IF(A26="","",SUMIFS('Recipe Ingredients'!$N$5:$N$1204,'Recipe Ingredients'!$B$5:$B$1204,A26)) -> 0 | AD26: =IF(OR(AC26="",G26=""),"",IF(G26=0,"",AC26/G26)) -> 0 | AE26: =IF(OR(A26="",G26=""),"",IF(G26=0,"",SUMIFS('Recipe Ingredients'!$Q$5:$Q$1204,'Recipe Ingredients'!$B$5:$B$1204,A26)/G26)) -> 0 | AF26: =IF(OR(A26="",G26=""),"",IF(G26=0,"",SUMIFS('Recipe Ingredients'!$R$5:$R$1204,'Recipe Ingredients'!$B$5:$B$1204,A26)/G26)) -> 0 | AG26: =IF(OR(A26="",G26=""),"",IF(G26=0,"",SUMIFS('Recipe Ingredients'!$S$5:$S$1204,'Recipe Ingredients'!$B$5:$B$1204,A26)/G26)) -> 0 | AH26: =IF(OR(A26="",G26=""),"",IF(G26=0,"",SUMIFS('Recipe Ingredients'!$T$5:$T$1204,'Recipe Ingredients'!$B$5:$B$1204,A26)/G26)) -> 0 | AI26: =IF(OR(A26="",G26=""),"",IF(G26=0,"",SUMIFS('Recipe Ingredients'!$U$5:$U$1204,'Recipe Ingredients'!$B$5:$B$1204,A26)/G26)) -> 0 | AJ26: =IF(A26="","",IF(COUNTIFS('Recipe Ingredients'!$B$5:$B$1204,A26,'Recipe Ingredients'!$V$5:$V$1204,"<>",'Recipe Ingredients'!$V$5:$V$1204,"<>None")=0,"None listed",COUNTIFS('Recipe Ingredients'!$B$5:$B$1204,A26,'Recipe Ingredients'!$V$5:$V$1204,"<>",'Recipe Ingredients'!$V$5:$V$1204,"<>None")&" ingredient(s) flagged")) -> 0 | AK26: =IF(OR(AD26="",NOT(ISNUMBER(AD26))),"",COUNTIFS($AD$5:$AD$204,"<"&AD26)+COUNTIFS($AD$5:AD26,AD26)) -> 0 | AL26: =IF(B26="",0,IF(AND(OR(FilterDiet="Any",T26=FilterDiet),OR(FilterCategory="Any",C26=FilterCategory),OR(FilterMethod="Any",L26=FilterMethod),OR(FilterTime=0,AND(J26<>"",J26<=FilterTime)),OR(FilterCost=0,AND(AD26<>"",ISNUMBER(AD26),AD26<=FilterCost)),OR(FilterAllergen="Any",COUNTIFS('Recipe Ingredients'!$B$5:$B$1204,A26,'Recipe Ingredients'!$V$5:$V$1204,FilterAllergen)=0)),1,0)) -> 0 | AM26: =IF(AL26=0,"",SUM($AL$5:AL26)) -> 0 | AN26: =IF(B26="","",COUNTIFS($AZ$5:$AZ$204,">"&AZ26)+COUNTIFS($AZ$5:AZ26,AZ26)) -> 0 | AO26: =IF(B26="","",COUNTIFS($AE$5:$AE$204,">"&AE26)+COUNTIFS($AE$5:AE26,AE26)) -> 0 | AP26: =IF(B26="","",COUNTIFS($AF$5:$AF$204,">"&AF26)+COUNTIFS($AF$5:AF26,AF26)) -> 0 | AQ26: =IF(B26="","",COUNTIFS($AI$5:$AI$204,">"&AI26)+COUNTIFS($AI$5:AI26,AI26)) -> 0 | AR26: =IF(B26="","",COUNTIFS($AS$5:$AS$204,">"&AS26)+COUNTIFS($AS$5:AS26,AS26)) -> 0 | AS26: =IF(B26="","",IF(BB26="",99999,BC26)) -> 0 | AT26: =IF(A26="",0,SUMIFS('Meal Plan'!$L$5:$L$504,'Meal Plan'!$G$5:$G$504,A26,'Meal Plan'!$B$5:$B$504,">="&ShopFrom,'Meal Plan'!$B$5:$B$504,"<="&ShopTo,'Meal Plan'!$M$5:$M$504,"Yes")) -> 0 | AU26: =IF(OR(A26="",AC26=""),"",AC26*AT26) -> 0 | AV26: =IF(A26="","",COUNTIFS('Recipe Ingredients'!$B$5:$B$1204,A26,'Recipe Ingredients'!$N$5:$N$1204,"")) -> 0 | AZ26: =IF(A26="","",COUNTIFS('Meal Plan'!$G$5:$G$504,A26)) -> 0 | BA26: =IF(A26="","",COUNTIFS('Meal Plan'!$G$5:$G$504,A26,'Meal Plan'!$N$5:$N$504,"Prepared")+COUNTIFS('Meal Plan'!$G$5:$G$504,A26,'Meal Plan'!$N$5:$N$504,"Eaten")) -> 0 | BB26: =IF(A26="","",IF(COUNTIFS('Meal Plan'!$G$5:$G$504,A26,'Meal Plan'!$B$5:$B$504,"<="&TODAY())=0,"",SUMPRODUCT(MAX(('Meal Plan'!$G$5:$G$504=A26)*('Meal Plan'!$B$5:$B$504<=TODAY())*'Meal Plan'!$B$5:$B$504)))) -> 0 | BC26: =IF(BB26="","",TODAY()-BB26) -> 0 | BF26: =IF(B26="","",IF(G26="","Add - how many does it serve?",IF(AB26=0,"Add - no ingredients listed yet",IF(AV26>0,"Check - "&AV26&" ingredient(s) have no price",IF(AND(BC26<>"",BC26<RotationGapDays),"Cooked recently","OK"))))) -> 0
A27: =IF(B27="","",RecipePrefix&TEXT(ROW()-4,"0000")) -> 0 | J27: =IF(B27="","",IF(AND(H27="",I27=""),"",IF(H27="",0,H27)+IF(I27="",0,I27))) -> 0 | K27: =IF(J27="","",IF(J27<=30,"Yes","No")) -> 0 | AB27: =IF(A27="","",COUNTIFS('Recipe Ingredients'!$B$5:$B$1204,A27)) -> 0 | AC27: =IF(A27="","",SUMIFS('Recipe Ingredients'!$N$5:$N$1204,'Recipe Ingredients'!$B$5:$B$1204,A27)) -> 0 | AD27: =IF(OR(AC27="",G27=""),"",IF(G27=0,"",AC27/G27)) -> 0 | AE27: =IF(OR(A27="",G27=""),"",IF(G27=0,"",SUMIFS('Recipe Ingredients'!$Q$5:$Q$1204,'Recipe Ingredients'!$B$5:$B$1204,A27)/G27)) -> 0 | AF27: =IF(OR(A27="",G27=""),"",IF(G27=0,"",SUMIFS('Recipe Ingredients'!$R$5:$R$1204,'Recipe Ingredients'!$B$5:$B$1204,A27)/G27)) -> 0 | AG27: =IF(OR(A27="",G27=""),"",IF(G27=0,"",SUMIFS('Recipe Ingredients'!$S$5:$S$1204,'Recipe Ingredients'!$B$5:$B$1204,A27)/G27)) -> 0 | AH27: =IF(OR(A27="",G27=""),"",IF(G27=0,"",SUMIFS('Recipe Ingredients'!$T$5:$T$1204,'Recipe Ingredients'!$B$5:$B$1204,A27)/G27)) -> 0 | AI27: =IF(OR(A27="",G27=""),"",IF(G27=0,"",SUMIFS('Recipe Ingredients'!$U$5:$U$1204,'Recipe Ingredients'!$B$5:$B$1204,A27)/G27)) -> 0 | AJ27: =IF(A27="","",IF(COUNTIFS('Recipe Ingredients'!$B$5:$B$1204,A27,'Recipe Ingredients'!$V$5:$V$1204,"<>",'Recipe Ingredients'!$V$5:$V$1204,"<>None")=0,"None listed",COUNTIFS('Recipe Ingredients'!$B$5:$B$1204,A27,'Recipe Ingredients'!$V$5:$V$1204,"<>",'Recipe Ingredients'!$V$5:$V$1204,"<>None")&" ingredient(s) flagged")) -> 0 | AK27: =IF(OR(AD27="",NOT(ISNUMBER(AD27))),"",COUNTIFS($AD$5:$AD$204,"<"&AD27)+COUNTIFS($AD$5:AD27,AD27)) -> 0 | AL27: =IF(B27="",0,IF(AND(OR(FilterDiet="Any",T27=FilterDiet),OR(FilterCategory="Any",C27=FilterCategory),OR(FilterMethod="Any",L27=FilterMethod),OR(FilterTime=0,AND(J27<>"",J27<=FilterTime)),OR(FilterCost=0,AND(AD27<>"",ISNUMBER(AD27),AD27<=FilterCost)),OR(FilterAllergen="Any",COUNTIFS('Recipe Ingredients'!$B$5:$B$1204,A27,'Recipe Ingredients'!$V$5:$V$1204,FilterAllergen)=0)),1,0)) -> 0 | AM27: =IF(AL27=0,"",SUM($AL$5:AL27)) -> 0 | AN27: =IF(B27="","",COUNTIFS($AZ$5:$AZ$204,">"&AZ27)+COUNTIFS($AZ$5:AZ27,AZ27)) -> 0 | AO27: =IF(B27="","",COUNTIFS($AE$5:$AE$204,">"&AE27)+COUNTIFS($AE$5:AE27,AE27)) -> 0 | AP27: =IF(B27="","",COUNTIFS($AF$5:$AF$204,">"&AF27)+COUNTIFS($AF$5:AF27,AF27)) -> 0 | AQ27: =IF(B27="","",COUNTIFS($AI$5:$AI$204,">"&AI27)+COUNTIFS($AI$5:AI27,AI27)) -> 0 | AR27: =IF(B27="","",COUNTIFS($AS$5:$AS$204,">"&AS27)+COUNTIFS($AS$5:AS27,AS27)) -> 0 | AS27: =IF(B27="","",IF(BB27="",99999,BC27)) -> 0 | AT27: =IF(A27="",0,SUMIFS('Meal Plan'!$L$5:$L$504,'Meal Plan'!$G$5:$G$504,A27,'Meal Plan'!$B$5:$B$504,">="&ShopFrom,'Meal Plan'!$B$5:$B$504,"<="&ShopTo,'Meal Plan'!$M$5:$M$504,"Yes")) -> 0 | AU27: =IF(OR(A27="",AC27=""),"",AC27*AT27) -> 0 | AV27: =IF(A27="","",COUNTIFS('Recipe Ingredients'!$B$5:$B$1204,A27,'Recipe Ingredients'!$N$5:$N$1204,"")) -> 0 | AZ27: =IF(A27="","",COUNTIFS('Meal Plan'!$G$5:$G$504,A27)) -> 0 | BA27: =IF(A27="","",COUNTIFS('Meal Plan'!$G$5:$G$504,A27,'Meal Plan'!$N$5:$N$504,"Prepared")+COUNTIFS('Meal Plan'!$G$5:$G$504,A27,'Meal Plan'!$N$5:$N$504,"Eaten")) -> 0 | BB27: =IF(A27="","",IF(COUNTIFS('Meal Plan'!$G$5:$G$504,A27,'Meal Plan'!$B$5:$B$504,"<="&TODAY())=0,"",SUMPRODUCT(MAX(('Meal Plan'!$G$5:$G$504=A27)*('Meal Plan'!$B$5:$B$504<=TODAY())*'Meal Plan'!$B$5:$B$504)))) -> 0 | BC27: =IF(BB27="","",TODAY()-BB27) -> 0 | BF27: =IF(B27="","",IF(G27="","Add - how many does it serve?",IF(AB27=0,"Add - no ingredients listed yet",IF(AV27>0,"Check - "&AV27&" ingredient(s) have no price",IF(AND(BC27<>"",BC27<RotationGapDays),"Cooked recently","OK"))))) -> 0
A28: =IF(B28="","",RecipePrefix&TEXT(ROW()-4,"0000")) -> 0 | J28: =IF(B28="","",IF(AND(H28="",I28=""),"",IF(H28="",0,H28)+IF(I28="",0,I28))) -> 0 | K28: =IF(J28="","",IF(J28<=30,"Yes","No")) -> 0 | AB28: =IF(A28="","",COUNTIFS('Recipe Ingredients'!$B$5:$B$1204,A28)) -> 0 | AC28: =IF(A28="","",SUMIFS('Recipe Ingredients'!$N$5:$N$1204,'Recipe Ingredients'!$B$5:$B$1204,A28)) -> 0 | AD28: =IF(OR(AC28="",G28=""),"",IF(G28=0,"",AC28/G28)) -> 0 | AE28: =IF(OR(A28="",G28=""),"",IF(G28=0,"",SUMIFS('Recipe Ingredients'!$Q$5:$Q$1204,'Recipe Ingredients'!$B$5:$B$1204,A28)/G28)) -> 0 | AF28: =IF(OR(A28="",G28=""),"",IF(G28=0,"",SUMIFS('Recipe Ingredients'!$R$5:$R$1204,'Recipe Ingredients'!$B$5:$B$1204,A28)/G28)) -> 0 | AG28: =IF(OR(A28="",G28=""),"",IF(G28=0,"",SUMIFS('Recipe Ingredients'!$S$5:$S$1204,'Recipe Ingredients'!$B$5:$B$1204,A28)/G28)) -> 0 | AH28: =IF(OR(A28="",G28=""),"",IF(G28=0,"",SUMIFS('Recipe Ingredients'!$T$5:$T$1204,'Recipe Ingredients'!$B$5:$B$1204,A28)/G28)) -> 0 | AI28: =IF(OR(A28="",G28=""),"",IF(G28=0,"",SUMIFS('Recipe Ingredients'!$U$5:$U$1204,'Recipe Ingredients'!$B$5:$B$1204,A28)/G28)) -> 0 | AJ28: =IF(A28="","",IF(COUNTIFS('Recipe Ingredients'!$B$5:$B$1204,A28,'Recipe Ingredients'!$V$5:$V$1204,"<>",'Recipe Ingredients'!$V$5:$V$1204,"<>None")=0,"None listed",COUNTIFS('Recipe Ingredients'!$B$5:$B$1204,A28,'Recipe Ingredients'!$V$5:$V$1204,"<>",'Recipe Ingredients'!$V$5:$V$1204,"<>None")&" ingredient(s) flagged")) -> 0 | AK28: =IF(OR(AD28="",NOT(ISNUMBER(AD28))),"",COUNTIFS($AD$5:$AD$204,"<"&AD28)+COUNTIFS($AD$5:AD28,AD28)) -> 0 | AL28: =IF(B28="",0,IF(AND(OR(FilterDiet="Any",T28=FilterDiet),OR(FilterCategory="Any",C28=FilterCategory),OR(FilterMethod="Any",L28=FilterMethod),OR(FilterTime=0,AND(J28<>"",J28<=FilterTime)),OR(FilterCost=0,AND(AD28<>"",ISNUMBER(AD28),AD28<=FilterCost)),OR(FilterAllergen="Any",COUNTIFS('Recipe Ingredients'!$B$5:$B$1204,A28,'Recipe Ingredients'!$V$5:$V$1204,FilterAllergen)=0)),1,0)) -> 0 | AM28: =IF(AL28=0,"",SUM($AL$5:AL28)) -> 0 | AN28: =IF(B28="","",COUNTIFS($AZ$5:$AZ$204,">"&AZ28)+COUNTIFS($AZ$5:AZ28,AZ28)) -> 0 | AO28: =IF(B28="","",COUNTIFS($AE$5:$AE$204,">"&AE28)+COUNTIFS($AE$5:AE28,AE28)) -> 0 | AP28: =IF(B28="","",COUNTIFS($AF$5:$AF$204,">"&AF28)+COUNTIFS($AF$5:AF28,AF28)) -> 0 | AQ28: =IF(B28="","",COUNTIFS($AI$5:$AI$204,">"&AI28)+COUNTIFS($AI$5:AI28,AI28)) -> 0 | AR28: =IF(B28="","",COUNTIFS($AS$5:$AS$204,">"&AS28)+COUNTIFS($AS$5:AS28,AS28)) -> 0 | AS28: =IF(B28="","",IF(BB28="",99999,BC28)) -> 0 | AT28: =IF(A28="",0,SUMIFS('Meal Plan'!$L$5:$L$504,'Meal Plan'!$G$5:$G$504,A28,'Meal Plan'!$B$5:$B$504,">="&ShopFrom,'Meal Plan'!$B$5:$B$504,"<="&ShopTo,'Meal Plan'!$M$5:$M$504,"Yes")) -> 0 | AU28: =IF(OR(A28="",AC28=""),"",AC28*AT28) -> 0 | AV28: =IF(A28="","",COUNTIFS('Recipe Ingredients'!$B$5:$B$1204,A28,'Recipe Ingredients'!$N$5:$N$1204,"")) -> 0 | AZ28: =IF(A28="","",COUNTIFS('Meal Plan'!$G$5:$G$504,A28)) -> 0 | BA28: =IF(A28="","",COUNTIFS('Meal Plan'!$G$5:$G$504,A28,'Meal Plan'!$N$5:$N$504,"Prepared")+COUNTIFS('Meal Plan'!$G$5:$G$504,A28,'Meal Plan'!$N$5:$N$504,"Eaten")) -> 0 | BB28: =IF(A28="","",IF(COUNTIFS('Meal Plan'!$G$5:$G$504,A28,'Meal Plan'!$B$5:$B$504,"<="&TODAY())=0,"",SUMPRODUCT(MAX(('Meal Plan'!$G$5:$G$504=A28)*('Meal Plan'!$B$5:$B$504<=TODAY())*'Meal Plan'!$B$5:$B$504)))) -> 0 | BC28: =IF(BB28="","",TODAY()-BB28) -> 0 | BF28: =IF(B28="","",IF(G28="","Add - how many does it serve?",IF(AB28=0,"Add - no ingredients listed yet",IF(AV28>0,"Check - "&AV28&" ingredient(s) have no price",IF(AND(BC28<>"",BC28<RotationGapDays),"Cooked recently","OK"))))) -> 0
A29: =IF(B29="","",RecipePrefix&TEXT(ROW()-4,"0000")) -> 0 | J29: =IF(B29="","",IF(AND(H29="",I29=""),"",IF(H29="",0,H29)+IF(I29="",0,I29))) -> 0 | K29: =IF(J29="","",IF(J29<=30,"Yes","No")) -> 0 | AB29: =IF(A29="","",COUNTIFS('Recipe Ingredients'!$B$5:$B$1204,A29)) -> 0 | AC29: =IF(A29="","",SUMIFS('Recipe Ingredients'!$N$5:$N$1204,'Recipe Ingredients'!$B$5:$B$1204,A29)) -> 0 | AD29: =IF(OR(AC29="",G29=""),"",IF(G29=0,"",AC29/G29)) -> 0 | AE29: =IF(OR(A29="",G29=""),"",IF(G29=0,"",SUMIFS('Recipe Ingredients'!$Q$5:$Q$1204,'Recipe Ingredients'!$B$5:$B$1204,A29)/G29)) -> 0 | AF29: =IF(OR(A29="",G29=""),"",IF(G29=0,"",SUMIFS('Recipe Ingredients'!$R$5:$R$1204,'Recipe Ingredients'!$B$5:$B$1204,A29)/G29)) -> 0 | AG29: =IF(OR(A29="",G29=""),"",IF(G29=0,"",SUMIFS('Recipe Ingredients'!$S$5:$S$1204,'Recipe Ingredients'!$B$5:$B$1204,A29)/G29)) -> 0 | AH29: =IF(OR(A29="",G29=""),"",IF(G29=0,"",SUMIFS('Recipe Ingredients'!$T$5:$T$1204,'Recipe Ingredients'!$B$5:$B$1204,A29)/G29)) -> 0 | AI29: =IF(OR(A29="",G29=""),"",IF(G29=0,"",SUMIFS('Recipe Ingredients'!$U$5:$U$1204,'Recipe Ingredients'!$B$5:$B$1204,A29)/G29)) -> 0 | AJ29: =IF(A29="","",IF(COUNTIFS('Recipe Ingredients'!$B$5:$B$1204,A29,'Recipe Ingredients'!$V$5:$V$1204,"<>",'Recipe Ingredients'!$V$5:$V$1204,"<>None")=0,"None listed",COUNTIFS('Recipe Ingredients'!$B$5:$B$1204,A29,'Recipe Ingredients'!$V$5:$V$1204,"<>",'Recipe Ingredients'!$V$5:$V$1204,"<>None")&" ingredient(s) flagged")) -> 0 | AK29: =IF(OR(AD29="",NOT(ISNUMBER(AD29))),"",COUNTIFS($AD$5:$AD$204,"<"&AD29)+COUNTIFS($AD$5:AD29,AD29)) -> 0 | AL29: =IF(B29="",0,IF(AND(OR(FilterDiet="Any",T29=FilterDiet),OR(FilterCategory="Any",C29=FilterCategory),OR(FilterMethod="Any",L29=FilterMethod),OR(FilterTime=0,AND(J29<>"",J29<=FilterTime)),OR(FilterCost=0,AND(AD29<>"",ISNUMBER(AD29),AD29<=FilterCost)),OR(FilterAllergen="Any",COUNTIFS('Recipe Ingredients'!$B$5:$B$1204,A29,'Recipe Ingredients'!$V$5:$V$1204,FilterAllergen)=0)),1,0)) -> 0 | AM29: =IF(AL29=0,"",SUM($AL$5:AL29)) -> 0 | AN29: =IF(B29="","",COUNTIFS($AZ$5:$AZ$204,">"&AZ29)+COUNTIFS($AZ$5:AZ29,AZ29)) -> 0 | AO29: =IF(B29="","",COUNTIFS($AE$5:$AE$204,">"&AE29)+COUNTIFS($AE$5:AE29,AE29)) -> 0 | AP29: =IF(B29="","",COUNTIFS($AF$5:$AF$204,">"&AF29)+COUNTIFS($AF$5:AF29,AF29)) -> 0 | AQ29: =IF(B29="","",COUNTIFS($AI$5:$AI$204,">"&AI29)+COUNTIFS($AI$5:AI29,AI29)) -> 0 | AR29: =IF(B29="","",COUNTIFS($AS$5:$AS$204,">"&AS29)+COUNTIFS($AS$5:AS29,AS29)) -> 0 | AS29: =IF(B29="","",IF(BB29="",99999,BC29)) -> 0 | AT29: =IF(A29="",0,SUMIFS('Meal Plan'!$L$5:$L$504,'Meal Plan'!$G$5:$G$504,A29,'Meal Plan'!$B$5:$B$504,">="&ShopFrom,'Meal Plan'!$B$5:$B$504,"<="&ShopTo,'Meal Plan'!$M$5:$M$504,"Yes")) -> 0 | AU29: =IF(OR(A29="",AC29=""),"",AC29*AT29) -> 0 | AV29: =IF(A29="","",COUNTIFS('Recipe Ingredients'!$B$5:$B$1204,A29,'Recipe Ingredients'!$N$5:$N$1204,"")) -> 0 | AZ29: =IF(A29="","",COUNTIFS('Meal Plan'!$G$5:$G$504,A29)) -> 0 | BA29: =IF(A29="","",COUNTIFS('Meal Plan'!$G$5:$G$504,A29,'Meal Plan'!$N$5:$N$504,"Prepared")+COUNTIFS('Meal Plan'!$G$5:$G$504,A29,'Meal Plan'!$N$5:$N$504,"Eaten")) -> 0 | BB29: =IF(A29="","",IF(COUNTIFS('Meal Plan'!$G$5:$G$504,A29,'Meal Plan'!$B$5:$B$504,"<="&TODAY())=0,"",SUMPRODUCT(MAX(('Meal Plan'!$G$5:$G$504=A29)*('Meal Plan'!$B$5:$B$504<=TODAY())*'Meal Plan'!$B$5:$B$504)))) -> 0 | BC29: =IF(BB29="","",TODAY()-BB29) -> 0 | BF29: =IF(B29="","",IF(G29="","Add - how many does it serve?",IF(AB29=0,"Add - no ingredients listed yet",IF(AV29>0,"Check - "&AV29&" ingredient(s) have no price",IF(AND(BC29<>"",BC29<RotationGapDays),"Cooked recently","OK"))))) -> 0
A30: =IF(B30="","",RecipePrefix&TEXT(ROW()-4,"0000")) -> 0 | J30: =IF(B30="","",IF(AND(H30="",I30=""),"",IF(H30="",0,H30)+IF(I30="",0,I30))) -> 0 | K30: =IF(J30="","",IF(J30<=30,"Yes","No")) -> 0 | AB30: =IF(A30="","",COUNTIFS('Recipe Ingredients'!$B$5:$B$1204,A30)) -> 0 | AC30: =IF(A30="","",SUMIFS('Recipe Ingredients'!$N$5:$N$1204,'Recipe Ingredients'!$B$5:$B$1204,A30)) -> 0 | AD30: =IF(OR(AC30="",G30=""),"",IF(G30=0,"",AC30/G30)) -> 0 | AE30: =IF(OR(A30="",G30=""),"",IF(G30=0,"",SUMIFS('Recipe Ingredients'!$Q$5:$Q$1204,'Recipe Ingredients'!$B$5:$B$1204,A30)/G30)) -> 0 | AF30: =IF(OR(A30="",G30=""),"",IF(G30=0,"",SUMIFS('Recipe Ingredients'!$R$5:$R$1204,'Recipe Ingredients'!$B$5:$B$1204,A30)/G30)) -> 0 | AG30: =IF(OR(A30="",G30=""),"",IF(G30=0,"",SUMIFS('Recipe Ingredients'!$S$5:$S$1204,'Recipe Ingredients'!$B$5:$B$1204,A30)/G30)) -> 0 | AH30: =IF(OR(A30="",G30=""),"",IF(G30=0,"",SUMIFS('Recipe Ingredients'!$T$5:$T$1204,'Recipe Ingredients'!$B$5:$B$1204,A30)/G30)) -> 0 | AI30: =IF(OR(A30="",G30=""),"",IF(G30=0,"",SUMIFS('Recipe Ingredients'!$U$5:$U$1204,'Recipe Ingredients'!$B$5:$B$1204,A30)/G30)) -> 0 | AJ30: =IF(A30="","",IF(COUNTIFS('Recipe Ingredients'!$B$5:$B$1204,A30,'Recipe Ingredients'!$V$5:$V$1204,"<>",'Recipe Ingredients'!$V$5:$V$1204,"<>None")=0,"None listed",COUNTIFS('Recipe Ingredients'!$B$5:$B$1204,A30,'Recipe Ingredients'!$V$5:$V$1204,"<>",'Recipe Ingredients'!$V$5:$V$1204,"<>None")&" ingredient(s) flagged")) -> 0 | AK30: =IF(OR(AD30="",NOT(ISNUMBER(AD30))),"",COUNTIFS($AD$5:$AD$204,"<"&AD30)+COUNTIFS($AD$5:AD30,AD30)) -> 0 | AL30: =IF(B30="",0,IF(AND(OR(FilterDiet="Any",T30=FilterDiet),OR(FilterCategory="Any",C30=FilterCategory),OR(FilterMethod="Any",L30=FilterMethod),OR(FilterTime=0,AND(J30<>"",J30<=FilterTime)),OR(FilterCost=0,AND(AD30<>"",ISNUMBER(AD30),AD30<=FilterCost)),OR(FilterAllergen="Any",COUNTIFS('Recipe Ingredients'!$B$5:$B$1204,A30,'Recipe Ingredients'!$V$5:$V$1204,FilterAllergen)=0)),1,0)) -> 0 | AM30: =IF(AL30=0,"",SUM($AL$5:AL30)) -> 0 | AN30: =IF(B30="","",COUNTIFS($AZ$5:$AZ$204,">"&AZ30)+COUNTIFS($AZ$5:AZ30,AZ30)) -> 0 | AO30: =IF(B30="","",COUNTIFS($AE$5:$AE$204,">"&AE30)+COUNTIFS($AE$5:AE30,AE30)) -> 0 | AP30: =IF(B30="","",COUNTIFS($AF$5:$AF$204,">"&AF30)+COUNTIFS($AF$5:AF30,AF30)) -> 0 | AQ30: =IF(B30="","",COUNTIFS($AI$5:$AI$204,">"&AI30)+COUNTIFS($AI$5:AI30,AI30)) -> 0 | AR30: =IF(B30="","",COUNTIFS($AS$5:$AS$204,">"&AS30)+COUNTIFS($AS$5:AS30,AS30)) -> 0 | AS30: =IF(B30="","",IF(BB30="",99999,BC30)) -> 0 | AT30: =IF(A30="",0,SUMIFS('Meal Plan'!$L$5:$L$504,'Meal Plan'!$G$5:$G$504,A30,'Meal Plan'!$B$5:$B$504,">="&ShopFrom,'Meal Plan'!$B$5:$B$504,"<="&ShopTo,'Meal Plan'!$M$5:$M$504,"Yes")) -> 0 | AU30: =IF(OR(A30="",AC30=""),"",AC30*AT30) -> 0 | AV30: =IF(A30="","",COUNTIFS('Recipe Ingredients'!$B$5:$B$1204,A30,'Recipe Ingredients'!$N$5:$N$1204,"")) -> 0 | AZ30: =IF(A30="","",COUNTIFS('Meal Plan'!$G$5:$G$504,A30)) -> 0 | BA30: =IF(A30="","",COUNTIFS('Meal Plan'!$G$5:$G$504,A30,'Meal Plan'!$N$5:$N$504,"Prepared")+COUNTIFS('Meal Plan'!$G$5:$G$504,A30,'Meal Plan'!$N$5:$N$504,"Eaten")) -> 0 | BB30: =IF(A30="","",IF(COUNTIFS('Meal Plan'!$G$5:$G$504,A30,'Meal Plan'!$B$5:$B$504,"<="&TODAY())=0,"",SUMPRODUCT(MAX(('Meal Plan'!$G$5:$G$504=A30)*('Meal Plan'!$B$5:$B$504<=TODAY())*'Meal Plan'!$B$5:$B$504)))) -> 0 | BC30: =IF(BB30="","",TODAY()-BB30) -> 0 | BF30: =IF(B30="","",IF(G30="","Add - how many does it serve?",IF(AB30=0,"Add - no ingredients listed yet",IF(AV30>0,"Check - "&AV30&" ingredient(s) have no price",IF(AND(BC30<>"",BC30<RotationGapDays),"Cooked recently","OK"))))) -> 0
A31: =IF(B31="","",RecipePrefix&TEXT(ROW()-4,"0000")) -> 0 | J31: =IF(B31="","",IF(AND(H31="",I31=""),"",IF(H31="",0,H31)+IF(I31="",0,I31))) -> 0 | K31: =IF(J31="","",IF(J31<=30,"Yes","No")) -> 0 | AB31: =IF(A31="","",COUNTIFS('Recipe Ingredients'!$B$5:$B$1204,A31)) -> 0 | AC31: =IF(A31="","",SUMIFS('Recipe Ingredients'!$N$5:$N$1204,'Recipe Ingredients'!$B$5:$B$1204,A31)) -> 0 | AD31: =IF(OR(AC31="",G31=""),"",IF(G31=0,"",AC31/G31)) -> 0 | AE31: =IF(OR(A31="",G31=""),"",IF(G31=0,"",SUMIFS('Recipe Ingredients'!$Q$5:$Q$1204,'Recipe Ingredients'!$B$5:$B$1204,A31)/G31)) -> 0 | AF31: =IF(OR(A31="",G31=""),"",IF(G31=0,"",SUMIFS('Recipe Ingredients'!$R$5:$R$1204,'Recipe Ingredients'!$B$5:$B$1204,A31)/G31)) -> 0 | AG31: =IF(OR(A31="",G31=""),"",IF(G31=0,"",SUMIFS('Recipe Ingredients'!$S$5:$S$1204,'Recipe Ingredients'!$B$5:$B$1204,A31)/G31)) -> 0 | AH31: =IF(OR(A31="",G31=""),"",IF(G31=0,"",SUMIFS('Recipe Ingredients'!$T$5:$T$1204,'Recipe Ingredients'!$B$5:$B$1204,A31)/G31)) -> 0 | AI31: =IF(OR(A31="",G31=""),"",IF(G31=0,"",SUMIFS('Recipe Ingredients'!$U$5:$U$1204,'Recipe Ingredients'!$B$5:$B$1204,A31)/G31)) -> 0 | AJ31: =IF(A31="","",IF(COUNTIFS('Recipe Ingredients'!$B$5:$B$1204,A31,'Recipe Ingredients'!$V$5:$V$1204,"<>",'Recipe Ingredients'!$V$5:$V$1204,"<>None")=0,"None listed",COUNTIFS('Recipe Ingredients'!$B$5:$B$1204,A31,'Recipe Ingredients'!$V$5:$V$1204,"<>",'Recipe Ingredients'!$V$5:$V$1204,"<>None")&" ingredient(s) flagged")) -> 0 | AK31: =IF(OR(AD31="",NOT(ISNUMBER(AD31))),"",COUNTIFS($AD$5:$AD$204,"<"&AD31)+COUNTIFS($AD$5:AD31,AD31)) -> 0 | AL31: =IF(B31="",0,IF(AND(OR(FilterDiet="Any",T31=FilterDiet),OR(FilterCategory="Any",C31=FilterCategory),OR(FilterMethod="Any",L31=FilterMethod),OR(FilterTime=0,AND(J31<>"",J31<=FilterTime)),OR(FilterCost=0,AND(AD31<>"",ISNUMBER(AD31),AD31<=FilterCost)),OR(FilterAllergen="Any",COUNTIFS('Recipe Ingredients'!$B$5:$B$1204,A31,'Recipe Ingredients'!$V$5:$V$1204,FilterAllergen)=0)),1,0)) -> 0 | AM31: =IF(AL31=0,"",SUM($AL$5:AL31)) -> 0 | AN31: =IF(B31="","",COUNTIFS($AZ$5:$AZ$204,">"&AZ31)+COUNTIFS($AZ$5:AZ31,AZ31)) -> 0 | AO31: =IF(B31="","",COUNTIFS($AE$5:$AE$204,">"&AE31)+COUNTIFS($AE$5:AE31,AE31)) -> 0 | AP31: =IF(B31="","",COUNTIFS($AF$5:$AF$204,">"&AF31)+COUNTIFS($AF$5:AF31,AF31)) -> 0 | AQ31: =IF(B31="","",COUNTIFS($AI$5:$AI$204,">"&AI31)+COUNTIFS($AI$5:AI31,AI31)) -> 0 | AR31: =IF(B31="","",COUNTIFS($AS$5:$AS$204,">"&AS31)+COUNTIFS($AS$5:AS31,AS31)) -> 0 | AS31: =IF(B31="","",IF(BB31="",99999,BC31)) -> 0 | AT31: =IF(A31="",0,SUMIFS('Meal Plan'!$L$5:$L$504,'Meal Plan'!$G$5:$G$504,A31,'Meal Plan'!$B$5:$B$504,">="&ShopFrom,'Meal Plan'!$B$5:$B$504,"<="&ShopTo,'Meal Plan'!$M$5:$M$504,"Yes")) -> 0 | AU31: =IF(OR(A31="",AC31=""),"",AC31*AT31) -> 0 | AV31: =IF(A31="","",COUNTIFS('Recipe Ingredients'!$B$5:$B$1204,A31,'Recipe Ingredients'!$N$5:$N$1204,"")) -> 0 | AZ31: =IF(A31="","",COUNTIFS('Meal Plan'!$G$5:$G$504,A31)) -> 0 | BA31: =IF(A31="","",COUNTIFS('Meal Plan'!$G$5:$G$504,A31,'Meal Plan'!$N$5:$N$504,"Prepared")+COUNTIFS('Meal Plan'!$G$5:$G$504,A31,'Meal Plan'!$N$5:$N$504,"Eaten")) -> 0 | BB31: =IF(A31="","",IF(COUNTIFS('Meal Plan'!$G$5:$G$504,A31,'Meal Plan'!$B$5:$B$504,"<="&TODAY())=0,"",SUMPRODUCT(MAX(('Meal Plan'!$G$5:$G$504=A31)*('Meal Plan'!$B$5:$B$504<=TODAY())*'Meal Plan'!$B$5:$B$504)))) -> 0 | BC31: =IF(BB31="","",TODAY()-BB31) -> 0 | BF31: =IF(B31="","",IF(G31="","Add - how many does it serve?",IF(AB31=0,"Add - no ingredients listed yet",IF(AV31>0,"Check - "&AV31&" ingredient(s) have no price",IF(AND(BC31<>"",BC31<RotationGapDays),"Cooked recently","OK"))))) -> 0
A32: =IF(B32="","",RecipePrefix&TEXT(ROW()-4,"0000")) -> 0 | J32: =IF(B32="","",IF(AND(H32="",I32=""),"",IF(H32="",0,H32)+IF(I32="",0,I32))) -> 0 | K32: =IF(J32="","",IF(J32<=30,"Yes","No")) -> 0 | AB32: =IF(A32="","",COUNTIFS('Recipe Ingredients'!$B$5:$B$1204,A32)) -> 0 | AC32: =IF(A32="","",SUMIFS('Recipe Ingredients'!$N$5:$N$1204,'Recipe Ingredients'!$B$5:$B$1204,A32)) -> 0 | AD32: =IF(OR(AC32="",G32=""),"",IF(G32=0,"",AC32/G32)) -> 0 | AE32: =IF(OR(A32="",G32=""),"",IF(G32=0,"",SUMIFS('Recipe Ingredients'!$Q$5:$Q$1204,'Recipe Ingredients'!$B$5:$B$1204,A32)/G32)) -> 0 | AF32: =IF(OR(A32="",G32=""),"",IF(G32=0,"",SUMIFS('Recipe Ingredients'!$R$5:$R$1204,'Recipe Ingredients'!$B$5:$B$1204,A32)/G32)) -> 0 | AG32: =IF(OR(A32="",G32=""),"",IF(G32=0,"",SUMIFS('Recipe Ingredients'!$S$5:$S$1204,'Recipe Ingredients'!$B$5:$B$1204,A32)/G32)) -> 0 | AH32: =IF(OR(A32="",G32=""),"",IF(G32=0,"",SUMIFS('Recipe Ingredients'!$T$5:$T$1204,'Recipe Ingredients'!$B$5:$B$1204,A32)/G32)) -> 0 | AI32: =IF(OR(A32="",G32=""),"",IF(G32=0,"",SUMIFS('Recipe Ingredients'!$U$5:$U$1204,'Recipe Ingredients'!$B$5:$B$1204,A32)/G32)) -> 0 | AJ32: =IF(A32="","",IF(COUNTIFS('Recipe Ingredients'!$B$5:$B$1204,A32,'Recipe Ingredients'!$V$5:$V$1204,"<>",'Recipe Ingredients'!$V$5:$V$1204,"<>None")=0,"None listed",COUNTIFS('Recipe Ingredients'!$B$5:$B$1204,A32,'Recipe Ingredients'!$V$5:$V$1204,"<>",'Recipe Ingredients'!$V$5:$V$1204,"<>None")&" ingredient(s) flagged")) -> 0 | AK32: =IF(OR(AD32="",NOT(ISNUMBER(AD32))),"",COUNTIFS($AD$5:$AD$204,"<"&AD32)+COUNTIFS($AD$5:AD32,AD32)) -> 0 | AL32: =IF(B32="",0,IF(AND(OR(FilterDiet="Any",T32=FilterDiet),OR(FilterCategory="Any",C32=FilterCategory),OR(FilterMethod="Any",L32=FilterMethod),OR(FilterTime=0,AND(J32<>"",J32<=FilterTime)),OR(FilterCost=0,AND(AD32<>"",ISNUMBER(AD32),AD32<=FilterCost)),OR(FilterAllergen="Any",COUNTIFS('Recipe Ingredients'!$B$5:$B$1204,A32,'Recipe Ingredients'!$V$5:$V$1204,FilterAllergen)=0)),1,0)) -> 0 | AM32: =IF(AL32=0,"",SUM($AL$5:AL32)) -> 0 | AN32: =IF(B32="","",COUNTIFS($AZ$5:$AZ$204,">"&AZ32)+COUNTIFS($AZ$5:AZ32,AZ32)) -> 0 | AO32: =IF(B32="","",COUNTIFS($AE$5:$AE$204,">"&AE32)+COUNTIFS($AE$5:AE32,AE32)) -> 0 | AP32: =IF(B32="","",COUNTIFS($AF$5:$AF$204,">"&AF32)+COUNTIFS($AF$5:AF32,AF32)) -> 0 | AQ32: =IF(B32="","",COUNTIFS($AI$5:$AI$204,">"&AI32)+COUNTIFS($AI$5:AI32,AI32)) -> 0 | AR32: =IF(B32="","",COUNTIFS($AS$5:$AS$204,">"&AS32)+COUNTIFS($AS$5:AS32,AS32)) -> 0 | AS32: =IF(B32="","",IF(BB32="",99999,BC32)) -> 0 | AT32: =IF(A32="",0,SUMIFS('Meal Plan'!$L$5:$L$504,'Meal Plan'!$G$5:$G$504,A32,'Meal Plan'!$B$5:$B$504,">="&ShopFrom,'Meal Plan'!$B$5:$B$504,"<="&ShopTo,'Meal Plan'!$M$5:$M$504,"Yes")) -> 0 | AU32: =IF(OR(A32="",AC32=""),"",AC32*AT32) -> 0 | AV32: =IF(A32="","",COUNTIFS('Recipe Ingredients'!$B$5:$B$1204,A32,'Recipe Ingredients'!$N$5:$N$1204,"")) -> 0 | AZ32: =IF(A32="","",COUNTIFS('Meal Plan'!$G$5:$G$504,A32)) -> 0 | BA32: =IF(A32="","",COUNTIFS('Meal Plan'!$G$5:$G$504,A32,'Meal Plan'!$N$5:$N$504,"Prepared")+COUNTIFS('Meal Plan'!$G$5:$G$504,A32,'Meal Plan'!$N$5:$N$504,"Eaten")) -> 0 | BB32: =IF(A32="","",IF(COUNTIFS('Meal Plan'!$G$5:$G$504,A32,'Meal Plan'!$B$5:$B$504,"<="&TODAY())=0,"",SUMPRODUCT(MAX(('Meal Plan'!$G$5:$G$504=A32)*('Meal Plan'!$B$5:$B$504<=TODAY())*'Meal Plan'!$B$5:$B$504)))) -> 0 | BC32: =IF(BB32="","",TODAY()-BB32) -> 0 | BF32: =IF(B32="","",IF(G32="","Add - how many does it serve?",IF(AB32=0,"Add - no ingredients listed yet",IF(AV32>0,"Check - "&AV32&" ingredient(s) have no price",IF(AND(BC32<>"",BC32<RotationGapDays),"Cooked recently","OK"))))) -> 0
A33: =IF(B33="","",RecipePrefix&TEXT(ROW()-4,"0000")) -> 0 | J33: =IF(B33="","",IF(AND(H33="",I33=""),"",IF(H33="",0,H33)+IF(I33="",0,I33))) -> 0 | K33: =IF(J33="","",IF(J33<=30,"Yes","No")) -> 0 | AB33: =IF(A33="","",COUNTIFS('Recipe Ingredients'!$B$5:$B$1204,A33)) -> 0 | AC33: =IF(A33="","",SUMIFS('Recipe Ingredients'!$N$5:$N$1204,'Recipe Ingredients'!$B$5:$B$1204,A33)) -> 0 | AD33: =IF(OR(AC33="",G33=""),"",IF(G33=0,"",AC33/G33)) -> 0 | AE33: =IF(OR(A33="",G33=""),"",IF(G33=0,"",SUMIFS('Recipe Ingredients'!$Q$5:$Q$1204,'Recipe Ingredients'!$B$5:$B$1204,A33)/G33)) -> 0 | AF33: =IF(OR(A33="",G33=""),"",IF(G33=0,"",SUMIFS('Recipe Ingredients'!$R$5:$R$1204,'Recipe Ingredients'!$B$5:$B$1204,A33)/G33)) -> 0 | AG33: =IF(OR(A33="",G33=""),"",IF(G33=0,"",SUMIFS('Recipe Ingredients'!$S$5:$S$1204,'Recipe Ingredients'!$B$5:$B$1204,A33)/G33)) -> 0 | AH33: =IF(OR(A33="",G33=""),"",IF(G33=0,"",SUMIFS('Recipe Ingredients'!$T$5:$T$1204,'Recipe Ingredients'!$B$5:$B$1204,A33)/G33)) -> 0 | AI33: =IF(OR(A33="",G33=""),"",IF(G33=0,"",SUMIFS('Recipe Ingredients'!$U$5:$U$1204,'Recipe Ingredients'!$B$5:$B$1204,A33)/G33)) -> 0 | AJ33: =IF(A33="","",IF(COUNTIFS('Recipe Ingredients'!$B$5:$B$1204,A33,'Recipe Ingredients'!$V$5:$V$1204,"<>",'Recipe Ingredients'!$V$5:$V$1204,"<>None")=0,"None listed",COUNTIFS('Recipe Ingredients'!$B$5:$B$1204,A33,'Recipe Ingredients'!$V$5:$V$1204,"<>",'Recipe Ingredients'!$V$5:$V$1204,"<>None")&" ingredient(s) flagged")) -> 0 | AK33: =IF(OR(AD33="",NOT(ISNUMBER(AD33))),"",COUNTIFS($AD$5:$AD$204,"<"&AD33)+COUNTIFS($AD$5:AD33,AD33)) -> 0 | AL33: =IF(B33="",0,IF(AND(OR(FilterDiet="Any",T33=FilterDiet),OR(FilterCategory="Any",C33=FilterCategory),OR(FilterMethod="Any",L33=FilterMethod),OR(FilterTime=0,AND(J33<>"",J33<=FilterTime)),OR(FilterCost=0,AND(AD33<>"",ISNUMBER(AD33),AD33<=FilterCost)),OR(FilterAllergen="Any",COUNTIFS('Recipe Ingredients'!$B$5:$B$1204,A33,'Recipe Ingredients'!$V$5:$V$1204,FilterAllergen)=0)),1,0)) -> 0 | AM33: =IF(AL33=0,"",SUM($AL$5:AL33)) -> 0 | AN33: =IF(B33="","",COUNTIFS($AZ$5:$AZ$204,">"&AZ33)+COUNTIFS($AZ$5:AZ33,AZ33)) -> 0 | AO33: =IF(B33="","",COUNTIFS($AE$5:$AE$204,">"&AE33)+COUNTIFS($AE$5:AE33,AE33)) -> 0 | AP33: =IF(B33="","",COUNTIFS($AF$5:$AF$204,">"&AF33)+COUNTIFS($AF$5:AF33,AF33)) -> 0 | AQ33: =IF(B33="","",COUNTIFS($AI$5:$AI$204,">"&AI33)+COUNTIFS($AI$5:AI33,AI33)) -> 0 | AR33: =IF(B33="","",COUNTIFS($AS$5:$AS$204,">"&AS33)+COUNTIFS($AS$5:AS33,AS33)) -> 0 | AS33: =IF(B33="","",IF(BB33="",99999,BC33)) -> 0 | AT33: =IF(A33="",0,SUMIFS('Meal Plan'!$L$5:$L$504,'Meal Plan'!$G$5:$G$504,A33,'Meal Plan'!$B$5:$B$504,">="&ShopFrom,'Meal Plan'!$B$5:$B$504,"<="&ShopTo,'Meal Plan'!$M$5:$M$504,"Yes")) -> 0 | AU33: =IF(OR(A33="",AC33=""),"",AC33*AT33) -> 0 | AV33: =IF(A33="","",COUNTIFS('Recipe Ingredients'!$B$5:$B$1204,A33,'Recipe Ingredients'!$N$5:$N$1204,"")) -> 0 | AZ33: =IF(A33="","",COUNTIFS('Meal Plan'!$G$5:$G$504,A33)) -> 0 | BA33: =IF(A33="","",COUNTIFS('Meal Plan'!$G$5:$G$504,A33,'Meal Plan'!$N$5:$N$504,"Prepared")+COUNTIFS('Meal Plan'!$G$5:$G$504,A33,'Meal Plan'!$N$5:$N$504,"Eaten")) -> 0 | BB33: =IF(A33="","",IF(COUNTIFS('Meal Plan'!$G$5:$G$504,A33,'Meal Plan'!$B$5:$B$504,"<="&TODAY())=0,"",SUMPRODUCT(MAX(('Meal Plan'!$G$5:$G$504=A33)*('Meal Plan'!$B$5:$B$504<=TODAY())*'Meal Plan'!$B$5:$B$504)))) -> 0 | BC33: =IF(BB33="","",TODAY()-BB33) -> 0 | BF33: =IF(B33="","",IF(G33="","Add - how many does it serve?",IF(AB33=0,"Add - no ingredients listed yet",IF(AV33>0,"Check - "&AV33&" ingredient(s) have no price",IF(AND(BC33<>"",BC33<RotationGapDays),"Cooked recently","OK"))))) -> 0
A34: =IF(B34="","",RecipePrefix&TEXT(ROW()-4,"0000")) -> 0 | J34: =IF(B34="","",IF(AND(H34="",I34=""),"",IF(H34="",0,H34)+IF(I34="",0,I34))) -> 0 | K34: =IF(J34="","",IF(J34<=30,"Yes","No")) -> 0 | AB34: =IF(A34="","",COUNTIFS('Recipe Ingredients'!$B$5:$B$1204,A34)) -> 0 | AC34: =IF(A34="","",SUMIFS('Recipe Ingredients'!$N$5:$N$1204,'Recipe Ingredients'!$B$5:$B$1204,A34)) -> 0 | AD34: =IF(OR(AC34="",G34=""),"",IF(G34=0,"",AC34/G34)) -> 0 | AE34: =IF(OR(A34="",G34=""),"",IF(G34=0,"",SUMIFS('Recipe Ingredients'!$Q$5:$Q$1204,'Recipe Ingredients'!$B$5:$B$1204,A34)/G34)) -> 0 | AF34: =IF(OR(A34="",G34=""),"",IF(G34=0,"",SUMIFS('Recipe Ingredients'!$R$5:$R$1204,'Recipe Ingredients'!$B$5:$B$1204,A34)/G34)) -> 0 | AG34: =IF(OR(A34="",G34=""),"",IF(G34=0,"",SUMIFS('Recipe Ingredients'!$S$5:$S$1204,'Recipe Ingredients'!$B$5:$B$1204,A34)/G34)) -> 0 | AH34: =IF(OR(A34="",G34=""),"",IF(G34=0,"",SUMIFS('Recipe Ingredients'!$T$5:$T$1204,'Recipe Ingredients'!$B$5:$B$1204,A34)/G34)) -> 0 | AI34: =IF(OR(A34="",G34=""),"",IF(G34=0,"",SUMIFS('Recipe Ingredients'!$U$5:$U$1204,'Recipe Ingredients'!$B$5:$B$1204,A34)/G34)) -> 0 | AJ34: =IF(A34="","",IF(COUNTIFS('Recipe Ingredients'!$B$5:$B$1204,A34,'Recipe Ingredients'!$V$5:$V$1204,"<>",'Recipe Ingredients'!$V$5:$V$1204,"<>None")=0,"None listed",COUNTIFS('Recipe Ingredients'!$B$5:$B$1204,A34,'Recipe Ingredients'!$V$5:$V$1204,"<>",'Recipe Ingredients'!$V$5:$V$1204,"<>None")&" ingredient(s) flagged")) -> 0 | AK34: =IF(OR(AD34="",NOT(ISNUMBER(AD34))),"",COUNTIFS($AD$5:$AD$204,"<"&AD34)+COUNTIFS($AD$5:AD34,AD34)) -> 0 | AL34: =IF(B34="",0,IF(AND(OR(FilterDiet="Any",T34=FilterDiet),OR(FilterCategory="Any",C34=FilterCategory),OR(FilterMethod="Any",L34=FilterMethod),OR(FilterTime=0,AND(J34<>"",J34<=FilterTime)),OR(FilterCost=0,AND(AD34<>"",ISNUMBER(AD34),AD34<=FilterCost)),OR(FilterAllergen="Any",COUNTIFS('Recipe Ingredients'!$B$5:$B$1204,A34,'Recipe Ingredients'!$V$5:$V$1204,FilterAllergen)=0)),1,0)) -> 0 | AM34: =IF(AL34=0,"",SUM($AL$5:AL34)) -> 0 | AN34: =IF(B34="","",COUNTIFS($AZ$5:$AZ$204,">"&AZ34)+COUNTIFS($AZ$5:AZ34,AZ34)) -> 0 | AO34: =IF(B34="","",COUNTIFS($AE$5:$AE$204,">"&AE34)+COUNTIFS($AE$5:AE34,AE34)) -> 0 | AP34: =IF(B34="","",COUNTIFS($AF$5:$AF$204,">"&AF34)+COUNTIFS($AF$5:AF34,AF34)) -> 0 | AQ34: =IF(B34="","",COUNTIFS($AI$5:$AI$204,">"&AI34)+COUNTIFS($AI$5:AI34,AI34)) -> 0 | AR34: =IF(B34="","",COUNTIFS($AS$5:$AS$204,">"&AS34)+COUNTIFS($AS$5:AS34,AS34)) -> 0 | AS34: =IF(B34="","",IF(BB34="",99999,BC34)) -> 0 | AT34: =IF(A34="",0,SUMIFS('Meal Plan'!$L$5:$L$504,'Meal Plan'!$G$5:$G$504,A34,'Meal Plan'!$B$5:$B$504,">="&ShopFrom,'Meal Plan'!$B$5:$B$504,"<="&ShopTo,'Meal Plan'!$M$5:$M$504,"Yes")) -> 0 | AU34: =IF(OR(A34="",AC34=""),"",AC34*AT34) -> 0 | AV34: =IF(A34="","",COUNTIFS('Recipe Ingredients'!$B$5:$B$1204,A34,'Recipe Ingredients'!$N$5:$N$1204,"")) -> 0 | AZ34: =IF(A34="","",COUNTIFS('Meal Plan'!$G$5:$G$504,A34)) -> 0 | BA34: =IF(A34="","",COUNTIFS('Meal Plan'!$G$5:$G$504,A34,'Meal Plan'!$N$5:$N$504,"Prepared")+COUNTIFS('Meal Plan'!$G$5:$G$504,A34,'Meal Plan'!$N$5:$N$504,"Eaten")) -> 0 | BB34: =IF(A34="","",IF(COUNTIFS('Meal Plan'!$G$5:$G$504,A34,'Meal Plan'!$B$5:$B$504,"<="&TODAY())=0,"",SUMPRODUCT(MAX(('Meal Plan'!$G$5:$G$504=A34)*('Meal Plan'!$B$5:$B$504<=TODAY())*'Meal Plan'!$B$5:$B$504)))) -> 0 | BC34: =IF(BB34="","",TODAY()-BB34) -> 0 | BF34: =IF(B34="","",IF(G34="","Add - how many does it serve?",IF(AB34=0,"Add - no ingredients listed yet",IF(AV34>0,"Check - "&AV34&" ingredient(s) have no price",IF(AND(BC34<>"",BC34<RotationGapDays),"Cooked recently","OK"))))) -> 0
