Workbook
Name AppetiteList: OFFSET(Lists!$T$5,0,0,MAX(1,COUNTIF(Lists!$T$5:$T$44,"?*")),1)
Name BillingUnitList: OFFSET(Lists!$M$5,0,0,MAX(1,COUNTIF(Lists!$M$5:$M$44,"?*")),1)
Name Biz_Address: Settings!$D$11
Name Biz_Bank: Settings!$D$17
Name Biz_City: Settings!$D$12
Name Biz_Country: Settings!$D$15
Name Biz_Email: Settings!$D$9
Name Biz_InsuranceRenewal: Settings!$D$20
Name Biz_Insurer: Settings!$D$18
Name Biz_Licence: Settings!$D$21
Name Biz_LicenceRenewal: Settings!$D$22
Name Biz_Name: Settings!$D$6
Name Biz_Owner: Settings!$D$7
Name Biz_Phone: Settings!$D$8
Name Biz_Policy: Settings!$D$19
Name Biz_Post: Settings!$D$14
Name Biz_State: Settings!$D$13
Name Biz_TaxID: Settings!$D$16
Name Biz_Web: Settings!$D$10
Name BookingIDs: OFFSET(Bookings!$A$5,0,0,MAX(1,COUNTIF(Bookings!$A$5:$A$404,"?*")),1)
Name BookingPrefix: Settings!$D$54
Name BookingStatusList: OFFSET(Lists!$N$5,0,0,MAX(1,COUNTIF(Lists!$N$5:$N$44,"?*")),1)
Name BusinessPersonalList: OFFSET(Lists!$AI$5,0,0,MAX(1,COUNTIF(Lists!$AI$5:$AI$44,"?*")),1)
Name CancelReasonList: OFFSET(Lists!$Q$5,0,0,MAX(1,COUNTIF(Lists!$Q$5:$Q$44,"?*")),1)
Name ChannelList: OFFSET(Lists!$AB$5,0,0,MAX(1,COUNTIF(Lists!$AB$5:$AB$44,"?*")),1)
Name ClientIDs: OFFSET(Clients!$A$5,0,0,MAX(1,COUNTIF(Clients!$A$5:$A$254,"?*")),1)
Name ClientNames: OFFSET(Clients!$B$5,0,0,MAX(1,COUNTIF(Clients!$B$5:$B$254,"?*")),1)
Name ClientPrefix: Settings!$D$52
Name ClientStatusList: OFFSET(Lists!$C$5,0,0,MAX(1,COUNTIF(Lists!$C$5:$C$44,"?*")),1)
Name ContactMethodList: OFFSET(Lists!$D$5,0,0,MAX(1,COUNTIF(Lists!$D$5:$D$44,"?*")),1)
Name ContractStatusList: OFFSET(Lists!$F$5,0,0,MAX(1,COUNTIF(Lists!$F$5:$F$44,"?*")),1)
Name CurrencyCode: Settings!$D$33
Name CurrencySymbol: Settings!$D$32
Name Dash_Expenses: Dashboard!$M$10
Name Dash_MonthName: Dashboard!$F$6
Name Dash_Profit: Dashboard!$P$10
Name Dash_Revenue: Dashboard!$A$10
Name Dash_Year: Dashboard!$C$6
Name DayEnd: Settings!$D$80
Name DayStart: Settings!$D$79
Name DefaultVisitMins: Settings!$D$78
Name DepositPct: Settings!$D$50
Name DirectionList: OFFSET(Lists!$AC$5,0,0,MAX(1,COUNTIF(Lists!$AC$5:$AC$44,"?*")),1)
Name DiscountTypeList: OFFSET(Lists!$P$5,0,0,MAX(1,COUNTIF(Lists!$P$5:$P$44,"?*")),1)
Name DistanceUnit: Settings!$D$36
Name EmergencyFee: Settings!$D$60
Name EmploymentTypeList: OFFSET(Lists!$AM$5,0,0,MAX(1,COUNTIF(Lists!$AM$5:$AM$44,"?*")),1)
Name ExpenseApprovalList: OFFSET(Lists!$AH$5,0,0,MAX(1,COUNTIF(Lists!$AH$5:$AH$44,"?*")),1)
Name ExpenseCategoryList: OFFSET(Lists!$AG$5,0,0,MAX(1,COUNTIF(Lists!$AG$5:$AG$44,"?*")),1)
Name ExpiryAlertDays: Settings!$D$77
Name ExtraPetFeeDefault: Settings!$D$57
Name FixedCosts: Budget!$B$10
Name FollowUpDays: Settings!$D$76
Name FreeTravelDistance: Settings!$D$69
Name FY_Start: Settings!$D$37
Name GrowthRate: Budget!$B$14
Name HealthRecordTypeList: OFFSET(Lists!$V$5,0,0,MAX(1,COUNTIF(Lists!$V$5:$V$44,"?*")),1)
Name HolidayDates: Settings!$B$85:$B$114
Name HolidaySurcharge: Settings!$D$58
Name InactiveDays: Settings!$D$75

Sheet Start Here
A1: Pet Sitting & Dog Walking Business Spreadsheet | H1: Novality Store - v1.0.0
A2: Client Booking, Pet Care Log, Invoices, Payments, Mileage & Profit Tracker
A4: ="Welcome "&Biz_Owner&" - this workbook is set up for "&Biz_Name&". Cream cells are yours to type in, grey cells are locked formulas that do the maths for you." -> 0
A6: Quick start - ten minutes to a working workbook
B7: 1. Open the Settings tab and enter your business details, currency, tax rate and mileage rate.
B8: 2. Edit the Services tab so the names and prices match what you actually sell.
B9: 3. Add your clients, then their pets (choose the owner from the drop down so they link up).
B10: 4. Add your team on the Staff tab - even if that is only you.
B11: 5. Take a booking: pick the client, pet and service and the price calculates itself.
B12: 6. After each visit, add a row to the Visit Log and tick off the care you gave.
B13: 7. Raise an invoice, link the booking, and record the payment when it lands.
B14: 8. Log expenses and trips as you go - future you will thank you at tax time.
B15: 9. Check the Reminders tab every morning and the Dashboard every week.
B16: 10. Print the reports you need at month end and save a dated backup.
A18: Where everything lives
B19: Tab | C19: What it does
B20: Settings | C20: Your business details, rates, tax, surcharges and reminder windows - set this up first.
B21: Lists | C21: Every drop down list in the workbook. Rename anything to match the way you talk about your services.
B22: Services | C22: Your price list. Billing unit, rate, extra pet fee and profit per service.
B23: Clients | C23: Client database with keys, contracts, lifetime revenue and follow-up flags.
B24: Pets | C24: Pet profiles: feeding, medication, vet, vaccinations, temperament and safety warnings.
B25: Bookings | C25: The schedule. Prices itself from the Services tab and warns you about double bookings.
B26: Visit Log | C26: Proof of every walk and visit: times, care given, mood, health notes and client updates.
B27: Health Log | C27: Medication administration, vaccinations and vet appointments.
B28: Incidents | C28: Emergency contacts and incident reports.
B29: Messages | C29: Client communication, feedback, ratings and complaints.
B30: Invoices | C30: Automatic invoice numbers, due dates, tax, balances and ageing.
... B44: Help | C44: Instructions, formula notes, troubleshooting and version history.
A46: Getting started checklist
B47: Step | C47: What to do | H47: Done?
B48: Step 1 | C48: Business details added on the Settings tab | H48: No
B49: Step 2 | C49: Currency, tax rate and payment terms checked | H49: No
B50: Step 3 | C50: Mileage rate and travel fees set | H50: No
B51: Step 4 | C51: Service names and prices updated | H51: No
B52: Step 5 | C52: Drop down lists adjusted to suit my business | H52: No
B53: Step 6 | C53: Public holidays added for this year | H53: No
B54: Step 7 | C54: First clients entered | H54: No
B55: Step 8 | C55: Pets added and linked to their owners | H55: No
B56: Step 9 | C56: Staff or contractors added | H56: No
B57: Step 10 | C57: Sample data deleted (rows 5 onwards on each tab) | H57: No
B58: Step 11 | C58: Invoice number and prefix set the way I want | H58: No
B59: Step 12 | C59: A backup copy saved somewhere safe | H59: No
B60: Setup progress | H60: =COUNTIF($H$48:$H$59,"Yes")/12 -> 0
A62: How to read the colours
B63: Cream cell | C63: Type here. These cells stay unlocked while the sheet is protected.
B64: Grey cell | C64: A locked formula. Protected with the password so it cannot be overwritten by accident.
B65: Red / amber | C65: Conditional formatting: red means act today, amber means act soon, green means you are on top of it.
A67: Product information
B68: Product | C68: Pet Sitting & Dog Walking Business Spreadsheet
B69: Edition | C69: Version 1.0.0 - released 2026-10-11
B70: Author | C70: Novality Store
B71: Formula protection | C71: Every sheet is protected. Password: premium (Review > Unprotect Sheet if you need to change a formula).
B72: Works with | C72: Microsoft Excel 2010 or newer on Windows and Mac, Excel 365, and Google Sheets after import.
B73: Support | C73: See the Help tab for troubleshooting, formula notes and backup guidance.
A75: (c) Novality Store - thank you for your purchase. Personal and single-business use.

Sheet Dashboard
A1: Business Dashboard | P1: Novality Store | v1.0.0
A2: Pick a period, then read the business at a glance. Every number is live - it updates as you fill in the other tabs.
A3: > Start Here | C3: > Dashboard | E3: > Clients | G3: > Pets | I3: > Bookings | K3: > Visit Log | M3: > Invoices | O3: > Reminders | Q3: > Help
A5: Reporting period
A6: Year | C6: 2026 | D6: Month | F6: All year | H6: Period start | J6: =IF(Dash_MonthName="All year",DATE(Dash_Year,1,1),DATE(Dash_Year,MAX(1,MATCH(Dash_MonthName,MonthList,0)-1),1)) -> 0 | L6: Period end | N6: =IF(Dash_MonthName="All year",DATE(Dash_Year,12,31),EOMONTH(PeriodStart,0)) -> 0 | P6: Today | R6: =TODAY() -> 0
A8: Money
A9: Revenue collected | D9: Invoiced | G9: Outstanding | J9: Overdue | M9: Expenses | P9: Net profit
A10: =SUMIFS(Payments!$L$5:$L$304,Payments!$B$5:$B$304,">="&PeriodStart,Payments!$B$5:$B$304,"<="&PeriodEnd) -> 0 | D10: =SUMIFS(Invoices!$O$5:$O$304,Invoices!$B$5:$B$304,">="&PeriodStart,Invoices!$B$5:$B$304,"<="&PeriodEnd,Invoices!$T$5:$T$304,"<>Cancelled") -> 0 | G10: =SUMIFS(Invoices!$S$5:$S$304,Invoices!$T$5:$T$304,"<>Cancelled") -> 0 | J10: =SUMIFS(Invoices!$S$5:$S$304,Invoices!$U$5:$U$304,"Overdue")+SUMIFS(Invoices!$S$5:$S$304,Invoices!$U$5:$U$304,"Overdue - part paid") -> 0 | M10: =SUMIFS(Expenses!$F$5:$F$304,Expenses!$B$5:$B$304,">="&PeriodStart,Expenses!$B$5:$B$304,"<="&PeriodEnd,Expenses!$J$5:$J$304,"<>Personal") -> 0 | P10: =Dash_Revenue-Dash_Expenses -> 0
A11: Payments received in the period | D11: Value of invoices raised | G11: Unpaid balance, all invoices | J11: Past the due date - chase today | M11: Business costs in the period | P11: Revenue collected less expenses
A12: Profit margin | D12: Average booking value | G12: Revenue per active client | J12: Mileage claim | M12: Tax to set aside | P12: Cash collected per visit
A13: =IFERROR(Dash_Profit/Dash_Revenue,0) -> 0 | D13: =IFERROR(SUMIFS(Bookings!$AK$5:$AK$404,Bookings!$I$5:$I$404,">="&PeriodStart,Bookings!$I$5:$I$404,"<="&PeriodEnd,Bookings!$AM$5:$AM$404,"<>Cancelled")/COUNTIFS(Bookings!$I$5:$I$404,">="&PeriodStart,Bookings!$I$5:$I$404,"<="&PeriodEnd,Bookings!$AM$5:$AM$404,"<>Cancelled"),0) -> 0 | G13: =IFERROR(Dash_Revenue/COUNTIF(Clients!$M$5:$M$254,"Active"),0) -> 0 | J13: =SUMIFS(Mileage!$U$5:$U$304,Mileage!$B$5:$B$304,">="&PeriodStart,Mileage!$B$5:$B$304,"<="&PeriodEnd) -> 0 | M13: =MAX(0,Dash_Profit)*TaxReservePct -> 0 | P13: =IFERROR(Dash_Revenue/COUNTIFS('Visit Log'!$C$5:$C$404,">="&PeriodStart,'Visit Log'!$C$5:$C$404,"<="&PeriodEnd,'Visit Log'!$AE$5:$AE$404,"Completed"),0) -> 0
A14: Net profit as a share of revenue | D14: Booked value per job | G14: Period revenue / active clients | J14: Travel you can claim back | M14: Profit x tax reserve % from Settings | P14: Revenue / completed visits
A16: Bookings, visits & clients
A17: Bookings in period | D17: Completed | G17: Cancelled | J17: Upcoming (7 days) | M17: Visits completed | P17: Missed visits
A18: =COUNTIFS(Bookings!$I$5:$I$404,">="&PeriodStart,Bookings!$I$5:$I$404,"<="&PeriodEnd,Bookings!$AM$5:$AM$404,"<>Cancelled") -> 0 | D18: =COUNTIFS(Bookings!$I$5:$I$404,">="&PeriodStart,Bookings!$I$5:$I$404,"<="&PeriodEnd,Bookings!$AM$5:$AM$404,"Completed") -> 0 | G18: =COUNTIFS(Bookings!$I$5:$I$404,">="&PeriodStart,Bookings!$I$5:$I$404,"<="&PeriodEnd,Bookings!$AM$5:$AM$404,"Cancelled") -> 0 | J18: =COUNTIFS(Bookings!$I$5:$I$404,">="&TODAY(),Bookings!$I$5:$I$404,"<="&TODAY()+7,Bookings!$AM$5:$AM$404,"<>Cancelled") -> 0 | M18: =COUNTIFS('Visit Log'!$C$5:$C$404,">="&PeriodStart,'Visit Log'!$C$5:$C$404,"<="&PeriodEnd,'Visit Log'!$AE$5:$AE$404,"Completed") -> 0 | P18: =COUNTIFS('Visit Log'!$C$5:$C$404,">="&PeriodStart,'Visit Log'!$C$5:$C$404,"<="&PeriodEnd,'Visit Log'!$AE$5:$AE$404,"Missed") -> 0
A19: Excludes cancellations | D19: Jobs delivered | G19: Watch the cancellation rate | J19: Next seven days | M19: Logged in the Visit Log | P19: Investigate every one
A20: Active clients | D20: Pets on the books | G20: New clients | J20: Repeat clients | M20: Unconfirmed bookings | P20: Average rating
A21: =COUNTIF(Clients!$M$5:$M$254,"Active") -> 0 | D21: =COUNTIF(Pets!$B$5:$B$254,"?*") -> 0 | G21: =COUNTIFS(Clients!$L$5:$L$254,">="&PeriodStart,Clients!$L$5:$L$254,"<="&PeriodEnd) -> 0 | J21: =COUNTIF(Clients!$Z$5:$Z$254,">1") -> 0 | M21: =COUNTIFS(Bookings!$I$5:$I$404,">="&TODAY(),Bookings!$AN$5:$AN$404,"<>Yes",Bookings!$AM$5:$AM$404,"<>Cancelled") -> 0 | P21: =IFERROR(AVERAGEIFS(Messages!$I$5:$I$204,Messages!$B$5:$B$204,">="&PeriodStart,Messages!$B$5:$B$204,"<="&PeriodEnd),"-") -> 0
A22: Clients marked Active | D22: All registered pets | G22: Registered in the period | J22: More than one booking | M22: Send a confirmation | P22: Client satisfaction, 1 to 5
A24: Monthly performance - trends for the selected year
A25: Month | B25: Revenue | C25: Invoiced | D25: Expenses | E25: Profit | F25: Margin | G25: Bookings | H25: Completed | I25: Cancelled | J25: Visits | K25: New clients | L25: Distance | M25: Last year | N25: Change
A26: =Calc!$U$5 -> 0 | B26: =Calc!$V$5 -> 0 | C26: =Calc!$W$5 -> 0 | D26: =Calc!$X$5 -> 0 | E26: =Calc!$Y$5 -> 0 | F26: =IFERROR(Calc!$Y$5/Calc!$V$5,"") -> 0 | G26: =Calc!$Z$5 -> 0 | H26: =Calc!$AA$5 -> 0 | I26: =Calc!$AB$5 -> 0 | J26: =Calc!$AC$5 -> 0 | K26: =Calc!$AD$5 -> 0 | L26: =Calc!$AE$5 -> 0 | M26: =Calc!$AF$5 -> 0 | N26: =IFERROR(Calc!$V$5/Calc!$AF$5-1,"") -> 0
A27: =Calc!$U$6 -> 0 | B27: =Calc!$V$6 -> 0 | C27: =Calc!$W$6 -> 0 | D27: =Calc!$X$6 -> 0 | E27: =Calc!$Y$6 -> 0 | F27: =IFERROR(Calc!$Y$6/Calc!$V$6,"") -> 0 | G27: =Calc!$Z$6 -> 0 | H27: =Calc!$AA$6 -> 0 | I27: =Calc!$AB$6 -> 0 | J27: =Calc!$AC$6 -> 0 | K27: =Calc!$AD$6 -> 0 | L27: =Calc!$AE$6 -> 0 | M27: =Calc!$AF$6 -> 0 | N27: =IFERROR(Calc!$V$6/Calc!$AF$6-1,"") -> 0
A28: =Calc!$U$7 -> 0 | B28: =Calc!$V$7 -> 0 | C28: =Calc!$W$7 -> 0 | D28: =Calc!$X$7 -> 0 | E28: =Calc!$Y$7 -> 0 | F28: =IFERROR(Calc!$Y$7/Calc!$V$7,"") -> 0 | G28: =Calc!$Z$7 -> 0 | H28: =Calc!$AA$7 -> 0 | I28: =Calc!$AB$7 -> 0 | J28: =Calc!$AC$7 -> 0 | K28: =Calc!$AD$7 -> 0 | L28: =Calc!$AE$7 -> 0 | M28: =Calc!$AF$7 -> 0 | N28: =IFERROR(Calc!$V$7/Calc!$AF$7-1,"") -> 0
A29: =Calc!$U$8 -> 0 | B29: =Calc!$V$8 -> 0 | C29: =Calc!$W$8 -> 0 | D29: =Calc!$X$8 -> 0 | E29: =Calc!$Y$8 -> 0 | F29: =IFERROR(Calc!$Y$8/Calc!$V$8,"") -> 0 | G29: =Calc!$Z$8 -> 0 | H29: =Calc!$AA$8 -> 0 | I29: =Calc!$AB$8 -> 0 | J29: =Calc!$AC$8 -> 0 | K29: =Calc!$AD$8 -> 0 | L29: =Calc!$AE$8 -> 0 | M29: =Calc!$AF$8 -> 0 | N29: =IFERROR(Calc!$V$8/Calc!$AF$8-1,"") -> 0
A30: =Calc!$U$9 -> 0 | B30: =Calc!$V$9 -> 0 | C30: =Calc!$W$9 -> 0 | D30: =Calc!$X$9 -> 0 | E30: =Calc!$Y$9 -> 0 | F30: =IFERROR(Calc!$Y$9/Calc!$V$9,"") -> 0 | G30: =Calc!$Z$9 -> 0 | H30: =Calc!$AA$9 -> 0 | I30: =Calc!$AB$9 -> 0 | J30: =Calc!$AC$9 -> 0 | K30: =Calc!$AD$9 -> 0 | L30: =Calc!$AE$9 -> 0 | M30: =Calc!$AF$9 -> 0 | N30: =IFERROR(Calc!$V$9/Calc!$AF$9-1,"") -> 0
A31: =Calc!$U$10 -> 0 | B31: =Calc!$V$10 -> 0 | C31: =Calc!$W$10 -> 0 | D31: =Calc!$X$10 -> 0 | E31: =Calc!$Y$10 -> 0 | F31: =IFERROR(Calc!$Y$10/Calc!$V$10,"") -> 0 | G31: =Calc!$Z$10 -> 0 | H31: =Calc!$AA$10 -> 0 | I31: =Calc!$AB$10 -> 0 | J31: =Calc!$AC$10 -> 0 | K31: =Calc!$AD$10 -> 0 | L31: =Calc!$AE$10 -> 0 | M31: =Calc!$AF$10 -> 0 | N31: =IFERROR(Calc!$V$10/Calc!$AF$10-1,"") -> 0
A32: =Calc!$U$11 -> 0 | B32: =Calc!$V$11 -> 0 | C32: =Calc!$W$11 -> 0 | D32: =Calc!$X$11 -> 0 | E32: =Calc!$Y$11 -> 0 | F32: =IFERROR(Calc!$Y$11/Calc!$V$11,"") -> 0 | G32: =Calc!$Z$11 -> 0 | H32: =Calc!$AA$11 -> 0 | I32: =Calc!$AB$11 -> 0 | J32: =Calc!$AC$11 -> 0 | K32: =Calc!$AD$11 -> 0 | L32: =Calc!$AE$11 -> 0 | M32: =Calc!$AF$11 -> 0 | N32: =IFERROR(Calc!$V$11/Calc!$AF$11-1,"") -> 0
A33: =Calc!$U$12 -> 0 | B33: =Calc!$V$12 -> 0 | C33: =Calc!$W$12 -> 0 | D33: =Calc!$X$12 -> 0 | E33: =Calc!$Y$12 -> 0 | F33: =IFERROR(Calc!$Y$12/Calc!$V$12,"") -> 0 | G33: =Calc!$Z$12 -> 0 | H33: =Calc!$AA$12 -> 0 | I33: =Calc!$AB$12 -> 0 | J33: =Calc!$AC$12 -> 0 | K33: =Calc!$AD$12 -> 0 | L33: =Calc!$AE$12 -> 0 | M33: =Calc!$AF$12 -> 0 | N33: =IFERROR(Calc!$V$12/Calc!$AF$12-1,"") -> 0
A34: =Calc!$U$13 -> 0 | B34: =Calc!$V$13 -> 0 | C34: =Calc!$W$13 -> 0 | D34: =Calc!$X$13 -> 0 | E34: =Calc!$Y$13 -> 0 | F34: =IFERROR(Calc!$Y$13/Calc!$V$13,"") -> 0 | G34: =Calc!$Z$13 -> 0 | H34: =Calc!$AA$13 -> 0 | I34: =Calc!$AB$13 -> 0 | J34: =Calc!$AC$13 -> 0 | K34: =Calc!$AD$13 -> 0 | L34: =Calc!$AE$13 -> 0 | M34: =Calc!$AF$13 -> 0 | N34: =IFERROR(Calc!$V$13/Calc!$AF$13-1,"") -> 0
A35: =Calc!$U$14 -> 0 | B35: =Calc!$V$14 -> 0 | C35: =Calc!$W$14 -> 0 | D35: =Calc!$X$14 -> 0 | E35: =Calc!$Y$14 -> 0 | F35: =IFERROR(Calc!$Y$14/Calc!$V$14,"") -> 0 | G35: =Calc!$Z$14 -> 0 | H35: =Calc!$AA$14 -> 0 | I35: =Calc!$AB$14 -> 0 | J35: =Calc!$AC$14 -> 0 | K35: =Calc!$AD$14 -> 0 | L35: =Calc!$AE$14 -> 0 | M35: =Calc!$AF$14 -> 0 | N35: =IFERROR(Calc!$V$14/Calc!$AF$14-1,"") -> 0
A36: =Calc!$U$15 -> 0 | B36: =Calc!$V$15 -> 0 | C36: =Calc!$W$15 -> 0 | D36: =Calc!$X$15 -> 0 | E36: =Calc!$Y$15 -> 0 | F36: =IFERROR(Calc!$Y$15/Calc!$V$15,"") -> 0 | G36: =Calc!$Z$15 -> 0 | H36: =Calc!$AA$15 -> 0 | I36: =Calc!$AB$15 -> 0 | J36: =Calc!$AC$15 -> 0 | K36: =Calc!$AD$15 -> 0 | L36: =Calc!$AE$15 -> 0 | M36: =Calc!$AF$15 -> 0 | N36: =IFERROR(Calc!$V$15/Calc!$AF$15-1,"") -> 0
A37: =Calc!$U$16 -> 0 | B37: =Calc!$V$16 -> 0 | C37: =Calc!$W$16 -> 0 | D37: =Calc!$X$16 -> 0 | E37: =Calc!$Y$16 -> 0 | F37: =IFERROR(Calc!$Y$16/Calc!$V$16,"") -> 0 | G37: =Calc!$Z$16 -> 0 | H37: =Calc!$AA$16 -> 0 | I37: =Calc!$AB$16 -> 0 | J37: =Calc!$AC$16 -> 0 | K37: =Calc!$AD$16 -> 0 | L37: =Calc!$AE$16 -> 0 | M37: =Calc!$AF$16 -> 0 | N37: =IFERROR(Calc!$V$16/Calc!$AF$16-1,"") -> 0
A38: Year total | B38: =SUM(B26:B37) -> 0 | C38: =SUM(C26:C37) -> 0 | D38: =SUM(D26:D37) -> 0 | E38: =SUM(E26:E37) -> 0 | F38: =IFERROR(E38/B38,"") -> 0 | G38: =SUM(G26:G37) -> 0 | H38: =SUM(H26:H37) -> 0 | I38: =SUM(I26:I37) -> 0 | J38: =SUM(J26:J37) -> 0 | K38: =SUM(K26:K37) -> 0 | L38: =SUM(L26:L37) -> 0 | M38: =SUM(M26:M37) -> 0 | N38: =IFERROR(B38/M38-1,"") -> 0
A39: Trend
A41: Where the money comes from - and where it goes
A42: Revenue by service (selected period) | H42: Expenses by category (selected period)
A43: Service | B43: Bookings | C43: Revenue | D43: Share | H43: Category | I43: Spend | J43: Share
A44: =IF(Calc!$I$5="","",Calc!$I$5) -> 0 | B44: =IF(Calc!$I$5="","",Calc!$K$5) -> 0 | C44: =IF(Calc!$I$5="","",Calc!$J$5) -> 0 | D44: =IFERROR(Calc!$J$5/SUM(Calc!$J$5:$J$254),"") -> 0 | H44: =IF(Calc!$P$5="","",Calc!$P$5) -> 0 | I44: =IF(Calc!$P$5="","",Calc!$Q$5) -> 0 | J44: =IFERROR(Calc!$Q$5/SUM(Calc!$Q$5:$Q$254),"") -> 0
A45: =IF(Calc!$I$6="","",Calc!$I$6) -> 0 | B45: =IF(Calc!$I$6="","",Calc!$K$6) -> 0 | C45: =IF(Calc!$I$6="","",Calc!$J$6) -> 0 | D45: =IFERROR(Calc!$J$6/SUM(Calc!$J$5:$J$254),"") -> 0 | H45: =IF(Calc!$P$6="","",Calc!$P$6) -> 0 | I45: =IF(Calc!$P$6="","",Calc!$Q$6) -> 0 | J45: =IFERROR(Calc!$Q$6/SUM(Calc!$Q$5:$Q$254),"") -> 0
A46: =IF(Calc!$I$7="","",Calc!$I$7) -> 0 | B46: =IF(Calc!$I$7="","",Calc!$K$7) -> 0 | C46: =IF(Calc!$I$7="","",Calc!$J$7) -> 0 | D46: =IFERROR(Calc!$J$7/SUM(Calc!$J$5:$J$254),"") -> 0 | H46: =IF(Calc!$P$7="","",Calc!$P$7) -> 0 | I46: =IF(Calc!$P$7="","",Calc!$Q$7) -> 0 | J46: =IFERROR(Calc!$Q$7/SUM(Calc!$Q$5:$Q$254),"") -> 0
A47: =IF(Calc!$I$8="","",Calc!$I$8) -> 0 | B47: =IF(Calc!$I$8="","",Calc!$K$8) -> 0 | C47: =IF(Calc!$I$8="","",Calc!$J$8) -> 0 | D47: =IFERROR(Calc!$J$8/SUM(Calc!$J$5:$J$254),"") -> 0 | H47: =IF(Calc!$P$8="","",Calc!$P$8) -> 0 | I47: =IF(Calc!$P$8="","",Calc!$Q$8) -> 0 | J47: =IFERROR(Calc!$Q$8/SUM(Calc!$Q$5:$Q$254),"") -> 0
A48: =IF(Calc!$I$9="","",Calc!$I$9) -> 0 | B48: =IF(Calc!$I$9="","",Calc!$K$9) -> 0 | C48: =IF(Calc!$I$9="","",Calc!$J$9) -> 0 | D48: =IFERROR(Calc!$J$9/SUM(Calc!$J$5:$J$254),"") -> 0 | H48: =IF(Calc!$P$9="","",Calc!$P$9) -> 0 | I48: =IF(Calc!$P$9="","",Calc!$Q$9) -> 0 | J48: =IFERROR(Calc!$Q$9/SUM(Calc!$Q$5:$Q$254),"") -> 0
A49: =IF(Calc!$I$10="","",Calc!$I$10) -> 0 | B49: =IF(Calc!$I$10="","",Calc!$K$10) -> 0 | C49: =IF(Calc!$I$10="","",Calc!$J$10) -> 0 | D49: =IFERROR(Calc!$J$10/SUM(Calc!$J$5:$J$254),"") -> 0 | H49: =IF(Calc!$P$10="","",Calc!$P$10) -> 0 | I49: =IF(Calc!$P$10="","",Calc!$Q$10) -> 0 | J49: =IFERROR(Calc!$Q$10/SUM(Calc!$Q$5:$Q$254),"") -> 0
A50: =IF(Calc!$I$11="","",Calc!$I$11) -> 0 | B50: =IF(Calc!$I$11="","",Calc!$K$11) -> 0 | C50: =IF(Calc!$I$11="","",Calc!$J$11) -> 0 | D50: =IFERROR(Calc!$J$11/SUM(Calc!$J$5:$J$254),"") -> 0 | H50: =IF(Calc!$P$11="","",Calc!$P$11) -> 0 | I50: =IF(Calc!$P$11="","",Calc!$Q$11) -> 0 | J50: =IFERROR(Calc!$Q$11/SUM(Calc!$Q$5:$Q$254),"") -> 0
A51: =IF(Calc!$I$12="","",Calc!$I$12) -> 0 | B51: =IF(Calc!$I$12="","",Calc!$K$12) -> 0 | C51: =IF(Calc!$I$12="","",Calc!$J$12) -> 0 | D51: =IFERROR(Calc!$J$12/SUM(Calc!$J$5:$J$254),"") -> 0 | H51: =IF(Calc!$P$12="","",Calc!$P$12) -> 0 | I51: =IF(Calc!$P$12="","",Calc!$Q$12) -> 0 | J51: =IFERROR(Calc!$Q$12/SUM(Calc!$Q$5:$Q$254),"") -> 0
A52: =IF(Calc!$I$13="","",Calc!$I$13) -> 0 | B52: =IF(Calc!$I$13="","",Calc!$K$13) -> 0 | C52: =IF(Calc!$I$13="","",Calc!$J$13) -> 0 | D52: =IFERROR(Calc!$J$13/SUM(Calc!$J$5:$J$254),"") -> 0 | H52: =IF(Calc!$P$13="","",Calc!$P$13) -> 0 | I52: =IF(Calc!$P$13="","",Calc!$Q$13) -> 0 | J52: =IFERROR(Calc!$Q$13/SUM(Calc!$Q$5:$Q$254),"") -> 0
A53: =IF(Calc!$I$14="","",Calc!$I$14) -> 0 | B53: =IF(Calc!$I$14="","",Calc!$K$14) -> 0 | C53: =IF(Calc!$I$14="","",Calc!$J$14) -> 0 | D53: =IFERROR(Calc!$J$14/SUM(Calc!$J$5:$J$254),"") -> 0 | H53: =IF(Calc!$P$14="","",Calc!$P$14) -> 0 | I53: =IF(Calc!$P$14="","",Calc!$Q$14) -> 0 | J53: =IFERROR(Calc!$Q$14/SUM(Calc!$Q$5:$Q$254),"") -> 0
A54: =IF(Calc!$I$15="","",Calc!$I$15) -> 0 | B54: =IF(Calc!$I$15="","",Calc!$K$15) -> 0 | C54: =IF(Calc!$I$15="","",Calc!$J$15) -> 0 | D54: =IFERROR(Calc!$J$15/SUM(Calc!$J$5:$J$254),"") -> 0 | H54: =IF(Calc!$P$15="","",Calc!$P$15) -> 0 | I54: =IF(Calc!$P$15="","",Calc!$Q$15) -> 0 | J54: =IFERROR(Calc!$Q$15/SUM(Calc!$Q$5:$Q$254),"") -> 0
A55: =IF(Calc!$I$16="","",Calc!$I$16) -> 0 | B55: =IF(Calc!$I$16="","",Calc!$K$16) -> 0 | C55: =IF(Calc!$I$16="","",Calc!$J$16) -> 0 | D55: =IFERROR(Calc!$J$16/SUM(Calc!$J$5:$J$254),"") -> 0 | H55: =IF(Calc!$P$16="","",Calc!$P$16) -> 0 | I55: =IF(Calc!$P$16="","",Calc!$Q$16) -> 0 | J55: =IFERROR(Calc!$Q$16/SUM(Calc!$Q$5:$Q$254),"") -> 0
A56: =IF(Calc!$I$17="","",Calc!$I$17) -> 0 | B56: =IF(Calc!$I$17="","",Calc!$K$17) -> 0 | C56: =IF(Calc!$I$17="","",Calc!$J$17) -> 0 | D56: =IFERROR(Calc!$J$17/SUM(Calc!$J$5:$J$254),"") -> 0 | H56: =IF(Calc!$P$17="","",Calc!$P$17) -> 0 | I56: =IF(Calc!$P$17="","",Calc!$Q$17) -> 0 | J56: =IFERROR(Calc!$Q$17/SUM(Calc!$Q$5:$Q$254),"") -> 0
A57: =IF(Calc!$I$18="","",Calc!$I$18) -> 0 | B57: =IF(Calc!$I$18="","",Calc!$K$18) -> 0 | C57: =IF(Calc!$I$18="","",Calc!$J$18) -> 0 | D57: =IFERROR(Calc!$J$18/SUM(Calc!$J$5:$J$254),"") -> 0 | H57: =IF(Calc!$P$18="","",Calc!$P$18) -> 0 | I57: =IF(Calc!$P$18="","",Calc!$Q$18) -> 0 | J57: =IFERROR(Calc!$Q$18/SUM(Calc!$Q$5:$Q$254),"") -> 0
A58: =IF(Calc!$I$19="","",Calc!$I$19) -> 0 | B58: =IF(Calc!$I$19="","",Calc!$K$19) -> 0 | C58: =IF(Calc!$I$19="","",Calc!$J$19) -> 0 | D58: =IFERROR(Calc!$J$19/SUM(Calc!$J$5:$J$254),"") -> 0 | H58: =IF(Calc!$P$19="","",Calc!$P$19) -> 0 | I58: =IF(Calc!$P$19="","",Calc!$Q$19) -> 0 | J58: =IFERROR(Calc!$Q$19/SUM(Calc!$Q$5:$Q$254),"") -> 0
A59: =IF(Calc!$I$20="","",Calc!$I$20) -> 0 | B59: =IF(Calc!$I$20="","",Calc!$K$20) -> 0 | C59: =IF(Calc!$I$20="","",Calc!$J$20) -> 0 | D59: =IFERROR(Calc!$J$20/SUM(Calc!$J$5:$J$254),"") -> 0 | H59: =IF(Calc!$P$20="","",Calc!$P$20) -> 0 | I59: =IF(Calc!$P$20="","",Calc!$Q$20) -> 0 | J59: =IFERROR(Calc!$Q$20/SUM(Calc!$Q$5:$Q$254),"") -> 0
H60: =IF(Calc!$P$21="","",Calc!$P$21) -> 0 | I60: =IF(Calc!$P$21="","",Calc!$Q$21) -> 0 | J60: =IFERROR(Calc!$Q$21/SUM(Calc!$Q$5:$Q$254),"") -> 0
H61: =IF(Calc!$P$22="","",Calc!$P$22) -> 0 | I61: =IF(Calc!$P$22="","",Calc!$Q$22) -> 0 | J61: =IFERROR(Calc!$Q$22/SUM(Calc!$Q$5:$Q$254),"") -> 0
H62: =IF(Calc!$P$23="","",Calc!$P$23) -> 0 | I62: =IF(Calc!$P$23="","",Calc!$Q$23) -> 0 | J62: =IFERROR(Calc!$Q$23/SUM(Calc!$Q$5:$Q$254),"") -> 0
A64: Top clients & action list
A65: Top 10 clients this period | H65: What needs attention right now
A66: # | B66: Client | C66: Revenue | D66: Share | H66: Alert | I66: Count | J66: Value
A67: 1 | B67: =IFERROR(INDEX(Calc!$A$5:$A$254,MATCH(LARGE(Calc!$C$5:$C$254,1),Calc!$C$5:$C$254,0)),"") -> 0 | C67: =IFERROR(INDEX(Calc!$B$5:$B$254,MATCH(LARGE(Calc!$C$5:$C$254,1),Calc!$C$5:$C$254,0)),"") -> 0 | D67: =IFERROR(INDEX(Calc!$B$5:$B$254,MATCH(LARGE(Calc!$C$5:$C$254,1),Calc!$C$5:$C$254,0))/SUM(Calc!$B$5:$B$254),"") -> 0 | H67: Overdue invoices | I67: =COUNTIFS(Invoices!$U$5:$U$304,"Overdue")+COUNTIFS(Invoices!$U$5:$U$304,"Overdue - part paid") -> 0 | J67: =SUMIFS(Invoices!$S$5:$S$304,Invoices!$U$5:$U$304,"Overdue")+SUMIFS(Invoices!$S$5:$S$304,Invoices!$U$5:$U$304,"Overdue - part paid") -> 0
A68: 2 | B68: =IFERROR(INDEX(Calc!$A$5:$A$254,MATCH(LARGE(Calc!$C$5:$C$254,2),Calc!$C$5:$C$254,0)),"") -> 0 | C68: =IFERROR(INDEX(Calc!$B$5:$B$254,MATCH(LARGE(Calc!$C$5:$C$254,2),Calc!$C$5:$C$254,0)),"") -> 0 | D68: =IFERROR(INDEX(Calc!$B$5:$B$254,MATCH(LARGE(Calc!$C$5:$C$254,2),Calc!$C$5:$C$254,0))/SUM(Calc!$B$5:$B$254),"") -> 0 | H68: Unconfirmed bookings | I68: =COUNTIFS(Bookings!$I$5:$I$404,">="&TODAY(),Bookings!$AN$5:$AN$404,"<>Yes",Bookings!$AM$5:$AM$404,"<>Cancelled") -> 0 | J68: =SUMIFS(Bookings!$AK$5:$AK$404,Bookings!$I$5:$I$404,">="&TODAY(),Bookings!$AN$5:$AN$404,"<>Yes",Bookings!$AM$5:$AM$404,"<>Cancelled") -> 0
A69: 3 | B69: =IFERROR(INDEX(Calc!$A$5:$A$254,MATCH(LARGE(Calc!$C$5:$C$254,3),Calc!$C$5:$C$254,0)),"") -> 0 | C69: =IFERROR(INDEX(Calc!$B$5:$B$254,MATCH(LARGE(Calc!$C$5:$C$254,3),Calc!$C$5:$C$254,0)),"") -> 0 | D69: =IFERROR(INDEX(Calc!$B$5:$B$254,MATCH(LARGE(Calc!$C$5:$C$254,3),Calc!$C$5:$C$254,0))/SUM(Calc!$B$5:$B$254),"") -> 0 | H69: Booking conflicts | I69: =COUNTIF(Bookings!$AR$5:$AR$404,"Conflict*") -> 0
A70: 4 | B70: =IFERROR(INDEX(Calc!$A$5:$A$254,MATCH(LARGE(Calc!$C$5:$C$254,4),Calc!$C$5:$C$254,0)),"") -> 0 | C70: =IFERROR(INDEX(Calc!$B$5:$B$254,MATCH(LARGE(Calc!$C$5:$C$254,4),Calc!$C$5:$C$254,0)),"") -> 0 | D70: =IFERROR(INDEX(Calc!$B$5:$B$254,MATCH(LARGE(Calc!$C$5:$C$254,4),Calc!$C$5:$C$254,0))/SUM(Calc!$B$5:$B$254),"") -> 0 | H70: Visits to log | I70: =COUNTIFS(Bookings!$AM$5:$AM$404,"Completed",Bookings!$AS$5:$AS$404,"No") -> 0
A71: 5 | B71: =IFERROR(INDEX(Calc!$A$5:$A$254,MATCH(LARGE(Calc!$C$5:$C$254,5),Calc!$C$5:$C$254,0)),"") -> 0 | C71: =IFERROR(INDEX(Calc!$B$5:$B$254,MATCH(LARGE(Calc!$C$5:$C$254,5),Calc!$C$5:$C$254,0)),"") -> 0 | D71: =IFERROR(INDEX(Calc!$B$5:$B$254,MATCH(LARGE(Calc!$C$5:$C$254,5),Calc!$C$5:$C$254,0))/SUM(Calc!$B$5:$B$254),"") -> 0 | H71: Vaccinations expired or due | I71: =COUNTIF(Pets!$Y$5:$Y$254,"Expired")+COUNTIF(Pets!$Y$5:$Y$254,"Due in*") -> 0
A72: 6 | B72: =IFERROR(INDEX(Calc!$A$5:$A$254,MATCH(LARGE(Calc!$C$5:$C$254,6),Calc!$C$5:$C$254,0)),"") -> 0 | C72: =IFERROR(INDEX(Calc!$B$5:$B$254,MATCH(LARGE(Calc!$C$5:$C$254,6),Calc!$C$5:$C$254,0)),"") -> 0 | D72: =IFERROR(INDEX(Calc!$B$5:$B$254,MATCH(LARGE(Calc!$C$5:$C$254,6),Calc!$C$5:$C$254,0))/SUM(Calc!$B$5:$B$254),"") -> 0 | H72: Medication follow-ups | I72: =COUNTIF('Health Log'!$L$5:$L$204,"Missed")+COUNTIF('Health Log'!$O$5:$O$204,"Overdue*") -> 0
A73: 7 | B73: =IFERROR(INDEX(Calc!$A$5:$A$254,MATCH(LARGE(Calc!$C$5:$C$254,7),Calc!$C$5:$C$254,0)),"") -> 0 | C73: =IFERROR(INDEX(Calc!$B$5:$B$254,MATCH(LARGE(Calc!$C$5:$C$254,7),Calc!$C$5:$C$254,0)),"") -> 0 | D73: =IFERROR(INDEX(Calc!$B$5:$B$254,MATCH(LARGE(Calc!$C$5:$C$254,7),Calc!$C$5:$C$254,0))/SUM(Calc!$B$5:$B$254),"") -> 0 | H73: Open incidents | I73: =COUNTIF(Incidents!$R$18:$R$117,"Open")+COUNTIF(Incidents!$R$18:$R$117,"In progress") -> 0
A74: 8 | B74: =IFERROR(INDEX(Calc!$A$5:$A$254,MATCH(LARGE(Calc!$C$5:$C$254,8),Calc!$C$5:$C$254,0)),"") -> 0 | C74: =IFERROR(INDEX(Calc!$B$5:$B$254,MATCH(LARGE(Calc!$C$5:$C$254,8),Calc!$C$5:$C$254,0)),"") -> 0 | D74: =IFERROR(INDEX(Calc!$B$5:$B$254,MATCH(LARGE(Calc!$C$5:$C$254,8),Calc!$C$5:$C$254,0))/SUM(Calc!$B$5:$B$254),"") -> 0 | H74: Low or out of stock | I74: =COUNTIF(Inventory!$K$5:$K$124,"Low*")+COUNTIF(Inventory!$K$5:$K$124,"Out of stock") -> 0 | J74: =SUMIFS(Inventory!$J$5:$J$124,Inventory!$K$5:$K$124,"Out of stock") -> 0
A75: 9 | B75: =IFERROR(INDEX(Calc!$A$5:$A$254,MATCH(LARGE(Calc!$C$5:$C$254,9),Calc!$C$5:$C$254,0)),"") -> 0 | C75: =IFERROR(INDEX(Calc!$B$5:$B$254,MATCH(LARGE(Calc!$C$5:$C$254,9),Calc!$C$5:$C$254,0)),"") -> 0 | D75: =IFERROR(INDEX(Calc!$B$5:$B$254,MATCH(LARGE(Calc!$C$5:$C$254,9),Calc!$C$5:$C$254,0))/SUM(Calc!$B$5:$B$254),"") -> 0 | H75: Inactive clients to win back | I75: =COUNTIFS(Clients!$AL$5:$AL$254,"Inactive*") -> 0
A76: 10 | B76: =IFERROR(INDEX(Calc!$A$5:$A$254,MATCH(LARGE(Calc!$C$5:$C$254,10),Calc!$C$5:$C$254,0)),"") -> 0 | C76: =IFERROR(INDEX(Calc!$B$5:$B$254,MATCH(LARGE(Calc!$C$5:$C$254,10),Calc!$C$5:$C$254,0)),"") -> 0 | D76: =IFERROR(INDEX(Calc!$B$5:$B$254,MATCH(LARGE(Calc!$C$5:$C$254,10),Calc!$C$5:$C$254,0))/SUM(Calc!$B$5:$B$254),"") -> 0 | H76: Unresolved complaints | I76: =COUNTIFS(Messages!$K$5:$K$204,"Yes",Messages!$M$5:$M$204,"<>Resolved") -> 0
A78: Tip: the Reminders tab lists every one of these alerts row by row, and the Reports tab turns the same data into printable monthly, quarterly and year-end reports.

Sheet Settings
A1: Business Setup & Settings | G1: Novality Store | v1.0.0
A2: Fill in the cream cells once. Grey cells are locked formulas. Everything else in the workbook reads these values.
A3: > Start Here | C3: > Dashboard | E3: > Clients | G3: > Pets
A5: 1. Business details (used on invoices and printables)
B6: Business name | D6: Happy Paws Pet Care | F6: Shown on every printable form and invoice.
B7: Owner / main contact | D7: Alex Morgan
B8: Phone | D8: +1 (555) 014 2200
B9: Email | D9: hello@happypawspetcare.com
B10: Website / social | D10: www.happypawspetcare.com
B11: Street address | D11: 28 Brookfield Lane
B12: City / suburb | D12: Springfield
B13: State / region | D13: IL
B14: Post / ZIP code | D14: 62704
B15: Country | D15: United States
B16: Business / tax number | D16: TAX-884 221 905
B17: Payment details for invoices | D17: Happy Paws Pet Care - Acct 1023 4455 - Routing 021000021 | F17: Bank account, payment link or app handle.
B18: Insurance provider | D18: PetGuard Business Insurance
B19: Insurance policy number | D19: PG-7741920
B20: Insurance renewal date | D20: 46426 | E20: Feeds the renewal reminder on the Reminders tab.
B21: Licence / permit | D21: City Pet Care Operator Licence
B22: Licence renewal date | D22: 46516
A24: 2. Logo & branding
B25: To add your logo: unprotect the sheet (Review > Unprotect Sheet, password 'premium'), click Insert > Pictures, place the image in the box below, then protect the sheet again. The printable forms have their own logo placeholders.
B26: LOGO PLACEHOLDER - insert your image here
A31: 3. Currency, date & time formats
B32: Currency symbol | D32: $ | E32: Display only. To change the cell formatting use Format Cells > Currency on the money columns.
B33: Currency code | D33: USD
B34: Date format in use | D34: DD-MMM-YYYY | E34: Select a date column and use Format Cells to switch to your local style.
B35: Time format in use | D35: h:mm AM/PM | E35: 24 hour clock: format as hh:mm.
B36: Distance unit | D36: km
B37: Financial year starts | D37: 46023
A39: 4. Tax settings
B40: Tax name | D40: Sales Tax | E40: GST, VAT, Sales Tax ...
B41: Registered for tax? | D41: Yes | E41: No = tax is never added to bookings or invoices.
B42: Tax rate | D42: 0.08 | E42: Enter as a percentage, e.g. 10%.
B43: Prices already include tax? | D43: No | E43: Yes = tax is extracted from the price. No = tax is added on top.
B44: Tax reserve to set aside | D44: 0.25 | E44: Used by the Budget tab to estimate money to park for the tax bill.
A46: 5. Invoicing & payments
B47: Invoice prefix | D47: INV-
B48: First invoice number | D48: 1001
B49: Payment terms (days) | D49: 7 | E49: Invoice due date = invoice date + this many days.
B50: Standard deposit | D50: 0.25
B51: Late fee | D51: 0.05 | E51: Suggested late fee on overdue invoices.
B52: Client ID prefix | D52: CL-
B53: Pet ID prefix | D53: PET-
B54: Booking ID prefix | D54: BK-
A56: 6. Pricing, surcharges & discounts
B57: Additional pet fee (default) | D57: 7.5 | E57: Used when a service has no fee of its own.
B58: Holiday surcharge | D58: 0.25
B59: Weekend surcharge | D59: 0.1
B60: Emergency / last-minute fee | D60: 15
B61: Last-minute window (days) | D61: 2 | E61: Booked this close to the visit = emergency fee.
B62: Loyalty discount | D62: 0.05
B63: Loyalty threshold (bookings) | D63: 20 | E63: Clients above this many bookings are flagged for the loyalty discount.
B64: Average staff cost per hour | D64: 18 | E64: Used for service profitability estimates.
A66: 7. Travel & mileage
B67: Mileage rate per km | D67: 0.67 | E67: Your tax office reimbursement rate.
B68: Client travel fee per km | D68: 0.8
B69: Free travel distance (km) | D69: 8 | E69: Travel inside this radius is not charged.
B70: Travel time allowance (mins) | D70: 15 | E70: Added to each booking when planning the day.
A72: 8. Reminders, alerts & operations
B73: Booking reminder lead (days) | D73: 3
B74: Vaccination alert (days before) | D74: 30
B75: Inactive client after (days) | D75: 60
B76: Follow-up after service (days) | D76: 5
B77: Expiry / renewal alert (days) | D77: 30
B78: Default visit length (mins) | D78: 30
B79: Working day starts | D79: 0.29166667
B80: Working day ends | D80: 0.79166667
A82: 9. Public holidays & peak dates (holiday surcharge)
B83: Any booking dated on one of these days automatically picks up the holiday surcharge set above.
B84: Date | C84: Occasion | D84: Notes
B116: Backup tip: save a dated copy of this workbook at the end of every month (File > Save As > add the date to the file name). Keep client addresses and access codes private - see the Help tab for data protection guidance.

Sheet Lists
A1: Customisable Drop Down Lists | AR1: Novality Store | v1.0.0
A2: Edit, add or delete options below - every drop down in the workbook updates automatically. Keep each list in one unbroken block, starting in row 5.
A3: > Start Here | C3: > Dashboard | E3: > Clients | G3: > Pets | I3: > Bookings | K3: > Visit Log | M3: > Invoices | O3: > Reminders | Q3: > Help | S3: TIP: lists grow automatically (up to row 44). Deleting an option does not change records that already use it.
A4: Yes / No | B4: Yes / No / N/A | C4: Client status | D4: Preferred contact | E4: Referral source | F4: Contract status | G4: Key / access status | H4: Pet type | I4: Pet gender | J4: Temperament | K4: Risk flag | L4: Service category | M4: Billing unit | N4: Booking status | O4: Recurring pattern | P4: Discount type | Q4: Cancellation reason | R4: Visit status | S4: Pet mood | T4: Appetite / intake | U4: Potty / litter | V4: Health record type | W4: Medication status | X4: Incident type | Y4: Severity | Z4: Incident status | AA4: Message type | AB4: Channel | AC4: Direction | AD4: Resolution status | AE4: Invoice status | AF4: Payment method | AG4: Expense category | AH4: Approval status | AI4: Business / personal | AJ4: Recurring expense | AK4: Trip purpose | AL4: Staff role | AM4: Employment type | AN4: Pay type | AO4: Staff status | AP4: Inventory category | AQ4: Priority | AR4: Task status | AS4: Satisfaction rating | AT4: Dashboard period
A5: Yes | B5: Yes | C5: Active | D5: Phone call | E5: Google search | F5: Not sent | G5: Not held | H5: Dog | I5: Male | J5: Friendly | K5: None | L5: Dog walking | M5: Per visit | N5: Enquiry | O5: None | P5: None | Q5: Client cancelled | R5: Scheduled | S5: Happy | T5: Normal | U5: Pee only | V5: Medication | W5: Scheduled | X5: Bite / nip | Y5: Low | Z5: Open | AA5: Booking confirmation | AB5: Phone call | AC5: Outgoing | AD5: Not required | AE5: Draft | AF5: Cash | AG5: Fuel | AH5: Pending | AI5: Business | AJ5: No | AK5: Client visit | AL5: Owner | AM5: Employee - full time | AN5: Hourly | AO5: Active | AP5: Pet food | AQ5: Low | AR5: Not started | AS5: 1 | AT5: All year
A6: No | B6: No | C6: Prospective | D6: SMS | E6: Facebook | F6: Sent | G6: Key held | H6: Cat | I6: Male (neutered) | J6: Calm | K6: Bite risk | L6: Drop-in visit | M6: Per hour | N6: Pending | O6: Daily | P6: Loyalty | Q6: Client away | R6: Completed | S6: Calm | T6: Reduced | U6: Poo only | V6: Vaccination | W6: Given | X6: Escape | Y6: Medium | Z6: In progress | AA6: Booking reminder | AB6: SMS | AC6: Incoming | AD6: Open | AE6: Sent | AF6: Bank transfer | AG6: Vehicle maintenance | AH6: Approved | AI6: Personal | AJ6: Weekly | AK6: Dog walk | AL6: Dog walker | AM6: Employee - part time | AN6: Per visit | AO6: On leave | AP6: Treats | AQ6: Medium | AR6: In progress | AS6: 2 | AT6: January
B7: N/A | C7: On hold | D7: Email | E7: Instagram | F7: Signed | G7: Key returned | H7: Bird | I7: Female | J7: Playful | K7: Escape artist | L7: Pet sitting | M7: Per night | N7: Confirmed | O7: Weekdays | P7: Promotional | Q7: Pet unwell | R7: Partially completed | S7: Playful | T7: None | U7: Both | V7: Vet visit | W7: Missed | X7: Injury | Y7: High | Z7: Resolved | AA7: Visit update | AB7: Email | AD7: In progress | AE7: Paid | AF7: Card - in person | AG7: Parking & tolls | AH7: Rejected | AI7: Mixed | AJ7: Fortnightly | AK7: Supplies run | AL7: Pet sitter | AM7: Casual | AN7: Salary | AO7: Inactive | AP7: Medication | AQ7: High | AR7: Waiting | AS7: 3 | AT7: February
C8: Inactive | D8: WhatsApp | E8: Word of mouth | F8: Expired | G8: Lockbox code | H8: Rabbit | I8: Female (spayed) | J8: Energetic | K8: Door dasher | L8: Overnight stay | M8: Per walk | N8: In progress | O8: Weekly | P8: Package | Q8: Weather | R8: Missed | S8: Sleepy | T8: Increased | U8: None | V8: Health observation | W8: Refused | X8: Illness | Y8: Critical | Z8: Closed | AA8: Payment reminder | AB8: WhatsApp | AD8: Resolved | AE8: Partially paid | AF8: Card - online | AG8: Pet supplies | AH8: Reimbursed | AJ8: Monthly | AK8: Vet trip | AL8: Assistant | AM8: Contractor | AN8: Commission % | AP8: First aid | AQ8: Urgent | AR8: Done | AS8: 4 | AT8: March
C9: Lost | D9: App message | E9: Client referral | F9: Renewal due | G9: Smart lock code | H9: Guinea pig | I9: Unknown | J9: Shy | K9: Pulls on lead | L9: House sitting | M9: Per day | N9: Completed | O9: Fortnightly | P9: Multi-pet | Q9: Staff unavailable | R9: Cancelled | S9: Anxious | T9: Not offered | U9: Litter cleaned | V9: Treatment | W9: Not required | X9: Property damage | AA9: Follow-up | AB9: In person | AE9: Cancelled | AF9: Digital wallet | AG9: Pet food & treats | AJ9: Quarterly | AK9: Admin / bank | AL9: Admin | AM9: Volunteer | AP9: Cleaning | AR9: Cancelled | AS9: 5 | AT9: April
E10: Vet clinic | G10: Owner home | H10: Small animal | J10: Anxious | K10: Not dog friendly | L10: Feeding visit | M10: Flat fee | N10: Cancelled | O10: Monthly | P10: Goodwill | Q10: Double booked | S10: Lethargic | U10: Accident indoors | V10: Grooming | X10: Lost key | AA10: Thank you | AB10: App message | AE10: Refunded | AF10: Direct debit | AG10: Cleaning supplies | AJ10: Annually | AK10: Marketing | AL10: Contractor | AP10: Waste bags | AT10: May
E11: Flyer / poster | H11: Reptile | J11: Reactive | K11: Not cat friendly | L11: Puppy care | N11: No show | P11: Custom | Q11: Payment issue | S11: Unwell | V11: Other | X11: Vehicle incident | AA11: Referral thank-you | AB11: Social media | AF11: Cheque | AG11: Equipment | AK11: Training | AL11: Trainee | AP11: Leads & harnesses | AT11: June
E12: Local directory | H12: Fish | J12: Protective | K12: Resource guarding | L12: Senior pet care | Q12: Rescheduled | S12: Aggressive | X12: Aggression | AA12: Birthday / anniversary | AF12: Other | AG12: Marketing & advertising | AK12: Personal | AP12: Toys | AT12: July
E13: Repeat client | H13: Other | J13: Needs slow introduction | K13: Needs muzzle | L13: Medication visit | Q13: No reason given | X13: Theft | AA13: Complaint | AG13: Software & subscriptions | AP13: Equipment | AT13: August
E14: Other | K14: Medical risk | L14: Pet transport | Q14: Other | X14: Other | AA14: Review request | AG14: Insurance | AP14: Office | AT14: September
K15: Other | L15: Add-on | AA15: Win-back offer | AG15: Licences & permits | AP15: Other | AT15: October
AA16: Other | AG16: Staff wages | AT16: November
AG17: Contractor payments | AT17: December
AG18: Training & certification
AG19: Phone & internet
AG20: Office & admin
AG21: Vet & emergency supplies
AG22: Bank & merchant fees
AG23: Other

Sheet Services
A1: Services & Price List | R1: Novality Store | v1.0.0
A2: Add every service you sell. Bookings pull the billing unit, rate, additional pet fee and surcharges straight from this table.
A3: > Start Here | C3: > Dashboard | E3: > Clients | G3: > Pets | I3: > Bookings | K3: > Visit Log | M3: > Invoices | O3: > Reminders | Q3: > Help
A4: ID | B4: Service name | C4: Category | D4: What is included | E4: Billing unit | F4: Standard length (mins) | G4: Base rate | H4: Additional pet fee | I4: Holiday surcharge | J4: Weekend surcharge | K4: Travel fee applies? | L4: Staff cost per unit | M4: Gross profit per unit | N4: Margin % | O4: Times booked | P4: Revenue to date | Q4: Average value | R4: Estimated profit | S4: Active? | T4: Notes
A5: =IF(B5="","","SV-"&TEXT(ROW()-4,"000")) -> 0 | M5: =IF(G5="","",G5-IF(L5="",0,L5)) -> 0 | N5: =IF(OR(G5="",G5=0),"",M5/G5) -> 0 | O5: =IF(B5="","",COUNTIFS(Bookings!$H$5:$H$404,B5,Bookings!$AM$5:$AM$404,"<>Cancelled")) -> 0 | P5: =IF(B5="","",SUMIFS(Bookings!$AK$5:$AK$404,Bookings!$H$5:$H$404,B5,Bookings!$AM$5:$AM$404,"<>Cancelled")) -> 0 | Q5: =IF(OR(O5="",O5=0),"",P5/O5) -> 0 | R5: =IF(OR(O5="",M5=""),"",O5*M5) -> 0
A6: =IF(B6="","","SV-"&TEXT(ROW()-4,"000")) -> 0 | M6: =IF(G6="","",G6-IF(L6="",0,L6)) -> 0 | N6: =IF(OR(G6="",G6=0),"",M6/G6) -> 0 | O6: =IF(B6="","",COUNTIFS(Bookings!$H$5:$H$404,B6,Bookings!$AM$5:$AM$404,"<>Cancelled")) -> 0 | P6: =IF(B6="","",SUMIFS(Bookings!$AK$5:$AK$404,Bookings!$H$5:$H$404,B6,Bookings!$AM$5:$AM$404,"<>Cancelled")) -> 0 | Q6: =IF(OR(O6="",O6=0),"",P6/O6) -> 0 | R6: =IF(OR(O6="",M6=""),"",O6*M6) -> 0
A7: =IF(B7="","","SV-"&TEXT(ROW()-4,"000")) -> 0 | M7: =IF(G7="","",G7-IF(L7="",0,L7)) -> 0 | N7: =IF(OR(G7="",G7=0),"",M7/G7) -> 0 | O7: =IF(B7="","",COUNTIFS(Bookings!$H$5:$H$404,B7,Bookings!$AM$5:$AM$404,"<>Cancelled")) -> 0 | P7: =IF(B7="","",SUMIFS(Bookings!$AK$5:$AK$404,Bookings!$H$5:$H$404,B7,Bookings!$AM$5:$AM$404,"<>Cancelled")) -> 0 | Q7: =IF(OR(O7="",O7=0),"",P7/O7) -> 0 | R7: =IF(OR(O7="",M7=""),"",O7*M7) -> 0
A8: =IF(B8="","","SV-"&TEXT(ROW()-4,"000")) -> 0 | M8: =IF(G8="","",G8-IF(L8="",0,L8)) -> 0 | N8: =IF(OR(G8="",G8=0),"",M8/G8) -> 0 | O8: =IF(B8="","",COUNTIFS(Bookings!$H$5:$H$404,B8,Bookings!$AM$5:$AM$404,"<>Cancelled")) -> 0 | P8: =IF(B8="","",SUMIFS(Bookings!$AK$5:$AK$404,Bookings!$H$5:$H$404,B8,Bookings!$AM$5:$AM$404,"<>Cancelled")) -> 0 | Q8: =IF(OR(O8="",O8=0),"",P8/O8) -> 0 | R8: =IF(OR(O8="",M8=""),"",O8*M8) -> 0
A9: =IF(B9="","","SV-"&TEXT(ROW()-4,"000")) -> 0 | M9: =IF(G9="","",G9-IF(L9="",0,L9)) -> 0 | N9: =IF(OR(G9="",G9=0),"",M9/G9) -> 0 | O9: =IF(B9="","",COUNTIFS(Bookings!$H$5:$H$404,B9,Bookings!$AM$5:$AM$404,"<>Cancelled")) -> 0 | P9: =IF(B9="","",SUMIFS(Bookings!$AK$5:$AK$404,Bookings!$H$5:$H$404,B9,Bookings!$AM$5:$AM$404,"<>Cancelled")) -> 0 | Q9: =IF(OR(O9="",O9=0),"",P9/O9) -> 0 | R9: =IF(OR(O9="",M9=""),"",O9*M9) -> 0
A10: =IF(B10="","","SV-"&TEXT(ROW()-4,"000")) -> 0 | M10: =IF(G10="","",G10-IF(L10="",0,L10)) -> 0 | N10: =IF(OR(G10="",G10=0),"",M10/G10) -> 0 | O10: =IF(B10="","",COUNTIFS(Bookings!$H$5:$H$404,B10,Bookings!$AM$5:$AM$404,"<>Cancelled")) -> 0 | P10: =IF(B10="","",SUMIFS(Bookings!$AK$5:$AK$404,Bookings!$H$5:$H$404,B10,Bookings!$AM$5:$AM$404,"<>Cancelled")) -> 0 | Q10: =IF(OR(O10="",O10=0),"",P10/O10) -> 0 | R10: =IF(OR(O10="",M10=""),"",O10*M10) -> 0
A11: =IF(B11="","","SV-"&TEXT(ROW()-4,"000")) -> 0 | M11: =IF(G11="","",G11-IF(L11="",0,L11)) -> 0 | N11: =IF(OR(G11="",G11=0),"",M11/G11) -> 0 | O11: =IF(B11="","",COUNTIFS(Bookings!$H$5:$H$404,B11,Bookings!$AM$5:$AM$404,"<>Cancelled")) -> 0 | P11: =IF(B11="","",SUMIFS(Bookings!$AK$5:$AK$404,Bookings!$H$5:$H$404,B11,Bookings!$AM$5:$AM$404,"<>Cancelled")) -> 0 | Q11: =IF(OR(O11="",O11=0),"",P11/O11) -> 0 | R11: =IF(OR(O11="",M11=""),"",O11*M11) -> 0
A12: =IF(B12="","","SV-"&TEXT(ROW()-4,"000")) -> 0 | M12: =IF(G12="","",G12-IF(L12="",0,L12)) -> 0 | N12: =IF(OR(G12="",G12=0),"",M12/G12) -> 0 | O12: =IF(B12="","",COUNTIFS(Bookings!$H$5:$H$404,B12,Bookings!$AM$5:$AM$404,"<>Cancelled")) -> 0 | P12: =IF(B12="","",SUMIFS(Bookings!$AK$5:$AK$404,Bookings!$H$5:$H$404,B12,Bookings!$AM$5:$AM$404,"<>Cancelled")) -> 0 | Q12: =IF(OR(O12="",O12=0),"",P12/O12) -> 0 | R12: =IF(OR(O12="",M12=""),"",O12*M12) -> 0
A13: =IF(B13="","","SV-"&TEXT(ROW()-4,"000")) -> 0 | M13: =IF(G13="","",G13-IF(L13="",0,L13)) -> 0 | N13: =IF(OR(G13="",G13=0),"",M13/G13) -> 0 | O13: =IF(B13="","",COUNTIFS(Bookings!$H$5:$H$404,B13,Bookings!$AM$5:$AM$404,"<>Cancelled")) -> 0 | P13: =IF(B13="","",SUMIFS(Bookings!$AK$5:$AK$404,Bookings!$H$5:$H$404,B13,Bookings!$AM$5:$AM$404,"<>Cancelled")) -> 0 | Q13: =IF(OR(O13="",O13=0),"",P13/O13) -> 0 | R13: =IF(OR(O13="",M13=""),"",O13*M13) -> 0
A14: =IF(B14="","","SV-"&TEXT(ROW()-4,"000")) -> 0 | M14: =IF(G14="","",G14-IF(L14="",0,L14)) -> 0 | N14: =IF(OR(G14="",G14=0),"",M14/G14) -> 0 | O14: =IF(B14="","",COUNTIFS(Bookings!$H$5:$H$404,B14,Bookings!$AM$5:$AM$404,"<>Cancelled")) -> 0 | P14: =IF(B14="","",SUMIFS(Bookings!$AK$5:$AK$404,Bookings!$H$5:$H$404,B14,Bookings!$AM$5:$AM$404,"<>Cancelled")) -> 0 | Q14: =IF(OR(O14="",O14=0),"",P14/O14) -> 0 | R14: =IF(OR(O14="",M14=""),"",O14*M14) -> 0
A15: =IF(B15="","","SV-"&TEXT(ROW()-4,"000")) -> 0 | M15: =IF(G15="","",G15-IF(L15="",0,L15)) -> 0 | N15: =IF(OR(G15="",G15=0),"",M15/G15) -> 0 | O15: =IF(B15="","",COUNTIFS(Bookings!$H$5:$H$404,B15,Bookings!$AM$5:$AM$404,"<>Cancelled")) -> 0 | P15: =IF(B15="","",SUMIFS(Bookings!$AK$5:$AK$404,Bookings!$H$5:$H$404,B15,Bookings!$AM$5:$AM$404,"<>Cancelled")) -> 0 | Q15: =IF(OR(O15="",O15=0),"",P15/O15) -> 0 | R15: =IF(OR(O15="",M15=""),"",O15*M15) -> 0
A16: =IF(B16="","","SV-"&TEXT(ROW()-4,"000")) -> 0 | M16: =IF(G16="","",G16-IF(L16="",0,L16)) -> 0 | N16: =IF(OR(G16="",G16=0),"",M16/G16) -> 0 | O16: =IF(B16="","",COUNTIFS(Bookings!$H$5:$H$404,B16,Bookings!$AM$5:$AM$404,"<>Cancelled")) -> 0 | P16: =IF(B16="","",SUMIFS(Bookings!$AK$5:$AK$404,Bookings!$H$5:$H$404,B16,Bookings!$AM$5:$AM$404,"<>Cancelled")) -> 0 | Q16: =IF(OR(O16="",O16=0),"",P16/O16) -> 0 | R16: =IF(OR(O16="",M16=""),"",O16*M16) -> 0
... A54: =IF(B54="","","SV-"&TEXT(ROW()-4,"000")) -> 0 | M54: =IF(G54="","",G54-IF(L54="",0,L54)) -> 0 | N54: =IF(OR(G54="",G54=0),"",M54/G54) -> 0 | O54: =IF(B54="","",COUNTIFS(Bookings!$H$5:$H$404,B54,Bookings!$AM$5:$AM$404,"<>Cancelled")) -> 0 | P54: =IF(B54="","",SUMIFS(Bookings!$AK$5:$AK$404,Bookings!$H$5:$H$404,B54,Bookings!$AM$5:$AM$404,"<>Cancelled")) -> 0 | Q54: =IF(OR(O54="",O54=0),"",P54/O54) -> 0 | R54: =IF(OR(O54="",M54=""),"",O54*M54) -> 0

Sheet Clients
A1: Client Database | AJ1: Novality Store | v1.0.0
A2: One row per client. Grey columns calculate pets, visits, lifetime revenue, outstanding balances and follow-up actions for you.
A3: > Start Here | C3: > Dashboard | E3: > Clients | G3: > Pets | I3: > Bookings | K3: > Visit Log | M3: > Invoices | O3: > Reminders | Q3: > Help | S3: Type the client name first - the Client ID appears automatically. Use the filter arrows in the header row to search; avoid re-sorting rows so IDs stay stable.
A4: ID | B4: Client name | C4: Phone | D4: Email | E4: Street address | F4: City / suburb | G4: Post code | H4: Emergency contact | I4: Emergency phone | J4: Preferred contact | K4: Referral source | L4: Registered on | M4: Status | N4: Key / access | O4: Key tag / ref | P4: Key returned on | Q4: Home access instructions | R4: Alarm / gate code | S4: Contract status | T4: Agreement signed | U4: Emergency vet consent | V4: Vet spend authority | W4: Preferences & special instructions | X4: Notes & communication history | Y4: Pets | Z4: Bookings | AA4: Visits done | AB4: Last service | AC4: Days since | AD4: Next booking | AE4: Lifetime revenue | AF4: Invoiced to date | AG4: Outstanding | AH4: Average booking | AI4: Loyalty status | AJ4: Duplicate check | AK4: Missing information | AL4: Action needed
A5: =IF(B5="","",ClientPrefix&TEXT(ROW()-4,"0000")) -> 0 | Y5: =IF(B5="","",COUNTIF(Pets!$C$5:$C$254,B5)) -> 0 | Z5: =IF(B5="","",COUNTIFS(Bookings!$C$5:$C$404,B5)) -> 0 | AA5: =IF(B5="","",COUNTIFS('Visit Log'!$D$5:$D$404,B5,'Visit Log'!$AE$5:$AE$404,"Completed")) -> 0 | AB5: =IF(B5="","",IF(SUMPRODUCT(MAX((Bookings!$C$5:$C$404=B5)*(Bookings!$AM$5:$AM$404="Completed")*Bookings!$I$5:$I$404))=0,"",SUMPRODUCT(MAX((Bookings!$C$5:$C$404=B5)*(Bookings!$AM$5:$AM$404="Completed")*Bookings!$I$5:$I$404)))) -> 0 | AC5: =IF(AB5="","",TODAY()-AB5) -> 0 | AD5: =IF(B5="","",IF(COUNTIFS(Bookings!$C$5:$C$404,B5,Bookings!$I$5:$I$404,">="&TODAY(),Bookings!$AM$5:$AM$404,"<>Cancelled")=0,"",SUMPRODUCT(MIN(((Bookings!$C$5:$C$404=B5)*(Bookings!$I$5:$I$404>=TODAY())*(Bookings!$AM$5:$AM$404<>"Cancelled"))*Bookings!$I$5:$I$404+(1-((Bookings!$C$5:$C$404=B5)*(Bookings!$I$5:$I$404>=TODAY())*(Bookings!$AM$5:$AM$404<>"Cancelled")))*2958465)))) -> 0 | AE5: =IF(B5="","",SUMIFS(Payments!$L$5:$L$304,Payments!$C$5:$C$304,B5)) -> 0 | AF5: =IF(B5="","",SUMIFS(Invoices!$O$5:$O$304,Invoices!$D$5:$D$304,B5,Invoices!$T$5:$T$304,"<>Draft")) -> 0 | AG5: =IF(B5="","",SUMIFS(Invoices!$S$5:$S$304,Invoices!$D$5:$D$304,B5,Invoices!$T$5:$T$304,"<>Cancelled")) -> 0 | AH5: =IF(OR(Z5="",Z5=0),"",SUMIFS(Bookings!$AK$5:$AK$404,Bookings!$C$5:$C$404,B5,Bookings!$AM$5:$AM$404,"<>Cancelled")/Z5) -> 0 | AI5: =IF(B5="","",IF(Z5>=LoyaltyThreshold,"Loyalty discount","Standard")) -> 0 | AJ5: =IF(B5="","",IF(COUNTIF(Clients!$B$5:$B$254,B5)>1,"Duplicate name",IF(AND(C5<>"",COUNTIF(Clients!$C$5:$C$254,C5)>1),"Duplicate phone","OK"))) -> 0 | AK5: =IF(B5="","",IF(AND(C5<>"",D5<>"",L5<>"",M5<>""),"OK","Add: "&IF(C5="","phone ","")&IF(D5="","email ","")&IF(L5="","date ","")&IF(M5="","status",""))) -> 0 | AL5: =IF(B5="","",IF(AG5>0.5,"Overdue - chase payment",IF(AND(M5="Active",ISNUMBER(AC5),AC5>InactiveDays),"Inactive - win back",IF(AND(M5="Active",S5<>"Signed"),"Action - contract not signed",IF(AND(M5="Prospective",AD5=""),"Action - follow up quote","OK"))))) -> 0
A6: =IF(B6="","",ClientPrefix&TEXT(ROW()-4,"0000")) -> 0 | Y6: =IF(B6="","",COUNTIF(Pets!$C$5:$C$254,B6)) -> 0 | Z6: =IF(B6="","",COUNTIFS(Bookings!$C$5:$C$404,B6)) -> 0 | AA6: =IF(B6="","",COUNTIFS('Visit Log'!$D$5:$D$404,B6,'Visit Log'!$AE$5:$AE$404,"Completed")) -> 0 | AB6: =IF(B6="","",IF(SUMPRODUCT(MAX((Bookings!$C$5:$C$404=B6)*(Bookings!$AM$5:$AM$404="Completed")*Bookings!$I$5:$I$404))=0,"",SUMPRODUCT(MAX((Bookings!$C$5:$C$404=B6)*(Bookings!$AM$5:$AM$404="Completed")*Bookings!$I$5:$I$404)))) -> 0 | AC6: =IF(AB6="","",TODAY()-AB6) -> 0 | AD6: =IF(B6="","",IF(COUNTIFS(Bookings!$C$5:$C$404,B6,Bookings!$I$5:$I$404,">="&TODAY(),Bookings!$AM$5:$AM$404,"<>Cancelled")=0,"",SUMPRODUCT(MIN(((Bookings!$C$5:$C$404=B6)*(Bookings!$I$5:$I$404>=TODAY())*(Bookings!$AM$5:$AM$404<>"Cancelled"))*Bookings!$I$5:$I$404+(1-((Bookings!$C$5:$C$404=B6)*(Bookings!$I$5:$I$404>=TODAY())*(Bookings!$AM$5:$AM$404<>"Cancelled")))*2958465)))) -> 0 | AE6: =IF(B6="","",SUMIFS(Payments!$L$5:$L$304,Payments!$C$5:$C$304,B6)) -> 0 | AF6: =IF(B6="","",SUMIFS(Invoices!$O$5:$O$304,Invoices!$D$5:$D$304,B6,Invoices!$T$5:$T$304,"<>Draft")) -> 0 | AG6: =IF(B6="","",SUMIFS(Invoices!$S$5:$S$304,Invoices!$D$5:$D$304,B6,Invoices!$T$5:$T$304,"<>Cancelled")) -> 0 | AH6: =IF(OR(Z6="",Z6=0),"",SUMIFS(Bookings!$AK$5:$AK$404,Bookings!$C$5:$C$404,B6,Bookings!$AM$5:$AM$404,"<>Cancelled")/Z6) -> 0 | AI6: =IF(B6="","",IF(Z6>=LoyaltyThreshold,"Loyalty discount","Standard")) -> 0 | AJ6: =IF(B6="","",IF(COUNTIF(Clients!$B$5:$B$254,B6)>1,"Duplicate name",IF(AND(C6<>"",COUNTIF(Clients!$C$5:$C$254,C6)>1),"Duplicate phone","OK"))) -> 0 | AK6: =IF(B6="","",IF(AND(C6<>"",D6<>"",L6<>"",M6<>""),"OK","Add: "&IF(C6="","phone ","")&IF(D6="","email ","")&IF(L6="","date ","")&IF(M6="","status",""))) -> 0 | AL6: =IF(B6="","",IF(AG6>0.5,"Overdue - chase payment",IF(AND(M6="Active",ISNUMBER(AC6),AC6>InactiveDays),"Inactive - win back",IF(AND(M6="Active",S6<>"Signed"),"Action - contract not signed",IF(AND(M6="Prospective",AD6=""),"Action - follow up quote","OK"))))) -> 0
A7: =IF(B7="","",ClientPrefix&TEXT(ROW()-4,"0000")) -> 0 | Y7: =IF(B7="","",COUNTIF(Pets!$C$5:$C$254,B7)) -> 0 | Z7: =IF(B7="","",COUNTIFS(Bookings!$C$5:$C$404,B7)) -> 0 | AA7: =IF(B7="","",COUNTIFS('Visit Log'!$D$5:$D$404,B7,'Visit Log'!$AE$5:$AE$404,"Completed")) -> 0 | AB7: =IF(B7="","",IF(SUMPRODUCT(MAX((Bookings!$C$5:$C$404=B7)*(Bookings!$AM$5:$AM$404="Completed")*Bookings!$I$5:$I$404))=0,"",SUMPRODUCT(MAX((Bookings!$C$5:$C$404=B7)*(Bookings!$AM$5:$AM$404="Completed")*Bookings!$I$5:$I$404)))) -> 0 | AC7: =IF(AB7="","",TODAY()-AB7) -> 0 | AD7: =IF(B7="","",IF(COUNTIFS(Bookings!$C$5:$C$404,B7,Bookings!$I$5:$I$404,">="&TODAY(),Bookings!$AM$5:$AM$404,"<>Cancelled")=0,"",SUMPRODUCT(MIN(((Bookings!$C$5:$C$404=B7)*(Bookings!$I$5:$I$404>=TODAY())*(Bookings!$AM$5:$AM$404<>"Cancelled"))*Bookings!$I$5:$I$404+(1-((Bookings!$C$5:$C$404=B7)*(Bookings!$I$5:$I$404>=TODAY())*(Bookings!$AM$5:$AM$404<>"Cancelled")))*2958465)))) -> 0 | AE7: =IF(B7="","",SUMIFS(Payments!$L$5:$L$304,Payments!$C$5:$C$304,B7)) -> 0 | AF7: =IF(B7="","",SUMIFS(Invoices!$O$5:$O$304,Invoices!$D$5:$D$304,B7,Invoices!$T$5:$T$304,"<>Draft")) -> 0 | AG7: =IF(B7="","",SUMIFS(Invoices!$S$5:$S$304,Invoices!$D$5:$D$304,B7,Invoices!$T$5:$T$304,"<>Cancelled")) -> 0 | AH7: =IF(OR(Z7="",Z7=0),"",SUMIFS(Bookings!$AK$5:$AK$404,Bookings!$C$5:$C$404,B7,Bookings!$AM$5:$AM$404,"<>Cancelled")/Z7) -> 0 | AI7: =IF(B7="","",IF(Z7>=LoyaltyThreshold,"Loyalty discount","Standard")) -> 0 | AJ7: =IF(B7="","",IF(COUNTIF(Clients!$B$5:$B$254,B7)>1,"Duplicate name",IF(AND(C7<>"",COUNTIF(Clients!$C$5:$C$254,C7)>1),"Duplicate phone","OK"))) -> 0 | AK7: =IF(B7="","",IF(AND(C7<>"",D7<>"",L7<>"",M7<>""),"OK","Add: "&IF(C7="","phone ","")&IF(D7="","email ","")&IF(L7="","date ","")&IF(M7="","status",""))) -> 0 | AL7: =IF(B7="","",IF(AG7>0.5,"Overdue - chase payment",IF(AND(M7="Active",ISNUMBER(AC7),AC7>InactiveDays),"Inactive - win back",IF(AND(M7="Active",S7<>"Signed"),"Action - contract not signed",IF(AND(M7="Prospective",AD7=""),"Action - follow up quote","OK"))))) -> 0
A8: =IF(B8="","",ClientPrefix&TEXT(ROW()-4,"0000")) -> 0 | Y8: =IF(B8="","",COUNTIF(Pets!$C$5:$C$254,B8)) -> 0 | Z8: =IF(B8="","",COUNTIFS(Bookings!$C$5:$C$404,B8)) -> 0 | AA8: =IF(B8="","",COUNTIFS('Visit Log'!$D$5:$D$404,B8,'Visit Log'!$AE$5:$AE$404,"Completed")) -> 0 | AB8: =IF(B8="","",IF(SUMPRODUCT(MAX((Bookings!$C$5:$C$404=B8)*(Bookings!$AM$5:$AM$404="Completed")*Bookings!$I$5:$I$404))=0,"",SUMPRODUCT(MAX((Bookings!$C$5:$C$404=B8)*(Bookings!$AM$5:$AM$404="Completed")*Bookings!$I$5:$I$404)))) -> 0 | AC8: =IF(AB8="","",TODAY()-AB8) -> 0 | AD8: =IF(B8="","",IF(COUNTIFS(Bookings!$C$5:$C$404,B8,Bookings!$I$5:$I$404,">="&TODAY(),Bookings!$AM$5:$AM$404,"<>Cancelled")=0,"",SUMPRODUCT(MIN(((Bookings!$C$5:$C$404=B8)*(Bookings!$I$5:$I$404>=TODAY())*(Bookings!$AM$5:$AM$404<>"Cancelled"))*Bookings!$I$5:$I$404+(1-((Bookings!$C$5:$C$404=B8)*(Bookings!$I$5:$I$404>=TODAY())*(Bookings!$AM$5:$AM$404<>"Cancelled")))*2958465)))) -> 0 | AE8: =IF(B8="","",SUMIFS(Payments!$L$5:$L$304,Payments!$C$5:$C$304,B8)) -> 0 | AF8: =IF(B8="","",SUMIFS(Invoices!$O$5:$O$304,Invoices!$D$5:$D$304,B8,Invoices!$T$5:$T$304,"<>Draft")) -> 0 | AG8: =IF(B8="","",SUMIFS(Invoices!$S$5:$S$304,Invoices!$D$5:$D$304,B8,Invoices!$T$5:$T$304,"<>Cancelled")) -> 0 | AH8: =IF(OR(Z8="",Z8=0),"",SUMIFS(Bookings!$AK$5:$AK$404,Bookings!$C$5:$C$404,B8,Bookings!$AM$5:$AM$404,"<>Cancelled")/Z8) -> 0 | AI8: =IF(B8="","",IF(Z8>=LoyaltyThreshold,"Loyalty discount","Standard")) -> 0 | AJ8: =IF(B8="","",IF(COUNTIF(Clients!$B$5:$B$254,B8)>1,"Duplicate name",IF(AND(C8<>"",COUNTIF(Clients!$C$5:$C$254,C8)>1),"Duplicate phone","OK"))) -> 0 | AK8: =IF(B8="","",IF(AND(C8<>"",D8<>"",L8<>"",M8<>""),"OK","Add: "&IF(C8="","phone ","")&IF(D8="","email ","")&IF(L8="","date ","")&IF(M8="","status",""))) -> 0 | AL8: =IF(B8="","",IF(AG8>0.5,"Overdue - chase payment",IF(AND(M8="Active",ISNUMBER(AC8),AC8>InactiveDays),"Inactive - win back",IF(AND(M8="Active",S8<>"Signed"),"Action - contract not signed",IF(AND(M8="Prospective",AD8=""),"Action - follow up quote","OK"))))) -> 0
A9: =IF(B9="","",ClientPrefix&TEXT(ROW()-4,"0000")) -> 0 | Y9: =IF(B9="","",COUNTIF(Pets!$C$5:$C$254,B9)) -> 0 | Z9: =IF(B9="","",COUNTIFS(Bookings!$C$5:$C$404,B9)) -> 0 | AA9: =IF(B9="","",COUNTIFS('Visit Log'!$D$5:$D$404,B9,'Visit Log'!$AE$5:$AE$404,"Completed")) -> 0 | AB9: =IF(B9="","",IF(SUMPRODUCT(MAX((Bookings!$C$5:$C$404=B9)*(Bookings!$AM$5:$AM$404="Completed")*Bookings!$I$5:$I$404))=0,"",SUMPRODUCT(MAX((Bookings!$C$5:$C$404=B9)*(Bookings!$AM$5:$AM$404="Completed")*Bookings!$I$5:$I$404)))) -> 0 | AC9: =IF(AB9="","",TODAY()-AB9) -> 0 | AD9: =IF(B9="","",IF(COUNTIFS(Bookings!$C$5:$C$404,B9,Bookings!$I$5:$I$404,">="&TODAY(),Bookings!$AM$5:$AM$404,"<>Cancelled")=0,"",SUMPRODUCT(MIN(((Bookings!$C$5:$C$404=B9)*(Bookings!$I$5:$I$404>=TODAY())*(Bookings!$AM$5:$AM$404<>"Cancelled"))*Bookings!$I$5:$I$404+(1-((Bookings!$C$5:$C$404=B9)*(Bookings!$I$5:$I$404>=TODAY())*(Bookings!$AM$5:$AM$404<>"Cancelled")))*2958465)))) -> 0 | AE9: =IF(B9="","",SUMIFS(Payments!$L$5:$L$304,Payments!$C$5:$C$304,B9)) -> 0 | AF9: =IF(B9="","",SUMIFS(Invoices!$O$5:$O$304,Invoices!$D$5:$D$304,B9,Invoices!$T$5:$T$304,"<>Draft")) -> 0 | AG9: =IF(B9="","",SUMIFS(Invoices!$S$5:$S$304,Invoices!$D$5:$D$304,B9,Invoices!$T$5:$T$304,"<>Cancelled")) -> 0 | AH9: =IF(OR(Z9="",Z9=0),"",SUMIFS(Bookings!$AK$5:$AK$404,Bookings!$C$5:$C$404,B9,Bookings!$AM$5:$AM$404,"<>Cancelled")/Z9) -> 0 | AI9: =IF(B9="","",IF(Z9>=LoyaltyThreshold,"Loyalty discount","Standard")) -> 0 | AJ9: =IF(B9="","",IF(COUNTIF(Clients!$B$5:$B$254,B9)>1,"Duplicate name",IF(AND(C9<>"",COUNTIF(Clients!$C$5:$C$254,C9)>1),"Duplicate phone","OK"))) -> 0 | AK9: =IF(B9="","",IF(AND(C9<>"",D9<>"",L9<>"",M9<>""),"OK","Add: "&IF(C9="","phone ","")&IF(D9="","email ","")&IF(L9="","date ","")&IF(M9="","status",""))) -> 0 | AL9: =IF(B9="","",IF(AG9>0.5,"Overdue - chase payment",IF(AND(M9="Active",ISNUMBER(AC9),AC9>InactiveDays),"Inactive - win back",IF(AND(M9="Active",S9<>"Signed"),"Action - contract not signed",IF(AND(M9="Prospective",AD9=""),"Action - follow up quote","OK"))))) -> 0
A10: =IF(B10="","",ClientPrefix&TEXT(ROW()-4,"0000")) -> 0 | Y10: =IF(B10="","",COUNTIF(Pets!$C$5:$C$254,B10)) -> 0 | Z10: =IF(B10="","",COUNTIFS(Bookings!$C$5:$C$404,B10)) -> 0 | AA10: =IF(B10="","",COUNTIFS('Visit Log'!$D$5:$D$404,B10,'Visit Log'!$AE$5:$AE$404,"Completed")) -> 0 | AB10: =IF(B10="","",IF(SUMPRODUCT(MAX((Bookings!$C$5:$C$404=B10)*(Bookings!$AM$5:$AM$404="Completed")*Bookings!$I$5:$I$404))=0,"",SUMPRODUCT(MAX((Bookings!$C$5:$C$404=B10)*(Bookings!$AM$5:$AM$404="Completed")*Bookings!$I$5:$I$404)))) -> 0 | AC10: =IF(AB10="","",TODAY()-AB10) -> 0 | AD10: =IF(B10="","",IF(COUNTIFS(Bookings!$C$5:$C$404,B10,Bookings!$I$5:$I$404,">="&TODAY(),Bookings!$AM$5:$AM$404,"<>Cancelled")=0,"",SUMPRODUCT(MIN(((Bookings!$C$5:$C$404=B10)*(Bookings!$I$5:$I$404>=TODAY())*(Bookings!$AM$5:$AM$404<>"Cancelled"))*Bookings!$I$5:$I$404+(1-((Bookings!$C$5:$C$404=B10)*(Bookings!$I$5:$I$404>=TODAY())*(Bookings!$AM$5:$AM$404<>"Cancelled")))*2958465)))) -> 0 | AE10: =IF(B10="","",SUMIFS(Payments!$L$5:$L$304,Payments!$C$5:$C$304,B10)) -> 0 | AF10: =IF(B10="","",SUMIFS(Invoices!$O$5:$O$304,Invoices!$D$5:$D$304,B10,Invoices!$T$5:$T$304,"<>Draft")) -> 0 | AG10: =IF(B10="","",SUMIFS(Invoices!$S$5:$S$304,Invoices!$D$5:$D$304,B10,Invoices!$T$5:$T$304,"<>Cancelled")) -> 0 | AH10: =IF(OR(Z10="",Z10=0),"",SUMIFS(Bookings!$AK$5:$AK$404,Bookings!$C$5:$C$404,B10,Bookings!$AM$5:$AM$404,"<>Cancelled")/Z10) -> 0 | AI10: =IF(B10="","",IF(Z10>=LoyaltyThreshold,"Loyalty discount","Standard")) -> 0 | AJ10: =IF(B10="","",IF(COUNTIF(Clients!$B$5:$B$254,B10)>1,"Duplicate name",IF(AND(C10<>"",COUNTIF(Clients!$C$5:$C$254,C10)>1),"Duplicate phone","OK"))) -> 0 | AK10: =IF(B10="","",IF(AND(C10<>"",D10<>"",L10<>"",M10<>""),"OK","Add: "&IF(C10="","phone ","")&IF(D10="","email ","")&IF(L10="","date ","")&IF(M10="","status",""))) -> 0 | AL10: =IF(B10="","",IF(AG10>0.5,"Overdue - chase payment",IF(AND(M10="Active",ISNUMBER(AC10),AC10>InactiveDays),"Inactive - win back",IF(AND(M10="Active",S10<>"Signed"),"Action - contract not signed",IF(AND(M10="Prospective",AD10=""),"Action - follow up quote","OK"))))) -> 0
A11: =IF(B11="","",ClientPrefix&TEXT(ROW()-4,"0000")) -> 0 | Y11: =IF(B11="","",COUNTIF(Pets!$C$5:$C$254,B11)) -> 0 | Z11: =IF(B11="","",COUNTIFS(Bookings!$C$5:$C$404,B11)) -> 0 | AA11: =IF(B11="","",COUNTIFS('Visit Log'!$D$5:$D$404,B11,'Visit Log'!$AE$5:$AE$404,"Completed")) -> 0 | AB11: =IF(B11="","",IF(SUMPRODUCT(MAX((Bookings!$C$5:$C$404=B11)*(Bookings!$AM$5:$AM$404="Completed")*Bookings!$I$5:$I$404))=0,"",SUMPRODUCT(MAX((Bookings!$C$5:$C$404=B11)*(Bookings!$AM$5:$AM$404="Completed")*Bookings!$I$5:$I$404)))) -> 0 | AC11: =IF(AB11="","",TODAY()-AB11) -> 0 | AD11: =IF(B11="","",IF(COUNTIFS(Bookings!$C$5:$C$404,B11,Bookings!$I$5:$I$404,">="&TODAY(),Bookings!$AM$5:$AM$404,"<>Cancelled")=0,"",SUMPRODUCT(MIN(((Bookings!$C$5:$C$404=B11)*(Bookings!$I$5:$I$404>=TODAY())*(Bookings!$AM$5:$AM$404<>"Cancelled"))*Bookings!$I$5:$I$404+(1-((Bookings!$C$5:$C$404=B11)*(Bookings!$I$5:$I$404>=TODAY())*(Bookings!$AM$5:$AM$404<>"Cancelled")))*2958465)))) -> 0 | AE11: =IF(B11="","",SUMIFS(Payments!$L$5:$L$304,Payments!$C$5:$C$304,B11)) -> 0 | AF11: =IF(B11="","",SUMIFS(Invoices!$O$5:$O$304,Invoices!$D$5:$D$304,B11,Invoices!$T$5:$T$304,"<>Draft")) -> 0 | AG11: =IF(B11="","",SUMIFS(Invoices!$S$5:$S$304,Invoices!$D$5:$D$304,B11,Invoices!$T$5:$T$304,"<>Cancelled")) -> 0 | AH11: =IF(OR(Z11="",Z11=0),"",SUMIFS(Bookings!$AK$5:$AK$404,Bookings!$C$5:$C$404,B11,Bookings!$AM$5:$AM$404,"<>Cancelled")/Z11) -> 0 | AI11: =IF(B11="","",IF(Z11>=LoyaltyThreshold,"Loyalty discount","Standard")) -> 0 | AJ11: =IF(B11="","",IF(COUNTIF(Clients!$B$5:$B$254,B11)>1,"Duplicate name",IF(AND(C11<>"",COUNTIF(Clients!$C$5:$C$254,C11)>1),"Duplicate phone","OK"))) -> 0 | AK11: =IF(B11="","",IF(AND(C11<>"",D11<>"",L11<>"",M11<>""),"OK","Add: "&IF(C11="","phone ","")&IF(D11="","email ","")&IF(L11="","date ","")&IF(M11="","status",""))) -> 0 | AL11: =IF(B11="","",IF(AG11>0.5,"Overdue - chase payment",IF(AND(M11="Active",ISNUMBER(AC11),AC11>InactiveDays),"Inactive - win back",IF(AND(M11="Active",S11<>"Signed"),"Action - contract not signed",IF(AND(M11="Prospective",AD11=""),"Action - follow up quote","OK"))))) -> 0
A12: =IF(B12="","",ClientPrefix&TEXT(ROW()-4,"0000")) -> 0 | Y12: =IF(B12="","",COUNTIF(Pets!$C$5:$C$254,B12)) -> 0 | Z12: =IF(B12="","",COUNTIFS(Bookings!$C$5:$C$404,B12)) -> 0 | AA12: =IF(B12="","",COUNTIFS('Visit Log'!$D$5:$D$404,B12,'Visit Log'!$AE$5:$AE$404,"Completed")) -> 0 | AB12: =IF(B12="","",IF(SUMPRODUCT(MAX((Bookings!$C$5:$C$404=B12)*(Bookings!$AM$5:$AM$404="Completed")*Bookings!$I$5:$I$404))=0,"",SUMPRODUCT(MAX((Bookings!$C$5:$C$404=B12)*(Bookings!$AM$5:$AM$404="Completed")*Bookings!$I$5:$I$404)))) -> 0 | AC12: =IF(AB12="","",TODAY()-AB12) -> 0 | AD12: =IF(B12="","",IF(COUNTIFS(Bookings!$C$5:$C$404,B12,Bookings!$I$5:$I$404,">="&TODAY(),Bookings!$AM$5:$AM$404,"<>Cancelled")=0,"",SUMPRODUCT(MIN(((Bookings!$C$5:$C$404=B12)*(Bookings!$I$5:$I$404>=TODAY())*(Bookings!$AM$5:$AM$404<>"Cancelled"))*Bookings!$I$5:$I$404+(1-((Bookings!$C$5:$C$404=B12)*(Bookings!$I$5:$I$404>=TODAY())*(Bookings!$AM$5:$AM$404<>"Cancelled")))*2958465)))) -> 0 | AE12: =IF(B12="","",SUMIFS(Payments!$L$5:$L$304,Payments!$C$5:$C$304,B12)) -> 0 | AF12: =IF(B12="","",SUMIFS(Invoices!$O$5:$O$304,Invoices!$D$5:$D$304,B12,Invoices!$T$5:$T$304,"<>Draft")) -> 0 | AG12: =IF(B12="","",SUMIFS(Invoices!$S$5:$S$304,Invoices!$D$5:$D$304,B12,Invoices!$T$5:$T$304,"<>Cancelled")) -> 0 | AH12: =IF(OR(Z12="",Z12=0),"",SUMIFS(Bookings!$AK$5:$AK$404,Bookings!$C$5:$C$404,B12,Bookings!$AM$5:$AM$404,"<>Cancelled")/Z12) -> 0 | AI12: =IF(B12="","",IF(Z12>=LoyaltyThreshold,"Loyalty discount","Standard")) -> 0 | AJ12: =IF(B12="","",IF(COUNTIF(Clients!$B$5:$B$254,B12)>1,"Duplicate name",IF(AND(C12<>"",COUNTIF(Clients!$C$5:$C$254,C12)>1),"Duplicate phone","OK"))) -> 0 | AK12: =IF(B12="","",IF(AND(C12<>"",D12<>"",L12<>"",M12<>""),"OK","Add: "&IF(C12="","phone ","")&IF(D12="","email ","")&IF(L12="","date ","")&IF(M12="","status",""))) -> 0 | AL12: =IF(B12="","",IF(AG12>0.5,"Overdue - chase payment",IF(AND(M12="Active",ISNUMBER(AC12),AC12>InactiveDays),"Inactive - win back",IF(AND(M12="Active",S12<>"Signed"),"Action - contract not signed",IF(AND(M12="Prospective",AD12=""),"Action - follow up quote","OK"))))) -> 0
A13: =IF(B13="","",ClientPrefix&TEXT(ROW()-4,"0000")) -> 0 | Y13: =IF(B13="","",COUNTIF(Pets!$C$5:$C$254,B13)) -> 0 | Z13: =IF(B13="","",COUNTIFS(Bookings!$C$5:$C$404,B13)) -> 0 | AA13: =IF(B13="","",COUNTIFS('Visit Log'!$D$5:$D$404,B13,'Visit Log'!$AE$5:$AE$404,"Completed")) -> 0 | AB13: =IF(B13="","",IF(SUMPRODUCT(MAX((Bookings!$C$5:$C$404=B13)*(Bookings!$AM$5:$AM$404="Completed")*Bookings!$I$5:$I$404))=0,"",SUMPRODUCT(MAX((Bookings!$C$5:$C$404=B13)*(Bookings!$AM$5:$AM$404="Completed")*Bookings!$I$5:$I$404)))) -> 0 | AC13: =IF(AB13="","",TODAY()-AB13) -> 0 | AD13: =IF(B13="","",IF(COUNTIFS(Bookings!$C$5:$C$404,B13,Bookings!$I$5:$I$404,">="&TODAY(),Bookings!$AM$5:$AM$404,"<>Cancelled")=0,"",SUMPRODUCT(MIN(((Bookings!$C$5:$C$404=B13)*(Bookings!$I$5:$I$404>=TODAY())*(Bookings!$AM$5:$AM$404<>"Cancelled"))*Bookings!$I$5:$I$404+(1-((Bookings!$C$5:$C$404=B13)*(Bookings!$I$5:$I$404>=TODAY())*(Bookings!$AM$5:$AM$404<>"Cancelled")))*2958465)))) -> 0 | AE13: =IF(B13="","",SUMIFS(Payments!$L$5:$L$304,Payments!$C$5:$C$304,B13)) -> 0 | AF13: =IF(B13="","",SUMIFS(Invoices!$O$5:$O$304,Invoices!$D$5:$D$304,B13,Invoices!$T$5:$T$304,"<>Draft")) -> 0 | AG13: =IF(B13="","",SUMIFS(Invoices!$S$5:$S$304,Invoices!$D$5:$D$304,B13,Invoices!$T$5:$T$304,"<>Cancelled")) -> 0 | AH13: =IF(OR(Z13="",Z13=0),"",SUMIFS(Bookings!$AK$5:$AK$404,Bookings!$C$5:$C$404,B13,Bookings!$AM$5:$AM$404,"<>Cancelled")/Z13) -> 0 | AI13: =IF(B13="","",IF(Z13>=LoyaltyThreshold,"Loyalty discount","Standard")) -> 0 | AJ13: =IF(B13="","",IF(COUNTIF(Clients!$B$5:$B$254,B13)>1,"Duplicate name",IF(AND(C13<>"",COUNTIF(Clients!$C$5:$C$254,C13)>1),"Duplicate phone","OK"))) -> 0 | AK13: =IF(B13="","",IF(AND(C13<>"",D13<>"",L13<>"",M13<>""),"OK","Add: "&IF(C13="","phone ","")&IF(D13="","email ","")&IF(L13="","date ","")&IF(M13="","status",""))) -> 0 | AL13: =IF(B13="","",IF(AG13>0.5,"Overdue - chase payment",IF(AND(M13="Active",ISNUMBER(AC13),AC13>InactiveDays),"Inactive - win back",IF(AND(M13="Active",S13<>"Signed"),"Action - contract not signed",IF(AND(M13="Prospective",AD13=""),"Action - follow up quote","OK"))))) -> 0
A14: =IF(B14="","",ClientPrefix&TEXT(ROW()-4,"0000")) -> 0 | Y14: =IF(B14="","",COUNTIF(Pets!$C$5:$C$254,B14)) -> 0 | Z14: =IF(B14="","",COUNTIFS(Bookings!$C$5:$C$404,B14)) -> 0 | AA14: =IF(B14="","",COUNTIFS('Visit Log'!$D$5:$D$404,B14,'Visit Log'!$AE$5:$AE$404,"Completed")) -> 0 | AB14: =IF(B14="","",IF(SUMPRODUCT(MAX((Bookings!$C$5:$C$404=B14)*(Bookings!$AM$5:$AM$404="Completed")*Bookings!$I$5:$I$404))=0,"",SUMPRODUCT(MAX((Bookings!$C$5:$C$404=B14)*(Bookings!$AM$5:$AM$404="Completed")*Bookings!$I$5:$I$404)))) -> 0 | AC14: =IF(AB14="","",TODAY()-AB14) -> 0 | AD14: =IF(B14="","",IF(COUNTIFS(Bookings!$C$5:$C$404,B14,Bookings!$I$5:$I$404,">="&TODAY(),Bookings!$AM$5:$AM$404,"<>Cancelled")=0,"",SUMPRODUCT(MIN(((Bookings!$C$5:$C$404=B14)*(Bookings!$I$5:$I$404>=TODAY())*(Bookings!$AM$5:$AM$404<>"Cancelled"))*Bookings!$I$5:$I$404+(1-((Bookings!$C$5:$C$404=B14)*(Bookings!$I$5:$I$404>=TODAY())*(Bookings!$AM$5:$AM$404<>"Cancelled")))*2958465)))) -> 0 | AE14: =IF(B14="","",SUMIFS(Payments!$L$5:$L$304,Payments!$C$5:$C$304,B14)) -> 0 | AF14: =IF(B14="","",SUMIFS(Invoices!$O$5:$O$304,Invoices!$D$5:$D$304,B14,Invoices!$T$5:$T$304,"<>Draft")) -> 0 | AG14: =IF(B14="","",SUMIFS(Invoices!$S$5:$S$304,Invoices!$D$5:$D$304,B14,Invoices!$T$5:$T$304,"<>Cancelled")) -> 0 | AH14: =IF(OR(Z14="",Z14=0),"",SUMIFS(Bookings!$AK$5:$AK$404,Bookings!$C$5:$C$404,B14,Bookings!$AM$5:$AM$404,"<>Cancelled")/Z14) -> 0 | AI14: =IF(B14="","",IF(Z14>=LoyaltyThreshold,"Loyalty discount","Standard")) -> 0 | AJ14: =IF(B14="","",IF(COUNTIF(Clients!$B$5:$B$254,B14)>1,"Duplicate name",IF(AND(C14<>"",COUNTIF(Clients!$C$5:$C$254,C14)>1),"Duplicate phone","OK"))) -> 0 | AK14: =IF(B14="","",IF(AND(C14<>"",D14<>"",L14<>"",M14<>""),"OK","Add: "&IF(C14="","phone ","")&IF(D14="","email ","")&IF(L14="","date ","")&IF(M14="","status",""))) -> 0 | AL14: =IF(B14="","",IF(AG14>0.5,"Overdue - chase payment",IF(AND(M14="Active",ISNUMBER(AC14),AC14>InactiveDays),"Inactive - win back",IF(AND(M14="Active",S14<>"Signed"),"Action - contract not signed",IF(AND(M14="Prospective",AD14=""),"Action - follow up quote","OK"))))) -> 0
A15: =IF(B15="","",ClientPrefix&TEXT(ROW()-4,"0000")) -> 0 | Y15: =IF(B15="","",COUNTIF(Pets!$C$5:$C$254,B15)) -> 0 | Z15: =IF(B15="","",COUNTIFS(Bookings!$C$5:$C$404,B15)) -> 0 | AA15: =IF(B15="","",COUNTIFS('Visit Log'!$D$5:$D$404,B15,'Visit Log'!$AE$5:$AE$404,"Completed")) -> 0 | AB15: =IF(B15="","",IF(SUMPRODUCT(MAX((Bookings!$C$5:$C$404=B15)*(Bookings!$AM$5:$AM$404="Completed")*Bookings!$I$5:$I$404))=0,"",SUMPRODUCT(MAX((Bookings!$C$5:$C$404=B15)*(Bookings!$AM$5:$AM$404="Completed")*Bookings!$I$5:$I$404)))) -> 0 | AC15: =IF(AB15="","",TODAY()-AB15) -> 0 | AD15: =IF(B15="","",IF(COUNTIFS(Bookings!$C$5:$C$404,B15,Bookings!$I$5:$I$404,">="&TODAY(),Bookings!$AM$5:$AM$404,"<>Cancelled")=0,"",SUMPRODUCT(MIN(((Bookings!$C$5:$C$404=B15)*(Bookings!$I$5:$I$404>=TODAY())*(Bookings!$AM$5:$AM$404<>"Cancelled"))*Bookings!$I$5:$I$404+(1-((Bookings!$C$5:$C$404=B15)*(Bookings!$I$5:$I$404>=TODAY())*(Bookings!$AM$5:$AM$404<>"Cancelled")))*2958465)))) -> 0 | AE15: =IF(B15="","",SUMIFS(Payments!$L$5:$L$304,Payments!$C$5:$C$304,B15)) -> 0 | AF15: =IF(B15="","",SUMIFS(Invoices!$O$5:$O$304,Invoices!$D$5:$D$304,B15,Invoices!$T$5:$T$304,"<>Draft")) -> 0 | AG15: =IF(B15="","",SUMIFS(Invoices!$S$5:$S$304,Invoices!$D$5:$D$304,B15,Invoices!$T$5:$T$304,"<>Cancelled")) -> 0 | AH15: =IF(OR(Z15="",Z15=0),"",SUMIFS(Bookings!$AK$5:$AK$404,Bookings!$C$5:$C$404,B15,Bookings!$AM$5:$AM$404,"<>Cancelled")/Z15) -> 0 | AI15: =IF(B15="","",IF(Z15>=LoyaltyThreshold,"Loyalty discount","Standard")) -> 0 | AJ15: =IF(B15="","",IF(COUNTIF(Clients!$B$5:$B$254,B15)>1,"Duplicate name",IF(AND(C15<>"",COUNTIF(Clients!$C$5:$C$254,C15)>1),"Duplicate phone","OK"))) -> 0 | AK15: =IF(B15="","",IF(AND(C15<>"",D15<>"",L15<>"",M15<>""),"OK","Add: "&IF(C15="","phone ","")&IF(D15="","email ","")&IF(L15="","date ","")&IF(M15="","status",""))) -> 0 | AL15: =IF(B15="","",IF(AG15>0.5,"Overdue - chase payment",IF(AND(M15="Active",ISNUMBER(AC15),AC15>InactiveDays),"Inactive - win back",IF(AND(M15="Active",S15<>"Signed"),"Action - contract not signed",IF(AND(M15="Prospective",AD15=""),"Action - follow up quote","OK"))))) -> 0
A16: =IF(B16="","",ClientPrefix&TEXT(ROW()-4,"0000")) -> 0 | Y16: =IF(B16="","",COUNTIF(Pets!$C$5:$C$254,B16)) -> 0 | Z16: =IF(B16="","",COUNTIFS(Bookings!$C$5:$C$404,B16)) -> 0 | AA16: =IF(B16="","",COUNTIFS('Visit Log'!$D$5:$D$404,B16,'Visit Log'!$AE$5:$AE$404,"Completed")) -> 0 | AB16: =IF(B16="","",IF(SUMPRODUCT(MAX((Bookings!$C$5:$C$404=B16)*(Bookings!$AM$5:$AM$404="Completed")*Bookings!$I$5:$I$404))=0,"",SUMPRODUCT(MAX((Bookings!$C$5:$C$404=B16)*(Bookings!$AM$5:$AM$404="Completed")*Bookings!$I$5:$I$404)))) -> 0 | AC16: =IF(AB16="","",TODAY()-AB16) -> 0 | AD16: =IF(B16="","",IF(COUNTIFS(Bookings!$C$5:$C$404,B16,Bookings!$I$5:$I$404,">="&TODAY(),Bookings!$AM$5:$AM$404,"<>Cancelled")=0,"",SUMPRODUCT(MIN(((Bookings!$C$5:$C$404=B16)*(Bookings!$I$5:$I$404>=TODAY())*(Bookings!$AM$5:$AM$404<>"Cancelled"))*Bookings!$I$5:$I$404+(1-((Bookings!$C$5:$C$404=B16)*(Bookings!$I$5:$I$404>=TODAY())*(Bookings!$AM$5:$AM$404<>"Cancelled")))*2958465)))) -> 0 | AE16: =IF(B16="","",SUMIFS(Payments!$L$5:$L$304,Payments!$C$5:$C$304,B16)) -> 0 | AF16: =IF(B16="","",SUMIFS(Invoices!$O$5:$O$304,Invoices!$D$5:$D$304,B16,Invoices!$T$5:$T$304,"<>Draft")) -> 0 | AG16: =IF(B16="","",SUMIFS(Invoices!$S$5:$S$304,Invoices!$D$5:$D$304,B16,Invoices!$T$5:$T$304,"<>Cancelled")) -> 0 | AH16: =IF(OR(Z16="",Z16=0),"",SUMIFS(Bookings!$AK$5:$AK$404,Bookings!$C$5:$C$404,B16,Bookings!$AM$5:$AM$404,"<>Cancelled")/Z16) -> 0 | AI16: =IF(B16="","",IF(Z16>=LoyaltyThreshold,"Loyalty discount","Standard")) -> 0 | AJ16: =IF(B16="","",IF(COUNTIF(Clients!$B$5:$B$254,B16)>1,"Duplicate name",IF(AND(C16<>"",COUNTIF(Clients!$C$5:$C$254,C16)>1),"Duplicate phone","OK"))) -> 0 | AK16: =IF(B16="","",IF(AND(C16<>"",D16<>"",L16<>"",M16<>""),"OK","Add: "&IF(C16="","phone ","")&IF(D16="","email ","")&IF(L16="","date ","")&IF(M16="","status",""))) -> 0 | AL16: =IF(B16="","",IF(AG16>0.5,"Overdue - chase payment",IF(AND(M16="Active",ISNUMBER(AC16),AC16>InactiveDays),"Inactive - win back",IF(AND(M16="Active",S16<>"Signed"),"Action - contract not signed",IF(AND(M16="Prospective",AD16=""),"Action - follow up quote","OK"))))) -> 0
... A254: =IF(B254="","",ClientPrefix&TEXT(ROW()-4,"0000")) -> 0 | Y254: =IF(B254="","",COUNTIF(Pets!$C$5:$C$254,B254)) -> 0 | Z254: =IF(B254="","",COUNTIFS(Bookings!$C$5:$C$404,B254)) -> 0 | AA254: =IF(B254="","",COUNTIFS('Visit Log'!$D$5:$D$404,B254,'Visit Log'!$AE$5:$AE$404,"Completed")) -> 0 | AB254: =IF(B254="","",IF(SUMPRODUCT(MAX((Bookings!$C$5:$C$404=B254)*(Bookings!$AM$5:$AM$404="Completed")*Bookings!$I$5:$I$404))=0,"",SUMPRODUCT(MAX((Bookings!$C$5:$C$404=B254)*(Bookings!$AM$5:$AM$404="Completed")*Bookings!$I$5:$I$404)))) -> 0 | AC254: =IF(AB254="","",TODAY()-AB254) -> 0 | AD254: =IF(B254="","",IF(COUNTIFS(Bookings!$C$5:$C$404,B254,Bookings!$I$5:$I$404,">="&TODAY(),Bookings!$AM$5:$AM$404,"<>Cancelled")=0,"",SUMPRODUCT(MIN(((Bookings!$C$5:$C$404=B254)*(Bookings!$I$5:$I$404>=TODAY())*(Bookings!$AM$5:$AM$404<>"Cancelled"))*Bookings!$I$5:$I$404+(1-((Bookings!$C$5:$C$404=B254)*(Bookings!$I$5:$I$404>=TODAY())*(Bookings!$AM$5:$AM$404<>"Cancelled")))*2958465)))) -> 0 | AE254: =IF(B254="","",SUMIFS(Payments!$L$5:$L$304,Payments!$C$5:$C$304,B254)) -> 0 | AF254: =IF(B254="","",SUMIFS(Invoices!$O$5:$O$304,Invoices!$D$5:$D$304,B254,Invoices!$T$5:$T$304,"<>Draft")) -> 0 | AG254: =IF(B254="","",SUMIFS(Invoices!$S$5:$S$304,Invoices!$D$5:$D$304,B254,Invoices!$T$5:$T$304,"<>Cancelled")) -> 0 | AH254: =IF(OR(Z254="",Z254=0),"",SUMIFS(Bookings!$AK$5:$AK$404,Bookings!$C$5:$C$404,B254,Bookings!$AM$5:$AM$404,"<>Cancelled")/Z254) -> 0 | AI254: =IF(B254="","",IF(Z254>=LoyaltyThreshold,"Loyalty discount","Standard")) -> 0 | AJ254: =IF(B254="","",IF(COUNTIF(Clients!$B$5:$B$254,B254)>1,"Duplicate name",IF(AND(C254<>"",COUNTIF(Clients!$C$5:$C$254,C254)>1),"Duplicate phone","OK"))) -> 0 | AK254: =IF(B254="","",IF(AND(C254<>"",D254<>"",L254<>"",M254<>""),"OK","Add: "&IF(C254="","phone ","")&IF(D254="","email ","")&IF(L254="","date ","")&IF(M254="","status",""))) -> 0 | AL254: =IF(B254="","",IF(AG254>0.5,"Overdue - chase payment",IF(AND(M254="Active",ISNUMBER(AC254),AC254>InactiveDays),"Inactive - win back",IF(AND(M254="Active",S254<>"Signed"),"Action - contract not signed",IF(AND(M254="Prospective",AD254=""),"Action - follow up quote","OK"))))) -> 0

Sheet Pets
A1: Pet Profiles | AR1: Novality Store | v1.0.0
A2: Everything a sitter needs before they walk through the door: routine, medical, vet, vaccination status and safety warnings.
A3: > Start Here | C3: > Dashboard | E3: > Clients | G3: > Pets | I3: > Bookings | K3: > Visit Log | M3: > Invoices | O3: > Reminders | Q3: > Help | S3: Choose the owner from the drop down first. The grey 'Pet reference' column is what bookings and visit logs use, so two pets with the same name never get mixed up.
A4: ID | B4: Pet name | C4: Owner (client) | D4: Pet reference | E4: Client ID | F4: Pet type | G4: Breed | H4: Date of birth | I4: Age (yrs) | J4: Gender | K4: Weight (kg) | L4: Colour & markings | M4: Photo link | N4: Microchip number | O4: Temperament | P4: Behaviour issues | Q4: Allergies | R4: Medical conditions / special needs | S4: Veterinarian | T4: Vet phone | U4: Emergency clinic | V4: Emergency clinic phone | W4: Vaccinated on | X4: Vaccination expires | Y4: Vaccination status | Z4: Pet insurance | AA4: Policy number | AB4: Insurance renewal | AC4: Feeding instructions | AD4: Food type | AE4: Portion size | AF4: Feeding schedule | AG4: Medication | AH4: Dosage & instructions | AI4: Medication schedule | AJ4: Walking & exercise preferences | AK4: Potty / litter routine | AL4: Grooming requirements | AM4: Favourite toys, treats & games | AN4: Risk flag | AO4: Handling instructions | AP4: Safety warnings | AQ4: Visits | AR4: Last visit | AS4: Med records | AT4: Alerts
A5: =IF(B5="","",PetPrefix&TEXT(ROW()-4,"0000")) -> 0 | D5: =IF(B5="","",B5&" ("&C5&")") -> 0 | E5: =IF(C5="","",IFERROR(INDEX(Clients!$A$5:$A$254,MATCH(C5,Clients!$B$5:$B$254,0)),"")) -> 0 | I5: =IF(H5="","",ROUND(YEARFRAC(H5,TODAY()),1)) -> 0 | Y5: =IF(X5="","",IF(X5<TODAY(),"Expired",IF(X5-TODAY()<=VaccAlertDays,"Due in "&TEXT(X5-TODAY(),"0")&" days","Valid"))) -> 0 | AQ5: =IF(D5="","",COUNTIFS('Visit Log'!$E$5:$E$404,D5,'Visit Log'!$AE$5:$AE$404,"Completed")) -> 0 | AR5: =IF(D5="","",IF(SUMPRODUCT(MAX(('Visit Log'!$E$5:$E$404=D5)*('Visit Log'!$AE$5:$AE$404="Completed")*'Visit Log'!$C$5:$C$404))=0,"",SUMPRODUCT(MAX(('Visit Log'!$E$5:$E$404=D5)*('Visit Log'!$AE$5:$AE$404="Completed")*'Visit Log'!$C$5:$C$404)))) -> 0 | AS5: =IF(D5="","",COUNTIFS('Health Log'!$D$5:$D$204,D5)) -> 0 | AT5: =IF(B5="","",TRIM(IF(Y5="Expired","VACCINATION EXPIRED. ",IF(LEFT(Y5,6)="Due in","Vaccination due. ",""))&IF(AND(AN5<>"",AN5<>"None"),AN5&". ","")&IF(AND(AG5<>"",AG5<>"None",AG5<>"-"),"On medication. ","")&IF(Q5<>"",IF(OR(Q5="None",Q5="None known"),"","Allergy: "&Q5),""))) -> 0
A6: =IF(B6="","",PetPrefix&TEXT(ROW()-4,"0000")) -> 0 | D6: =IF(B6="","",B6&" ("&C6&")") -> 0 | E6: =IF(C6="","",IFERROR(INDEX(Clients!$A$5:$A$254,MATCH(C6,Clients!$B$5:$B$254,0)),"")) -> 0 | I6: =IF(H6="","",ROUND(YEARFRAC(H6,TODAY()),1)) -> 0 | Y6: =IF(X6="","",IF(X6<TODAY(),"Expired",IF(X6-TODAY()<=VaccAlertDays,"Due in "&TEXT(X6-TODAY(),"0")&" days","Valid"))) -> 0 | AQ6: =IF(D6="","",COUNTIFS('Visit Log'!$E$5:$E$404,D6,'Visit Log'!$AE$5:$AE$404,"Completed")) -> 0 | AR6: =IF(D6="","",IF(SUMPRODUCT(MAX(('Visit Log'!$E$5:$E$404=D6)*('Visit Log'!$AE$5:$AE$404="Completed")*'Visit Log'!$C$5:$C$404))=0,"",SUMPRODUCT(MAX(('Visit Log'!$E$5:$E$404=D6)*('Visit Log'!$AE$5:$AE$404="Completed")*'Visit Log'!$C$5:$C$404)))) -> 0 | AS6: =IF(D6="","",COUNTIFS('Health Log'!$D$5:$D$204,D6)) -> 0 | AT6: =IF(B6="","",TRIM(IF(Y6="Expired","VACCINATION EXPIRED. ",IF(LEFT(Y6,6)="Due in","Vaccination due. ",""))&IF(AND(AN6<>"",AN6<>"None"),AN6&". ","")&IF(AND(AG6<>"",AG6<>"None",AG6<>"-"),"On medication. ","")&IF(Q6<>"",IF(OR(Q6="None",Q6="None known"),"","Allergy: "&Q6),""))) -> 0
A7: =IF(B7="","",PetPrefix&TEXT(ROW()-4,"0000")) -> 0 | D7: =IF(B7="","",B7&" ("&C7&")") -> 0 | E7: =IF(C7="","",IFERROR(INDEX(Clients!$A$5:$A$254,MATCH(C7,Clients!$B$5:$B$254,0)),"")) -> 0 | I7: =IF(H7="","",ROUND(YEARFRAC(H7,TODAY()),1)) -> 0 | Y7: =IF(X7="","",IF(X7<TODAY(),"Expired",IF(X7-TODAY()<=VaccAlertDays,"Due in "&TEXT(X7-TODAY(),"0")&" days","Valid"))) -> 0 | AQ7: =IF(D7="","",COUNTIFS('Visit Log'!$E$5:$E$404,D7,'Visit Log'!$AE$5:$AE$404,"Completed")) -> 0 | AR7: =IF(D7="","",IF(SUMPRODUCT(MAX(('Visit Log'!$E$5:$E$404=D7)*('Visit Log'!$AE$5:$AE$404="Completed")*'Visit Log'!$C$5:$C$404))=0,"",SUMPRODUCT(MAX(('Visit Log'!$E$5:$E$404=D7)*('Visit Log'!$AE$5:$AE$404="Completed")*'Visit Log'!$C$5:$C$404)))) -> 0 | AS7: =IF(D7="","",COUNTIFS('Health Log'!$D$5:$D$204,D7)) -> 0 | AT7: =IF(B7="","",TRIM(IF(Y7="Expired","VACCINATION EXPIRED. ",IF(LEFT(Y7,6)="Due in","Vaccination due. ",""))&IF(AND(AN7<>"",AN7<>"None"),AN7&". ","")&IF(AND(AG7<>"",AG7<>"None",AG7<>"-"),"On medication. ","")&IF(Q7<>"",IF(OR(Q7="None",Q7="None known"),"","Allergy: "&Q7),""))) -> 0
A8: =IF(B8="","",PetPrefix&TEXT(ROW()-4,"0000")) -> 0 | D8: =IF(B8="","",B8&" ("&C8&")") -> 0 | E8: =IF(C8="","",IFERROR(INDEX(Clients!$A$5:$A$254,MATCH(C8,Clients!$B$5:$B$254,0)),"")) -> 0 | I8: =IF(H8="","",ROUND(YEARFRAC(H8,TODAY()),1)) -> 0 | Y8: =IF(X8="","",IF(X8<TODAY(),"Expired",IF(X8-TODAY()<=VaccAlertDays,"Due in "&TEXT(X8-TODAY(),"0")&" days","Valid"))) -> 0 | AQ8: =IF(D8="","",COUNTIFS('Visit Log'!$E$5:$E$404,D8,'Visit Log'!$AE$5:$AE$404,"Completed")) -> 0 | AR8: =IF(D8="","",IF(SUMPRODUCT(MAX(('Visit Log'!$E$5:$E$404=D8)*('Visit Log'!$AE$5:$AE$404="Completed")*'Visit Log'!$C$5:$C$404))=0,"",SUMPRODUCT(MAX(('Visit Log'!$E$5:$E$404=D8)*('Visit Log'!$AE$5:$AE$404="Completed")*'Visit Log'!$C$5:$C$404)))) -> 0 | AS8: =IF(D8="","",COUNTIFS('Health Log'!$D$5:$D$204,D8)) -> 0 | AT8: =IF(B8="","",TRIM(IF(Y8="Expired","VACCINATION EXPIRED. ",IF(LEFT(Y8,6)="Due in","Vaccination due. ",""))&IF(AND(AN8<>"",AN8<>"None"),AN8&". ","")&IF(AND(AG8<>"",AG8<>"None",AG8<>"-"),"On medication. ","")&IF(Q8<>"",IF(OR(Q8="None",Q8="None known"),"","Allergy: "&Q8),""))) -> 0
A9: =IF(B9="","",PetPrefix&TEXT(ROW()-4,"0000")) -> 0 | D9: =IF(B9="","",B9&" ("&C9&")") -> 0 | E9: =IF(C9="","",IFERROR(INDEX(Clients!$A$5:$A$254,MATCH(C9,Clients!$B$5:$B$254,0)),"")) -> 0 | I9: =IF(H9="","",ROUND(YEARFRAC(H9,TODAY()),1)) -> 0 | Y9: =IF(X9="","",IF(X9<TODAY(),"Expired",IF(X9-TODAY()<=VaccAlertDays,"Due in "&TEXT(X9-TODAY(),"0")&" days","Valid"))) -> 0 | AQ9: =IF(D9="","",COUNTIFS('Visit Log'!$E$5:$E$404,D9,'Visit Log'!$AE$5:$AE$404,"Completed")) -> 0 | AR9: =IF(D9="","",IF(SUMPRODUCT(MAX(('Visit Log'!$E$5:$E$404=D9)*('Visit Log'!$AE$5:$AE$404="Completed")*'Visit Log'!$C$5:$C$404))=0,"",SUMPRODUCT(MAX(('Visit Log'!$E$5:$E$404=D9)*('Visit Log'!$AE$5:$AE$404="Completed")*'Visit Log'!$C$5:$C$404)))) -> 0 | AS9: =IF(D9="","",COUNTIFS('Health Log'!$D$5:$D$204,D9)) -> 0 | AT9: =IF(B9="","",TRIM(IF(Y9="Expired","VACCINATION EXPIRED. ",IF(LEFT(Y9,6)="Due in","Vaccination due. ",""))&IF(AND(AN9<>"",AN9<>"None"),AN9&". ","")&IF(AND(AG9<>"",AG9<>"None",AG9<>"-"),"On medication. ","")&IF(Q9<>"",IF(OR(Q9="None",Q9="None known"),"","Allergy: "&Q9),""))) -> 0
A10: =IF(B10="","",PetPrefix&TEXT(ROW()-4,"0000")) -> 0 | D10: =IF(B10="","",B10&" ("&C10&")") -> 0 | E10: =IF(C10="","",IFERROR(INDEX(Clients!$A$5:$A$254,MATCH(C10,Clients!$B$5:$B$254,0)),"")) -> 0 | I10: =IF(H10="","",ROUND(YEARFRAC(H10,TODAY()),1)) -> 0 | Y10: =IF(X10="","",IF(X10<TODAY(),"Expired",IF(X10-TODAY()<=VaccAlertDays,"Due in "&TEXT(X10-TODAY(),"0")&" days","Valid"))) -> 0 | AQ10: =IF(D10="","",COUNTIFS('Visit Log'!$E$5:$E$404,D10,'Visit Log'!$AE$5:$AE$404,"Completed")) -> 0 | AR10: =IF(D10="","",IF(SUMPRODUCT(MAX(('Visit Log'!$E$5:$E$404=D10)*('Visit Log'!$AE$5:$AE$404="Completed")*'Visit Log'!$C$5:$C$404))=0,"",SUMPRODUCT(MAX(('Visit Log'!$E$5:$E$404=D10)*('Visit Log'!$AE$5:$AE$404="Completed")*'Visit Log'!$C$5:$C$404)))) -> 0 | AS10: =IF(D10="","",COUNTIFS('Health Log'!$D$5:$D$204,D10)) -> 0 | AT10: =IF(B10="","",TRIM(IF(Y10="Expired","VACCINATION EXPIRED. ",IF(LEFT(Y10,6)="Due in","Vaccination due. ",""))&IF(AND(AN10<>"",AN10<>"None"),AN10&". ","")&IF(AND(AG10<>"",AG10<>"None",AG10<>"-"),"On medication. ","")&IF(Q10<>"",IF(OR(Q10="None",Q10="None known"),"","Allergy: "&Q10),""))) -> 0
A11: =IF(B11="","",PetPrefix&TEXT(ROW()-4,"0000")) -> 0 | D11: =IF(B11="","",B11&" ("&C11&")") -> 0 | E11: =IF(C11="","",IFERROR(INDEX(Clients!$A$5:$A$254,MATCH(C11,Clients!$B$5:$B$254,0)),"")) -> 0 | I11: =IF(H11="","",ROUND(YEARFRAC(H11,TODAY()),1)) -> 0 | Y11: =IF(X11="","",IF(X11<TODAY(),"Expired",IF(X11-TODAY()<=VaccAlertDays,"Due in "&TEXT(X11-TODAY(),"0")&" days","Valid"))) -> 0 | AQ11: =IF(D11="","",COUNTIFS('Visit Log'!$E$5:$E$404,D11,'Visit Log'!$AE$5:$AE$404,"Completed")) -> 0 | AR11: =IF(D11="","",IF(SUMPRODUCT(MAX(('Visit Log'!$E$5:$E$404=D11)*('Visit Log'!$AE$5:$AE$404="Completed")*'Visit Log'!$C$5:$C$404))=0,"",SUMPRODUCT(MAX(('Visit Log'!$E$5:$E$404=D11)*('Visit Log'!$AE$5:$AE$404="Completed")*'Visit Log'!$C$5:$C$404)))) -> 0 | AS11: =IF(D11="","",COUNTIFS('Health Log'!$D$5:$D$204,D11)) -> 0 | AT11: =IF(B11="","",TRIM(IF(Y11="Expired","VACCINATION EXPIRED. ",IF(LEFT(Y11,6)="Due in","Vaccination due. ",""))&IF(AND(AN11<>"",AN11<>"None"),AN11&". ","")&IF(AND(AG11<>"",AG11<>"None",AG11<>"-"),"On medication. ","")&IF(Q11<>"",IF(OR(Q11="None",Q11="None known"),"","Allergy: "&Q11),""))) -> 0
A12: =IF(B12="","",PetPrefix&TEXT(ROW()-4,"0000")) -> 0 | D12: =IF(B12="","",B12&" ("&C12&")") -> 0 | E12: =IF(C12="","",IFERROR(INDEX(Clients!$A$5:$A$254,MATCH(C12,Clients!$B$5:$B$254,0)),"")) -> 0 | I12: =IF(H12="","",ROUND(YEARFRAC(H12,TODAY()),1)) -> 0 | Y12: =IF(X12="","",IF(X12<TODAY(),"Expired",IF(X12-TODAY()<=VaccAlertDays,"Due in "&TEXT(X12-TODAY(),"0")&" days","Valid"))) -> 0 | AQ12: =IF(D12="","",COUNTIFS('Visit Log'!$E$5:$E$404,D12,'Visit Log'!$AE$5:$AE$404,"Completed")) -> 0 | AR12: =IF(D12="","",IF(SUMPRODUCT(MAX(('Visit Log'!$E$5:$E$404=D12)*('Visit Log'!$AE$5:$AE$404="Completed")*'Visit Log'!$C$5:$C$404))=0,"",SUMPRODUCT(MAX(('Visit Log'!$E$5:$E$404=D12)*('Visit Log'!$AE$5:$AE$404="Completed")*'Visit Log'!$C$5:$C$404)))) -> 0 | AS12: =IF(D12="","",COUNTIFS('Health Log'!$D$5:$D$204,D12)) -> 0 | AT12: =IF(B12="","",TRIM(IF(Y12="Expired","VACCINATION EXPIRED. ",IF(LEFT(Y12,6)="Due in","Vaccination due. ",""))&IF(AND(AN12<>"",AN12<>"None"),AN12&". ","")&IF(AND(AG12<>"",AG12<>"None",AG12<>"-"),"On medication. ","")&IF(Q12<>"",IF(OR(Q12="None",Q12="None known"),"","Allergy: "&Q12),""))) -> 0
A13: =IF(B13="","",PetPrefix&TEXT(ROW()-4,"0000")) -> 0 | D13: =IF(B13="","",B13&" ("&C13&")") -> 0 | E13: =IF(C13="","",IFERROR(INDEX(Clients!$A$5:$A$254,MATCH(C13,Clients!$B$5:$B$254,0)),"")) -> 0 | I13: =IF(H13="","",ROUND(YEARFRAC(H13,TODAY()),1)) -> 0 | Y13: =IF(X13="","",IF(X13<TODAY(),"Expired",IF(X13-TODAY()<=VaccAlertDays,"Due in "&TEXT(X13-TODAY(),"0")&" days","Valid"))) -> 0 | AQ13: =IF(D13="","",COUNTIFS('Visit Log'!$E$5:$E$404,D13,'Visit Log'!$AE$5:$AE$404,"Completed")) -> 0 | AR13: =IF(D13="","",IF(SUMPRODUCT(MAX(('Visit Log'!$E$5:$E$404=D13)*('Visit Log'!$AE$5:$AE$404="Completed")*'Visit Log'!$C$5:$C$404))=0,"",SUMPRODUCT(MAX(('Visit Log'!$E$5:$E$404=D13)*('Visit Log'!$AE$5:$AE$404="Completed")*'Visit Log'!$C$5:$C$404)))) -> 0 | AS13: =IF(D13="","",COUNTIFS('Health Log'!$D$5:$D$204,D13)) -> 0 | AT13: =IF(B13="","",TRIM(IF(Y13="Expired","VACCINATION EXPIRED. ",IF(LEFT(Y13,6)="Due in","Vaccination due. ",""))&IF(AND(AN13<>"",AN13<>"None"),AN13&". ","")&IF(AND(AG13<>"",AG13<>"None",AG13<>"-"),"On medication. ","")&IF(Q13<>"",IF(OR(Q13="None",Q13="None known"),"","Allergy: "&Q13),""))) -> 0
A14: =IF(B14="","",PetPrefix&TEXT(ROW()-4,"0000")) -> 0 | D14: =IF(B14="","",B14&" ("&C14&")") -> 0 | E14: =IF(C14="","",IFERROR(INDEX(Clients!$A$5:$A$254,MATCH(C14,Clients!$B$5:$B$254,0)),"")) -> 0 | I14: =IF(H14="","",ROUND(YEARFRAC(H14,TODAY()),1)) -> 0 | Y14: =IF(X14="","",IF(X14<TODAY(),"Expired",IF(X14-TODAY()<=VaccAlertDays,"Due in "&TEXT(X14-TODAY(),"0")&" days","Valid"))) -> 0 | AQ14: =IF(D14="","",COUNTIFS('Visit Log'!$E$5:$E$404,D14,'Visit Log'!$AE$5:$AE$404,"Completed")) -> 0 | AR14: =IF(D14="","",IF(SUMPRODUCT(MAX(('Visit Log'!$E$5:$E$404=D14)*('Visit Log'!$AE$5:$AE$404="Completed")*'Visit Log'!$C$5:$C$404))=0,"",SUMPRODUCT(MAX(('Visit Log'!$E$5:$E$404=D14)*('Visit Log'!$AE$5:$AE$404="Completed")*'Visit Log'!$C$5:$C$404)))) -> 0 | AS14: =IF(D14="","",COUNTIFS('Health Log'!$D$5:$D$204,D14)) -> 0 | AT14: =IF(B14="","",TRIM(IF(Y14="Expired","VACCINATION EXPIRED. ",IF(LEFT(Y14,6)="Due in","Vaccination due. ",""))&IF(AND(AN14<>"",AN14<>"None"),AN14&". ","")&IF(AND(AG14<>"",AG14<>"None",AG14<>"-"),"On medication. ","")&IF(Q14<>"",IF(OR(Q14="None",Q14="None known"),"","Allergy: "&Q14),""))) -> 0
A15: =IF(B15="","",PetPrefix&TEXT(ROW()-4,"0000")) -> 0 | D15: =IF(B15="","",B15&" ("&C15&")") -> 0 | E15: =IF(C15="","",IFERROR(INDEX(Clients!$A$5:$A$254,MATCH(C15,Clients!$B$5:$B$254,0)),"")) -> 0 | I15: =IF(H15="","",ROUND(YEARFRAC(H15,TODAY()),1)) -> 0 | Y15: =IF(X15="","",IF(X15<TODAY(),"Expired",IF(X15-TODAY()<=VaccAlertDays,"Due in "&TEXT(X15-TODAY(),"0")&" days","Valid"))) -> 0 | AQ15: =IF(D15="","",COUNTIFS('Visit Log'!$E$5:$E$404,D15,'Visit Log'!$AE$5:$AE$404,"Completed")) -> 0 | AR15: =IF(D15="","",IF(SUMPRODUCT(MAX(('Visit Log'!$E$5:$E$404=D15)*('Visit Log'!$AE$5:$AE$404="Completed")*'Visit Log'!$C$5:$C$404))=0,"",SUMPRODUCT(MAX(('Visit Log'!$E$5:$E$404=D15)*('Visit Log'!$AE$5:$AE$404="Completed")*'Visit Log'!$C$5:$C$404)))) -> 0 | AS15: =IF(D15="","",COUNTIFS('Health Log'!$D$5:$D$204,D15)) -> 0 | AT15: =IF(B15="","",TRIM(IF(Y15="Expired","VACCINATION EXPIRED. ",IF(LEFT(Y15,6)="Due in","Vaccination due. ",""))&IF(AND(AN15<>"",AN15<>"None"),AN15&". ","")&IF(AND(AG15<>"",AG15<>"None",AG15<>"-"),"On medication. ","")&IF(Q15<>"",IF(OR(Q15="None",Q15="None known"),"","Allergy: "&Q15),""))) -> 0
A16: =IF(B16="","",PetPrefix&TEXT(ROW()-4,"0000")) -> 0 | D16: =IF(B16="","",B16&" ("&C16&")") -> 0 | E16: =IF(C16="","",IFERROR(INDEX(Clients!$A$5:$A$254,MATCH(C16,Clients!$B$5:$B$254,0)),"")) -> 0 | I16: =IF(H16="","",ROUND(YEARFRAC(H16,TODAY()),1)) -> 0 | Y16: =IF(X16="","",IF(X16<TODAY(),"Expired",IF(X16-TODAY()<=VaccAlertDays,"Due in "&TEXT(X16-TODAY(),"0")&" days","Valid"))) -> 0 | AQ16: =IF(D16="","",COUNTIFS('Visit Log'!$E$5:$E$404,D16,'Visit Log'!$AE$5:$AE$404,"Completed")) -> 0 | AR16: =IF(D16="","",IF(SUMPRODUCT(MAX(('Visit Log'!$E$5:$E$404=D16)*('Visit Log'!$AE$5:$AE$404="Completed")*'Visit Log'!$C$5:$C$404))=0,"",SUMPRODUCT(MAX(('Visit Log'!$E$5:$E$404=D16)*('Visit Log'!$AE$5:$AE$404="Completed")*'Visit Log'!$C$5:$C$404)))) -> 0 | AS16: =IF(D16="","",COUNTIFS('Health Log'!$D$5:$D$204,D16)) -> 0 | AT16: =IF(B16="","",TRIM(IF(Y16="Expired","VACCINATION EXPIRED. ",IF(LEFT(Y16,6)="Due in","Vaccination due. ",""))&IF(AND(AN16<>"",AN16<>"None"),AN16&". ","")&IF(AND(AG16<>"",AG16<>"None",AG16<>"-"),"On medication. ","")&IF(Q16<>"",IF(OR(Q16="None",Q16="None known"),"","Allergy: "&Q16),""))) -> 0
... A254: =IF(B254="","",PetPrefix&TEXT(ROW()-4,"0000")) -> 0 | D254: =IF(B254="","",B254&" ("&C254&")") -> 0 | E254: =IF(C254="","",IFERROR(INDEX(Clients!$A$5:$A$254,MATCH(C254,Clients!$B$5:$B$254,0)),"")) -> 0 | I254: =IF(H254="","",ROUND(YEARFRAC(H254,TODAY()),1)) -> 0 | Y254: =IF(X254="","",IF(X254<TODAY(),"Expired",IF(X254-TODAY()<=VaccAlertDays,"Due in "&TEXT(X254-TODAY(),"0")&" days","Valid"))) -> 0 | AQ254: =IF(D254="","",COUNTIFS('Visit Log'!$E$5:$E$404,D254,'Visit Log'!$AE$5:$AE$404,"Completed")) -> 0 | AR254: =IF(D254="","",IF(SUMPRODUCT(MAX(('Visit Log'!$E$5:$E$404=D254)*('Visit Log'!$AE$5:$AE$404="Completed")*'Visit Log'!$C$5:$C$404))=0,"",SUMPRODUCT(MAX(('Visit Log'!$E$5:$E$404=D254)*('Visit Log'!$AE$5:$AE$404="Completed")*'Visit Log'!$C$5:$C$404)))) -> 0 | AS254: =IF(D254="","",COUNTIFS('Health Log'!$D$5:$D$204,D254)) -> 0 | AT254: =IF(B254="","",TRIM(IF(Y254="Expired","VACCINATION EXPIRED. ",IF(LEFT(Y254,6)="Due in","Vaccination due. ",""))&IF(AND(AN254<>"",AN254<>"None"),AN254&". ","")&IF(AND(AG254<>"",AG254<>"None",AG254<>"-"),"On medication. ","")&IF(Q254<>"",IF(OR(Q254="None",Q254="None known"),"","Allergy: "&Q254),""))) -> 0

Sheet Bookings
A1: Bookings & Schedule | AX1: Novality Store | v1.0.0
A2: Every booking, priced automatically from the Services tab with holiday, weekend, extra pet, travel and last-minute rules applied.
A3: > Start Here | C3: > Dashboard | E3: > Clients | G3: > Pets | I3: > Bookings | K3: > Visit Log | M3: > Invoices | O3: > Reminders | Q3: > Help | S3: Fill the cream cells from left to right. Everything grey - prices, surcharges, totals, conflicts and alerts - is calculated and locked.
A4: ID | B4: Requested on | C4: Client | D4: Client ID | E4: Pet | F4: Additional pets | G4: No. of pets | H4: Service | I4: Booking date | J4: Day | K4: Start | L4: End | M4: Hours | N4: Qty / nights | O4: Billing unit | P4: Rate | Q4: Extra pet rate | R4: Holiday % | S4: Weekend % | T4: Travel billable | U4: Base charge | V4: Extra pet fee | W4: Holiday? | X4: Weekend? | Y4: Surcharges | Z4: Travel distance | AA4: Travel fee | AB4: Travel allowance (min) | AC4: Last-minute fee | AD4: Discount type | AE4: Discount % | AF4: Discount | AG4: Price override | AH4: Override reason | AI4: Subtotal | AJ4: Tax | AK4: Booking total | AL4: Assigned to | AM4: Status | AN4: Confirmed to client | AO4: Reminder sent | AP4: Repeats | AQ4: Next booking due | AR4: Schedule check | AS4: Visit logged | AT4: Invoice | AU4: Payment status | AV4: Cancellation reason | AW4: Rescheduled from | AX4: Notes & special requests | AY4: Month | AZ4: Action needed
A5: =IF(C5="","",BookingPrefix&TEXT(ROW()-4,"0000")) -> 0 | D5: =IF(C5="","",IFERROR(INDEX(Clients!$A$5:$A$254,MATCH(C5,Clients!$B$5:$B$254,0)),"")) -> 0 | J5: =IF(I5="","",TEXT(I5,"ddd")) -> 0 | M5: =IF(OR(K5="",L5=""),"",ROUND((L5-K5+IF(L5<K5,1,0))*24,2)) -> 0 | O5: =IF(H5="","",IFERROR(INDEX(Services!$E$5:$E$54,MATCH(H5,Services!$B$5:$B$54,0)),"")) -> 0 | P5: =IF(H5="","",IFERROR(INDEX(Services!$G$5:$G$54,MATCH(H5,Services!$B$5:$B$54,0)),0)) -> 0 | Q5: =IF(H5="","",IF(IFERROR(INDEX(Services!$H$5:$H$54,MATCH(H5,Services!$B$5:$B$54,0)),0)=0,ExtraPetFeeDefault,IFERROR(INDEX(Services!$H$5:$H$54,MATCH(H5,Services!$B$5:$B$54,0)),0))) -> 0 | R5: =IF(H5="","",IF(IFERROR(INDEX(Services!$I$5:$I$54,MATCH(H5,Services!$B$5:$B$54,0)),0)=0,HolidaySurcharge,IFERROR(INDEX(Services!$I$5:$I$54,MATCH(H5,Services!$B$5:$B$54,0)),0))) -> 0 | S5: =IF(H5="","",IF(IFERROR(INDEX(Services!$J$5:$J$54,MATCH(H5,Services!$B$5:$B$54,0)),0)=0,WeekendSurcharge,IFERROR(INDEX(Services!$J$5:$J$54,MATCH(H5,Services!$B$5:$B$54,0)),0))) -> 0 | T5: =IF(H5="","",IFERROR(INDEX(Services!$K$5:$K$54,MATCH(H5,Services!$B$5:$B$54,0)),"No")) -> 0 | U5: =IF(H5="","",ROUND(IF(O5="Per hour",P5*IF(M5="",IF(N5="",1,N5),M5),P5*IF(N5="",1,N5)),2)) -> 0 | V5: =IF(H5="","",ROUND(MAX(0,IF(G5="",1,G5)-1)*Q5,2)) -> 0 | W5: =IF(I5="","",IF(COUNTIF(HolidayDates,I5)>0,"Yes","No")) -> 0 | X5: =IF(I5="","",IF(WEEKDAY(I5,2)>5,"Yes","No")) -> 0 | Y5: =IF(H5="","",ROUND((U5+V5)*(IF(W5="Yes",R5,0)+IF(X5="Yes",S5,0)),2)) -> 0 | AA5: =IF(H5="","",IF(T5<>"Yes",0,ROUND(MAX(0,IF(Z5="",0,Z5)-FreeTravelDistance)*TravelFeeRate,2))) -> 0 | AB5: =IF(I5="","",TravelTimeMins) -> 0 | AC5: =IF(OR(I5="",B5=""),0,IF(I5-B5<=LastMinuteDays,EmergencyFee,0)) -> 0 | AF5: =IF(H5="","",ROUND((U5+V5+Y5+AA5+AC5)*IF(AE5="",0,AE5),2)) -> 0 | AI5: =IF(H5="","",IF(AG5<>"",AG5,ROUND(U5+V5+Y5+AA5+AC5-AF5,2))) -> 0 | AJ5: =IF(AI5="","",IF(TaxRegistered<>"Yes",0,IF(PricesIncludeTax="Yes",ROUND(AI5-AI5/(1+TaxRate),2),ROUND(AI5*TaxRate,2)))) -> 0 | AK5: =IF(AI5="","",IF(PricesIncludeTax="Yes",AI5,ROUND(AI5+AJ5,2))) -> 0 | AQ5: =IF(OR(I5="",AP5="",AP5="None"),"",IF(AP5="Monthly",EDATE(I5,1),I5+IF(AP5="Daily",1,IF(AP5="Weekdays",IF(WEEKDAY(I5,2)>=5,8-WEEKDAY(I5,2),1),IF(AP5="Weekly",7,IF(AP5="Fortnightly",14,0)))))) -> 0 | AR5: =IF(OR(I5="",AL5="",K5="",L5=""),"",IF(SUMPRODUCT((Bookings!$AL$5:$AL$404=AL5)*(Bookings!$I$5:$I$404=I5)*(Bookings!$K$5:$K$404<L5)*(Bookings!$L$5:$L$404>K5)*(Bookings!$AM$5:$AM$404<>"Cancelled"))>1,"Conflict - double booked","OK")) -> 0 | AS5: =IF(A5="","",IF(COUNTIF('Visit Log'!$B$5:$B$404,A5)>0,"Yes","No")) -> 0 | AT5: =IF(A5="","",IFERROR(INDEX(Invoices!$A$5:$A$304,MATCH(A5,Invoices!$E$5:$E$304,0)),"")) -> 0 | AU5: =IF(A5="","",IF(AT5="","Not invoiced",IFERROR(INDEX(Invoices!$U$5:$U$304,MATCH(AT5,Invoices!$A$5:$A$304,0)),""))) -> 0 | AY5: =IF(I5="","",TEXT(I5,"yyyy-mm")) -> 0 | AZ5: =IF(I5="","",IF(AM5="Cancelled","Cancelled",IF(AND(I5<TODAY(),OR(AM5="Pending",AM5="Confirmed",AM5="Enquiry")),"Overdue - update status",IF(AND(AM5="Completed",AS5="No"),"Action - log the visit",IF(I5=TODAY(),"Today",IF(AND(I5>TODAY(),I5-TODAY()<=ReminderLeadDays,AN5<>"Yes"),"Action - unconfirmed",IF(AND(I5>TODAY(),I5-TODAY()<=ReminderLeadDays),"Upcoming","OK"))))))) -> 0
A6: =IF(C6="","",BookingPrefix&TEXT(ROW()-4,"0000")) -> 0 | D6: =IF(C6="","",IFERROR(INDEX(Clients!$A$5:$A$254,MATCH(C6,Clients!$B$5:$B$254,0)),"")) -> 0 | J6: =IF(I6="","",TEXT(I6,"ddd")) -> 0 | M6: =IF(OR(K6="",L6=""),"",ROUND((L6-K6+IF(L6<K6,1,0))*24,2)) -> 0 | O6: =IF(H6="","",IFERROR(INDEX(Services!$E$5:$E$54,MATCH(H6,Services!$B$5:$B$54,0)),"")) -> 0 | P6: =IF(H6="","",IFERROR(INDEX(Services!$G$5:$G$54,MATCH(H6,Services!$B$5:$B$54,0)),0)) -> 0 | Q6: =IF(H6="","",IF(IFERROR(INDEX(Services!$H$5:$H$54,MATCH(H6,Services!$B$5:$B$54,0)),0)=0,ExtraPetFeeDefault,IFERROR(INDEX(Services!$H$5:$H$54,MATCH(H6,Services!$B$5:$B$54,0)),0))) -> 0 | R6: =IF(H6="","",IF(IFERROR(INDEX(Services!$I$5:$I$54,MATCH(H6,Services!$B$5:$B$54,0)),0)=0,HolidaySurcharge,IFERROR(INDEX(Services!$I$5:$I$54,MATCH(H6,Services!$B$5:$B$54,0)),0))) -> 0 | S6: =IF(H6="","",IF(IFERROR(INDEX(Services!$J$5:$J$54,MATCH(H6,Services!$B$5:$B$54,0)),0)=0,WeekendSurcharge,IFERROR(INDEX(Services!$J$5:$J$54,MATCH(H6,Services!$B$5:$B$54,0)),0))) -> 0 | T6: =IF(H6="","",IFERROR(INDEX(Services!$K$5:$K$54,MATCH(H6,Services!$B$5:$B$54,0)),"No")) -> 0 | U6: =IF(H6="","",ROUND(IF(O6="Per hour",P6*IF(M6="",IF(N6="",1,N6),M6),P6*IF(N6="",1,N6)),2)) -> 0 | V6: =IF(H6="","",ROUND(MAX(0,IF(G6="",1,G6)-1)*Q6,2)) -> 0 | W6: =IF(I6="","",IF(COUNTIF(HolidayDates,I6)>0,"Yes","No")) -> 0 | X6: =IF(I6="","",IF(WEEKDAY(I6,2)>5,"Yes","No")) -> 0 | Y6: =IF(H6="","",ROUND((U6+V6)*(IF(W6="Yes",R6,0)+IF(X6="Yes",S6,0)),2)) -> 0 | AA6: =IF(H6="","",IF(T6<>"Yes",0,ROUND(MAX(0,IF(Z6="",0,Z6)-FreeTravelDistance)*TravelFeeRate,2))) -> 0 | AB6: =IF(I6="","",TravelTimeMins) -> 0 | AC6: =IF(OR(I6="",B6=""),0,IF(I6-B6<=LastMinuteDays,EmergencyFee,0)) -> 0 | AF6: =IF(H6="","",ROUND((U6+V6+Y6+AA6+AC6)*IF(AE6="",0,AE6),2)) -> 0 | AI6: =IF(H6="","",IF(AG6<>"",AG6,ROUND(U6+V6+Y6+AA6+AC6-AF6,2))) -> 0 | AJ6: =IF(AI6="","",IF(TaxRegistered<>"Yes",0,IF(PricesIncludeTax="Yes",ROUND(AI6-AI6/(1+TaxRate),2),ROUND(AI6*TaxRate,2)))) -> 0 | AK6: =IF(AI6="","",IF(PricesIncludeTax="Yes",AI6,ROUND(AI6+AJ6,2))) -> 0 | AQ6: =IF(OR(I6="",AP6="",AP6="None"),"",IF(AP6="Monthly",EDATE(I6,1),I6+IF(AP6="Daily",1,IF(AP6="Weekdays",IF(WEEKDAY(I6,2)>=5,8-WEEKDAY(I6,2),1),IF(AP6="Weekly",7,IF(AP6="Fortnightly",14,0)))))) -> 0 | AR6: =IF(OR(I6="",AL6="",K6="",L6=""),"",IF(SUMPRODUCT((Bookings!$AL$5:$AL$404=AL6)*(Bookings!$I$5:$I$404=I6)*(Bookings!$K$5:$K$404<L6)*(Bookings!$L$5:$L$404>K6)*(Bookings!$AM$5:$AM$404<>"Cancelled"))>1,"Conflict - double booked","OK")) -> 0 | AS6: =IF(A6="","",IF(COUNTIF('Visit Log'!$B$5:$B$404,A6)>0,"Yes","No")) -> 0 | AT6: =IF(A6="","",IFERROR(INDEX(Invoices!$A$5:$A$304,MATCH(A6,Invoices!$E$5:$E$304,0)),"")) -> 0 | AU6: =IF(A6="","",IF(AT6="","Not invoiced",IFERROR(INDEX(Invoices!$U$5:$U$304,MATCH(AT6,Invoices!$A$5:$A$304,0)),""))) -> 0 | AY6: =IF(I6="","",TEXT(I6,"yyyy-mm")) -> 0 | AZ6: =IF(I6="","",IF(AM6="Cancelled","Cancelled",IF(AND(I6<TODAY(),OR(AM6="Pending",AM6="Confirmed",AM6="Enquiry")),"Overdue - update status",IF(AND(AM6="Completed",AS6="No"),"Action - log the visit",IF(I6=TODAY(),"Today",IF(AND(I6>TODAY(),I6-TODAY()<=ReminderLeadDays,AN6<>"Yes"),"Action - unconfirmed",IF(AND(I6>TODAY(),I6-TODAY()<=ReminderLeadDays),"Upcoming","OK"))))))) -> 0
A7: =IF(C7="","",BookingPrefix&TEXT(ROW()-4,"0000")) -> 0 | D7: =IF(C7="","",IFERROR(INDEX(Clients!$A$5:$A$254,MATCH(C7,Clients!$B$5:$B$254,0)),"")) -> 0 | J7: =IF(I7="","",TEXT(I7,"ddd")) -> 0 | M7: =IF(OR(K7="",L7=""),"",ROUND((L7-K7+IF(L7<K7,1,0))*24,2)) -> 0 | O7: =IF(H7="","",IFERROR(INDEX(Services!$E$5:$E$54,MATCH(H7,Services!$B$5:$B$54,0)),"")) -> 0 | P7: =IF(H7="","",IFERROR(INDEX(Services!$G$5:$G$54,MATCH(H7,Services!$B$5:$B$54,0)),0)) -> 0 | Q7: =IF(H7="","",IF(IFERROR(INDEX(Services!$H$5:$H$54,MATCH(H7,Services!$B$5:$B$54,0)),0)=0,ExtraPetFeeDefault,IFERROR(INDEX(Services!$H$5:$H$54,MATCH(H7,Services!$B$5:$B$54,0)),0))) -> 0 | R7: =IF(H7="","",IF(IFERROR(INDEX(Services!$I$5:$I$54,MATCH(H7,Services!$B$5:$B$54,0)),0)=0,HolidaySurcharge,IFERROR(INDEX(Services!$I$5:$I$54,MATCH(H7,Services!$B$5:$B$54,0)),0))) -> 0 | S7: =IF(H7="","",IF(IFERROR(INDEX(Services!$J$5:$J$54,MATCH(H7,Services!$B$5:$B$54,0)),0)=0,WeekendSurcharge,IFERROR(INDEX(Services!$J$5:$J$54,MATCH(H7,Services!$B$5:$B$54,0)),0))) -> 0 | T7: =IF(H7="","",IFERROR(INDEX(Services!$K$5:$K$54,MATCH(H7,Services!$B$5:$B$54,0)),"No")) -> 0 | U7: =IF(H7="","",ROUND(IF(O7="Per hour",P7*IF(M7="",IF(N7="",1,N7),M7),P7*IF(N7="",1,N7)),2)) -> 0 | V7: =IF(H7="","",ROUND(MAX(0,IF(G7="",1,G7)-1)*Q7,2)) -> 0 | W7: =IF(I7="","",IF(COUNTIF(HolidayDates,I7)>0,"Yes","No")) -> 0 | X7: =IF(I7="","",IF(WEEKDAY(I7,2)>5,"Yes","No")) -> 0 | Y7: =IF(H7="","",ROUND((U7+V7)*(IF(W7="Yes",R7,0)+IF(X7="Yes",S7,0)),2)) -> 0 | AA7: =IF(H7="","",IF(T7<>"Yes",0,ROUND(MAX(0,IF(Z7="",0,Z7)-FreeTravelDistance)*TravelFeeRate,2))) -> 0 | AB7: =IF(I7="","",TravelTimeMins) -> 0 | AC7: =IF(OR(I7="",B7=""),0,IF(I7-B7<=LastMinuteDays,EmergencyFee,0)) -> 0 | AF7: =IF(H7="","",ROUND((U7+V7+Y7+AA7+AC7)*IF(AE7="",0,AE7),2)) -> 0 | AI7: =IF(H7="","",IF(AG7<>"",AG7,ROUND(U7+V7+Y7+AA7+AC7-AF7,2))) -> 0 | AJ7: =IF(AI7="","",IF(TaxRegistered<>"Yes",0,IF(PricesIncludeTax="Yes",ROUND(AI7-AI7/(1+TaxRate),2),ROUND(AI7*TaxRate,2)))) -> 0 | AK7: =IF(AI7="","",IF(PricesIncludeTax="Yes",AI7,ROUND(AI7+AJ7,2))) -> 0 | AQ7: =IF(OR(I7="",AP7="",AP7="None"),"",IF(AP7="Monthly",EDATE(I7,1),I7+IF(AP7="Daily",1,IF(AP7="Weekdays",IF(WEEKDAY(I7,2)>=5,8-WEEKDAY(I7,2),1),IF(AP7="Weekly",7,IF(AP7="Fortnightly",14,0)))))) -> 0 | AR7: =IF(OR(I7="",AL7="",K7="",L7=""),"",IF(SUMPRODUCT((Bookings!$AL$5:$AL$404=AL7)*(Bookings!$I$5:$I$404=I7)*(Bookings!$K$5:$K$404<L7)*(Bookings!$L$5:$L$404>K7)*(Bookings!$AM$5:$AM$404<>"Cancelled"))>1,"Conflict - double booked","OK")) -> 0 | AS7: =IF(A7="","",IF(COUNTIF('Visit Log'!$B$5:$B$404,A7)>0,"Yes","No")) -> 0 | AT7: =IF(A7="","",IFERROR(INDEX(Invoices!$A$5:$A$304,MATCH(A7,Invoices!$E$5:$E$304,0)),"")) -> 0 | AU7: =IF(A7="","",IF(AT7="","Not invoiced",IFERROR(INDEX(Invoices!$U$5:$U$304,MATCH(AT7,Invoices!$A$5:$A$304,0)),""))) -> 0 | AY7: =IF(I7="","",TEXT(I7,"yyyy-mm")) -> 0 | AZ7: =IF(I7="","",IF(AM7="Cancelled","Cancelled",IF(AND(I7<TODAY(),OR(AM7="Pending",AM7="Confirmed",AM7="Enquiry")),"Overdue - update status",IF(AND(AM7="Completed",AS7="No"),"Action - log the visit",IF(I7=TODAY(),"Today",IF(AND(I7>TODAY(),I7-TODAY()<=ReminderLeadDays,AN7<>"Yes"),"Action - unconfirmed",IF(AND(I7>TODAY(),I7-TODAY()<=ReminderLeadDays),"Upcoming","OK"))))))) -> 0
A8: =IF(C8="","",BookingPrefix&TEXT(ROW()-4,"0000")) -> 0 | D8: =IF(C8="","",IFERROR(INDEX(Clients!$A$5:$A$254,MATCH(C8,Clients!$B$5:$B$254,0)),"")) -> 0 | J8: =IF(I8="","",TEXT(I8,"ddd")) -> 0 | M8: =IF(OR(K8="",L8=""),"",ROUND((L8-K8+IF(L8<K8,1,0))*24,2)) -> 0 | O8: =IF(H8="","",IFERROR(INDEX(Services!$E$5:$E$54,MATCH(H8,Services!$B$5:$B$54,0)),"")) -> 0 | P8: =IF(H8="","",IFERROR(INDEX(Services!$G$5:$G$54,MATCH(H8,Services!$B$5:$B$54,0)),0)) -> 0 | Q8: =IF(H8="","",IF(IFERROR(INDEX(Services!$H$5:$H$54,MATCH(H8,Services!$B$5:$B$54,0)),0)=0,ExtraPetFeeDefault,IFERROR(INDEX(Services!$H$5:$H$54,MATCH(H8,Services!$B$5:$B$54,0)),0))) -> 0 | R8: =IF(H8="","",IF(IFERROR(INDEX(Services!$I$5:$I$54,MATCH(H8,Services!$B$5:$B$54,0)),0)=0,HolidaySurcharge,IFERROR(INDEX(Services!$I$5:$I$54,MATCH(H8,Services!$B$5:$B$54,0)),0))) -> 0 | S8: =IF(H8="","",IF(IFERROR(INDEX(Services!$J$5:$J$54,MATCH(H8,Services!$B$5:$B$54,0)),0)=0,WeekendSurcharge,IFERROR(INDEX(Services!$J$5:$J$54,MATCH(H8,Services!$B$5:$B$54,0)),0))) -> 0 | T8: =IF(H8="","",IFERROR(INDEX(Services!$K$5:$K$54,MATCH(H8,Services!$B$5:$B$54,0)),"No")) -> 0 | U8: =IF(H8="","",ROUND(IF(O8="Per hour",P8*IF(M8="",IF(N8="",1,N8),M8),P8*IF(N8="",1,N8)),2)) -> 0 | V8: =IF(H8="","",ROUND(MAX(0,IF(G8="",1,G8)-1)*Q8,2)) -> 0 | W8: =IF(I8="","",IF(COUNTIF(HolidayDates,I8)>0,"Yes","No")) -> 0 | X8: =IF(I8="","",IF(WEEKDAY(I8,2)>5,"Yes","No")) -> 0 | Y8: =IF(H8="","",ROUND((U8+V8)*(IF(W8="Yes",R8,0)+IF(X8="Yes",S8,0)),2)) -> 0 | AA8: =IF(H8="","",IF(T8<>"Yes",0,ROUND(MAX(0,IF(Z8="",0,Z8)-FreeTravelDistance)*TravelFeeRate,2))) -> 0 | AB8: =IF(I8="","",TravelTimeMins) -> 0 | AC8: =IF(OR(I8="",B8=""),0,IF(I8-B8<=LastMinuteDays,EmergencyFee,0)) -> 0 | AF8: =IF(H8="","",ROUND((U8+V8+Y8+AA8+AC8)*IF(AE8="",0,AE8),2)) -> 0 | AI8: =IF(H8="","",IF(AG8<>"",AG8,ROUND(U8+V8+Y8+AA8+AC8-AF8,2))) -> 0 | AJ8: =IF(AI8="","",IF(TaxRegistered<>"Yes",0,IF(PricesIncludeTax="Yes",ROUND(AI8-AI8/(1+TaxRate),2),ROUND(AI8*TaxRate,2)))) -> 0 | AK8: =IF(AI8="","",IF(PricesIncludeTax="Yes",AI8,ROUND(AI8+AJ8,2))) -> 0 | AQ8: =IF(OR(I8="",AP8="",AP8="None"),"",IF(AP8="Monthly",EDATE(I8,1),I8+IF(AP8="Daily",1,IF(AP8="Weekdays",IF(WEEKDAY(I8,2)>=5,8-WEEKDAY(I8,2),1),IF(AP8="Weekly",7,IF(AP8="Fortnightly",14,0)))))) -> 0 | AR8: =IF(OR(I8="",AL8="",K8="",L8=""),"",IF(SUMPRODUCT((Bookings!$AL$5:$AL$404=AL8)*(Bookings!$I$5:$I$404=I8)*(Bookings!$K$5:$K$404<L8)*(Bookings!$L$5:$L$404>K8)*(Bookings!$AM$5:$AM$404<>"Cancelled"))>1,"Conflict - double booked","OK")) -> 0 | AS8: =IF(A8="","",IF(COUNTIF('Visit Log'!$B$5:$B$404,A8)>0,"Yes","No")) -> 0 | AT8: =IF(A8="","",IFERROR(INDEX(Invoices!$A$5:$A$304,MATCH(A8,Invoices!$E$5:$E$304,0)),"")) -> 0 | AU8: =IF(A8="","",IF(AT8="","Not invoiced",IFERROR(INDEX(Invoices!$U$5:$U$304,MATCH(AT8,Invoices!$A$5:$A$304,0)),""))) -> 0 | AY8: =IF(I8="","",TEXT(I8,"yyyy-mm")) -> 0 | AZ8: =IF(I8="","",IF(AM8="Cancelled","Cancelled",IF(AND(I8<TODAY(),OR(AM8="Pending",AM8="Confirmed",AM8="Enquiry")),"Overdue - update status",IF(AND(AM8="Completed",AS8="No"),"Action - log the visit",IF(I8=TODAY(),"Today",IF(AND(I8>TODAY(),I8-TODAY()<=ReminderLeadDays,AN8<>"Yes"),"Action - unconfirmed",IF(AND(I8>TODAY(),I8-TODAY()<=ReminderLeadDays),"Upcoming","OK"))))))) -> 0
A9: =IF(C9="","",BookingPrefix&TEXT(ROW()-4,"0000")) -> 0 | D9: =IF(C9="","",IFERROR(INDEX(Clients!$A$5:$A$254,MATCH(C9,Clients!$B$5:$B$254,0)),"")) -> 0 | J9: =IF(I9="","",TEXT(I9,"ddd")) -> 0 | M9: =IF(OR(K9="",L9=""),"",ROUND((L9-K9+IF(L9<K9,1,0))*24,2)) -> 0 | O9: =IF(H9="","",IFERROR(INDEX(Services!$E$5:$E$54,MATCH(H9,Services!$B$5:$B$54,0)),"")) -> 0 | P9: =IF(H9="","",IFERROR(INDEX(Services!$G$5:$G$54,MATCH(H9,Services!$B$5:$B$54,0)),0)) -> 0 | Q9: =IF(H9="","",IF(IFERROR(INDEX(Services!$H$5:$H$54,MATCH(H9,Services!$B$5:$B$54,0)),0)=0,ExtraPetFeeDefault,IFERROR(INDEX(Services!$H$5:$H$54,MATCH(H9,Services!$B$5:$B$54,0)),0))) -> 0 | R9: =IF(H9="","",IF(IFERROR(INDEX(Services!$I$5:$I$54,MATCH(H9,Services!$B$5:$B$54,0)),0)=0,HolidaySurcharge,IFERROR(INDEX(Services!$I$5:$I$54,MATCH(H9,Services!$B$5:$B$54,0)),0))) -> 0 | S9: =IF(H9="","",IF(IFERROR(INDEX(Services!$J$5:$J$54,MATCH(H9,Services!$B$5:$B$54,0)),0)=0,WeekendSurcharge,IFERROR(INDEX(Services!$J$5:$J$54,MATCH(H9,Services!$B$5:$B$54,0)),0))) -> 0 | T9: =IF(H9="","",IFERROR(INDEX(Services!$K$5:$K$54,MATCH(H9,Services!$B$5:$B$54,0)),"No")) -> 0 | U9: =IF(H9="","",ROUND(IF(O9="Per hour",P9*IF(M9="",IF(N9="",1,N9),M9),P9*IF(N9="",1,N9)),2)) -> 0 | V9: =IF(H9="","",ROUND(MAX(0,IF(G9="",1,G9)-1)*Q9,2)) -> 0 | W9: =IF(I9="","",IF(COUNTIF(HolidayDates,I9)>0,"Yes","No")) -> 0 | X9: =IF(I9="","",IF(WEEKDAY(I9,2)>5,"Yes","No")) -> 0 | Y9: =IF(H9="","",ROUND((U9+V9)*(IF(W9="Yes",R9,0)+IF(X9="Yes",S9,0)),2)) -> 0 | AA9: =IF(H9="","",IF(T9<>"Yes",0,ROUND(MAX(0,IF(Z9="",0,Z9)-FreeTravelDistance)*TravelFeeRate,2))) -> 0 | AB9: =IF(I9="","",TravelTimeMins) -> 0 | AC9: =IF(OR(I9="",B9=""),0,IF(I9-B9<=LastMinuteDays,EmergencyFee,0)) -> 0 | AF9: =IF(H9="","",ROUND((U9+V9+Y9+AA9+AC9)*IF(AE9="",0,AE9),2)) -> 0 | AI9: =IF(H9="","",IF(AG9<>"",AG9,ROUND(U9+V9+Y9+AA9+AC9-AF9,2))) -> 0 | AJ9: =IF(AI9="","",IF(TaxRegistered<>"Yes",0,IF(PricesIncludeTax="Yes",ROUND(AI9-AI9/(1+TaxRate),2),ROUND(AI9*TaxRate,2)))) -> 0 | AK9: =IF(AI9="","",IF(PricesIncludeTax="Yes",AI9,ROUND(AI9+AJ9,2))) -> 0 | AQ9: =IF(OR(I9="",AP9="",AP9="None"),"",IF(AP9="Monthly",EDATE(I9,1),I9+IF(AP9="Daily",1,IF(AP9="Weekdays",IF(WEEKDAY(I9,2)>=5,8-WEEKDAY(I9,2),1),IF(AP9="Weekly",7,IF(AP9="Fortnightly",14,0)))))) -> 0 | AR9: =IF(OR(I9="",AL9="",K9="",L9=""),"",IF(SUMPRODUCT((Bookings!$AL$5:$AL$404=AL9)*(Bookings!$I$5:$I$404=I9)*(Bookings!$K$5:$K$404<L9)*(Bookings!$L$5:$L$404>K9)*(Bookings!$AM$5:$AM$404<>"Cancelled"))>1,"Conflict - double booked","OK")) -> 0 | AS9: =IF(A9="","",IF(COUNTIF('Visit Log'!$B$5:$B$404,A9)>0,"Yes","No")) -> 0 | AT9: =IF(A9="","",IFERROR(INDEX(Invoices!$A$5:$A$304,MATCH(A9,Invoices!$E$5:$E$304,0)),"")) -> 0 | AU9: =IF(A9="","",IF(AT9="","Not invoiced",IFERROR(INDEX(Invoices!$U$5:$U$304,MATCH(AT9,Invoices!$A$5:$A$304,0)),""))) -> 0 | AY9: =IF(I9="","",TEXT(I9,"yyyy-mm")) -> 0 | AZ9: =IF(I9="","",IF(AM9="Cancelled","Cancelled",IF(AND(I9<TODAY(),OR(AM9="Pending",AM9="Confirmed",AM9="Enquiry")),"Overdue - update status",IF(AND(AM9="Completed",AS9="No"),"Action - log the visit",IF(I9=TODAY(),"Today",IF(AND(I9>TODAY(),I9-TODAY()<=ReminderLeadDays,AN9<>"Yes"),"Action - unconfirmed",IF(AND(I9>TODAY(),I9-TODAY()<=ReminderLeadDays),"Upcoming","OK"))))))) -> 0
A10: =IF(C10="","",BookingPrefix&TEXT(ROW()-4,"0000")) -> 0 | D10: =IF(C10="","",IFERROR(INDEX(Clients!$A$5:$A$254,MATCH(C10,Clients!$B$5:$B$254,0)),"")) -> 0 | J10: =IF(I10="","",TEXT(I10,"ddd")) -> 0 | M10: =IF(OR(K10="",L10=""),"",ROUND((L10-K10+IF(L10<K10,1,0))*24,2)) -> 0 | O10: =IF(H10="","",IFERROR(INDEX(Services!$E$5:$E$54,MATCH(H10,Services!$B$5:$B$54,0)),"")) -> 0 | P10: =IF(H10="","",IFERROR(INDEX(Services!$G$5:$G$54,MATCH(H10,Services!$B$5:$B$54,0)),0)) -> 0 | Q10: =IF(H10="","",IF(IFERROR(INDEX(Services!$H$5:$H$54,MATCH(H10,Services!$B$5:$B$54,0)),0)=0,ExtraPetFeeDefault,IFERROR(INDEX(Services!$H$5:$H$54,MATCH(H10,Services!$B$5:$B$54,0)),0))) -> 0 | R10: =IF(H10="","",IF(IFERROR(INDEX(Services!$I$5:$I$54,MATCH(H10,Services!$B$5:$B$54,0)),0)=0,HolidaySurcharge,IFERROR(INDEX(Services!$I$5:$I$54,MATCH(H10,Services!$B$5:$B$54,0)),0))) -> 0 | S10: =IF(H10="","",IF(IFERROR(INDEX(Services!$J$5:$J$54,MATCH(H10,Services!$B$5:$B$54,0)),0)=0,WeekendSurcharge,IFERROR(INDEX(Services!$J$5:$J$54,MATCH(H10,Services!$B$5:$B$54,0)),0))) -> 0 | T10: =IF(H10="","",IFERROR(INDEX(Services!$K$5:$K$54,MATCH(H10,Services!$B$5:$B$54,0)),"No")) -> 0 | U10: =IF(H10="","",ROUND(IF(O10="Per hour",P10*IF(M10="",IF(N10="",1,N10),M10),P10*IF(N10="",1,N10)),2)) -> 0 | V10: =IF(H10="","",ROUND(MAX(0,IF(G10="",1,G10)-1)*Q10,2)) -> 0 | W10: =IF(I10="","",IF(COUNTIF(HolidayDates,I10)>0,"Yes","No")) -> 0 | X10: =IF(I10="","",IF(WEEKDAY(I10,2)>5,"Yes","No")) -> 0 | Y10: =IF(H10="","",ROUND((U10+V10)*(IF(W10="Yes",R10,0)+IF(X10="Yes",S10,0)),2)) -> 0 | AA10: =IF(H10="","",IF(T10<>"Yes",0,ROUND(MAX(0,IF(Z10="",0,Z10)-FreeTravelDistance)*TravelFeeRate,2))) -> 0 | AB10: =IF(I10="","",TravelTimeMins) -> 0 | AC10: =IF(OR(I10="",B10=""),0,IF(I10-B10<=LastMinuteDays,EmergencyFee,0)) -> 0 | AF10: =IF(H10="","",ROUND((U10+V10+Y10+AA10+AC10)*IF(AE10="",0,AE10),2)) -> 0 | AI10: =IF(H10="","",IF(AG10<>"",AG10,ROUND(U10+V10+Y10+AA10+AC10-AF10,2))) -> 0 | AJ10: =IF(AI10="","",IF(TaxRegistered<>"Yes",0,IF(PricesIncludeTax="Yes",ROUND(AI10-AI10/(1+TaxRate),2),ROUND(AI10*TaxRate,2)))) -> 0 | AK10: =IF(AI10="","",IF(PricesIncludeTax="Yes",AI10,ROUND(AI10+AJ10,2))) -> 0 | AQ10: =IF(OR(I10="",AP10="",AP10="None"),"",IF(AP10="Monthly",EDATE(I10,1),I10+IF(AP10="Daily",1,IF(AP10="Weekdays",IF(WEEKDAY(I10,2)>=5,8-WEEKDAY(I10,2),1),IF(AP10="Weekly",7,IF(AP10="Fortnightly",14,0)))))) -> 0 | AR10: =IF(OR(I10="",AL10="",K10="",L10=""),"",IF(SUMPRODUCT((Bookings!$AL$5:$AL$404=AL10)*(Bookings!$I$5:$I$404=I10)*(Bookings!$K$5:$K$404<L10)*(Bookings!$L$5:$L$404>K10)*(Bookings!$AM$5:$AM$404<>"Cancelled"))>1,"Conflict - double booked","OK")) -> 0 | AS10: =IF(A10="","",IF(COUNTIF('Visit Log'!$B$5:$B$404,A10)>0,"Yes","No")) -> 0 | AT10: =IF(A10="","",IFERROR(INDEX(Invoices!$A$5:$A$304,MATCH(A10,Invoices!$E$5:$E$304,0)),"")) -> 0 | AU10: =IF(A10="","",IF(AT10="","Not invoiced",IFERROR(INDEX(Invoices!$U$5:$U$304,MATCH(AT10,Invoices!$A$5:$A$304,0)),""))) -> 0 | AY10: =IF(I10="","",TEXT(I10,"yyyy-mm")) -> 0 | AZ10: =IF(I10="","",IF(AM10="Cancelled","Cancelled",IF(AND(I10<TODAY(),OR(AM10="Pending",AM10="Confirmed",AM10="Enquiry")),"Overdue - update status",IF(AND(AM10="Completed",AS10="No"),"Action - log the visit",IF(I10=TODAY(),"Today",IF(AND(I10>TODAY(),I10-TODAY()<=ReminderLeadDays,AN10<>"Yes"),"Action - unconfirmed",IF(AND(I10>TODAY(),I10-TODAY()<=ReminderLeadDays),"Upcoming","OK"))))))) -> 0
A11: =IF(C11="","",BookingPrefix&TEXT(ROW()-4,"0000")) -> 0 | D11: =IF(C11="","",IFERROR(INDEX(Clients!$A$5:$A$254,MATCH(C11,Clients!$B$5:$B$254,0)),"")) -> 0 | J11: =IF(I11="","",TEXT(I11,"ddd")) -> 0 | M11: =IF(OR(K11="",L11=""),"",ROUND((L11-K11+IF(L11<K11,1,0))*24,2)) -> 0 | O11: =IF(H11="","",IFERROR(INDEX(Services!$E$5:$E$54,MATCH(H11,Services!$B$5:$B$54,0)),"")) -> 0 | P11: =IF(H11="","",IFERROR(INDEX(Services!$G$5:$G$54,MATCH(H11,Services!$B$5:$B$54,0)),0)) -> 0 | Q11: =IF(H11="","",IF(IFERROR(INDEX(Services!$H$5:$H$54,MATCH(H11,Services!$B$5:$B$54,0)),0)=0,ExtraPetFeeDefault,IFERROR(INDEX(Services!$H$5:$H$54,MATCH(H11,Services!$B$5:$B$54,0)),0))) -> 0 | R11: =IF(H11="","",IF(IFERROR(INDEX(Services!$I$5:$I$54,MATCH(H11,Services!$B$5:$B$54,0)),0)=0,HolidaySurcharge,IFERROR(INDEX(Services!$I$5:$I$54,MATCH(H11,Services!$B$5:$B$54,0)),0))) -> 0 | S11: =IF(H11="","",IF(IFERROR(INDEX(Services!$J$5:$J$54,MATCH(H11,Services!$B$5:$B$54,0)),0)=0,WeekendSurcharge,IFERROR(INDEX(Services!$J$5:$J$54,MATCH(H11,Services!$B$5:$B$54,0)),0))) -> 0 | T11: =IF(H11="","",IFERROR(INDEX(Services!$K$5:$K$54,MATCH(H11,Services!$B$5:$B$54,0)),"No")) -> 0 | U11: =IF(H11="","",ROUND(IF(O11="Per hour",P11*IF(M11="",IF(N11="",1,N11),M11),P11*IF(N11="",1,N11)),2)) -> 0 | V11: =IF(H11="","",ROUND(MAX(0,IF(G11="",1,G11)-1)*Q11,2)) -> 0 | W11: =IF(I11="","",IF(COUNTIF(HolidayDates,I11)>0,"Yes","No")) -> 0 | X11: =IF(I11="","",IF(WEEKDAY(I11,2)>5,"Yes","No")) -> 0 | Y11: =IF(H11="","",ROUND((U11+V11)*(IF(W11="Yes",R11,0)+IF(X11="Yes",S11,0)),2)) -> 0 | AA11: =IF(H11="","",IF(T11<>"Yes",0,ROUND(MAX(0,IF(Z11="",0,Z11)-FreeTravelDistance)*TravelFeeRate,2))) -> 0 | AB11: =IF(I11="","",TravelTimeMins) -> 0 | AC11: =IF(OR(I11="",B11=""),0,IF(I11-B11<=LastMinuteDays,EmergencyFee,0)) -> 0 | AF11: =IF(H11="","",ROUND((U11+V11+Y11+AA11+AC11)*IF(AE11="",0,AE11),2)) -> 0 | AI11: =IF(H11="","",IF(AG11<>"",AG11,ROUND(U11+V11+Y11+AA11+AC11-AF11,2))) -> 0 | AJ11: =IF(AI11="","",IF(TaxRegistered<>"Yes",0,IF(PricesIncludeTax="Yes",ROUND(AI11-AI11/(1+TaxRate),2),ROUND(AI11*TaxRate,2)))) -> 0 | AK11: =IF(AI11="","",IF(PricesIncludeTax="Yes",AI11,ROUND(AI11+AJ11,2))) -> 0 | AQ11: =IF(OR(I11="",AP11="",AP11="None"),"",IF(AP11="Monthly",EDATE(I11,1),I11+IF(AP11="Daily",1,IF(AP11="Weekdays",IF(WEEKDAY(I11,2)>=5,8-WEEKDAY(I11,2),1),IF(AP11="Weekly",7,IF(AP11="Fortnightly",14,0)))))) -> 0 | AR11: =IF(OR(I11="",AL11="",K11="",L11=""),"",IF(SUMPRODUCT((Bookings!$AL$5:$AL$404=AL11)*(Bookings!$I$5:$I$404=I11)*(Bookings!$K$5:$K$404<L11)*(Bookings!$L$5:$L$404>K11)*(Bookings!$AM$5:$AM$404<>"Cancelled"))>1,"Conflict - double booked","OK")) -> 0 | AS11: =IF(A11="","",IF(COUNTIF('Visit Log'!$B$5:$B$404,A11)>0,"Yes","No")) -> 0 | AT11: =IF(A11="","",IFERROR(INDEX(Invoices!$A$5:$A$304,MATCH(A11,Invoices!$E$5:$E$304,0)),"")) -> 0 | AU11: =IF(A11="","",IF(AT11="","Not invoiced",IFERROR(INDEX(Invoices!$U$5:$U$304,MATCH(AT11,Invoices!$A$5:$A$304,0)),""))) -> 0 | AY11: =IF(I11="","",TEXT(I11,"yyyy-mm")) -> 0 | AZ11: =IF(I11="","",IF(AM11="Cancelled","Cancelled",IF(AND(I11<TODAY(),OR(AM11="Pending",AM11="Confirmed",AM11="Enquiry")),"Overdue - update status",IF(AND(AM11="Completed",AS11="No"),"Action - log the visit",IF(I11=TODAY(),"Today",IF(AND(I11>TODAY(),I11-TODAY()<=ReminderLeadDays,AN11<>"Yes"),"Action - unconfirmed",IF(AND(I11>TODAY(),I11-TODAY()<=ReminderLeadDays),"Upcoming","OK"))))))) -> 0
A12: =IF(C12="","",BookingPrefix&TEXT(ROW()-4,"0000")) -> 0 | D12: =IF(C12="","",IFERROR(INDEX(Clients!$A$5:$A$254,MATCH(C12,Clients!$B$5:$B$254,0)),"")) -> 0 | J12: =IF(I12="","",TEXT(I12,"ddd")) -> 0 | M12: =IF(OR(K12="",L12=""),"",ROUND((L12-K12+IF(L12<K12,1,0))*24,2)) -> 0 | O12: =IF(H12="","",IFERROR(INDEX(Services!$E$5:$E$54,MATCH(H12,Services!$B$5:$B$54,0)),"")) -> 0 | P12: =IF(H12="","",IFERROR(INDEX(Services!$G$5:$G$54,MATCH(H12,Services!$B$5:$B$54,0)),0)) -> 0 | Q12: =IF(H12="","",IF(IFERROR(INDEX(Services!$H$5:$H$54,MATCH(H12,Services!$B$5:$B$54,0)),0)=0,ExtraPetFeeDefault,IFERROR(INDEX(Services!$H$5:$H$54,MATCH(H12,Services!$B$5:$B$54,0)),0))) -> 0 | R12: =IF(H12="","",IF(IFERROR(INDEX(Services!$I$5:$I$54,MATCH(H12,Services!$B$5:$B$54,0)),0)=0,HolidaySurcharge,IFERROR(INDEX(Services!$I$5:$I$54,MATCH(H12,Services!$B$5:$B$54,0)),0))) -> 0 | S12: =IF(H12="","",IF(IFERROR(INDEX(Services!$J$5:$J$54,MATCH(H12,Services!$B$5:$B$54,0)),0)=0,WeekendSurcharge,IFERROR(INDEX(Services!$J$5:$J$54,MATCH(H12,Services!$B$5:$B$54,0)),0))) -> 0 | T12: =IF(H12="","",IFERROR(INDEX(Services!$K$5:$K$54,MATCH(H12,Services!$B$5:$B$54,0)),"No")) -> 0 | U12: =IF(H12="","",ROUND(IF(O12="Per hour",P12*IF(M12="",IF(N12="",1,N12),M12),P12*IF(N12="",1,N12)),2)) -> 0 | V12: =IF(H12="","",ROUND(MAX(0,IF(G12="",1,G12)-1)*Q12,2)) -> 0 | W12: =IF(I12="","",IF(COUNTIF(HolidayDates,I12)>0,"Yes","No")) -> 0 | X12: =IF(I12="","",IF(WEEKDAY(I12,2)>5,"Yes","No")) -> 0 | Y12: =IF(H12="","",ROUND((U12+V12)*(IF(W12="Yes",R12,0)+IF(X12="Yes",S12,0)),2)) -> 0 | AA12: =IF(H12="","",IF(T12<>"Yes",0,ROUND(MAX(0,IF(Z12="",0,Z12)-FreeTravelDistance)*TravelFeeRate,2))) -> 0 | AB12: =IF(I12="","",TravelTimeMins) -> 0 | AC12: =IF(OR(I12="",B12=""),0,IF(I12-B12<=LastMinuteDays,EmergencyFee,0)) -> 0 | AF12: =IF(H12="","",ROUND((U12+V12+Y12+AA12+AC12)*IF(AE12="",0,AE12),2)) -> 0 | AI12: =IF(H12="","",IF(AG12<>"",AG12,ROUND(U12+V12+Y12+AA12+AC12-AF12,2))) -> 0 | AJ12: =IF(AI12="","",IF(TaxRegistered<>"Yes",0,IF(PricesIncludeTax="Yes",ROUND(AI12-AI12/(1+TaxRate),2),ROUND(AI12*TaxRate,2)))) -> 0 | AK12: =IF(AI12="","",IF(PricesIncludeTax="Yes",AI12,ROUND(AI12+AJ12,2))) -> 0 | AQ12: =IF(OR(I12="",AP12="",AP12="None"),"",IF(AP12="Monthly",EDATE(I12,1),I12+IF(AP12="Daily",1,IF(AP12="Weekdays",IF(WEEKDAY(I12,2)>=5,8-WEEKDAY(I12,2),1),IF(AP12="Weekly",7,IF(AP12="Fortnightly",14,0)))))) -> 0 | AR12: =IF(OR(I12="",AL12="",K12="",L12=""),"",IF(SUMPRODUCT((Bookings!$AL$5:$AL$404=AL12)*(Bookings!$I$5:$I$404=I12)*(Bookings!$K$5:$K$404<L12)*(Bookings!$L$5:$L$404>K12)*(Bookings!$AM$5:$AM$404<>"Cancelled"))>1,"Conflict - double booked","OK")) -> 0 | AS12: =IF(A12="","",IF(COUNTIF('Visit Log'!$B$5:$B$404,A12)>0,"Yes","No")) -> 0 | AT12: =IF(A12="","",IFERROR(INDEX(Invoices!$A$5:$A$304,MATCH(A12,Invoices!$E$5:$E$304,0)),"")) -> 0 | AU12: =IF(A12="","",IF(AT12="","Not invoiced",IFERROR(INDEX(Invoices!$U$5:$U$304,MATCH(AT12,Invoices!$A$5:$A$304,0)),""))) -> 0 | AY12: =IF(I12="","",TEXT(I12,"yyyy-mm")) -> 0 | AZ12: =IF(I12="","",IF(AM12="Cancelled","Cancelled",IF(AND(I12<TODAY(),OR(AM12="Pending",AM12="Confirmed",AM12="Enquiry")),"Overdue - update status",IF(AND(AM12="Completed",AS12="No"),"Action - log the visit",IF(I12=TODAY(),"Today",IF(AND(I12>TODAY(),I12-TODAY()<=ReminderLeadDays,AN12<>"Yes"),"Action - unconfirmed",IF(AND(I12>TODAY(),I12-TODAY()<=ReminderLeadDays),"Upcoming","OK"))))))) -> 0
A13: =IF(C13="","",BookingPrefix&TEXT(ROW()-4,"0000")) -> 0 | D13: =IF(C13="","",IFERROR(INDEX(Clients!$A$5:$A$254,MATCH(C13,Clients!$B$5:$B$254,0)),"")) -> 0 | J13: =IF(I13="","",TEXT(I13,"ddd")) -> 0 | M13: =IF(OR(K13="",L13=""),"",ROUND((L13-K13+IF(L13<K13,1,0))*24,2)) -> 0 | O13: =IF(H13="","",IFERROR(INDEX(Services!$E$5:$E$54,MATCH(H13,Services!$B$5:$B$54,0)),"")) -> 0 | P13: =IF(H13="","",IFERROR(INDEX(Services!$G$5:$G$54,MATCH(H13,Services!$B$5:$B$54,0)),0)) -> 0 | Q13: =IF(H13="","",IF(IFERROR(INDEX(Services!$H$5:$H$54,MATCH(H13,Services!$B$5:$B$54,0)),0)=0,ExtraPetFeeDefault,IFERROR(INDEX(Services!$H$5:$H$54,MATCH(H13,Services!$B$5:$B$54,0)),0))) -> 0 | R13: =IF(H13="","",IF(IFERROR(INDEX(Services!$I$5:$I$54,MATCH(H13,Services!$B$5:$B$54,0)),0)=0,HolidaySurcharge,IFERROR(INDEX(Services!$I$5:$I$54,MATCH(H13,Services!$B$5:$B$54,0)),0))) -> 0 | S13: =IF(H13="","",IF(IFERROR(INDEX(Services!$J$5:$J$54,MATCH(H13,Services!$B$5:$B$54,0)),0)=0,WeekendSurcharge,IFERROR(INDEX(Services!$J$5:$J$54,MATCH(H13,Services!$B$5:$B$54,0)),0))) -> 0 | T13: =IF(H13="","",IFERROR(INDEX(Services!$K$5:$K$54,MATCH(H13,Services!$B$5:$B$54,0)),"No")) -> 0 | U13: =IF(H13="","",ROUND(IF(O13="Per hour",P13*IF(M13="",IF(N13="",1,N13),M13),P13*IF(N13="",1,N13)),2)) -> 0 | V13: =IF(H13="","",ROUND(MAX(0,IF(G13="",1,G13)-1)*Q13,2)) -> 0 | W13: =IF(I13="","",IF(COUNTIF(HolidayDates,I13)>0,"Yes","No")) -> 0 | X13: =IF(I13="","",IF(WEEKDAY(I13,2)>5,"Yes","No")) -> 0 | Y13: =IF(H13="","",ROUND((U13+V13)*(IF(W13="Yes",R13,0)+IF(X13="Yes",S13,0)),2)) -> 0 | AA13: =IF(H13="","",IF(T13<>"Yes",0,ROUND(MAX(0,IF(Z13="",0,Z13)-FreeTravelDistance)*TravelFeeRate,2))) -> 0 | AB13: =IF(I13="","",TravelTimeMins) -> 0 | AC13: =IF(OR(I13="",B13=""),0,IF(I13-B13<=LastMinuteDays,EmergencyFee,0)) -> 0 | AF13: =IF(H13="","",ROUND((U13+V13+Y13+AA13+AC13)*IF(AE13="",0,AE13),2)) -> 0 | AI13: =IF(H13="","",IF(AG13<>"",AG13,ROUND(U13+V13+Y13+AA13+AC13-AF13,2))) -> 0 | AJ13: =IF(AI13="","",IF(TaxRegistered<>"Yes",0,IF(PricesIncludeTax="Yes",ROUND(AI13-AI13/(1+TaxRate),2),ROUND(AI13*TaxRate,2)))) -> 0 | AK13: =IF(AI13="","",IF(PricesIncludeTax="Yes",AI13,ROUND(AI13+AJ13,2))) -> 0 | AQ13: =IF(OR(I13="",AP13="",AP13="None"),"",IF(AP13="Monthly",EDATE(I13,1),I13+IF(AP13="Daily",1,IF(AP13="Weekdays",IF(WEEKDAY(I13,2)>=5,8-WEEKDAY(I13,2),1),IF(AP13="Weekly",7,IF(AP13="Fortnightly",14,0)))))) -> 0 | AR13: =IF(OR(I13="",AL13="",K13="",L13=""),"",IF(SUMPRODUCT((Bookings!$AL$5:$AL$404=AL13)*(Bookings!$I$5:$I$404=I13)*(Bookings!$K$5:$K$404<L13)*(Bookings!$L$5:$L$404>K13)*(Bookings!$AM$5:$AM$404<>"Cancelled"))>1,"Conflict - double booked","OK")) -> 0 | AS13: =IF(A13="","",IF(COUNTIF('Visit Log'!$B$5:$B$404,A13)>0,"Yes","No")) -> 0 | AT13: =IF(A13="","",IFERROR(INDEX(Invoices!$A$5:$A$304,MATCH(A13,Invoices!$E$5:$E$304,0)),"")) -> 0 | AU13: =IF(A13="","",IF(AT13="","Not invoiced",IFERROR(INDEX(Invoices!$U$5:$U$304,MATCH(AT13,Invoices!$A$5:$A$304,0)),""))) -> 0 | AY13: =IF(I13="","",TEXT(I13,"yyyy-mm")) -> 0 | AZ13: =IF(I13="","",IF(AM13="Cancelled","Cancelled",IF(AND(I13<TODAY(),OR(AM13="Pending",AM13="Confirmed",AM13="Enquiry")),"Overdue - update status",IF(AND(AM13="Completed",AS13="No"),"Action - log the visit",IF(I13=TODAY(),"Today",IF(AND(I13>TODAY(),I13-TODAY()<=ReminderLeadDays,AN13<>"Yes"),"Action - unconfirmed",IF(AND(I13>TODAY(),I13-TODAY()<=ReminderLeadDays),"Upcoming","OK"))))))) -> 0
A14: =IF(C14="","",BookingPrefix&TEXT(ROW()-4,"0000")) -> 0 | D14: =IF(C14="","",IFERROR(INDEX(Clients!$A$5:$A$254,MATCH(C14,Clients!$B$5:$B$254,0)),"")) -> 0 | J14: =IF(I14="","",TEXT(I14,"ddd")) -> 0 | M14: =IF(OR(K14="",L14=""),"",ROUND((L14-K14+IF(L14<K14,1,0))*24,2)) -> 0 | O14: =IF(H14="","",IFERROR(INDEX(Services!$E$5:$E$54,MATCH(H14,Services!$B$5:$B$54,0)),"")) -> 0 | P14: =IF(H14="","",IFERROR(INDEX(Services!$G$5:$G$54,MATCH(H14,Services!$B$5:$B$54,0)),0)) -> 0 | Q14: =IF(H14="","",IF(IFERROR(INDEX(Services!$H$5:$H$54,MATCH(H14,Services!$B$5:$B$54,0)),0)=0,ExtraPetFeeDefault,IFERROR(INDEX(Services!$H$5:$H$54,MATCH(H14,Services!$B$5:$B$54,0)),0))) -> 0 | R14: =IF(H14="","",IF(IFERROR(INDEX(Services!$I$5:$I$54,MATCH(H14,Services!$B$5:$B$54,0)),0)=0,HolidaySurcharge,IFERROR(INDEX(Services!$I$5:$I$54,MATCH(H14,Services!$B$5:$B$54,0)),0))) -> 0 | S14: =IF(H14="","",IF(IFERROR(INDEX(Services!$J$5:$J$54,MATCH(H14,Services!$B$5:$B$54,0)),0)=0,WeekendSurcharge,IFERROR(INDEX(Services!$J$5:$J$54,MATCH(H14,Services!$B$5:$B$54,0)),0))) -> 0 | T14: =IF(H14="","",IFERROR(INDEX(Services!$K$5:$K$54,MATCH(H14,Services!$B$5:$B$54,0)),"No")) -> 0 | U14: =IF(H14="","",ROUND(IF(O14="Per hour",P14*IF(M14="",IF(N14="",1,N14),M14),P14*IF(N14="",1,N14)),2)) -> 0 | V14: =IF(H14="","",ROUND(MAX(0,IF(G14="",1,G14)-1)*Q14,2)) -> 0 | W14: =IF(I14="","",IF(COUNTIF(HolidayDates,I14)>0,"Yes","No")) -> 0 | X14: =IF(I14="","",IF(WEEKDAY(I14,2)>5,"Yes","No")) -> 0 | Y14: =IF(H14="","",ROUND((U14+V14)*(IF(W14="Yes",R14,0)+IF(X14="Yes",S14,0)),2)) -> 0 | AA14: =IF(H14="","",IF(T14<>"Yes",0,ROUND(MAX(0,IF(Z14="",0,Z14)-FreeTravelDistance)*TravelFeeRate,2))) -> 0 | AB14: =IF(I14="","",TravelTimeMins) -> 0 | AC14: =IF(OR(I14="",B14=""),0,IF(I14-B14<=LastMinuteDays,EmergencyFee,0)) -> 0 | AF14: =IF(H14="","",ROUND((U14+V14+Y14+AA14+AC14)*IF(AE14="",0,AE14),2)) -> 0 | AI14: =IF(H14="","",IF(AG14<>"",AG14,ROUND(U14+V14+Y14+AA14+AC14-AF14,2))) -> 0 | AJ14: =IF(AI14="","",IF(TaxRegistered<>"Yes",0,IF(PricesIncludeTax="Yes",ROUND(AI14-AI14/(1+TaxRate),2),ROUND(AI14*TaxRate,2)))) -> 0 | AK14: =IF(AI14="","",IF(PricesIncludeTax="Yes",AI14,ROUND(AI14+AJ14,2))) -> 0 | AQ14: =IF(OR(I14="",AP14="",AP14="None"),"",IF(AP14="Monthly",EDATE(I14,1),I14+IF(AP14="Daily",1,IF(AP14="Weekdays",IF(WEEKDAY(I14,2)>=5,8-WEEKDAY(I14,2),1),IF(AP14="Weekly",7,IF(AP14="Fortnightly",14,0)))))) -> 0 | AR14: =IF(OR(I14="",AL14="",K14="",L14=""),"",IF(SUMPRODUCT((Bookings!$AL$5:$AL$404=AL14)*(Bookings!$I$5:$I$404=I14)*(Bookings!$K$5:$K$404<L14)*(Bookings!$L$5:$L$404>K14)*(Bookings!$AM$5:$AM$404<>"Cancelled"))>1,"Conflict - double booked","OK")) -> 0 | AS14: =IF(A14="","",IF(COUNTIF('Visit Log'!$B$5:$B$404,A14)>0,"Yes","No")) -> 0 | AT14: =IF(A14="","",IFERROR(INDEX(Invoices!$A$5:$A$304,MATCH(A14,Invoices!$E$5:$E$304,0)),"")) -> 0 | AU14: =IF(A14="","",IF(AT14="","Not invoiced",IFERROR(INDEX(Invoices!$U$5:$U$304,MATCH(AT14,Invoices!$A$5:$A$304,0)),""))) -> 0 | AY14: =IF(I14="","",TEXT(I14,"yyyy-mm")) -> 0 | AZ14: =IF(I14="","",IF(AM14="Cancelled","Cancelled",IF(AND(I14<TODAY(),OR(AM14="Pending",AM14="Confirmed",AM14="Enquiry")),"Overdue - update status",IF(AND(AM14="Completed",AS14="No"),"Action - log the visit",IF(I14=TODAY(),"Today",IF(AND(I14>TODAY(),I14-TODAY()<=ReminderLeadDays,AN14<>"Yes"),"Action - unconfirmed",IF(AND(I14>TODAY(),I14-TODAY()<=ReminderLeadDays),"Upcoming","OK"))))))) -> 0
A15: =IF(C15="","",BookingPrefix&TEXT(ROW()-4,"0000")) -> 0 | D15: =IF(C15="","",IFERROR(INDEX(Clients!$A$5:$A$254,MATCH(C15,Clients!$B$5:$B$254,0)),"")) -> 0 | J15: =IF(I15="","",TEXT(I15,"ddd")) -> 0 | M15: =IF(OR(K15="",L15=""),"",ROUND((L15-K15+IF(L15<K15,1,0))*24,2)) -> 0 | O15: =IF(H15="","",IFERROR(INDEX(Services!$E$5:$E$54,MATCH(H15,Services!$B$5:$B$54,0)),"")) -> 0 | P15: =IF(H15="","",IFERROR(INDEX(Services!$G$5:$G$54,MATCH(H15,Services!$B$5:$B$54,0)),0)) -> 0 | Q15: =IF(H15="","",IF(IFERROR(INDEX(Services!$H$5:$H$54,MATCH(H15,Services!$B$5:$B$54,0)),0)=0,ExtraPetFeeDefault,IFERROR(INDEX(Services!$H$5:$H$54,MATCH(H15,Services!$B$5:$B$54,0)),0))) -> 0 | R15: =IF(H15="","",IF(IFERROR(INDEX(Services!$I$5:$I$54,MATCH(H15,Services!$B$5:$B$54,0)),0)=0,HolidaySurcharge,IFERROR(INDEX(Services!$I$5:$I$54,MATCH(H15,Services!$B$5:$B$54,0)),0))) -> 0 | S15: =IF(H15="","",IF(IFERROR(INDEX(Services!$J$5:$J$54,MATCH(H15,Services!$B$5:$B$54,0)),0)=0,WeekendSurcharge,IFERROR(INDEX(Services!$J$5:$J$54,MATCH(H15,Services!$B$5:$B$54,0)),0))) -> 0 | T15: =IF(H15="","",IFERROR(INDEX(Services!$K$5:$K$54,MATCH(H15,Services!$B$5:$B$54,0)),"No")) -> 0 | U15: =IF(H15="","",ROUND(IF(O15="Per hour",P15*IF(M15="",IF(N15="",1,N15),M15),P15*IF(N15="",1,N15)),2)) -> 0 | V15: =IF(H15="","",ROUND(MAX(0,IF(G15="",1,G15)-1)*Q15,2)) -> 0 | W15: =IF(I15="","",IF(COUNTIF(HolidayDates,I15)>0,"Yes","No")) -> 0 | X15: =IF(I15="","",IF(WEEKDAY(I15,2)>5,"Yes","No")) -> 0 | Y15: =IF(H15="","",ROUND((U15+V15)*(IF(W15="Yes",R15,0)+IF(X15="Yes",S15,0)),2)) -> 0 | AA15: =IF(H15="","",IF(T15<>"Yes",0,ROUND(MAX(0,IF(Z15="",0,Z15)-FreeTravelDistance)*TravelFeeRate,2))) -> 0 | AB15: =IF(I15="","",TravelTimeMins) -> 0 | AC15: =IF(OR(I15="",B15=""),0,IF(I15-B15<=LastMinuteDays,EmergencyFee,0)) -> 0 | AF15: =IF(H15="","",ROUND((U15+V15+Y15+AA15+AC15)*IF(AE15="",0,AE15),2)) -> 0 | AI15: =IF(H15="","",IF(AG15<>"",AG15,ROUND(U15+V15+Y15+AA15+AC15-AF15,2))) -> 0 | AJ15: =IF(AI15="","",IF(TaxRegistered<>"Yes",0,IF(PricesIncludeTax="Yes",ROUND(AI15-AI15/(1+TaxRate),2),ROUND(AI15*TaxRate,2)))) -> 0 | AK15: =IF(AI15="","",IF(PricesIncludeTax="Yes",AI15,ROUND(AI15+AJ15,2))) -> 0 | AQ15: =IF(OR(I15="",AP15="",AP15="None"),"",IF(AP15="Monthly",EDATE(I15,1),I15+IF(AP15="Daily",1,IF(AP15="Weekdays",IF(WEEKDAY(I15,2)>=5,8-WEEKDAY(I15,2),1),IF(AP15="Weekly",7,IF(AP15="Fortnightly",14,0)))))) -> 0 | AR15: =IF(OR(I15="",AL15="",K15="",L15=""),"",IF(SUMPRODUCT((Bookings!$AL$5:$AL$404=AL15)*(Bookings!$I$5:$I$404=I15)*(Bookings!$K$5:$K$404<L15)*(Bookings!$L$5:$L$404>K15)*(Bookings!$AM$5:$AM$404<>"Cancelled"))>1,"Conflict - double booked","OK")) -> 0 | AS15: =IF(A15="","",IF(COUNTIF('Visit Log'!$B$5:$B$404,A15)>0,"Yes","No")) -> 0 | AT15: =IF(A15="","",IFERROR(INDEX(Invoices!$A$5:$A$304,MATCH(A15,Invoices!$E$5:$E$304,0)),"")) -> 0 | AU15: =IF(A15="","",IF(AT15="","Not invoiced",IFERROR(INDEX(Invoices!$U$5:$U$304,MATCH(AT15,Invoices!$A$5:$A$304,0)),""))) -> 0 | AY15: =IF(I15="","",TEXT(I15,"yyyy-mm")) -> 0 | AZ15: =IF(I15="","",IF(AM15="Cancelled","Cancelled",IF(AND(I15<TODAY(),OR(AM15="Pending",AM15="Confirmed",AM15="Enquiry")),"Overdue - update status",IF(AND(AM15="Completed",AS15="No"),"Action - log the visit",IF(I15=TODAY(),"Today",IF(AND(I15>TODAY(),I15-TODAY()<=ReminderLeadDays,AN15<>"Yes"),"Action - unconfirmed",IF(AND(I15>TODAY(),I15-TODAY()<=ReminderLeadDays),"Upcoming","OK"))))))) -> 0
A16: =IF(C16="","",BookingPrefix&TEXT(ROW()-4,"0000")) -> 0 | D16: =IF(C16="","",IFERROR(INDEX(Clients!$A$5:$A$254,MATCH(C16,Clients!$B$5:$B$254,0)),"")) -> 0 | J16: =IF(I16="","",TEXT(I16,"ddd")) -> 0 | M16: =IF(OR(K16="",L16=""),"",ROUND((L16-K16+IF(L16<K16,1,0))*24,2)) -> 0 | O16: =IF(H16="","",IFERROR(INDEX(Services!$E$5:$E$54,MATCH(H16,Services!$B$5:$B$54,0)),"")) -> 0 | P16: =IF(H16="","",IFERROR(INDEX(Services!$G$5:$G$54,MATCH(H16,Services!$B$5:$B$54,0)),0)) -> 0 | Q16: =IF(H16="","",IF(IFERROR(INDEX(Services!$H$5:$H$54,MATCH(H16,Services!$B$5:$B$54,0)),0)=0,ExtraPetFeeDefault,IFERROR(INDEX(Services!$H$5:$H$54,MATCH(H16,Services!$B$5:$B$54,0)),0))) -> 0 | R16: =IF(H16="","",IF(IFERROR(INDEX(Services!$I$5:$I$54,MATCH(H16,Services!$B$5:$B$54,0)),0)=0,HolidaySurcharge,IFERROR(INDEX(Services!$I$5:$I$54,MATCH(H16,Services!$B$5:$B$54,0)),0))) -> 0 | S16: =IF(H16="","",IF(IFERROR(INDEX(Services!$J$5:$J$54,MATCH(H16,Services!$B$5:$B$54,0)),0)=0,WeekendSurcharge,IFERROR(INDEX(Services!$J$5:$J$54,MATCH(H16,Services!$B$5:$B$54,0)),0))) -> 0 | T16: =IF(H16="","",IFERROR(INDEX(Services!$K$5:$K$54,MATCH(H16,Services!$B$5:$B$54,0)),"No")) -> 0 | U16: =IF(H16="","",ROUND(IF(O16="Per hour",P16*IF(M16="",IF(N16="",1,N16),M16),P16*IF(N16="",1,N16)),2)) -> 0 | V16: =IF(H16="","",ROUND(MAX(0,IF(G16="",1,G16)-1)*Q16,2)) -> 0 | W16: =IF(I16="","",IF(COUNTIF(HolidayDates,I16)>0,"Yes","No")) -> 0 | X16: =IF(I16="","",IF(WEEKDAY(I16,2)>5,"Yes","No")) -> 0 | Y16: =IF(H16="","",ROUND((U16+V16)*(IF(W16="Yes",R16,0)+IF(X16="Yes",S16,0)),2)) -> 0 | AA16: =IF(H16="","",IF(T16<>"Yes",0,ROUND(MAX(0,IF(Z16="",0,Z16)-FreeTravelDistance)*TravelFeeRate,2))) -> 0 | AB16: =IF(I16="","",TravelTimeMins) -> 0 | AC16: =IF(OR(I16="",B16=""),0,IF(I16-B16<=LastMinuteDays,EmergencyFee,0)) -> 0 | AF16: =IF(H16="","",ROUND((U16+V16+Y16+AA16+AC16)*IF(AE16="",0,AE16),2)) -> 0 | AI16: =IF(H16="","",IF(AG16<>"",AG16,ROUND(U16+V16+Y16+AA16+AC16-AF16,2))) -> 0 | AJ16: =IF(AI16="","",IF(TaxRegistered<>"Yes",0,IF(PricesIncludeTax="Yes",ROUND(AI16-AI16/(1+TaxRate),2),ROUND(AI16*TaxRate,2)))) -> 0 | AK16: =IF(AI16="","",IF(PricesIncludeTax="Yes",AI16,ROUND(AI16+AJ16,2))) -> 0 | AQ16: =IF(OR(I16="",AP16="",AP16="None"),"",IF(AP16="Monthly",EDATE(I16,1),I16+IF(AP16="Daily",1,IF(AP16="Weekdays",IF(WEEKDAY(I16,2)>=5,8-WEEKDAY(I16,2),1),IF(AP16="Weekly",7,IF(AP16="Fortnightly",14,0)))))) -> 0 | AR16: =IF(OR(I16="",AL16="",K16="",L16=""),"",IF(SUMPRODUCT((Bookings!$AL$5:$AL$404=AL16)*(Bookings!$I$5:$I$404=I16)*(Bookings!$K$5:$K$404<L16)*(Bookings!$L$5:$L$404>K16)*(Bookings!$AM$5:$AM$404<>"Cancelled"))>1,"Conflict - double booked","OK")) -> 0 | AS16: =IF(A16="","",IF(COUNTIF('Visit Log'!$B$5:$B$404,A16)>0,"Yes","No")) -> 0 | AT16: =IF(A16="","",IFERROR(INDEX(Invoices!$A$5:$A$304,MATCH(A16,Invoices!$E$5:$E$304,0)),"")) -> 0 | AU16: =IF(A16="","",IF(AT16="","Not invoiced",IFERROR(INDEX(Invoices!$U$5:$U$304,MATCH(AT16,Invoices!$A$5:$A$304,0)),""))) -> 0 | AY16: =IF(I16="","",TEXT(I16,"yyyy-mm")) -> 0 | AZ16: =IF(I16="","",IF(AM16="Cancelled","Cancelled",IF(AND(I16<TODAY(),OR(AM16="Pending",AM16="Confirmed",AM16="Enquiry")),"Overdue - update status",IF(AND(AM16="Completed",AS16="No"),"Action - log the visit",IF(I16=TODAY(),"Today",IF(AND(I16>TODAY(),I16-TODAY()<=ReminderLeadDays,AN16<>"Yes"),"Action - unconfirmed",IF(AND(I16>TODAY(),I16-TODAY()<=ReminderLeadDays),"Upcoming","OK"))))))) -> 0
... A404: =IF(C404="","",BookingPrefix&TEXT(ROW()-4,"0000")) -> 0 | D404: =IF(C404="","",IFERROR(INDEX(Clients!$A$5:$A$254,MATCH(C404,Clients!$B$5:$B$254,0)),"")) -> 0 | J404: =IF(I404="","",TEXT(I404,"ddd")) -> 0 | M404: =IF(OR(K404="",L404=""),"",ROUND((L404-K404+IF(L404<K404,1,0))*24,2)) -> 0 | O404: =IF(H404="","",IFERROR(INDEX(Services!$E$5:$E$54,MATCH(H404,Services!$B$5:$B$54,0)),"")) -> 0 | P404: =IF(H404="","",IFERROR(INDEX(Services!$G$5:$G$54,MATCH(H404,Services!$B$5:$B$54,0)),0)) -> 0 | Q404: =IF(H404="","",IF(IFERROR(INDEX(Services!$H$5:$H$54,MATCH(H404,Services!$B$5:$B$54,0)),0)=0,ExtraPetFeeDefault,IFERROR(INDEX(Services!$H$5:$H$54,MATCH(H404,Services!$B$5:$B$54,0)),0))) -> 0 | R404: =IF(H404="","",IF(IFERROR(INDEX(Services!$I$5:$I$54,MATCH(H404,Services!$B$5:$B$54,0)),0)=0,HolidaySurcharge,IFERROR(INDEX(Services!$I$5:$I$54,MATCH(H404,Services!$B$5:$B$54,0)),0))) -> 0 | S404: =IF(H404="","",IF(IFERROR(INDEX(Services!$J$5:$J$54,MATCH(H404,Services!$B$5:$B$54,0)),0)=0,WeekendSurcharge,IFERROR(INDEX(Services!$J$5:$J$54,MATCH(H404,Services!$B$5:$B$54,0)),0))) -> 0 | T404: =IF(H404="","",IFERROR(INDEX(Services!$K$5:$K$54,MATCH(H404,Services!$B$5:$B$54,0)),"No")) -> 0 | U404: =IF(H404="","",ROUND(IF(O404="Per hour",P404*IF(M404="",IF(N404="",1,N404),M404),P404*IF(N404="",1,N404)),2)) -> 0 | V404: =IF(H404="","",ROUND(MAX(0,IF(G404="",1,G404)-1)*Q404,2)) -> 0 | W404: =IF(I404="","",IF(COUNTIF(HolidayDates,I404)>0,"Yes","No")) -> 0 | X404: =IF(I404="","",IF(WEEKDAY(I404,2)>5,"Yes","No")) -> 0 | Y404: =IF(H404="","",ROUND((U404+V404)*(IF(W404="Yes",R404,0)+IF(X404="Yes",S404,0)),2)) -> 0 | AA404: =IF(H404="","",IF(T404<>"Yes",0,ROUND(MAX(0,IF(Z404="",0,Z404)-FreeTravelDistance)*TravelFeeRate,2))) -> 0 | AB404: =IF(I404="","",TravelTimeMins) -> 0 | AC404: =IF(OR(I404="",B404=""),0,IF(I404-B404<=LastMinuteDays,EmergencyFee,0)) -> 0 | AF404: =IF(H404="","",ROUND((U404+V404+Y404+AA404+AC404)*IF(AE404="",0,AE404),2)) -> 0 | AI404: =IF(H404="","",IF(AG404<>"",AG404,ROUND(U404+V404+Y404+AA404+AC404-AF404,2))) -> 0 | AJ404: =IF(AI404="","",IF(TaxRegistered<>"Yes",0,IF(PricesIncludeTax="Yes",ROUND(AI404-AI404/(1+TaxRate),2),ROUND(AI404*TaxRate,2)))) -> 0 | AK404: =IF(AI404="","",IF(PricesIncludeTax="Yes",AI404,ROUND(AI404+AJ404,2))) -> 0 | AQ404: =IF(OR(I404="",AP404="",AP404="None"),"",IF(AP404="Monthly",EDATE(I404,1),I404+IF(AP404="Daily",1,IF(AP404="Weekdays",IF(WEEKDAY(I404,2)>=5,8-WEEKDAY(I404,2),1),IF(AP404="Weekly",7,IF(AP404="Fortnightly",14,0)))))) -> 0 | AR404: =IF(OR(I404="",AL404="",K404="",L404=""),"",IF(SUMPRODUCT((Bookings!$AL$5:$AL$404=AL404)*(Bookings!$I$5:$I$404=I404)*(Bookings!$K$5:$K$404<L404)*(Bookings!$L$5:$L$404>K404)*(Bookings!$AM$5:$AM$404<>"Cancelled"))>1,"Conflict - double booked","OK")) -> 0 | AS404: =IF(A404="","",IF(COUNTIF('Visit Log'!$B$5:$B$404,A404)>0,"Yes","No")) -> 0 | AT404: =IF(A404="","",IFERROR(INDEX(Invoices!$A$5:$A$304,MATCH(A404,Invoices!$E$5:$E$304,0)),"")) -> 0 | AU404: =IF(A404="","",IF(AT404="","Not invoiced",IFERROR(INDEX(Invoices!$U$5:$U$304,MATCH(AT404,Invoices!$A$5:$A$304,0)),""))) -> 0 | AY404: =IF(I404="","",TEXT(I404,"yyyy-mm")) -> 0 | AZ404: =IF(I404="","",IF(AM404="Cancelled","Cancelled",IF(AND(I404<TODAY(),OR(AM404="Pending",AM404="Confirmed",AM404="Enquiry")),"Overdue - update status",IF(AND(AM404="Completed",AS404="No"),"Action - log the visit",IF(I404=TODAY(),"Today",IF(AND(I404>TODAY(),I404-TODAY()<=ReminderLeadDays,AN404<>"Yes"),"Action - unconfirmed",IF(AND(I404>TODAY(),I404-TODAY()<=ReminderLeadDays),"Upcoming","OK"))))))) -> 0

Sheet Visit Log
A1: Daily Visit & Pet Care Log | AH1: Novality Store | v1.0.0
A2: Proof of service for every walk, drop-in and overnight: times, care given, mood, health notes and client updates.
A3: > Start Here | C3: > Dashboard | E3: > Clients | G3: > Pets | I3: > Bookings | K3: > Visit Log | M3: > Invoices | O3: > Reminders | Q3: > Help | S3: Start with the Booking ID - the client, pet, service and scheduled time are pulled in automatically. Minutes on site, punctuality and alerts are calculated.
A4: ID | B4: Booking ID | C4: Visit date | D4: Client | E4: Pet | F4: Service | G4: Carer | H4: Scheduled | I4: Arrived | J4: Departed | K4: Minutes on site | L4: On time? | M4: Walk start | N4: Walk end | O4: Walk minutes | P4: Distance walked | Q4: Fed | R4: Fresh water | S4: Medication given | T4: Potty / litter | U4: Exercise & play | V4: Grooming / cleaning | W4: Mood & behaviour | X4: Appetite | Y4: Health observations | Z4: Incident? | AA4: Incident ref | AB4: Photos / report link | AC4: Client updated | AD4: Care checklist done | AE4: Visit status | AF4: Visit notes | AG4: Month | AH4: Line key | AI4: Pet key | AJ4: Action needed
A5: =IF(C5="","","VS-"&TEXT(ROW()-4,"0000")) -> 0 | D5: =IF(B5="","",IFERROR(INDEX(Bookings!$C$5:$C$404,MATCH(B5,Bookings!$A$5:$A$404,0)),"")) -> 0 | E5: =IF(B5="","",IFERROR(INDEX(Bookings!$E$5:$E$404,MATCH(B5,Bookings!$A$5:$A$404,0)),"")) -> 0 | F5: =IF(B5="","",IFERROR(INDEX(Bookings!$H$5:$H$404,MATCH(B5,Bookings!$A$5:$A$404,0)),"")) -> 0 | H5: =IF(B5="","",IFERROR(INDEX(Bookings!$K$5:$K$404,MATCH(B5,Bookings!$A$5:$A$404,0)),"")) -> 0 | K5: =IF(OR(I5="",J5=""),"",ROUND((J5-I5+IF(J5<I5,1,0))*1440,0)) -> 0 | L5: =IF(OR(I5="",H5=""),"",IF(I5<=H5+TIME(0,10,0),"On time","Late "&TEXT((I5-H5)*1440,"0")&" min")) -> 0 | O5: =IF(OR(M5="",N5=""),"",ROUND((N5-M5+IF(N5<M5,1,0))*1440,0)) -> 0 | AG5: =IF(C5="","",TEXT(C5,"yyyy-mm")) -> 0 | AH5: =IF(B5="","",B5&"|"&COUNTIF($B$5:$B5,B5)) -> 0 | AI5: =IF(E5="","",E5&"|"&COUNTIF($E$5:$E5,E5)) -> 0 | AJ5: =IF(C5="","",IF(AE5="Missed","Missed visit - contact client",IF(Z5="Yes","Incident logged - follow up",IF(AND(AE5="Completed",AC5<>"Yes"),"Action - send client update",IF(AND(AE5="Completed",AD5<>"Yes"),"Check care checklist",IF(AND(C5<TODAY(),AE5="Scheduled"),"Overdue - log the result","OK")))))) -> 0
A6: =IF(C6="","","VS-"&TEXT(ROW()-4,"0000")) -> 0 | D6: =IF(B6="","",IFERROR(INDEX(Bookings!$C$5:$C$404,MATCH(B6,Bookings!$A$5:$A$404,0)),"")) -> 0 | E6: =IF(B6="","",IFERROR(INDEX(Bookings!$E$5:$E$404,MATCH(B6,Bookings!$A$5:$A$404,0)),"")) -> 0 | F6: =IF(B6="","",IFERROR(INDEX(Bookings!$H$5:$H$404,MATCH(B6,Bookings!$A$5:$A$404,0)),"")) -> 0 | H6: =IF(B6="","",IFERROR(INDEX(Bookings!$K$5:$K$404,MATCH(B6,Bookings!$A$5:$A$404,0)),"")) -> 0 | K6: =IF(OR(I6="",J6=""),"",ROUND((J6-I6+IF(J6<I6,1,0))*1440,0)) -> 0 | L6: =IF(OR(I6="",H6=""),"",IF(I6<=H6+TIME(0,10,0),"On time","Late "&TEXT((I6-H6)*1440,"0")&" min")) -> 0 | O6: =IF(OR(M6="",N6=""),"",ROUND((N6-M6+IF(N6<M6,1,0))*1440,0)) -> 0 | AG6: =IF(C6="","",TEXT(C6,"yyyy-mm")) -> 0 | AH6: =IF(B6="","",B6&"|"&COUNTIF($B$5:$B6,B6)) -> 0 | AI6: =IF(E6="","",E6&"|"&COUNTIF($E$5:$E6,E6)) -> 0 | AJ6: =IF(C6="","",IF(AE6="Missed","Missed visit - contact client",IF(Z6="Yes","Incident logged - follow up",IF(AND(AE6="Completed",AC6<>"Yes"),"Action - send client update",IF(AND(AE6="Completed",AD6<>"Yes"),"Check care checklist",IF(AND(C6<TODAY(),AE6="Scheduled"),"Overdue - log the result","OK")))))) -> 0
A7: =IF(C7="","","VS-"&TEXT(ROW()-4,"0000")) -> 0 | D7: =IF(B7="","",IFERROR(INDEX(Bookings!$C$5:$C$404,MATCH(B7,Bookings!$A$5:$A$404,0)),"")) -> 0 | E7: =IF(B7="","",IFERROR(INDEX(Bookings!$E$5:$E$404,MATCH(B7,Bookings!$A$5:$A$404,0)),"")) -> 0 | F7: =IF(B7="","",IFERROR(INDEX(Bookings!$H$5:$H$404,MATCH(B7,Bookings!$A$5:$A$404,0)),"")) -> 0 | H7: =IF(B7="","",IFERROR(INDEX(Bookings!$K$5:$K$404,MATCH(B7,Bookings!$A$5:$A$404,0)),"")) -> 0 | K7: =IF(OR(I7="",J7=""),"",ROUND((J7-I7+IF(J7<I7,1,0))*1440,0)) -> 0 | L7: =IF(OR(I7="",H7=""),"",IF(I7<=H7+TIME(0,10,0),"On time","Late "&TEXT((I7-H7)*1440,"0")&" min")) -> 0 | O7: =IF(OR(M7="",N7=""),"",ROUND((N7-M7+IF(N7<M7,1,0))*1440,0)) -> 0 | AG7: =IF(C7="","",TEXT(C7,"yyyy-mm")) -> 0 | AH7: =IF(B7="","",B7&"|"&COUNTIF($B$5:$B7,B7)) -> 0 | AI7: =IF(E7="","",E7&"|"&COUNTIF($E$5:$E7,E7)) -> 0 | AJ7: =IF(C7="","",IF(AE7="Missed","Missed visit - contact client",IF(Z7="Yes","Incident logged - follow up",IF(AND(AE7="Completed",AC7<>"Yes"),"Action - send client update",IF(AND(AE7="Completed",AD7<>"Yes"),"Check care checklist",IF(AND(C7<TODAY(),AE7="Scheduled"),"Overdue - log the result","OK")))))) -> 0
A8: =IF(C8="","","VS-"&TEXT(ROW()-4,"0000")) -> 0 | D8: =IF(B8="","",IFERROR(INDEX(Bookings!$C$5:$C$404,MATCH(B8,Bookings!$A$5:$A$404,0)),"")) -> 0 | E8: =IF(B8="","",IFERROR(INDEX(Bookings!$E$5:$E$404,MATCH(B8,Bookings!$A$5:$A$404,0)),"")) -> 0 | F8: =IF(B8="","",IFERROR(INDEX(Bookings!$H$5:$H$404,MATCH(B8,Bookings!$A$5:$A$404,0)),"")) -> 0 | H8: =IF(B8="","",IFERROR(INDEX(Bookings!$K$5:$K$404,MATCH(B8,Bookings!$A$5:$A$404,0)),"")) -> 0 | K8: =IF(OR(I8="",J8=""),"",ROUND((J8-I8+IF(J8<I8,1,0))*1440,0)) -> 0 | L8: =IF(OR(I8="",H8=""),"",IF(I8<=H8+TIME(0,10,0),"On time","Late "&TEXT((I8-H8)*1440,"0")&" min")) -> 0 | O8: =IF(OR(M8="",N8=""),"",ROUND((N8-M8+IF(N8<M8,1,0))*1440,0)) -> 0 | AG8: =IF(C8="","",TEXT(C8,"yyyy-mm")) -> 0 | AH8: =IF(B8="","",B8&"|"&COUNTIF($B$5:$B8,B8)) -> 0 | AI8: =IF(E8="","",E8&"|"&COUNTIF($E$5:$E8,E8)) -> 0 | AJ8: =IF(C8="","",IF(AE8="Missed","Missed visit - contact client",IF(Z8="Yes","Incident logged - follow up",IF(AND(AE8="Completed",AC8<>"Yes"),"Action - send client update",IF(AND(AE8="Completed",AD8<>"Yes"),"Check care checklist",IF(AND(C8<TODAY(),AE8="Scheduled"),"Overdue - log the result","OK")))))) -> 0
A9: =IF(C9="","","VS-"&TEXT(ROW()-4,"0000")) -> 0 | D9: =IF(B9="","",IFERROR(INDEX(Bookings!$C$5:$C$404,MATCH(B9,Bookings!$A$5:$A$404,0)),"")) -> 0 | E9: =IF(B9="","",IFERROR(INDEX(Bookings!$E$5:$E$404,MATCH(B9,Bookings!$A$5:$A$404,0)),"")) -> 0 | F9: =IF(B9="","",IFERROR(INDEX(Bookings!$H$5:$H$404,MATCH(B9,Bookings!$A$5:$A$404,0)),"")) -> 0 | H9: =IF(B9="","",IFERROR(INDEX(Bookings!$K$5:$K$404,MATCH(B9,Bookings!$A$5:$A$404,0)),"")) -> 0 | K9: =IF(OR(I9="",J9=""),"",ROUND((J9-I9+IF(J9<I9,1,0))*1440,0)) -> 0 | L9: =IF(OR(I9="",H9=""),"",IF(I9<=H9+TIME(0,10,0),"On time","Late "&TEXT((I9-H9)*1440,"0")&" min")) -> 0 | O9: =IF(OR(M9="",N9=""),"",ROUND((N9-M9+IF(N9<M9,1,0))*1440,0)) -> 0 | AG9: =IF(C9="","",TEXT(C9,"yyyy-mm")) -> 0 | AH9: =IF(B9="","",B9&"|"&COUNTIF($B$5:$B9,B9)) -> 0 | AI9: =IF(E9="","",E9&"|"&COUNTIF($E$5:$E9,E9)) -> 0 | AJ9: =IF(C9="","",IF(AE9="Missed","Missed visit - contact client",IF(Z9="Yes","Incident logged - follow up",IF(AND(AE9="Completed",AC9<>"Yes"),"Action - send client update",IF(AND(AE9="Completed",AD9<>"Yes"),"Check care checklist",IF(AND(C9<TODAY(),AE9="Scheduled"),"Overdue - log the result","OK")))))) -> 0
A10: =IF(C10="","","VS-"&TEXT(ROW()-4,"0000")) -> 0 | D10: =IF(B10="","",IFERROR(INDEX(Bookings!$C$5:$C$404,MATCH(B10,Bookings!$A$5:$A$404,0)),"")) -> 0 | E10: =IF(B10="","",IFERROR(INDEX(Bookings!$E$5:$E$404,MATCH(B10,Bookings!$A$5:$A$404,0)),"")) -> 0 | F10: =IF(B10="","",IFERROR(INDEX(Bookings!$H$5:$H$404,MATCH(B10,Bookings!$A$5:$A$404,0)),"")) -> 0 | H10: =IF(B10="","",IFERROR(INDEX(Bookings!$K$5:$K$404,MATCH(B10,Bookings!$A$5:$A$404,0)),"")) -> 0 | K10: =IF(OR(I10="",J10=""),"",ROUND((J10-I10+IF(J10<I10,1,0))*1440,0)) -> 0 | L10: =IF(OR(I10="",H10=""),"",IF(I10<=H10+TIME(0,10,0),"On time","Late "&TEXT((I10-H10)*1440,"0")&" min")) -> 0 | O10: =IF(OR(M10="",N10=""),"",ROUND((N10-M10+IF(N10<M10,1,0))*1440,0)) -> 0 | AG10: =IF(C10="","",TEXT(C10,"yyyy-mm")) -> 0 | AH10: =IF(B10="","",B10&"|"&COUNTIF($B$5:$B10,B10)) -> 0 | AI10: =IF(E10="","",E10&"|"&COUNTIF($E$5:$E10,E10)) -> 0 | AJ10: =IF(C10="","",IF(AE10="Missed","Missed visit - contact client",IF(Z10="Yes","Incident logged - follow up",IF(AND(AE10="Completed",AC10<>"Yes"),"Action - send client update",IF(AND(AE10="Completed",AD10<>"Yes"),"Check care checklist",IF(AND(C10<TODAY(),AE10="Scheduled"),"Overdue - log the result","OK")))))) -> 0
A11: =IF(C11="","","VS-"&TEXT(ROW()-4,"0000")) -> 0 | D11: =IF(B11="","",IFERROR(INDEX(Bookings!$C$5:$C$404,MATCH(B11,Bookings!$A$5:$A$404,0)),"")) -> 0 | E11: =IF(B11="","",IFERROR(INDEX(Bookings!$E$5:$E$404,MATCH(B11,Bookings!$A$5:$A$404,0)),"")) -> 0 | F11: =IF(B11="","",IFERROR(INDEX(Bookings!$H$5:$H$404,MATCH(B11,Bookings!$A$5:$A$404,0)),"")) -> 0 | H11: =IF(B11="","",IFERROR(INDEX(Bookings!$K$5:$K$404,MATCH(B11,Bookings!$A$5:$A$404,0)),"")) -> 0 | K11: =IF(OR(I11="",J11=""),"",ROUND((J11-I11+IF(J11<I11,1,0))*1440,0)) -> 0 | L11: =IF(OR(I11="",H11=""),"",IF(I11<=H11+TIME(0,10,0),"On time","Late "&TEXT((I11-H11)*1440,"0")&" min")) -> 0 | O11: =IF(OR(M11="",N11=""),"",ROUND((N11-M11+IF(N11<M11,1,0))*1440,0)) -> 0 | AG11: =IF(C11="","",TEXT(C11,"yyyy-mm")) -> 0 | AH11: =IF(B11="","",B11&"|"&COUNTIF($B$5:$B11,B11)) -> 0 | AI11: =IF(E11="","",E11&"|"&COUNTIF($E$5:$E11,E11)) -> 0 | AJ11: =IF(C11="","",IF(AE11="Missed","Missed visit - contact client",IF(Z11="Yes","Incident logged - follow up",IF(AND(AE11="Completed",AC11<>"Yes"),"Action - send client update",IF(AND(AE11="Completed",AD11<>"Yes"),"Check care checklist",IF(AND(C11<TODAY(),AE11="Scheduled"),"Overdue - log the result","OK")))))) -> 0
A12: =IF(C12="","","VS-"&TEXT(ROW()-4,"0000")) -> 0 | D12: =IF(B12="","",IFERROR(INDEX(Bookings!$C$5:$C$404,MATCH(B12,Bookings!$A$5:$A$404,0)),"")) -> 0 | E12: =IF(B12="","",IFERROR(INDEX(Bookings!$E$5:$E$404,MATCH(B12,Bookings!$A$5:$A$404,0)),"")) -> 0 | F12: =IF(B12="","",IFERROR(INDEX(Bookings!$H$5:$H$404,MATCH(B12,Bookings!$A$5:$A$404,0)),"")) -> 0 | H12: =IF(B12="","",IFERROR(INDEX(Bookings!$K$5:$K$404,MATCH(B12,Bookings!$A$5:$A$404,0)),"")) -> 0 | K12: =IF(OR(I12="",J12=""),"",ROUND((J12-I12+IF(J12<I12,1,0))*1440,0)) -> 0 | L12: =IF(OR(I12="",H12=""),"",IF(I12<=H12+TIME(0,10,0),"On time","Late "&TEXT((I12-H12)*1440,"0")&" min")) -> 0 | O12: =IF(OR(M12="",N12=""),"",ROUND((N12-M12+IF(N12<M12,1,0))*1440,0)) -> 0 | AG12: =IF(C12="","",TEXT(C12,"yyyy-mm")) -> 0 | AH12: =IF(B12="","",B12&"|"&COUNTIF($B$5:$B12,B12)) -> 0 | AI12: =IF(E12="","",E12&"|"&COUNTIF($E$5:$E12,E12)) -> 0 | AJ12: =IF(C12="","",IF(AE12="Missed","Missed visit - contact client",IF(Z12="Yes","Incident logged - follow up",IF(AND(AE12="Completed",AC12<>"Yes"),"Action - send client update",IF(AND(AE12="Completed",AD12<>"Yes"),"Check care checklist",IF(AND(C12<TODAY(),AE12="Scheduled"),"Overdue - log the result","OK")))))) -> 0
A13: =IF(C13="","","VS-"&TEXT(ROW()-4,"0000")) -> 0 | D13: =IF(B13="","",IFERROR(INDEX(Bookings!$C$5:$C$404,MATCH(B13,Bookings!$A$5:$A$404,0)),"")) -> 0 | E13: =IF(B13="","",IFERROR(INDEX(Bookings!$E$5:$E$404,MATCH(B13,Bookings!$A$5:$A$404,0)),"")) -> 0 | F13: =IF(B13="","",IFERROR(INDEX(Bookings!$H$5:$H$404,MATCH(B13,Bookings!$A$5:$A$404,0)),"")) -> 0 | H13: =IF(B13="","",IFERROR(INDEX(Bookings!$K$5:$K$404,MATCH(B13,Bookings!$A$5:$A$404,0)),"")) -> 0 | K13: =IF(OR(I13="",J13=""),"",ROUND((J13-I13+IF(J13<I13,1,0))*1440,0)) -> 0 | L13: =IF(OR(I13="",H13=""),"",IF(I13<=H13+TIME(0,10,0),"On time","Late "&TEXT((I13-H13)*1440,"0")&" min")) -> 0 | O13: =IF(OR(M13="",N13=""),"",ROUND((N13-M13+IF(N13<M13,1,0))*1440,0)) -> 0 | AG13: =IF(C13="","",TEXT(C13,"yyyy-mm")) -> 0 | AH13: =IF(B13="","",B13&"|"&COUNTIF($B$5:$B13,B13)) -> 0 | AI13: =IF(E13="","",E13&"|"&COUNTIF($E$5:$E13,E13)) -> 0 | AJ13: =IF(C13="","",IF(AE13="Missed","Missed visit - contact client",IF(Z13="Yes","Incident logged - follow up",IF(AND(AE13="Completed",AC13<>"Yes"),"Action - send client update",IF(AND(AE13="Completed",AD13<>"Yes"),"Check care checklist",IF(AND(C13<TODAY(),AE13="Scheduled"),"Overdue - log the result","OK")))))) -> 0
A14: =IF(C14="","","VS-"&TEXT(ROW()-4,"0000")) -> 0 | D14: =IF(B14="","",IFERROR(INDEX(Bookings!$C$5:$C$404,MATCH(B14,Bookings!$A$5:$A$404,0)),"")) -> 0 | E14: =IF(B14="","",IFERROR(INDEX(Bookings!$E$5:$E$404,MATCH(B14,Bookings!$A$5:$A$404,0)),"")) -> 0 | F14: =IF(B14="","",IFERROR(INDEX(Bookings!$H$5:$H$404,MATCH(B14,Bookings!$A$5:$A$404,0)),"")) -> 0 | H14: =IF(B14="","",IFERROR(INDEX(Bookings!$K$5:$K$404,MATCH(B14,Bookings!$A$5:$A$404,0)),"")) -> 0 | K14: =IF(OR(I14="",J14=""),"",ROUND((J14-I14+IF(J14<I14,1,0))*1440,0)) -> 0 | L14: =IF(OR(I14="",H14=""),"",IF(I14<=H14+TIME(0,10,0),"On time","Late "&TEXT((I14-H14)*1440,"0")&" min")) -> 0 | O14: =IF(OR(M14="",N14=""),"",ROUND((N14-M14+IF(N14<M14,1,0))*1440,0)) -> 0 | AG14: =IF(C14="","",TEXT(C14,"yyyy-mm")) -> 0 | AH14: =IF(B14="","",B14&"|"&COUNTIF($B$5:$B14,B14)) -> 0 | AI14: =IF(E14="","",E14&"|"&COUNTIF($E$5:$E14,E14)) -> 0 | AJ14: =IF(C14="","",IF(AE14="Missed","Missed visit - contact client",IF(Z14="Yes","Incident logged - follow up",IF(AND(AE14="Completed",AC14<>"Yes"),"Action - send client update",IF(AND(AE14="Completed",AD14<>"Yes"),"Check care checklist",IF(AND(C14<TODAY(),AE14="Scheduled"),"Overdue - log the result","OK")))))) -> 0
A15: =IF(C15="","","VS-"&TEXT(ROW()-4,"0000")) -> 0 | D15: =IF(B15="","",IFERROR(INDEX(Bookings!$C$5:$C$404,MATCH(B15,Bookings!$A$5:$A$404,0)),"")) -> 0 | E15: =IF(B15="","",IFERROR(INDEX(Bookings!$E$5:$E$404,MATCH(B15,Bookings!$A$5:$A$404,0)),"")) -> 0 | F15: =IF(B15="","",IFERROR(INDEX(Bookings!$H$5:$H$404,MATCH(B15,Bookings!$A$5:$A$404,0)),"")) -> 0 | H15: =IF(B15="","",IFERROR(INDEX(Bookings!$K$5:$K$404,MATCH(B15,Bookings!$A$5:$A$404,0)),"")) -> 0 | K15: =IF(OR(I15="",J15=""),"",ROUND((J15-I15+IF(J15<I15,1,0))*1440,0)) -> 0 | L15: =IF(OR(I15="",H15=""),"",IF(I15<=H15+TIME(0,10,0),"On time","Late "&TEXT((I15-H15)*1440,"0")&" min")) -> 0 | O15: =IF(OR(M15="",N15=""),"",ROUND((N15-M15+IF(N15<M15,1,0))*1440,0)) -> 0 | AG15: =IF(C15="","",TEXT(C15,"yyyy-mm")) -> 0 | AH15: =IF(B15="","",B15&"|"&COUNTIF($B$5:$B15,B15)) -> 0 | AI15: =IF(E15="","",E15&"|"&COUNTIF($E$5:$E15,E15)) -> 0 | AJ15: =IF(C15="","",IF(AE15="Missed","Missed visit - contact client",IF(Z15="Yes","Incident logged - follow up",IF(AND(AE15="Completed",AC15<>"Yes"),"Action - send client update",IF(AND(AE15="Completed",AD15<>"Yes"),"Check care checklist",IF(AND(C15<TODAY(),AE15="Scheduled"),"Overdue - log the result","OK")))))) -> 0
A16: =IF(C16="","","VS-"&TEXT(ROW()-4,"0000")) -> 0 | D16: =IF(B16="","",IFERROR(INDEX(Bookings!$C$5:$C$404,MATCH(B16,Bookings!$A$5:$A$404,0)),"")) -> 0 | E16: =IF(B16="","",IFERROR(INDEX(Bookings!$E$5:$E$404,MATCH(B16,Bookings!$A$5:$A$404,0)),"")) -> 0 | F16: =IF(B16="","",IFERROR(INDEX(Bookings!$H$5:$H$404,MATCH(B16,Bookings!$A$5:$A$404,0)),"")) -> 0 | H16: =IF(B16="","",IFERROR(INDEX(Bookings!$K$5:$K$404,MATCH(B16,Bookings!$A$5:$A$404,0)),"")) -> 0 | K16: =IF(OR(I16="",J16=""),"",ROUND((J16-I16+IF(J16<I16,1,0))*1440,0)) -> 0 | L16: =IF(OR(I16="",H16=""),"",IF(I16<=H16+TIME(0,10,0),"On time","Late "&TEXT((I16-H16)*1440,"0")&" min")) -> 0 | O16: =IF(OR(M16="",N16=""),"",ROUND((N16-M16+IF(N16<M16,1,0))*1440,0)) -> 0 | AG16: =IF(C16="","",TEXT(C16,"yyyy-mm")) -> 0 | AH16: =IF(B16="","",B16&"|"&COUNTIF($B$5:$B16,B16)) -> 0 | AI16: =IF(E16="","",E16&"|"&COUNTIF($E$5:$E16,E16)) -> 0 | AJ16: =IF(C16="","",IF(AE16="Missed","Missed visit - contact client",IF(Z16="Yes","Incident logged - follow up",IF(AND(AE16="Completed",AC16<>"Yes"),"Action - send client update",IF(AND(AE16="Completed",AD16<>"Yes"),"Check care checklist",IF(AND(C16<TODAY(),AE16="Scheduled"),"Overdue - log the result","OK")))))) -> 0
... A404: =IF(C404="","","VS-"&TEXT(ROW()-4,"0000")) -> 0 | D404: =IF(B404="","",IFERROR(INDEX(Bookings!$C$5:$C$404,MATCH(B404,Bookings!$A$5:$A$404,0)),"")) -> 0 | E404: =IF(B404="","",IFERROR(INDEX(Bookings!$E$5:$E$404,MATCH(B404,Bookings!$A$5:$A$404,0)),"")) -> 0 | F404: =IF(B404="","",IFERROR(INDEX(Bookings!$H$5:$H$404,MATCH(B404,Bookings!$A$5:$A$404,0)),"")) -> 0 | H404: =IF(B404="","",IFERROR(INDEX(Bookings!$K$5:$K$404,MATCH(B404,Bookings!$A$5:$A$404,0)),"")) -> 0 | K404: =IF(OR(I404="",J404=""),"",ROUND((J404-I404+IF(J404<I404,1,0))*1440,0)) -> 0 | L404: =IF(OR(I404="",H404=""),"",IF(I404<=H404+TIME(0,10,0),"On time","Late "&TEXT((I404-H404)*1440,"0")&" min")) -> 0 | O404: =IF(OR(M404="",N404=""),"",ROUND((N404-M404+IF(N404<M404,1,0))*1440,0)) -> 0 | AG404: =IF(C404="","",TEXT(C404,"yyyy-mm")) -> 0 | AH404: =IF(B404="","",B404&"|"&COUNTIF($B$5:$B404,B404)) -> 0 | AI404: =IF(E404="","",E404&"|"&COUNTIF($E$5:$E404,E404)) -> 0 | AJ404: =IF(C404="","",IF(AE404="Missed","Missed visit - contact client",IF(Z404="Yes","Incident logged - follow up",IF(AND(AE404="Completed",AC404<>"Yes"),"Action - send client update",IF(AND(AE404="Completed",AD404<>"Yes"),"Check care checklist",IF(AND(C404<TODAY(),AE404="Scheduled"),"Overdue - log the result","OK")))))) -> 0

Sheet Health Log
A1: Medication & Health Monitoring | T1: Novality Store | v1.0.0
A2: A dated record of every dose given, vaccination, vet visit and health observation - your proof of care.
A3: > Start Here | C3: > Dashboard | E3: > Clients | G3: > Pets | I3: > Bookings | K3: > Visit Log | M3: > Invoices | O3: > Reminders | Q3: > Help
A4: ID | B4: Date | C4: Time | D4: Pet | E4: Client | F4: Record type | G4: Medication / treatment | H4: Dosage & instructions | I4: Scheduled | J4: Given at | K4: Given by | L4: Status | M4: Supply left | N4: Refill due | O4: Refill alert | P4: Vet appointment | Q4: Appointment alert | R4: Cost | S4: Owner notified | T4: Notes | U4: Month | V4: Action needed
A5: =IF(B5="","","HL-"&TEXT(ROW()-4,"0000")) -> 0 | E5: =IF(D5="","",IFERROR(INDEX(Pets!$C$5:$C$254,MATCH(D5,Pets!$D$5:$D$254,0)),"")) -> 0 | O5: =IF(N5="","",IF(N5<TODAY(),"Overdue - refill now",IF(N5-TODAY()<=ExpiryAlertDays,"Due in "&TEXT(N5-TODAY(),"0")&" days","OK"))) -> 0 | Q5: =IF(P5="","",IF(P5<TODAY(),"Past",IF(P5-TODAY()<=ExpiryAlertDays,"Due in "&TEXT(P5-TODAY(),"0")&" days","Booked"))) -> 0 | U5: =IF(B5="","",TEXT(B5,"yyyy-mm")) -> 0 | V5: =IF(B5="","",IF(L5="Missed","Missed dose - tell the owner",IF(L5="Refused","Refused - monitor and report",IF(AND(L5="Scheduled",B5<TODAY()),"Overdue - not recorded",IF(AND(S5<>"Yes",F5="Vet visit"),"Action - update the owner","OK"))))) -> 0
A6: =IF(B6="","","HL-"&TEXT(ROW()-4,"0000")) -> 0 | E6: =IF(D6="","",IFERROR(INDEX(Pets!$C$5:$C$254,MATCH(D6,Pets!$D$5:$D$254,0)),"")) -> 0 | O6: =IF(N6="","",IF(N6<TODAY(),"Overdue - refill now",IF(N6-TODAY()<=ExpiryAlertDays,"Due in "&TEXT(N6-TODAY(),"0")&" days","OK"))) -> 0 | Q6: =IF(P6="","",IF(P6<TODAY(),"Past",IF(P6-TODAY()<=ExpiryAlertDays,"Due in "&TEXT(P6-TODAY(),"0")&" days","Booked"))) -> 0 | U6: =IF(B6="","",TEXT(B6,"yyyy-mm")) -> 0 | V6: =IF(B6="","",IF(L6="Missed","Missed dose - tell the owner",IF(L6="Refused","Refused - monitor and report",IF(AND(L6="Scheduled",B6<TODAY()),"Overdue - not recorded",IF(AND(S6<>"Yes",F6="Vet visit"),"Action - update the owner","OK"))))) -> 0
A7: =IF(B7="","","HL-"&TEXT(ROW()-4,"0000")) -> 0 | E7: =IF(D7="","",IFERROR(INDEX(Pets!$C$5:$C$254,MATCH(D7,Pets!$D$5:$D$254,0)),"")) -> 0 | O7: =IF(N7="","",IF(N7<TODAY(),"Overdue - refill now",IF(N7-TODAY()<=ExpiryAlertDays,"Due in "&TEXT(N7-TODAY(),"0")&" days","OK"))) -> 0 | Q7: =IF(P7="","",IF(P7<TODAY(),"Past",IF(P7-TODAY()<=ExpiryAlertDays,"Due in "&TEXT(P7-TODAY(),"0")&" days","Booked"))) -> 0 | U7: =IF(B7="","",TEXT(B7,"yyyy-mm")) -> 0 | V7: =IF(B7="","",IF(L7="Missed","Missed dose - tell the owner",IF(L7="Refused","Refused - monitor and report",IF(AND(L7="Scheduled",B7<TODAY()),"Overdue - not recorded",IF(AND(S7<>"Yes",F7="Vet visit"),"Action - update the owner","OK"))))) -> 0
A8: =IF(B8="","","HL-"&TEXT(ROW()-4,"0000")) -> 0 | E8: =IF(D8="","",IFERROR(INDEX(Pets!$C$5:$C$254,MATCH(D8,Pets!$D$5:$D$254,0)),"")) -> 0 | O8: =IF(N8="","",IF(N8<TODAY(),"Overdue - refill now",IF(N8-TODAY()<=ExpiryAlertDays,"Due in "&TEXT(N8-TODAY(),"0")&" days","OK"))) -> 0 | Q8: =IF(P8="","",IF(P8<TODAY(),"Past",IF(P8-TODAY()<=ExpiryAlertDays,"Due in "&TEXT(P8-TODAY(),"0")&" days","Booked"))) -> 0 | U8: =IF(B8="","",TEXT(B8,"yyyy-mm")) -> 0 | V8: =IF(B8="","",IF(L8="Missed","Missed dose - tell the owner",IF(L8="Refused","Refused - monitor and report",IF(AND(L8="Scheduled",B8<TODAY()),"Overdue - not recorded",IF(AND(S8<>"Yes",F8="Vet visit"),"Action - update the owner","OK"))))) -> 0
A9: =IF(B9="","","HL-"&TEXT(ROW()-4,"0000")) -> 0 | E9: =IF(D9="","",IFERROR(INDEX(Pets!$C$5:$C$254,MATCH(D9,Pets!$D$5:$D$254,0)),"")) -> 0 | O9: =IF(N9="","",IF(N9<TODAY(),"Overdue - refill now",IF(N9-TODAY()<=ExpiryAlertDays,"Due in "&TEXT(N9-TODAY(),"0")&" days","OK"))) -> 0 | Q9: =IF(P9="","",IF(P9<TODAY(),"Past",IF(P9-TODAY()<=ExpiryAlertDays,"Due in "&TEXT(P9-TODAY(),"0")&" days","Booked"))) -> 0 | U9: =IF(B9="","",TEXT(B9,"yyyy-mm")) -> 0 | V9: =IF(B9="","",IF(L9="Missed","Missed dose - tell the owner",IF(L9="Refused","Refused - monitor and report",IF(AND(L9="Scheduled",B9<TODAY()),"Overdue - not recorded",IF(AND(S9<>"Yes",F9="Vet visit"),"Action - update the owner","OK"))))) -> 0
A10: =IF(B10="","","HL-"&TEXT(ROW()-4,"0000")) -> 0 | E10: =IF(D10="","",IFERROR(INDEX(Pets!$C$5:$C$254,MATCH(D10,Pets!$D$5:$D$254,0)),"")) -> 0 | O10: =IF(N10="","",IF(N10<TODAY(),"Overdue - refill now",IF(N10-TODAY()<=ExpiryAlertDays,"Due in "&TEXT(N10-TODAY(),"0")&" days","OK"))) -> 0 | Q10: =IF(P10="","",IF(P10<TODAY(),"Past",IF(P10-TODAY()<=ExpiryAlertDays,"Due in "&TEXT(P10-TODAY(),"0")&" days","Booked"))) -> 0 | U10: =IF(B10="","",TEXT(B10,"yyyy-mm")) -> 0 | V10: =IF(B10="","",IF(L10="Missed","Missed dose - tell the owner",IF(L10="Refused","Refused - monitor and report",IF(AND(L10="Scheduled",B10<TODAY()),"Overdue - not recorded",IF(AND(S10<>"Yes",F10="Vet visit"),"Action - update the owner","OK"))))) -> 0
A11: =IF(B11="","","HL-"&TEXT(ROW()-4,"0000")) -> 0 | E11: =IF(D11="","",IFERROR(INDEX(Pets!$C$5:$C$254,MATCH(D11,Pets!$D$5:$D$254,0)),"")) -> 0 | O11: =IF(N11="","",IF(N11<TODAY(),"Overdue - refill now",IF(N11-TODAY()<=ExpiryAlertDays,"Due in "&TEXT(N11-TODAY(),"0")&" days","OK"))) -> 0 | Q11: =IF(P11="","",IF(P11<TODAY(),"Past",IF(P11-TODAY()<=ExpiryAlertDays,"Due in "&TEXT(P11-TODAY(),"0")&" days","Booked"))) -> 0 | U11: =IF(B11="","",TEXT(B11,"yyyy-mm")) -> 0 | V11: =IF(B11="","",IF(L11="Missed","Missed dose - tell the owner",IF(L11="Refused","Refused - monitor and report",IF(AND(L11="Scheduled",B11<TODAY()),"Overdue - not recorded",IF(AND(S11<>"Yes",F11="Vet visit"),"Action - update the owner","OK"))))) -> 0
A12: =IF(B12="","","HL-"&TEXT(ROW()-4,"0000")) -> 0 | E12: =IF(D12="","",IFERROR(INDEX(Pets!$C$5:$C$254,MATCH(D12,Pets!$D$5:$D$254,0)),"")) -> 0 | O12: =IF(N12="","",IF(N12<TODAY(),"Overdue - refill now",IF(N12-TODAY()<=ExpiryAlertDays,"Due in "&TEXT(N12-TODAY(),"0")&" days","OK"))) -> 0 | Q12: =IF(P12="","",IF(P12<TODAY(),"Past",IF(P12-TODAY()<=ExpiryAlertDays,"Due in "&TEXT(P12-TODAY(),"0")&" days","Booked"))) -> 0 | U12: =IF(B12="","",TEXT(B12,"yyyy-mm")) -> 0 | V12: =IF(B12="","",IF(L12="Missed","Missed dose - tell the owner",IF(L12="Refused","Refused - monitor and report",IF(AND(L12="Scheduled",B12<TODAY()),"Overdue - not recorded",IF(AND(S12<>"Yes",F12="Vet visit"),"Action - update the owner","OK"))))) -> 0
A13: =IF(B13="","","HL-"&TEXT(ROW()-4,"0000")) -> 0 | E13: =IF(D13="","",IFERROR(INDEX(Pets!$C$5:$C$254,MATCH(D13,Pets!$D$5:$D$254,0)),"")) -> 0 | O13: =IF(N13="","",IF(N13<TODAY(),"Overdue - refill now",IF(N13-TODAY()<=ExpiryAlertDays,"Due in "&TEXT(N13-TODAY(),"0")&" days","OK"))) -> 0 | Q13: =IF(P13="","",IF(P13<TODAY(),"Past",IF(P13-TODAY()<=ExpiryAlertDays,"Due in "&TEXT(P13-TODAY(),"0")&" days","Booked"))) -> 0 | U13: =IF(B13="","",TEXT(B13,"yyyy-mm")) -> 0 | V13: =IF(B13="","",IF(L13="Missed","Missed dose - tell the owner",IF(L13="Refused","Refused - monitor and report",IF(AND(L13="Scheduled",B13<TODAY()),"Overdue - not recorded",IF(AND(S13<>"Yes",F13="Vet visit"),"Action - update the owner","OK"))))) -> 0
A14: =IF(B14="","","HL-"&TEXT(ROW()-4,"0000")) -> 0 | E14: =IF(D14="","",IFERROR(INDEX(Pets!$C$5:$C$254,MATCH(D14,Pets!$D$5:$D$254,0)),"")) -> 0 | O14: =IF(N14="","",IF(N14<TODAY(),"Overdue - refill now",IF(N14-TODAY()<=ExpiryAlertDays,"Due in "&TEXT(N14-TODAY(),"0")&" days","OK"))) -> 0 | Q14: =IF(P14="","",IF(P14<TODAY(),"Past",IF(P14-TODAY()<=ExpiryAlertDays,"Due in "&TEXT(P14-TODAY(),"0")&" days","Booked"))) -> 0 | U14: =IF(B14="","",TEXT(B14,"yyyy-mm")) -> 0 | V14: =IF(B14="","",IF(L14="Missed","Missed dose - tell the owner",IF(L14="Refused","Refused - monitor and report",IF(AND(L14="Scheduled",B14<TODAY()),"Overdue - not recorded",IF(AND(S14<>"Yes",F14="Vet visit"),"Action - update the owner","OK"))))) -> 0
A15: =IF(B15="","","HL-"&TEXT(ROW()-4,"0000")) -> 0 | E15: =IF(D15="","",IFERROR(INDEX(Pets!$C$5:$C$254,MATCH(D15,Pets!$D$5:$D$254,0)),"")) -> 0 | O15: =IF(N15="","",IF(N15<TODAY(),"Overdue - refill now",IF(N15-TODAY()<=ExpiryAlertDays,"Due in "&TEXT(N15-TODAY(),"0")&" days","OK"))) -> 0 | Q15: =IF(P15="","",IF(P15<TODAY(),"Past",IF(P15-TODAY()<=ExpiryAlertDays,"Due in "&TEXT(P15-TODAY(),"0")&" days","Booked"))) -> 0 | U15: =IF(B15="","",TEXT(B15,"yyyy-mm")) -> 0 | V15: =IF(B15="","",IF(L15="Missed","Missed dose - tell the owner",IF(L15="Refused","Refused - monitor and report",IF(AND(L15="Scheduled",B15<TODAY()),"Overdue - not recorded",IF(AND(S15<>"Yes",F15="Vet visit"),"Action - update the owner","OK"))))) -> 0
A16: =IF(B16="","","HL-"&TEXT(ROW()-4,"0000")) -> 0 | E16: =IF(D16="","",IFERROR(INDEX(Pets!$C$5:$C$254,MATCH(D16,Pets!$D$5:$D$254,0)),"")) -> 0 | O16: =IF(N16="","",IF(N16<TODAY(),"Overdue - refill now",IF(N16-TODAY()<=ExpiryAlertDays,"Due in "&TEXT(N16-TODAY(),"0")&" days","OK"))) -> 0 | Q16: =IF(P16="","",IF(P16<TODAY(),"Past",IF(P16-TODAY()<=ExpiryAlertDays,"Due in "&TEXT(P16-TODAY(),"0")&" days","Booked"))) -> 0 | U16: =IF(B16="","",TEXT(B16,"yyyy-mm")) -> 0 | V16: =IF(B16="","",IF(L16="Missed","Missed dose - tell the owner",IF(L16="Refused","Refused - monitor and report",IF(AND(L16="Scheduled",B16<TODAY()),"Overdue - not recorded",IF(AND(S16<>"Yes",F16="Vet visit"),"Action - update the owner","OK"))))) -> 0
... A204: =IF(B204="","","HL-"&TEXT(ROW()-4,"0000")) -> 0 | E204: =IF(D204="","",IFERROR(INDEX(Pets!$C$5:$C$254,MATCH(D204,Pets!$D$5:$D$254,0)),"")) -> 0 | O204: =IF(N204="","",IF(N204<TODAY(),"Overdue - refill now",IF(N204-TODAY()<=ExpiryAlertDays,"Due in "&TEXT(N204-TODAY(),"0")&" days","OK"))) -> 0 | Q204: =IF(P204="","",IF(P204<TODAY(),"Past",IF(P204-TODAY()<=ExpiryAlertDays,"Due in "&TEXT(P204-TODAY(),"0")&" days","Booked"))) -> 0 | U204: =IF(B204="","",TEXT(B204,"yyyy-mm")) -> 0 | V204: =IF(B204="","",IF(L204="Missed","Missed dose - tell the owner",IF(L204="Refused","Refused - monitor and report",IF(AND(L204="Scheduled",B204<TODAY()),"Overdue - not recorded",IF(AND(S204<>"Yes",F204="Vet visit"),"Action - update the owner","OK"))))) -> 0

Sheet Incidents
A1: Pet Safety, Emergencies & Incident Reports | U1: Novality Store | v1.0.0
A2: Emergency numbers at the top, a dated incident report register below. Print a row straight from this tab if an owner or insurer asks for it.
A3: > Start Here | C3: > Dashboard | E3: > Clients | G3: > Pets | I3: > Bookings | K3: > Visit Log | M3: > Invoices | O3: > Reminders | Q3: > Help
A4: Emergency contact directory - keep this current
A5: Contact | B5: Name | D5: Number / details | H5: Notes
A6: Business emergency line | B6: =Biz_Phone -> 0 | D6: Answered 07:00 - 21:00
A7: Owner / manager | B7: =Biz_Owner -> 0 | D7: Call for any High or Critical event
A8: 24/7 emergency vet | B8: 24/7 Springfield Pet ER | D8: +1 (555) 100 9111 - open all night
A9: Backup emergency vet | B9: Riverton Vet Clinic | D9: +1 (555) 100 2000 - 08:00 to 18:00
A10: Animal poison helpline | B10: Pet Poison Hotline | D10: +1 (555) 100 7788
A11: Animal control / council | B11: Springfield Animal Services | D11: +1 (555) 100 4422
A12: Insurance claims | B12: =Biz_Insurer -> 0 | D12: =Biz_Policy -> 0
A13: Backup sitter on call | B13: Priya Shah | D13: +1 (555) 772 6690
A14: Locksmith / key issues | B14: Springfield Locks | D14: +1 (555) 100 6655
A16: Every incident needs: what happened, what you did, who you told and when. The alert column chases anything still open.
A17: ID | B17: Date | C17: Time | D17: Client | E17: Pet | F17: Reported by | G17: Booking / visit ref | H17: Incident type | I17: Severity | J17: What happened | K17: Action taken | L17: Vet contacted | M17: Clinic attended | N17: Owner notified | O17: Notified when | P17: Follow-up needed | Q17: Follow-up due | R17: Status | S17: Cost incurred | T17: Insurance claim | U17: Days open | V17: Notes & outcome | W17: Action needed
A18: =IF(B18="","","IN-"&TEXT(ROW()-4,"000")) -> 0 | U18: =IF(B18="","",IF(OR(R18="Resolved",R18="Closed"),"Closed",TEXT(TODAY()-B18,"0")&" days")) -> 0 | W18: =IF(B18="","",IF(N18<>"Yes","Action - notify the owner",IF(AND(P18="Yes",Q18<>"",Q18<TODAY(),R18<>"Resolved",R18<>"Closed"),"Overdue follow-up",IF(OR(R18="Open",R18="In progress"),"Open - keep working it","OK")))) -> 0
A19: =IF(B19="","","IN-"&TEXT(ROW()-4,"000")) -> 0 | U19: =IF(B19="","",IF(OR(R19="Resolved",R19="Closed"),"Closed",TEXT(TODAY()-B19,"0")&" days")) -> 0 | W19: =IF(B19="","",IF(N19<>"Yes","Action - notify the owner",IF(AND(P19="Yes",Q19<>"",Q19<TODAY(),R19<>"Resolved",R19<>"Closed"),"Overdue follow-up",IF(OR(R19="Open",R19="In progress"),"Open - keep working it","OK")))) -> 0
A20: =IF(B20="","","IN-"&TEXT(ROW()-4,"000")) -> 0 | U20: =IF(B20="","",IF(OR(R20="Resolved",R20="Closed"),"Closed",TEXT(TODAY()-B20,"0")&" days")) -> 0 | W20: =IF(B20="","",IF(N20<>"Yes","Action - notify the owner",IF(AND(P20="Yes",Q20<>"",Q20<TODAY(),R20<>"Resolved",R20<>"Closed"),"Overdue follow-up",IF(OR(R20="Open",R20="In progress"),"Open - keep working it","OK")))) -> 0
A21: =IF(B21="","","IN-"&TEXT(ROW()-4,"000")) -> 0 | U21: =IF(B21="","",IF(OR(R21="Resolved",R21="Closed"),"Closed",TEXT(TODAY()-B21,"0")&" days")) -> 0 | W21: =IF(B21="","",IF(N21<>"Yes","Action - notify the owner",IF(AND(P21="Yes",Q21<>"",Q21<TODAY(),R21<>"Resolved",R21<>"Closed"),"Overdue follow-up",IF(OR(R21="Open",R21="In progress"),"Open - keep working it","OK")))) -> 0
A22: =IF(B22="","","IN-"&TEXT(ROW()-4,"000")) -> 0 | U22: =IF(B22="","",IF(OR(R22="Resolved",R22="Closed"),"Closed",TEXT(TODAY()-B22,"0")&" days")) -> 0 | W22: =IF(B22="","",IF(N22<>"Yes","Action - notify the owner",IF(AND(P22="Yes",Q22<>"",Q22<TODAY(),R22<>"Resolved",R22<>"Closed"),"Overdue follow-up",IF(OR(R22="Open",R22="In progress"),"Open - keep working it","OK")))) -> 0
A23: =IF(B23="","","IN-"&TEXT(ROW()-4,"000")) -> 0 | U23: =IF(B23="","",IF(OR(R23="Resolved",R23="Closed"),"Closed",TEXT(TODAY()-B23,"0")&" days")) -> 0 | W23: =IF(B23="","",IF(N23<>"Yes","Action - notify the owner",IF(AND(P23="Yes",Q23<>"",Q23<TODAY(),R23<>"Resolved",R23<>"Closed"),"Overdue follow-up",IF(OR(R23="Open",R23="In progress"),"Open - keep working it","OK")))) -> 0
A24: =IF(B24="","","IN-"&TEXT(ROW()-4,"000")) -> 0 | U24: =IF(B24="","",IF(OR(R24="Resolved",R24="Closed"),"Closed",TEXT(TODAY()-B24,"0")&" days")) -> 0 | W24: =IF(B24="","",IF(N24<>"Yes","Action - notify the owner",IF(AND(P24="Yes",Q24<>"",Q24<TODAY(),R24<>"Resolved",R24<>"Closed"),"Overdue follow-up",IF(OR(R24="Open",R24="In progress"),"Open - keep working it","OK")))) -> 0
A25: =IF(B25="","","IN-"&TEXT(ROW()-4,"000")) -> 0 | U25: =IF(B25="","",IF(OR(R25="Resolved",R25="Closed"),"Closed",TEXT(TODAY()-B25,"0")&" days")) -> 0 | W25: =IF(B25="","",IF(N25<>"Yes","Action - notify the owner",IF(AND(P25="Yes",Q25<>"",Q25<TODAY(),R25<>"Resolved",R25<>"Closed"),"Overdue follow-up",IF(OR(R25="Open",R25="In progress"),"Open - keep working it","OK")))) -> 0
A26: =IF(B26="","","IN-"&TEXT(ROW()-4,"000")) -> 0 | U26: =IF(B26="","",IF(OR(R26="Resolved",R26="Closed"),"Closed",TEXT(TODAY()-B26,"0")&" days")) -> 0 | W26: =IF(B26="","",IF(N26<>"Yes","Action - notify the owner",IF(AND(P26="Yes",Q26<>"",Q26<TODAY(),R26<>"Resolved",R26<>"Closed"),"Overdue follow-up",IF(OR(R26="Open",R26="In progress"),"Open - keep working it","OK")))) -> 0
A27: =IF(B27="","","IN-"&TEXT(ROW()-4,"000")) -> 0 | U27: =IF(B27="","",IF(OR(R27="Resolved",R27="Closed"),"Closed",TEXT(TODAY()-B27,"0")&" days")) -> 0 | W27: =IF(B27="","",IF(N27<>"Yes","Action - notify the owner",IF(AND(P27="Yes",Q27<>"",Q27<TODAY(),R27<>"Resolved",R27<>"Closed"),"Overdue follow-up",IF(OR(R27="Open",R27="In progress"),"Open - keep working it","OK")))) -> 0
A28: =IF(B28="","","IN-"&TEXT(ROW()-4,"000")) -> 0 | U28: =IF(B28="","",IF(OR(R28="Resolved",R28="Closed"),"Closed",TEXT(TODAY()-B28,"0")&" days")) -> 0 | W28: =IF(B28="","",IF(N28<>"Yes","Action - notify the owner",IF(AND(P28="Yes",Q28<>"",Q28<TODAY(),R28<>"Resolved",R28<>"Closed"),"Overdue follow-up",IF(OR(R28="Open",R28="In progress"),"Open - keep working it","OK")))) -> 0
A29: =IF(B29="","","IN-"&TEXT(ROW()-4,"000")) -> 0 | U29: =IF(B29="","",IF(OR(R29="Resolved",R29="Closed"),"Closed",TEXT(TODAY()-B29,"0")&" days")) -> 0 | W29: =IF(B29="","",IF(N29<>"Yes","Action - notify the owner",IF(AND(P29="Yes",Q29<>"",Q29<TODAY(),R29<>"Resolved",R29<>"Closed"),"Overdue follow-up",IF(OR(R29="Open",R29="In progress"),"Open - keep working it","OK")))) -> 0
... A117: =IF(B117="","","IN-"&TEXT(ROW()-4,"000")) -> 0 | U117: =IF(B117="","",IF(OR(R117="Resolved",R117="Closed"),"Closed",TEXT(TODAY()-B117,"0")&" days")) -> 0 | W117: =IF(B117="","",IF(N117<>"Yes","Action - notify the owner",IF(AND(P117="Yes",Q117<>"",Q117<TODAY(),R117<>"Resolved",R117<>"Closed"),"Overdue follow-up",IF(OR(R117="Open",R117="In progress"),"Open - keep working it","OK")))) -> 0

Sheet Messages
A1: Client Communication, Feedback & Complaints | R1: Novality Store | v1.0.0
A2: Every confirmation, reminder, update, review and complaint in one searchable history.
A3: > Start Here | C3: > Dashboard | E3: > Clients | G3: > Pets | I3: > Bookings | K3: > Visit Log | M3: > Invoices | O3: > Reminders | Q3: > Help
A4: ID | B4: Date | C4: Client | D4: Message type | E4: Channel | F4: Direction | G4: Summary | H4: Reply received | I4: Satisfaction (1-5) | J4: Feedback / review | K4: Complaint? | L4: Issue raised | M4: Resolution status | N4: Resolved on | O4: Follow-up due | P4: Follow-up done | Q4: Days open | R4: Notes | S4: Month | T4: Action needed
A5: =IF(B5="","","MSG-"&TEXT(ROW()-4,"0000")) -> 0 | Q5: =IF(AND(K5="Yes",M5<>"Resolved",B5<>""),TODAY()-B5,"") -> 0 | S5: =IF(B5="","",TEXT(B5,"yyyy-mm")) -> 0 | T5: =IF(B5="","",IF(AND(K5="Yes",M5<>"Resolved"),"Action - unresolved complaint",IF(AND(O5<>"",O5<TODAY(),P5<>"Yes"),"Overdue follow-up",IF(AND(O5<>"",O5-TODAY()<=ReminderLeadDays,P5<>"Yes"),"Follow-up due soon","OK")))) -> 0
A6: =IF(B6="","","MSG-"&TEXT(ROW()-4,"0000")) -> 0 | Q6: =IF(AND(K6="Yes",M6<>"Resolved",B6<>""),TODAY()-B6,"") -> 0 | S6: =IF(B6="","",TEXT(B6,"yyyy-mm")) -> 0 | T6: =IF(B6="","",IF(AND(K6="Yes",M6<>"Resolved"),"Action - unresolved complaint",IF(AND(O6<>"",O6<TODAY(),P6<>"Yes"),"Overdue follow-up",IF(AND(O6<>"",O6-TODAY()<=ReminderLeadDays,P6<>"Yes"),"Follow-up due soon","OK")))) -> 0
A7: =IF(B7="","","MSG-"&TEXT(ROW()-4,"0000")) -> 0 | Q7: =IF(AND(K7="Yes",M7<>"Resolved",B7<>""),TODAY()-B7,"") -> 0 | S7: =IF(B7="","",TEXT(B7,"yyyy-mm")) -> 0 | T7: =IF(B7="","",IF(AND(K7="Yes",M7<>"Resolved"),"Action - unresolved complaint",IF(AND(O7<>"",O7<TODAY(),P7<>"Yes"),"Overdue follow-up",IF(AND(O7<>"",O7-TODAY()<=ReminderLeadDays,P7<>"Yes"),"Follow-up due soon","OK")))) -> 0
A8: =IF(B8="","","MSG-"&TEXT(ROW()-4,"0000")) -> 0 | Q8: =IF(AND(K8="Yes",M8<>"Resolved",B8<>""),TODAY()-B8,"") -> 0 | S8: =IF(B8="","",TEXT(B8,"yyyy-mm")) -> 0 | T8: =IF(B8="","",IF(AND(K8="Yes",M8<>"Resolved"),"Action - unresolved complaint",IF(AND(O8<>"",O8<TODAY(),P8<>"Yes"),"Overdue follow-up",IF(AND(O8<>"",O8-TODAY()<=ReminderLeadDays,P8<>"Yes"),"Follow-up due soon","OK")))) -> 0
A9: =IF(B9="","","MSG-"&TEXT(ROW()-4,"0000")) -> 0 | Q9: =IF(AND(K9="Yes",M9<>"Resolved",B9<>""),TODAY()-B9,"") -> 0 | S9: =IF(B9="","",TEXT(B9,"yyyy-mm")) -> 0 | T9: =IF(B9="","",IF(AND(K9="Yes",M9<>"Resolved"),"Action - unresolved complaint",IF(AND(O9<>"",O9<TODAY(),P9<>"Yes"),"Overdue follow-up",IF(AND(O9<>"",O9-TODAY()<=ReminderLeadDays,P9<>"Yes"),"Follow-up due soon","OK")))) -> 0
A10: =IF(B10="","","MSG-"&TEXT(ROW()-4,"0000")) -> 0 | Q10: =IF(AND(K10="Yes",M10<>"Resolved",B10<>""),TODAY()-B10,"") -> 0 | S10: =IF(B10="","",TEXT(B10,"yyyy-mm")) -> 0 | T10: =IF(B10="","",IF(AND(K10="Yes",M10<>"Resolved"),"Action - unresolved complaint",IF(AND(O10<>"",O10<TODAY(),P10<>"Yes"),"Overdue follow-up",IF(AND(O10<>"",O10-TODAY()<=ReminderLeadDays,P10<>"Yes"),"Follow-up due soon","OK")))) -> 0
A11: =IF(B11="","","MSG-"&TEXT(ROW()-4,"0000")) -> 0 | Q11: =IF(AND(K11="Yes",M11<>"Resolved",B11<>""),TODAY()-B11,"") -> 0 | S11: =IF(B11="","",TEXT(B11,"yyyy-mm")) -> 0 | T11: =IF(B11="","",IF(AND(K11="Yes",M11<>"Resolved"),"Action - unresolved complaint",IF(AND(O11<>"",O11<TODAY(),P11<>"Yes"),"Overdue follow-up",IF(AND(O11<>"",O11-TODAY()<=ReminderLeadDays,P11<>"Yes"),"Follow-up due soon","OK")))) -> 0
A12: =IF(B12="","","MSG-"&TEXT(ROW()-4,"0000")) -> 0 | Q12: =IF(AND(K12="Yes",M12<>"Resolved",B12<>""),TODAY()-B12,"") -> 0 | S12: =IF(B12="","",TEXT(B12,"yyyy-mm")) -> 0 | T12: =IF(B12="","",IF(AND(K12="Yes",M12<>"Resolved"),"Action - unresolved complaint",IF(AND(O12<>"",O12<TODAY(),P12<>"Yes"),"Overdue follow-up",IF(AND(O12<>"",O12-TODAY()<=ReminderLeadDays,P12<>"Yes"),"Follow-up due soon","OK")))) -> 0
A13: =IF(B13="","","MSG-"&TEXT(ROW()-4,"0000")) -> 0 | Q13: =IF(AND(K13="Yes",M13<>"Resolved",B13<>""),TODAY()-B13,"") -> 0 | S13: =IF(B13="","",TEXT(B13,"yyyy-mm")) -> 0 | T13: =IF(B13="","",IF(AND(K13="Yes",M13<>"Resolved"),"Action - unresolved complaint",IF(AND(O13<>"",O13<TODAY(),P13<>"Yes"),"Overdue follow-up",IF(AND(O13<>"",O13-TODAY()<=ReminderLeadDays,P13<>"Yes"),"Follow-up due soon","OK")))) -> 0
A14: =IF(B14="","","MSG-"&TEXT(ROW()-4,"0000")) -> 0 | Q14: =IF(AND(K14="Yes",M14<>"Resolved",B14<>""),TODAY()-B14,"") -> 0 | S14: =IF(B14="","",TEXT(B14,"yyyy-mm")) -> 0 | T14: =IF(B14="","",IF(AND(K14="Yes",M14<>"Resolved"),"Action - unresolved complaint",IF(AND(O14<>"",O14<TODAY(),P14<>"Yes"),"Overdue follow-up",IF(AND(O14<>"",O14-TODAY()<=ReminderLeadDays,P14<>"Yes"),"Follow-up due soon","OK")))) -> 0
A15: =IF(B15="","","MSG-"&TEXT(ROW()-4,"0000")) -> 0 | Q15: =IF(AND(K15="Yes",M15<>"Resolved",B15<>""),TODAY()-B15,"") -> 0 | S15: =IF(B15="","",TEXT(B15,"yyyy-mm")) -> 0 | T15: =IF(B15="","",IF(AND(K15="Yes",M15<>"Resolved"),"Action - unresolved complaint",IF(AND(O15<>"",O15<TODAY(),P15<>"Yes"),"Overdue follow-up",IF(AND(O15<>"",O15-TODAY()<=ReminderLeadDays,P15<>"Yes"),"Follow-up due soon","OK")))) -> 0
A16: =IF(B16="","","MSG-"&TEXT(ROW()-4,"0000")) -> 0 | Q16: =IF(AND(K16="Yes",M16<>"Resolved",B16<>""),TODAY()-B16,"") -> 0 | S16: =IF(B16="","",TEXT(B16,"yyyy-mm")) -> 0 | T16: =IF(B16="","",IF(AND(K16="Yes",M16<>"Resolved"),"Action - unresolved complaint",IF(AND(O16<>"",O16<TODAY(),P16<>"Yes"),"Overdue follow-up",IF(AND(O16<>"",O16-TODAY()<=ReminderLeadDays,P16<>"Yes"),"Follow-up due soon","OK")))) -> 0
... A204: =IF(B204="","","MSG-"&TEXT(ROW()-4,"0000")) -> 0 | Q204: =IF(AND(K204="Yes",M204<>"Resolved",B204<>""),TODAY()-B204,"") -> 0 | S204: =IF(B204="","",TEXT(B204,"yyyy-mm")) -> 0 | T204: =IF(B204="","",IF(AND(K204="Yes",M204<>"Resolved"),"Action - unresolved complaint",IF(AND(O204<>"",O204<TODAY(),P204<>"Yes"),"Overdue follow-up",IF(AND(O204<>"",O204-TODAY()<=ReminderLeadDays,P204<>"Yes"),"Follow-up due soon","OK")))) -> 0

Sheet Invoices
A1: Invoices | AB1: Novality Store | v1.0.0
A2: Automatic numbering, due dates, tax, balances, ageing buckets and overdue alerts - all from the booking you link.
A3: > Start Here | C3: > Dashboard | E3: > Clients | G3: > Pets | I3: > Bookings | K3: > Visit Log | M3: > Invoices | O3: > Reminders | Q3: > Help | S3: Type the client name to create the invoice number. Link a Booking ID to bill the calculated booking total, or use Qty x Rate for anything custom.
A4: Invoice no. | B4: Invoice date | C4: Due date | D4: Client | E4: Booking ref | F4: Booking total | G4: Description of service | H4: Qty | I4: Rate | J4: Line amount | K4: Additional fees | L4: Discount | M4: Subtotal | N4: Tax | O4: Invoice total | P4: Deposit received | Q4: Amount paid | R4: Refunded | S4: Balance due | T4: Invoice status | U4: Payment status | V4: Days overdue | W4: Ageing bucket | X4: Suggested late fee | Y4: Sent on | Z4: Reminder sent | AA4: Number check | AB4: Invoice notes | AC4: Month | AD4: Action needed
A5: =IF(D5="","",InvoicePrefix&TEXT(InvoiceStartNo+ROW()-5,"0000")) -> 0 | C5: =IF(B5="","",B5+PaymentTermsDays) -> 0 | F5: =IF(E5="",0,IFERROR(INDEX(Bookings!$AI$5:$AI$404,MATCH(E5,Bookings!$A$5:$A$404,0)),0)) -> 0 | J5: =IF(D5="","",IF(E5<>"",F5,ROUND(IF(H5="",0,H5)*IF(I5="",0,I5),2))) -> 0 | M5: =IF(D5="","",ROUND(J5+IF(K5="",0,K5)-IF(L5="",0,L5),2)) -> 0 | N5: =IF(M5="","",IF(TaxRegistered<>"Yes",0,IF(PricesIncludeTax="Yes",ROUND(M5-M5/(1+TaxRate),2),ROUND(M5*TaxRate,2)))) -> 0 | O5: =IF(M5="","",IF(PricesIncludeTax="Yes",M5,ROUND(M5+N5,2))) -> 0 | P5: =IF(A5="","",SUMIFS(Payments!$E$5:$E$304,Payments!$D$5:$D$304,A5,Payments!$M$5:$M$304,"Yes")) -> 0 | Q5: =IF(A5="","",SUMIFS(Payments!$K$5:$K$304,Payments!$D$5:$D$304,A5)) -> 0 | R5: =IF(A5="","",SUMIFS(Payments!$J$5:$J$304,Payments!$D$5:$D$304,A5)) -> 0 | S5: =IF(D5="","",ROUND(IF(T5="Cancelled",0,O5-Q5),2)) -> 0 | U5: =IF(A5="","",IF(T5="Cancelled","Cancelled",IF(S5<=0.004,"Paid",IF(Q5>0.004,IF(AND(C5<>"",TODAY()>C5),"Overdue - part paid","Partially paid"),IF(AND(C5<>"",TODAY()>C5),"Overdue",IF(T5="Draft","Draft","Unpaid")))))) -> 0 | V5: =IF(OR(C5="",S5<=0.004),"",MAX(0,TODAY()-C5)) -> 0 | W5: =IF(A5="","",IF(S5<=0.004,"Paid",IF(V5="","Not due",IF(V5=0,"Current",IF(V5<=30,"1-30 days",IF(V5<=60,"31-60 days",IF(V5<=90,"61-90 days","90+ days"))))))) -> 0 | X5: =IF(OR(V5="",V5=0),0,ROUND(S5*LateFeePct,2)) -> 0 | AA5: =IF(A5="","",IF(COUNTIF(Invoices!$A$5:$A$304,A5)>1,"Duplicate number","OK")) -> 0 | AC5: =IF(B5="","",TEXT(B5,"yyyy-mm")) -> 0 | AD5: =IF(A5="","",IF(T5="Draft","Action - still a draft",IF(U5="Overdue","Overdue - chase payment",IF(U5="Overdue - part paid","Overdue - chase the balance",IF(AND(S5>0.004,C5<>"",C5-TODAY()<=ReminderLeadDays,C5>=TODAY()),"Due soon - send a reminder","OK"))))) -> 0
A6: =IF(D6="","",InvoicePrefix&TEXT(InvoiceStartNo+ROW()-5,"0000")) -> 0 | C6: =IF(B6="","",B6+PaymentTermsDays) -> 0 | F6: =IF(E6="",0,IFERROR(INDEX(Bookings!$AI$5:$AI$404,MATCH(E6,Bookings!$A$5:$A$404,0)),0)) -> 0 | J6: =IF(D6="","",IF(E6<>"",F6,ROUND(IF(H6="",0,H6)*IF(I6="",0,I6),2))) -> 0 | M6: =IF(D6="","",ROUND(J6+IF(K6="",0,K6)-IF(L6="",0,L6),2)) -> 0 | N6: =IF(M6="","",IF(TaxRegistered<>"Yes",0,IF(PricesIncludeTax="Yes",ROUND(M6-M6/(1+TaxRate),2),ROUND(M6*TaxRate,2)))) -> 0 | O6: =IF(M6="","",IF(PricesIncludeTax="Yes",M6,ROUND(M6+N6,2))) -> 0 | P6: =IF(A6="","",SUMIFS(Payments!$E$5:$E$304,Payments!$D$5:$D$304,A6,Payments!$M$5:$M$304,"Yes")) -> 0 | Q6: =IF(A6="","",SUMIFS(Payments!$K$5:$K$304,Payments!$D$5:$D$304,A6)) -> 0 | R6: =IF(A6="","",SUMIFS(Payments!$J$5:$J$304,Payments!$D$5:$D$304,A6)) -> 0 | S6: =IF(D6="","",ROUND(IF(T6="Cancelled",0,O6-Q6),2)) -> 0 | U6: =IF(A6="","",IF(T6="Cancelled","Cancelled",IF(S6<=0.004,"Paid",IF(Q6>0.004,IF(AND(C6<>"",TODAY()>C6),"Overdue - part paid","Partially paid"),IF(AND(C6<>"",TODAY()>C6),"Overdue",IF(T6="Draft","Draft","Unpaid")))))) -> 0 | V6: =IF(OR(C6="",S6<=0.004),"",MAX(0,TODAY()-C6)) -> 0 | W6: =IF(A6="","",IF(S6<=0.004,"Paid",IF(V6="","Not due",IF(V6=0,"Current",IF(V6<=30,"1-30 days",IF(V6<=60,"31-60 days",IF(V6<=90,"61-90 days","90+ days"))))))) -> 0 | X6: =IF(OR(V6="",V6=0),0,ROUND(S6*LateFeePct,2)) -> 0 | AA6: =IF(A6="","",IF(COUNTIF(Invoices!$A$5:$A$304,A6)>1,"Duplicate number","OK")) -> 0 | AC6: =IF(B6="","",TEXT(B6,"yyyy-mm")) -> 0 | AD6: =IF(A6="","",IF(T6="Draft","Action - still a draft",IF(U6="Overdue","Overdue - chase payment",IF(U6="Overdue - part paid","Overdue - chase the balance",IF(AND(S6>0.004,C6<>"",C6-TODAY()<=ReminderLeadDays,C6>=TODAY()),"Due soon - send a reminder","OK"))))) -> 0
A7: =IF(D7="","",InvoicePrefix&TEXT(InvoiceStartNo+ROW()-5,"0000")) -> 0 | C7: =IF(B7="","",B7+PaymentTermsDays) -> 0 | F7: =IF(E7="",0,IFERROR(INDEX(Bookings!$AI$5:$AI$404,MATCH(E7,Bookings!$A$5:$A$404,0)),0)) -> 0 | J7: =IF(D7="","",IF(E7<>"",F7,ROUND(IF(H7="",0,H7)*IF(I7="",0,I7),2))) -> 0 | M7: =IF(D7="","",ROUND(J7+IF(K7="",0,K7)-IF(L7="",0,L7),2)) -> 0 | N7: =IF(M7="","",IF(TaxRegistered<>"Yes",0,IF(PricesIncludeTax="Yes",ROUND(M7-M7/(1+TaxRate),2),ROUND(M7*TaxRate,2)))) -> 0 | O7: =IF(M7="","",IF(PricesIncludeTax="Yes",M7,ROUND(M7+N7,2))) -> 0 | P7: =IF(A7="","",SUMIFS(Payments!$E$5:$E$304,Payments!$D$5:$D$304,A7,Payments!$M$5:$M$304,"Yes")) -> 0 | Q7: =IF(A7="","",SUMIFS(Payments!$K$5:$K$304,Payments!$D$5:$D$304,A7)) -> 0 | R7: =IF(A7="","",SUMIFS(Payments!$J$5:$J$304,Payments!$D$5:$D$304,A7)) -> 0 | S7: =IF(D7="","",ROUND(IF(T7="Cancelled",0,O7-Q7),2)) -> 0 | U7: =IF(A7="","",IF(T7="Cancelled","Cancelled",IF(S7<=0.004,"Paid",IF(Q7>0.004,IF(AND(C7<>"",TODAY()>C7),"Overdue - part paid","Partially paid"),IF(AND(C7<>"",TODAY()>C7),"Overdue",IF(T7="Draft","Draft","Unpaid")))))) -> 0 | V7: =IF(OR(C7="",S7<=0.004),"",MAX(0,TODAY()-C7)) -> 0 | W7: =IF(A7="","",IF(S7<=0.004,"Paid",IF(V7="","Not due",IF(V7=0,"Current",IF(V7<=30,"1-30 days",IF(V7<=60,"31-60 days",IF(V7<=90,"61-90 days","90+ days"))))))) -> 0 | X7: =IF(OR(V7="",V7=0),0,ROUND(S7*LateFeePct,2)) -> 0 | AA7: =IF(A7="","",IF(COUNTIF(Invoices!$A$5:$A$304,A7)>1,"Duplicate number","OK")) -> 0 | AC7: =IF(B7="","",TEXT(B7,"yyyy-mm")) -> 0 | AD7: =IF(A7="","",IF(T7="Draft","Action - still a draft",IF(U7="Overdue","Overdue - chase payment",IF(U7="Overdue - part paid","Overdue - chase the balance",IF(AND(S7>0.004,C7<>"",C7-TODAY()<=ReminderLeadDays,C7>=TODAY()),"Due soon - send a reminder","OK"))))) -> 0
A8: =IF(D8="","",InvoicePrefix&TEXT(InvoiceStartNo+ROW()-5,"0000")) -> 0 | C8: =IF(B8="","",B8+PaymentTermsDays) -> 0 | F8: =IF(E8="",0,IFERROR(INDEX(Bookings!$AI$5:$AI$404,MATCH(E8,Bookings!$A$5:$A$404,0)),0)) -> 0 | J8: =IF(D8="","",IF(E8<>"",F8,ROUND(IF(H8="",0,H8)*IF(I8="",0,I8),2))) -> 0 | M8: =IF(D8="","",ROUND(J8+IF(K8="",0,K8)-IF(L8="",0,L8),2)) -> 0 | N8: =IF(M8="","",IF(TaxRegistered<>"Yes",0,IF(PricesIncludeTax="Yes",ROUND(M8-M8/(1+TaxRate),2),ROUND(M8*TaxRate,2)))) -> 0 | O8: =IF(M8="","",IF(PricesIncludeTax="Yes",M8,ROUND(M8+N8,2))) -> 0 | P8: =IF(A8="","",SUMIFS(Payments!$E$5:$E$304,Payments!$D$5:$D$304,A8,Payments!$M$5:$M$304,"Yes")) -> 0 | Q8: =IF(A8="","",SUMIFS(Payments!$K$5:$K$304,Payments!$D$5:$D$304,A8)) -> 0 | R8: =IF(A8="","",SUMIFS(Payments!$J$5:$J$304,Payments!$D$5:$D$304,A8)) -> 0 | S8: =IF(D8="","",ROUND(IF(T8="Cancelled",0,O8-Q8),2)) -> 0 | U8: =IF(A8="","",IF(T8="Cancelled","Cancelled",IF(S8<=0.004,"Paid",IF(Q8>0.004,IF(AND(C8<>"",TODAY()>C8),"Overdue - part paid","Partially paid"),IF(AND(C8<>"",TODAY()>C8),"Overdue",IF(T8="Draft","Draft","Unpaid")))))) -> 0 | V8: =IF(OR(C8="",S8<=0.004),"",MAX(0,TODAY()-C8)) -> 0 | W8: =IF(A8="","",IF(S8<=0.004,"Paid",IF(V8="","Not due",IF(V8=0,"Current",IF(V8<=30,"1-30 days",IF(V8<=60,"31-60 days",IF(V8<=90,"61-90 days","90+ days"))))))) -> 0 | X8: =IF(OR(V8="",V8=0),0,ROUND(S8*LateFeePct,2)) -> 0 | AA8: =IF(A8="","",IF(COUNTIF(Invoices!$A$5:$A$304,A8)>1,"Duplicate number","OK")) -> 0 | AC8: =IF(B8="","",TEXT(B8,"yyyy-mm")) -> 0 | AD8: =IF(A8="","",IF(T8="Draft","Action - still a draft",IF(U8="Overdue","Overdue - chase payment",IF(U8="Overdue - part paid","Overdue - chase the balance",IF(AND(S8>0.004,C8<>"",C8-TODAY()<=ReminderLeadDays,C8>=TODAY()),"Due soon - send a reminder","OK"))))) -> 0
A9: =IF(D9="","",InvoicePrefix&TEXT(InvoiceStartNo+ROW()-5,"0000")) -> 0 | C9: =IF(B9="","",B9+PaymentTermsDays) -> 0 | F9: =IF(E9="",0,IFERROR(INDEX(Bookings!$AI$5:$AI$404,MATCH(E9,Bookings!$A$5:$A$404,0)),0)) -> 0 | J9: =IF(D9="","",IF(E9<>"",F9,ROUND(IF(H9="",0,H9)*IF(I9="",0,I9),2))) -> 0 | M9: =IF(D9="","",ROUND(J9+IF(K9="",0,K9)-IF(L9="",0,L9),2)) -> 0 | N9: =IF(M9="","",IF(TaxRegistered<>"Yes",0,IF(PricesIncludeTax="Yes",ROUND(M9-M9/(1+TaxRate),2),ROUND(M9*TaxRate,2)))) -> 0 | O9: =IF(M9="","",IF(PricesIncludeTax="Yes",M9,ROUND(M9+N9,2))) -> 0 | P9: =IF(A9="","",SUMIFS(Payments!$E$5:$E$304,Payments!$D$5:$D$304,A9,Payments!$M$5:$M$304,"Yes")) -> 0 | Q9: =IF(A9="","",SUMIFS(Payments!$K$5:$K$304,Payments!$D$5:$D$304,A9)) -> 0 | R9: =IF(A9="","",SUMIFS(Payments!$J$5:$J$304,Payments!$D$5:$D$304,A9)) -> 0 | S9: =IF(D9="","",ROUND(IF(T9="Cancelled",0,O9-Q9),2)) -> 0 | U9: =IF(A9="","",IF(T9="Cancelled","Cancelled",IF(S9<=0.004,"Paid",IF(Q9>0.004,IF(AND(C9<>"",TODAY()>C9),"Overdue - part paid","Partially paid"),IF(AND(C9<>"",TODAY()>C9),"Overdue",IF(T9="Draft","Draft","Unpaid")))))) -> 0 | V9: =IF(OR(C9="",S9<=0.004),"",MAX(0,TODAY()-C9)) -> 0 | W9: =IF(A9="","",IF(S9<=0.004,"Paid",IF(V9="","Not due",IF(V9=0,"Current",IF(V9<=30,"1-30 days",IF(V9<=60,"31-60 days",IF(V9<=90,"61-90 days","90+ days"))))))) -> 0 | X9: =IF(OR(V9="",V9=0),0,ROUND(S9*LateFeePct,2)) -> 0 | AA9: =IF(A9="","",IF(COUNTIF(Invoices!$A$5:$A$304,A9)>1,"Duplicate number","OK")) -> 0 | AC9: =IF(B9="","",TEXT(B9,"yyyy-mm")) -> 0 | AD9: =IF(A9="","",IF(T9="Draft","Action - still a draft",IF(U9="Overdue","Overdue - chase payment",IF(U9="Overdue - part paid","Overdue - chase the balance",IF(AND(S9>0.004,C9<>"",C9-TODAY()<=ReminderLeadDays,C9>=TODAY()),"Due soon - send a reminder","OK"))))) -> 0
A10: =IF(D10="","",InvoicePrefix&TEXT(InvoiceStartNo+ROW()-5,"0000")) -> 0 | C10: =IF(B10="","",B10+PaymentTermsDays) -> 0 | F10: =IF(E10="",0,IFERROR(INDEX(Bookings!$AI$5:$AI$404,MATCH(E10,Bookings!$A$5:$A$404,0)),0)) -> 0 | J10: =IF(D10="","",IF(E10<>"",F10,ROUND(IF(H10="",0,H10)*IF(I10="",0,I10),2))) -> 0 | M10: =IF(D10="","",ROUND(J10+IF(K10="",0,K10)-IF(L10="",0,L10),2)) -> 0 | N10: =IF(M10="","",IF(TaxRegistered<>"Yes",0,IF(PricesIncludeTax="Yes",ROUND(M10-M10/(1+TaxRate),2),ROUND(M10*TaxRate,2)))) -> 0 | O10: =IF(M10="","",IF(PricesIncludeTax="Yes",M10,ROUND(M10+N10,2))) -> 0 | P10: =IF(A10="","",SUMIFS(Payments!$E$5:$E$304,Payments!$D$5:$D$304,A10,Payments!$M$5:$M$304,"Yes")) -> 0 | Q10: =IF(A10="","",SUMIFS(Payments!$K$5:$K$304,Payments!$D$5:$D$304,A10)) -> 0 | R10: =IF(A10="","",SUMIFS(Payments!$J$5:$J$304,Payments!$D$5:$D$304,A10)) -> 0 | S10: =IF(D10="","",ROUND(IF(T10="Cancelled",0,O10-Q10),2)) -> 0 | U10: =IF(A10="","",IF(T10="Cancelled","Cancelled",IF(S10<=0.004,"Paid",IF(Q10>0.004,IF(AND(C10<>"",TODAY()>C10),"Overdue - part paid","Partially paid"),IF(AND(C10<>"",TODAY()>C10),"Overdue",IF(T10="Draft","Draft","Unpaid")))))) -> 0 | V10: =IF(OR(C10="",S10<=0.004),"",MAX(0,TODAY()-C10)) -> 0 | W10: =IF(A10="","",IF(S10<=0.004,"Paid",IF(V10="","Not due",IF(V10=0,"Current",IF(V10<=30,"1-30 days",IF(V10<=60,"31-60 days",IF(V10<=90,"61-90 days","90+ days"))))))) -> 0 | X10: =IF(OR(V10="",V10=0),0,ROUND(S10*LateFeePct,2)) -> 0 | AA10: =IF(A10="","",IF(COUNTIF(Invoices!$A$5:$A$304,A10)>1,"Duplicate number","OK")) -> 0 | AC10: =IF(B10="","",TEXT(B10,"yyyy-mm")) -> 0 | AD10: =IF(A10="","",IF(T10="Draft","Action - still a draft",IF(U10="Overdue","Overdue - chase payment",IF(U10="Overdue - part paid","Overdue - chase the balance",IF(AND(S10>0.004,C10<>"",C10-TODAY()<=ReminderLeadDays,C10>=TODAY()),"Due soon - send a reminder","OK"))))) -> 0
A11: =IF(D11="","",InvoicePrefix&TEXT(InvoiceStartNo+ROW()-5,"0000")) -> 0 | C11: =IF(B11="","",B11+PaymentTermsDays) -> 0 | F11: =IF(E11="",0,IFERROR(INDEX(Bookings!$AI$5:$AI$404,MATCH(E11,Bookings!$A$5:$A$404,0)),0)) -> 0 | J11: =IF(D11="","",IF(E11<>"",F11,ROUND(IF(H11="",0,H11)*IF(I11="",0,I11),2))) -> 0 | M11: =IF(D11="","",ROUND(J11+IF(K11="",0,K11)-IF(L11="",0,L11),2)) -> 0 | N11: =IF(M11="","",IF(TaxRegistered<>"Yes",0,IF(PricesIncludeTax="Yes",ROUND(M11-M11/(1+TaxRate),2),ROUND(M11*TaxRate,2)))) -> 0 | O11: =IF(M11="","",IF(PricesIncludeTax="Yes",M11,ROUND(M11+N11,2))) -> 0 | P11: =IF(A11="","",SUMIFS(Payments!$E$5:$E$304,Payments!$D$5:$D$304,A11,Payments!$M$5:$M$304,"Yes")) -> 0 | Q11: =IF(A11="","",SUMIFS(Payments!$K$5:$K$304,Payments!$D$5:$D$304,A11)) -> 0 | R11: =IF(A11="","",SUMIFS(Payments!$J$5:$J$304,Payments!$D$5:$D$304,A11)) -> 0 | S11: =IF(D11="","",ROUND(IF(T11="Cancelled",0,O11-Q11),2)) -> 0 | U11: =IF(A11="","",IF(T11="Cancelled","Cancelled",IF(S11<=0.004,"Paid",IF(Q11>0.004,IF(AND(C11<>"",TODAY()>C11),"Overdue - part paid","Partially paid"),IF(AND(C11<>"",TODAY()>C11),"Overdue",IF(T11="Draft","Draft","Unpaid")))))) -> 0 | V11: =IF(OR(C11="",S11<=0.004),"",MAX(0,TODAY()-C11)) -> 0 | W11: =IF(A11="","",IF(S11<=0.004,"Paid",IF(V11="","Not due",IF(V11=0,"Current",IF(V11<=30,"1-30 days",IF(V11<=60,"31-60 days",IF(V11<=90,"61-90 days","90+ days"))))))) -> 0 | X11: =IF(OR(V11="",V11=0),0,ROUND(S11*LateFeePct,2)) -> 0 | AA11: =IF(A11="","",IF(COUNTIF(Invoices!$A$5:$A$304,A11)>1,"Duplicate number","OK")) -> 0 | AC11: =IF(B11="","",TEXT(B11,"yyyy-mm")) -> 0 | AD11: =IF(A11="","",IF(T11="Draft","Action - still a draft",IF(U11="Overdue","Overdue - chase payment",IF(U11="Overdue - part paid","Overdue - chase the balance",IF(AND(S11>0.004,C11<>"",C11-TODAY()<=ReminderLeadDays,C11>=TODAY()),"Due soon - send a reminder","OK"))))) -> 0
A12: =IF(D12="","",InvoicePrefix&TEXT(InvoiceStartNo+ROW()-5,"0000")) -> 0 | C12: =IF(B12="","",B12+PaymentTermsDays) -> 0 | F12: =IF(E12="",0,IFERROR(INDEX(Bookings!$AI$5:$AI$404,MATCH(E12,Bookings!$A$5:$A$404,0)),0)) -> 0 | J12: =IF(D12="","",IF(E12<>"",F12,ROUND(IF(H12="",0,H12)*IF(I12="",0,I12),2))) -> 0 | M12: =IF(D12="","",ROUND(J12+IF(K12="",0,K12)-IF(L12="",0,L12),2)) -> 0 | N12: =IF(M12="","",IF(TaxRegistered<>"Yes",0,IF(PricesIncludeTax="Yes",ROUND(M12-M12/(1+TaxRate),2),ROUND(M12*TaxRate,2)))) -> 0 | O12: =IF(M12="","",IF(PricesIncludeTax="Yes",M12,ROUND(M12+N12,2))) -> 0 | P12: =IF(A12="","",SUMIFS(Payments!$E$5:$E$304,Payments!$D$5:$D$304,A12,Payments!$M$5:$M$304,"Yes")) -> 0 | Q12: =IF(A12="","",SUMIFS(Payments!$K$5:$K$304,Payments!$D$5:$D$304,A12)) -> 0 | R12: =IF(A12="","",SUMIFS(Payments!$J$5:$J$304,Payments!$D$5:$D$304,A12)) -> 0 | S12: =IF(D12="","",ROUND(IF(T12="Cancelled",0,O12-Q12),2)) -> 0 | U12: =IF(A12="","",IF(T12="Cancelled","Cancelled",IF(S12<=0.004,"Paid",IF(Q12>0.004,IF(AND(C12<>"",TODAY()>C12),"Overdue - part paid","Partially paid"),IF(AND(C12<>"",TODAY()>C12),"Overdue",IF(T12="Draft","Draft","Unpaid")))))) -> 0 | V12: =IF(OR(C12="",S12<=0.004),"",MAX(0,TODAY()-C12)) -> 0 | W12: =IF(A12="","",IF(S12<=0.004,"Paid",IF(V12="","Not due",IF(V12=0,"Current",IF(V12<=30,"1-30 days",IF(V12<=60,"31-60 days",IF(V12<=90,"61-90 days","90+ days"))))))) -> 0 | X12: =IF(OR(V12="",V12=0),0,ROUND(S12*LateFeePct,2)) -> 0 | AA12: =IF(A12="","",IF(COUNTIF(Invoices!$A$5:$A$304,A12)>1,"Duplicate number","OK")) -> 0 | AC12: =IF(B12="","",TEXT(B12,"yyyy-mm")) -> 0 | AD12: =IF(A12="","",IF(T12="Draft","Action - still a draft",IF(U12="Overdue","Overdue - chase payment",IF(U12="Overdue - part paid","Overdue - chase the balance",IF(AND(S12>0.004,C12<>"",C12-TODAY()<=ReminderLeadDays,C12>=TODAY()),"Due soon - send a reminder","OK"))))) -> 0
A13: =IF(D13="","",InvoicePrefix&TEXT(InvoiceStartNo+ROW()-5,"0000")) -> 0 | C13: =IF(B13="","",B13+PaymentTermsDays) -> 0 | F13: =IF(E13="",0,IFERROR(INDEX(Bookings!$AI$5:$AI$404,MATCH(E13,Bookings!$A$5:$A$404,0)),0)) -> 0 | J13: =IF(D13="","",IF(E13<>"",F13,ROUND(IF(H13="",0,H13)*IF(I13="",0,I13),2))) -> 0 | M13: =IF(D13="","",ROUND(J13+IF(K13="",0,K13)-IF(L13="",0,L13),2)) -> 0 | N13: =IF(M13="","",IF(TaxRegistered<>"Yes",0,IF(PricesIncludeTax="Yes",ROUND(M13-M13/(1+TaxRate),2),ROUND(M13*TaxRate,2)))) -> 0 | O13: =IF(M13="","",IF(PricesIncludeTax="Yes",M13,ROUND(M13+N13,2))) -> 0 | P13: =IF(A13="","",SUMIFS(Payments!$E$5:$E$304,Payments!$D$5:$D$304,A13,Payments!$M$5:$M$304,"Yes")) -> 0 | Q13: =IF(A13="","",SUMIFS(Payments!$K$5:$K$304,Payments!$D$5:$D$304,A13)) -> 0 | R13: =IF(A13="","",SUMIFS(Payments!$J$5:$J$304,Payments!$D$5:$D$304,A13)) -> 0 | S13: =IF(D13="","",ROUND(IF(T13="Cancelled",0,O13-Q13),2)) -> 0 | U13: =IF(A13="","",IF(T13="Cancelled","Cancelled",IF(S13<=0.004,"Paid",IF(Q13>0.004,IF(AND(C13<>"",TODAY()>C13),"Overdue - part paid","Partially paid"),IF(AND(C13<>"",TODAY()>C13),"Overdue",IF(T13="Draft","Draft","Unpaid")))))) -> 0 | V13: =IF(OR(C13="",S13<=0.004),"",MAX(0,TODAY()-C13)) -> 0 | W13: =IF(A13="","",IF(S13<=0.004,"Paid",IF(V13="","Not due",IF(V13=0,"Current",IF(V13<=30,"1-30 days",IF(V13<=60,"31-60 days",IF(V13<=90,"61-90 days","90+ days"))))))) -> 0 | X13: =IF(OR(V13="",V13=0),0,ROUND(S13*LateFeePct,2)) -> 0 | AA13: =IF(A13="","",IF(COUNTIF(Invoices!$A$5:$A$304,A13)>1,"Duplicate number","OK")) -> 0 | AC13: =IF(B13="","",TEXT(B13,"yyyy-mm")) -> 0 | AD13: =IF(A13="","",IF(T13="Draft","Action - still a draft",IF(U13="Overdue","Overdue - chase payment",IF(U13="Overdue - part paid","Overdue - chase the balance",IF(AND(S13>0.004,C13<>"",C13-TODAY()<=ReminderLeadDays,C13>=TODAY()),"Due soon - send a reminder","OK"))))) -> 0
A14: =IF(D14="","",InvoicePrefix&TEXT(InvoiceStartNo+ROW()-5,"0000")) -> 0 | C14: =IF(B14="","",B14+PaymentTermsDays) -> 0 | F14: =IF(E14="",0,IFERROR(INDEX(Bookings!$AI$5:$AI$404,MATCH(E14,Bookings!$A$5:$A$404,0)),0)) -> 0 | J14: =IF(D14="","",IF(E14<>"",F14,ROUND(IF(H14="",0,H14)*IF(I14="",0,I14),2))) -> 0 | M14: =IF(D14="","",ROUND(J14+IF(K14="",0,K14)-IF(L14="",0,L14),2)) -> 0 | N14: =IF(M14="","",IF(TaxRegistered<>"Yes",0,IF(PricesIncludeTax="Yes",ROUND(M14-M14/(1+TaxRate),2),ROUND(M14*TaxRate,2)))) -> 0 | O14: =IF(M14="","",IF(PricesIncludeTax="Yes",M14,ROUND(M14+N14,2))) -> 0 | P14: =IF(A14="","",SUMIFS(Payments!$E$5:$E$304,Payments!$D$5:$D$304,A14,Payments!$M$5:$M$304,"Yes")) -> 0 | Q14: =IF(A14="","",SUMIFS(Payments!$K$5:$K$304,Payments!$D$5:$D$304,A14)) -> 0 | R14: =IF(A14="","",SUMIFS(Payments!$J$5:$J$304,Payments!$D$5:$D$304,A14)) -> 0 | S14: =IF(D14="","",ROUND(IF(T14="Cancelled",0,O14-Q14),2)) -> 0 | U14: =IF(A14="","",IF(T14="Cancelled","Cancelled",IF(S14<=0.004,"Paid",IF(Q14>0.004,IF(AND(C14<>"",TODAY()>C14),"Overdue - part paid","Partially paid"),IF(AND(C14<>"",TODAY()>C14),"Overdue",IF(T14="Draft","Draft","Unpaid")))))) -> 0 | V14: =IF(OR(C14="",S14<=0.004),"",MAX(0,TODAY()-C14)) -> 0 | W14: =IF(A14="","",IF(S14<=0.004,"Paid",IF(V14="","Not due",IF(V14=0,"Current",IF(V14<=30,"1-30 days",IF(V14<=60,"31-60 days",IF(V14<=90,"61-90 days","90+ days"))))))) -> 0 | X14: =IF(OR(V14="",V14=0),0,ROUND(S14*LateFeePct,2)) -> 0 | AA14: =IF(A14="","",IF(COUNTIF(Invoices!$A$5:$A$304,A14)>1,"Duplicate number","OK")) -> 0 | AC14: =IF(B14="","",TEXT(B14,"yyyy-mm")) -> 0 | AD14: =IF(A14="","",IF(T14="Draft","Action - still a draft",IF(U14="Overdue","Overdue - chase payment",IF(U14="Overdue - part paid","Overdue - chase the balance",IF(AND(S14>0.004,C14<>"",C14-TODAY()<=ReminderLeadDays,C14>=TODAY()),"Due soon - send a reminder","OK"))))) -> 0
A15: =IF(D15="","",InvoicePrefix&TEXT(InvoiceStartNo+ROW()-5,"0000")) -> 0 | C15: =IF(B15="","",B15+PaymentTermsDays) -> 0 | F15: =IF(E15="",0,IFERROR(INDEX(Bookings!$AI$5:$AI$404,MATCH(E15,Bookings!$A$5:$A$404,0)),0)) -> 0 | J15: =IF(D15="","",IF(E15<>"",F15,ROUND(IF(H15="",0,H15)*IF(I15="",0,I15),2))) -> 0 | M15: =IF(D15="","",ROUND(J15+IF(K15="",0,K15)-IF(L15="",0,L15),2)) -> 0 | N15: =IF(M15="","",IF(TaxRegistered<>"Yes",0,IF(PricesIncludeTax="Yes",ROUND(M15-M15/(1+TaxRate),2),ROUND(M15*TaxRate,2)))) -> 0 | O15: =IF(M15="","",IF(PricesIncludeTax="Yes",M15,ROUND(M15+N15,2))) -> 0 | P15: =IF(A15="","",SUMIFS(Payments!$E$5:$E$304,Payments!$D$5:$D$304,A15,Payments!$M$5:$M$304,"Yes")) -> 0 | Q15: =IF(A15="","",SUMIFS(Payments!$K$5:$K$304,Payments!$D$5:$D$304,A15)) -> 0 | R15: =IF(A15="","",SUMIFS(Payments!$J$5:$J$304,Payments!$D$5:$D$304,A15)) -> 0 | S15: =IF(D15="","",ROUND(IF(T15="Cancelled",0,O15-Q15),2)) -> 0 | U15: =IF(A15="","",IF(T15="Cancelled","Cancelled",IF(S15<=0.004,"Paid",IF(Q15>0.004,IF(AND(C15<>"",TODAY()>C15),"Overdue - part paid","Partially paid"),IF(AND(C15<>"",TODAY()>C15),"Overdue",IF(T15="Draft","Draft","Unpaid")))))) -> 0 | V15: =IF(OR(C15="",S15<=0.004),"",MAX(0,TODAY()-C15)) -> 0 | W15: =IF(A15="","",IF(S15<=0.004,"Paid",IF(V15="","Not due",IF(V15=0,"Current",IF(V15<=30,"1-30 days",IF(V15<=60,"31-60 days",IF(V15<=90,"61-90 days","90+ days"))))))) -> 0 | X15: =IF(OR(V15="",V15=0),0,ROUND(S15*LateFeePct,2)) -> 0 | AA15: =IF(A15="","",IF(COUNTIF(Invoices!$A$5:$A$304,A15)>1,"Duplicate number","OK")) -> 0 | AC15: =IF(B15="","",TEXT(B15,"yyyy-mm")) -> 0 | AD15: =IF(A15="","",IF(T15="Draft","Action - still a draft",IF(U15="Overdue","Overdue - chase payment",IF(U15="Overdue - part paid","Overdue - chase the balance",IF(AND(S15>0.004,C15<>"",C15-TODAY()<=ReminderLeadDays,C15>=TODAY()),"Due soon - send a reminder","OK"))))) -> 0
A16: =IF(D16="","",InvoicePrefix&TEXT(InvoiceStartNo+ROW()-5,"0000")) -> 0 | C16: =IF(B16="","",B16+PaymentTermsDays) -> 0 | F16: =IF(E16="",0,IFERROR(INDEX(Bookings!$AI$5:$AI$404,MATCH(E16,Bookings!$A$5:$A$404,0)),0)) -> 0 | J16: =IF(D16="","",IF(E16<>"",F16,ROUND(IF(H16="",0,H16)*IF(I16="",0,I16),2))) -> 0 | M16: =IF(D16="","",ROUND(J16+IF(K16="",0,K16)-IF(L16="",0,L16),2)) -> 0 | N16: =IF(M16="","",IF(TaxRegistered<>"Yes",0,IF(PricesIncludeTax="Yes",ROUND(M16-M16/(1+TaxRate),2),ROUND(M16*TaxRate,2)))) -> 0 | O16: =IF(M16="","",IF(PricesIncludeTax="Yes",M16,ROUND(M16+N16,2))) -> 0 | P16: =IF(A16="","",SUMIFS(Payments!$E$5:$E$304,Payments!$D$5:$D$304,A16,Payments!$M$5:$M$304,"Yes")) -> 0 | Q16: =IF(A16="","",SUMIFS(Payments!$K$5:$K$304,Payments!$D$5:$D$304,A16)) -> 0 | R16: =IF(A16="","",SUMIFS(Payments!$J$5:$J$304,Payments!$D$5:$D$304,A16)) -> 0 | S16: =IF(D16="","",ROUND(IF(T16="Cancelled",0,O16-Q16),2)) -> 0 | U16: =IF(A16="","",IF(T16="Cancelled","Cancelled",IF(S16<=0.004,"Paid",IF(Q16>0.004,IF(AND(C16<>"",TODAY()>C16),"Overdue - part paid","Partially paid"),IF(AND(C16<>"",TODAY()>C16),"Overdue",IF(T16="Draft","Draft","Unpaid")))))) -> 0 | V16: =IF(OR(C16="",S16<=0.004),"",MAX(0,TODAY()-C16)) -> 0 | W16: =IF(A16="","",IF(S16<=0.004,"Paid",IF(V16="","Not due",IF(V16=0,"Current",IF(V16<=30,"1-30 days",IF(V16<=60,"31-60 days",IF(V16<=90,"61-90 days","90+ days"))))))) -> 0 | X16: =IF(OR(V16="",V16=0),0,ROUND(S16*LateFeePct,2)) -> 0 | AA16: =IF(A16="","",IF(COUNTIF(Invoices!$A$5:$A$304,A16)>1,"Duplicate number","OK")) -> 0 | AC16: =IF(B16="","",TEXT(B16,"yyyy-mm")) -> 0 | AD16: =IF(A16="","",IF(T16="Draft","Action - still a draft",IF(U16="Overdue","Overdue - chase payment",IF(U16="Overdue - part paid","Overdue - chase the balance",IF(AND(S16>0.004,C16<>"",C16-TODAY()<=ReminderLeadDays,C16>=TODAY()),"Due soon - send a reminder","OK"))))) -> 0
... A304: =IF(D304="","",InvoicePrefix&TEXT(InvoiceStartNo+ROW()-5,"0000")) -> 0 | C304: =IF(B304="","",B304+PaymentTermsDays) -> 0 | F304: =IF(E304="",0,IFERROR(INDEX(Bookings!$AI$5:$AI$404,MATCH(E304,Bookings!$A$5:$A$404,0)),0)) -> 0 | J304: =IF(D304="","",IF(E304<>"",F304,ROUND(IF(H304="",0,H304)*IF(I304="",0,I304),2))) -> 0 | M304: =IF(D304="","",ROUND(J304+IF(K304="",0,K304)-IF(L304="",0,L304),2)) -> 0 | N304: =IF(M304="","",IF(TaxRegistered<>"Yes",0,IF(PricesIncludeTax="Yes",ROUND(M304-M304/(1+TaxRate),2),ROUND(M304*TaxRate,2)))) -> 0 | O304: =IF(M304="","",IF(PricesIncludeTax="Yes",M304,ROUND(M304+N304,2))) -> 0 | P304: =IF(A304="","",SUMIFS(Payments!$E$5:$E$304,Payments!$D$5:$D$304,A304,Payments!$M$5:$M$304,"Yes")) -> 0 | Q304: =IF(A304="","",SUMIFS(Payments!$K$5:$K$304,Payments!$D$5:$D$304,A304)) -> 0 | R304: =IF(A304="","",SUMIFS(Payments!$J$5:$J$304,Payments!$D$5:$D$304,A304)) -> 0 | S304: =IF(D304="","",ROUND(IF(T304="Cancelled",0,O304-Q304),2)) -> 0 | U304: =IF(A304="","",IF(T304="Cancelled","Cancelled",IF(S304<=0.004,"Paid",IF(Q304>0.004,IF(AND(C304<>"",TODAY()>C304),"Overdue - part paid","Partially paid"),IF(AND(C304<>"",TODAY()>C304),"Overdue",IF(T304="Draft","Draft","Unpaid")))))) -> 0 | V304: =IF(OR(C304="",S304<=0.004),"",MAX(0,TODAY()-C304)) -> 0 | W304: =IF(A304="","",IF(S304<=0.004,"Paid",IF(V304="","Not due",IF(V304=0,"Current",IF(V304<=30,"1-30 days",IF(V304<=60,"31-60 days",IF(V304<=90,"61-90 days","90+ days"))))))) -> 0 | X304: =IF(OR(V304="",V304=0),0,ROUND(S304*LateFeePct,2)) -> 0 | AA304: =IF(A304="","",IF(COUNTIF(Invoices!$A$5:$A$304,A304)>1,"Duplicate number","OK")) -> 0 | AC304: =IF(B304="","",TEXT(B304,"yyyy-mm")) -> 0 | AD304: =IF(A304="","",IF(T304="Draft","Action - still a draft",IF(U304="Overdue","Overdue - chase payment",IF(U304="Overdue - part paid","Overdue - chase the balance",IF(AND(S304>0.004,C304<>"",C304-TODAY()<=ReminderLeadDays,C304>=TODAY()),"Due soon - send a reminder","OK"))))) -> 0

Sheet Payments
A1: Payment Tracking | R1: Novality Store | v1.0.0
A2: Every cash, card, transfer, wallet and deposit payment, with tips, refunds and bank reconciliation.
