Workbook
Name AppointmentDates: OFFSET(Appointments!$B$5,0,0,MAX(1,COUNTIF(Appointments!$B$5:$B$1204,"?*")),1)
Name AppointmentIDs: OFFSET(Appointments!$A$5,0,0,MAX(1,COUNTIF(Appointments!$A$5:$A$1204,"?*")),1)
Name AppointmentPrefix: Settings!$C$106
Name AppointmentStatus: OFFSET(Appointments!$M$5,0,0,MAX(1,COUNTIF(Appointments!$M$5:$M$1204,"?*")),1)
Name AppointmentStatusList: Settings!$A$148:$A$161
Name ApprenticeCommission: Settings!$D$55
Name BudgetAmount: 'Goals & Budget'!$C$45:$C$64
Name BudgetCategory: 'Goals & Budget'!$B$45:$B$64
Name BudgetMonthlyTotal: 'Goals & Budget'!$C$65
Name CampaignPrefix: Settings!$G$107
Name CampaignStatusList: Settings!$D$232:$D$242
Name CancellationHours: Settings!$D$44
Name CancelReasonList: Settings!$G$148:$G$163
Name CardFeeFixed: Settings!$D$41
Name CardFeePercent: Settings!$D$40
Name ChairHoursWeek: Settings!$D$31
Name ChairRentWeek: Settings!$D$59
Name Chairs: Settings!$D$30
Name ClientCount: Settings!$D$117
Name ClientList: OFFSET(Clients!$A$5,0,0,MAX(1,COUNTIF(Clients!$A$5:$A$504,"?*")),1)
Name ClientNames: OFFSET(Clients!$B$5,0,0,MAX(1,COUNTIF(Clients!$B$5:$B$504,"?*")),1)
Name ClientPrefix: Settings!$C$103
Name ClientSegments: OFFSET(Clients!$AM$5,0,0,MAX(1,COUNTIF(Clients!$AM$5:$AM$504,"?*")),1)
Name ClientStatusList: Settings!$A$169:$A$181
Name ClientTargetYear: 'Goals & Budget'!$D$20
Name CloseHour: Settings!$D$28
Name CommissionMethodList: Settings!$G$185:$G$198
Name CommissionOn: Settings!$D$58
Name CommissionPrefix: Settings!$C$109
Name ContactList: Settings!$J$148:$J$159
Name CurrencySign: Settings!$D$19
Name DashKey: Dashboard!$H$5
Name DashPrevKey: Dashboard!$K$5
Name DefaultHourly: Settings!$D$56
Name DepositPercent: Settings!$D$42
Name DepositThreshold: Settings!$D$43
Name ExpenseAmounts: OFFSET(Expenses!$F$5,0,0,MAX(1,COUNTIF(Expenses!$F$5:$F$604,"?*")),1)
Name ExpenseCategoriesCol: OFFSET(Expenses!$C$5,0,0,MAX(1,COUNTIF(Expenses!$C$5:$C$604,"?*")),1)
Name ExpenseCategoryList: Settings!$A$201:$A$229
Name ExpenseMonths: OFFSET(Expenses!$P$5,0,0,MAX(1,COUNTIF(Expenses!$P$5:$P$604,"?*")),1)
Name ExpensePrefix: Settings!$G$104
Name FrequencyList: Settings!$D$201:$D$214
Name InactiveDays: Settings!$D$93
Name LapsingDays: Settings!$D$92
Name LoyaltyPrefix: Settings!$G$108
Name LoyaltyRewardList: Settings!$G$232:$G$245
Name MarketingChannelList: Settings!$A$232:$A$252
Name MonthCostOfSales: Dashboard!$B$80
Name MonthExpenses: Dashboard!$E$80
Name MonthKeyList: Settings!$A$259:$A$283
Name MonthKeys: OFFSET(Settings!$A$259,0,0,MAX(1,COUNTIF(Settings!$A$259:$A$283,"?*")),1)
Name MonthNetSales: Dashboard!$A$80
Name MonthWages: Dashboard!$D$80
Name NetSalesAll: Settings!$D$116
Name NewClientTargetYear: 'Goals & Budget'!$D$21
Name NoShowFee: Settings!$D$45
Name OpenDays: Settings!$D$29
Name OpenHour: Settings!$D$27
Name OwnerName: Settings!$D$9
Name PatchTestDays: Settings!$D$94

Sheet Start Here
A1: Salon Business Management Spreadsheet | H1: Novality Store | v1.0.0
A2: A complete salon business system in one spreadsheet - diary, clients, prices, takings, staff pay, stock and profit.
A3: > Start Here | C3: > Dashboard | E3: > Diary | G3: > Clients | I3: > Services
A5: Everything in this workbook is worked out from four tabs you fill in as you go: the diary, the till, the expenses and the pay runs. Fill those honestly and the dashboard, the profit and loss and the reports look after themselves.
A7: Setting up, in six steps
B8: 1. Settings first | C8: Open the Settings tab and work down it: salon name, currency, tax rate and what tax applies to, deposit rule, rounding, the commission defaults and your targets. Ten minutes here saves every other tab from guessing.
B9: 2. Put your menu in | C9: On the Services tab, type each treatment with its price, how many minutes it takes and what the product costs you. The minutes matter as much as the price - that is what turns a price list into a profit list.
B10: 3. Add the team | C10: On the Staff tab, add everyone and pick their commission method. Nothing is assumed: commission only, hourly, a flat amount per service, tiered, a chair renter who pays you rent, or none at all.
B11: 4. Bring the clients across | C11: Paste or type your client list - name, phone, email and the 'found you by' column. Everything else fills itself in as you start logging visits.
B12: 5. Work the diary and the till | C12: Log appointments as you book them and sales as you ring them up. A deposit goes on the Payments tab against the booking; it is applied to the bill when the client comes in, so it can never be counted as revenue twice.
B13: 6. Once a month | C13: Add a commission row per stylist, run the payroll rows, log the bills on Expenses, count the stock, and read the Profit & Loss. Twenty minutes, and you know exactly how the month went.
A15: What is on each tab
B16: Tab | C16: What it is for | D16: You
B17: Dashboard | C17: The month at a glance: takings against target, average ticket, utilisation, rebooking, and the jobs that need doing today. | J17: Read it
B18: Appointments | C18: The diary. Date, time, client, service, stylist and status - with a double-booking alarm. | J18: Type here
B19: Clients | C19: The client book: contact details, formula, patch test, spend, last visit, and who is drifting away. | J19: Type here
B20: Services | C20: Your menu, with the minutes, the product cost and what each treatment earns an hour. | J20: Type here
B21: Sales | C21: The till. One row per thing sold - gross, discount, refund, net, tax and profit. | J21: Type here
B22: Payments | C22: Money in and out: deposits, balances, tips, refunds and the card fees. | J22: Type here
B23: Staff | C23: The team, their pay basis and what each chair brings in an hour. | J23: Type here
B24: Commissions | C24: One row per stylist per month. Eight methods supported - you choose, per person. | J24: Type here
B25: Payroll | C25: Pay runs: hours, commission released, tips passed on and the employer costs on top. | J25: Type here
B26: Expenses | C26: Every cost, categorised the way a profit and loss wants it, with the recurring ones spread. | J26: Type here
B27: Profit & Loss | C27: Twelve months of income, cost of sales, staff cost, overheads and operating profit. | J27: Read it
B28: Inventory | C28: Retail and backbar stock: what is left, what it is worth, what to order. | J28: Type here
... B35: Settings | C35: Your salon, your tax rules, your pay model, your lists. Set these first. | J35: Set it up
A37: Seven rules that keep it working
B38: - Blue cells are yours. Grey cells are formulas - they are locked so a stray paste cannot break the workbook.
B39: - Every sheet is protected with the password 'premium'. Review > Unprotect Sheet if you want to change the structure.
B40: - IDs number themselves from the row. Filter and sort freely, but do not cut and paste rows around - copy the values instead.
B41: - Type dates as real dates. 14/03 or 3/14 depending on where you are, not '14 march'.
B42: - Status is the engine: Completed, Cancelled and No show are the three final answers an appointment can have. Everything else is still open and is left out of the completion and cancellation rates.
B43: - Never type over a formula to make a number look right. Find the row that is wrong instead - the alert columns are there to point at it.
B44: - Add rows by typing in the first empty row of a tab. Every tab has hundreds already formatted and waiting.
A46: What this workbook does not do
B47: - It does not send confirmations, reminders, texts or emails, and it does not sync with any booking platform, till or card reader. Everything in here is typed in or pasted in by you.
B48: - It is not accounting, payroll or tax software, and nothing in it is accounting, payroll or tax advice. It organises your business so that the conversation with your accountant is a short one.
B49: - It does not calculate income tax, national insurance or social security on wages. It shows what a pay run costs the salon.
B50: - It does not take payments or store card details.
B51: - Sales tax is whatever you set it to be. There is no country baked in, and the two switches let you tax retail, services, both or neither.
A53: The sums behind the headline numbers
B54: Figure | C54: How it is worked out
B55: Net sales | C55: Gross, less discounts, less refunds.
B56: Operating profit | C56: Net sales, less the cost of what was sold, less the full cost of the pay runs, less the expenses logged.
B57: Average ticket | C57: Net sales divided by completed appointments that were paid for.
B58: Completion rate | C58: Completed appointments divided by the appointments that reached a final answer - completed, cancelled or no show.
B59: Cancellation rate | C59: Cancelled appointments over the same final-answer total.
B60: Client balance | C60: What was billed, less discounts, less every payment applied - deposits included.
B61: Commission | C61: Eligible revenue times the rate, by whichever of the eight methods that stylist is on.
B62: Service gross profit | C62: Price less the direct costs: the product used and the commission earned on it.
B63: Stock on hand | C63: Opening, plus received, less used in services, less sold, less waste, plus adjustments.
B64: Budget variance | C64: Actual spend less the budget. Positive means over.
B65: Repeat client rate | C65: Clients who came back at least twice, over the clients you have served.
A67: The small print
A68: This workbook is a business organising tool. It is not accounting, payroll, legal or tax advice, and it does not file anything for you. Tax, commission and payroll settings are yours to set and check against your own country's rules, and nothing here replaces an accountant or a booking system that sends confirmations.
B70: Version | C70: 1.0.0 | E70: Made by | F70: Novality Store
B71: Password | C71: premium | E71: Built for | F71: Excel 2010 and later, Google Sheets, LibreOffice, Numbers

Sheet Dashboard
A1: Salon Dashboard | K1: Novality Store | v1.0.0
A2: Takings, bookings, clients and chairs - worked out from the diary, the till and the payroll you have already filled in.
A3: > Start Here | C3: > Dashboard | E3: > Diary | G3: > Clients | I3: > Services | K3: > Sales
A5: Salon | B5: =SalonName -> 0 | E5: Month | F5: =TEXT(TodayDate,"mmmm yyyy") -> 0 | G5: Month key | H5: =TEXT(TodayDate,"yyyy-mm") -> 0 | I5: Last month | K5: =TEXT(DATE(YEAR(TodayDate),MONTH(TodayDate)-1,1),"yyyy-mm") -> 0 | L5: Today | M5: =TodayDate -> 0
A7: Net sales this month | D7: Against target | G7: Operating profit, month | J7: Profit margin
A8: =ROUND(SUMIFS(Sales!$Y$5:$Y$1204,Sales!$R$5:$R$1204,DashKey),2) -> 0 | D8: =IFERROR(SUMIFS(Sales!$Y$5:$Y$1204,Sales!$R$5:$R$1204,DashKey)/MAX(0.01,RevenueTargetMonth),"") -> 0 | G8: =ROUND(MonthNetSales-MonthCostOfSales-MonthWages-MonthExpenses,2) -> 0 | J8: =IF(MonthNetSales<=0,"",(MonthNetSales-MonthCostOfSales-MonthWages-MonthExpenses)/MonthNetSales) -> 0
A9: target $28,000 | D9: 100% means the month is made | G9: net sales less stock, wages and costs | J9: what is left of every dollar
A11: Clients served, month | D11: Average ticket | G11: Retail share | J11: Tips passed on
A12: =COUNTIFS(Appointments!$S$5:$S$1204,DashKey,Appointments!$M$5:$M$1204,"Completed") -> 0 | D12: =IFERROR(SUMIFS(Sales!$Y$5:$Y$1204,Sales!$R$5:$R$1204,DashKey)/MAX(1,COUNTIFS(Appointments!$S$5:$S$1204,DashKey,Appointments!$M$5:$M$1204,"Completed")),"") -> 0 | G12: =IFERROR(SUMIFS(Sales!$Y$5:$Y$1204,Sales!$R$5:$R$1204,DashKey,Sales!$H$5:$H$1204,"Retail")/MAX(0.01,SUMIFS(Sales!$Y$5:$Y$1204,Sales!$R$5:$R$1204,DashKey)),"") -> 0 | J12: =ROUND(SUMIFS(Payments!$G$5:$G$1204,Payments!$O$5:$O$1204,DashKey,Payments!$E$5:$E$1204,"Tip"),2) -> 0
A13: completed appointments | D13: target $78 | G13: target 12% | J13: the team's money, not the salon's
A15: Completion rate | D15: Cancellation rate | G15: No-show rate | J15: Chair utilisation
A16: =IFERROR(COUNTIFS(Appointments!$S$5:$S$1204,DashKey,Appointments!$M$5:$M$1204,"Completed")/MAX(1,COUNTIFS(Appointments!$S$5:$S$1204,DashKey,Appointments!$AC$5:$AC$1204,"Yes")),"") -> 0 | D16: =IFERROR(COUNTIFS(Appointments!$S$5:$S$1204,DashKey,Appointments!$M$5:$M$1204,"Cancelled")/MAX(1,COUNTIFS(Appointments!$S$5:$S$1204,DashKey,Appointments!$AC$5:$AC$1204,"Yes")),"") -> 0 | G16: =IFERROR(COUNTIFS(Appointments!$S$5:$S$1204,DashKey,Appointments!$M$5:$M$1204,"No show")/MAX(1,COUNTIFS(Appointments!$S$5:$S$1204,DashKey,Appointments!$AC$5:$AC$1204,"Yes")),"") -> 0 | J16: =IFERROR(SUMIFS(Appointments!$X$5:$X$1204,Appointments!$S$5:$S$1204,DashKey,Appointments!$M$5:$M$1204,"Completed")/MAX(1,ChairHoursWeek*4.33),"") -> 0
A17: of bookings that reached a final answer | D17: cancelled, not no-showed | G17: the most expensive hour in the salon | J17: target 75% of sellable hours
A19: Rebooking rate | D19: Repeat client rate | G19: Owed to you | J19: Stock on the shelf
A20: =IFERROR(COUNTIFS(Appointments!$S$5:$S$1204,DashKey,Appointments!$AF$5:$AF$1204,"Yes")/MAX(1,COUNTIFS(Appointments!$S$5:$S$1204,DashKey,Appointments!$M$5:$M$1204,"Completed")),"") -> 0 | D20: =IFERROR(COUNTIFS(Clients!$AN$5:$AN$504,"Yes")/MAX(1,COUNTIFS(Clients!$T$5:$T$504,">0")),"") -> 0 | G20: =ROUND(SUMIFS(Sales!$AH$5:$AH$1204,Sales!$AH$5:$AH$1204,">0.004"),2) -> 0 | J20: =ROUND(SUM(Inventory!$AB$5:$AB$304),2) -> 0
A21: target 60% leaving with the next one booked | D21: clients served who came back at least twice | G21: unpaid balances across every client | J21: at cost, retail and backbar
A23: Needs doing today
A24: What | B24: How many | C24: What it means | D24: Where to fix it
A25: Clashes in the diary | B25: =COUNTIF(Appointments!$AG$5:$AG$1204,"Clash") -> 0 | C25: ="Two bookings for the same stylist at the same time" -> 0 | L25: Appointments
A26: Bookings to confirm | B26: =COUNTIF(Appointments!$AH$5:$AH$1204,"Confirm*") -> 0 | C26: ="Coming up in the next two days and not confirmed" -> 0 | L26: Appointments
A27: Deposits not taken | B27: =COUNTIF(Appointments!$AH$5:$AH$1204,"Due - deposit*") -> 0 | C27: ="Bookings over "&TEXT(DepositThreshold,"0")&" with no deposit against them" -> 0 | L27: Appointments
A28: Visits with nothing rung up | B28: =COUNTIF(Appointments!$AH$5:$AH$1204,"Unpaid*") -> 0 | C28: ="Marked completed but no sale was logged" -> 0 | L28: Sales
A29: Unpaid balances | B29: =COUNTIFS(Sales!$AH$5:$AH$1204,">0.004") -> 0 | C29: ="Sales where money is still owed" -> 0 | L29: Payments
A30: Clients lapsing | B30: =COUNTIF(Clients!$AM$5:$AM$504,"Lapsing") -> 0 | C30: ="Not in for "&LapsingDays&" days. Call them before they become inactive" -> 0 | L30: Clients
A31: Clients due a rebook | B31: =COUNTIF(Clients!$AQ$5:$AQ$504,"Rebook*") -> 0 | C31: ="Past their usual gap with nothing in the book" -> 0 | L31: Clients
A32: Patch tests out of date | B32: =COUNTIF(Clients!$AQ$5:$AQ$504,"Due - patch*") -> 0 | C32: ="Colour clients whose patch test is older than "&PatchTestDays&" days" -> 0 | L32: Clients
A33: Products out of stock | B33: =COUNTIF(Inventory!$Z$5:$Z$304,"Out of stock") -> 0 | C33: ="Nothing left on the shelf to sell or use" -> 0 | L33: Inventory
A34: Products to reorder | B34: =COUNTIF(Inventory!$Z$5:$Z$304,"Low stock") -> 0 | C34: ="Below the reorder point or under "&StockWarningWeeks&" weeks of cover" -> 0 | L34: Inventory
A35: Deliveries late | B35: =COUNTIF(Purchases!$Y$5:$Y$304,"Late*") -> 0 | C35: ="Ordered, expected, still not here" -> 0 | L35: Purchases
A36: Bills overdue | B36: =COUNTIF(Expenses!$V$5:$V$604,"Overdue") -> 0 | C36: ="Past the due date and not marked paid" -> 0 | L36: Expenses
A37: Commission to approve | B37: =COUNTIFS(Commissions!$H$5:$H$244,"<>Yes",Commissions!$B$5:$B$244,"<>") -> 0 | C37: ="Calculated and waiting for your sign-off" -> 0 | L37: Commissions
A38: Pay runs not paid | B38: =COUNTIFS(Payroll!$M$5:$M$364,"<>Yes",Payroll!$B$5:$B$364,"<>") -> 0 | C38: ="Payroll rows still open" -> 0 | L38: Payroll
A39: Loyalty rewards ready | B39: =COUNTIF(Loyalty!$X$5:$X$504,"Action - reward*") -> 0 | C39: ="Clients who have earned something. Tell them" -> 0 | L39: Loyalty
A40: Services below your chair rate | B40: =SUMPRODUCT((IFERROR(Services!$V$5:$V$204*1,0)>0)*(IFERROR(Services!$V$5:$V$204*1,0)<TargetChairRate)) -> 0 | C40: ="Earning less than "&TEXT(TargetChairRate,"0")&" an hour before commission" -> 0 | L40: Services
A42: Who is earning what
A43: Stylist | B43: Sales this month | C43: Against target | D43: Completed | E43: Average ticket | F43: Retail share | G43: Utilisation | H43: Rebook rate | I43: Commission | J43: Pay this month | K43: Leaves behind
A44: =IFERROR(INDEX(Staff!$B$5:$B$44,MATCH(1,Staff!$AN$5:$AN$44,0)),"") -> 0 | B44: =IFERROR(INDEX(Staff!$AD$5:$AD$44,MATCH(1,Staff!$AN$5:$AN$44,0)),"") -> 0 | C44: =IFERROR(INDEX(Staff!$AE$5:$AE$44,MATCH(1,Staff!$AN$5:$AN$44,0)),"") -> 0 | D44: =IFERROR(INDEX(Staff!$U$5:$U$44,MATCH(1,Staff!$AN$5:$AN$44,0)),"") -> 0 | E44: =IFERROR(INDEX(Staff!$AF$5:$AF$44,MATCH(1,Staff!$AN$5:$AN$44,0)),"") -> 0 | F44: =IFERROR(INDEX(Staff!$AG$5:$AG$44,MATCH(1,Staff!$AN$5:$AN$44,0)),"") -> 0 | G44: =IFERROR(INDEX(Staff!$Z$5:$Z$44,MATCH(1,Staff!$AN$5:$AN$44,0)),"") -> 0 | H44: =IFERROR(INDEX(Staff!$AI$5:$AI$44,MATCH(1,Staff!$AN$5:$AN$44,0)),"") -> 0 | I44: =IFERROR(INDEX(Staff!$AK$5:$AK$44,MATCH(1,Staff!$AN$5:$AN$44,0)),"") -> 0 | J44: =IFERROR(INDEX(Staff!$AL$5:$AL$44,MATCH(1,Staff!$AN$5:$AN$44,0)),"") -> 0 | K44: =IFERROR(INDEX(Staff!$AM$5:$AM$44,MATCH(1,Staff!$AN$5:$AN$44,0)),"") -> 0
A45: =IFERROR(INDEX(Staff!$B$5:$B$44,MATCH(2,Staff!$AN$5:$AN$44,0)),"") -> 0 | B45: =IFERROR(INDEX(Staff!$AD$5:$AD$44,MATCH(2,Staff!$AN$5:$AN$44,0)),"") -> 0 | C45: =IFERROR(INDEX(Staff!$AE$5:$AE$44,MATCH(2,Staff!$AN$5:$AN$44,0)),"") -> 0 | D45: =IFERROR(INDEX(Staff!$U$5:$U$44,MATCH(2,Staff!$AN$5:$AN$44,0)),"") -> 0 | E45: =IFERROR(INDEX(Staff!$AF$5:$AF$44,MATCH(2,Staff!$AN$5:$AN$44,0)),"") -> 0 | F45: =IFERROR(INDEX(Staff!$AG$5:$AG$44,MATCH(2,Staff!$AN$5:$AN$44,0)),"") -> 0 | G45: =IFERROR(INDEX(Staff!$Z$5:$Z$44,MATCH(2,Staff!$AN$5:$AN$44,0)),"") -> 0 | H45: =IFERROR(INDEX(Staff!$AI$5:$AI$44,MATCH(2,Staff!$AN$5:$AN$44,0)),"") -> 0 | I45: =IFERROR(INDEX(Staff!$AK$5:$AK$44,MATCH(2,Staff!$AN$5:$AN$44,0)),"") -> 0 | J45: =IFERROR(INDEX(Staff!$AL$5:$AL$44,MATCH(2,Staff!$AN$5:$AN$44,0)),"") -> 0 | K45: =IFERROR(INDEX(Staff!$AM$5:$AM$44,MATCH(2,Staff!$AN$5:$AN$44,0)),"") -> 0
A46: =IFERROR(INDEX(Staff!$B$5:$B$44,MATCH(3,Staff!$AN$5:$AN$44,0)),"") -> 0 | B46: =IFERROR(INDEX(Staff!$AD$5:$AD$44,MATCH(3,Staff!$AN$5:$AN$44,0)),"") -> 0 | C46: =IFERROR(INDEX(Staff!$AE$5:$AE$44,MATCH(3,Staff!$AN$5:$AN$44,0)),"") -> 0 | D46: =IFERROR(INDEX(Staff!$U$5:$U$44,MATCH(3,Staff!$AN$5:$AN$44,0)),"") -> 0 | E46: =IFERROR(INDEX(Staff!$AF$5:$AF$44,MATCH(3,Staff!$AN$5:$AN$44,0)),"") -> 0 | F46: =IFERROR(INDEX(Staff!$AG$5:$AG$44,MATCH(3,Staff!$AN$5:$AN$44,0)),"") -> 0 | G46: =IFERROR(INDEX(Staff!$Z$5:$Z$44,MATCH(3,Staff!$AN$5:$AN$44,0)),"") -> 0 | H46: =IFERROR(INDEX(Staff!$AI$5:$AI$44,MATCH(3,Staff!$AN$5:$AN$44,0)),"") -> 0 | I46: =IFERROR(INDEX(Staff!$AK$5:$AK$44,MATCH(3,Staff!$AN$5:$AN$44,0)),"") -> 0 | J46: =IFERROR(INDEX(Staff!$AL$5:$AL$44,MATCH(3,Staff!$AN$5:$AN$44,0)),"") -> 0 | K46: =IFERROR(INDEX(Staff!$AM$5:$AM$44,MATCH(3,Staff!$AN$5:$AN$44,0)),"") -> 0
A47: =IFERROR(INDEX(Staff!$B$5:$B$44,MATCH(4,Staff!$AN$5:$AN$44,0)),"") -> 0 | B47: =IFERROR(INDEX(Staff!$AD$5:$AD$44,MATCH(4,Staff!$AN$5:$AN$44,0)),"") -> 0 | C47: =IFERROR(INDEX(Staff!$AE$5:$AE$44,MATCH(4,Staff!$AN$5:$AN$44,0)),"") -> 0 | D47: =IFERROR(INDEX(Staff!$U$5:$U$44,MATCH(4,Staff!$AN$5:$AN$44,0)),"") -> 0 | E47: =IFERROR(INDEX(Staff!$AF$5:$AF$44,MATCH(4,Staff!$AN$5:$AN$44,0)),"") -> 0 | F47: =IFERROR(INDEX(Staff!$AG$5:$AG$44,MATCH(4,Staff!$AN$5:$AN$44,0)),"") -> 0 | G47: =IFERROR(INDEX(Staff!$Z$5:$Z$44,MATCH(4,Staff!$AN$5:$AN$44,0)),"") -> 0 | H47: =IFERROR(INDEX(Staff!$AI$5:$AI$44,MATCH(4,Staff!$AN$5:$AN$44,0)),"") -> 0 | I47: =IFERROR(INDEX(Staff!$AK$5:$AK$44,MATCH(4,Staff!$AN$5:$AN$44,0)),"") -> 0 | J47: =IFERROR(INDEX(Staff!$AL$5:$AL$44,MATCH(4,Staff!$AN$5:$AN$44,0)),"") -> 0 | K47: =IFERROR(INDEX(Staff!$AM$5:$AM$44,MATCH(4,Staff!$AN$5:$AN$44,0)),"") -> 0
A48: =IFERROR(INDEX(Staff!$B$5:$B$44,MATCH(5,Staff!$AN$5:$AN$44,0)),"") -> 0 | B48: =IFERROR(INDEX(Staff!$AD$5:$AD$44,MATCH(5,Staff!$AN$5:$AN$44,0)),"") -> 0 | C48: =IFERROR(INDEX(Staff!$AE$5:$AE$44,MATCH(5,Staff!$AN$5:$AN$44,0)),"") -> 0 | D48: =IFERROR(INDEX(Staff!$U$5:$U$44,MATCH(5,Staff!$AN$5:$AN$44,0)),"") -> 0 | E48: =IFERROR(INDEX(Staff!$AF$5:$AF$44,MATCH(5,Staff!$AN$5:$AN$44,0)),"") -> 0 | F48: =IFERROR(INDEX(Staff!$AG$5:$AG$44,MATCH(5,Staff!$AN$5:$AN$44,0)),"") -> 0 | G48: =IFERROR(INDEX(Staff!$Z$5:$Z$44,MATCH(5,Staff!$AN$5:$AN$44,0)),"") -> 0 | H48: =IFERROR(INDEX(Staff!$AI$5:$AI$44,MATCH(5,Staff!$AN$5:$AN$44,0)),"") -> 0 | I48: =IFERROR(INDEX(Staff!$AK$5:$AK$44,MATCH(5,Staff!$AN$5:$AN$44,0)),"") -> 0 | J48: =IFERROR(INDEX(Staff!$AL$5:$AL$44,MATCH(5,Staff!$AN$5:$AN$44,0)),"") -> 0 | K48: =IFERROR(INDEX(Staff!$AM$5:$AM$44,MATCH(5,Staff!$AN$5:$AN$44,0)),"") -> 0
A49: =IFERROR(INDEX(Staff!$B$5:$B$44,MATCH(6,Staff!$AN$5:$AN$44,0)),"") -> 0 | B49: =IFERROR(INDEX(Staff!$AD$5:$AD$44,MATCH(6,Staff!$AN$5:$AN$44,0)),"") -> 0 | C49: =IFERROR(INDEX(Staff!$AE$5:$AE$44,MATCH(6,Staff!$AN$5:$AN$44,0)),"") -> 0 | D49: =IFERROR(INDEX(Staff!$U$5:$U$44,MATCH(6,Staff!$AN$5:$AN$44,0)),"") -> 0 | E49: =IFERROR(INDEX(Staff!$AF$5:$AF$44,MATCH(6,Staff!$AN$5:$AN$44,0)),"") -> 0 | F49: =IFERROR(INDEX(Staff!$AG$5:$AG$44,MATCH(6,Staff!$AN$5:$AN$44,0)),"") -> 0 | G49: =IFERROR(INDEX(Staff!$Z$5:$Z$44,MATCH(6,Staff!$AN$5:$AN$44,0)),"") -> 0 | H49: =IFERROR(INDEX(Staff!$AI$5:$AI$44,MATCH(6,Staff!$AN$5:$AN$44,0)),"") -> 0 | I49: =IFERROR(INDEX(Staff!$AK$5:$AK$44,MATCH(6,Staff!$AN$5:$AN$44,0)),"") -> 0 | J49: =IFERROR(INDEX(Staff!$AL$5:$AL$44,MATCH(6,Staff!$AN$5:$AN$44,0)),"") -> 0 | K49: =IFERROR(INDEX(Staff!$AM$5:$AM$44,MATCH(6,Staff!$AN$5:$AN$44,0)),"") -> 0
A50: =IFERROR(INDEX(Staff!$B$5:$B$44,MATCH(7,Staff!$AN$5:$AN$44,0)),"") -> 0 | B50: =IFERROR(INDEX(Staff!$AD$5:$AD$44,MATCH(7,Staff!$AN$5:$AN$44,0)),"") -> 0 | C50: =IFERROR(INDEX(Staff!$AE$5:$AE$44,MATCH(7,Staff!$AN$5:$AN$44,0)),"") -> 0 | D50: =IFERROR(INDEX(Staff!$U$5:$U$44,MATCH(7,Staff!$AN$5:$AN$44,0)),"") -> 0 | E50: =IFERROR(INDEX(Staff!$AF$5:$AF$44,MATCH(7,Staff!$AN$5:$AN$44,0)),"") -> 0 | F50: =IFERROR(INDEX(Staff!$AG$5:$AG$44,MATCH(7,Staff!$AN$5:$AN$44,0)),"") -> 0 | G50: =IFERROR(INDEX(Staff!$Z$5:$Z$44,MATCH(7,Staff!$AN$5:$AN$44,0)),"") -> 0 | H50: =IFERROR(INDEX(Staff!$AI$5:$AI$44,MATCH(7,Staff!$AN$5:$AN$44,0)),"") -> 0 | I50: =IFERROR(INDEX(Staff!$AK$5:$AK$44,MATCH(7,Staff!$AN$5:$AN$44,0)),"") -> 0 | J50: =IFERROR(INDEX(Staff!$AL$5:$AL$44,MATCH(7,Staff!$AN$5:$AN$44,0)),"") -> 0 | K50: =IFERROR(INDEX(Staff!$AM$5:$AM$44,MATCH(7,Staff!$AN$5:$AN$44,0)),"") -> 0
A51: =IFERROR(INDEX(Staff!$B$5:$B$44,MATCH(8,Staff!$AN$5:$AN$44,0)),"") -> 0 | B51: =IFERROR(INDEX(Staff!$AD$5:$AD$44,MATCH(8,Staff!$AN$5:$AN$44,0)),"") -> 0 | C51: =IFERROR(INDEX(Staff!$AE$5:$AE$44,MATCH(8,Staff!$AN$5:$AN$44,0)),"") -> 0 | D51: =IFERROR(INDEX(Staff!$U$5:$U$44,MATCH(8,Staff!$AN$5:$AN$44,0)),"") -> 0 | E51: =IFERROR(INDEX(Staff!$AF$5:$AF$44,MATCH(8,Staff!$AN$5:$AN$44,0)),"") -> 0 | F51: =IFERROR(INDEX(Staff!$AG$5:$AG$44,MATCH(8,Staff!$AN$5:$AN$44,0)),"") -> 0 | G51: =IFERROR(INDEX(Staff!$Z$5:$Z$44,MATCH(8,Staff!$AN$5:$AN$44,0)),"") -> 0 | H51: =IFERROR(INDEX(Staff!$AI$5:$AI$44,MATCH(8,Staff!$AN$5:$AN$44,0)),"") -> 0 | I51: =IFERROR(INDEX(Staff!$AK$5:$AK$44,MATCH(8,Staff!$AN$5:$AN$44,0)),"") -> 0 | J51: =IFERROR(INDEX(Staff!$AL$5:$AL$44,MATCH(8,Staff!$AN$5:$AN$44,0)),"") -> 0 | K51: =IFERROR(INDEX(Staff!$AM$5:$AM$44,MATCH(8,Staff!$AN$5:$AN$44,0)),"") -> 0
A53: What the chairs are selling
A54: Most booked | B54: Times | C54: Biggest earner | D54: Revenue | E54: Best an hour | F54: An hour | G54: Best clients | H54: Spent
A55: =IFERROR(INDEX(Services!$B$5:$B$204,MATCH(1,Services!$AL$5:$AL$204,0)),"") -> 0 | B55: =IFERROR(INDEX(Services!$AB$5:$AB$204,MATCH(1,Services!$AL$5:$AL$204,0)),"") -> 0 | C55: =IFERROR(INDEX(Services!$B$5:$B$204,MATCH(1,Services!$AJ$5:$AJ$204,0)),"") -> 0 | D55: =IFERROR(INDEX(Services!$AD$5:$AD$204,MATCH(1,Services!$AJ$5:$AJ$204,0)),"") -> 0 | E55: =IFERROR(INDEX(Services!$B$5:$B$204,MATCH(1,Services!$AK$5:$AK$204,0)),"") -> 0 | F55: =IFERROR(INDEX(Services!$V$5:$V$204,MATCH(1,Services!$AK$5:$AK$204,0)),"") -> 0 | G55: =IFERROR(INDEX(Clients!$B$5:$B$504,MATCH(1,Clients!$AO$5:$AO$504,0)),"") -> 0 | H55: =IFERROR(INDEX(Clients!$AE$5:$AE$504,MATCH(1,Clients!$AO$5:$AO$504,0)),"") -> 0
A56: =IFERROR(INDEX(Services!$B$5:$B$204,MATCH(2,Services!$AL$5:$AL$204,0)),"") -> 0 | B56: =IFERROR(INDEX(Services!$AB$5:$AB$204,MATCH(2,Services!$AL$5:$AL$204,0)),"") -> 0 | C56: =IFERROR(INDEX(Services!$B$5:$B$204,MATCH(2,Services!$AJ$5:$AJ$204,0)),"") -> 0 | D56: =IFERROR(INDEX(Services!$AD$5:$AD$204,MATCH(2,Services!$AJ$5:$AJ$204,0)),"") -> 0 | E56: =IFERROR(INDEX(Services!$B$5:$B$204,MATCH(2,Services!$AK$5:$AK$204,0)),"") -> 0 | F56: =IFERROR(INDEX(Services!$V$5:$V$204,MATCH(2,Services!$AK$5:$AK$204,0)),"") -> 0 | G56: =IFERROR(INDEX(Clients!$B$5:$B$504,MATCH(2,Clients!$AO$5:$AO$504,0)),"") -> 0 | H56: =IFERROR(INDEX(Clients!$AE$5:$AE$504,MATCH(2,Clients!$AO$5:$AO$504,0)),"") -> 0
A57: =IFERROR(INDEX(Services!$B$5:$B$204,MATCH(3,Services!$AL$5:$AL$204,0)),"") -> 0 | B57: =IFERROR(INDEX(Services!$AB$5:$AB$204,MATCH(3,Services!$AL$5:$AL$204,0)),"") -> 0 | C57: =IFERROR(INDEX(Services!$B$5:$B$204,MATCH(3,Services!$AJ$5:$AJ$204,0)),"") -> 0 | D57: =IFERROR(INDEX(Services!$AD$5:$AD$204,MATCH(3,Services!$AJ$5:$AJ$204,0)),"") -> 0 | E57: =IFERROR(INDEX(Services!$B$5:$B$204,MATCH(3,Services!$AK$5:$AK$204,0)),"") -> 0 | F57: =IFERROR(INDEX(Services!$V$5:$V$204,MATCH(3,Services!$AK$5:$AK$204,0)),"") -> 0 | G57: =IFERROR(INDEX(Clients!$B$5:$B$504,MATCH(3,Clients!$AO$5:$AO$504,0)),"") -> 0 | H57: =IFERROR(INDEX(Clients!$AE$5:$AE$504,MATCH(3,Clients!$AO$5:$AO$504,0)),"") -> 0
A58: =IFERROR(INDEX(Services!$B$5:$B$204,MATCH(4,Services!$AL$5:$AL$204,0)),"") -> 0 | B58: =IFERROR(INDEX(Services!$AB$5:$AB$204,MATCH(4,Services!$AL$5:$AL$204,0)),"") -> 0 | C58: =IFERROR(INDEX(Services!$B$5:$B$204,MATCH(4,Services!$AJ$5:$AJ$204,0)),"") -> 0 | D58: =IFERROR(INDEX(Services!$AD$5:$AD$204,MATCH(4,Services!$AJ$5:$AJ$204,0)),"") -> 0 | E58: =IFERROR(INDEX(Services!$B$5:$B$204,MATCH(4,Services!$AK$5:$AK$204,0)),"") -> 0 | F58: =IFERROR(INDEX(Services!$V$5:$V$204,MATCH(4,Services!$AK$5:$AK$204,0)),"") -> 0 | G58: =IFERROR(INDEX(Clients!$B$5:$B$504,MATCH(4,Clients!$AO$5:$AO$504,0)),"") -> 0 | H58: =IFERROR(INDEX(Clients!$AE$5:$AE$504,MATCH(4,Clients!$AO$5:$AO$504,0)),"") -> 0
A59: =IFERROR(INDEX(Services!$B$5:$B$204,MATCH(5,Services!$AL$5:$AL$204,0)),"") -> 0 | B59: =IFERROR(INDEX(Services!$AB$5:$AB$204,MATCH(5,Services!$AL$5:$AL$204,0)),"") -> 0 | C59: =IFERROR(INDEX(Services!$B$5:$B$204,MATCH(5,Services!$AJ$5:$AJ$204,0)),"") -> 0 | D59: =IFERROR(INDEX(Services!$AD$5:$AD$204,MATCH(5,Services!$AJ$5:$AJ$204,0)),"") -> 0 | E59: =IFERROR(INDEX(Services!$B$5:$B$204,MATCH(5,Services!$AK$5:$AK$204,0)),"") -> 0 | F59: =IFERROR(INDEX(Services!$V$5:$V$204,MATCH(5,Services!$AK$5:$AK$204,0)),"") -> 0 | G59: =IFERROR(INDEX(Clients!$B$5:$B$504,MATCH(5,Clients!$AO$5:$AO$504,0)),"") -> 0 | H59: =IFERROR(INDEX(Clients!$AE$5:$AE$504,MATCH(5,Clients!$AO$5:$AO$504,0)),"") -> 0
A60: =IFERROR(INDEX(Services!$B$5:$B$204,MATCH(6,Services!$AL$5:$AL$204,0)),"") -> 0 | B60: =IFERROR(INDEX(Services!$AB$5:$AB$204,MATCH(6,Services!$AL$5:$AL$204,0)),"") -> 0 | C60: =IFERROR(INDEX(Services!$B$5:$B$204,MATCH(6,Services!$AJ$5:$AJ$204,0)),"") -> 0 | D60: =IFERROR(INDEX(Services!$AD$5:$AD$204,MATCH(6,Services!$AJ$5:$AJ$204,0)),"") -> 0 | E60: =IFERROR(INDEX(Services!$B$5:$B$204,MATCH(6,Services!$AK$5:$AK$204,0)),"") -> 0 | F60: =IFERROR(INDEX(Services!$V$5:$V$204,MATCH(6,Services!$AK$5:$AK$204,0)),"") -> 0 | G60: =IFERROR(INDEX(Clients!$B$5:$B$504,MATCH(6,Clients!$AO$5:$AO$504,0)),"") -> 0 | H60: =IFERROR(INDEX(Clients!$AE$5:$AE$504,MATCH(6,Clients!$AO$5:$AO$504,0)),"") -> 0
A62: The last twelve months
A63: Month | B63: Net sales | C63: Target | D63: Against target | E63: Services | F63: Retail | G63: Cost of sales | H63: Wages | I63: Expenses | J63: Operating profit | K63: Margin | L63: Clients served | M63: Average ticket
A64: =TEXT(DATE(YEAR(TodayDate),MONTH(TodayDate)-11,1),"mmm yy") -> 0 | B64: =ROUND(SUMIFS(Sales!$Y$5:$Y$1204,Sales!$R$5:$R$1204,TEXT(DATE(YEAR(TodayDate),MONTH(TodayDate)-11,1),"yyyy-mm")),2) -> 0 | C64: =ROUND(RevenueTargetMonth,2) -> 0 | D64: =ROUND(SUMIFS(Sales!$Y$5:$Y$1204,Sales!$R$5:$R$1204,TEXT(DATE(YEAR(TodayDate),MONTH(TodayDate)-11,1),"yyyy-mm"))-RevenueTargetMonth,2) -> 0 | E64: =ROUND(SUMIFS(Sales!$Y$5:$Y$1204,Sales!$R$5:$R$1204,TEXT(DATE(YEAR(TodayDate),MONTH(TodayDate)-11,1),"yyyy-mm"),Sales!$H$5:$H$1204,"Service"),2) -> 0 | F64: =ROUND(SUMIFS(Sales!$Y$5:$Y$1204,Sales!$R$5:$R$1204,TEXT(DATE(YEAR(TodayDate),MONTH(TodayDate)-11,1),"yyyy-mm"),Sales!$H$5:$H$1204,"Retail"),2) -> 0 | G64: =ROUND(SUMIFS(Sales!$AB$5:$AB$1204,Sales!$R$5:$R$1204,TEXT(DATE(YEAR(TodayDate),MONTH(TodayDate)-11,1),"yyyy-mm")),2) -> 0 | H64: =ROUND(SUMIFS(Payroll!$Y$5:$Y$364,Payroll!$Q$5:$Q$364,TEXT(DATE(YEAR(TodayDate),MONTH(TodayDate)-11,1),"yyyy-mm")),2) -> 0 | I64: =ROUND(SUMIFS(Expenses!$F$5:$F$604,Expenses!$P$5:$P$604,TEXT(DATE(YEAR(TodayDate),MONTH(TodayDate)-11,1),"yyyy-mm")),2) -> 0 | J64: =ROUND(SUMIFS(Sales!$Y$5:$Y$1204,Sales!$R$5:$R$1204,TEXT(DATE(YEAR(TodayDate),MONTH(TodayDate)-11,1),"yyyy-mm"))-SUMIFS(Sales!$AB$5:$AB$1204,Sales!$R$5:$R$1204,TEXT(DATE(YEAR(TodayDate),MONTH(TodayDate)-11,1),"yyyy-mm"))-SUMIFS(Payroll!$Y$5:$Y$364,Payroll!$Q$5:$Q$364,TEXT(DATE(YEAR(TodayDate),MONTH(TodayDate)-11,1),"yyyy-mm"))-SUMIFS(Expenses!$F$5:$F$604,Expenses!$P$5:$P$604,TEXT(DATE(YEAR(TodayDate),MONTH(TodayDate)-11,1),"yyyy-mm")),2) -> 0 | K64: =IF(SUMIFS(Sales!$Y$5:$Y$1204,Sales!$R$5:$R$1204,TEXT(DATE(YEAR(TodayDate),MONTH(TodayDate)-11,1),"yyyy-mm"))<=0,"",(SUMIFS(Sales!$Y$5:$Y$1204,Sales!$R$5:$R$1204,TEXT(DATE(YEAR(TodayDate),MONTH(TodayDate)-11,1),"yyyy-mm"))-SUMIFS(Sales!$AB$5:$AB$1204,Sales!$R$5:$R$1204,TEXT(DATE(YEAR(TodayDate),MONTH(TodayDate)-11,1),"yyyy-mm"))-SUMIFS(Payroll!$Y$5:$Y$364,Payroll!$Q$5:$Q$364,TEXT(DATE(YEAR(TodayDate),MONTH(TodayDate)-11,1),"yyyy-mm"))-SUMIFS(Expenses!$F$5:$F$604,Expenses!$P$5:$P$604,TEXT(DATE(YEAR(TodayDate),MONTH(TodayDate)-11,1),"yyyy-mm")))/SUMIFS(Sales!$Y$5:$Y$1204,Sales!$R$5:$R$1204,TEXT(DATE(YEAR(TodayDate),MONTH(TodayDate)-11,1),"yyyy-mm"))) -> 0 | L64: =COUNTIFS(Appointments!$S$5:$S$1204,TEXT(DATE(YEAR(TodayDate),MONTH(TodayDate)-11,1),"yyyy-mm"),Appointments!$M$5:$M$1204,"Completed") -> 0 | M64: =IFERROR(SUMIFS(Sales!$Y$5:$Y$1204,Sales!$R$5:$R$1204,TEXT(DATE(YEAR(TodayDate),MONTH(TodayDate)-11,1),"yyyy-mm"))/MAX(1,COUNTIFS(Appointments!$S$5:$S$1204,TEXT(DATE(YEAR(TodayDate),MONTH(TodayDate)-11,1),"yyyy-mm"),Appointments!$M$5:$M$1204,"Completed")),"") -> 0
A65: =TEXT(DATE(YEAR(TodayDate),MONTH(TodayDate)-10,1),"mmm yy") -> 0 | B65: =ROUND(SUMIFS(Sales!$Y$5:$Y$1204,Sales!$R$5:$R$1204,TEXT(DATE(YEAR(TodayDate),MONTH(TodayDate)-10,1),"yyyy-mm")),2) -> 0 | C65: =ROUND(RevenueTargetMonth,2) -> 0 | D65: =ROUND(SUMIFS(Sales!$Y$5:$Y$1204,Sales!$R$5:$R$1204,TEXT(DATE(YEAR(TodayDate),MONTH(TodayDate)-10,1),"yyyy-mm"))-RevenueTargetMonth,2) -> 0 | E65: =ROUND(SUMIFS(Sales!$Y$5:$Y$1204,Sales!$R$5:$R$1204,TEXT(DATE(YEAR(TodayDate),MONTH(TodayDate)-10,1),"yyyy-mm"),Sales!$H$5:$H$1204,"Service"),2) -> 0 | F65: =ROUND(SUMIFS(Sales!$Y$5:$Y$1204,Sales!$R$5:$R$1204,TEXT(DATE(YEAR(TodayDate),MONTH(TodayDate)-10,1),"yyyy-mm"),Sales!$H$5:$H$1204,"Retail"),2) -> 0 | G65: =ROUND(SUMIFS(Sales!$AB$5:$AB$1204,Sales!$R$5:$R$1204,TEXT(DATE(YEAR(TodayDate),MONTH(TodayDate)-10,1),"yyyy-mm")),2) -> 0 | H65: =ROUND(SUMIFS(Payroll!$Y$5:$Y$364,Payroll!$Q$5:$Q$364,TEXT(DATE(YEAR(TodayDate),MONTH(TodayDate)-10,1),"yyyy-mm")),2) -> 0 | I65: =ROUND(SUMIFS(Expenses!$F$5:$F$604,Expenses!$P$5:$P$604,TEXT(DATE(YEAR(TodayDate),MONTH(TodayDate)-10,1),"yyyy-mm")),2) -> 0 | J65: =ROUND(SUMIFS(Sales!$Y$5:$Y$1204,Sales!$R$5:$R$1204,TEXT(DATE(YEAR(TodayDate),MONTH(TodayDate)-10,1),"yyyy-mm"))-SUMIFS(Sales!$AB$5:$AB$1204,Sales!$R$5:$R$1204,TEXT(DATE(YEAR(TodayDate),MONTH(TodayDate)-10,1),"yyyy-mm"))-SUMIFS(Payroll!$Y$5:$Y$364,Payroll!$Q$5:$Q$364,TEXT(DATE(YEAR(TodayDate),MONTH(TodayDate)-10,1),"yyyy-mm"))-SUMIFS(Expenses!$F$5:$F$604,Expenses!$P$5:$P$604,TEXT(DATE(YEAR(TodayDate),MONTH(TodayDate)-10,1),"yyyy-mm")),2) -> 0 | K65: =IF(SUMIFS(Sales!$Y$5:$Y$1204,Sales!$R$5:$R$1204,TEXT(DATE(YEAR(TodayDate),MONTH(TodayDate)-10,1),"yyyy-mm"))<=0,"",(SUMIFS(Sales!$Y$5:$Y$1204,Sales!$R$5:$R$1204,TEXT(DATE(YEAR(TodayDate),MONTH(TodayDate)-10,1),"yyyy-mm"))-SUMIFS(Sales!$AB$5:$AB$1204,Sales!$R$5:$R$1204,TEXT(DATE(YEAR(TodayDate),MONTH(TodayDate)-10,1),"yyyy-mm"))-SUMIFS(Payroll!$Y$5:$Y$364,Payroll!$Q$5:$Q$364,TEXT(DATE(YEAR(TodayDate),MONTH(TodayDate)-10,1),"yyyy-mm"))-SUMIFS(Expenses!$F$5:$F$604,Expenses!$P$5:$P$604,TEXT(DATE(YEAR(TodayDate),MONTH(TodayDate)-10,1),"yyyy-mm")))/SUMIFS(Sales!$Y$5:$Y$1204,Sales!$R$5:$R$1204,TEXT(DATE(YEAR(TodayDate),MONTH(TodayDate)-10,1),"yyyy-mm"))) -> 0 | L65: =COUNTIFS(Appointments!$S$5:$S$1204,TEXT(DATE(YEAR(TodayDate),MONTH(TodayDate)-10,1),"yyyy-mm"),Appointments!$M$5:$M$1204,"Completed") -> 0 | M65: =IFERROR(SUMIFS(Sales!$Y$5:$Y$1204,Sales!$R$5:$R$1204,TEXT(DATE(YEAR(TodayDate),MONTH(TodayDate)-10,1),"yyyy-mm"))/MAX(1,COUNTIFS(Appointments!$S$5:$S$1204,TEXT(DATE(YEAR(TodayDate),MONTH(TodayDate)-10,1),"yyyy-mm"),Appointments!$M$5:$M$1204,"Completed")),"") -> 0
A66: =TEXT(DATE(YEAR(TodayDate),MONTH(TodayDate)-9,1),"mmm yy") -> 0 | B66: =ROUND(SUMIFS(Sales!$Y$5:$Y$1204,Sales!$R$5:$R$1204,TEXT(DATE(YEAR(TodayDate),MONTH(TodayDate)-9,1),"yyyy-mm")),2) -> 0 | C66: =ROUND(RevenueTargetMonth,2) -> 0 | D66: =ROUND(SUMIFS(Sales!$Y$5:$Y$1204,Sales!$R$5:$R$1204,TEXT(DATE(YEAR(TodayDate),MONTH(TodayDate)-9,1),"yyyy-mm"))-RevenueTargetMonth,2) -> 0 | E66: =ROUND(SUMIFS(Sales!$Y$5:$Y$1204,Sales!$R$5:$R$1204,TEXT(DATE(YEAR(TodayDate),MONTH(TodayDate)-9,1),"yyyy-mm"),Sales!$H$5:$H$1204,"Service"),2) -> 0 | F66: =ROUND(SUMIFS(Sales!$Y$5:$Y$1204,Sales!$R$5:$R$1204,TEXT(DATE(YEAR(TodayDate),MONTH(TodayDate)-9,1),"yyyy-mm"),Sales!$H$5:$H$1204,"Retail"),2) -> 0 | G66: =ROUND(SUMIFS(Sales!$AB$5:$AB$1204,Sales!$R$5:$R$1204,TEXT(DATE(YEAR(TodayDate),MONTH(TodayDate)-9,1),"yyyy-mm")),2) -> 0 | H66: =ROUND(SUMIFS(Payroll!$Y$5:$Y$364,Payroll!$Q$5:$Q$364,TEXT(DATE(YEAR(TodayDate),MONTH(TodayDate)-9,1),"yyyy-mm")),2) -> 0 | I66: =ROUND(SUMIFS(Expenses!$F$5:$F$604,Expenses!$P$5:$P$604,TEXT(DATE(YEAR(TodayDate),MONTH(TodayDate)-9,1),"yyyy-mm")),2) -> 0 | J66: =ROUND(SUMIFS(Sales!$Y$5:$Y$1204,Sales!$R$5:$R$1204,TEXT(DATE(YEAR(TodayDate),MONTH(TodayDate)-9,1),"yyyy-mm"))-SUMIFS(Sales!$AB$5:$AB$1204,Sales!$R$5:$R$1204,TEXT(DATE(YEAR(TodayDate),MONTH(TodayDate)-9,1),"yyyy-mm"))-SUMIFS(Payroll!$Y$5:$Y$364,Payroll!$Q$5:$Q$364,TEXT(DATE(YEAR(TodayDate),MONTH(TodayDate)-9,1),"yyyy-mm"))-SUMIFS(Expenses!$F$5:$F$604,Expenses!$P$5:$P$604,TEXT(DATE(YEAR(TodayDate),MONTH(TodayDate)-9,1),"yyyy-mm")),2) -> 0 | K66: =IF(SUMIFS(Sales!$Y$5:$Y$1204,Sales!$R$5:$R$1204,TEXT(DATE(YEAR(TodayDate),MONTH(TodayDate)-9,1),"yyyy-mm"))<=0,"",(SUMIFS(Sales!$Y$5:$Y$1204,Sales!$R$5:$R$1204,TEXT(DATE(YEAR(TodayDate),MONTH(TodayDate)-9,1),"yyyy-mm"))-SUMIFS(Sales!$AB$5:$AB$1204,Sales!$R$5:$R$1204,TEXT(DATE(YEAR(TodayDate),MONTH(TodayDate)-9,1),"yyyy-mm"))-SUMIFS(Payroll!$Y$5:$Y$364,Payroll!$Q$5:$Q$364,TEXT(DATE(YEAR(TodayDate),MONTH(TodayDate)-9,1),"yyyy-mm"))-SUMIFS(Expenses!$F$5:$F$604,Expenses!$P$5:$P$604,TEXT(DATE(YEAR(TodayDate),MONTH(TodayDate)-9,1),"yyyy-mm")))/SUMIFS(Sales!$Y$5:$Y$1204,Sales!$R$5:$R$1204,TEXT(DATE(YEAR(TodayDate),MONTH(TodayDate)-9,1),"yyyy-mm"))) -> 0 | L66: =COUNTIFS(Appointments!$S$5:$S$1204,TEXT(DATE(YEAR(TodayDate),MONTH(TodayDate)-9,1),"yyyy-mm"),Appointments!$M$5:$M$1204,"Completed") -> 0 | M66: =IFERROR(SUMIFS(Sales!$Y$5:$Y$1204,Sales!$R$5:$R$1204,TEXT(DATE(YEAR(TodayDate),MONTH(TodayDate)-9,1),"yyyy-mm"))/MAX(1,COUNTIFS(Appointments!$S$5:$S$1204,TEXT(DATE(YEAR(TodayDate),MONTH(TodayDate)-9,1),"yyyy-mm"),Appointments!$M$5:$M$1204,"Completed")),"") -> 0
A67: =TEXT(DATE(YEAR(TodayDate),MONTH(TodayDate)-8,1),"mmm yy") -> 0 | B67: =ROUND(SUMIFS(Sales!$Y$5:$Y$1204,Sales!$R$5:$R$1204,TEXT(DATE(YEAR(TodayDate),MONTH(TodayDate)-8,1),"yyyy-mm")),2) -> 0 | C67: =ROUND(RevenueTargetMonth,2) -> 0 | D67: =ROUND(SUMIFS(Sales!$Y$5:$Y$1204,Sales!$R$5:$R$1204,TEXT(DATE(YEAR(TodayDate),MONTH(TodayDate)-8,1),"yyyy-mm"))-RevenueTargetMonth,2) -> 0 | E67: =ROUND(SUMIFS(Sales!$Y$5:$Y$1204,Sales!$R$5:$R$1204,TEXT(DATE(YEAR(TodayDate),MONTH(TodayDate)-8,1),"yyyy-mm"),Sales!$H$5:$H$1204,"Service"),2) -> 0 | F67: =ROUND(SUMIFS(Sales!$Y$5:$Y$1204,Sales!$R$5:$R$1204,TEXT(DATE(YEAR(TodayDate),MONTH(TodayDate)-8,1),"yyyy-mm"),Sales!$H$5:$H$1204,"Retail"),2) -> 0 | G67: =ROUND(SUMIFS(Sales!$AB$5:$AB$1204,Sales!$R$5:$R$1204,TEXT(DATE(YEAR(TodayDate),MONTH(TodayDate)-8,1),"yyyy-mm")),2) -> 0 | H67: =ROUND(SUMIFS(Payroll!$Y$5:$Y$364,Payroll!$Q$5:$Q$364,TEXT(DATE(YEAR(TodayDate),MONTH(TodayDate)-8,1),"yyyy-mm")),2) -> 0 | I67: =ROUND(SUMIFS(Expenses!$F$5:$F$604,Expenses!$P$5:$P$604,TEXT(DATE(YEAR(TodayDate),MONTH(TodayDate)-8,1),"yyyy-mm")),2) -> 0 | J67: =ROUND(SUMIFS(Sales!$Y$5:$Y$1204,Sales!$R$5:$R$1204,TEXT(DATE(YEAR(TodayDate),MONTH(TodayDate)-8,1),"yyyy-mm"))-SUMIFS(Sales!$AB$5:$AB$1204,Sales!$R$5:$R$1204,TEXT(DATE(YEAR(TodayDate),MONTH(TodayDate)-8,1),"yyyy-mm"))-SUMIFS(Payroll!$Y$5:$Y$364,Payroll!$Q$5:$Q$364,TEXT(DATE(YEAR(TodayDate),MONTH(TodayDate)-8,1),"yyyy-mm"))-SUMIFS(Expenses!$F$5:$F$604,Expenses!$P$5:$P$604,TEXT(DATE(YEAR(TodayDate),MONTH(TodayDate)-8,1),"yyyy-mm")),2) -> 0 | K67: =IF(SUMIFS(Sales!$Y$5:$Y$1204,Sales!$R$5:$R$1204,TEXT(DATE(YEAR(TodayDate),MONTH(TodayDate)-8,1),"yyyy-mm"))<=0,"",(SUMIFS(Sales!$Y$5:$Y$1204,Sales!$R$5:$R$1204,TEXT(DATE(YEAR(TodayDate),MONTH(TodayDate)-8,1),"yyyy-mm"))-SUMIFS(Sales!$AB$5:$AB$1204,Sales!$R$5:$R$1204,TEXT(DATE(YEAR(TodayDate),MONTH(TodayDate)-8,1),"yyyy-mm"))-SUMIFS(Payroll!$Y$5:$Y$364,Payroll!$Q$5:$Q$364,TEXT(DATE(YEAR(TodayDate),MONTH(TodayDate)-8,1),"yyyy-mm"))-SUMIFS(Expenses!$F$5:$F$604,Expenses!$P$5:$P$604,TEXT(DATE(YEAR(TodayDate),MONTH(TodayDate)-8,1),"yyyy-mm")))/SUMIFS(Sales!$Y$5:$Y$1204,Sales!$R$5:$R$1204,TEXT(DATE(YEAR(TodayDate),MONTH(TodayDate)-8,1),"yyyy-mm"))) -> 0 | L67: =COUNTIFS(Appointments!$S$5:$S$1204,TEXT(DATE(YEAR(TodayDate),MONTH(TodayDate)-8,1),"yyyy-mm"),Appointments!$M$5:$M$1204,"Completed") -> 0 | M67: =IFERROR(SUMIFS(Sales!$Y$5:$Y$1204,Sales!$R$5:$R$1204,TEXT(DATE(YEAR(TodayDate),MONTH(TodayDate)-8,1),"yyyy-mm"))/MAX(1,COUNTIFS(Appointments!$S$5:$S$1204,TEXT(DATE(YEAR(TodayDate),MONTH(TodayDate)-8,1),"yyyy-mm"),Appointments!$M$5:$M$1204,"Completed")),"") -> 0
A68: =TEXT(DATE(YEAR(TodayDate),MONTH(TodayDate)-7,1),"mmm yy") -> 0 | B68: =ROUND(SUMIFS(Sales!$Y$5:$Y$1204,Sales!$R$5:$R$1204,TEXT(DATE(YEAR(TodayDate),MONTH(TodayDate)-7,1),"yyyy-mm")),2) -> 0 | C68: =ROUND(RevenueTargetMonth,2) -> 0 | D68: =ROUND(SUMIFS(Sales!$Y$5:$Y$1204,Sales!$R$5:$R$1204,TEXT(DATE(YEAR(TodayDate),MONTH(TodayDate)-7,1),"yyyy-mm"))-RevenueTargetMonth,2) -> 0 | E68: =ROUND(SUMIFS(Sales!$Y$5:$Y$1204,Sales!$R$5:$R$1204,TEXT(DATE(YEAR(TodayDate),MONTH(TodayDate)-7,1),"yyyy-mm"),Sales!$H$5:$H$1204,"Service"),2) -> 0 | F68: =ROUND(SUMIFS(Sales!$Y$5:$Y$1204,Sales!$R$5:$R$1204,TEXT(DATE(YEAR(TodayDate),MONTH(TodayDate)-7,1),"yyyy-mm"),Sales!$H$5:$H$1204,"Retail"),2) -> 0 | G68: =ROUND(SUMIFS(Sales!$AB$5:$AB$1204,Sales!$R$5:$R$1204,TEXT(DATE(YEAR(TodayDate),MONTH(TodayDate)-7,1),"yyyy-mm")),2) -> 0 | H68: =ROUND(SUMIFS(Payroll!$Y$5:$Y$364,Payroll!$Q$5:$Q$364,TEXT(DATE(YEAR(TodayDate),MONTH(TodayDate)-7,1),"yyyy-mm")),2) -> 0 | I68: =ROUND(SUMIFS(Expenses!$F$5:$F$604,Expenses!$P$5:$P$604,TEXT(DATE(YEAR(TodayDate),MONTH(TodayDate)-7,1),"yyyy-mm")),2) -> 0 | J68: =ROUND(SUMIFS(Sales!$Y$5:$Y$1204,Sales!$R$5:$R$1204,TEXT(DATE(YEAR(TodayDate),MONTH(TodayDate)-7,1),"yyyy-mm"))-SUMIFS(Sales!$AB$5:$AB$1204,Sales!$R$5:$R$1204,TEXT(DATE(YEAR(TodayDate),MONTH(TodayDate)-7,1),"yyyy-mm"))-SUMIFS(Payroll!$Y$5:$Y$364,Payroll!$Q$5:$Q$364,TEXT(DATE(YEAR(TodayDate),MONTH(TodayDate)-7,1),"yyyy-mm"))-SUMIFS(Expenses!$F$5:$F$604,Expenses!$P$5:$P$604,TEXT(DATE(YEAR(TodayDate),MONTH(TodayDate)-7,1),"yyyy-mm")),2) -> 0 | K68: =IF(SUMIFS(Sales!$Y$5:$Y$1204,Sales!$R$5:$R$1204,TEXT(DATE(YEAR(TodayDate),MONTH(TodayDate)-7,1),"yyyy-mm"))<=0,"",(SUMIFS(Sales!$Y$5:$Y$1204,Sales!$R$5:$R$1204,TEXT(DATE(YEAR(TodayDate),MONTH(TodayDate)-7,1),"yyyy-mm"))-SUMIFS(Sales!$AB$5:$AB$1204,Sales!$R$5:$R$1204,TEXT(DATE(YEAR(TodayDate),MONTH(TodayDate)-7,1),"yyyy-mm"))-SUMIFS(Payroll!$Y$5:$Y$364,Payroll!$Q$5:$Q$364,TEXT(DATE(YEAR(TodayDate),MONTH(TodayDate)-7,1),"yyyy-mm"))-SUMIFS(Expenses!$F$5:$F$604,Expenses!$P$5:$P$604,TEXT(DATE(YEAR(TodayDate),MONTH(TodayDate)-7,1),"yyyy-mm")))/SUMIFS(Sales!$Y$5:$Y$1204,Sales!$R$5:$R$1204,TEXT(DATE(YEAR(TodayDate),MONTH(TodayDate)-7,1),"yyyy-mm"))) -> 0 | L68: =COUNTIFS(Appointments!$S$5:$S$1204,TEXT(DATE(YEAR(TodayDate),MONTH(TodayDate)-7,1),"yyyy-mm"),Appointments!$M$5:$M$1204,"Completed") -> 0 | M68: =IFERROR(SUMIFS(Sales!$Y$5:$Y$1204,Sales!$R$5:$R$1204,TEXT(DATE(YEAR(TodayDate),MONTH(TodayDate)-7,1),"yyyy-mm"))/MAX(1,COUNTIFS(Appointments!$S$5:$S$1204,TEXT(DATE(YEAR(TodayDate),MONTH(TodayDate)-7,1),"yyyy-mm"),Appointments!$M$5:$M$1204,"Completed")),"") -> 0
A69: =TEXT(DATE(YEAR(TodayDate),MONTH(TodayDate)-6,1),"mmm yy") -> 0 | B69: =ROUND(SUMIFS(Sales!$Y$5:$Y$1204,Sales!$R$5:$R$1204,TEXT(DATE(YEAR(TodayDate),MONTH(TodayDate)-6,1),"yyyy-mm")),2) -> 0 | C69: =ROUND(RevenueTargetMonth,2) -> 0 | D69: =ROUND(SUMIFS(Sales!$Y$5:$Y$1204,Sales!$R$5:$R$1204,TEXT(DATE(YEAR(TodayDate),MONTH(TodayDate)-6,1),"yyyy-mm"))-RevenueTargetMonth,2) -> 0 | E69: =ROUND(SUMIFS(Sales!$Y$5:$Y$1204,Sales!$R$5:$R$1204,TEXT(DATE(YEAR(TodayDate),MONTH(TodayDate)-6,1),"yyyy-mm"),Sales!$H$5:$H$1204,"Service"),2) -> 0 | F69: =ROUND(SUMIFS(Sales!$Y$5:$Y$1204,Sales!$R$5:$R$1204,TEXT(DATE(YEAR(TodayDate),MONTH(TodayDate)-6,1),"yyyy-mm"),Sales!$H$5:$H$1204,"Retail"),2) -> 0 | G69: =ROUND(SUMIFS(Sales!$AB$5:$AB$1204,Sales!$R$5:$R$1204,TEXT(DATE(YEAR(TodayDate),MONTH(TodayDate)-6,1),"yyyy-mm")),2) -> 0 | H69: =ROUND(SUMIFS(Payroll!$Y$5:$Y$364,Payroll!$Q$5:$Q$364,TEXT(DATE(YEAR(TodayDate),MONTH(TodayDate)-6,1),"yyyy-mm")),2) -> 0 | I69: =ROUND(SUMIFS(Expenses!$F$5:$F$604,Expenses!$P$5:$P$604,TEXT(DATE(YEAR(TodayDate),MONTH(TodayDate)-6,1),"yyyy-mm")),2) -> 0 | J69: =ROUND(SUMIFS(Sales!$Y$5:$Y$1204,Sales!$R$5:$R$1204,TEXT(DATE(YEAR(TodayDate),MONTH(TodayDate)-6,1),"yyyy-mm"))-SUMIFS(Sales!$AB$5:$AB$1204,Sales!$R$5:$R$1204,TEXT(DATE(YEAR(TodayDate),MONTH(TodayDate)-6,1),"yyyy-mm"))-SUMIFS(Payroll!$Y$5:$Y$364,Payroll!$Q$5:$Q$364,TEXT(DATE(YEAR(TodayDate),MONTH(TodayDate)-6,1),"yyyy-mm"))-SUMIFS(Expenses!$F$5:$F$604,Expenses!$P$5:$P$604,TEXT(DATE(YEAR(TodayDate),MONTH(TodayDate)-6,1),"yyyy-mm")),2) -> 0 | K69: =IF(SUMIFS(Sales!$Y$5:$Y$1204,Sales!$R$5:$R$1204,TEXT(DATE(YEAR(TodayDate),MONTH(TodayDate)-6,1),"yyyy-mm"))<=0,"",(SUMIFS(Sales!$Y$5:$Y$1204,Sales!$R$5:$R$1204,TEXT(DATE(YEAR(TodayDate),MONTH(TodayDate)-6,1),"yyyy-mm"))-SUMIFS(Sales!$AB$5:$AB$1204,Sales!$R$5:$R$1204,TEXT(DATE(YEAR(TodayDate),MONTH(TodayDate)-6,1),"yyyy-mm"))-SUMIFS(Payroll!$Y$5:$Y$364,Payroll!$Q$5:$Q$364,TEXT(DATE(YEAR(TodayDate),MONTH(TodayDate)-6,1),"yyyy-mm"))-SUMIFS(Expenses!$F$5:$F$604,Expenses!$P$5:$P$604,TEXT(DATE(YEAR(TodayDate),MONTH(TodayDate)-6,1),"yyyy-mm")))/SUMIFS(Sales!$Y$5:$Y$1204,Sales!$R$5:$R$1204,TEXT(DATE(YEAR(TodayDate),MONTH(TodayDate)-6,1),"yyyy-mm"))) -> 0 | L69: =COUNTIFS(Appointments!$S$5:$S$1204,TEXT(DATE(YEAR(TodayDate),MONTH(TodayDate)-6,1),"yyyy-mm"),Appointments!$M$5:$M$1204,"Completed") -> 0 | M69: =IFERROR(SUMIFS(Sales!$Y$5:$Y$1204,Sales!$R$5:$R$1204,TEXT(DATE(YEAR(TodayDate),MONTH(TodayDate)-6,1),"yyyy-mm"))/MAX(1,COUNTIFS(Appointments!$S$5:$S$1204,TEXT(DATE(YEAR(TodayDate),MONTH(TodayDate)-6,1),"yyyy-mm"),Appointments!$M$5:$M$1204,"Completed")),"") -> 0
A70: =TEXT(DATE(YEAR(TodayDate),MONTH(TodayDate)-5,1),"mmm yy") -> 0 | B70: =ROUND(SUMIFS(Sales!$Y$5:$Y$1204,Sales!$R$5:$R$1204,TEXT(DATE(YEAR(TodayDate),MONTH(TodayDate)-5,1),"yyyy-mm")),2) -> 0 | C70: =ROUND(RevenueTargetMonth,2) -> 0 | D70: =ROUND(SUMIFS(Sales!$Y$5:$Y$1204,Sales!$R$5:$R$1204,TEXT(DATE(YEAR(TodayDate),MONTH(TodayDate)-5,1),"yyyy-mm"))-RevenueTargetMonth,2) -> 0 | E70: =ROUND(SUMIFS(Sales!$Y$5:$Y$1204,Sales!$R$5:$R$1204,TEXT(DATE(YEAR(TodayDate),MONTH(TodayDate)-5,1),"yyyy-mm"),Sales!$H$5:$H$1204,"Service"),2) -> 0 | F70: =ROUND(SUMIFS(Sales!$Y$5:$Y$1204,Sales!$R$5:$R$1204,TEXT(DATE(YEAR(TodayDate),MONTH(TodayDate)-5,1),"yyyy-mm"),Sales!$H$5:$H$1204,"Retail"),2) -> 0 | G70: =ROUND(SUMIFS(Sales!$AB$5:$AB$1204,Sales!$R$5:$R$1204,TEXT(DATE(YEAR(TodayDate),MONTH(TodayDate)-5,1),"yyyy-mm")),2) -> 0 | H70: =ROUND(SUMIFS(Payroll!$Y$5:$Y$364,Payroll!$Q$5:$Q$364,TEXT(DATE(YEAR(TodayDate),MONTH(TodayDate)-5,1),"yyyy-mm")),2) -> 0 | I70: =ROUND(SUMIFS(Expenses!$F$5:$F$604,Expenses!$P$5:$P$604,TEXT(DATE(YEAR(TodayDate),MONTH(TodayDate)-5,1),"yyyy-mm")),2) -> 0 | J70: =ROUND(SUMIFS(Sales!$Y$5:$Y$1204,Sales!$R$5:$R$1204,TEXT(DATE(YEAR(TodayDate),MONTH(TodayDate)-5,1),"yyyy-mm"))-SUMIFS(Sales!$AB$5:$AB$1204,Sales!$R$5:$R$1204,TEXT(DATE(YEAR(TodayDate),MONTH(TodayDate)-5,1),"yyyy-mm"))-SUMIFS(Payroll!$Y$5:$Y$364,Payroll!$Q$5:$Q$364,TEXT(DATE(YEAR(TodayDate),MONTH(TodayDate)-5,1),"yyyy-mm"))-SUMIFS(Expenses!$F$5:$F$604,Expenses!$P$5:$P$604,TEXT(DATE(YEAR(TodayDate),MONTH(TodayDate)-5,1),"yyyy-mm")),2) -> 0 | K70: =IF(SUMIFS(Sales!$Y$5:$Y$1204,Sales!$R$5:$R$1204,TEXT(DATE(YEAR(TodayDate),MONTH(TodayDate)-5,1),"yyyy-mm"))<=0,"",(SUMIFS(Sales!$Y$5:$Y$1204,Sales!$R$5:$R$1204,TEXT(DATE(YEAR(TodayDate),MONTH(TodayDate)-5,1),"yyyy-mm"))-SUMIFS(Sales!$AB$5:$AB$1204,Sales!$R$5:$R$1204,TEXT(DATE(YEAR(TodayDate),MONTH(TodayDate)-5,1),"yyyy-mm"))-SUMIFS(Payroll!$Y$5:$Y$364,Payroll!$Q$5:$Q$364,TEXT(DATE(YEAR(TodayDate),MONTH(TodayDate)-5,1),"yyyy-mm"))-SUMIFS(Expenses!$F$5:$F$604,Expenses!$P$5:$P$604,TEXT(DATE(YEAR(TodayDate),MONTH(TodayDate)-5,1),"yyyy-mm")))/SUMIFS(Sales!$Y$5:$Y$1204,Sales!$R$5:$R$1204,TEXT(DATE(YEAR(TodayDate),MONTH(TodayDate)-5,1),"yyyy-mm"))) -> 0 | L70: =COUNTIFS(Appointments!$S$5:$S$1204,TEXT(DATE(YEAR(TodayDate),MONTH(TodayDate)-5,1),"yyyy-mm"),Appointments!$M$5:$M$1204,"Completed") -> 0 | M70: =IFERROR(SUMIFS(Sales!$Y$5:$Y$1204,Sales!$R$5:$R$1204,TEXT(DATE(YEAR(TodayDate),MONTH(TodayDate)-5,1),"yyyy-mm"))/MAX(1,COUNTIFS(Appointments!$S$5:$S$1204,TEXT(DATE(YEAR(TodayDate),MONTH(TodayDate)-5,1),"yyyy-mm"),Appointments!$M$5:$M$1204,"Completed")),"") -> 0
A71: =TEXT(DATE(YEAR(TodayDate),MONTH(TodayDate)-4,1),"mmm yy") -> 0 | B71: =ROUND(SUMIFS(Sales!$Y$5:$Y$1204,Sales!$R$5:$R$1204,TEXT(DATE(YEAR(TodayDate),MONTH(TodayDate)-4,1),"yyyy-mm")),2) -> 0 | C71: =ROUND(RevenueTargetMonth,2) -> 0 | D71: =ROUND(SUMIFS(Sales!$Y$5:$Y$1204,Sales!$R$5:$R$1204,TEXT(DATE(YEAR(TodayDate),MONTH(TodayDate)-4,1),"yyyy-mm"))-RevenueTargetMonth,2) -> 0 | E71: =ROUND(SUMIFS(Sales!$Y$5:$Y$1204,Sales!$R$5:$R$1204,TEXT(DATE(YEAR(TodayDate),MONTH(TodayDate)-4,1),"yyyy-mm"),Sales!$H$5:$H$1204,"Service"),2) -> 0 | F71: =ROUND(SUMIFS(Sales!$Y$5:$Y$1204,Sales!$R$5:$R$1204,TEXT(DATE(YEAR(TodayDate),MONTH(TodayDate)-4,1),"yyyy-mm"),Sales!$H$5:$H$1204,"Retail"),2) -> 0 | G71: =ROUND(SUMIFS(Sales!$AB$5:$AB$1204,Sales!$R$5:$R$1204,TEXT(DATE(YEAR(TodayDate),MONTH(TodayDate)-4,1),"yyyy-mm")),2) -> 0 | H71: =ROUND(SUMIFS(Payroll!$Y$5:$Y$364,Payroll!$Q$5:$Q$364,TEXT(DATE(YEAR(TodayDate),MONTH(TodayDate)-4,1),"yyyy-mm")),2) -> 0 | I71: =ROUND(SUMIFS(Expenses!$F$5:$F$604,Expenses!$P$5:$P$604,TEXT(DATE(YEAR(TodayDate),MONTH(TodayDate)-4,1),"yyyy-mm")),2) -> 0 | J71: =ROUND(SUMIFS(Sales!$Y$5:$Y$1204,Sales!$R$5:$R$1204,TEXT(DATE(YEAR(TodayDate),MONTH(TodayDate)-4,1),"yyyy-mm"))-SUMIFS(Sales!$AB$5:$AB$1204,Sales!$R$5:$R$1204,TEXT(DATE(YEAR(TodayDate),MONTH(TodayDate)-4,1),"yyyy-mm"))-SUMIFS(Payroll!$Y$5:$Y$364,Payroll!$Q$5:$Q$364,TEXT(DATE(YEAR(TodayDate),MONTH(TodayDate)-4,1),"yyyy-mm"))-SUMIFS(Expenses!$F$5:$F$604,Expenses!$P$5:$P$604,TEXT(DATE(YEAR(TodayDate),MONTH(TodayDate)-4,1),"yyyy-mm")),2) -> 0 | K71: =IF(SUMIFS(Sales!$Y$5:$Y$1204,Sales!$R$5:$R$1204,TEXT(DATE(YEAR(TodayDate),MONTH(TodayDate)-4,1),"yyyy-mm"))<=0,"",(SUMIFS(Sales!$Y$5:$Y$1204,Sales!$R$5:$R$1204,TEXT(DATE(YEAR(TodayDate),MONTH(TodayDate)-4,1),"yyyy-mm"))-SUMIFS(Sales!$AB$5:$AB$1204,Sales!$R$5:$R$1204,TEXT(DATE(YEAR(TodayDate),MONTH(TodayDate)-4,1),"yyyy-mm"))-SUMIFS(Payroll!$Y$5:$Y$364,Payroll!$Q$5:$Q$364,TEXT(DATE(YEAR(TodayDate),MONTH(TodayDate)-4,1),"yyyy-mm"))-SUMIFS(Expenses!$F$5:$F$604,Expenses!$P$5:$P$604,TEXT(DATE(YEAR(TodayDate),MONTH(TodayDate)-4,1),"yyyy-mm")))/SUMIFS(Sales!$Y$5:$Y$1204,Sales!$R$5:$R$1204,TEXT(DATE(YEAR(TodayDate),MONTH(TodayDate)-4,1),"yyyy-mm"))) -> 0 | L71: =COUNTIFS(Appointments!$S$5:$S$1204,TEXT(DATE(YEAR(TodayDate),MONTH(TodayDate)-4,1),"yyyy-mm"),Appointments!$M$5:$M$1204,"Completed") -> 0 | M71: =IFERROR(SUMIFS(Sales!$Y$5:$Y$1204,Sales!$R$5:$R$1204,TEXT(DATE(YEAR(TodayDate),MONTH(TodayDate)-4,1),"yyyy-mm"))/MAX(1,COUNTIFS(Appointments!$S$5:$S$1204,TEXT(DATE(YEAR(TodayDate),MONTH(TodayDate)-4,1),"yyyy-mm"),Appointments!$M$5:$M$1204,"Completed")),"") -> 0
A72: =TEXT(DATE(YEAR(TodayDate),MONTH(TodayDate)-3,1),"mmm yy") -> 0 | B72: =ROUND(SUMIFS(Sales!$Y$5:$Y$1204,Sales!$R$5:$R$1204,TEXT(DATE(YEAR(TodayDate),MONTH(TodayDate)-3,1),"yyyy-mm")),2) -> 0 | C72: =ROUND(RevenueTargetMonth,2) -> 0 | D72: =ROUND(SUMIFS(Sales!$Y$5:$Y$1204,Sales!$R$5:$R$1204,TEXT(DATE(YEAR(TodayDate),MONTH(TodayDate)-3,1),"yyyy-mm"))-RevenueTargetMonth,2) -> 0 | E72: =ROUND(SUMIFS(Sales!$Y$5:$Y$1204,Sales!$R$5:$R$1204,TEXT(DATE(YEAR(TodayDate),MONTH(TodayDate)-3,1),"yyyy-mm"),Sales!$H$5:$H$1204,"Service"),2) -> 0 | F72: =ROUND(SUMIFS(Sales!$Y$5:$Y$1204,Sales!$R$5:$R$1204,TEXT(DATE(YEAR(TodayDate),MONTH(TodayDate)-3,1),"yyyy-mm"),Sales!$H$5:$H$1204,"Retail"),2) -> 0 | G72: =ROUND(SUMIFS(Sales!$AB$5:$AB$1204,Sales!$R$5:$R$1204,TEXT(DATE(YEAR(TodayDate),MONTH(TodayDate)-3,1),"yyyy-mm")),2) -> 0 | H72: =ROUND(SUMIFS(Payroll!$Y$5:$Y$364,Payroll!$Q$5:$Q$364,TEXT(DATE(YEAR(TodayDate),MONTH(TodayDate)-3,1),"yyyy-mm")),2) -> 0 | I72: =ROUND(SUMIFS(Expenses!$F$5:$F$604,Expenses!$P$5:$P$604,TEXT(DATE(YEAR(TodayDate),MONTH(TodayDate)-3,1),"yyyy-mm")),2) -> 0 | J72: =ROUND(SUMIFS(Sales!$Y$5:$Y$1204,Sales!$R$5:$R$1204,TEXT(DATE(YEAR(TodayDate),MONTH(TodayDate)-3,1),"yyyy-mm"))-SUMIFS(Sales!$AB$5:$AB$1204,Sales!$R$5:$R$1204,TEXT(DATE(YEAR(TodayDate),MONTH(TodayDate)-3,1),"yyyy-mm"))-SUMIFS(Payroll!$Y$5:$Y$364,Payroll!$Q$5:$Q$364,TEXT(DATE(YEAR(TodayDate),MONTH(TodayDate)-3,1),"yyyy-mm"))-SUMIFS(Expenses!$F$5:$F$604,Expenses!$P$5:$P$604,TEXT(DATE(YEAR(TodayDate),MONTH(TodayDate)-3,1),"yyyy-mm")),2) -> 0 | K72: =IF(SUMIFS(Sales!$Y$5:$Y$1204,Sales!$R$5:$R$1204,TEXT(DATE(YEAR(TodayDate),MONTH(TodayDate)-3,1),"yyyy-mm"))<=0,"",(SUMIFS(Sales!$Y$5:$Y$1204,Sales!$R$5:$R$1204,TEXT(DATE(YEAR(TodayDate),MONTH(TodayDate)-3,1),"yyyy-mm"))-SUMIFS(Sales!$AB$5:$AB$1204,Sales!$R$5:$R$1204,TEXT(DATE(YEAR(TodayDate),MONTH(TodayDate)-3,1),"yyyy-mm"))-SUMIFS(Payroll!$Y$5:$Y$364,Payroll!$Q$5:$Q$364,TEXT(DATE(YEAR(TodayDate),MONTH(TodayDate)-3,1),"yyyy-mm"))-SUMIFS(Expenses!$F$5:$F$604,Expenses!$P$5:$P$604,TEXT(DATE(YEAR(TodayDate),MONTH(TodayDate)-3,1),"yyyy-mm")))/SUMIFS(Sales!$Y$5:$Y$1204,Sales!$R$5:$R$1204,TEXT(DATE(YEAR(TodayDate),MONTH(TodayDate)-3,1),"yyyy-mm"))) -> 0 | L72: =COUNTIFS(Appointments!$S$5:$S$1204,TEXT(DATE(YEAR(TodayDate),MONTH(TodayDate)-3,1),"yyyy-mm"),Appointments!$M$5:$M$1204,"Completed") -> 0 | M72: =IFERROR(SUMIFS(Sales!$Y$5:$Y$1204,Sales!$R$5:$R$1204,TEXT(DATE(YEAR(TodayDate),MONTH(TodayDate)-3,1),"yyyy-mm"))/MAX(1,COUNTIFS(Appointments!$S$5:$S$1204,TEXT(DATE(YEAR(TodayDate),MONTH(TodayDate)-3,1),"yyyy-mm"),Appointments!$M$5:$M$1204,"Completed")),"") -> 0
A73: =TEXT(DATE(YEAR(TodayDate),MONTH(TodayDate)-2,1),"mmm yy") -> 0 | B73: =ROUND(SUMIFS(Sales!$Y$5:$Y$1204,Sales!$R$5:$R$1204,TEXT(DATE(YEAR(TodayDate),MONTH(TodayDate)-2,1),"yyyy-mm")),2) -> 0 | C73: =ROUND(RevenueTargetMonth,2) -> 0 | D73: =ROUND(SUMIFS(Sales!$Y$5:$Y$1204,Sales!$R$5:$R$1204,TEXT(DATE(YEAR(TodayDate),MONTH(TodayDate)-2,1),"yyyy-mm"))-RevenueTargetMonth,2) -> 0 | E73: =ROUND(SUMIFS(Sales!$Y$5:$Y$1204,Sales!$R$5:$R$1204,TEXT(DATE(YEAR(TodayDate),MONTH(TodayDate)-2,1),"yyyy-mm"),Sales!$H$5:$H$1204,"Service"),2) -> 0 | F73: =ROUND(SUMIFS(Sales!$Y$5:$Y$1204,Sales!$R$5:$R$1204,TEXT(DATE(YEAR(TodayDate),MONTH(TodayDate)-2,1),"yyyy-mm"),Sales!$H$5:$H$1204,"Retail"),2) -> 0 | G73: =ROUND(SUMIFS(Sales!$AB$5:$AB$1204,Sales!$R$5:$R$1204,TEXT(DATE(YEAR(TodayDate),MONTH(TodayDate)-2,1),"yyyy-mm")),2) -> 0 | H73: =ROUND(SUMIFS(Payroll!$Y$5:$Y$364,Payroll!$Q$5:$Q$364,TEXT(DATE(YEAR(TodayDate),MONTH(TodayDate)-2,1),"yyyy-mm")),2) -> 0 | I73: =ROUND(SUMIFS(Expenses!$F$5:$F$604,Expenses!$P$5:$P$604,TEXT(DATE(YEAR(TodayDate),MONTH(TodayDate)-2,1),"yyyy-mm")),2) -> 0 | J73: =ROUND(SUMIFS(Sales!$Y$5:$Y$1204,Sales!$R$5:$R$1204,TEXT(DATE(YEAR(TodayDate),MONTH(TodayDate)-2,1),"yyyy-mm"))-SUMIFS(Sales!$AB$5:$AB$1204,Sales!$R$5:$R$1204,TEXT(DATE(YEAR(TodayDate),MONTH(TodayDate)-2,1),"yyyy-mm"))-SUMIFS(Payroll!$Y$5:$Y$364,Payroll!$Q$5:$Q$364,TEXT(DATE(YEAR(TodayDate),MONTH(TodayDate)-2,1),"yyyy-mm"))-SUMIFS(Expenses!$F$5:$F$604,Expenses!$P$5:$P$604,TEXT(DATE(YEAR(TodayDate),MONTH(TodayDate)-2,1),"yyyy-mm")),2) -> 0 | K73: =IF(SUMIFS(Sales!$Y$5:$Y$1204,Sales!$R$5:$R$1204,TEXT(DATE(YEAR(TodayDate),MONTH(TodayDate)-2,1),"yyyy-mm"))<=0,"",(SUMIFS(Sales!$Y$5:$Y$1204,Sales!$R$5:$R$1204,TEXT(DATE(YEAR(TodayDate),MONTH(TodayDate)-2,1),"yyyy-mm"))-SUMIFS(Sales!$AB$5:$AB$1204,Sales!$R$5:$R$1204,TEXT(DATE(YEAR(TodayDate),MONTH(TodayDate)-2,1),"yyyy-mm"))-SUMIFS(Payroll!$Y$5:$Y$364,Payroll!$Q$5:$Q$364,TEXT(DATE(YEAR(TodayDate),MONTH(TodayDate)-2,1),"yyyy-mm"))-SUMIFS(Expenses!$F$5:$F$604,Expenses!$P$5:$P$604,TEXT(DATE(YEAR(TodayDate),MONTH(TodayDate)-2,1),"yyyy-mm")))/SUMIFS(Sales!$Y$5:$Y$1204,Sales!$R$5:$R$1204,TEXT(DATE(YEAR(TodayDate),MONTH(TodayDate)-2,1),"yyyy-mm"))) -> 0 | L73: =COUNTIFS(Appointments!$S$5:$S$1204,TEXT(DATE(YEAR(TodayDate),MONTH(TodayDate)-2,1),"yyyy-mm"),Appointments!$M$5:$M$1204,"Completed") -> 0 | M73: =IFERROR(SUMIFS(Sales!$Y$5:$Y$1204,Sales!$R$5:$R$1204,TEXT(DATE(YEAR(TodayDate),MONTH(TodayDate)-2,1),"yyyy-mm"))/MAX(1,COUNTIFS(Appointments!$S$5:$S$1204,TEXT(DATE(YEAR(TodayDate),MONTH(TodayDate)-2,1),"yyyy-mm"),Appointments!$M$5:$M$1204,"Completed")),"") -> 0
A74: =TEXT(DATE(YEAR(TodayDate),MONTH(TodayDate)-1,1),"mmm yy") -> 0 | B74: =ROUND(SUMIFS(Sales!$Y$5:$Y$1204,Sales!$R$5:$R$1204,TEXT(DATE(YEAR(TodayDate),MONTH(TodayDate)-1,1),"yyyy-mm")),2) -> 0 | C74: =ROUND(RevenueTargetMonth,2) -> 0 | D74: =ROUND(SUMIFS(Sales!$Y$5:$Y$1204,Sales!$R$5:$R$1204,TEXT(DATE(YEAR(TodayDate),MONTH(TodayDate)-1,1),"yyyy-mm"))-RevenueTargetMonth,2) -> 0 | E74: =ROUND(SUMIFS(Sales!$Y$5:$Y$1204,Sales!$R$5:$R$1204,TEXT(DATE(YEAR(TodayDate),MONTH(TodayDate)-1,1),"yyyy-mm"),Sales!$H$5:$H$1204,"Service"),2) -> 0 | F74: =ROUND(SUMIFS(Sales!$Y$5:$Y$1204,Sales!$R$5:$R$1204,TEXT(DATE(YEAR(TodayDate),MONTH(TodayDate)-1,1),"yyyy-mm"),Sales!$H$5:$H$1204,"Retail"),2) -> 0 | G74: =ROUND(SUMIFS(Sales!$AB$5:$AB$1204,Sales!$R$5:$R$1204,TEXT(DATE(YEAR(TodayDate),MONTH(TodayDate)-1,1),"yyyy-mm")),2) -> 0 | H74: =ROUND(SUMIFS(Payroll!$Y$5:$Y$364,Payroll!$Q$5:$Q$364,TEXT(DATE(YEAR(TodayDate),MONTH(TodayDate)-1,1),"yyyy-mm")),2) -> 0 | I74: =ROUND(SUMIFS(Expenses!$F$5:$F$604,Expenses!$P$5:$P$604,TEXT(DATE(YEAR(TodayDate),MONTH(TodayDate)-1,1),"yyyy-mm")),2) -> 0 | J74: =ROUND(SUMIFS(Sales!$Y$5:$Y$1204,Sales!$R$5:$R$1204,TEXT(DATE(YEAR(TodayDate),MONTH(TodayDate)-1,1),"yyyy-mm"))-SUMIFS(Sales!$AB$5:$AB$1204,Sales!$R$5:$R$1204,TEXT(DATE(YEAR(TodayDate),MONTH(TodayDate)-1,1),"yyyy-mm"))-SUMIFS(Payroll!$Y$5:$Y$364,Payroll!$Q$5:$Q$364,TEXT(DATE(YEAR(TodayDate),MONTH(TodayDate)-1,1),"yyyy-mm"))-SUMIFS(Expenses!$F$5:$F$604,Expenses!$P$5:$P$604,TEXT(DATE(YEAR(TodayDate),MONTH(TodayDate)-1,1),"yyyy-mm")),2) -> 0 | K74: =IF(SUMIFS(Sales!$Y$5:$Y$1204,Sales!$R$5:$R$1204,TEXT(DATE(YEAR(TodayDate),MONTH(TodayDate)-1,1),"yyyy-mm"))<=0,"",(SUMIFS(Sales!$Y$5:$Y$1204,Sales!$R$5:$R$1204,TEXT(DATE(YEAR(TodayDate),MONTH(TodayDate)-1,1),"yyyy-mm"))-SUMIFS(Sales!$AB$5:$AB$1204,Sales!$R$5:$R$1204,TEXT(DATE(YEAR(TodayDate),MONTH(TodayDate)-1,1),"yyyy-mm"))-SUMIFS(Payroll!$Y$5:$Y$364,Payroll!$Q$5:$Q$364,TEXT(DATE(YEAR(TodayDate),MONTH(TodayDate)-1,1),"yyyy-mm"))-SUMIFS(Expenses!$F$5:$F$604,Expenses!$P$5:$P$604,TEXT(DATE(YEAR(TodayDate),MONTH(TodayDate)-1,1),"yyyy-mm")))/SUMIFS(Sales!$Y$5:$Y$1204,Sales!$R$5:$R$1204,TEXT(DATE(YEAR(TodayDate),MONTH(TodayDate)-1,1),"yyyy-mm"))) -> 0 | L74: =COUNTIFS(Appointments!$S$5:$S$1204,TEXT(DATE(YEAR(TodayDate),MONTH(TodayDate)-1,1),"yyyy-mm"),Appointments!$M$5:$M$1204,"Completed") -> 0 | M74: =IFERROR(SUMIFS(Sales!$Y$5:$Y$1204,Sales!$R$5:$R$1204,TEXT(DATE(YEAR(TodayDate),MONTH(TodayDate)-1,1),"yyyy-mm"))/MAX(1,COUNTIFS(Appointments!$S$5:$S$1204,TEXT(DATE(YEAR(TodayDate),MONTH(TodayDate)-1,1),"yyyy-mm"),Appointments!$M$5:$M$1204,"Completed")),"") -> 0
A75: =TEXT(DATE(YEAR(TodayDate),MONTH(TodayDate)-0,1),"mmm yy") -> 0 | B75: =ROUND(SUMIFS(Sales!$Y$5:$Y$1204,Sales!$R$5:$R$1204,TEXT(DATE(YEAR(TodayDate),MONTH(TodayDate)-0,1),"yyyy-mm")),2) -> 0 | C75: =ROUND(RevenueTargetMonth,2) -> 0 | D75: =ROUND(SUMIFS(Sales!$Y$5:$Y$1204,Sales!$R$5:$R$1204,TEXT(DATE(YEAR(TodayDate),MONTH(TodayDate)-0,1),"yyyy-mm"))-RevenueTargetMonth,2) -> 0 | E75: =ROUND(SUMIFS(Sales!$Y$5:$Y$1204,Sales!$R$5:$R$1204,TEXT(DATE(YEAR(TodayDate),MONTH(TodayDate)-0,1),"yyyy-mm"),Sales!$H$5:$H$1204,"Service"),2) -> 0 | F75: =ROUND(SUMIFS(Sales!$Y$5:$Y$1204,Sales!$R$5:$R$1204,TEXT(DATE(YEAR(TodayDate),MONTH(TodayDate)-0,1),"yyyy-mm"),Sales!$H$5:$H$1204,"Retail"),2) -> 0 | G75: =ROUND(SUMIFS(Sales!$AB$5:$AB$1204,Sales!$R$5:$R$1204,TEXT(DATE(YEAR(TodayDate),MONTH(TodayDate)-0,1),"yyyy-mm")),2) -> 0 | H75: =ROUND(SUMIFS(Payroll!$Y$5:$Y$364,Payroll!$Q$5:$Q$364,TEXT(DATE(YEAR(TodayDate),MONTH(TodayDate)-0,1),"yyyy-mm")),2) -> 0 | I75: =ROUND(SUMIFS(Expenses!$F$5:$F$604,Expenses!$P$5:$P$604,TEXT(DATE(YEAR(TodayDate),MONTH(TodayDate)-0,1),"yyyy-mm")),2) -> 0 | J75: =ROUND(SUMIFS(Sales!$Y$5:$Y$1204,Sales!$R$5:$R$1204,TEXT(DATE(YEAR(TodayDate),MONTH(TodayDate)-0,1),"yyyy-mm"))-SUMIFS(Sales!$AB$5:$AB$1204,Sales!$R$5:$R$1204,TEXT(DATE(YEAR(TodayDate),MONTH(TodayDate)-0,1),"yyyy-mm"))-SUMIFS(Payroll!$Y$5:$Y$364,Payroll!$Q$5:$Q$364,TEXT(DATE(YEAR(TodayDate),MONTH(TodayDate)-0,1),"yyyy-mm"))-SUMIFS(Expenses!$F$5:$F$604,Expenses!$P$5:$P$604,TEXT(DATE(YEAR(TodayDate),MONTH(TodayDate)-0,1),"yyyy-mm")),2) -> 0 | K75: =IF(SUMIFS(Sales!$Y$5:$Y$1204,Sales!$R$5:$R$1204,TEXT(DATE(YEAR(TodayDate),MONTH(TodayDate)-0,1),"yyyy-mm"))<=0,"",(SUMIFS(Sales!$Y$5:$Y$1204,Sales!$R$5:$R$1204,TEXT(DATE(YEAR(TodayDate),MONTH(TodayDate)-0,1),"yyyy-mm"))-SUMIFS(Sales!$AB$5:$AB$1204,Sales!$R$5:$R$1204,TEXT(DATE(YEAR(TodayDate),MONTH(TodayDate)-0,1),"yyyy-mm"))-SUMIFS(Payroll!$Y$5:$Y$364,Payroll!$Q$5:$Q$364,TEXT(DATE(YEAR(TodayDate),MONTH(TodayDate)-0,1),"yyyy-mm"))-SUMIFS(Expenses!$F$5:$F$604,Expenses!$P$5:$P$604,TEXT(DATE(YEAR(TodayDate),MONTH(TodayDate)-0,1),"yyyy-mm")))/SUMIFS(Sales!$Y$5:$Y$1204,Sales!$R$5:$R$1204,TEXT(DATE(YEAR(TodayDate),MONTH(TodayDate)-0,1),"yyyy-mm"))) -> 0 | L75: =COUNTIFS(Appointments!$S$5:$S$1204,TEXT(DATE(YEAR(TodayDate),MONTH(TodayDate)-0,1),"yyyy-mm"),Appointments!$M$5:$M$1204,"Completed") -> 0 | M75: =IFERROR(SUMIFS(Sales!$Y$5:$Y$1204,Sales!$R$5:$R$1204,TEXT(DATE(YEAR(TodayDate),MONTH(TodayDate)-0,1),"yyyy-mm"))/MAX(1,COUNTIFS(Appointments!$S$5:$S$1204,TEXT(DATE(YEAR(TodayDate),MONTH(TodayDate)-0,1),"yyyy-mm"),Appointments!$M$5:$M$1204,"Completed")),"") -> 0
C76: Net sales, twelve months | G76: Operating profit, twelve months
A78: The month in one line
A79: Net sales | B79: Cost of sales | C79: Gross profit | D79: Wages | E79: Other costs | F79: Operating profit | G79: Margin | H79: Break-even sales
A80: =ROUND(SUMIFS(Sales!$Y$5:$Y$1204,Sales!$R$5:$R$1204,DashKey),2) -> 0 | B80: =ROUND(SUMIFS(Sales!$AB$5:$AB$1204,Sales!$R$5:$R$1204,DashKey),2) -> 0 | C80: =ROUND(MonthNetSales-MonthCostOfSales,2) -> 0 | D80: =ROUND(SUMIFS(Payroll!$Y$5:$Y$364,Payroll!$Q$5:$Q$364,DashKey),2) -> 0 | E80: =ROUND(SUMIFS(Expenses!$F$5:$F$604,Expenses!$P$5:$P$604,DashKey),2) -> 0 | F80: =ROUND(MonthNetSales-MonthCostOfSales-MonthWages-MonthExpenses,2) -> 0 | G80: =IF(MonthNetSales<=0,"",(MonthNetSales-MonthCostOfSales-MonthWages-MonthExpenses)/MonthNetSales) -> 0 | H80: =IF(MonthNetSales<=0,"",ROUND((MonthWages+MonthExpenses)/MAX(0.05,(MonthNetSales-MonthCostOfSales)/MonthNetSales),2)) -> 0
A82: Operating profit here is net sales less the cost of what you sold, less the full cost of the pay runs, less the expenses logged for the month. It is not a tax computation and it does not know about depreciation, drawings or loans - it is the number that tells you whether the month worked.

Sheet Appointments
A1: Appointment Planner | AF1: Novality Store | v1.0.0
A2: The diary: who, with whom, how long, how much - and a double-booking alarm that checks every row.
A3: > Start Here | C3: > Dashboard | E3: > Diary | G3: > Clients | I3: > Services | K3: > Sales | M3: > Staff | O3: > Profit | Q3: > Settings | S3: Date, start time, client, service, stylist, status. The finish time, the price and the clash check look after themselves.
A4: ID | B4: Date | C4: Day | D4: Start | E4: Client ID | F4: Client | G4: Service ID | H4: Service | I4: Stylist ID | J4: Stylist | K4: Minutes | L4: Price | M4: Status | N4: Booked via | O4: Deposit asked | P4: Notes | Q4: If cancelled, why | R4: Late fee charged | S4: Month | T4: Week | U4: Minutes used | V4: Finishes | W4: Hour | X4: Chair hours | Y4: Price charged | Z4: Deposit wanted | AA4: Deposit paid | AB4: Billed | AC4: Final? | AD4: Booked ahead | AE4: Booked on | AF4: Rebooked? | AG4: Clash? | AH4: Action
A5: =IF(B5="","",AppointmentPrefix&TEXT(ROW()-4,"0000")) -> 0 | C5: =IF(B5="","",TEXT(B5,"ddd")) -> 0 | F5: =IF(E5="","",IFERROR(INDEX(Clients!$B$5:$B$504,MATCH(E5,Clients!$A$5:$A$504,0)),"Walk-in")) -> 0 | H5: =IF(G5="","",IFERROR(INDEX(Services!$B$5:$B$204,MATCH(G5,Services!$A$5:$A$204,0)),"Not in Services")) -> 0 | J5: =IF(I5="","",IFERROR(INDEX(Staff!$B$5:$B$44,MATCH(I5,Staff!$A$5:$A$44,0)),"Unassigned")) -> 0 | S5: =IF(B5="","",TEXT(B5,"yyyy-mm")) -> 0 | T5: =IF(B5="","",WEEKNUM(B5,2)) -> 0 | U5: =IF(B5="","",IF(K5<>"",K5,IFERROR(INDEX(Services!$E$5:$E$204,MATCH(G5,Services!$A$5:$A$204,0))*1,0)+IFERROR(INDEX(Services!$F$5:$F$204,MATCH(G5,Services!$A$5:$A$204,0))*1,0))) -> 0 | V5: =IF(B5="","",IF(D5="","",D5+U5/1440)) -> 0 | W5: =IF(B5="","",IF(D5="","",HOUR(D5))) -> 0 | X5: =IF(B5="","",ROUND(U5/60,2)) -> 0 | Y5: =IF(B5="","",IF(L5<>"",L5,IFERROR(INDEX(Services!$G$5:$G$204,MATCH(G5,Services!$A$5:$A$204,0))*1,0))) -> 0 | Z5: =IF(B5="","",IF(O5<>"",O5,IF(Y5>=DepositThreshold,ROUND(Y5*DepositPercent,2),0))) -> 0 | AA5: =IF(B5="","",ROUND(SUMIFS(Payments!$G$5:$G$1204,Payments!$I$5:$I$1204,A5,Payments!$E$5:$E$1204,"Deposit"),2)) -> 0 | AB5: =IF(B5="","",ROUND(SUMIFS(Sales!$Y$5:$Y$1204,Sales!$C$5:$C$1204,A5),2)) -> 0 | AC5: =IF(B5="","",IF(M5="Completed","Yes",IF(M5="Cancelled","Yes",IF(M5="No show","Yes","No")))) -> 0 | AD5: =IF(B5="","",IF(AE5="","",B5-AE5)) -> 0 | AF5: =IF(B5="","",IF(M5<>"Completed","",IF(E5="","No",IF(COUNTIFS(Appointments!$E$5:$E$1204,E5,Appointments!$B$5:$B$1204,">"&B5,Appointments!$M$5:$M$1204,"<>Cancelled")>0,"Yes","No")))) -> 0 | AG5: =IF(B5="","",IF(I5="","",IF(D5="","",IF(COUNTIFS($I$5:$I$1204,I5,$B$5:$B$1204,B5,$D$5:$D$1204,"<"&V5,$V$5:$V$1204,">"&D5,$M$5:$M$1204,"<>Cancelled")>1,"Clash","")))) -> 0 | AH5: =IF(B5="","",IF(AG5="Clash","Clash - stylist double booked",IF(I5="","Assign - no stylist yet",IF(G5="","Add - no service chosen",IF(M5="No show","No show - charge the fee?",IF(M5="Cancelled","",IF(IF(M5="Completed",AB5<Y5-0.004,FALSE),"Unpaid - nothing rung up for this visit",IF(IF(B5<TodayDate,M5="Booked",FALSE),"Overdue - past date, still only Booked",IF(IF(B5=TodayDate,TRUE,FALSE),"Today",IF(IF(Z5>0,AA5<Z5-0.004,FALSE),"Due - deposit not taken",IF(IF(B5>TodayDate,B5<=TodayDate+2,FALSE),"Confirm - coming up","OK"))))))))))) -> 0
A6: =IF(B6="","",AppointmentPrefix&TEXT(ROW()-4,"0000")) -> 0 | C6: =IF(B6="","",TEXT(B6,"ddd")) -> 0 | F6: =IF(E6="","",IFERROR(INDEX(Clients!$B$5:$B$504,MATCH(E6,Clients!$A$5:$A$504,0)),"Walk-in")) -> 0 | H6: =IF(G6="","",IFERROR(INDEX(Services!$B$5:$B$204,MATCH(G6,Services!$A$5:$A$204,0)),"Not in Services")) -> 0 | J6: =IF(I6="","",IFERROR(INDEX(Staff!$B$5:$B$44,MATCH(I6,Staff!$A$5:$A$44,0)),"Unassigned")) -> 0 | S6: =IF(B6="","",TEXT(B6,"yyyy-mm")) -> 0 | T6: =IF(B6="","",WEEKNUM(B6,2)) -> 0 | U6: =IF(B6="","",IF(K6<>"",K6,IFERROR(INDEX(Services!$E$5:$E$204,MATCH(G6,Services!$A$5:$A$204,0))*1,0)+IFERROR(INDEX(Services!$F$5:$F$204,MATCH(G6,Services!$A$5:$A$204,0))*1,0))) -> 0 | V6: =IF(B6="","",IF(D6="","",D6+U6/1440)) -> 0 | W6: =IF(B6="","",IF(D6="","",HOUR(D6))) -> 0 | X6: =IF(B6="","",ROUND(U6/60,2)) -> 0 | Y6: =IF(B6="","",IF(L6<>"",L6,IFERROR(INDEX(Services!$G$5:$G$204,MATCH(G6,Services!$A$5:$A$204,0))*1,0))) -> 0 | Z6: =IF(B6="","",IF(O6<>"",O6,IF(Y6>=DepositThreshold,ROUND(Y6*DepositPercent,2),0))) -> 0 | AA6: =IF(B6="","",ROUND(SUMIFS(Payments!$G$5:$G$1204,Payments!$I$5:$I$1204,A6,Payments!$E$5:$E$1204,"Deposit"),2)) -> 0 | AB6: =IF(B6="","",ROUND(SUMIFS(Sales!$Y$5:$Y$1204,Sales!$C$5:$C$1204,A6),2)) -> 0 | AC6: =IF(B6="","",IF(M6="Completed","Yes",IF(M6="Cancelled","Yes",IF(M6="No show","Yes","No")))) -> 0 | AD6: =IF(B6="","",IF(AE6="","",B6-AE6)) -> 0 | AF6: =IF(B6="","",IF(M6<>"Completed","",IF(E6="","No",IF(COUNTIFS(Appointments!$E$5:$E$1204,E6,Appointments!$B$5:$B$1204,">"&B6,Appointments!$M$5:$M$1204,"<>Cancelled")>0,"Yes","No")))) -> 0 | AG6: =IF(B6="","",IF(I6="","",IF(D6="","",IF(COUNTIFS($I$5:$I$1204,I6,$B$5:$B$1204,B6,$D$5:$D$1204,"<"&V6,$V$5:$V$1204,">"&D6,$M$5:$M$1204,"<>Cancelled")>1,"Clash","")))) -> 0 | AH6: =IF(B6="","",IF(AG6="Clash","Clash - stylist double booked",IF(I6="","Assign - no stylist yet",IF(G6="","Add - no service chosen",IF(M6="No show","No show - charge the fee?",IF(M6="Cancelled","",IF(IF(M6="Completed",AB6<Y6-0.004,FALSE),"Unpaid - nothing rung up for this visit",IF(IF(B6<TodayDate,M6="Booked",FALSE),"Overdue - past date, still only Booked",IF(IF(B6=TodayDate,TRUE,FALSE),"Today",IF(IF(Z6>0,AA6<Z6-0.004,FALSE),"Due - deposit not taken",IF(IF(B6>TodayDate,B6<=TodayDate+2,FALSE),"Confirm - coming up","OK"))))))))))) -> 0
A7: =IF(B7="","",AppointmentPrefix&TEXT(ROW()-4,"0000")) -> 0 | C7: =IF(B7="","",TEXT(B7,"ddd")) -> 0 | F7: =IF(E7="","",IFERROR(INDEX(Clients!$B$5:$B$504,MATCH(E7,Clients!$A$5:$A$504,0)),"Walk-in")) -> 0 | H7: =IF(G7="","",IFERROR(INDEX(Services!$B$5:$B$204,MATCH(G7,Services!$A$5:$A$204,0)),"Not in Services")) -> 0 | J7: =IF(I7="","",IFERROR(INDEX(Staff!$B$5:$B$44,MATCH(I7,Staff!$A$5:$A$44,0)),"Unassigned")) -> 0 | S7: =IF(B7="","",TEXT(B7,"yyyy-mm")) -> 0 | T7: =IF(B7="","",WEEKNUM(B7,2)) -> 0 | U7: =IF(B7="","",IF(K7<>"",K7,IFERROR(INDEX(Services!$E$5:$E$204,MATCH(G7,Services!$A$5:$A$204,0))*1,0)+IFERROR(INDEX(Services!$F$5:$F$204,MATCH(G7,Services!$A$5:$A$204,0))*1,0))) -> 0 | V7: =IF(B7="","",IF(D7="","",D7+U7/1440)) -> 0 | W7: =IF(B7="","",IF(D7="","",HOUR(D7))) -> 0 | X7: =IF(B7="","",ROUND(U7/60,2)) -> 0 | Y7: =IF(B7="","",IF(L7<>"",L7,IFERROR(INDEX(Services!$G$5:$G$204,MATCH(G7,Services!$A$5:$A$204,0))*1,0))) -> 0 | Z7: =IF(B7="","",IF(O7<>"",O7,IF(Y7>=DepositThreshold,ROUND(Y7*DepositPercent,2),0))) -> 0 | AA7: =IF(B7="","",ROUND(SUMIFS(Payments!$G$5:$G$1204,Payments!$I$5:$I$1204,A7,Payments!$E$5:$E$1204,"Deposit"),2)) -> 0 | AB7: =IF(B7="","",ROUND(SUMIFS(Sales!$Y$5:$Y$1204,Sales!$C$5:$C$1204,A7),2)) -> 0 | AC7: =IF(B7="","",IF(M7="Completed","Yes",IF(M7="Cancelled","Yes",IF(M7="No show","Yes","No")))) -> 0 | AD7: =IF(B7="","",IF(AE7="","",B7-AE7)) -> 0 | AF7: =IF(B7="","",IF(M7<>"Completed","",IF(E7="","No",IF(COUNTIFS(Appointments!$E$5:$E$1204,E7,Appointments!$B$5:$B$1204,">"&B7,Appointments!$M$5:$M$1204,"<>Cancelled")>0,"Yes","No")))) -> 0 | AG7: =IF(B7="","",IF(I7="","",IF(D7="","",IF(COUNTIFS($I$5:$I$1204,I7,$B$5:$B$1204,B7,$D$5:$D$1204,"<"&V7,$V$5:$V$1204,">"&D7,$M$5:$M$1204,"<>Cancelled")>1,"Clash","")))) -> 0 | AH7: =IF(B7="","",IF(AG7="Clash","Clash - stylist double booked",IF(I7="","Assign - no stylist yet",IF(G7="","Add - no service chosen",IF(M7="No show","No show - charge the fee?",IF(M7="Cancelled","",IF(IF(M7="Completed",AB7<Y7-0.004,FALSE),"Unpaid - nothing rung up for this visit",IF(IF(B7<TodayDate,M7="Booked",FALSE),"Overdue - past date, still only Booked",IF(IF(B7=TodayDate,TRUE,FALSE),"Today",IF(IF(Z7>0,AA7<Z7-0.004,FALSE),"Due - deposit not taken",IF(IF(B7>TodayDate,B7<=TodayDate+2,FALSE),"Confirm - coming up","OK"))))))))))) -> 0
A8: =IF(B8="","",AppointmentPrefix&TEXT(ROW()-4,"0000")) -> 0 | C8: =IF(B8="","",TEXT(B8,"ddd")) -> 0 | F8: =IF(E8="","",IFERROR(INDEX(Clients!$B$5:$B$504,MATCH(E8,Clients!$A$5:$A$504,0)),"Walk-in")) -> 0 | H8: =IF(G8="","",IFERROR(INDEX(Services!$B$5:$B$204,MATCH(G8,Services!$A$5:$A$204,0)),"Not in Services")) -> 0 | J8: =IF(I8="","",IFERROR(INDEX(Staff!$B$5:$B$44,MATCH(I8,Staff!$A$5:$A$44,0)),"Unassigned")) -> 0 | S8: =IF(B8="","",TEXT(B8,"yyyy-mm")) -> 0 | T8: =IF(B8="","",WEEKNUM(B8,2)) -> 0 | U8: =IF(B8="","",IF(K8<>"",K8,IFERROR(INDEX(Services!$E$5:$E$204,MATCH(G8,Services!$A$5:$A$204,0))*1,0)+IFERROR(INDEX(Services!$F$5:$F$204,MATCH(G8,Services!$A$5:$A$204,0))*1,0))) -> 0 | V8: =IF(B8="","",IF(D8="","",D8+U8/1440)) -> 0 | W8: =IF(B8="","",IF(D8="","",HOUR(D8))) -> 0 | X8: =IF(B8="","",ROUND(U8/60,2)) -> 0 | Y8: =IF(B8="","",IF(L8<>"",L8,IFERROR(INDEX(Services!$G$5:$G$204,MATCH(G8,Services!$A$5:$A$204,0))*1,0))) -> 0 | Z8: =IF(B8="","",IF(O8<>"",O8,IF(Y8>=DepositThreshold,ROUND(Y8*DepositPercent,2),0))) -> 0 | AA8: =IF(B8="","",ROUND(SUMIFS(Payments!$G$5:$G$1204,Payments!$I$5:$I$1204,A8,Payments!$E$5:$E$1204,"Deposit"),2)) -> 0 | AB8: =IF(B8="","",ROUND(SUMIFS(Sales!$Y$5:$Y$1204,Sales!$C$5:$C$1204,A8),2)) -> 0 | AC8: =IF(B8="","",IF(M8="Completed","Yes",IF(M8="Cancelled","Yes",IF(M8="No show","Yes","No")))) -> 0 | AD8: =IF(B8="","",IF(AE8="","",B8-AE8)) -> 0 | AF8: =IF(B8="","",IF(M8<>"Completed","",IF(E8="","No",IF(COUNTIFS(Appointments!$E$5:$E$1204,E8,Appointments!$B$5:$B$1204,">"&B8,Appointments!$M$5:$M$1204,"<>Cancelled")>0,"Yes","No")))) -> 0 | AG8: =IF(B8="","",IF(I8="","",IF(D8="","",IF(COUNTIFS($I$5:$I$1204,I8,$B$5:$B$1204,B8,$D$5:$D$1204,"<"&V8,$V$5:$V$1204,">"&D8,$M$5:$M$1204,"<>Cancelled")>1,"Clash","")))) -> 0 | AH8: =IF(B8="","",IF(AG8="Clash","Clash - stylist double booked",IF(I8="","Assign - no stylist yet",IF(G8="","Add - no service chosen",IF(M8="No show","No show - charge the fee?",IF(M8="Cancelled","",IF(IF(M8="Completed",AB8<Y8-0.004,FALSE),"Unpaid - nothing rung up for this visit",IF(IF(B8<TodayDate,M8="Booked",FALSE),"Overdue - past date, still only Booked",IF(IF(B8=TodayDate,TRUE,FALSE),"Today",IF(IF(Z8>0,AA8<Z8-0.004,FALSE),"Due - deposit not taken",IF(IF(B8>TodayDate,B8<=TodayDate+2,FALSE),"Confirm - coming up","OK"))))))))))) -> 0
A9: =IF(B9="","",AppointmentPrefix&TEXT(ROW()-4,"0000")) -> 0 | C9: =IF(B9="","",TEXT(B9,"ddd")) -> 0 | F9: =IF(E9="","",IFERROR(INDEX(Clients!$B$5:$B$504,MATCH(E9,Clients!$A$5:$A$504,0)),"Walk-in")) -> 0 | H9: =IF(G9="","",IFERROR(INDEX(Services!$B$5:$B$204,MATCH(G9,Services!$A$5:$A$204,0)),"Not in Services")) -> 0 | J9: =IF(I9="","",IFERROR(INDEX(Staff!$B$5:$B$44,MATCH(I9,Staff!$A$5:$A$44,0)),"Unassigned")) -> 0 | S9: =IF(B9="","",TEXT(B9,"yyyy-mm")) -> 0 | T9: =IF(B9="","",WEEKNUM(B9,2)) -> 0 | U9: =IF(B9="","",IF(K9<>"",K9,IFERROR(INDEX(Services!$E$5:$E$204,MATCH(G9,Services!$A$5:$A$204,0))*1,0)+IFERROR(INDEX(Services!$F$5:$F$204,MATCH(G9,Services!$A$5:$A$204,0))*1,0))) -> 0 | V9: =IF(B9="","",IF(D9="","",D9+U9/1440)) -> 0 | W9: =IF(B9="","",IF(D9="","",HOUR(D9))) -> 0 | X9: =IF(B9="","",ROUND(U9/60,2)) -> 0 | Y9: =IF(B9="","",IF(L9<>"",L9,IFERROR(INDEX(Services!$G$5:$G$204,MATCH(G9,Services!$A$5:$A$204,0))*1,0))) -> 0 | Z9: =IF(B9="","",IF(O9<>"",O9,IF(Y9>=DepositThreshold,ROUND(Y9*DepositPercent,2),0))) -> 0 | AA9: =IF(B9="","",ROUND(SUMIFS(Payments!$G$5:$G$1204,Payments!$I$5:$I$1204,A9,Payments!$E$5:$E$1204,"Deposit"),2)) -> 0 | AB9: =IF(B9="","",ROUND(SUMIFS(Sales!$Y$5:$Y$1204,Sales!$C$5:$C$1204,A9),2)) -> 0 | AC9: =IF(B9="","",IF(M9="Completed","Yes",IF(M9="Cancelled","Yes",IF(M9="No show","Yes","No")))) -> 0 | AD9: =IF(B9="","",IF(AE9="","",B9-AE9)) -> 0 | AF9: =IF(B9="","",IF(M9<>"Completed","",IF(E9="","No",IF(COUNTIFS(Appointments!$E$5:$E$1204,E9,Appointments!$B$5:$B$1204,">"&B9,Appointments!$M$5:$M$1204,"<>Cancelled")>0,"Yes","No")))) -> 0 | AG9: =IF(B9="","",IF(I9="","",IF(D9="","",IF(COUNTIFS($I$5:$I$1204,I9,$B$5:$B$1204,B9,$D$5:$D$1204,"<"&V9,$V$5:$V$1204,">"&D9,$M$5:$M$1204,"<>Cancelled")>1,"Clash","")))) -> 0 | AH9: =IF(B9="","",IF(AG9="Clash","Clash - stylist double booked",IF(I9="","Assign - no stylist yet",IF(G9="","Add - no service chosen",IF(M9="No show","No show - charge the fee?",IF(M9="Cancelled","",IF(IF(M9="Completed",AB9<Y9-0.004,FALSE),"Unpaid - nothing rung up for this visit",IF(IF(B9<TodayDate,M9="Booked",FALSE),"Overdue - past date, still only Booked",IF(IF(B9=TodayDate,TRUE,FALSE),"Today",IF(IF(Z9>0,AA9<Z9-0.004,FALSE),"Due - deposit not taken",IF(IF(B9>TodayDate,B9<=TodayDate+2,FALSE),"Confirm - coming up","OK"))))))))))) -> 0
A10: =IF(B10="","",AppointmentPrefix&TEXT(ROW()-4,"0000")) -> 0 | C10: =IF(B10="","",TEXT(B10,"ddd")) -> 0 | F10: =IF(E10="","",IFERROR(INDEX(Clients!$B$5:$B$504,MATCH(E10,Clients!$A$5:$A$504,0)),"Walk-in")) -> 0 | H10: =IF(G10="","",IFERROR(INDEX(Services!$B$5:$B$204,MATCH(G10,Services!$A$5:$A$204,0)),"Not in Services")) -> 0 | J10: =IF(I10="","",IFERROR(INDEX(Staff!$B$5:$B$44,MATCH(I10,Staff!$A$5:$A$44,0)),"Unassigned")) -> 0 | S10: =IF(B10="","",TEXT(B10,"yyyy-mm")) -> 0 | T10: =IF(B10="","",WEEKNUM(B10,2)) -> 0 | U10: =IF(B10="","",IF(K10<>"",K10,IFERROR(INDEX(Services!$E$5:$E$204,MATCH(G10,Services!$A$5:$A$204,0))*1,0)+IFERROR(INDEX(Services!$F$5:$F$204,MATCH(G10,Services!$A$5:$A$204,0))*1,0))) -> 0 | V10: =IF(B10="","",IF(D10="","",D10+U10/1440)) -> 0 | W10: =IF(B10="","",IF(D10="","",HOUR(D10))) -> 0 | X10: =IF(B10="","",ROUND(U10/60,2)) -> 0 | Y10: =IF(B10="","",IF(L10<>"",L10,IFERROR(INDEX(Services!$G$5:$G$204,MATCH(G10,Services!$A$5:$A$204,0))*1,0))) -> 0 | Z10: =IF(B10="","",IF(O10<>"",O10,IF(Y10>=DepositThreshold,ROUND(Y10*DepositPercent,2),0))) -> 0 | AA10: =IF(B10="","",ROUND(SUMIFS(Payments!$G$5:$G$1204,Payments!$I$5:$I$1204,A10,Payments!$E$5:$E$1204,"Deposit"),2)) -> 0 | AB10: =IF(B10="","",ROUND(SUMIFS(Sales!$Y$5:$Y$1204,Sales!$C$5:$C$1204,A10),2)) -> 0 | AC10: =IF(B10="","",IF(M10="Completed","Yes",IF(M10="Cancelled","Yes",IF(M10="No show","Yes","No")))) -> 0 | AD10: =IF(B10="","",IF(AE10="","",B10-AE10)) -> 0 | AF10: =IF(B10="","",IF(M10<>"Completed","",IF(E10="","No",IF(COUNTIFS(Appointments!$E$5:$E$1204,E10,Appointments!$B$5:$B$1204,">"&B10,Appointments!$M$5:$M$1204,"<>Cancelled")>0,"Yes","No")))) -> 0 | AG10: =IF(B10="","",IF(I10="","",IF(D10="","",IF(COUNTIFS($I$5:$I$1204,I10,$B$5:$B$1204,B10,$D$5:$D$1204,"<"&V10,$V$5:$V$1204,">"&D10,$M$5:$M$1204,"<>Cancelled")>1,"Clash","")))) -> 0 | AH10: =IF(B10="","",IF(AG10="Clash","Clash - stylist double booked",IF(I10="","Assign - no stylist yet",IF(G10="","Add - no service chosen",IF(M10="No show","No show - charge the fee?",IF(M10="Cancelled","",IF(IF(M10="Completed",AB10<Y10-0.004,FALSE),"Unpaid - nothing rung up for this visit",IF(IF(B10<TodayDate,M10="Booked",FALSE),"Overdue - past date, still only Booked",IF(IF(B10=TodayDate,TRUE,FALSE),"Today",IF(IF(Z10>0,AA10<Z10-0.004,FALSE),"Due - deposit not taken",IF(IF(B10>TodayDate,B10<=TodayDate+2,FALSE),"Confirm - coming up","OK"))))))))))) -> 0
A11: =IF(B11="","",AppointmentPrefix&TEXT(ROW()-4,"0000")) -> 0 | C11: =IF(B11="","",TEXT(B11,"ddd")) -> 0 | F11: =IF(E11="","",IFERROR(INDEX(Clients!$B$5:$B$504,MATCH(E11,Clients!$A$5:$A$504,0)),"Walk-in")) -> 0 | H11: =IF(G11="","",IFERROR(INDEX(Services!$B$5:$B$204,MATCH(G11,Services!$A$5:$A$204,0)),"Not in Services")) -> 0 | J11: =IF(I11="","",IFERROR(INDEX(Staff!$B$5:$B$44,MATCH(I11,Staff!$A$5:$A$44,0)),"Unassigned")) -> 0 | S11: =IF(B11="","",TEXT(B11,"yyyy-mm")) -> 0 | T11: =IF(B11="","",WEEKNUM(B11,2)) -> 0 | U11: =IF(B11="","",IF(K11<>"",K11,IFERROR(INDEX(Services!$E$5:$E$204,MATCH(G11,Services!$A$5:$A$204,0))*1,0)+IFERROR(INDEX(Services!$F$5:$F$204,MATCH(G11,Services!$A$5:$A$204,0))*1,0))) -> 0 | V11: =IF(B11="","",IF(D11="","",D11+U11/1440)) -> 0 | W11: =IF(B11="","",IF(D11="","",HOUR(D11))) -> 0 | X11: =IF(B11="","",ROUND(U11/60,2)) -> 0 | Y11: =IF(B11="","",IF(L11<>"",L11,IFERROR(INDEX(Services!$G$5:$G$204,MATCH(G11,Services!$A$5:$A$204,0))*1,0))) -> 0 | Z11: =IF(B11="","",IF(O11<>"",O11,IF(Y11>=DepositThreshold,ROUND(Y11*DepositPercent,2),0))) -> 0 | AA11: =IF(B11="","",ROUND(SUMIFS(Payments!$G$5:$G$1204,Payments!$I$5:$I$1204,A11,Payments!$E$5:$E$1204,"Deposit"),2)) -> 0 | AB11: =IF(B11="","",ROUND(SUMIFS(Sales!$Y$5:$Y$1204,Sales!$C$5:$C$1204,A11),2)) -> 0 | AC11: =IF(B11="","",IF(M11="Completed","Yes",IF(M11="Cancelled","Yes",IF(M11="No show","Yes","No")))) -> 0 | AD11: =IF(B11="","",IF(AE11="","",B11-AE11)) -> 0 | AF11: =IF(B11="","",IF(M11<>"Completed","",IF(E11="","No",IF(COUNTIFS(Appointments!$E$5:$E$1204,E11,Appointments!$B$5:$B$1204,">"&B11,Appointments!$M$5:$M$1204,"<>Cancelled")>0,"Yes","No")))) -> 0 | AG11: =IF(B11="","",IF(I11="","",IF(D11="","",IF(COUNTIFS($I$5:$I$1204,I11,$B$5:$B$1204,B11,$D$5:$D$1204,"<"&V11,$V$5:$V$1204,">"&D11,$M$5:$M$1204,"<>Cancelled")>1,"Clash","")))) -> 0 | AH11: =IF(B11="","",IF(AG11="Clash","Clash - stylist double booked",IF(I11="","Assign - no stylist yet",IF(G11="","Add - no service chosen",IF(M11="No show","No show - charge the fee?",IF(M11="Cancelled","",IF(IF(M11="Completed",AB11<Y11-0.004,FALSE),"Unpaid - nothing rung up for this visit",IF(IF(B11<TodayDate,M11="Booked",FALSE),"Overdue - past date, still only Booked",IF(IF(B11=TodayDate,TRUE,FALSE),"Today",IF(IF(Z11>0,AA11<Z11-0.004,FALSE),"Due - deposit not taken",IF(IF(B11>TodayDate,B11<=TodayDate+2,FALSE),"Confirm - coming up","OK"))))))))))) -> 0
A12: =IF(B12="","",AppointmentPrefix&TEXT(ROW()-4,"0000")) -> 0 | C12: =IF(B12="","",TEXT(B12,"ddd")) -> 0 | F12: =IF(E12="","",IFERROR(INDEX(Clients!$B$5:$B$504,MATCH(E12,Clients!$A$5:$A$504,0)),"Walk-in")) -> 0 | H12: =IF(G12="","",IFERROR(INDEX(Services!$B$5:$B$204,MATCH(G12,Services!$A$5:$A$204,0)),"Not in Services")) -> 0 | J12: =IF(I12="","",IFERROR(INDEX(Staff!$B$5:$B$44,MATCH(I12,Staff!$A$5:$A$44,0)),"Unassigned")) -> 0 | S12: =IF(B12="","",TEXT(B12,"yyyy-mm")) -> 0 | T12: =IF(B12="","",WEEKNUM(B12,2)) -> 0 | U12: =IF(B12="","",IF(K12<>"",K12,IFERROR(INDEX(Services!$E$5:$E$204,MATCH(G12,Services!$A$5:$A$204,0))*1,0)+IFERROR(INDEX(Services!$F$5:$F$204,MATCH(G12,Services!$A$5:$A$204,0))*1,0))) -> 0 | V12: =IF(B12="","",IF(D12="","",D12+U12/1440)) -> 0 | W12: =IF(B12="","",IF(D12="","",HOUR(D12))) -> 0 | X12: =IF(B12="","",ROUND(U12/60,2)) -> 0 | Y12: =IF(B12="","",IF(L12<>"",L12,IFERROR(INDEX(Services!$G$5:$G$204,MATCH(G12,Services!$A$5:$A$204,0))*1,0))) -> 0 | Z12: =IF(B12="","",IF(O12<>"",O12,IF(Y12>=DepositThreshold,ROUND(Y12*DepositPercent,2),0))) -> 0 | AA12: =IF(B12="","",ROUND(SUMIFS(Payments!$G$5:$G$1204,Payments!$I$5:$I$1204,A12,Payments!$E$5:$E$1204,"Deposit"),2)) -> 0 | AB12: =IF(B12="","",ROUND(SUMIFS(Sales!$Y$5:$Y$1204,Sales!$C$5:$C$1204,A12),2)) -> 0 | AC12: =IF(B12="","",IF(M12="Completed","Yes",IF(M12="Cancelled","Yes",IF(M12="No show","Yes","No")))) -> 0 | AD12: =IF(B12="","",IF(AE12="","",B12-AE12)) -> 0 | AF12: =IF(B12="","",IF(M12<>"Completed","",IF(E12="","No",IF(COUNTIFS(Appointments!$E$5:$E$1204,E12,Appointments!$B$5:$B$1204,">"&B12,Appointments!$M$5:$M$1204,"<>Cancelled")>0,"Yes","No")))) -> 0 | AG12: =IF(B12="","",IF(I12="","",IF(D12="","",IF(COUNTIFS($I$5:$I$1204,I12,$B$5:$B$1204,B12,$D$5:$D$1204,"<"&V12,$V$5:$V$1204,">"&D12,$M$5:$M$1204,"<>Cancelled")>1,"Clash","")))) -> 0 | AH12: =IF(B12="","",IF(AG12="Clash","Clash - stylist double booked",IF(I12="","Assign - no stylist yet",IF(G12="","Add - no service chosen",IF(M12="No show","No show - charge the fee?",IF(M12="Cancelled","",IF(IF(M12="Completed",AB12<Y12-0.004,FALSE),"Unpaid - nothing rung up for this visit",IF(IF(B12<TodayDate,M12="Booked",FALSE),"Overdue - past date, still only Booked",IF(IF(B12=TodayDate,TRUE,FALSE),"Today",IF(IF(Z12>0,AA12<Z12-0.004,FALSE),"Due - deposit not taken",IF(IF(B12>TodayDate,B12<=TodayDate+2,FALSE),"Confirm - coming up","OK"))))))))))) -> 0
A13: =IF(B13="","",AppointmentPrefix&TEXT(ROW()-4,"0000")) -> 0 | C13: =IF(B13="","",TEXT(B13,"ddd")) -> 0 | F13: =IF(E13="","",IFERROR(INDEX(Clients!$B$5:$B$504,MATCH(E13,Clients!$A$5:$A$504,0)),"Walk-in")) -> 0 | H13: =IF(G13="","",IFERROR(INDEX(Services!$B$5:$B$204,MATCH(G13,Services!$A$5:$A$204,0)),"Not in Services")) -> 0 | J13: =IF(I13="","",IFERROR(INDEX(Staff!$B$5:$B$44,MATCH(I13,Staff!$A$5:$A$44,0)),"Unassigned")) -> 0 | S13: =IF(B13="","",TEXT(B13,"yyyy-mm")) -> 0 | T13: =IF(B13="","",WEEKNUM(B13,2)) -> 0 | U13: =IF(B13="","",IF(K13<>"",K13,IFERROR(INDEX(Services!$E$5:$E$204,MATCH(G13,Services!$A$5:$A$204,0))*1,0)+IFERROR(INDEX(Services!$F$5:$F$204,MATCH(G13,Services!$A$5:$A$204,0))*1,0))) -> 0 | V13: =IF(B13="","",IF(D13="","",D13+U13/1440)) -> 0 | W13: =IF(B13="","",IF(D13="","",HOUR(D13))) -> 0 | X13: =IF(B13="","",ROUND(U13/60,2)) -> 0 | Y13: =IF(B13="","",IF(L13<>"",L13,IFERROR(INDEX(Services!$G$5:$G$204,MATCH(G13,Services!$A$5:$A$204,0))*1,0))) -> 0 | Z13: =IF(B13="","",IF(O13<>"",O13,IF(Y13>=DepositThreshold,ROUND(Y13*DepositPercent,2),0))) -> 0 | AA13: =IF(B13="","",ROUND(SUMIFS(Payments!$G$5:$G$1204,Payments!$I$5:$I$1204,A13,Payments!$E$5:$E$1204,"Deposit"),2)) -> 0 | AB13: =IF(B13="","",ROUND(SUMIFS(Sales!$Y$5:$Y$1204,Sales!$C$5:$C$1204,A13),2)) -> 0 | AC13: =IF(B13="","",IF(M13="Completed","Yes",IF(M13="Cancelled","Yes",IF(M13="No show","Yes","No")))) -> 0 | AD13: =IF(B13="","",IF(AE13="","",B13-AE13)) -> 0 | AF13: =IF(B13="","",IF(M13<>"Completed","",IF(E13="","No",IF(COUNTIFS(Appointments!$E$5:$E$1204,E13,Appointments!$B$5:$B$1204,">"&B13,Appointments!$M$5:$M$1204,"<>Cancelled")>0,"Yes","No")))) -> 0 | AG13: =IF(B13="","",IF(I13="","",IF(D13="","",IF(COUNTIFS($I$5:$I$1204,I13,$B$5:$B$1204,B13,$D$5:$D$1204,"<"&V13,$V$5:$V$1204,">"&D13,$M$5:$M$1204,"<>Cancelled")>1,"Clash","")))) -> 0 | AH13: =IF(B13="","",IF(AG13="Clash","Clash - stylist double booked",IF(I13="","Assign - no stylist yet",IF(G13="","Add - no service chosen",IF(M13="No show","No show - charge the fee?",IF(M13="Cancelled","",IF(IF(M13="Completed",AB13<Y13-0.004,FALSE),"Unpaid - nothing rung up for this visit",IF(IF(B13<TodayDate,M13="Booked",FALSE),"Overdue - past date, still only Booked",IF(IF(B13=TodayDate,TRUE,FALSE),"Today",IF(IF(Z13>0,AA13<Z13-0.004,FALSE),"Due - deposit not taken",IF(IF(B13>TodayDate,B13<=TodayDate+2,FALSE),"Confirm - coming up","OK"))))))))))) -> 0
A14: =IF(B14="","",AppointmentPrefix&TEXT(ROW()-4,"0000")) -> 0 | C14: =IF(B14="","",TEXT(B14,"ddd")) -> 0 | F14: =IF(E14="","",IFERROR(INDEX(Clients!$B$5:$B$504,MATCH(E14,Clients!$A$5:$A$504,0)),"Walk-in")) -> 0 | H14: =IF(G14="","",IFERROR(INDEX(Services!$B$5:$B$204,MATCH(G14,Services!$A$5:$A$204,0)),"Not in Services")) -> 0 | J14: =IF(I14="","",IFERROR(INDEX(Staff!$B$5:$B$44,MATCH(I14,Staff!$A$5:$A$44,0)),"Unassigned")) -> 0 | S14: =IF(B14="","",TEXT(B14,"yyyy-mm")) -> 0 | T14: =IF(B14="","",WEEKNUM(B14,2)) -> 0 | U14: =IF(B14="","",IF(K14<>"",K14,IFERROR(INDEX(Services!$E$5:$E$204,MATCH(G14,Services!$A$5:$A$204,0))*1,0)+IFERROR(INDEX(Services!$F$5:$F$204,MATCH(G14,Services!$A$5:$A$204,0))*1,0))) -> 0 | V14: =IF(B14="","",IF(D14="","",D14+U14/1440)) -> 0 | W14: =IF(B14="","",IF(D14="","",HOUR(D14))) -> 0 | X14: =IF(B14="","",ROUND(U14/60,2)) -> 0 | Y14: =IF(B14="","",IF(L14<>"",L14,IFERROR(INDEX(Services!$G$5:$G$204,MATCH(G14,Services!$A$5:$A$204,0))*1,0))) -> 0 | Z14: =IF(B14="","",IF(O14<>"",O14,IF(Y14>=DepositThreshold,ROUND(Y14*DepositPercent,2),0))) -> 0 | AA14: =IF(B14="","",ROUND(SUMIFS(Payments!$G$5:$G$1204,Payments!$I$5:$I$1204,A14,Payments!$E$5:$E$1204,"Deposit"),2)) -> 0 | AB14: =IF(B14="","",ROUND(SUMIFS(Sales!$Y$5:$Y$1204,Sales!$C$5:$C$1204,A14),2)) -> 0 | AC14: =IF(B14="","",IF(M14="Completed","Yes",IF(M14="Cancelled","Yes",IF(M14="No show","Yes","No")))) -> 0 | AD14: =IF(B14="","",IF(AE14="","",B14-AE14)) -> 0 | AF14: =IF(B14="","",IF(M14<>"Completed","",IF(E14="","No",IF(COUNTIFS(Appointments!$E$5:$E$1204,E14,Appointments!$B$5:$B$1204,">"&B14,Appointments!$M$5:$M$1204,"<>Cancelled")>0,"Yes","No")))) -> 0 | AG14: =IF(B14="","",IF(I14="","",IF(D14="","",IF(COUNTIFS($I$5:$I$1204,I14,$B$5:$B$1204,B14,$D$5:$D$1204,"<"&V14,$V$5:$V$1204,">"&D14,$M$5:$M$1204,"<>Cancelled")>1,"Clash","")))) -> 0 | AH14: =IF(B14="","",IF(AG14="Clash","Clash - stylist double booked",IF(I14="","Assign - no stylist yet",IF(G14="","Add - no service chosen",IF(M14="No show","No show - charge the fee?",IF(M14="Cancelled","",IF(IF(M14="Completed",AB14<Y14-0.004,FALSE),"Unpaid - nothing rung up for this visit",IF(IF(B14<TodayDate,M14="Booked",FALSE),"Overdue - past date, still only Booked",IF(IF(B14=TodayDate,TRUE,FALSE),"Today",IF(IF(Z14>0,AA14<Z14-0.004,FALSE),"Due - deposit not taken",IF(IF(B14>TodayDate,B14<=TodayDate+2,FALSE),"Confirm - coming up","OK"))))))))))) -> 0
A15: =IF(B15="","",AppointmentPrefix&TEXT(ROW()-4,"0000")) -> 0 | C15: =IF(B15="","",TEXT(B15,"ddd")) -> 0 | F15: =IF(E15="","",IFERROR(INDEX(Clients!$B$5:$B$504,MATCH(E15,Clients!$A$5:$A$504,0)),"Walk-in")) -> 0 | H15: =IF(G15="","",IFERROR(INDEX(Services!$B$5:$B$204,MATCH(G15,Services!$A$5:$A$204,0)),"Not in Services")) -> 0 | J15: =IF(I15="","",IFERROR(INDEX(Staff!$B$5:$B$44,MATCH(I15,Staff!$A$5:$A$44,0)),"Unassigned")) -> 0 | S15: =IF(B15="","",TEXT(B15,"yyyy-mm")) -> 0 | T15: =IF(B15="","",WEEKNUM(B15,2)) -> 0 | U15: =IF(B15="","",IF(K15<>"",K15,IFERROR(INDEX(Services!$E$5:$E$204,MATCH(G15,Services!$A$5:$A$204,0))*1,0)+IFERROR(INDEX(Services!$F$5:$F$204,MATCH(G15,Services!$A$5:$A$204,0))*1,0))) -> 0 | V15: =IF(B15="","",IF(D15="","",D15+U15/1440)) -> 0 | W15: =IF(B15="","",IF(D15="","",HOUR(D15))) -> 0 | X15: =IF(B15="","",ROUND(U15/60,2)) -> 0 | Y15: =IF(B15="","",IF(L15<>"",L15,IFERROR(INDEX(Services!$G$5:$G$204,MATCH(G15,Services!$A$5:$A$204,0))*1,0))) -> 0 | Z15: =IF(B15="","",IF(O15<>"",O15,IF(Y15>=DepositThreshold,ROUND(Y15*DepositPercent,2),0))) -> 0 | AA15: =IF(B15="","",ROUND(SUMIFS(Payments!$G$5:$G$1204,Payments!$I$5:$I$1204,A15,Payments!$E$5:$E$1204,"Deposit"),2)) -> 0 | AB15: =IF(B15="","",ROUND(SUMIFS(Sales!$Y$5:$Y$1204,Sales!$C$5:$C$1204,A15),2)) -> 0 | AC15: =IF(B15="","",IF(M15="Completed","Yes",IF(M15="Cancelled","Yes",IF(M15="No show","Yes","No")))) -> 0 | AD15: =IF(B15="","",IF(AE15="","",B15-AE15)) -> 0 | AF15: =IF(B15="","",IF(M15<>"Completed","",IF(E15="","No",IF(COUNTIFS(Appointments!$E$5:$E$1204,E15,Appointments!$B$5:$B$1204,">"&B15,Appointments!$M$5:$M$1204,"<>Cancelled")>0,"Yes","No")))) -> 0 | AG15: =IF(B15="","",IF(I15="","",IF(D15="","",IF(COUNTIFS($I$5:$I$1204,I15,$B$5:$B$1204,B15,$D$5:$D$1204,"<"&V15,$V$5:$V$1204,">"&D15,$M$5:$M$1204,"<>Cancelled")>1,"Clash","")))) -> 0 | AH15: =IF(B15="","",IF(AG15="Clash","Clash - stylist double booked",IF(I15="","Assign - no stylist yet",IF(G15="","Add - no service chosen",IF(M15="No show","No show - charge the fee?",IF(M15="Cancelled","",IF(IF(M15="Completed",AB15<Y15-0.004,FALSE),"Unpaid - nothing rung up for this visit",IF(IF(B15<TodayDate,M15="Booked",FALSE),"Overdue - past date, still only Booked",IF(IF(B15=TodayDate,TRUE,FALSE),"Today",IF(IF(Z15>0,AA15<Z15-0.004,FALSE),"Due - deposit not taken",IF(IF(B15>TodayDate,B15<=TodayDate+2,FALSE),"Confirm - coming up","OK"))))))))))) -> 0
A16: =IF(B16="","",AppointmentPrefix&TEXT(ROW()-4,"0000")) -> 0 | C16: =IF(B16="","",TEXT(B16,"ddd")) -> 0 | F16: =IF(E16="","",IFERROR(INDEX(Clients!$B$5:$B$504,MATCH(E16,Clients!$A$5:$A$504,0)),"Walk-in")) -> 0 | H16: =IF(G16="","",IFERROR(INDEX(Services!$B$5:$B$204,MATCH(G16,Services!$A$5:$A$204,0)),"Not in Services")) -> 0 | J16: =IF(I16="","",IFERROR(INDEX(Staff!$B$5:$B$44,MATCH(I16,Staff!$A$5:$A$44,0)),"Unassigned")) -> 0 | S16: =IF(B16="","",TEXT(B16,"yyyy-mm")) -> 0 | T16: =IF(B16="","",WEEKNUM(B16,2)) -> 0 | U16: =IF(B16="","",IF(K16<>"",K16,IFERROR(INDEX(Services!$E$5:$E$204,MATCH(G16,Services!$A$5:$A$204,0))*1,0)+IFERROR(INDEX(Services!$F$5:$F$204,MATCH(G16,Services!$A$5:$A$204,0))*1,0))) -> 0 | V16: =IF(B16="","",IF(D16="","",D16+U16/1440)) -> 0 | W16: =IF(B16="","",IF(D16="","",HOUR(D16))) -> 0 | X16: =IF(B16="","",ROUND(U16/60,2)) -> 0 | Y16: =IF(B16="","",IF(L16<>"",L16,IFERROR(INDEX(Services!$G$5:$G$204,MATCH(G16,Services!$A$5:$A$204,0))*1,0))) -> 0 | Z16: =IF(B16="","",IF(O16<>"",O16,IF(Y16>=DepositThreshold,ROUND(Y16*DepositPercent,2),0))) -> 0 | AA16: =IF(B16="","",ROUND(SUMIFS(Payments!$G$5:$G$1204,Payments!$I$5:$I$1204,A16,Payments!$E$5:$E$1204,"Deposit"),2)) -> 0 | AB16: =IF(B16="","",ROUND(SUMIFS(Sales!$Y$5:$Y$1204,Sales!$C$5:$C$1204,A16),2)) -> 0 | AC16: =IF(B16="","",IF(M16="Completed","Yes",IF(M16="Cancelled","Yes",IF(M16="No show","Yes","No")))) -> 0 | AD16: =IF(B16="","",IF(AE16="","",B16-AE16)) -> 0 | AF16: =IF(B16="","",IF(M16<>"Completed","",IF(E16="","No",IF(COUNTIFS(Appointments!$E$5:$E$1204,E16,Appointments!$B$5:$B$1204,">"&B16,Appointments!$M$5:$M$1204,"<>Cancelled")>0,"Yes","No")))) -> 0 | AG16: =IF(B16="","",IF(I16="","",IF(D16="","",IF(COUNTIFS($I$5:$I$1204,I16,$B$5:$B$1204,B16,$D$5:$D$1204,"<"&V16,$V$5:$V$1204,">"&D16,$M$5:$M$1204,"<>Cancelled")>1,"Clash","")))) -> 0 | AH16: =IF(B16="","",IF(AG16="Clash","Clash - stylist double booked",IF(I16="","Assign - no stylist yet",IF(G16="","Add - no service chosen",IF(M16="No show","No show - charge the fee?",IF(M16="Cancelled","",IF(IF(M16="Completed",AB16<Y16-0.004,FALSE),"Unpaid - nothing rung up for this visit",IF(IF(B16<TodayDate,M16="Booked",FALSE),"Overdue - past date, still only Booked",IF(IF(B16=TodayDate,TRUE,FALSE),"Today",IF(IF(Z16>0,AA16<Z16-0.004,FALSE),"Due - deposit not taken",IF(IF(B16>TodayDate,B16<=TodayDate+2,FALSE),"Confirm - coming up","OK"))))))))))) -> 0
... A1204: =IF(B1204="","",AppointmentPrefix&TEXT(ROW()-4,"0000")) -> 0 | C1204: =IF(B1204="","",TEXT(B1204,"ddd")) -> 0 | F1204: =IF(E1204="","",IFERROR(INDEX(Clients!$B$5:$B$504,MATCH(E1204,Clients!$A$5:$A$504,0)),"Walk-in")) -> 0 | H1204: =IF(G1204="","",IFERROR(INDEX(Services!$B$5:$B$204,MATCH(G1204,Services!$A$5:$A$204,0)),"Not in Services")) -> 0 | J1204: =IF(I1204="","",IFERROR(INDEX(Staff!$B$5:$B$44,MATCH(I1204,Staff!$A$5:$A$44,0)),"Unassigned")) -> 0 | S1204: =IF(B1204="","",TEXT(B1204,"yyyy-mm")) -> 0 | T1204: =IF(B1204="","",WEEKNUM(B1204,2)) -> 0 | U1204: =IF(B1204="","",IF(K1204<>"",K1204,IFERROR(INDEX(Services!$E$5:$E$204,MATCH(G1204,Services!$A$5:$A$204,0))*1,0)+IFERROR(INDEX(Services!$F$5:$F$204,MATCH(G1204,Services!$A$5:$A$204,0))*1,0))) -> 0 | V1204: =IF(B1204="","",IF(D1204="","",D1204+U1204/1440)) -> 0 | W1204: =IF(B1204="","",IF(D1204="","",HOUR(D1204))) -> 0 | X1204: =IF(B1204="","",ROUND(U1204/60,2)) -> 0 | Y1204: =IF(B1204="","",IF(L1204<>"",L1204,IFERROR(INDEX(Services!$G$5:$G$204,MATCH(G1204,Services!$A$5:$A$204,0))*1,0))) -> 0 | Z1204: =IF(B1204="","",IF(O1204<>"",O1204,IF(Y1204>=DepositThreshold,ROUND(Y1204*DepositPercent,2),0))) -> 0 | AA1204: =IF(B1204="","",ROUND(SUMIFS(Payments!$G$5:$G$1204,Payments!$I$5:$I$1204,A1204,Payments!$E$5:$E$1204,"Deposit"),2)) -> 0 | AB1204: =IF(B1204="","",ROUND(SUMIFS(Sales!$Y$5:$Y$1204,Sales!$C$5:$C$1204,A1204),2)) -> 0 | AC1204: =IF(B1204="","",IF(M1204="Completed","Yes",IF(M1204="Cancelled","Yes",IF(M1204="No show","Yes","No")))) -> 0 | AD1204: =IF(B1204="","",IF(AE1204="","",B1204-AE1204)) -> 0 | AF1204: =IF(B1204="","",IF(M1204<>"Completed","",IF(E1204="","No",IF(COUNTIFS(Appointments!$E$5:$E$1204,E1204,Appointments!$B$5:$B$1204,">"&B1204,Appointments!$M$5:$M$1204,"<>Cancelled")>0,"Yes","No")))) -> 0 | AG1204: =IF(B1204="","",IF(I1204="","",IF(D1204="","",IF(COUNTIFS($I$5:$I$1204,I1204,$B$5:$B$1204,B1204,$D$5:$D$1204,"<"&V1204,$V$5:$V$1204,">"&D1204,$M$5:$M$1204,"<>Cancelled")>1,"Clash","")))) -> 0 | AH1204: =IF(B1204="","",IF(AG1204="Clash","Clash - stylist double booked",IF(I1204="","Assign - no stylist yet",IF(G1204="","Add - no service chosen",IF(M1204="No show","No show - charge the fee?",IF(M1204="Cancelled","",IF(IF(M1204="Completed",AB1204<Y1204-0.004,FALSE),"Unpaid - nothing rung up for this visit",IF(IF(B1204<TodayDate,M1204="Booked",FALSE),"Overdue - past date, still only Booked",IF(IF(B1204=TodayDate,TRUE,FALSE),"Today",IF(IF(Z1204>0,AA1204<Z1204-0.004,FALSE),"Due - deposit not taken",IF(IF(B1204>TodayDate,B1204<=TodayDate+2,FALSE),"Confirm - coming up","OK"))))))))))) -> 0
A1206: The diary in numbers
A1207: Appointments logged | B1207: Completed | C1207: Cancelled | D1207: No shows | E1207: Completion rate | F1207: Cancellation rate | G1207: No-show rate | H1207: Booked value, completed | I1207: Chair hours, completed | J1207: Clashes to fix
A1208: =COUNTIF(Appointments!$B$5:$B$1204,"<>") -> 0 | B1208: =COUNTIFS(Appointments!$M$5:$M$1204,"Completed") -> 0 | C1208: =COUNTIFS(Appointments!$M$5:$M$1204,"Cancelled") -> 0 | D1208: =COUNTIFS(Appointments!$M$5:$M$1204,"No show") -> 0 | E1208: =IFERROR(COUNTIFS(Appointments!$M$5:$M$1204,"Completed")/MAX(1,COUNTIFS(Appointments!$AC$5:$AC$1204,"Yes")),0) -> 0 | F1208: =IFERROR(COUNTIFS(Appointments!$M$5:$M$1204,"Cancelled")/MAX(1,COUNTIFS(Appointments!$AC$5:$AC$1204,"Yes")),0) -> 0 | G1208: =IFERROR(COUNTIFS(Appointments!$M$5:$M$1204,"No show")/MAX(1,COUNTIFS(Appointments!$AC$5:$AC$1204,"Yes")),0) -> 0 | H1208: =ROUND(SUMIFS(Appointments!$Y$5:$Y$1204,Appointments!$M$5:$M$1204,"Completed"),2) -> 0 | I1208: =ROUND(SUMIFS(Appointments!$X$5:$X$1204,Appointments!$M$5:$M$1204,"Completed"),1) -> 0 | J1208: =COUNTIFS(Appointments!$AG$5:$AG$1204,"Clash") -> 0

Sheet Clients
A1: Client CRM | AO1: Novality Store | v1.0.0
A2: Who they are, what they have spent, when they were last in - and which of them you are about to lose.
A3: > Start Here | C3: > Dashboard | E3: > Diary | G3: > Clients | I3: > Services | K3: > Sales | M3: > Staff | O3: > Profit | Q3: > Settings | S3: Type the name and the contact details. Visits, spend, last visit and the chase list all build themselves from the appointments and sales tabs.
A4: ID | B4: Client | C4: Phone | D4: Email | E4: Contact by | F4: First seen | G4: Found you by | H4: Referred by | I4: Usual stylist | J4: Stylist | K4: Birthday | L4: Formula & preferences | M4: Allergies & notes | N4: Patch test | O4: Marketing OK? | P4: Photos OK? | Q4: Tags | R4: Status | S4: Notes | T4: Visits | U4: Visits, 12m | V4: Cancelled | W4: No shows | X4: First visit | Y4: Last visit | Z4: Days since | AA4: Next raw | AB4: Next booked | AC4: Usual gap | AD4: Rebook by | AE4: Lifetime spend | AF4: On services | AG4: On retail | AH4: Spend, 12m | AI4: Average ticket | AJ4: A year is worth | AK4: Balance owed | AL4: Loyalty points | AM4: Segment | AN4: Came back? | AO4: Spend rank | AP4: Visit rank | AQ4: Action
A5: =IF(B5="","",ClientPrefix&TEXT(ROW()-4,"0000")) -> 0 | J5: =IF(I5="","",IFERROR(INDEX(Staff!$B$5:$B$44,MATCH(I5,Staff!$A$5:$A$44,0)),"Not in Staff")) -> 0 | T5: =IF(B5="","",COUNTIFS(Appointments!$E$5:$E$1204,A5,Appointments!$M$5:$M$1204,"Completed")) -> 0 | U5: =IF(B5="","",COUNTIFS(Appointments!$E$5:$E$1204,A5,Appointments!$M$5:$M$1204,"Completed",Appointments!$B$5:$B$1204,">="&TodayDate-365)) -> 0 | V5: =IF(B5="","",COUNTIFS(Appointments!$E$5:$E$1204,A5,Appointments!$M$5:$M$1204,"Cancelled")) -> 0 | W5: =IF(B5="","",COUNTIFS(Appointments!$E$5:$E$1204,A5,Appointments!$M$5:$M$1204,"No show")) -> 0 | X5: =IF(B5="","",IF(F5<>"",F5,IF(T5=0,"",SUMPRODUCT(MIN((Appointments!$E$5:$E$1204=A5)*(Appointments!$M$5:$M$1204="Completed")*Appointments!$B$5:$B$1204+(1-(Appointments!$E$5:$E$1204=A5)*(Appointments!$M$5:$M$1204="Completed"))*2958465))))) -> 0 | Y5: =IF(B5="","",IF(T5=0,"",SUMPRODUCT(MAX((Appointments!$E$5:$E$1204=A5)*(Appointments!$M$5:$M$1204="Completed")*Appointments!$B$5:$B$1204)))) -> 0 | Z5: =IF(B5="","",IF(Y5="","",TodayDate-Y5)) -> 0 | AA5: =IF(B5="","",SUMPRODUCT(MIN((Appointments!$E$5:$E$1204=A5)*(Appointments!$M$5:$M$1204<>"Cancelled")*(Appointments!$M$5:$M$1204<>"Completed")*(Appointments!$M$5:$M$1204<>"No show")*(Appointments!$B$5:$B$1204>=TodayDate)*Appointments!$B$5:$B$1204+(1-(Appointments!$E$5:$E$1204=A5)*(Appointments!$M$5:$M$1204<>"Cancelled")*(Appointments!$M$5:$M$1204<>"Completed")*(Appointments!$M$5:$M$1204<>"No show")*(Appointments!$B$5:$B$1204>=TodayDate))*2958465))) -> 0 | AB5: =IF(B5="","",IF(AA5>=2958465,"",AA5)) -> 0 | AC5: =IF(B5="","",IF(T5<2,"",ROUND((Y5-X5)/MAX(1,T5-1),0))) -> 0 | AD5: =IF(B5="","",IF(Y5="","",Y5+IF(AC5="",RebookWeeks*7,MAX(14,AC5)))) -> 0 | AE5: =IF(B5="","",ROUND(SUMIFS(Sales!$Y$5:$Y$1204,Sales!$D$5:$D$1204,A5),2)) -> 0 | AF5: =IF(B5="","",ROUND(SUMIFS(Sales!$Y$5:$Y$1204,Sales!$D$5:$D$1204,A5,Sales!$H$5:$H$1204,"Service"),2)) -> 0 | AG5: =IF(B5="","",ROUND(SUMIFS(Sales!$Y$5:$Y$1204,Sales!$D$5:$D$1204,A5,Sales!$H$5:$H$1204,"Retail"),2)) -> 0 | AH5: =IF(B5="","",ROUND(SUMIFS(Sales!$Y$5:$Y$1204,Sales!$D$5:$D$1204,A5,Sales!$B$5:$B$1204,">="&TodayDate-365),2)) -> 0 | AI5: =IF(B5="","",IF(T5=0,"",ROUND(AE5/T5,2))) -> 0 | AJ5: =IF(B5="","",IF(AI5="","",IF(AC5="","",ROUND(AI5*(365/MAX(14,AC5)),2)))) -> 0 | AK5: =IF(B5="","",ROUND(SUMIFS(Sales!$AH$5:$AH$1204,Sales!$D$5:$D$1204,A5),2)) -> 0 | AL5: =IF(B5="","",IFERROR(INDEX(Loyalty!$P$5:$P$504,MATCH(A5,Loyalty!$B$5:$B$504,0))*1,0)) -> 0 | AM5: =IF(B5="","",IF(R5="Archived","Archived",IF(T5=0,"Not been yet",IF(Z5>=InactiveDays,"Inactive",IF(Z5>=LapsingDays,"Lapsing",IF(T5=1,"New",IF(AH5>=VipSpend,"VIP",IF(U5>=4,"Regular","Active")))))))) -> 0 | AN5: =IF(B5="","",IF(T5>=2,"Yes","No")) -> 0 | AO5: =IF(B5="","",COUNTIFS($AE$5:$AE$504,">"&AE5)+COUNTIFS($AE$5:AE5,AE5)) -> 0 | AP5: =IF(B5="","",COUNTIFS($T$5:$T$504,">"&T5)+COUNTIFS($T$5:T5,T5)) -> 0 | AQ5: =IF(B5="","",IF(COUNTIF($B$5:$B$504,B5)>1,"Duplicate - same name twice",IF(R5="Archived","",IF(AK5>0.004,"Chase - balance outstanding",IF(AM5="Inactive","Gone - win-back offer",IF(AM5="Lapsing","Chase - lapsing, call them",IF(IF(N5="",FALSE,TodayDate-N5>PatchTestDays),"Due - patch test out of date",IF(IF(AD5="",FALSE,IF(AB5<>"",FALSE,AD5<=TodayDate+14)),"Rebook - due and nothing booked",IF(IF(K5="",FALSE,ABS(DATE(YEAR(TodayDate),MONTH(K5),DAY(K5))-TodayDate)<=7),"Birthday - send the treat","OK"))))))))) -> 0
A6: =IF(B6="","",ClientPrefix&TEXT(ROW()-4,"0000")) -> 0 | J6: =IF(I6="","",IFERROR(INDEX(Staff!$B$5:$B$44,MATCH(I6,Staff!$A$5:$A$44,0)),"Not in Staff")) -> 0 | T6: =IF(B6="","",COUNTIFS(Appointments!$E$5:$E$1204,A6,Appointments!$M$5:$M$1204,"Completed")) -> 0 | U6: =IF(B6="","",COUNTIFS(Appointments!$E$5:$E$1204,A6,Appointments!$M$5:$M$1204,"Completed",Appointments!$B$5:$B$1204,">="&TodayDate-365)) -> 0 | V6: =IF(B6="","",COUNTIFS(Appointments!$E$5:$E$1204,A6,Appointments!$M$5:$M$1204,"Cancelled")) -> 0 | W6: =IF(B6="","",COUNTIFS(Appointments!$E$5:$E$1204,A6,Appointments!$M$5:$M$1204,"No show")) -> 0 | X6: =IF(B6="","",IF(F6<>"",F6,IF(T6=0,"",SUMPRODUCT(MIN((Appointments!$E$5:$E$1204=A6)*(Appointments!$M$5:$M$1204="Completed")*Appointments!$B$5:$B$1204+(1-(Appointments!$E$5:$E$1204=A6)*(Appointments!$M$5:$M$1204="Completed"))*2958465))))) -> 0 | Y6: =IF(B6="","",IF(T6=0,"",SUMPRODUCT(MAX((Appointments!$E$5:$E$1204=A6)*(Appointments!$M$5:$M$1204="Completed")*Appointments!$B$5:$B$1204)))) -> 0 | Z6: =IF(B6="","",IF(Y6="","",TodayDate-Y6)) -> 0 | AA6: =IF(B6="","",SUMPRODUCT(MIN((Appointments!$E$5:$E$1204=A6)*(Appointments!$M$5:$M$1204<>"Cancelled")*(Appointments!$M$5:$M$1204<>"Completed")*(Appointments!$M$5:$M$1204<>"No show")*(Appointments!$B$5:$B$1204>=TodayDate)*Appointments!$B$5:$B$1204+(1-(Appointments!$E$5:$E$1204=A6)*(Appointments!$M$5:$M$1204<>"Cancelled")*(Appointments!$M$5:$M$1204<>"Completed")*(Appointments!$M$5:$M$1204<>"No show")*(Appointments!$B$5:$B$1204>=TodayDate))*2958465))) -> 0 | AB6: =IF(B6="","",IF(AA6>=2958465,"",AA6)) -> 0 | AC6: =IF(B6="","",IF(T6<2,"",ROUND((Y6-X6)/MAX(1,T6-1),0))) -> 0 | AD6: =IF(B6="","",IF(Y6="","",Y6+IF(AC6="",RebookWeeks*7,MAX(14,AC6)))) -> 0 | AE6: =IF(B6="","",ROUND(SUMIFS(Sales!$Y$5:$Y$1204,Sales!$D$5:$D$1204,A6),2)) -> 0 | AF6: =IF(B6="","",ROUND(SUMIFS(Sales!$Y$5:$Y$1204,Sales!$D$5:$D$1204,A6,Sales!$H$5:$H$1204,"Service"),2)) -> 0 | AG6: =IF(B6="","",ROUND(SUMIFS(Sales!$Y$5:$Y$1204,Sales!$D$5:$D$1204,A6,Sales!$H$5:$H$1204,"Retail"),2)) -> 0 | AH6: =IF(B6="","",ROUND(SUMIFS(Sales!$Y$5:$Y$1204,Sales!$D$5:$D$1204,A6,Sales!$B$5:$B$1204,">="&TodayDate-365),2)) -> 0 | AI6: =IF(B6="","",IF(T6=0,"",ROUND(AE6/T6,2))) -> 0 | AJ6: =IF(B6="","",IF(AI6="","",IF(AC6="","",ROUND(AI6*(365/MAX(14,AC6)),2)))) -> 0 | AK6: =IF(B6="","",ROUND(SUMIFS(Sales!$AH$5:$AH$1204,Sales!$D$5:$D$1204,A6),2)) -> 0 | AL6: =IF(B6="","",IFERROR(INDEX(Loyalty!$P$5:$P$504,MATCH(A6,Loyalty!$B$5:$B$504,0))*1,0)) -> 0 | AM6: =IF(B6="","",IF(R6="Archived","Archived",IF(T6=0,"Not been yet",IF(Z6>=InactiveDays,"Inactive",IF(Z6>=LapsingDays,"Lapsing",IF(T6=1,"New",IF(AH6>=VipSpend,"VIP",IF(U6>=4,"Regular","Active")))))))) -> 0 | AN6: =IF(B6="","",IF(T6>=2,"Yes","No")) -> 0 | AO6: =IF(B6="","",COUNTIFS($AE$5:$AE$504,">"&AE6)+COUNTIFS($AE$5:AE6,AE6)) -> 0 | AP6: =IF(B6="","",COUNTIFS($T$5:$T$504,">"&T6)+COUNTIFS($T$5:T6,T6)) -> 0 | AQ6: =IF(B6="","",IF(COUNTIF($B$5:$B$504,B6)>1,"Duplicate - same name twice",IF(R6="Archived","",IF(AK6>0.004,"Chase - balance outstanding",IF(AM6="Inactive","Gone - win-back offer",IF(AM6="Lapsing","Chase - lapsing, call them",IF(IF(N6="",FALSE,TodayDate-N6>PatchTestDays),"Due - patch test out of date",IF(IF(AD6="",FALSE,IF(AB6<>"",FALSE,AD6<=TodayDate+14)),"Rebook - due and nothing booked",IF(IF(K6="",FALSE,ABS(DATE(YEAR(TodayDate),MONTH(K6),DAY(K6))-TodayDate)<=7),"Birthday - send the treat","OK"))))))))) -> 0
A7: =IF(B7="","",ClientPrefix&TEXT(ROW()-4,"0000")) -> 0 | J7: =IF(I7="","",IFERROR(INDEX(Staff!$B$5:$B$44,MATCH(I7,Staff!$A$5:$A$44,0)),"Not in Staff")) -> 0 | T7: =IF(B7="","",COUNTIFS(Appointments!$E$5:$E$1204,A7,Appointments!$M$5:$M$1204,"Completed")) -> 0 | U7: =IF(B7="","",COUNTIFS(Appointments!$E$5:$E$1204,A7,Appointments!$M$5:$M$1204,"Completed",Appointments!$B$5:$B$1204,">="&TodayDate-365)) -> 0 | V7: =IF(B7="","",COUNTIFS(Appointments!$E$5:$E$1204,A7,Appointments!$M$5:$M$1204,"Cancelled")) -> 0 | W7: =IF(B7="","",COUNTIFS(Appointments!$E$5:$E$1204,A7,Appointments!$M$5:$M$1204,"No show")) -> 0 | X7: =IF(B7="","",IF(F7<>"",F7,IF(T7=0,"",SUMPRODUCT(MIN((Appointments!$E$5:$E$1204=A7)*(Appointments!$M$5:$M$1204="Completed")*Appointments!$B$5:$B$1204+(1-(Appointments!$E$5:$E$1204=A7)*(Appointments!$M$5:$M$1204="Completed"))*2958465))))) -> 0 | Y7: =IF(B7="","",IF(T7=0,"",SUMPRODUCT(MAX((Appointments!$E$5:$E$1204=A7)*(Appointments!$M$5:$M$1204="Completed")*Appointments!$B$5:$B$1204)))) -> 0 | Z7: =IF(B7="","",IF(Y7="","",TodayDate-Y7)) -> 0 | AA7: =IF(B7="","",SUMPRODUCT(MIN((Appointments!$E$5:$E$1204=A7)*(Appointments!$M$5:$M$1204<>"Cancelled")*(Appointments!$M$5:$M$1204<>"Completed")*(Appointments!$M$5:$M$1204<>"No show")*(Appointments!$B$5:$B$1204>=TodayDate)*Appointments!$B$5:$B$1204+(1-(Appointments!$E$5:$E$1204=A7)*(Appointments!$M$5:$M$1204<>"Cancelled")*(Appointments!$M$5:$M$1204<>"Completed")*(Appointments!$M$5:$M$1204<>"No show")*(Appointments!$B$5:$B$1204>=TodayDate))*2958465))) -> 0 | AB7: =IF(B7="","",IF(AA7>=2958465,"",AA7)) -> 0 | AC7: =IF(B7="","",IF(T7<2,"",ROUND((Y7-X7)/MAX(1,T7-1),0))) -> 0 | AD7: =IF(B7="","",IF(Y7="","",Y7+IF(AC7="",RebookWeeks*7,MAX(14,AC7)))) -> 0 | AE7: =IF(B7="","",ROUND(SUMIFS(Sales!$Y$5:$Y$1204,Sales!$D$5:$D$1204,A7),2)) -> 0 | AF7: =IF(B7="","",ROUND(SUMIFS(Sales!$Y$5:$Y$1204,Sales!$D$5:$D$1204,A7,Sales!$H$5:$H$1204,"Service"),2)) -> 0 | AG7: =IF(B7="","",ROUND(SUMIFS(Sales!$Y$5:$Y$1204,Sales!$D$5:$D$1204,A7,Sales!$H$5:$H$1204,"Retail"),2)) -> 0 | AH7: =IF(B7="","",ROUND(SUMIFS(Sales!$Y$5:$Y$1204,Sales!$D$5:$D$1204,A7,Sales!$B$5:$B$1204,">="&TodayDate-365),2)) -> 0 | AI7: =IF(B7="","",IF(T7=0,"",ROUND(AE7/T7,2))) -> 0 | AJ7: =IF(B7="","",IF(AI7="","",IF(AC7="","",ROUND(AI7*(365/MAX(14,AC7)),2)))) -> 0 | AK7: =IF(B7="","",ROUND(SUMIFS(Sales!$AH$5:$AH$1204,Sales!$D$5:$D$1204,A7),2)) -> 0 | AL7: =IF(B7="","",IFERROR(INDEX(Loyalty!$P$5:$P$504,MATCH(A7,Loyalty!$B$5:$B$504,0))*1,0)) -> 0 | AM7: =IF(B7="","",IF(R7="Archived","Archived",IF(T7=0,"Not been yet",IF(Z7>=InactiveDays,"Inactive",IF(Z7>=LapsingDays,"Lapsing",IF(T7=1,"New",IF(AH7>=VipSpend,"VIP",IF(U7>=4,"Regular","Active")))))))) -> 0 | AN7: =IF(B7="","",IF(T7>=2,"Yes","No")) -> 0 | AO7: =IF(B7="","",COUNTIFS($AE$5:$AE$504,">"&AE7)+COUNTIFS($AE$5:AE7,AE7)) -> 0 | AP7: =IF(B7="","",COUNTIFS($T$5:$T$504,">"&T7)+COUNTIFS($T$5:T7,T7)) -> 0 | AQ7: =IF(B7="","",IF(COUNTIF($B$5:$B$504,B7)>1,"Duplicate - same name twice",IF(R7="Archived","",IF(AK7>0.004,"Chase - balance outstanding",IF(AM7="Inactive","Gone - win-back offer",IF(AM7="Lapsing","Chase - lapsing, call them",IF(IF(N7="",FALSE,TodayDate-N7>PatchTestDays),"Due - patch test out of date",IF(IF(AD7="",FALSE,IF(AB7<>"",FALSE,AD7<=TodayDate+14)),"Rebook - due and nothing booked",IF(IF(K7="",FALSE,ABS(DATE(YEAR(TodayDate),MONTH(K7),DAY(K7))-TodayDate)<=7),"Birthday - send the treat","OK"))))))))) -> 0
A8: =IF(B8="","",ClientPrefix&TEXT(ROW()-4,"0000")) -> 0 | J8: =IF(I8="","",IFERROR(INDEX(Staff!$B$5:$B$44,MATCH(I8,Staff!$A$5:$A$44,0)),"Not in Staff")) -> 0 | T8: =IF(B8="","",COUNTIFS(Appointments!$E$5:$E$1204,A8,Appointments!$M$5:$M$1204,"Completed")) -> 0 | U8: =IF(B8="","",COUNTIFS(Appointments!$E$5:$E$1204,A8,Appointments!$M$5:$M$1204,"Completed",Appointments!$B$5:$B$1204,">="&TodayDate-365)) -> 0 | V8: =IF(B8="","",COUNTIFS(Appointments!$E$5:$E$1204,A8,Appointments!$M$5:$M$1204,"Cancelled")) -> 0 | W8: =IF(B8="","",COUNTIFS(Appointments!$E$5:$E$1204,A8,Appointments!$M$5:$M$1204,"No show")) -> 0 | X8: =IF(B8="","",IF(F8<>"",F8,IF(T8=0,"",SUMPRODUCT(MIN((Appointments!$E$5:$E$1204=A8)*(Appointments!$M$5:$M$1204="Completed")*Appointments!$B$5:$B$1204+(1-(Appointments!$E$5:$E$1204=A8)*(Appointments!$M$5:$M$1204="Completed"))*2958465))))) -> 0 | Y8: =IF(B8="","",IF(T8=0,"",SUMPRODUCT(MAX((Appointments!$E$5:$E$1204=A8)*(Appointments!$M$5:$M$1204="Completed")*Appointments!$B$5:$B$1204)))) -> 0 | Z8: =IF(B8="","",IF(Y8="","",TodayDate-Y8)) -> 0 | AA8: =IF(B8="","",SUMPRODUCT(MIN((Appointments!$E$5:$E$1204=A8)*(Appointments!$M$5:$M$1204<>"Cancelled")*(Appointments!$M$5:$M$1204<>"Completed")*(Appointments!$M$5:$M$1204<>"No show")*(Appointments!$B$5:$B$1204>=TodayDate)*Appointments!$B$5:$B$1204+(1-(Appointments!$E$5:$E$1204=A8)*(Appointments!$M$5:$M$1204<>"Cancelled")*(Appointments!$M$5:$M$1204<>"Completed")*(Appointments!$M$5:$M$1204<>"No show")*(Appointments!$B$5:$B$1204>=TodayDate))*2958465))) -> 0 | AB8: =IF(B8="","",IF(AA8>=2958465,"",AA8)) -> 0 | AC8: =IF(B8="","",IF(T8<2,"",ROUND((Y8-X8)/MAX(1,T8-1),0))) -> 0 | AD8: =IF(B8="","",IF(Y8="","",Y8+IF(AC8="",RebookWeeks*7,MAX(14,AC8)))) -> 0 | AE8: =IF(B8="","",ROUND(SUMIFS(Sales!$Y$5:$Y$1204,Sales!$D$5:$D$1204,A8),2)) -> 0 | AF8: =IF(B8="","",ROUND(SUMIFS(Sales!$Y$5:$Y$1204,Sales!$D$5:$D$1204,A8,Sales!$H$5:$H$1204,"Service"),2)) -> 0 | AG8: =IF(B8="","",ROUND(SUMIFS(Sales!$Y$5:$Y$1204,Sales!$D$5:$D$1204,A8,Sales!$H$5:$H$1204,"Retail"),2)) -> 0 | AH8: =IF(B8="","",ROUND(SUMIFS(Sales!$Y$5:$Y$1204,Sales!$D$5:$D$1204,A8,Sales!$B$5:$B$1204,">="&TodayDate-365),2)) -> 0 | AI8: =IF(B8="","",IF(T8=0,"",ROUND(AE8/T8,2))) -> 0 | AJ8: =IF(B8="","",IF(AI8="","",IF(AC8="","",ROUND(AI8*(365/MAX(14,AC8)),2)))) -> 0 | AK8: =IF(B8="","",ROUND(SUMIFS(Sales!$AH$5:$AH$1204,Sales!$D$5:$D$1204,A8),2)) -> 0 | AL8: =IF(B8="","",IFERROR(INDEX(Loyalty!$P$5:$P$504,MATCH(A8,Loyalty!$B$5:$B$504,0))*1,0)) -> 0 | AM8: =IF(B8="","",IF(R8="Archived","Archived",IF(T8=0,"Not been yet",IF(Z8>=InactiveDays,"Inactive",IF(Z8>=LapsingDays,"Lapsing",IF(T8=1,"New",IF(AH8>=VipSpend,"VIP",IF(U8>=4,"Regular","Active")))))))) -> 0 | AN8: =IF(B8="","",IF(T8>=2,"Yes","No")) -> 0 | AO8: =IF(B8="","",COUNTIFS($AE$5:$AE$504,">"&AE8)+COUNTIFS($AE$5:AE8,AE8)) -> 0 | AP8: =IF(B8="","",COUNTIFS($T$5:$T$504,">"&T8)+COUNTIFS($T$5:T8,T8)) -> 0 | AQ8: =IF(B8="","",IF(COUNTIF($B$5:$B$504,B8)>1,"Duplicate - same name twice",IF(R8="Archived","",IF(AK8>0.004,"Chase - balance outstanding",IF(AM8="Inactive","Gone - win-back offer",IF(AM8="Lapsing","Chase - lapsing, call them",IF(IF(N8="",FALSE,TodayDate-N8>PatchTestDays),"Due - patch test out of date",IF(IF(AD8="",FALSE,IF(AB8<>"",FALSE,AD8<=TodayDate+14)),"Rebook - due and nothing booked",IF(IF(K8="",FALSE,ABS(DATE(YEAR(TodayDate),MONTH(K8),DAY(K8))-TodayDate)<=7),"Birthday - send the treat","OK"))))))))) -> 0
A9: =IF(B9="","",ClientPrefix&TEXT(ROW()-4,"0000")) -> 0 | J9: =IF(I9="","",IFERROR(INDEX(Staff!$B$5:$B$44,MATCH(I9,Staff!$A$5:$A$44,0)),"Not in Staff")) -> 0 | T9: =IF(B9="","",COUNTIFS(Appointments!$E$5:$E$1204,A9,Appointments!$M$5:$M$1204,"Completed")) -> 0 | U9: =IF(B9="","",COUNTIFS(Appointments!$E$5:$E$1204,A9,Appointments!$M$5:$M$1204,"Completed",Appointments!$B$5:$B$1204,">="&TodayDate-365)) -> 0 | V9: =IF(B9="","",COUNTIFS(Appointments!$E$5:$E$1204,A9,Appointments!$M$5:$M$1204,"Cancelled")) -> 0 | W9: =IF(B9="","",COUNTIFS(Appointments!$E$5:$E$1204,A9,Appointments!$M$5:$M$1204,"No show")) -> 0 | X9: =IF(B9="","",IF(F9<>"",F9,IF(T9=0,"",SUMPRODUCT(MIN((Appointments!$E$5:$E$1204=A9)*(Appointments!$M$5:$M$1204="Completed")*Appointments!$B$5:$B$1204+(1-(Appointments!$E$5:$E$1204=A9)*(Appointments!$M$5:$M$1204="Completed"))*2958465))))) -> 0 | Y9: =IF(B9="","",IF(T9=0,"",SUMPRODUCT(MAX((Appointments!$E$5:$E$1204=A9)*(Appointments!$M$5:$M$1204="Completed")*Appointments!$B$5:$B$1204)))) -> 0 | Z9: =IF(B9="","",IF(Y9="","",TodayDate-Y9)) -> 0 | AA9: =IF(B9="","",SUMPRODUCT(MIN((Appointments!$E$5:$E$1204=A9)*(Appointments!$M$5:$M$1204<>"Cancelled")*(Appointments!$M$5:$M$1204<>"Completed")*(Appointments!$M$5:$M$1204<>"No show")*(Appointments!$B$5:$B$1204>=TodayDate)*Appointments!$B$5:$B$1204+(1-(Appointments!$E$5:$E$1204=A9)*(Appointments!$M$5:$M$1204<>"Cancelled")*(Appointments!$M$5:$M$1204<>"Completed")*(Appointments!$M$5:$M$1204<>"No show")*(Appointments!$B$5:$B$1204>=TodayDate))*2958465))) -> 0 | AB9: =IF(B9="","",IF(AA9>=2958465,"",AA9)) -> 0 | AC9: =IF(B9="","",IF(T9<2,"",ROUND((Y9-X9)/MAX(1,T9-1),0))) -> 0 | AD9: =IF(B9="","",IF(Y9="","",Y9+IF(AC9="",RebookWeeks*7,MAX(14,AC9)))) -> 0 | AE9: =IF(B9="","",ROUND(SUMIFS(Sales!$Y$5:$Y$1204,Sales!$D$5:$D$1204,A9),2)) -> 0 | AF9: =IF(B9="","",ROUND(SUMIFS(Sales!$Y$5:$Y$1204,Sales!$D$5:$D$1204,A9,Sales!$H$5:$H$1204,"Service"),2)) -> 0 | AG9: =IF(B9="","",ROUND(SUMIFS(Sales!$Y$5:$Y$1204,Sales!$D$5:$D$1204,A9,Sales!$H$5:$H$1204,"Retail"),2)) -> 0 | AH9: =IF(B9="","",ROUND(SUMIFS(Sales!$Y$5:$Y$1204,Sales!$D$5:$D$1204,A9,Sales!$B$5:$B$1204,">="&TodayDate-365),2)) -> 0 | AI9: =IF(B9="","",IF(T9=0,"",ROUND(AE9/T9,2))) -> 0 | AJ9: =IF(B9="","",IF(AI9="","",IF(AC9="","",ROUND(AI9*(365/MAX(14,AC9)),2)))) -> 0 | AK9: =IF(B9="","",ROUND(SUMIFS(Sales!$AH$5:$AH$1204,Sales!$D$5:$D$1204,A9),2)) -> 0 | AL9: =IF(B9="","",IFERROR(INDEX(Loyalty!$P$5:$P$504,MATCH(A9,Loyalty!$B$5:$B$504,0))*1,0)) -> 0 | AM9: =IF(B9="","",IF(R9="Archived","Archived",IF(T9=0,"Not been yet",IF(Z9>=InactiveDays,"Inactive",IF(Z9>=LapsingDays,"Lapsing",IF(T9=1,"New",IF(AH9>=VipSpend,"VIP",IF(U9>=4,"Regular","Active")))))))) -> 0 | AN9: =IF(B9="","",IF(T9>=2,"Yes","No")) -> 0 | AO9: =IF(B9="","",COUNTIFS($AE$5:$AE$504,">"&AE9)+COUNTIFS($AE$5:AE9,AE9)) -> 0 | AP9: =IF(B9="","",COUNTIFS($T$5:$T$504,">"&T9)+COUNTIFS($T$5:T9,T9)) -> 0 | AQ9: =IF(B9="","",IF(COUNTIF($B$5:$B$504,B9)>1,"Duplicate - same name twice",IF(R9="Archived","",IF(AK9>0.004,"Chase - balance outstanding",IF(AM9="Inactive","Gone - win-back offer",IF(AM9="Lapsing","Chase - lapsing, call them",IF(IF(N9="",FALSE,TodayDate-N9>PatchTestDays),"Due - patch test out of date",IF(IF(AD9="",FALSE,IF(AB9<>"",FALSE,AD9<=TodayDate+14)),"Rebook - due and nothing booked",IF(IF(K9="",FALSE,ABS(DATE(YEAR(TodayDate),MONTH(K9),DAY(K9))-TodayDate)<=7),"Birthday - send the treat","OK"))))))))) -> 0
A10: =IF(B10="","",ClientPrefix&TEXT(ROW()-4,"0000")) -> 0 | J10: =IF(I10="","",IFERROR(INDEX(Staff!$B$5:$B$44,MATCH(I10,Staff!$A$5:$A$44,0)),"Not in Staff")) -> 0 | T10: =IF(B10="","",COUNTIFS(Appointments!$E$5:$E$1204,A10,Appointments!$M$5:$M$1204,"Completed")) -> 0 | U10: =IF(B10="","",COUNTIFS(Appointments!$E$5:$E$1204,A10,Appointments!$M$5:$M$1204,"Completed",Appointments!$B$5:$B$1204,">="&TodayDate-365)) -> 0 | V10: =IF(B10="","",COUNTIFS(Appointments!$E$5:$E$1204,A10,Appointments!$M$5:$M$1204,"Cancelled")) -> 0 | W10: =IF(B10="","",COUNTIFS(Appointments!$E$5:$E$1204,A10,Appointments!$M$5:$M$1204,"No show")) -> 0 | X10: =IF(B10="","",IF(F10<>"",F10,IF(T10=0,"",SUMPRODUCT(MIN((Appointments!$E$5:$E$1204=A10)*(Appointments!$M$5:$M$1204="Completed")*Appointments!$B$5:$B$1204+(1-(Appointments!$E$5:$E$1204=A10)*(Appointments!$M$5:$M$1204="Completed"))*2958465))))) -> 0 | Y10: =IF(B10="","",IF(T10=0,"",SUMPRODUCT(MAX((Appointments!$E$5:$E$1204=A10)*(Appointments!$M$5:$M$1204="Completed")*Appointments!$B$5:$B$1204)))) -> 0 | Z10: =IF(B10="","",IF(Y10="","",TodayDate-Y10)) -> 0 | AA10: =IF(B10="","",SUMPRODUCT(MIN((Appointments!$E$5:$E$1204=A10)*(Appointments!$M$5:$M$1204<>"Cancelled")*(Appointments!$M$5:$M$1204<>"Completed")*(Appointments!$M$5:$M$1204<>"No show")*(Appointments!$B$5:$B$1204>=TodayDate)*Appointments!$B$5:$B$1204+(1-(Appointments!$E$5:$E$1204=A10)*(Appointments!$M$5:$M$1204<>"Cancelled")*(Appointments!$M$5:$M$1204<>"Completed")*(Appointments!$M$5:$M$1204<>"No show")*(Appointments!$B$5:$B$1204>=TodayDate))*2958465))) -> 0 | AB10: =IF(B10="","",IF(AA10>=2958465,"",AA10)) -> 0 | AC10: =IF(B10="","",IF(T10<2,"",ROUND((Y10-X10)/MAX(1,T10-1),0))) -> 0 | AD10: =IF(B10="","",IF(Y10="","",Y10+IF(AC10="",RebookWeeks*7,MAX(14,AC10)))) -> 0 | AE10: =IF(B10="","",ROUND(SUMIFS(Sales!$Y$5:$Y$1204,Sales!$D$5:$D$1204,A10),2)) -> 0 | AF10: =IF(B10="","",ROUND(SUMIFS(Sales!$Y$5:$Y$1204,Sales!$D$5:$D$1204,A10,Sales!$H$5:$H$1204,"Service"),2)) -> 0 | AG10: =IF(B10="","",ROUND(SUMIFS(Sales!$Y$5:$Y$1204,Sales!$D$5:$D$1204,A10,Sales!$H$5:$H$1204,"Retail"),2)) -> 0 | AH10: =IF(B10="","",ROUND(SUMIFS(Sales!$Y$5:$Y$1204,Sales!$D$5:$D$1204,A10,Sales!$B$5:$B$1204,">="&TodayDate-365),2)) -> 0 | AI10: =IF(B10="","",IF(T10=0,"",ROUND(AE10/T10,2))) -> 0 | AJ10: =IF(B10="","",IF(AI10="","",IF(AC10="","",ROUND(AI10*(365/MAX(14,AC10)),2)))) -> 0 | AK10: =IF(B10="","",ROUND(SUMIFS(Sales!$AH$5:$AH$1204,Sales!$D$5:$D$1204,A10),2)) -> 0 | AL10: =IF(B10="","",IFERROR(INDEX(Loyalty!$P$5:$P$504,MATCH(A10,Loyalty!$B$5:$B$504,0))*1,0)) -> 0 | AM10: =IF(B10="","",IF(R10="Archived","Archived",IF(T10=0,"Not been yet",IF(Z10>=InactiveDays,"Inactive",IF(Z10>=LapsingDays,"Lapsing",IF(T10=1,"New",IF(AH10>=VipSpend,"VIP",IF(U10>=4,"Regular","Active")))))))) -> 0 | AN10: =IF(B10="","",IF(T10>=2,"Yes","No")) -> 0 | AO10: =IF(B10="","",COUNTIFS($AE$5:$AE$504,">"&AE10)+COUNTIFS($AE$5:AE10,AE10)) -> 0 | AP10: =IF(B10="","",COUNTIFS($T$5:$T$504,">"&T10)+COUNTIFS($T$5:T10,T10)) -> 0 | AQ10: =IF(B10="","",IF(COUNTIF($B$5:$B$504,B10)>1,"Duplicate - same name twice",IF(R10="Archived","",IF(AK10>0.004,"Chase - balance outstanding",IF(AM10="Inactive","Gone - win-back offer",IF(AM10="Lapsing","Chase - lapsing, call them",IF(IF(N10="",FALSE,TodayDate-N10>PatchTestDays),"Due - patch test out of date",IF(IF(AD10="",FALSE,IF(AB10<>"",FALSE,AD10<=TodayDate+14)),"Rebook - due and nothing booked",IF(IF(K10="",FALSE,ABS(DATE(YEAR(TodayDate),MONTH(K10),DAY(K10))-TodayDate)<=7),"Birthday - send the treat","OK"))))))))) -> 0
A11: =IF(B11="","",ClientPrefix&TEXT(ROW()-4,"0000")) -> 0 | J11: =IF(I11="","",IFERROR(INDEX(Staff!$B$5:$B$44,MATCH(I11,Staff!$A$5:$A$44,0)),"Not in Staff")) -> 0 | T11: =IF(B11="","",COUNTIFS(Appointments!$E$5:$E$1204,A11,Appointments!$M$5:$M$1204,"Completed")) -> 0 | U11: =IF(B11="","",COUNTIFS(Appointments!$E$5:$E$1204,A11,Appointments!$M$5:$M$1204,"Completed",Appointments!$B$5:$B$1204,">="&TodayDate-365)) -> 0 | V11: =IF(B11="","",COUNTIFS(Appointments!$E$5:$E$1204,A11,Appointments!$M$5:$M$1204,"Cancelled")) -> 0 | W11: =IF(B11="","",COUNTIFS(Appointments!$E$5:$E$1204,A11,Appointments!$M$5:$M$1204,"No show")) -> 0 | X11: =IF(B11="","",IF(F11<>"",F11,IF(T11=0,"",SUMPRODUCT(MIN((Appointments!$E$5:$E$1204=A11)*(Appointments!$M$5:$M$1204="Completed")*Appointments!$B$5:$B$1204+(1-(Appointments!$E$5:$E$1204=A11)*(Appointments!$M$5:$M$1204="Completed"))*2958465))))) -> 0 | Y11: =IF(B11="","",IF(T11=0,"",SUMPRODUCT(MAX((Appointments!$E$5:$E$1204=A11)*(Appointments!$M$5:$M$1204="Completed")*Appointments!$B$5:$B$1204)))) -> 0 | Z11: =IF(B11="","",IF(Y11="","",TodayDate-Y11)) -> 0 | AA11: =IF(B11="","",SUMPRODUCT(MIN((Appointments!$E$5:$E$1204=A11)*(Appointments!$M$5:$M$1204<>"Cancelled")*(Appointments!$M$5:$M$1204<>"Completed")*(Appointments!$M$5:$M$1204<>"No show")*(Appointments!$B$5:$B$1204>=TodayDate)*Appointments!$B$5:$B$1204+(1-(Appointments!$E$5:$E$1204=A11)*(Appointments!$M$5:$M$1204<>"Cancelled")*(Appointments!$M$5:$M$1204<>"Completed")*(Appointments!$M$5:$M$1204<>"No show")*(Appointments!$B$5:$B$1204>=TodayDate))*2958465))) -> 0 | AB11: =IF(B11="","",IF(AA11>=2958465,"",AA11)) -> 0 | AC11: =IF(B11="","",IF(T11<2,"",ROUND((Y11-X11)/MAX(1,T11-1),0))) -> 0 | AD11: =IF(B11="","",IF(Y11="","",Y11+IF(AC11="",RebookWeeks*7,MAX(14,AC11)))) -> 0 | AE11: =IF(B11="","",ROUND(SUMIFS(Sales!$Y$5:$Y$1204,Sales!$D$5:$D$1204,A11),2)) -> 0 | AF11: =IF(B11="","",ROUND(SUMIFS(Sales!$Y$5:$Y$1204,Sales!$D$5:$D$1204,A11,Sales!$H$5:$H$1204,"Service"),2)) -> 0 | AG11: =IF(B11="","",ROUND(SUMIFS(Sales!$Y$5:$Y$1204,Sales!$D$5:$D$1204,A11,Sales!$H$5:$H$1204,"Retail"),2)) -> 0 | AH11: =IF(B11="","",ROUND(SUMIFS(Sales!$Y$5:$Y$1204,Sales!$D$5:$D$1204,A11,Sales!$B$5:$B$1204,">="&TodayDate-365),2)) -> 0 | AI11: =IF(B11="","",IF(T11=0,"",ROUND(AE11/T11,2))) -> 0 | AJ11: =IF(B11="","",IF(AI11="","",IF(AC11="","",ROUND(AI11*(365/MAX(14,AC11)),2)))) -> 0 | AK11: =IF(B11="","",ROUND(SUMIFS(Sales!$AH$5:$AH$1204,Sales!$D$5:$D$1204,A11),2)) -> 0 | AL11: =IF(B11="","",IFERROR(INDEX(Loyalty!$P$5:$P$504,MATCH(A11,Loyalty!$B$5:$B$504,0))*1,0)) -> 0 | AM11: =IF(B11="","",IF(R11="Archived","Archived",IF(T11=0,"Not been yet",IF(Z11>=InactiveDays,"Inactive",IF(Z11>=LapsingDays,"Lapsing",IF(T11=1,"New",IF(AH11>=VipSpend,"VIP",IF(U11>=4,"Regular","Active")))))))) -> 0 | AN11: =IF(B11="","",IF(T11>=2,"Yes","No")) -> 0 | AO11: =IF(B11="","",COUNTIFS($AE$5:$AE$504,">"&AE11)+COUNTIFS($AE$5:AE11,AE11)) -> 0 | AP11: =IF(B11="","",COUNTIFS($T$5:$T$504,">"&T11)+COUNTIFS($T$5:T11,T11)) -> 0 | AQ11: =IF(B11="","",IF(COUNTIF($B$5:$B$504,B11)>1,"Duplicate - same name twice",IF(R11="Archived","",IF(AK11>0.004,"Chase - balance outstanding",IF(AM11="Inactive","Gone - win-back offer",IF(AM11="Lapsing","Chase - lapsing, call them",IF(IF(N11="",FALSE,TodayDate-N11>PatchTestDays),"Due - patch test out of date",IF(IF(AD11="",FALSE,IF(AB11<>"",FALSE,AD11<=TodayDate+14)),"Rebook - due and nothing booked",IF(IF(K11="",FALSE,ABS(DATE(YEAR(TodayDate),MONTH(K11),DAY(K11))-TodayDate)<=7),"Birthday - send the treat","OK"))))))))) -> 0
A12: =IF(B12="","",ClientPrefix&TEXT(ROW()-4,"0000")) -> 0 | J12: =IF(I12="","",IFERROR(INDEX(Staff!$B$5:$B$44,MATCH(I12,Staff!$A$5:$A$44,0)),"Not in Staff")) -> 0 | T12: =IF(B12="","",COUNTIFS(Appointments!$E$5:$E$1204,A12,Appointments!$M$5:$M$1204,"Completed")) -> 0 | U12: =IF(B12="","",COUNTIFS(Appointments!$E$5:$E$1204,A12,Appointments!$M$5:$M$1204,"Completed",Appointments!$B$5:$B$1204,">="&TodayDate-365)) -> 0 | V12: =IF(B12="","",COUNTIFS(Appointments!$E$5:$E$1204,A12,Appointments!$M$5:$M$1204,"Cancelled")) -> 0 | W12: =IF(B12="","",COUNTIFS(Appointments!$E$5:$E$1204,A12,Appointments!$M$5:$M$1204,"No show")) -> 0 | X12: =IF(B12="","",IF(F12<>"",F12,IF(T12=0,"",SUMPRODUCT(MIN((Appointments!$E$5:$E$1204=A12)*(Appointments!$M$5:$M$1204="Completed")*Appointments!$B$5:$B$1204+(1-(Appointments!$E$5:$E$1204=A12)*(Appointments!$M$5:$M$1204="Completed"))*2958465))))) -> 0 | Y12: =IF(B12="","",IF(T12=0,"",SUMPRODUCT(MAX((Appointments!$E$5:$E$1204=A12)*(Appointments!$M$5:$M$1204="Completed")*Appointments!$B$5:$B$1204)))) -> 0 | Z12: =IF(B12="","",IF(Y12="","",TodayDate-Y12)) -> 0 | AA12: =IF(B12="","",SUMPRODUCT(MIN((Appointments!$E$5:$E$1204=A12)*(Appointments!$M$5:$M$1204<>"Cancelled")*(Appointments!$M$5:$M$1204<>"Completed")*(Appointments!$M$5:$M$1204<>"No show")*(Appointments!$B$5:$B$1204>=TodayDate)*Appointments!$B$5:$B$1204+(1-(Appointments!$E$5:$E$1204=A12)*(Appointments!$M$5:$M$1204<>"Cancelled")*(Appointments!$M$5:$M$1204<>"Completed")*(Appointments!$M$5:$M$1204<>"No show")*(Appointments!$B$5:$B$1204>=TodayDate))*2958465))) -> 0 | AB12: =IF(B12="","",IF(AA12>=2958465,"",AA12)) -> 0 | AC12: =IF(B12="","",IF(T12<2,"",ROUND((Y12-X12)/MAX(1,T12-1),0))) -> 0 | AD12: =IF(B12="","",IF(Y12="","",Y12+IF(AC12="",RebookWeeks*7,MAX(14,AC12)))) -> 0 | AE12: =IF(B12="","",ROUND(SUMIFS(Sales!$Y$5:$Y$1204,Sales!$D$5:$D$1204,A12),2)) -> 0 | AF12: =IF(B12="","",ROUND(SUMIFS(Sales!$Y$5:$Y$1204,Sales!$D$5:$D$1204,A12,Sales!$H$5:$H$1204,"Service"),2)) -> 0 | AG12: =IF(B12="","",ROUND(SUMIFS(Sales!$Y$5:$Y$1204,Sales!$D$5:$D$1204,A12,Sales!$H$5:$H$1204,"Retail"),2)) -> 0 | AH12: =IF(B12="","",ROUND(SUMIFS(Sales!$Y$5:$Y$1204,Sales!$D$5:$D$1204,A12,Sales!$B$5:$B$1204,">="&TodayDate-365),2)) -> 0 | AI12: =IF(B12="","",IF(T12=0,"",ROUND(AE12/T12,2))) -> 0 | AJ12: =IF(B12="","",IF(AI12="","",IF(AC12="","",ROUND(AI12*(365/MAX(14,AC12)),2)))) -> 0 | AK12: =IF(B12="","",ROUND(SUMIFS(Sales!$AH$5:$AH$1204,Sales!$D$5:$D$1204,A12),2)) -> 0 | AL12: =IF(B12="","",IFERROR(INDEX(Loyalty!$P$5:$P$504,MATCH(A12,Loyalty!$B$5:$B$504,0))*1,0)) -> 0 | AM12: =IF(B12="","",IF(R12="Archived","Archived",IF(T12=0,"Not been yet",IF(Z12>=InactiveDays,"Inactive",IF(Z12>=LapsingDays,"Lapsing",IF(T12=1,"New",IF(AH12>=VipSpend,"VIP",IF(U12>=4,"Regular","Active")))))))) -> 0 | AN12: =IF(B12="","",IF(T12>=2,"Yes","No")) -> 0 | AO12: =IF(B12="","",COUNTIFS($AE$5:$AE$504,">"&AE12)+COUNTIFS($AE$5:AE12,AE12)) -> 0 | AP12: =IF(B12="","",COUNTIFS($T$5:$T$504,">"&T12)+COUNTIFS($T$5:T12,T12)) -> 0 | AQ12: =IF(B12="","",IF(COUNTIF($B$5:$B$504,B12)>1,"Duplicate - same name twice",IF(R12="Archived","",IF(AK12>0.004,"Chase - balance outstanding",IF(AM12="Inactive","Gone - win-back offer",IF(AM12="Lapsing","Chase - lapsing, call them",IF(IF(N12="",FALSE,TodayDate-N12>PatchTestDays),"Due - patch test out of date",IF(IF(AD12="",FALSE,IF(AB12<>"",FALSE,AD12<=TodayDate+14)),"Rebook - due and nothing booked",IF(IF(K12="",FALSE,ABS(DATE(YEAR(TodayDate),MONTH(K12),DAY(K12))-TodayDate)<=7),"Birthday - send the treat","OK"))))))))) -> 0
A13: =IF(B13="","",ClientPrefix&TEXT(ROW()-4,"0000")) -> 0 | J13: =IF(I13="","",IFERROR(INDEX(Staff!$B$5:$B$44,MATCH(I13,Staff!$A$5:$A$44,0)),"Not in Staff")) -> 0 | T13: =IF(B13="","",COUNTIFS(Appointments!$E$5:$E$1204,A13,Appointments!$M$5:$M$1204,"Completed")) -> 0 | U13: =IF(B13="","",COUNTIFS(Appointments!$E$5:$E$1204,A13,Appointments!$M$5:$M$1204,"Completed",Appointments!$B$5:$B$1204,">="&TodayDate-365)) -> 0 | V13: =IF(B13="","",COUNTIFS(Appointments!$E$5:$E$1204,A13,Appointments!$M$5:$M$1204,"Cancelled")) -> 0 | W13: =IF(B13="","",COUNTIFS(Appointments!$E$5:$E$1204,A13,Appointments!$M$5:$M$1204,"No show")) -> 0 | X13: =IF(B13="","",IF(F13<>"",F13,IF(T13=0,"",SUMPRODUCT(MIN((Appointments!$E$5:$E$1204=A13)*(Appointments!$M$5:$M$1204="Completed")*Appointments!$B$5:$B$1204+(1-(Appointments!$E$5:$E$1204=A13)*(Appointments!$M$5:$M$1204="Completed"))*2958465))))) -> 0 | Y13: =IF(B13="","",IF(T13=0,"",SUMPRODUCT(MAX((Appointments!$E$5:$E$1204=A13)*(Appointments!$M$5:$M$1204="Completed")*Appointments!$B$5:$B$1204)))) -> 0 | Z13: =IF(B13="","",IF(Y13="","",TodayDate-Y13)) -> 0 | AA13: =IF(B13="","",SUMPRODUCT(MIN((Appointments!$E$5:$E$1204=A13)*(Appointments!$M$5:$M$1204<>"Cancelled")*(Appointments!$M$5:$M$1204<>"Completed")*(Appointments!$M$5:$M$1204<>"No show")*(Appointments!$B$5:$B$1204>=TodayDate)*Appointments!$B$5:$B$1204+(1-(Appointments!$E$5:$E$1204=A13)*(Appointments!$M$5:$M$1204<>"Cancelled")*(Appointments!$M$5:$M$1204<>"Completed")*(Appointments!$M$5:$M$1204<>"No show")*(Appointments!$B$5:$B$1204>=TodayDate))*2958465))) -> 0 | AB13: =IF(B13="","",IF(AA13>=2958465,"",AA13)) -> 0 | AC13: =IF(B13="","",IF(T13<2,"",ROUND((Y13-X13)/MAX(1,T13-1),0))) -> 0 | AD13: =IF(B13="","",IF(Y13="","",Y13+IF(AC13="",RebookWeeks*7,MAX(14,AC13)))) -> 0 | AE13: =IF(B13="","",ROUND(SUMIFS(Sales!$Y$5:$Y$1204,Sales!$D$5:$D$1204,A13),2)) -> 0 | AF13: =IF(B13="","",ROUND(SUMIFS(Sales!$Y$5:$Y$1204,Sales!$D$5:$D$1204,A13,Sales!$H$5:$H$1204,"Service"),2)) -> 0 | AG13: =IF(B13="","",ROUND(SUMIFS(Sales!$Y$5:$Y$1204,Sales!$D$5:$D$1204,A13,Sales!$H$5:$H$1204,"Retail"),2)) -> 0 | AH13: =IF(B13="","",ROUND(SUMIFS(Sales!$Y$5:$Y$1204,Sales!$D$5:$D$1204,A13,Sales!$B$5:$B$1204,">="&TodayDate-365),2)) -> 0 | AI13: =IF(B13="","",IF(T13=0,"",ROUND(AE13/T13,2))) -> 0 | AJ13: =IF(B13="","",IF(AI13="","",IF(AC13="","",ROUND(AI13*(365/MAX(14,AC13)),2)))) -> 0 | AK13: =IF(B13="","",ROUND(SUMIFS(Sales!$AH$5:$AH$1204,Sales!$D$5:$D$1204,A13),2)) -> 0 | AL13: =IF(B13="","",IFERROR(INDEX(Loyalty!$P$5:$P$504,MATCH(A13,Loyalty!$B$5:$B$504,0))*1,0)) -> 0 | AM13: =IF(B13="","",IF(R13="Archived","Archived",IF(T13=0,"Not been yet",IF(Z13>=InactiveDays,"Inactive",IF(Z13>=LapsingDays,"Lapsing",IF(T13=1,"New",IF(AH13>=VipSpend,"VIP",IF(U13>=4,"Regular","Active")))))))) -> 0 | AN13: =IF(B13="","",IF(T13>=2,"Yes","No")) -> 0 | AO13: =IF(B13="","",COUNTIFS($AE$5:$AE$504,">"&AE13)+COUNTIFS($AE$5:AE13,AE13)) -> 0 | AP13: =IF(B13="","",COUNTIFS($T$5:$T$504,">"&T13)+COUNTIFS($T$5:T13,T13)) -> 0 | AQ13: =IF(B13="","",IF(COUNTIF($B$5:$B$504,B13)>1,"Duplicate - same name twice",IF(R13="Archived","",IF(AK13>0.004,"Chase - balance outstanding",IF(AM13="Inactive","Gone - win-back offer",IF(AM13="Lapsing","Chase - lapsing, call them",IF(IF(N13="",FALSE,TodayDate-N13>PatchTestDays),"Due - patch test out of date",IF(IF(AD13="",FALSE,IF(AB13<>"",FALSE,AD13<=TodayDate+14)),"Rebook - due and nothing booked",IF(IF(K13="",FALSE,ABS(DATE(YEAR(TodayDate),MONTH(K13),DAY(K13))-TodayDate)<=7),"Birthday - send the treat","OK"))))))))) -> 0
A14: =IF(B14="","",ClientPrefix&TEXT(ROW()-4,"0000")) -> 0 | J14: =IF(I14="","",IFERROR(INDEX(Staff!$B$5:$B$44,MATCH(I14,Staff!$A$5:$A$44,0)),"Not in Staff")) -> 0 | T14: =IF(B14="","",COUNTIFS(Appointments!$E$5:$E$1204,A14,Appointments!$M$5:$M$1204,"Completed")) -> 0 | U14: =IF(B14="","",COUNTIFS(Appointments!$E$5:$E$1204,A14,Appointments!$M$5:$M$1204,"Completed",Appointments!$B$5:$B$1204,">="&TodayDate-365)) -> 0 | V14: =IF(B14="","",COUNTIFS(Appointments!$E$5:$E$1204,A14,Appointments!$M$5:$M$1204,"Cancelled")) -> 0 | W14: =IF(B14="","",COUNTIFS(Appointments!$E$5:$E$1204,A14,Appointments!$M$5:$M$1204,"No show")) -> 0 | X14: =IF(B14="","",IF(F14<>"",F14,IF(T14=0,"",SUMPRODUCT(MIN((Appointments!$E$5:$E$1204=A14)*(Appointments!$M$5:$M$1204="Completed")*Appointments!$B$5:$B$1204+(1-(Appointments!$E$5:$E$1204=A14)*(Appointments!$M$5:$M$1204="Completed"))*2958465))))) -> 0 | Y14: =IF(B14="","",IF(T14=0,"",SUMPRODUCT(MAX((Appointments!$E$5:$E$1204=A14)*(Appointments!$M$5:$M$1204="Completed")*Appointments!$B$5:$B$1204)))) -> 0 | Z14: =IF(B14="","",IF(Y14="","",TodayDate-Y14)) -> 0 | AA14: =IF(B14="","",SUMPRODUCT(MIN((Appointments!$E$5:$E$1204=A14)*(Appointments!$M$5:$M$1204<>"Cancelled")*(Appointments!$M$5:$M$1204<>"Completed")*(Appointments!$M$5:$M$1204<>"No show")*(Appointments!$B$5:$B$1204>=TodayDate)*Appointments!$B$5:$B$1204+(1-(Appointments!$E$5:$E$1204=A14)*(Appointments!$M$5:$M$1204<>"Cancelled")*(Appointments!$M$5:$M$1204<>"Completed")*(Appointments!$M$5:$M$1204<>"No show")*(Appointments!$B$5:$B$1204>=TodayDate))*2958465))) -> 0 | AB14: =IF(B14="","",IF(AA14>=2958465,"",AA14)) -> 0 | AC14: =IF(B14="","",IF(T14<2,"",ROUND((Y14-X14)/MAX(1,T14-1),0))) -> 0 | AD14: =IF(B14="","",IF(Y14="","",Y14+IF(AC14="",RebookWeeks*7,MAX(14,AC14)))) -> 0 | AE14: =IF(B14="","",ROUND(SUMIFS(Sales!$Y$5:$Y$1204,Sales!$D$5:$D$1204,A14),2)) -> 0 | AF14: =IF(B14="","",ROUND(SUMIFS(Sales!$Y$5:$Y$1204,Sales!$D$5:$D$1204,A14,Sales!$H$5:$H$1204,"Service"),2)) -> 0 | AG14: =IF(B14="","",ROUND(SUMIFS(Sales!$Y$5:$Y$1204,Sales!$D$5:$D$1204,A14,Sales!$H$5:$H$1204,"Retail"),2)) -> 0 | AH14: =IF(B14="","",ROUND(SUMIFS(Sales!$Y$5:$Y$1204,Sales!$D$5:$D$1204,A14,Sales!$B$5:$B$1204,">="&TodayDate-365),2)) -> 0 | AI14: =IF(B14="","",IF(T14=0,"",ROUND(AE14/T14,2))) -> 0 | AJ14: =IF(B14="","",IF(AI14="","",IF(AC14="","",ROUND(AI14*(365/MAX(14,AC14)),2)))) -> 0 | AK14: =IF(B14="","",ROUND(SUMIFS(Sales!$AH$5:$AH$1204,Sales!$D$5:$D$1204,A14),2)) -> 0 | AL14: =IF(B14="","",IFERROR(INDEX(Loyalty!$P$5:$P$504,MATCH(A14,Loyalty!$B$5:$B$504,0))*1,0)) -> 0 | AM14: =IF(B14="","",IF(R14="Archived","Archived",IF(T14=0,"Not been yet",IF(Z14>=InactiveDays,"Inactive",IF(Z14>=LapsingDays,"Lapsing",IF(T14=1,"New",IF(AH14>=VipSpend,"VIP",IF(U14>=4,"Regular","Active")))))))) -> 0 | AN14: =IF(B14="","",IF(T14>=2,"Yes","No")) -> 0 | AO14: =IF(B14="","",COUNTIFS($AE$5:$AE$504,">"&AE14)+COUNTIFS($AE$5:AE14,AE14)) -> 0 | AP14: =IF(B14="","",COUNTIFS($T$5:$T$504,">"&T14)+COUNTIFS($T$5:T14,T14)) -> 0 | AQ14: =IF(B14="","",IF(COUNTIF($B$5:$B$504,B14)>1,"Duplicate - same name twice",IF(R14="Archived","",IF(AK14>0.004,"Chase - balance outstanding",IF(AM14="Inactive","Gone - win-back offer",IF(AM14="Lapsing","Chase - lapsing, call them",IF(IF(N14="",FALSE,TodayDate-N14>PatchTestDays),"Due - patch test out of date",IF(IF(AD14="",FALSE,IF(AB14<>"",FALSE,AD14<=TodayDate+14)),"Rebook - due and nothing booked",IF(IF(K14="",FALSE,ABS(DATE(YEAR(TodayDate),MONTH(K14),DAY(K14))-TodayDate)<=7),"Birthday - send the treat","OK"))))))))) -> 0
A15: =IF(B15="","",ClientPrefix&TEXT(ROW()-4,"0000")) -> 0 | J15: =IF(I15="","",IFERROR(INDEX(Staff!$B$5:$B$44,MATCH(I15,Staff!$A$5:$A$44,0)),"Not in Staff")) -> 0 | T15: =IF(B15="","",COUNTIFS(Appointments!$E$5:$E$1204,A15,Appointments!$M$5:$M$1204,"Completed")) -> 0 | U15: =IF(B15="","",COUNTIFS(Appointments!$E$5:$E$1204,A15,Appointments!$M$5:$M$1204,"Completed",Appointments!$B$5:$B$1204,">="&TodayDate-365)) -> 0 | V15: =IF(B15="","",COUNTIFS(Appointments!$E$5:$E$1204,A15,Appointments!$M$5:$M$1204,"Cancelled")) -> 0 | W15: =IF(B15="","",COUNTIFS(Appointments!$E$5:$E$1204,A15,Appointments!$M$5:$M$1204,"No show")) -> 0 | X15: =IF(B15="","",IF(F15<>"",F15,IF(T15=0,"",SUMPRODUCT(MIN((Appointments!$E$5:$E$1204=A15)*(Appointments!$M$5:$M$1204="Completed")*Appointments!$B$5:$B$1204+(1-(Appointments!$E$5:$E$1204=A15)*(Appointments!$M$5:$M$1204="Completed"))*2958465))))) -> 0 | Y15: =IF(B15="","",IF(T15=0,"",SUMPRODUCT(MAX((Appointments!$E$5:$E$1204=A15)*(Appointments!$M$5:$M$1204="Completed")*Appointments!$B$5:$B$1204)))) -> 0 | Z15: =IF(B15="","",IF(Y15="","",TodayDate-Y15)) -> 0 | AA15: =IF(B15="","",SUMPRODUCT(MIN((Appointments!$E$5:$E$1204=A15)*(Appointments!$M$5:$M$1204<>"Cancelled")*(Appointments!$M$5:$M$1204<>"Completed")*(Appointments!$M$5:$M$1204<>"No show")*(Appointments!$B$5:$B$1204>=TodayDate)*Appointments!$B$5:$B$1204+(1-(Appointments!$E$5:$E$1204=A15)*(Appointments!$M$5:$M$1204<>"Cancelled")*(Appointments!$M$5:$M$1204<>"Completed")*(Appointments!$M$5:$M$1204<>"No show")*(Appointments!$B$5:$B$1204>=TodayDate))*2958465))) -> 0 | AB15: =IF(B15="","",IF(AA15>=2958465,"",AA15)) -> 0 | AC15: =IF(B15="","",IF(T15<2,"",ROUND((Y15-X15)/MAX(1,T15-1),0))) -> 0 | AD15: =IF(B15="","",IF(Y15="","",Y15+IF(AC15="",RebookWeeks*7,MAX(14,AC15)))) -> 0 | AE15: =IF(B15="","",ROUND(SUMIFS(Sales!$Y$5:$Y$1204,Sales!$D$5:$D$1204,A15),2)) -> 0 | AF15: =IF(B15="","",ROUND(SUMIFS(Sales!$Y$5:$Y$1204,Sales!$D$5:$D$1204,A15,Sales!$H$5:$H$1204,"Service"),2)) -> 0 | AG15: =IF(B15="","",ROUND(SUMIFS(Sales!$Y$5:$Y$1204,Sales!$D$5:$D$1204,A15,Sales!$H$5:$H$1204,"Retail"),2)) -> 0 | AH15: =IF(B15="","",ROUND(SUMIFS(Sales!$Y$5:$Y$1204,Sales!$D$5:$D$1204,A15,Sales!$B$5:$B$1204,">="&TodayDate-365),2)) -> 0 | AI15: =IF(B15="","",IF(T15=0,"",ROUND(AE15/T15,2))) -> 0 | AJ15: =IF(B15="","",IF(AI15="","",IF(AC15="","",ROUND(AI15*(365/MAX(14,AC15)),2)))) -> 0 | AK15: =IF(B15="","",ROUND(SUMIFS(Sales!$AH$5:$AH$1204,Sales!$D$5:$D$1204,A15),2)) -> 0 | AL15: =IF(B15="","",IFERROR(INDEX(Loyalty!$P$5:$P$504,MATCH(A15,Loyalty!$B$5:$B$504,0))*1,0)) -> 0 | AM15: =IF(B15="","",IF(R15="Archived","Archived",IF(T15=0,"Not been yet",IF(Z15>=InactiveDays,"Inactive",IF(Z15>=LapsingDays,"Lapsing",IF(T15=1,"New",IF(AH15>=VipSpend,"VIP",IF(U15>=4,"Regular","Active")))))))) -> 0 | AN15: =IF(B15="","",IF(T15>=2,"Yes","No")) -> 0 | AO15: =IF(B15="","",COUNTIFS($AE$5:$AE$504,">"&AE15)+COUNTIFS($AE$5:AE15,AE15)) -> 0 | AP15: =IF(B15="","",COUNTIFS($T$5:$T$504,">"&T15)+COUNTIFS($T$5:T15,T15)) -> 0 | AQ15: =IF(B15="","",IF(COUNTIF($B$5:$B$504,B15)>1,"Duplicate - same name twice",IF(R15="Archived","",IF(AK15>0.004,"Chase - balance outstanding",IF(AM15="Inactive","Gone - win-back offer",IF(AM15="Lapsing","Chase - lapsing, call them",IF(IF(N15="",FALSE,TodayDate-N15>PatchTestDays),"Due - patch test out of date",IF(IF(AD15="",FALSE,IF(AB15<>"",FALSE,AD15<=TodayDate+14)),"Rebook - due and nothing booked",IF(IF(K15="",FALSE,ABS(DATE(YEAR(TodayDate),MONTH(K15),DAY(K15))-TodayDate)<=7),"Birthday - send the treat","OK"))))))))) -> 0
A16: =IF(B16="","",ClientPrefix&TEXT(ROW()-4,"0000")) -> 0 | J16: =IF(I16="","",IFERROR(INDEX(Staff!$B$5:$B$44,MATCH(I16,Staff!$A$5:$A$44,0)),"Not in Staff")) -> 0 | T16: =IF(B16="","",COUNTIFS(Appointments!$E$5:$E$1204,A16,Appointments!$M$5:$M$1204,"Completed")) -> 0 | U16: =IF(B16="","",COUNTIFS(Appointments!$E$5:$E$1204,A16,Appointments!$M$5:$M$1204,"Completed",Appointments!$B$5:$B$1204,">="&TodayDate-365)) -> 0 | V16: =IF(B16="","",COUNTIFS(Appointments!$E$5:$E$1204,A16,Appointments!$M$5:$M$1204,"Cancelled")) -> 0 | W16: =IF(B16="","",COUNTIFS(Appointments!$E$5:$E$1204,A16,Appointments!$M$5:$M$1204,"No show")) -> 0 | X16: =IF(B16="","",IF(F16<>"",F16,IF(T16=0,"",SUMPRODUCT(MIN((Appointments!$E$5:$E$1204=A16)*(Appointments!$M$5:$M$1204="Completed")*Appointments!$B$5:$B$1204+(1-(Appointments!$E$5:$E$1204=A16)*(Appointments!$M$5:$M$1204="Completed"))*2958465))))) -> 0 | Y16: =IF(B16="","",IF(T16=0,"",SUMPRODUCT(MAX((Appointments!$E$5:$E$1204=A16)*(Appointments!$M$5:$M$1204="Completed")*Appointments!$B$5:$B$1204)))) -> 0 | Z16: =IF(B16="","",IF(Y16="","",TodayDate-Y16)) -> 0 | AA16: =IF(B16="","",SUMPRODUCT(MIN((Appointments!$E$5:$E$1204=A16)*(Appointments!$M$5:$M$1204<>"Cancelled")*(Appointments!$M$5:$M$1204<>"Completed")*(Appointments!$M$5:$M$1204<>"No show")*(Appointments!$B$5:$B$1204>=TodayDate)*Appointments!$B$5:$B$1204+(1-(Appointments!$E$5:$E$1204=A16)*(Appointments!$M$5:$M$1204<>"Cancelled")*(Appointments!$M$5:$M$1204<>"Completed")*(Appointments!$M$5:$M$1204<>"No show")*(Appointments!$B$5:$B$1204>=TodayDate))*2958465))) -> 0 | AB16: =IF(B16="","",IF(AA16>=2958465,"",AA16)) -> 0 | AC16: =IF(B16="","",IF(T16<2,"",ROUND((Y16-X16)/MAX(1,T16-1),0))) -> 0 | AD16: =IF(B16="","",IF(Y16="","",Y16+IF(AC16="",RebookWeeks*7,MAX(14,AC16)))) -> 0 | AE16: =IF(B16="","",ROUND(SUMIFS(Sales!$Y$5:$Y$1204,Sales!$D$5:$D$1204,A16),2)) -> 0 | AF16: =IF(B16="","",ROUND(SUMIFS(Sales!$Y$5:$Y$1204,Sales!$D$5:$D$1204,A16,Sales!$H$5:$H$1204,"Service"),2)) -> 0 | AG16: =IF(B16="","",ROUND(SUMIFS(Sales!$Y$5:$Y$1204,Sales!$D$5:$D$1204,A16,Sales!$H$5:$H$1204,"Retail"),2)) -> 0 | AH16: =IF(B16="","",ROUND(SUMIFS(Sales!$Y$5:$Y$1204,Sales!$D$5:$D$1204,A16,Sales!$B$5:$B$1204,">="&TodayDate-365),2)) -> 0 | AI16: =IF(B16="","",IF(T16=0,"",ROUND(AE16/T16,2))) -> 0 | AJ16: =IF(B16="","",IF(AI16="","",IF(AC16="","",ROUND(AI16*(365/MAX(14,AC16)),2)))) -> 0 | AK16: =IF(B16="","",ROUND(SUMIFS(Sales!$AH$5:$AH$1204,Sales!$D$5:$D$1204,A16),2)) -> 0 | AL16: =IF(B16="","",IFERROR(INDEX(Loyalty!$P$5:$P$504,MATCH(A16,Loyalty!$B$5:$B$504,0))*1,0)) -> 0 | AM16: =IF(B16="","",IF(R16="Archived","Archived",IF(T16=0,"Not been yet",IF(Z16>=InactiveDays,"Inactive",IF(Z16>=LapsingDays,"Lapsing",IF(T16=1,"New",IF(AH16>=VipSpend,"VIP",IF(U16>=4,"Regular","Active")))))))) -> 0 | AN16: =IF(B16="","",IF(T16>=2,"Yes","No")) -> 0 | AO16: =IF(B16="","",COUNTIFS($AE$5:$AE$504,">"&AE16)+COUNTIFS($AE$5:AE16,AE16)) -> 0 | AP16: =IF(B16="","",COUNTIFS($T$5:$T$504,">"&T16)+COUNTIFS($T$5:T16,T16)) -> 0 | AQ16: =IF(B16="","",IF(COUNTIF($B$5:$B$504,B16)>1,"Duplicate - same name twice",IF(R16="Archived","",IF(AK16>0.004,"Chase - balance outstanding",IF(AM16="Inactive","Gone - win-back offer",IF(AM16="Lapsing","Chase - lapsing, call them",IF(IF(N16="",FALSE,TodayDate-N16>PatchTestDays),"Due - patch test out of date",IF(IF(AD16="",FALSE,IF(AB16<>"",FALSE,AD16<=TodayDate+14)),"Rebook - due and nothing booked",IF(IF(K16="",FALSE,ABS(DATE(YEAR(TodayDate),MONTH(K16),DAY(K16))-TodayDate)<=7),"Birthday - send the treat","OK"))))))))) -> 0
... A504: =IF(B504="","",ClientPrefix&TEXT(ROW()-4,"0000")) -> 0 | J504: =IF(I504="","",IFERROR(INDEX(Staff!$B$5:$B$44,MATCH(I504,Staff!$A$5:$A$44,0)),"Not in Staff")) -> 0 | T504: =IF(B504="","",COUNTIFS(Appointments!$E$5:$E$1204,A504,Appointments!$M$5:$M$1204,"Completed")) -> 0 | U504: =IF(B504="","",COUNTIFS(Appointments!$E$5:$E$1204,A504,Appointments!$M$5:$M$1204,"Completed",Appointments!$B$5:$B$1204,">="&TodayDate-365)) -> 0 | V504: =IF(B504="","",COUNTIFS(Appointments!$E$5:$E$1204,A504,Appointments!$M$5:$M$1204,"Cancelled")) -> 0 | W504: =IF(B504="","",COUNTIFS(Appointments!$E$5:$E$1204,A504,Appointments!$M$5:$M$1204,"No show")) -> 0 | X504: =IF(B504="","",IF(F504<>"",F504,IF(T504=0,"",SUMPRODUCT(MIN((Appointments!$E$5:$E$1204=A504)*(Appointments!$M$5:$M$1204="Completed")*Appointments!$B$5:$B$1204+(1-(Appointments!$E$5:$E$1204=A504)*(Appointments!$M$5:$M$1204="Completed"))*2958465))))) -> 0 | Y504: =IF(B504="","",IF(T504=0,"",SUMPRODUCT(MAX((Appointments!$E$5:$E$1204=A504)*(Appointments!$M$5:$M$1204="Completed")*Appointments!$B$5:$B$1204)))) -> 0 | Z504: =IF(B504="","",IF(Y504="","",TodayDate-Y504)) -> 0 | AA504: =IF(B504="","",SUMPRODUCT(MIN((Appointments!$E$5:$E$1204=A504)*(Appointments!$M$5:$M$1204<>"Cancelled")*(Appointments!$M$5:$M$1204<>"Completed")*(Appointments!$M$5:$M$1204<>"No show")*(Appointments!$B$5:$B$1204>=TodayDate)*Appointments!$B$5:$B$1204+(1-(Appointments!$E$5:$E$1204=A504)*(Appointments!$M$5:$M$1204<>"Cancelled")*(Appointments!$M$5:$M$1204<>"Completed")*(Appointments!$M$5:$M$1204<>"No show")*(Appointments!$B$5:$B$1204>=TodayDate))*2958465))) -> 0 | AB504: =IF(B504="","",IF(AA504>=2958465,"",AA504)) -> 0 | AC504: =IF(B504="","",IF(T504<2,"",ROUND((Y504-X504)/MAX(1,T504-1),0))) -> 0 | AD504: =IF(B504="","",IF(Y504="","",Y504+IF(AC504="",RebookWeeks*7,MAX(14,AC504)))) -> 0 | AE504: =IF(B504="","",ROUND(SUMIFS(Sales!$Y$5:$Y$1204,Sales!$D$5:$D$1204,A504),2)) -> 0 | AF504: =IF(B504="","",ROUND(SUMIFS(Sales!$Y$5:$Y$1204,Sales!$D$5:$D$1204,A504,Sales!$H$5:$H$1204,"Service"),2)) -> 0 | AG504: =IF(B504="","",ROUND(SUMIFS(Sales!$Y$5:$Y$1204,Sales!$D$5:$D$1204,A504,Sales!$H$5:$H$1204,"Retail"),2)) -> 0 | AH504: =IF(B504="","",ROUND(SUMIFS(Sales!$Y$5:$Y$1204,Sales!$D$5:$D$1204,A504,Sales!$B$5:$B$1204,">="&TodayDate-365),2)) -> 0 | AI504: =IF(B504="","",IF(T504=0,"",ROUND(AE504/T504,2))) -> 0 | AJ504: =IF(B504="","",IF(AI504="","",IF(AC504="","",ROUND(AI504*(365/MAX(14,AC504)),2)))) -> 0 | AK504: =IF(B504="","",ROUND(SUMIFS(Sales!$AH$5:$AH$1204,Sales!$D$5:$D$1204,A504),2)) -> 0 | AL504: =IF(B504="","",IFERROR(INDEX(Loyalty!$P$5:$P$504,MATCH(A504,Loyalty!$B$5:$B$504,0))*1,0)) -> 0 | AM504: =IF(B504="","",IF(R504="Archived","Archived",IF(T504=0,"Not been yet",IF(Z504>=InactiveDays,"Inactive",IF(Z504>=LapsingDays,"Lapsing",IF(T504=1,"New",IF(AH504>=VipSpend,"VIP",IF(U504>=4,"Regular","Active")))))))) -> 0 | AN504: =IF(B504="","",IF(T504>=2,"Yes","No")) -> 0 | AO504: =IF(B504="","",COUNTIFS($AE$5:$AE$504,">"&AE504)+COUNTIFS($AE$5:AE504,AE504)) -> 0 | AP504: =IF(B504="","",COUNTIFS($T$5:$T$504,">"&T504)+COUNTIFS($T$5:T504,T504)) -> 0 | AQ504: =IF(B504="","",IF(COUNTIF($B$5:$B$504,B504)>1,"Duplicate - same name twice",IF(R504="Archived","",IF(AK504>0.004,"Chase - balance outstanding",IF(AM504="Inactive","Gone - win-back offer",IF(AM504="Lapsing","Chase - lapsing, call them",IF(IF(N504="",FALSE,TodayDate-N504>PatchTestDays),"Due - patch test out of date",IF(IF(AD504="",FALSE,IF(AB504<>"",FALSE,AD504<=TodayDate+14)),"Rebook - due and nothing booked",IF(IF(K504="",FALSE,ABS(DATE(YEAR(TodayDate),MONTH(K504),DAY(K504))-TodayDate)<=7),"Birthday - send the treat","OK"))))))))) -> 0
A506: The client book
A507: Clients on file | B507: Active | C507: New this year | D507: Lapsing | E507: Inactive | F507: Average lifetime spend | G507: Average visits | H507: Owing you money | I507: Marketing opt-ins
A508: =COUNTIF(Clients!$B$5:$B$504,"<>") -> 0 | B508: =COUNTIFS(Clients!$AM$5:$AM$504,"Active")+COUNTIFS(Clients!$AM$5:$AM$504,"Regular")+COUNTIFS(Clients!$AM$5:$AM$504,"VIP")+COUNTIFS(Clients!$AM$5:$AM$504,"New") -> 0 | C508: =COUNTIFS(Clients!$X$5:$X$504,">="&TodayDate-365) -> 0 | D508: =COUNTIFS(Clients!$AM$5:$AM$504,"Lapsing") -> 0 | E508: =COUNTIFS(Clients!$AM$5:$AM$504,"Inactive") -> 0 | F508: =IFERROR(ROUND(SUM(Clients!$AE$5:$AE$504)/MAX(1,COUNTIF(Clients!$B$5:$B$504,"<>")),2),0) -> 0 | G508: =IFERROR(ROUND(SUM(Clients!$T$5:$T$504)/MAX(1,COUNTIF(Clients!$B$5:$B$504,"<>")),1),0) -> 0 | H508: =COUNTIFS(Clients!$AK$5:$AK$504,">0.004") -> 0 | I508: =COUNTIFS(Clients!$O$5:$O$504,"Yes") -> 0

Sheet Services
A1: Services & Pricing | AK1: Novality Store | v1.0.0
A2: The menu, the chair time, the product cost and what each treatment actually earns an hour.
A3: > Start Here | C3: > Dashboard | E3: > Diary | G3: > Clients | I3: > Services | K3: > Sales | M3: > Staff | O3: > Profit | Q3: > Settings | S3: Price, minutes and product cost are the three things to get right. Everything to the right of them is worked out for you.
A4: ID | B4: Service | C4: Category | D4: Description | E4: Minutes | F4: Turnaround | G4: Price | H4: Product cost | I4: Add-on? | J4: Pays commission? | K4: Bookable online? | L4: Stylist level | M4: Status | N4: Price set on | O4: Notes | P4: Chair hours | Q4: Product cost used | R4: Commission | S4: Direct cost | T4: Gross profit | U4: Margin | V4: Price an hour | W4: Profit an hour | X4: Suggested, raw | Y4: Suggested price | Z4: Price gap | AA4: Booked | AB4: Completed | AC4: Sold | AD4: Revenue | AE4: Share of sales | AF4: Profit earned | AG4: Chair hours used | AH4: Retail attached | AI4: Last done | AJ4: Revenue rank | AK4: Rate rank | AL4: Popularity | AM4: Action
A5: =IF(B5="","",ServicePrefix&TEXT(ROW()-4,"000")) -> 0 | P5: =IF(B5="","",ROUND((IF(E5="",0,E5)+IF(F5="",0,F5))/60,3)) -> 0 | Q5: =IF(B5="","",IF(H5<>"",H5,IF(G5="",0,ROUND(G5*ProductCostPercent,2)))) -> 0 | R5: =IF(B5="","",IF(J5="No",0,IF(G5="",0,ROUND(G5*ServiceCommission,2)))) -> 0 | S5: =IF(B5="","",ROUND(Q5+R5,2)) -> 0 | T5: =IF(B5="","",IF(G5="","",ROUND(G5-S5,2))) -> 0 | U5: =IF(B5="","",IF(G5="","",IF(G5=0,"",T5/G5))) -> 0 | V5: =IF(B5="","",IF(G5="","",IF(P5=0,"",ROUND(G5/P5,2)))) -> 0 | W5: =IF(B5="","",IF(T5="","",IF(P5=0,"",ROUND(T5/P5,2)))) -> 0 | X5: =IF(B5="","",IF(P5=0,"",IF(ServiceCommission>=1,"",(Q5+TargetChairRate*P5)/IF(J5="No",1,1-ServiceCommission)))) -> 0 | Y5: =IF(B5="","",IF(X5="","",ROUND(IF(RoundingRule="None",X5,IF(RoundingRule="Nearest 0.99",MAX(0.99,CEILING(X5,1)-0.01),IF(RoundingRule="Nearest 0.95",MAX(0.95,CEILING(X5,1)-0.05),IF(RoundingRule="Nearest 0.50",CEILING(X5,0.5),IF(RoundingRule="Nearest 1",CEILING(X5,1),IF(RoundingRule="Nearest 5",CEILING(X5,5),IF(RoundingRule="Up to whole 1",CEILING(X5,1),IF(RoundingRule="Up to whole 5",CEILING(X5,5),ROUND(X5,2))))))))),2))) -> 0 | Z5: =IF(B5="","",IF(Y5="","",IF(G5="","",ROUND(G5-Y5,2)))) -> 0 | AA5: =IF(B5="","",COUNTIFS(Appointments!$G$5:$G$1204,A5)) -> 0 | AB5: =IF(B5="","",COUNTIFS(Appointments!$G$5:$G$1204,A5,Appointments!$M$5:$M$1204,"Completed")) -> 0 | AC5: =IF(B5="","",SUMIFS(Sales!$K$5:$K$1204,Sales!$I$5:$I$1204,A5,Sales!$H$5:$H$1204,"Service")) -> 0 | AD5: =IF(B5="","",ROUND(SUMIFS(Sales!$Y$5:$Y$1204,Sales!$I$5:$I$1204,A5,Sales!$H$5:$H$1204,"Service"),2)) -> 0 | AE5: =IF(B5="","",IF(ServiceRevenueAll=0,"",AD5/ServiceRevenueAll)) -> 0 | AF5: =IF(B5="","",ROUND(AC5*T5,2)) -> 0 | AG5: =IF(B5="","",ROUND(AC5*P5,1)) -> 0 | AH5: =IF(B5="","",IF(AB5=0,"",COUNTIFS(Sales!$I$5:$I$1204,A5,Sales!$AJ$5:$AJ$1204,"Yes")/AB5)) -> 0 | AI5: =IF(B5="","",IFERROR(IF(COUNTIFS(Appointments!$G$5:$G$1204,A5)=0,"",SUMPRODUCT(MAX((Appointments!$G$5:$G$1204=A5)*IFERROR(Appointments!$B$5:$B$1204*1,0)))),"")) -> 0 | AJ5: =IF(B5="","",COUNTIFS($AD$5:$AD$204,">"&AD5)+COUNTIFS($AD$5:AD5,AD5)) -> 0 | AK5: =IF(B5="","",COUNTIFS($W$5:$W$204,">"&W5)+COUNTIFS($W$5:W5,W5)) -> 0 | AL5: =IF(B5="","",COUNTIFS($AB$5:$AB$204,">"&AB5)+COUNTIFS($AB$5:AB5,AB5)) -> 0 | AM5: =IF(B5="","",IF(G5="","Add - no price yet",IF(E5="","Add - how long does it take?",IF(T5<0,"Loss - this service costs you money",IF(V5<TargetChairRate*0.7,"Check - well under your chair rate",IF(IF(N5="",FALSE,TodayDate-N5>PriceReviewDays),"Due - price has not been reviewed",IF(IF(M5="Active",AB5=0,FALSE),"Check - on the menu but never booked","OK"))))))) -> 0
A6: =IF(B6="","",ServicePrefix&TEXT(ROW()-4,"000")) -> 0 | P6: =IF(B6="","",ROUND((IF(E6="",0,E6)+IF(F6="",0,F6))/60,3)) -> 0 | Q6: =IF(B6="","",IF(H6<>"",H6,IF(G6="",0,ROUND(G6*ProductCostPercent,2)))) -> 0 | R6: =IF(B6="","",IF(J6="No",0,IF(G6="",0,ROUND(G6*ServiceCommission,2)))) -> 0 | S6: =IF(B6="","",ROUND(Q6+R6,2)) -> 0 | T6: =IF(B6="","",IF(G6="","",ROUND(G6-S6,2))) -> 0 | U6: =IF(B6="","",IF(G6="","",IF(G6=0,"",T6/G6))) -> 0 | V6: =IF(B6="","",IF(G6="","",IF(P6=0,"",ROUND(G6/P6,2)))) -> 0 | W6: =IF(B6="","",IF(T6="","",IF(P6=0,"",ROUND(T6/P6,2)))) -> 0 | X6: =IF(B6="","",IF(P6=0,"",IF(ServiceCommission>=1,"",(Q6+TargetChairRate*P6)/IF(J6="No",1,1-ServiceCommission)))) -> 0 | Y6: =IF(B6="","",IF(X6="","",ROUND(IF(RoundingRule="None",X6,IF(RoundingRule="Nearest 0.99",MAX(0.99,CEILING(X6,1)-0.01),IF(RoundingRule="Nearest 0.95",MAX(0.95,CEILING(X6,1)-0.05),IF(RoundingRule="Nearest 0.50",CEILING(X6,0.5),IF(RoundingRule="Nearest 1",CEILING(X6,1),IF(RoundingRule="Nearest 5",CEILING(X6,5),IF(RoundingRule="Up to whole 1",CEILING(X6,1),IF(RoundingRule="Up to whole 5",CEILING(X6,5),ROUND(X6,2))))))))),2))) -> 0 | Z6: =IF(B6="","",IF(Y6="","",IF(G6="","",ROUND(G6-Y6,2)))) -> 0 | AA6: =IF(B6="","",COUNTIFS(Appointments!$G$5:$G$1204,A6)) -> 0 | AB6: =IF(B6="","",COUNTIFS(Appointments!$G$5:$G$1204,A6,Appointments!$M$5:$M$1204,"Completed")) -> 0 | AC6: =IF(B6="","",SUMIFS(Sales!$K$5:$K$1204,Sales!$I$5:$I$1204,A6,Sales!$H$5:$H$1204,"Service")) -> 0 | AD6: =IF(B6="","",ROUND(SUMIFS(Sales!$Y$5:$Y$1204,Sales!$I$5:$I$1204,A6,Sales!$H$5:$H$1204,"Service"),2)) -> 0 | AE6: =IF(B6="","",IF(ServiceRevenueAll=0,"",AD6/ServiceRevenueAll)) -> 0 | AF6: =IF(B6="","",ROUND(AC6*T6,2)) -> 0 | AG6: =IF(B6="","",ROUND(AC6*P6,1)) -> 0 | AH6: =IF(B6="","",IF(AB6=0,"",COUNTIFS(Sales!$I$5:$I$1204,A6,Sales!$AJ$5:$AJ$1204,"Yes")/AB6)) -> 0 | AI6: =IF(B6="","",IFERROR(IF(COUNTIFS(Appointments!$G$5:$G$1204,A6)=0,"",SUMPRODUCT(MAX((Appointments!$G$5:$G$1204=A6)*IFERROR(Appointments!$B$5:$B$1204*1,0)))),"")) -> 0 | AJ6: =IF(B6="","",COUNTIFS($AD$5:$AD$204,">"&AD6)+COUNTIFS($AD$5:AD6,AD6)) -> 0 | AK6: =IF(B6="","",COUNTIFS($W$5:$W$204,">"&W6)+COUNTIFS($W$5:W6,W6)) -> 0 | AL6: =IF(B6="","",COUNTIFS($AB$5:$AB$204,">"&AB6)+COUNTIFS($AB$5:AB6,AB6)) -> 0 | AM6: =IF(B6="","",IF(G6="","Add - no price yet",IF(E6="","Add - how long does it take?",IF(T6<0,"Loss - this service costs you money",IF(V6<TargetChairRate*0.7,"Check - well under your chair rate",IF(IF(N6="",FALSE,TodayDate-N6>PriceReviewDays),"Due - price has not been reviewed",IF(IF(M6="Active",AB6=0,FALSE),"Check - on the menu but never booked","OK"))))))) -> 0
A7: =IF(B7="","",ServicePrefix&TEXT(ROW()-4,"000")) -> 0 | P7: =IF(B7="","",ROUND((IF(E7="",0,E7)+IF(F7="",0,F7))/60,3)) -> 0 | Q7: =IF(B7="","",IF(H7<>"",H7,IF(G7="",0,ROUND(G7*ProductCostPercent,2)))) -> 0 | R7: =IF(B7="","",IF(J7="No",0,IF(G7="",0,ROUND(G7*ServiceCommission,2)))) -> 0 | S7: =IF(B7="","",ROUND(Q7+R7,2)) -> 0 | T7: =IF(B7="","",IF(G7="","",ROUND(G7-S7,2))) -> 0 | U7: =IF(B7="","",IF(G7="","",IF(G7=0,"",T7/G7))) -> 0 | V7: =IF(B7="","",IF(G7="","",IF(P7=0,"",ROUND(G7/P7,2)))) -> 0 | W7: =IF(B7="","",IF(T7="","",IF(P7=0,"",ROUND(T7/P7,2)))) -> 0 | X7: =IF(B7="","",IF(P7=0,"",IF(ServiceCommission>=1,"",(Q7+TargetChairRate*P7)/IF(J7="No",1,1-ServiceCommission)))) -> 0 | Y7: =IF(B7="","",IF(X7="","",ROUND(IF(RoundingRule="None",X7,IF(RoundingRule="Nearest 0.99",MAX(0.99,CEILING(X7,1)-0.01),IF(RoundingRule="Nearest 0.95",MAX(0.95,CEILING(X7,1)-0.05),IF(RoundingRule="Nearest 0.50",CEILING(X7,0.5),IF(RoundingRule="Nearest 1",CEILING(X7,1),IF(RoundingRule="Nearest 5",CEILING(X7,5),IF(RoundingRule="Up to whole 1",CEILING(X7,1),IF(RoundingRule="Up to whole 5",CEILING(X7,5),ROUND(X7,2))))))))),2))) -> 0 | Z7: =IF(B7="","",IF(Y7="","",IF(G7="","",ROUND(G7-Y7,2)))) -> 0 | AA7: =IF(B7="","",COUNTIFS(Appointments!$G$5:$G$1204,A7)) -> 0 | AB7: =IF(B7="","",COUNTIFS(Appointments!$G$5:$G$1204,A7,Appointments!$M$5:$M$1204,"Completed")) -> 0 | AC7: =IF(B7="","",SUMIFS(Sales!$K$5:$K$1204,Sales!$I$5:$I$1204,A7,Sales!$H$5:$H$1204,"Service")) -> 0 | AD7: =IF(B7="","",ROUND(SUMIFS(Sales!$Y$5:$Y$1204,Sales!$I$5:$I$1204,A7,Sales!$H$5:$H$1204,"Service"),2)) -> 0 | AE7: =IF(B7="","",IF(ServiceRevenueAll=0,"",AD7/ServiceRevenueAll)) -> 0 | AF7: =IF(B7="","",ROUND(AC7*T7,2)) -> 0 | AG7: =IF(B7="","",ROUND(AC7*P7,1)) -> 0 | AH7: =IF(B7="","",IF(AB7=0,"",COUNTIFS(Sales!$I$5:$I$1204,A7,Sales!$AJ$5:$AJ$1204,"Yes")/AB7)) -> 0 | AI7: =IF(B7="","",IFERROR(IF(COUNTIFS(Appointments!$G$5:$G$1204,A7)=0,"",SUMPRODUCT(MAX((Appointments!$G$5:$G$1204=A7)*IFERROR(Appointments!$B$5:$B$1204*1,0)))),"")) -> 0 | AJ7: =IF(B7="","",COUNTIFS($AD$5:$AD$204,">"&AD7)+COUNTIFS($AD$5:AD7,AD7)) -> 0 | AK7: =IF(B7="","",COUNTIFS($W$5:$W$204,">"&W7)+COUNTIFS($W$5:W7,W7)) -> 0 | AL7: =IF(B7="","",COUNTIFS($AB$5:$AB$204,">"&AB7)+COUNTIFS($AB$5:AB7,AB7)) -> 0 | AM7: =IF(B7="","",IF(G7="","Add - no price yet",IF(E7="","Add - how long does it take?",IF(T7<0,"Loss - this service costs you money",IF(V7<TargetChairRate*0.7,"Check - well under your chair rate",IF(IF(N7="",FALSE,TodayDate-N7>PriceReviewDays),"Due - price has not been reviewed",IF(IF(M7="Active",AB7=0,FALSE),"Check - on the menu but never booked","OK"))))))) -> 0
A8: =IF(B8="","",ServicePrefix&TEXT(ROW()-4,"000")) -> 0 | P8: =IF(B8="","",ROUND((IF(E8="",0,E8)+IF(F8="",0,F8))/60,3)) -> 0 | Q8: =IF(B8="","",IF(H8<>"",H8,IF(G8="",0,ROUND(G8*ProductCostPercent,2)))) -> 0 | R8: =IF(B8="","",IF(J8="No",0,IF(G8="",0,ROUND(G8*ServiceCommission,2)))) -> 0 | S8: =IF(B8="","",ROUND(Q8+R8,2)) -> 0 | T8: =IF(B8="","",IF(G8="","",ROUND(G8-S8,2))) -> 0 | U8: =IF(B8="","",IF(G8="","",IF(G8=0,"",T8/G8))) -> 0 | V8: =IF(B8="","",IF(G8="","",IF(P8=0,"",ROUND(G8/P8,2)))) -> 0 | W8: =IF(B8="","",IF(T8="","",IF(P8=0,"",ROUND(T8/P8,2)))) -> 0 | X8: =IF(B8="","",IF(P8=0,"",IF(ServiceCommission>=1,"",(Q8+TargetChairRate*P8)/IF(J8="No",1,1-ServiceCommission)))) -> 0 | Y8: =IF(B8="","",IF(X8="","",ROUND(IF(RoundingRule="None",X8,IF(RoundingRule="Nearest 0.99",MAX(0.99,CEILING(X8,1)-0.01),IF(RoundingRule="Nearest 0.95",MAX(0.95,CEILING(X8,1)-0.05),IF(RoundingRule="Nearest 0.50",CEILING(X8,0.5),IF(RoundingRule="Nearest 1",CEILING(X8,1),IF(RoundingRule="Nearest 5",CEILING(X8,5),IF(RoundingRule="Up to whole 1",CEILING(X8,1),IF(RoundingRule="Up to whole 5",CEILING(X8,5),ROUND(X8,2))))))))),2))) -> 0 | Z8: =IF(B8="","",IF(Y8="","",IF(G8="","",ROUND(G8-Y8,2)))) -> 0 | AA8: =IF(B8="","",COUNTIFS(Appointments!$G$5:$G$1204,A8)) -> 0 | AB8: =IF(B8="","",COUNTIFS(Appointments!$G$5:$G$1204,A8,Appointments!$M$5:$M$1204,"Completed")) -> 0 | AC8: =IF(B8="","",SUMIFS(Sales!$K$5:$K$1204,Sales!$I$5:$I$1204,A8,Sales!$H$5:$H$1204,"Service")) -> 0 | AD8: =IF(B8="","",ROUND(SUMIFS(Sales!$Y$5:$Y$1204,Sales!$I$5:$I$1204,A8,Sales!$H$5:$H$1204,"Service"),2)) -> 0 | AE8: =IF(B8="","",IF(ServiceRevenueAll=0,"",AD8/ServiceRevenueAll)) -> 0 | AF8: =IF(B8="","",ROUND(AC8*T8,2)) -> 0 | AG8: =IF(B8="","",ROUND(AC8*P8,1)) -> 0 | AH8: =IF(B8="","",IF(AB8=0,"",COUNTIFS(Sales!$I$5:$I$1204,A8,Sales!$AJ$5:$AJ$1204,"Yes")/AB8)) -> 0 | AI8: =IF(B8="","",IFERROR(IF(COUNTIFS(Appointments!$G$5:$G$1204,A8)=0,"",SUMPRODUCT(MAX((Appointments!$G$5:$G$1204=A8)*IFERROR(Appointments!$B$5:$B$1204*1,0)))),"")) -> 0 | AJ8: =IF(B8="","",COUNTIFS($AD$5:$AD$204,">"&AD8)+COUNTIFS($AD$5:AD8,AD8)) -> 0 | AK8: =IF(B8="","",COUNTIFS($W$5:$W$204,">"&W8)+COUNTIFS($W$5:W8,W8)) -> 0 | AL8: =IF(B8="","",COUNTIFS($AB$5:$AB$204,">"&AB8)+COUNTIFS($AB$5:AB8,AB8)) -> 0 | AM8: =IF(B8="","",IF(G8="","Add - no price yet",IF(E8="","Add - how long does it take?",IF(T8<0,"Loss - this service costs you money",IF(V8<TargetChairRate*0.7,"Check - well under your chair rate",IF(IF(N8="",FALSE,TodayDate-N8>PriceReviewDays),"Due - price has not been reviewed",IF(IF(M8="Active",AB8=0,FALSE),"Check - on the menu but never booked","OK"))))))) -> 0
A9: =IF(B9="","",ServicePrefix&TEXT(ROW()-4,"000")) -> 0 | P9: =IF(B9="","",ROUND((IF(E9="",0,E9)+IF(F9="",0,F9))/60,3)) -> 0 | Q9: =IF(B9="","",IF(H9<>"",H9,IF(G9="",0,ROUND(G9*ProductCostPercent,2)))) -> 0 | R9: =IF(B9="","",IF(J9="No",0,IF(G9="",0,ROUND(G9*ServiceCommission,2)))) -> 0 | S9: =IF(B9="","",ROUND(Q9+R9,2)) -> 0 | T9: =IF(B9="","",IF(G9="","",ROUND(G9-S9,2))) -> 0 | U9: =IF(B9="","",IF(G9="","",IF(G9=0,"",T9/G9))) -> 0 | V9: =IF(B9="","",IF(G9="","",IF(P9=0,"",ROUND(G9/P9,2)))) -> 0 | W9: =IF(B9="","",IF(T9="","",IF(P9=0,"",ROUND(T9/P9,2)))) -> 0 | X9: =IF(B9="","",IF(P9=0,"",IF(ServiceCommission>=1,"",(Q9+TargetChairRate*P9)/IF(J9="No",1,1-ServiceCommission)))) -> 0 | Y9: =IF(B9="","",IF(X9="","",ROUND(IF(RoundingRule="None",X9,IF(RoundingRule="Nearest 0.99",MAX(0.99,CEILING(X9,1)-0.01),IF(RoundingRule="Nearest 0.95",MAX(0.95,CEILING(X9,1)-0.05),IF(RoundingRule="Nearest 0.50",CEILING(X9,0.5),IF(RoundingRule="Nearest 1",CEILING(X9,1),IF(RoundingRule="Nearest 5",CEILING(X9,5),IF(RoundingRule="Up to whole 1",CEILING(X9,1),IF(RoundingRule="Up to whole 5",CEILING(X9,5),ROUND(X9,2))))))))),2))) -> 0 | Z9: =IF(B9="","",IF(Y9="","",IF(G9="","",ROUND(G9-Y9,2)))) -> 0 | AA9: =IF(B9="","",COUNTIFS(Appointments!$G$5:$G$1204,A9)) -> 0 | AB9: =IF(B9="","",COUNTIFS(Appointments!$G$5:$G$1204,A9,Appointments!$M$5:$M$1204,"Completed")) -> 0 | AC9: =IF(B9="","",SUMIFS(Sales!$K$5:$K$1204,Sales!$I$5:$I$1204,A9,Sales!$H$5:$H$1204,"Service")) -> 0 | AD9: =IF(B9="","",ROUND(SUMIFS(Sales!$Y$5:$Y$1204,Sales!$I$5:$I$1204,A9,Sales!$H$5:$H$1204,"Service"),2)) -> 0 | AE9: =IF(B9="","",IF(ServiceRevenueAll=0,"",AD9/ServiceRevenueAll)) -> 0 | AF9: =IF(B9="","",ROUND(AC9*T9,2)) -> 0 | AG9: =IF(B9="","",ROUND(AC9*P9,1)) -> 0 | AH9: =IF(B9="","",IF(AB9=0,"",COUNTIFS(Sales!$I$5:$I$1204,A9,Sales!$AJ$5:$AJ$1204,"Yes")/AB9)) -> 0 | AI9: =IF(B9="","",IFERROR(IF(COUNTIFS(Appointments!$G$5:$G$1204,A9)=0,"",SUMPRODUCT(MAX((Appointments!$G$5:$G$1204=A9)*IFERROR(Appointments!$B$5:$B$1204*1,0)))),"")) -> 0 | AJ9: =IF(B9="","",COUNTIFS($AD$5:$AD$204,">"&AD9)+COUNTIFS($AD$5:AD9,AD9)) -> 0 | AK9: =IF(B9="","",COUNTIFS($W$5:$W$204,">"&W9)+COUNTIFS($W$5:W9,W9)) -> 0 | AL9: =IF(B9="","",COUNTIFS($AB$5:$AB$204,">"&AB9)+COUNTIFS($AB$5:AB9,AB9)) -> 0 | AM9: =IF(B9="","",IF(G9="","Add - no price yet",IF(E9="","Add - how long does it take?",IF(T9<0,"Loss - this service costs you money",IF(V9<TargetChairRate*0.7,"Check - well under your chair rate",IF(IF(N9="",FALSE,TodayDate-N9>PriceReviewDays),"Due - price has not been reviewed",IF(IF(M9="Active",AB9=0,FALSE),"Check - on the menu but never booked","OK"))))))) -> 0
A10: =IF(B10="","",ServicePrefix&TEXT(ROW()-4,"000")) -> 0 | P10: =IF(B10="","",ROUND((IF(E10="",0,E10)+IF(F10="",0,F10))/60,3)) -> 0 | Q10: =IF(B10="","",IF(H10<>"",H10,IF(G10="",0,ROUND(G10*ProductCostPercent,2)))) -> 0 | R10: =IF(B10="","",IF(J10="No",0,IF(G10="",0,ROUND(G10*ServiceCommission,2)))) -> 0 | S10: =IF(B10="","",ROUND(Q10+R10,2)) -> 0 | T10: =IF(B10="","",IF(G10="","",ROUND(G10-S10,2))) -> 0 | U10: =IF(B10="","",IF(G10="","",IF(G10=0,"",T10/G10))) -> 0 | V10: =IF(B10="","",IF(G10="","",IF(P10=0,"",ROUND(G10/P10,2)))) -> 0 | W10: =IF(B10="","",IF(T10="","",IF(P10=0,"",ROUND(T10/P10,2)))) -> 0 | X10: =IF(B10="","",IF(P10=0,"",IF(ServiceCommission>=1,"",(Q10+TargetChairRate*P10)/IF(J10="No",1,1-ServiceCommission)))) -> 0 | Y10: =IF(B10="","",IF(X10="","",ROUND(IF(RoundingRule="None",X10,IF(RoundingRule="Nearest 0.99",MAX(0.99,CEILING(X10,1)-0.01),IF(RoundingRule="Nearest 0.95",MAX(0.95,CEILING(X10,1)-0.05),IF(RoundingRule="Nearest 0.50",CEILING(X10,0.5),IF(RoundingRule="Nearest 1",CEILING(X10,1),IF(RoundingRule="Nearest 5",CEILING(X10,5),IF(RoundingRule="Up to whole 1",CEILING(X10,1),IF(RoundingRule="Up to whole 5",CEILING(X10,5),ROUND(X10,2))))))))),2))) -> 0 | Z10: =IF(B10="","",IF(Y10="","",IF(G10="","",ROUND(G10-Y10,2)))) -> 0 | AA10: =IF(B10="","",COUNTIFS(Appointments!$G$5:$G$1204,A10)) -> 0 | AB10: =IF(B10="","",COUNTIFS(Appointments!$G$5:$G$1204,A10,Appointments!$M$5:$M$1204,"Completed")) -> 0 | AC10: =IF(B10="","",SUMIFS(Sales!$K$5:$K$1204,Sales!$I$5:$I$1204,A10,Sales!$H$5:$H$1204,"Service")) -> 0 | AD10: =IF(B10="","",ROUND(SUMIFS(Sales!$Y$5:$Y$1204,Sales!$I$5:$I$1204,A10,Sales!$H$5:$H$1204,"Service"),2)) -> 0 | AE10: =IF(B10="","",IF(ServiceRevenueAll=0,"",AD10/ServiceRevenueAll)) -> 0 | AF10: =IF(B10="","",ROUND(AC10*T10,2)) -> 0 | AG10: =IF(B10="","",ROUND(AC10*P10,1)) -> 0 | AH10: =IF(B10="","",IF(AB10=0,"",COUNTIFS(Sales!$I$5:$I$1204,A10,Sales!$AJ$5:$AJ$1204,"Yes")/AB10)) -> 0 | AI10: =IF(B10="","",IFERROR(IF(COUNTIFS(Appointments!$G$5:$G$1204,A10)=0,"",SUMPRODUCT(MAX((Appointments!$G$5:$G$1204=A10)*IFERROR(Appointments!$B$5:$B$1204*1,0)))),"")) -> 0 | AJ10: =IF(B10="","",COUNTIFS($AD$5:$AD$204,">"&AD10)+COUNTIFS($AD$5:AD10,AD10)) -> 0 | AK10: =IF(B10="","",COUNTIFS($W$5:$W$204,">"&W10)+COUNTIFS($W$5:W10,W10)) -> 0 | AL10: =IF(B10="","",COUNTIFS($AB$5:$AB$204,">"&AB10)+COUNTIFS($AB$5:AB10,AB10)) -> 0 | AM10: =IF(B10="","",IF(G10="","Add - no price yet",IF(E10="","Add - how long does it take?",IF(T10<0,"Loss - this service costs you money",IF(V10<TargetChairRate*0.7,"Check - well under your chair rate",IF(IF(N10="",FALSE,TodayDate-N10>PriceReviewDays),"Due - price has not been reviewed",IF(IF(M10="Active",AB10=0,FALSE),"Check - on the menu but never booked","OK"))))))) -> 0
A11: =IF(B11="","",ServicePrefix&TEXT(ROW()-4,"000")) -> 0 | P11: =IF(B11="","",ROUND((IF(E11="",0,E11)+IF(F11="",0,F11))/60,3)) -> 0 | Q11: =IF(B11="","",IF(H11<>"",H11,IF(G11="",0,ROUND(G11*ProductCostPercent,2)))) -> 0 | R11: =IF(B11="","",IF(J11="No",0,IF(G11="",0,ROUND(G11*ServiceCommission,2)))) -> 0 | S11: =IF(B11="","",ROUND(Q11+R11,2)) -> 0 | T11: =IF(B11="","",IF(G11="","",ROUND(G11-S11,2))) -> 0 | U11: =IF(B11="","",IF(G11="","",IF(G11=0,"",T11/G11))) -> 0 | V11: =IF(B11="","",IF(G11="","",IF(P11=0,"",ROUND(G11/P11,2)))) -> 0 | W11: =IF(B11="","",IF(T11="","",IF(P11=0,"",ROUND(T11/P11,2)))) -> 0 | X11: =IF(B11="","",IF(P11=0,"",IF(ServiceCommission>=1,"",(Q11+TargetChairRate*P11)/IF(J11="No",1,1-ServiceCommission)))) -> 0 | Y11: =IF(B11="","",IF(X11="","",ROUND(IF(RoundingRule="None",X11,IF(RoundingRule="Nearest 0.99",MAX(0.99,CEILING(X11,1)-0.01),IF(RoundingRule="Nearest 0.95",MAX(0.95,CEILING(X11,1)-0.05),IF(RoundingRule="Nearest 0.50",CEILING(X11,0.5),IF(RoundingRule="Nearest 1",CEILING(X11,1),IF(RoundingRule="Nearest 5",CEILING(X11,5),IF(RoundingRule="Up to whole 1",CEILING(X11,1),IF(RoundingRule="Up to whole 5",CEILING(X11,5),ROUND(X11,2))))))))),2))) -> 0 | Z11: =IF(B11="","",IF(Y11="","",IF(G11="","",ROUND(G11-Y11,2)))) -> 0 | AA11: =IF(B11="","",COUNTIFS(Appointments!$G$5:$G$1204,A11)) -> 0 | AB11: =IF(B11="","",COUNTIFS(Appointments!$G$5:$G$1204,A11,Appointments!$M$5:$M$1204,"Completed")) -> 0 | AC11: =IF(B11="","",SUMIFS(Sales!$K$5:$K$1204,Sales!$I$5:$I$1204,A11,Sales!$H$5:$H$1204,"Service")) -> 0 | AD11: =IF(B11="","",ROUND(SUMIFS(Sales!$Y$5:$Y$1204,Sales!$I$5:$I$1204,A11,Sales!$H$5:$H$1204,"Service"),2)) -> 0 | AE11: =IF(B11="","",IF(ServiceRevenueAll=0,"",AD11/ServiceRevenueAll)) -> 0 | AF11: =IF(B11="","",ROUND(AC11*T11,2)) -> 0 | AG11: =IF(B11="","",ROUND(AC11*P11,1)) -> 0 | AH11: =IF(B11="","",IF(AB11=0,"",COUNTIFS(Sales!$I$5:$I$1204,A11,Sales!$AJ$5:$AJ$1204,"Yes")/AB11)) -> 0 | AI11: =IF(B11="","",IFERROR(IF(COUNTIFS(Appointments!$G$5:$G$1204,A11)=0,"",SUMPRODUCT(MAX((Appointments!$G$5:$G$1204=A11)*IFERROR(Appointments!$B$5:$B$1204*1,0)))),"")) -> 0 | AJ11: =IF(B11="","",COUNTIFS($AD$5:$AD$204,">"&AD11)+COUNTIFS($AD$5:AD11,AD11)) -> 0 | AK11: =IF(B11="","",COUNTIFS($W$5:$W$204,">"&W11)+COUNTIFS($W$5:W11,W11)) -> 0 | AL11: =IF(B11="","",COUNTIFS($AB$5:$AB$204,">"&AB11)+COUNTIFS($AB$5:AB11,AB11)) -> 0 | AM11: =IF(B11="","",IF(G11="","Add - no price yet",IF(E11="","Add - how long does it take?",IF(T11<0,"Loss - this service costs you money",IF(V11<TargetChairRate*0.7,"Check - well under your chair rate",IF(IF(N11="",FALSE,TodayDate-N11>PriceReviewDays),"Due - price has not been reviewed",IF(IF(M11="Active",AB11=0,FALSE),"Check - on the menu but never booked","OK"))))))) -> 0
A12: =IF(B12="","",ServicePrefix&TEXT(ROW()-4,"000")) -> 0 | P12: =IF(B12="","",ROUND((IF(E12="",0,E12)+IF(F12="",0,F12))/60,3)) -> 0 | Q12: =IF(B12="","",IF(H12<>"",H12,IF(G12="",0,ROUND(G12*ProductCostPercent,2)))) -> 0 | R12: =IF(B12="","",IF(J12="No",0,IF(G12="",0,ROUND(G12*ServiceCommission,2)))) -> 0 | S12: =IF(B12="","",ROUND(Q12+R12,2)) -> 0 | T12: =IF(B12="","",IF(G12="","",ROUND(G12-S12,2))) -> 0 | U12: =IF(B12="","",IF(G12="","",IF(G12=0,"",T12/G12))) -> 0 | V12: =IF(B12="","",IF(G12="","",IF(P12=0,"",ROUND(G12/P12,2)))) -> 0 | W12: =IF(B12="","",IF(T12="","",IF(P12=0,"",ROUND(T12/P12,2)))) -> 0 | X12: =IF(B12="","",IF(P12=0,"",IF(ServiceCommission>=1,"",(Q12+TargetChairRate*P12)/IF(J12="No",1,1-ServiceCommission)))) -> 0 | Y12: =IF(B12="","",IF(X12="","",ROUND(IF(RoundingRule="None",X12,IF(RoundingRule="Nearest 0.99",MAX(0.99,CEILING(X12,1)-0.01),IF(RoundingRule="Nearest 0.95",MAX(0.95,CEILING(X12,1)-0.05),IF(RoundingRule="Nearest 0.50",CEILING(X12,0.5),IF(RoundingRule="Nearest 1",CEILING(X12,1),IF(RoundingRule="Nearest 5",CEILING(X12,5),IF(RoundingRule="Up to whole 1",CEILING(X12,1),IF(RoundingRule="Up to whole 5",CEILING(X12,5),ROUND(X12,2))))))))),2))) -> 0 | Z12: =IF(B12="","",IF(Y12="","",IF(G12="","",ROUND(G12-Y12,2)))) -> 0 | AA12: =IF(B12="","",COUNTIFS(Appointments!$G$5:$G$1204,A12)) -> 0 | AB12: =IF(B12="","",COUNTIFS(Appointments!$G$5:$G$1204,A12,Appointments!$M$5:$M$1204,"Completed")) -> 0 | AC12: =IF(B12="","",SUMIFS(Sales!$K$5:$K$1204,Sales!$I$5:$I$1204,A12,Sales!$H$5:$H$1204,"Service")) -> 0 | AD12: =IF(B12="","",ROUND(SUMIFS(Sales!$Y$5:$Y$1204,Sales!$I$5:$I$1204,A12,Sales!$H$5:$H$1204,"Service"),2)) -> 0 | AE12: =IF(B12="","",IF(ServiceRevenueAll=0,"",AD12/ServiceRevenueAll)) -> 0 | AF12: =IF(B12="","",ROUND(AC12*T12,2)) -> 0 | AG12: =IF(B12="","",ROUND(AC12*P12,1)) -> 0 | AH12: =IF(B12="","",IF(AB12=0,"",COUNTIFS(Sales!$I$5:$I$1204,A12,Sales!$AJ$5:$AJ$1204,"Yes")/AB12)) -> 0 | AI12: =IF(B12="","",IFERROR(IF(COUNTIFS(Appointments!$G$5:$G$1204,A12)=0,"",SUMPRODUCT(MAX((Appointments!$G$5:$G$1204=A12)*IFERROR(Appointments!$B$5:$B$1204*1,0)))),"")) -> 0 | AJ12: =IF(B12="","",COUNTIFS($AD$5:$AD$204,">"&AD12)+COUNTIFS($AD$5:AD12,AD12)) -> 0 | AK12: =IF(B12="","",COUNTIFS($W$5:$W$204,">"&W12)+COUNTIFS($W$5:W12,W12)) -> 0 | AL12: =IF(B12="","",COUNTIFS($AB$5:$AB$204,">"&AB12)+COUNTIFS($AB$5:AB12,AB12)) -> 0 | AM12: =IF(B12="","",IF(G12="","Add - no price yet",IF(E12="","Add - how long does it take?",IF(T12<0,"Loss - this service costs you money",IF(V12<TargetChairRate*0.7,"Check - well under your chair rate",IF(IF(N12="",FALSE,TodayDate-N12>PriceReviewDays),"Due - price has not been reviewed",IF(IF(M12="Active",AB12=0,FALSE),"Check - on the menu but never booked","OK"))))))) -> 0
A13: =IF(B13="","",ServicePrefix&TEXT(ROW()-4,"000")) -> 0 | P13: =IF(B13="","",ROUND((IF(E13="",0,E13)+IF(F13="",0,F13))/60,3)) -> 0 | Q13: =IF(B13="","",IF(H13<>"",H13,IF(G13="",0,ROUND(G13*ProductCostPercent,2)))) -> 0 | R13: =IF(B13="","",IF(J13="No",0,IF(G13="",0,ROUND(G13*ServiceCommission,2)))) -> 0 | S13: =IF(B13="","",ROUND(Q13+R13,2)) -> 0 | T13: =IF(B13="","",IF(G13="","",ROUND(G13-S13,2))) -> 0 | U13: =IF(B13="","",IF(G13="","",IF(G13=0,"",T13/G13))) -> 0 | V13: =IF(B13="","",IF(G13="","",IF(P13=0,"",ROUND(G13/P13,2)))) -> 0 | W13: =IF(B13="","",IF(T13="","",IF(P13=0,"",ROUND(T13/P13,2)))) -> 0 | X13: =IF(B13="","",IF(P13=0,"",IF(ServiceCommission>=1,"",(Q13+TargetChairRate*P13)/IF(J13="No",1,1-ServiceCommission)))) -> 0 | Y13: =IF(B13="","",IF(X13="","",ROUND(IF(RoundingRule="None",X13,IF(RoundingRule="Nearest 0.99",MAX(0.99,CEILING(X13,1)-0.01),IF(RoundingRule="Nearest 0.95",MAX(0.95,CEILING(X13,1)-0.05),IF(RoundingRule="Nearest 0.50",CEILING(X13,0.5),IF(RoundingRule="Nearest 1",CEILING(X13,1),IF(RoundingRule="Nearest 5",CEILING(X13,5),IF(RoundingRule="Up to whole 1",CEILING(X13,1),IF(RoundingRule="Up to whole 5",CEILING(X13,5),ROUND(X13,2))))))))),2))) -> 0 | Z13: =IF(B13="","",IF(Y13="","",IF(G13="","",ROUND(G13-Y13,2)))) -> 0 | AA13: =IF(B13="","",COUNTIFS(Appointments!$G$5:$G$1204,A13)) -> 0 | AB13: =IF(B13="","",COUNTIFS(Appointments!$G$5:$G$1204,A13,Appointments!$M$5:$M$1204,"Completed")) -> 0 | AC13: =IF(B13="","",SUMIFS(Sales!$K$5:$K$1204,Sales!$I$5:$I$1204,A13,Sales!$H$5:$H$1204,"Service")) -> 0 | AD13: =IF(B13="","",ROUND(SUMIFS(Sales!$Y$5:$Y$1204,Sales!$I$5:$I$1204,A13,Sales!$H$5:$H$1204,"Service"),2)) -> 0 | AE13: =IF(B13="","",IF(ServiceRevenueAll=0,"",AD13/ServiceRevenueAll)) -> 0 | AF13: =IF(B13="","",ROUND(AC13*T13,2)) -> 0 | AG13: =IF(B13="","",ROUND(AC13*P13,1)) -> 0 | AH13: =IF(B13="","",IF(AB13=0,"",COUNTIFS(Sales!$I$5:$I$1204,A13,Sales!$AJ$5:$AJ$1204,"Yes")/AB13)) -> 0 | AI13: =IF(B13="","",IFERROR(IF(COUNTIFS(Appointments!$G$5:$G$1204,A13)=0,"",SUMPRODUCT(MAX((Appointments!$G$5:$G$1204=A13)*IFERROR(Appointments!$B$5:$B$1204*1,0)))),"")) -> 0 | AJ13: =IF(B13="","",COUNTIFS($AD$5:$AD$204,">"&AD13)+COUNTIFS($AD$5:AD13,AD13)) -> 0 | AK13: =IF(B13="","",COUNTIFS($W$5:$W$204,">"&W13)+COUNTIFS($W$5:W13,W13)) -> 0 | AL13: =IF(B13="","",COUNTIFS($AB$5:$AB$204,">"&AB13)+COUNTIFS($AB$5:AB13,AB13)) -> 0 | AM13: =IF(B13="","",IF(G13="","Add - no price yet",IF(E13="","Add - how long does it take?",IF(T13<0,"Loss - this service costs you money",IF(V13<TargetChairRate*0.7,"Check - well under your chair rate",IF(IF(N13="",FALSE,TodayDate-N13>PriceReviewDays),"Due - price has not been reviewed",IF(IF(M13="Active",AB13=0,FALSE),"Check - on the menu but never booked","OK"))))))) -> 0
A14: =IF(B14="","",ServicePrefix&TEXT(ROW()-4,"000")) -> 0 | P14: =IF(B14="","",ROUND((IF(E14="",0,E14)+IF(F14="",0,F14))/60,3)) -> 0 | Q14: =IF(B14="","",IF(H14<>"",H14,IF(G14="",0,ROUND(G14*ProductCostPercent,2)))) -> 0 | R14: =IF(B14="","",IF(J14="No",0,IF(G14="",0,ROUND(G14*ServiceCommission,2)))) -> 0 | S14: =IF(B14="","",ROUND(Q14+R14,2)) -> 0 | T14: =IF(B14="","",IF(G14="","",ROUND(G14-S14,2))) -> 0 | U14: =IF(B14="","",IF(G14="","",IF(G14=0,"",T14/G14))) -> 0 | V14: =IF(B14="","",IF(G14="","",IF(P14=0,"",ROUND(G14/P14,2)))) -> 0 | W14: =IF(B14="","",IF(T14="","",IF(P14=0,"",ROUND(T14/P14,2)))) -> 0 | X14: =IF(B14="","",IF(P14=0,"",IF(ServiceCommission>=1,"",(Q14+TargetChairRate*P14)/IF(J14="No",1,1-ServiceCommission)))) -> 0 | Y14: =IF(B14="","",IF(X14="","",ROUND(IF(RoundingRule="None",X14,IF(RoundingRule="Nearest 0.99",MAX(0.99,CEILING(X14,1)-0.01),IF(RoundingRule="Nearest 0.95",MAX(0.95,CEILING(X14,1)-0.05),IF(RoundingRule="Nearest 0.50",CEILING(X14,0.5),IF(RoundingRule="Nearest 1",CEILING(X14,1),IF(RoundingRule="Nearest 5",CEILING(X14,5),IF(RoundingRule="Up to whole 1",CEILING(X14,1),IF(RoundingRule="Up to whole 5",CEILING(X14,5),ROUND(X14,2))))))))),2))) -> 0 | Z14: =IF(B14="","",IF(Y14="","",IF(G14="","",ROUND(G14-Y14,2)))) -> 0 | AA14: =IF(B14="","",COUNTIFS(Appointments!$G$5:$G$1204,A14)) -> 0 | AB14: =IF(B14="","",COUNTIFS(Appointments!$G$5:$G$1204,A14,Appointments!$M$5:$M$1204,"Completed")) -> 0 | AC14: =IF(B14="","",SUMIFS(Sales!$K$5:$K$1204,Sales!$I$5:$I$1204,A14,Sales!$H$5:$H$1204,"Service")) -> 0 | AD14: =IF(B14="","",ROUND(SUMIFS(Sales!$Y$5:$Y$1204,Sales!$I$5:$I$1204,A14,Sales!$H$5:$H$1204,"Service"),2)) -> 0 | AE14: =IF(B14="","",IF(ServiceRevenueAll=0,"",AD14/ServiceRevenueAll)) -> 0 | AF14: =IF(B14="","",ROUND(AC14*T14,2)) -> 0 | AG14: =IF(B14="","",ROUND(AC14*P14,1)) -> 0 | AH14: =IF(B14="","",IF(AB14=0,"",COUNTIFS(Sales!$I$5:$I$1204,A14,Sales!$AJ$5:$AJ$1204,"Yes")/AB14)) -> 0 | AI14: =IF(B14="","",IFERROR(IF(COUNTIFS(Appointments!$G$5:$G$1204,A14)=0,"",SUMPRODUCT(MAX((Appointments!$G$5:$G$1204=A14)*IFERROR(Appointments!$B$5:$B$1204*1,0)))),"")) -> 0 | AJ14: =IF(B14="","",COUNTIFS($AD$5:$AD$204,">"&AD14)+COUNTIFS($AD$5:AD14,AD14)) -> 0 | AK14: =IF(B14="","",COUNTIFS($W$5:$W$204,">"&W14)+COUNTIFS($W$5:W14,W14)) -> 0 | AL14: =IF(B14="","",COUNTIFS($AB$5:$AB$204,">"&AB14)+COUNTIFS($AB$5:AB14,AB14)) -> 0 | AM14: =IF(B14="","",IF(G14="","Add - no price yet",IF(E14="","Add - how long does it take?",IF(T14<0,"Loss - this service costs you money",IF(V14<TargetChairRate*0.7,"Check - well under your chair rate",IF(IF(N14="",FALSE,TodayDate-N14>PriceReviewDays),"Due - price has not been reviewed",IF(IF(M14="Active",AB14=0,FALSE),"Check - on the menu but never booked","OK"))))))) -> 0
A15: =IF(B15="","",ServicePrefix&TEXT(ROW()-4,"000")) -> 0 | P15: =IF(B15="","",ROUND((IF(E15="",0,E15)+IF(F15="",0,F15))/60,3)) -> 0 | Q15: =IF(B15="","",IF(H15<>"",H15,IF(G15="",0,ROUND(G15*ProductCostPercent,2)))) -> 0 | R15: =IF(B15="","",IF(J15="No",0,IF(G15="",0,ROUND(G15*ServiceCommission,2)))) -> 0 | S15: =IF(B15="","",ROUND(Q15+R15,2)) -> 0 | T15: =IF(B15="","",IF(G15="","",ROUND(G15-S15,2))) -> 0 | U15: =IF(B15="","",IF(G15="","",IF(G15=0,"",T15/G15))) -> 0 | V15: =IF(B15="","",IF(G15="","",IF(P15=0,"",ROUND(G15/P15,2)))) -> 0 | W15: =IF(B15="","",IF(T15="","",IF(P15=0,"",ROUND(T15/P15,2)))) -> 0 | X15: =IF(B15="","",IF(P15=0,"",IF(ServiceCommission>=1,"",(Q15+TargetChairRate*P15)/IF(J15="No",1,1-ServiceCommission)))) -> 0 | Y15: =IF(B15="","",IF(X15="","",ROUND(IF(RoundingRule="None",X15,IF(RoundingRule="Nearest 0.99",MAX(0.99,CEILING(X15,1)-0.01),IF(RoundingRule="Nearest 0.95",MAX(0.95,CEILING(X15,1)-0.05),IF(RoundingRule="Nearest 0.50",CEILING(X15,0.5),IF(RoundingRule="Nearest 1",CEILING(X15,1),IF(RoundingRule="Nearest 5",CEILING(X15,5),IF(RoundingRule="Up to whole 1",CEILING(X15,1),IF(RoundingRule="Up to whole 5",CEILING(X15,5),ROUND(X15,2))))))))),2))) -> 0 | Z15: =IF(B15="","",IF(Y15="","",IF(G15="","",ROUND(G15-Y15,2)))) -> 0 | AA15: =IF(B15="","",COUNTIFS(Appointments!$G$5:$G$1204,A15)) -> 0 | AB15: =IF(B15="","",COUNTIFS(Appointments!$G$5:$G$1204,A15,Appointments!$M$5:$M$1204,"Completed")) -> 0 | AC15: =IF(B15="","",SUMIFS(Sales!$K$5:$K$1204,Sales!$I$5:$I$1204,A15,Sales!$H$5:$H$1204,"Service")) -> 0 | AD15: =IF(B15="","",ROUND(SUMIFS(Sales!$Y$5:$Y$1204,Sales!$I$5:$I$1204,A15,Sales!$H$5:$H$1204,"Service"),2)) -> 0 | AE15: =IF(B15="","",IF(ServiceRevenueAll=0,"",AD15/ServiceRevenueAll)) -> 0 | AF15: =IF(B15="","",ROUND(AC15*T15,2)) -> 0 | AG15: =IF(B15="","",ROUND(AC15*P15,1)) -> 0 | AH15: =IF(B15="","",IF(AB15=0,"",COUNTIFS(Sales!$I$5:$I$1204,A15,Sales!$AJ$5:$AJ$1204,"Yes")/AB15)) -> 0 | AI15: =IF(B15="","",IFERROR(IF(COUNTIFS(Appointments!$G$5:$G$1204,A15)=0,"",SUMPRODUCT(MAX((Appointments!$G$5:$G$1204=A15)*IFERROR(Appointments!$B$5:$B$1204*1,0)))),"")) -> 0 | AJ15: =IF(B15="","",COUNTIFS($AD$5:$AD$204,">"&AD15)+COUNTIFS($AD$5:AD15,AD15)) -> 0 | AK15: =IF(B15="","",COUNTIFS($W$5:$W$204,">"&W15)+COUNTIFS($W$5:W15,W15)) -> 0 | AL15: =IF(B15="","",COUNTIFS($AB$5:$AB$204,">"&AB15)+COUNTIFS($AB$5:AB15,AB15)) -> 0 | AM15: =IF(B15="","",IF(G15="","Add - no price yet",IF(E15="","Add - how long does it take?",IF(T15<0,"Loss - this service costs you money",IF(V15<TargetChairRate*0.7,"Check - well under your chair rate",IF(IF(N15="",FALSE,TodayDate-N15>PriceReviewDays),"Due - price has not been reviewed",IF(IF(M15="Active",AB15=0,FALSE),"Check - on the menu but never booked","OK"))))))) -> 0
A16: =IF(B16="","",ServicePrefix&TEXT(ROW()-4,"000")) -> 0 | P16: =IF(B16="","",ROUND((IF(E16="",0,E16)+IF(F16="",0,F16))/60,3)) -> 0 | Q16: =IF(B16="","",IF(H16<>"",H16,IF(G16="",0,ROUND(G16*ProductCostPercent,2)))) -> 0 | R16: =IF(B16="","",IF(J16="No",0,IF(G16="",0,ROUND(G16*ServiceCommission,2)))) -> 0 | S16: =IF(B16="","",ROUND(Q16+R16,2)) -> 0 | T16: =IF(B16="","",IF(G16="","",ROUND(G16-S16,2))) -> 0 | U16: =IF(B16="","",IF(G16="","",IF(G16=0,"",T16/G16))) -> 0 | V16: =IF(B16="","",IF(G16="","",IF(P16=0,"",ROUND(G16/P16,2)))) -> 0 | W16: =IF(B16="","",IF(T16="","",IF(P16=0,"",ROUND(T16/P16,2)))) -> 0 | X16: =IF(B16="","",IF(P16=0,"",IF(ServiceCommission>=1,"",(Q16+TargetChairRate*P16)/IF(J16="No",1,1-ServiceCommission)))) -> 0 | Y16: =IF(B16="","",IF(X16="","",ROUND(IF(RoundingRule="None",X16,IF(RoundingRule="Nearest 0.99",MAX(0.99,CEILING(X16,1)-0.01),IF(RoundingRule="Nearest 0.95",MAX(0.95,CEILING(X16,1)-0.05),IF(RoundingRule="Nearest 0.50",CEILING(X16,0.5),IF(RoundingRule="Nearest 1",CEILING(X16,1),IF(RoundingRule="Nearest 5",CEILING(X16,5),IF(RoundingRule="Up to whole 1",CEILING(X16,1),IF(RoundingRule="Up to whole 5",CEILING(X16,5),ROUND(X16,2))))))))),2))) -> 0 | Z16: =IF(B16="","",IF(Y16="","",IF(G16="","",ROUND(G16-Y16,2)))) -> 0 | AA16: =IF(B16="","",COUNTIFS(Appointments!$G$5:$G$1204,A16)) -> 0 | AB16: =IF(B16="","",COUNTIFS(Appointments!$G$5:$G$1204,A16,Appointments!$M$5:$M$1204,"Completed")) -> 0 | AC16: =IF(B16="","",SUMIFS(Sales!$K$5:$K$1204,Sales!$I$5:$I$1204,A16,Sales!$H$5:$H$1204,"Service")) -> 0 | AD16: =IF(B16="","",ROUND(SUMIFS(Sales!$Y$5:$Y$1204,Sales!$I$5:$I$1204,A16,Sales!$H$5:$H$1204,"Service"),2)) -> 0 | AE16: =IF(B16="","",IF(ServiceRevenueAll=0,"",AD16/ServiceRevenueAll)) -> 0 | AF16: =IF(B16="","",ROUND(AC16*T16,2)) -> 0 | AG16: =IF(B16="","",ROUND(AC16*P16,1)) -> 0 | AH16: =IF(B16="","",IF(AB16=0,"",COUNTIFS(Sales!$I$5:$I$1204,A16,Sales!$AJ$5:$AJ$1204,"Yes")/AB16)) -> 0 | AI16: =IF(B16="","",IFERROR(IF(COUNTIFS(Appointments!$G$5:$G$1204,A16)=0,"",SUMPRODUCT(MAX((Appointments!$G$5:$G$1204=A16)*IFERROR(Appointments!$B$5:$B$1204*1,0)))),"")) -> 0 | AJ16: =IF(B16="","",COUNTIFS($AD$5:$AD$204,">"&AD16)+COUNTIFS($AD$5:AD16,AD16)) -> 0 | AK16: =IF(B16="","",COUNTIFS($W$5:$W$204,">"&W16)+COUNTIFS($W$5:W16,W16)) -> 0 | AL16: =IF(B16="","",COUNTIFS($AB$5:$AB$204,">"&AB16)+COUNTIFS($AB$5:AB16,AB16)) -> 0 | AM16: =IF(B16="","",IF(G16="","Add - no price yet",IF(E16="","Add - how long does it take?",IF(T16<0,"Loss - this service costs you money",IF(V16<TargetChairRate*0.7,"Check - well under your chair rate",IF(IF(N16="",FALSE,TodayDate-N16>PriceReviewDays),"Due - price has not been reviewed",IF(IF(M16="Active",AB16=0,FALSE),"Check - on the menu but never booked","OK"))))))) -> 0
... A204: =IF(B204="","",ServicePrefix&TEXT(ROW()-4,"000")) -> 0 | P204: =IF(B204="","",ROUND((IF(E204="",0,E204)+IF(F204="",0,F204))/60,3)) -> 0 | Q204: =IF(B204="","",IF(H204<>"",H204,IF(G204="",0,ROUND(G204*ProductCostPercent,2)))) -> 0 | R204: =IF(B204="","",IF(J204="No",0,IF(G204="",0,ROUND(G204*ServiceCommission,2)))) -> 0 | S204: =IF(B204="","",ROUND(Q204+R204,2)) -> 0 | T204: =IF(B204="","",IF(G204="","",ROUND(G204-S204,2))) -> 0 | U204: =IF(B204="","",IF(G204="","",IF(G204=0,"",T204/G204))) -> 0 | V204: =IF(B204="","",IF(G204="","",IF(P204=0,"",ROUND(G204/P204,2)))) -> 0 | W204: =IF(B204="","",IF(T204="","",IF(P204=0,"",ROUND(T204/P204,2)))) -> 0 | X204: =IF(B204="","",IF(P204=0,"",IF(ServiceCommission>=1,"",(Q204+TargetChairRate*P204)/IF(J204="No",1,1-ServiceCommission)))) -> 0 | Y204: =IF(B204="","",IF(X204="","",ROUND(IF(RoundingRule="None",X204,IF(RoundingRule="Nearest 0.99",MAX(0.99,CEILING(X204,1)-0.01),IF(RoundingRule="Nearest 0.95",MAX(0.95,CEILING(X204,1)-0.05),IF(RoundingRule="Nearest 0.50",CEILING(X204,0.5),IF(RoundingRule="Nearest 1",CEILING(X204,1),IF(RoundingRule="Nearest 5",CEILING(X204,5),IF(RoundingRule="Up to whole 1",CEILING(X204,1),IF(RoundingRule="Up to whole 5",CEILING(X204,5),ROUND(X204,2))))))))),2))) -> 0 | Z204: =IF(B204="","",IF(Y204="","",IF(G204="","",ROUND(G204-Y204,2)))) -> 0 | AA204: =IF(B204="","",COUNTIFS(Appointments!$G$5:$G$1204,A204)) -> 0 | AB204: =IF(B204="","",COUNTIFS(Appointments!$G$5:$G$1204,A204,Appointments!$M$5:$M$1204,"Completed")) -> 0 | AC204: =IF(B204="","",SUMIFS(Sales!$K$5:$K$1204,Sales!$I$5:$I$1204,A204,Sales!$H$5:$H$1204,"Service")) -> 0 | AD204: =IF(B204="","",ROUND(SUMIFS(Sales!$Y$5:$Y$1204,Sales!$I$5:$I$1204,A204,Sales!$H$5:$H$1204,"Service"),2)) -> 0 | AE204: =IF(B204="","",IF(ServiceRevenueAll=0,"",AD204/ServiceRevenueAll)) -> 0 | AF204: =IF(B204="","",ROUND(AC204*T204,2)) -> 0 | AG204: =IF(B204="","",ROUND(AC204*P204,1)) -> 0 | AH204: =IF(B204="","",IF(AB204=0,"",COUNTIFS(Sales!$I$5:$I$1204,A204,Sales!$AJ$5:$AJ$1204,"Yes")/AB204)) -> 0 | AI204: =IF(B204="","",IFERROR(IF(COUNTIFS(Appointments!$G$5:$G$1204,A204)=0,"",SUMPRODUCT(MAX((Appointments!$G$5:$G$1204=A204)*IFERROR(Appointments!$B$5:$B$1204*1,0)))),"")) -> 0 | AJ204: =IF(B204="","",COUNTIFS($AD$5:$AD$204,">"&AD204)+COUNTIFS($AD$5:AD204,AD204)) -> 0 | AK204: =IF(B204="","",COUNTIFS($W$5:$W$204,">"&W204)+COUNTIFS($W$5:W204,W204)) -> 0 | AL204: =IF(B204="","",COUNTIFS($AB$5:$AB$204,">"&AB204)+COUNTIFS($AB$5:AB204,AB204)) -> 0 | AM204: =IF(B204="","",IF(G204="","Add - no price yet",IF(E204="","Add - how long does it take?",IF(T204<0,"Loss - this service costs you money",IF(V204<TargetChairRate*0.7,"Check - well under your chair rate",IF(IF(N204="",FALSE,TodayDate-N204>PriceReviewDays),"Due - price has not been reviewed",IF(IF(M204="Active",AB204=0,FALSE),"Check - on the menu but never booked","OK"))))))) -> 0
A206: The menu at a glance
A207: Services listed | B207: Active | C207: Average price | D207: Average minutes | E207: Average price an hour | F207: Best rate an hour | G207: Never booked | H207: Priced under target
A208: =COUNTIF(Services!$B$5:$B$204,"<>") -> 0 | B208: =COUNTIFS(Services!$M$5:$M$204,"Active") -> 0 | C208: =IFERROR(ROUND(AVERAGEIF(Services!$G$5:$G$204,">0"),2),0) -> 0 | D208: =IFERROR(ROUND(AVERAGEIF(Services!$E$5:$E$204,">0"),0),0) -> 0 | E208: =IFERROR(ROUND(SUMPRODUCT(IFERROR(Services!$V$5:$V$204*1,0))/MAX(1,COUNTIF(Services!$B$5:$B$204,"<>")),2),0) -> 0 | F208: =ROUND(MAX(IFERROR(Services!$V$5:$V$204*1,0)),2) -> 0 | G208: =COUNTIFS(Services!$B$5:$B$204,"<>",Services!$AB$5:$AB$204,0) -> 0 | H208: =SUMPRODUCT((IFERROR(Services!$V$5:$V$204*1,0)>0)*(IFERROR(Services!$V$5:$V$204*1,0)<TargetChairRate)) -> 0

Sheet Sales
A1: Sales & Transactions | AJ1: Novality Store | v1.0.0
A2: Every service, product and voucher sold - gross, discount, refund, net, tax and the profit left over.
A3: > Start Here | C3: > Dashboard | E3: > Diary | G3: > Clients | I3: > Services | K3: > Sales | M3: > Staff | O3: > Profit | Q3: > Settings | S3: One row per thing sold. Two lines for a client who had a colour and bought shampoo - that is how the retail figures stay separate from the service figures.
A4: ID | B4: Date | C4: Appointment | D4: Client ID | E4: Client | F4: Stylist ID | G4: Stylist | H4: Kind | I4: Service / product | J4: Description | K4: Qty | L4: Unit price | M4: Discount % | N4: Discount $ | O4: Promo code | P4: Refunded | Q4: Notes | R4: Month | S4: Week | T4: Qty used | U4: Item | V4: Price used | W4: Gross | X4: Discount | Y4: Net sale | Z4: Tax | AA4: Total due | AB4: Cost | AC4: Gross profit | AD4: First line? | AE4: Paid to this sale | AF4: Deposit applied | AG4: Paid | AH4: Balance | AI4: Paid? | AJ4: Retail too? | AK4: Sale rank | AL4: Check
A5: =IF(B5="","",SalePrefix&TEXT(ROW()-4,"0000")) -> 0 | E5: =IF(D5="","",IFERROR(INDEX(Clients!$B$5:$B$504,MATCH(D5,Clients!$A$5:$A$504,0)),"Walk-in")) -> 0 | G5: =IF(F5="","",IFERROR(INDEX(Staff!$B$5:$B$44,MATCH(F5,Staff!$A$5:$A$44,0)),"House")) -> 0 | R5: =IF(B5="","",TEXT(B5,"yyyy-mm")) -> 0 | S5: =IF(B5="","",WEEKNUM(B5,2)) -> 0 | T5: =IF(B5="","",IF(K5="",1,K5)) -> 0 | U5: =IF(B5="","",IF(J5<>"",J5,IF(H5="Retail",IFERROR(INDEX(Inventory!$B$5:$B$304,MATCH(I5,Inventory!$A$5:$A$304,0))&"","Not in Inventory"),IFERROR(INDEX(Services!$B$5:$B$204,MATCH(I5,Services!$A$5:$A$204,0))&"","Not in Services")))) -> 0 | V5: =IF(B5="","",IF(L5<>"",L5,IF(H5="Retail",IFERROR(INDEX(Inventory!$I$5:$I$304,MATCH(I5,Inventory!$A$5:$A$304,0))*1,0),IFERROR(INDEX(Services!$G$5:$G$204,MATCH(I5,Services!$A$5:$A$204,0))*1,0)))) -> 0 | W5: =IF(B5="","",ROUND(T5*V5,2)) -> 0 | X5: =IF(B5="","",ROUND(IF(M5="",0,W5*M5)+IF(N5="",0,N5),2)) -> 0 | Y5: =IF(B5="","",ROUND(W5-X5-IF(P5="",0,P5),2)) -> 0 | Z5: =IF(B5="","",IF(H5="Retail",IF(TaxOnRetail="Yes",ROUND(Y5*TaxRate,2),0),IF(H5="Service",IF(TaxOnServices="Yes",ROUND(Y5*TaxRate,2),0),0))) -> 0 | AA5: =IF(B5="","",ROUND(Y5+Z5,2)) -> 0 | AB5: =IF(B5="","",ROUND(T5*IF(H5="Retail",IFERROR(INDEX(Inventory!$H$5:$H$304,MATCH(I5,Inventory!$A$5:$A$304,0))*1,0),IFERROR(INDEX(Services!$Q$5:$Q$204,MATCH(I5,Services!$A$5:$A$204,0))*1,0)),2)) -> 0 | AC5: =IF(B5="","",ROUND(Y5-AB5,2)) -> 0 | AD5: =IF(B5="","",IF(C5="","No",IF(COUNTIFS($C$5:C5,C5)=1,"Yes","No"))) -> 0 | AE5: =IF(B5="","",ROUND(SUMIFS(Payments!$G$5:$G$1204,Payments!$H$5:$H$1204,A5,Payments!$Q$5:$Q$1204,"Yes"),2)) -> 0 | AF5: =IF(B5="","",IF(AD5="No",0,ROUND(SUMIFS(Payments!$G$5:$G$1204,Payments!$I$5:$I$1204,C5,Payments!$H$5:$H$1204,"",Payments!$Q$5:$Q$1204,"Yes"),2))) -> 0 | AG5: =IF(B5="","",ROUND(AE5+AF5,2)) -> 0 | AH5: =IF(B5="","",ROUND(AA5-AG5,2)) -> 0 | AI5: =IF(B5="","",IF(AA5<=0,"No charge",IF(AH5<=0.004,"Paid",IF(AG5<=0.004,"Unpaid","Part paid")))) -> 0 | AJ5: =IF(B5="","",IF(H5<>"Service","",IF(D5="","No",IF(COUNTIFS($D$5:$D$1204,D5,$B$5:$B$1204,B5,$H$5:$H$1204,"Retail")>0,"Yes","No")))) -> 0 | AK5: =IF(B5="","",COUNTIFS($Y$5:$Y$1204,">"&Y5)+COUNTIFS($Y$5:Y5,Y5)) -> 0 | AL5: =IF(B5="","",IF(H5="","Add - what kind of sale is this?",IF(IF(V5<=0,P5="",FALSE),"Check - no price found for this item",IF(F5="","Assign - nobody credited",IF(AH5>0.004,"Unpaid - balance outstanding",IF(AC5<0,"Loss - sold below cost",IF(X5>W5*0.5,"Check - more than half off","OK"))))))) -> 0
A6: =IF(B6="","",SalePrefix&TEXT(ROW()-4,"0000")) -> 0 | E6: =IF(D6="","",IFERROR(INDEX(Clients!$B$5:$B$504,MATCH(D6,Clients!$A$5:$A$504,0)),"Walk-in")) -> 0 | G6: =IF(F6="","",IFERROR(INDEX(Staff!$B$5:$B$44,MATCH(F6,Staff!$A$5:$A$44,0)),"House")) -> 0 | R6: =IF(B6="","",TEXT(B6,"yyyy-mm")) -> 0 | S6: =IF(B6="","",WEEKNUM(B6,2)) -> 0 | T6: =IF(B6="","",IF(K6="",1,K6)) -> 0 | U6: =IF(B6="","",IF(J6<>"",J6,IF(H6="Retail",IFERROR(INDEX(Inventory!$B$5:$B$304,MATCH(I6,Inventory!$A$5:$A$304,0))&"","Not in Inventory"),IFERROR(INDEX(Services!$B$5:$B$204,MATCH(I6,Services!$A$5:$A$204,0))&"","Not in Services")))) -> 0 | V6: =IF(B6="","",IF(L6<>"",L6,IF(H6="Retail",IFERROR(INDEX(Inventory!$I$5:$I$304,MATCH(I6,Inventory!$A$5:$A$304,0))*1,0),IFERROR(INDEX(Services!$G$5:$G$204,MATCH(I6,Services!$A$5:$A$204,0))*1,0)))) -> 0 | W6: =IF(B6="","",ROUND(T6*V6,2)) -> 0 | X6: =IF(B6="","",ROUND(IF(M6="",0,W6*M6)+IF(N6="",0,N6),2)) -> 0 | Y6: =IF(B6="","",ROUND(W6-X6-IF(P6="",0,P6),2)) -> 0 | Z6: =IF(B6="","",IF(H6="Retail",IF(TaxOnRetail="Yes",ROUND(Y6*TaxRate,2),0),IF(H6="Service",IF(TaxOnServices="Yes",ROUND(Y6*TaxRate,2),0),0))) -> 0 | AA6: =IF(B6="","",ROUND(Y6+Z6,2)) -> 0 | AB6: =IF(B6="","",ROUND(T6*IF(H6="Retail",IFERROR(INDEX(Inventory!$H$5:$H$304,MATCH(I6,Inventory!$A$5:$A$304,0))*1,0),IFERROR(INDEX(Services!$Q$5:$Q$204,MATCH(I6,Services!$A$5:$A$204,0))*1,0)),2)) -> 0 | AC6: =IF(B6="","",ROUND(Y6-AB6,2)) -> 0 | AD6: =IF(B6="","",IF(C6="","No",IF(COUNTIFS($C$5:C6,C6)=1,"Yes","No"))) -> 0 | AE6: =IF(B6="","",ROUND(SUMIFS(Payments!$G$5:$G$1204,Payments!$H$5:$H$1204,A6,Payments!$Q$5:$Q$1204,"Yes"),2)) -> 0 | AF6: =IF(B6="","",IF(AD6="No",0,ROUND(SUMIFS(Payments!$G$5:$G$1204,Payments!$I$5:$I$1204,C6,Payments!$H$5:$H$1204,"",Payments!$Q$5:$Q$1204,"Yes"),2))) -> 0 | AG6: =IF(B6="","",ROUND(AE6+AF6,2)) -> 0 | AH6: =IF(B6="","",ROUND(AA6-AG6,2)) -> 0 | AI6: =IF(B6="","",IF(AA6<=0,"No charge",IF(AH6<=0.004,"Paid",IF(AG6<=0.004,"Unpaid","Part paid")))) -> 0 | AJ6: =IF(B6="","",IF(H6<>"Service","",IF(D6="","No",IF(COUNTIFS($D$5:$D$1204,D6,$B$5:$B$1204,B6,$H$5:$H$1204,"Retail")>0,"Yes","No")))) -> 0 | AK6: =IF(B6="","",COUNTIFS($Y$5:$Y$1204,">"&Y6)+COUNTIFS($Y$5:Y6,Y6)) -> 0 | AL6: =IF(B6="","",IF(H6="","Add - what kind of sale is this?",IF(IF(V6<=0,P6="",FALSE),"Check - no price found for this item",IF(F6="","Assign - nobody credited",IF(AH6>0.004,"Unpaid - balance outstanding",IF(AC6<0,"Loss - sold below cost",IF(X6>W6*0.5,"Check - more than half off","OK"))))))) -> 0
A7: =IF(B7="","",SalePrefix&TEXT(ROW()-4,"0000")) -> 0 | E7: =IF(D7="","",IFERROR(INDEX(Clients!$B$5:$B$504,MATCH(D7,Clients!$A$5:$A$504,0)),"Walk-in")) -> 0 | G7: =IF(F7="","",IFERROR(INDEX(Staff!$B$5:$B$44,MATCH(F7,Staff!$A$5:$A$44,0)),"House")) -> 0 | R7: =IF(B7="","",TEXT(B7,"yyyy-mm")) -> 0 | S7: =IF(B7="","",WEEKNUM(B7,2)) -> 0 | T7: =IF(B7="","",IF(K7="",1,K7)) -> 0 | U7: =IF(B7="","",IF(J7<>"",J7,IF(H7="Retail",IFERROR(INDEX(Inventory!$B$5:$B$304,MATCH(I7,Inventory!$A$5:$A$304,0))&"","Not in Inventory"),IFERROR(INDEX(Services!$B$5:$B$204,MATCH(I7,Services!$A$5:$A$204,0))&"","Not in Services")))) -> 0 | V7: =IF(B7="","",IF(L7<>"",L7,IF(H7="Retail",IFERROR(INDEX(Inventory!$I$5:$I$304,MATCH(I7,Inventory!$A$5:$A$304,0))*1,0),IFERROR(INDEX(Services!$G$5:$G$204,MATCH(I7,Services!$A$5:$A$204,0))*1,0)))) -> 0 | W7: =IF(B7="","",ROUND(T7*V7,2)) -> 0 | X7: =IF(B7="","",ROUND(IF(M7="",0,W7*M7)+IF(N7="",0,N7),2)) -> 0 | Y7: =IF(B7="","",ROUND(W7-X7-IF(P7="",0,P7),2)) -> 0 | Z7: =IF(B7="","",IF(H7="Retail",IF(TaxOnRetail="Yes",ROUND(Y7*TaxRate,2),0),IF(H7="Service",IF(TaxOnServices="Yes",ROUND(Y7*TaxRate,2),0),0))) -> 0 | AA7: =IF(B7="","",ROUND(Y7+Z7,2)) -> 0 | AB7: =IF(B7="","",ROUND(T7*IF(H7="Retail",IFERROR(INDEX(Inventory!$H$5:$H$304,MATCH(I7,Inventory!$A$5:$A$304,0))*1,0),IFERROR(INDEX(Services!$Q$5:$Q$204,MATCH(I7,Services!$A$5:$A$204,0))*1,0)),2)) -> 0 | AC7: =IF(B7="","",ROUND(Y7-AB7,2)) -> 0 | AD7: =IF(B7="","",IF(C7="","No",IF(COUNTIFS($C$5:C7,C7)=1,"Yes","No"))) -> 0 | AE7: =IF(B7="","",ROUND(SUMIFS(Payments!$G$5:$G$1204,Payments!$H$5:$H$1204,A7,Payments!$Q$5:$Q$1204,"Yes"),2)) -> 0 | AF7: =IF(B7="","",IF(AD7="No",0,ROUND(SUMIFS(Payments!$G$5:$G$1204,Payments!$I$5:$I$1204,C7,Payments!$H$5:$H$1204,"",Payments!$Q$5:$Q$1204,"Yes"),2))) -> 0 | AG7: =IF(B7="","",ROUND(AE7+AF7,2)) -> 0 | AH7: =IF(B7="","",ROUND(AA7-AG7,2)) -> 0 | AI7: =IF(B7="","",IF(AA7<=0,"No charge",IF(AH7<=0.004,"Paid",IF(AG7<=0.004,"Unpaid","Part paid")))) -> 0 | AJ7: =IF(B7="","",IF(H7<>"Service","",IF(D7="","No",IF(COUNTIFS($D$5:$D$1204,D7,$B$5:$B$1204,B7,$H$5:$H$1204,"Retail")>0,"Yes","No")))) -> 0 | AK7: =IF(B7="","",COUNTIFS($Y$5:$Y$1204,">"&Y7)+COUNTIFS($Y$5:Y7,Y7)) -> 0 | AL7: =IF(B7="","",IF(H7="","Add - what kind of sale is this?",IF(IF(V7<=0,P7="",FALSE),"Check - no price found for this item",IF(F7="","Assign - nobody credited",IF(AH7>0.004,"Unpaid - balance outstanding",IF(AC7<0,"Loss - sold below cost",IF(X7>W7*0.5,"Check - more than half off","OK"))))))) -> 0
A8: =IF(B8="","",SalePrefix&TEXT(ROW()-4,"0000")) -> 0 | E8: =IF(D8="","",IFERROR(INDEX(Clients!$B$5:$B$504,MATCH(D8,Clients!$A$5:$A$504,0)),"Walk-in")) -> 0 | G8: =IF(F8="","",IFERROR(INDEX(Staff!$B$5:$B$44,MATCH(F8,Staff!$A$5:$A$44,0)),"House")) -> 0 | R8: =IF(B8="","",TEXT(B8,"yyyy-mm")) -> 0 | S8: =IF(B8="","",WEEKNUM(B8,2)) -> 0 | T8: =IF(B8="","",IF(K8="",1,K8)) -> 0 | U8: =IF(B8="","",IF(J8<>"",J8,IF(H8="Retail",IFERROR(INDEX(Inventory!$B$5:$B$304,MATCH(I8,Inventory!$A$5:$A$304,0))&"","Not in Inventory"),IFERROR(INDEX(Services!$B$5:$B$204,MATCH(I8,Services!$A$5:$A$204,0))&"","Not in Services")))) -> 0 | V8: =IF(B8="","",IF(L8<>"",L8,IF(H8="Retail",IFERROR(INDEX(Inventory!$I$5:$I$304,MATCH(I8,Inventory!$A$5:$A$304,0))*1,0),IFERROR(INDEX(Services!$G$5:$G$204,MATCH(I8,Services!$A$5:$A$204,0))*1,0)))) -> 0 | W8: =IF(B8="","",ROUND(T8*V8,2)) -> 0 | X8: =IF(B8="","",ROUND(IF(M8="",0,W8*M8)+IF(N8="",0,N8),2)) -> 0 | Y8: =IF(B8="","",ROUND(W8-X8-IF(P8="",0,P8),2)) -> 0 | Z8: =IF(B8="","",IF(H8="Retail",IF(TaxOnRetail="Yes",ROUND(Y8*TaxRate,2),0),IF(H8="Service",IF(TaxOnServices="Yes",ROUND(Y8*TaxRate,2),0),0))) -> 0 | AA8: =IF(B8="","",ROUND(Y8+Z8,2)) -> 0 | AB8: =IF(B8="","",ROUND(T8*IF(H8="Retail",IFERROR(INDEX(Inventory!$H$5:$H$304,MATCH(I8,Inventory!$A$5:$A$304,0))*1,0),IFERROR(INDEX(Services!$Q$5:$Q$204,MATCH(I8,Services!$A$5:$A$204,0))*1,0)),2)) -> 0 | AC8: =IF(B8="","",ROUND(Y8-AB8,2)) -> 0 | AD8: =IF(B8="","",IF(C8="","No",IF(COUNTIFS($C$5:C8,C8)=1,"Yes","No"))) -> 0 | AE8: =IF(B8="","",ROUND(SUMIFS(Payments!$G$5:$G$1204,Payments!$H$5:$H$1204,A8,Payments!$Q$5:$Q$1204,"Yes"),2)) -> 0 | AF8: =IF(B8="","",IF(AD8="No",0,ROUND(SUMIFS(Payments!$G$5:$G$1204,Payments!$I$5:$I$1204,C8,Payments!$H$5:$H$1204,"",Payments!$Q$5:$Q$1204,"Yes"),2))) -> 0 | AG8: =IF(B8="","",ROUND(AE8+AF8,2)) -> 0 | AH8: =IF(B8="","",ROUND(AA8-AG8,2)) -> 0 | AI8: =IF(B8="","",IF(AA8<=0,"No charge",IF(AH8<=0.004,"Paid",IF(AG8<=0.004,"Unpaid","Part paid")))) -> 0 | AJ8: =IF(B8="","",IF(H8<>"Service","",IF(D8="","No",IF(COUNTIFS($D$5:$D$1204,D8,$B$5:$B$1204,B8,$H$5:$H$1204,"Retail")>0,"Yes","No")))) -> 0 | AK8: =IF(B8="","",COUNTIFS($Y$5:$Y$1204,">"&Y8)+COUNTIFS($Y$5:Y8,Y8)) -> 0 | AL8: =IF(B8="","",IF(H8="","Add - what kind of sale is this?",IF(IF(V8<=0,P8="",FALSE),"Check - no price found for this item",IF(F8="","Assign - nobody credited",IF(AH8>0.004,"Unpaid - balance outstanding",IF(AC8<0,"Loss - sold below cost",IF(X8>W8*0.5,"Check - more than half off","OK"))))))) -> 0
A9: =IF(B9="","",SalePrefix&TEXT(ROW()-4,"0000")) -> 0 | E9: =IF(D9="","",IFERROR(INDEX(Clients!$B$5:$B$504,MATCH(D9,Clients!$A$5:$A$504,0)),"Walk-in")) -> 0 | G9: =IF(F9="","",IFERROR(INDEX(Staff!$B$5:$B$44,MATCH(F9,Staff!$A$5:$A$44,0)),"House")) -> 0 | R9: =IF(B9="","",TEXT(B9,"yyyy-mm")) -> 0 | S9: =IF(B9="","",WEEKNUM(B9,2)) -> 0 | T9: =IF(B9="","",IF(K9="",1,K9)) -> 0 | U9: =IF(B9="","",IF(J9<>"",J9,IF(H9="Retail",IFERROR(INDEX(Inventory!$B$5:$B$304,MATCH(I9,Inventory!$A$5:$A$304,0))&"","Not in Inventory"),IFERROR(INDEX(Services!$B$5:$B$204,MATCH(I9,Services!$A$5:$A$204,0))&"","Not in Services")))) -> 0 | V9: =IF(B9="","",IF(L9<>"",L9,IF(H9="Retail",IFERROR(INDEX(Inventory!$I$5:$I$304,MATCH(I9,Inventory!$A$5:$A$304,0))*1,0),IFERROR(INDEX(Services!$G$5:$G$204,MATCH(I9,Services!$A$5:$A$204,0))*1,0)))) -> 0 | W9: =IF(B9="","",ROUND(T9*V9,2)) -> 0 | X9: =IF(B9="","",ROUND(IF(M9="",0,W9*M9)+IF(N9="",0,N9),2)) -> 0 | Y9: =IF(B9="","",ROUND(W9-X9-IF(P9="",0,P9),2)) -> 0 | Z9: =IF(B9="","",IF(H9="Retail",IF(TaxOnRetail="Yes",ROUND(Y9*TaxRate,2),0),IF(H9="Service",IF(TaxOnServices="Yes",ROUND(Y9*TaxRate,2),0),0))) -> 0 | AA9: =IF(B9="","",ROUND(Y9+Z9,2)) -> 0 | AB9: =IF(B9="","",ROUND(T9*IF(H9="Retail",IFERROR(INDEX(Inventory!$H$5:$H$304,MATCH(I9,Inventory!$A$5:$A$304,0))*1,0),IFERROR(INDEX(Services!$Q$5:$Q$204,MATCH(I9,Services!$A$5:$A$204,0))*1,0)),2)) -> 0 | AC9: =IF(B9="","",ROUND(Y9-AB9,2)) -> 0 | AD9: =IF(B9="","",IF(C9="","No",IF(COUNTIFS($C$5:C9,C9)=1,"Yes","No"))) -> 0 | AE9: =IF(B9="","",ROUND(SUMIFS(Payments!$G$5:$G$1204,Payments!$H$5:$H$1204,A9,Payments!$Q$5:$Q$1204,"Yes"),2)) -> 0 | AF9: =IF(B9="","",IF(AD9="No",0,ROUND(SUMIFS(Payments!$G$5:$G$1204,Payments!$I$5:$I$1204,C9,Payments!$H$5:$H$1204,"",Payments!$Q$5:$Q$1204,"Yes"),2))) -> 0 | AG9: =IF(B9="","",ROUND(AE9+AF9,2)) -> 0 | AH9: =IF(B9="","",ROUND(AA9-AG9,2)) -> 0 | AI9: =IF(B9="","",IF(AA9<=0,"No charge",IF(AH9<=0.004,"Paid",IF(AG9<=0.004,"Unpaid","Part paid")))) -> 0 | AJ9: =IF(B9="","",IF(H9<>"Service","",IF(D9="","No",IF(COUNTIFS($D$5:$D$1204,D9,$B$5:$B$1204,B9,$H$5:$H$1204,"Retail")>0,"Yes","No")))) -> 0 | AK9: =IF(B9="","",COUNTIFS($Y$5:$Y$1204,">"&Y9)+COUNTIFS($Y$5:Y9,Y9)) -> 0 | AL9: =IF(B9="","",IF(H9="","Add - what kind of sale is this?",IF(IF(V9<=0,P9="",FALSE),"Check - no price found for this item",IF(F9="","Assign - nobody credited",IF(AH9>0.004,"Unpaid - balance outstanding",IF(AC9<0,"Loss - sold below cost",IF(X9>W9*0.5,"Check - more than half off","OK"))))))) -> 0
A10: =IF(B10="","",SalePrefix&TEXT(ROW()-4,"0000")) -> 0 | E10: =IF(D10="","",IFERROR(INDEX(Clients!$B$5:$B$504,MATCH(D10,Clients!$A$5:$A$504,0)),"Walk-in")) -> 0 | G10: =IF(F10="","",IFERROR(INDEX(Staff!$B$5:$B$44,MATCH(F10,Staff!$A$5:$A$44,0)),"House")) -> 0 | R10: =IF(B10="","",TEXT(B10,"yyyy-mm")) -> 0 | S10: =IF(B10="","",WEEKNUM(B10,2)) -> 0 | T10: =IF(B10="","",IF(K10="",1,K10)) -> 0 | U10: =IF(B10="","",IF(J10<>"",J10,IF(H10="Retail",IFERROR(INDEX(Inventory!$B$5:$B$304,MATCH(I10,Inventory!$A$5:$A$304,0))&"","Not in Inventory"),IFERROR(INDEX(Services!$B$5:$B$204,MATCH(I10,Services!$A$5:$A$204,0))&"","Not in Services")))) -> 0 | V10: =IF(B10="","",IF(L10<>"",L10,IF(H10="Retail",IFERROR(INDEX(Inventory!$I$5:$I$304,MATCH(I10,Inventory!$A$5:$A$304,0))*1,0),IFERROR(INDEX(Services!$G$5:$G$204,MATCH(I10,Services!$A$5:$A$204,0))*1,0)))) -> 0 | W10: =IF(B10="","",ROUND(T10*V10,2)) -> 0 | X10: =IF(B10="","",ROUND(IF(M10="",0,W10*M10)+IF(N10="",0,N10),2)) -> 0 | Y10: =IF(B10="","",ROUND(W10-X10-IF(P10="",0,P10),2)) -> 0 | Z10: =IF(B10="","",IF(H10="Retail",IF(TaxOnRetail="Yes",ROUND(Y10*TaxRate,2),0),IF(H10="Service",IF(TaxOnServices="Yes",ROUND(Y10*TaxRate,2),0),0))) -> 0 | AA10: =IF(B10="","",ROUND(Y10+Z10,2)) -> 0 | AB10: =IF(B10="","",ROUND(T10*IF(H10="Retail",IFERROR(INDEX(Inventory!$H$5:$H$304,MATCH(I10,Inventory!$A$5:$A$304,0))*1,0),IFERROR(INDEX(Services!$Q$5:$Q$204,MATCH(I10,Services!$A$5:$A$204,0))*1,0)),2)) -> 0 | AC10: =IF(B10="","",ROUND(Y10-AB10,2)) -> 0 | AD10: =IF(B10="","",IF(C10="","No",IF(COUNTIFS($C$5:C10,C10)=1,"Yes","No"))) -> 0 | AE10: =IF(B10="","",ROUND(SUMIFS(Payments!$G$5:$G$1204,Payments!$H$5:$H$1204,A10,Payments!$Q$5:$Q$1204,"Yes"),2)) -> 0 | AF10: =IF(B10="","",IF(AD10="No",0,ROUND(SUMIFS(Payments!$G$5:$G$1204,Payments!$I$5:$I$1204,C10,Payments!$H$5:$H$1204,"",Payments!$Q$5:$Q$1204,"Yes"),2))) -> 0 | AG10: =IF(B10="","",ROUND(AE10+AF10,2)) -> 0 | AH10: =IF(B10="","",ROUND(AA10-AG10,2)) -> 0 | AI10: =IF(B10="","",IF(AA10<=0,"No charge",IF(AH10<=0.004,"Paid",IF(AG10<=0.004,"Unpaid","Part paid")))) -> 0 | AJ10: =IF(B10="","",IF(H10<>"Service","",IF(D10="","No",IF(COUNTIFS($D$5:$D$1204,D10,$B$5:$B$1204,B10,$H$5:$H$1204,"Retail")>0,"Yes","No")))) -> 0 | AK10: =IF(B10="","",COUNTIFS($Y$5:$Y$1204,">"&Y10)+COUNTIFS($Y$5:Y10,Y10)) -> 0 | AL10: =IF(B10="","",IF(H10="","Add - what kind of sale is this?",IF(IF(V10<=0,P10="",FALSE),"Check - no price found for this item",IF(F10="","Assign - nobody credited",IF(AH10>0.004,"Unpaid - balance outstanding",IF(AC10<0,"Loss - sold below cost",IF(X10>W10*0.5,"Check - more than half off","OK"))))))) -> 0
A11: =IF(B11="","",SalePrefix&TEXT(ROW()-4,"0000")) -> 0 | E11: =IF(D11="","",IFERROR(INDEX(Clients!$B$5:$B$504,MATCH(D11,Clients!$A$5:$A$504,0)),"Walk-in")) -> 0 | G11: =IF(F11="","",IFERROR(INDEX(Staff!$B$5:$B$44,MATCH(F11,Staff!$A$5:$A$44,0)),"House")) -> 0 | R11: =IF(B11="","",TEXT(B11,"yyyy-mm")) -> 0 | S11: =IF(B11="","",WEEKNUM(B11,2)) -> 0 | T11: =IF(B11="","",IF(K11="",1,K11)) -> 0 | U11: =IF(B11="","",IF(J11<>"",J11,IF(H11="Retail",IFERROR(INDEX(Inventory!$B$5:$B$304,MATCH(I11,Inventory!$A$5:$A$304,0))&"","Not in Inventory"),IFERROR(INDEX(Services!$B$5:$B$204,MATCH(I11,Services!$A$5:$A$204,0))&"","Not in Services")))) -> 0 | V11: =IF(B11="","",IF(L11<>"",L11,IF(H11="Retail",IFERROR(INDEX(Inventory!$I$5:$I$304,MATCH(I11,Inventory!$A$5:$A$304,0))*1,0),IFERROR(INDEX(Services!$G$5:$G$204,MATCH(I11,Services!$A$5:$A$204,0))*1,0)))) -> 0 | W11: =IF(B11="","",ROUND(T11*V11,2)) -> 0 | X11: =IF(B11="","",ROUND(IF(M11="",0,W11*M11)+IF(N11="",0,N11),2)) -> 0 | Y11: =IF(B11="","",ROUND(W11-X11-IF(P11="",0,P11),2)) -> 0 | Z11: =IF(B11="","",IF(H11="Retail",IF(TaxOnRetail="Yes",ROUND(Y11*TaxRate,2),0),IF(H11="Service",IF(TaxOnServices="Yes",ROUND(Y11*TaxRate,2),0),0))) -> 0 | AA11: =IF(B11="","",ROUND(Y11+Z11,2)) -> 0 | AB11: =IF(B11="","",ROUND(T11*IF(H11="Retail",IFERROR(INDEX(Inventory!$H$5:$H$304,MATCH(I11,Inventory!$A$5:$A$304,0))*1,0),IFERROR(INDEX(Services!$Q$5:$Q$204,MATCH(I11,Services!$A$5:$A$204,0))*1,0)),2)) -> 0 | AC11: =IF(B11="","",ROUND(Y11-AB11,2)) -> 0 | AD11: =IF(B11="","",IF(C11="","No",IF(COUNTIFS($C$5:C11,C11)=1,"Yes","No"))) -> 0 | AE11: =IF(B11="","",ROUND(SUMIFS(Payments!$G$5:$G$1204,Payments!$H$5:$H$1204,A11,Payments!$Q$5:$Q$1204,"Yes"),2)) -> 0 | AF11: =IF(B11="","",IF(AD11="No",0,ROUND(SUMIFS(Payments!$G$5:$G$1204,Payments!$I$5:$I$1204,C11,Payments!$H$5:$H$1204,"",Payments!$Q$5:$Q$1204,"Yes"),2))) -> 0 | AG11: =IF(B11="","",ROUND(AE11+AF11,2)) -> 0 | AH11: =IF(B11="","",ROUND(AA11-AG11,2)) -> 0 | AI11: =IF(B11="","",IF(AA11<=0,"No charge",IF(AH11<=0.004,"Paid",IF(AG11<=0.004,"Unpaid","Part paid")))) -> 0 | AJ11: =IF(B11="","",IF(H11<>"Service","",IF(D11="","No",IF(COUNTIFS($D$5:$D$1204,D11,$B$5:$B$1204,B11,$H$5:$H$1204,"Retail")>0,"Yes","No")))) -> 0 | AK11: =IF(B11="","",COUNTIFS($Y$5:$Y$1204,">"&Y11)+COUNTIFS($Y$5:Y11,Y11)) -> 0 | AL11: =IF(B11="","",IF(H11="","Add - what kind of sale is this?",IF(IF(V11<=0,P11="",FALSE),"Check - no price found for this item",IF(F11="","Assign - nobody credited",IF(AH11>0.004,"Unpaid - balance outstanding",IF(AC11<0,"Loss - sold below cost",IF(X11>W11*0.5,"Check - more than half off","OK"))))))) -> 0
A12: =IF(B12="","",SalePrefix&TEXT(ROW()-4,"0000")) -> 0 | E12: =IF(D12="","",IFERROR(INDEX(Clients!$B$5:$B$504,MATCH(D12,Clients!$A$5:$A$504,0)),"Walk-in")) -> 0 | G12: =IF(F12="","",IFERROR(INDEX(Staff!$B$5:$B$44,MATCH(F12,Staff!$A$5:$A$44,0)),"House")) -> 0 | R12: =IF(B12="","",TEXT(B12,"yyyy-mm")) -> 0 | S12: =IF(B12="","",WEEKNUM(B12,2)) -> 0 | T12: =IF(B12="","",IF(K12="",1,K12)) -> 0 | U12: =IF(B12="","",IF(J12<>"",J12,IF(H12="Retail",IFERROR(INDEX(Inventory!$B$5:$B$304,MATCH(I12,Inventory!$A$5:$A$304,0))&"","Not in Inventory"),IFERROR(INDEX(Services!$B$5:$B$204,MATCH(I12,Services!$A$5:$A$204,0))&"","Not in Services")))) -> 0 | V12: =IF(B12="","",IF(L12<>"",L12,IF(H12="Retail",IFERROR(INDEX(Inventory!$I$5:$I$304,MATCH(I12,Inventory!$A$5:$A$304,0))*1,0),IFERROR(INDEX(Services!$G$5:$G$204,MATCH(I12,Services!$A$5:$A$204,0))*1,0)))) -> 0 | W12: =IF(B12="","",ROUND(T12*V12,2)) -> 0 | X12: =IF(B12="","",ROUND(IF(M12="",0,W12*M12)+IF(N12="",0,N12),2)) -> 0 | Y12: =IF(B12="","",ROUND(W12-X12-IF(P12="",0,P12),2)) -> 0 | Z12: =IF(B12="","",IF(H12="Retail",IF(TaxOnRetail="Yes",ROUND(Y12*TaxRate,2),0),IF(H12="Service",IF(TaxOnServices="Yes",ROUND(Y12*TaxRate,2),0),0))) -> 0 | AA12: =IF(B12="","",ROUND(Y12+Z12,2)) -> 0 | AB12: =IF(B12="","",ROUND(T12*IF(H12="Retail",IFERROR(INDEX(Inventory!$H$5:$H$304,MATCH(I12,Inventory!$A$5:$A$304,0))*1,0),IFERROR(INDEX(Services!$Q$5:$Q$204,MATCH(I12,Services!$A$5:$A$204,0))*1,0)),2)) -> 0 | AC12: =IF(B12="","",ROUND(Y12-AB12,2)) -> 0 | AD12: =IF(B12="","",IF(C12="","No",IF(COUNTIFS($C$5:C12,C12)=1,"Yes","No"))) -> 0 | AE12: =IF(B12="","",ROUND(SUMIFS(Payments!$G$5:$G$1204,Payments!$H$5:$H$1204,A12,Payments!$Q$5:$Q$1204,"Yes"),2)) -> 0 | AF12: =IF(B12="","",IF(AD12="No",0,ROUND(SUMIFS(Payments!$G$5:$G$1204,Payments!$I$5:$I$1204,C12,Payments!$H$5:$H$1204,"",Payments!$Q$5:$Q$1204,"Yes"),2))) -> 0 | AG12: =IF(B12="","",ROUND(AE12+AF12,2)) -> 0 | AH12: =IF(B12="","",ROUND(AA12-AG12,2)) -> 0 | AI12: =IF(B12="","",IF(AA12<=0,"No charge",IF(AH12<=0.004,"Paid",IF(AG12<=0.004,"Unpaid","Part paid")))) -> 0 | AJ12: =IF(B12="","",IF(H12<>"Service","",IF(D12="","No",IF(COUNTIFS($D$5:$D$1204,D12,$B$5:$B$1204,B12,$H$5:$H$1204,"Retail")>0,"Yes","No")))) -> 0 | AK12: =IF(B12="","",COUNTIFS($Y$5:$Y$1204,">"&Y12)+COUNTIFS($Y$5:Y12,Y12)) -> 0 | AL12: =IF(B12="","",IF(H12="","Add - what kind of sale is this?",IF(IF(V12<=0,P12="",FALSE),"Check - no price found for this item",IF(F12="","Assign - nobody credited",IF(AH12>0.004,"Unpaid - balance outstanding",IF(AC12<0,"Loss - sold below cost",IF(X12>W12*0.5,"Check - more than half off","OK"))))))) -> 0
