Workbook
Name AccountNames: OFFSET(Accounts!$C$5,0,0,MAX(1,COUNTIF(Accounts!$C$5:$C$34,"?*")),1)
Name AccountTypeList: OFFSET(Lists!$D$5,0,0,MAX(1,COUNTIF(Lists!$D$5:$D$44,"?*")),1)
Name AdObjectiveList: OFFSET(Lists!$AF$5,0,0,MAX(1,COUNTIF(Lists!$AF$5:$AF$44,"?*")),1)
Name AnnualBudget: Settings!$D$44
Name ApprovalDays: Settings!$D$50
Name ApprovalStatusList: OFFSET(Lists!$V$5,0,0,MAX(1,COUNTIF(Lists!$V$5:$V$44,"?*")),1)
Name AssetIDs: OFFSET(Assets!$A$5,0,0,MAX(1,COUNTIF(Assets!$A$5:$A$254,"?*")),1)
Name AssetPrefix: Settings!$D$62
Name AssetReviewDays: Settings!$D$53
Name AssetTypeList: OFFSET(Lists!$T$5,0,0,MAX(1,COUNTIF(Lists!$T$5:$T$44,"?*")),1)
Name BrandAudience: Settings!$D$14
Name BrandEmail: Settings!$D$8
Name BrandFolder: Settings!$D$22
Name BrandFonts: Settings!$D$21
Name BrandGoal: Settings!$D$15
Name BrandHashtag: Settings!$D$16
Name BrandIndustry: Settings!$D$12
Name BrandLogo: Settings!$D$19
Name BrandName: Settings!$D$6
Name BrandNiche: Settings!$D$13
Name BrandOwner: Settings!$D$7
Name BrandPalette: Settings!$D$20
Name BrandPhone: Settings!$D$9
Name BrandShop: Settings!$D$11
Name BrandTimeZone: Settings!$D$27
Name BrandWeb: Settings!$D$10
Name BriefID: 'Print Brief'!$C$1
Name CampaignNames: OFFSET(Campaigns!$B$5,0,0,MAX(1,COUNTIF(Campaigns!$B$5:$B$64,"?*")),1)
Name CampaignPrefix: Settings!$D$61
Name CampaignStatusList: OFFSET(Lists!$P$5,0,0,MAX(1,COUNTIF(Lists!$P$5:$P$44,"?*")),1)
Name CaptionIDs: OFFSET('Caption Bank'!$A$5,0,0,MAX(1,COUNTIF('Caption Bank'!$A$5:$A$204,"?*")),1)
Name CaptionPrefix: Settings!$D$59
Name CaptionTitles: OFFSET('Caption Bank'!$B$5,0,0,MAX(1,COUNTIF('Caption Bank'!$B$5:$B$204,"?*")),1)
Name ClickGoal: Settings!$D$37
Name CollabTypeList: OFFSET(Lists!$W$5,0,0,MAX(1,COUNTIF(Lists!$W$5:$W$44,"?*")),1)
Name CompetitorNames: OFFSET(Competitors!$B$5,0,0,MAX(1,COUNTIF(Competitors!$B$5:$B$44,"?*")),1)
Name ComplianceStatusList: OFFSET(Lists!$AM$5,0,0,MAX(1,COUNTIF(Lists!$AM$5:$AM$44,"?*")),1)
Name ContentIDs: OFFSET('Content Calendar'!$A$5,0,0,MAX(1,COUNTIF('Content Calendar'!$A$5:$A$604,"?*")),1)
Name ContentPrefix: Settings!$D$57
Name ContentStatusList: OFFSET(Lists!$F$5,0,0,MAX(1,COUNTIF(Lists!$F$5:$F$44,"?*")),1)
Name ContentTitles: OFFSET('Content Calendar'!$H$5,0,0,MAX(1,COUNTIF('Content Calendar'!$H$5:$H$604,"?*")),1)
Name ConversionGoal: Settings!$D$39
Name CostCategoryList: OFFSET(Lists!$AE$5,0,0,MAX(1,COUNTIF(Lists!$AE$5:$AE$44,"?*")),1)
Name CplTarget: Settings!$D$46
Name CTAList: OFFSET(Lists!$I$5,0,0,MAX(1,COUNTIF(Lists!$I$5:$I$44,"?*")),1)
Name CurrencyCode: Settings!$D$28
Name Dash_Engagements: Dashboard!$G$15
Name Dash_Published: Dashboard!$D$10
Name Dash_Reach: Dashboard!$A$15
Name Dash_Revenue: Dashboard!$P$20
Name Dash_Spend: Dashboard!$A$25
Name DashEnd: Dashboard!$K$6
Name DashKey: Dashboard!$O$6
Name DashMonthName: Dashboard!$C$6
Name DashStart: Dashboard!$G$6
Name DifficultyList: OFFSET(Lists!$S$5,0,0,MAX(1,COUNTIF(Lists!$S$5:$S$44,"?*")),1)
Name FiscalStartMonth: Settings!$D$29
Name FollowerGoal: Settings!$D$35
Name FormatList: OFFSET(Lists!$E$5,0,0,MAX(1,COUNTIF(Lists!$E$5:$E$44,"?*")),1)
Name FrequencyList: OFFSET(Lists!$AK$5,0,0,MAX(1,COUNTIF(Lists!$AK$5:$AK$44,"?*")),1)

Sheet Start Here
A1: Social Media Content Calendar & Analytics Planner | J1: Novality Store | v1.0.0
A2: Plan a year of content, keep every caption and hashtag in one place, and see what actually worked.
A3: > Start Here | C3: > Dashboard | E3: > Calendar | G3: > Ideas | I3: > Captions | K3: > Hashtags
B5: Everything in this workbook is linked. Type something once - a post, a caption, a number from Instagram - and it appears wherever it is needed: the dashboards, the reports, the printable brief and the alerts. Cream cells are yours to fill in; grey cells are formulas and are locked so they cannot be broken by accident.
A7: Six steps to set it up
B8: Step | C8: Where | D8: What to do
B9: 1 | C9: Settings | D9: Put your brand name, handles, plan year, targets and budget in. Ten minutes, and it feeds every other tab.
B10: 2 | C10: Accounts & Brand Voice | D10: List every profile you post to, then write down how the brand sounds so captions stay consistent.
B11: 3 | C11: Personas & Content Pillars | D11: Decide who you are talking to and the five or six themes you post about. The pillars become drop downs everywhere else.
B12: 4 | C12: Idea Bank, Captions & Hashtags | D12: Dump every idea in, write captions you can reuse and build hashtag groups of 20-30 tags.
B13: 5 | C13: Content Calendar | D13: Plan the year. One row per post: date, platform, title, pillar, caption, hashtag group, asset, owner, status.
B14: 6 | C14: Analytics & Performance | D14: On the first of each month enter the account numbers, and after each post record how it did. The dashboards do the rest.
A16: The weekly rhythm
B17: MONDAY - clear the overdue list on the Dashboard, then look at the next posts due on the Workflow tab.
B18: ONE BATCH DAY - make the week's content in one sitting. It is always faster than making it one post at a time.
B19: BEFORE YOU POST - check the caption, the hashtag group, the asset and the link. The calendar flags anything missing.
B20: AFTER YOU POST - paste the link into the calendar. Two days later, add the numbers on the Performance tab.
B21: FIRST OF THE MONTH - fill in the Analytics tab (ten minutes), update your Goals, then read the Monthly Dashboard.
A23: What is in the workbook
B24: Tab | C24: What it is for
B25: Dashboard | C25: This month at a glance, with alerts and the queue
B26: Annual Dashboard | C26: The whole year, quarter by quarter
B27: Settings | C27: Your brand, targets, budget and reminder windows
B28: Lists | C28: Every drop down list - edit these to suit your business
B29: Brand Voice | C29: How the brand sounds, looks and behaves
B30: Audience Personas | C30: Who you are talking to
B31: Accounts | C31: Every profile, with a six point optimisation check
B32: Content Pillars | C32: Your themes and the mix you planned
B33: Content Calendar | C33: THE MAIN TAB - one row per post, all year
B34: Month View | C34: The same calendar laid out as a printable grid
B35: Workflow | C35: The production pipeline: what is where, what is late
... B61: Help | C61: Every question answered, including the honest limits
A63: Good to know
B64: PROTECTION - every sheet is protected so the formulas cannot be edited by accident. The password is 'premium'. Review > Unprotect Sheet if you want to change something.
B65: ADDING ROWS - every register has spare rows ready to use. Right click a row inside the list and choose Insert to add more; the formulas copy down.
B66: SORTING - use the filter arrows in the header row rather than re-sorting the sheet, so the content IDs keep matching the other tabs.
B67: DROP DOWNS - every list lives on the Lists tab. Edit it there and the drop downs follow.
B68: GOOGLE SHEETS - File > Import works, and everything except the sparklines and the sheet protection carries over.
B69: YOUR CURRENCY - set the symbol on the Settings tab, or rebuild the workbook with a different currency.
A71: What a spreadsheet can and cannot do
B72: Being straight with you: this workbook organises your content and does the maths on the numbers you give it. It cannot pull your analytics automatically, it cannot publish or schedule posts, and it does not talk to Instagram, TikTok, Pinterest, YouTube or Facebook. You copy the headline numbers in once a month - about ten minutes - and in return you get a plan, a history and a set of dashboards no scheduling app will give you. If you want automatic posting, pair this with a scheduler; if you want automatic analytics, export a CSV from the platform and paste it in.
B74: Social Media Content Calendar & Analytics Planner | Novality Store | version 1.0.0

Sheet Dashboard
A1: Monthly Dashboard | P1: Novality Store | v1.0.0
A2: Pick a month, then read your whole social media presence at a glance. Every number is live - it updates as you fill in the calendar and the Analytics tab.
A3: > Start Here | C3: > Dashboard | E3: > Calendar | G3: > Ideas | I3: > Captions | K3: > Hashtags | M3: > Analytics | O3: > Reports | Q3: > Help
A5: Which month are you looking at?
A6: Month | C6: October | E6: Period start | G6: =IF(DashMonthName="All year",DATE(PlanYear,1,1),DATE(PlanYear,MAX(1,MATCH(DashMonthName,MonthList,0)-1),1)) -> 0 | I6: Period end | K6: =IF(DashMonthName="All year",DATE(PlanYear,12,31),EOMONTH(DashStart,0)) -> 0 | M6: Month key | O6: =TEXT(DashStart,"yyyy-mm") -> 0 | Q6: Today | R6: =TODAY() -> 0
A8: What you published
A9: Posts planned | D9: Published | G9: Still to come | J9: Target for the month | M9: Against target | P9: Needing attention
A10: =COUNTIFS('Content Calendar'!$B$5:$B$604,">="&DashStart,'Content Calendar'!$B$5:$B$604,"<="&DashEnd) -> 0 | D10: =COUNTIFS('Content Calendar'!$B$5:$B$604,">="&DashStart,'Content Calendar'!$B$5:$B$604,"<="&DashEnd,'Content Calendar'!$X$5:$X$604,"Published") -> 0 | G10: =COUNTIFS('Content Calendar'!$B$5:$B$604,">="&DashStart,'Content Calendar'!$B$5:$B$604,"<="&DashEnd,'Content Calendar'!$X$5:$X$604,"Scheduled")+COUNTIFS('Content Calendar'!$B$5:$B$604,">="&DashStart,'Content Calendar'!$B$5:$B$604,"<="&DashEnd,'Content Calendar'!$X$5:$X$604,"Approved") -> 0 | J10: =IF(DashMonthName="All year",MonthlyPostTarget*12,MonthlyPostTarget) -> 0 | M10: =IFERROR(Dash_Published/IF(DashMonthName="All year",MonthlyPostTarget*12,MonthlyPostTarget),0) -> 0 | P10: =COUNTIFS('Content Calendar'!$AM$5:$AM$604,"<>OK",'Content Calendar'!$H$5:$H$604,"<>") -> 0
A11: Everything on the calendar in this period | D11: Actually went out | G11: Approved or scheduled, not yet live | J11: From the Settings tab | M11: Published divided by your target | P11: Rows with an action in the last column
A13: How it performed
A14: Reach | D14: Impressions | G14: Engagements | J14: Engagement rate | M14: Target rate | P14: Reach per post
A15: =SUMIFS(Analytics!$J$5:$J$154,Analytics!$B$5:$B$154,">="&DashStart,Analytics!$B$5:$B$154,"<="&DashEnd) -> 0 | D15: =SUMIFS(Analytics!$K$5:$K$154,Analytics!$B$5:$B$154,">="&DashStart,Analytics!$B$5:$B$154,"<="&DashEnd) -> 0 | G15: =SUMIFS(Analytics!$L$5:$L$154,Analytics!$B$5:$B$154,">="&DashStart,Analytics!$B$5:$B$154,"<="&DashEnd) -> 0 | J15: =IFERROR(Dash_Engagements/Dash_Reach,0) -> 0 | M15: =TargetEngagement -> 0 | P15: =IFERROR(Dash_Reach/Dash_Published,0) -> 0
A16: People reached across every account | D16: Times your content was shown | G16: Likes, comments, shares and saves | J16: Engagements divided by reach | M16: Your goal, set on the Settings tab | P16: How far the average post travelled
A18: Audience & results
A19: Followers | D19: Follower growth | G19: Link clicks | J19: Leads | M19: Sales | P19: Revenue
A20: =SUMIFS(Analytics!$G$5:$G$154,Analytics!$B$5:$B$154,">="&DashStart,Analytics!$B$5:$B$154,"<="&DashEnd) -> 0 | D20: =SUMIFS(Analytics!$X$5:$X$154,Analytics!$B$5:$B$154,">="&DashStart,Analytics!$B$5:$B$154,"<="&DashEnd) -> 0 | G20: =SUMIFS(Analytics!$R$5:$R$154,Analytics!$B$5:$B$154,">="&DashStart,Analytics!$B$5:$B$154,"<="&DashEnd) -> 0 | J20: =SUMIFS(Analytics!$S$5:$S$154,Analytics!$B$5:$B$154,">="&DashStart,Analytics!$B$5:$B$154,"<="&DashEnd) -> 0 | M20: =SUMIFS(Analytics!$T$5:$T$154,Analytics!$B$5:$B$154,">="&DashStart,Analytics!$B$5:$B$154,"<="&DashEnd) -> 0 | P20: =SUMIFS(Analytics!$U$5:$U$154,Analytics!$B$5:$B$154,">="&DashStart,Analytics!$B$5:$B$154,"<="&DashEnd) -> 0
A21: Total across every account at the end of the period | D21: New followers less unfollows | G21: Traffic you sent out | J21: Sign-ups, enquiries, waitlist joins | M21: Orders you can trace back to social | P21: Money attributed to social
A23: What it cost
A24: Spend | D24: Budget | G24: Left to spend | J24: Return on spend | M24: Cost per lead | P24: Revenue per post
A25: =SUMIFS(Budget!$H$5:$H$64,Budget!$B$5:$B$64,">="&DashStart,Budget!$B$5:$B$64,"<="&DashEnd) -> 0 | D25: =IF(DashMonthName="All year",AnnualBudget,MonthlyBudget) -> 0 | G25: =IF(DashMonthName="All year",AnnualBudget,MonthlyBudget)-Dash_Spend -> 0 | J25: =IFERROR(Dash_Revenue/Dash_Spend,0) -> 0 | M25: =IFERROR(Dash_Spend/SUMIFS(Analytics!$S$5:$S$154,Analytics!$B$5:$B$154,">="&DashStart,Analytics!$B$5:$B$154,"<="&DashEnd),0) -> 0 | P25: =IFERROR(Dash_Revenue/Dash_Published,0) -> 0
A26: Everything on the Budget tab for this period | D26: From the Settings tab | G26: Budget less actual spend | J26: Revenue divided by spend | M26: Spend divided by leads | P26: Money per published post
A28: The whole of 2026 month by month
A29: Month | B29: Published | C29: Reach | D29: Engagements | E29: Eng. rate | F29: Followers | G29: Growth | H29: Clicks | I29: Leads | J29: Sales | K29: Revenue | L29: Spend | M29: Net
A30: =Calc!$D$5 -> 0 | B30: =Calc!$F$5 -> 0 | C30: =Calc!$G$5 -> 0 | D30: =Calc!$I$5 -> 0 | E30: =Calc!$J$5 -> 0 | F30: =Calc!$K$5 -> 0 | G30: =Calc!$L$5 -> 0 | H30: =Calc!$M$5 -> 0 | I30: =Calc!$N$5 -> 0 | J30: =Calc!$O$5 -> 0 | K30: =Calc!$P$5 -> 0 | L30: =Calc!$Q$5 -> 0 | M30: =Calc!$R$5 -> 0
A31: =Calc!$D$6 -> 0 | B31: =Calc!$F$6 -> 0 | C31: =Calc!$G$6 -> 0 | D31: =Calc!$I$6 -> 0 | E31: =Calc!$J$6 -> 0 | F31: =Calc!$K$6 -> 0 | G31: =Calc!$L$6 -> 0 | H31: =Calc!$M$6 -> 0 | I31: =Calc!$N$6 -> 0 | J31: =Calc!$O$6 -> 0 | K31: =Calc!$P$6 -> 0 | L31: =Calc!$Q$6 -> 0 | M31: =Calc!$R$6 -> 0
A32: =Calc!$D$7 -> 0 | B32: =Calc!$F$7 -> 0 | C32: =Calc!$G$7 -> 0 | D32: =Calc!$I$7 -> 0 | E32: =Calc!$J$7 -> 0 | F32: =Calc!$K$7 -> 0 | G32: =Calc!$L$7 -> 0 | H32: =Calc!$M$7 -> 0 | I32: =Calc!$N$7 -> 0 | J32: =Calc!$O$7 -> 0 | K32: =Calc!$P$7 -> 0 | L32: =Calc!$Q$7 -> 0 | M32: =Calc!$R$7 -> 0
A33: =Calc!$D$8 -> 0 | B33: =Calc!$F$8 -> 0 | C33: =Calc!$G$8 -> 0 | D33: =Calc!$I$8 -> 0 | E33: =Calc!$J$8 -> 0 | F33: =Calc!$K$8 -> 0 | G33: =Calc!$L$8 -> 0 | H33: =Calc!$M$8 -> 0 | I33: =Calc!$N$8 -> 0 | J33: =Calc!$O$8 -> 0 | K33: =Calc!$P$8 -> 0 | L33: =Calc!$Q$8 -> 0 | M33: =Calc!$R$8 -> 0
A34: =Calc!$D$9 -> 0 | B34: =Calc!$F$9 -> 0 | C34: =Calc!$G$9 -> 0 | D34: =Calc!$I$9 -> 0 | E34: =Calc!$J$9 -> 0 | F34: =Calc!$K$9 -> 0 | G34: =Calc!$L$9 -> 0 | H34: =Calc!$M$9 -> 0 | I34: =Calc!$N$9 -> 0 | J34: =Calc!$O$9 -> 0 | K34: =Calc!$P$9 -> 0 | L34: =Calc!$Q$9 -> 0 | M34: =Calc!$R$9 -> 0
A35: =Calc!$D$10 -> 0 | B35: =Calc!$F$10 -> 0 | C35: =Calc!$G$10 -> 0 | D35: =Calc!$I$10 -> 0 | E35: =Calc!$J$10 -> 0 | F35: =Calc!$K$10 -> 0 | G35: =Calc!$L$10 -> 0 | H35: =Calc!$M$10 -> 0 | I35: =Calc!$N$10 -> 0 | J35: =Calc!$O$10 -> 0 | K35: =Calc!$P$10 -> 0 | L35: =Calc!$Q$10 -> 0 | M35: =Calc!$R$10 -> 0
A36: =Calc!$D$11 -> 0 | B36: =Calc!$F$11 -> 0 | C36: =Calc!$G$11 -> 0 | D36: =Calc!$I$11 -> 0 | E36: =Calc!$J$11 -> 0 | F36: =Calc!$K$11 -> 0 | G36: =Calc!$L$11 -> 0 | H36: =Calc!$M$11 -> 0 | I36: =Calc!$N$11 -> 0 | J36: =Calc!$O$11 -> 0 | K36: =Calc!$P$11 -> 0 | L36: =Calc!$Q$11 -> 0 | M36: =Calc!$R$11 -> 0
A37: =Calc!$D$12 -> 0 | B37: =Calc!$F$12 -> 0 | C37: =Calc!$G$12 -> 0 | D37: =Calc!$I$12 -> 0 | E37: =Calc!$J$12 -> 0 | F37: =Calc!$K$12 -> 0 | G37: =Calc!$L$12 -> 0 | H37: =Calc!$M$12 -> 0 | I37: =Calc!$N$12 -> 0 | J37: =Calc!$O$12 -> 0 | K37: =Calc!$P$12 -> 0 | L37: =Calc!$Q$12 -> 0 | M37: =Calc!$R$12 -> 0
A38: =Calc!$D$13 -> 0 | B38: =Calc!$F$13 -> 0 | C38: =Calc!$G$13 -> 0 | D38: =Calc!$I$13 -> 0 | E38: =Calc!$J$13 -> 0 | F38: =Calc!$K$13 -> 0 | G38: =Calc!$L$13 -> 0 | H38: =Calc!$M$13 -> 0 | I38: =Calc!$N$13 -> 0 | J38: =Calc!$O$13 -> 0 | K38: =Calc!$P$13 -> 0 | L38: =Calc!$Q$13 -> 0 | M38: =Calc!$R$13 -> 0
A39: =Calc!$D$14 -> 0 | B39: =Calc!$F$14 -> 0 | C39: =Calc!$G$14 -> 0 | D39: =Calc!$I$14 -> 0 | E39: =Calc!$J$14 -> 0 | F39: =Calc!$K$14 -> 0 | G39: =Calc!$L$14 -> 0 | H39: =Calc!$M$14 -> 0 | I39: =Calc!$N$14 -> 0 | J39: =Calc!$O$14 -> 0 | K39: =Calc!$P$14 -> 0 | L39: =Calc!$Q$14 -> 0 | M39: =Calc!$R$14 -> 0
A40: =Calc!$D$15 -> 0 | B40: =Calc!$F$15 -> 0 | C40: =Calc!$G$15 -> 0 | D40: =Calc!$I$15 -> 0 | E40: =Calc!$J$15 -> 0 | F40: =Calc!$K$15 -> 0 | G40: =Calc!$L$15 -> 0 | H40: =Calc!$M$15 -> 0 | I40: =Calc!$N$15 -> 0 | J40: =Calc!$O$15 -> 0 | K40: =Calc!$P$15 -> 0 | L40: =Calc!$Q$15 -> 0 | M40: =Calc!$R$15 -> 0
A41: =Calc!$D$16 -> 0 | B41: =Calc!$F$16 -> 0 | C41: =Calc!$G$16 -> 0 | D41: =Calc!$I$16 -> 0 | E41: =Calc!$J$16 -> 0 | F41: =Calc!$K$16 -> 0 | G41: =Calc!$L$16 -> 0 | H41: =Calc!$M$16 -> 0 | I41: =Calc!$N$16 -> 0 | J41: =Calc!$O$16 -> 0 | K41: =Calc!$P$16 -> 0 | L41: =Calc!$Q$16 -> 0 | M41: =Calc!$R$16 -> 0
A42: Trend
A44: Platform by platform (selected period) | K44: Content pillars (this year)
A45: Platform | B45: Posts | C45: Reach | D45: Engagements | E45: Eng. rate | F45: Followers | G45: Growth | H45: Clicks | I45: Revenue | K45: Pillar | L45: Posts | M45: Reach | N45: Engagements | O45: Eng. rate | P45: Share
A46: =IF(Calc!$T$5="","",Calc!$T$5) -> 0 | B46: =IF(Calc!$T$5="","",Calc!$V$5) -> 0 | C46: =IF(Calc!$T$5="","",Calc!$W$5) -> 0 | D46: =IF(Calc!$T$5="","",Calc!$X$5) -> 0 | E46: =IF(Calc!$T$5="","",Calc!$Y$5) -> 0 | F46: =IF(Calc!$T$5="","",Calc!$Z$5) -> 0 | G46: =IF(Calc!$T$5="","",Calc!$AA$5) -> 0 | H46: =IF(Calc!$T$5="","",Calc!$AB$5) -> 0 | I46: =IF(Calc!$T$5="","",Calc!$AC$5) -> 0 | K46: =IF(Calc!$AJ$5="","",Calc!$AJ$5) -> 0 | L46: =IF(Calc!$AJ$5="","",Calc!$AK$5) -> 0 | M46: =IF(Calc!$AJ$5="","",Calc!$AL$5) -> 0 | N46: =IF(Calc!$AJ$5="","",Calc!$AM$5) -> 0 | O46: =IF(Calc!$AJ$5="","",Calc!$AN$5) -> 0 | P46: =IFERROR(Calc!$AK$5/SUM(Calc!$AK$5:$AK$604),"") -> 0
A47: =IF(Calc!$T$6="","",Calc!$T$6) -> 0 | B47: =IF(Calc!$T$6="","",Calc!$V$6) -> 0 | C47: =IF(Calc!$T$6="","",Calc!$W$6) -> 0 | D47: =IF(Calc!$T$6="","",Calc!$X$6) -> 0 | E47: =IF(Calc!$T$6="","",Calc!$Y$6) -> 0 | F47: =IF(Calc!$T$6="","",Calc!$Z$6) -> 0 | G47: =IF(Calc!$T$6="","",Calc!$AA$6) -> 0 | H47: =IF(Calc!$T$6="","",Calc!$AB$6) -> 0 | I47: =IF(Calc!$T$6="","",Calc!$AC$6) -> 0 | K47: =IF(Calc!$AJ$6="","",Calc!$AJ$6) -> 0 | L47: =IF(Calc!$AJ$6="","",Calc!$AK$6) -> 0 | M47: =IF(Calc!$AJ$6="","",Calc!$AL$6) -> 0 | N47: =IF(Calc!$AJ$6="","",Calc!$AM$6) -> 0 | O47: =IF(Calc!$AJ$6="","",Calc!$AN$6) -> 0 | P47: =IFERROR(Calc!$AK$6/SUM(Calc!$AK$5:$AK$604),"") -> 0
A48: =IF(Calc!$T$7="","",Calc!$T$7) -> 0 | B48: =IF(Calc!$T$7="","",Calc!$V$7) -> 0 | C48: =IF(Calc!$T$7="","",Calc!$W$7) -> 0 | D48: =IF(Calc!$T$7="","",Calc!$X$7) -> 0 | E48: =IF(Calc!$T$7="","",Calc!$Y$7) -> 0 | F48: =IF(Calc!$T$7="","",Calc!$Z$7) -> 0 | G48: =IF(Calc!$T$7="","",Calc!$AA$7) -> 0 | H48: =IF(Calc!$T$7="","",Calc!$AB$7) -> 0 | I48: =IF(Calc!$T$7="","",Calc!$AC$7) -> 0 | K48: =IF(Calc!$AJ$7="","",Calc!$AJ$7) -> 0 | L48: =IF(Calc!$AJ$7="","",Calc!$AK$7) -> 0 | M48: =IF(Calc!$AJ$7="","",Calc!$AL$7) -> 0 | N48: =IF(Calc!$AJ$7="","",Calc!$AM$7) -> 0 | O48: =IF(Calc!$AJ$7="","",Calc!$AN$7) -> 0 | P48: =IFERROR(Calc!$AK$7/SUM(Calc!$AK$5:$AK$604),"") -> 0
A49: =IF(Calc!$T$8="","",Calc!$T$8) -> 0 | B49: =IF(Calc!$T$8="","",Calc!$V$8) -> 0 | C49: =IF(Calc!$T$8="","",Calc!$W$8) -> 0 | D49: =IF(Calc!$T$8="","",Calc!$X$8) -> 0 | E49: =IF(Calc!$T$8="","",Calc!$Y$8) -> 0 | F49: =IF(Calc!$T$8="","",Calc!$Z$8) -> 0 | G49: =IF(Calc!$T$8="","",Calc!$AA$8) -> 0 | H49: =IF(Calc!$T$8="","",Calc!$AB$8) -> 0 | I49: =IF(Calc!$T$8="","",Calc!$AC$8) -> 0 | K49: =IF(Calc!$AJ$8="","",Calc!$AJ$8) -> 0 | L49: =IF(Calc!$AJ$8="","",Calc!$AK$8) -> 0 | M49: =IF(Calc!$AJ$8="","",Calc!$AL$8) -> 0 | N49: =IF(Calc!$AJ$8="","",Calc!$AM$8) -> 0 | O49: =IF(Calc!$AJ$8="","",Calc!$AN$8) -> 0 | P49: =IFERROR(Calc!$AK$8/SUM(Calc!$AK$5:$AK$604),"") -> 0
A50: =IF(Calc!$T$9="","",Calc!$T$9) -> 0 | B50: =IF(Calc!$T$9="","",Calc!$V$9) -> 0 | C50: =IF(Calc!$T$9="","",Calc!$W$9) -> 0 | D50: =IF(Calc!$T$9="","",Calc!$X$9) -> 0 | E50: =IF(Calc!$T$9="","",Calc!$Y$9) -> 0 | F50: =IF(Calc!$T$9="","",Calc!$Z$9) -> 0 | G50: =IF(Calc!$T$9="","",Calc!$AA$9) -> 0 | H50: =IF(Calc!$T$9="","",Calc!$AB$9) -> 0 | I50: =IF(Calc!$T$9="","",Calc!$AC$9) -> 0 | K50: =IF(Calc!$AJ$9="","",Calc!$AJ$9) -> 0 | L50: =IF(Calc!$AJ$9="","",Calc!$AK$9) -> 0 | M50: =IF(Calc!$AJ$9="","",Calc!$AL$9) -> 0 | N50: =IF(Calc!$AJ$9="","",Calc!$AM$9) -> 0 | O50: =IF(Calc!$AJ$9="","",Calc!$AN$9) -> 0 | P50: =IFERROR(Calc!$AK$9/SUM(Calc!$AK$5:$AK$604),"") -> 0
A51: =IF(Calc!$T$10="","",Calc!$T$10) -> 0 | B51: =IF(Calc!$T$10="","",Calc!$V$10) -> 0 | C51: =IF(Calc!$T$10="","",Calc!$W$10) -> 0 | D51: =IF(Calc!$T$10="","",Calc!$X$10) -> 0 | E51: =IF(Calc!$T$10="","",Calc!$Y$10) -> 0 | F51: =IF(Calc!$T$10="","",Calc!$Z$10) -> 0 | G51: =IF(Calc!$T$10="","",Calc!$AA$10) -> 0 | H51: =IF(Calc!$T$10="","",Calc!$AB$10) -> 0 | I51: =IF(Calc!$T$10="","",Calc!$AC$10) -> 0 | K51: =IF(Calc!$AJ$10="","",Calc!$AJ$10) -> 0 | L51: =IF(Calc!$AJ$10="","",Calc!$AK$10) -> 0 | M51: =IF(Calc!$AJ$10="","",Calc!$AL$10) -> 0 | N51: =IF(Calc!$AJ$10="","",Calc!$AM$10) -> 0 | O51: =IF(Calc!$AJ$10="","",Calc!$AN$10) -> 0 | P51: =IFERROR(Calc!$AK$10/SUM(Calc!$AK$5:$AK$604),"") -> 0
A52: =IF(Calc!$T$11="","",Calc!$T$11) -> 0 | B52: =IF(Calc!$T$11="","",Calc!$V$11) -> 0 | C52: =IF(Calc!$T$11="","",Calc!$W$11) -> 0 | D52: =IF(Calc!$T$11="","",Calc!$X$11) -> 0 | E52: =IF(Calc!$T$11="","",Calc!$Y$11) -> 0 | F52: =IF(Calc!$T$11="","",Calc!$Z$11) -> 0 | G52: =IF(Calc!$T$11="","",Calc!$AA$11) -> 0 | H52: =IF(Calc!$T$11="","",Calc!$AB$11) -> 0 | I52: =IF(Calc!$T$11="","",Calc!$AC$11) -> 0 | K52: =IF(Calc!$AJ$11="","",Calc!$AJ$11) -> 0 | L52: =IF(Calc!$AJ$11="","",Calc!$AK$11) -> 0 | M52: =IF(Calc!$AJ$11="","",Calc!$AL$11) -> 0 | N52: =IF(Calc!$AJ$11="","",Calc!$AM$11) -> 0 | O52: =IF(Calc!$AJ$11="","",Calc!$AN$11) -> 0 | P52: =IFERROR(Calc!$AK$11/SUM(Calc!$AK$5:$AK$604),"") -> 0
A53: =IF(Calc!$T$12="","",Calc!$T$12) -> 0 | B53: =IF(Calc!$T$12="","",Calc!$V$12) -> 0 | C53: =IF(Calc!$T$12="","",Calc!$W$12) -> 0 | D53: =IF(Calc!$T$12="","",Calc!$X$12) -> 0 | E53: =IF(Calc!$T$12="","",Calc!$Y$12) -> 0 | F53: =IF(Calc!$T$12="","",Calc!$Z$12) -> 0 | G53: =IF(Calc!$T$12="","",Calc!$AA$12) -> 0 | H53: =IF(Calc!$T$12="","",Calc!$AB$12) -> 0 | I53: =IF(Calc!$T$12="","",Calc!$AC$12) -> 0 | K53: =IF(Calc!$AJ$12="","",Calc!$AJ$12) -> 0 | L53: =IF(Calc!$AJ$12="","",Calc!$AK$12) -> 0 | M53: =IF(Calc!$AJ$12="","",Calc!$AL$12) -> 0 | N53: =IF(Calc!$AJ$12="","",Calc!$AM$12) -> 0 | O53: =IF(Calc!$AJ$12="","",Calc!$AN$12) -> 0 | P53: =IFERROR(Calc!$AK$12/SUM(Calc!$AK$5:$AK$604),"") -> 0
A55: Your best posts & what needs doing
A56: Top 8 posts in this period (by engagement rate) | K56: What needs attention right now
A57: # | B57: Post | C57: Platform | D57: Pillar | E57: Date | F57: Reach | G57: Eng. rate | K57: Action | L57: How many
A58: 1 | B58: =IFERROR(INDEX(Calc!$BH$5:$BH$604,MATCH(LARGE(Calc!$BO$5:$BO$604,1),Calc!$BO$5:$BO$604,0)),"") -> 0 | C58: =IFERROR(INDEX(Calc!$BI$5:$BI$604,MATCH(LARGE(Calc!$BO$5:$BO$604,1),Calc!$BO$5:$BO$604,0)),"") -> 0 | D58: =IFERROR(INDEX(Calc!$BJ$5:$BJ$604,MATCH(LARGE(Calc!$BO$5:$BO$604,1),Calc!$BO$5:$BO$604,0)),"") -> 0 | E58: =IFERROR(INDEX(Calc!$BK$5:$BK$604,MATCH(LARGE(Calc!$BO$5:$BO$604,1),Calc!$BO$5:$BO$604,0)),"") -> 0 | F58: =IFERROR(INDEX(Calc!$BM$5:$BM$604,MATCH(LARGE(Calc!$BO$5:$BO$604,1),Calc!$BO$5:$BO$604,0)),"") -> 0 | G58: =IFERROR(INDEX(Calc!$BN$5:$BN$604,MATCH(LARGE(Calc!$BO$5:$BO$604,1),Calc!$BO$5:$BO$604,0)),"") -> 0 | K58: Posts overdue | L58: =COUNTIF('Content Calendar'!$AM$5:$AM$604,"Overdue*") -> 0
A59: 2 | B59: =IFERROR(INDEX(Calc!$BH$5:$BH$604,MATCH(LARGE(Calc!$BO$5:$BO$604,2),Calc!$BO$5:$BO$604,0)),"") -> 0 | C59: =IFERROR(INDEX(Calc!$BI$5:$BI$604,MATCH(LARGE(Calc!$BO$5:$BO$604,2),Calc!$BO$5:$BO$604,0)),"") -> 0 | D59: =IFERROR(INDEX(Calc!$BJ$5:$BJ$604,MATCH(LARGE(Calc!$BO$5:$BO$604,2),Calc!$BO$5:$BO$604,0)),"") -> 0 | E59: =IFERROR(INDEX(Calc!$BK$5:$BK$604,MATCH(LARGE(Calc!$BO$5:$BO$604,2),Calc!$BO$5:$BO$604,0)),"") -> 0 | F59: =IFERROR(INDEX(Calc!$BM$5:$BM$604,MATCH(LARGE(Calc!$BO$5:$BO$604,2),Calc!$BO$5:$BO$604,0)),"") -> 0 | G59: =IFERROR(INDEX(Calc!$BN$5:$BN$604,MATCH(LARGE(Calc!$BO$5:$BO$604,2),Calc!$BO$5:$BO$604,0)),"") -> 0 | K59: Drafts running late | L59: =COUNTIF('Content Calendar'!$AM$5:$AM$604,"Late*") -> 0
A60: 3 | B60: =IFERROR(INDEX(Calc!$BH$5:$BH$604,MATCH(LARGE(Calc!$BO$5:$BO$604,3),Calc!$BO$5:$BO$604,0)),"") -> 0 | C60: =IFERROR(INDEX(Calc!$BI$5:$BI$604,MATCH(LARGE(Calc!$BO$5:$BO$604,3),Calc!$BO$5:$BO$604,0)),"") -> 0 | D60: =IFERROR(INDEX(Calc!$BJ$5:$BJ$604,MATCH(LARGE(Calc!$BO$5:$BO$604,3),Calc!$BO$5:$BO$604,0)),"") -> 0 | E60: =IFERROR(INDEX(Calc!$BK$5:$BK$604,MATCH(LARGE(Calc!$BO$5:$BO$604,3),Calc!$BO$5:$BO$604,0)),"") -> 0 | F60: =IFERROR(INDEX(Calc!$BM$5:$BM$604,MATCH(LARGE(Calc!$BO$5:$BO$604,3),Calc!$BO$5:$BO$604,0)),"") -> 0 | G60: =IFERROR(INDEX(Calc!$BN$5:$BN$604,MATCH(LARGE(Calc!$BO$5:$BO$604,3),Calc!$BO$5:$BO$604,0)),"") -> 0 | K60: Waiting for approval | L60: =COUNTIF('Content Calendar'!$X$5:$X$604,"Awaiting review") -> 0
A61: 4 | B61: =IFERROR(INDEX(Calc!$BH$5:$BH$604,MATCH(LARGE(Calc!$BO$5:$BO$604,4),Calc!$BO$5:$BO$604,0)),"") -> 0 | C61: =IFERROR(INDEX(Calc!$BI$5:$BI$604,MATCH(LARGE(Calc!$BO$5:$BO$604,4),Calc!$BO$5:$BO$604,0)),"") -> 0 | D61: =IFERROR(INDEX(Calc!$BJ$5:$BJ$604,MATCH(LARGE(Calc!$BO$5:$BO$604,4),Calc!$BO$5:$BO$604,0)),"") -> 0 | E61: =IFERROR(INDEX(Calc!$BK$5:$BK$604,MATCH(LARGE(Calc!$BO$5:$BO$604,4),Calc!$BO$5:$BO$604,0)),"") -> 0 | F61: =IFERROR(INDEX(Calc!$BM$5:$BM$604,MATCH(LARGE(Calc!$BO$5:$BO$604,4),Calc!$BO$5:$BO$604,0)),"") -> 0 | G61: =IFERROR(INDEX(Calc!$BN$5:$BN$604,MATCH(LARGE(Calc!$BO$5:$BO$604,4),Calc!$BO$5:$BO$604,0)),"") -> 0 | K61: Posts with no caption | L61: =COUNTIFS('Content Calendar'!$H$5:$H$604,"<>",'Content Calendar'!$P$5:$P$604,"") -> 0
A62: 5 | B62: =IFERROR(INDEX(Calc!$BH$5:$BH$604,MATCH(LARGE(Calc!$BO$5:$BO$604,5),Calc!$BO$5:$BO$604,0)),"") -> 0 | C62: =IFERROR(INDEX(Calc!$BI$5:$BI$604,MATCH(LARGE(Calc!$BO$5:$BO$604,5),Calc!$BO$5:$BO$604,0)),"") -> 0 | D62: =IFERROR(INDEX(Calc!$BJ$5:$BJ$604,MATCH(LARGE(Calc!$BO$5:$BO$604,5),Calc!$BO$5:$BO$604,0)),"") -> 0 | E62: =IFERROR(INDEX(Calc!$BK$5:$BK$604,MATCH(LARGE(Calc!$BO$5:$BO$604,5),Calc!$BO$5:$BO$604,0)),"") -> 0 | F62: =IFERROR(INDEX(Calc!$BM$5:$BM$604,MATCH(LARGE(Calc!$BO$5:$BO$604,5),Calc!$BO$5:$BO$604,0)),"") -> 0 | G62: =IFERROR(INDEX(Calc!$BN$5:$BN$604,MATCH(LARGE(Calc!$BO$5:$BO$604,5),Calc!$BO$5:$BO$604,0)),"") -> 0 | K62: Published with no link | L62: =COUNTIF('Content Calendar'!$AC$5:$AC$604,"Add*") -> 0
A63: 6 | B63: =IFERROR(INDEX(Calc!$BH$5:$BH$604,MATCH(LARGE(Calc!$BO$5:$BO$604,6),Calc!$BO$5:$BO$604,0)),"") -> 0 | C63: =IFERROR(INDEX(Calc!$BI$5:$BI$604,MATCH(LARGE(Calc!$BO$5:$BO$604,6),Calc!$BO$5:$BO$604,0)),"") -> 0 | D63: =IFERROR(INDEX(Calc!$BJ$5:$BJ$604,MATCH(LARGE(Calc!$BO$5:$BO$604,6),Calc!$BO$5:$BO$604,0)),"") -> 0 | E63: =IFERROR(INDEX(Calc!$BK$5:$BK$604,MATCH(LARGE(Calc!$BO$5:$BO$604,6),Calc!$BO$5:$BO$604,0)),"") -> 0 | F63: =IFERROR(INDEX(Calc!$BM$5:$BM$604,MATCH(LARGE(Calc!$BO$5:$BO$604,6),Calc!$BO$5:$BO$604,0)),"") -> 0 | G63: =IFERROR(INDEX(Calc!$BN$5:$BN$604,MATCH(LARGE(Calc!$BO$5:$BO$604,6),Calc!$BO$5:$BO$604,0)),"") -> 0 | K63: Published with no numbers yet | L63: =COUNTIFS('Content Calendar'!$X$5:$X$604,"Published",'Content Calendar'!$AD$5:$AD$604,"") -> 0
A64: 7 | B64: =IFERROR(INDEX(Calc!$BH$5:$BH$604,MATCH(LARGE(Calc!$BO$5:$BO$604,7),Calc!$BO$5:$BO$604,0)),"") -> 0 | C64: =IFERROR(INDEX(Calc!$BI$5:$BI$604,MATCH(LARGE(Calc!$BO$5:$BO$604,7),Calc!$BO$5:$BO$604,0)),"") -> 0 | D64: =IFERROR(INDEX(Calc!$BJ$5:$BJ$604,MATCH(LARGE(Calc!$BO$5:$BO$604,7),Calc!$BO$5:$BO$604,0)),"") -> 0 | E64: =IFERROR(INDEX(Calc!$BK$5:$BK$604,MATCH(LARGE(Calc!$BO$5:$BO$604,7),Calc!$BO$5:$BO$604,0)),"") -> 0 | F64: =IFERROR(INDEX(Calc!$BM$5:$BM$604,MATCH(LARGE(Calc!$BO$5:$BO$604,7),Calc!$BO$5:$BO$604,0)),"") -> 0 | G64: =IFERROR(INDEX(Calc!$BN$5:$BN$604,MATCH(LARGE(Calc!$BO$5:$BO$604,7),Calc!$BO$5:$BO$604,0)),"") -> 0 | K64: Ideas worth scheduling | L64: =COUNTIF('Idea Bank'!$AD$5:$AD$304,"Plan*") -> 0
A65: 8 | B65: =IFERROR(INDEX(Calc!$BH$5:$BH$604,MATCH(LARGE(Calc!$BO$5:$BO$604,8),Calc!$BO$5:$BO$604,0)),"") -> 0 | C65: =IFERROR(INDEX(Calc!$BI$5:$BI$604,MATCH(LARGE(Calc!$BO$5:$BO$604,8),Calc!$BO$5:$BO$604,0)),"") -> 0 | D65: =IFERROR(INDEX(Calc!$BJ$5:$BJ$604,MATCH(LARGE(Calc!$BO$5:$BO$604,8),Calc!$BO$5:$BO$604,0)),"") -> 0 | E65: =IFERROR(INDEX(Calc!$BK$5:$BK$604,MATCH(LARGE(Calc!$BO$5:$BO$604,8),Calc!$BO$5:$BO$604,0)),"") -> 0 | F65: =IFERROR(INDEX(Calc!$BM$5:$BM$604,MATCH(LARGE(Calc!$BO$5:$BO$604,8),Calc!$BO$5:$BO$604,0)),"") -> 0 | G65: =IFERROR(INDEX(Calc!$BN$5:$BN$604,MATCH(LARGE(Calc!$BO$5:$BO$604,8),Calc!$BO$5:$BO$604,0)),"") -> 0 | K65: Overdue tasks | L65: =COUNTIF(Tasks!$L$5:$L$64,"Overdue*") -> 0
K66: UGC waiting on permission | L66: =COUNTIF('UGC Tracker'!$T$5:$T$104,"Action*") -> 0
K67: Goals behind pace | L67: =COUNTIF(Goals!$V$5:$V$44,"Behind*") -> 0
K68: Accounts gone quiet | L68: =COUNTIF(Accounts!$AC$5:$AC$34,"Check - account*") -> 0
K69: Trends about to expire | L69: =COUNTIF(Trends!$V$5:$V$84,"Expired*") -> 0
A71: Coming up & running late
A72: Next 8 posts due | K72: Overdue - deal with these first
A73: Date | B73: Platform | C73: Post | D73: Status | E73: Owner | F73: Days | K73: Date | L73: Platform | M73: Post | N73: Status | O73: Owner | P73: Days late
A74: =IFERROR(INDEX('Content Calendar'!$B$5:$B$604,MATCH(SMALL('Content Calendar'!$AJ$5:$AJ$604,1),'Content Calendar'!$AJ$5:$AJ$604,0)),"") -> 0 | B74: =IFERROR(INDEX('Content Calendar'!$G$5:$G$604,MATCH(SMALL('Content Calendar'!$AJ$5:$AJ$604,1),'Content Calendar'!$AJ$5:$AJ$604,0)),"") -> 0 | C74: =IFERROR(INDEX('Content Calendar'!$H$5:$H$604,MATCH(SMALL('Content Calendar'!$AJ$5:$AJ$604,1),'Content Calendar'!$AJ$5:$AJ$604,0)),"") -> 0 | D74: =IFERROR(INDEX('Content Calendar'!$X$5:$X$604,MATCH(SMALL('Content Calendar'!$AJ$5:$AJ$604,1),'Content Calendar'!$AJ$5:$AJ$604,0)),"") -> 0 | E74: =IFERROR(INDEX('Content Calendar'!$W$5:$W$604,MATCH(SMALL('Content Calendar'!$AJ$5:$AJ$604,1),'Content Calendar'!$AJ$5:$AJ$604,0)),"") -> 0 | F74: =IFERROR(INDEX('Content Calendar'!$AA$5:$AA$604,MATCH(SMALL('Content Calendar'!$AJ$5:$AJ$604,1),'Content Calendar'!$AJ$5:$AJ$604,0)),"") -> 0 | K74: =IFERROR(INDEX('Content Calendar'!$B$5:$B$604,MATCH(SMALL('Content Calendar'!$AK$5:$AK$604,1),'Content Calendar'!$AK$5:$AK$604,0)),"") -> 0 | L74: =IFERROR(INDEX('Content Calendar'!$G$5:$G$604,MATCH(SMALL('Content Calendar'!$AK$5:$AK$604,1),'Content Calendar'!$AK$5:$AK$604,0)),"") -> 0 | M74: =IFERROR(INDEX('Content Calendar'!$H$5:$H$604,MATCH(SMALL('Content Calendar'!$AK$5:$AK$604,1),'Content Calendar'!$AK$5:$AK$604,0)),"") -> 0 | N74: =IFERROR(INDEX('Content Calendar'!$X$5:$X$604,MATCH(SMALL('Content Calendar'!$AK$5:$AK$604,1),'Content Calendar'!$AK$5:$AK$604,0)),"") -> 0 | O74: =IFERROR(INDEX('Content Calendar'!$W$5:$W$604,MATCH(SMALL('Content Calendar'!$AK$5:$AK$604,1),'Content Calendar'!$AK$5:$AK$604,0)),"") -> 0 | P74: =IFERROR(-INDEX('Content Calendar'!$AA$5:$AA$604,MATCH(SMALL('Content Calendar'!$AK$5:$AK$604,1),'Content Calendar'!$AK$5:$AK$604,0)),"") -> 0
A75: =IFERROR(INDEX('Content Calendar'!$B$5:$B$604,MATCH(SMALL('Content Calendar'!$AJ$5:$AJ$604,2),'Content Calendar'!$AJ$5:$AJ$604,0)),"") -> 0 | B75: =IFERROR(INDEX('Content Calendar'!$G$5:$G$604,MATCH(SMALL('Content Calendar'!$AJ$5:$AJ$604,2),'Content Calendar'!$AJ$5:$AJ$604,0)),"") -> 0 | C75: =IFERROR(INDEX('Content Calendar'!$H$5:$H$604,MATCH(SMALL('Content Calendar'!$AJ$5:$AJ$604,2),'Content Calendar'!$AJ$5:$AJ$604,0)),"") -> 0 | D75: =IFERROR(INDEX('Content Calendar'!$X$5:$X$604,MATCH(SMALL('Content Calendar'!$AJ$5:$AJ$604,2),'Content Calendar'!$AJ$5:$AJ$604,0)),"") -> 0 | E75: =IFERROR(INDEX('Content Calendar'!$W$5:$W$604,MATCH(SMALL('Content Calendar'!$AJ$5:$AJ$604,2),'Content Calendar'!$AJ$5:$AJ$604,0)),"") -> 0 | F75: =IFERROR(INDEX('Content Calendar'!$AA$5:$AA$604,MATCH(SMALL('Content Calendar'!$AJ$5:$AJ$604,2),'Content Calendar'!$AJ$5:$AJ$604,0)),"") -> 0 | K75: =IFERROR(INDEX('Content Calendar'!$B$5:$B$604,MATCH(SMALL('Content Calendar'!$AK$5:$AK$604,2),'Content Calendar'!$AK$5:$AK$604,0)),"") -> 0 | L75: =IFERROR(INDEX('Content Calendar'!$G$5:$G$604,MATCH(SMALL('Content Calendar'!$AK$5:$AK$604,2),'Content Calendar'!$AK$5:$AK$604,0)),"") -> 0 | M75: =IFERROR(INDEX('Content Calendar'!$H$5:$H$604,MATCH(SMALL('Content Calendar'!$AK$5:$AK$604,2),'Content Calendar'!$AK$5:$AK$604,0)),"") -> 0 | N75: =IFERROR(INDEX('Content Calendar'!$X$5:$X$604,MATCH(SMALL('Content Calendar'!$AK$5:$AK$604,2),'Content Calendar'!$AK$5:$AK$604,0)),"") -> 0 | O75: =IFERROR(INDEX('Content Calendar'!$W$5:$W$604,MATCH(SMALL('Content Calendar'!$AK$5:$AK$604,2),'Content Calendar'!$AK$5:$AK$604,0)),"") -> 0 | P75: =IFERROR(-INDEX('Content Calendar'!$AA$5:$AA$604,MATCH(SMALL('Content Calendar'!$AK$5:$AK$604,2),'Content Calendar'!$AK$5:$AK$604,0)),"") -> 0
A76: =IFERROR(INDEX('Content Calendar'!$B$5:$B$604,MATCH(SMALL('Content Calendar'!$AJ$5:$AJ$604,3),'Content Calendar'!$AJ$5:$AJ$604,0)),"") -> 0 | B76: =IFERROR(INDEX('Content Calendar'!$G$5:$G$604,MATCH(SMALL('Content Calendar'!$AJ$5:$AJ$604,3),'Content Calendar'!$AJ$5:$AJ$604,0)),"") -> 0 | C76: =IFERROR(INDEX('Content Calendar'!$H$5:$H$604,MATCH(SMALL('Content Calendar'!$AJ$5:$AJ$604,3),'Content Calendar'!$AJ$5:$AJ$604,0)),"") -> 0 | D76: =IFERROR(INDEX('Content Calendar'!$X$5:$X$604,MATCH(SMALL('Content Calendar'!$AJ$5:$AJ$604,3),'Content Calendar'!$AJ$5:$AJ$604,0)),"") -> 0 | E76: =IFERROR(INDEX('Content Calendar'!$W$5:$W$604,MATCH(SMALL('Content Calendar'!$AJ$5:$AJ$604,3),'Content Calendar'!$AJ$5:$AJ$604,0)),"") -> 0 | F76: =IFERROR(INDEX('Content Calendar'!$AA$5:$AA$604,MATCH(SMALL('Content Calendar'!$AJ$5:$AJ$604,3),'Content Calendar'!$AJ$5:$AJ$604,0)),"") -> 0 | K76: =IFERROR(INDEX('Content Calendar'!$B$5:$B$604,MATCH(SMALL('Content Calendar'!$AK$5:$AK$604,3),'Content Calendar'!$AK$5:$AK$604,0)),"") -> 0 | L76: =IFERROR(INDEX('Content Calendar'!$G$5:$G$604,MATCH(SMALL('Content Calendar'!$AK$5:$AK$604,3),'Content Calendar'!$AK$5:$AK$604,0)),"") -> 0 | M76: =IFERROR(INDEX('Content Calendar'!$H$5:$H$604,MATCH(SMALL('Content Calendar'!$AK$5:$AK$604,3),'Content Calendar'!$AK$5:$AK$604,0)),"") -> 0 | N76: =IFERROR(INDEX('Content Calendar'!$X$5:$X$604,MATCH(SMALL('Content Calendar'!$AK$5:$AK$604,3),'Content Calendar'!$AK$5:$AK$604,0)),"") -> 0 | O76: =IFERROR(INDEX('Content Calendar'!$W$5:$W$604,MATCH(SMALL('Content Calendar'!$AK$5:$AK$604,3),'Content Calendar'!$AK$5:$AK$604,0)),"") -> 0 | P76: =IFERROR(-INDEX('Content Calendar'!$AA$5:$AA$604,MATCH(SMALL('Content Calendar'!$AK$5:$AK$604,3),'Content Calendar'!$AK$5:$AK$604,0)),"") -> 0
A77: =IFERROR(INDEX('Content Calendar'!$B$5:$B$604,MATCH(SMALL('Content Calendar'!$AJ$5:$AJ$604,4),'Content Calendar'!$AJ$5:$AJ$604,0)),"") -> 0 | B77: =IFERROR(INDEX('Content Calendar'!$G$5:$G$604,MATCH(SMALL('Content Calendar'!$AJ$5:$AJ$604,4),'Content Calendar'!$AJ$5:$AJ$604,0)),"") -> 0 | C77: =IFERROR(INDEX('Content Calendar'!$H$5:$H$604,MATCH(SMALL('Content Calendar'!$AJ$5:$AJ$604,4),'Content Calendar'!$AJ$5:$AJ$604,0)),"") -> 0 | D77: =IFERROR(INDEX('Content Calendar'!$X$5:$X$604,MATCH(SMALL('Content Calendar'!$AJ$5:$AJ$604,4),'Content Calendar'!$AJ$5:$AJ$604,0)),"") -> 0 | E77: =IFERROR(INDEX('Content Calendar'!$W$5:$W$604,MATCH(SMALL('Content Calendar'!$AJ$5:$AJ$604,4),'Content Calendar'!$AJ$5:$AJ$604,0)),"") -> 0 | F77: =IFERROR(INDEX('Content Calendar'!$AA$5:$AA$604,MATCH(SMALL('Content Calendar'!$AJ$5:$AJ$604,4),'Content Calendar'!$AJ$5:$AJ$604,0)),"") -> 0 | K77: =IFERROR(INDEX('Content Calendar'!$B$5:$B$604,MATCH(SMALL('Content Calendar'!$AK$5:$AK$604,4),'Content Calendar'!$AK$5:$AK$604,0)),"") -> 0 | L77: =IFERROR(INDEX('Content Calendar'!$G$5:$G$604,MATCH(SMALL('Content Calendar'!$AK$5:$AK$604,4),'Content Calendar'!$AK$5:$AK$604,0)),"") -> 0 | M77: =IFERROR(INDEX('Content Calendar'!$H$5:$H$604,MATCH(SMALL('Content Calendar'!$AK$5:$AK$604,4),'Content Calendar'!$AK$5:$AK$604,0)),"") -> 0 | N77: =IFERROR(INDEX('Content Calendar'!$X$5:$X$604,MATCH(SMALL('Content Calendar'!$AK$5:$AK$604,4),'Content Calendar'!$AK$5:$AK$604,0)),"") -> 0 | O77: =IFERROR(INDEX('Content Calendar'!$W$5:$W$604,MATCH(SMALL('Content Calendar'!$AK$5:$AK$604,4),'Content Calendar'!$AK$5:$AK$604,0)),"") -> 0 | P77: =IFERROR(-INDEX('Content Calendar'!$AA$5:$AA$604,MATCH(SMALL('Content Calendar'!$AK$5:$AK$604,4),'Content Calendar'!$AK$5:$AK$604,0)),"") -> 0
A78: =IFERROR(INDEX('Content Calendar'!$B$5:$B$604,MATCH(SMALL('Content Calendar'!$AJ$5:$AJ$604,5),'Content Calendar'!$AJ$5:$AJ$604,0)),"") -> 0 | B78: =IFERROR(INDEX('Content Calendar'!$G$5:$G$604,MATCH(SMALL('Content Calendar'!$AJ$5:$AJ$604,5),'Content Calendar'!$AJ$5:$AJ$604,0)),"") -> 0 | C78: =IFERROR(INDEX('Content Calendar'!$H$5:$H$604,MATCH(SMALL('Content Calendar'!$AJ$5:$AJ$604,5),'Content Calendar'!$AJ$5:$AJ$604,0)),"") -> 0 | D78: =IFERROR(INDEX('Content Calendar'!$X$5:$X$604,MATCH(SMALL('Content Calendar'!$AJ$5:$AJ$604,5),'Content Calendar'!$AJ$5:$AJ$604,0)),"") -> 0 | E78: =IFERROR(INDEX('Content Calendar'!$W$5:$W$604,MATCH(SMALL('Content Calendar'!$AJ$5:$AJ$604,5),'Content Calendar'!$AJ$5:$AJ$604,0)),"") -> 0 | F78: =IFERROR(INDEX('Content Calendar'!$AA$5:$AA$604,MATCH(SMALL('Content Calendar'!$AJ$5:$AJ$604,5),'Content Calendar'!$AJ$5:$AJ$604,0)),"") -> 0 | K78: =IFERROR(INDEX('Content Calendar'!$B$5:$B$604,MATCH(SMALL('Content Calendar'!$AK$5:$AK$604,5),'Content Calendar'!$AK$5:$AK$604,0)),"") -> 0 | L78: =IFERROR(INDEX('Content Calendar'!$G$5:$G$604,MATCH(SMALL('Content Calendar'!$AK$5:$AK$604,5),'Content Calendar'!$AK$5:$AK$604,0)),"") -> 0 | M78: =IFERROR(INDEX('Content Calendar'!$H$5:$H$604,MATCH(SMALL('Content Calendar'!$AK$5:$AK$604,5),'Content Calendar'!$AK$5:$AK$604,0)),"") -> 0 | N78: =IFERROR(INDEX('Content Calendar'!$X$5:$X$604,MATCH(SMALL('Content Calendar'!$AK$5:$AK$604,5),'Content Calendar'!$AK$5:$AK$604,0)),"") -> 0 | O78: =IFERROR(INDEX('Content Calendar'!$W$5:$W$604,MATCH(SMALL('Content Calendar'!$AK$5:$AK$604,5),'Content Calendar'!$AK$5:$AK$604,0)),"") -> 0 | P78: =IFERROR(-INDEX('Content Calendar'!$AA$5:$AA$604,MATCH(SMALL('Content Calendar'!$AK$5:$AK$604,5),'Content Calendar'!$AK$5:$AK$604,0)),"") -> 0
A79: =IFERROR(INDEX('Content Calendar'!$B$5:$B$604,MATCH(SMALL('Content Calendar'!$AJ$5:$AJ$604,6),'Content Calendar'!$AJ$5:$AJ$604,0)),"") -> 0 | B79: =IFERROR(INDEX('Content Calendar'!$G$5:$G$604,MATCH(SMALL('Content Calendar'!$AJ$5:$AJ$604,6),'Content Calendar'!$AJ$5:$AJ$604,0)),"") -> 0 | C79: =IFERROR(INDEX('Content Calendar'!$H$5:$H$604,MATCH(SMALL('Content Calendar'!$AJ$5:$AJ$604,6),'Content Calendar'!$AJ$5:$AJ$604,0)),"") -> 0 | D79: =IFERROR(INDEX('Content Calendar'!$X$5:$X$604,MATCH(SMALL('Content Calendar'!$AJ$5:$AJ$604,6),'Content Calendar'!$AJ$5:$AJ$604,0)),"") -> 0 | E79: =IFERROR(INDEX('Content Calendar'!$W$5:$W$604,MATCH(SMALL('Content Calendar'!$AJ$5:$AJ$604,6),'Content Calendar'!$AJ$5:$AJ$604,0)),"") -> 0 | F79: =IFERROR(INDEX('Content Calendar'!$AA$5:$AA$604,MATCH(SMALL('Content Calendar'!$AJ$5:$AJ$604,6),'Content Calendar'!$AJ$5:$AJ$604,0)),"") -> 0 | K79: =IFERROR(INDEX('Content Calendar'!$B$5:$B$604,MATCH(SMALL('Content Calendar'!$AK$5:$AK$604,6),'Content Calendar'!$AK$5:$AK$604,0)),"") -> 0 | L79: =IFERROR(INDEX('Content Calendar'!$G$5:$G$604,MATCH(SMALL('Content Calendar'!$AK$5:$AK$604,6),'Content Calendar'!$AK$5:$AK$604,0)),"") -> 0 | M79: =IFERROR(INDEX('Content Calendar'!$H$5:$H$604,MATCH(SMALL('Content Calendar'!$AK$5:$AK$604,6),'Content Calendar'!$AK$5:$AK$604,0)),"") -> 0 | N79: =IFERROR(INDEX('Content Calendar'!$X$5:$X$604,MATCH(SMALL('Content Calendar'!$AK$5:$AK$604,6),'Content Calendar'!$AK$5:$AK$604,0)),"") -> 0 | O79: =IFERROR(INDEX('Content Calendar'!$W$5:$W$604,MATCH(SMALL('Content Calendar'!$AK$5:$AK$604,6),'Content Calendar'!$AK$5:$AK$604,0)),"") -> 0 | P79: =IFERROR(-INDEX('Content Calendar'!$AA$5:$AA$604,MATCH(SMALL('Content Calendar'!$AK$5:$AK$604,6),'Content Calendar'!$AK$5:$AK$604,0)),"") -> 0
A80: =IFERROR(INDEX('Content Calendar'!$B$5:$B$604,MATCH(SMALL('Content Calendar'!$AJ$5:$AJ$604,7),'Content Calendar'!$AJ$5:$AJ$604,0)),"") -> 0 | B80: =IFERROR(INDEX('Content Calendar'!$G$5:$G$604,MATCH(SMALL('Content Calendar'!$AJ$5:$AJ$604,7),'Content Calendar'!$AJ$5:$AJ$604,0)),"") -> 0 | C80: =IFERROR(INDEX('Content Calendar'!$H$5:$H$604,MATCH(SMALL('Content Calendar'!$AJ$5:$AJ$604,7),'Content Calendar'!$AJ$5:$AJ$604,0)),"") -> 0 | D80: =IFERROR(INDEX('Content Calendar'!$X$5:$X$604,MATCH(SMALL('Content Calendar'!$AJ$5:$AJ$604,7),'Content Calendar'!$AJ$5:$AJ$604,0)),"") -> 0 | E80: =IFERROR(INDEX('Content Calendar'!$W$5:$W$604,MATCH(SMALL('Content Calendar'!$AJ$5:$AJ$604,7),'Content Calendar'!$AJ$5:$AJ$604,0)),"") -> 0 | F80: =IFERROR(INDEX('Content Calendar'!$AA$5:$AA$604,MATCH(SMALL('Content Calendar'!$AJ$5:$AJ$604,7),'Content Calendar'!$AJ$5:$AJ$604,0)),"") -> 0 | K80: =IFERROR(INDEX('Content Calendar'!$B$5:$B$604,MATCH(SMALL('Content Calendar'!$AK$5:$AK$604,7),'Content Calendar'!$AK$5:$AK$604,0)),"") -> 0 | L80: =IFERROR(INDEX('Content Calendar'!$G$5:$G$604,MATCH(SMALL('Content Calendar'!$AK$5:$AK$604,7),'Content Calendar'!$AK$5:$AK$604,0)),"") -> 0 | M80: =IFERROR(INDEX('Content Calendar'!$H$5:$H$604,MATCH(SMALL('Content Calendar'!$AK$5:$AK$604,7),'Content Calendar'!$AK$5:$AK$604,0)),"") -> 0 | N80: =IFERROR(INDEX('Content Calendar'!$X$5:$X$604,MATCH(SMALL('Content Calendar'!$AK$5:$AK$604,7),'Content Calendar'!$AK$5:$AK$604,0)),"") -> 0 | O80: =IFERROR(INDEX('Content Calendar'!$W$5:$W$604,MATCH(SMALL('Content Calendar'!$AK$5:$AK$604,7),'Content Calendar'!$AK$5:$AK$604,0)),"") -> 0 | P80: =IFERROR(-INDEX('Content Calendar'!$AA$5:$AA$604,MATCH(SMALL('Content Calendar'!$AK$5:$AK$604,7),'Content Calendar'!$AK$5:$AK$604,0)),"") -> 0
A81: =IFERROR(INDEX('Content Calendar'!$B$5:$B$604,MATCH(SMALL('Content Calendar'!$AJ$5:$AJ$604,8),'Content Calendar'!$AJ$5:$AJ$604,0)),"") -> 0 | B81: =IFERROR(INDEX('Content Calendar'!$G$5:$G$604,MATCH(SMALL('Content Calendar'!$AJ$5:$AJ$604,8),'Content Calendar'!$AJ$5:$AJ$604,0)),"") -> 0 | C81: =IFERROR(INDEX('Content Calendar'!$H$5:$H$604,MATCH(SMALL('Content Calendar'!$AJ$5:$AJ$604,8),'Content Calendar'!$AJ$5:$AJ$604,0)),"") -> 0 | D81: =IFERROR(INDEX('Content Calendar'!$X$5:$X$604,MATCH(SMALL('Content Calendar'!$AJ$5:$AJ$604,8),'Content Calendar'!$AJ$5:$AJ$604,0)),"") -> 0 | E81: =IFERROR(INDEX('Content Calendar'!$W$5:$W$604,MATCH(SMALL('Content Calendar'!$AJ$5:$AJ$604,8),'Content Calendar'!$AJ$5:$AJ$604,0)),"") -> 0 | F81: =IFERROR(INDEX('Content Calendar'!$AA$5:$AA$604,MATCH(SMALL('Content Calendar'!$AJ$5:$AJ$604,8),'Content Calendar'!$AJ$5:$AJ$604,0)),"") -> 0 | K81: =IFERROR(INDEX('Content Calendar'!$B$5:$B$604,MATCH(SMALL('Content Calendar'!$AK$5:$AK$604,8),'Content Calendar'!$AK$5:$AK$604,0)),"") -> 0 | L81: =IFERROR(INDEX('Content Calendar'!$G$5:$G$604,MATCH(SMALL('Content Calendar'!$AK$5:$AK$604,8),'Content Calendar'!$AK$5:$AK$604,0)),"") -> 0 | M81: =IFERROR(INDEX('Content Calendar'!$H$5:$H$604,MATCH(SMALL('Content Calendar'!$AK$5:$AK$604,8),'Content Calendar'!$AK$5:$AK$604,0)),"") -> 0 | N81: =IFERROR(INDEX('Content Calendar'!$X$5:$X$604,MATCH(SMALL('Content Calendar'!$AK$5:$AK$604,8),'Content Calendar'!$AK$5:$AK$604,0)),"") -> 0 | O81: =IFERROR(INDEX('Content Calendar'!$W$5:$W$604,MATCH(SMALL('Content Calendar'!$AK$5:$AK$604,8),'Content Calendar'!$AK$5:$AK$604,0)),"") -> 0 | P81: =IFERROR(-INDEX('Content Calendar'!$AA$5:$AA$604,MATCH(SMALL('Content Calendar'!$AK$5:$AK$604,8),'Content Calendar'!$AK$5:$AK$604,0)),"") -> 0
A83: Tip: pick 'All year' in the month box to see the whole plan. The Annual Dashboard compares every month side by side, and the Reports tab turns the same numbers into something you can print or send to a client.

Sheet Annual Dashboard
A1: Annual Dashboard | P1: Novality Store | v1.0.0
A2: Everything you planned and published in 2026, quarter by quarter and month by month.
A3: > Start Here | C3: > Dashboard | E3: > Calendar | G3: > Ideas | I3: > Captions | K3: > Hashtags | M3: > Analytics | O3: > Reports | Q3: > Help
A5: 2026 in numbers
A6: Posts planned | D6: Published | G6: Reach | J6: Engagements | M6: Engagement rate | P6: Follower growth
A7: =COUNTIFS('Content Calendar'!$B$5:$B$604,">="&DATE(PlanYear,1,1),'Content Calendar'!$B$5:$B$604,"<="&DATE(PlanYear,12,31)) -> 0 | D7: =COUNTIFS('Content Calendar'!$B$5:$B$604,">="&DATE(PlanYear,1,1),'Content Calendar'!$B$5:$B$604,"<="&DATE(PlanYear,12,31),'Content Calendar'!$X$5:$X$604,"Published") -> 0 | G7: =SUM(Calc!$G$5:$G$604) -> 0 | J7: =SUM(Calc!$I$5:$I$604) -> 0 | M7: =IFERROR(Year_Eng/Year_Reach,0) -> 0 | P7: =SUM(Calc!$L$5:$L$604) -> 0
A8: Every row on the calendar this year | D8: Actually went out | G8: Across every account and month | J8: Likes, comments, shares, saves | M8: The year's average | P8: New followers less unfollows
A10: Clicks | D10: Leads | G10: Sales | J10: Revenue | M10: Spend | P10: Return on spend
A11: =SUM(Calc!$M$5:$M$604) -> 0 | D11: =SUM(Calc!$N$5:$N$604) -> 0 | G11: =SUM(Calc!$O$5:$O$604) -> 0 | J11: =SUM(Calc!$P$5:$P$604) -> 0 | M11: =SUM(Calc!$Q$5:$Q$604) -> 0 | P11: =IFERROR(Year_Revenue/Year_Spend,0) -> 0
A12: Traffic sent out | D12: Enquiries and sign-ups | G12: Orders traced back to social | J12: Money attributed to social | M12: Everything on the Budget tab | P12: Revenue divided by spend
A14: Posts a week | D14: Reach per post | G14: Revenue per post | J14: Best month | M14: Best platform | P14: Best day to post
A15: =IFERROR(Year_Published/52,0) -> 0 | D15: =IFERROR(Year_Reach/Year_Published,0) -> 0 | G15: =IFERROR(Year_Revenue/Year_Published,0) -> 0 | J15: =IFERROR(INDEX(Calc!$D$5:$D$604,MATCH(MAX(Calc!$G$5:$G$604),Calc!$G$5:$G$604,0)),"") -> 0 | M15: =IFERROR(INDEX(Calc!$T$5:$T$604,MATCH(MAX(Calc!$AI$5:$AI$604),Calc!$AI$5:$AI$604,0)),"") -> 0 | P15: =IFERROR(INDEX(Calc!$AV$5:$AV$604,MATCH(MAX(Calc!$BA$5:$BA$604),Calc!$BA$5:$BA$604,0)),"") -> 0
A16: Your real publishing rhythm | D16: How far the average post travelled | G16: Money per published post | J16: By reach | M16: By reach this year | P16: Highest average engagement rate
A18: Quarter by quarter
A19: Quarter | B19: Published | C19: Reach | D19: Engagements | E19: Eng. rate | F19: Followers gained | G19: Clicks | H19: Leads | I19: Sales | J19: Revenue | K19: Spend | L19: Net
A20: Q1 | B20: =N(Calc!$F$5)+N(Calc!$F$6)+N(Calc!$F$7) -> 0 | C20: =N(Calc!$G$5)+N(Calc!$G$6)+N(Calc!$G$7) -> 0 | D20: =N(Calc!$I$5)+N(Calc!$I$6)+N(Calc!$I$7) -> 0 | E20: =IFERROR(D20/C20,"") -> 0 | F20: =N(Calc!$L$5)+N(Calc!$L$6)+N(Calc!$L$7) -> 0 | G20: =N(Calc!$M$5)+N(Calc!$M$6)+N(Calc!$M$7) -> 0 | H20: =N(Calc!$N$5)+N(Calc!$N$6)+N(Calc!$N$7) -> 0 | I20: =N(Calc!$O$5)+N(Calc!$O$6)+N(Calc!$O$7) -> 0 | J20: =N(Calc!$P$5)+N(Calc!$P$6)+N(Calc!$P$7) -> 0 | K20: =N(Calc!$Q$5)+N(Calc!$Q$6)+N(Calc!$Q$7) -> 0 | L20: =J20-K20 -> 0
A21: Q2 | B21: =N(Calc!$F$8)+N(Calc!$F$9)+N(Calc!$F$10) -> 0 | C21: =N(Calc!$G$8)+N(Calc!$G$9)+N(Calc!$G$10) -> 0 | D21: =N(Calc!$I$8)+N(Calc!$I$9)+N(Calc!$I$10) -> 0 | E21: =IFERROR(D21/C21,"") -> 0 | F21: =N(Calc!$L$8)+N(Calc!$L$9)+N(Calc!$L$10) -> 0 | G21: =N(Calc!$M$8)+N(Calc!$M$9)+N(Calc!$M$10) -> 0 | H21: =N(Calc!$N$8)+N(Calc!$N$9)+N(Calc!$N$10) -> 0 | I21: =N(Calc!$O$8)+N(Calc!$O$9)+N(Calc!$O$10) -> 0 | J21: =N(Calc!$P$8)+N(Calc!$P$9)+N(Calc!$P$10) -> 0 | K21: =N(Calc!$Q$8)+N(Calc!$Q$9)+N(Calc!$Q$10) -> 0 | L21: =J21-K21 -> 0
A22: Q3 | B22: =N(Calc!$F$11)+N(Calc!$F$12)+N(Calc!$F$13) -> 0 | C22: =N(Calc!$G$11)+N(Calc!$G$12)+N(Calc!$G$13) -> 0 | D22: =N(Calc!$I$11)+N(Calc!$I$12)+N(Calc!$I$13) -> 0 | E22: =IFERROR(D22/C22,"") -> 0 | F22: =N(Calc!$L$11)+N(Calc!$L$12)+N(Calc!$L$13) -> 0 | G22: =N(Calc!$M$11)+N(Calc!$M$12)+N(Calc!$M$13) -> 0 | H22: =N(Calc!$N$11)+N(Calc!$N$12)+N(Calc!$N$13) -> 0 | I22: =N(Calc!$O$11)+N(Calc!$O$12)+N(Calc!$O$13) -> 0 | J22: =N(Calc!$P$11)+N(Calc!$P$12)+N(Calc!$P$13) -> 0 | K22: =N(Calc!$Q$11)+N(Calc!$Q$12)+N(Calc!$Q$13) -> 0 | L22: =J22-K22 -> 0
A23: Q4 | B23: =N(Calc!$F$14)+N(Calc!$F$15)+N(Calc!$F$16) -> 0 | C23: =N(Calc!$G$14)+N(Calc!$G$15)+N(Calc!$G$16) -> 0 | D23: =N(Calc!$I$14)+N(Calc!$I$15)+N(Calc!$I$16) -> 0 | E23: =IFERROR(D23/C23,"") -> 0 | F23: =N(Calc!$L$14)+N(Calc!$L$15)+N(Calc!$L$16) -> 0 | G23: =N(Calc!$M$14)+N(Calc!$M$15)+N(Calc!$M$16) -> 0 | H23: =N(Calc!$N$14)+N(Calc!$N$15)+N(Calc!$N$16) -> 0 | I23: =N(Calc!$O$14)+N(Calc!$O$15)+N(Calc!$O$16) -> 0 | J23: =N(Calc!$P$14)+N(Calc!$P$15)+N(Calc!$P$16) -> 0 | K23: =N(Calc!$Q$14)+N(Calc!$Q$15)+N(Calc!$Q$16) -> 0 | L23: =J23-K23 -> 0
A25: Every month in detail
A26: Month | B26: Planned | C26: Published | D26: On target? | E26: Reach | F26: Impressions | G26: Engagements | H26: Eng. rate | I26: Followers | J26: Growth | K26: Clicks | L26: Leads | M26: Sales | N26: Revenue | O26: Spend | P26: Net | Q26: Return
A27: =Calc!$D$5 -> 0 | B27: =Calc!$E$5 -> 0 | C27: =Calc!$F$5 -> 0 | D27: =IFERROR(Calc!$F$5/Calc!$S$5,"") -> 0 | E27: =Calc!$G$5 -> 0 | F27: =Calc!$H$5 -> 0 | G27: =Calc!$I$5 -> 0 | H27: =Calc!$J$5 -> 0 | I27: =Calc!$K$5 -> 0 | J27: =Calc!$L$5 -> 0 | K27: =Calc!$M$5 -> 0 | L27: =Calc!$N$5 -> 0 | M27: =Calc!$O$5 -> 0 | N27: =Calc!$P$5 -> 0 | O27: =Calc!$Q$5 -> 0 | P27: =N27-O27 -> 0 | Q27: =IFERROR(N27/O27,"") -> 0
A28: =Calc!$D$6 -> 0 | B28: =Calc!$E$6 -> 0 | C28: =Calc!$F$6 -> 0 | D28: =IFERROR(Calc!$F$6/Calc!$S$6,"") -> 0 | E28: =Calc!$G$6 -> 0 | F28: =Calc!$H$6 -> 0 | G28: =Calc!$I$6 -> 0 | H28: =Calc!$J$6 -> 0 | I28: =Calc!$K$6 -> 0 | J28: =Calc!$L$6 -> 0 | K28: =Calc!$M$6 -> 0 | L28: =Calc!$N$6 -> 0 | M28: =Calc!$O$6 -> 0 | N28: =Calc!$P$6 -> 0 | O28: =Calc!$Q$6 -> 0 | P28: =N28-O28 -> 0 | Q28: =IFERROR(N28/O28,"") -> 0
A29: =Calc!$D$7 -> 0 | B29: =Calc!$E$7 -> 0 | C29: =Calc!$F$7 -> 0 | D29: =IFERROR(Calc!$F$7/Calc!$S$7,"") -> 0 | E29: =Calc!$G$7 -> 0 | F29: =Calc!$H$7 -> 0 | G29: =Calc!$I$7 -> 0 | H29: =Calc!$J$7 -> 0 | I29: =Calc!$K$7 -> 0 | J29: =Calc!$L$7 -> 0 | K29: =Calc!$M$7 -> 0 | L29: =Calc!$N$7 -> 0 | M29: =Calc!$O$7 -> 0 | N29: =Calc!$P$7 -> 0 | O29: =Calc!$Q$7 -> 0 | P29: =N29-O29 -> 0 | Q29: =IFERROR(N29/O29,"") -> 0
A30: =Calc!$D$8 -> 0 | B30: =Calc!$E$8 -> 0 | C30: =Calc!$F$8 -> 0 | D30: =IFERROR(Calc!$F$8/Calc!$S$8,"") -> 0 | E30: =Calc!$G$8 -> 0 | F30: =Calc!$H$8 -> 0 | G30: =Calc!$I$8 -> 0 | H30: =Calc!$J$8 -> 0 | I30: =Calc!$K$8 -> 0 | J30: =Calc!$L$8 -> 0 | K30: =Calc!$M$8 -> 0 | L30: =Calc!$N$8 -> 0 | M30: =Calc!$O$8 -> 0 | N30: =Calc!$P$8 -> 0 | O30: =Calc!$Q$8 -> 0 | P30: =N30-O30 -> 0 | Q30: =IFERROR(N30/O30,"") -> 0
A31: =Calc!$D$9 -> 0 | B31: =Calc!$E$9 -> 0 | C31: =Calc!$F$9 -> 0 | D31: =IFERROR(Calc!$F$9/Calc!$S$9,"") -> 0 | E31: =Calc!$G$9 -> 0 | F31: =Calc!$H$9 -> 0 | G31: =Calc!$I$9 -> 0 | H31: =Calc!$J$9 -> 0 | I31: =Calc!$K$9 -> 0 | J31: =Calc!$L$9 -> 0 | K31: =Calc!$M$9 -> 0 | L31: =Calc!$N$9 -> 0 | M31: =Calc!$O$9 -> 0 | N31: =Calc!$P$9 -> 0 | O31: =Calc!$Q$9 -> 0 | P31: =N31-O31 -> 0 | Q31: =IFERROR(N31/O31,"") -> 0
A32: =Calc!$D$10 -> 0 | B32: =Calc!$E$10 -> 0 | C32: =Calc!$F$10 -> 0 | D32: =IFERROR(Calc!$F$10/Calc!$S$10,"") -> 0 | E32: =Calc!$G$10 -> 0 | F32: =Calc!$H$10 -> 0 | G32: =Calc!$I$10 -> 0 | H32: =Calc!$J$10 -> 0 | I32: =Calc!$K$10 -> 0 | J32: =Calc!$L$10 -> 0 | K32: =Calc!$M$10 -> 0 | L32: =Calc!$N$10 -> 0 | M32: =Calc!$O$10 -> 0 | N32: =Calc!$P$10 -> 0 | O32: =Calc!$Q$10 -> 0 | P32: =N32-O32 -> 0 | Q32: =IFERROR(N32/O32,"") -> 0
A33: =Calc!$D$11 -> 0 | B33: =Calc!$E$11 -> 0 | C33: =Calc!$F$11 -> 0 | D33: =IFERROR(Calc!$F$11/Calc!$S$11,"") -> 0 | E33: =Calc!$G$11 -> 0 | F33: =Calc!$H$11 -> 0 | G33: =Calc!$I$11 -> 0 | H33: =Calc!$J$11 -> 0 | I33: =Calc!$K$11 -> 0 | J33: =Calc!$L$11 -> 0 | K33: =Calc!$M$11 -> 0 | L33: =Calc!$N$11 -> 0 | M33: =Calc!$O$11 -> 0 | N33: =Calc!$P$11 -> 0 | O33: =Calc!$Q$11 -> 0 | P33: =N33-O33 -> 0 | Q33: =IFERROR(N33/O33,"") -> 0
A34: =Calc!$D$12 -> 0 | B34: =Calc!$E$12 -> 0 | C34: =Calc!$F$12 -> 0 | D34: =IFERROR(Calc!$F$12/Calc!$S$12,"") -> 0 | E34: =Calc!$G$12 -> 0 | F34: =Calc!$H$12 -> 0 | G34: =Calc!$I$12 -> 0 | H34: =Calc!$J$12 -> 0 | I34: =Calc!$K$12 -> 0 | J34: =Calc!$L$12 -> 0 | K34: =Calc!$M$12 -> 0 | L34: =Calc!$N$12 -> 0 | M34: =Calc!$O$12 -> 0 | N34: =Calc!$P$12 -> 0 | O34: =Calc!$Q$12 -> 0 | P34: =N34-O34 -> 0 | Q34: =IFERROR(N34/O34,"") -> 0
A35: =Calc!$D$13 -> 0 | B35: =Calc!$E$13 -> 0 | C35: =Calc!$F$13 -> 0 | D35: =IFERROR(Calc!$F$13/Calc!$S$13,"") -> 0 | E35: =Calc!$G$13 -> 0 | F35: =Calc!$H$13 -> 0 | G35: =Calc!$I$13 -> 0 | H35: =Calc!$J$13 -> 0 | I35: =Calc!$K$13 -> 0 | J35: =Calc!$L$13 -> 0 | K35: =Calc!$M$13 -> 0 | L35: =Calc!$N$13 -> 0 | M35: =Calc!$O$13 -> 0 | N35: =Calc!$P$13 -> 0 | O35: =Calc!$Q$13 -> 0 | P35: =N35-O35 -> 0 | Q35: =IFERROR(N35/O35,"") -> 0
A36: =Calc!$D$14 -> 0 | B36: =Calc!$E$14 -> 0 | C36: =Calc!$F$14 -> 0 | D36: =IFERROR(Calc!$F$14/Calc!$S$14,"") -> 0 | E36: =Calc!$G$14 -> 0 | F36: =Calc!$H$14 -> 0 | G36: =Calc!$I$14 -> 0 | H36: =Calc!$J$14 -> 0 | I36: =Calc!$K$14 -> 0 | J36: =Calc!$L$14 -> 0 | K36: =Calc!$M$14 -> 0 | L36: =Calc!$N$14 -> 0 | M36: =Calc!$O$14 -> 0 | N36: =Calc!$P$14 -> 0 | O36: =Calc!$Q$14 -> 0 | P36: =N36-O36 -> 0 | Q36: =IFERROR(N36/O36,"") -> 0
A37: =Calc!$D$15 -> 0 | B37: =Calc!$E$15 -> 0 | C37: =Calc!$F$15 -> 0 | D37: =IFERROR(Calc!$F$15/Calc!$S$15,"") -> 0 | E37: =Calc!$G$15 -> 0 | F37: =Calc!$H$15 -> 0 | G37: =Calc!$I$15 -> 0 | H37: =Calc!$J$15 -> 0 | I37: =Calc!$K$15 -> 0 | J37: =Calc!$L$15 -> 0 | K37: =Calc!$M$15 -> 0 | L37: =Calc!$N$15 -> 0 | M37: =Calc!$O$15 -> 0 | N37: =Calc!$P$15 -> 0 | O37: =Calc!$Q$15 -> 0 | P37: =N37-O37 -> 0 | Q37: =IFERROR(N37/O37,"") -> 0
A38: =Calc!$D$16 -> 0 | B38: =Calc!$E$16 -> 0 | C38: =Calc!$F$16 -> 0 | D38: =IFERROR(Calc!$F$16/Calc!$S$16,"") -> 0 | E38: =Calc!$G$16 -> 0 | F38: =Calc!$H$16 -> 0 | G38: =Calc!$I$16 -> 0 | H38: =Calc!$J$16 -> 0 | I38: =Calc!$K$16 -> 0 | J38: =Calc!$L$16 -> 0 | K38: =Calc!$M$16 -> 0 | L38: =Calc!$N$16 -> 0 | M38: =Calc!$O$16 -> 0 | N38: =Calc!$P$16 -> 0 | O38: =Calc!$Q$16 -> 0 | P38: =N38-O38 -> 0 | Q38: =IFERROR(N38/O38,"") -> 0
A39: Trend
A41: Platforms, formats and goals
A42: Platform totals for the year | I42: Goals
A43: Platform | B43: Posts | C43: Reach | D43: Engagements | E43: Eng. rate | F43: Growth | G43: Share of reach | I43: Goal | J43: Target | K43: Now | L43: Progress | M43: On track? | N43: By when
A44: =IF(Calc!$T$5="","",Calc!$T$5) -> 0 | B44: =IF(Calc!$T$5="","",Calc!$AD$5) -> 0 | C44: =IF(Calc!$T$5="","",Calc!$AE$5) -> 0 | D44: =IF(Calc!$T$5="","",Calc!$AF$5) -> 0 | E44: =IF(Calc!$T$5="","",Calc!$AG$5) -> 0 | F44: =IF(Calc!$T$5="","",Calc!$AH$5) -> 0 | G44: =IFERROR(Calc!$AE$5/SUM(Calc!$AE$5:$AE$604),"") -> 0 | I44: =IF(Goals!$B$5="","",Goals!$B$5) -> 0 | J44: =IF(Goals!$B$5="","",Goals!$K$5) -> 0 | K44: =IF(Goals!$B$5="","",Goals!$J$5) -> 0 | L44: =IF(Goals!$B$5="","",Goals!$R$5) -> 0 | M44: =IF(Goals!$B$5="","",Goals!$V$5) -> 0 | N44: =IF(Goals!$B$5="","",Goals!$L$5) -> 0
A45: =IF(Calc!$T$6="","",Calc!$T$6) -> 0 | B45: =IF(Calc!$T$6="","",Calc!$AD$6) -> 0 | C45: =IF(Calc!$T$6="","",Calc!$AE$6) -> 0 | D45: =IF(Calc!$T$6="","",Calc!$AF$6) -> 0 | E45: =IF(Calc!$T$6="","",Calc!$AG$6) -> 0 | F45: =IF(Calc!$T$6="","",Calc!$AH$6) -> 0 | G45: =IFERROR(Calc!$AE$6/SUM(Calc!$AE$5:$AE$604),"") -> 0 | I45: =IF(Goals!$B$6="","",Goals!$B$6) -> 0 | J45: =IF(Goals!$B$6="","",Goals!$K$6) -> 0 | K45: =IF(Goals!$B$6="","",Goals!$J$6) -> 0 | L45: =IF(Goals!$B$6="","",Goals!$R$6) -> 0 | M45: =IF(Goals!$B$6="","",Goals!$V$6) -> 0 | N45: =IF(Goals!$B$6="","",Goals!$L$6) -> 0
A46: =IF(Calc!$T$7="","",Calc!$T$7) -> 0 | B46: =IF(Calc!$T$7="","",Calc!$AD$7) -> 0 | C46: =IF(Calc!$T$7="","",Calc!$AE$7) -> 0 | D46: =IF(Calc!$T$7="","",Calc!$AF$7) -> 0 | E46: =IF(Calc!$T$7="","",Calc!$AG$7) -> 0 | F46: =IF(Calc!$T$7="","",Calc!$AH$7) -> 0 | G46: =IFERROR(Calc!$AE$7/SUM(Calc!$AE$5:$AE$604),"") -> 0 | I46: =IF(Goals!$B$7="","",Goals!$B$7) -> 0 | J46: =IF(Goals!$B$7="","",Goals!$K$7) -> 0 | K46: =IF(Goals!$B$7="","",Goals!$J$7) -> 0 | L46: =IF(Goals!$B$7="","",Goals!$R$7) -> 0 | M46: =IF(Goals!$B$7="","",Goals!$V$7) -> 0 | N46: =IF(Goals!$B$7="","",Goals!$L$7) -> 0
A47: =IF(Calc!$T$8="","",Calc!$T$8) -> 0 | B47: =IF(Calc!$T$8="","",Calc!$AD$8) -> 0 | C47: =IF(Calc!$T$8="","",Calc!$AE$8) -> 0 | D47: =IF(Calc!$T$8="","",Calc!$AF$8) -> 0 | E47: =IF(Calc!$T$8="","",Calc!$AG$8) -> 0 | F47: =IF(Calc!$T$8="","",Calc!$AH$8) -> 0 | G47: =IFERROR(Calc!$AE$8/SUM(Calc!$AE$5:$AE$604),"") -> 0 | I47: =IF(Goals!$B$8="","",Goals!$B$8) -> 0 | J47: =IF(Goals!$B$8="","",Goals!$K$8) -> 0 | K47: =IF(Goals!$B$8="","",Goals!$J$8) -> 0 | L47: =IF(Goals!$B$8="","",Goals!$R$8) -> 0 | M47: =IF(Goals!$B$8="","",Goals!$V$8) -> 0 | N47: =IF(Goals!$B$8="","",Goals!$L$8) -> 0
A48: =IF(Calc!$T$9="","",Calc!$T$9) -> 0 | B48: =IF(Calc!$T$9="","",Calc!$AD$9) -> 0 | C48: =IF(Calc!$T$9="","",Calc!$AE$9) -> 0 | D48: =IF(Calc!$T$9="","",Calc!$AF$9) -> 0 | E48: =IF(Calc!$T$9="","",Calc!$AG$9) -> 0 | F48: =IF(Calc!$T$9="","",Calc!$AH$9) -> 0 | G48: =IFERROR(Calc!$AE$9/SUM(Calc!$AE$5:$AE$604),"") -> 0 | I48: =IF(Goals!$B$9="","",Goals!$B$9) -> 0 | J48: =IF(Goals!$B$9="","",Goals!$K$9) -> 0 | K48: =IF(Goals!$B$9="","",Goals!$J$9) -> 0 | L48: =IF(Goals!$B$9="","",Goals!$R$9) -> 0 | M48: =IF(Goals!$B$9="","",Goals!$V$9) -> 0 | N48: =IF(Goals!$B$9="","",Goals!$L$9) -> 0
A49: =IF(Calc!$T$10="","",Calc!$T$10) -> 0 | B49: =IF(Calc!$T$10="","",Calc!$AD$10) -> 0 | C49: =IF(Calc!$T$10="","",Calc!$AE$10) -> 0 | D49: =IF(Calc!$T$10="","",Calc!$AF$10) -> 0 | E49: =IF(Calc!$T$10="","",Calc!$AG$10) -> 0 | F49: =IF(Calc!$T$10="","",Calc!$AH$10) -> 0 | G49: =IFERROR(Calc!$AE$10/SUM(Calc!$AE$5:$AE$604),"") -> 0 | I49: =IF(Goals!$B$10="","",Goals!$B$10) -> 0 | J49: =IF(Goals!$B$10="","",Goals!$K$10) -> 0 | K49: =IF(Goals!$B$10="","",Goals!$J$10) -> 0 | L49: =IF(Goals!$B$10="","",Goals!$R$10) -> 0 | M49: =IF(Goals!$B$10="","",Goals!$V$10) -> 0 | N49: =IF(Goals!$B$10="","",Goals!$L$10) -> 0
A50: =IF(Calc!$T$11="","",Calc!$T$11) -> 0 | B50: =IF(Calc!$T$11="","",Calc!$AD$11) -> 0 | C50: =IF(Calc!$T$11="","",Calc!$AE$11) -> 0 | D50: =IF(Calc!$T$11="","",Calc!$AF$11) -> 0 | E50: =IF(Calc!$T$11="","",Calc!$AG$11) -> 0 | F50: =IF(Calc!$T$11="","",Calc!$AH$11) -> 0 | G50: =IFERROR(Calc!$AE$11/SUM(Calc!$AE$5:$AE$604),"") -> 0 | I50: =IF(Goals!$B$11="","",Goals!$B$11) -> 0 | J50: =IF(Goals!$B$11="","",Goals!$K$11) -> 0 | K50: =IF(Goals!$B$11="","",Goals!$J$11) -> 0 | L50: =IF(Goals!$B$11="","",Goals!$R$11) -> 0 | M50: =IF(Goals!$B$11="","",Goals!$V$11) -> 0 | N50: =IF(Goals!$B$11="","",Goals!$L$11) -> 0
A51: =IF(Calc!$T$12="","",Calc!$T$12) -> 0 | B51: =IF(Calc!$T$12="","",Calc!$AD$12) -> 0 | C51: =IF(Calc!$T$12="","",Calc!$AE$12) -> 0 | D51: =IF(Calc!$T$12="","",Calc!$AF$12) -> 0 | E51: =IF(Calc!$T$12="","",Calc!$AG$12) -> 0 | F51: =IF(Calc!$T$12="","",Calc!$AH$12) -> 0 | G51: =IFERROR(Calc!$AE$12/SUM(Calc!$AE$5:$AE$604),"") -> 0 | I51: =IF(Goals!$B$12="","",Goals!$B$12) -> 0 | J51: =IF(Goals!$B$12="","",Goals!$K$12) -> 0 | K51: =IF(Goals!$B$12="","",Goals!$J$12) -> 0 | L51: =IF(Goals!$B$12="","",Goals!$R$12) -> 0 | M51: =IF(Goals!$B$12="","",Goals!$V$12) -> 0 | N51: =IF(Goals!$B$12="","",Goals!$L$12) -> 0
A53: Best of 2026
A54: Top 10 posts of the year (by engagement rate) | J54: Where your reach came from
A55: # | B55: Post | C55: Platform | D55: Pillar | E55: Date | F55: Reach | G55: Eng. rate | J55: Format | K55: Posts | L55: Reach | M55: Engagements | N55: Eng. rate
A56: 1 | B56: =IFERROR(INDEX(Calc!$BH$5:$BH$604,MATCH(LARGE(Calc!$BQ$5:$BQ$604,1),Calc!$BQ$5:$BQ$604,0)),"") -> 0 | C56: =IFERROR(INDEX(Calc!$BI$5:$BI$604,MATCH(LARGE(Calc!$BQ$5:$BQ$604,1),Calc!$BQ$5:$BQ$604,0)),"") -> 0 | D56: =IFERROR(INDEX(Calc!$BJ$5:$BJ$604,MATCH(LARGE(Calc!$BQ$5:$BQ$604,1),Calc!$BQ$5:$BQ$604,0)),"") -> 0 | E56: =IFERROR(INDEX(Calc!$BK$5:$BK$604,MATCH(LARGE(Calc!$BQ$5:$BQ$604,1),Calc!$BQ$5:$BQ$604,0)),"") -> 0 | F56: =IFERROR(INDEX(Calc!$BM$5:$BM$604,MATCH(LARGE(Calc!$BQ$5:$BQ$604,1),Calc!$BQ$5:$BQ$604,0)),"") -> 0 | G56: =IFERROR(INDEX(Calc!$BN$5:$BN$604,MATCH(LARGE(Calc!$BQ$5:$BQ$604,1),Calc!$BQ$5:$BQ$604,0)),"") -> 0 | J56: =IF(Calc!$AP$5="","",Calc!$AP$5) -> 0 | K56: =IF(Calc!$AP$5="","",Calc!$AQ$5) -> 0 | L56: =IF(Calc!$AP$5="","",Calc!$AR$5) -> 0 | M56: =IF(Calc!$AP$5="","",Calc!$AS$5) -> 0 | N56: =IF(Calc!$AP$5="","",Calc!$AT$5) -> 0
A57: 2 | B57: =IFERROR(INDEX(Calc!$BH$5:$BH$604,MATCH(LARGE(Calc!$BQ$5:$BQ$604,2),Calc!$BQ$5:$BQ$604,0)),"") -> 0 | C57: =IFERROR(INDEX(Calc!$BI$5:$BI$604,MATCH(LARGE(Calc!$BQ$5:$BQ$604,2),Calc!$BQ$5:$BQ$604,0)),"") -> 0 | D57: =IFERROR(INDEX(Calc!$BJ$5:$BJ$604,MATCH(LARGE(Calc!$BQ$5:$BQ$604,2),Calc!$BQ$5:$BQ$604,0)),"") -> 0 | E57: =IFERROR(INDEX(Calc!$BK$5:$BK$604,MATCH(LARGE(Calc!$BQ$5:$BQ$604,2),Calc!$BQ$5:$BQ$604,0)),"") -> 0 | F57: =IFERROR(INDEX(Calc!$BM$5:$BM$604,MATCH(LARGE(Calc!$BQ$5:$BQ$604,2),Calc!$BQ$5:$BQ$604,0)),"") -> 0 | G57: =IFERROR(INDEX(Calc!$BN$5:$BN$604,MATCH(LARGE(Calc!$BQ$5:$BQ$604,2),Calc!$BQ$5:$BQ$604,0)),"") -> 0 | J57: =IF(Calc!$AP$6="","",Calc!$AP$6) -> 0 | K57: =IF(Calc!$AP$6="","",Calc!$AQ$6) -> 0 | L57: =IF(Calc!$AP$6="","",Calc!$AR$6) -> 0 | M57: =IF(Calc!$AP$6="","",Calc!$AS$6) -> 0 | N57: =IF(Calc!$AP$6="","",Calc!$AT$6) -> 0
A58: 3 | B58: =IFERROR(INDEX(Calc!$BH$5:$BH$604,MATCH(LARGE(Calc!$BQ$5:$BQ$604,3),Calc!$BQ$5:$BQ$604,0)),"") -> 0 | C58: =IFERROR(INDEX(Calc!$BI$5:$BI$604,MATCH(LARGE(Calc!$BQ$5:$BQ$604,3),Calc!$BQ$5:$BQ$604,0)),"") -> 0 | D58: =IFERROR(INDEX(Calc!$BJ$5:$BJ$604,MATCH(LARGE(Calc!$BQ$5:$BQ$604,3),Calc!$BQ$5:$BQ$604,0)),"") -> 0 | E58: =IFERROR(INDEX(Calc!$BK$5:$BK$604,MATCH(LARGE(Calc!$BQ$5:$BQ$604,3),Calc!$BQ$5:$BQ$604,0)),"") -> 0 | F58: =IFERROR(INDEX(Calc!$BM$5:$BM$604,MATCH(LARGE(Calc!$BQ$5:$BQ$604,3),Calc!$BQ$5:$BQ$604,0)),"") -> 0 | G58: =IFERROR(INDEX(Calc!$BN$5:$BN$604,MATCH(LARGE(Calc!$BQ$5:$BQ$604,3),Calc!$BQ$5:$BQ$604,0)),"") -> 0 | J58: =IF(Calc!$AP$7="","",Calc!$AP$7) -> 0 | K58: =IF(Calc!$AP$7="","",Calc!$AQ$7) -> 0 | L58: =IF(Calc!$AP$7="","",Calc!$AR$7) -> 0 | M58: =IF(Calc!$AP$7="","",Calc!$AS$7) -> 0 | N58: =IF(Calc!$AP$7="","",Calc!$AT$7) -> 0
A59: 4 | B59: =IFERROR(INDEX(Calc!$BH$5:$BH$604,MATCH(LARGE(Calc!$BQ$5:$BQ$604,4),Calc!$BQ$5:$BQ$604,0)),"") -> 0 | C59: =IFERROR(INDEX(Calc!$BI$5:$BI$604,MATCH(LARGE(Calc!$BQ$5:$BQ$604,4),Calc!$BQ$5:$BQ$604,0)),"") -> 0 | D59: =IFERROR(INDEX(Calc!$BJ$5:$BJ$604,MATCH(LARGE(Calc!$BQ$5:$BQ$604,4),Calc!$BQ$5:$BQ$604,0)),"") -> 0 | E59: =IFERROR(INDEX(Calc!$BK$5:$BK$604,MATCH(LARGE(Calc!$BQ$5:$BQ$604,4),Calc!$BQ$5:$BQ$604,0)),"") -> 0 | F59: =IFERROR(INDEX(Calc!$BM$5:$BM$604,MATCH(LARGE(Calc!$BQ$5:$BQ$604,4),Calc!$BQ$5:$BQ$604,0)),"") -> 0 | G59: =IFERROR(INDEX(Calc!$BN$5:$BN$604,MATCH(LARGE(Calc!$BQ$5:$BQ$604,4),Calc!$BQ$5:$BQ$604,0)),"") -> 0 | J59: =IF(Calc!$AP$8="","",Calc!$AP$8) -> 0 | K59: =IF(Calc!$AP$8="","",Calc!$AQ$8) -> 0 | L59: =IF(Calc!$AP$8="","",Calc!$AR$8) -> 0 | M59: =IF(Calc!$AP$8="","",Calc!$AS$8) -> 0 | N59: =IF(Calc!$AP$8="","",Calc!$AT$8) -> 0
A60: 5 | B60: =IFERROR(INDEX(Calc!$BH$5:$BH$604,MATCH(LARGE(Calc!$BQ$5:$BQ$604,5),Calc!$BQ$5:$BQ$604,0)),"") -> 0 | C60: =IFERROR(INDEX(Calc!$BI$5:$BI$604,MATCH(LARGE(Calc!$BQ$5:$BQ$604,5),Calc!$BQ$5:$BQ$604,0)),"") -> 0 | D60: =IFERROR(INDEX(Calc!$BJ$5:$BJ$604,MATCH(LARGE(Calc!$BQ$5:$BQ$604,5),Calc!$BQ$5:$BQ$604,0)),"") -> 0 | E60: =IFERROR(INDEX(Calc!$BK$5:$BK$604,MATCH(LARGE(Calc!$BQ$5:$BQ$604,5),Calc!$BQ$5:$BQ$604,0)),"") -> 0 | F60: =IFERROR(INDEX(Calc!$BM$5:$BM$604,MATCH(LARGE(Calc!$BQ$5:$BQ$604,5),Calc!$BQ$5:$BQ$604,0)),"") -> 0 | G60: =IFERROR(INDEX(Calc!$BN$5:$BN$604,MATCH(LARGE(Calc!$BQ$5:$BQ$604,5),Calc!$BQ$5:$BQ$604,0)),"") -> 0 | J60: =IF(Calc!$AP$9="","",Calc!$AP$9) -> 0 | K60: =IF(Calc!$AP$9="","",Calc!$AQ$9) -> 0 | L60: =IF(Calc!$AP$9="","",Calc!$AR$9) -> 0 | M60: =IF(Calc!$AP$9="","",Calc!$AS$9) -> 0 | N60: =IF(Calc!$AP$9="","",Calc!$AT$9) -> 0
A61: 6 | B61: =IFERROR(INDEX(Calc!$BH$5:$BH$604,MATCH(LARGE(Calc!$BQ$5:$BQ$604,6),Calc!$BQ$5:$BQ$604,0)),"") -> 0 | C61: =IFERROR(INDEX(Calc!$BI$5:$BI$604,MATCH(LARGE(Calc!$BQ$5:$BQ$604,6),Calc!$BQ$5:$BQ$604,0)),"") -> 0 | D61: =IFERROR(INDEX(Calc!$BJ$5:$BJ$604,MATCH(LARGE(Calc!$BQ$5:$BQ$604,6),Calc!$BQ$5:$BQ$604,0)),"") -> 0 | E61: =IFERROR(INDEX(Calc!$BK$5:$BK$604,MATCH(LARGE(Calc!$BQ$5:$BQ$604,6),Calc!$BQ$5:$BQ$604,0)),"") -> 0 | F61: =IFERROR(INDEX(Calc!$BM$5:$BM$604,MATCH(LARGE(Calc!$BQ$5:$BQ$604,6),Calc!$BQ$5:$BQ$604,0)),"") -> 0 | G61: =IFERROR(INDEX(Calc!$BN$5:$BN$604,MATCH(LARGE(Calc!$BQ$5:$BQ$604,6),Calc!$BQ$5:$BQ$604,0)),"") -> 0 | J61: =IF(Calc!$AP$10="","",Calc!$AP$10) -> 0 | K61: =IF(Calc!$AP$10="","",Calc!$AQ$10) -> 0 | L61: =IF(Calc!$AP$10="","",Calc!$AR$10) -> 0 | M61: =IF(Calc!$AP$10="","",Calc!$AS$10) -> 0 | N61: =IF(Calc!$AP$10="","",Calc!$AT$10) -> 0
A62: 7 | B62: =IFERROR(INDEX(Calc!$BH$5:$BH$604,MATCH(LARGE(Calc!$BQ$5:$BQ$604,7),Calc!$BQ$5:$BQ$604,0)),"") -> 0 | C62: =IFERROR(INDEX(Calc!$BI$5:$BI$604,MATCH(LARGE(Calc!$BQ$5:$BQ$604,7),Calc!$BQ$5:$BQ$604,0)),"") -> 0 | D62: =IFERROR(INDEX(Calc!$BJ$5:$BJ$604,MATCH(LARGE(Calc!$BQ$5:$BQ$604,7),Calc!$BQ$5:$BQ$604,0)),"") -> 0 | E62: =IFERROR(INDEX(Calc!$BK$5:$BK$604,MATCH(LARGE(Calc!$BQ$5:$BQ$604,7),Calc!$BQ$5:$BQ$604,0)),"") -> 0 | F62: =IFERROR(INDEX(Calc!$BM$5:$BM$604,MATCH(LARGE(Calc!$BQ$5:$BQ$604,7),Calc!$BQ$5:$BQ$604,0)),"") -> 0 | G62: =IFERROR(INDEX(Calc!$BN$5:$BN$604,MATCH(LARGE(Calc!$BQ$5:$BQ$604,7),Calc!$BQ$5:$BQ$604,0)),"") -> 0 | J62: =IF(Calc!$AP$11="","",Calc!$AP$11) -> 0 | K62: =IF(Calc!$AP$11="","",Calc!$AQ$11) -> 0 | L62: =IF(Calc!$AP$11="","",Calc!$AR$11) -> 0 | M62: =IF(Calc!$AP$11="","",Calc!$AS$11) -> 0 | N62: =IF(Calc!$AP$11="","",Calc!$AT$11) -> 0
A63: 8 | B63: =IFERROR(INDEX(Calc!$BH$5:$BH$604,MATCH(LARGE(Calc!$BQ$5:$BQ$604,8),Calc!$BQ$5:$BQ$604,0)),"") -> 0 | C63: =IFERROR(INDEX(Calc!$BI$5:$BI$604,MATCH(LARGE(Calc!$BQ$5:$BQ$604,8),Calc!$BQ$5:$BQ$604,0)),"") -> 0 | D63: =IFERROR(INDEX(Calc!$BJ$5:$BJ$604,MATCH(LARGE(Calc!$BQ$5:$BQ$604,8),Calc!$BQ$5:$BQ$604,0)),"") -> 0 | E63: =IFERROR(INDEX(Calc!$BK$5:$BK$604,MATCH(LARGE(Calc!$BQ$5:$BQ$604,8),Calc!$BQ$5:$BQ$604,0)),"") -> 0 | F63: =IFERROR(INDEX(Calc!$BM$5:$BM$604,MATCH(LARGE(Calc!$BQ$5:$BQ$604,8),Calc!$BQ$5:$BQ$604,0)),"") -> 0 | G63: =IFERROR(INDEX(Calc!$BN$5:$BN$604,MATCH(LARGE(Calc!$BQ$5:$BQ$604,8),Calc!$BQ$5:$BQ$604,0)),"") -> 0 | J63: =IF(Calc!$AP$12="","",Calc!$AP$12) -> 0 | K63: =IF(Calc!$AP$12="","",Calc!$AQ$12) -> 0 | L63: =IF(Calc!$AP$12="","",Calc!$AR$12) -> 0 | M63: =IF(Calc!$AP$12="","",Calc!$AS$12) -> 0 | N63: =IF(Calc!$AP$12="","",Calc!$AT$12) -> 0
A64: 9 | B64: =IFERROR(INDEX(Calc!$BH$5:$BH$604,MATCH(LARGE(Calc!$BQ$5:$BQ$604,9),Calc!$BQ$5:$BQ$604,0)),"") -> 0 | C64: =IFERROR(INDEX(Calc!$BI$5:$BI$604,MATCH(LARGE(Calc!$BQ$5:$BQ$604,9),Calc!$BQ$5:$BQ$604,0)),"") -> 0 | D64: =IFERROR(INDEX(Calc!$BJ$5:$BJ$604,MATCH(LARGE(Calc!$BQ$5:$BQ$604,9),Calc!$BQ$5:$BQ$604,0)),"") -> 0 | E64: =IFERROR(INDEX(Calc!$BK$5:$BK$604,MATCH(LARGE(Calc!$BQ$5:$BQ$604,9),Calc!$BQ$5:$BQ$604,0)),"") -> 0 | F64: =IFERROR(INDEX(Calc!$BM$5:$BM$604,MATCH(LARGE(Calc!$BQ$5:$BQ$604,9),Calc!$BQ$5:$BQ$604,0)),"") -> 0 | G64: =IFERROR(INDEX(Calc!$BN$5:$BN$604,MATCH(LARGE(Calc!$BQ$5:$BQ$604,9),Calc!$BQ$5:$BQ$604,0)),"") -> 0 | J64: =IF(Calc!$AP$13="","",Calc!$AP$13) -> 0 | K64: =IF(Calc!$AP$13="","",Calc!$AQ$13) -> 0 | L64: =IF(Calc!$AP$13="","",Calc!$AR$13) -> 0 | M64: =IF(Calc!$AP$13="","",Calc!$AS$13) -> 0 | N64: =IF(Calc!$AP$13="","",Calc!$AT$13) -> 0
A65: 10 | B65: =IFERROR(INDEX(Calc!$BH$5:$BH$604,MATCH(LARGE(Calc!$BQ$5:$BQ$604,10),Calc!$BQ$5:$BQ$604,0)),"") -> 0 | C65: =IFERROR(INDEX(Calc!$BI$5:$BI$604,MATCH(LARGE(Calc!$BQ$5:$BQ$604,10),Calc!$BQ$5:$BQ$604,0)),"") -> 0 | D65: =IFERROR(INDEX(Calc!$BJ$5:$BJ$604,MATCH(LARGE(Calc!$BQ$5:$BQ$604,10),Calc!$BQ$5:$BQ$604,0)),"") -> 0 | E65: =IFERROR(INDEX(Calc!$BK$5:$BK$604,MATCH(LARGE(Calc!$BQ$5:$BQ$604,10),Calc!$BQ$5:$BQ$604,0)),"") -> 0 | F65: =IFERROR(INDEX(Calc!$BM$5:$BM$604,MATCH(LARGE(Calc!$BQ$5:$BQ$604,10),Calc!$BQ$5:$BQ$604,0)),"") -> 0 | G65: =IFERROR(INDEX(Calc!$BN$5:$BN$604,MATCH(LARGE(Calc!$BQ$5:$BQ$604,10),Calc!$BQ$5:$BQ$604,0)),"") -> 0 | J65: =IF(Calc!$AP$14="","",Calc!$AP$14) -> 0 | K65: =IF(Calc!$AP$14="","",Calc!$AQ$14) -> 0 | L65: =IF(Calc!$AP$14="","",Calc!$AR$14) -> 0 | M65: =IF(Calc!$AP$14="","",Calc!$AS$14) -> 0 | N65: =IF(Calc!$AP$14="","",Calc!$AT$14) -> 0
A67: When to post & what to do next
A68: Day | B68: Posts | C68: Reach | D68: Engagements | E68: Eng. rate | G68: Time slot | H68: Posts | I68: Reach | J68: Engagements | K68: Eng. rate | M68: Campaigns by revenue
A69: =IF(Calc!$AV$5="","",Calc!$AV$5) -> 0 | B69: =IF(Calc!$AV$5="","",Calc!$AW$5) -> 0 | C69: =IF(Calc!$AV$5="","",Calc!$AX$5) -> 0 | D69: =IF(Calc!$AV$5="","",Calc!$AY$5) -> 0 | E69: =IF(Calc!$AV$5="","",Calc!$AZ$5) -> 0 | G69: =IF(Calc!$BB$5="","",Calc!$BB$5) -> 0 | H69: =IF(Calc!$BB$5="","",Calc!$BC$5) -> 0 | I69: =IF(Calc!$BB$5="","",Calc!$BD$5) -> 0 | J69: =IF(Calc!$BB$5="","",Calc!$BE$5) -> 0 | K69: =IF(Calc!$BB$5="","",Calc!$BF$5) -> 0 | M69: Campaign | N69: Revenue | O69: Spend | P69: Return
A70: =IF(Calc!$AV$6="","",Calc!$AV$6) -> 0 | B70: =IF(Calc!$AV$6="","",Calc!$AW$6) -> 0 | C70: =IF(Calc!$AV$6="","",Calc!$AX$6) -> 0 | D70: =IF(Calc!$AV$6="","",Calc!$AY$6) -> 0 | E70: =IF(Calc!$AV$6="","",Calc!$AZ$6) -> 0 | G70: =IF(Calc!$BB$6="","",Calc!$BB$6) -> 0 | H70: =IF(Calc!$BB$6="","",Calc!$BC$6) -> 0 | I70: =IF(Calc!$BB$6="","",Calc!$BD$6) -> 0 | J70: =IF(Calc!$BB$6="","",Calc!$BE$6) -> 0 | K70: =IF(Calc!$BB$6="","",Calc!$BF$6) -> 0 | M70: =IFERROR(INDEX(Calc!$CA$5:$CA$604,MATCH(LARGE(Calc!$CE$5:$CE$604,1),Calc!$CE$5:$CE$604,0)),"") -> 0 | N70: =IFERROR(INDEX(Calc!$CB$5:$CB$604,MATCH(LARGE(Calc!$CE$5:$CE$604,1),Calc!$CE$5:$CE$604,0)),"") -> 0 | O70: =IFERROR(INDEX(Calc!$CC$5:$CC$604,MATCH(LARGE(Calc!$CE$5:$CE$604,1),Calc!$CE$5:$CE$604,0)),"") -> 0 | P70: =IFERROR(INDEX(Calc!$CB$5:$CB$604,MATCH(LARGE(Calc!$CE$5:$CE$604,1),Calc!$CE$5:$CE$604,0))/INDEX(Calc!$CC$5:$CC$604,MATCH(LARGE(Calc!$CE$5:$CE$604,1),Calc!$CE$5:$CE$604,0)),"") -> 0
A71: =IF(Calc!$AV$7="","",Calc!$AV$7) -> 0 | B71: =IF(Calc!$AV$7="","",Calc!$AW$7) -> 0 | C71: =IF(Calc!$AV$7="","",Calc!$AX$7) -> 0 | D71: =IF(Calc!$AV$7="","",Calc!$AY$7) -> 0 | E71: =IF(Calc!$AV$7="","",Calc!$AZ$7) -> 0 | G71: =IF(Calc!$BB$7="","",Calc!$BB$7) -> 0 | H71: =IF(Calc!$BB$7="","",Calc!$BC$7) -> 0 | I71: =IF(Calc!$BB$7="","",Calc!$BD$7) -> 0 | J71: =IF(Calc!$BB$7="","",Calc!$BE$7) -> 0 | K71: =IF(Calc!$BB$7="","",Calc!$BF$7) -> 0 | M71: =IFERROR(INDEX(Calc!$CA$5:$CA$604,MATCH(LARGE(Calc!$CE$5:$CE$604,2),Calc!$CE$5:$CE$604,0)),"") -> 0 | N71: =IFERROR(INDEX(Calc!$CB$5:$CB$604,MATCH(LARGE(Calc!$CE$5:$CE$604,2),Calc!$CE$5:$CE$604,0)),"") -> 0 | O71: =IFERROR(INDEX(Calc!$CC$5:$CC$604,MATCH(LARGE(Calc!$CE$5:$CE$604,2),Calc!$CE$5:$CE$604,0)),"") -> 0 | P71: =IFERROR(INDEX(Calc!$CB$5:$CB$604,MATCH(LARGE(Calc!$CE$5:$CE$604,2),Calc!$CE$5:$CE$604,0))/INDEX(Calc!$CC$5:$CC$604,MATCH(LARGE(Calc!$CE$5:$CE$604,2),Calc!$CE$5:$CE$604,0)),"") -> 0
A72: =IF(Calc!$AV$8="","",Calc!$AV$8) -> 0 | B72: =IF(Calc!$AV$8="","",Calc!$AW$8) -> 0 | C72: =IF(Calc!$AV$8="","",Calc!$AX$8) -> 0 | D72: =IF(Calc!$AV$8="","",Calc!$AY$8) -> 0 | E72: =IF(Calc!$AV$8="","",Calc!$AZ$8) -> 0 | G72: =IF(Calc!$BB$8="","",Calc!$BB$8) -> 0 | H72: =IF(Calc!$BB$8="","",Calc!$BC$8) -> 0 | I72: =IF(Calc!$BB$8="","",Calc!$BD$8) -> 0 | J72: =IF(Calc!$BB$8="","",Calc!$BE$8) -> 0 | K72: =IF(Calc!$BB$8="","",Calc!$BF$8) -> 0 | M72: =IFERROR(INDEX(Calc!$CA$5:$CA$604,MATCH(LARGE(Calc!$CE$5:$CE$604,3),Calc!$CE$5:$CE$604,0)),"") -> 0 | N72: =IFERROR(INDEX(Calc!$CB$5:$CB$604,MATCH(LARGE(Calc!$CE$5:$CE$604,3),Calc!$CE$5:$CE$604,0)),"") -> 0 | O72: =IFERROR(INDEX(Calc!$CC$5:$CC$604,MATCH(LARGE(Calc!$CE$5:$CE$604,3),Calc!$CE$5:$CE$604,0)),"") -> 0 | P72: =IFERROR(INDEX(Calc!$CB$5:$CB$604,MATCH(LARGE(Calc!$CE$5:$CE$604,3),Calc!$CE$5:$CE$604,0))/INDEX(Calc!$CC$5:$CC$604,MATCH(LARGE(Calc!$CE$5:$CE$604,3),Calc!$CE$5:$CE$604,0)),"") -> 0
A73: =IF(Calc!$AV$9="","",Calc!$AV$9) -> 0 | B73: =IF(Calc!$AV$9="","",Calc!$AW$9) -> 0 | C73: =IF(Calc!$AV$9="","",Calc!$AX$9) -> 0 | D73: =IF(Calc!$AV$9="","",Calc!$AY$9) -> 0 | E73: =IF(Calc!$AV$9="","",Calc!$AZ$9) -> 0 | G73: =IF(Calc!$BB$9="","",Calc!$BB$9) -> 0 | H73: =IF(Calc!$BB$9="","",Calc!$BC$9) -> 0 | I73: =IF(Calc!$BB$9="","",Calc!$BD$9) -> 0 | J73: =IF(Calc!$BB$9="","",Calc!$BE$9) -> 0 | K73: =IF(Calc!$BB$9="","",Calc!$BF$9) -> 0 | M73: =IFERROR(INDEX(Calc!$CA$5:$CA$604,MATCH(LARGE(Calc!$CE$5:$CE$604,4),Calc!$CE$5:$CE$604,0)),"") -> 0 | N73: =IFERROR(INDEX(Calc!$CB$5:$CB$604,MATCH(LARGE(Calc!$CE$5:$CE$604,4),Calc!$CE$5:$CE$604,0)),"") -> 0 | O73: =IFERROR(INDEX(Calc!$CC$5:$CC$604,MATCH(LARGE(Calc!$CE$5:$CE$604,4),Calc!$CE$5:$CE$604,0)),"") -> 0 | P73: =IFERROR(INDEX(Calc!$CB$5:$CB$604,MATCH(LARGE(Calc!$CE$5:$CE$604,4),Calc!$CE$5:$CE$604,0))/INDEX(Calc!$CC$5:$CC$604,MATCH(LARGE(Calc!$CE$5:$CE$604,4),Calc!$CE$5:$CE$604,0)),"") -> 0
A74: =IF(Calc!$AV$10="","",Calc!$AV$10) -> 0 | B74: =IF(Calc!$AV$10="","",Calc!$AW$10) -> 0 | C74: =IF(Calc!$AV$10="","",Calc!$AX$10) -> 0 | D74: =IF(Calc!$AV$10="","",Calc!$AY$10) -> 0 | E74: =IF(Calc!$AV$10="","",Calc!$AZ$10) -> 0 | G74: =IF(Calc!$BB$10="","",Calc!$BB$10) -> 0 | H74: =IF(Calc!$BB$10="","",Calc!$BC$10) -> 0 | I74: =IF(Calc!$BB$10="","",Calc!$BD$10) -> 0 | J74: =IF(Calc!$BB$10="","",Calc!$BE$10) -> 0 | K74: =IF(Calc!$BB$10="","",Calc!$BF$10) -> 0 | M74: =IFERROR(INDEX(Calc!$CA$5:$CA$604,MATCH(LARGE(Calc!$CE$5:$CE$604,5),Calc!$CE$5:$CE$604,0)),"") -> 0 | N74: =IFERROR(INDEX(Calc!$CB$5:$CB$604,MATCH(LARGE(Calc!$CE$5:$CE$604,5),Calc!$CE$5:$CE$604,0)),"") -> 0 | O74: =IFERROR(INDEX(Calc!$CC$5:$CC$604,MATCH(LARGE(Calc!$CE$5:$CE$604,5),Calc!$CE$5:$CE$604,0)),"") -> 0 | P74: =IFERROR(INDEX(Calc!$CB$5:$CB$604,MATCH(LARGE(Calc!$CE$5:$CE$604,5),Calc!$CE$5:$CE$604,0))/INDEX(Calc!$CC$5:$CC$604,MATCH(LARGE(Calc!$CE$5:$CE$604,5),Calc!$CE$5:$CE$604,0)),"") -> 0
A75: =IF(Calc!$AV$11="","",Calc!$AV$11) -> 0 | B75: =IF(Calc!$AV$11="","",Calc!$AW$11) -> 0 | C75: =IF(Calc!$AV$11="","",Calc!$AX$11) -> 0 | D75: =IF(Calc!$AV$11="","",Calc!$AY$11) -> 0 | E75: =IF(Calc!$AV$11="","",Calc!$AZ$11) -> 0 | G75: =IF(Calc!$BB$11="","",Calc!$BB$11) -> 0 | H75: =IF(Calc!$BB$11="","",Calc!$BC$11) -> 0 | I75: =IF(Calc!$BB$11="","",Calc!$BD$11) -> 0 | J75: =IF(Calc!$BB$11="","",Calc!$BE$11) -> 0 | K75: =IF(Calc!$BB$11="","",Calc!$BF$11) -> 0 | M75: =IFERROR(INDEX(Calc!$CA$5:$CA$604,MATCH(LARGE(Calc!$CE$5:$CE$604,6),Calc!$CE$5:$CE$604,0)),"") -> 0 | N75: =IFERROR(INDEX(Calc!$CB$5:$CB$604,MATCH(LARGE(Calc!$CE$5:$CE$604,6),Calc!$CE$5:$CE$604,0)),"") -> 0 | O75: =IFERROR(INDEX(Calc!$CC$5:$CC$604,MATCH(LARGE(Calc!$CE$5:$CE$604,6),Calc!$CE$5:$CE$604,0)),"") -> 0 | P75: =IFERROR(INDEX(Calc!$CB$5:$CB$604,MATCH(LARGE(Calc!$CE$5:$CE$604,6),Calc!$CE$5:$CE$604,0))/INDEX(Calc!$CC$5:$CC$604,MATCH(LARGE(Calc!$CE$5:$CE$604,6),Calc!$CE$5:$CE$604,0)),"") -> 0
A77: Use this page at the end of the year: look at the best month, the best day, the best format and your top ten posts, then build next year's pillars around what actually worked.

Sheet Settings
A1: Business Setup & Settings | G1: Novality Store | v1.0.0
A2: Fill in the cream cells once. Grey cells are locked formulas. Everything else in the workbook reads these values.
A3: > Start Here | C3: > Dashboard | E3: > Calendar | G3: > Ideas
A5: 1. Brand details
B6: Business or brand name | D6: Wildflower Studio | F6: Shown on every printable page and report.
B7: Owner / main contact | D7: Jordan Avery
B8: Email | D8: hello@wildflowerstudio.com
B9: Phone | D9: +1 (555) 017 4410
B10: Website | D10: www.wildflowerstudio.com
B11: Shop / booking link | D11: shop.wildflowerstudio.com | F11: The link you send people to - used in the campaign and launch planners.
B12: Industry | D12: Handmade home & lifestyle
B13: Niche / speciality | D13: Sustainable ceramics and home styling
B14: Target audience | D14: Women 28-45 who love slow living, handmade homeware and styling their first home | F14: One sentence. The Audience Personas tab breaks this down properly.
B15: Main marketing goal | D15: Grow to 25,000 followers and 1,200 shop visits a month
B16: Branded hashtag | D16: #wildflowerstudio
A18: 2. Visual identity reference
B19: Logo file / link | D19: brand-assets/wildflower-logo.png | F19: Paste a cloud link. Spreadsheets cannot preview an external image, so keep the link handy.
B20: Brand colour palette | D20: #3B2A6B indigo, #F2665E coral, #F4EFE6 oat
B21: Fonts / typography | D21: Headings: Canela. Body: Inter.
B22: Brand asset folder | D22: brand-assets/
A24: 3. Calendar & time settings
B25: Planning year | D25: 2026 | E25: The year the dashboards and the 12 month calendar open on.
B26: Week starts on | D26: Monday | E26: Used by the week numbers on the calendar.
B27: Time zone | D27: GMT-05:00 Eastern Time | F27: Posting times on the calendar are in this zone.
B28: Currency code | D28: USD | E28: Budget and revenue columns use the currency symbol set when the workbook was built.
B29: Fiscal year starts in month | D29: 1 | E29: 1 = January. Used by the quarterly report.
A31: 4. Targets (the dashboards measure against these)
B32: Posts per week target | D32: 3
B33: Posts per month target | D33: 13 | E33: Actual against planned is on the dashboard.
B34: Engagement rate target | D34: 0.045 | E34: Posts at or above this rate turn green.
B35: Follower goal (end of year) | D35: 25000
B36: Reach goal (per month) | D36: 120000
B37: Website click goal (per month) | D37: 1800
B38: Lead goal (per month) | D38: 240
B39: Conversion goal (per month) | D39: 90
B40: Revenue goal (per year) | D40: 36000
A42: 5. Budget & return
B43: Marketing budget per month | D43: 900
B44: Marketing budget per year | D44: 10800
B45: Return on ad spend target | D45: 4 | E45: 4 means every 1 spent should bring back 4.
B46: Cost per lead target | D46: 6
A48: 6. Workflow & reminder windows (days)
B49: Draft ready before publishing | D49: 5 | E49: The calendar works out your draft deadline from the publishing date.
B50: Approval needed before publishing | D50: 2
B51: Idea review window | D51: 14 | E51: Ideas older than this still sitting at 'New' are flagged.
B52: Trend acts-fast window | D52: 14
B53: Asset refresh window | D53: 180
B54: Account counts as quiet after | D54: 30
A56: 7. Reference prefixes
B57: Content ID prefix | D57: C- | E57: C-0001, C-0002 ... on the Content Calendar.
B58: Idea ID prefix | D58: IDEA-
B59: Caption ID prefix | D59: CAP-
B60: Hashtag ID prefix | D60: TAG-
B61: Campaign ID prefix | D61: CMP-
B62: Asset ID prefix | D62: AS-
B64: Tip: everything on this tab is a named cell, so you can use the names in your own formulas too - type =TargetEngagement or =BrandName in any empty cell to see. The drop down options live on the Lists tab.

Sheet Lists
A1: Customisable Drop Down Lists | AN1: Novality Store | v1.0.0
A2: Edit, add or delete options below - every drop down in the workbook updates automatically. Keep each list in one unbroken block, starting in row 5.
A3: > Start Here | C3: > Dashboard | E3: > Calendar | G3: > Ideas | I3: > Captions | K3: > Hashtags | M3: > Analytics | O3: > Reports | Q3: > Help | S3: TIP: lists grow automatically (up to row 44). Deleting an option does not change posts that already use it.
A4: Yes / No | B4: Yes / No / N/A | C4: Platform | D4: Account type | E4: Content format | F4: Content status | G4: Objective | H4: Funnel stage | I4: Call to action | J4: Hook type | K4: Tone of voice | L4: Priority | M4: Idea status | N4: Idea source | O4: Seasonal event type | P4: Campaign status | Q4: Hashtag type | R4: Search intent | S4: Keyword difficulty | T4: Asset type | U4: Usage rights | V4: Approval status | W4: Collaboration type | X4: Outreach status | Y4: UGC permission | Z4: UGC source | AA4: Team role | AB4: Task status | AC4: Goal category | AD4: Goal status | AE4: Cost category | AF4: Ad objective | AG4: Test variable | AH4: Test status | AI4: Trend type | AJ4: Repurpose status | AK4: Frequency | AL4: Posting slot | AM4: Compliance status | AN4: Month | AO4: Quarter | AP4: Week starts on
A5: Yes | B5: Yes | C5: Instagram | D5: Business account | E5: Feed post | F5: Idea | G5: Awareness | H5: Awareness | I5: Follow for more | J5: Question | K5: Friendly | L5: High | M5: New | N5: Own idea | O5: Public holiday | P5: Planned | Q5: Broad reach | R5: Informational | S5: Low | T5: Photo | U5: Owned | V5: Not started | W5: Gifted product | X5: Not contacted | Y5: Not requested | Z5: Tagged post | AA5: Owner | AB5: Not started | AC5: Followers | AD5: Not started | AE5: Paid advertising | AF5: Awareness | AG5: Hook | AH5: Planned | AI5: Audio | AJ5: Planned | AK5: Daily | AL5: Early morning | AM5: Not checked | AN5: All year | AO5: All year | AP5: Monday
A6: No | B6: No | C6: TikTok | D6: Creator account | E6: Carousel | F6: Brief | G6: Engagement | H6: Consideration | I6: Save this | J6: Bold statement | K6: Playful | L6: Medium | M6: Shortlisted | N6: Customer question | O6: Awareness day | P6: Running | Q6: Niche | R6: Inspirational | S6: Medium | T6: Video clip | U6: Licensed | V6: Awaiting review | W6: Paid post | X6: Contacted | Y6: Requested | Z6: Story mention | AA6: Social media manager | AB6: In progress | AC6: Engagement | AD6: On track | AE6: Influencer fees | AF6: Traffic | AG6: Caption length | AH6: Running | AI6: Format | AJ6: In progress | AK6: 3 x week | AL6: Morning | AM6: Checked | AN6: January | AO6: Q1 | AP6: Sunday
B7: N/A | C7: Pinterest | D7: Personal profile | E7: Reel | F7: In production | G7: Traffic | H7: Conversion | I7: Share with a friend | J7: Statistic | K7: Inspiring | L7: Low | M7: Scheduled | N7: Comment | O7: Industry event | P7: Paused | Q7: Community | R7: Commercial | S7: High | T7: Graphic | U7: Royalty free | V7: Approved | W7: Affiliate | X7: Replied | Y7: Granted | Z7: Product review | AA7: Content creator | AB7: Blocked | AC7: Reach | AD7: At risk | AE7: Content production | AF7: Engagement | AG7: Thumbnail | AH7: Complete | AI7: Topic | AJ7: Published | AK7: Weekly | AL7: Lunchtime | AM7: Not required | AN7: February | AO7: Q2
C8: YouTube | D8: Page | E8: Story | F8: Draft | G8: Leads | H8: Retention | I8: Comment below | J8: Story | K8: Educational | M8: Used | N8: Direct message | O8: Seasonal sale | P8: Complete | Q8: Branded | R8: Navigational | T8: Canva template | U8: UGC with permission | V8: Revision needed | W8: Brand ambassador | X8: Negotiating | Y8: Refused | Z8: Email | AA8: Copywriter | AB8: Complete | AC8: Website traffic | AD8: Behind | AE8: Design & editing | AF8: Video views | AG8: Posting time | AH8: Inconclusive | AI8: Challenge | AJ8: Not suitable | AK8: Fortnightly | AL8: Afternoon | AM8: Issue found | AN8: March | AO8: Q3
C9: Facebook | D9: Group | E9: Short video | F9: Awaiting review | G9: Sales | I9: Link in bio | J9: Problem | K9: Professional | M9: On hold | N9: Product review | O9: Product launch | P9: Cancelled | Q9: Campaign | R9: Transactional | T9: Reel cover | U9: Influencer content | V9: Rejected | W9: Giveaway | X9: Agreed | Y9: Expired | Z9: Direct message | AA9: Designer | AC9: Leads | AD9: Achieved | AE9: Software & subscriptions | AF9: Lead generation | AG9: Format | AI9: Meme | AK9: Monthly | AL9: Evening | AM9: Fixed | AN9: April | AO9: Q4
C10: LinkedIn | D10: Channel | E10: Long video | F10: Revision needed | G10: Community | I10: Shop now | J10: Myth bust | K10: Warm | M10: Archived | N10: Competitor post | O10: Local event | Q10: Product | T10: Thumbnail | U10: Stock library | W10: Account takeover | X10: Declined | Z10: Hashtag | AA10: Video editor | AC10: Sales | AD10: Missed | AE10: Contractor fees | AF10: Sales | AG10: Call to action | AI10: Hashtag | AK10: Quarterly | AL10: Night | AN10: May
C11: X (Twitter) | D11: Shop | E11: Live | F11: Approved | G11: Retention | I11: Sign up | J11: How-to | K11: Bold | N11: Trend | O11: Cultural moment | Q11: Location | T11: Carousel set | U11: Expired | W11: Guest content | X11: Complete | Z11: Competition entry | AA11: Photographer | AC11: Revenue | AE11: Props & samples | AF11: Retargeting | AG11: Hashtag set | AI11: Platform feature | AK11: Ad hoc | AN11: June
C12: Threads | E12: Photo | F12: Scheduled | G12: Brand authority | I12: Download the guide | J12: Listicle | K12: Calm | N12: Keyword research | Q12: Seasonal | T12: Audio | W12: Event | Z12: Influencer content | AA12: Virtual assistant | AC12: Content output | AE12: Training | AF12: App installs | AG12: Cover image | AN12: July
C13: Blog | E13: Graphic | F13: Published | G13: Launch support | I13: Book a call | J13: Before and after | K13: Witty | N13: Analytics | Q13: Trending | T13: Font | AA13: Contractor | AC13: Email list | AE13: Stock media | AG13: Audio | AN13: August
C14: Email newsletter | E14: Infographic | F14: Archived | I14: Watch to the end | J14: POV | K14: Honest | N14: Team suggestion | T14: Logo | AA14: Agency | AC14: Community | AE14: Printing | AG14: Offer | AN14: September
C15: Other | E15: Text post | F15: Cancelled | I15: Reply to this | J15: Tutorial | N15: Newsletter | T15: Mockup | AE15: Other | AG15: First comment | AN15: October
E16: Poll | I16: Tag a friend | J16: Behind the scenes | N16: Repurposed | T16: UGC clip | AN16: November
E17: Standard Pin | I17: None | T17: Product shot | AN17: December
E18: Video Pin
E19: Idea Pin
E20: Blog post
E21: Newsletter
E22: Podcast
E23: UGC repost

Sheet Brand Voice
A1: Brand Voice & Identity | H1: Novality Store | v1.0.0
A2: Fill this in once. Every caption you write, every reply you send and anyone you hire should match what is on this page.
A3: > Start Here | C3: > Dashboard | E3: > Calendar | G3: > Ideas | I3: > Captions
A5: Who you are
B6: Mission - why the business exists | D6: We make everyday objects worth keeping.
B7: Vision - where it is going | D7: A handmade piece on every table, not in every cabinet.
B8: Brand promise - what people can count on | D8: Made slowly, built to be used, replaced if it fails.
B9: Brand story in one paragraph | D9: Started at a night class, kept going because people kept asking. Everything is thrown, glazed and packed by hand.
B10: What makes you different | D10: Small batches, named glazes, and the maker answers the messages.
A12: How you sound
B13: Three words that describe your voice | D13: Warm, honest, playful
B14: Three words you are not | D14: Corporate, pushy, precious
B15: Reading age / tone | D15: Chatty but clear - write like you talk
B16: Point of view | D16: First person: I made this, we packed this
B17: Humour | D17: Dry and self-deprecating, never at anyone's expense
B18: Emoji use | D18: One or two, never a wall
B19: Exclamation marks | D19: One per post at most
A21: Words
B22: Words and phrases you use | D22: handmade, small batch, slow made, everyday, kiln, glaze
B23: Words and phrases you avoid | D23: cheap, luxury, must-have, hurry, limited time only
B24: How you describe the product | D24: Stoneware made in small batches, dishwasher and microwave safe.
B25: How you describe the customer | D25: People who use the good stuff on a Tuesday.
B26: Your sign-off / signature line | D26: Made slowly, used daily.
A28: Rules
B29: Always do | D29: Reply to every comment in the first hour
B30: Never do | D30: Argue in the comments, or repost without asking
B31: How you handle a complaint | D31: Reply once publicly, move it to messages, fix it, follow up
B32: How you handle a troll | D32: Hide, do not engage, block if repeated
B33: How you handle a mistake | D33: Say it plainly, say what you are doing about it
A35: How you look
B36: Logo file / link | D36: drive/wildflower/logo
B37: Colour palette | D37: Clay #C8734A, Sand #EAE0D2, Ink #241B38
B38: Fonts | D38: Headlines: Fraunces. Body: Inter.
B39: Photo style | D39: Daylight, linen, slight mess - real tables, not studios
B40: Video style | D40: Hands, process, no voiceover, captions always
B41: Grid / feed style | D41: Alternating product, process, person
B42: Template files | D42: canva.com/wildflower-templates
A44: Profile copy
B45: Bio - short (150 characters) | D45: Handmade stoneware for everyday use. Made slowly in the studio. Shop below.
B46: Bio - long | D46: Hand-thrown ceramics made in small batches. Dishwasher safe, built to be used, shipped carefully. New glazes monthly.
B47: Link in bio destination | D47: shop.wildflowerstudio.com
B48: Pinned post / highlight | D48: Start here: how a mug is made, and how to choose a size
B49: Signature hashtag | D49: #wildflowerstudio
A51: Tone by situation
B52: Situation | C52: How you sound | D52: Example line
B53: Launching something | C53: Confident, warm | D53: It is here, and there are only forty.
B54: Teaching something | C54: Patient, plain | D54: Here is how to tell a good glaze from a lazy one.
B55: Sharing a mistake | C55: Honest, light | D55: Forty mugs, one wobbly kiln shelf. We live and learn.
B56: Celebrating a customer | C56: Generous, specific | D56: Look what Hannah did with the breakfast set.
B57: Asking for the sale | C57: Direct, no apology | D57: The restock is live. Link in bio.
B58: Replying to a complaint | C58: Calm, quick, human | D58: That should not have happened - I am sorting it today.
A60: Consistency check
B61: Check | C61: Your answer
B62: Does every profile use the same name and handle?
B63: Do all five profile pictures match?
B64: Is the bio the same tone everywhere?
B65: Do you use the same colours and fonts on graphics?
B66: Does your signature hashtag appear on every post?
B67: Could someone else write a post that sounds like you?
B69: A brand people recognise is worth more than a brand people like. Pick a voice you can keep up on a bad week, write it down here, and stick to it.

Sheet Accounts
A1: Social Media Accounts | AB1: Novality Store | v1.0.0
A2: One row per account. The grey columns count your posts, pull the reach and engagement from the Analytics tab and tell you when a profile needs attention.
A3: > Start Here | C3: > Dashboard | E3: > Calendar | G3: > Ideas | I3: > Captions | K3: > Hashtags | M3: > Analytics | O3: > Reports | Q3: > Help | S3: Add every account you post to - the dashboards compare them side by side. Mark the six profile checks Yes once you have optimised each profile.
A4: ID | B4: Platform | C4: Account / profile name | D4: Username / handle | E4: Profile URL | F4: Account type | G4: Account owner | H4: What this account is for | I4: Primary audience | J4: Followers today | K4: Account started | L4: Posts per week target | M4: Bio / description checked | N4: Profile picture on brand | O4: Cover image current | P4: Website link works | Q4: Contact details correct | R4: Platform branding done | S4: Profile score | T4: Access & responsibility notes | U4: Posts this year | V4: Published | W4: Reach this year | X4: Engagements | Y4: Engagement rate | Z4: Follower growth | AA4: Last published | AB4: Days since | AC4: Action needed | AD4: Notes
A5: =IF(C5="","","ACC-"&TEXT(ROW()-4,"000")) -> 0 | B5: Instagram | C5: Wildflower Studio | D5: @wildflower.studio | E5: instagram.com/wildflower.studio | F5: Business account | G5: Jordan Avery | H5: Main shop window - product, styling and community | I5: Home lovers 28-45 | J5: 8420 | K5: 45586 | L5: 5 | M5: Yes | N5: Yes | O5: Yes | P5: Yes | Q5: Yes | R5: Yes | S5: =IF(C5="","",(((M5="Yes")*1)+((N5="Yes")*1)+((O5="Yes")*1)+((P5="Yes")*1)+((Q5="Yes")*1)+((R5="Yes")*1))/6) -> 0 | T5: Owner + manager, 2FA on | U5: =IF(B5="","",COUNTIFS('Content Calendar'!$G$5:$G$604,B5,'Content Calendar'!$B$5:$B$604,">="&DATE(PlanYear,1,1),'Content Calendar'!$B$5:$B$604,"<="&DATE(PlanYear,12,31))) -> 0 | V5: =IF(B5="","",COUNTIFS('Content Calendar'!$G$5:$G$604,B5,'Content Calendar'!$X$5:$X$604,"Published",'Content Calendar'!$B$5:$B$604,">="&DATE(PlanYear,1,1),'Content Calendar'!$B$5:$B$604,"<="&DATE(PlanYear,12,31))) -> 0 | W5: =IF(C5="","",SUMIFS(Analytics!$J$5:$J$154,Analytics!$E$5:$E$154,C5,Analytics!$D$5:$D$154,B5)) -> 0 | X5: =IF(C5="","",SUMIFS(Analytics!$L$5:$L$154,Analytics!$E$5:$E$154,C5,Analytics!$D$5:$D$154,B5)) -> 0 | Y5: =IF(OR(W5="",W5=0),"",X5/W5) -> 0 | Z5: =IF(C5="","",SUMIFS(Analytics!$G$5:$G$154,Analytics!$E$5:$E$154,C5)-SUMIFS(Analytics!$F$5:$F$154,Analytics!$E$5:$E$154,C5)) -> 0 | AA5: =IF(B5="","",IF(SUMPRODUCT(MAX(('Content Calendar'!$G$5:$G$604=B5)*('Content Calendar'!$X$5:$X$604="Published")*'Content Calendar'!$B$5:$B$604))=0,"",SUMPRODUCT(MAX(('Content Calendar'!$G$5:$G$604=B5)*('Content Calendar'!$X$5:$X$604="Published")*'Content Calendar'!$B$5:$B$604)))) -> 0 | AB5: =IF(AA5="","",TODAY()-AA5) -> 0 | AC5: =IF(C5="","",IF(S5<1,"Action - finish the profile checklist",IF(AND(ISNUMBER(AB5),AB5>QuietAccountDays),"Check - account has gone quiet",IF(AND(Y5<>"",Y5<TargetEngagement),"Check - engagement below target","OK")))) -> 0 | AD5: Link in bio points at the shop
A6: =IF(C6="","","ACC-"&TEXT(ROW()-4,"000")) -> 0 | B6: TikTok | C6: Wildflower Studio | D6: @wildflowerstudio | E6: tiktok.com/@wildflowerstudio | F6: Creator account | G6: Priya Nair | H6: Reach new people with process and personality | I6: Home lovers 28-45 | J6: 5260 | K6: 45676 | L6: 4 | M6: Yes | N6: Yes | O6: No | P6: Yes | Q6: Yes | R6: Yes | S6: =IF(C6="","",(((M6="Yes")*1)+((N6="Yes")*1)+((O6="Yes")*1)+((P6="Yes")*1)+((Q6="Yes")*1)+((R6="Yes")*1))/6) -> 0 | T6: Owner + manager, 2FA on | U6: =IF(B6="","",COUNTIFS('Content Calendar'!$G$5:$G$604,B6,'Content Calendar'!$B$5:$B$604,">="&DATE(PlanYear,1,1),'Content Calendar'!$B$5:$B$604,"<="&DATE(PlanYear,12,31))) -> 0 | V6: =IF(B6="","",COUNTIFS('Content Calendar'!$G$5:$G$604,B6,'Content Calendar'!$X$5:$X$604,"Published",'Content Calendar'!$B$5:$B$604,">="&DATE(PlanYear,1,1),'Content Calendar'!$B$5:$B$604,"<="&DATE(PlanYear,12,31))) -> 0 | W6: =IF(C6="","",SUMIFS(Analytics!$J$5:$J$154,Analytics!$E$5:$E$154,C6,Analytics!$D$5:$D$154,B6)) -> 0 | X6: =IF(C6="","",SUMIFS(Analytics!$L$5:$L$154,Analytics!$E$5:$E$154,C6,Analytics!$D$5:$D$154,B6)) -> 0 | Y6: =IF(OR(W6="",W6=0),"",X6/W6) -> 0 | Z6: =IF(C6="","",SUMIFS(Analytics!$G$5:$G$154,Analytics!$E$5:$E$154,C6)-SUMIFS(Analytics!$F$5:$F$154,Analytics!$E$5:$E$154,C6)) -> 0 | AA6: =IF(B6="","",IF(SUMPRODUCT(MAX(('Content Calendar'!$G$5:$G$604=B6)*('Content Calendar'!$X$5:$X$604="Published")*'Content Calendar'!$B$5:$B$604))=0,"",SUMPRODUCT(MAX(('Content Calendar'!$G$5:$G$604=B6)*('Content Calendar'!$X$5:$X$604="Published")*'Content Calendar'!$B$5:$B$604)))) -> 0 | AB6: =IF(AA6="","",TODAY()-AA6) -> 0 | AC6: =IF(C6="","",IF(S6<1,"Action - finish the profile checklist",IF(AND(ISNUMBER(AB6),AB6>QuietAccountDays),"Check - account has gone quiet",IF(AND(Y6<>"",Y6<TargetEngagement),"Check - engagement below target","OK")))) -> 0
A7: =IF(C7="","","ACC-"&TEXT(ROW()-4,"000")) -> 0 | B7: Pinterest | C7: Wildflower Studio | D7: wildflowerstudio | E7: pinterest.com/wildflowerstudio | F7: Business account | G7: Sam Okonkwo | H7: Evergreen search traffic to the shop | I7: Home lovers 28-45 | J7: 3180 | K7: 45766 | L7: 3 | M7: Yes | N7: Yes | O7: Yes | P7: Yes | Q7: Yes | R7: Yes | S7: =IF(C7="","",(((M7="Yes")*1)+((N7="Yes")*1)+((O7="Yes")*1)+((P7="Yes")*1)+((Q7="Yes")*1)+((R7="Yes")*1))/6) -> 0 | T7: Owner + manager, 2FA on | U7: =IF(B7="","",COUNTIFS('Content Calendar'!$G$5:$G$604,B7,'Content Calendar'!$B$5:$B$604,">="&DATE(PlanYear,1,1),'Content Calendar'!$B$5:$B$604,"<="&DATE(PlanYear,12,31))) -> 0 | V7: =IF(B7="","",COUNTIFS('Content Calendar'!$G$5:$G$604,B7,'Content Calendar'!$X$5:$X$604,"Published",'Content Calendar'!$B$5:$B$604,">="&DATE(PlanYear,1,1),'Content Calendar'!$B$5:$B$604,"<="&DATE(PlanYear,12,31))) -> 0 | W7: =IF(C7="","",SUMIFS(Analytics!$J$5:$J$154,Analytics!$E$5:$E$154,C7,Analytics!$D$5:$D$154,B7)) -> 0 | X7: =IF(C7="","",SUMIFS(Analytics!$L$5:$L$154,Analytics!$E$5:$E$154,C7,Analytics!$D$5:$D$154,B7)) -> 0 | Y7: =IF(OR(W7="",W7=0),"",X7/W7) -> 0 | Z7: =IF(C7="","",SUMIFS(Analytics!$G$5:$G$154,Analytics!$E$5:$E$154,C7)-SUMIFS(Analytics!$F$5:$F$154,Analytics!$E$5:$E$154,C7)) -> 0 | AA7: =IF(B7="","",IF(SUMPRODUCT(MAX(('Content Calendar'!$G$5:$G$604=B7)*('Content Calendar'!$X$5:$X$604="Published")*'Content Calendar'!$B$5:$B$604))=0,"",SUMPRODUCT(MAX(('Content Calendar'!$G$5:$G$604=B7)*('Content Calendar'!$X$5:$X$604="Published")*'Content Calendar'!$B$5:$B$604)))) -> 0 | AB7: =IF(AA7="","",TODAY()-AA7) -> 0 | AC7: =IF(C7="","",IF(S7<1,"Action - finish the profile checklist",IF(AND(ISNUMBER(AB7),AB7>QuietAccountDays),"Check - account has gone quiet",IF(AND(Y7<>"",Y7<TargetEngagement),"Check - engagement below target","OK")))) -> 0
A8: =IF(C8="","","ACC-"&TEXT(ROW()-4,"000")) -> 0 | B8: YouTube | C8: Wildflower Studio | D8: @wildflowerstudio | E8: youtube.com/@wildflowerstudio | F8: Channel | G8: Elena Dias | H8: Long form studio films and buying guides | I8: Makers and buyers | J8: 1240 | K8: 45856 | L8: 1 | M8: Yes | N8: Yes | O8: Yes | P8: Yes | Q8: No | R8: Yes | S8: =IF(C8="","",(((M8="Yes")*1)+((N8="Yes")*1)+((O8="Yes")*1)+((P8="Yes")*1)+((Q8="Yes")*1)+((R8="Yes")*1))/6) -> 0 | T8: Owner + manager, 2FA on | U8: =IF(B8="","",COUNTIFS('Content Calendar'!$G$5:$G$604,B8,'Content Calendar'!$B$5:$B$604,">="&DATE(PlanYear,1,1),'Content Calendar'!$B$5:$B$604,"<="&DATE(PlanYear,12,31))) -> 0 | V8: =IF(B8="","",COUNTIFS('Content Calendar'!$G$5:$G$604,B8,'Content Calendar'!$X$5:$X$604,"Published",'Content Calendar'!$B$5:$B$604,">="&DATE(PlanYear,1,1),'Content Calendar'!$B$5:$B$604,"<="&DATE(PlanYear,12,31))) -> 0 | W8: =IF(C8="","",SUMIFS(Analytics!$J$5:$J$154,Analytics!$E$5:$E$154,C8,Analytics!$D$5:$D$154,B8)) -> 0 | X8: =IF(C8="","",SUMIFS(Analytics!$L$5:$L$154,Analytics!$E$5:$E$154,C8,Analytics!$D$5:$D$154,B8)) -> 0 | Y8: =IF(OR(W8="",W8=0),"",X8/W8) -> 0 | Z8: =IF(C8="","",SUMIFS(Analytics!$G$5:$G$154,Analytics!$E$5:$E$154,C8)-SUMIFS(Analytics!$F$5:$F$154,Analytics!$E$5:$E$154,C8)) -> 0 | AA8: =IF(B8="","",IF(SUMPRODUCT(MAX(('Content Calendar'!$G$5:$G$604=B8)*('Content Calendar'!$X$5:$X$604="Published")*'Content Calendar'!$B$5:$B$604))=0,"",SUMPRODUCT(MAX(('Content Calendar'!$G$5:$G$604=B8)*('Content Calendar'!$X$5:$X$604="Published")*'Content Calendar'!$B$5:$B$604)))) -> 0 | AB8: =IF(AA8="","",TODAY()-AA8) -> 0 | AC8: =IF(C8="","",IF(S8<1,"Action - finish the profile checklist",IF(AND(ISNUMBER(AB8),AB8>QuietAccountDays),"Check - account has gone quiet",IF(AND(Y8<>"",Y8<TargetEngagement),"Check - engagement below target","OK")))) -> 0
A9: =IF(C9="","","ACC-"&TEXT(ROW()-4,"000")) -> 0 | B9: Facebook | C9: Wildflower Studio | D9: wildflowerstudiohome | E9: facebook.com/wildflowerstudiohome | F9: Page | G9: Jordan Avery | H9: Local customers, markets and events | I9: Home lovers 28-45 | J9: 2640 | K9: 45946 | L9: 2 | M9: Yes | N9: Yes | O9: Yes | P9: Yes | Q9: Yes | R9: Yes | S9: =IF(C9="","",(((M9="Yes")*1)+((N9="Yes")*1)+((O9="Yes")*1)+((P9="Yes")*1)+((Q9="Yes")*1)+((R9="Yes")*1))/6) -> 0 | T9: Owner + manager, 2FA on | U9: =IF(B9="","",COUNTIFS('Content Calendar'!$G$5:$G$604,B9,'Content Calendar'!$B$5:$B$604,">="&DATE(PlanYear,1,1),'Content Calendar'!$B$5:$B$604,"<="&DATE(PlanYear,12,31))) -> 0 | V9: =IF(B9="","",COUNTIFS('Content Calendar'!$G$5:$G$604,B9,'Content Calendar'!$X$5:$X$604,"Published",'Content Calendar'!$B$5:$B$604,">="&DATE(PlanYear,1,1),'Content Calendar'!$B$5:$B$604,"<="&DATE(PlanYear,12,31))) -> 0 | W9: =IF(C9="","",SUMIFS(Analytics!$J$5:$J$154,Analytics!$E$5:$E$154,C9,Analytics!$D$5:$D$154,B9)) -> 0 | X9: =IF(C9="","",SUMIFS(Analytics!$L$5:$L$154,Analytics!$E$5:$E$154,C9,Analytics!$D$5:$D$154,B9)) -> 0 | Y9: =IF(OR(W9="",W9=0),"",X9/W9) -> 0 | Z9: =IF(C9="","",SUMIFS(Analytics!$G$5:$G$154,Analytics!$E$5:$E$154,C9)-SUMIFS(Analytics!$F$5:$F$154,Analytics!$E$5:$E$154,C9)) -> 0 | AA9: =IF(B9="","",IF(SUMPRODUCT(MAX(('Content Calendar'!$G$5:$G$604=B9)*('Content Calendar'!$X$5:$X$604="Published")*'Content Calendar'!$B$5:$B$604))=0,"",SUMPRODUCT(MAX(('Content Calendar'!$G$5:$G$604=B9)*('Content Calendar'!$X$5:$X$604="Published")*'Content Calendar'!$B$5:$B$604)))) -> 0 | AB9: =IF(AA9="","",TODAY()-AA9) -> 0 | AC9: =IF(C9="","",IF(S9<1,"Action - finish the profile checklist",IF(AND(ISNUMBER(AB9),AB9>QuietAccountDays),"Check - account has gone quiet",IF(AND(Y9<>"",Y9<TargetEngagement),"Check - engagement below target","OK")))) -> 0
A10: =IF(C10="","","ACC-"&TEXT(ROW()-4,"000")) -> 0 | S10: =IF(C10="","",(((M10="Yes")*1)+((N10="Yes")*1)+((O10="Yes")*1)+((P10="Yes")*1)+((Q10="Yes")*1)+((R10="Yes")*1))/6) -> 0 | U10: =IF(B10="","",COUNTIFS('Content Calendar'!$G$5:$G$604,B10,'Content Calendar'!$B$5:$B$604,">="&DATE(PlanYear,1,1),'Content Calendar'!$B$5:$B$604,"<="&DATE(PlanYear,12,31))) -> 0 | V10: =IF(B10="","",COUNTIFS('Content Calendar'!$G$5:$G$604,B10,'Content Calendar'!$X$5:$X$604,"Published",'Content Calendar'!$B$5:$B$604,">="&DATE(PlanYear,1,1),'Content Calendar'!$B$5:$B$604,"<="&DATE(PlanYear,12,31))) -> 0 | W10: =IF(C10="","",SUMIFS(Analytics!$J$5:$J$154,Analytics!$E$5:$E$154,C10,Analytics!$D$5:$D$154,B10)) -> 0 | X10: =IF(C10="","",SUMIFS(Analytics!$L$5:$L$154,Analytics!$E$5:$E$154,C10,Analytics!$D$5:$D$154,B10)) -> 0 | Y10: =IF(OR(W10="",W10=0),"",X10/W10) -> 0 | Z10: =IF(C10="","",SUMIFS(Analytics!$G$5:$G$154,Analytics!$E$5:$E$154,C10)-SUMIFS(Analytics!$F$5:$F$154,Analytics!$E$5:$E$154,C10)) -> 0 | AA10: =IF(B10="","",IF(SUMPRODUCT(MAX(('Content Calendar'!$G$5:$G$604=B10)*('Content Calendar'!$X$5:$X$604="Published")*'Content Calendar'!$B$5:$B$604))=0,"",SUMPRODUCT(MAX(('Content Calendar'!$G$5:$G$604=B10)*('Content Calendar'!$X$5:$X$604="Published")*'Content Calendar'!$B$5:$B$604)))) -> 0 | AB10: =IF(AA10="","",TODAY()-AA10) -> 0 | AC10: =IF(C10="","",IF(S10<1,"Action - finish the profile checklist",IF(AND(ISNUMBER(AB10),AB10>QuietAccountDays),"Check - account has gone quiet",IF(AND(Y10<>"",Y10<TargetEngagement),"Check - engagement below target","OK")))) -> 0
A11: =IF(C11="","","ACC-"&TEXT(ROW()-4,"000")) -> 0 | S11: =IF(C11="","",(((M11="Yes")*1)+((N11="Yes")*1)+((O11="Yes")*1)+((P11="Yes")*1)+((Q11="Yes")*1)+((R11="Yes")*1))/6) -> 0 | U11: =IF(B11="","",COUNTIFS('Content Calendar'!$G$5:$G$604,B11,'Content Calendar'!$B$5:$B$604,">="&DATE(PlanYear,1,1),'Content Calendar'!$B$5:$B$604,"<="&DATE(PlanYear,12,31))) -> 0 | V11: =IF(B11="","",COUNTIFS('Content Calendar'!$G$5:$G$604,B11,'Content Calendar'!$X$5:$X$604,"Published",'Content Calendar'!$B$5:$B$604,">="&DATE(PlanYear,1,1),'Content Calendar'!$B$5:$B$604,"<="&DATE(PlanYear,12,31))) -> 0 | W11: =IF(C11="","",SUMIFS(Analytics!$J$5:$J$154,Analytics!$E$5:$E$154,C11,Analytics!$D$5:$D$154,B11)) -> 0 | X11: =IF(C11="","",SUMIFS(Analytics!$L$5:$L$154,Analytics!$E$5:$E$154,C11,Analytics!$D$5:$D$154,B11)) -> 0 | Y11: =IF(OR(W11="",W11=0),"",X11/W11) -> 0 | Z11: =IF(C11="","",SUMIFS(Analytics!$G$5:$G$154,Analytics!$E$5:$E$154,C11)-SUMIFS(Analytics!$F$5:$F$154,Analytics!$E$5:$E$154,C11)) -> 0 | AA11: =IF(B11="","",IF(SUMPRODUCT(MAX(('Content Calendar'!$G$5:$G$604=B11)*('Content Calendar'!$X$5:$X$604="Published")*'Content Calendar'!$B$5:$B$604))=0,"",SUMPRODUCT(MAX(('Content Calendar'!$G$5:$G$604=B11)*('Content Calendar'!$X$5:$X$604="Published")*'Content Calendar'!$B$5:$B$604)))) -> 0 | AB11: =IF(AA11="","",TODAY()-AA11) -> 0 | AC11: =IF(C11="","",IF(S11<1,"Action - finish the profile checklist",IF(AND(ISNUMBER(AB11),AB11>QuietAccountDays),"Check - account has gone quiet",IF(AND(Y11<>"",Y11<TargetEngagement),"Check - engagement below target","OK")))) -> 0
A12: =IF(C12="","","ACC-"&TEXT(ROW()-4,"000")) -> 0 | S12: =IF(C12="","",(((M12="Yes")*1)+((N12="Yes")*1)+((O12="Yes")*1)+((P12="Yes")*1)+((Q12="Yes")*1)+((R12="Yes")*1))/6) -> 0 | U12: =IF(B12="","",COUNTIFS('Content Calendar'!$G$5:$G$604,B12,'Content Calendar'!$B$5:$B$604,">="&DATE(PlanYear,1,1),'Content Calendar'!$B$5:$B$604,"<="&DATE(PlanYear,12,31))) -> 0 | V12: =IF(B12="","",COUNTIFS('Content Calendar'!$G$5:$G$604,B12,'Content Calendar'!$X$5:$X$604,"Published",'Content Calendar'!$B$5:$B$604,">="&DATE(PlanYear,1,1),'Content Calendar'!$B$5:$B$604,"<="&DATE(PlanYear,12,31))) -> 0 | W12: =IF(C12="","",SUMIFS(Analytics!$J$5:$J$154,Analytics!$E$5:$E$154,C12,Analytics!$D$5:$D$154,B12)) -> 0 | X12: =IF(C12="","",SUMIFS(Analytics!$L$5:$L$154,Analytics!$E$5:$E$154,C12,Analytics!$D$5:$D$154,B12)) -> 0 | Y12: =IF(OR(W12="",W12=0),"",X12/W12) -> 0 | Z12: =IF(C12="","",SUMIFS(Analytics!$G$5:$G$154,Analytics!$E$5:$E$154,C12)-SUMIFS(Analytics!$F$5:$F$154,Analytics!$E$5:$E$154,C12)) -> 0 | AA12: =IF(B12="","",IF(SUMPRODUCT(MAX(('Content Calendar'!$G$5:$G$604=B12)*('Content Calendar'!$X$5:$X$604="Published")*'Content Calendar'!$B$5:$B$604))=0,"",SUMPRODUCT(MAX(('Content Calendar'!$G$5:$G$604=B12)*('Content Calendar'!$X$5:$X$604="Published")*'Content Calendar'!$B$5:$B$604)))) -> 0 | AB12: =IF(AA12="","",TODAY()-AA12) -> 0 | AC12: =IF(C12="","",IF(S12<1,"Action - finish the profile checklist",IF(AND(ISNUMBER(AB12),AB12>QuietAccountDays),"Check - account has gone quiet",IF(AND(Y12<>"",Y12<TargetEngagement),"Check - engagement below target","OK")))) -> 0
A13: =IF(C13="","","ACC-"&TEXT(ROW()-4,"000")) -> 0 | S13: =IF(C13="","",(((M13="Yes")*1)+((N13="Yes")*1)+((O13="Yes")*1)+((P13="Yes")*1)+((Q13="Yes")*1)+((R13="Yes")*1))/6) -> 0 | U13: =IF(B13="","",COUNTIFS('Content Calendar'!$G$5:$G$604,B13,'Content Calendar'!$B$5:$B$604,">="&DATE(PlanYear,1,1),'Content Calendar'!$B$5:$B$604,"<="&DATE(PlanYear,12,31))) -> 0 | V13: =IF(B13="","",COUNTIFS('Content Calendar'!$G$5:$G$604,B13,'Content Calendar'!$X$5:$X$604,"Published",'Content Calendar'!$B$5:$B$604,">="&DATE(PlanYear,1,1),'Content Calendar'!$B$5:$B$604,"<="&DATE(PlanYear,12,31))) -> 0 | W13: =IF(C13="","",SUMIFS(Analytics!$J$5:$J$154,Analytics!$E$5:$E$154,C13,Analytics!$D$5:$D$154,B13)) -> 0 | X13: =IF(C13="","",SUMIFS(Analytics!$L$5:$L$154,Analytics!$E$5:$E$154,C13,Analytics!$D$5:$D$154,B13)) -> 0 | Y13: =IF(OR(W13="",W13=0),"",X13/W13) -> 0 | Z13: =IF(C13="","",SUMIFS(Analytics!$G$5:$G$154,Analytics!$E$5:$E$154,C13)-SUMIFS(Analytics!$F$5:$F$154,Analytics!$E$5:$E$154,C13)) -> 0 | AA13: =IF(B13="","",IF(SUMPRODUCT(MAX(('Content Calendar'!$G$5:$G$604=B13)*('Content Calendar'!$X$5:$X$604="Published")*'Content Calendar'!$B$5:$B$604))=0,"",SUMPRODUCT(MAX(('Content Calendar'!$G$5:$G$604=B13)*('Content Calendar'!$X$5:$X$604="Published")*'Content Calendar'!$B$5:$B$604)))) -> 0 | AB13: =IF(AA13="","",TODAY()-AA13) -> 0 | AC13: =IF(C13="","",IF(S13<1,"Action - finish the profile checklist",IF(AND(ISNUMBER(AB13),AB13>QuietAccountDays),"Check - account has gone quiet",IF(AND(Y13<>"",Y13<TargetEngagement),"Check - engagement below target","OK")))) -> 0
A14: =IF(C14="","","ACC-"&TEXT(ROW()-4,"000")) -> 0 | S14: =IF(C14="","",(((M14="Yes")*1)+((N14="Yes")*1)+((O14="Yes")*1)+((P14="Yes")*1)+((Q14="Yes")*1)+((R14="Yes")*1))/6) -> 0 | U14: =IF(B14="","",COUNTIFS('Content Calendar'!$G$5:$G$604,B14,'Content Calendar'!$B$5:$B$604,">="&DATE(PlanYear,1,1),'Content Calendar'!$B$5:$B$604,"<="&DATE(PlanYear,12,31))) -> 0 | V14: =IF(B14="","",COUNTIFS('Content Calendar'!$G$5:$G$604,B14,'Content Calendar'!$X$5:$X$604,"Published",'Content Calendar'!$B$5:$B$604,">="&DATE(PlanYear,1,1),'Content Calendar'!$B$5:$B$604,"<="&DATE(PlanYear,12,31))) -> 0 | W14: =IF(C14="","",SUMIFS(Analytics!$J$5:$J$154,Analytics!$E$5:$E$154,C14,Analytics!$D$5:$D$154,B14)) -> 0 | X14: =IF(C14="","",SUMIFS(Analytics!$L$5:$L$154,Analytics!$E$5:$E$154,C14,Analytics!$D$5:$D$154,B14)) -> 0 | Y14: =IF(OR(W14="",W14=0),"",X14/W14) -> 0 | Z14: =IF(C14="","",SUMIFS(Analytics!$G$5:$G$154,Analytics!$E$5:$E$154,C14)-SUMIFS(Analytics!$F$5:$F$154,Analytics!$E$5:$E$154,C14)) -> 0 | AA14: =IF(B14="","",IF(SUMPRODUCT(MAX(('Content Calendar'!$G$5:$G$604=B14)*('Content Calendar'!$X$5:$X$604="Published")*'Content Calendar'!$B$5:$B$604))=0,"",SUMPRODUCT(MAX(('Content Calendar'!$G$5:$G$604=B14)*('Content Calendar'!$X$5:$X$604="Published")*'Content Calendar'!$B$5:$B$604)))) -> 0 | AB14: =IF(AA14="","",TODAY()-AA14) -> 0 | AC14: =IF(C14="","",IF(S14<1,"Action - finish the profile checklist",IF(AND(ISNUMBER(AB14),AB14>QuietAccountDays),"Check - account has gone quiet",IF(AND(Y14<>"",Y14<TargetEngagement),"Check - engagement below target","OK")))) -> 0
A15: =IF(C15="","","ACC-"&TEXT(ROW()-4,"000")) -> 0 | S15: =IF(C15="","",(((M15="Yes")*1)+((N15="Yes")*1)+((O15="Yes")*1)+((P15="Yes")*1)+((Q15="Yes")*1)+((R15="Yes")*1))/6) -> 0 | U15: =IF(B15="","",COUNTIFS('Content Calendar'!$G$5:$G$604,B15,'Content Calendar'!$B$5:$B$604,">="&DATE(PlanYear,1,1),'Content Calendar'!$B$5:$B$604,"<="&DATE(PlanYear,12,31))) -> 0 | V15: =IF(B15="","",COUNTIFS('Content Calendar'!$G$5:$G$604,B15,'Content Calendar'!$X$5:$X$604,"Published",'Content Calendar'!$B$5:$B$604,">="&DATE(PlanYear,1,1),'Content Calendar'!$B$5:$B$604,"<="&DATE(PlanYear,12,31))) -> 0 | W15: =IF(C15="","",SUMIFS(Analytics!$J$5:$J$154,Analytics!$E$5:$E$154,C15,Analytics!$D$5:$D$154,B15)) -> 0 | X15: =IF(C15="","",SUMIFS(Analytics!$L$5:$L$154,Analytics!$E$5:$E$154,C15,Analytics!$D$5:$D$154,B15)) -> 0 | Y15: =IF(OR(W15="",W15=0),"",X15/W15) -> 0 | Z15: =IF(C15="","",SUMIFS(Analytics!$G$5:$G$154,Analytics!$E$5:$E$154,C15)-SUMIFS(Analytics!$F$5:$F$154,Analytics!$E$5:$E$154,C15)) -> 0 | AA15: =IF(B15="","",IF(SUMPRODUCT(MAX(('Content Calendar'!$G$5:$G$604=B15)*('Content Calendar'!$X$5:$X$604="Published")*'Content Calendar'!$B$5:$B$604))=0,"",SUMPRODUCT(MAX(('Content Calendar'!$G$5:$G$604=B15)*('Content Calendar'!$X$5:$X$604="Published")*'Content Calendar'!$B$5:$B$604)))) -> 0 | AB15: =IF(AA15="","",TODAY()-AA15) -> 0 | AC15: =IF(C15="","",IF(S15<1,"Action - finish the profile checklist",IF(AND(ISNUMBER(AB15),AB15>QuietAccountDays),"Check - account has gone quiet",IF(AND(Y15<>"",Y15<TargetEngagement),"Check - engagement below target","OK")))) -> 0
A16: =IF(C16="","","ACC-"&TEXT(ROW()-4,"000")) -> 0 | S16: =IF(C16="","",(((M16="Yes")*1)+((N16="Yes")*1)+((O16="Yes")*1)+((P16="Yes")*1)+((Q16="Yes")*1)+((R16="Yes")*1))/6) -> 0 | U16: =IF(B16="","",COUNTIFS('Content Calendar'!$G$5:$G$604,B16,'Content Calendar'!$B$5:$B$604,">="&DATE(PlanYear,1,1),'Content Calendar'!$B$5:$B$604,"<="&DATE(PlanYear,12,31))) -> 0 | V16: =IF(B16="","",COUNTIFS('Content Calendar'!$G$5:$G$604,B16,'Content Calendar'!$X$5:$X$604,"Published",'Content Calendar'!$B$5:$B$604,">="&DATE(PlanYear,1,1),'Content Calendar'!$B$5:$B$604,"<="&DATE(PlanYear,12,31))) -> 0 | W16: =IF(C16="","",SUMIFS(Analytics!$J$5:$J$154,Analytics!$E$5:$E$154,C16,Analytics!$D$5:$D$154,B16)) -> 0 | X16: =IF(C16="","",SUMIFS(Analytics!$L$5:$L$154,Analytics!$E$5:$E$154,C16,Analytics!$D$5:$D$154,B16)) -> 0 | Y16: =IF(OR(W16="",W16=0),"",X16/W16) -> 0 | Z16: =IF(C16="","",SUMIFS(Analytics!$G$5:$G$154,Analytics!$E$5:$E$154,C16)-SUMIFS(Analytics!$F$5:$F$154,Analytics!$E$5:$E$154,C16)) -> 0 | AA16: =IF(B16="","",IF(SUMPRODUCT(MAX(('Content Calendar'!$G$5:$G$604=B16)*('Content Calendar'!$X$5:$X$604="Published")*'Content Calendar'!$B$5:$B$604))=0,"",SUMPRODUCT(MAX(('Content Calendar'!$G$5:$G$604=B16)*('Content Calendar'!$X$5:$X$604="Published")*'Content Calendar'!$B$5:$B$604)))) -> 0 | AB16: =IF(AA16="","",TODAY()-AA16) -> 0 | AC16: =IF(C16="","",IF(S16<1,"Action - finish the profile checklist",IF(AND(ISNUMBER(AB16),AB16>QuietAccountDays),"Check - account has gone quiet",IF(AND(Y16<>"",Y16<TargetEngagement),"Check - engagement below target","OK")))) -> 0
A17: =IF(C17="","","ACC-"&TEXT(ROW()-4,"000")) -> 0 | S17: =IF(C17="","",(((M17="Yes")*1)+((N17="Yes")*1)+((O17="Yes")*1)+((P17="Yes")*1)+((Q17="Yes")*1)+((R17="Yes")*1))/6) -> 0 | U17: =IF(B17="","",COUNTIFS('Content Calendar'!$G$5:$G$604,B17,'Content Calendar'!$B$5:$B$604,">="&DATE(PlanYear,1,1),'Content Calendar'!$B$5:$B$604,"<="&DATE(PlanYear,12,31))) -> 0 | V17: =IF(B17="","",COUNTIFS('Content Calendar'!$G$5:$G$604,B17,'Content Calendar'!$X$5:$X$604,"Published",'Content Calendar'!$B$5:$B$604,">="&DATE(PlanYear,1,1),'Content Calendar'!$B$5:$B$604,"<="&DATE(PlanYear,12,31))) -> 0 | W17: =IF(C17="","",SUMIFS(Analytics!$J$5:$J$154,Analytics!$E$5:$E$154,C17,Analytics!$D$5:$D$154,B17)) -> 0 | X17: =IF(C17="","",SUMIFS(Analytics!$L$5:$L$154,Analytics!$E$5:$E$154,C17,Analytics!$D$5:$D$154,B17)) -> 0 | Y17: =IF(OR(W17="",W17=0),"",X17/W17) -> 0 | Z17: =IF(C17="","",SUMIFS(Analytics!$G$5:$G$154,Analytics!$E$5:$E$154,C17)-SUMIFS(Analytics!$F$5:$F$154,Analytics!$E$5:$E$154,C17)) -> 0 | AA17: =IF(B17="","",IF(SUMPRODUCT(MAX(('Content Calendar'!$G$5:$G$604=B17)*('Content Calendar'!$X$5:$X$604="Published")*'Content Calendar'!$B$5:$B$604))=0,"",SUMPRODUCT(MAX(('Content Calendar'!$G$5:$G$604=B17)*('Content Calendar'!$X$5:$X$604="Published")*'Content Calendar'!$B$5:$B$604)))) -> 0 | AB17: =IF(AA17="","",TODAY()-AA17) -> 0 | AC17: =IF(C17="","",IF(S17<1,"Action - finish the profile checklist",IF(AND(ISNUMBER(AB17),AB17>QuietAccountDays),"Check - account has gone quiet",IF(AND(Y17<>"",Y17<TargetEngagement),"Check - engagement below target","OK")))) -> 0
A18: =IF(C18="","","ACC-"&TEXT(ROW()-4,"000")) -> 0 | S18: =IF(C18="","",(((M18="Yes")*1)+((N18="Yes")*1)+((O18="Yes")*1)+((P18="Yes")*1)+((Q18="Yes")*1)+((R18="Yes")*1))/6) -> 0 | U18: =IF(B18="","",COUNTIFS('Content Calendar'!$G$5:$G$604,B18,'Content Calendar'!$B$5:$B$604,">="&DATE(PlanYear,1,1),'Content Calendar'!$B$5:$B$604,"<="&DATE(PlanYear,12,31))) -> 0 | V18: =IF(B18="","",COUNTIFS('Content Calendar'!$G$5:$G$604,B18,'Content Calendar'!$X$5:$X$604,"Published",'Content Calendar'!$B$5:$B$604,">="&DATE(PlanYear,1,1),'Content Calendar'!$B$5:$B$604,"<="&DATE(PlanYear,12,31))) -> 0 | W18: =IF(C18="","",SUMIFS(Analytics!$J$5:$J$154,Analytics!$E$5:$E$154,C18,Analytics!$D$5:$D$154,B18)) -> 0 | X18: =IF(C18="","",SUMIFS(Analytics!$L$5:$L$154,Analytics!$E$5:$E$154,C18,Analytics!$D$5:$D$154,B18)) -> 0 | Y18: =IF(OR(W18="",W18=0),"",X18/W18) -> 0 | Z18: =IF(C18="","",SUMIFS(Analytics!$G$5:$G$154,Analytics!$E$5:$E$154,C18)-SUMIFS(Analytics!$F$5:$F$154,Analytics!$E$5:$E$154,C18)) -> 0 | AA18: =IF(B18="","",IF(SUMPRODUCT(MAX(('Content Calendar'!$G$5:$G$604=B18)*('Content Calendar'!$X$5:$X$604="Published")*'Content Calendar'!$B$5:$B$604))=0,"",SUMPRODUCT(MAX(('Content Calendar'!$G$5:$G$604=B18)*('Content Calendar'!$X$5:$X$604="Published")*'Content Calendar'!$B$5:$B$604)))) -> 0 | AB18: =IF(AA18="","",TODAY()-AA18) -> 0 | AC18: =IF(C18="","",IF(S18<1,"Action - finish the profile checklist",IF(AND(ISNUMBER(AB18),AB18>QuietAccountDays),"Check - account has gone quiet",IF(AND(Y18<>"",Y18<TargetEngagement),"Check - engagement below target","OK")))) -> 0
A19: =IF(C19="","","ACC-"&TEXT(ROW()-4,"000")) -> 0 | S19: =IF(C19="","",(((M19="Yes")*1)+((N19="Yes")*1)+((O19="Yes")*1)+((P19="Yes")*1)+((Q19="Yes")*1)+((R19="Yes")*1))/6) -> 0 | U19: =IF(B19="","",COUNTIFS('Content Calendar'!$G$5:$G$604,B19,'Content Calendar'!$B$5:$B$604,">="&DATE(PlanYear,1,1),'Content Calendar'!$B$5:$B$604,"<="&DATE(PlanYear,12,31))) -> 0 | V19: =IF(B19="","",COUNTIFS('Content Calendar'!$G$5:$G$604,B19,'Content Calendar'!$X$5:$X$604,"Published",'Content Calendar'!$B$5:$B$604,">="&DATE(PlanYear,1,1),'Content Calendar'!$B$5:$B$604,"<="&DATE(PlanYear,12,31))) -> 0 | W19: =IF(C19="","",SUMIFS(Analytics!$J$5:$J$154,Analytics!$E$5:$E$154,C19,Analytics!$D$5:$D$154,B19)) -> 0 | X19: =IF(C19="","",SUMIFS(Analytics!$L$5:$L$154,Analytics!$E$5:$E$154,C19,Analytics!$D$5:$D$154,B19)) -> 0 | Y19: =IF(OR(W19="",W19=0),"",X19/W19) -> 0 | Z19: =IF(C19="","",SUMIFS(Analytics!$G$5:$G$154,Analytics!$E$5:$E$154,C19)-SUMIFS(Analytics!$F$5:$F$154,Analytics!$E$5:$E$154,C19)) -> 0 | AA19: =IF(B19="","",IF(SUMPRODUCT(MAX(('Content Calendar'!$G$5:$G$604=B19)*('Content Calendar'!$X$5:$X$604="Published")*'Content Calendar'!$B$5:$B$604))=0,"",SUMPRODUCT(MAX(('Content Calendar'!$G$5:$G$604=B19)*('Content Calendar'!$X$5:$X$604="Published")*'Content Calendar'!$B$5:$B$604)))) -> 0 | AB19: =IF(AA19="","",TODAY()-AA19) -> 0 | AC19: =IF(C19="","",IF(S19<1,"Action - finish the profile checklist",IF(AND(ISNUMBER(AB19),AB19>QuietAccountDays),"Check - account has gone quiet",IF(AND(Y19<>"",Y19<TargetEngagement),"Check - engagement below target","OK")))) -> 0
A20: =IF(C20="","","ACC-"&TEXT(ROW()-4,"000")) -> 0 | S20: =IF(C20="","",(((M20="Yes")*1)+((N20="Yes")*1)+((O20="Yes")*1)+((P20="Yes")*1)+((Q20="Yes")*1)+((R20="Yes")*1))/6) -> 0 | U20: =IF(B20="","",COUNTIFS('Content Calendar'!$G$5:$G$604,B20,'Content Calendar'!$B$5:$B$604,">="&DATE(PlanYear,1,1),'Content Calendar'!$B$5:$B$604,"<="&DATE(PlanYear,12,31))) -> 0 | V20: =IF(B20="","",COUNTIFS('Content Calendar'!$G$5:$G$604,B20,'Content Calendar'!$X$5:$X$604,"Published",'Content Calendar'!$B$5:$B$604,">="&DATE(PlanYear,1,1),'Content Calendar'!$B$5:$B$604,"<="&DATE(PlanYear,12,31))) -> 0 | W20: =IF(C20="","",SUMIFS(Analytics!$J$5:$J$154,Analytics!$E$5:$E$154,C20,Analytics!$D$5:$D$154,B20)) -> 0 | X20: =IF(C20="","",SUMIFS(Analytics!$L$5:$L$154,Analytics!$E$5:$E$154,C20,Analytics!$D$5:$D$154,B20)) -> 0 | Y20: =IF(OR(W20="",W20=0),"",X20/W20) -> 0 | Z20: =IF(C20="","",SUMIFS(Analytics!$G$5:$G$154,Analytics!$E$5:$E$154,C20)-SUMIFS(Analytics!$F$5:$F$154,Analytics!$E$5:$E$154,C20)) -> 0 | AA20: =IF(B20="","",IF(SUMPRODUCT(MAX(('Content Calendar'!$G$5:$G$604=B20)*('Content Calendar'!$X$5:$X$604="Published")*'Content Calendar'!$B$5:$B$604))=0,"",SUMPRODUCT(MAX(('Content Calendar'!$G$5:$G$604=B20)*('Content Calendar'!$X$5:$X$604="Published")*'Content Calendar'!$B$5:$B$604)))) -> 0 | AB20: =IF(AA20="","",TODAY()-AA20) -> 0 | AC20: =IF(C20="","",IF(S20<1,"Action - finish the profile checklist",IF(AND(ISNUMBER(AB20),AB20>QuietAccountDays),"Check - account has gone quiet",IF(AND(Y20<>"",Y20<TargetEngagement),"Check - engagement below target","OK")))) -> 0
A21: =IF(C21="","","ACC-"&TEXT(ROW()-4,"000")) -> 0 | S21: =IF(C21="","",(((M21="Yes")*1)+((N21="Yes")*1)+((O21="Yes")*1)+((P21="Yes")*1)+((Q21="Yes")*1)+((R21="Yes")*1))/6) -> 0 | U21: =IF(B21="","",COUNTIFS('Content Calendar'!$G$5:$G$604,B21,'Content Calendar'!$B$5:$B$604,">="&DATE(PlanYear,1,1),'Content Calendar'!$B$5:$B$604,"<="&DATE(PlanYear,12,31))) -> 0 | V21: =IF(B21="","",COUNTIFS('Content Calendar'!$G$5:$G$604,B21,'Content Calendar'!$X$5:$X$604,"Published",'Content Calendar'!$B$5:$B$604,">="&DATE(PlanYear,1,1),'Content Calendar'!$B$5:$B$604,"<="&DATE(PlanYear,12,31))) -> 0 | W21: =IF(C21="","",SUMIFS(Analytics!$J$5:$J$154,Analytics!$E$5:$E$154,C21,Analytics!$D$5:$D$154,B21)) -> 0 | X21: =IF(C21="","",SUMIFS(Analytics!$L$5:$L$154,Analytics!$E$5:$E$154,C21,Analytics!$D$5:$D$154,B21)) -> 0 | Y21: =IF(OR(W21="",W21=0),"",X21/W21) -> 0 | Z21: =IF(C21="","",SUMIFS(Analytics!$G$5:$G$154,Analytics!$E$5:$E$154,C21)-SUMIFS(Analytics!$F$5:$F$154,Analytics!$E$5:$E$154,C21)) -> 0 | AA21: =IF(B21="","",IF(SUMPRODUCT(MAX(('Content Calendar'!$G$5:$G$604=B21)*('Content Calendar'!$X$5:$X$604="Published")*'Content Calendar'!$B$5:$B$604))=0,"",SUMPRODUCT(MAX(('Content Calendar'!$G$5:$G$604=B21)*('Content Calendar'!$X$5:$X$604="Published")*'Content Calendar'!$B$5:$B$604)))) -> 0 | AB21: =IF(AA21="","",TODAY()-AA21) -> 0 | AC21: =IF(C21="","",IF(S21<1,"Action - finish the profile checklist",IF(AND(ISNUMBER(AB21),AB21>QuietAccountDays),"Check - account has gone quiet",IF(AND(Y21<>"",Y21<TargetEngagement),"Check - engagement below target","OK")))) -> 0
... A34: =IF(C34="","","ACC-"&TEXT(ROW()-4,"000")) -> 0 | S34: =IF(C34="","",(((M34="Yes")*1)+((N34="Yes")*1)+((O34="Yes")*1)+((P34="Yes")*1)+((Q34="Yes")*1)+((R34="Yes")*1))/6) -> 0 | U34: =IF(B34="","",COUNTIFS('Content Calendar'!$G$5:$G$604,B34,'Content Calendar'!$B$5:$B$604,">="&DATE(PlanYear,1,1),'Content Calendar'!$B$5:$B$604,"<="&DATE(PlanYear,12,31))) -> 0 | V34: =IF(B34="","",COUNTIFS('Content Calendar'!$G$5:$G$604,B34,'Content Calendar'!$X$5:$X$604,"Published",'Content Calendar'!$B$5:$B$604,">="&DATE(PlanYear,1,1),'Content Calendar'!$B$5:$B$604,"<="&DATE(PlanYear,12,31))) -> 0 | W34: =IF(C34="","",SUMIFS(Analytics!$J$5:$J$154,Analytics!$E$5:$E$154,C34,Analytics!$D$5:$D$154,B34)) -> 0 | X34: =IF(C34="","",SUMIFS(Analytics!$L$5:$L$154,Analytics!$E$5:$E$154,C34,Analytics!$D$5:$D$154,B34)) -> 0 | Y34: =IF(OR(W34="",W34=0),"",X34/W34) -> 0 | Z34: =IF(C34="","",SUMIFS(Analytics!$G$5:$G$154,Analytics!$E$5:$E$154,C34)-SUMIFS(Analytics!$F$5:$F$154,Analytics!$E$5:$E$154,C34)) -> 0 | AA34: =IF(B34="","",IF(SUMPRODUCT(MAX(('Content Calendar'!$G$5:$G$604=B34)*('Content Calendar'!$X$5:$X$604="Published")*'Content Calendar'!$B$5:$B$604))=0,"",SUMPRODUCT(MAX(('Content Calendar'!$G$5:$G$604=B34)*('Content Calendar'!$X$5:$X$604="Published")*'Content Calendar'!$B$5:$B$604)))) -> 0 | AB34: =IF(AA34="","",TODAY()-AA34) -> 0 | AC34: =IF(C34="","",IF(S34<1,"Action - finish the profile checklist",IF(AND(ISNUMBER(AB34),AB34>QuietAccountDays),"Check - account has gone quiet",IF(AND(Y34<>"",Y34<TargetEngagement),"Check - engagement below target","OK")))) -> 0

Sheet Audience Personas
A1: Audience Research & Customer Personas | X1: Novality Store | v1.0.0
A2: Three or four personas is plenty. Every post on the calendar can be pointed at one of them, and the grey columns show whether you are actually making content for each.
A3: > Start Here | C3: > Dashboard | E3: > Calendar | G3: > Ideas | I3: > Captions | K3: > Hashtags | M3: > Analytics | O3: > Reports | Q3: > Help | S3: Write these in your customer's words, not marketing words. The four 'idea' columns become entries in the Idea Bank.
A4: ID | B4: Persona name | C4: Age range | D4: Location / market | E4: Interests & hobbies | F4: Main challenge / pain point | G4: What they want | H4: Buying motivation | I4: Common objection | J4: Favourite platform | K4: Favourite format | L4: Journey stage | M4: How they engage | N4: Question they always ask | O4: Words they use | P4: Awareness content idea | Q4: Consideration idea | R4: Conversion idea | S4: Retention idea | T4: Posts planned | U4: Published | V4: Ideas waiting | W4: Captions written | X4: Share of the plan | Y4: Action needed | Z4: Notes
A5: =IF(B5="","","P-"&TEXT(ROW()-4,"00")) -> 0 | B5: First-home Freya | C5: 28-34 | D5: City flats, UK & US | E5: Slow living, thrifting, cooking for friends | F5: Her flat feels unfinished and everything matches too much | G5: A home that feels personal without spending a fortune | H5: Wants pieces with a story | I5: Worries handmade means fragile | J5: Instagram | K5: Carousel | L5: Awareness | M5: Replies to stories, saves carousels | N5: How long does delivery take? | O5: 'shelfie', 'tablescape', 'slow made' | P5: Styling inspiration reels | Q5: Material and care explainers | R5: Shop the look carousels | S5: Customer features and care tips | T5: =IF(B5="","",COUNTIF('Content Calendar'!$O$5:$O$604,B5)) -> 0 | U5: =IF(B5="","",COUNTIFS('Content Calendar'!$O$5:$O$604,B5,'Content Calendar'!$X$5:$X$604,"Published")) -> 0 | V5: =IF(B5="","",COUNTIFS('Idea Bank'!$D$5:$D$304,B5,'Idea Bank'!$T$5:$T$304,"<>Used")) -> 0 | W5: =IF(B5="","",COUNTIF('Caption Bank'!$E$5:$E$204,B5)) -> 0 | X5: =IF(OR(B5="",COUNTA('Content Calendar'!$O$5:$O$604)=0),"",T5/MAX(1,COUNTA('Content Calendar'!$O$5:$O$604))) -> 0 | Y5: =IF(B5="","",IF(T5=0,"Action - nothing planned for this persona",IF(W5=0,"Add - no captions written yet","OK"))) -> 0
A6: =IF(B6="","","P-"&TEXT(ROW()-4,"00")) -> 0 | B6: Gifting Grace | C6: 35-45 | D6: Suburban US & Canada | E6: Hosting, gift giving, seasonal decorating | F6: Finding a present that is not generic, close to the deadline | G6: To be the person who gives the thoughtful gift | H6: Buys for others, values packaging | I6: Will it arrive in time? | J6: Pinterest | K6: Standard Pin | L6: Conversion | M6: Replies to stories, saves carousels | N6: How long does delivery take? | O6: 'shelfie', 'tablescape', 'slow made' | P6: Styling inspiration reels | Q6: Material and care explainers | R6: Shop the look carousels | S6: Customer features and care tips | T6: =IF(B6="","",COUNTIF('Content Calendar'!$O$5:$O$604,B6)) -> 0 | U6: =IF(B6="","",COUNTIFS('Content Calendar'!$O$5:$O$604,B6,'Content Calendar'!$X$5:$X$604,"Published")) -> 0 | V6: =IF(B6="","",COUNTIFS('Idea Bank'!$D$5:$D$304,B6,'Idea Bank'!$T$5:$T$304,"<>Used")) -> 0 | W6: =IF(B6="","",COUNTIF('Caption Bank'!$E$5:$E$204,B6)) -> 0 | X6: =IF(OR(B6="",COUNTA('Content Calendar'!$O$5:$O$604)=0),"",T6/MAX(1,COUNTA('Content Calendar'!$O$5:$O$604))) -> 0 | Y6: =IF(B6="","",IF(T6=0,"Action - nothing planned for this persona",IF(W6=0,"Add - no captions written yet","OK"))) -> 0 | Z6: Highest spend per order
A7: =IF(B7="","","P-"&TEXT(ROW()-4,"00")) -> 0 | B7: Interiors Isla | C7: 30-42 | D7: Design-led cities | E7: Interiors, ceramics, neutral palettes, slow design | F7: Mass produced homeware feels soulless | G7: A considered home she is proud to photograph | H7: Follows makers, buys a piece at a time | I7: Is the colour true to the photo? | J7: Instagram | K7: Reel | L7: Consideration | M7: Replies to stories, saves carousels | N7: How long does delivery take? | O7: 'shelfie', 'tablescape', 'slow made' | P7: Styling inspiration reels | Q7: Material and care explainers | R7: Shop the look carousels | S7: Customer features and care tips | T7: =IF(B7="","",COUNTIF('Content Calendar'!$O$5:$O$604,B7)) -> 0 | U7: =IF(B7="","",COUNTIFS('Content Calendar'!$O$5:$O$604,B7,'Content Calendar'!$X$5:$X$604,"Published")) -> 0 | V7: =IF(B7="","",COUNTIFS('Idea Bank'!$D$5:$D$304,B7,'Idea Bank'!$T$5:$T$304,"<>Used")) -> 0 | W7: =IF(B7="","",COUNTIF('Caption Bank'!$E$5:$E$204,B7)) -> 0 | X7: =IF(OR(B7="",COUNTA('Content Calendar'!$O$5:$O$604)=0),"",T7/MAX(1,COUNTA('Content Calendar'!$O$5:$O$604))) -> 0 | Y7: =IF(B7="","",IF(T7=0,"Action - nothing planned for this persona",IF(W7=0,"Add - no captions written yet","OK"))) -> 0
A8: =IF(B8="","","P-"&TEXT(ROW()-4,"00")) -> 0 | T8: =IF(B8="","",COUNTIF('Content Calendar'!$O$5:$O$604,B8)) -> 0 | U8: =IF(B8="","",COUNTIFS('Content Calendar'!$O$5:$O$604,B8,'Content Calendar'!$X$5:$X$604,"Published")) -> 0 | V8: =IF(B8="","",COUNTIFS('Idea Bank'!$D$5:$D$304,B8,'Idea Bank'!$T$5:$T$304,"<>Used")) -> 0 | W8: =IF(B8="","",COUNTIF('Caption Bank'!$E$5:$E$204,B8)) -> 0 | X8: =IF(OR(B8="",COUNTA('Content Calendar'!$O$5:$O$604)=0),"",T8/MAX(1,COUNTA('Content Calendar'!$O$5:$O$604))) -> 0 | Y8: =IF(B8="","",IF(T8=0,"Action - nothing planned for this persona",IF(W8=0,"Add - no captions written yet","OK"))) -> 0
A9: =IF(B9="","","P-"&TEXT(ROW()-4,"00")) -> 0 | T9: =IF(B9="","",COUNTIF('Content Calendar'!$O$5:$O$604,B9)) -> 0 | U9: =IF(B9="","",COUNTIFS('Content Calendar'!$O$5:$O$604,B9,'Content Calendar'!$X$5:$X$604,"Published")) -> 0 | V9: =IF(B9="","",COUNTIFS('Idea Bank'!$D$5:$D$304,B9,'Idea Bank'!$T$5:$T$304,"<>Used")) -> 0 | W9: =IF(B9="","",COUNTIF('Caption Bank'!$E$5:$E$204,B9)) -> 0 | X9: =IF(OR(B9="",COUNTA('Content Calendar'!$O$5:$O$604)=0),"",T9/MAX(1,COUNTA('Content Calendar'!$O$5:$O$604))) -> 0 | Y9: =IF(B9="","",IF(T9=0,"Action - nothing planned for this persona",IF(W9=0,"Add - no captions written yet","OK"))) -> 0
A10: =IF(B10="","","P-"&TEXT(ROW()-4,"00")) -> 0 | T10: =IF(B10="","",COUNTIF('Content Calendar'!$O$5:$O$604,B10)) -> 0 | U10: =IF(B10="","",COUNTIFS('Content Calendar'!$O$5:$O$604,B10,'Content Calendar'!$X$5:$X$604,"Published")) -> 0 | V10: =IF(B10="","",COUNTIFS('Idea Bank'!$D$5:$D$304,B10,'Idea Bank'!$T$5:$T$304,"<>Used")) -> 0 | W10: =IF(B10="","",COUNTIF('Caption Bank'!$E$5:$E$204,B10)) -> 0 | X10: =IF(OR(B10="",COUNTA('Content Calendar'!$O$5:$O$604)=0),"",T10/MAX(1,COUNTA('Content Calendar'!$O$5:$O$604))) -> 0 | Y10: =IF(B10="","",IF(T10=0,"Action - nothing planned for this persona",IF(W10=0,"Add - no captions written yet","OK"))) -> 0
A11: =IF(B11="","","P-"&TEXT(ROW()-4,"00")) -> 0 | T11: =IF(B11="","",COUNTIF('Content Calendar'!$O$5:$O$604,B11)) -> 0 | U11: =IF(B11="","",COUNTIFS('Content Calendar'!$O$5:$O$604,B11,'Content Calendar'!$X$5:$X$604,"Published")) -> 0 | V11: =IF(B11="","",COUNTIFS('Idea Bank'!$D$5:$D$304,B11,'Idea Bank'!$T$5:$T$304,"<>Used")) -> 0 | W11: =IF(B11="","",COUNTIF('Caption Bank'!$E$5:$E$204,B11)) -> 0 | X11: =IF(OR(B11="",COUNTA('Content Calendar'!$O$5:$O$604)=0),"",T11/MAX(1,COUNTA('Content Calendar'!$O$5:$O$604))) -> 0 | Y11: =IF(B11="","",IF(T11=0,"Action - nothing planned for this persona",IF(W11=0,"Add - no captions written yet","OK"))) -> 0
A12: =IF(B12="","","P-"&TEXT(ROW()-4,"00")) -> 0 | T12: =IF(B12="","",COUNTIF('Content Calendar'!$O$5:$O$604,B12)) -> 0 | U12: =IF(B12="","",COUNTIFS('Content Calendar'!$O$5:$O$604,B12,'Content Calendar'!$X$5:$X$604,"Published")) -> 0 | V12: =IF(B12="","",COUNTIFS('Idea Bank'!$D$5:$D$304,B12,'Idea Bank'!$T$5:$T$304,"<>Used")) -> 0 | W12: =IF(B12="","",COUNTIF('Caption Bank'!$E$5:$E$204,B12)) -> 0 | X12: =IF(OR(B12="",COUNTA('Content Calendar'!$O$5:$O$604)=0),"",T12/MAX(1,COUNTA('Content Calendar'!$O$5:$O$604))) -> 0 | Y12: =IF(B12="","",IF(T12=0,"Action - nothing planned for this persona",IF(W12=0,"Add - no captions written yet","OK"))) -> 0
A13: =IF(B13="","","P-"&TEXT(ROW()-4,"00")) -> 0 | T13: =IF(B13="","",COUNTIF('Content Calendar'!$O$5:$O$604,B13)) -> 0 | U13: =IF(B13="","",COUNTIFS('Content Calendar'!$O$5:$O$604,B13,'Content Calendar'!$X$5:$X$604,"Published")) -> 0 | V13: =IF(B13="","",COUNTIFS('Idea Bank'!$D$5:$D$304,B13,'Idea Bank'!$T$5:$T$304,"<>Used")) -> 0 | W13: =IF(B13="","",COUNTIF('Caption Bank'!$E$5:$E$204,B13)) -> 0 | X13: =IF(OR(B13="",COUNTA('Content Calendar'!$O$5:$O$604)=0),"",T13/MAX(1,COUNTA('Content Calendar'!$O$5:$O$604))) -> 0 | Y13: =IF(B13="","",IF(T13=0,"Action - nothing planned for this persona",IF(W13=0,"Add - no captions written yet","OK"))) -> 0
A14: =IF(B14="","","P-"&TEXT(ROW()-4,"00")) -> 0 | T14: =IF(B14="","",COUNTIF('Content Calendar'!$O$5:$O$604,B14)) -> 0 | U14: =IF(B14="","",COUNTIFS('Content Calendar'!$O$5:$O$604,B14,'Content Calendar'!$X$5:$X$604,"Published")) -> 0 | V14: =IF(B14="","",COUNTIFS('Idea Bank'!$D$5:$D$304,B14,'Idea Bank'!$T$5:$T$304,"<>Used")) -> 0 | W14: =IF(B14="","",COUNTIF('Caption Bank'!$E$5:$E$204,B14)) -> 0 | X14: =IF(OR(B14="",COUNTA('Content Calendar'!$O$5:$O$604)=0),"",T14/MAX(1,COUNTA('Content Calendar'!$O$5:$O$604))) -> 0 | Y14: =IF(B14="","",IF(T14=0,"Action - nothing planned for this persona",IF(W14=0,"Add - no captions written yet","OK"))) -> 0
A15: =IF(B15="","","P-"&TEXT(ROW()-4,"00")) -> 0 | T15: =IF(B15="","",COUNTIF('Content Calendar'!$O$5:$O$604,B15)) -> 0 | U15: =IF(B15="","",COUNTIFS('Content Calendar'!$O$5:$O$604,B15,'Content Calendar'!$X$5:$X$604,"Published")) -> 0 | V15: =IF(B15="","",COUNTIFS('Idea Bank'!$D$5:$D$304,B15,'Idea Bank'!$T$5:$T$304,"<>Used")) -> 0 | W15: =IF(B15="","",COUNTIF('Caption Bank'!$E$5:$E$204,B15)) -> 0 | X15: =IF(OR(B15="",COUNTA('Content Calendar'!$O$5:$O$604)=0),"",T15/MAX(1,COUNTA('Content Calendar'!$O$5:$O$604))) -> 0 | Y15: =IF(B15="","",IF(T15=0,"Action - nothing planned for this persona",IF(W15=0,"Add - no captions written yet","OK"))) -> 0
A16: =IF(B16="","","P-"&TEXT(ROW()-4,"00")) -> 0 | T16: =IF(B16="","",COUNTIF('Content Calendar'!$O$5:$O$604,B16)) -> 0 | U16: =IF(B16="","",COUNTIFS('Content Calendar'!$O$5:$O$604,B16,'Content Calendar'!$X$5:$X$604,"Published")) -> 0 | V16: =IF(B16="","",COUNTIFS('Idea Bank'!$D$5:$D$304,B16,'Idea Bank'!$T$5:$T$304,"<>Used")) -> 0 | W16: =IF(B16="","",COUNTIF('Caption Bank'!$E$5:$E$204,B16)) -> 0 | X16: =IF(OR(B16="",COUNTA('Content Calendar'!$O$5:$O$604)=0),"",T16/MAX(1,COUNTA('Content Calendar'!$O$5:$O$604))) -> 0 | Y16: =IF(B16="","",IF(T16=0,"Action - nothing planned for this persona",IF(W16=0,"Add - no captions written yet","OK"))) -> 0

Sheet Content Pillars
A1: Content Pillars & Strategy | Q1: Novality Store | v1.0.0
A2: Set the mix you want, then watch the grey columns tell you the mix you actually published.
A3: > Start Here | C3: > Dashboard | E3: > Calendar | G3: > Ideas | I3: > Captions | K3: > Hashtags | M3: > Analytics | O3: > Reports | Q3: > Help
A4: ID | B4: Pillar name | C4: Target share of posts | D4: What this pillar is for | E4: Main objective | F4: Usual format | G4: Mainly for | H4: Example post ideas | I4: Posts planned | J4: Published | K4: Actual share | L4: Off target by | M4: Reach | N4: Engagements | O4: Engagement rate | P4: Clicks | Q4: Best post | R4: Action needed | S4: Notes
A5: =IF(B5="","","PIL-"&TEXT(ROW()-4,"00")) -> 0 | B5: Educate | C5: 0.25 | D5: Teach one useful thing about living with handmade pieces | E5: Brand authority | F5: Carousel | G5: First-home Freya | H5: How to, explainers, care guides | I5: =IF(B5="","",COUNTIFS('Content Calendar'!$J$5:$J$604,B5,'Content Calendar'!$B$5:$B$604,">="&DATE(PlanYear,1,1),'Content Calendar'!$B$5:$B$604,"<="&DATE(PlanYear,12,31))) -> 0 | J5: =IF(B5="","",COUNTIFS('Content Calendar'!$J$5:$J$604,B5,'Content Calendar'!$X$5:$X$604,"Published",'Content Calendar'!$B$5:$B$604,">="&DATE(PlanYear,1,1),'Content Calendar'!$B$5:$B$604,"<="&DATE(PlanYear,12,31))) -> 0 | K5: =IF(OR(B5="",SUM('Content Pillars'!$I$5:$I$24)=0),"",I5/SUM('Content Pillars'!$I$5:$I$24)) -> 0 | L5: =IF(OR(K5="",C5=""),"",K5-C5) -> 0 | M5: =IF(B5="","",SUMIFS(Performance!$O$5:$O$404,Performance!$H$5:$H$404,B5)) -> 0 | N5: =IF(B5="","",SUMIFS(Performance!$Z$5:$Z$404,Performance!$H$5:$H$404,B5)) -> 0 | O5: =IF(OR(M5="",M5=0),"",N5/M5) -> 0 | P5: =IF(B5="","",SUMIFS(Performance!$U$5:$U$404,Performance!$H$5:$H$404,B5)) -> 0 | Q5: =IF(OR(B5="",J5=0),"",IFERROR(INDEX(Performance!$C$5:$C$404,MATCH(SUMPRODUCT(MAX((Performance!$H$5:$H$404=B5)*Performance!$AJ$5:$AJ$404)),Performance!$AJ$5:$AJ$404,0)),"")) -> 0 | R5: =IF(B5="","",IF(I5=0,"Action - no posts planned",IF(L5>0.1,"Check - over-used pillar",IF(L5<-0.1,"Check - under-used pillar","OK")))) -> 0
A6: =IF(B6="","","PIL-"&TEXT(ROW()-4,"00")) -> 0 | B6: Inspire | C6: 0.2 | D6: Show the feeling of a slow, styled home | E6: Awareness | F6: Reel | G6: Interiors Isla | H6: Styling, light, seasonal tables | I6: =IF(B6="","",COUNTIFS('Content Calendar'!$J$5:$J$604,B6,'Content Calendar'!$B$5:$B$604,">="&DATE(PlanYear,1,1),'Content Calendar'!$B$5:$B$604,"<="&DATE(PlanYear,12,31))) -> 0 | J6: =IF(B6="","",COUNTIFS('Content Calendar'!$J$5:$J$604,B6,'Content Calendar'!$X$5:$X$604,"Published",'Content Calendar'!$B$5:$B$604,">="&DATE(PlanYear,1,1),'Content Calendar'!$B$5:$B$604,"<="&DATE(PlanYear,12,31))) -> 0 | K6: =IF(OR(B6="",SUM('Content Pillars'!$I$5:$I$24)=0),"",I6/SUM('Content Pillars'!$I$5:$I$24)) -> 0 | L6: =IF(OR(K6="",C6=""),"",K6-C6) -> 0 | M6: =IF(B6="","",SUMIFS(Performance!$O$5:$O$404,Performance!$H$5:$H$404,B6)) -> 0 | N6: =IF(B6="","",SUMIFS(Performance!$Z$5:$Z$404,Performance!$H$5:$H$404,B6)) -> 0 | O6: =IF(OR(M6="",M6=0),"",N6/M6) -> 0 | P6: =IF(B6="","",SUMIFS(Performance!$U$5:$U$404,Performance!$H$5:$H$404,B6)) -> 0 | Q6: =IF(OR(B6="",J6=0),"",IFERROR(INDEX(Performance!$C$5:$C$404,MATCH(SUMPRODUCT(MAX((Performance!$H$5:$H$404=B6)*Performance!$AJ$5:$AJ$404)),Performance!$AJ$5:$AJ$404,0)),"")) -> 0 | R6: =IF(B6="","",IF(I6=0,"Action - no posts planned",IF(L6>0.1,"Check - over-used pillar",IF(L6<-0.1,"Check - under-used pillar","OK")))) -> 0
A7: =IF(B7="","","PIL-"&TEXT(ROW()-4,"00")) -> 0 | B7: Behind the scenes | C7: 0.18 | D7: Let people watch the making | E7: Community | F7: Reel | G7: Interiors Isla | H7: Studio days, kiln openings, packing | I7: =IF(B7="","",COUNTIFS('Content Calendar'!$J$5:$J$604,B7,'Content Calendar'!$B$5:$B$604,">="&DATE(PlanYear,1,1),'Content Calendar'!$B$5:$B$604,"<="&DATE(PlanYear,12,31))) -> 0 | J7: =IF(B7="","",COUNTIFS('Content Calendar'!$J$5:$J$604,B7,'Content Calendar'!$X$5:$X$604,"Published",'Content Calendar'!$B$5:$B$604,">="&DATE(PlanYear,1,1),'Content Calendar'!$B$5:$B$604,"<="&DATE(PlanYear,12,31))) -> 0 | K7: =IF(OR(B7="",SUM('Content Pillars'!$I$5:$I$24)=0),"",I7/SUM('Content Pillars'!$I$5:$I$24)) -> 0 | L7: =IF(OR(K7="",C7=""),"",K7-C7) -> 0 | M7: =IF(B7="","",SUMIFS(Performance!$O$5:$O$404,Performance!$H$5:$H$404,B7)) -> 0 | N7: =IF(B7="","",SUMIFS(Performance!$Z$5:$Z$404,Performance!$H$5:$H$404,B7)) -> 0 | O7: =IF(OR(M7="",M7=0),"",N7/M7) -> 0 | P7: =IF(B7="","",SUMIFS(Performance!$U$5:$U$404,Performance!$H$5:$H$404,B7)) -> 0 | Q7: =IF(OR(B7="",J7=0),"",IFERROR(INDEX(Performance!$C$5:$C$404,MATCH(SUMPRODUCT(MAX((Performance!$H$5:$H$404=B7)*Performance!$AJ$5:$AJ$404)),Performance!$AJ$5:$AJ$404,0)),"")) -> 0 | R7: =IF(B7="","",IF(I7=0,"Action - no posts planned",IF(L7>0.1,"Check - over-used pillar",IF(L7<-0.1,"Check - under-used pillar","OK")))) -> 0
A8: =IF(B8="","","PIL-"&TEXT(ROW()-4,"00")) -> 0 | B8: Community | C8: 0.12 | D8: Talk with people, not at them | E8: Engagement | F8: Story | G8: Interiors Isla | H8: Questions, votes, customer features | I8: =IF(B8="","",COUNTIFS('Content Calendar'!$J$5:$J$604,B8,'Content Calendar'!$B$5:$B$604,">="&DATE(PlanYear,1,1),'Content Calendar'!$B$5:$B$604,"<="&DATE(PlanYear,12,31))) -> 0 | J8: =IF(B8="","",COUNTIFS('Content Calendar'!$J$5:$J$604,B8,'Content Calendar'!$X$5:$X$604,"Published",'Content Calendar'!$B$5:$B$604,">="&DATE(PlanYear,1,1),'Content Calendar'!$B$5:$B$604,"<="&DATE(PlanYear,12,31))) -> 0 | K8: =IF(OR(B8="",SUM('Content Pillars'!$I$5:$I$24)=0),"",I8/SUM('Content Pillars'!$I$5:$I$24)) -> 0 | L8: =IF(OR(K8="",C8=""),"",K8-C8) -> 0 | M8: =IF(B8="","",SUMIFS(Performance!$O$5:$O$404,Performance!$H$5:$H$404,B8)) -> 0 | N8: =IF(B8="","",SUMIFS(Performance!$Z$5:$Z$404,Performance!$H$5:$H$404,B8)) -> 0 | O8: =IF(OR(M8="",M8=0),"",N8/M8) -> 0 | P8: =IF(B8="","",SUMIFS(Performance!$U$5:$U$404,Performance!$H$5:$H$404,B8)) -> 0 | Q8: =IF(OR(B8="",J8=0),"",IFERROR(INDEX(Performance!$C$5:$C$404,MATCH(SUMPRODUCT(MAX((Performance!$H$5:$H$404=B8)*Performance!$AJ$5:$AJ$404)),Performance!$AJ$5:$AJ$404,0)),"")) -> 0 | R8: =IF(B8="","",IF(I8=0,"Action - no posts planned",IF(L8>0.1,"Check - over-used pillar",IF(L8<-0.1,"Check - under-used pillar","OK")))) -> 0
A9: =IF(B9="","","PIL-"&TEXT(ROW()-4,"00")) -> 0 | B9: Promote | C9: 0.15 | D9: Ask for the sale, clearly and kindly | E9: Sales | F9: Carousel | G9: Interiors Isla | H9: Launches, restocks, gift guides | I9: =IF(B9="","",COUNTIFS('Content Calendar'!$J$5:$J$604,B9,'Content Calendar'!$B$5:$B$604,">="&DATE(PlanYear,1,1),'Content Calendar'!$B$5:$B$604,"<="&DATE(PlanYear,12,31))) -> 0 | J9: =IF(B9="","",COUNTIFS('Content Calendar'!$J$5:$J$604,B9,'Content Calendar'!$X$5:$X$604,"Published",'Content Calendar'!$B$5:$B$604,">="&DATE(PlanYear,1,1),'Content Calendar'!$B$5:$B$604,"<="&DATE(PlanYear,12,31))) -> 0 | K9: =IF(OR(B9="",SUM('Content Pillars'!$I$5:$I$24)=0),"",I9/SUM('Content Pillars'!$I$5:$I$24)) -> 0 | L9: =IF(OR(K9="",C9=""),"",K9-C9) -> 0 | M9: =IF(B9="","",SUMIFS(Performance!$O$5:$O$404,Performance!$H$5:$H$404,B9)) -> 0 | N9: =IF(B9="","",SUMIFS(Performance!$Z$5:$Z$404,Performance!$H$5:$H$404,B9)) -> 0 | O9: =IF(OR(M9="",M9=0),"",N9/M9) -> 0 | P9: =IF(B9="","",SUMIFS(Performance!$U$5:$U$404,Performance!$H$5:$H$404,B9)) -> 0 | Q9: =IF(OR(B9="",J9=0),"",IFERROR(INDEX(Performance!$C$5:$C$404,MATCH(SUMPRODUCT(MAX((Performance!$H$5:$H$404=B9)*Performance!$AJ$5:$AJ$404)),Performance!$AJ$5:$AJ$404,0)),"")) -> 0 | R9: =IF(B9="","",IF(I9=0,"Action - no posts planned",IF(L9>0.1,"Check - over-used pillar",IF(L9<-0.1,"Check - under-used pillar","OK")))) -> 0
A10: =IF(B10="","","PIL-"&TEXT(ROW()-4,"00")) -> 0 | B10: Entertain | C10: 0.05 | D10: Make someone smile and share it | E10: Awareness | F10: Reel | G10: Interiors Isla | H10: Studio bloopers, trends, satisfying clips | I10: =IF(B10="","",COUNTIFS('Content Calendar'!$J$5:$J$604,B10,'Content Calendar'!$B$5:$B$604,">="&DATE(PlanYear,1,1),'Content Calendar'!$B$5:$B$604,"<="&DATE(PlanYear,12,31))) -> 0 | J10: =IF(B10="","",COUNTIFS('Content Calendar'!$J$5:$J$604,B10,'Content Calendar'!$X$5:$X$604,"Published",'Content Calendar'!$B$5:$B$604,">="&DATE(PlanYear,1,1),'Content Calendar'!$B$5:$B$604,"<="&DATE(PlanYear,12,31))) -> 0 | K10: =IF(OR(B10="",SUM('Content Pillars'!$I$5:$I$24)=0),"",I10/SUM('Content Pillars'!$I$5:$I$24)) -> 0 | L10: =IF(OR(K10="",C10=""),"",K10-C10) -> 0 | M10: =IF(B10="","",SUMIFS(Performance!$O$5:$O$404,Performance!$H$5:$H$404,B10)) -> 0 | N10: =IF(B10="","",SUMIFS(Performance!$Z$5:$Z$404,Performance!$H$5:$H$404,B10)) -> 0 | O10: =IF(OR(M10="",M10=0),"",N10/M10) -> 0 | P10: =IF(B10="","",SUMIFS(Performance!$U$5:$U$404,Performance!$H$5:$H$404,B10)) -> 0 | Q10: =IF(OR(B10="",J10=0),"",IFERROR(INDEX(Performance!$C$5:$C$404,MATCH(SUMPRODUCT(MAX((Performance!$H$5:$H$404=B10)*Performance!$AJ$5:$AJ$404)),Performance!$AJ$5:$AJ$404,0)),"")) -> 0 | R10: =IF(B10="","",IF(I10=0,"Action - no posts planned",IF(L10>0.1,"Check - over-used pillar",IF(L10<-0.1,"Check - under-used pillar","OK")))) -> 0
A11: =IF(B11="","","PIL-"&TEXT(ROW()-4,"00")) -> 0 | B11: Personal | C11: 0.05 | D11: The person behind the brand | E11: Community | F11: Feed post | G11: Interiors Isla | H11: Story of the maker, lessons, opinions | I11: =IF(B11="","",COUNTIFS('Content Calendar'!$J$5:$J$604,B11,'Content Calendar'!$B$5:$B$604,">="&DATE(PlanYear,1,1),'Content Calendar'!$B$5:$B$604,"<="&DATE(PlanYear,12,31))) -> 0 | J11: =IF(B11="","",COUNTIFS('Content Calendar'!$J$5:$J$604,B11,'Content Calendar'!$X$5:$X$604,"Published",'Content Calendar'!$B$5:$B$604,">="&DATE(PlanYear,1,1),'Content Calendar'!$B$5:$B$604,"<="&DATE(PlanYear,12,31))) -> 0 | K11: =IF(OR(B11="",SUM('Content Pillars'!$I$5:$I$24)=0),"",I11/SUM('Content Pillars'!$I$5:$I$24)) -> 0 | L11: =IF(OR(K11="",C11=""),"",K11-C11) -> 0 | M11: =IF(B11="","",SUMIFS(Performance!$O$5:$O$404,Performance!$H$5:$H$404,B11)) -> 0 | N11: =IF(B11="","",SUMIFS(Performance!$Z$5:$Z$404,Performance!$H$5:$H$404,B11)) -> 0 | O11: =IF(OR(M11="",M11=0),"",N11/M11) -> 0 | P11: =IF(B11="","",SUMIFS(Performance!$U$5:$U$404,Performance!$H$5:$H$404,B11)) -> 0 | Q11: =IF(OR(B11="",J11=0),"",IFERROR(INDEX(Performance!$C$5:$C$404,MATCH(SUMPRODUCT(MAX((Performance!$H$5:$H$404=B11)*Performance!$AJ$5:$AJ$404)),Performance!$AJ$5:$AJ$404,0)),"")) -> 0 | R11: =IF(B11="","",IF(I11=0,"Action - no posts planned",IF(L11>0.1,"Check - over-used pillar",IF(L11<-0.1,"Check - under-used pillar","OK")))) -> 0
A12: =IF(B12="","","PIL-"&TEXT(ROW()-4,"00")) -> 0 | I12: =IF(B12="","",COUNTIFS('Content Calendar'!$J$5:$J$604,B12,'Content Calendar'!$B$5:$B$604,">="&DATE(PlanYear,1,1),'Content Calendar'!$B$5:$B$604,"<="&DATE(PlanYear,12,31))) -> 0 | J12: =IF(B12="","",COUNTIFS('Content Calendar'!$J$5:$J$604,B12,'Content Calendar'!$X$5:$X$604,"Published",'Content Calendar'!$B$5:$B$604,">="&DATE(PlanYear,1,1),'Content Calendar'!$B$5:$B$604,"<="&DATE(PlanYear,12,31))) -> 0 | K12: =IF(OR(B12="",SUM('Content Pillars'!$I$5:$I$24)=0),"",I12/SUM('Content Pillars'!$I$5:$I$24)) -> 0 | L12: =IF(OR(K12="",C12=""),"",K12-C12) -> 0 | M12: =IF(B12="","",SUMIFS(Performance!$O$5:$O$404,Performance!$H$5:$H$404,B12)) -> 0 | N12: =IF(B12="","",SUMIFS(Performance!$Z$5:$Z$404,Performance!$H$5:$H$404,B12)) -> 0 | O12: =IF(OR(M12="",M12=0),"",N12/M12) -> 0 | P12: =IF(B12="","",SUMIFS(Performance!$U$5:$U$404,Performance!$H$5:$H$404,B12)) -> 0 | Q12: =IF(OR(B12="",J12=0),"",IFERROR(INDEX(Performance!$C$5:$C$404,MATCH(SUMPRODUCT(MAX((Performance!$H$5:$H$404=B12)*Performance!$AJ$5:$AJ$404)),Performance!$AJ$5:$AJ$404,0)),"")) -> 0 | R12: =IF(B12="","",IF(I12=0,"Action - no posts planned",IF(L12>0.1,"Check - over-used pillar",IF(L12<-0.1,"Check - under-used pillar","OK")))) -> 0
A13: =IF(B13="","","PIL-"&TEXT(ROW()-4,"00")) -> 0 | I13: =IF(B13="","",COUNTIFS('Content Calendar'!$J$5:$J$604,B13,'Content Calendar'!$B$5:$B$604,">="&DATE(PlanYear,1,1),'Content Calendar'!$B$5:$B$604,"<="&DATE(PlanYear,12,31))) -> 0 | J13: =IF(B13="","",COUNTIFS('Content Calendar'!$J$5:$J$604,B13,'Content Calendar'!$X$5:$X$604,"Published",'Content Calendar'!$B$5:$B$604,">="&DATE(PlanYear,1,1),'Content Calendar'!$B$5:$B$604,"<="&DATE(PlanYear,12,31))) -> 0 | K13: =IF(OR(B13="",SUM('Content Pillars'!$I$5:$I$24)=0),"",I13/SUM('Content Pillars'!$I$5:$I$24)) -> 0 | L13: =IF(OR(K13="",C13=""),"",K13-C13) -> 0 | M13: =IF(B13="","",SUMIFS(Performance!$O$5:$O$404,Performance!$H$5:$H$404,B13)) -> 0 | N13: =IF(B13="","",SUMIFS(Performance!$Z$5:$Z$404,Performance!$H$5:$H$404,B13)) -> 0 | O13: =IF(OR(M13="",M13=0),"",N13/M13) -> 0 | P13: =IF(B13="","",SUMIFS(Performance!$U$5:$U$404,Performance!$H$5:$H$404,B13)) -> 0 | Q13: =IF(OR(B13="",J13=0),"",IFERROR(INDEX(Performance!$C$5:$C$404,MATCH(SUMPRODUCT(MAX((Performance!$H$5:$H$404=B13)*Performance!$AJ$5:$AJ$404)),Performance!$AJ$5:$AJ$404,0)),"")) -> 0 | R13: =IF(B13="","",IF(I13=0,"Action - no posts planned",IF(L13>0.1,"Check - over-used pillar",IF(L13<-0.1,"Check - under-used pillar","OK")))) -> 0
A14: =IF(B14="","","PIL-"&TEXT(ROW()-4,"00")) -> 0 | I14: =IF(B14="","",COUNTIFS('Content Calendar'!$J$5:$J$604,B14,'Content Calendar'!$B$5:$B$604,">="&DATE(PlanYear,1,1),'Content Calendar'!$B$5:$B$604,"<="&DATE(PlanYear,12,31))) -> 0 | J14: =IF(B14="","",COUNTIFS('Content Calendar'!$J$5:$J$604,B14,'Content Calendar'!$X$5:$X$604,"Published",'Content Calendar'!$B$5:$B$604,">="&DATE(PlanYear,1,1),'Content Calendar'!$B$5:$B$604,"<="&DATE(PlanYear,12,31))) -> 0 | K14: =IF(OR(B14="",SUM('Content Pillars'!$I$5:$I$24)=0),"",I14/SUM('Content Pillars'!$I$5:$I$24)) -> 0 | L14: =IF(OR(K14="",C14=""),"",K14-C14) -> 0 | M14: =IF(B14="","",SUMIFS(Performance!$O$5:$O$404,Performance!$H$5:$H$404,B14)) -> 0 | N14: =IF(B14="","",SUMIFS(Performance!$Z$5:$Z$404,Performance!$H$5:$H$404,B14)) -> 0 | O14: =IF(OR(M14="",M14=0),"",N14/M14) -> 0 | P14: =IF(B14="","",SUMIFS(Performance!$U$5:$U$404,Performance!$H$5:$H$404,B14)) -> 0 | Q14: =IF(OR(B14="",J14=0),"",IFERROR(INDEX(Performance!$C$5:$C$404,MATCH(SUMPRODUCT(MAX((Performance!$H$5:$H$404=B14)*Performance!$AJ$5:$AJ$404)),Performance!$AJ$5:$AJ$404,0)),"")) -> 0 | R14: =IF(B14="","",IF(I14=0,"Action - no posts planned",IF(L14>0.1,"Check - over-used pillar",IF(L14<-0.1,"Check - under-used pillar","OK")))) -> 0
A15: =IF(B15="","","PIL-"&TEXT(ROW()-4,"00")) -> 0 | I15: =IF(B15="","",COUNTIFS('Content Calendar'!$J$5:$J$604,B15,'Content Calendar'!$B$5:$B$604,">="&DATE(PlanYear,1,1),'Content Calendar'!$B$5:$B$604,"<="&DATE(PlanYear,12,31))) -> 0 | J15: =IF(B15="","",COUNTIFS('Content Calendar'!$J$5:$J$604,B15,'Content Calendar'!$X$5:$X$604,"Published",'Content Calendar'!$B$5:$B$604,">="&DATE(PlanYear,1,1),'Content Calendar'!$B$5:$B$604,"<="&DATE(PlanYear,12,31))) -> 0 | K15: =IF(OR(B15="",SUM('Content Pillars'!$I$5:$I$24)=0),"",I15/SUM('Content Pillars'!$I$5:$I$24)) -> 0 | L15: =IF(OR(K15="",C15=""),"",K15-C15) -> 0 | M15: =IF(B15="","",SUMIFS(Performance!$O$5:$O$404,Performance!$H$5:$H$404,B15)) -> 0 | N15: =IF(B15="","",SUMIFS(Performance!$Z$5:$Z$404,Performance!$H$5:$H$404,B15)) -> 0 | O15: =IF(OR(M15="",M15=0),"",N15/M15) -> 0 | P15: =IF(B15="","",SUMIFS(Performance!$U$5:$U$404,Performance!$H$5:$H$404,B15)) -> 0 | Q15: =IF(OR(B15="",J15=0),"",IFERROR(INDEX(Performance!$C$5:$C$404,MATCH(SUMPRODUCT(MAX((Performance!$H$5:$H$404=B15)*Performance!$AJ$5:$AJ$404)),Performance!$AJ$5:$AJ$404,0)),"")) -> 0 | R15: =IF(B15="","",IF(I15=0,"Action - no posts planned",IF(L15>0.1,"Check - over-used pillar",IF(L15<-0.1,"Check - under-used pillar","OK")))) -> 0
A16: =IF(B16="","","PIL-"&TEXT(ROW()-4,"00")) -> 0 | I16: =IF(B16="","",COUNTIFS('Content Calendar'!$J$5:$J$604,B16,'Content Calendar'!$B$5:$B$604,">="&DATE(PlanYear,1,1),'Content Calendar'!$B$5:$B$604,"<="&DATE(PlanYear,12,31))) -> 0 | J16: =IF(B16="","",COUNTIFS('Content Calendar'!$J$5:$J$604,B16,'Content Calendar'!$X$5:$X$604,"Published",'Content Calendar'!$B$5:$B$604,">="&DATE(PlanYear,1,1),'Content Calendar'!$B$5:$B$604,"<="&DATE(PlanYear,12,31))) -> 0 | K16: =IF(OR(B16="",SUM('Content Pillars'!$I$5:$I$24)=0),"",I16/SUM('Content Pillars'!$I$5:$I$24)) -> 0 | L16: =IF(OR(K16="",C16=""),"",K16-C16) -> 0 | M16: =IF(B16="","",SUMIFS(Performance!$O$5:$O$404,Performance!$H$5:$H$404,B16)) -> 0 | N16: =IF(B16="","",SUMIFS(Performance!$Z$5:$Z$404,Performance!$H$5:$H$404,B16)) -> 0 | O16: =IF(OR(M16="",M16=0),"",N16/M16) -> 0 | P16: =IF(B16="","",SUMIFS(Performance!$U$5:$U$404,Performance!$H$5:$H$404,B16)) -> 0 | Q16: =IF(OR(B16="",J16=0),"",IFERROR(INDEX(Performance!$C$5:$C$404,MATCH(SUMPRODUCT(MAX((Performance!$H$5:$H$404=B16)*Performance!$AJ$5:$AJ$404)),Performance!$AJ$5:$AJ$404,0)),"")) -> 0 | R16: =IF(B16="","",IF(I16=0,"Action - no posts planned",IF(L16>0.1,"Check - over-used pillar",IF(L16<-0.1,"Check - under-used pillar","OK")))) -> 0
A17: =IF(B17="","","PIL-"&TEXT(ROW()-4,"00")) -> 0 | I17: =IF(B17="","",COUNTIFS('Content Calendar'!$J$5:$J$604,B17,'Content Calendar'!$B$5:$B$604,">="&DATE(PlanYear,1,1),'Content Calendar'!$B$5:$B$604,"<="&DATE(PlanYear,12,31))) -> 0 | J17: =IF(B17="","",COUNTIFS('Content Calendar'!$J$5:$J$604,B17,'Content Calendar'!$X$5:$X$604,"Published",'Content Calendar'!$B$5:$B$604,">="&DATE(PlanYear,1,1),'Content Calendar'!$B$5:$B$604,"<="&DATE(PlanYear,12,31))) -> 0 | K17: =IF(OR(B17="",SUM('Content Pillars'!$I$5:$I$24)=0),"",I17/SUM('Content Pillars'!$I$5:$I$24)) -> 0 | L17: =IF(OR(K17="",C17=""),"",K17-C17) -> 0 | M17: =IF(B17="","",SUMIFS(Performance!$O$5:$O$404,Performance!$H$5:$H$404,B17)) -> 0 | N17: =IF(B17="","",SUMIFS(Performance!$Z$5:$Z$404,Performance!$H$5:$H$404,B17)) -> 0 | O17: =IF(OR(M17="",M17=0),"",N17/M17) -> 0 | P17: =IF(B17="","",SUMIFS(Performance!$U$5:$U$404,Performance!$H$5:$H$404,B17)) -> 0 | Q17: =IF(OR(B17="",J17=0),"",IFERROR(INDEX(Performance!$C$5:$C$404,MATCH(SUMPRODUCT(MAX((Performance!$H$5:$H$404=B17)*Performance!$AJ$5:$AJ$404)),Performance!$AJ$5:$AJ$404,0)),"")) -> 0 | R17: =IF(B17="","",IF(I17=0,"Action - no posts planned",IF(L17>0.1,"Check - over-used pillar",IF(L17<-0.1,"Check - under-used pillar","OK")))) -> 0
A18: =IF(B18="","","PIL-"&TEXT(ROW()-4,"00")) -> 0 | I18: =IF(B18="","",COUNTIFS('Content Calendar'!$J$5:$J$604,B18,'Content Calendar'!$B$5:$B$604,">="&DATE(PlanYear,1,1),'Content Calendar'!$B$5:$B$604,"<="&DATE(PlanYear,12,31))) -> 0 | J18: =IF(B18="","",COUNTIFS('Content Calendar'!$J$5:$J$604,B18,'Content Calendar'!$X$5:$X$604,"Published",'Content Calendar'!$B$5:$B$604,">="&DATE(PlanYear,1,1),'Content Calendar'!$B$5:$B$604,"<="&DATE(PlanYear,12,31))) -> 0 | K18: =IF(OR(B18="",SUM('Content Pillars'!$I$5:$I$24)=0),"",I18/SUM('Content Pillars'!$I$5:$I$24)) -> 0 | L18: =IF(OR(K18="",C18=""),"",K18-C18) -> 0 | M18: =IF(B18="","",SUMIFS(Performance!$O$5:$O$404,Performance!$H$5:$H$404,B18)) -> 0 | N18: =IF(B18="","",SUMIFS(Performance!$Z$5:$Z$404,Performance!$H$5:$H$404,B18)) -> 0 | O18: =IF(OR(M18="",M18=0),"",N18/M18) -> 0 | P18: =IF(B18="","",SUMIFS(Performance!$U$5:$U$404,Performance!$H$5:$H$404,B18)) -> 0 | Q18: =IF(OR(B18="",J18=0),"",IFERROR(INDEX(Performance!$C$5:$C$404,MATCH(SUMPRODUCT(MAX((Performance!$H$5:$H$404=B18)*Performance!$AJ$5:$AJ$404)),Performance!$AJ$5:$AJ$404,0)),"")) -> 0 | R18: =IF(B18="","",IF(I18=0,"Action - no posts planned",IF(L18>0.1,"Check - over-used pillar",IF(L18<-0.1,"Check - under-used pillar","OK")))) -> 0
A19: =IF(B19="","","PIL-"&TEXT(ROW()-4,"00")) -> 0 | I19: =IF(B19="","",COUNTIFS('Content Calendar'!$J$5:$J$604,B19,'Content Calendar'!$B$5:$B$604,">="&DATE(PlanYear,1,1),'Content Calendar'!$B$5:$B$604,"<="&DATE(PlanYear,12,31))) -> 0 | J19: =IF(B19="","",COUNTIFS('Content Calendar'!$J$5:$J$604,B19,'Content Calendar'!$X$5:$X$604,"Published",'Content Calendar'!$B$5:$B$604,">="&DATE(PlanYear,1,1),'Content Calendar'!$B$5:$B$604,"<="&DATE(PlanYear,12,31))) -> 0 | K19: =IF(OR(B19="",SUM('Content Pillars'!$I$5:$I$24)=0),"",I19/SUM('Content Pillars'!$I$5:$I$24)) -> 0 | L19: =IF(OR(K19="",C19=""),"",K19-C19) -> 0 | M19: =IF(B19="","",SUMIFS(Performance!$O$5:$O$404,Performance!$H$5:$H$404,B19)) -> 0 | N19: =IF(B19="","",SUMIFS(Performance!$Z$5:$Z$404,Performance!$H$5:$H$404,B19)) -> 0 | O19: =IF(OR(M19="",M19=0),"",N19/M19) -> 0 | P19: =IF(B19="","",SUMIFS(Performance!$U$5:$U$404,Performance!$H$5:$H$404,B19)) -> 0 | Q19: =IF(OR(B19="",J19=0),"",IFERROR(INDEX(Performance!$C$5:$C$404,MATCH(SUMPRODUCT(MAX((Performance!$H$5:$H$404=B19)*Performance!$AJ$5:$AJ$404)),Performance!$AJ$5:$AJ$404,0)),"")) -> 0 | R19: =IF(B19="","",IF(I19=0,"Action - no posts planned",IF(L19>0.1,"Check - over-used pillar",IF(L19<-0.1,"Check - under-used pillar","OK")))) -> 0
A20: =IF(B20="","","PIL-"&TEXT(ROW()-4,"00")) -> 0 | I20: =IF(B20="","",COUNTIFS('Content Calendar'!$J$5:$J$604,B20,'Content Calendar'!$B$5:$B$604,">="&DATE(PlanYear,1,1),'Content Calendar'!$B$5:$B$604,"<="&DATE(PlanYear,12,31))) -> 0 | J20: =IF(B20="","",COUNTIFS('Content Calendar'!$J$5:$J$604,B20,'Content Calendar'!$X$5:$X$604,"Published",'Content Calendar'!$B$5:$B$604,">="&DATE(PlanYear,1,1),'Content Calendar'!$B$5:$B$604,"<="&DATE(PlanYear,12,31))) -> 0 | K20: =IF(OR(B20="",SUM('Content Pillars'!$I$5:$I$24)=0),"",I20/SUM('Content Pillars'!$I$5:$I$24)) -> 0 | L20: =IF(OR(K20="",C20=""),"",K20-C20) -> 0 | M20: =IF(B20="","",SUMIFS(Performance!$O$5:$O$404,Performance!$H$5:$H$404,B20)) -> 0 | N20: =IF(B20="","",SUMIFS(Performance!$Z$5:$Z$404,Performance!$H$5:$H$404,B20)) -> 0 | O20: =IF(OR(M20="",M20=0),"",N20/M20) -> 0 | P20: =IF(B20="","",SUMIFS(Performance!$U$5:$U$404,Performance!$H$5:$H$404,B20)) -> 0 | Q20: =IF(OR(B20="",J20=0),"",IFERROR(INDEX(Performance!$C$5:$C$404,MATCH(SUMPRODUCT(MAX((Performance!$H$5:$H$404=B20)*Performance!$AJ$5:$AJ$404)),Performance!$AJ$5:$AJ$404,0)),"")) -> 0 | R20: =IF(B20="","",IF(I20=0,"Action - no posts planned",IF(L20>0.1,"Check - over-used pillar",IF(L20<-0.1,"Check - under-used pillar","OK")))) -> 0
A21: =IF(B21="","","PIL-"&TEXT(ROW()-4,"00")) -> 0 | I21: =IF(B21="","",COUNTIFS('Content Calendar'!$J$5:$J$604,B21,'Content Calendar'!$B$5:$B$604,">="&DATE(PlanYear,1,1),'Content Calendar'!$B$5:$B$604,"<="&DATE(PlanYear,12,31))) -> 0 | J21: =IF(B21="","",COUNTIFS('Content Calendar'!$J$5:$J$604,B21,'Content Calendar'!$X$5:$X$604,"Published",'Content Calendar'!$B$5:$B$604,">="&DATE(PlanYear,1,1),'Content Calendar'!$B$5:$B$604,"<="&DATE(PlanYear,12,31))) -> 0 | K21: =IF(OR(B21="",SUM('Content Pillars'!$I$5:$I$24)=0),"",I21/SUM('Content Pillars'!$I$5:$I$24)) -> 0 | L21: =IF(OR(K21="",C21=""),"",K21-C21) -> 0 | M21: =IF(B21="","",SUMIFS(Performance!$O$5:$O$404,Performance!$H$5:$H$404,B21)) -> 0 | N21: =IF(B21="","",SUMIFS(Performance!$Z$5:$Z$404,Performance!$H$5:$H$404,B21)) -> 0 | O21: =IF(OR(M21="",M21=0),"",N21/M21) -> 0 | P21: =IF(B21="","",SUMIFS(Performance!$U$5:$U$404,Performance!$H$5:$H$404,B21)) -> 0 | Q21: =IF(OR(B21="",J21=0),"",IFERROR(INDEX(Performance!$C$5:$C$404,MATCH(SUMPRODUCT(MAX((Performance!$H$5:$H$404=B21)*Performance!$AJ$5:$AJ$404)),Performance!$AJ$5:$AJ$404,0)),"")) -> 0 | R21: =IF(B21="","",IF(I21=0,"Action - no posts planned",IF(L21>0.1,"Check - over-used pillar",IF(L21<-0.1,"Check - under-used pillar","OK")))) -> 0
A22: =IF(B22="","","PIL-"&TEXT(ROW()-4,"00")) -> 0 | I22: =IF(B22="","",COUNTIFS('Content Calendar'!$J$5:$J$604,B22,'Content Calendar'!$B$5:$B$604,">="&DATE(PlanYear,1,1),'Content Calendar'!$B$5:$B$604,"<="&DATE(PlanYear,12,31))) -> 0 | J22: =IF(B22="","",COUNTIFS('Content Calendar'!$J$5:$J$604,B22,'Content Calendar'!$X$5:$X$604,"Published",'Content Calendar'!$B$5:$B$604,">="&DATE(PlanYear,1,1),'Content Calendar'!$B$5:$B$604,"<="&DATE(PlanYear,12,31))) -> 0 | K22: =IF(OR(B22="",SUM('Content Pillars'!$I$5:$I$24)=0),"",I22/SUM('Content Pillars'!$I$5:$I$24)) -> 0 | L22: =IF(OR(K22="",C22=""),"",K22-C22) -> 0 | M22: =IF(B22="","",SUMIFS(Performance!$O$5:$O$404,Performance!$H$5:$H$404,B22)) -> 0 | N22: =IF(B22="","",SUMIFS(Performance!$Z$5:$Z$404,Performance!$H$5:$H$404,B22)) -> 0 | O22: =IF(OR(M22="",M22=0),"",N22/M22) -> 0 | P22: =IF(B22="","",SUMIFS(Performance!$U$5:$U$404,Performance!$H$5:$H$404,B22)) -> 0 | Q22: =IF(OR(B22="",J22=0),"",IFERROR(INDEX(Performance!$C$5:$C$404,MATCH(SUMPRODUCT(MAX((Performance!$H$5:$H$404=B22)*Performance!$AJ$5:$AJ$404)),Performance!$AJ$5:$AJ$404,0)),"")) -> 0 | R22: =IF(B22="","",IF(I22=0,"Action - no posts planned",IF(L22>0.1,"Check - over-used pillar",IF(L22<-0.1,"Check - under-used pillar","OK")))) -> 0
A23: =IF(B23="","","PIL-"&TEXT(ROW()-4,"00")) -> 0 | I23: =IF(B23="","",COUNTIFS('Content Calendar'!$J$5:$J$604,B23,'Content Calendar'!$B$5:$B$604,">="&DATE(PlanYear,1,1),'Content Calendar'!$B$5:$B$604,"<="&DATE(PlanYear,12,31))) -> 0 | J23: =IF(B23="","",COUNTIFS('Content Calendar'!$J$5:$J$604,B23,'Content Calendar'!$X$5:$X$604,"Published",'Content Calendar'!$B$5:$B$604,">="&DATE(PlanYear,1,1),'Content Calendar'!$B$5:$B$604,"<="&DATE(PlanYear,12,31))) -> 0 | K23: =IF(OR(B23="",SUM('Content Pillars'!$I$5:$I$24)=0),"",I23/SUM('Content Pillars'!$I$5:$I$24)) -> 0 | L23: =IF(OR(K23="",C23=""),"",K23-C23) -> 0 | M23: =IF(B23="","",SUMIFS(Performance!$O$5:$O$404,Performance!$H$5:$H$404,B23)) -> 0 | N23: =IF(B23="","",SUMIFS(Performance!$Z$5:$Z$404,Performance!$H$5:$H$404,B23)) -> 0 | O23: =IF(OR(M23="",M23=0),"",N23/M23) -> 0 | P23: =IF(B23="","",SUMIFS(Performance!$U$5:$U$404,Performance!$H$5:$H$404,B23)) -> 0 | Q23: =IF(OR(B23="",J23=0),"",IFERROR(INDEX(Performance!$C$5:$C$404,MATCH(SUMPRODUCT(MAX((Performance!$H$5:$H$404=B23)*Performance!$AJ$5:$AJ$404)),Performance!$AJ$5:$AJ$404,0)),"")) -> 0 | R23: =IF(B23="","",IF(I23=0,"Action - no posts planned",IF(L23>0.1,"Check - over-used pillar",IF(L23<-0.1,"Check - under-used pillar","OK")))) -> 0
A24: =IF(B24="","","PIL-"&TEXT(ROW()-4,"00")) -> 0 | I24: =IF(B24="","",COUNTIFS('Content Calendar'!$J$5:$J$604,B24,'Content Calendar'!$B$5:$B$604,">="&DATE(PlanYear,1,1),'Content Calendar'!$B$5:$B$604,"<="&DATE(PlanYear,12,31))) -> 0 | J24: =IF(B24="","",COUNTIFS('Content Calendar'!$J$5:$J$604,B24,'Content Calendar'!$X$5:$X$604,"Published",'Content Calendar'!$B$5:$B$604,">="&DATE(PlanYear,1,1),'Content Calendar'!$B$5:$B$604,"<="&DATE(PlanYear,12,31))) -> 0 | K24: =IF(OR(B24="",SUM('Content Pillars'!$I$5:$I$24)=0),"",I24/SUM('Content Pillars'!$I$5:$I$24)) -> 0 | L24: =IF(OR(K24="",C24=""),"",K24-C24) -> 0 | M24: =IF(B24="","",SUMIFS(Performance!$O$5:$O$404,Performance!$H$5:$H$404,B24)) -> 0 | N24: =IF(B24="","",SUMIFS(Performance!$Z$5:$Z$404,Performance!$H$5:$H$404,B24)) -> 0 | O24: =IF(OR(M24="",M24=0),"",N24/M24) -> 0 | P24: =IF(B24="","",SUMIFS(Performance!$U$5:$U$404,Performance!$H$5:$H$404,B24)) -> 0 | Q24: =IF(OR(B24="",J24=0),"",IFERROR(INDEX(Performance!$C$5:$C$404,MATCH(SUMPRODUCT(MAX((Performance!$H$5:$H$404=B24)*Performance!$AJ$5:$AJ$404)),Performance!$AJ$5:$AJ$404,0)),"")) -> 0 | R24: =IF(B24="","",IF(I24=0,"Action - no posts planned",IF(L24>0.1,"Check - over-used pillar",IF(L24<-0.1,"Check - under-used pillar","OK")))) -> 0
A26: Totals | C26: =SUM(C5:C24) -> 0 | D26: The target column should add up to 100%. | I26: =SUM(I5:I24) -> 0

Sheet Content Calendar
A1: 12-Month Content Calendar | AL1: Novality Store | v1.0.0
A2: One row per post, on any platform, for the whole year. Filter by month, platform, pillar or status - the grey columns keep the deadlines, links and results up to date for you.
A3: > Start Here | C3: > Dashboard | E3: > Calendar | G3: > Ideas | I3: > Captions | K3: > Hashtags | M3: > Analytics | O3: > Reports | Q3: > Help | S3: Type the publish date and a title - the ID, month, week, deadlines and alerts fill themselves in. Use the filter arrows rather than re-sorting so the content IDs stay matched to the other tabs.
A4: ID | B4: Publish date | C4: Time slot | D4: Month | E4: Week | F4: Day | G4: Platform | H4: Content title | I4: What it is about | J4: Content pillar | K4: Format | L4: Campaign | M4: Objective | N4: Funnel stage | O4: Written for | P4: Caption (from the bank) | Q4: Caption ready | R4: Hashtag group | S4: Tags in group | T4: Creative asset | U4: Asset approved | V4: Call to action | W4: Owner | X4: Status | Y4: Draft due | Z4: Approval due | AA4: Days to go | AB4: Published link | AC4: Live? | AD4: Reach | AE4: Engagements | AF4: Engagement rate | AG4: Clicks | AH4: Repurposed | AI4: Day key | AJ4: Queue key | AK4: Late key | AL4: Duplicate check | AM4: Action needed | AN4: Notes
A5: =IF(H5="","",ContentPrefix&TEXT(ROW()-4,"0000")) -> 0 | B5: 46250 | C5: Morning | D5: =IF(B5="","",TEXT(B5,"yyyy-mm")) -> 0 | E5: =IF(B5="","",WEEKNUM(B5,IF(WeekStart="Sunday",1,2))) -> 0 | F5: =IF(B5="","",TEXT(B5,"ddd")) -> 0 | G5: Instagram | H5: 5 ways to style a single stem vase | I5: Educate post for instagram: 5 ways to style a single stem vase. | J5: Educate | K5: Carousel | L5: Autumn Table Styling | M5: Brand authority | N5: Consideration | O5: First-home Freya | P5: Single stem styling | Q5: =IF(H5="","",IF(P5="","Add - no caption",IFERROR(INDEX('Caption Bank'!$R$5:$R$204,MATCH(P5,'Caption Bank'!$B$5:$B$204,0)),"Check - not in bank"))) -> 0 | R5: Group 1 | S5: =IF(R5="","",COUNTIF('Hashtag Bank'!$D$5:$D$304,R5)) -> 0 | T5: AS-0001 | U5: =IF(H5="","",IF(T5="","Add - no asset",IFERROR(INDEX(Assets!$N$5:$N$254,MATCH(T5,Assets!$A$5:$A$254,0)),"Check - not in library"))) -> 0 | V5: Save this | W5: Jordan Avery | X5: Published | Y5: =IF(B5="","",B5-ProductionDays) -> 0 | Z5: =IF(B5="","",B5-ApprovalDays) -> 0 | AA5: =IF(B5="","",B5-TODAY()) -> 0 | AB5: instagram.com/wildflowerstudio/p/5600 | AC5: =IF(H5="","",IF(X5="Published",IF(AB5="","Add - link missing","Yes"),"No")) -> 0 | AD5: =IF(A5="","",IF(COUNTIF(Performance!$B$5:$B$404,A5)=0,"",SUMIFS(Performance!$O$5:$O$404,Performance!$B$5:$B$404,A5))) -> 0 | AE5: =IF(AD5="","",SUMIFS(Performance!$Z$5:$Z$404,Performance!$B$5:$B$404,A5)) -> 0 | AF5: =IF(OR(AD5="",AD5=0),"",AE5/AD5) -> 0 | AG5: =IF(AD5="","",SUMIFS(Performance!$U$5:$U$404,Performance!$B$5:$B$404,A5)) -> 0 | AH5: =IF(A5="","",COUNTIF(Repurposing!$B$5:$B$154,A5)) -> 0 | AI5: =IF(OR(H5="",B5=""),"",B5+ROW()/100000) -> 0 | AJ5: =IF(OR(H5="",B5=""),"",IF(OR(X5="Published",X5="Cancelled",X5="Archived"),"",IF(B5<TODAY(),"",B5+ROW()/100000))) -> 0 | AK5: =IF(OR(H5="",B5=""),"",IF(OR(X5="Published",X5="Cancelled",X5="Archived"),"",IF(B5>=TODAY(),"",B5+ROW()/100000))) -> 0 | AL5: =IF(H5="","",IF(COUNTIFS('Content Calendar'!$H$5:$H$604,H5,'Content Calendar'!$G$5:$G$604,G5,'Content Calendar'!$B$5:$B$604,B5)>1,"Duplicate","OK")) -> 0 | AM5: =IF(H5="","",IF(AND(B5<>"",B5<TODAY(),X5<>"Published",X5<>"Cancelled",X5<>"Archived"),"Overdue - date has passed",IF(AND(X5="Published",AB5=""),"Add - publish link missing",IF(AND(B5=TODAY(),X5<>"Published"),"Today - due to go live",IF(AND(Y5<>"",Y5<TODAY(),OR(X5="Idea",X5="Brief",X5="In production")),"Late - draft not ready",IF(AND(AA5>=0,AA5<=3,OR(X5="Draft",X5="Awaiting review")),"Due - needs approval",IF(AND(H5<>"",P5=""),"Add - caption missing","OK"))))))) -> 0
A6: =IF(H6="","",ContentPrefix&TEXT(ROW()-4,"0000")) -> 0 | B6: 46251 | C6: Lunchtime | D6: =IF(B6="","",TEXT(B6,"yyyy-mm")) -> 0 | E6: =IF(B6="","",WEEKNUM(B6,IF(WeekStart="Sunday",1,2))) -> 0 | F6: =IF(B6="","",TEXT(B6,"ddd")) -> 0 | G6: Pinterest | H6: Autumn table styling checklist | I6: Educate post for pinterest: Autumn table styling checklist. | J6: Educate | K6: Standard Pin | L6: Autumn Table Styling | M6: Brand authority | N6: Consideration | O6: Gifting Grace | P6: Kiln opening | Q6: =IF(H6="","",IF(P6="","Add - no caption",IFERROR(INDEX('Caption Bank'!$R$5:$R$204,MATCH(P6,'Caption Bank'!$B$5:$B$204,0)),"Check - not in bank"))) -> 0 | R6: Group 2 | S6: =IF(R6="","",COUNTIF('Hashtag Bank'!$D$5:$D$304,R6)) -> 0 | T6: AS-0002 | U6: =IF(H6="","",IF(T6="","Add - no asset",IFERROR(INDEX(Assets!$N$5:$N$254,MATCH(T6,Assets!$A$5:$A$254,0)),"Check - not in library"))) -> 0 | V6: Save this | W6: Priya Nair | X6: Published | Y6: =IF(B6="","",B6-ProductionDays) -> 0 | Z6: =IF(B6="","",B6-ApprovalDays) -> 0 | AA6: =IF(B6="","",B6-TODAY()) -> 0 | AB6: pinterest.com/wildflowerstudio/p/5501 | AC6: =IF(H6="","",IF(X6="Published",IF(AB6="","Add - link missing","Yes"),"No")) -> 0 | AD6: =IF(A6="","",IF(COUNTIF(Performance!$B$5:$B$404,A6)=0,"",SUMIFS(Performance!$O$5:$O$404,Performance!$B$5:$B$404,A6))) -> 0 | AE6: =IF(AD6="","",SUMIFS(Performance!$Z$5:$Z$404,Performance!$B$5:$B$404,A6)) -> 0 | AF6: =IF(OR(AD6="",AD6=0),"",AE6/AD6) -> 0 | AG6: =IF(AD6="","",SUMIFS(Performance!$U$5:$U$404,Performance!$B$5:$B$404,A6)) -> 0 | AH6: =IF(A6="","",COUNTIF(Repurposing!$B$5:$B$154,A6)) -> 0 | AI6: =IF(OR(H6="",B6=""),"",B6+ROW()/100000) -> 0 | AJ6: =IF(OR(H6="",B6=""),"",IF(OR(X6="Published",X6="Cancelled",X6="Archived"),"",IF(B6<TODAY(),"",B6+ROW()/100000))) -> 0 | AK6: =IF(OR(H6="",B6=""),"",IF(OR(X6="Published",X6="Cancelled",X6="Archived"),"",IF(B6>=TODAY(),"",B6+ROW()/100000))) -> 0 | AL6: =IF(H6="","",IF(COUNTIFS('Content Calendar'!$H$5:$H$604,H6,'Content Calendar'!$G$5:$G$604,G6,'Content Calendar'!$B$5:$B$604,B6)>1,"Duplicate","OK")) -> 0 | AM6: =IF(H6="","",IF(AND(B6<>"",B6<TODAY(),X6<>"Published",X6<>"Cancelled",X6<>"Archived"),"Overdue - date has passed",IF(AND(X6="Published",AB6=""),"Add - publish link missing",IF(AND(B6=TODAY(),X6<>"Published"),"Today - due to go live",IF(AND(Y6<>"",Y6<TODAY(),OR(X6="Idea",X6="Brief",X6="In production")),"Late - draft not ready",IF(AND(AA6>=0,AA6<=3,OR(X6="Draft",X6="Awaiting review")),"Due - needs approval",IF(AND(H6<>"",P6=""),"Add - caption missing","OK"))))))) -> 0
A7: =IF(H7="","",ContentPrefix&TEXT(ROW()-4,"0000")) -> 0 | B7: 46252 | C7: Evening | D7: =IF(B7="","",TEXT(B7,"yyyy-mm")) -> 0 | E7: =IF(B7="","",WEEKNUM(B7,IF(WeekStart="Sunday",1,2))) -> 0 | F7: =IF(B7="","",TEXT(B7,"ddd")) -> 0 | G7: TikTok | H7: Throwing a mug from start to finish | I7: Behind the scenes post for tiktok: Throwing a mug from start to finish. | J7: Behind the scenes | K7: Reel | L7: Autumn Table Styling | M7: Community | N7: Awareness | O7: Interiors Isla | P7: Autumn collection live | Q7: =IF(H7="","",IF(P7="","Add - no caption",IFERROR(INDEX('Caption Bank'!$R$5:$R$204,MATCH(P7,'Caption Bank'!$B$5:$B$204,0)),"Check - not in bank"))) -> 0 | R7: Group 3 | S7: =IF(R7="","",COUNTIF('Hashtag Bank'!$D$5:$D$304,R7)) -> 0 | T7: AS-0003 | U7: =IF(H7="","",IF(T7="","Add - no asset",IFERROR(INDEX(Assets!$N$5:$N$254,MATCH(T7,Assets!$A$5:$A$254,0)),"Check - not in library"))) -> 0 | V7: Comment below | W7: Sam Okonkwo | X7: Published | Y7: =IF(B7="","",B7-ProductionDays) -> 0 | Z7: =IF(B7="","",B7-ApprovalDays) -> 0 | AA7: =IF(B7="","",B7-TODAY()) -> 0 | AB7: tiktok.com/wildflowerstudio/p/5402 | AC7: =IF(H7="","",IF(X7="Published",IF(AB7="","Add - link missing","Yes"),"No")) -> 0 | AD7: =IF(A7="","",IF(COUNTIF(Performance!$B$5:$B$404,A7)=0,"",SUMIFS(Performance!$O$5:$O$404,Performance!$B$5:$B$404,A7))) -> 0 | AE7: =IF(AD7="","",SUMIFS(Performance!$Z$5:$Z$404,Performance!$B$5:$B$404,A7)) -> 0 | AF7: =IF(OR(AD7="",AD7=0),"",AE7/AD7) -> 0 | AG7: =IF(AD7="","",SUMIFS(Performance!$U$5:$U$404,Performance!$B$5:$B$404,A7)) -> 0 | AH7: =IF(A7="","",COUNTIF(Repurposing!$B$5:$B$154,A7)) -> 0 | AI7: =IF(OR(H7="",B7=""),"",B7+ROW()/100000) -> 0 | AJ7: =IF(OR(H7="",B7=""),"",IF(OR(X7="Published",X7="Cancelled",X7="Archived"),"",IF(B7<TODAY(),"",B7+ROW()/100000))) -> 0 | AK7: =IF(OR(H7="",B7=""),"",IF(OR(X7="Published",X7="Cancelled",X7="Archived"),"",IF(B7>=TODAY(),"",B7+ROW()/100000))) -> 0 | AL7: =IF(H7="","",IF(COUNTIFS('Content Calendar'!$H$5:$H$604,H7,'Content Calendar'!$G$5:$G$604,G7,'Content Calendar'!$B$5:$B$604,B7)>1,"Duplicate","OK")) -> 0 | AM7: =IF(H7="","",IF(AND(B7<>"",B7<TODAY(),X7<>"Published",X7<>"Cancelled",X7<>"Archived"),"Overdue - date has passed",IF(AND(X7="Published",AB7=""),"Add - publish link missing",IF(AND(B7=TODAY(),X7<>"Published"),"Today - due to go live",IF(AND(Y7<>"",Y7<TODAY(),OR(X7="Idea",X7="Brief",X7="In production")),"Late - draft not ready",IF(AND(AA7>=0,AA7<=3,OR(X7="Draft",X7="Awaiting review")),"Due - needs approval",IF(AND(H7<>"",P7=""),"Add - caption missing","OK"))))))) -> 0
A8: =IF(H8="","",ContentPrefix&TEXT(ROW()-4,"0000")) -> 0 | B8: 46254 | C8: Morning | D8: =IF(B8="","",TEXT(B8,"yyyy-mm")) -> 0 | E8: =IF(B8="","",WEEKNUM(B8,IF(WeekStart="Sunday",1,2))) -> 0 | F8: =IF(B8="","",TEXT(B8,"ddd")) -> 0 | G8: Instagram | H8: Morning light in the studio | I8: Inspire post for instagram: Morning light in the studio. | J8: Inspire | K8: Reel | L8: Autumn Table Styling | M8: Awareness | N8: Awareness | O8: First-home Freya | P8: Stoneware vs porcelain | Q8: =IF(H8="","",IF(P8="","Add - no caption",IFERROR(INDEX('Caption Bank'!$R$5:$R$204,MATCH(P8,'Caption Bank'!$B$5:$B$204,0)),"Check - not in bank"))) -> 0 | R8: Group 4 | S8: =IF(R8="","",COUNTIF('Hashtag Bank'!$D$5:$D$304,R8)) -> 0 | T8: AS-0004 | U8: =IF(H8="","",IF(T8="","Add - no asset",IFERROR(INDEX(Assets!$N$5:$N$254,MATCH(T8,Assets!$A$5:$A$254,0)),"Check - not in library"))) -> 0 | V8: Follow for more | W8: Elena Dias | X8: Published | Y8: =IF(B8="","",B8-ProductionDays) -> 0 | Z8: =IF(B8="","",B8-ApprovalDays) -> 0 | AA8: =IF(B8="","",B8-TODAY()) -> 0 | AB8: instagram.com/wildflowerstudio/p/5203 | AC8: =IF(H8="","",IF(X8="Published",IF(AB8="","Add - link missing","Yes"),"No")) -> 0 | AD8: =IF(A8="","",IF(COUNTIF(Performance!$B$5:$B$404,A8)=0,"",SUMIFS(Performance!$O$5:$O$404,Performance!$B$5:$B$404,A8))) -> 0 | AE8: =IF(AD8="","",SUMIFS(Performance!$Z$5:$Z$404,Performance!$B$5:$B$404,A8)) -> 0 | AF8: =IF(OR(AD8="",AD8=0),"",AE8/AD8) -> 0 | AG8: =IF(AD8="","",SUMIFS(Performance!$U$5:$U$404,Performance!$B$5:$B$404,A8)) -> 0 | AH8: =IF(A8="","",COUNTIF(Repurposing!$B$5:$B$154,A8)) -> 0 | AI8: =IF(OR(H8="",B8=""),"",B8+ROW()/100000) -> 0 | AJ8: =IF(OR(H8="",B8=""),"",IF(OR(X8="Published",X8="Cancelled",X8="Archived"),"",IF(B8<TODAY(),"",B8+ROW()/100000))) -> 0 | AK8: =IF(OR(H8="",B8=""),"",IF(OR(X8="Published",X8="Cancelled",X8="Archived"),"",IF(B8>=TODAY(),"",B8+ROW()/100000))) -> 0 | AL8: =IF(H8="","",IF(COUNTIFS('Content Calendar'!$H$5:$H$604,H8,'Content Calendar'!$G$5:$G$604,G8,'Content Calendar'!$B$5:$B$604,B8)>1,"Duplicate","OK")) -> 0 | AM8: =IF(H8="","",IF(AND(B8<>"",B8<TODAY(),X8<>"Published",X8<>"Cancelled",X8<>"Archived"),"Overdue - date has passed",IF(AND(X8="Published",AB8=""),"Add - publish link missing",IF(AND(B8=TODAY(),X8<>"Published"),"Today - due to go live",IF(AND(Y8<>"",Y8<TODAY(),OR(X8="Idea",X8="Brief",X8="In production")),"Late - draft not ready",IF(AND(AA8>=0,AA8<=3,OR(X8="Draft",X8="Awaiting review")),"Due - needs approval",IF(AND(H8<>"",P8=""),"Add - caption missing","OK"))))))) -> 0 | AN8: Top performer
A9: =IF(H9="","",ContentPrefix&TEXT(ROW()-4,"0000")) -> 0 | B9: 46256 | C9: Morning | D9: =IF(B9="","",TEXT(B9,"yyyy-mm")) -> 0 | E9: =IF(B9="","",WEEKNUM(B9,IF(WeekStart="Sunday",1,2))) -> 0 | F9: =IF(B9="","",TEXT(B9,"ddd")) -> 0 | G9: Facebook | H9: Meet the makers behind your mugs | I9: Community post for facebook: Meet the makers behind your mugs. | J9: Community | K9: Feed post | L9: Autumn Table Styling | M9: Engagement | N9: Retention | O9: Gifting Grace | P9: Customer shelfie | Q9: =IF(H9="","",IF(P9="","Add - no caption",IFERROR(INDEX('Caption Bank'!$R$5:$R$204,MATCH(P9,'Caption Bank'!$B$5:$B$204,0)),"Check - not in bank"))) -> 0 | R9: Group 1 | S9: =IF(R9="","",COUNTIF('Hashtag Bank'!$D$5:$D$304,R9)) -> 0 | T9: AS-0005 | U9: =IF(H9="","",IF(T9="","Add - no asset",IFERROR(INDEX(Assets!$N$5:$N$254,MATCH(T9,Assets!$A$5:$A$254,0)),"Check - not in library"))) -> 0 | V9: Tag a friend | W9: Jordan Avery | X9: Published | Y9: =IF(B9="","",B9-ProductionDays) -> 0 | Z9: =IF(B9="","",B9-ApprovalDays) -> 0 | AA9: =IF(B9="","",B9-TODAY()) -> 0 | AB9: facebook.com/wildflowerstudio/p/5004 | AC9: =IF(H9="","",IF(X9="Published",IF(AB9="","Add - link missing","Yes"),"No")) -> 0 | AD9: =IF(A9="","",IF(COUNTIF(Performance!$B$5:$B$404,A9)=0,"",SUMIFS(Performance!$O$5:$O$404,Performance!$B$5:$B$404,A9))) -> 0 | AE9: =IF(AD9="","",SUMIFS(Performance!$Z$5:$Z$404,Performance!$B$5:$B$404,A9)) -> 0 | AF9: =IF(OR(AD9="",AD9=0),"",AE9/AD9) -> 0 | AG9: =IF(AD9="","",SUMIFS(Performance!$U$5:$U$404,Performance!$B$5:$B$404,A9)) -> 0 | AH9: =IF(A9="","",COUNTIF(Repurposing!$B$5:$B$154,A9)) -> 0 | AI9: =IF(OR(H9="",B9=""),"",B9+ROW()/100000) -> 0 | AJ9: =IF(OR(H9="",B9=""),"",IF(OR(X9="Published",X9="Cancelled",X9="Archived"),"",IF(B9<TODAY(),"",B9+ROW()/100000))) -> 0 | AK9: =IF(OR(H9="",B9=""),"",IF(OR(X9="Published",X9="Cancelled",X9="Archived"),"",IF(B9>=TODAY(),"",B9+ROW()/100000))) -> 0 | AL9: =IF(H9="","",IF(COUNTIFS('Content Calendar'!$H$5:$H$604,H9,'Content Calendar'!$G$5:$G$604,G9,'Content Calendar'!$B$5:$B$604,B9)>1,"Duplicate","OK")) -> 0 | AM9: =IF(H9="","",IF(AND(B9<>"",B9<TODAY(),X9<>"Published",X9<>"Cancelled",X9<>"Archived"),"Overdue - date has passed",IF(AND(X9="Published",AB9=""),"Add - publish link missing",IF(AND(B9=TODAY(),X9<>"Published"),"Today - due to go live",IF(AND(Y9<>"",Y9<TODAY(),OR(X9="Idea",X9="Brief",X9="In production")),"Late - draft not ready",IF(AND(AA9>=0,AA9<=3,OR(X9="Draft",X9="Awaiting review")),"Due - needs approval",IF(AND(H9<>"",P9=""),"Add - caption missing","OK"))))))) -> 0
A10: =IF(H10="","",ContentPrefix&TEXT(ROW()-4,"0000")) -> 0 | B10: 46257 | C10: Morning | D10: =IF(B10="","",TEXT(B10,"yyyy-mm")) -> 0 | E10: =IF(B10="","",WEEKNUM(B10,IF(WeekStart="Sunday",1,2))) -> 0 | F10: =IF(B10="","",TEXT(B10,"ddd")) -> 0 | G10: Instagram | H10: Last 12 speckled bowls of the batch | I10: Promote post for instagram: Last 12 speckled bowls of the batch. | J10: Promote | K10: Story | L10: Autumn Table Styling | M10: Sales | N10: Conversion | O10: Interiors Isla | P10: Why I left my desk job | Q10: =IF(H10="","",IF(P10="","Add - no caption",IFERROR(INDEX('Caption Bank'!$R$5:$R$204,MATCH(P10,'Caption Bank'!$B$5:$B$204,0)),"Check - not in bank"))) -> 0 | R10: Group 2 | S10: =IF(R10="","",COUNTIF('Hashtag Bank'!$D$5:$D$304,R10)) -> 0 | T10: AS-0006 | U10: =IF(H10="","",IF(T10="","Add - no asset",IFERROR(INDEX(Assets!$N$5:$N$254,MATCH(T10,Assets!$A$5:$A$254,0)),"Check - not in library"))) -> 0 | V10: Shop now | W10: Priya Nair | X10: Published | Y10: =IF(B10="","",B10-ProductionDays) -> 0 | Z10: =IF(B10="","",B10-ApprovalDays) -> 0 | AA10: =IF(B10="","",B10-TODAY()) -> 0 | AB10: instagram.com/wildflowerstudio/p/4905 | AC10: =IF(H10="","",IF(X10="Published",IF(AB10="","Add - link missing","Yes"),"No")) -> 0 | AD10: =IF(A10="","",IF(COUNTIF(Performance!$B$5:$B$404,A10)=0,"",SUMIFS(Performance!$O$5:$O$404,Performance!$B$5:$B$404,A10))) -> 0 | AE10: =IF(AD10="","",SUMIFS(Performance!$Z$5:$Z$404,Performance!$B$5:$B$404,A10)) -> 0 | AF10: =IF(OR(AD10="",AD10=0),"",AE10/AD10) -> 0 | AG10: =IF(AD10="","",SUMIFS(Performance!$U$5:$U$404,Performance!$B$5:$B$404,A10)) -> 0 | AH10: =IF(A10="","",COUNTIF(Repurposing!$B$5:$B$154,A10)) -> 0 | AI10: =IF(OR(H10="",B10=""),"",B10+ROW()/100000) -> 0 | AJ10: =IF(OR(H10="",B10=""),"",IF(OR(X10="Published",X10="Cancelled",X10="Archived"),"",IF(B10<TODAY(),"",B10+ROW()/100000))) -> 0 | AK10: =IF(OR(H10="",B10=""),"",IF(OR(X10="Published",X10="Cancelled",X10="Archived"),"",IF(B10>=TODAY(),"",B10+ROW()/100000))) -> 0 | AL10: =IF(H10="","",IF(COUNTIFS('Content Calendar'!$H$5:$H$604,H10,'Content Calendar'!$G$5:$G$604,G10,'Content Calendar'!$B$5:$B$604,B10)>1,"Duplicate","OK")) -> 0 | AM10: =IF(H10="","",IF(AND(B10<>"",B10<TODAY(),X10<>"Published",X10<>"Cancelled",X10<>"Archived"),"Overdue - date has passed",IF(AND(X10="Published",AB10=""),"Add - publish link missing",IF(AND(B10=TODAY(),X10<>"Published"),"Today - due to go live",IF(AND(Y10<>"",Y10<TODAY(),OR(X10="Idea",X10="Brief",X10="In production")),"Late - draft not ready",IF(AND(AA10>=0,AA10<=3,OR(X10="Draft",X10="Awaiting review")),"Due - needs approval",IF(AND(H10<>"",P10=""),"Add - caption missing","OK"))))))) -> 0
A11: =IF(H11="","",ContentPrefix&TEXT(ROW()-4,"0000")) -> 0 | B11: 46258 | C11: Afternoon | D11: =IF(B11="","",TEXT(B11,"yyyy-mm")) -> 0 | E11: =IF(B11="","",WEEKNUM(B11,IF(WeekStart="Sunday",1,2))) -> 0 | F11: =IF(B11="","",TEXT(B11,"ddd")) -> 0 | G11: YouTube | H11: How a glaze is mixed - full studio tour | I11: Educate post for youtube: How a glaze is mixed - full studio tour. | J11: Educate | K11: Long video | L11: Autumn Table Styling | M11: Brand authority | N11: Consideration | O11: First-home Freya | P11: Restock alert | Q11: =IF(H11="","",IF(P11="","Add - no caption",IFERROR(INDEX('Caption Bank'!$R$5:$R$204,MATCH(P11,'Caption Bank'!$B$5:$B$204,0)),"Check - not in bank"))) -> 0 | R11: Group 3 | S11: =IF(R11="","",COUNTIF('Hashtag Bank'!$D$5:$D$304,R11)) -> 0 | T11: AS-0007 | U11: =IF(H11="","",IF(T11="","Add - no asset",IFERROR(INDEX(Assets!$N$5:$N$254,MATCH(T11,Assets!$A$5:$A$254,0)),"Check - not in library"))) -> 0 | V11: Save this | W11: Sam Okonkwo | X11: Published | Y11: =IF(B11="","",B11-ProductionDays) -> 0 | Z11: =IF(B11="","",B11-ApprovalDays) -> 0 | AA11: =IF(B11="","",B11-TODAY()) -> 0 | AB11: youtube.com/wildflowerstudio/p/4806 | AC11: =IF(H11="","",IF(X11="Published",IF(AB11="","Add - link missing","Yes"),"No")) -> 0 | AD11: =IF(A11="","",IF(COUNTIF(Performance!$B$5:$B$404,A11)=0,"",SUMIFS(Performance!$O$5:$O$404,Performance!$B$5:$B$404,A11))) -> 0 | AE11: =IF(AD11="","",SUMIFS(Performance!$Z$5:$Z$404,Performance!$B$5:$B$404,A11)) -> 0 | AF11: =IF(OR(AD11="",AD11=0),"",AE11/AD11) -> 0 | AG11: =IF(AD11="","",SUMIFS(Performance!$U$5:$U$404,Performance!$B$5:$B$404,A11)) -> 0 | AH11: =IF(A11="","",COUNTIF(Repurposing!$B$5:$B$154,A11)) -> 0 | AI11: =IF(OR(H11="",B11=""),"",B11+ROW()/100000) -> 0 | AJ11: =IF(OR(H11="",B11=""),"",IF(OR(X11="Published",X11="Cancelled",X11="Archived"),"",IF(B11<TODAY(),"",B11+ROW()/100000))) -> 0 | AK11: =IF(OR(H11="",B11=""),"",IF(OR(X11="Published",X11="Cancelled",X11="Archived"),"",IF(B11>=TODAY(),"",B11+ROW()/100000))) -> 0 | AL11: =IF(H11="","",IF(COUNTIFS('Content Calendar'!$H$5:$H$604,H11,'Content Calendar'!$G$5:$G$604,G11,'Content Calendar'!$B$5:$B$604,B11)>1,"Duplicate","OK")) -> 0 | AM11: =IF(H11="","",IF(AND(B11<>"",B11<TODAY(),X11<>"Published",X11<>"Cancelled",X11<>"Archived"),"Overdue - date has passed",IF(AND(X11="Published",AB11=""),"Add - publish link missing",IF(AND(B11=TODAY(),X11<>"Published"),"Today - due to go live",IF(AND(Y11<>"",Y11<TODAY(),OR(X11="Idea",X11="Brief",X11="In production")),"Late - draft not ready",IF(AND(AA11>=0,AA11<=3,OR(X11="Draft",X11="Awaiting review")),"Due - needs approval",IF(AND(H11<>"",P11=""),"Add - caption missing","OK"))))))) -> 0
A12: =IF(H12="","",ContentPrefix&TEXT(ROW()-4,"0000")) -> 0 | B12: 46259 | C12: Lunchtime | D12: =IF(B12="","",TEXT(B12,"yyyy-mm")) -> 0 | E12: =IF(B12="","",WEEKNUM(B12,IF(WeekStart="Sunday",1,2))) -> 0 | F12: =IF(B12="","",TEXT(B12,"ddd")) -> 0 | G12: Pinterest | H12: Neutral shelf styling in 6 steps | I12: Inspire post for pinterest: Neutral shelf styling in 6 steps. | J12: Inspire | K12: Standard Pin | L12: Autumn Table Styling | M12: Awareness | N12: Awareness | O12: Gifting Grace | P12: Care guide | Q12: =IF(H12="","",IF(P12="","Add - no caption",IFERROR(INDEX('Caption Bank'!$R$5:$R$204,MATCH(P12,'Caption Bank'!$B$5:$B$204,0)),"Check - not in bank"))) -> 0 | R12: Group 4 | S12: =IF(R12="","",COUNTIF('Hashtag Bank'!$D$5:$D$304,R12)) -> 0 | T12: AS-0008 | U12: =IF(H12="","",IF(T12="","Add - no asset",IFERROR(INDEX(Assets!$N$5:$N$254,MATCH(T12,Assets!$A$5:$A$254,0)),"Check - not in library"))) -> 0 | V12: Follow for more | W12: Elena Dias | X12: Published | Y12: =IF(B12="","",B12-ProductionDays) -> 0 | Z12: =IF(B12="","",B12-ApprovalDays) -> 0 | AA12: =IF(B12="","",B12-TODAY()) -> 0 | AB12: pinterest.com/wildflowerstudio/p/4707 | AC12: =IF(H12="","",IF(X12="Published",IF(AB12="","Add - link missing","Yes"),"No")) -> 0 | AD12: =IF(A12="","",IF(COUNTIF(Performance!$B$5:$B$404,A12)=0,"",SUMIFS(Performance!$O$5:$O$404,Performance!$B$5:$B$404,A12))) -> 0 | AE12: =IF(AD12="","",SUMIFS(Performance!$Z$5:$Z$404,Performance!$B$5:$B$404,A12)) -> 0 | AF12: =IF(OR(AD12="",AD12=0),"",AE12/AD12) -> 0 | AG12: =IF(AD12="","",SUMIFS(Performance!$U$5:$U$404,Performance!$B$5:$B$404,A12)) -> 0 | AH12: =IF(A12="","",COUNTIF(Repurposing!$B$5:$B$154,A12)) -> 0 | AI12: =IF(OR(H12="",B12=""),"",B12+ROW()/100000) -> 0 | AJ12: =IF(OR(H12="",B12=""),"",IF(OR(X12="Published",X12="Cancelled",X12="Archived"),"",IF(B12<TODAY(),"",B12+ROW()/100000))) -> 0 | AK12: =IF(OR(H12="",B12=""),"",IF(OR(X12="Published",X12="Cancelled",X12="Archived"),"",IF(B12>=TODAY(),"",B12+ROW()/100000))) -> 0 | AL12: =IF(H12="","",IF(COUNTIFS('Content Calendar'!$H$5:$H$604,H12,'Content Calendar'!$G$5:$G$604,G12,'Content Calendar'!$B$5:$B$604,B12)>1,"Duplicate","OK")) -> 0 | AM12: =IF(H12="","",IF(AND(B12<>"",B12<TODAY(),X12<>"Published",X12<>"Cancelled",X12<>"Archived"),"Overdue - date has passed",IF(AND(X12="Published",AB12=""),"Add - publish link missing",IF(AND(B12=TODAY(),X12<>"Published"),"Today - due to go live",IF(AND(Y12<>"",Y12<TODAY(),OR(X12="Idea",X12="Brief",X12="In production")),"Late - draft not ready",IF(AND(AA12>=0,AA12<=3,OR(X12="Draft",X12="Awaiting review")),"Due - needs approval",IF(AND(H12<>"",P12=""),"Add - caption missing","OK"))))))) -> 0
A13: =IF(H13="","",ContentPrefix&TEXT(ROW()-4,"0000")) -> 0 | B13: 46261 | C13: Evening | D13: =IF(B13="","",TEXT(B13,"yyyy-mm")) -> 0 | E13: =IF(B13="","",WEEKNUM(B13,IF(WeekStart="Sunday",1,2))) -> 0 | F13: =IF(B13="","",TEXT(B13,"ddd")) -> 0 | G13: TikTok | H13: Kiln opening - did they survive? | I13: Behind the scenes post for tiktok: Kiln opening - did they survive?. | J13: Behind the scenes | K13: Short video | L13: Autumn Table Styling | M13: Community | N13: Awareness | O13: Interiors Isla | P13: Gift guide | Q13: =IF(H13="","",IF(P13="","Add - no caption",IFERROR(INDEX('Caption Bank'!$R$5:$R$204,MATCH(P13,'Caption Bank'!$B$5:$B$204,0)),"Check - not in bank"))) -> 0 | R13: Group 1 | S13: =IF(R13="","",COUNTIF('Hashtag Bank'!$D$5:$D$304,R13)) -> 0 | T13: AS-0009 | U13: =IF(H13="","",IF(T13="","Add - no asset",IFERROR(INDEX(Assets!$N$5:$N$254,MATCH(T13,Assets!$A$5:$A$254,0)),"Check - not in library"))) -> 0 | V13: Comment below | W13: Jordan Avery | X13: Published | Y13: =IF(B13="","",B13-ProductionDays) -> 0 | Z13: =IF(B13="","",B13-ApprovalDays) -> 0 | AA13: =IF(B13="","",B13-TODAY()) -> 0 | AB13: tiktok.com/wildflowerstudio/p/4508 | AC13: =IF(H13="","",IF(X13="Published",IF(AB13="","Add - link missing","Yes"),"No")) -> 0 | AD13: =IF(A13="","",IF(COUNTIF(Performance!$B$5:$B$404,A13)=0,"",SUMIFS(Performance!$O$5:$O$404,Performance!$B$5:$B$404,A13))) -> 0 | AE13: =IF(AD13="","",SUMIFS(Performance!$Z$5:$Z$404,Performance!$B$5:$B$404,A13)) -> 0 | AF13: =IF(OR(AD13="",AD13=0),"",AE13/AD13) -> 0 | AG13: =IF(AD13="","",SUMIFS(Performance!$U$5:$U$404,Performance!$B$5:$B$404,A13)) -> 0 | AH13: =IF(A13="","",COUNTIF(Repurposing!$B$5:$B$154,A13)) -> 0 | AI13: =IF(OR(H13="",B13=""),"",B13+ROW()/100000) -> 0 | AJ13: =IF(OR(H13="",B13=""),"",IF(OR(X13="Published",X13="Cancelled",X13="Archived"),"",IF(B13<TODAY(),"",B13+ROW()/100000))) -> 0 | AK13: =IF(OR(H13="",B13=""),"",IF(OR(X13="Published",X13="Cancelled",X13="Archived"),"",IF(B13>=TODAY(),"",B13+ROW()/100000))) -> 0 | AL13: =IF(H13="","",IF(COUNTIFS('Content Calendar'!$H$5:$H$604,H13,'Content Calendar'!$G$5:$G$604,G13,'Content Calendar'!$B$5:$B$604,B13)>1,"Duplicate","OK")) -> 0 | AM13: =IF(H13="","",IF(AND(B13<>"",B13<TODAY(),X13<>"Published",X13<>"Cancelled",X13<>"Archived"),"Overdue - date has passed",IF(AND(X13="Published",AB13=""),"Add - publish link missing",IF(AND(B13=TODAY(),X13<>"Published"),"Today - due to go live",IF(AND(Y13<>"",Y13<TODAY(),OR(X13="Idea",X13="Brief",X13="In production")),"Late - draft not ready",IF(AND(AA13>=0,AA13<=3,OR(X13="Draft",X13="Awaiting review")),"Due - needs approval",IF(AND(H13<>"",P13=""),"Add - caption missing","OK"))))))) -> 0
A14: =IF(H14="","",ContentPrefix&TEXT(ROW()-4,"0000")) -> 0 | B14: 46262 | C14: Morning | D14: =IF(B14="","",TEXT(B14,"yyyy-mm")) -> 0 | E14: =IF(B14="","",WEEKNUM(B14,IF(WeekStart="Sunday",1,2))) -> 0 | F14: =IF(B14="","",TEXT(B14,"ddd")) -> 0 | G14: Instagram | H14: Your kitchen shelfies - UGC round up | I14: Community post for instagram: Your kitchen shelfies - UGC round up. | J14: Community | K14: Feed post | L14: Autumn Table Styling | M14: Engagement | N14: Retention | O14: First-home Freya | P14: Slow Sunday | Q14: =IF(H14="","",IF(P14="","Add - no caption",IFERROR(INDEX('Caption Bank'!$R$5:$R$204,MATCH(P14,'Caption Bank'!$B$5:$B$204,0)),"Check - not in bank"))) -> 0 | R14: Group 2 | S14: =IF(R14="","",COUNTIF('Hashtag Bank'!$D$5:$D$304,R14)) -> 0 | T14: AS-0010 | U14: =IF(H14="","",IF(T14="","Add - no asset",IFERROR(INDEX(Assets!$N$5:$N$254,MATCH(T14,Assets!$A$5:$A$254,0)),"Check - not in library"))) -> 0 | V14: Tag a friend | W14: Priya Nair | X14: Published | Y14: =IF(B14="","",B14-ProductionDays) -> 0 | Z14: =IF(B14="","",B14-ApprovalDays) -> 0 | AA14: =IF(B14="","",B14-TODAY()) -> 0 | AB14: instagram.com/wildflowerstudio/p/4409 | AC14: =IF(H14="","",IF(X14="Published",IF(AB14="","Add - link missing","Yes"),"No")) -> 0 | AD14: =IF(A14="","",IF(COUNTIF(Performance!$B$5:$B$404,A14)=0,"",SUMIFS(Performance!$O$5:$O$404,Performance!$B$5:$B$404,A14))) -> 0 | AE14: =IF(AD14="","",SUMIFS(Performance!$Z$5:$Z$404,Performance!$B$5:$B$404,A14)) -> 0 | AF14: =IF(OR(AD14="",AD14=0),"",AE14/AD14) -> 0 | AG14: =IF(AD14="","",SUMIFS(Performance!$U$5:$U$404,Performance!$B$5:$B$404,A14)) -> 0 | AH14: =IF(A14="","",COUNTIF(Repurposing!$B$5:$B$154,A14)) -> 0 | AI14: =IF(OR(H14="",B14=""),"",B14+ROW()/100000) -> 0 | AJ14: =IF(OR(H14="",B14=""),"",IF(OR(X14="Published",X14="Cancelled",X14="Archived"),"",IF(B14<TODAY(),"",B14+ROW()/100000))) -> 0 | AK14: =IF(OR(H14="",B14=""),"",IF(OR(X14="Published",X14="Cancelled",X14="Archived"),"",IF(B14>=TODAY(),"",B14+ROW()/100000))) -> 0 | AL14: =IF(H14="","",IF(COUNTIFS('Content Calendar'!$H$5:$H$604,H14,'Content Calendar'!$G$5:$G$604,G14,'Content Calendar'!$B$5:$B$604,B14)>1,"Duplicate","OK")) -> 0 | AM14: =IF(H14="","",IF(AND(B14<>"",B14<TODAY(),X14<>"Published",X14<>"Cancelled",X14<>"Archived"),"Overdue - date has passed",IF(AND(X14="Published",AB14=""),"Add - publish link missing",IF(AND(B14=TODAY(),X14<>"Published"),"Today - due to go live",IF(AND(Y14<>"",Y14<TODAY(),OR(X14="Idea",X14="Brief",X14="In production")),"Late - draft not ready",IF(AND(AA14>=0,AA14<=3,OR(X14="Draft",X14="Awaiting review")),"Due - needs approval",IF(AND(H14<>"",P14=""),"Add - caption missing","OK"))))))) -> 0
A15: =IF(H15="","",ContentPrefix&TEXT(ROW()-4,"0000")) -> 0 | B15: 46264 | C15: Morning | D15: =IF(B15="","",TEXT(B15,"yyyy-mm")) -> 0 | E15: =IF(B15="","",WEEKNUM(B15,IF(WeekStart="Sunday",1,2))) -> 0 | F15: =IF(B15="","",TEXT(B15,"ddd")) -> 0 | G15: Instagram | H15: Stoneware vs porcelain - which to buy | I15: Educate post for instagram: Stoneware vs porcelain - which to buy. | J15: Educate | K15: Carousel | L15: Autumn Table Styling | M15: Brand authority | N15: Consideration | O15: Gifting Grace | P15: Studio week | Q15: =IF(H15="","",IF(P15="","Add - no caption",IFERROR(INDEX('Caption Bank'!$R$5:$R$204,MATCH(P15,'Caption Bank'!$B$5:$B$204,0)),"Check - not in bank"))) -> 0 | R15: Group 3 | S15: =IF(R15="","",COUNTIF('Hashtag Bank'!$D$5:$D$304,R15)) -> 0 | T15: AS-0011 | U15: =IF(H15="","",IF(T15="","Add - no asset",IFERROR(INDEX(Assets!$N$5:$N$254,MATCH(T15,Assets!$A$5:$A$254,0)),"Check - not in library"))) -> 0 | V15: Save this | W15: Sam Okonkwo | X15: Published | Y15: =IF(B15="","",B15-ProductionDays) -> 0 | Z15: =IF(B15="","",B15-ApprovalDays) -> 0 | AA15: =IF(B15="","",B15-TODAY()) -> 0 | AB15: instagram.com/wildflowerstudio/p/4210 | AC15: =IF(H15="","",IF(X15="Published",IF(AB15="","Add - link missing","Yes"),"No")) -> 0 | AD15: =IF(A15="","",IF(COUNTIF(Performance!$B$5:$B$404,A15)=0,"",SUMIFS(Performance!$O$5:$O$404,Performance!$B$5:$B$404,A15))) -> 0 | AE15: =IF(AD15="","",SUMIFS(Performance!$Z$5:$Z$404,Performance!$B$5:$B$404,A15)) -> 0 | AF15: =IF(OR(AD15="",AD15=0),"",AE15/AD15) -> 0 | AG15: =IF(AD15="","",SUMIFS(Performance!$U$5:$U$404,Performance!$B$5:$B$404,A15)) -> 0 | AH15: =IF(A15="","",COUNTIF(Repurposing!$B$5:$B$154,A15)) -> 0 | AI15: =IF(OR(H15="",B15=""),"",B15+ROW()/100000) -> 0 | AJ15: =IF(OR(H15="",B15=""),"",IF(OR(X15="Published",X15="Cancelled",X15="Archived"),"",IF(B15<TODAY(),"",B15+ROW()/100000))) -> 0 | AK15: =IF(OR(H15="",B15=""),"",IF(OR(X15="Published",X15="Cancelled",X15="Archived"),"",IF(B15>=TODAY(),"",B15+ROW()/100000))) -> 0 | AL15: =IF(H15="","",IF(COUNTIFS('Content Calendar'!$H$5:$H$604,H15,'Content Calendar'!$G$5:$G$604,G15,'Content Calendar'!$B$5:$B$604,B15)>1,"Duplicate","OK")) -> 0 | AM15: =IF(H15="","",IF(AND(B15<>"",B15<TODAY(),X15<>"Published",X15<>"Cancelled",X15<>"Archived"),"Overdue - date has passed",IF(AND(X15="Published",AB15=""),"Add - publish link missing",IF(AND(B15=TODAY(),X15<>"Published"),"Today - due to go live",IF(AND(Y15<>"",Y15<TODAY(),OR(X15="Idea",X15="Brief",X15="In production")),"Late - draft not ready",IF(AND(AA15>=0,AA15<=3,OR(X15="Draft",X15="Awaiting review")),"Due - needs approval",IF(AND(H15<>"",P15=""),"Add - caption missing","OK"))))))) -> 0
A16: =IF(H16="","",ContentPrefix&TEXT(ROW()-4,"0000")) -> 0 | B16: 46265 | C16: Morning | D16: =IF(B16="","",TEXT(B16,"yyyy-mm")) -> 0 | E16: =IF(B16="","",WEEKNUM(B16,IF(WeekStart="Sunday",1,2))) -> 0 | F16: =IF(B16="","",TEXT(B16,"ddd")) -> 0 | G16: Facebook | H16: Autumn collection now in the shop | I16: Promote post for facebook: Autumn collection now in the shop. | J16: Promote | K16: Photo | L16: Autumn Table Styling | M16: Sales | N16: Conversion | O16: Interiors Isla | P16: Holiday shipping | Q16: =IF(H16="","",IF(P16="","Add - no caption",IFERROR(INDEX('Caption Bank'!$R$5:$R$204,MATCH(P16,'Caption Bank'!$B$5:$B$204,0)),"Check - not in bank"))) -> 0 | R16: Group 4 | S16: =IF(R16="","",COUNTIF('Hashtag Bank'!$D$5:$D$304,R16)) -> 0 | T16: AS-0012 | U16: =IF(H16="","",IF(T16="","Add - no asset",IFERROR(INDEX(Assets!$N$5:$N$254,MATCH(T16,Assets!$A$5:$A$254,0)),"Check - not in library"))) -> 0 | V16: Shop now | W16: Elena Dias | X16: Published | Y16: =IF(B16="","",B16-ProductionDays) -> 0 | Z16: =IF(B16="","",B16-ApprovalDays) -> 0 | AA16: =IF(B16="","",B16-TODAY()) -> 0 | AB16: facebook.com/wildflowerstudio/p/4111 | AC16: =IF(H16="","",IF(X16="Published",IF(AB16="","Add - link missing","Yes"),"No")) -> 0 | AD16: =IF(A16="","",IF(COUNTIF(Performance!$B$5:$B$404,A16)=0,"",SUMIFS(Performance!$O$5:$O$404,Performance!$B$5:$B$404,A16))) -> 0 | AE16: =IF(AD16="","",SUMIFS(Performance!$Z$5:$Z$404,Performance!$B$5:$B$404,A16)) -> 0 | AF16: =IF(OR(AD16="",AD16=0),"",AE16/AD16) -> 0 | AG16: =IF(AD16="","",SUMIFS(Performance!$U$5:$U$404,Performance!$B$5:$B$404,A16)) -> 0 | AH16: =IF(A16="","",COUNTIF(Repurposing!$B$5:$B$154,A16)) -> 0 | AI16: =IF(OR(H16="",B16=""),"",B16+ROW()/100000) -> 0 | AJ16: =IF(OR(H16="",B16=""),"",IF(OR(X16="Published",X16="Cancelled",X16="Archived"),"",IF(B16<TODAY(),"",B16+ROW()/100000))) -> 0 | AK16: =IF(OR(H16="",B16=""),"",IF(OR(X16="Published",X16="Cancelled",X16="Archived"),"",IF(B16>=TODAY(),"",B16+ROW()/100000))) -> 0 | AL16: =IF(H16="","",IF(COUNTIFS('Content Calendar'!$H$5:$H$604,H16,'Content Calendar'!$G$5:$G$604,G16,'Content Calendar'!$B$5:$B$604,B16)>1,"Duplicate","OK")) -> 0 | AM16: =IF(H16="","",IF(AND(B16<>"",B16<TODAY(),X16<>"Published",X16<>"Cancelled",X16<>"Archived"),"Overdue - date has passed",IF(AND(X16="Published",AB16=""),"Add - publish link missing",IF(AND(B16=TODAY(),X16<>"Published"),"Today - due to go live",IF(AND(Y16<>"",Y16<TODAY(),OR(X16="Idea",X16="Brief",X16="In production")),"Late - draft not ready",IF(AND(AA16>=0,AA16<=3,OR(X16="Draft",X16="Awaiting review")),"Due - needs approval",IF(AND(H16<>"",P16=""),"Add - caption missing","OK"))))))) -> 0
A17: =IF(H17="","",ContentPrefix&TEXT(ROW()-4,"0000")) -> 0 | B17: 46266 | C17: Lunchtime | D17: =IF(B17="","",TEXT(B17,"yyyy-mm")) -> 0 | E17: =IF(B17="","",WEEKNUM(B17,IF(WeekStart="Sunday",1,2))) -> 0 | F17: =IF(B17="","",TEXT(B17,"ddd")) -> 0 | G17: Pinterest | H17: Three ways to fold a linen napkin | I17: Educate post for pinterest: Three ways to fold a linen napkin. | J17: Educate | K17: Video Pin | L17: Autumn Table Styling | M17: Brand authority | N17: Consideration | O17: First-home Freya | P17: Single stem styling | Q17: =IF(H17="","",IF(P17="","Add - no caption",IFERROR(INDEX('Caption Bank'!$R$5:$R$204,MATCH(P17,'Caption Bank'!$B$5:$B$204,0)),"Check - not in bank"))) -> 0 | R17: Group 1 | S17: =IF(R17="","",COUNTIF('Hashtag Bank'!$D$5:$D$304,R17)) -> 0 | T17: AS-0013 | U17: =IF(H17="","",IF(T17="","Add - no asset",IFERROR(INDEX(Assets!$N$5:$N$254,MATCH(T17,Assets!$A$5:$A$254,0)),"Check - not in library"))) -> 0 | V17: Save this | W17: Jordan Avery | X17: Published | Y17: =IF(B17="","",B17-ProductionDays) -> 0 | Z17: =IF(B17="","",B17-ApprovalDays) -> 0 | AA17: =IF(B17="","",B17-TODAY()) -> 0 | AB17: pinterest.com/wildflowerstudio/p/4012 | AC17: =IF(H17="","",IF(X17="Published",IF(AB17="","Add - link missing","Yes"),"No")) -> 0 | AD17: =IF(A17="","",IF(COUNTIF(Performance!$B$5:$B$404,A17)=0,"",SUMIFS(Performance!$O$5:$O$404,Performance!$B$5:$B$404,A17))) -> 0 | AE17: =IF(AD17="","",SUMIFS(Performance!$Z$5:$Z$404,Performance!$B$5:$B$404,A17)) -> 0 | AF17: =IF(OR(AD17="",AD17=0),"",AE17/AD17) -> 0 | AG17: =IF(AD17="","",SUMIFS(Performance!$U$5:$U$404,Performance!$B$5:$B$404,A17)) -> 0 | AH17: =IF(A17="","",COUNTIF(Repurposing!$B$5:$B$154,A17)) -> 0 | AI17: =IF(OR(H17="",B17=""),"",B17+ROW()/100000) -> 0 | AJ17: =IF(OR(H17="",B17=""),"",IF(OR(X17="Published",X17="Cancelled",X17="Archived"),"",IF(B17<TODAY(),"",B17+ROW()/100000))) -> 0 | AK17: =IF(OR(H17="",B17=""),"",IF(OR(X17="Published",X17="Cancelled",X17="Archived"),"",IF(B17>=TODAY(),"",B17+ROW()/100000))) -> 0 | AL17: =IF(H17="","",IF(COUNTIFS('Content Calendar'!$H$5:$H$604,H17,'Content Calendar'!$G$5:$G$604,G17,'Content Calendar'!$B$5:$B$604,B17)>1,"Duplicate","OK")) -> 0 | AM17: =IF(H17="","",IF(AND(B17<>"",B17<TODAY(),X17<>"Published",X17<>"Cancelled",X17<>"Archived"),"Overdue - date has passed",IF(AND(X17="Published",AB17=""),"Add - publish link missing",IF(AND(B17=TODAY(),X17<>"Published"),"Today - due to go live",IF(AND(Y17<>"",Y17<TODAY(),OR(X17="Idea",X17="Brief",X17="In production")),"Late - draft not ready",IF(AND(AA17>=0,AA17<=3,OR(X17="Draft",X17="Awaiting review")),"Due - needs approval",IF(AND(H17<>"",P17=""),"Add - caption missing","OK"))))))) -> 0
A18: =IF(H18="","",ContentPrefix&TEXT(ROW()-4,"0000")) -> 0 | B18: 46268 | C18: Evening | D18: =IF(B18="","",TEXT(B18,"yyyy-mm")) -> 0 | E18: =IF(B18="","",WEEKNUM(B18,IF(WeekStart="Sunday",1,2))) -> 0 | F18: =IF(B18="","",TEXT(B18,"ddd")) -> 0 | G18: TikTok | H18: Pottery fails you asked to see | I18: Entertain post for tiktok: Pottery fails you asked to see. | J18: Entertain | K18: Reel | L18: Autumn Table Styling | M18: Awareness | N18: Awareness | O18: Gifting Grace | P18: Kiln opening | Q18: =IF(H18="","",IF(P18="","Add - no caption",IFERROR(INDEX('Caption Bank'!$R$5:$R$204,MATCH(P18,'Caption Bank'!$B$5:$B$204,0)),"Check - not in bank"))) -> 0 | R18: Group 2 | S18: =IF(R18="","",COUNTIF('Hashtag Bank'!$D$5:$D$304,R18)) -> 0 | T18: AS-0014 | U18: =IF(H18="","",IF(T18="","Add - no asset",IFERROR(INDEX(Assets!$N$5:$N$254,MATCH(T18,Assets!$A$5:$A$254,0)),"Check - not in library"))) -> 0 | V18: Share with a friend | W18: Priya Nair | X18: Published | Y18: =IF(B18="","",B18-ProductionDays) -> 0 | Z18: =IF(B18="","",B18-ApprovalDays) -> 0 | AA18: =IF(B18="","",B18-TODAY()) -> 0 | AB18: tiktok.com/wildflowerstudio/p/3813 | AC18: =IF(H18="","",IF(X18="Published",IF(AB18="","Add - link missing","Yes"),"No")) -> 0 | AD18: =IF(A18="","",IF(COUNTIF(Performance!$B$5:$B$404,A18)=0,"",SUMIFS(Performance!$O$5:$O$404,Performance!$B$5:$B$404,A18))) -> 0 | AE18: =IF(AD18="","",SUMIFS(Performance!$Z$5:$Z$404,Performance!$B$5:$B$404,A18)) -> 0 | AF18: =IF(OR(AD18="",AD18=0),"",AE18/AD18) -> 0 | AG18: =IF(AD18="","",SUMIFS(Performance!$U$5:$U$404,Performance!$B$5:$B$404,A18)) -> 0 | AH18: =IF(A18="","",COUNTIF(Repurposing!$B$5:$B$154,A18)) -> 0 | AI18: =IF(OR(H18="",B18=""),"",B18+ROW()/100000) -> 0 | AJ18: =IF(OR(H18="",B18=""),"",IF(OR(X18="Published",X18="Cancelled",X18="Archived"),"",IF(B18<TODAY(),"",B18+ROW()/100000))) -> 0 | AK18: =IF(OR(H18="",B18=""),"",IF(OR(X18="Published",X18="Cancelled",X18="Archived"),"",IF(B18>=TODAY(),"",B18+ROW()/100000))) -> 0 | AL18: =IF(H18="","",IF(COUNTIFS('Content Calendar'!$H$5:$H$604,H18,'Content Calendar'!$G$5:$G$604,G18,'Content Calendar'!$B$5:$B$604,B18)>1,"Duplicate","OK")) -> 0 | AM18: =IF(H18="","",IF(AND(B18<>"",B18<TODAY(),X18<>"Published",X18<>"Cancelled",X18<>"Archived"),"Overdue - date has passed",IF(AND(X18="Published",AB18=""),"Add - publish link missing",IF(AND(B18=TODAY(),X18<>"Published"),"Today - due to go live",IF(AND(Y18<>"",Y18<TODAY(),OR(X18="Idea",X18="Brief",X18="In production")),"Late - draft not ready",IF(AND(AA18>=0,AA18<=3,OR(X18="Draft",X18="Awaiting review")),"Due - needs approval",IF(AND(H18<>"",P18=""),"Add - caption missing","OK"))))))) -> 0
A19: =IF(H19="","",ContentPrefix&TEXT(ROW()-4,"0000")) -> 0 | B19: 46269 | C19: Morning | D19: =IF(B19="","",TEXT(B19,"yyyy-mm")) -> 0 | E19: =IF(B19="","",WEEKNUM(B19,IF(WeekStart="Sunday",1,2))) -> 0 | F19: =IF(B19="","",TEXT(B19,"ddd")) -> 0 | G19: Instagram | H19: Unboxing the autumn table set | I19: Promote post for instagram: Unboxing the autumn table set. | J19: Promote | K19: Reel | L19: Autumn Table Styling | M19: Sales | N19: Conversion | O19: Interiors Isla | P19: Autumn collection live | Q19: =IF(H19="","",IF(P19="","Add - no caption",IFERROR(INDEX('Caption Bank'!$R$5:$R$204,MATCH(P19,'Caption Bank'!$B$5:$B$204,0)),"Check - not in bank"))) -> 0 | R19: Group 3 | S19: =IF(R19="","",COUNTIF('Hashtag Bank'!$D$5:$D$304,R19)) -> 0 | T19: AS-0001 | U19: =IF(H19="","",IF(T19="","Add - no asset",IFERROR(INDEX(Assets!$N$5:$N$254,MATCH(T19,Assets!$A$5:$A$254,0)),"Check - not in library"))) -> 0 | V19: Shop now | W19: Sam Okonkwo | X19: Published | Y19: =IF(B19="","",B19-ProductionDays) -> 0 | Z19: =IF(B19="","",B19-ApprovalDays) -> 0 | AA19: =IF(B19="","",B19-TODAY()) -> 0 | AB19: instagram.com/wildflowerstudio/p/3714 | AC19: =IF(H19="","",IF(X19="Published",IF(AB19="","Add - link missing","Yes"),"No")) -> 0 | AD19: =IF(A19="","",IF(COUNTIF(Performance!$B$5:$B$404,A19)=0,"",SUMIFS(Performance!$O$5:$O$404,Performance!$B$5:$B$404,A19))) -> 0 | AE19: =IF(AD19="","",SUMIFS(Performance!$Z$5:$Z$404,Performance!$B$5:$B$404,A19)) -> 0 | AF19: =IF(OR(AD19="",AD19=0),"",AE19/AD19) -> 0 | AG19: =IF(AD19="","",SUMIFS(Performance!$U$5:$U$404,Performance!$B$5:$B$404,A19)) -> 0 | AH19: =IF(A19="","",COUNTIF(Repurposing!$B$5:$B$154,A19)) -> 0 | AI19: =IF(OR(H19="",B19=""),"",B19+ROW()/100000) -> 0 | AJ19: =IF(OR(H19="",B19=""),"",IF(OR(X19="Published",X19="Cancelled",X19="Archived"),"",IF(B19<TODAY(),"",B19+ROW()/100000))) -> 0 | AK19: =IF(OR(H19="",B19=""),"",IF(OR(X19="Published",X19="Cancelled",X19="Archived"),"",IF(B19>=TODAY(),"",B19+ROW()/100000))) -> 0 | AL19: =IF(H19="","",IF(COUNTIFS('Content Calendar'!$H$5:$H$604,H19,'Content Calendar'!$G$5:$G$604,G19,'Content Calendar'!$B$5:$B$604,B19)>1,"Duplicate","OK")) -> 0 | AM19: =IF(H19="","",IF(AND(B19<>"",B19<TODAY(),X19<>"Published",X19<>"Cancelled",X19<>"Archived"),"Overdue - date has passed",IF(AND(X19="Published",AB19=""),"Add - publish link missing",IF(AND(B19=TODAY(),X19<>"Published"),"Today - due to go live",IF(AND(Y19<>"",Y19<TODAY(),OR(X19="Idea",X19="Brief",X19="In production")),"Late - draft not ready",IF(AND(AA19>=0,AA19<=3,OR(X19="Draft",X19="Awaiting review")),"Due - needs approval",IF(AND(H19<>"",P19=""),"Add - caption missing","OK"))))))) -> 0
